Workbook
Name Inverter_Capacity: #REF!
Name Inverter_Supplier: #REF!
Name Project_Size: 'Certificate - Financial Close'!Projectsize
Name Project_Size: 'Finance - Revenue'!Projectsize
Name Project_Size: Projectsize
Name Projectsize: #REF!
Name Projectsize: #REF!
Name Projectsize: 'Project Margins'!$K$5
Name Security_Serv: #REF!
Name Security_Serv: #REF!
Name SSS: #REF!
Name SSS: #REF!
Name USD_ZAR: #REF!

Sheet Revenue Tracking
B2: HIGH LEVEL PROJECT REVENUE TRACKING
D3: COSTED | F3: ACTUAL | L3: FINANCIAL REVIEW | N3: TIMELINE REVIEW | R3: Allocated in 2025 | S3: Budgeted | T3: Actual | W3: 2025 Actual Revenue | X3: 2025 Actual COS | Y3: 2026 Budget Revenue | Z3: 2026 Budget COS | AA3: 2026 Actual Revenue | AB3: 2026 Actual COS
B4: 1 | C4: Planned Revenue | D4: ='Project Plan'!E6 -> 59995000 | F4: =F23 -> 59995000 | L4: 59995000 | N4: Start Date | P4: Sales | S4: =F4-R4 -> 59995000 | T4: =F4-R4 -> 59995000 | W4: =SUMIFS('Expenditure Breakdown'!$U:$U, 'Expenditure Breakdown'!$T:$T, ">"&DATE(2024,8,31), 'Expenditure Breakdown'!$T:$T, "<="&DATE(2025,8,31), 'Expenditure Breakdown'!$S:$S, "<>") -> 44416314 | X4: =SUMIFS('Expenditure Breakdown'!$Q:$Q, 'Expenditure Breakdown'!$T:$T, ">"&DATE(2024,8,31), 'Expenditure Breakdown'!$T:$T, "<="&DATE(2025,8,31), 'Expenditure Breakdown'!$S:$S, "<>") -> 37030035 | Y4: =SUMIFS('Expenditure Breakdown'!$U:$U, 'Expenditure Breakdown'!$T:$T, ">"&DATE(2025,8,31), 'Expenditure Breakdown'!$T:$T, "<="&DATE(2026,8,31)) -> 13730977 | Z4: =SUMIFS('Expenditure Breakdown'!$Q:$Q, 'Expenditure Breakdown'!$T:$T, ">"&DATE(2025,8,31), 'Expenditure Breakdown'!$T:$T, "<="&DATE(2026,8,31)) -> 11262128 | AA4: =SUMIFS('Expenditure Breakdown'!$U:$U, 'Expenditure Breakdown'!$T:$T, ">"&DATE(2025,8,31), 'Expenditure Breakdown'!$T:$T, "<="&DATE(2026,8,31), 'Expenditure Breakdown'!$S:$S, "<>") -> 13730977 | AB4: =SUMIFS('Expenditure Breakdown'!$Q:$Q, 'Expenditure Breakdown'!$T:$T, ">"&DATE(2025,8,31), 'Expenditure Breakdown'!$T:$T, "<="&DATE(2026,8,31), 'Expenditure Breakdown'!$S:$S, "<>") -> 10418741
B5: 2 | C5: Planned Expenditure | D5: =+'Expenditure Tracking'!F5 -> 56096452 | F5: =+'Expenditure Tracking'!H5 -> 48292163 | G5: VO PM Limit | H5: Current VO Total | L5: 46345971 | N5: 45894 | P5: COS | S5: =F5-R5 -> 48292163 | T5: =F5-R5 -> 48292163
B6: 3 | C6: Planned Profit | D6: =+D4-D5 -> 3898547.9 | F6: =+F4-F5 -> 11702837 | G6: =D6*0.05 -> 194927.4 | H6: =SUMIF('Expenditure Breakdown'!N:N,"*VO*",'Expenditure Breakdown'!Q:Q) -> 0 | L6: 13649029 | N6: End Date - PC | P6: GP | R6: =R4-R5 -> 0 | S6: =S4-S5 -> 11702837 | T6: =T4-T5 -> 11702837
B7: 4 | C7: Planned Margin | D7: =+D6/D4 -> 0.064981214 | F7: =+F6/F4 -> 0.19506354 | L7: 0.22750277 | N7: 45982
B10: CONTRACT
B12: No. | C12: PAYMENT MILESTONE | E12: % | F12: VALUE | H12: PLANNED PAYMENT DATE | L12: INVOICE NUMBER | N12: INVOICE RAISED DATE | P12: PAYMENT RECEIVED DATE | R12: MILESTONE NOTES & COMMENTS
B13: 1 | C13: Deposit - Coega Steel | E13: 0.25 | F13: 15000000 | H13: 45808 | L13: 004753 | N13: 45805 | P13: 45828
B14: 2 | C14: Delivery of Panels - Batch 1 | E14: 0.15 | F14: =($D$4*E14)-1250 -> 8998000 | H14: =P14 -> 45898 | L14: 004823 | N14: 45895 | P14: 45898
B15: 3 | C15: Delivery of Panels - Batch 2 | E15: 0.15 | F15: =$D$4*E15 -> 8999250 | H15: 45922 | L15: 004838 | N15: 45912 | P15: 45918
B16: 4 | C16: Delivery of Inverters | E16: 0.3 | F16: =$D$4*E16 -> 17998500 | H16: =P16 -> 45862 | L16: 004783 | N16: 45852 | P16: 45862
B17: 5 | C17: Practical Completion | E17: 0.1 | F17: =33990.72/1.15 -> 29557.148 | H17: ='Project Plan'!G99+7 -> 45980 | L17: 004933 | N17: 46055 | P17: 46002
B18: 5 | C18: Practical Completion | F18: =23326.12/1.15 -> 20283.583 | H18: 45980 | L18: 004933 | N18: 46055 | P18: 46002
B19: 5 | C19: Practical Completion | F19: =5999500-F17-F18 -> 5949659.3 | H19: 45980 | L19: 004933 | N19: 46055 | P19: 46066
B20: 6 | C20: Handover | E20: 0.05 | F20: =$D$4*E20 -> 2999750 | H20: ='Project Plan'!E123+7 -> 45999 | L20: 004963 | N20: 46098 | P20: 46108
B21: 7 | C21: - | E21: 0 | F21: =$D$4*E21 -> 0
E23: =SUM(E13:E21) -> 1 | F23: =SUM(F13:F21) -> 59995000
B25: KEY: | C25: contains an error (in result or a check has failed)
C26: Red Font - IF TEXT : content not yet confirmed | F26: =F17+F18+F19 -> 5999500
C27: Red Font - IF NUMBER: Negative value
C28: Anything in yellow is a concern or risk for noting or action
C29: confirmed
C30: [ADD INITIALS: comment for noting in square brackets, use colour or red to draw attention if important]
C31: [RT: When adding rows into sheet, ensure you insert between first and last row of each category]
C32: end of sheet - do not insert information below/beyond this

Sheet Data
C2: Public holidays | F2: Drop down list
C3: 45658 | D3: New Years Day | F3: Approved
C4: 45737 | D4: Human Rights day | F4: Pending
C5: 45765 | D5: Good Friday | F5: Declined
C6: 45768 | D6: Family Day | F6: Abanded
C7: 45774 | D7: Freedom Day
C8: 45765 | D8: Freedom DayObserved
C9: 45778 | D9: Workers day
C10: 45824 | D10: Youth Day Holiday
C11: 45878 | D11: Womens Day
C12: 45924 | D12: Heritage Day
H13: Manual dates
C17: 46011 | D17: Builders Break
C18: 46012 | D18: Builders Break
C19: 46013 | D19: Builders Break
C20: 46014 | D20: Builders Break
C21: 46015 | D21: Builders Break
C22: 46016 | D22: Builders Break
C23: 46017 | D23: Builders Break
C24: 46018 | D24: Builders Break
C25: 46019 | D25: Builders Break
C26: 46020 | D26: Builders Break
C27: 46021 | D27: Builders Break
C28: 46022 | D28: Builders Break
... C42: 46017 | D42: Day of Goodwill

Sheet Project Plan
N1: =TODAY() -> 46160 | O1: =TODAY() -> 46160
C2: PROJECT PLAN | E2: Coega Steels Phase 2 | N2: 0 | O2: 1
C3: PROJECT SIZE (kWp) | E3: 7080
C4: PROJECT DEVELOPER | E4: Gordon Upton
C5: PROJECT MANAGERS | E5: Lloyd Brown
C6: CONTRACT VALUE | E6: 59995000
C7: Phase: | E7: QA
B8: No. | C8: HIGH LEVEL PROGRAMME | E8: Planned Start | F8: Duration (work days) | G8: Planned End | I8: Actual Start | J8: Duration (work days) | K8: Actual End | M8: Status | N8: Expected Status | O8: Comment
F9: =G108-E19 -> 160 | J9: =K108-I19 -> 240 | M9: =AVERAGE(M11,M18,M32,M42,M58,M67,M74,M81,M88,M98,M110,M117) -> 0.98797619 | N9: =AVERAGE(N11,N18,N32,N42,N58,N67,N74,N81,N88,N98,N110,N117) -> 0.98809524
B11: 1 | C11: Project Initiation | E11: =MIN(E12:E16) -> 45796 | F11: =G11-E11 -> 74 | G11: =MAX(G12:G16) -> 45870 | I11: =MIN(I12:I16) -> 45796 | J11: =K11-I11 -> 74 | K11: =MAX(K12:K16) -> 45870 | M11: =AVERAGE(M12:M16) -> 1 | N11: =AVERAGE(N12:N16) -> 1
B12: =B11+0.1 -> 1.1 | C12: PD Handover | E12: 45796 | F12: 1 | G12: =WORKDAY.INTL(E12,F12,1,Data!$C$3:$C$41) -> 45797 | I12: 45796 | J12: 1 | K12: =WORKDAY.INTL(I12,J12,1,Data!$C$3:$C$41) -> 45797 | M12: 1 | N12: =_xlfn.LET( _xlpm.s,VALUE(I12), _xlpm.e,VALUE(K12), IF(OR(_xlpm.s="",_xlpm.e=""),"", IF(_xlpm.e<=_xlpm.s, IF(TODAY()>=_xlpm.e,1,0), MAX(0,MIN(1,(TODAY()-_xlpm.s)/(_xlpm.e-_xlpm.s))))) ) -> 1
B13: =B12+0.1 -> 1.2 | C13: Financial Close | E13: =WORKDAY.INTL(E19,0,1,Data!$C$3:$C$41)-7 -> 45808 | F13: 1 | G13: =WORKDAY.INTL(E13,F13,1,Data!$C$3:$C$41) -> 45810 | I13: =WORKDAY.INTL(I19,0,1,Data!$C$3:$C$41)-7 -> 45808 | J13: 1 | K13: =WORKDAY.INTL(I13,J13,1,Data!$C$3:$C$41) -> 45810 | M13: 1 | N13: =_xlfn.LET( _xlpm.s,VALUE(I13), _xlpm.e,VALUE(K13), IF(OR(_xlpm.s="",_xlpm.e=""),"", IF(_xlpm.e<=_xlpm.s, IF(TODAY()>=_xlpm.e,1,0), MAX(0,MIN(1,(TODAY()-_xlpm.s)/(_xlpm.e-_xlpm.s))))) ) -> 1
B14: =B13+0.1 -> 1.3 | C14: Structural Assessment | E14: =E12 -> 45796 | F14: 1 | G14: =WORKDAY.INTL(E14,F14,1,Data!$C$3:$C$41) -> 45797 | I14: =I12 -> 45796 | J14: 1 | K14: =WORKDAY.INTL(I14,J14,1,Data!$C$3:$C$41) -> 45797 | M14: 1 | N14: =_xlfn.LET( _xlpm.s,VALUE(I14), _xlpm.e,VALUE(K14), IF(OR(_xlpm.s="",_xlpm.e=""),"", IF(_xlpm.e<=_xlpm.s, IF(TODAY()>=_xlpm.e,1,0), MAX(0,MIN(1,(TODAY()-_xlpm.s)/(_xlpm.e-_xlpm.s))))) ) -> 1
B15: =B14+0.1 -> 1.4 | C15: Project Introduction | E15: 45867 | F15: 1 | G15: =WORKDAY.INTL(E15,F15,1,Data!$C$3:$C$41) -> 45868 | I15: 45867 | J15: 1 | K15: =WORKDAY.INTL(I15,J15,1,Data!$C$3:$C$41) -> 45868 | M15: 1 | N15: =_xlfn.LET( _xlpm.s,VALUE(I15), _xlpm.e,VALUE(K15), IF(OR(_xlpm.s="",_xlpm.e=""),"", IF(_xlpm.e<=_xlpm.s, IF(TODAY()>=_xlpm.e,1,0), MAX(0,MIN(1,(TODAY()-_xlpm.s)/(_xlpm.e-_xlpm.s))))) ) -> 1 | Y15: 0
B16: =B15+0.1 -> 1.5 | C16: Project Review | E16: 45870 | F16: 0 | G16: =WORKDAY.INTL(E16,F16,1,Data!$C$3:$C$41) -> 45870 | I16: 45870 | J16: 0 | K16: =WORKDAY.INTL(I16,J16,1,Data!$C$3:$C$41) -> 45870 | M16: 1 | N16: =_xlfn.LET( _xlpm.s,VALUE(I16), _xlpm.e,VALUE(K16), IF(OR(_xlpm.s="",_xlpm.e=""),"", IF(_xlpm.e<=_xlpm.s, IF(TODAY()>=_xlpm.e,1,0), MAX(0,MIN(1,(TODAY()-_xlpm.s)/(_xlpm.e-_xlpm.s))))) ) -> 1 | Y16: 1
B18: 2 | C18: Site Establishment Preperation | E18: =MIN(E19:E31) -> 45815 | F18: =G18-E18 -> 6 | G18: =MAX(G19) -> 45821 | I18: =MIN(I19:I31) -> 45815 | J18: =K18-I18 -> 95 | K18: =MAX(K19:K30) -> 45910 | M18: =AVERAGE(M19:M30) -> 1 | N18: =AVERAGE(N19:N30) -> 1 | S18: Milestone | T18: Start Date | U18: Total Duration | V18: Total WorkDays | W18: End Date | X18: Progress Percentage | Y18: Project Overall Progress Percentage
B19: =B18+0.1 -> 2.1 | C19: HSE Requirements | E19: 45815 | F19: 5 | G19: =WORKDAY.INTL(E19,F19,1,Data!$C$3:$C$41) -> 45821 | I19: 45815 | J19: 5 | K19: =WORKDAY.INTL(I19,J19,1,Data!$C$3:$C$41) -> 45821 | M19: 1 | N19: =_xlfn.LET( _xlpm.s,VALUE(I19), _xlpm.e,VALUE(K19), IF(OR(_xlpm.s="",_xlpm.e=""),"", IF(_xlpm.e<=_xlpm.s, IF(TODAY()>=_xlpm.e,1,0), MAX(0,MIN(1,(TODAY()-_xlpm.s)/(_xlpm.e-_xlpm.s))))) ) -> 1 | S19: =C32 -> Procurement & Contracting | T19: =I32 -> 45796 | U19: =J32 -> 193 | V19: =F32 -> 124 | W19: =K32 -> 45989 | X19: =M32 -> 1 | Y19: =M9 -> 0.98797619
B20: =B19+0.1 -> 2.2 | C20: EE File | E20: =WORKDAY.INTL(G18,0,1,Data!$C$3:$C$41) -> 45821 | F20: 17 | G20: =WORKDAY.INTL(E20,F20,1,Data!$C$3:$C$41) -> 45847 | I20: =WORKDAY.INTL(K19,0,1,Data!$C$3:$C$41) -> 45821 | J20: 17 | K20: =WORKDAY.INTL(I20,J20,1,Data!$C$3:$C$41) -> 45847 | M20: 1 | N20: =_xlfn.LET( _xlpm.s,VALUE(I20), _xlpm.e,VALUE(K20), IF(OR(_xlpm.s="",_xlpm.e=""),"", IF(_xlpm.e<=_xlpm.s, IF(TODAY()>=_xlpm.e,1,0), MAX(0,MIN(1,(TODAY()-_xlpm.s)/(_xlpm.e-_xlpm.s))))) ) -> 1 | S20: =C42 -> Extras & Civil Works | T20: =I42 -> 45830 | U20: =J42 -> 212 | V20: =F42 -> 71 | W20: =K42 -> 46042 | X20: =M42 -> 1
B21: =B20+0.1 -> 2.3 | C21: Subcontractor File - Solar Contractor | E21: =WORKDAY.INTL(G20,0,1,Data!$C$3:$C$41) -> 45847 | F21: 8 | G21: =WORKDAY.INTL(E21,F21,1,Data!$C$3:$C$41) -> 45859 | I21: =WORKDAY.INTL(K20,0,1,Data!$C$3:$C$41) -> 45847 | J21: 31 | K21: =WORKDAY.INTL(I21,J21,1,Data!$C$3:$C$41) -> 45890 | M21: 1 | N21: =_xlfn.LET( _xlpm.s,VALUE(I21), _xlpm.e,VALUE(K21), IF(OR(_xlpm.s="",_xlpm.e=""),"", IF(_xlpm.e<=_xlpm.s, IF(TODAY()>=_xlpm.e,1,0), MAX(0,MIN(1,(TODAY()-_xlpm.s)/(_xlpm.e-_xlpm.s))))) ) -> 1 | S21: =C58 -> DC Works - Rooftop | T21: =I58 -> 45894 | U21: =J58 -> 147 | V21: =F58 -> 51 | W21: =K58 -> 46041 | X21: =M58 -> 1 | AE21: =TODAY() -> 46160 | AF21: =TODAY() -> 46160
B22: =B21+0.1 -> 2.4 | C22: Subcontractor File - Civil Contractor (Bay View Construction & Engineering Hub) | I22: 45875 | J22: 25 | K22: =WORKDAY.INTL(I22,J22,1,Data!$C$3:$C$41) -> 45910 | M22: 1 | N22: =_xlfn.LET( _xlpm.s,VALUE(I22), _xlpm.e,VALUE(K22), IF(OR(_xlpm.s="",_xlpm.e=""),"", IF(_xlpm.e<=_xlpm.s, IF(TODAY()>=_xlpm.e,1,0), MAX(0,MIN(1,(TODAY()-_xlpm.s)/(_xlpm.e-_xlpm.s))))) ) -> 1 | O22: Bayview file pending - awaiting Medical approvals | S22: =C67 -> DC Works - Ground Mount | U22: =J67 -> 120 | V22: =F67 -> 58 | W22: =K67 -> 46058 | X22: =M67 -> 1 | AE22: 1 | AF22: 0
B23: =B22+0.1 -> 2.5 | C23: Subcontractor File - Anchor Point Contractor | E23: =WORKDAY.INTL(G20,0,1,Data!$C$3:$C$41) -> 45847 | F23: 8 | G23: =WORKDAY.INTL(E23,F23,1,Data!$C$3:$C$41) -> 45859 | I23: =WORKDAY.INTL(K20,0,1,Data!$C$3:$C$41) -> 45847 | J23: 31 | K23: =WORKDAY.INTL(I23,J23,1,Data!$C$3:$C$41) -> 45890 | M23: 1 | N23: =_xlfn.LET( _xlpm.s,VALUE(I23), _xlpm.e,VALUE(K23), IF(OR(_xlpm.s="",_xlpm.e=""),"", IF(_xlpm.e<=_xlpm.s, IF(TODAY()>=_xlpm.e,1,0), MAX(0,MIN(1,(TODAY()-_xlpm.s)/(_xlpm.e-_xlpm.s))))) ) -> 1 | S23: =C74 -> AC Installation - Ground Mount | T23: =I74 -> 45990 | U23: =J74 -> 17 | V23: =F74 -> 26 | W23: =K74 -> 46007 | X23: =M74 -> 1
B24: =B23+0.1 -> 2.6 | C24: HSE Permit Issued | I24: 45847 | J24: 33 | K24: =WORKDAY.INTL(I24,J24,1,Data!$C$3:$C$41) -> 45894 | M24: 1 | N24: =_xlfn.LET( _xlpm.s,VALUE(I24), _xlpm.e,VALUE(K24), IF(OR(_xlpm.s="",_xlpm.e=""),"", IF(_xlpm.e<=_xlpm.s, IF(TODAY()>=_xlpm.e,1,0), MAX(0,MIN(1,(TODAY()-_xlpm.s)/(_xlpm.e-_xlpm.s))))) ) -> 1 | O24: CDC/Coega Delays | S24: =C81 -> AC Installation - Rooftop | T24: =I81 -> 45915 | U24: =J81 -> 92 | V24: =F81 -> 21 | W24: =K81 -> 46007 | X24: =M81 -> 1
B25: =B24+0.1 -> 2.7 | C25: Establishment of site entry & Exit points | I25: 45867 | J25: 0 | K25: =WORKDAY.INTL(I25,J25,1,Data!$C$3:$C$41) -> 45867 | M25: 1 | N25: =_xlfn.LET( _xlpm.s,VALUE(I25), _xlpm.e,VALUE(K25), IF(OR(_xlpm.s="",_xlpm.e=""),"", IF(_xlpm.e<=_xlpm.s, IF(TODAY()>=_xlpm.e,1,0), MAX(0,MIN(1,(TODAY()-_xlpm.s)/(_xlpm.e-_xlpm.s))))) ) -> 1 | S25: =C88 -> Transformer Installation | T25: =I88 -> 45986 | U25: =J88 -> 22 | V25: =F88 -> 43 | W25: =K88 -> 46008 | X25: =M88 -> 1
B26: =B25+0.1 -> 2.8 | C26: Laydown Area Demarcated | I26: 45867 | J26: 0 | K26: =WORKDAY.INTL(I26,J26,1,Data!$C$3:$C$41) -> 45867 | M26: 1 | N26: =_xlfn.LET( _xlpm.s,VALUE(I26), _xlpm.e,VALUE(K26), IF(OR(_xlpm.s="",_xlpm.e=""),"", IF(_xlpm.e<=_xlpm.s, IF(TODAY()>=_xlpm.e,1,0), MAX(0,MIN(1,(TODAY()-_xlpm.s)/(_xlpm.e-_xlpm.s))))) ) -> 1 | S26: =C98 -> Commissioning | T26: =I98 -> 46006 | U26: =J98 -> 59 | V26: =F98 -> 4 | W26: =K98 -> 46065 | X26: =M98 -> 1
B27: =B26+0.1 -> 2.9 | C27: Ground Mount Demarcated | I27: 45867 | J27: 0 | K27: =WORKDAY.INTL(I27,J27,1,Data!$C$3:$C$41) -> 45867 | M27: 1 | N27: =_xlfn.LET( _xlpm.s,VALUE(I27), _xlpm.e,VALUE(K27), IF(OR(_xlpm.s="",_xlpm.e=""),"", IF(_xlpm.e<=_xlpm.s, IF(TODAY()>=_xlpm.e,1,0), MAX(0,MIN(1,(TODAY()-_xlpm.s)/(_xlpm.e-_xlpm.s))))) ) -> 1 | S27: =C110 -> QA Inspection & Snag Completion | T27: =I110 -> 46048 | U27: =J110 -> 29 | V27: =F110 -> 58 | W27: =K110 -> 46077 | X27: =M110 -> 1
B28: 2.1 | C28: Designated area fencing | I28: 45867 | J28: 0 | K28: =WORKDAY.INTL(I28,J28,1,Data!$C$3:$C$41) -> 45867 | M28: 1 | N28: =_xlfn.LET( _xlpm.s,VALUE(I28), _xlpm.e,VALUE(K28), IF(OR(_xlpm.s="",_xlpm.e=""),"", IF(_xlpm.e<=_xlpm.s, IF(TODAY()>=_xlpm.e,1,0), MAX(0,MIN(1,(TODAY()-_xlpm.s)/(_xlpm.e-_xlpm.s))))) ) -> 1 | S28: =C117 -> Project Closure | T28: =I117 -> 46006 | U28: =J117 -> 168 | V28: =F117 -> 70 | W28: =K117 -> 46174 | X28: =M117 -> 0.85571429
B29: 2.11 | C29: Site Ablutions | I29: 45867 | J29: 21 | K29: =WORKDAY.INTL(I29,J29,1,Data!$C$3:$C$41) -> 45896 | M29: 1 | N29: =_xlfn.LET( _xlpm.s,VALUE(I29), _xlpm.e,VALUE(K29), IF(OR(_xlpm.s="",_xlpm.e=""),"", IF(_xlpm.e<=_xlpm.s, IF(TODAY()>=_xlpm.e,1,0), MAX(0,MIN(1,(TODAY()-_xlpm.s)/(_xlpm.e-_xlpm.s))))) ) -> 1 | O29: Appointment finalised by eow
B30: 2.12 | C30: Site Establishment Permit Issued | I30: 45867 | J30: =K30-I30 -> 23 | K30: =K23 -> 45890 | M30: 1 | N30: =_xlfn.LET( _xlpm.s,VALUE(I30), _xlpm.e,VALUE(K30), IF(OR(_xlpm.s="",_xlpm.e=""),"", IF(_xlpm.e<=_xlpm.s, IF(TODAY()>=_xlpm.e,1,0), MAX(0,MIN(1,(TODAY()-_xlpm.s)/(_xlpm.e-_xlpm.s))))) ) -> 1
B32: 3 | C32: Procurement & Contracting | E32: =MIN(E33:E40) -> 45795 | F32: =G32-E32 -> 124 | G32: =MAX(G33:G40) -> 45919 | I32: 45796 | J32: =K32-I32 -> 193 | K32: =MAX(K33:K40) -> 45989 | M32: =AVERAGE(M33:M40) -> 1 | N32: =AVERAGE(N33:N40) -> 1
B33: =B32+0.1 -> 3.1 | C33: Huawei Transformers (16 weeks lead time) | E33: 45795 | F33: 89 | G33: =WORKDAY.INTL(E33,F33,1,Data!$C$3:$C$41) -> 45919 | I33: 45795 | J33: 138 | K33: =WORKDAY.INTL(I33,J33,1,Data!$C$3:$C$41) -> 45989 | M33: 1 | N33: =_xlfn.LET( _xlpm.s,VALUE(I33), _xlpm.e,VALUE(K33), IF(OR(_xlpm.s="",_xlpm.e=""),"", IF(_xlpm.e<=_xlpm.s, IF(TODAY()>=_xlpm.e,1,0), MAX(0,MIN(1,(TODAY()-_xlpm.s)/(_xlpm.e-_xlpm.s))))) ) -> 1 | O33: Delay of shipping as of 14 Oct
B34: =B33+0.1 -> 3.2 | C34: Panels (6 - 8 Weeks) | E34: 45820 | F34: 36 | G34: =WORKDAY.INTL(E34,F34,1,Data!$C$3:$C$41) -> 45873 | I34: 45820 | J34: 93 | K34: =WORKDAY.INTL(I34,J34,1,Data!$C$3:$C$41) -> 45953 | M34: 1 | N34: =_xlfn.LET( _xlpm.s,VALUE(I34), _xlpm.e,VALUE(K34), IF(OR(_xlpm.s="",_xlpm.e=""),"", IF(_xlpm.e<=_xlpm.s, IF(TODAY()>=_xlpm.e,1,0), MAX(0,MIN(1,(TODAY()-_xlpm.s)/(_xlpm.e-_xlpm.s))))) ) -> 1 | O34: 30 pallets deliverd 26/08; 90 pallets 15 Oct; 185 pallets 20 Oct
B35: =B34+0.1 -> 3.3 | C35: Ground Mount Structure (10 Weeks) | E35: 45820 | F35: 58 | G35: =WORKDAY.INTL(E35,F35,1,Data!$C$3:$C$41) -> 45903 | I35: 45820 | J35: 66 | K35: =WORKDAY.INTL(I35,J35,1,Data!$C$3:$C$41) -> 45915 | M35: 1 | N35: =_xlfn.LET( _xlpm.s,VALUE(I35), _xlpm.e,VALUE(K35), IF(OR(_xlpm.s="",_xlpm.e=""),"", IF(_xlpm.e<=_xlpm.s, IF(TODAY()>=_xlpm.e,1,0), MAX(0,MIN(1,(TODAY()-_xlpm.s)/(_xlpm.e-_xlpm.s))))) ) -> 1
B36: =B35+0.1 -> 3.4 | C36: Inverters (8 to 12 weeks) | E36: 45820 | F36: 18 | G36: =WORKDAY.INTL(E36,F36,1,Data!$C$3:$C$41) -> 45847 | I36: 45820 | J36: 18 | K36: =WORKDAY.INTL(I36,J36,1,Data!$C$3:$C$41) -> 45847 | M36: 1 | N36: =_xlfn.LET( _xlpm.s,VALUE(I36), _xlpm.e,VALUE(K36), IF(OR(_xlpm.s="",_xlpm.e=""),"", IF(_xlpm.e<=_xlpm.s, IF(TODAY()>=_xlpm.e,1,0), MAX(0,MIN(1,(TODAY()-_xlpm.s)/(_xlpm.e-_xlpm.s))))) ) -> 1
B37: =B36+0.1 -> 3.5 | C37: DC Cable | E37: 45820 | F37: 18 | G37: =WORKDAY.INTL(E37,F37,1,Data!$C$3:$C$41) -> 45847 | I37: 45820 | J37: 66 | K37: =WORKDAY.INTL(I37,J37,1,Data!$C$3:$C$41) -> 45915 | M37: 1 | N37: =_xlfn.LET( _xlpm.s,VALUE(I37), _xlpm.e,VALUE(K37), IF(OR(_xlpm.s="",_xlpm.e=""),"", IF(_xlpm.e<=_xlpm.s, IF(TODAY()>=_xlpm.e,1,0), MAX(0,MIN(1,(TODAY()-_xlpm.s)/(_xlpm.e-_xlpm.s))))) ) -> 1
B38: =B37+0.1 -> 3.6 | C38: LV Cable (2-4 Weeks) | E38: 45855 | F38: 10 | G38: =WORKDAY.INTL(E38,F38,1,Data!$C$3:$C$41) -> 45869 | I38: 45855 | J38: 10 | K38: =WORKDAY.INTL(I38,J38,1,Data!$C$3:$C$41) -> 45869 | M38: 1 | N38: =_xlfn.LET( _xlpm.s,VALUE(I38), _xlpm.e,VALUE(K38), IF(OR(_xlpm.s="",_xlpm.e=""),"", IF(_xlpm.e<=_xlpm.s, IF(TODAY()>=_xlpm.e,1,0), MAX(0,MIN(1,(TODAY()-_xlpm.s)/(_xlpm.e-_xlpm.s))))) ) -> 1
B39: =B38+0.1 -> 3.7 | C39: MV Cable (2-4 Weeks) | E39: 45855 | F39: 10 | G39: =WORKDAY.INTL(E39,F39,1,Data!$C$3:$C$41) -> 45869 | I39: 45855 | J39: 10 | K39: =WORKDAY.INTL(I39,J39,1,Data!$C$3:$C$41) -> 45869 | M39: 1 | N39: =_xlfn.LET( _xlpm.s,VALUE(I39), _xlpm.e,VALUE(K39), IF(OR(_xlpm.s="",_xlpm.e=""),"", IF(_xlpm.e<=_xlpm.s, IF(TODAY()>=_xlpm.e,1,0), MAX(0,MIN(1,(TODAY()-_xlpm.s)/(_xlpm.e-_xlpm.s))))) ) -> 1
B40: =B39+0.1 -> 3.8 | C40: Distribution Boards (6 - 8 Weeks) | E40: 45848 | F40: 20 | G40: =WORKDAY.INTL(E40,F40,1,Data!$C$3:$C$41) -> 45876 | I40: 45848 | J40: 34 | K40: =WORKDAY.INTL(I40,J40,1,Data!$C$3:$C$41) -> 45896 | M40: 1 | N40: =_xlfn.LET( _xlpm.s,VALUE(I40), _xlpm.e,VALUE(K40), IF(OR(_xlpm.s="",_xlpm.e=""),"", IF(_xlpm.e<=_xlpm.s, IF(TODAY()>=_xlpm.e,1,0), MAX(0,MIN(1,(TODAY()-_xlpm.s)/(_xlpm.e-_xlpm.s))))) ) -> 1 | O40: ABB hold up on the breakers
B42: 4 | C42: Extras & Civil Works | E42: =MIN(E43:E56) -> 45830 | F42: =G42-E42 -> 71 | G42: =MAX(G43:G56) -> 45901 | I42: =MIN(I43:I56) -> 45830 | J42: =K42-I42 -> 212 | K42: =MAX(K43:K56) -> 46042 | M42: =AVERAGE(M43:M56) -> 1 | N42: =AVERAGE(N43:N56) -> 1
B43: =B42+0.1 -> 4.1 | C43: Staircase Installation - Coega Scope | I43: 45830 | J43: 61 | K43: =WORKDAY.INTL(I43,J43,1,Data!$C$3:$C$41) -> 45915 | M43: 1 | N43: =_xlfn.LET( _xlpm.s,VALUE(I43), _xlpm.e,VALUE(K43), IF(OR(_xlpm.s="",_xlpm.e=""),"", IF(_xlpm.e<=_xlpm.s, IF(TODAY()>=_xlpm.e,1,0), MAX(0,MIN(1,(TODAY()-_xlpm.s)/(_xlpm.e-_xlpm.s))))) ) -> 1 | O43: Follow up with Coega
B44: =B43+0.1 -> 4.2 | C44: Ground Mount Fence - Coega Scope | E44: 45830 | F44: 42 | G44: =WORKDAY.INTL(E44,F44,1,Data!$C$3:$C$41) -> 45888 | I44: 45830 | J44: 135 | K44: =WORKDAY.INTL(I44,J44,1,Data!$C$3:$C$41) -> 46042 | M44: 1 | N44: =_xlfn.LET( _xlpm.s,VALUE(I44), _xlpm.e,VALUE(K44), IF(OR(_xlpm.s="",_xlpm.e=""),"", IF(_xlpm.e<=_xlpm.s, IF(TODAY()>=_xlpm.e,1,0), MAX(0,MIN(1,(TODAY()-_xlpm.s)/(_xlpm.e-_xlpm.s))))) ) -> 1 | O44: Resuming 01 Oct
B45: =B44+0.1 -> 4.3 | C45: Catladder Fabrication | E45: 45854 | F45: 15 | G45: =WORKDAY.INTL(E45,F45,1,Data!$C$3:$C$41) -> 45875 | I45: 45854 | J45: 31 | K45: =WORKDAY.INTL(I45,J45,1,Data!$C$3:$C$41) -> 45897 | M45: 1 | N45: =_xlfn.LET( _xlpm.s,VALUE(I45), _xlpm.e,VALUE(K45), IF(OR(_xlpm.s="",_xlpm.e=""),"", IF(_xlpm.e<=_xlpm.s, IF(TODAY()>=_xlpm.e,1,0), MAX(0,MIN(1,(TODAY()-_xlpm.s)/(_xlpm.e-_xlpm.s))))) ) -> 1
B46: =B45+0.1 -> 4.4 | C46: Catladder Installation | E46: =WORKDAY.INTL(G45,0,1,Data!$C$3:$C$41) -> 45875 | F46: 5 | G46: =WORKDAY.INTL(E46,F46,1,Data!$C$3:$C$41) -> 45882 | I46: =K22+3 -> 45913 | J46: 15 | K46: =WORKDAY.INTL(I46,J46,1,Data!$C$3:$C$41) -> 45936 | M46: 1 | N46: =_xlfn.LET( _xlpm.s,VALUE(I46), _xlpm.e,VALUE(K46), IF(OR(_xlpm.s="",_xlpm.e=""),"", IF(_xlpm.e<=_xlpm.s, IF(TODAY()>=_xlpm.e,1,0), MAX(0,MIN(1,(TODAY()-_xlpm.s)/(_xlpm.e-_xlpm.s))))) ) -> 1 | O46: Awaiting sign off form Subbie
B47: =B46+0.1 -> 4.5 | C47: Rooftop Inverter Cage Fabrication | E47: 45873 | F47: 15 | G47: =WORKDAY.INTL(E47,F47,1,Data!$C$3:$C$41) -> 45894 | I47: 45947 | J47: 19 | K47: =WORKDAY.INTL(I47,J47,1,Data!$C$3:$C$41) -> 45974 | M47: 1 | N47: =_xlfn.LET( _xlpm.s,VALUE(I47), _xlpm.e,VALUE(K47), IF(OR(_xlpm.s="",_xlpm.e=""),"", IF(_xlpm.e<=_xlpm.s, IF(TODAY()>=_xlpm.e,1,0), MAX(0,MIN(1,(TODAY()-_xlpm.s)/(_xlpm.e-_xlpm.s))))) ) -> 1
B48: =B47+0.1 -> 4.6 | C48: Rooftop Inverter Cage Installation | E48: =WORKDAY.INTL(G47,0,1,Data!$C$3:$C$41) -> 45894 | F48: 5 | G48: =WORKDAY.INTL(E48,F48,1,Data!$C$3:$C$41) -> 45901 | I48: =WORKDAY.INTL(K47,0,1,Data!$C$3:$C$41) -> 45974 | J48: 5 | K48: =WORKDAY.INTL(I48,J48,1,Data!$C$3:$C$41) -> 45981 | M48: 1 | N48: =_xlfn.LET( _xlpm.s,VALUE(I48), _xlpm.e,VALUE(K48), IF(OR(_xlpm.s="",_xlpm.e=""),"", IF(_xlpm.e<=_xlpm.s, IF(TODAY()>=_xlpm.e,1,0), MAX(0,MIN(1,(TODAY()-_xlpm.s)/(_xlpm.e-_xlpm.s))))) ) -> 1
B49: =B48+0.1 -> 4.7 | C49: Plinths - Casting & Curing | E49: 45880 | F49: 15 | G49: =WORKDAY.INTL(E49,F49,1,Data!$C$3:$C$41) -> 45901 | I49: 45953 | J49: 32 | K49: =WORKDAY.INTL(I49,J49,1,Data!$C$3:$C$41) -> 45999 | M49: 1 | N49: =_xlfn.LET( _xlpm.s,VALUE(I49), _xlpm.e,VALUE(K49), IF(OR(_xlpm.s="",_xlpm.e=""),"", IF(_xlpm.e<=_xlpm.s, IF(TODAY()>=_xlpm.e,1,0), MAX(0,MIN(1,(TODAY()-_xlpm.s)/(_xlpm.e-_xlpm.s))))) ) -> 1
B50: =B49+0.1 -> 4.8 | C50: Walkway Installation | E50: =WORKDAY.INTL(G51,0,1,Data!$C$3:$C$41)-2 -> 45878 | F50: 5 | G50: =WORKDAY.INTL(E50,F50,1,Data!$C$3:$C$41) -> 45884 | I50: =WORKDAY.INTL(I51,0,1,Data!$C$3:$C$41)+5 -> 45899 | J50: 10 | K50: =WORKDAY.INTL(I50,J50,1,Data!$C$3:$C$41) -> 45912 | M50: 1 | N50: =_xlfn.LET( _xlpm.s,VALUE(I50), _xlpm.e,VALUE(K50), IF(OR(_xlpm.s="",_xlpm.e=""),"", IF(_xlpm.e<=_xlpm.s, IF(TODAY()>=_xlpm.e,1,0), MAX(0,MIN(1,(TODAY()-_xlpm.s)/(_xlpm.e-_xlpm.s))))) ) -> 1 | O50: Complete on Furnance, staring on mill
B51: =B50+0.1 -> 4.9 | C51: Anchor Point Installation | E51: 45873 | F51: 5 | G51: =WORKDAY.INTL(E51,F51,1,Data!$C$3:$C$41) -> 45880 | I51: 45894 | J51: 7 | K51: =WORKDAY.INTL(I51,J51,1,Data!$C$3:$C$41) -> 45903 | M51: 1 | N51: =_xlfn.LET( _xlpm.s,VALUE(I51), _xlpm.e,VALUE(K51), IF(OR(_xlpm.s="",_xlpm.e=""),"", IF(_xlpm.e<=_xlpm.s, IF(TODAY()>=_xlpm.e,1,0), MAX(0,MIN(1,(TODAY()-_xlpm.s)/(_xlpm.e-_xlpm.s))))) ) -> 1
B52: 4.1 | C52: Optic Fiber Installation | I52: 45994 | J52: 2 | K52: =WORKDAY.INTL(I52,J52,1,Data!$C$3:$C$41) -> 45996 | M52: 1 | N52: =_xlfn.LET( _xlpm.s,VALUE(I52), _xlpm.e,VALUE(K52), IF(OR(_xlpm.s="",_xlpm.e=""),"", IF(_xlpm.e<=_xlpm.s, IF(TODAY()>=_xlpm.e,1,0), MAX(0,MIN(1,(TODAY()-_xlpm.s)/(_xlpm.e-_xlpm.s))))) ) -> 1
B53: 4.11 | C53: Trenching - Fiber | M53: 1 | N53: =_xlfn.LET( _xlpm.s,VALUE(I53), _xlpm.e,VALUE(K53), IF(OR(_xlpm.s="",_xlpm.e=""),"", IF(_xlpm.e<=_xlpm.s, IF(TODAY()>=_xlpm.e,1,0), MAX(0,MIN(1,(TODAY()-_xlpm.s)/(_xlpm.e-_xlpm.s))))) ) -> 1
B54: 4.12 | C54: Directional Drilling | M54: 1 | N54: =_xlfn.LET( _xlpm.s,VALUE(I54), _xlpm.e,VALUE(K54), IF(OR(_xlpm.s="",_xlpm.e=""),"", IF(_xlpm.e<=_xlpm.s, IF(TODAY()>=_xlpm.e,1,0), MAX(0,MIN(1,(TODAY()-_xlpm.s)/(_xlpm.e-_xlpm.s))))) ) -> 1
B55: 4.13 | C55: Trenching - Ground Mount to Mill | M55: 1 | N55: =_xlfn.LET( _xlpm.s,VALUE(I55), _xlpm.e,VALUE(K55), IF(OR(_xlpm.s="",_xlpm.e=""),"", IF(_xlpm.e<=_xlpm.s, IF(TODAY()>=_xlpm.e,1,0), MAX(0,MIN(1,(TODAY()-_xlpm.s)/(_xlpm.e-_xlpm.s))))) ) -> 1
B56: 4.14 | C56: Trenching - Furnance & Mill - Coega Scope | I56: 45992 | J56: 12 | K56: =WORKDAY.INTL(I56,J56,1,Data!$C$3:$C$41) -> 46008 | M56: 1 | N56: =_xlfn.LET( _xlpm.s,VALUE(I56), _xlpm.e,VALUE(K56), IF(OR(_xlpm.s="",_xlpm.e=""),"", IF(_xlpm.e<=_xlpm.s, IF(TODAY()>=_xlpm.e,1,0), MAX(0,MIN(1,(TODAY()-_xlpm.s)/(_xlpm.e-_xlpm.s))))) ) -> 1 | O56: Direct impact on pulling strings from the furnance to the mill. Impacts approx. 1,6MW
B58: 5 | C58: DC Works - Rooftop | E58: =MIN(E60:E64) -> 45878 | F58: =G58-E58 -> 51 | G58: =MAX(G60:G64) -> 45929 | I58: =MIN(I60:I64) -> 45894 | J58: =K58-I58 -> 147 | K58: =MAX(K60:K64) -> 46041 | M58: =AVERAGE(M59:M64) -> 1 | N58: =AVERAGE(N59:N64) -> 1
B59: 5.1 | C59: Mounting Structure delivered | E59: 45835 | F59: 1 | G59: =WORKDAY.INTL(E59,F59,1,Data!$C$3:$C$41) -> 45838 | I59: 45835 | J59: 1 | K59: =WORKDAY.INTL(I59,J59,1,Data!$C$3:$C$41) -> 45838 | M59: 1 | N59: =_xlfn.LET( _xlpm.s,VALUE(I59), _xlpm.e,VALUE(K59), IF(OR(_xlpm.s="",_xlpm.e=""),"", IF(_xlpm.e<=_xlpm.s, IF(TODAY()>=_xlpm.e,1,0), MAX(0,MIN(1,(TODAY()-_xlpm.s)/(_xlpm.e-_xlpm.s))))) ) -> 1
B60: 5.2 | C60: Mounting Structure installation - Frunance | E60: =WORKDAY.INTL(G51,0,1,Data!$C$3:$C$41)-2 -> 45878 | F60: 12 | G60: =WORKDAY.INTL(E60,F60,1,Data!$C$3:$C$41) -> 45895 | I60: 45894 | J60: 5 | K60: =WORKDAY.INTL(I60,J60,1,Data!$C$3:$C$41) -> 45901 | M60: 1 | N60: =_xlfn.LET( _xlpm.s,VALUE(I60), _xlpm.e,VALUE(K60), IF(OR(_xlpm.s="",_xlpm.e=""),"", IF(_xlpm.e<=_xlpm.s, IF(TODAY()>=_xlpm.e,1,0), MAX(0,MIN(1,(TODAY()-_xlpm.s)/(_xlpm.e-_xlpm.s))))) ) -> 1
B61: 5.3 | C61: Mounting Structure installation - Mill | I61: 45901 | J61: 5 | K61: =WORKDAY.INTL(I61,J61,1,Data!$C$3:$C$41) -> 45908 | M61: 1 | N61: =_xlfn.LET( _xlpm.s,VALUE(I61), _xlpm.e,VALUE(K61), IF(OR(_xlpm.s="",_xlpm.e=""),"", IF(_xlpm.e<=_xlpm.s, IF(TODAY()>=_xlpm.e,1,0), MAX(0,MIN(1,(TODAY()-_xlpm.s)/(_xlpm.e-_xlpm.s))))) ) -> 1
B62: 5.4 | C62: Panel Installation - Furnace | E62: =WORKDAY.INTL(G60,0,1,Data!$C$3:$C$41)+1 -> 45896 | F62: 17 | G62: =WORKDAY.INTL(E62,F62,1,Data!$C$3:$C$41) -> 45919 | I62: 45915 | J62: 24 | K62: =WORKDAY.INTL(I62,J62,1,Data!$C$3:$C$41) -> 45950 | M62: 1 | N62: =_xlfn.LET( _xlpm.s,VALUE(I62), _xlpm.e,VALUE(K62), IF(OR(_xlpm.s="",_xlpm.e=""),"", IF(_xlpm.e<=_xlpm.s, IF(TODAY()>=_xlpm.e,1,0), MAX(0,MIN(1,(TODAY()-_xlpm.s)/(_xlpm.e-_xlpm.s))))) ) -> 1 | O62: Waiting for delivery of panels
B63: 5.5 | C63: Panel Installation - Mill | I63: 45951 | J63: 22 | K63: =WORKDAY.INTL(I63,J63,1,Data!$C$3:$C$41) -> 45981 | M63: 1 | N63: =_xlfn.LET( _xlpm.s,VALUE(I63), _xlpm.e,VALUE(K63), IF(OR(_xlpm.s="",_xlpm.e=""),"", IF(_xlpm.e<=_xlpm.s, IF(TODAY()>=_xlpm.e,1,0), MAX(0,MIN(1,(TODAY()-_xlpm.s)/(_xlpm.e-_xlpm.s))))) ) -> 1 | O63: Roof risk delayed
B64: 5.6 | C64: DC Stringing - Furnace | E64: =WORKDAY.INTL(G62,0,1,Data!$C$3:$C$41)+2 -> 45921 | F64: 5 | G64: =WORKDAY.INTL(E64,F64,1,Data!$C$3:$C$41) -> 45929 | I64: 45940 | J64: 55 | K64: =WORKDAY.INTL(I64,J64,1,Data!$C$3:$C$41) -> 46041 | M64: 1 | N64: =_xlfn.LET( _xlpm.s,VALUE(I64), _xlpm.e,VALUE(K64), IF(OR(_xlpm.s="",_xlpm.e=""),"", IF(_xlpm.e<=_xlpm.s, IF(TODAY()>=_xlpm.e,1,0), MAX(0,MIN(1,(TODAY()-_xlpm.s)/(_xlpm.e-_xlpm.s))))) ) -> 1
B65: 5.7 | C65: DC Stringing - Mill | I65: 45929 | J65: 9 | K65: =WORKDAY.INTL(I65,J65,1,Data!$C$3:$C$41) -> 45940 | M65: 1 | N65: =_xlfn.LET( _xlpm.s,VALUE(I65), _xlpm.e,VALUE(K65), IF(OR(_xlpm.s="",_xlpm.e=""),"", IF(_xlpm.e<=_xlpm.s, IF(TODAY()>=_xlpm.e,1,0), MAX(0,MIN(1,(TODAY()-_xlpm.s)/(_xlpm.e-_xlpm.s))))) ) -> 1
B67: 6 | C67: DC Works - Ground Mount | E67: =MIN(E68:E71) -> 45894 | F67: =G67-E67 -> 58 | G67: =MAX(G68:G71) -> 45952 | I67: =MIN(I68:I71) -> 45938 | J67: =K67-I67 -> 120 | K67: =MAX(K68:K72) -> 46058 | M67: =AVERAGE(M68:M72) -> 1 | N67: =AVERAGE(N68:N72) -> 1
B68: 6.1 | C68: Drilling | E68: 45894 | F68: 7 | G68: =WORKDAY.INTL(E68,F68,1,Data!$C$3:$C$41) -> 45903 | I68: 45938 | J68: 34 | K68: =WORKDAY.INTL(I68,J68,1,Data!$C$3:$C$41) -> 45986 | M68: 1 | N68: =_xlfn.LET( _xlpm.s,VALUE(I68), _xlpm.e,VALUE(K68), IF(OR(_xlpm.s="",_xlpm.e=""),"", IF(_xlpm.e<=_xlpm.s, IF(TODAY()>=_xlpm.e,1,0), MAX(0,MIN(1,(TODAY()-_xlpm.s)/(_xlpm.e-_xlpm.s))))) ) -> 1 | O68: 1. Top layer soil was building rubble. 2. Levelling and approval of installation took 4 weeks longer than intially communicated by Coega. 3. Baseline date was 12 Sept 2025, Bayview only started 08 Oct 2025. 4. This has caused a 4 week delay.
B69: 6.2 | C69: Pillar Installation | E69: =WORKDAY.INTL(G68,0,1,Data!$C$3:$C$41) -> 45903 | F69: 7 | G69: =WORKDAY.INTL(E69,F69,1,Data!$C$3:$C$41) -> 45912 | I69: 45956 | J69: 37 | K69: =WORKDAY.INTL(I69,J69,1,Data!$C$3:$C$41) -> 46007 | M69: 1 | N69: =_xlfn.LET( _xlpm.s,VALUE(I69), _xlpm.e,VALUE(K69), IF(OR(_xlpm.s="",_xlpm.e=""),"", IF(_xlpm.e<=_xlpm.s, IF(TODAY()>=_xlpm.e,1,0), MAX(0,MIN(1,(TODAY()-_xlpm.s)/(_xlpm.e-_xlpm.s))))) ) -> 1 | O69: Busy with the north facing pillars
B70: 6.3 | C70: Structure Installation | E70: 45915 | F70: 14 | G70: =WORKDAY.INTL(E70,F70,1,Data!$C$3:$C$41) -> 45936 | I70: 45963 | J70: 42 | K70: =WORKDAY.INTL(I70,J70,1,Data!$C$3:$C$41) -> 46043 | M70: 1 | N70: =_xlfn.LET( _xlpm.s,VALUE(I70), _xlpm.e,VALUE(K70), IF(OR(_xlpm.s="",_xlpm.e=""),"", IF(_xlpm.e<=_xlpm.s, IF(TODAY()>=_xlpm.e,1,0), MAX(0,MIN(1,(TODAY()-_xlpm.s)/(_xlpm.e-_xlpm.s))))) ) -> 1
B71: 6.4 | C71: Panel Installation | E71: =WORKDAY.INTL(G70,0,1,Data!$C$3:$C$41)+2 -> 45938 | F71: 10 | G71: =WORKDAY.INTL(E71,F71,1,Data!$C$3:$C$41) -> 45952 | I71: 45985 | J71: 33 | K71: =WORKDAY.INTL(I71,J71,1,Data!$C$3:$C$41) -> 46052 | M71: 1 | N71: =_xlfn.LET( _xlpm.s,VALUE(I71), _xlpm.e,VALUE(K71), IF(OR(_xlpm.s="",_xlpm.e=""),"", IF(_xlpm.e<=_xlpm.s, IF(TODAY()>=_xlpm.e,1,0), MAX(0,MIN(1,(TODAY()-_xlpm.s)/(_xlpm.e-_xlpm.s))))) ) -> 1
B72: 6.5 | C72: DC Stringing | E72: =WORKDAY.INTL(G71,0,1,Data!$C$3:$C$41)+2 -> 45954 | F72: 10 | G72: =WORKDAY.INTL(E72,F72,1,Data!$C$3:$C$41) -> 45968 | I72: =K70-20 -> 46023 | J72: 18 | K72: =WORKDAY.INTL(I72,J72,1,Data!$C$3:$C$41) -> 46058 | M72: 1 | N72: =_xlfn.LET( _xlpm.s,VALUE(I72), _xlpm.e,VALUE(K72), IF(OR(_xlpm.s="",_xlpm.e=""),"", IF(_xlpm.e<=_xlpm.s, IF(TODAY()>=_xlpm.e,1,0), MAX(0,MIN(1,(TODAY()-_xlpm.s)/(_xlpm.e-_xlpm.s))))) ) -> 1
B74: 7 | C74: AC Installation - Ground Mount | E74: =MIN(E76:E79) -> 45945 | F74: =G74-E74 -> 26 | G74: =MAX(G75:G79) -> 45971 | I74: =MIN(I76:I79) -> 45990 | J74: =K74-I74 -> 17 | K74: =MAX(K75:K79) -> 46007 | M74: =AVERAGE(M75:M79) -> 1 | N74: =AVERAGE(N75:N79) -> 1
B75: 7.1 | C75: Inverters Delivered | E75: 45848 | F75: 1 | G75: =E75+F75 -> 45849 | I75: 45848 | J75: 1 | K75: =I75+J75 -> 45849 | M75: 1 | N75: =_xlfn.LET( _xlpm.s,VALUE(I75), _xlpm.e,VALUE(K75), IF(OR(_xlpm.s="",_xlpm.e=""),"", IF(_xlpm.e<=_xlpm.s, IF(TODAY()>=_xlpm.e,1,0), MAX(0,MIN(1,(TODAY()-_xlpm.s)/(_xlpm.e-_xlpm.s))))) ) -> 1
B76: 7.2 | C76: Inverters Mounted | E76: 45945 | F76: 6 | G76: =WORKDAY.INTL(E76,F76,1,Data!$C$3:$C$41) -> 45953 | I76: 45990 | J76: 4 | K76: =WORKDAY.INTL(I76,J76,1,Data!$C$3:$C$41) -> 45995 | M76: 1 | N76: =_xlfn.LET( _xlpm.s,VALUE(I76), _xlpm.e,VALUE(K76), IF(OR(_xlpm.s="",_xlpm.e=""),"", IF(_xlpm.e<=_xlpm.s, IF(TODAY()>=_xlpm.e,1,0), MAX(0,MIN(1,(TODAY()-_xlpm.s)/(_xlpm.e-_xlpm.s))))) ) -> 1
B77: 7.3 | C77: DB Placement | E77: =WORKDAY.INTL(G76,0,1,Data!$C$3:$C$41) -> 45953 | F77: 2 | G77: =WORKDAY.INTL(E77,F77,1,Data!$C$3:$C$41) -> 45957 | I77: =WORKDAY.INTL(I76,0,1,Data!$C$3:$C$41) -> 45990 | J77: 4 | K77: =WORKDAY.INTL(I77,J77,1,Data!$C$3:$C$41) -> 45995 | M77: 1 | N77: =_xlfn.LET( _xlpm.s,VALUE(I77), _xlpm.e,VALUE(K77), IF(OR(_xlpm.s="",_xlpm.e=""),"", IF(_xlpm.e<=_xlpm.s, IF(TODAY()>=_xlpm.e,1,0), MAX(0,MIN(1,(TODAY()-_xlpm.s)/(_xlpm.e-_xlpm.s))))) ) -> 1
B78: 7.4 | C78: Cabling - Inverter to DB | E78: =WORKDAY.INTL(G77,0,1,Data!$C$3:$C$41) -> 45957 | F78: 5 | G78: =WORKDAY.INTL(E78,F78,1,Data!$C$3:$C$41) -> 45964 | I78: =WORKDAY.INTL(K77,0,1,Data!$C$3:$C$41) -> 45995 | J78: 5 | K78: =WORKDAY.INTL(I78,J78,1,Data!$C$3:$C$41) -> 46002 | M78: 1 | N78: =_xlfn.LET( _xlpm.s,VALUE(I78), _xlpm.e,VALUE(K78), IF(OR(_xlpm.s="",_xlpm.e=""),"", IF(_xlpm.e<=_xlpm.s, IF(TODAY()>=_xlpm.e,1,0), MAX(0,MIN(1,(TODAY()-_xlpm.s)/(_xlpm.e-_xlpm.s))))) ) -> 1
B79: 7.5 | C79: Cabling - DB to Transformer | E79: =WORKDAY.INTL(G78,0,1,Data!$C$3:$C$41) -> 45964 | F79: 5 | G79: =WORKDAY.INTL(E79,F79,1,Data!$C$3:$C$41) -> 45971 | I79: =WORKDAY.INTL(K76,0,1,Data!$C$3:$C$41) -> 45995 | J79: 8 | K79: =WORKDAY.INTL(I79,J79,1,Data!$C$3:$C$41) -> 46007 | M79: 1 | N79: =_xlfn.LET( _xlpm.s,VALUE(I79), _xlpm.e,VALUE(K79), IF(OR(_xlpm.s="",_xlpm.e=""),"", IF(_xlpm.e<=_xlpm.s, IF(TODAY()>=_xlpm.e,1,0), MAX(0,MIN(1,(TODAY()-_xlpm.s)/(_xlpm.e-_xlpm.s))))) ) -> 1
B81: 8 | C81: AC Installation - Rooftop | E81: =MIN(E83:E86) -> 45950 | F81: =G81-E81 -> 21 | G81: =MAX(G82:G86) -> 45971 | I81: =MIN(I83:I86) -> 45915 | J81: =K81-I81 -> 92 | K81: =MAX(K82:K86) -> 46007 | M81: =AVERAGE(M82:M86) -> 1 | N81: =AVERAGE(N82:N86) -> 1
B82: 8.1 | C82: Inverters Delivered | E82: 45848 | F82: 1 | G82: =E82+F82 -> 45849 | I82: 45848 | J82: 1 | K82: =I82+J82 -> 45849 | M82: 1 | N82: =_xlfn.LET( _xlpm.s,VALUE(I82), _xlpm.e,VALUE(K82), IF(OR(_xlpm.s="",_xlpm.e=""),"", IF(_xlpm.e<=_xlpm.s, IF(TODAY()>=_xlpm.e,1,0), MAX(0,MIN(1,(TODAY()-_xlpm.s)/(_xlpm.e-_xlpm.s))))) ) -> 1
B83: 8.2 | C83: Inverters Mounted | E83: 45950 | F83: 4 | G83: =WORKDAY.INTL(E83,F83,1,Data!$C$3:$C$41) -> 45954 | I83: 45915 | J83: 3 | K83: =WORKDAY.INTL(I83,J83,1,Data!$C$3:$C$41) -> 45918 | M83: 1 | N83: 1
B84: 8.3 | C84: DB Placement | E84: =WORKDAY.INTL(G83,0,1,Data!$C$3:$C$41) -> 45954 | F84: 2 | G84: =WORKDAY.INTL(E84,F84,1,Data!$C$3:$C$41) -> 45958 | I84: =WORKDAY.INTL(K83,0,1,Data!$C$3:$C$41) -> 45918 | J84: 2 | K84: =WORKDAY.INTL(I84,J84,1,Data!$C$3:$C$41) -> 45922 | M84: 1 | N84: =_xlfn.LET( _xlpm.s,VALUE(I84), _xlpm.e,VALUE(K84), IF(OR(_xlpm.s="",_xlpm.e=""),"", IF(_xlpm.e<=_xlpm.s, IF(TODAY()>=_xlpm.e,1,0), MAX(0,MIN(1,(TODAY()-_xlpm.s)/(_xlpm.e-_xlpm.s))))) ) -> 1
B85: 8.4 | C85: Cabling - Inverter to DB | E85: =WORKDAY.INTL(G84,0,1,Data!$C$3:$C$41) -> 45958 | F85: 4 | G85: =WORKDAY.INTL(E85,F85,1,Data!$C$3:$C$41) -> 45964 | I85: =WORKDAY.INTL(K84,0,1,Data!$C$3:$C$41) -> 45922 | J85: 7 | K85: =WORKDAY.INTL(I85,J85,1,Data!$C$3:$C$41) -> 45932 | M85: 1 | N85: =_xlfn.LET( _xlpm.s,VALUE(I85), _xlpm.e,VALUE(K85), IF(OR(_xlpm.s="",_xlpm.e=""),"", IF(_xlpm.e<=_xlpm.s, IF(TODAY()>=_xlpm.e,1,0), MAX(0,MIN(1,(TODAY()-_xlpm.s)/(_xlpm.e-_xlpm.s))))) ) -> 1
B86: 8.5 | C86: Cabling - DB to Transformer | E86: =WORKDAY.INTL(G85,0,1,Data!$C$3:$C$41) -> 45964 | F86: 5 | G86: =WORKDAY.INTL(E86,F86,1,Data!$C$3:$C$41) -> 45971 | I86: =WORKDAY.INTL(K49,0,1,Data!$C$3:$C$41) -> 45999 | J86: 6 | K86: =WORKDAY.INTL(I86,J86,1,Data!$C$3:$C$41) -> 46007 | M86: 1 | N86: =_xlfn.LET( _xlpm.s,VALUE(I86), _xlpm.e,VALUE(K86), IF(OR(_xlpm.s="",_xlpm.e=""),"", IF(_xlpm.e<=_xlpm.s, IF(TODAY()>=_xlpm.e,1,0), MAX(0,MIN(1,(TODAY()-_xlpm.s)/(_xlpm.e-_xlpm.s))))) ) -> 1
B88: 9 | C88: Transformer Installation | E88: =MIN(E89:E96) -> 45922 | F88: =G88-E88 -> 43 | G88: =MAX(G89:G96) -> 45965 | I88: =MIN(I89:I96) -> 45986 | J88: =K88-I88 -> 22 | K88: =MAX(K89:K96) -> 46008 | M88: =AVERAGE(M89:M96) -> 1 | N88: =AVERAGE(N89:N96) -> 1
B89: 9.1 | C89: Transformer Offloading | E89: 45922 | F89: 2 | G89: =WORKDAY.INTL(E89,F89,1,Data!$C$3:$C$41) -> 45925 | I89: =K33-1 -> 45988 | J89: 1 | K89: =WORKDAY.INTL(I89,J89,1,Data!$C$3:$C$41) -> 45989 | M89: 1 | N89: =_xlfn.LET( _xlpm.s,VALUE(I89), _xlpm.e,VALUE(K89), IF(OR(_xlpm.s="",_xlpm.e=""),"", IF(_xlpm.e<=_xlpm.s, IF(TODAY()>=_xlpm.e,1,0), MAX(0,MIN(1,(TODAY()-_xlpm.s)/(_xlpm.e-_xlpm.s))))) ) -> 1
C90: Transformer Rigging risk assessment and offloading plan | I90: 45986 | J90: 4 | K90: =WORKDAY.INTL(I90,J90,1,Data!$C$3:$C$41) -> 45992 | M90: 1 | N90: =_xlfn.LET( _xlpm.s,VALUE(I90), _xlpm.e,VALUE(K90), IF(OR(_xlpm.s="",_xlpm.e=""),"", IF(_xlpm.e<=_xlpm.s, IF(TODAY()>=_xlpm.e,1,0), MAX(0,MIN(1,(TODAY()-_xlpm.s)/(_xlpm.e-_xlpm.s))))) ) -> 1
B91: =B89+0.1 -> 9.2 | C91: Transformer 1 - MV - Install MV cabling | E91: 45953 | F91: 2 | G91: =WORKDAY.INTL(E91,F91,1,Data!$C$3:$C$41) -> 45957 | I91: =K78-7 -> 45995 | J91: 2 | K91: =WORKDAY.INTL(I91,J91,1,Data!$C$3:$C$41) -> 45999 | M91: 1 | N91: =_xlfn.LET( _xlpm.s,VALUE(I91), _xlpm.e,VALUE(K91), IF(OR(_xlpm.s="",_xlpm.e=""),"", IF(_xlpm.e<=_xlpm.s, IF(TODAY()>=_xlpm.e,1,0), MAX(0,MIN(1,(TODAY()-_xlpm.s)/(_xlpm.e-_xlpm.s))))) ) -> 1
B92: =B91+0.1 -> 9.3 | C92: Transformer 1 - MV - Terminate and connect cabling at RMU - Assuming Coega has the tie in breaker ready | E92: =WORKDAY.INTL(G91,0,1,Data!$C$3:$C$41) -> 45957 | F92: 0 | G92: =WORKDAY.INTL(E92,F92,1,Data!$C$3:$C$41) -> 45957 | I92: 46002 | J92: 0 | K92: =WORKDAY.INTL(I92,J92,1,Data!$C$3:$C$41) -> 46002 | M92: 1 | N92: =_xlfn.LET( _xlpm.s,VALUE(I92), _xlpm.e,VALUE(K92), IF(OR(_xlpm.s="",_xlpm.e=""),"", IF(_xlpm.e<=_xlpm.s, IF(TODAY()>=_xlpm.e,1,0), MAX(0,MIN(1,(TODAY()-_xlpm.s)/(_xlpm.e-_xlpm.s))))) ) -> 1
B93: =B92+0.1 -> 9.4 | C93: Transformer 1 - MV - Cable pressure testing and protection calibrations | E93: =WORKDAY.INTL(G92,0,1,Data!$C$3:$C$41) -> 45957 | F93: 2 | G93: =WORKDAY.INTL(E93,F93,1,Data!$C$3:$C$41) -> 45959 | I93: =WORKDAY.INTL(K92,0,1,Data!$C$3:$C$41) -> 46002 | J93: 2 | K93: =WORKDAY.INTL(I93,J93,1,Data!$C$3:$C$41) -> 46006 | M93: 1 | N93: =_xlfn.LET( _xlpm.s,VALUE(I93), _xlpm.e,VALUE(K93), IF(OR(_xlpm.s="",_xlpm.e=""),"", IF(_xlpm.e<=_xlpm.s, IF(TODAY()>=_xlpm.e,1,0), MAX(0,MIN(1,(TODAY()-_xlpm.s)/(_xlpm.e-_xlpm.s))))) ) -> 1
B94: =B93+0.1 -> 9.5 | C94: Transformer 2 - MV - Install MV cabling | E94: =WORKDAY.INTL(G93,0,1,Data!$C$3:$C$41) -> 45959 | F94: 2 | G94: =WORKDAY.INTL(E94,F94,1,Data!$C$3:$C$41) -> 45961 | I94: =WORKDAY.INTL(K93,0,1,Data!$C$3:$C$41) -> 46006 | J94: 2 | K94: =WORKDAY.INTL(I94,J94,1,Data!$C$3:$C$41) -> 46008 | M94: 1 | N94: =_xlfn.LET( _xlpm.s,VALUE(I94), _xlpm.e,VALUE(K94), IF(OR(_xlpm.s="",_xlpm.e=""),"", IF(_xlpm.e<=_xlpm.s, IF(TODAY()>=_xlpm.e,1,0), MAX(0,MIN(1,(TODAY()-_xlpm.s)/(_xlpm.e-_xlpm.s))))) ) -> 1
B95: =B94+0.1 -> 9.6 | C95: Transformer 2 - MV - Terminate and connect cabling at RMU | E95: =WORKDAY.INTL(G94,0,1,Data!$C$3:$C$41) -> 45961 | F95: 0 | G95: =WORKDAY.INTL(E95,F95,1,Data!$C$3:$C$41) -> 45961 | I95: =WORKDAY.INTL(K94,0,1,Data!$C$3:$C$41)-2 -> 46006 | J95: 0 | K95: =WORKDAY.INTL(I95,J95,1,Data!$C$3:$C$41) -> 46006 | M95: 1 | N95: =_xlfn.LET( _xlpm.s,VALUE(I95), _xlpm.e,VALUE(K95), IF(OR(_xlpm.s="",_xlpm.e=""),"", IF(_xlpm.e<=_xlpm.s, IF(TODAY()>=_xlpm.e,1,0), MAX(0,MIN(1,(TODAY()-_xlpm.s)/(_xlpm.e-_xlpm.s))))) ) -> 1
B96: =B95+0.1 -> 9.7 | C96: Transformer 2 - MV - Cable pressure testing and protection calibrations | E96: =WORKDAY.INTL(G95,0,1,Data!$C$3:$C$41) -> 45961 | F96: 2 | G96: =WORKDAY.INTL(E96,F96,1,Data!$C$3:$C$41) -> 45965 | I96: =WORKDAY.INTL(K95,0,1,Data!$C$3:$C$41) -> 46006 | J96: 2 | K96: =WORKDAY.INTL(I96,J96,1,Data!$C$3:$C$41) -> 46008 | M96: 1 | N96: =_xlfn.LET( _xlpm.s,VALUE(I96), _xlpm.e,VALUE(K96), IF(OR(_xlpm.s="",_xlpm.e=""),"", IF(_xlpm.e<=_xlpm.s, IF(TODAY()>=_xlpm.e,1,0), MAX(0,MIN(1,(TODAY()-_xlpm.s)/(_xlpm.e-_xlpm.s))))) ) -> 1
B98: 10 | C98: Commissioning | E98: =MIN(E99:E108) -> 45971 | F98: =G98-E98 -> 4 | G98: =MAX(G99:G108) -> 45975 | I98: =MIN(I99:I108) -> 46006 | J98: =K98-I98 -> 59 | K98: =MAX(K99:K108) -> 46065 | M98: =AVERAGE(M99:M108) -> 1 | N98: =AVERAGE(N99:N108) -> 1
B99: =B98+0.1 -> 10.1 | C99: MV Signoff and COC | E99: =WORKDAY.INTL(MAX(G88,G81,G74,G67,G58),0,1,Data!$C$3:$C$41) -> 45971 | F99: 2 | G99: =WORKDAY.INTL(E99,F99,1,Data!$C$3:$C$41) -> 45973 | I99: 46006 | J99: 3 | K99: =WORKDAY.INTL(I99,J99,1,Data!$C$3:$C$41) -> 46009 | M99: 1 | N99: =_xlfn.LET( _xlpm.s,VALUE(I99), _xlpm.e,VALUE(K99), IF(OR(_xlpm.s="",_xlpm.e=""),"", IF(_xlpm.e<=_xlpm.s, IF(TODAY()>=_xlpm.e,1,0), MAX(0,MIN(1,(TODAY()-_xlpm.s)/(_xlpm.e-_xlpm.s))))) ) -> 1
B100: 10.2 | C100: Transformer Commissioning | I100: 46006 | J100: 2 | K100: =WORKDAY.INTL(I100,J100,1,Data!$C$3:$C$41) -> 46008 | M100: 1 | N100: =_xlfn.LET( _xlpm.s,VALUE(I100), _xlpm.e,VALUE(K100), IF(OR(_xlpm.s="",_xlpm.e=""),"", IF(_xlpm.e<=_xlpm.s, IF(TODAY()>=_xlpm.e,1,0), MAX(0,MIN(1,(TODAY()-_xlpm.s)/(_xlpm.e-_xlpm.s))))) ) -> 1
B101: 10.3 | C101: Inverter Commissioning | I101: =K100 -> 46008 | J101: 2 | K101: =WORKDAY.INTL(I101,J101,1,Data!$C$3:$C$41) -> 46010 | M101: 1 | N101: =_xlfn.LET( _xlpm.s,VALUE(I101), _xlpm.e,VALUE(K101), IF(OR(_xlpm.s="",_xlpm.e=""),"", IF(_xlpm.e<=_xlpm.s, IF(TODAY()>=_xlpm.e,1,0), MAX(0,MIN(1,(TODAY()-_xlpm.s)/(_xlpm.e-_xlpm.s))))) ) -> 1
B102: 10.4 | C102: Energy Flowing - Partial | I102: =K101-1 -> 46009 | J102: 1 | K102: =WORKDAY.INTL(I102,J102,1,Data!$C$3:$C$41) -> 46010 | M102: 1 | N102: =_xlfn.LET( _xlpm.s,VALUE(I102), _xlpm.e,VALUE(K102), IF(OR(_xlpm.s="",_xlpm.e=""),"", IF(_xlpm.e<=_xlpm.s, IF(TODAY()>=_xlpm.e,1,0), MAX(0,MIN(1,(TODAY()-_xlpm.s)/(_xlpm.e-_xlpm.s))))) ) -> 1
B103: 10.5 | C103: Energy Flowing - Full | I103: 46055 | J103: 3 | K103: =WORKDAY.INTL(I103,J103,1,Data!$C$3:$C$41) -> 46058 | M103: 1 | N103: =_xlfn.LET( _xlpm.s,VALUE(I103), _xlpm.e,VALUE(K103), IF(OR(_xlpm.s="",_xlpm.e=""),"", IF(_xlpm.e<=_xlpm.s, IF(TODAY()>=_xlpm.e,1,0), MAX(0,MIN(1,(TODAY()-_xlpm.s)/(_xlpm.e-_xlpm.s))))) ) -> 1
B104: 10.6 | C104: Issue Compeltion Certificates | I104: =K103 -> 46058 | J104: 5 | K104: =WORKDAY.INTL(I104,J104,1,Data!$C$3:$C$41) -> 46065 | M104: 1 | N104: =_xlfn.LET( _xlpm.s,VALUE(I104), _xlpm.e,VALUE(K104), IF(OR(_xlpm.s="",_xlpm.e=""),"", IF(_xlpm.e<=_xlpm.s, IF(TODAY()>=_xlpm.e,1,0), MAX(0,MIN(1,(TODAY()-_xlpm.s)/(_xlpm.e-_xlpm.s))))) ) -> 1
B105: 10.7 | C105: Techsitter Installation | I105: 46048 | J105: 2 | K105: =WORKDAY.INTL(I105,J105,1,Data!$C$3:$C$41) -> 46050 | M105: 1 | N105: =_xlfn.LET( _xlpm.s,VALUE(I105), _xlpm.e,VALUE(K105), IF(OR(_xlpm.s="",_xlpm.e=""),"", IF(_xlpm.e<=_xlpm.s, IF(TODAY()>=_xlpm.e,1,0), MAX(0,MIN(1,(TODAY()-_xlpm.s)/(_xlpm.e-_xlpm.s))))) ) -> 1
B106: 10.8 | C106: Grid Meter Setup | I106: 46034 | J106: 10 | K106: =WORKDAY.INTL(I106,J106,1,Data!$C$3:$C$41) -> 46048 | M106: 1 | N106: =_xlfn.LET( _xlpm.s,VALUE(I106), _xlpm.e,VALUE(K106), IF(OR(_xlpm.s="",_xlpm.e=""),"", IF(_xlpm.e<=_xlpm.s, IF(TODAY()>=_xlpm.e,1,0), MAX(0,MIN(1,(TODAY()-_xlpm.s)/(_xlpm.e-_xlpm.s))))) ) -> 1
B107: 10.9 | C107: Inverter 4 Rolling Mill (Inverter 14) Faulty string | I107: 46048 | J107: 2 | K107: =WORKDAY.INTL(I107,J107,1,Data!$C$3:$C$41) -> 46050 | M107: 1 | N107: 1
B108: 10.1 | C108: Practical Completion | E108: =WORKDAY.INTL(G99,0,1,Data!$C$3:$C$41) -> 45973 | F108: 2 | G108: =WORKDAY.INTL(E108,F108,1,Data!$C$3:$C$41) -> 45975 | I108: 46055 | J108: 0 | K108: =WORKDAY.INTL(I108,J108,1,Data!$C$3:$C$41) -> 46055 | M108: 1 | N108: 1
J109: `
B110: 11 | C110: QA Inspection & Snag Completion | E110: =MIN(E111:E115) -> 45929 | F110: =G110-E110 -> 58 | G110: =MAX(G111:G115) -> 45987 | I110: =MIN(I111:I115) -> 46048 | J110: =K110-I110 -> 29 | K110: =MAX(K111:K115) -> 46077 | M110: =AVERAGE(M111:M115) -> 1 | N110: =AVERAGE(N111:N115) -> 1
...

Sheet Expenditure Tracking
B2: HIGH LEVEL PROJECT EXPENDITURE TRACKING
F4: COSTED | H4: ACTUAL | J4: Difference from costed
B5: EXPENDITURE | F5: =SUM(F9:F23) -> 56096452 | H5: =SUM(H9:H23) -> 48292163 | J5: =SUM(J9:J23) -> 7804288.9
B7: No. | D7: Item | F7: Costed Expenditure | H7: Actual Expenditure | J7: Saving / Overrun | L7: Comments on variations from planned expenditure
B9: ='Expenditure Breakdown'!L6 -> 1 | D9: ='Expenditure Breakdown'!M6 -> 1. Panels | F9: ='Expenditure Breakdown'!I6 -> 14537831 | H9: ='Expenditure Breakdown'!X6 -> 13751216 | J9: =F9-H9 -> 786615.3
B10: ='Expenditure Breakdown'!L23 -> 2 | D10: ='Expenditure Breakdown'!M23 -> 2. Inverters | F10: ='Expenditure Breakdown'!I23 -> 2760000 | H10: ='Expenditure Breakdown'!X23 -> 2495176.2 | J10: =F10-H10 -> 264823.78
B11: ='Expenditure Breakdown'!L31 -> 3 | D11: ='Expenditure Breakdown'!M31 -> 3. Mounting Structures | F11: ='Expenditure Breakdown'!I31 -> 7358785.9 | H11: ='Expenditure Breakdown'!X31 -> 4061009.9 | J11: =F11-H11 -> 3297776
B12: ='Expenditure Breakdown'!L53 -> 4 | D12: ='Expenditure Breakdown'!M53 -> 4. DC Equipment | F12: ='Expenditure Breakdown'!I53 -> 8057942 | H12: ='Expenditure Breakdown'!X53 -> 3193174 | J12: =F12-H12 -> 4864768
B13: ='Expenditure Breakdown'!L92 -> 5 | D13: ='Expenditure Breakdown'!M92 -> 5. Monitoring | F13: ='Expenditure Breakdown'!I92 -> 64000 | H13: ='Expenditure Breakdown'!X92 -> 241577.3 | J13: =F13-H13 -> -177577.3
B14: ='Expenditure Breakdown'!L115 -> 6 | D14: ='Expenditure Breakdown'!M115 -> 6. AC Equipment | F14: ='Expenditure Breakdown'!I115 -> 2941866.9 | H14: ='Expenditure Breakdown'!X115 -> 2258542.4 | J14: =F14-H14 -> 683324.55
B15: ='Expenditure Breakdown'!L151 -> 7 | D15: ='Expenditure Breakdown'!M151 -> 7.MV Substation | F15: ='Expenditure Breakdown'!I151 -> 12030861 | H15: ='Expenditure Breakdown'!X151 -> 7046627.6 | J15: =F15-H15 -> 4984233
B16: ='Expenditure Breakdown'!L190 -> 8 | D16: ='Expenditure Breakdown'!M190 -> 8. Product Add On | F16: ='Expenditure Breakdown'!I190 -> 2015000 | H16: ='Expenditure Breakdown'!X190 -> 2175649.8 | J16: =F16-H16 -> -160649.81
B17: ='Expenditure Breakdown'!L214 -> 9 | D17: ='Expenditure Breakdown'!M214 -> 9. AC & DC installation | F17: ='Expenditure Breakdown'!I214 -> 4360411.2 | H17: ='Expenditure Breakdown'!X214 -> 8055680 | J17: =F17-H17 -> -3695268.8
B18: ='Expenditure Breakdown'!L258 -> 10 | D18: ='Expenditure Breakdown'!M258 -> 10. Site Logistics | F18: ='Expenditure Breakdown'!I258 -> 394304.23 | H18: ='Expenditure Breakdown'!X258 -> 989880.47 | J18: =F18-H18 -> -595576.24
B19: ='Expenditure Breakdown'!L324 -> 11 | D19: ='Expenditure Breakdown'!M324 -> 11. Due Dilligence | F19: ='Expenditure Breakdown'!I324 -> 420000 | H19: ='Expenditure Breakdown'!X324 -> 426656 | J19: =F19-H19 -> -6656
B20: ='Expenditure Breakdown'!L339 -> 12 | D20: ='Expenditure Breakdown'!M339 -> 12. BDP Commission | F20: ='Expenditure Breakdown'!I339 -> 205449.89 | H20: ='Expenditure Breakdown'!X339 -> 0 | J20: =F20-H20 -> 205449.89
B21: ='Expenditure Breakdown'!L342 -> 13 | D21: ='Expenditure Breakdown'!M354 -> 13. Engineering | F21: ='Expenditure Breakdown'!I342 -> 950000 | H21: ='Expenditure Breakdown'!X342 -> 1011275 | J21: =F21-H21 -> -61275
B22: ='Expenditure Breakdown'!L366 -> 14 | D22: ='Expenditure Breakdown'!M366 -> 14. General Expenses | F22: ='Expenditure Breakdown'!I366 -> 0 | H22: ='Expenditure Breakdown'!X366 -> 310187.17 | J22: =F22-H22 -> -310187.17
B23: ='Expenditure Breakdown'!L383 -> 15 | D23: ='Expenditure Breakdown'!M383 -> 15. Service Add On | F23: ='Expenditure Breakdown'!I383 -> 0 | H23: ='Expenditure Breakdown'!X383 -> 2275511.4 | J23: =F23-H23 -> -2275511.4
D25: check: | F25: ='Expenditure Breakdown'!I2-'Expenditure Tracking'!F5 -> 0 | G25: =#REF!-G5 -> #REF! | H25: ='Expenditure Breakdown'!X2-H5 -> 0

Sheet Expenditure Breakdown
B2: COSTED EXPENDITURE BREAKDOWN | I2: =SUM(I6:I440) -> 56096452 | J2: =SUM(J6:J440)-5000 -> 59995000 | L2: ACTUAL EXPENDITURE BREAKDOWN | R2: FINANCE ONLY | X2: =SUM(X6:X440) -> 48292163
B4: No. | C4: Product / Service | D4: Description of Work | E4: QTY | F4: Rate / Unit | G4: Budget Total | H4: FINANCE PAYMENT DATE | I4: Total COS | J4: =IF(J2-'Revenue Tracking'!D4>=0, "Total Revenue", "ERROR on REV" ) -> ERROR on REV | L4: No. | M4: Product/ Service | N4: Description of Work | O4: QTY | P4: Rate / Unit | Q4: Actual Total | R4: PO NUMBER | S4: INVOICE NUMBER | T4: INVOICE RAISED DATE | U4: REVENUE RECOGNITION AMOUNT | V4: CHECK | W4: FINANCE PAYMENT DATE | X4: Total COS
B6: 1 | C6: Panels | D6: Panels Budget | G6: =D441 -> 14537831 | H6: 45827 | I6: =SUM(G6:G19) -> 14537831 | J6: =F441 -> 15101046 | L6: 1 | M6: 1. Panels | N6: Jinko 620W - Deposit | O6: 11420 | P6: 0.1 | Q6: =13735976*0.1 -> 1373597.6 | R6: PO3993-CSPH2-20260610 - RV Approved | S6: Menlo INV0003003 | T6: 45869 | U6: 1510104.6 | V6: =J6-SUM(U6:U19) -> 0 | W6: 45827 | X6: =SUM(Q6:Q21) -> 13751216
B7: 1 | D7: Delivery Budget | L7: 1 | M7: 1. Panels | U7: 0
B8: 1 | L8: 1 | M8: 1. Panels | N8: Jinko 620W - Ground Mount | O8: 5112 | P8: 1202.8 | Q8: =1675740.96/1.15 -> 1457166.1 | S8: Menlo INV0003103 | T8: 45869 | U8: 6083790.8 | W8: 45925
L9: 1 | M9: 1. Panels | O9: =O8*620/1000 -> 3169.44 | Q9: =(2000000+237905.06+2243727.74)/1.15 -> 3897072 | S9: Menlo INV0003103 | T9: 45869 | U9: 0 | W9: 45946
L10: 1 | M10: 1. Panels | Q10: =6148713.6-Q8-Q9-614871.36 -> 179604.19 | S10: Menlo INV0003103 | T10: 45869 | U10: 0 | W10: 46031
B11: 1 | L11: 1 | M11: 1. Panels | N11: Jinko 620W - Rooftop | O11: =4032+2268 -> 6300 | P11: 1202.8 | Q11: 869565.22 | S11: Menlo INV0003103 | T11: 45869 | U11: 7497629.5 | W11: 46031
L12: 1 | M12: 1. Panels | O12: =O11*620/1000 -> 3906 | Q12: 637461.31 | S12: Menlo INV0003103 | T12: 45869 | U12: 0 | W12: 46031
L13: 1 | M13: 1. Panels | Q13: 1006679.1 | S13: Menlo INV0003103 | T13: 45869 | U13: 0 | W13: 46037
L14: 1 | M14: 1. Panels | Q14: 1277597.2 | S14: Menlo INV0003103 | T14: 45869 | U14: 0 | W14: 46045
L15: 1 | M15: 1. Panels | Q15: 1304347.8 | S15: Menlo INV0003103 | T15: 45869 | U15: 0 | W15: 46051
L16: 1 | M16: 1. Panels | Q16: =6819876-Q11-Q12-Q13-Q14-Q15 -> 1724225.3 | S16: Menlo INV0003103 | T16: 45869 | U16: 0 | W16: 46051
B17: 1 | L17: 1 | M17: 1. Panels | N17: Spare | O17: 8 | P17: 1202.8 | Q17: =13735976*0.9*(O17/$O$6) -> 8660.16 | S17: Menlo INV0003103 | T17: 45869 | U17: 9520.7993 | W17: =W16 -> 46051 | AB17: Luken Solar
B18: 1 | L18: 1 | M18: 1. Panels | N18: Extra Pallet | O18: 1 | P18: 43292.88 | Q18: =P18 -> 43292.88 | S18: Menlo INV0003160 | T18: 45900 | U18: 0 | W18: =W9 -> 45946 | Y18: BUDGET | Z18: Installer Allocation
B19: 1 | L19: 1 | M19: 1. Panels | N19: Extra Pallet | O19: 1 | P19: -43292.88 | Q19: =P19 -> -43292.88 | S19: MSA Energy: CRN0000262 | T19: 45991 | U19: 0 | W19: =W16 -> 46051 | Y19: BUDGET | Z19: Installer Allocation
L20: 1 | M20: 1. Panels | N20: Replace damaged modules | O20: 11 | P20: 1240 | Q20: =O20*P20 -> 13640 | S20: MSA Energy INV000681 | T20: 46112 | W20: 46149
L21: 1 | M21: 1. Panels | N21: Transport | Q21: 1600 | S21: MSA Energy INV000681 | T21: 46112 | W21: 46149
T22: =IF(W22>1,EOMONTH(W22,0),"") | Y22: AC Equipment | Z22: =G115 -> 2941866.9 | AB22: Installation of 4MW Roof Mount including electrical work, labour and logistics | AC22: 4000000 | AD22: 4MW | AE22: =AC22/4000000 -> 1
B23: 2 | C23: Inverters | D23: Inverter Budget | G23: =D442 -> 2760000 | H23: 45820 | I23: =SUM(G23:G29) -> 2760000 | J23: =F442 -> 2982470.7 | L23: 2 | M23: 2. Inverters | N23: Huawei 330KTL - Deposit 30% | O23: 23 | P23: =6087*17.7457 -> 108018.08 | Q23: =O23*P23*30% -> 745324.72 | R23: PO3991-CSPH2-20250610 - JP Approved | S23: Kathea S19625 | T23: 45869 | U23: 886426.77 | V23: =J23-SUM(U23:U29) -> -0.00028844411 | W23: 45820 | X23: =SUM(Q23:Q29) -> 2495176.2 | Y23: DC Equipment | Z23: =G54 -> 4558110
B24: 2 | L24: 2 | M24: 2. Inverters | N24: Huawei 330KTL - Balance 70% | Q24: 1749851.5 | S24: Kathea - 519704 | T24: 45869 | U24: 2081126.7 | W24: 45855 | Y24: AC Labour | Z24: =G214 -> 1062060 | AA24: =Z24/7080000 -> 0.15000847 | AB24: Special lifting equipment
B25: 2 | L25: 2 | M25: 2. Inverters | T25: =IF(W25>1,EOMONTH(W25,0),"") | U25: =(Q25/$X$23*$J$23) -> 0 | Y25: DC Labour | Z25: =G215 -> 3298351.2 | AA25: =Z25/7080000 -> 0.46586882 | AB25: Elctrical and installation small components (not provided by Emergent) | AC25: 550000
B26: 2 | L26: 2 | M26: 2. Inverters | T26: 45900 | U26: 14917.19 | W26: 45820 | Y26: Offloading | Z26: =G258 -> 85000
B27: 2 | L27: 2 | M27: 2. Inverters | N27: Huawei SUN2000 HAV5-Inverter Accessories - 330KTL Inverters | Q27: 899.72 | S27: Kathea - 500335 | T27: 46022 | U27: 0 | W27: 46053 | Y27: Scaffolding | Z27: =G259 -> 133245.9 | AB27: Installation of Ground Mount system:
B28: 2 | L28: 2 | M28: 2. Inverters | Q28: -899.72 | S28: Kathea - 500335 | T28: 46053 | U28: 0 | W28: 46053 | Y28: Storage | Z28: =G263 -> 176058.33
B29: 2 | L29: 2 | M29: 2. Inverters | T29: =IF(W29>1,EOMONTH(W29,0),"") | U29: =(Q29/$X$23*$J$23) -> 0 | Y29: Telehandler | Z29: 0 | AB29: Installation of 3MW Ground Mount including electrical work, labour and logistics (incl. Structures) | AC29: 2500000 | AD29: 3MW | AE29: =AC29/3000000 -> 0.83333333
T30: =IF(W30>1,EOMONTH(W30,0),"")
B31: 3 | C31: Mounting Structures | D31: Structure Budget | G31: =D443 -> 7358785.9 | H31: 45867 | I31: =SUM(G31:G51) -> 7358785.9 | J31: =F443 -> 7951943.3 | L31: 3 | M31: 3. Mounting Structures | N31: IBR short rail - Rooftop | O31: 19830 | P31: 22.88 | Q31: =O31*P31 -> 453710.4 | R31: PO3994-CSPH2-20260610 - RV Approved | S31: Schletter - INV1895 | T31: 45838 | U31: 870407.92 | V31: =J31-SUM(U31:U51) -> 0 | W31: 45867 | X31: =SUM(Q31:Q51) -> 4061009.9 | Y31: Other | Z31: 0 | AB31: Trenching and pipes
B32: 3 | L32: 3 | M32: 3. Mounting Structures | N32: Screws - Rooftop | O32: 39660 | P32: 5.87 | Q32: =O32*P32 -> 232804.2 | S32: Schletter - INV1895 | T32: 45838 | U32: 446616.65 | W32: 45867 | Y32: Total | Z32: =SUM(Z22:Z31) -> 12254692 | AB32: Elctrical and installation small components (not provided by Emergent) | AC32: 590000
L33: 3 | M33: 3. Mounting Structures | N33: Inner Clamp - 30mm - Rooftop | O33: 18030 | P33: 10.64 | Q33: 197183 | S33: Schletter - INV1895 | T33: 45838 | U33: 378280.17 | W33: 45867 | Y33: Less 15% | Z33: =+Z32*0.85 -> 10416489
L34: 3 | M34: 3. Mounting Structures | N34: Mid Clamps - | O34: -470 | P34: 10.64 | Q34: =O34*P34 -> -5000.8 | S34: Allocated to Ziegler Warehouse | T34: 46081 | W34: 46081
L35: 3 | M35: 3. Mounting Structures | N35: End Clamp - 30mm - Rooftop | O35: 1820 | P35: 10.96 | Q35: 20391.2 | S35: Schletter - INV1895 | T35: 45838 | U35: 39118.923 | W35: 45867 | Y35: R/Wp | Z35: =Z33/'Project Plan'!$E$3/1000 -> 1.4712554
L36: 3 | M36: 3. Mounting Structures | U36: 0
L37: 3 | M37: 3. Mounting Structures | N37: IBR Mounting clamps - Cable Trays | O37: =O31*0.1 -> 1983 | P37: 22.88 | Q37: =O37*P37 -> 45371.04 | S37: Schletter - INV1895 | T37: 45838 | U37: 87040.792 | W37: 45867 | Y37: ACTUAL | Z37: Installer Price
L38: 3 | M38: 3. Mounting Structures | N38: IBR Mounting clamps - 130004-200 returned to stock | O38: -220 | P38: 22.88 | Q38: =O38*P38 -> -5033.6 | S38: Allocated to Ziegler Warehouse | T38: 46081 | W38: 46081
L39: 3 | M39: 3. Mounting Structures | N39: Screws - Cable Trays | O39: =O37*2 -> 3966 | P39: 5.87 | Q39: =O39*P39 -> 23280.42 | S39: Schletter - INV1895 | T39: 45838 | U39: 44661.665 | W39: 45867 | Y39: =Y22 -> AC Equipment | Z39: 2941866.9
L40: 3 | M40: 3. Mounting Structures | U40: 0 | Y40: =Y23 -> DC Equipment | Z40: 4558110
L41: 3 | M41: 3. Mounting Structures | N41: Freight Charges | Q41: 17564 | S41: Schletter - INV1895 | T41: 45838 | U41: 33695.161 | W41: 45867 | Y41: =Y24 -> AC Labour | Z41: =AA41*7080000 -> 1770000 | AA41: 0.25
L42: 3 | M42: 3. Mounting Structures | U42: =(Q42/$X$31*$J$31) -> 0 | W42: 45930 | Y42: =Y25 -> DC Labour | Z42: =AA42*7080000 -> 4602000 | AA42: 0.65
L43: 3 | M43: 3. Mounting Structures | U43: =(Q43/$X$31*$J$31) -> 0 | W43: 45930 | Y43: =Y26 -> Offloading | Z43: 85000
L44: 3 | M44: 3. Mounting Structures | T44: =IF(W44>1,EOMONTH(W44,0),"") | U44: =(Q44/$X$31*$J$31) -> 0 | Y44: =Y27 -> Scaffolding | Z44: 133245.9
B45: 3 | L45: 3 | M45: 3. Mounting Structures | N45: Ground mount - Deposit | O45: =O8*620/1000 -> 3169.44 | P45: 0.97201398 | Q45: =O45*P45*1000*0.5 -> 1540370 | R45: PO3992-CSPH2-20250610 - RV Approved | S45: Schletter : INV1887 | T45: 45900 | U45: 2955079.4 | W45: 45827 | Y45: =Y28 -> Storage | Z45: 176058.33
B46: 3 | L46: 3 | M46: 3. Mounting Structures | N46: Ground mount - Balance | Q46: =O45*P45*1000*0.5 -> 1540370 | S46: Schletter: INV2113 | T46: 45900 | U46: 2955079.4 | W46: 45930 | Y46: =Y29 -> Telehandler | Z46: 150000
L47: 3 | M47: 3. Mounting Structures | Q47: -1540370 | S47: Schletter - CRN0271 | T47: 45930 | U47: 0 | W47: 45930
L48: 3 | M48: 3. Mounting Structures | Q48: -1540370 | S48: Schletter - CRN0272 | T48: 45930 | U48: 0 | W48: 45930
L49: 3 | M49: 3. Mounting Structures | Q49: 3006740 | S49: Schletter - INV2231 | T49: 45930 | U49: 0 | W49: 45930
B50: 3 | L50: 3 | M50: 3. Mounting Structures | N50: Engineering Signoff - deposit | Q50: =74000*50% -> 37000 | S50: Schletter : INV1887 | T50: 45838 | U50: 70981.607 | W50: 45827 | Y50: HSE | Z50: 4500
B51: 3 | L51: 3 | M51: 3. Mounting Structures | N51: Engineering Signoff - balance | Q51: =74000*50% -> 37000 | S51: Schletter: INV2113 | T51: 45900 | U51: 70981.607 | W51: =W46 -> 45930 | Y51: Other | Z51: 0
T52: =IF(W52>1,EOMONTH(W52,0),"") | Y52: Other | Z52: 0
B53: 4 | C53: DC Equipment | D53: DC Cable Budget | E53: 249988 | G53: 3499832 | H53: =H54 -> 45901 | I53: =SUM(G53:G90) -> 8057942 | J53: =F444 -> 8707455.1 | L53: 4 | M53: 4. DC Equipment | N53: DC Cable Budget | O53: 24000 | P53: 0 | Q53: =O53*P53 -> 0 | U53: =(Q53/$X$53*$J$53) -> 0 | V53: =J53-SUM(U53:U90) -> -0.0047537833 | X53: =SUM(Q53:Q90) -> 3193174 | Y53: Total | Z53: =SUM(Z39:Z52) -> 14420781
B54: 4 | D54: DC Equipment Budget | G54: =D444-G53 -> 4558110 | H54: 45901 | L54: 4 | M54: 4. DC Equipment | N54: DC Cable - Balance to be delivered | O54: 0.1 | P54: 2376000 | Q54: =O54*P54 -> 237600 | R54: PO3993-CSPH2-20260610 - RV Approved | S54: Menlo INV0003003 | T54: 45838 | U54: 465334.02 | W54: 45901 | Y54: R/Wp | Z54: =Z53/'Project Plan'!$E$3/1000 -> 2.0368335
L55: 4 | M55: 4. DC Equipment | N55: DC Cable | O55: 0.9 | Q55: =O55*P54 -> 2138400 | S55: Menlo INV0003047 | T55: 45838 | U55: 4188006.2 | W55: 45901
B56: 4 | L56: 4 | M56: 4. DC Equipment | N56: Jinko Connectors - Male | O56: 500 | P56: 13 | Q56: =O56*P56 -> 6500 | R56: PO4154-COEGA-20250723 - RV Approved | S56: Menlo INV0003096 | T56: 45869 | U56: 13627.717 | W56: 45925
B57: 4 | L57: 4 | M57: 4. DC Equipment | N57: Jinko Connectors - Female | O57: 500 | P57: 13 | Q57: =O57*P57 -> 6500 | S57: Menlo INV0003096 | T57: 45869 | U57: 13627.717 | W57: =W56 -> 45925
L58: 4 | M58: 4. DC Equipment | N58: DC Cable Red (Returned to stock) | O58: -4000 | P58: 13 | Q58: =O58*P58 -> -52000 | S58: Allocated to Ziegler Warehouse | T58: 46081 | U58: 0 | W58: 46081
L59: 4 | M59: 4. DC Equipment | N59: DC Cable Black (Returned to stock) | O59: -4790 | P59: 13 | Q59: =O59*P59 -> -62270 | S59: Allocated to Ziegler Warehouse | T59: 46081 | U59: 0 | W59: 46081
L60: 4 | M60: 4. DC Equipment | T60: =IF(W60>1,EOMONTH(W60,0),"") | U60: =(Q60/$X$53*$J$53) -> 0
L61: 4 | M61: 4. DC Equipment | N61: DC Cable Trays - As Per BOQ | Q61: 370187 | R61: PO4126-CSPH2-20250716 - RV Approved | S61: Advanced Strut INV IN152953 | T61: 45869 | U61: 1724074.2 | W61: 45904
L62: 4 | M62: 4. DC Equipment | T62: 45900 | U62: 1117518.2 | W62: 45900
L63: 4 | M63: 4. DC Equipment | N63: 50mm x 3m R/Flange cable tray - | O63: -4 | P63: 225 | Q63: =O63*P63 -> -900 | S63: Allocated to Ziegler Warehouse | T63: 46081 | U63: 0 | W63: 46081
L64: 4 | M64: 4. DC Equipment | N64: 50mm x 3m R/Flange cable tray covers | O64: -3 | P64: 87 | Q64: =O64*P64 -> -261 | S64: Allocated to Ziegler Warehouse | T64: 46081 | U64: 0 | W64: 46081
L65: 4 | M65: 4. DC Equipment | N65: 300mm x 3m R/Flange cable tray | O65: -16 | P65: 501 | Q65: =O65*P65 -> -8016 | S65: Allocated to Ziegler Warehouse | T65: 46081 | U65: 0 | W65: 46081
L66: 4 | M66: 4. DC Equipment | N66: 300mm x 3m R/Flange cable tray covers | O66: -20 | P66: 360 | Q66: =O66*P66 -> -7200 | S66: Allocated to Ziegler Warehouse | T66: 46081 | U66: 0 | W66: 46081
L67: 4 | M67: 4. DC Equipment | N67: 75mm x 3m R/Flange cable tray | O67: -3 | P67: 237 | Q67: =O67*P67 -> -711 | S67: Allocated to Ziegler Warehouse | T67: 46081 | U67: 0 | W67: 46081
L68: 4 | M68: 4. DC Equipment | N68: 75mm x 3m R/Flange cable tray cover | O68: -2 | P68: 117 | Q68: =O68*P68 -> -234 | S68: Allocated to Ziegler Warehouse | T68: 46081 | U68: 0 | W68: 46081
L69: 4 | M69: 4. DC Equipment | N69: 110mm x 3m R/Flange cable tray | O69: -2 | P69: 246 | Q69: =O69*P69 -> -492 | S69: Allocated to Ziegler Warehouse | T69: 46081 | U69: 0 | W69: 46081
L70: 4 | M70: 4. DC Equipment | N70: 225mm x 3m R/Flange cable tray | O70: -2 | P70: 375 | Q70: =O70*P70 -> -750 | S70: Allocated to Ziegler Warehouse | T70: 46081 | U70: 0 | W70: 46081
L71: 4 | M71: 4. DC Equipment | N71: 300mm R/F Elbow | O71: -2 | P71: 189 | Q71: =O71*P71 -> -378 | S71: Allocated to Ziegler Warehouse | T71: 46081 | U71: 0 | W71: 46081
L72: 4 | M72: 4. DC Equipment | N72: 300mm R/F Elbow cover | O72: -2 | P72: 180 | Q72: =O72*P72 -> -360 | S72: Allocated to Ziegler Warehouse | T72: 46081 | U72: 0 | W72: 46081
L73: 4 | M73: 4. DC Equipment | N73: 450mm R/F Elbow | O73: -3 | P73: 470 | Q73: =O73*P73 -> -1410 | S73: Allocated to Ziegler Warehouse | T73: 46081 | U73: 0 | W73: 46081
L74: 4 | M74: 4. DC Equipment | N74: 450mm R/F Elbow cover | O74: -2 | P74: 270 | Q74: =O74*P74 -> -540 | S74: Allocated to Ziegler Warehouse | T74: 46081 | U74: 0 | W74: 46081
L75: 4 | M75: 4. DC Equipment | N75: 600mm Ladderack elbow | O75: -1 | P75: 491 | Q75: =O75*P75 -> -491 | S75: Allocated to Ziegler Warehouse | T75: 46081 | U75: 0 | W75: 46081
L76: 4 | M76: 4. DC Equipment
L77: 4 | M77: 4. DC Equipment
L78: 4 | M78: 4. DC Equipment | T78: =IF(W78>1,EOMONTH(W78,0),"") | U78: =(Q78/$X$53*$J$53) -> 0
L79: 4 | M79: 4. DC Equipment | T79: =IF(W79>1,EOMONTH(W79,0),"") | U79: =(Q79/$X$53*$J$53) -> 0
B80: 4 | L80: 4 | M80: 4. DC Equipment | N80: Project Kick Off - Rooftop | O80: =AC25/2 -> 275000 | P80: 0.5 | Q80: =$O$80*P80 -> 137500 | R80: PO4029-CSPH2-20250624 - RV Approved | S80: Luken Solar Inv: 0654 | T80: 45838 | U80: 269290.52 | W80: =W85 -> 45834
B81: 4 | L81: 4 | M81: 4. DC Equipment | N81: DC Equipment Onsite - Rooftop | P81: 0.4 | Q81: =$O$80*P81 -> 110000 | S81: Luken Solar Inv: 0660 | T81: =T86 -> 45869 | U81: 230622.91 | W81: =W86 -> 45904
B82: 4 | L82: 4 | M82: 4. DC Equipment | N82: End of Defects Period - Rooftop | P82: 0.1 | Q82: =$O$80*P82 -> 27500 | S82: Luken Solar Inv 0665 | T82: =T87 -> 45900 | U82: 71925.973 | W82: =W222 -> 46142
B83: 4 | L83: 4 | M83: 4. DC Equipment | T83: =IF(W83>1,EOMONTH(W83,0),"") | U83: =(Q83/$X$53*$J$53) -> 0
B84: 4 | L84: 4 | M84: 4. DC Equipment | T84: =IF(W84>1,EOMONTH(W84,0),"") | U84: =(Q84/$X$53*$J$53) -> 0
B85: 4 | L85: 4 | M85: 4. DC Equipment | N85: Project Kick Off - Ground Mount | O85: =AC32/2 -> 295000 | P85: 0.5 | Q85: =$O$85*P85 -> 147500 | S85: Luken Solar Inv: 0654 | T85: 45838 | U85: 288875.28 | W85: =W215 -> 45834
B86: 4 | L86: 4 | M86: 4. DC Equipment | N86: DC Equipment Onsite - Ground Mount | P86: 0.4 | Q86: =$O$85*P86 -> 118000 | S86: Luken Solar Inv: 0660 | T86: 45869 | U86: 247395.48 | W86: 45904
B87: 4 | L87: 4 | M87: 4. DC Equipment | N87: End of Defects Period - Ground Mount | P87: 0.1 | Q87: =$O$85*P87 -> 29500 | S87: Luken Solar Inv 0665 | T87: 45900 | U87: 77156.953 | W87: =W222 -> 46142
B88: 4 | L88: 4 | M88: 4. DC Equipment | T88: =IF(W88>1,EOMONTH(W88,0),"") | U88: =(Q88/$X$53*$J$53) -> 0
B89: 4 | L89: 4 | M89: 4. DC Equipment | T89: =IF(W89>1,EOMONTH(W89,0),"") | U89: =(Q89/$X$53*$J$53) -> 0
B90: 4 | L90: 4 | M90: 4. DC Equipment | T90: =IF(W90>1,EOMONTH(W90,0),"") | U90: =(Q90/$X$53*$J$53) -> 0
T91: =IF(W91>1,EOMONTH(W91,0),"")
B92: 5 | C92: Monitoring | D92: Monitoring Budget | G92: 26000 | H92: =H93 -> 45862 | I92: =SUM(G92:G113) -> 64000 | J92: =F446 -> 69158.741 | L92: 5 | M92: 5. Monitoring | N92: Metering Budget | U92: =(Q92/$X$92*$J$92) -> 0 | V92: =J92-SUM(U92:U113) -> 0.00054426001 | X92: =SUM(Q92:Q113) -> 241577.3
B93: 5 | D93: Comms DB | G93: 8000 | H93: 45862 | L93: 5 | M93: 5. Monitoring | N93: Janitza UMG604 pro | O93: 1 | Q93: 19205.5 | R93: PO4129-CSPH2-2020717 - RV Approved | S93: Harmonious Technical - QU100635 | T93: 45869 | U93: 3006.8452 | W93: 45862
L94: 5 | M94: 5. Monitoring | N94: Delivery of Janitza | Q94: 264.26 | S94: DSV Inv: 180140895 | T94: 45869 | U94: 41.372987 | W94: 45900
B95: 5 | D95: Revenue Grade Meter | G95: 30000 | H95: 45900 | L95: 5 | M95: 5. Monitoring | N95: Techsitter | O95: 1 | Q95: 11169 | S95: Matriarch - INV-4999 | T95: 45900 | U95: 26948.87 | W95: 45900 | Y95: TC: Changed amount - 30k
L96: 5 | M96: 5. Monitoring | N96: Delivery of Techsitter | Q96: 175.56 | S96: DSV Inv: 180140895 | T96: 45869 | U96: 27.485967 | W96: 45900
L97: 5 | M97: 5. Monitoring | N97: Encombi controller complete kit | O97: 1 | Q97: 95374 | R97: PO4128-CSPH2-20250717 - RV Approved | S97: Kathea Inv: 519753 + 519759 + 519762 | T97: 45869 | U97: 14931.913 | W97: 45930
L98: 5 | M98: 5. Monitoring | N98: Router and CTs | Q98: 15921 | R98: PO4125-COEG-20250716 - RV Approved | S98: AccuEnergy - ASAI-005973 | T98: 45869 | U98: 2492.6183 | W98: =T98+30 -> 45899
L99: 5 | M99: 5. Monitoring | N99: Optic Fiber Installation | Q99: 83760 | R99: PO4506-CSPH2-20251128 - RV Approve | S99: Paul van Vuuren Inv: IOG090 | T99: 46022 | U99: 17237.103 | W99: 46037
L100: 5 | M100: 5. Monitoring | N100: Supply & Delivery - Mode Duplex Fibre Modules | Q100: 1980 | S100: Paul Van Vuuren - IOG122 | T100: 46053 | U100: 562.22433 | W100: 46053
L101: 5 | M101: 5. Monitoring | Q101: -1980 | S101: Paul van Vuuren - CN000217 | T101: 46053 | W101: 46053
L102: 5 | M102: 5. Monitoring | N102: Meanwell MDR-100-24 | O102: 1 | Q102: 1060 | R102: PO4259-CSHP2-20250821 - RV Approved | S102: Mantech INV1078143 | T102: 45930 | U102: 335.8169 | W102: 45904
L103: 5 | M103: 5. Monitoring | U103: =(Q103/$X$92*$J$92) -> 0
...

Sheet Sheet1
A1: COS
A2: 45930 | B2: 2025/09/30(Outstanding Invoice) | C2: 45961 | D2: 2025/10/31(Outstanding Invoice) | E2: 45991 | F2: 2025/11/30(Outstanding Invoice) | G2: 46022 | H2: 2025/12/31(Outstanding Invoice) | I2: 46053 | J2: 2026/01/31(Outstanding Invoice) | K2: 46081 | L2: 2026/02/28(Outstanding Invoice) | M2: 46112 | N2: 2026/03/31(Outstanding Invoice) | O2: 46142 | P2: 2026/04/30(Outstanding Invoice) | Q2: 46173 | R2: 2026/05/31(Outstanding Invoice) | S2: 46203 | T2: 2026/06/30(Outstanding Invoice) | U2: 46234 | V2: 2026/07/31(Outstanding Invoice) | W2: 46265 | X2: 2026/08/31(Outstanding Invoice)
A3: =SUMIF('Expenditure Breakdown'!$T$6:$T$558,EOMONTH(A$2,0),'Expenditure Breakdown'!$Q$6:$Q$558) -> -26633.37 | B3: =SUMIFS('Expenditure Breakdown'!$Q$6:$Q$558,'Expenditure Breakdown'!$T$6:$T$558,"="&A$2,'Expenditure Breakdown'!$S$6:$S$558,"") -> 0 | C3: =SUMIF('Expenditure Breakdown'!$T$6:$T$558,EOMONTH(C$2,0),'Expenditure Breakdown'!$Q$6:$Q$558) -> 138858.56 | D3: =SUMIFS('Expenditure Breakdown'!$Q$6:$Q$558,'Expenditure Breakdown'!$T$6:$T$558,"="&C$2,'Expenditure Breakdown'!$S$6:$S$558,"") -> 0 | E3: =SUMIF('Expenditure Breakdown'!$T$6:$T$558,EOMONTH(E$2,0),'Expenditure Breakdown'!$Q$6:$Q$558) -> 6751442.6 | F3: =SUMIFS('Expenditure Breakdown'!$Q$6:$Q$558,'Expenditure Breakdown'!$T$6:$T$558,"="&E$2,'Expenditure Breakdown'!$S$6:$S$558,"") -> 0 | G3: =SUMIF('Expenditure Breakdown'!$T$6:$T$558,EOMONTH(G$2,0),'Expenditure Breakdown'!$Q$6:$Q$558) -> 350823.2 | H3: =SUMIFS('Expenditure Breakdown'!$Q$6:$Q$558,'Expenditure Breakdown'!$T$6:$T$558,"="&G$2,'Expenditure Breakdown'!$S$6:$S$558,"") -> 0 | I3: =SUMIF('Expenditure Breakdown'!$T$6:$T$558,EOMONTH(I$2,0),'Expenditure Breakdown'!$Q$6:$Q$558) -> 1363577.9 | J3: =SUMIFS('Expenditure Breakdown'!$Q$6:$Q$558,'Expenditure Breakdown'!$T$6:$T$558,"="&I$2,'Expenditure Breakdown'!$S$6:$S$558,"") -> 0 | K3: =SUMIF('Expenditure Breakdown'!$T$6:$T$558,EOMONTH(K$2,0),'Expenditure Breakdown'!$Q$6:$Q$558) -> 1116186.5 | L3: =SUMIFS('Expenditure Breakdown'!$Q$6:$Q$558,'Expenditure Breakdown'!$T$6:$T$558,"="&K$2,'Expenditure Breakdown'!$S$6:$S$558,"") -> 0 | M3: =SUMIF('Expenditure Breakdown'!$T$6:$T$558,EOMONTH(M$2,0),'Expenditure Breakdown'!$Q$6:$Q$558) -> 32195.86 | N3: =SUMIFS('Expenditure Breakdown'!$Q$6:$Q$558,'Expenditure Breakdown'!$T$6:$T$558,"="&M$2,'Expenditure Breakdown'!$S$6:$S$558,"") -> 0 | O3: =SUMIF('Expenditure Breakdown'!$T$6:$T$558,EOMONTH(O$2,0),'Expenditure Breakdown'!$Q$6:$Q$558) -> 683454.53 | P3: =SUMIFS('Expenditure Breakdown'!$Q$6:$Q$558,'Expenditure Breakdown'!$T$6:$T$558,"="&O$2,'Expenditure Breakdown'!$S$6:$S$558,"") -> 0 | Q3: =SUMIF('Expenditure Breakdown'!$T$6:$T$558,EOMONTH(Q$2,0),'Expenditure Breakdown'!$Q$6:$Q$558) -> 9535.8 | R3: =SUMIFS('Expenditure Breakdown'!$Q$6:$Q$558,'Expenditure Breakdown'!$T$6:$T$558,"="&Q$2,'Expenditure Breakdown'!$S$6:$S$558,"") -> 700 | S3: =SUMIF('Expenditure Breakdown'!$T$6:$T$558,EOMONTH(S$2,0),'Expenditure Breakdown'!$Q$6:$Q$558) -> 770090.68 | T3: =SUMIFS('Expenditure Breakdown'!$Q$6:$Q$558,'Expenditure Breakdown'!$T$6:$T$558,"="&S$2,'Expenditure Breakdown'!$S$6:$S$558,"") -> 770090.68 | U3: =SUMIF('Expenditure Breakdown'!$T$6:$T$558,EOMONTH(U$2,0),'Expenditure Breakdown'!$Q$6:$Q$558) -> 700 | V3: =SUMIFS('Expenditure Breakdown'!$Q$6:$Q$558,'Expenditure Breakdown'!$T$6:$T$558,"="&U$2,'Expenditure Breakdown'!$S$6:$S$558,"") -> 700 | W3: =SUMIF('Expenditure Breakdown'!$T$6:$T$558,EOMONTH(W$2,0),'Expenditure Breakdown'!$Q$6:$Q$558) -> 71895.6 | X3: =SUMIFS('Expenditure Breakdown'!$Q$6:$Q$558,'Expenditure Breakdown'!$T$6:$T$558,"="&W$2,'Expenditure Breakdown'!$S$6:$S$558,"") -> 71895.6
A5: REV
A6: =SUMIF('Expenditure Breakdown'!$T$6:$T$558,EOMONTH(A$2,0),'Expenditure Breakdown'!$U$6:$U$558) -> 4759.0838 | B6: =SUMIFS('Expenditure Breakdown'!$U$6:$U$558,'Expenditure Breakdown'!$T$6:$T$558,"="&A$2,'Expenditure Breakdown'!$S$6:$S$558,"") -> 0 | C6: =SUMIF('Expenditure Breakdown'!$T$6:$T$558,EOMONTH(C$2,0),'Expenditure Breakdown'!$U$6:$U$558) -> 71787.337 | D6: =SUMIFS('Expenditure Breakdown'!$U$6:$U$558,'Expenditure Breakdown'!$T$6:$T$558,"="&C$2,'Expenditure Breakdown'!$S$6:$S$558,"") -> 0 | E6: =SUMIF('Expenditure Breakdown'!$T$6:$T$558,EOMONTH(E$2,0),'Expenditure Breakdown'!$U$6:$U$558) -> 11651406 | F6: =SUMIFS('Expenditure Breakdown'!$U$6:$U$558,'Expenditure Breakdown'!$T$6:$T$558,"="&E$2,'Expenditure Breakdown'!$S$6:$S$558,"") -> 0 | G6: =SUMIF('Expenditure Breakdown'!$T$6:$T$558,EOMONTH(G$2,0),'Expenditure Breakdown'!$U$6:$U$558) -> 22058.316 | H6: =SUMIFS('Expenditure Breakdown'!$U$6:$U$558,'Expenditure Breakdown'!$T$6:$T$558,"="&G$2,'Expenditure Breakdown'!$S$6:$S$558,"") -> 0 | I6: =SUMIF('Expenditure Breakdown'!$T$6:$T$558,EOMONTH(I$2,0),'Expenditure Breakdown'!$U$6:$U$558) -> 673630.88 | J6: =SUMIFS('Expenditure Breakdown'!$U$6:$U$558,'Expenditure Breakdown'!$T$6:$T$558,"="&I$2,'Expenditure Breakdown'!$S$6:$S$558,"") -> 0 | K6: =SUMIF('Expenditure Breakdown'!$T$6:$T$558,EOMONTH(K$2,0),'Expenditure Breakdown'!$U$6:$U$558) -> 1307335.4 | L6: =SUMIFS('Expenditure Breakdown'!$U$6:$U$558,'Expenditure Breakdown'!$T$6:$T$558,"="&K$2,'Expenditure Breakdown'!$S$6:$S$558,"") -> 0 | M6: =SUMIF('Expenditure Breakdown'!$T$6:$T$558,EOMONTH(M$2,0),'Expenditure Breakdown'!$U$6:$U$558) -> 0 | N6: =SUMIFS('Expenditure Breakdown'!$U$6:$U$558,'Expenditure Breakdown'!$T$6:$T$558,"="&M$2,'Expenditure Breakdown'!$S$6:$S$558,"") -> 0 | O6: =SUMIF('Expenditure Breakdown'!$T$6:$T$558,EOMONTH(O$2,0),'Expenditure Breakdown'!$U$6:$U$558) -> 0 | P6: =SUMIFS('Expenditure Breakdown'!$U$6:$U$558,'Expenditure Breakdown'!$T$6:$T$558,"="&O$2,'Expenditure Breakdown'!$S$6:$S$558,"") -> 0 | Q6: =SUMIF('Expenditure Breakdown'!$T$6:$T$558,EOMONTH(Q$2,0),'Expenditure Breakdown'!$U$6:$U$558) -> 0 | R6: =SUMIFS('Expenditure Breakdown'!$U$6:$U$558,'Expenditure Breakdown'!$T$6:$T$558,"="&Q$2,'Expenditure Breakdown'!$S$6:$S$558,"") -> 0 | S6: =SUMIF('Expenditure Breakdown'!$T$6:$T$558,EOMONTH(S$2,0),'Expenditure Breakdown'!$U$6:$U$558) -> 0 | T6: =SUMIFS('Expenditure Breakdown'!$U$6:$U$558,'Expenditure Breakdown'!$T$6:$T$558,"="&S$2,'Expenditure Breakdown'!$S$6:$S$558,"") -> 0 | U6: =SUMIF('Expenditure Breakdown'!$T$6:$T$558,EOMONTH(U$2,0),'Expenditure Breakdown'!$U$6:$U$558) -> 0 | V6: =SUMIFS('Expenditure Breakdown'!$U$6:$U$558,'Expenditure Breakdown'!$T$6:$T$558,"="&U$2,'Expenditure Breakdown'!$S$6:$S$558,"") -> 0 | W6: =SUMIF('Expenditure Breakdown'!$T$6:$T$558,EOMONTH(W$2,0),'Expenditure Breakdown'!$U$6:$U$558) -> 0 | X6: =SUMIFS('Expenditure Breakdown'!$U$6:$U$558,'Expenditure Breakdown'!$T$6:$T$558,"="&W$2,'Expenditure Breakdown'!$S$6:$S$558,"") -> 0

Sheet Cashflow
D1: [RT: Double Check the first date is always a MONDAY] | F1: 45677 | G1: =F1+7 -> 45684 | H1: =G1+7 -> 45691 | I1: =H1+7 -> 45698 | J1: =I1+7 -> 45705 | K1: =J1+7 -> 45712 | L1: =K1+7 -> 45719 | M1: =L1+7 -> 45726 | N1: =M1+7 -> 45733 | ... LD1: =LC1+7 -> 47847
A2: PLANNED | C2: CHECK | D2: CHECK
B3: Planned Revenue | C3: ='Revenue Tracking'!D4 -> 59995000 | D3: =SUM(F3:LD3) -> 59995000 | F3: =SUMIFS('Revenue Tracking'!$F$13:$F$21, 'Revenue Tracking'!$H$13:$H$21, ">="&F1,'Revenue Tracking'!$H$13:$H$21, "<"&G1) -> 0 | G3: =SUMIFS('Revenue Tracking'!$F$13:$F$21, 'Revenue Tracking'!$H$13:$H$21, ">="&G1,'Revenue Tracking'!$H$13:$H$21, "<"&H1) -> 0 | H3: =SUMIFS('Revenue Tracking'!$F$13:$F$21, 'Revenue Tracking'!$H$13:$H$21, ">="&H1,'Revenue Tracking'!$H$13:$H$21, "<"&I1) -> 0 | I3: =SUMIFS('Revenue Tracking'!$F$13:$F$21, 'Revenue Tracking'!$H$13:$H$21, ">="&I1,'Revenue Tracking'!$H$13:$H$21, "<"&J1) -> 0 | J3: =SUMIFS('Revenue Tracking'!$F$13:$F$21, 'Revenue Tracking'!$H$13:$H$21, ">="&J1,'Revenue Tracking'!$H$13:$H$21, "<"&K1) -> 0 | K3: =SUMIFS('Revenue Tracking'!$F$13:$F$21, 'Revenue Tracking'!$H$13:$H$21, ">="&K1,'Revenue Tracking'!$H$13:$H$21, "<"&L1) -> 0 | L3: =SUMIFS('Revenue Tracking'!$F$13:$F$21, 'Revenue Tracking'!$H$13:$H$21, ">="&L1,'Revenue Tracking'!$H$13:$H$21, "<"&M1) -> 0 | M3: =SUMIFS('Revenue Tracking'!$F$13:$F$21, 'Revenue Tracking'!$H$13:$H$21, ">="&M1,'Revenue Tracking'!$H$13:$H$21, "<"&N1) -> 0 | ... LC3: =SUMIFS('Revenue Tracking'!$F$13:$F$21, 'Revenue Tracking'!$H$13:$H$21, ">="&LC1,'Revenue Tracking'!$H$13:$H$21, "<"&LD1) -> 0 | LD3: =SUMIFS('Revenue Tracking'!$F$13:$F$21, 'Revenue Tracking'!$H$13:$H$21, ">="&LD1,'Revenue Tracking'!$H$13:$H$21, "<"&#REF!) -> 0
B4: Planned Revenue - Cumulative | F4: =F3 -> 0 | G4: =F4+G3 -> 0 | H4: =G4+H3 -> 0 | I4: =H4+I3 -> 0 | J4: =I4+J3 -> 0 | K4: =J4+K3 -> 0 | L4: =K4+L3 -> 0 | M4: =L4+M3 -> 0 | N4: =M4+N3 -> 0 | ... LD4: =LC4+LD3 -> 59995000
B5: Planned Expenditure | C5: ='Revenue Tracking'!D5 -> 56096452 | D5: =SUM(F5:LD5) -> 56096452 | F5: =SUMIFS('Expenditure Breakdown'!$G$6:$G$447, 'Expenditure Breakdown'!$H$6:$H$447, ">="&F1,'Expenditure Breakdown'!$H$6:$H$447, "<"&G1) -> 0 | G5: =SUMIFS('Expenditure Breakdown'!$G$6:$G$447, 'Expenditure Breakdown'!$H$6:$H$447, ">="&G1,'Expenditure Breakdown'!$H$6:$H$447, "<"&H1) -> 0 | H5: =SUMIFS('Expenditure Breakdown'!$G$6:$G$447, 'Expenditure Breakdown'!$H$6:$H$447, ">="&H1,'Expenditure Breakdown'!$H$6:$H$447, "<"&I1) -> 0 | I5: =SUMIFS('Expenditure Breakdown'!$G$6:$G$447, 'Expenditure Breakdown'!$H$6:$H$447, ">="&I1,'Expenditure Breakdown'!$H$6:$H$447, "<"&J1) -> 0 | J5: =SUMIFS('Expenditure Breakdown'!$G$6:$G$447, 'Expenditure Breakdown'!$H$6:$H$447, ">="&J1,'Expenditure Breakdown'!$H$6:$H$447, "<"&K1) -> 0 | K5: =SUMIFS('Expenditure Breakdown'!$G$6:$G$447, 'Expenditure Breakdown'!$H$6:$H$447, ">="&K1,'Expenditure Breakdown'!$H$6:$H$447, "<"&L1) -> 0 | L5: =SUMIFS('Expenditure Breakdown'!$G$6:$G$447, 'Expenditure Breakdown'!$H$6:$H$447, ">="&L1,'Expenditure Breakdown'!$H$6:$H$447, "<"&M1) -> 0 | M5: =SUMIFS('Expenditure Breakdown'!$G$6:$G$447, 'Expenditure Breakdown'!$H$6:$H$447, ">="&M1,'Expenditure Breakdown'!$H$6:$H$447, "<"&N1) -> 0 | ... LC5: =SUMIFS('Expenditure Breakdown'!$G$6:$G$447, 'Expenditure Breakdown'!$H$6:$H$447, ">="&LC1,'Expenditure Breakdown'!$H$6:$H$447, "<"&LD1) -> 0 | LD5: =SUMIFS('Expenditure Breakdown'!$G$6:$G$447, 'Expenditure Breakdown'!$H$6:$H$447, ">="&LD1,'Expenditure Breakdown'!$H$6:$H$447, "<"&#REF!) -> 0
B6: Planned Expenditure - Cumulative | F6: =F5 -> 0 | G6: =F6+G5 -> 0 | H6: =G6+H5 -> 0 | I6: =H6+I5 -> 0 | J6: =I6+J5 -> 0 | K6: =J6+K5 -> 0 | L6: =K6+L5 -> 0 | M6: =L6+M5 -> 0 | N6: =M6+N5 -> 0 | ... LD6: =LC6+LD5 -> 56096452
B7: PLANNED CashFlow | F7: =F4-F6 -> 0 | G7: =G4-G6 -> 0 | H7: =H4-H6 -> 0 | I7: =I4-I6 -> 0 | J7: =J4-J6 -> 0 | K7: =K4-K6 -> 0 | L7: =L4-L6 -> 0 | M7: =M4-M6 -> 0 | ... LD7: =LD4-LD6 -> 3898547.9
A8: ACTUAL | C8: CHECK | D8: CHECK
B9: Actual + Planned Revenue | C9: ='Revenue Tracking'!F4 -> 59995000 | D9: =SUM(F9:LD9) -> 59995000 | F9: =SUMIFS('Revenue Tracking'!$F$13:$F$21, 'Revenue Tracking'!$P$13:$P$21, ">="&F1,'Revenue Tracking'!$P$13:$P$21, "<"&G1) -> 0 | G9: =SUMIFS('Revenue Tracking'!$F$13:$F$21, 'Revenue Tracking'!$P$13:$P$21, ">="&G1,'Revenue Tracking'!$P$13:$P$21, "<"&H1) -> 0 | H9: =SUMIFS('Revenue Tracking'!$F$13:$F$21, 'Revenue Tracking'!$P$13:$P$21, ">="&H1,'Revenue Tracking'!$P$13:$P$21, "<"&I1) -> 0 | I9: =SUMIFS('Revenue Tracking'!$F$13:$F$21, 'Revenue Tracking'!$P$13:$P$21, ">="&I1,'Revenue Tracking'!$P$13:$P$21, "<"&J1) -> 0 | J9: =SUMIFS('Revenue Tracking'!$F$13:$F$21, 'Revenue Tracking'!$P$13:$P$21, ">="&J1,'Revenue Tracking'!$P$13:$P$21, "<"&K1) -> 0 | K9: =SUMIFS('Revenue Tracking'!$F$13:$F$21, 'Revenue Tracking'!$P$13:$P$21, ">="&K1,'Revenue Tracking'!$P$13:$P$21, "<"&L1) -> 0 | L9: =SUMIFS('Revenue Tracking'!$F$13:$F$21, 'Revenue Tracking'!$P$13:$P$21, ">="&L1,'Revenue Tracking'!$P$13:$P$21, "<"&M1) -> 0 | M9: =SUMIFS('Revenue Tracking'!$F$13:$F$21, 'Revenue Tracking'!$P$13:$P$21, ">="&M1,'Revenue Tracking'!$P$13:$P$21, "<"&N1) -> 0 | ... LC9: =SUMIFS('Revenue Tracking'!$F$13:$F$21, 'Revenue Tracking'!$P$13:$P$21, ">="&LC1,'Revenue Tracking'!$P$13:$P$21, "<"&LD1) -> 0 | LD9: =SUMIFS('Revenue Tracking'!$F$13:$F$21, 'Revenue Tracking'!$P$13:$P$21, ">="&LD1,'Revenue Tracking'!$P$13:$P$21, "<"&#REF!) -> 0
B10: Actual + Planned Revenue - Cumulative | F10: =F9 -> 0 | G10: =F10+G9 -> 0 | H10: =G10+H9 -> 0 | I10: =H10+I9 -> 0 | J10: =I10+J9 -> 0 | K10: =J10+K9 -> 0 | L10: =K10+L9 -> 0 | M10: =L10+M9 -> 0 | N10: =M10+N9 -> 0 | ... LD10: =LC10+LD9 -> 59995000
B11: Actual + Planned Expenditure | C11: ='Revenue Tracking'!F5 -> 48292163 | D11: =SUM(F11:LD11) -> 48292163 | F11: =SUMIFS('Expenditure Breakdown'!$Q$6:$Q$447, 'Expenditure Breakdown'!$W$6:$W$447, ">="&F1,'Expenditure Breakdown'!$W$6:$W$447, "<"&G1) -> 0 | G11: =SUMIFS('Expenditure Breakdown'!$Q$6:$Q$447, 'Expenditure Breakdown'!$W$6:$W$447, ">="&G1,'Expenditure Breakdown'!$W$6:$W$447, "<"&H1) -> 0 | H11: =SUMIFS('Expenditure Breakdown'!$Q$6:$Q$447, 'Expenditure Breakdown'!$W$6:$W$447, ">="&H1,'Expenditure Breakdown'!$W$6:$W$447, "<"&I1) -> 0 | I11: =SUMIFS('Expenditure Breakdown'!$Q$6:$Q$447, 'Expenditure Breakdown'!$W$6:$W$447, ">="&I1,'Expenditure Breakdown'!$W$6:$W$447, "<"&J1) -> 0 | J11: =SUMIFS('Expenditure Breakdown'!$Q$6:$Q$447, 'Expenditure Breakdown'!$W$6:$W$447, ">="&J1,'Expenditure Breakdown'!$W$6:$W$447, "<"&K1) -> 0 | K11: =SUMIFS('Expenditure Breakdown'!$Q$6:$Q$447, 'Expenditure Breakdown'!$W$6:$W$447, ">="&K1,'Expenditure Breakdown'!$W$6:$W$447, "<"&L1) -> 0 | L11: =SUMIFS('Expenditure Breakdown'!$Q$6:$Q$447, 'Expenditure Breakdown'!$W$6:$W$447, ">="&L1,'Expenditure Breakdown'!$W$6:$W$447, "<"&M1) -> 0 | M11: =SUMIFS('Expenditure Breakdown'!$Q$6:$Q$447, 'Expenditure Breakdown'!$W$6:$W$447, ">="&M1,'Expenditure Breakdown'!$W$6:$W$447, "<"&N1) -> 0 | ... LD11: =SUMIFS('Expenditure Breakdown'!$Q$6:$Q$447, 'Expenditure Breakdown'!$W$6:$W$447, ">="&LD1,'Expenditure Breakdown'!$W$6:$W$447, "<"&LE1) -> 0
B12: Actual + Planned Expenditure - Cumulative | F12: =F11 -> 0 | G12: =F12+G11 -> 0 | H12: =G12+H11 -> 0 | I12: =H12+I11 -> 0 | J12: =I12+J11 -> 0 | K12: =J12+K11 -> 0 | L12: =K12+L11 -> 0 | M12: =L12+M11 -> 0 | N12: =M12+N11 -> 0 | ... LD12: =LC12+LD11 -> 48292163
B14: ACTUAL CashFlow | F14: =F10-F12 -> 0 | G14: =G10-G12 -> 0 | H14: =H10-H12 -> 0 | I14: =I10-I12 -> 0 | J14: =J10-J12 -> 0 | K14: =K10-K12 -> 0 | L14: =L10-L12 -> 0 | M14: =M10-M12 -> 0 | ... LD14: =LD10-LD12 -> 11702837
C16: CHECK | D16: CHECK
B17: Revenue Recognition | C17: =C3-D17 -> -5000.0029 | D17: =SUM(F17:LD17) -> 60000000 | F17: =SUMIFS('Expenditure Breakdown'!$U$6:$U$447, 'Expenditure Breakdown'!$T$6:$T$447, ">="&F1,'Expenditure Breakdown'!$T$6:$T$447, "<"&G1) -> 0 | G17: =SUMIFS('Expenditure Breakdown'!$U$6:$U$447, 'Expenditure Breakdown'!$T$6:$T$447, ">="&G1,'Expenditure Breakdown'!$T$6:$T$447, "<"&H1) -> 0 | H17: =SUMIFS('Expenditure Breakdown'!$U$6:$U$447, 'Expenditure Breakdown'!$T$6:$T$447, ">="&H1,'Expenditure Breakdown'!$T$6:$T$447, "<"&I1) -> 0 | I17: =SUMIFS('Expenditure Breakdown'!$U$6:$U$447, 'Expenditure Breakdown'!$T$6:$T$447, ">="&I1,'Expenditure Breakdown'!$T$6:$T$447, "<"&J1) -> 0 | J17: =SUMIFS('Expenditure Breakdown'!$U$6:$U$447, 'Expenditure Breakdown'!$T$6:$T$447, ">="&J1,'Expenditure Breakdown'!$T$6:$T$447, "<"&K1) -> 0 | K17: =SUMIFS('Expenditure Breakdown'!$U$6:$U$447, 'Expenditure Breakdown'!$T$6:$T$447, ">="&K1,'Expenditure Breakdown'!$T$6:$T$447, "<"&L1) -> 0 | L17: =SUMIFS('Expenditure Breakdown'!$U$6:$U$447, 'Expenditure Breakdown'!$T$6:$T$447, ">="&L1,'Expenditure Breakdown'!$T$6:$T$447, "<"&M1) -> 0 | M17: =SUMIFS('Expenditure Breakdown'!$U$6:$U$447, 'Expenditure Breakdown'!$T$6:$T$447, ">="&M1,'Expenditure Breakdown'!$T$6:$T$447, "<"&N1) -> 0 | ... LC17: =SUMIFS('Expenditure Breakdown'!$U$6:$U$447, 'Expenditure Breakdown'!$T$6:$T$447, ">="&LC1,'Expenditure Breakdown'!$T$6:$T$447, "<"&LD1) -> 0 | LD17: =SUMIFS('Expenditure Breakdown'!$U$6:$U$447, 'Expenditure Breakdown'!$T$6:$T$447, ">="&LD1,'Expenditure Breakdown'!$T$6:$T$447, "<"&#REF!) -> 0
B18: Revenue Recognition Cumulative | C18: =D17-D18 -> 0 | D18: =MAX(F18:LD18) -> 60000000 | F18: =F17 -> 0 | G18: =F18+G17 -> 0 | H18: =G18+H17 -> 0 | I18: =H18+I17 -> 0 | J18: =I18+J17 -> 0 | K18: =J18+K17 -> 0 | L18: =K18+L17 -> 0 | M18: =L18+M17 -> 0 | N18: =M18+N17 -> 0 | ... LD18: =LC18+LD17 -> 60000000

Sheet Finance - Revenue
A3: Sum of REVENUE RECOGNITION AMOUNT | B3: Column Labels
A4: Row Labels | B4: (blank) | C4: 45808 | D4: 45838 | E4: 45869 | F4: 45900 | G4: 45930 | H4: 45961 | I4: 45991 | J4: 46022 | L4: 46053 | M4: 46081 | N4: 46112 | O4: 46142 | P4: 46173 | Q4: 46265 | R4: Grand Total
A5: (blank)
A6: 1. Panels | E6: 15101046 | F6: 0 | I6: 0 | K6: 0 | R6: 15101046
A7: 2. Inverters | E7: 2967553.5 | F7: 14917.19 | J7: 0 | K7: 0 | L7: 0 | R7: 2982470.7
A8: 3. Mounting Structures | B8: 0 | D8: 1970802.9 | F8: 5981140.4 | G8: 0 | K8: 0 | R8: 7951943.3
A9: 4. DC Equipment | B9: 0 | D9: 5211506 | E9: 2229348 | F9: 1266601.1 | K9: 0 | M9: 0 | R9: 8707455.1
A10: 5. Monitoring | B10: 0 | E10: 20500.235 | F10: 26948.87 | G10: 335.8169 | H10: 3567.0709 | J10: 17237.103 | K10: 0 | L10: 569.64433 | R10: 69158.741
A11: 6. AC Equipment | B11: 0 | D11: 283072.81 | E11: 2094714.6 | F11: 801209.65 | I11: 0 | K11: 0 | M11: 0 | O11: 0 | R11: 3178997
A12: 8. Product Add On | B12: 0 | D12: 322824.35 | E12: 1106461.4 | F12: 698976.6 | H12: 1352.2372 | K12: 0 | M12: 47805.18 | R12: 2177419.7
A13: 9. AC & DC installation | B13: 0 | D13: 795716.76 | E13: 1384002.1 | F13: 2288695.7 | K13: 0 | L13: 661480.97 | R13: 5129895.6
A14: 10. Site Logistics | B14: 0 | D14: 219100.52 | E14: 182063.65 | F14: 48905.674 | G14: 1258.8741 | H14: 4983.0804 | I14: 5872.3514 | J14: 1703.1875 | K14: 0 | L14: 0 | M14: 0 | N14: 0 | R14: 463887.33
A15: 11. Due Dilligence | B15: 0 | D15: 12174.422 | E15: 184585.66 | H15: 58776.044 | I15: 21812.498 | L15: 0 | M15: 216769.03 | R15: 494117.65
A16: 13. Engineering | B16: 0 | F16: 12657.571 | G16: 3164.3928 | H16: 3108.9043 | I16: 3155.1443 | J16: 3118.0251 | K16: 0 | L16: 11580.26 | M16: 1042761.2 | R16: 1079545.5
A17: 14. General Expenses | C17: 0 | D17: 0 | E17: 0 | F17: 0 | G17: 0 | H17: 0 | I17: 0 | J17: 0 | K17: 0 | L17: 0 | M17: 0 | N17: 0 | O17: 0 | P17: 0 | R17: 0
A18: 15. Service Add On
A19: 12. BDP Commission
A20: 7.MV Substation | B20: 0 | F20: 1043498.1 | I20: 11620566 | K20: 0 | R20: 12664064
A21: Grand Total | B21: 0 | C21: 0 | D21: 8815197.7 | E21: 25270275 | F21: 12183551 | G21: 4759.0838 | H21: 71787.337 | I21: 11651406 | J21: 22058.316 | K21: 0 | L21: 673630.88 | M21: 1307335.4 | N21: 0 | O21: 0 | P21: 0 | R21: 60000000
D23: 8815197.7 | E23: 25270275 | F23: 12183551
D24: =GETPIVOTDATA("REVENUE RECOGNITION AMOUNT",$A$3,"INVOICE RAISED DATE",DATE(2025,6,30))-D23 -> -0.00050674379 | E24: =GETPIVOTDATA("REVENUE RECOGNITION AMOUNT",$A$3,"INVOICE RAISED DATE",DATE(2025,7,31))-E23 -> 0.00043057278 | F24: =GETPIVOTDATA("REVENUE RECOGNITION AMOUNT",$A$3,"INVOICE RAISED DATE",DATE(2025,8,31))-F23 -> 0.00043023936

Sheet Finance - COS
A3: Sum of Actual Total | B3: Column Labels
A4: Row Labels | B4: (blank) | C4: 45808 | D4: 45838 | E4: 45869 | F4: 45900 | G4: 45930 | H4: 45961 | I4: 45991 | J4: 46022 | L4: 46053 | M4: 46081 | N4: 46112 | O4: 46142 | P4: 46173 | Q4: 46265 | R4: Grand Total
A5: (blank)
A6: 1. Panels | E6: 13735976 | F6: 43292.88 | I6: -43292.88 | N6: 15240 | R6: 13751216
A7: 2. Inverters | E7: 2495176.2 | J7: 899.72 | L7: -899.72 | R7: 2495176.2
A8: 3. Mounting Structures | D8: 1027304.3 | F8: 3117740 | G8: -74000 | M8: -10034.4 | R8: 4061009.9
A9: 4. DC Equipment | B9: 0 | D9: 2661000 | E9: 611187 | F9: 57000 | M9: -136013 | R9: 3193174
A10: 5. Monitoring | E10: 130940.32 | F10: 11169 | G10: 1060 | H10: 11477.98 | J10: 83760 | L10: 3170 | R10: 241577.3
A11: 6. AC Equipment | D11: 285000 | E11: 1896843 | F11: 57000 | I11: 51044 | J11: 111600 | M11: -392334.65 | O11: 249390 | R11: 2258542.4
A12: 8. Product Add On | D12: 274155.94 | E12: 1142236 | F12: 748350 | H12: 1376.27 | M12: 9531.6 | R12: 2175649.8
A13: 9. AC & DC installation | D13: 1023750 | E13: 2272840 | F13: 3720340 | L13: 1038750 | R13: 8055680
A14: 10. Site Logistics | B14: 0 | D14: 335650 | E14: 271950 | F14: 164367.17 | G14: 7908.92 | H14: 8636.97 | I14: 49179.8 | J14: 90501.1 | L14: 7919.15 | M14: 50857.17 | N14: 2910.19 | R14: 989880.47
A15: 11. Due Dilligence | D15: 10400 | E15: 252556 | H15: 79700 | I15: 28400 | M15: 55600 | R15: 426656
A16: 13. Engineering | F16: 11372 | G16: 2843 | H16: 2843 | I16: 2843 | J16: 2843 | L16: 11580.26 | M16: 976950.74 | R16: 1011275
A17: 14. General Expenses | C17: 6509.86 | D17: 5770.84 | E17: 21295.98 | F17: 50534.6 | G17: 32154.96 | H17: 20629.91 | I17: 15266.94 | J17: 59700.29 | L17: 28655.7 | M17: 52616.57 | N17: 14045.67 | O17: 905.85 | P17: 700 | R17: 308787.17
A18: 15. Service Add On | B18: 0 | F18: 5983.56 | G18: 3399.75 | H18: 14194.43 | I18: 183718.93 | J18: 1519.09 | L18: 274402.47 | M18: 509012.42 | O18: 433158.68 | P18: 728226.48 | Q18: 71895.6 | R18: 2225511.4
A19: 12. BDP Commission | K19: 0 | R19: 0
A20: 7.MV Substation | F20: 582344.8 | I20: 6464282.8 | R20: 7046627.6
A21: Grand Total | B21: 0 | C21: 6509.86 | D21: 5623031 | E21: 22831001 | F21: 8569494 | G21: -26633.37 | H21: 138858.56 | I21: 6751442.6 | J21: 350823.2 | K21: 0 | L21: 1363577.9 | M21: 1116186.4 | N21: 32195.86 | O21: 683454.53 | P21: 728926.48 | Q21: 71895.6 | R21: 48240763
D23: 4704545
D25: =GETPIVOTDATA("Actual Total ",$A$3,"INVOICE RAISED DATE",DATE(2025,6,30))-D23 -> 918486.04

Sheet Certificate - Financial Close
B2: Emergent Energy – Financial Close Completion Certificate | H2: FINANCIAL CLOSE CERTIFICATE
B4: Project Name: | C4: ='Project Plan'!E2 -> Coega Steels Phase 2
B5: COO: | C5: Johannes Potgieter
B6: Programme Manager: | C6: Roedolph Venter
B7: HoPD: | C7: Natasha Watkins-Baker
B9: Date of Phase Completion:
B10: Phase Deliverables Checklist: (Y/N)
B11: Product Agreement | C11: NA
B12: EPC Agreement | C12: NA
B13: O&M Agreeement | C13: NA
B14: Cost Proposal | C14: Signed
B15: Deposit Received | C15: Yes
B16: Risks / Notes | C16: None
B18: Acknowledgement and Acceptance:
B19: Role | C19: Name | D19: Signature | E19: Date
B20: COO | C20: Johannes | D20: JTP | E20: 45953

Sheet Project Margins
A1: [capture project margins from costing sheet]
A3: Products | D3: 0.32
A4: Services | D4: 0.5
A5: Expenses | D5: 0.15
A6: Subcontractors | D6: 0.2

Sheet Equipment Quotes
B2: Equipment Quote and Budget comparision
B4: Description | D4: Budget | F4: Supplier 1 | H4: Variance | J4: Supplier 2 | L4: Variance | N4: Comments / Notes
F7: >Name< | J7: >Name<
B9: Inverters | D9: =SUM(D10:D11) -> #REF! | F9: =SUM(F10:F13) -> 0 | H9: =$D$9-F9 -> #REF! | J9: =SUM(J10:J13) -> 0 | L9: =$D$9-J9 -> #REF!
B10: Inverters | D10: =#REF! -> #REF!
B11: Optimizers | D11: =#REF! -> #REF!
B12: Warranty
B13: Delivery fee
F15: >Name< | J15: >Name<
B17: Mounting Structure | D17: =SUM(D18:D19) -> #REF! | F17: =SUM(F18:F20) -> 0 | H17: =$D$17- F17 -> #REF! | J17: =SUM(J18:J20) -> 0 | L17: =$D$17- J17 -> #REF!
B18: Mounting Structure | D18: =#REF! -> #REF!
B19: Delivery fee
F21: >Name< | J21: >Name<
B23: DC Cable | D23: =SUM(D24:D25) -> #REF! | F23: =SUM(F24:F25) -> 0 | H23: =$D$23- F23 -> #REF! | J23: =SUM(J24:J25) -> 0 | L23: =$D$23- J23 -> #REF!
B24: DC Cable | D24: =#REF! -> #REF!
B25: Delivery fee
F27: >Name< | J27: >Name<
B29: Monitoring system | D29: =SUM(D30:D32) -> #REF! | F29: =SUM(F30:F42) -> 0 | H29: =$D$29-F29 -> #REF! | J29: =SUM(J30:J32) -> 0 | L29: =$D$29-J29 -> #REF!
B30: =#REF! -> #REF! | D30: =#REF! -> #REF!
B31: =#REF! -> #REF! | D31: =#REF! -> #REF!
B32: Delivery fee
F34: >Name< | J34: >Name<
B36: Additional Scope | D36: =SUM(D37:D41) -> #REF! | F36: =SUM(F37:F41) -> 0 | H36: =$D$29-F36 -> #REF! | J36: =SUM(J37:J41) -> 0 | L36: =$D$29-J36 -> #REF!
B37: SCADA | D37: =#REF! -> #REF!
B38: Inverter cage
B39: Cat ladders
B40: Gen Integration
B41: Lifelines
B43: Totals | D43: =D36+D29+D23+D17+D9 -> #REF! | H43: =SUM(H7:H42) -> #REF! | L43: =SUM(L7:L42) -> #REF!
B47: All amounts are incl VAT

Sheet Installer Quotes
B2: Installer Quote and Budget comparision
B4: Description | D4: Budget | G4: Cosmic Sun | J4: Variance | L4: Matthews Group | O4: Variance
B6: AC Equipment | D6: =#REF! -> #REF! | E6: =D6/(1000*'Project Plan'!$E$3) -> #REF! | G6: 277892.91 | H6: =G6/('Project Plan'!$E$3*1000) -> 0.039250411 | J6: =D6-G6 -> #REF! | M6: =L6/('Project Plan'!$E$3*1000) -> 0 | O6: =D6-L6 -> #REF!
B7: DC Equipment | D7: =#REF! -> #REF! | E7: =D7/(1000*'Project Plan'!$E$3) -> #REF! | G7: 142158.25 | H7: =G7/('Project Plan'!$E$3*1000) -> 0.020078849 | J7: =D7-G7 -> #REF! | M7: =L7/('Project Plan'!$E$3*1000) -> 0 | O7: =D7-L7 -> #REF!
B8: AC Labour | D8: =#REF! -> #REF! | E8: =D8/(1000*'Project Plan'!$E$3) -> #REF! | G8: 96174 | H8: =G8/('Project Plan'!$E$3*1000) -> 0.013583898 | J8: =D8-G8 -> #REF! | M8: =L8/('Project Plan'!$E$3*1000) -> 0 | O8: =D8-L8 -> #REF!
B9: DC Labour | D9: =#REF! -> #REF! | E9: =D9/(1000*'Project Plan'!$E$3) -> #REF! | G9: 230160 | H9: =G9/('Project Plan'!$E$3*1000) -> 0.032508475 | J9: =D9-G9 -> #REF! | M9: =L9/('Project Plan'!$E$3*1000) -> 0 | O9: =D9-L9 -> #REF!
B10: Offloading | D10: =#REF! -> #REF! | G10: 0 | J10: =D10-G10 -> #REF! | O10: =D10-L10 -> #REF!
B11: Roof Access/Scaffolding | D11: =#REF! -> #REF! | G11: 29257.61 | J11: =D11-G11 -> #REF! | O11: =D11-L11 -> #REF!
B12: Storage | D12: =#REF! -> #REF! | J12: =D12-G12 -> #REF! | O12: =D12-L12 -> #REF!
B13: Telehandler | D13: =#REF! -> #REF!
B14: HSE | D14: 0
B15: Totals | D15: =SUM(D6:D13) -> #REF! | G15: =SUM(G6:G13) -> 775642.77 | J15: =SUM(J6:J14) -> #REF! | L15: =SUM(L6:L13) -> 0 | O15: =SUM(O6:O14) -> #REF!
B18: Description | D18: Budget | G18: >Installer Name 3< | J18: Variance | L18: >Installer Name 4< | O18: Variance
B20: AC installation | D20: =#REF! -> #REF! | E20: =D20/(1000*'Project Plan'!$E$3) -> #REF! | H20: =G20/(1000*'Project Plan'!$E$3) -> 0 | J20: =D20-G20 -> #REF! | M20: =L20/(1000*'Project Plan'!$E$3) -> 0 | O20: =D6-L20 -> #REF!
B21: AC equipment | D21: =#REF! -> #REF! | E21: =D21/(1000*'Project Plan'!$E$3) -> #REF! | J21: =D21-G21 -> #REF! | M21: =L21/(1000*'Project Plan'!$E$3) -> 0 | O21: =D7-L21 -> #REF!
B22: DC installation | D22: =#REF! -> #REF! | E22: =D22/(1000*'Project Plan'!$E$3) -> #REF! | H22: =G22/(1000*'Project Plan'!$E$3) -> 0 | J22: =D22-G22 -> #REF! | M22: =L22/(1000*'Project Plan'!$E$3) -> 0 | O22: =D8-L22 -> #REF!
B23: DC equipment | D23: =SUM(#REF!) -> #REF! | E23: =D23/(1000*'Project Plan'!$E$3) -> #REF! | J23: =D23-G23 -> #REF! | O23: =D9-L23 -> #REF!
B24: Storage | D24: =#REF! -> #REF! | J24: =D24-G24 -> #REF! | O24: =D10-L24 -> #REF!
B25: Panel lifting equipment | D25: =SUM(#REF!) -> #REF! | J25: =D25-G25 -> #REF! | O25: =D11-L25 -> #REF!
B26: Offloading | D26: =#REF! -> #REF! | J26: =D26-G26 -> #REF! | O26: =D12-L26 -> #REF!
B29: Totals | D29: =SUM(D20:D27) -> #REF! | G29: =SUM(G20:G27) -> 0 | J29: =SUM(J20:J28) -> #REF! | L29: =SUM(L20:L27) -> 0 | O29: =SUM(O20:O28) -> #REF!
B32: Budget Summary
B34: Budget | D34: =D15 -> #REF!
B35: =G4 -> Cosmic Sun | D35: =G15 -> 775642.77
B36: =L4 -> Matthews Group | D36: =L15 -> 0
B37: =G18 -> >Installer Name 3< | D37: =G29 -> 0
B38: =L18 -> >Installer Name 4< | D38: =L29 -> 0
B40: =IF(D40<D34,"Saving","Loss") -> #REF! | D40: =D34-MIN(D35:D38) -> #REF!
B42: All amounts are exc VAT

Sheet Decision Register
B1: =D15 -> Coega Steels Phase 2 | E1: Decision Register
B3: ID | C3: Decision Description | D3: Decision Impact | E3: Proposed Date | F3: Proposed By | G3: Status | H3: Approved By | I3: Date | J3: Results / Comments
B4: DEC001
B5: DEC002
B6: DEC003
B7: DEC004
B8: DEC005
B9: DEC006
B10: DEC007
B11: DEC008
B12: DEC009
B13: DEC010
D15: {='Project Plan'!E2:H2} -> Coega Steels Phase 2 | E15: 0 | F15: 0 | G15: 0
