Workbook
Name Inverter_Capacity: #REF!
Name Inverter_Supplier: #REF!
Name Inverter_Supplier: #REF!
Name Inverter_Supplier: #REF!
Name Project_Size: 'Certificate - Financial Close'!Projectsize
Name Project_Size: Compliance!Projectsize
Name Project_Size: 'Finance - Revenue'!Projectsize
Name Project_Size: Projectsize
Name Projectsize: #REF!
Name Projectsize: #REF!
Name Projectsize: #REF!
Name Projectsize: 'Project Margins'!$K$5
Name Security_Serv: #REF!
Name Security_Serv: #REF!
Name SSS: #REF!
Name SSS: #REF!
Name USD_ZAR: #REF!
Name USD_ZAR: #REF!
Name USD_ZAR: #REF!

Sheet Sheet1
A1: PROJECT PLAN
A2: # | B2: Project Milestone | C2: Planned Start Date | D2: Duration (Work Days) | E2: Planned End Date | F2: Actual Start Date | H2: Actual End Date | J2: Comments | L2: =C3 -> 43831 | M2: =L2+3 -> 43834 | N2: =M2+7 -> 43841 | O2: =N2+7 -> 43848 | P2: =O2+7 -> 43855 | Q2: =P2+6 -> 43861 | R2: =Q2+1 -> 43862 | S2: =R2+7 -> 43869 | T2: =S2+7 -> 43876 | U2: =T2+7 -> 43883 | V2: =U2+6 -> 43889 | W2: =V2+7 -> 43896 | X2: =W2+7 -> 43903 | Y2: =X2+7 -> 43910 | Z2: =Y2+7 -> 43917 | AA2: =Z2+3 -> 43920 | AB2: =AA2+4 -> 43924 | AC2: =AB2+7 -> 43931 | AD2: =AC2+7 -> 43938 | AE2: =AD2+7 -> 43945 | AF2: =AE2+6 -> 43951 | AG2: =AF2+2 -> 43953 | AH2: =AG2+7 -> 43960 | AI2: =AH2+7 -> 43967 | AJ2: =AI2+7 -> 43974 | AK2: =AJ2+7 -> 43981 | AL2: =AK2+1 -> 43982 | AM2: =AL2+6 -> 43988 | AN2: =AM2+7 -> 43995 | AO2: =AN2+7 -> 44002 | AP2: =AO2+7 -> 44009 | AQ2: =AP2+3 -> 44012 | AR2: =AQ2+4 -> 44016 | AS2: =AR2+7 -> 44023 | AT2: =AS2+7 -> 44030 | AU2: =AT2+7 -> 44037 | AV2: =AU2+6 -> 44043 | AW2: =AV2+1 -> 44044 | AX2: =AW2+7 -> 44051 | AY2: =AX2+7 -> 44058 | AZ2: =AY2+7 -> 44065 | BA2: =AZ2+7 -> 44072 | BB2: =BA2+2 -> 44074 | BC2: =BB2+5 -> 44079 | BD2: =BC2+7 -> 44086 | BE2: =BD2+7 -> 44093 | BF2: =BE2+7 -> 44100 | BG2: =BF2+4 -> 44104
A3: 1 | B3: Contract Signature | C3: 43831 | D3: 1 | E3: 43832 | F3: 43831 | G3: 1 | H3: 43832 | L3: =IF(AND($F3<(L$2+7),$F3>L$2),1, IF(AND($H3<L$2+7,$H3>L$2),3, IF(AND($F3<=L$2, $H3>=L$2), 2, "" ))) -> 3 | M3: =IF(AND($F3<(M$2+7),$F3>M$2),1, IF(AND($H3<M$2+7,$H3>M$2),3, IF(AND($F3<=M$2, $H3>=M$2), 2, "" ))) | N3: =IF(AND($F3<(N$2+7),$F3>N$2),1, IF(AND($H3<N$2+7,$H3>N$2),3, IF(AND($F3<=N$2, $H3>=N$2), 2, "" ))) | O3: =IF(AND($F3<(O$2+7),$F3>O$2),1, IF(AND($H3<O$2+7,$H3>O$2),3, IF(AND($F3<=O$2, $H3>=O$2), 2, "" ))) | P3: =IF(AND($F3<(P$2+7),$F3>P$2),1, IF(AND($H3<P$2+7,$H3>P$2),3, IF(AND($F3<=P$2, $H3>=P$2), 2, "" ))) | Q3: =IF(AND($F3<(Q$2+7),$F3>Q$2),1, IF(AND($H3<Q$2+7,$H3>Q$2),3, IF(AND($F3<=Q$2, $H3>=Q$2), 2, "" ))) | R3: =IF(AND($F3<(R$2+7),$F3>R$2),1, IF(AND($H3<R$2+7,$H3>R$2),3, IF(AND($F3<=R$2, $H3>=R$2), 2, "" ))) | S3: =IF(AND($F3<(S$2+7),$F3>S$2),1, IF(AND($H3<S$2+7,$H3>S$2),3, IF(AND($F3<=S$2, $H3>=S$2), 2, "" ))) | ... AQ3: =IF(AND($F3<(AQ$2+7),$F3>AQ$2),1, IF(AND($H3<AQ$2+7,$H3>AQ$2),3, IF(AND($F3<=AQ$2, $H3>=AQ$2), 2, "" )))
A4: A | B4: PAYMENT MILESTONE 1: DEPOSIT | C4: 43832 | D4: 1 | E4: 43833 | F4: 43832 | G4: 1 | H4: 43833 | L4: =IF(AND($F4<(L$2+7),$F4>L$2),1, IF(AND($H4<L$2+7,$H4>L$2),3, IF(AND($F4<=L$2, $H4>=L$2), 2, "" ))) -> 1 | M4: =IF(AND($F4<(M$2+7),$F4>M$2),1, IF(AND($H4<M$2+7,$H4>M$2),3, IF(AND($F4<=M$2, $H4>=M$2), 2, "" ))) | N4: =IF(AND($F4<(N$2+7),$F4>N$2),1, IF(AND($H4<N$2+7,$H4>N$2),3, IF(AND($F4<=N$2, $H4>=N$2), 2, "" ))) | O4: =IF(AND($F4<(O$2+7),$F4>O$2),1, IF(AND($H4<O$2+7,$H4>O$2),3, IF(AND($F4<=O$2, $H4>=O$2), 2, "" ))) | P4: =IF(AND($F4<(P$2+7),$F4>P$2),1, IF(AND($H4<P$2+7,$H4>P$2),3, IF(AND($F4<=P$2, $H4>=P$2), 2, "" ))) | Q4: =IF(AND($F4<(Q$2+7),$F4>Q$2),1, IF(AND($H4<Q$2+7,$H4>Q$2),3, IF(AND($F4<=Q$2, $H4>=Q$2), 2, "" ))) | R4: =IF(AND($F4<(R$2+7),$F4>R$2),1, IF(AND($H4<R$2+7,$H4>R$2),3, IF(AND($F4<=R$2, $H4>=R$2), 2, "" ))) | S4: =IF(AND($F4<(S$2+7),$F4>S$2),1, IF(AND($H4<S$2+7,$H4>S$2),3, IF(AND($F4<=S$2, $H4>=S$2), 2, "" ))) | ... AQ4: =IF(AND($F4<(AQ$2+7),$F4>AQ$2),1, IF(AND($H4<AQ$2+7,$H4>AQ$2),3, IF(AND($F4<=AQ$2, $H4>=AQ$2), 2, "" )))
A5: 2 | B5: Structural and Electrical Due Diligences | C5: 43833 | D5: 5 | E5: 43840 | F5: 43833 | G5: 5 | H5: 43840 | L5: =IF(AND($F5<(L$2+7),$F5>L$2),1, IF(AND($H5<L$2+7,$H5>L$2),3, IF(AND($F5<=L$2, $H5>=L$2), 2, "" ))) -> 1 | M5: =IF(AND($F5<(M$2+7),$F5>M$2),1, IF(AND($H5<M$2+7,$H5>M$2),3, IF(AND($F5<=M$2, $H5>=M$2), 2, "" ))) -> 3 | N5: =IF(AND($F5<(N$2+7),$F5>N$2),1, IF(AND($H5<N$2+7,$H5>N$2),3, IF(AND($F5<=N$2, $H5>=N$2), 2, "" ))) | O5: =IF(AND($F5<(O$2+7),$F5>O$2),1, IF(AND($H5<O$2+7,$H5>O$2),3, IF(AND($F5<=O$2, $H5>=O$2), 2, "" ))) | P5: =IF(AND($F5<(P$2+7),$F5>P$2),1, IF(AND($H5<P$2+7,$H5>P$2),3, IF(AND($F5<=P$2, $H5>=P$2), 2, "" ))) | Q5: =IF(AND($F5<(Q$2+7),$F5>Q$2),1, IF(AND($H5<Q$2+7,$H5>Q$2),3, IF(AND($F5<=Q$2, $H5>=Q$2), 2, "" ))) | R5: =IF(AND($F5<(R$2+7),$F5>R$2),1, IF(AND($H5<R$2+7,$H5>R$2),3, IF(AND($F5<=R$2, $H5>=R$2), 2, "" ))) | S5: =IF(AND($F5<(S$2+7),$F5>S$2),1, IF(AND($H5<S$2+7,$H5>S$2),3, IF(AND($F5<=S$2, $H5>=S$2), 2, "" ))) | ... AQ5: =IF(AND($F5<(AQ$2+7),$F5>AQ$2),1, IF(AND($H5<AQ$2+7,$H5>AQ$2),3, IF(AND($F5<=AQ$2, $H5>=AQ$2), 2, "" )))
A6: 3 | B6: Design Confirmation | C6: 43841 | D6: 2 | E6: 43844 | F6: 43841 | G6: 2 | H6: 43844 | L6: =IF(AND($F6<(L$2+7),$F6>L$2),1, IF(AND($H6<L$2+7,$H6>L$2),3, IF(AND($F6<=L$2, $H6>=L$2), 2, "" ))) | M6: =IF(AND($F6<(M$2+7),$F6>M$2),1, IF(AND($H6<M$2+7,$H6>M$2),3, IF(AND($F6<=M$2, $H6>=M$2), 2, "" ))) | N6: =IF(AND($F6<(N$2+7),$F6>N$2),1, IF(AND($H6<N$2+7,$H6>N$2),3, IF(AND($F6<=N$2, $H6>=N$2), 2, "" ))) -> 3 | O6: =IF(AND($F6<(O$2+7),$F6>O$2),1, IF(AND($H6<O$2+7,$H6>O$2),3, IF(AND($F6<=O$2, $H6>=O$2), 2, "" ))) | P6: =IF(AND($F6<(P$2+7),$F6>P$2),1, IF(AND($H6<P$2+7,$H6>P$2),3, IF(AND($F6<=P$2, $H6>=P$2), 2, "" ))) | Q6: =IF(AND($F6<(Q$2+7),$F6>Q$2),1, IF(AND($H6<Q$2+7,$H6>Q$2),3, IF(AND($F6<=Q$2, $H6>=Q$2), 2, "" ))) | R6: =IF(AND($F6<(R$2+7),$F6>R$2),1, IF(AND($H6<R$2+7,$H6>R$2),3, IF(AND($F6<=R$2, $H6>=R$2), 2, "" ))) | S6: =IF(AND($F6<(S$2+7),$F6>S$2),1, IF(AND($H6<S$2+7,$H6>S$2),3, IF(AND($F6<=S$2, $H6>=S$2), 2, "" ))) | ... AQ6: =IF(AND($F6<(AQ$2+7),$F6>AQ$2),1, IF(AND($H6<AQ$2+7,$H6>AQ$2),3, IF(AND($F6<=AQ$2, $H6>=AQ$2), 2, "" )))
A7: 4 | B7: Equipment Procurement | C7: 43833 | E7: 43949 | F7: 43833 | H7: 43949 | L7: =IF(AND($F7<(L$2+7),$F7>L$2),1, IF(AND($H7<L$2+7,$H7>L$2),3, IF(AND($F7<=L$2, $H7>=L$2), 2, "" ))) -> 1 | M7: =IF(AND($F7<(M$2+7),$F7>M$2),1, IF(AND($H7<M$2+7,$H7>M$2),3, IF(AND($F7<=M$2, $H7>=M$2), 2, "" ))) -> 2 | N7: =IF(AND($F7<(N$2+7),$F7>N$2),1, IF(AND($H7<N$2+7,$H7>N$2),3, IF(AND($F7<=N$2, $H7>=N$2), 2, "" ))) -> 2 | O7: =IF(AND($F7<(O$2+7),$F7>O$2),1, IF(AND($H7<O$2+7,$H7>O$2),3, IF(AND($F7<=O$2, $H7>=O$2), 2, "" ))) -> 2 | P7: =IF(AND($F7<(P$2+7),$F7>P$2),1, IF(AND($H7<P$2+7,$H7>P$2),3, IF(AND($F7<=P$2, $H7>=P$2), 2, "" ))) -> 2 | Q7: =IF(AND($F7<(Q$2+7),$F7>Q$2),1, IF(AND($H7<Q$2+7,$H7>Q$2),3, IF(AND($F7<=Q$2, $H7>=Q$2), 2, "" ))) -> 2 | R7: =IF(AND($F7<(R$2+7),$F7>R$2),1, IF(AND($H7<R$2+7,$H7>R$2),3, IF(AND($F7<=R$2, $H7>=R$2), 2, "" ))) -> 2 | S7: =IF(AND($F7<(S$2+7),$F7>S$2),1, IF(AND($H7<S$2+7,$H7>S$2),3, IF(AND($F7<=S$2, $H7>=S$2), 2, "" ))) -> 2 | ... AQ7: =IF(AND($F7<(AQ$2+7),$F7>AQ$2),1, IF(AND($H7<AQ$2+7,$H7>AQ$2),3, IF(AND($F7<=AQ$2, $H7>=AQ$2), 2, "" )))
B8: Panel Procurement | C8: 43833 | D8: 5 | E8: 43840 | F8: 43833 | G8: 5 | H8: 43840 | L8: =IF(AND($F8<(L$2+7),$F8>L$2),1, IF(AND($H8<L$2+7,$H8>L$2),3, IF(AND($F8<=L$2, $H8>=L$2), 2, "" ))) -> 1 | M8: =IF(AND($F8<(M$2+7),$F8>M$2),1, IF(AND($H8<M$2+7,$H8>M$2),3, IF(AND($F8<=M$2, $H8>=M$2), 2, "" ))) -> 3 | N8: =IF(AND($F8<(N$2+7),$F8>N$2),1, IF(AND($H8<N$2+7,$H8>N$2),3, IF(AND($F8<=N$2, $H8>=N$2), 2, "" ))) | O8: =IF(AND($F8<(O$2+7),$F8>O$2),1, IF(AND($H8<O$2+7,$H8>O$2),3, IF(AND($F8<=O$2, $H8>=O$2), 2, "" ))) | P8: =IF(AND($F8<(P$2+7),$F8>P$2),1, IF(AND($H8<P$2+7,$H8>P$2),3, IF(AND($F8<=P$2, $H8>=P$2), 2, "" ))) | Q8: =IF(AND($F8<(Q$2+7),$F8>Q$2),1, IF(AND($H8<Q$2+7,$H8>Q$2),3, IF(AND($F8<=Q$2, $H8>=Q$2), 2, "" ))) | R8: =IF(AND($F8<(R$2+7),$F8>R$2),1, IF(AND($H8<R$2+7,$H8>R$2),3, IF(AND($F8<=R$2, $H8>=R$2), 2, "" ))) | S8: =IF(AND($F8<(S$2+7),$F8>S$2),1, IF(AND($H8<S$2+7,$H8>S$2),3, IF(AND($F8<=S$2, $H8>=S$2), 2, "" ))) | ... AQ8: =IF(AND($F8<(AQ$2+7),$F8>AQ$2),1, IF(AND($H8<AQ$2+7,$H8>AQ$2),3, IF(AND($F8<=AQ$2, $H8>=AQ$2), 2, "" )))
B9: Inverter Procurement | C9: 43941 | D9: 5 | E9: 43949 | F9: 43941 | G9: 5 | H9: 43949 | L9: =IF(AND($F9<(L$2+7),$F9>L$2),1, IF(AND($H9<L$2+7,$H9>L$2),3, IF(AND($F9<=L$2, $H9>=L$2), 2, "" ))) | M9: =IF(AND($F9<(M$2+7),$F9>M$2),1, IF(AND($H9<M$2+7,$H9>M$2),3, IF(AND($F9<=M$2, $H9>=M$2), 2, "" ))) | N9: =IF(AND($F9<(N$2+7),$F9>N$2),1, IF(AND($H9<N$2+7,$H9>N$2),3, IF(AND($F9<=N$2, $H9>=N$2), 2, "" ))) | O9: =IF(AND($F9<(O$2+7),$F9>O$2),1, IF(AND($H9<O$2+7,$H9>O$2),3, IF(AND($F9<=O$2, $H9>=O$2), 2, "" ))) | P9: =IF(AND($F9<(P$2+7),$F9>P$2),1, IF(AND($H9<P$2+7,$H9>P$2),3, IF(AND($F9<=P$2, $H9>=P$2), 2, "" ))) | Q9: =IF(AND($F9<(Q$2+7),$F9>Q$2),1, IF(AND($H9<Q$2+7,$H9>Q$2),3, IF(AND($F9<=Q$2, $H9>=Q$2), 2, "" ))) | R9: =IF(AND($F9<(R$2+7),$F9>R$2),1, IF(AND($H9<R$2+7,$H9>R$2),3, IF(AND($F9<=R$2, $H9>=R$2), 2, "" ))) | S9: =IF(AND($F9<(S$2+7),$F9>S$2),1, IF(AND($H9<S$2+7,$H9>S$2),3, IF(AND($F9<=S$2, $H9>=S$2), 2, "" ))) | ... AQ9: =IF(AND($F9<(AQ$2+7),$F9>AQ$2),1, IF(AND($H9<AQ$2+7,$H9>AQ$2),3, IF(AND($F9<=AQ$2, $H9>=AQ$2), 2, "" )))
B10: Mounting Structure Procurement | C10: 43941 | D10: 5 | E10: 43949 | F10: 43941 | G10: 5 | H10: 43949 | L10: =IF(AND($F10<(L$2+7),$F10>L$2),1, IF(AND($H10<L$2+7,$H10>L$2),3, IF(AND($F10<=L$2, $H10>=L$2), 2, "" ))) | M10: =IF(AND($F10<(M$2+7),$F10>M$2),1, IF(AND($H10<M$2+7,$H10>M$2),3, IF(AND($F10<=M$2, $H10>=M$2), 2, "" ))) | N10: =IF(AND($F10<(N$2+7),$F10>N$2),1, IF(AND($H10<N$2+7,$H10>N$2),3, IF(AND($F10<=N$2, $H10>=N$2), 2, "" ))) | O10: =IF(AND($F10<(O$2+7),$F10>O$2),1, IF(AND($H10<O$2+7,$H10>O$2),3, IF(AND($F10<=O$2, $H10>=O$2), 2, "" ))) | P10: =IF(AND($F10<(P$2+7),$F10>P$2),1, IF(AND($H10<P$2+7,$H10>P$2),3, IF(AND($F10<=P$2, $H10>=P$2), 2, "" ))) | Q10: =IF(AND($F10<(Q$2+7),$F10>Q$2),1, IF(AND($H10<Q$2+7,$H10>Q$2),3, IF(AND($F10<=Q$2, $H10>=Q$2), 2, "" ))) | R10: =IF(AND($F10<(R$2+7),$F10>R$2),1, IF(AND($H10<R$2+7,$H10>R$2),3, IF(AND($F10<=R$2, $H10>=R$2), 2, "" ))) | S10: =IF(AND($F10<(S$2+7),$F10>S$2),1, IF(AND($H10<S$2+7,$H10>S$2),3, IF(AND($F10<=S$2, $H10>=S$2), 2, "" ))) | ... AQ10: =IF(AND($F10<(AQ$2+7),$F10>AQ$2),1, IF(AND($H10<AQ$2+7,$H10>AQ$2),3, IF(AND($F10<=AQ$2, $H10>=AQ$2), 2, "" )))
B11: BOS Procurement | C11: 43941 | D11: 5 | E11: 43949 | F11: 43941 | G11: 5 | H11: 43949 | L11: =IF(AND($F11<(L$2+7),$F11>L$2),1, IF(AND($H11<L$2+7,$H11>L$2),3, IF(AND($F11<=L$2, $H11>=L$2), 2, "" ))) | M11: =IF(AND($F11<(M$2+7),$F11>M$2),1, IF(AND($H11<M$2+7,$H11>M$2),3, IF(AND($F11<=M$2, $H11>=M$2), 2, "" ))) | N11: =IF(AND($F11<(N$2+7),$F11>N$2),1, IF(AND($H11<N$2+7,$H11>N$2),3, IF(AND($F11<=N$2, $H11>=N$2), 2, "" ))) | O11: =IF(AND($F11<(O$2+7),$F11>O$2),1, IF(AND($H11<O$2+7,$H11>O$2),3, IF(AND($F11<=O$2, $H11>=O$2), 2, "" ))) | P11: =IF(AND($F11<(P$2+7),$F11>P$2),1, IF(AND($H11<P$2+7,$H11>P$2),3, IF(AND($F11<=P$2, $H11>=P$2), 2, "" ))) | Q11: =IF(AND($F11<(Q$2+7),$F11>Q$2),1, IF(AND($H11<Q$2+7,$H11>Q$2),3, IF(AND($F11<=Q$2, $H11>=Q$2), 2, "" ))) | R11: =IF(AND($F11<(R$2+7),$F11>R$2),1, IF(AND($H11<R$2+7,$H11>R$2),3, IF(AND($F11<=R$2, $H11>=R$2), 2, "" ))) | S11: =IF(AND($F11<(S$2+7),$F11>S$2),1, IF(AND($H11<S$2+7,$H11>S$2),3, IF(AND($F11<=S$2, $H11>=S$2), 2, "" ))) | ... AQ11: =IF(AND($F11<(AQ$2+7),$F11>AQ$2),1, IF(AND($H11<AQ$2+7,$H11>AQ$2),3, IF(AND($F11<=AQ$2, $H11>=AQ$2), 2, "" )))
A12: 5 | B12: Internal Project Kick off | C12: 43936 | D12: 5 | E12: 43943 | F12: 43936 | G12: 5 | H12: 43943
A13: 6 | B13: Client Project Kick-off | C13: 43963 | D13: 5 | E13: 43970 | F13: 43963 | G13: 5 | H13: 43970 | L13: =IF(AND($F13<(L$2+7),$F13>L$2),1, IF(AND($H13<L$2+7,$H13>L$2),3, IF(AND($F13<=L$2, $H13>=L$2), 2, "" ))) | M13: =IF(AND($F13<(M$2+7),$F13>M$2),1, IF(AND($H13<M$2+7,$H13>M$2),3, IF(AND($F13<=M$2, $H13>=M$2), 2, "" ))) | N13: =IF(AND($F13<(N$2+7),$F13>N$2),1, IF(AND($H13<N$2+7,$H13>N$2),3, IF(AND($F13<=N$2, $H13>=N$2), 2, "" ))) | O13: =IF(AND($F13<(O$2+7),$F13>O$2),1, IF(AND($H13<O$2+7,$H13>O$2),3, IF(AND($F13<=O$2, $H13>=O$2), 2, "" ))) | P13: =IF(AND($F13<(P$2+7),$F13>P$2),1, IF(AND($H13<P$2+7,$H13>P$2),3, IF(AND($F13<=P$2, $H13>=P$2), 2, "" ))) | Q13: =IF(AND($F13<(Q$2+7),$F13>Q$2),1, IF(AND($H13<Q$2+7,$H13>Q$2),3, IF(AND($F13<=Q$2, $H13>=Q$2), 2, "" ))) | R13: =IF(AND($F13<(R$2+7),$F13>R$2),1, IF(AND($H13<R$2+7,$H13>R$2),3, IF(AND($F13<=R$2, $H13>=R$2), 2, "" ))) | S13: =IF(AND($F13<(S$2+7),$F13>S$2),1, IF(AND($H13<S$2+7,$H13>S$2),3, IF(AND($F13<=S$2, $H13>=S$2), 2, "" ))) | ... AQ13: =IF(AND($F13<(AQ$2+7),$F13>AQ$2),1, IF(AND($H13<AQ$2+7,$H13>AQ$2),3, IF(AND($F13<=AQ$2, $H13>=AQ$2), 2, "" )))
A14: 7 | B14: Equipment Delivery | C14: 43983 | D14: 9 | E14: 43994 | F14: 43983 | G14: 9 | H14: 43994 | L14: =IF(AND($F14<(L$2+7),$F14>L$2),1, IF(AND($H14<L$2+7,$H14>L$2),3, IF(AND($F14<=L$2, $H14>=L$2), 2, "" ))) | M14: =IF(AND($F14<(M$2+7),$F14>M$2),1, IF(AND($H14<M$2+7,$H14>M$2),3, IF(AND($F14<=M$2, $H14>=M$2), 2, "" ))) | N14: =IF(AND($F14<(N$2+7),$F14>N$2),1, IF(AND($H14<N$2+7,$H14>N$2),3, IF(AND($F14<=N$2, $H14>=N$2), 2, "" ))) | O14: =IF(AND($F14<(O$2+7),$F14>O$2),1, IF(AND($H14<O$2+7,$H14>O$2),3, IF(AND($F14<=O$2, $H14>=O$2), 2, "" ))) | P14: =IF(AND($F14<(P$2+7),$F14>P$2),1, IF(AND($H14<P$2+7,$H14>P$2),3, IF(AND($F14<=P$2, $H14>=P$2), 2, "" ))) | Q14: =IF(AND($F14<(Q$2+7),$F14>Q$2),1, IF(AND($H14<Q$2+7,$H14>Q$2),3, IF(AND($F14<=Q$2, $H14>=Q$2), 2, "" ))) | R14: =IF(AND($F14<(R$2+7),$F14>R$2),1, IF(AND($H14<R$2+7,$H14>R$2),3, IF(AND($F14<=R$2, $H14>=R$2), 2, "" ))) | S14: =IF(AND($F14<(S$2+7),$F14>S$2),1, IF(AND($H14<S$2+7,$H14>S$2),3, IF(AND($F14<=S$2, $H14>=S$2), 2, "" ))) | ... AQ14: =IF(AND($F14<(AQ$2+7),$F14>AQ$2),1, IF(AND($H14<AQ$2+7,$H14>AQ$2),3, IF(AND($F14<=AQ$2, $H14>=AQ$2), 2, "" )))
B15: Mounting Structure Delivery | C15: 43983 | D15: 2 | E15: 43985 | F15: 43983 | G15: 2 | H15: 43985
B16: Panel Delivery | C16: 43990 | D16: 2 | E16: 43992 | F16: 43990 | G16: 2 | H16: 43992 | L16: =IF(AND($F16<(L$2+7),$F16>L$2),1, IF(AND($H16<L$2+7,$H16>L$2),3, IF(AND($F16<=L$2, $H16>=L$2), 2, "" ))) | M16: =IF(AND($F16<(M$2+7),$F16>M$2),1, IF(AND($H16<M$2+7,$H16>M$2),3, IF(AND($F16<=M$2, $H16>=M$2), 2, "" ))) | N16: =IF(AND($F16<(N$2+7),$F16>N$2),1, IF(AND($H16<N$2+7,$H16>N$2),3, IF(AND($F16<=N$2, $H16>=N$2), 2, "" ))) | O16: =IF(AND($F16<(O$2+7),$F16>O$2),1, IF(AND($H16<O$2+7,$H16>O$2),3, IF(AND($F16<=O$2, $H16>=O$2), 2, "" ))) | P16: =IF(AND($F16<(P$2+7),$F16>P$2),1, IF(AND($H16<P$2+7,$H16>P$2),3, IF(AND($F16<=P$2, $H16>=P$2), 2, "" ))) | Q16: =IF(AND($F16<(Q$2+7),$F16>Q$2),1, IF(AND($H16<Q$2+7,$H16>Q$2),3, IF(AND($F16<=Q$2, $H16>=Q$2), 2, "" ))) | R16: =IF(AND($F16<(R$2+7),$F16>R$2),1, IF(AND($H16<R$2+7,$H16>R$2),3, IF(AND($F16<=R$2, $H16>=R$2), 2, "" ))) | S16: =IF(AND($F16<(S$2+7),$F16>S$2),1, IF(AND($H16<S$2+7,$H16>S$2),3, IF(AND($F16<=S$2, $H16>=S$2), 2, "" ))) | ... AQ16: =IF(AND($F16<(AQ$2+7),$F16>AQ$2),1, IF(AND($H16<AQ$2+7,$H16>AQ$2),3, IF(AND($F16<=AQ$2, $H16>=AQ$2), 2, "" )))
B17: Generator Delivery | C17: 43983 | D17: 2 | E17: 43985 | F17: 43983 | G17: 2 | H17: 43985
A18: B | B18: PAYMENT MILESTONE 2: DELIVERY OF PV PANELS | C18: 43992 | D18: 2 | E18: 43994 | F18: 43992 | G18: 2 | H18: 43994
B19: Inverter Delivery | C19: 43983 | D19: 2 | E19: 43985 | F19: 43983 | G19: 2 | H19: 43985 | L19: =IF(AND($F19<(L$2+7),$F19>L$2),1, IF(AND($H19<L$2+7,$H19>L$2),3, IF(AND($F19<=L$2, $H19>=L$2), 2, "" ))) | M19: =IF(AND($F19<(M$2+7),$F19>M$2),1, IF(AND($H19<M$2+7,$H19>M$2),3, IF(AND($F19<=M$2, $H19>=M$2), 2, "" ))) | N19: =IF(AND($F19<(N$2+7),$F19>N$2),1, IF(AND($H19<N$2+7,$H19>N$2),3, IF(AND($F19<=N$2, $H19>=N$2), 2, "" ))) | O19: =IF(AND($F19<(O$2+7),$F19>O$2),1, IF(AND($H19<O$2+7,$H19>O$2),3, IF(AND($F19<=O$2, $H19>=O$2), 2, "" ))) | P19: =IF(AND($F19<(P$2+7),$F19>P$2),1, IF(AND($H19<P$2+7,$H19>P$2),3, IF(AND($F19<=P$2, $H19>=P$2), 2, "" ))) | Q19: =IF(AND($F19<(Q$2+7),$F19>Q$2),1, IF(AND($H19<Q$2+7,$H19>Q$2),3, IF(AND($F19<=Q$2, $H19>=Q$2), 2, "" ))) | R19: =IF(AND($F19<(R$2+7),$F19>R$2),1, IF(AND($H19<R$2+7,$H19>R$2),3, IF(AND($F19<=R$2, $H19>=R$2), 2, "" ))) | S19: =IF(AND($F19<(S$2+7),$F19>S$2),1, IF(AND($H19<S$2+7,$H19>S$2),3, IF(AND($F19<=S$2, $H19>=S$2), 2, "" ))) | ... AQ19: =IF(AND($F19<(AQ$2+7),$F19>AQ$2),1, IF(AND($H19<AQ$2+7,$H19>AQ$2),3, IF(AND($F19<=AQ$2, $H19>=AQ$2), 2, "" )))
B20: BOS Delivery | C20: 43983 | D20: 1 | E20: 43984 | F20: 43983 | G20: 1 | H20: 43984 | L20: =IF(AND($F20<(L$2+7),$F20>L$2),1, IF(AND($H20<L$2+7,$H20>L$2),3, IF(AND($F20<=L$2, $H20>=L$2), 2, "" ))) | M20: =IF(AND($F20<(M$2+7),$F20>M$2),1, IF(AND($H20<M$2+7,$H20>M$2),3, IF(AND($F20<=M$2, $H20>=M$2), 2, "" ))) | N20: =IF(AND($F20<(N$2+7),$F20>N$2),1, IF(AND($H20<N$2+7,$H20>N$2),3, IF(AND($F20<=N$2, $H20>=N$2), 2, "" ))) | O20: =IF(AND($F20<(O$2+7),$F20>O$2),1, IF(AND($H20<O$2+7,$H20>O$2),3, IF(AND($F20<=O$2, $H20>=O$2), 2, "" ))) | P20: =IF(AND($F20<(P$2+7),$F20>P$2),1, IF(AND($H20<P$2+7,$H20>P$2),3, IF(AND($F20<=P$2, $H20>=P$2), 2, "" ))) | Q20: =IF(AND($F20<(Q$2+7),$F20>Q$2),1, IF(AND($H20<Q$2+7,$H20>Q$2),3, IF(AND($F20<=Q$2, $H20>=Q$2), 2, "" ))) | R20: =IF(AND($F20<(R$2+7),$F20>R$2),1, IF(AND($H20<R$2+7,$H20>R$2),3, IF(AND($F20<=R$2, $H20>=R$2), 2, "" ))) | S20: =IF(AND($F20<(S$2+7),$F20>S$2),1, IF(AND($H20<S$2+7,$H20>S$2),3, IF(AND($F20<=S$2, $H20>=S$2), 2, "" ))) | ... AQ20: =IF(AND($F20<(AQ$2+7),$F20>AQ$2),1, IF(AND($H20<AQ$2+7,$H20>AQ$2),3, IF(AND($F20<=AQ$2, $H20>=AQ$2), 2, "" )))
A21: C | B21: PAYMENT MILESTONE 3: DELIVERY OF INVERTERS AND BOS | C21: 43985 | D21: 2 | E21: 43987 | F21: 43985 | G21: 2 | H21: 43987
A22: 8 | B22: Installation | C22: 43990 | D22: 22 | E22: 44012 | F22: 43990 | G22: 22 | H22: 44012 | L22: =IF(AND($F22<(L$2+7),$F22>L$2),1, IF(AND($H22<L$2+7,$H22>L$2),3, IF(AND($F22<=L$2, $H22>=L$2), 2, "" ))) | M22: =IF(AND($F22<(M$2+7),$F22>M$2),1, IF(AND($H22<M$2+7,$H22>M$2),3, IF(AND($F22<=M$2, $H22>=M$2), 2, "" ))) | N22: =IF(AND($F22<(N$2+7),$F22>N$2),1, IF(AND($H22<N$2+7,$H22>N$2),3, IF(AND($F22<=N$2, $H22>=N$2), 2, "" ))) | O22: =IF(AND($F22<(O$2+7),$F22>O$2),1, IF(AND($H22<O$2+7,$H22>O$2),3, IF(AND($F22<=O$2, $H22>=O$2), 2, "" ))) | P22: =IF(AND($F22<(P$2+7),$F22>P$2),1, IF(AND($H22<P$2+7,$H22>P$2),3, IF(AND($F22<=P$2, $H22>=P$2), 2, "" ))) | Q22: =IF(AND($F22<(Q$2+7),$F22>Q$2),1, IF(AND($H22<Q$2+7,$H22>Q$2),3, IF(AND($F22<=Q$2, $H22>=Q$2), 2, "" ))) | R22: =IF(AND($F22<(R$2+7),$F22>R$2),1, IF(AND($H22<R$2+7,$H22>R$2),3, IF(AND($F22<=R$2, $H22>=R$2), 2, "" ))) | S22: =IF(AND($F22<(S$2+7),$F22>S$2),1, IF(AND($H22<S$2+7,$H22>S$2),3, IF(AND($F22<=S$2, $H22>=S$2), 2, "" ))) | ... AQ22: =IF(AND($F22<(AQ$2+7),$F22>AQ$2),1, IF(AND($H22<AQ$2+7,$H22>AQ$2),3, IF(AND($F22<=AQ$2, $H22>=AQ$2), 2, "" ))) -> 2
B23: Site Establishment | C23: 43990 | D23: 1 | E23: 43991 | F23: 43990 | G23: 1 | H23: 43991 | J23: Installation placed on hold due to Covid-19 case | L23: =IF(AND($F23<(L$2+7),$F23>L$2),1, IF(AND($H23<L$2+7,$H23>L$2),3, IF(AND($F23<=L$2, $H23>=L$2), 2, "" ))) | M23: =IF(AND($F23<(M$2+7),$F23>M$2),1, IF(AND($H23<M$2+7,$H23>M$2),3, IF(AND($F23<=M$2, $H23>=M$2), 2, "" ))) | N23: =IF(AND($F23<(N$2+7),$F23>N$2),1, IF(AND($H23<N$2+7,$H23>N$2),3, IF(AND($F23<=N$2, $H23>=N$2), 2, "" ))) | O23: =IF(AND($F23<(O$2+7),$F23>O$2),1, IF(AND($H23<O$2+7,$H23>O$2),3, IF(AND($F23<=O$2, $H23>=O$2), 2, "" ))) | P23: =IF(AND($F23<(P$2+7),$F23>P$2),1, IF(AND($H23<P$2+7,$H23>P$2),3, IF(AND($F23<=P$2, $H23>=P$2), 2, "" ))) | Q23: =IF(AND($F23<(Q$2+7),$F23>Q$2),1, IF(AND($H23<Q$2+7,$H23>Q$2),3, IF(AND($F23<=Q$2, $H23>=Q$2), 2, "" ))) | R23: =IF(AND($F23<(R$2+7),$F23>R$2),1, IF(AND($H23<R$2+7,$H23>R$2),3, IF(AND($F23<=R$2, $H23>=R$2), 2, "" ))) | S23: =IF(AND($F23<(S$2+7),$F23>S$2),1, IF(AND($H23<S$2+7,$H23>S$2),3, IF(AND($F23<=S$2, $H23>=S$2), 2, "" ))) | ... AQ23: =IF(AND($F23<(AQ$2+7),$F23>AQ$2),1, IF(AND($H23<AQ$2+7,$H23>AQ$2),3, IF(AND($F23<=AQ$2, $H23>=AQ$2), 2, "" )))
A24: 9 | B24: DC Works | C24: 43991 | D24: 16 | E24: 44012 | F24: 43991 | G24: 16 | H24: 44012 | L24: =IF(AND($F24<(L$2+7),$F24>L$2),1, IF(AND($H24<L$2+7,$H24>L$2),3, IF(AND($F24<=L$2, $H24>=L$2), 2, "" ))) | M24: =IF(AND($F24<(M$2+7),$F24>M$2),1, IF(AND($H24<M$2+7,$H24>M$2),3, IF(AND($F24<=M$2, $H24>=M$2), 2, "" ))) | N24: =IF(AND($F24<(N$2+7),$F24>N$2),1, IF(AND($H24<N$2+7,$H24>N$2),3, IF(AND($F24<=N$2, $H24>=N$2), 2, "" ))) | O24: =IF(AND($F24<(O$2+7),$F24>O$2),1, IF(AND($H24<O$2+7,$H24>O$2),3, IF(AND($F24<=O$2, $H24>=O$2), 2, "" ))) | P24: =IF(AND($F24<(P$2+7),$F24>P$2),1, IF(AND($H24<P$2+7,$H24>P$2),3, IF(AND($F24<=P$2, $H24>=P$2), 2, "" ))) | Q24: =IF(AND($F24<(Q$2+7),$F24>Q$2),1, IF(AND($H24<Q$2+7,$H24>Q$2),3, IF(AND($F24<=Q$2, $H24>=Q$2), 2, "" ))) | R24: =IF(AND($F24<(R$2+7),$F24>R$2),1, IF(AND($H24<R$2+7,$H24>R$2),3, IF(AND($F24<=R$2, $H24>=R$2), 2, "" ))) | S24: =IF(AND($F24<(S$2+7),$F24>S$2),1, IF(AND($H24<S$2+7,$H24>S$2),3, IF(AND($F24<=S$2, $H24>=S$2), 2, "" ))) | ... AQ24: =IF(AND($F24<(AQ$2+7),$F24>AQ$2),1, IF(AND($H24<AQ$2+7,$H24>AQ$2),3, IF(AND($F24<=AQ$2, $H24>=AQ$2), 2, "" ))) -> 2
B25: Mounting structure Installation | C25: 43991 | D25: 4 | E25: 43997 | F25: 43991 | G25: 4 | H25: 43997 | L25: =IF(AND($F25<(L$2+7),$F25>L$2),1, IF(AND($H25<L$2+7,$H25>L$2),3, IF(AND($F25<=L$2, $H25>=L$2), 2, "" ))) | M25: =IF(AND($F25<(M$2+7),$F25>M$2),1, IF(AND($H25<M$2+7,$H25>M$2),3, IF(AND($F25<=M$2, $H25>=M$2), 2, "" ))) | N25: =IF(AND($F25<(N$2+7),$F25>N$2),1, IF(AND($H25<N$2+7,$H25>N$2),3, IF(AND($F25<=N$2, $H25>=N$2), 2, "" ))) | O25: =IF(AND($F25<(O$2+7),$F25>O$2),1, IF(AND($H25<O$2+7,$H25>O$2),3, IF(AND($F25<=O$2, $H25>=O$2), 2, "" ))) | P25: =IF(AND($F25<(P$2+7),$F25>P$2),1, IF(AND($H25<P$2+7,$H25>P$2),3, IF(AND($F25<=P$2, $H25>=P$2), 2, "" ))) | Q25: =IF(AND($F25<(Q$2+7),$F25>Q$2),1, IF(AND($H25<Q$2+7,$H25>Q$2),3, IF(AND($F25<=Q$2, $H25>=Q$2), 2, "" ))) | R25: =IF(AND($F25<(R$2+7),$F25>R$2),1, IF(AND($H25<R$2+7,$H25>R$2),3, IF(AND($F25<=R$2, $H25>=R$2), 2, "" ))) | S25: =IF(AND($F25<(S$2+7),$F25>S$2),1, IF(AND($H25<S$2+7,$H25>S$2),3, IF(AND($F25<=S$2, $H25>=S$2), 2, "" ))) | ... AQ25: =IF(AND($F25<(AQ$2+7),$F25>AQ$2),1, IF(AND($H25<AQ$2+7,$H25>AQ$2),3, IF(AND($F25<=AQ$2, $H25>=AQ$2), 2, "" )))
B26: Cable tray Installation | C26: 43997 | D26: 3 | E26: 44004 | F26: 43997 | G26: 3 | H26: 44004 | L26: =IF(AND($F26<(L$2+7),$F26>L$2),1, IF(AND($H26<L$2+7,$H26>L$2),3, IF(AND($F26<=L$2, $H26>=L$2), 2, "" ))) | M26: =IF(AND($F26<(M$2+7),$F26>M$2),1, IF(AND($H26<M$2+7,$H26>M$2),3, IF(AND($F26<=M$2, $H26>=M$2), 2, "" ))) | N26: =IF(AND($F26<(N$2+7),$F26>N$2),1, IF(AND($H26<N$2+7,$H26>N$2),3, IF(AND($F26<=N$2, $H26>=N$2), 2, "" ))) | O26: =IF(AND($F26<(O$2+7),$F26>O$2),1, IF(AND($H26<O$2+7,$H26>O$2),3, IF(AND($F26<=O$2, $H26>=O$2), 2, "" ))) | P26: =IF(AND($F26<(P$2+7),$F26>P$2),1, IF(AND($H26<P$2+7,$H26>P$2),3, IF(AND($F26<=P$2, $H26>=P$2), 2, "" ))) | Q26: =IF(AND($F26<(Q$2+7),$F26>Q$2),1, IF(AND($H26<Q$2+7,$H26>Q$2),3, IF(AND($F26<=Q$2, $H26>=Q$2), 2, "" ))) | R26: =IF(AND($F26<(R$2+7),$F26>R$2),1, IF(AND($H26<R$2+7,$H26>R$2),3, IF(AND($F26<=R$2, $H26>=R$2), 2, "" ))) | S26: =IF(AND($F26<(S$2+7),$F26>S$2),1, IF(AND($H26<S$2+7,$H26>S$2),3, IF(AND($F26<=S$2, $H26>=S$2), 2, "" ))) | ... AQ26: =IF(AND($F26<(AQ$2+7),$F26>AQ$2),1, IF(AND($H26<AQ$2+7,$H26>AQ$2),3, IF(AND($F26<=AQ$2, $H26>=AQ$2), 2, "" )))
B27: DC Cable Installation | C27: 44004 | D27: 2 | E27: 44006 | F27: 44004 | G27: 2 | H27: 44006 | L27: =IF(AND($F27<(L$2+7),$F27>L$2),1, IF(AND($H27<L$2+7,$H27>L$2),3, IF(AND($F27<=L$2, $H27>=L$2), 2, "" ))) | M27: =IF(AND($F27<(M$2+7),$F27>M$2),1, IF(AND($H27<M$2+7,$H27>M$2),3, IF(AND($F27<=M$2, $H27>=M$2), 2, "" ))) | N27: =IF(AND($F27<(N$2+7),$F27>N$2),1, IF(AND($H27<N$2+7,$H27>N$2),3, IF(AND($F27<=N$2, $H27>=N$2), 2, "" ))) | O27: =IF(AND($F27<(O$2+7),$F27>O$2),1, IF(AND($H27<O$2+7,$H27>O$2),3, IF(AND($F27<=O$2, $H27>=O$2), 2, "" ))) | P27: =IF(AND($F27<(P$2+7),$F27>P$2),1, IF(AND($H27<P$2+7,$H27>P$2),3, IF(AND($F27<=P$2, $H27>=P$2), 2, "" ))) | Q27: =IF(AND($F27<(Q$2+7),$F27>Q$2),1, IF(AND($H27<Q$2+7,$H27>Q$2),3, IF(AND($F27<=Q$2, $H27>=Q$2), 2, "" ))) | R27: =IF(AND($F27<(R$2+7),$F27>R$2),1, IF(AND($H27<R$2+7,$H27>R$2),3, IF(AND($F27<=R$2, $H27>=R$2), 2, "" ))) | S27: =IF(AND($F27<(S$2+7),$F27>S$2),1, IF(AND($H27<S$2+7,$H27>S$2),3, IF(AND($F27<=S$2, $H27>=S$2), 2, "" ))) | ... AQ27: =IF(AND($F27<(AQ$2+7),$F27>AQ$2),1, IF(AND($H27<AQ$2+7,$H27>AQ$2),3, IF(AND($F27<=AQ$2, $H27>=AQ$2), 2, "" )))
B28: Module Installation | C28: 44006 | D28: 4 | E28: 44012 | F28: 44006 | G28: 4 | H28: 44012 | L28: =IF(AND($F28<(L$2+7),$F28>L$2),1, IF(AND($H28<L$2+7,$H28>L$2),3, IF(AND($F28<=L$2, $H28>=L$2), 2, "" ))) | M28: =IF(AND($F28<(M$2+7),$F28>M$2),1, IF(AND($H28<M$2+7,$H28>M$2),3, IF(AND($F28<=M$2, $H28>=M$2), 2, "" ))) | N28: =IF(AND($F28<(N$2+7),$F28>N$2),1, IF(AND($H28<N$2+7,$H28>N$2),3, IF(AND($F28<=N$2, $H28>=N$2), 2, "" ))) | O28: =IF(AND($F28<(O$2+7),$F28>O$2),1, IF(AND($H28<O$2+7,$H28>O$2),3, IF(AND($F28<=O$2, $H28>=O$2), 2, "" ))) | P28: =IF(AND($F28<(P$2+7),$F28>P$2),1, IF(AND($H28<P$2+7,$H28>P$2),3, IF(AND($F28<=P$2, $H28>=P$2), 2, "" ))) | Q28: =IF(AND($F28<(Q$2+7),$F28>Q$2),1, IF(AND($H28<Q$2+7,$H28>Q$2),3, IF(AND($F28<=Q$2, $H28>=Q$2), 2, "" ))) | R28: =IF(AND($F28<(R$2+7),$F28>R$2),1, IF(AND($H28<R$2+7,$H28>R$2),3, IF(AND($F28<=R$2, $H28>=R$2), 2, "" ))) | S28: =IF(AND($F28<(S$2+7),$F28>S$2),1, IF(AND($H28<S$2+7,$H28>S$2),3, IF(AND($F28<=S$2, $H28>=S$2), 2, "" ))) | ... AQ28: =IF(AND($F28<(AQ$2+7),$F28>AQ$2),1, IF(AND($H28<AQ$2+7,$H28>AQ$2),3, IF(AND($F28<=AQ$2, $H28>=AQ$2), 2, "" ))) -> 2
B29: Earth Cable Installation | C29: 44004 | D29: 1 | E29: 44005 | F29: 44004 | G29: 1 | H29: 44005 | L29: =IF(AND($F29<(L$2+7),$F29>L$2),1, IF(AND($H29<L$2+7,$H29>L$2),3, IF(AND($F29<=L$2, $H29>=L$2), 2, "" ))) | M29: =IF(AND($F29<(M$2+7),$F29>M$2),1, IF(AND($H29<M$2+7,$H29>M$2),3, IF(AND($F29<=M$2, $H29>=M$2), 2, "" ))) | N29: =IF(AND($F29<(N$2+7),$F29>N$2),1, IF(AND($H29<N$2+7,$H29>N$2),3, IF(AND($F29<=N$2, $H29>=N$2), 2, "" ))) | O29: =IF(AND($F29<(O$2+7),$F29>O$2),1, IF(AND($H29<O$2+7,$H29>O$2),3, IF(AND($F29<=O$2, $H29>=O$2), 2, "" ))) | P29: =IF(AND($F29<(P$2+7),$F29>P$2),1, IF(AND($H29<P$2+7,$H29>P$2),3, IF(AND($F29<=P$2, $H29>=P$2), 2, "" ))) | Q29: =IF(AND($F29<(Q$2+7),$F29>Q$2),1, IF(AND($H29<Q$2+7,$H29>Q$2),3, IF(AND($F29<=Q$2, $H29>=Q$2), 2, "" ))) | R29: =IF(AND($F29<(R$2+7),$F29>R$2),1, IF(AND($H29<R$2+7,$H29>R$2),3, IF(AND($F29<=R$2, $H29>=R$2), 2, "" ))) | S29: =IF(AND($F29<(S$2+7),$F29>S$2),1, IF(AND($H29<S$2+7,$H29>S$2),3, IF(AND($F29<=S$2, $H29>=S$2), 2, "" ))) | ... AQ29: =IF(AND($F29<(AQ$2+7),$F29>AQ$2),1, IF(AND($H29<AQ$2+7,$H29>AQ$2),3, IF(AND($F29<=AQ$2, $H29>=AQ$2), 2, "" )))
A30: 10 | B30: AC Works | C30: 43991 | D30: 8 | E30: 44000 | F30: 43991 | G30: 8 | H30: 44000
B31: Inverters Installation | C31: 43991 | D31: 2 | E31: 43993 | F31: 43991 | G31: 2 | H31: 43993 | L31: =IF(AND($F31<(L$2+7),$F31>L$2),1, IF(AND($H31<L$2+7,$H31>L$2),3, IF(AND($F31<=L$2, $H31>=L$2), 2, "" ))) | M31: =IF(AND($F31<(M$2+7),$F31>M$2),1, IF(AND($H31<M$2+7,$H31>M$2),3, IF(AND($F31<=M$2, $H31>=M$2), 2, "" ))) | N31: =IF(AND($F31<(N$2+7),$F31>N$2),1, IF(AND($H31<N$2+7,$H31>N$2),3, IF(AND($F31<=N$2, $H31>=N$2), 2, "" ))) | O31: =IF(AND($F31<(O$2+7),$F31>O$2),1, IF(AND($H31<O$2+7,$H31>O$2),3, IF(AND($F31<=O$2, $H31>=O$2), 2, "" ))) | P31: =IF(AND($F31<(P$2+7),$F31>P$2),1, IF(AND($H31<P$2+7,$H31>P$2),3, IF(AND($F31<=P$2, $H31>=P$2), 2, "" ))) | Q31: =IF(AND($F31<(Q$2+7),$F31>Q$2),1, IF(AND($H31<Q$2+7,$H31>Q$2),3, IF(AND($F31<=Q$2, $H31>=Q$2), 2, "" ))) | R31: =IF(AND($F31<(R$2+7),$F31>R$2),1, IF(AND($H31<R$2+7,$H31>R$2),3, IF(AND($F31<=R$2, $H31>=R$2), 2, "" ))) | S31: =IF(AND($F31<(S$2+7),$F31>S$2),1, IF(AND($H31<S$2+7,$H31>S$2),3, IF(AND($F31<=S$2, $H31>=S$2), 2, "" ))) | ... AQ31: =IF(AND($F31<(AQ$2+7),$F31>AQ$2),1, IF(AND($H31<AQ$2+7,$H31>AQ$2),3, IF(AND($F31<=AQ$2, $H31>=AQ$2), 2, "" )))
B32: AC BOS Installation | C32: 43993 | D32: 3 | E32: 44000 | F32: 43993 | G32: 3 | H32: 44000 | L32: =IF(AND($F32<(L$2+7),$F32>L$2),1, IF(AND($H32<L$2+7,$H32>L$2),3, IF(AND($F32<=L$2, $H32>=L$2), 2, "" ))) | M32: =IF(AND($F32<(M$2+7),$F32>M$2),1, IF(AND($H32<M$2+7,$H32>M$2),3, IF(AND($F32<=M$2, $H32>=M$2), 2, "" ))) | N32: =IF(AND($F32<(N$2+7),$F32>N$2),1, IF(AND($H32<N$2+7,$H32>N$2),3, IF(AND($F32<=N$2, $H32>=N$2), 2, "" ))) | O32: =IF(AND($F32<(O$2+7),$F32>O$2),1, IF(AND($H32<O$2+7,$H32>O$2),3, IF(AND($F32<=O$2, $H32>=O$2), 2, "" ))) | P32: =IF(AND($F32<(P$2+7),$F32>P$2),1, IF(AND($H32<P$2+7,$H32>P$2),3, IF(AND($F32<=P$2, $H32>=P$2), 2, "" ))) | Q32: =IF(AND($F32<(Q$2+7),$F32>Q$2),1, IF(AND($H32<Q$2+7,$H32>Q$2),3, IF(AND($F32<=Q$2, $H32>=Q$2), 2, "" ))) | R32: =IF(AND($F32<(R$2+7),$F32>R$2),1, IF(AND($H32<R$2+7,$H32>R$2),3, IF(AND($F32<=R$2, $H32>=R$2), 2, "" ))) | S32: =IF(AND($F32<(S$2+7),$F32>S$2),1, IF(AND($H32<S$2+7,$H32>S$2),3, IF(AND($F32<=S$2, $H32>=S$2), 2, "" ))) | ... AQ32: =IF(AND($F32<(AQ$2+7),$F32>AQ$2),1, IF(AND($H32<AQ$2+7,$H32>AQ$2),3, IF(AND($F32<=AQ$2, $H32>=AQ$2), 2, "" )))
B33: AC Cable/Tie-In | C33: 43992 | D33: 3 | E33: 43997 | F33: 43992 | G33: 3 | H33: 43997 | L33: =IF(AND($F33<(L$2+7),$F33>L$2),1, IF(AND($H33<L$2+7,$H33>L$2),3, IF(AND($F33<=L$2, $H33>=L$2), 2, "" ))) | M33: =IF(AND($F33<(M$2+7),$F33>M$2),1, IF(AND($H33<M$2+7,$H33>M$2),3, IF(AND($F33<=M$2, $H33>=M$2), 2, "" ))) | N33: =IF(AND($F33<(N$2+7),$F33>N$2),1, IF(AND($H33<N$2+7,$H33>N$2),3, IF(AND($F33<=N$2, $H33>=N$2), 2, "" ))) | O33: =IF(AND($F33<(O$2+7),$F33>O$2),1, IF(AND($H33<O$2+7,$H33>O$2),3, IF(AND($F33<=O$2, $H33>=O$2), 2, "" ))) | P33: =IF(AND($F33<(P$2+7),$F33>P$2),1, IF(AND($H33<P$2+7,$H33>P$2),3, IF(AND($F33<=P$2, $H33>=P$2), 2, "" ))) | Q33: =IF(AND($F33<(Q$2+7),$F33>Q$2),1, IF(AND($H33<Q$2+7,$H33>Q$2),3, IF(AND($F33<=Q$2, $H33>=Q$2), 2, "" ))) | R33: =IF(AND($F33<(R$2+7),$F33>R$2),1, IF(AND($H33<R$2+7,$H33>R$2),3, IF(AND($F33<=R$2, $H33>=R$2), 2, "" ))) | S33: =IF(AND($F33<(S$2+7),$F33>S$2),1, IF(AND($H33<S$2+7,$H33>S$2),3, IF(AND($F33<=S$2, $H33>=S$2), 2, "" ))) | ... AQ33: =IF(AND($F33<(AQ$2+7),$F33>AQ$2),1, IF(AND($H33<AQ$2+7,$H33>AQ$2),3, IF(AND($F33<=AQ$2, $H33>=AQ$2), 2, "" )))
B34: Monitoring Platform Installation | C34: 43997 | D34: 1 | E34: 44000 | F34: 43997 | G34: 1 | H34: 44000
A35: 11 | B35: Completion | C35: 44000 | D35: 14 | E35: 44014 | F35: 44000 | G35: 14 | H35: 44014 | L35: =IF(AND($F35<(L$2+7),$F35>L$2),1, IF(AND($H35<L$2+7,$H35>L$2),3, IF(AND($F35<=L$2, $H35>=L$2), 2, "" ))) | M35: =IF(AND($F35<(M$2+7),$F35>M$2),1, IF(AND($H35<M$2+7,$H35>M$2),3, IF(AND($F35<=M$2, $H35>=M$2), 2, "" ))) | N35: =IF(AND($F35<(N$2+7),$F35>N$2),1, IF(AND($H35<N$2+7,$H35>N$2),3, IF(AND($F35<=N$2, $H35>=N$2), 2, "" ))) | O35: =IF(AND($F35<(O$2+7),$F35>O$2),1, IF(AND($H35<O$2+7,$H35>O$2),3, IF(AND($F35<=O$2, $H35>=O$2), 2, "" ))) | P35: =IF(AND($F35<(P$2+7),$F35>P$2),1, IF(AND($H35<P$2+7,$H35>P$2),3, IF(AND($F35<=P$2, $H35>=P$2), 2, "" ))) | Q35: =IF(AND($F35<(Q$2+7),$F35>Q$2),1, IF(AND($H35<Q$2+7,$H35>Q$2),3, IF(AND($F35<=Q$2, $H35>=Q$2), 2, "" ))) | R35: =IF(AND($F35<(R$2+7),$F35>R$2),1, IF(AND($H35<R$2+7,$H35>R$2),3, IF(AND($F35<=R$2, $H35>=R$2), 2, "" ))) | S35: =IF(AND($F35<(S$2+7),$F35>S$2),1, IF(AND($H35<S$2+7,$H35>S$2),3, IF(AND($F35<=S$2, $H35>=S$2), 2, "" ))) | ... AQ35: =IF(AND($F35<(AQ$2+7),$F35>AQ$2),1, IF(AND($H35<AQ$2+7,$H35>AQ$2),3, IF(AND($F35<=AQ$2, $H35>=AQ$2), 2, "" ))) -> 3
B36: DC Works | C36: 44012 | D36: 2 | E36: 44014 | F36: 44012 | G36: 2 | H36: 44014 | L36: =IF(AND($F36<(L$2+7),$F36>L$2),1, IF(AND($H36<L$2+7,$H36>L$2),3, IF(AND($F36<=L$2, $H36>=L$2), 2, "" ))) | M36: =IF(AND($F36<(M$2+7),$F36>M$2),1, IF(AND($H36<M$2+7,$H36>M$2),3, IF(AND($F36<=M$2, $H36>=M$2), 2, "" ))) | N36: =IF(AND($F36<(N$2+7),$F36>N$2),1, IF(AND($H36<N$2+7,$H36>N$2),3, IF(AND($F36<=N$2, $H36>=N$2), 2, "" ))) | O36: =IF(AND($F36<(O$2+7),$F36>O$2),1, IF(AND($H36<O$2+7,$H36>O$2),3, IF(AND($F36<=O$2, $H36>=O$2), 2, "" ))) | P36: =IF(AND($F36<(P$2+7),$F36>P$2),1, IF(AND($H36<P$2+7,$H36>P$2),3, IF(AND($F36<=P$2, $H36>=P$2), 2, "" ))) | Q36: =IF(AND($F36<(Q$2+7),$F36>Q$2),1, IF(AND($H36<Q$2+7,$H36>Q$2),3, IF(AND($F36<=Q$2, $H36>=Q$2), 2, "" ))) | R36: =IF(AND($F36<(R$2+7),$F36>R$2),1, IF(AND($H36<R$2+7,$H36>R$2),3, IF(AND($F36<=R$2, $H36>=R$2), 2, "" ))) | S36: =IF(AND($F36<(S$2+7),$F36>S$2),1, IF(AND($H36<S$2+7,$H36>S$2),3, IF(AND($F36<=S$2, $H36>=S$2), 2, "" ))) | ... AQ36: =IF(AND($F36<(AQ$2+7),$F36>AQ$2),1, IF(AND($H36<AQ$2+7,$H36>AQ$2),3, IF(AND($F36<=AQ$2, $H36>=AQ$2), 2, "" ))) -> 3
B37: AC Works | C37: 44000 | D37: 2 | E37: 44004 | F37: 44000 | G37: 2 | H37: 44004 | L37: =IF(AND($F37<(L$2+7),$F37>L$2),1, IF(AND($H37<L$2+7,$H37>L$2),3, IF(AND($F37<=L$2, $H37>=L$2), 2, "" ))) | M37: =IF(AND($F37<(M$2+7),$F37>M$2),1, IF(AND($H37<M$2+7,$H37>M$2),3, IF(AND($F37<=M$2, $H37>=M$2), 2, "" ))) | N37: =IF(AND($F37<(N$2+7),$F37>N$2),1, IF(AND($H37<N$2+7,$H37>N$2),3, IF(AND($F37<=N$2, $H37>=N$2), 2, "" ))) | O37: =IF(AND($F37<(O$2+7),$F37>O$2),1, IF(AND($H37<O$2+7,$H37>O$2),3, IF(AND($F37<=O$2, $H37>=O$2), 2, "" ))) | P37: =IF(AND($F37<(P$2+7),$F37>P$2),1, IF(AND($H37<P$2+7,$H37>P$2),3, IF(AND($F37<=P$2, $H37>=P$2), 2, "" ))) | Q37: =IF(AND($F37<(Q$2+7),$F37>Q$2),1, IF(AND($H37<Q$2+7,$H37>Q$2),3, IF(AND($F37<=Q$2, $H37>=Q$2), 2, "" ))) | R37: =IF(AND($F37<(R$2+7),$F37>R$2),1, IF(AND($H37<R$2+7,$H37>R$2),3, IF(AND($F37<=R$2, $H37>=R$2), 2, "" ))) | S37: =IF(AND($F37<(S$2+7),$F37>S$2),1, IF(AND($H37<S$2+7,$H37>S$2),3, IF(AND($F37<=S$2, $H37>=S$2), 2, "" ))) | ... AQ37: =IF(AND($F37<(AQ$2+7),$F37>AQ$2),1, IF(AND($H37<AQ$2+7,$H37>AQ$2),3, IF(AND($F37<=AQ$2, $H37>=AQ$2), 2, "" )))
A38: D | B38: PAYMENT MILESTONE 4: PRACTICAL COMPLETION | C38: 44012 | D38: 1 | E38: 44013 | F38: 44012 | G38: 1 | H38: 44013 | L38: =IF(AND($F38<(L$2+7),$F38>L$2),1, IF(AND($H38<L$2+7,$H38>L$2),3, IF(AND($F38<=L$2, $H38>=L$2), 2, "" ))) | M38: =IF(AND($F38<(M$2+7),$F38>M$2),1, IF(AND($H38<M$2+7,$H38>M$2),3, IF(AND($F38<=M$2, $H38>=M$2), 2, "" ))) | N38: =IF(AND($F38<(N$2+7),$F38>N$2),1, IF(AND($H38<N$2+7,$H38>N$2),3, IF(AND($F38<=N$2, $H38>=N$2), 2, "" ))) | O38: =IF(AND($F38<(O$2+7),$F38>O$2),1, IF(AND($H38<O$2+7,$H38>O$2),3, IF(AND($F38<=O$2, $H38>=O$2), 2, "" ))) | P38: =IF(AND($F38<(P$2+7),$F38>P$2),1, IF(AND($H38<P$2+7,$H38>P$2),3, IF(AND($F38<=P$2, $H38>=P$2), 2, "" ))) | Q38: =IF(AND($F38<(Q$2+7),$F38>Q$2),1, IF(AND($H38<Q$2+7,$H38>Q$2),3, IF(AND($F38<=Q$2, $H38>=Q$2), 2, "" ))) | R38: =IF(AND($F38<(R$2+7),$F38>R$2),1, IF(AND($H38<R$2+7,$H38>R$2),3, IF(AND($F38<=R$2, $H38>=R$2), 2, "" ))) | S38: =IF(AND($F38<(S$2+7),$F38>S$2),1, IF(AND($H38<S$2+7,$H38>S$2),3, IF(AND($F38<=S$2, $H38>=S$2), 2, "" ))) | ... AQ38: =IF(AND($F38<(AQ$2+7),$F38>AQ$2),1, IF(AND($H38<AQ$2+7,$H38>AQ$2),3, IF(AND($F38<=AQ$2, $H38>=AQ$2), 2, "" ))) -> 3
A39: 12 | B39: Commissioning | C39: 43997 | D39: 22 | E39: 44019 | F39: 43997 | G39: 22 | H39: 44019 | L39: =IF(AND($F39<(L$2+7),$F39>L$2),1, IF(AND($H39<L$2+7,$H39>L$2),3, IF(AND($F39<=L$2, $H39>=L$2), 2, "" ))) | M39: =IF(AND($F39<(M$2+7),$F39>M$2),1, IF(AND($H39<M$2+7,$H39>M$2),3, IF(AND($F39<=M$2, $H39>=M$2), 2, "" ))) | N39: =IF(AND($F39<(N$2+7),$F39>N$2),1, IF(AND($H39<N$2+7,$H39>N$2),3, IF(AND($F39<=N$2, $H39>=N$2), 2, "" ))) | O39: =IF(AND($F39<(O$2+7),$F39>O$2),1, IF(AND($H39<O$2+7,$H39>O$2),3, IF(AND($F39<=O$2, $H39>=O$2), 2, "" ))) | P39: =IF(AND($F39<(P$2+7),$F39>P$2),1, IF(AND($H39<P$2+7,$H39>P$2),3, IF(AND($F39<=P$2, $H39>=P$2), 2, "" ))) | Q39: =IF(AND($F39<(Q$2+7),$F39>Q$2),1, IF(AND($H39<Q$2+7,$H39>Q$2),3, IF(AND($F39<=Q$2, $H39>=Q$2), 2, "" ))) | R39: =IF(AND($F39<(R$2+7),$F39>R$2),1, IF(AND($H39<R$2+7,$H39>R$2),3, IF(AND($F39<=R$2, $H39>=R$2), 2, "" ))) | S39: =IF(AND($F39<(S$2+7),$F39>S$2),1, IF(AND($H39<S$2+7,$H39>S$2),3, IF(AND($F39<=S$2, $H39>=S$2), 2, "" ))) | ... AQ39: =IF(AND($F39<(AQ$2+7),$F39>AQ$2),1, IF(AND($H39<AQ$2+7,$H39>AQ$2),3, IF(AND($F39<=AQ$2, $H39>=AQ$2), 2, "" ))) -> 2
B40: Snag List | C40: 44014 | D40: 3 | E40: 44019 | F40: 44014 | G40: 3 | H40: 44019
B41: Pre-Commissioning Checks | C41: 44010 | D41: 2 | E41: 44012 | F41: 44010 | G41: 2 | H41: 44012
B42: Issue CoC | C42: 43997 | D42: 2 | E42: 44001 | F42: 43997 | G42: 2 | H42: 44001 | L42: =IF(AND($F42<(L$2+7),$F42>L$2),1, IF(AND($H42<L$2+7,$H42>L$2),3, IF(AND($F42<=L$2, $H42>=L$2), 2, "" ))) | M42: =IF(AND($F42<(M$2+7),$F42>M$2),1, IF(AND($H42<M$2+7,$H42>M$2),3, IF(AND($F42<=M$2, $H42>=M$2), 2, "" ))) | N42: =IF(AND($F42<(N$2+7),$F42>N$2),1, IF(AND($H42<N$2+7,$H42>N$2),3, IF(AND($F42<=N$2, $H42>=N$2), 2, "" ))) | O42: =IF(AND($F42<(O$2+7),$F42>O$2),1, IF(AND($H42<O$2+7,$H42>O$2),3, IF(AND($F42<=O$2, $H42>=O$2), 2, "" ))) | P42: =IF(AND($F42<(P$2+7),$F42>P$2),1, IF(AND($H42<P$2+7,$H42>P$2),3, IF(AND($F42<=P$2, $H42>=P$2), 2, "" ))) | Q42: =IF(AND($F42<(Q$2+7),$F42>Q$2),1, IF(AND($H42<Q$2+7,$H42>Q$2),3, IF(AND($F42<=Q$2, $H42>=Q$2), 2, "" ))) | R42: =IF(AND($F42<(R$2+7),$F42>R$2),1, IF(AND($H42<R$2+7,$H42>R$2),3, IF(AND($F42<=R$2, $H42>=R$2), 2, "" ))) | S42: =IF(AND($F42<(S$2+7),$F42>S$2),1, IF(AND($H42<S$2+7,$H42>S$2),3, IF(AND($F42<=S$2, $H42>=S$2), 2, "" ))) | ... AQ42: =IF(AND($F42<(AQ$2+7),$F42>AQ$2),1, IF(AND($H42<AQ$2+7,$H42>AQ$2),3, IF(AND($F42<=AQ$2, $H42>=AQ$2), 2, "" )))
B43: Cold Commissioning | C43: 44012 | D43: 1 | E43: 44013 | F43: 44012 | G43: 1 | H43: 44013 | L43: =IF(AND($F43<(L$2+7),$F43>L$2),1, IF(AND($H43<L$2+7,$H43>L$2),3, IF(AND($F43<=L$2, $H43>=L$2), 2, "" ))) | M43: =IF(AND($F43<(M$2+7),$F43>M$2),1, IF(AND($H43<M$2+7,$H43>M$2),3, IF(AND($F43<=M$2, $H43>=M$2), 2, "" ))) | N43: =IF(AND($F43<(N$2+7),$F43>N$2),1, IF(AND($H43<N$2+7,$H43>N$2),3, IF(AND($F43<=N$2, $H43>=N$2), 2, "" ))) | O43: =IF(AND($F43<(O$2+7),$F43>O$2),1, IF(AND($H43<O$2+7,$H43>O$2),3, IF(AND($F43<=O$2, $H43>=O$2), 2, "" ))) | P43: =IF(AND($F43<(P$2+7),$F43>P$2),1, IF(AND($H43<P$2+7,$H43>P$2),3, IF(AND($F43<=P$2, $H43>=P$2), 2, "" ))) | Q43: =IF(AND($F43<(Q$2+7),$F43>Q$2),1, IF(AND($H43<Q$2+7,$H43>Q$2),3, IF(AND($F43<=Q$2, $H43>=Q$2), 2, "" ))) | R43: =IF(AND($F43<(R$2+7),$F43>R$2),1, IF(AND($H43<R$2+7,$H43>R$2),3, IF(AND($F43<=R$2, $H43>=R$2), 2, "" ))) | S43: =IF(AND($F43<(S$2+7),$F43>S$2),1, IF(AND($H43<S$2+7,$H43>S$2),3, IF(AND($F43<=S$2, $H43>=S$2), 2, "" ))) | ... AQ43: =IF(AND($F43<(AQ$2+7),$F43>AQ$2),1, IF(AND($H43<AQ$2+7,$H43>AQ$2),3, IF(AND($F43<=AQ$2, $H43>=AQ$2), 2, "" ))) -> 3
B44: Hot Commissioning | C44: 44013 | D44: 2 | E44: 44015 | F44: 44013 | G44: 2 | H44: 44015 | L44: =IF(AND($F44<(L$2+7),$F44>L$2),1, IF(AND($H44<L$2+7,$H44>L$2),3, IF(AND($F44<=L$2, $H44>=L$2), 2, "" ))) | M44: =IF(AND($F44<(M$2+7),$F44>M$2),1, IF(AND($H44<M$2+7,$H44>M$2),3, IF(AND($F44<=M$2, $H44>=M$2), 2, "" ))) | N44: =IF(AND($F44<(N$2+7),$F44>N$2),1, IF(AND($H44<N$2+7,$H44>N$2),3, IF(AND($F44<=N$2, $H44>=N$2), 2, "" ))) | O44: =IF(AND($F44<(O$2+7),$F44>O$2),1, IF(AND($H44<O$2+7,$H44>O$2),3, IF(AND($F44<=O$2, $H44>=O$2), 2, "" ))) | P44: =IF(AND($F44<(P$2+7),$F44>P$2),1, IF(AND($H44<P$2+7,$H44>P$2),3, IF(AND($F44<=P$2, $H44>=P$2), 2, "" ))) | Q44: =IF(AND($F44<(Q$2+7),$F44>Q$2),1, IF(AND($H44<Q$2+7,$H44>Q$2),3, IF(AND($F44<=Q$2, $H44>=Q$2), 2, "" ))) | R44: =IF(AND($F44<(R$2+7),$F44>R$2),1, IF(AND($H44<R$2+7,$H44>R$2),3, IF(AND($F44<=R$2, $H44>=R$2), 2, "" ))) | S44: =IF(AND($F44<(S$2+7),$F44>S$2),1, IF(AND($H44<S$2+7,$H44>S$2),3, IF(AND($F44<=S$2, $H44>=S$2), 2, "" ))) | ... AQ44: =IF(AND($F44<(AQ$2+7),$F44>AQ$2),1, IF(AND($H44<AQ$2+7,$H44>AQ$2),3, IF(AND($F44<=AQ$2, $H44>=AQ$2), 2, "" ))) -> 1
A45: 13 | B45: Handover | C45: 44020 | D45: 1 | E45: 44021 | F45: 44020 | G45: 1 | H45: 44021 | L45: =IF(AND($F45<(L$2+7),$F45>L$2),1, IF(AND($H45<L$2+7,$H45>L$2),3, IF(AND($F45<=L$2, $H45>=L$2), 2, "" ))) | M45: =IF(AND($F45<(M$2+7),$F45>M$2),1, IF(AND($H45<M$2+7,$H45>M$2),3, IF(AND($F45<=M$2, $H45>=M$2), 2, "" ))) | N45: =IF(AND($F45<(N$2+7),$F45>N$2),1, IF(AND($H45<N$2+7,$H45>N$2),3, IF(AND($F45<=N$2, $H45>=N$2), 2, "" ))) | O45: =IF(AND($F45<(O$2+7),$F45>O$2),1, IF(AND($H45<O$2+7,$H45>O$2),3, IF(AND($F45<=O$2, $H45>=O$2), 2, "" ))) | P45: =IF(AND($F45<(P$2+7),$F45>P$2),1, IF(AND($H45<P$2+7,$H45>P$2),3, IF(AND($F45<=P$2, $H45>=P$2), 2, "" ))) | Q45: =IF(AND($F45<(Q$2+7),$F45>Q$2),1, IF(AND($H45<Q$2+7,$H45>Q$2),3, IF(AND($F45<=Q$2, $H45>=Q$2), 2, "" ))) | R45: =IF(AND($F45<(R$2+7),$F45>R$2),1, IF(AND($H45<R$2+7,$H45>R$2),3, IF(AND($F45<=R$2, $H45>=R$2), 2, "" ))) | S45: =IF(AND($F45<(S$2+7),$F45>S$2),1, IF(AND($H45<S$2+7,$H45>S$2),3, IF(AND($F45<=S$2, $H45>=S$2), 2, "" ))) | ... AQ45: =IF(AND($F45<(AQ$2+7),$F45>AQ$2),1, IF(AND($H45<AQ$2+7,$H45>AQ$2),3, IF(AND($F45<=AQ$2, $H45>=AQ$2), 2, "" )))
A46: E | B46: PAYMENT MILESTONE 6: HANDOVER COMPLETE | C46: 44022 | D46: 1 | E46: 44025 | F46: 44022 | G46: 1 | H46: 44025
C47: 43831 | D47: These numbers are used to set the start and end dates on the Gantt Chart
C48: 44014

Sheet Compliance
B2: HSE
B4: Description | C4: Status | D4: Approved By | E4: Date | F4: Results / Comments
B5: NOC
B6: 7.1 Agreement
B7: 13.2 Agreement
B8: EE File
B9: Subbie File
B16: SSEG
B18: Description | C18: Status | D18: Approved By | E18: Date | F18: Results / Comments
B19: SSEG Application
B20: PTI
B21: Commissioning Approval

Sheet Project Plan
N1: =TODAY() -> 46055 | O1: =TODAY() -> 46055
C2: PROJECT PLAN | E2: Cascades Lifestyle Center | N2: 0 | O2: 1
C3: PROJECT SIZE (kWp) | E3: 1510
C4: PROJECT DEVELOPER | E4: Dayne Sage
C5: PROJECT MANAGERS | E5: Lloyd Brown
C6: CONTRACT VALUE | E6: 9650000
C7: Phase: | E7: Hold
B8: No. | C8: HIGH LEVEL PROGRAMME | E8: Planned Start | F8: Duration (days) | G8: Planned End | I8: Actual Start | J8: Duration (days) | K8: Actual End | M8: Status | O8: Comment
F9: =G145-E114 -> 97 | J9: =K145-I114 -> 108 | M9: =AVERAGE(M11,M24,M40,M78,M86,M99) -> 0.89583333
B11: 1 | C11: M1: Mobilisation | I11: =MIN(I12:I22) -> 45422 | J11: =K11-I11 -> 113 | K11: =MAX(K12:K22) -> 45535 | M11: =AVERAGE(M12:M22) -> 1
B12: 1.1 | C12: Signed Project Task Order | I12: 45454 | J12: =K12-I12 -> 36 | K12: 45490 | M12: 1
B13: 1.2 | C13: Proof of Required Insurance Policies per Master Contract Details (Deferred to M2) | I13: 45478 | J13: =K13-I13 -> 57 | K13: 45535 | M13: 1 | O13: M2
B14: 1.3 | C14: Pre-Installation Roof Condition Report | I14: 45463 | J14: =K14-I14 -> 20 | K14: 45483 | M14: 1
B15: 1.4 | C15: Structural Report | I15: 45490 | J15: =K15-I15 -> 0 | K15: 45490 | M15: 1
B16: 1.5 | C16: Lightning Risk Assessment (BOQ & Quote) | I16: 45422 | J16: =K16-I16 -> 105 | K16: 45527 | M16: 1
B17: 1.6 | C17: Detailed Design Drawings Package | I17: 45467 | J17: =K17-I17 -> 53 | K17: 45520 | M17: 1
B18: 1.7 | C18: Bill of Materials | I18: 45478 | J18: =K18-I18 -> 13 | K18: 45491 | M18: 1
B19: 1.8 | C19: Project Timeline/Programme | I19: 45478 | J19: =K19-I19 -> 42 | K19: 45520 | M19: 1
B20: 1.9 | C20: H&S Plan Approved by Candi | I20: 45489 | J20: =K20-I20 -> 31 | K20: 45520 | M20: 1
B21: 1.10 | C21: Signed Contractor Code of Conduct | I21: 45478 | J21: =K21-I21 -> 5 | K21: 45483 | M21: 1
B22: 1.11 | C22: Grid Connection Application submitted to Municipality | I22: 45440 | J22: =K22-I22 -> 43 | K22: 45483 | M22: 1
B24: 2 | C24: M2: Delivery of Major Components | I24: =MIN(I25:I38) -> 45478 | J24: =K24-I24 -> 84 | K24: =MAX(K25:K38) -> 45562 | M24: =AVERAGE(M25:M38) -> 1
B25: 2.1 | C25: H&S File Approved by CANDI | I25: 45478 | J25: 35 | K25: =WORKDAY.INTL(I25,J25,1,Data!$C$3:$C$14) -> 45530 | M25: 1
B26: 2.2 | C26: Construction Design Package Approved by Candi | I26: 45503 | J26: 59 | K26: =I26+J26 -> 45562 | M26: 1 | O26: Final approval Tie in 1 / Approved in theory
B27: 2.3 | C27: Evidence demonstrating arrival to site of all Major Components | I27: =MIN(I28:I37) -> 45510 | J27: =K27-I27 -> 43 | K27: =MAX(K28:K37) -> 45553 | M27: =AVERAGE(M28:M37) -> 1
B28: 2.3.1 | C28: Delivery of Inverters | I28: 45510 | J28: =K28-I28 -> 0 | K28: 45510 | M28: 1
B29: 2.3.2 | C29: Delivery of Modules | I29: =MIN(I30:I32) -> 45526 | J29: =K29-I29 -> 21 | K29: =MAX(K30:K32) -> 45547 | M29: 1
B30: 2.3.2.1 | C30: Delivery of Batch 1 | I30: 45526 | J30: =K30-I30 -> 0 | K30: =I30 -> 45526 | M30: 1
B31: 2.3.2.2 | C31: Delivery of Batch 2 | I31: 45540 | J31: =K31-I31 -> 0 | K31: =I31 -> 45540 | M31: 1
B32: 2.3.2.3 | C32: Delivery of Batch 3 | I32: 45547 | J32: =K32-I32 -> 0 | K32: =I32 -> 45547 | M32: 1
B33: 2.3.3 | C33: Delivery of Mounting Structure | I33: 45510 | J33: =K33-I33 -> 0 | K33: 45510 | M33: 1
B34: 2.3.4 | C34: Delivery of DC Cable | I34: 45530 | J34: =K34-I34 -> 0 | K34: 45530 | M34: 1
B35: 2.3.5 | C35: Delivery of DBs | I35: =MIN(I36:I37) -> 45525 | J35: 1 | K35: =MAX(K36:K37) -> 45553 | M35: 1
B36: 2.3.5.1 | C36: PVDB 1&2 | I36: 45552 | J36: 1 | K36: =I36+J36 -> 45553 | M36: 1
B37: 2.3.5.2 | C37: Comms DB, Meters, Sensors, Etc (Supplied by Candi) | I37: 45525 | J37: 1 | K37: =I37+J37 -> 45526 | M37: 1
B38: 2.4 | C38: Photos of each of the aforementioned subsystem materials delivered to site | I38: =K36 -> 45553 | J38: 9 | K38: =I38+J38 -> 45562 | M38: 1
B40: 3 | C40: Emergent Energy Construction | I40: =MIN(I41:I76) -> 45510 | J40: =K40-I40 -> 115 | K40: =MAX(K41:K76) -> 45625 | M40: =AVERAGE(M41:M76) -> 1
B41: 3.1 | C41: Fixed Anchor Point & Lifeline Approvals | I41: 45518 | J41: 2 | K41: =WORKDAY.INTL(I41,J41,1,Data!$C$3:$C$14) -> 45520 | M41: 1
B42: 3.2 | C42: Fixed Anchor Point & Lifeline Installation | I42: =WORKDAY.INTL(K41,0,1,Data!$C$3:$C$14) -> 45520 | J42: 5 | K42: =WORKDAY.INTL(I42,J42,1,Data!$C$3:$C$14) -> 45527 | M42: 1
B43: 3.3 | C43: Fixed Anchor Point & Lifeline Sign Off | I43: =WORKDAY.INTL(K42,0,1,Data!$C$3:$C$14) -> 45527 | J43: 4 | K43: =WORKDAY.INTL(I43,J43,1,Data!$C$3:$C$14) -> 45533 | M43: 1
B44: 3.4 | C44: SteelWork Fabrication (Offsite) | I44: 45510 | J44: 15 | K44: =WORKDAY.INTL(I44,J44,1,Data!$C$3:$C$14) -> 45532 | M44: 1
B45: 3.5 | C45: SteelWork Installation (onsite) - CRITICAL PATH | I45: 45574 | J45: 16 | K45: =WORKDAY.INTL(I45,J45,1,Data!$C$3:$C$14) -> 45596 | M45: 1
B46: 3.6 | C46: SteelWork Sign Off | I46: =WORKDAY.INTL(K45,0,1,Data!$C$3:$C$14) -> 45596 | J46: 1 | K46: =WORKDAY.INTL(I46,J46,1,Data!$C$3:$C$14) -> 45597 | M46: 1
B47: 3.7 | C47: Mounting Structure Installation | I47: 45532 | J47: 12 | K47: =WORKDAY.INTL(I47,J47,1,Data!$C$3:$C$14) -> 45548 | M47: 1
B48: 3.8 | C48: DC Cable Tray Installation & Earthing | I48: =WORKDAY.INTL(I47,0,1,Data!$C$3:$C$14)+3 -> 45535 | J48: 43 | K48: =WORKDAY.INTL(I48,J48,1,Data!$C$3:$C$14) -> 45596 | M48: 1 | O48: Dependant on the approval from Candi
B49: 3.9 | C49: DC Cable Stringing | I49: =WORKDAY.INTL(K48,0,1,Data!$C$3:$C$14) -> 45596 | J49: 4 | K49: =WORKDAY.INTL(I49,J49,1,Data!$C$3:$C$14) -> 45602 | M49: 1 | O49: Dependant on the approval from Candi
B50: 3.10 | C50: DC Cable Termination | I50: =WORKDAY.INTL(I49,0,1,Data!$C$3:$C$14) -> 45596 | J50: 5 | K50: =WORKDAY.INTL(I50,J50,1,Data!$C$3:$C$14) -> 45603 | M50: 1
B51: 3.11 | C51: String Voltage Tests | I51: =K58 -> 45603 | J51: 3 | K51: =WORKDAY.INTL(I51,J51,1,Data!$C$3:$C$14) -> 45608 | M51: 1
B52: 3.12 | C52: Module Lifting - Batch 1 | I52: 45540 | J52: 5 | K52: =WORKDAY.INTL(I52,J52,1,Data!$C$3:$C$14) -> 45547 | M52: 1
B53: 3.13 | C53: Module Mounting Batch 1 | I53: =WORKDAY.INTL(K52,0,1,Data!$C$3:$C$14) -> 45547 | J53: 4 | K53: =WORKDAY.INTL(I53,J53,1,Data!$C$3:$C$14) -> 45553 | M53: 1
B54: 3.14 | C54: Module Lifting - Batch 2 | I54: =WORKDAY.INTL(I31,0,1,Data!$C$3:$C$14) -> 45540 | J54: 5 | K54: =WORKDAY.INTL(I54,J54,1,Data!$C$3:$C$14) -> 45547 | M54: 1
B55: 3.15 | C55: Module Mounting Batch 2 | I55: =WORKDAY.INTL(K53,0,1,Data!$C$3:$C$14) -> 45553 | J55: 4 | K55: =WORKDAY.INTL(I55,J55,1,Data!$C$3:$C$14) -> 45560 | M55: 1
B56: 3.16 | C56: Module Lifting - Batch 3 | I56: =WORKDAY.INTL(I32,0,1,Data!$C$3:$C$14)-4 -> 45543 | J56: 5 | K56: =WORKDAY.INTL(I56,J56,1,Data!$C$3:$C$14) -> 45548 | M56: 1
B57: 3.17 | C57: Module Mounting Batch 3 | I57: =WORKDAY.INTL(K55,0,1,Data!$C$3:$C$14) -> 45560 | J57: 5 | K57: =WORKDAY.INTL(I57,J57,1,Data!$C$3:$C$14) -> 45567 | M57: 1
B58: 3.18 | C58: Inverter Installation - Tie In 1 | I58: =WORKDAY.INTL(K46,0,1,Data!$C$3:$C$14) -> 45597 | J58: 4 | K58: =WORKDAY.INTL(I58,J58,1,Data!$C$3:$C$14) -> 45603 | M58: 1
B59: 3.19 | C59: Inverter Installation - Tie In 2 | I59: 45579 | J59: 5 | K59: =WORKDAY.INTL(I59,J59,1,Data!$C$3:$C$14) -> 45586 | M59: 1
B60: 3.20 | C60: PVDB Installation - Tie In 1 | I60: =WORKDAY.INTL(K46,0,1,Data!$C$3:$C$14) -> 45597 | J60: 4 | K60: =WORKDAY.INTL(I60,J60,1,Data!$C$3:$C$14) -> 45603 | M60: 1
B61: 3.21 | C61: PVDB Installation - Tie In 2 | I61: 45586 | J61: 9 | K61: =WORKDAY.INTL(I61,J61,1,Data!$C$3:$C$14) -> 45597 | M61: 1
B62: 3.22 | C62: Candi Comms Board Installation | I62: =WORKDAY.INTL(I60,0,1,Data!$C$3:$C$14) -> 45597 | J62: 8 | K62: =WORKDAY.INTL(I62,J62,1,Data!$C$3:$C$14) -> 45609 | M62: 1
B63: 3.23 | C63: Cable Tray Installation - Tie In 1 | I63: =WORKDAY.INTL(I48,0,1,Data!$C$3:$C$14) -> 45535 | J63: 43 | K63: =WORKDAY.INTL(I63,J63,1,Data!$C$3:$C$14) -> 45596 | M63: 1
B64: 3.24 | C64: Cable Tray Installation - Tie In 2 | I64: =WORKDAY.INTL(I63,0,1,Data!$C$3:$C$14) -> 45535 | J64: 40 | K64: =WORKDAY.INTL(I64,J64,1,Data!$C$3:$C$14) -> 45593 | M64: 1
B65: 3.25 | C65: Inverter AC Cable Installation - Tie In 1 | I65: =WORKDAY.INTL(I58,0,1,Data!$C$3:$C$14) -> 45597 | J65: 3 | K65: =WORKDAY.INTL(I65,J65,1,Data!$C$3:$C$14) -> 45602 | M65: 1
B66: 3.26 | C66: Inverter AC Cable Installation - Tie In 2 | I66: =WORKDAY.INTL(I65,0,1,Data!$C$3:$C$14) -> 45597 | J66: 3 | K66: =WORKDAY.INTL(I66,J66,1,Data!$C$3:$C$14) -> 45602 | M66: 1
B67: 3.27 | C67: AC Supply Cable Installation - Tie In 1 | I67: =WORKDAY.INTL(K66,0,1,Data!$C$3:$C$14) -> 45602 | J67: 2 | K67: =WORKDAY.INTL(I67,J67,1,Data!$C$3:$C$14) -> 45604 | M67: 1
B68: 3.28 | C68: AC Supply Cable Installation - Tie In 2 | I68: =WORKDAY.INTL(I67,0,1,Data!$C$3:$C$14) -> 45602 | J68: 2 | K68: =WORKDAY.INTL(I68,J68,1,Data!$C$3:$C$14) -> 45604 | M68: 1
B69: 3.29 | C69: AC Soft Commissioning | I69: =WORKDAY.INTL(K68,0,1,Data!$C$3:$C$14) -> 45604 | J69: 2 | K69: =WORKDAY.INTL(I69,J69,1,Data!$C$3:$C$14) -> 45608 | M69: 1
B70: 3.30 | C70: Comms Soft Commissioning | I70: =WORKDAY.INTL(I69,0,1,Data!$C$3:$C$14) -> 45604 | J70: 3 | K70: =WORKDAY.INTL(I70,J70,1,Data!$C$3:$C$14) -> 45609 | M70: 1
B71: 3.31 | C71: DC Soft Commissioning | I71: =WORKDAY.INTL(I51,0,1,Data!$C$3:$C$14) -> 45603 | J71: 4 | K71: =WORKDAY.INTL(I71,J71,1,Data!$C$3:$C$14) -> 45609 | M71: 1
B72: 3.32 | C72: Shutdown Tie In 1 | I72: 45606 | J72: 1 | K72: =WORKDAY.INTL(I72,J72,1,Data!$C$3:$C$14) -> 45607 | M72: 1
B73: 3.33 | C73: Shutdown Tie In 2 | I73: 45606 | J73: 1 | K73: =WORKDAY.INTL(I73,J73,1,Data!$C$3:$C$14) -> 45607 | M73: 1
B74: 3.34 | C74: System Energising | I74: =WORKDAY.INTL(K69,0,1,Data!$C$3:$C$14) -> 45608 | J74: 2 | K74: =WORKDAY.INTL(I74,J74,1,Data!$C$3:$C$14) -> 45610 | M74: 1
B75: 3.35 | C75: Production Monitoring | I75: =WORKDAY.INTL(K74,0,1,Data!$C$3:$C$14) -> 45610 | J75: 5 | K75: =WORKDAY.INTL(I75,J75,1,Data!$C$3:$C$14) -> 45617 | M75: 1
B76: 3.36 | C76: PrEng Signoff | I76: 45624 | J76: 1 | K76: =WORKDAY.INTL(I76,J76,1,Data!$C$3:$C$14) -> 45625 | M76: 1
B78: 4 | C78: M3: Practical Completion | I78: =MIN(I79:I84) -> 45604 | J78: =K78-I78 -> 11 | K78: =MAX(K79:K83) -> 45615 | M78: =AVERAGE(M79:M84) -> 1
B79: 4.1 | C79: Commissioning Form/Checklist | I79: =WORKDAY.INTL(I69,0,1,Data!$C$3:$C$14) -> 45604 | J79: 7 | K79: =WORKDAY.INTL(I79,J79,1,Data!$C$3:$C$14) -> 45615 | M79: 1
B80: 4.2 | C80: Evidence demonstrating achievement of all Capacity Tests | I80: =WORKDAY.INTL(I79,0,1,Data!$C$3:$C$14) -> 45604 | J80: 7 | K80: =WORKDAY.INTL(I80,J80,1,Data!$C$3:$C$14) -> 45615 | M80: 1 | O80: Done by Candi
B81: 4.3 | C81: Electrical Certificate of Compliance | I81: =WORKDAY.INTL(K69,0,1,Data!$C$3:$C$14) -> 45608 | J81: 1 | K81: =WORKDAY.INTL(I81,J81,1,Data!$C$3:$C$14) -> 45609 | M81: 1
B82: 4.4 | C82: Completed Quantum PVForm | I82: =WORKDAY.INTL(I79,0,1,Data!$C$3:$C$14) -> 45604 | J82: 7 | K82: =WORKDAY.INTL(I82,J82,1,Data!$C$3:$C$14) -> 45615 | M82: 1
B83: 4.5 | C83: Site Rubble Removal | I83: =WORKDAY.INTL(I79,0,1,Data!$C$3:$C$14) -> 45604 | J83: 3 | K83: =WORKDAY.INTL(I83,J83,1,Data!$C$3:$C$14) -> 45609 | M83: 1
B84: 4.6 | C84: Creation of Snag List - M4 | I84: 45635 | J84: 1 | K84: =WORKDAY.INTL(I84,J84,1,Data!$C$3:$C$14) -> 45636 | M84: 1
B86: 5 | C86: M4: Provisional Acceptance | I86: =MIN(I87:I97) -> 45635 | J86: =K86-I86 -> 102 | K86: =MAX(K87:K97) -> 45737 | M86: =AVERAGE(M87:M97) -> 1
B87: 5.1 | C87: Close out of Snag List | I87: 45677 | J87: 5 | K87: =WORKDAY.INTL(I87,J87,1,Data!$C$3:$C$14) -> 45684 | M87: 1
B88: 5.1.1 | C88: Platform Installation at Tie-In 2 | I88: 45698 | J88: 24 | K88: =WORKDAY.INTL(I88,J88,1,Data!$C$3:$C$14) -> 45730 | M88: 1
B89: 5.2 | C89: Successful audit of HSE file by Candi | I89: =K88 -> 45730 | J89: 3 | K89: =WORKDAY.INTL(I89,J89,1,Data!$C$3:$C$14) -> 45735 | M89: 1
B90: 5.3 | C90: Training of designated CANDI and/or Customer personnel | I90: 45635 | J90: 1 | K90: =WORKDAY.INTL(I90,J90,1,Data!$C$3:$C$14) -> 45636 | M90: 1
B91: 5.4 | C91: Completed asset register of all components on site including serial numbers | I91: =WORKDAY.INTL(I88,0,1,Data!$C$3:$C$14) -> 45698 | J91: 5 | K91: =WORKDAY.INTL(I91,J91,1,Data!$C$3:$C$14) -> 45705 | M91: 1
B92: 5.5 | C92: Successful reception of data on CANDI servers | I92: =WORKDAY.INTL(K91,0,1,Data!$C$3:$C$14) -> 45705 | J92: 1 | K92: =WORKDAY.INTL(I92,J92,1,Data!$C$3:$C$14) -> 45706 | M92: 1
B93: 5.6 | C93: As-built drawings package | I93: =WORKDAY.INTL(I90,0,1,Data!$C$3:$C$14) -> 45635 | J93: 5 | K93: =WORKDAY.INTL(I93,J93,1,Data!$C$3:$C$14) -> 45643 | M93: 1
B94: 5.7 | C94: Final as-built EYA | I94: =WORKDAY.INTL(I89,0,1,Data!$C$3:$C$14) -> 45730 | J94: 5 | K94: =WORKDAY.INTL(I94,J94,1,Data!$C$3:$C$14) -> 45737 | M94: 1
B95: 5.8 | C95: Handover of equipment warranty documents, Owners Manuals & Datasheets | I95: =WORKDAY.INTL(I89,0,1,Data!$C$3:$C$14) -> 45730 | J95: 5 | K95: =WORKDAY.INTL(I95,J95,1,Data!$C$3:$C$14) -> 45737 | M95: 1
B96: 5.9 | C96: Signed Milestone 3 - Certificate of Practical Completion | I96: =WORKDAY.INTL(K84,0,1,Data!$C$3:$C$14) -> 45636 | J96: 0 | K96: =WORKDAY.INTL(I96,J96,1,Data!$C$3:$C$14) -> 45636 | M96: 1
B97: 5.10 | C97: Guaranteed PR achieved during Acceptance Test | I97: 45639 | J97: 3 | K97: =WORKDAY.INTL(I97,J97,1,Data!$C$3:$C$14) -> 45645 | M97: 1
B99: 6 | C99: M5: Final Acceptance | M99: =AVERAGE(M100:M103) -> 0.375
C100: Request subdeliverables from Candi | I100: =K86+1 -> 45738 | J100: 5 | K100: =I100+J100 -> 45743 | M100: 0
C101: NERSA Application | I101: =WORKDAY.INTL(K76,0,1,Data!$C$3:$C$14) -> 45625 | J101: 190 | K101: =WORKDAY.INTL(I101,J101,1,Data!$C$3:$C$14) -> 45896 | M101: 0.75
B106: 1 | C106: Project Initiation | E106: =MIN(E107:E111) -> 45454 | F106: =G106-E106 -> 16 | G106: =MAX(G107:G111) -> 45470 | I106: =MIN(I107:I111) -> 45467 | J106: =K106-I106 -> 17 | K106: =MAX(K107:K111) -> 45484 | M106: =(J107*M107+J108*M108+J109*M109+J110*M110+J111*M111)/SUM(J107:J111) -> 1 | N106: =M106*J106 -> 17
B107: 1.1 | C107: BD Handover | E107: 45461 | F107: 1 | G107: =WORKDAY.INTL(E107,F107,1,Data!$C$3:$C$14) -> 45462 | I107: 45467 | J107: 1 | K107: =WORKDAY.INTL(I107,J107,1,Data!$C$3:$C$14) -> 45468 | M107: 1
B108: 1.2 | C108: Project Introduction | E108: =G107 -> 45462 | F108: 1 | G108: =WORKDAY.INTL(E108,F108,1,Data!$C$3:$C$14) -> 45463 | I108: =K107 -> 45468 | J108: 1 | K108: =WORKDAY.INTL(I108,J108,1,Data!$C$3:$C$14) -> 45469 | M108: 1
B109: 1.3 | C109: HSE | E109: 45454 | F109: 10 | G109: =E109+F109 -> 45464 | I109: =K108 -> 45469 | J109: 10 | K109: =I109+J109 -> 45479 | M109: 1
B110: 1.4 | C110: Installer Kick Off | E110: =G111 -> 45469 | F110: 1 | G110: =WORKDAY.INTL(E110,F110,1,Data!$C$3:$C$14) -> 45470 | I110: =K109 -> 45479 | J110: 1 | K110: =WORKDAY.INTL(I110,J110,1,Data!$C$3:$C$14) -> 45481 | M110: 1
...

Sheet Revenue Tracking
B2: HIGH LEVEL PROJECT REVENUE TRACKING
D3: PLANNED | F3: ACTUAL | L3: FINANCIAL REVIEW | N3: TIMELINE REVIEW | R3: Allocated in 2024 | S3: Budgeted | T3: Actual
B4: 1 | C4: Planned Revenue | D4: ='Project Plan'!E6 -> 9650000 | F4: =F21 -> 9734366 | L4: 9650000 | N4: Start Date | P4: Sales | R4: 5633108.4 | S4: 4091891.6 | T4: =F4-R4 -> 4101257.6
B5: 2 | C5: Planned Expenditure | D5: =+'Expenditure Tracking'!F5 -> 8749927.2 | F5: =+'Expenditure Tracking'!H5 -> 6993121.8 | L5: 7262932.2 | N5: TBC | P5: COS | R5: 3426357.1 | S5: 3444874.5 | T5: =F5-R5 -> 3566764.7
B6: 3 | C6: Planned Profit | D6: =+D4-D5 -> 900072.82 | F6: =+F4-F5 -> 2741244.2 | L6: 2387067.8 | N6: End Date - PC | P6: GP | R6: =R4-R5 -> 2206751.3 | S6: =S4-S5 -> 647017.14 | T6: =T4-T5 -> 534492.92
B7: 4 | C7: Planned Margin | D7: =+D6/D4 -> 0.093271795 | F7: =+F6/F4 -> 0.2816048 | L7: 0.24736454 | N7: TBC
B10: CONTRACT
B12: No. | C12: PAYMENT MILESTONE | E12: % | F12: VALUE | H12: PLANNED PAYMENT DATE | L12: INVOICE NUMBER | N12: INVOICE RAISED DATE | P12: PAYMENT RECEIVED DATE | R12: MILESTONE NOTES & COMMENTS
B13: 1 | C13: M1 - Mobilisation | E13: 0.2 | F13: =$D$4*E13 -> 1930000 | H13: ='Project Plan'!I114+7 -> 45510 | L13: 004486 | N13: 45492 | P13: 45499
B14: 2 | C14: M2 - Upon delivery to site of all Major Equipment | E14: 0.55 | F14: =$D$4*E14 -> 5307500 | H14: ='Project Plan'!G117+7 -> 45512 | L14: 004564 | N14: 45579 | P14: 45595
B15: 3 | C15: M3 - Upon receipt of the Practical Completion Certificate | E15: 0.1 | F15: =$D$4*E15 -> 965000 | H15: ='Project Plan'!G145 -> 45600 | L15: 004624 | N15: 45630 | P15: 45673
B16: 4 | C16: M4 - Upon receipt of the Provisional Acceptance Certificate | E16: 0.1 | F16: =$D$4*E16 -> 965000 | H16: ='Project Plan'!G152 -> 45623 | L16: 004816 | N16: 45887 | P16: 45898
B17: 5 | C17: M5 - Upon receipt of the Final Acceptance Certificate | E17: 0.05 | F17: =$D$4*E17 -> 482500 | H17: =H16+365 -> 45988 | P17: 46112
B18: 6 | C18: VO - Anchor Point | E18: 0 | F18: 75000 | H18: 45623 | L18: 004780 | N18: 45841 | P18: 45887
B19: 7 | C19: VO - Waterpoint Clamps | E19: 0 | F19: 9366 | H19: 45716 | L19: 004780 | N19: 45841 | P19: 45887
E21: =SUM(E13:E19) -> 1 | F21: =SUM(F13:F19) -> 9734366
B23: KEY: | C23: contains an error (in result or a check has failed)
C24: Red Font - IF TEXT : content not yet confirmed
C25: Red Font - IF NUMBER: Negative value
C26: Anything in yellow is a concern or risk for noting or action
C27: confirmed
C28: [ADD INITIALS: comment for noting in square brackets, use colour or red to draw attention if important]
C29: [RT: When adding rows into sheet, ensure you insert between first and last row of each category]
C30: end of sheet - do not insert information below/beyond this
B40: No. | C40: PAYMENT MILESTONE | E40: % | F40: VALUE
B41: 1 | C41: Deposit - Project commencement | E41: 0.35 | F41: =$F$47*E41 -> 3407028.1
B42: 2 | C42: Delivery of Panels | E42: 0.3 | F42: =$F$47*E42 -> 2920309.8
B43: 3 | C43: Delivery of Inverters | E43: 0.2 | F43: =$F$47*E43 -> 1946873.2
B44: 4 | C44: Practical Completion | E44: 0.1 | F44: =$F$47*E44 -> 973436.6
B45: 5 | C45: Handover | E45: 0.05 | F45: =$F$47*E45 -> 486718.3
C46: Total | E46: =SUM(E41:E45) -> 1 | F46: =SUM(F41:F45) -> 9734366
E47: =SUM(E41:E45) -> 1 | F47: =F21 -> 9734366

Sheet Data
C2: Public holidays | F2: Drop down list
C3: 45292 | D3: New Years Day | F3: Approved
C4: 45372 | D4: Human Rights day | F4: Pending
C5: 45380 | D5: Good Friday | F5: Declined
C6: 45383 | D6: Family Day | F6: Abanded
C7: 45413 | D7: Workers day
C8: 45460 | D8: Youth Day Holiday
C9: 45513 | D9: Womens Day
C10: 45559 | D10: Heritage Day
C11: 45642 | D11: Day of Reconciliation
C12: 45651 | D12: Christmas Day
C13: 45652 | D13: Day of Goodwill | H13: Manual dates

Sheet Expenditure Tracking
B2: HIGH LEVEL PROJECT EXPENDITURE TRACKING
F4: COSTED | H4: ACTUAL | J4: Difference from costed
B5: EXPENDITURE | F5: =SUM(F9:F23) -> 8749927.2 | H5: =SUM(H9:H23) -> 6993121.8 | J5: =SUM(J9:J23) -> 1756805.4
B7: No. | D7: Item | F7: Costed Expenditure | H7: Actual Expenditure | J7: Saving / Overrun | L7: Comments on variations from planned expenditure
B9: ='Expenditure Breakdown'!B6 -> 1 | D9: ='Expenditure Breakdown'!C6 -> Panels | F9: ='Expenditure Breakdown'!I6 -> 0 | H9: ='Expenditure Breakdown'!X6 -> 0 | J9: =F9-H9 -> 0
B10: ='Expenditure Breakdown'!B13 -> 2 | D10: ='Expenditure Breakdown'!C13 -> Inverters | F10: =+'Expenditure Breakdown'!I13 -> 864000 | H10: =+'Expenditure Breakdown'!X13 -> 757680 | J10: =F10-H10 -> 106320
B11: ='Expenditure Breakdown'!B18 -> 3 | D11: ='Expenditure Breakdown'!C18 -> Mounting Structures | F11: =+'Expenditure Breakdown'!I18 -> 679320 | H11: =+'Expenditure Breakdown'!X18 -> 619184.87 | J11: =F11-H11 -> 60135.13
B12: ='Expenditure Breakdown'!B32 -> 4 | D12: ='Expenditure Breakdown'!C32 -> DC Equipment | F12: =+'Expenditure Breakdown'!I32 -> 1357297 | H12: =+'Expenditure Breakdown'!X32 -> 810195 | J12: =F12-H12 -> 547102
B13: ='Expenditure Breakdown'!B46 -> 5 | D13: ='Expenditure Breakdown'!C46 -> Monitoring | F13: =+'Expenditure Breakdown'!I46 -> 49000 | H13: =+'Expenditure Breakdown'!X46 -> 28480 | J13: =F13-H13 -> 20520
B14: ='Expenditure Breakdown'!B53 -> 6 | D14: ='Expenditure Breakdown'!C53 -> AC Equipment | F14: =+'Expenditure Breakdown'!I53 -> 3348396.3 | H14: =+'Expenditure Breakdown'!X53 -> 1177114.1 | J14: =F14-H14 -> 2171282.1
B15: ='Expenditure Breakdown'!B68 -> 7 | D15: ='Expenditure Breakdown'!C68 -> Battery Systems | F15: =+'Expenditure Breakdown'!I68 -> 0 | H15: ='Expenditure Breakdown'!X68 -> 0 | J15: =F15-H15 -> 0
B16: ='Expenditure Breakdown'!B77 -> 8 | D16: ='Expenditure Breakdown'!C77 -> Product Add On | F16: ='Expenditure Breakdown'!I77 -> 255000 | H16: ='Expenditure Breakdown'!X77 -> 1488603.7 | J16: =F16-H16 -> -1233603.7
B17: ='Expenditure Breakdown'!L101 -> 9 | D17: ='Expenditure Breakdown'!C101 -> AC & DC Installation | F17: =+'Expenditure Breakdown'!I101 -> 1281800 | H17: =+'Expenditure Breakdown'!X101 -> 1500000 | J17: =F17-H17 -> -218200
B18: ='Expenditure Breakdown'!B110 -> 10 | D18: ='Expenditure Breakdown'!C110 -> Site Logistics | F18: =+'Expenditure Breakdown'!I110 -> 529807.5 | H18: =+'Expenditure Breakdown'!X110 -> 24394.2 | J18: =F18-H18 -> 505413.3
B19: ='Expenditure Breakdown'!B116 -> 11 | D19: ='Expenditure Breakdown'!C116 -> Due Dilligence | F19: ='Expenditure Breakdown'!I116 -> 200220 | H19: ='Expenditure Breakdown'!X116 -> 116600 | J19: =F19-H19 -> 83620
B20: ='Expenditure Breakdown'!B126 -> 12 | D20: ='Expenditure Breakdown'!C126 -> BDP Commission | F20: ='Expenditure Breakdown'!G125 -> 158836.38 | H20: ='Expenditure Breakdown'!X125 -> 264727.3 | J20: =F20-H20 -> -105890.92
B21: ='Expenditure Breakdown'!B128 -> 13 | D21: ='Expenditure Breakdown'!C128 -> Engineering | F21: =+'Expenditure Breakdown'!I128 -> 0 | H21: =+'Expenditure Breakdown'!X128 -> 120625 | J21: =F21-H21 -> -120625 | L21: RV: Matriarch defects percentage 1.25%
B22: ='Expenditure Breakdown'!B136 -> 14 | D22: ='Expenditure Breakdown'!C136 -> General Expenses | F22: =+'Expenditure Breakdown'!I136 -> 26250 | H22: =+'Expenditure Breakdown'!X136 -> 85517.61 | J22: =F22-H22 -> -59267.61
B23: ='Expenditure Breakdown'!B149 -> 15 | D23: ='Expenditure Breakdown'!C149 -> Service Add On | F23: =+'Expenditure Breakdown'!I149 -> 0 | H23: =+'Expenditure Breakdown'!X149 -> 0 | J23: =F23-H23 -> 0
D25: check: | F25: ='Expenditure Breakdown'!I2-'Expenditure Tracking'!F5 -> 0 | G25: ='Expenditure Breakdown'!#REF!-G5 -> #REF! | H25: ='Expenditure Breakdown'!X2-H5 -> 0
A27: Copy amounts in column H and paste as values at Project review.

Sheet Expenditure Breakdown
B2: COSTED EXPENDITURE BREAKDOWN | I2: =SUM(I6:I153) -> 8749927.2 | J2: =SUM(J6:J153) -> 9734366.1 | L2: ACTUAL EXPENDITURE BREAKDOWN | S2: FINANCE ONLY | X2: =SUM(X6:X153) -> 6993121.8
B4: No. | C4: Product / Service | D4: Description of Work | E4: QTY | F4: Rate / Unit | G4: Budget Total | H4: Project Related date | I4: Total COS | J4: =IF(J2-'Revenue Tracking'!D4>=0, "Total Revenue", "ERROR on REV" ) -> Total Revenue | L4: No. | M4: Product/ Service | N4: Description of Work | O4: QTY | P4: Rate / Unit | Q4: Actual Total | R4: PO NUMBER | S4: INVOICE NUMBER | T4: INVOICE RAISED DATE | U4: REVENUE RECOGNITION AMOUNT | V4: CHECK | W4: FINANCE PAYMENT DATE | X4: Total COS | Y4: COMMENTS
B6: 1 | C6: Panels | D6: Panels will be free-issued | E6: 2720 | F6: 1484.97 | L6: 1 | M6: 1. Panels | T6: =IF(W6>1,EOMONTH(W6,0),"") | Z6: 19
B7: 1 | L7: 1 | M7: 1. Panels | T7: =IF(W7>1,EOMONTH(W7,0),"") | Z7: BUDGET | AA7: Installer Allocation
B8: 1 | L8: 1 | M8: 1. Panels | T8: =IF(W8>1,EOMONTH(W8,0),"") | Z8: AC Equipment | AA8: =C60 -> 3348396.3
B9: 1 | L9: 1 | M9: 1. Panels | T9: =IF(W9>1,EOMONTH(W9,0),"") | Z9: DC Equipment | AA9: =SUM(G33:G44) -> 757137
B10: 1 | L10: 1 | M10: 1. Panels | T10: =IF(W10>1,EOMONTH(W10,0),"") | Z10: AC Labour | AA10: =C103 -> 377400
B11: 1 | L11: 1 | M11: 1. Panels | T11: =IF(W11>1,EOMONTH(W11,0),"") | Z11: DC Labour | AA11: =C102 -> 904400
T12: =IF(W12>1,EOMONTH(W12,0),"") | Z12: Offloading | AA12: =G111 -> 8500
B13: 2 | C13: Inverters | D13: Huawei 100KTL | E13: 12 | F13: 72000 | G13: =E13*F13 -> 864000 | H13: ='Project Plan'!E117+30 -> 45533 | I13: =SUM(G13:G16) -> 864000 | J13: 956194.33 | L13: 2 | M13: 2. Inverters | N13: Huawei 100KTL - Aarden Solar | O13: 11 | P13: 68880 | Q13: =O13*P13 -> 757680 | R13: PO3260-CAS-20240725 - RV Approved | S13: Arden Inv: NV-05927 | T13: 45535 | U13: 956194.33 | V13: =J13-SUM(U13:U16) -> 0 | W13: 45569 | X13: =SUM(Q13:Q16) -> 757680 | Y13: Aarden Solar quote - 30 days from statement | Z13: Roof Access/Scaffolding | AA13: =G110 -> 115057.5
B14: 2 | L14: 2 | M14: 2. Inverters | N14: Price include deilvery | T14: =IF(W14>1,EOMONTH(W14,0),"") | Z14: Storage | AA14: =G112 -> 46250
B15: 2 | L15: 2 | M15: 2. Inverters | T15: =IF(W15>1,EOMONTH(W15,0),"") | Z15: Telehandler | AA15: 0
B16: 2 | L16: 2 | M16: 2. Inverters | T16: =IF(W16>1,EOMONTH(W16,0),"") | Z16: Other | AA16: 0
T17: =IF(W17>1,EOMONTH(W17,0),"") | Z17: Total | AA17: =SUM(AA8:AA16) -> 5557140.8
B18: 3 | C18: Mounting Structures | D18: KlipLok Roof | E18: 1509600 | F18: 0.45 | G18: =E18*F18 -> 679320 | H18: ='Project Plan'!E114+30 -> 45533 | I18: =SUM(G18:G30) -> 679320 | J18: 751807.79 | L18: 3 | M18: 3. Mounting Structures | N18: KlipLok/Novatexi Roof - Lumax | O18: 1 | P18: 364557.56 | Q18: =O18*P18 -> 364557.56 | S18: Lumax Inv: INV00045783 | T18: 45535 | U18: 723092.46 | V18: =J18-SUM(U18:U30) -> 0.0018009 | W18: 45562 | X18: =SUM(Q18:Q30) -> 619184.87 | Z18: Less 15% | AA18: =+AA17*0.85 -> 4723569.7 | AC18: [SM: Target Installation Price]
B19: 3 | L19: 3 | M19: 3. Mounting Structures | N19: LUMAX additional Clamps | Q19: 14477.25 | R19: PO3346-CAS-2024090 - RV Approved | S19: Lumax Inv: INV0046571 | T19: 45565 | U19: 16828.079 | W19: 45595 | Z19: R/Wp | AA19: =+AA18/'Project Plan'!$E$3/1000 -> 3.1281918
B20: 3 | L20: 3 | M20: 3. Mounting Structures | N20: DC Cable Tray Clamps | Q20: 11908 | R20: PO3379-CAS-20241002 - RV Approved | S20: Lumax Inv: INV0047410 | T20: 45596 | U20: 11887.248 | W20: =T20+29 -> 45625
L21: 3 | M21: 3. Mounting Structures | N21: Test Clamps | Q21: 2352.38 | R21: PO3797-CAS-20250410 - RV Approved | S21: Lumax - Inv 1001/70001421 | T21: 45777 | U21: 0 | W21: 45806
L22: 3 | M22: 3. Mounting Structures
L23: 3 | M23: 3. Mounting Structures | Q23: 6831.28 | R23: PO4021-CAS-20250623 - RV Approved | S23: Lumax - INV 1001/70002518 | T23: 45838 | W23: 45867 | Y23: TC: added cost PO4021-CAS-20250623
L24: 3 | M24: 3. Mounting Structures
L25: 3 | M25: 3. Mounting Structures | N25: Mid Clamps | Q25: 1823 | R25: PO4015-CAS-20250620 - RV Approved | S25: Lumax - Inv 1001/70002494 | T25: 45838 | W25: 45867
L26: 3 | M26: 3. Mounting Structures | N26: Lumax Replacement Clamps | Q26: 197641.6 | R26: PO3961-CAS-20250527 - RV Approved | S26: Lumax INV1001/70002085 | T26: 45808 | W26: 45835
L27: 3 | M27: 3. Mounting Structures | N27: Delivery | Q27: 2950 | S27: Lumax INV1001/70002084 | T27: 45808 | W27: 45835
L28: 3 | M28: 3. Mounting Structures | N28: Return of MS to Lumax | Q28: 10295.19 | S28: DSV Inv: 180138260 | T28: 45869 | W28: 45898
L29: 3 | M29: 3. Mounting Structures | N29: MS Scrapped | Q29: -3017.39 | S29: Scrapped MS | T29: 45991 | W29: 45985
B30: 3 | L30: 3 | M30: 3. Mounting Structures | N30: Waterpoints Clamps | Q30: 9366 | R30: PO3652-CAS-20250212 - RV Approved | S30: Schletter - INV1422 | T30: 45716 | U30: 0 | W30: 45744 | Y30: We are doing Candi a favour here, they have issued a PO to us for the procurement of this equipment. | Z30: ACTUAL | AA30: Installer Price
T31: =IF(W31>1,EOMONTH(W31,0),"") | Z31: AC Equipment | AA31: 0
B32: 4 | C32: DC Equipment | D32: DC Cable | E32: 37510 | F32: 16 | G32: =E32*F32 -> 600160 | H32: ='Project Plan'!E136+30 -> 45553 | I32: =SUM(G32:G44) -> 1357297 | J32: 1502129.3 | L32: 4 | M32: 4. DC Equipment | N32: DC Cable - Menlo | O32: 44000 | P32: 13.52 | Q32: =O32*P32 -> 594880 | R32: PO3313-CAS-20240822 - RV Approved | S32: Menlo Inv: 0001925 | T32: 45535 | U32: 1160037.7 | V32: =J32-SUM(U32:U44) -> 0.0043202403 | W32: 45600 | X32: =SUM(Q32:Q44) -> 810195 | Z32: DC Equipment | AA32: 0
B33: 4 | D33: DC Surge Arrestor | E33: 4 | F33: 5500 | G33: =E33*F33 -> 22000 | H33: ='Project Plan'!E137+30 -> 45573 | L33: 4 | M33: 4. DC Equipment | N33: DC Cable - Menlo | O33: 1000 | P33: 13.52 | Q33: =O33*P33 -> 13520 | S33: Menlo Inv: 0001926 | T33: 45535 | U33: 26361.355 | W33: 45600 | Z33: AC Labour | AA33: 0
L34: 4 | M34: 4. DC Equipment | N34: Delivery | Q34: 450 | S34: Menlo Inv: 0002198 | T34: 45626 | U34: 0 | W34: 45663
L35: 4 | M35: 4. DC Equipment | N35: DC Cable allocated from Stock | O35: 1500 | P35: 13.09 | Q35: =O35*P35 -> 19635 | S35: Allocated from Stock | T35: 45535 | U35: 0 | W35: 45535
L36: 4 | M36: 4. DC Equipment | N36: DC Cable allocated from Stock | O36: 1500 | P36: 13.14 | Q36: =O36*P36 -> 19710 | S36: Allocated from Stock | T36: 45535 | U36: 0 | W36: 45535
B37: 4 | D37: DC Cable Tray | E37: 220 | F37: 1020 | G37: =E37*F37 -> 224400 | H37: ='Project Plan'!E139+30 -> 45553 | L37: 4 | M37: 4. DC Equipment | N37: Project Kick Off | O37: =AD47 -> 162000 | P37: 0.1 | Q37: =$O$37*P37 -> 16200 | R37: PO3211-CAS-20240703 | S37: Luken Inv0556 | T37: =IF(W37>1,EOMONTH(W37,0),"") -> 45504 | U37: 31531.577 | W37: =W101 -> 45498 | Z37: DC Labour | AA37: 0
B38: 4 | L38: 4 | M38: 4. DC Equipment | N38: Site Establishment | P38: 0.15 | Q38: =$O$37*P38 -> 24300 | S38: Luken Inv0559 | T38: 45504 | U38: 47297.365 | W38: =W102 -> 45512 | Z38: Offloading | AA38: 0
B39: 4 | L39: 4 | M39: 4. DC Equipment | N39: AC Installation Complete | P39: 0.2 | Q39: =$O$37*P39 -> 32400 | S39: Luken Inv0593 | T39: =IF(W39>1,EOMONTH(W39,0),"") -> 45626 | U39: 60154.16 | W39: =W103 -> 45610 | Z39: Roof Access/Scaffolding | AA39: 0
B40: 4 | L40: 4 | M40: 4. DC Equipment | N40: DC Installation Complete | P40: 0.25 | Q40: =$O$37*P40 -> 40500 | S40: Luken Inv 0576 | T40: 45596 | U40: 86641.006 | W40: =W104 -> 45575 | Z40: Compliance | AA40: 0
B41: 4 | L41: 4 | M41: 4. DC Equipment | N41: Commissioning Complete | P41: 0.1 | Q41: =$O$37*P41 -> 16200 | S41: Luken Inv 0594 | T41: =IF(W41>1,EOMONTH(W41,0),"") -> 45626 | U41: 30035.355 | W41: 45617 | Z41: Travel | AA41: 0
B42: 4 | L42: 4 | M42: 4. DC Equipment | N42: Site De-establisment | P42: 0.1 | Q42: =$O$37*P42 -> 16200 | S42: Luken Inv 0595 | T42: =IF(W42>1,EOMONTH(W42,0),"") -> 45626 | U42: 30035.355 | W42: 45617 | Z42: Other | AA42: 0
B43: 4 | D43: Earth Cable | E43: 37510 | F43: 13.5 | G43: =E43*F43 -> 506385 | H43: =H32 -> 45553 | L43: 4 | M43: 4. DC Equipment | N43: Handover Document Complete | P43: 0.05 | Q43: =$O$37*P43 -> 8100 | S43: Luken Inv 0598 | T43: =T107 -> 45626 | U43: 15017.677 | W43: =W107 -> 45631 | Z43: Other | AA43: 0
B44: 4 | D44: Earth clamp | E44: 272 | F44: 16 | G44: =E44*F44 -> 4352 | H44: ='Project Plan'!E145 -> 45593 | L44: 4 | M44: 4. DC Equipment | N44: End of Defects Period | P44: 0.05 | Q44: =$O$37*P44 -> 8100 | S44: Luken Inv 0599 | T44: 45626 | U44: 15017.677 | W44: =W108 -> 45890 | Z44: Other | AA44: 0 | AC44: Labour | AD44: Equipment
T45: =IF(W45>1,EOMONTH(W45,0),"") | Z45: Total | AA45: 2400000 | AC45: =AA45-AD45 -> 1500000 | AD45: 900000
B46: 5 | C46: Monitoring | D46: Smartlogger 3000 | E46: 1 | F46: 26000 | G46: =F46*E46 -> 26000 | H46: =H13 -> 45533 | I46: =SUM(G46:G51) -> 49000 | J46: 54228.614 | L46: 5 | M46: 5. Monitoring | T46: =IF(W46>1,EOMONTH(W46,0),"") | U46: 0 | V46: =J46-SUM(U46:U51) -> -0.0017633556 | X46: =SUM(Q46:Q51) -> 28480 | Z46: R/Wp | AA46: =+AA45/'Project Plan'!$E$3/1000 -> 1.589404 | AD46: =AD45*0.82 -> 738000 | AE46: AC
B47: 5 | D47: Comms DB | G47: 8000 | H47: =H46 -> 45533 | L47: 5 | M47: 5. Monitoring | N47: CTs | Q47: 24770 | R47: PO3317-CAS-20240826 - RV Approved | S47: AccuEnergy - IN ASAI-003703 | T47: 45535 | U47: 11215.185 | W47: 45562 | AD47: =AD45*0.18 -> 162000 | AE47: DC
B48: 5 | D48: Revenue Grade Meter | E48: 1 | F48: 15000 | G48: =F48*E48 -> 15000 | H48: ='Project Plan'!G156 -> 45609 | L48: 5 | M48: 5. Monitoring | N48: Replacement CTs | Q48: 3710 | R48: PO3556-CAS-20250122 - RV Approved | S48: Acccuenergy - ASAI-004594 | T48: 45688 | U48: 0 | W48: 45715
B49: 5 | L49: 5 | M49: 5. Monitoring | U49: 0
B50: 5 | L50: 5 | M50: 5. Monitoring | N50: Candi Monitoring Box Wiring | U50: 0
B51: 5 | L51: 5 | M51: 5. Monitoring | N51: Tester - EE Stock | Q51: 0 | S51: Removed | T51: 45596 | U51: 43013.43 | W51: =T51+30 -> 45626
T52: =IF(W52>1,EOMONTH(W52,0),"")
B53: 6 | C53: AC Equipment | D53: Project Kick Off | F53: 0.1 | G53: =$C$60*F53 -> 334839.63 | H53: =H101 -> 45496 | I53: =SUM(G53:G66) -> 3348396.3 | J53: 3705691.6 | L53: 6 | M53: 6. AC Equipment | T53: =IF(W53>1,EOMONTH(W53,0),"") | U53: 0 | V53: =J53-SUM(U53:U66) -> -0.00054849591 | X53: =SUM(Q53:Q66) -> 1177114.1
B54: 6 | L54: 6 | M54: 6. AC Equipment | N54: AC Board Tie In 1 - SOLAR PVDB 1 | P54: 185475.16 | Q54: =P54 -> 185475.16 | S54: Switchboard - INV 2-SOI001204 | T54: 45535 | U54: 611631.51 | W54: 45589
B55: 6 | L55: 6 | M55: 6. AC Equipment | N55: AC Board Tie In 2 - SOLAR PVDB 2 | P55: 200263.12 | Q55: =P55 -> 200263.12 | S55: Switchboard - INV 2-SOI001204 | T55: 45535 | U55: 660396.98 | W55: =W54 -> 45589
B56: 6 | L56: 6 | M56: 6. AC Equipment | T56: =IF(W56>1,EOMONTH(W56,0),"") | U56: 0
B57: 6 | L57: 6 | M57: 6. AC Equipment | N57: AC Cable - Corrected Tie in | Q57: 53375.87 | R57: PO3613-CAS-20250203 - RV Approved | S57: Luken Inv0618 | T57: 45716 | U57: 22070.738 | W57: 45695
B58: 6 | L58: 6 | M58: 6. AC Equipment | T58: =IF(W58>1,EOMONTH(W58,0),"") | U58: 0
B59: 6 | L59: 6 | M59: 6. AC Equipment | N59: Project Kick Off | O59: =AD46 -> 738000 | P59: 0.1 | Q59: =$O$59*P59 -> 73800 | R59: PO3211-CAS-20240703 | S59: Luken Inv0556 | T59: =IF(W59>1,EOMONTH(W59,0),"") -> 45504 | U59: 243366.31 | W59: =W101 -> 45498
B60: 6 | C60: 3348396.3 | D60: Site Establishment | F60: 0.15 | G60: =$C$60*F60 -> 502259.44 | H60: =H102 -> 45503 | L60: 6 | M60: 6. AC Equipment | N60: Site Establishment | P60: 0.15 | Q60: =$O$59*P60 -> 110700 | S60: Luken Inv0559 | T60: 45504 | U60: 365049.47 | W60: =W102 -> 45512
B61: 6 | D61: AC Installation Complete | F61: 0.2 | G61: =$C$60*F61 -> 669679.26 | H61: =H103 -> 45589 | L61: 6 | M61: 6. AC Equipment | N61: AC Installation Complete | P61: 0.2 | Q61: =$O$59*P61 -> 147600 | S61: Luken Inv0593 | T61: =IF(W61>1,EOMONTH(W61,0),"") -> 45626 | U61: =(Q61/$X$53*$J$53) -> 464661.89 | W61: =W103 -> 45610
B62: 6 | D62: DC Installation Complete | F62: 0.25 | G62: =$C$60*F62 -> 837099.07 | H62: =H104 -> 45593 | L62: 6 | M62: 6. AC Equipment | N62: DC Installation Complete | P62: 0.25 | Q62: =$O$59*P62 -> 184500 | S62: Luken Inv 0576 | T62: 45596 | U62: 608415.78 | W62: =W104 -> 45575
B63: 6 | D63: Commissioning Complete | F63: 0.1 | G63: =$C$60*F63 -> 334839.63 | H63: =H105 -> 45600 | L63: 6 | M63: 6. AC Equipment | N63: Commissioning Complete | P63: 0.1 | Q63: =$O$59*P63 -> 73800 | S63: Luken Inv 0594 | T63: 45626 | U63: 243366.31 | W63: 45617
B64: 6 | D64: Site De-establisment | F64: 0.1 | G64: =$C$60*F64 -> 334839.63 | H64: =H106 -> 45623 | L64: 6 | M64: 6. AC Equipment | N64: Site De-establisment | P64: 0.1 | Q64: =$O$59*P64 -> 73800 | S64: Luken Inv 0595 | T64: 45626 | U64: 243366.31 | W64: 45617
B65: 6 | D65: Handover Document Complete | F65: 0.05 | G65: =$C$60*F65 -> 167419.81 | H65: =H107 -> 45629 | L65: 6 | M65: 6. AC Equipment | N65: Handover Document Complete | P65: 0.05 | Q65: =$O$59*P65 -> 36900 | S65: Luken Inv 0598 | T65: 45626 | U65: 121683.16 | W65: =W107 -> 45631
B66: 6 | D66: End of Defects Period | F66: 0.05 | G66: =$C$60*F66 -> 167419.81 | H66: =H108 -> 45719 | L66: 6 | M66: 6. AC Equipment | N66: End of Defects Period | P66: 0.05 | Q66: =$O$59*P66 -> 36900 | S66: Luken Inv 0599 | T66: 45626 | U66: 121683.16 | W66: =W108 -> 45890
T67: =IF(W67>1,EOMONTH(W67,0),"")
B68: 7 | C68: Battery Systems | I68: =SUM(G68:G75) -> 0 | J68: 0 | L68: 7 | M68: Battery Systems | T68: =IF(W68>1,EOMONTH(W68,0),"") | V68: =J68-SUM(U68:U75) -> 0 | X68: =SUM(Q68:Q75) -> 0
B69: 7 | L69: 7 | T69: =IF(W69>1,EOMONTH(W69,0),"")
B70: 7 | L70: 7 | T70: =IF(W70>1,EOMONTH(W70,0),"")
B71: 7 | L71: 7 | T71: =IF(W71>1,EOMONTH(W71,0),"")
B72: 7 | L72: 7 | T72: =IF(W72>1,EOMONTH(W72,0),"")
B73: 7 | L73: 7 | T73: =IF(W73>1,EOMONTH(W73,0),"")
B74: 7 | L74: 7 | T74: =IF(W74>1,EOMONTH(W74,0),"")
B75: 7 | L75: 7 | T75: =IF(W75>1,EOMONTH(W75,0),"")
T76: =IF(W76>1,EOMONTH(W76,0),"")
B77: 8 | C77: Product Add On | D77: Welcome Bonus | E77: 1 | F77: 255000 | G77: =E77*F77 -> 255000 | H77: =H66 -> 45719 | I77: =SUM(G77:G99) -> 255000 | J77: =282210.132432919+84366 -> 366576.13 | L77: 8 | M77: 8. Product Add On | U77: =(Q77/$X$77*$J$77) -> 0 | V77: =J77-SUM(U77:U99) -> -0.0027259443 | X77: =SUM(Q77:Q99) -> 1488603.7
B78: 8 | L78: 8 | M78: 8. Product Add On | N78: Platform Supports | Q78: 61627.5 | R78: PO3467-CAS-20241119 - RV Approved | S78: Anthony's Steel Inv INA28450 | T78: 45626 | U78: 13306.013 | W78: 45624
B79: 8 | L79: 8 | M79: 8. Product Add On | N79: Steel Work For Both Tie Ins | O79: 0.5 | P79: 260060.56 | Q79: =O79*P79 -> 130030.28 | R79: PO3210-CAS-20240703 | S79: Anthony's Steel: Inv INA28238 | T79: =IF(W79>1,EOMONTH(W79,0),"") -> 45504 | U79: 53875.09 | W79: 45504
L80: 8 | M80: 8. Product Add On | N80: Balance Payable | O80: 0.5 | Q80: =O80*P79 -> 130030.28 | S80: aNThony's Steel: Inv INA28243 | T80: 45504 | U80: 53875.09 | W80: 45624
L81: 8 | M81: 8. Product Add On | N81: Platform Tie In 2 | O81: 0.5 | P81: 291115 | Q81: =O81*P81 -> 145557.5 | R81: PO3512-CAS-20241205 - RV Approved | S81: Anthony's Steel: INV INA28494 | T81: 45657 | U81: 31427.367 | W81: 45638
L82: 8 | M82: 8. Product Add On | N82: Platform Tie In 2 | O82: 0.5 | Q82: =O82*P81 -> 145557.5 | S82: Anthony's Steel INVINA28646 | T82: 45747 | U82: 0 | W82: 45750
L83: 8 | M83: 8. Product Add On | N83: Anchor Points - Active Rope ATS - Deposit | O83: 0.5 | P83: 38068 | Q83: =O83*P83 -> 19034 | R83: PO3262-CAS-20240726 - RV Approved | S83: ATS Africa Inv: INV-0318 | T83: 45504 | U83: 7886.3051 | W83: 45715
L84: 8 | M84: 8. Product Add On | N84: Anchor Points - Active Rope ATS - Balance | O84: 0.5 | Q84: =P83*O84 -> 19034 | S84: ATS Africa Inv: INV-0318 | T84: 45504 | U84: 7886.3051 | W84: =W83 -> 45715
L85: 8 | M85: 8. Product Add On | N85: VO - Anchor Point | T85: 45838 | U85: 84366
L86: 8 | M86: 8. Product Add On | N86: Temp Lifelines | Q86: 38800 | S86: ATS Africa Inv: INV-0337 | T86: 45626 | U86: 0 | W86: 45610
L87: 8 | M87: 8. Product Add On | N87: Panel Clean | Q87: 27281 | R87: PO704-CAS-20241107 - RV Approved | S87: Camperdown Solar Inv INA11114 | T87: 45626 | U87: 4508.7895 | W87: 45631
L88: 8 | M88: 8. Product Add On | N88: Luken Solar AC Cable VO | Q88: 266859.84 | R88: PO3443-CAS-20241031 - RV Approved | S88: Luken Inv0591 | T88: 45596 | U88: 38723.42 | W88: 45610
B89: 8 | L89: 8 | M89: 8. Product Add On | N89: Luken Solar Tie In Breakers | Q89: 68259.15 | R89: PO3455-CAS-20241106 - RV Approved | S89: Luken Inv0592 | T89: 45626 | U89: 15664.615 | W89: 45610
L90: 8 | M90: 8. Product Add On
L91: 8 | M91: 8. Product Add On | O91: 434782.61 | P91: 0.3 | Q91: =$O$91*P91 -> 130434.78 | R91: PO3962-CAS-20250527 - RV Approved | S91: Luken Inv-0648 | T91: 45808 | U91: 13742.769 | W91: 45806
L92: 8 | M92: 8. Product Add On | N92: Luken Corrective Installation - On Completion | P92: 0.6 | Q92: =$O$91*P92 -> 260869.57 | S92: Luken Inv-0651 | T92: 45838 | U92: 41314.37 | W92: 45841
L93: 8 | M93: 8. Product Add On | N93: Luken Corrective Installation - Retention | P93: 0.1 | Q93: =$O$91*P93 -> 43478.261 | S93: Luken Inv-0652 | T93: 45838 | U93: 0 | W93: 46052
L94: 8 | M94: 8. Product Add On
L95: 8 | M95: 8. Product Add On | N95: Repair Damaged Downpipe | Q95: 1750 | R95: PO4206-CAS-20250807 - RV Approved | S95: Anthony's Wedlding - INA28967 | T95: 45900 | W95: 46058
L96: 8 | M96: 8. Product Add On
L97: 8 | M97: 8. Product Add On
L98: 8 | M98: 8. Product Add On
B99: 8 | L99: 8 | M99: 8. Product Add On | T99: =IF(W99>1,EOMONTH(W99,0),"") | U99: =(Q99/$X$77*$J$77) -> 0
K100: Only services to be capture below, products above | T100: =IF(W100>1,EOMONTH(W100,0),"")
B101: 9 | C101: AC & DC Installation | D101: Project Kick Off | F101: 0.1 | G101: =SUM($C$102:$C$103)*F101 -> 128180 | H101: ='Project Plan'!E114-7 -> 45496 | I101: =SUM(G101:G108) -> 1281800 | J101: 1508000 | L101: 9 | M101: 9. AC & DC installation | N101: Project Kick Off | O101: =AC45 -> 1500000 | P101: 0.1 | Q101: =$O$101*P101 -> 150000 | R101: PO3211-CAS-20240703 | S101: Luken Inv0556 | T101: =IF(W101>1,EOMONTH(W101,0),"") -> 45504 | U101: 150800 | V101: 0 | W101: ='Project Plan'!I114-5 -> 45498 | X101: =SUM(Q101:Q108) -> 1500000
B102: 9 | C102: 904400 | D102: Site Establishment | F102: 0.15 | G102: =SUM($C$102:$C$103)*F102 -> 192270 | H102: ='Project Plan'!I114 -> 45503 | L102: 9 | M102: 9. AC & DC installation | N102: Site Establishment | P102: 0.15 | Q102: =$O$101*P102 -> 225000 | S102: Luken Inv 0559 | T102: 45504 | U102: 226200 | W102: 45512
B103: 9 | C103: 377400 | D103: AC Installation Complete | F103: 0.2 | G103: =SUM($C$102:$C$103)*F103 -> 256360 | H103: ='Project Plan'!G116 -> 45589 | L103: 9 | M103: 9. AC & DC installation | N103: AC Installation Complete | P103: 0.2 | Q103: =$O$101*P103 -> 300000 | S103: Luken Inv0593 | T103: =IF(W103>1,EOMONTH(W103,0),"") -> 45626 | U103: 301600 | W103: 45610
...

Sheet Cashflow
D1: [RT: Double Check the first date is always a MONDAY] | F1: 45460 | G1: =F1+7 -> 45467 | H1: =G1+7 -> 45474 | I1: =H1+7 -> 45481 | J1: =I1+7 -> 45488 | K1: =J1+7 -> 45495 | L1: =K1+7 -> 45502 | M1: =L1+7 -> 45509 | N1: =M1+7 -> 45516 | ... DS1: =DR1+7 -> 46279
A2: PLANNED | C2: CHECK | D2: CHECK
B3: Planned Revenue | C3: ='Revenue Tracking'!D4 -> 9650000 | D3: =SUM(F3:CP3) -> 9734366 | F3: =SUMIFS('Revenue Tracking'!$F$13:$F$19, 'Revenue Tracking'!$H$13:$H$19, ">="&F1,'Revenue Tracking'!$H$13:$H$19, "<"&G1) -> 0 | G3: =SUMIFS('Revenue Tracking'!$F$13:$F$19, 'Revenue Tracking'!$H$13:$H$19, ">="&G1,'Revenue Tracking'!$H$13:$H$19, "<"&H1) -> 0 | H3: =SUMIFS('Revenue Tracking'!$F$13:$F$19, 'Revenue Tracking'!$H$13:$H$19, ">="&H1,'Revenue Tracking'!$H$13:$H$19, "<"&I1) -> 0 | I3: =SUMIFS('Revenue Tracking'!$F$13:$F$19, 'Revenue Tracking'!$H$13:$H$19, ">="&I1,'Revenue Tracking'!$H$13:$H$19, "<"&J1) -> 0 | J3: =SUMIFS('Revenue Tracking'!$F$13:$F$19, 'Revenue Tracking'!$H$13:$H$19, ">="&J1,'Revenue Tracking'!$H$13:$H$19, "<"&K1) -> 0 | K3: =SUMIFS('Revenue Tracking'!$F$13:$F$19, 'Revenue Tracking'!$H$13:$H$19, ">="&K1,'Revenue Tracking'!$H$13:$H$19, "<"&L1) -> 0 | L3: =SUMIFS('Revenue Tracking'!$F$13:$F$19, 'Revenue Tracking'!$H$13:$H$19, ">="&L1,'Revenue Tracking'!$H$13:$H$19, "<"&M1) -> 0 | M3: =SUMIFS('Revenue Tracking'!$F$13:$F$19, 'Revenue Tracking'!$H$13:$H$19, ">="&M1,'Revenue Tracking'!$H$13:$H$19, "<"&N1) -> 7237500 | ... DS3: =SUMIFS('Revenue Tracking'!$F$13:$F$19, 'Revenue Tracking'!$H$13:$H$19, ">="&DS1,'Revenue Tracking'!$H$13:$H$19, "<"&DT1) -> 0
B4: Planned Revenue - Cumulative | F4: =F3 -> 0 | G4: =F4+G3 -> 0 | H4: =G4+H3 -> 0 | I4: =H4+I3 -> 0 | J4: =I4+J3 -> 0 | K4: =J4+K3 -> 0 | L4: =K4+L3 -> 0 | M4: =L4+M3 -> 7237500 | N4: =M4+N3 -> 7237500 | ... DS4: =DR4+DS3 -> 9734366
B5: Planned Expenditure | C5: ='Revenue Tracking'!D5 -> 8749927.2 | D5: =SUM(F5:CP5) -> 8749927.2 | F5: =SUMIFS('Expenditure Breakdown'!$G$6:$G$152, 'Expenditure Breakdown'!$H$6:$H$152, ">="&F1,'Expenditure Breakdown'!$H$6:$H$152, "<"&G1) -> 0 | G5: =SUMIFS('Expenditure Breakdown'!$G$6:$G$152, 'Expenditure Breakdown'!$H$6:$H$152, ">="&G1,'Expenditure Breakdown'!$H$6:$H$152, "<"&H1) -> 0 | H5: =SUMIFS('Expenditure Breakdown'!$G$6:$G$152, 'Expenditure Breakdown'!$H$6:$H$152, ">="&H1,'Expenditure Breakdown'!$H$6:$H$152, "<"&I1) -> 0 | I5: =SUMIFS('Expenditure Breakdown'!$G$6:$G$152, 'Expenditure Breakdown'!$H$6:$H$152, ">="&I1,'Expenditure Breakdown'!$H$6:$H$152, "<"&J1) -> 0 | J5: =SUMIFS('Expenditure Breakdown'!$G$6:$G$152, 'Expenditure Breakdown'!$H$6:$H$152, ">="&J1,'Expenditure Breakdown'!$H$6:$H$152, "<"&K1) -> 0 | K5: =SUMIFS('Expenditure Breakdown'!$G$6:$G$152, 'Expenditure Breakdown'!$H$6:$H$152, ">="&K1,'Expenditure Breakdown'!$H$6:$H$152, "<"&L1) -> 463019.63 | L5: =SUMIFS('Expenditure Breakdown'!$G$6:$G$152, 'Expenditure Breakdown'!$H$6:$H$152, ">="&L1,'Expenditure Breakdown'!$H$6:$H$152, "<"&M1) -> 892066.94 | M5: =SUMIFS('Expenditure Breakdown'!$G$6:$G$152, 'Expenditure Breakdown'!$H$6:$H$152, ">="&M1,'Expenditure Breakdown'!$H$6:$H$152, "<"&N1) -> 0 | ... DS5: =SUMIFS('Expenditure Breakdown'!$G$6:$G$152, 'Expenditure Breakdown'!$H$6:$H$152, ">="&DS1,'Expenditure Breakdown'!$H$6:$H$152, "<"&DT1) -> 0
B6: Planned Expenditure - Cumulative | F6: =F5 -> 0 | G6: =F6+G5 -> 0 | H6: =G6+H5 -> 0 | I6: =H6+I5 -> 0 | J6: =I6+J5 -> 0 | K6: =J6+K5 -> 463019.63 | L6: =K6+L5 -> 1355086.6 | M6: =L6+M5 -> 1355086.6 | N6: =M6+N5 -> 1355086.6 | ... DS6: =DR6+DS5 -> 8749927.2
B7: PLANNED CashFlow | F7: =F4-F6 -> 0 | G7: =G4-G6 -> 0 | H7: =H4-H6 -> 0 | I7: =I4-I6 -> 0 | J7: =J4-J6 -> 0 | K7: =K4-K6 -> -463019.63 | L7: =L4-L6 -> -1355086.6 | M7: =M4-M6 -> 5882413.4 | ... DS7: =DS4-DS6 -> 984438.82
A8: ACTUAL | C8: CHECK | D8: CHECK
B9: Actual + Planned Revenue | C9: ='Revenue Tracking'!F4 -> 9734366 | D9: =SUM(F9:CP9) -> 9251866 | F9: =SUMIFS('Revenue Tracking'!$F$13:$F$19, 'Revenue Tracking'!$P$13:$P$19, ">="&F1,'Revenue Tracking'!$P$13:$P$19, "<"&G1) -> 0 | G9: =SUMIFS('Revenue Tracking'!$F$13:$F$19, 'Revenue Tracking'!$P$13:$P$19, ">="&G1,'Revenue Tracking'!$P$13:$P$19, "<"&H1) -> 0 | H9: =SUMIFS('Revenue Tracking'!$F$13:$F$19, 'Revenue Tracking'!$P$13:$P$19, ">="&H1,'Revenue Tracking'!$P$13:$P$19, "<"&I1) -> 0 | I9: =SUMIFS('Revenue Tracking'!$F$13:$F$19, 'Revenue Tracking'!$P$13:$P$19, ">="&I1,'Revenue Tracking'!$P$13:$P$19, "<"&J1) -> 0 | J9: =SUMIFS('Revenue Tracking'!$F$13:$F$19, 'Revenue Tracking'!$P$13:$P$19, ">="&J1,'Revenue Tracking'!$P$13:$P$19, "<"&K1) -> 0 | K9: =SUMIFS('Revenue Tracking'!$F$13:$F$19, 'Revenue Tracking'!$P$13:$P$19, ">="&K1,'Revenue Tracking'!$P$13:$P$19, "<"&L1) -> 1930000 | L9: =SUMIFS('Revenue Tracking'!$F$13:$F$19, 'Revenue Tracking'!$P$13:$P$19, ">="&L1,'Revenue Tracking'!$P$13:$P$19, "<"&M1) -> 0 | M9: =SUMIFS('Revenue Tracking'!$F$13:$F$19, 'Revenue Tracking'!$P$13:$P$19, ">="&M1,'Revenue Tracking'!$P$13:$P$19, "<"&N1) -> 0 | ... DS9: =SUMIFS('Revenue Tracking'!$F$13:$F$19, 'Revenue Tracking'!$P$13:$P$19, ">="&DS1,'Revenue Tracking'!$P$13:$P$19, "<"&DT1) -> 0
B10: Actual + Planned Revenue - Cumulative | F10: =F9 -> 0 | G10: =F10+G9 -> 0 | H10: =G10+H9 -> 0 | I10: =H10+I9 -> 0 | J10: =I10+J9 -> 0 | K10: =J10+K9 -> 1930000 | L10: =K10+L9 -> 1930000 | M10: =L10+M9 -> 1930000 | N10: =M10+N9 -> 1930000 | ... DS10: =DR10+DS9 -> 9734366
B11: Actual + Planned Expenditure | C11: ='Revenue Tracking'!F5 -> 6993121.8 | D11: =SUM(F11:CP11) -> 6983221.8 | F11: =SUMIFS('Expenditure Breakdown'!$Q$6:$Q$152, 'Expenditure Breakdown'!$W$6:$W$152, ">="&F1,'Expenditure Breakdown'!$W$6:$W$152, "<"&G1) -> 0 | G11: =SUMIFS('Expenditure Breakdown'!$Q$6:$Q$152, 'Expenditure Breakdown'!$W$6:$W$152, ">="&G1,'Expenditure Breakdown'!$W$6:$W$152, "<"&H1) -> 0 | H11: =SUMIFS('Expenditure Breakdown'!$Q$6:$Q$152, 'Expenditure Breakdown'!$W$6:$W$152, ">="&H1,'Expenditure Breakdown'!$W$6:$W$152, "<"&I1) -> 11927.09 | I11: =SUMIFS('Expenditure Breakdown'!$Q$6:$Q$152, 'Expenditure Breakdown'!$W$6:$W$152, ">="&I1,'Expenditure Breakdown'!$W$6:$W$152, "<"&J1) -> 0 | J11: =SUMIFS('Expenditure Breakdown'!$Q$6:$Q$152, 'Expenditure Breakdown'!$W$6:$W$152, ">="&J1,'Expenditure Breakdown'!$W$6:$W$152, "<"&K1) -> 0 | K11: =SUMIFS('Expenditure Breakdown'!$Q$6:$Q$152, 'Expenditure Breakdown'!$W$6:$W$152, ">="&K1,'Expenditure Breakdown'!$W$6:$W$152, "<"&L1) -> 240000 | L11: =SUMIFS('Expenditure Breakdown'!$Q$6:$Q$152, 'Expenditure Breakdown'!$W$6:$W$152, ">="&L1,'Expenditure Breakdown'!$W$6:$W$152, "<"&M1) -> 130030.28 | M11: =SUMIFS('Expenditure Breakdown'!$Q$6:$Q$152, 'Expenditure Breakdown'!$W$6:$W$152, ">="&M1,'Expenditure Breakdown'!$W$6:$W$152, "<"&N1) -> 503234.17 | ... DS11: =SUMIFS('Expenditure Breakdown'!$Q$6:$Q$152, 'Expenditure Breakdown'!$W$6:$W$152, ">="&DS1,'Expenditure Breakdown'!$W$6:$W$152, "<"&DT1) -> 0
B12: Actual + Planned Expenditure - Cumulative | F12: =F11 -> 0 | G12: =F12+G11 -> 0 | H12: =G12+H11 -> 11927.09 | I12: =H12+I11 -> 11927.09 | J12: =I12+J11 -> 11927.09 | K12: =J12+K11 -> 251927.09 | L12: =K12+L11 -> 381957.37 | M12: =L12+M11 -> 885191.54 | N12: =M12+N11 -> 885191.54 | ... DS12: =DR12+DS11 -> 6983221.8
B14: ACTUAL CashFlow | F14: =F10-F12 -> 0 | G14: =G10-G12 -> 0 | H14: =H10-H12 -> -11927.09 | I14: =I10-I12 -> -11927.09 | J14: =J10-J12 -> -11927.09 | K14: =K10-K12 -> 1678072.9 | L14: =L10-L12 -> 1548042.6 | M14: =M10-M12 -> 1044808.5 | ... DS14: =DS10-DS12 -> 2751144.2
C16: CHECK | D16: CHECK
B17: Revenue Recognition | C17: =C3-D17 -> -84366.062 | D17: =SUM(F17:CP17) -> 9734366.1 | F17: =SUMIFS('Expenditure Breakdown'!$U$6:$U$152, 'Expenditure Breakdown'!$T$6:$T$152, ">="&F1,'Expenditure Breakdown'!$T$6:$T$152, "<"&G1) -> 0 | G17: =SUMIFS('Expenditure Breakdown'!$U$6:$U$152, 'Expenditure Breakdown'!$T$6:$T$152, ">="&G1,'Expenditure Breakdown'!$T$6:$T$152, "<"&H1) -> 16955.327 | H17: =SUMIFS('Expenditure Breakdown'!$U$6:$U$152, 'Expenditure Breakdown'!$T$6:$T$152, ">="&H1,'Expenditure Breakdown'!$T$6:$T$152, "<"&I1) -> 0 | I17: =SUMIFS('Expenditure Breakdown'!$U$6:$U$152, 'Expenditure Breakdown'!$T$6:$T$152, ">="&I1,'Expenditure Breakdown'!$T$6:$T$152, "<"&J1) -> 0 | J17: =SUMIFS('Expenditure Breakdown'!$U$6:$U$152, 'Expenditure Breakdown'!$T$6:$T$152, ">="&J1,'Expenditure Breakdown'!$T$6:$T$152, "<"&K1) -> 0 | K17: =SUMIFS('Expenditure Breakdown'!$U$6:$U$152, 'Expenditure Breakdown'!$T$6:$T$152, ">="&K1,'Expenditure Breakdown'!$T$6:$T$152, "<"&L1) -> 0 | L17: =SUMIFS('Expenditure Breakdown'!$U$6:$U$152, 'Expenditure Breakdown'!$T$6:$T$152, ">="&L1,'Expenditure Breakdown'!$T$6:$T$152, "<"&M1) -> 1196475.1 | M17: =SUMIFS('Expenditure Breakdown'!$U$6:$U$152, 'Expenditure Breakdown'!$T$6:$T$152, ">="&M1,'Expenditure Breakdown'!$T$6:$T$152, "<"&N1) -> 0 | ... DS17: =SUMIFS('Expenditure Breakdown'!$U$6:$U$152, 'Expenditure Breakdown'!$T$6:$T$152, ">="&DS1,'Expenditure Breakdown'!$T$6:$T$152, "<"&DT1) -> 0
B18: Revenue Recognition Cumulative | C18: =D17-D18 -> 0 | D18: =MAX(F18:CP18) -> 9734366.1 | F18: =F17 -> 0 | G18: =F18+G17 -> 16955.327 | H18: =G18+H17 -> 16955.327 | I18: =H18+I17 -> 16955.327 | J18: =I18+J17 -> 16955.327 | K18: =J18+K17 -> 16955.327 | L18: =K18+L17 -> 1213430.4 | M18: =L18+M17 -> 1213430.4 | N18: =M18+N17 -> 1213430.4 | ... DS18: =DR18+DS17 -> 9734366.1
B20: Installer Expenditure | D20: =SUM(F20:CP20) -> 2400000 | F20: =SUMIFS('Expenditure Breakdown'!$Q$37:$Q$44, 'Expenditure Breakdown'!$W$37:$W$44, ">="&F1,'Expenditure Breakdown'!$W$37:$W$44, "<"&G1)+SUMIFS('Expenditure Breakdown'!$Q$59:$Q$66, 'Expenditure Breakdown'!$W$59:$W$66, ">="&F1,'Expenditure Breakdown'!$W$59:$W$66, "<"&G1)+SUMIFS('Expenditure Breakdown'!$Q$101:$Q$108, 'Expenditure Breakdown'!$W$101:$W$108, ">="&F1,'Expenditure Breakdown'!$W$101:$W$108, "<"&G1) -> 0 | G20: =SUMIFS('Expenditure Breakdown'!$Q$37:$Q$44, 'Expenditure Breakdown'!$W$37:$W$44, ">="&G1,'Expenditure Breakdown'!$W$37:$W$44, "<"&H1)+SUMIFS('Expenditure Breakdown'!$Q$59:$Q$66, 'Expenditure Breakdown'!$W$59:$W$66, ">="&G1,'Expenditure Breakdown'!$W$59:$W$66, "<"&H1)+SUMIFS('Expenditure Breakdown'!$Q$101:$Q$108, 'Expenditure Breakdown'!$W$101:$W$108, ">="&G1,'Expenditure Breakdown'!$W$101:$W$108, "<"&H1) -> 0 | H20: =SUMIFS('Expenditure Breakdown'!$Q$37:$Q$44, 'Expenditure Breakdown'!$W$37:$W$44, ">="&H1,'Expenditure Breakdown'!$W$37:$W$44, "<"&I1)+SUMIFS('Expenditure Breakdown'!$Q$59:$Q$66, 'Expenditure Breakdown'!$W$59:$W$66, ">="&H1,'Expenditure Breakdown'!$W$59:$W$66, "<"&I1)+SUMIFS('Expenditure Breakdown'!$Q$101:$Q$108, 'Expenditure Breakdown'!$W$101:$W$108, ">="&H1,'Expenditure Breakdown'!$W$101:$W$108, "<"&I1) -> 0 | I20: =SUMIFS('Expenditure Breakdown'!$Q$37:$Q$44, 'Expenditure Breakdown'!$W$37:$W$44, ">="&I1,'Expenditure Breakdown'!$W$37:$W$44, "<"&J1)+SUMIFS('Expenditure Breakdown'!$Q$59:$Q$66, 'Expenditure Breakdown'!$W$59:$W$66, ">="&I1,'Expenditure Breakdown'!$W$59:$W$66, "<"&J1)+SUMIFS('Expenditure Breakdown'!$Q$101:$Q$108, 'Expenditure Breakdown'!$W$101:$W$108, ">="&I1,'Expenditure Breakdown'!$W$101:$W$108, "<"&J1) -> 0 | J20: =SUMIFS('Expenditure Breakdown'!$Q$37:$Q$44, 'Expenditure Breakdown'!$W$37:$W$44, ">="&J1,'Expenditure Breakdown'!$W$37:$W$44, "<"&K1)+SUMIFS('Expenditure Breakdown'!$Q$59:$Q$66, 'Expenditure Breakdown'!$W$59:$W$66, ">="&J1,'Expenditure Breakdown'!$W$59:$W$66, "<"&K1)+SUMIFS('Expenditure Breakdown'!$Q$101:$Q$108, 'Expenditure Breakdown'!$W$101:$W$108, ">="&J1,'Expenditure Breakdown'!$W$101:$W$108, "<"&K1) -> 0 | K20: =SUMIFS('Expenditure Breakdown'!$Q$37:$Q$44, 'Expenditure Breakdown'!$W$37:$W$44, ">="&K1,'Expenditure Breakdown'!$W$37:$W$44, "<"&L1)+SUMIFS('Expenditure Breakdown'!$Q$59:$Q$66, 'Expenditure Breakdown'!$W$59:$W$66, ">="&K1,'Expenditure Breakdown'!$W$59:$W$66, "<"&L1)+SUMIFS('Expenditure Breakdown'!$Q$101:$Q$108, 'Expenditure Breakdown'!$W$101:$W$108, ">="&K1,'Expenditure Breakdown'!$W$101:$W$108, "<"&L1) -> 240000 | L20: =SUMIFS('Expenditure Breakdown'!$Q$37:$Q$44, 'Expenditure Breakdown'!$W$37:$W$44, ">="&L1,'Expenditure Breakdown'!$W$37:$W$44, "<"&M1)+SUMIFS('Expenditure Breakdown'!$Q$59:$Q$66, 'Expenditure Breakdown'!$W$59:$W$66, ">="&L1,'Expenditure Breakdown'!$W$59:$W$66, "<"&M1)+SUMIFS('Expenditure Breakdown'!$Q$101:$Q$108, 'Expenditure Breakdown'!$W$101:$W$108, ">="&L1,'Expenditure Breakdown'!$W$101:$W$108, "<"&M1) -> 0 | M20: =SUMIFS('Expenditure Breakdown'!$Q$37:$Q$44, 'Expenditure Breakdown'!$W$37:$W$44, ">="&M1,'Expenditure Breakdown'!$W$37:$W$44, "<"&N1)+SUMIFS('Expenditure Breakdown'!$Q$59:$Q$66, 'Expenditure Breakdown'!$W$59:$W$66, ">="&M1,'Expenditure Breakdown'!$W$59:$W$66, "<"&N1)+SUMIFS('Expenditure Breakdown'!$Q$101:$Q$108, 'Expenditure Breakdown'!$W$101:$W$108, ">="&M1,'Expenditure Breakdown'!$W$101:$W$108, "<"&N1) -> 360000 | ... DS20: =SUMIFS('Expenditure Breakdown'!$Q$37:$Q$44, 'Expenditure Breakdown'!$W$37:$W$44, ">="&DS1,'Expenditure Breakdown'!$W$37:$W$44, "<"&DT1)+SUMIFS('Expenditure Breakdown'!$Q$59:$Q$66, 'Expenditure Breakdown'!$W$59:$W$66, ">="&DS1,'Expenditure Breakdown'!$W$59:$W$66, "<"&DT1)+SUMIFS('Expenditure Breakdown'!$Q$101:$Q$108, 'Expenditure Breakdown'!$W$101:$W$108, ">="&DS1,'Expenditure Breakdown'!$W$101:$W$108, "<"&DT1) -> 0
B21: Installer Expenditure - Cumulative | F21: =F20 -> 0 | G21: =G20+F21 -> 0 | H21: =H20+G21 -> 0 | I21: =I20+H21 -> 0 | J21: =J20+I21 -> 0 | K21: =K20+J21 -> 240000 | L21: =L20+K21 -> 240000 | M21: =M20+L21 -> 600000 | N21: =N20+M21 -> 600000 | ... DS21: =DS20+DR21 -> 2400000

Sheet Finance - COS
A3: Sum of Actual Total | B3: Column Labels
A4: Row Labels | B4: (blank) | C4: 45473 | D4: 45504 | E4: 45535 | F4: 45565 | G4: 45596 | H4: 45626 | I4: 45657 | J4: 45688 | K4: 45716 | M4: 45747 | N4: 45777 | O4: 45808 | P4: 45838 | Q4: 45869 | R4: 45900 | S4: 45991 | T4: Grand Total
A5: Battery Systems
A6: BDP Commission | E6: 264727.3 | T6: 264727.3
A7: (blank)
A8: 1. Panels
A9: 2. Inverters | E9: 757680 | T9: 757680
A10: 3. Mounting Structures | E10: 364557.56 | F10: 14477.25 | G10: 11908 | K10: 9366 | N10: 2352.38 | O10: 200591.6 | P10: 8654.28 | Q10: 10295.19 | S10: -3017.39 | T10: 619184.87
A11: 4. DC Equipment | D11: 40500 | E11: 647745 | G11: 40500 | H11: 81450 | T11: 810195
A12: 5. Monitoring | E12: 24770 | G12: 0 | J12: 3710 | T12: 28480
A13: 6. AC Equipment | D13: 184500 | E13: 385738.28 | G13: 184500 | H13: 369000 | K13: 53375.87 | T13: 1177114.2
A14: 8. Product Add On | D14: 298128.56 | G14: 266859.84 | H14: 195967.65 | I14: 145557.5 | M14: 145557.5 | O14: 130434.78 | P14: 304347.83 | R14: 1750 | T14: 1488603.7
A15: 9. AC & DC installation | D15: 375000 | G15: 375000 | H15: 750000 | T15: 1500000
A16: 10. Site Logistics | E16: 22200 | G16: 2194.2 | T16: 24394.2
A17: 11. Due Dilligence | B17: 0 | C17: 17100 | D17: 9500 | H17: 26800 | O17: 63200 | P17: 0 | T17: 116600
A18: 13. Engineering | H18: 120625 | T18: 120625
A19: 14. General Expenses | C19: 11927.09 | D19: 1370.52 | E19: 20912.77 | F19: 11749.01 | G19: 10391.33 | H19: 7950.72 | I19: 1766.96 | J19: 10295.2 | K19: 0 | M19: 0 | N19: 9154.01 | R19: 0 | T19: 85517.61
A20: 15. Service Add On | O20: 7200 | T20: 7200
A21: Grand Total | B21: 0 | C21: 29027.09 | D21: 908999.08 | E21: 2488330.9 | F21: 26226.26 | G21: 891353.37 | H21: 1551793.4 | I21: 147324.46 | J21: 14005.2 | K21: 62741.87 | M21: 145557.5 | N21: 11506.39 | O21: 401426.38 | P21: 313002.11 | Q21: 10295.19 | R21: 1750 | S21: -3017.39 | T21: 7000321.8
C23: =SUM(C21:E21) -> 3426357.1
C25: ='Revenue Tracking'!R10 -> 0
C27: =C23-C25 -> 3426357.1

Sheet Finance - Revenue
A1: REVENUE RECOGNITION AMOUNT | B1: (All)
A3: Sum of REVENUE RECOGNITION AMOUNT | B3: Column Labels
A4: Row Labels | C4: (blank) | D4: 45473 | E4: 45504 | F4: 45535 | G4: 45565 | H4: 45596 | I4: 45626 | J4: 45657 | K4: 45688 | L4: 45716 | M4: 45747 | N4: 45777 | O4: 45808 | P4: 45838 | Q4: 45869 | R4: 45900 | S4: 45991 | T4: Grand Total
A5: (blank)
A6: Battery Systems
A7: BDP Commission
A8: 1. Panels
A9: 2. Inverters | F9: 956194.33 | T9: 956194.33
A10: 3. Mounting Structures | F10: 723092.46 | G10: 16828.079 | H10: 11887.248 | L10: 0 | N10: 0 | T10: 751807.79
A11: 4. DC Equipment | E11: 78828.942 | F11: 1186399.1 | H11: 86641.006 | I11: 150260.22 | T11: 1502129.3
A12: 5. Monitoring | B12: 0 | C12: 0 | F12: 11215.185 | H12: 43013.43 | K12: 0 | T12: 54228.615
A13: 6. AC Equipment | B13: 0 | E13: 608415.78 | F13: 1272028.5 | H13: 608415.78 | I13: 1194760.8 | L13: 22070.738 | T13: 3705691.6
A14: 8. Product Add On | B14: 0 | C14: 0 | E14: 123522.79 | H14: 38723.42 | I14: 33479.418 | J14: 31427.367 | M14: 0 | O14: 13742.769 | P14: 125680.37 | T14: 366576.14 | U14: =SUM(T8:T14) -> 7336627.8
A15: 9. AC & DC installation | E15: 377000 | H15: 377000 | I15: 754000 | T15: 1508000
A16: 10. Site Logistics | B16: 0 | C16: 0 | F16: 265082.89 | H16: 358220.12 | T16: 623303
A17: 11. Due Dilligence | C17: 0 | D17: 14411.289 | E17: 8403.1278 | I17: 35385.756 | O17: 96604.812 | P17: 80747.96 | T17: 235552.94
A18: 13. Engineering
A19: 14. General Expenses | D19: 2544.0381 | E19: 304.4695 | F19: 5665.4689 | G19: 2937.86 | H19: 10206.25 | I19: 3217.9857 | J19: 801.66248 | K19: 3956.2688 | L19: 0 | M19: 0 | N19: 1248.3503 | R19: 0 | T19: 30882.354
A20: 15. Service Add On
A21: Grand Total | B21: 0 | C21: 0 | D21: 16955.327 | E21: 1196475.1 | F21: 4419677.9 | G21: 19765.939 | H21: 1534107.3 | I21: 2171104.2 | J21: 32229.029 | K21: 3956.2688 | L21: 22070.738 | M21: 0 | N21: 1248.3503 | O21: 110347.58 | P21: 206428.33 | R21: 0 | T21: 9734366.1
D23: =SUM(D21:F21) -> 5633108.4
R27: =R24-GETPIVOTDATA("REVENUE RECOGNITION AMOUNT",$A$3) -> -9734366.1

Sheet Certificate - Financial Close
B2: Emergent Energy – Financial Close Completion Certificate | H2: FINANCIAL CLOSE CERTIFICATE
B4: Project Name: | C4: ='Project Plan'!E2 -> Cascades Lifestyle Center
B5: COO: | C5: Johannes Potgieter
B6: Programme Manager: | C6: Roedolph Venter
B7: HoPD: | C7: Natasha Watkins-Baker
B9: Date of Phase Completion: | F9: {=_xlfn.LET(_xlpm.w,$B$10:$B$54,_xlpm.r,$M$10:$M$54,_xlpm.v,IF(ISNUMBER(_xlpm.r),_xlpm.r,IFERROR(VALUE(SUBSTITUTE(_xlpm.r,"%",""))/100,0)),_xlpm.g,IFERROR(VALUE(LEFT(_xlpm.w,1)),0),_xlpm.bdOnly,(SUMPRODUCT((_xlpm.w="1.1")*(_xlpm.v>0))>0)*(SUMPRODUCT((_xlpm.w<>"1.1")*(_xlpm.v>0))=0),_xlpm.anyConstr,SUMPRODUCT((_xlpm.g>=2)*(_xlpm.g<=6)*(_xlpm.v>0))>0,_xlpm.anyQA,SUMPRODUCT((_xlpm.g=7)*(_xlpm.v>0))>0,_xlpm.anyHO,SUMPRODUCT((_xlpm.g=8)*(_xlpm.v>0))>0,_xlpm.anyPlan,SUMPRODUCT((_xlpm.g=1)*(_xlpm.v>0))>0,IF(_xlpm.bdOnly,"1. Financial Close",IF(_xlpm.anyConstr,"3. Construction",IF(_xlpm.anyQA,"4. QA",IF(_xlpm.anyHO,"5. Handover",IF(_xlpm.anyPlan,"2. Planning","1. Financial Close"))))))} -> 1. Financial Close | G9: {=_xlfn.LET(_xlpm.w,$B$10:$B$54,_xlpm.r,$N$10:$N$54,_xlpm.v,IF(ISNUMBER(_xlpm.r),_xlpm.r,IFERROR(VALUE(SUBSTITUTE(_xlpm.r,"%",""))/100,0)),_xlpm.g,IFERROR(VALUE(LEFT(_xlpm.w,1)),0),_xlpm.bdOnly,(SUMPRODUCT((_xlpm.w="1.1")*(_xlpm.v>0))>0)*(SUMPRODUCT((_xlpm.w<>"1.1")*(_xlpm.v>0))=0),_xlpm.anyConstr,SUMPRODUCT((_xlpm.g>=2)*(_xlpm.g<=6)*(_xlpm.v>0))>0,_xlpm.anyQA,SUMPRODUCT((_xlpm.g=7)*(_xlpm.v>0))>0,_xlpm.anyHO,SUMPRODUCT((_xlpm.g=8)*(_xlpm.v>0))>0,_xlpm.anyPlan,SUMPRODUCT((_xlpm.g=1)*(_xlpm.v>0))>0,IF(_xlpm.bdOnly,"1. Financial Close",IF(_xlpm.anyConstr,"3. Construction",IF(_xlpm.anyQA,"4. QA",IF(_xlpm.anyHO,"5. Handover",IF(_xlpm.anyPlan,"2. Planning","1. Financial Close"))))))} -> 1. Financial Close
B10: Phase Deliverables Checklist: (Y/N)
B11: Product Agreement | C11: NA
B12: EPC Agreement | C12: NA
B13: O&M Agreeement | C13: NA
B14: Cost Proposal | C14: Signed
B15: Deposit Received | C15: Yes
B16: Risks / Notes | C16: None
B18: Acknowledgement and Acceptance:
B19: Role | C19: Name | D19: Signature | E19: Date
B20: COO | C20: Johannes | D20: JTP | E20: 45953

Sheet Project Margins
A1: [capture project margins from costing sheet]
A3: Products | D3: 0.32
A4: Services | D4: 0.5
A5: Expenses | D5: 0.15
A6: Subcontractors | D6: 0.2

Sheet Equipment Quotes
B2: Equipment Quote and Budget comparision
B4: Description | D4: Budget | F4: Supplier 1 | H4: Variance | J4: Supplier 2 | L4: Variance | N4: Comments / Notes
F7: >Name< | J7: >Name<
B9: Inverters | D9: =SUM(D10:D11) -> 864000 | F9: =SUM(F10:F13) -> 0 | H9: =$D$9-F9 -> 864000 | J9: =SUM(J10:J13) -> 0 | L9: =$D$9-J9 -> 864000
B10: Inverters | D10: ='Expenditure Breakdown'!G13 -> 864000
B11: Optimizers | D11: ='Expenditure Breakdown'!G14 -> 0
B12: Warranty
B13: Delivery fee
F15: >Name< | J15: >Name<
B17: Mounting Structure | D17: =SUM(D18:D19) -> 679320 | F17: =SUM(F18:F20) -> 0 | H17: =$D$17- F17 -> 679320 | J17: =SUM(J18:J20) -> 0 | L17: =$D$17- J17 -> 679320
B18: Mounting Structure | D18: ='Expenditure Breakdown'!G18 -> 679320
B19: Delivery fee
F21: >Name< | J21: >Name<
B23: DC Cable | D23: =SUM(D24:D25) -> 600160 | F23: =SUM(F24:F25) -> 0 | H23: =$D$23- F23 -> 600160 | J23: =SUM(J24:J25) -> 0 | L23: =$D$23- J23 -> 600160
B24: DC Cable | D24: ='Expenditure Breakdown'!G32 -> 600160
B25: Delivery fee
F27: >Name< | J27: >Name<
B29: Monitoring system | D29: =SUM(D30:D32) -> #REF! | F29: =SUM(F30:F42) -> 0 | H29: =$D$29-F29 -> #REF! | J29: =SUM(J30:J32) -> 0 | L29: =$D$29-J29 -> #REF!
B30: ='Expenditure Breakdown'!D46 -> Smartlogger 3000 | D30: ='Expenditure Breakdown'!G46 -> 26000
B31: ='Expenditure Breakdown'!#REF! -> #REF! | D31: ='Expenditure Breakdown'!#REF! -> #REF!
B32: Delivery fee
F34: >Name< | J34: >Name<
B36: Additional Scope | D36: =SUM(D37:D41) -> 255000 | F36: =SUM(F37:F41) -> 0 | H36: =$D$29-F36 -> #REF! | J36: =SUM(J37:J41) -> 0 | L36: =$D$29-J36 -> #REF!
B37: SCADA | D37: ='Expenditure Breakdown'!G77 -> 255000
B38: Inverter cage
B39: Cat ladders
B40: Gen Integration
B41: Lifelines
B43: Totals | D43: =D36+D29+D23+D17+D9 -> #REF! | H43: =SUM(H7:H42) -> #REF! | L43: =SUM(L7:L42) -> #REF!
B47: All amounts are incl VAT

Sheet Installer Quotes
B2: Installer Quote and Budget comparision
B4: Description | D4: Budget | G4: Cosmic Sun | J4: Variance | L4: Matthews Group | O4: Variance
B6: AC Equipment | D6: ='Expenditure Breakdown'!AA8 -> 3348396.3 | E6: =D6/(1000*'Project Plan'!$E$3) -> 2.217481 | G6: 277892.91 | H6: =G6/('Project Plan'!$E$3*1000) -> 0.18403504 | J6: =D6-G6 -> 3070503.4 | M6: =L6/('Project Plan'!$E$3*1000) -> 0 | O6: =D6-L6 -> 3348396.3
B7: DC Equipment | D7: ='Expenditure Breakdown'!AA9 -> 757137 | E7: =D7/(1000*'Project Plan'!$E$3) -> 0.50141523 | G7: 142158.25 | H7: =G7/('Project Plan'!$E$3*1000) -> 0.094144536 | J7: =D7-G7 -> 614978.75 | M7: =L7/('Project Plan'!$E$3*1000) -> 0 | O7: =D7-L7 -> 757137
B8: AC Labour | D8: ='Expenditure Breakdown'!AA10 -> 377400 | E8: =D8/(1000*'Project Plan'!$E$3) -> 0.24993377 | G8: 96174 | H8: =G8/('Project Plan'!$E$3*1000) -> 0.063691391 | J8: =D8-G8 -> 281226 | M8: =L8/('Project Plan'!$E$3*1000) -> 0 | O8: =D8-L8 -> 377400
B9: DC Labour | D9: ='Expenditure Breakdown'!AA11 -> 904400 | E9: =D9/(1000*'Project Plan'!$E$3) -> 0.5989404 | G9: 230160 | H9: =G9/('Project Plan'!$E$3*1000) -> 0.15242384 | J9: =D9-G9 -> 674240 | M9: =L9/('Project Plan'!$E$3*1000) -> 0 | O9: =D9-L9 -> 904400
B10: Offloading | D10: ='Expenditure Breakdown'!AA12 -> 8500 | G10: 0 | J10: =D10-G10 -> 8500 | O10: =D10-L10 -> 8500
B11: Roof Access/Scaffolding | D11: ='Expenditure Breakdown'!AA13 -> 115057.5 | G11: 29257.61 | J11: =D11-G11 -> 85799.89 | O11: =D11-L11 -> 115057.5
B12: Storage | D12: ='Expenditure Breakdown'!AA14 -> 46250 | J12: =D12-G12 -> 46250 | O12: =D12-L12 -> 46250
B13: Telehandler | D13: ='Expenditure Breakdown'!AA15 -> 0
B14: HSE | D14: 0
B15: Totals | D15: =SUM(D6:D13) -> 5557140.8 | G15: =SUM(G6:G13) -> 775642.77 | J15: =SUM(J6:J14) -> 4781498 | L15: =SUM(L6:L13) -> 0 | O15: =SUM(O6:O14) -> 5557140.8
B18: Description | D18: Budget | G18: >Installer Name 3< | J18: Variance | L18: >Installer Name 4< | O18: Variance
B20: AC installation | D20: ='Expenditure Breakdown'!#REF! -> #REF! | E20: =D20/(1000*'Project Plan'!$E$3) -> #REF! | H20: =G20/(1000*'Project Plan'!$E$3) -> 0 | J20: =D20-G20 -> #REF! | M20: =L20/(1000*'Project Plan'!$E$3) -> 0 | O20: =D6-L20 -> 3348396.3
B21: AC equipment | D21: ='Expenditure Breakdown'!C66 -> 0 | E21: =D21/(1000*'Project Plan'!$E$3) -> 0 | J21: =D21-G21 -> 0 | M21: =L21/(1000*'Project Plan'!$E$3) -> 0 | O21: =D7-L21 -> 757137
B22: DC installation | D22: ='Expenditure Breakdown'!#REF! -> #REF! | E22: =D22/(1000*'Project Plan'!$E$3) -> #REF! | H22: =G22/(1000*'Project Plan'!$E$3) -> 0 | J22: =D22-G22 -> #REF! | M22: =L22/(1000*'Project Plan'!$E$3) -> 0 | O22: =D8-L22 -> 377400
B23: DC equipment | D23: =SUM('Expenditure Breakdown'!G42:G43) -> 506385 | E23: =D23/(1000*'Project Plan'!$E$3) -> 0.3353543 | J23: =D23-G23 -> 506385 | O23: =D9-L23 -> 904400
B24: Storage | D24: ='Expenditure Breakdown'!G123 -> 0 | J24: =D24-G24 -> 0 | O24: =D10-L24 -> 8500
B25: Panel lifting equipment | D25: =SUM('Expenditure Breakdown'!G110:G112) -> 169807.5 | J25: =D25-G25 -> 169807.5 | O25: =D11-L25 -> 115057.5
B26: Offloading | D26: ='Expenditure Breakdown'!G114 -> 0 | J26: =D26-G26 -> 0 | O26: =D12-L26 -> 46250
B29: Totals | D29: =SUM(D20:D27) -> #REF! | G29: =SUM(G20:G27) -> 0 | J29: =SUM(J20:J28) -> #REF! | L29: =SUM(L20:L27) -> 0 | O29: =SUM(O20:O28) -> 5557140.8
B32: Budget Summary
B34: Budget | D34: =D15 -> 5557140.8
B35: =G4 -> Cosmic Sun | D35: =G15 -> 775642.77
B36: =L4 -> Matthews Group | D36: =L15 -> 0
B37: =G18 -> >Installer Name 3< | D37: =G29 -> 0
B38: =L18 -> >Installer Name 4< | D38: =L29 -> 0
B40: =IF(D40<D34,"Saving","Loss") -> Loss | D40: =D34-MIN(D35:D38) -> 5557140.8
B42: All amounts are exc VAT

Sheet Decision Register
B1: =D15 -> Cascades Lifestyle Center | E1: Decision Register
B3: ID | C3: Decision Description | D3: Decision Impact | E3: Proposed Date | F3: Proposed By | G3: Status | H3: Approved By | I3: Date | J3: Results / Comments
B4: DEC001
B5: DEC002
B6: DEC003
B7: DEC004
B8: DEC005
B9: DEC006
B10: DEC007
B11: DEC008
B12: DEC009
B13: DEC010
D15: {='Project Plan'!E2:H2} -> Cascades Lifestyle Center | E15: 0 | F15: 0 | G15: 0
