Workbook
Name Inverter_Capacity: #REF!
Name Inverter_Supplier: #REF!
Name Project_Size: 'Certificate - Financial Close'!Projectsize
Name Project_Size: 'Finance - Revenue'!Projectsize
Name Project_Size: Projectsize
Name Projectsize: #REF!
Name Projectsize: #REF!
Name Projectsize: 'Project Margins'!$K$5
Name Security_Serv: #REF!
Name Security_Serv: #REF!
Name SSS: #REF!
Name SSS: #REF!
Name USD_ZAR: #REF!

Sheet Sheet1
A1: PROJECT PLAN
A2: # | B2: Project Milestone | C2: Planned Start Date | D2: Duration (Work Days) | E2: Planned End Date | F2: Actual Start Date | H2: Actual End Date | J2: Comments | L2: =C3 -> 43831 | M2: =L2+3 -> 43834 | N2: =M2+7 -> 43841 | O2: =N2+7 -> 43848 | P2: =O2+7 -> 43855 | Q2: =P2+6 -> 43861 | R2: =Q2+1 -> 43862 | S2: =R2+7 -> 43869 | T2: =S2+7 -> 43876 | U2: =T2+7 -> 43883 | V2: =U2+6 -> 43889 | W2: =V2+7 -> 43896 | X2: =W2+7 -> 43903 | Y2: =X2+7 -> 43910 | Z2: =Y2+7 -> 43917 | AA2: =Z2+3 -> 43920 | AB2: =AA2+4 -> 43924 | AC2: =AB2+7 -> 43931 | AD2: =AC2+7 -> 43938 | AE2: =AD2+7 -> 43945 | AF2: =AE2+6 -> 43951 | AG2: =AF2+2 -> 43953 | AH2: =AG2+7 -> 43960 | AI2: =AH2+7 -> 43967 | AJ2: =AI2+7 -> 43974 | AK2: =AJ2+7 -> 43981 | AL2: =AK2+1 -> 43982 | AM2: =AL2+6 -> 43988 | AN2: =AM2+7 -> 43995 | AO2: =AN2+7 -> 44002 | AP2: =AO2+7 -> 44009 | AQ2: =AP2+3 -> 44012 | AR2: =AQ2+4 -> 44016 | AS2: =AR2+7 -> 44023 | AT2: =AS2+7 -> 44030 | AU2: =AT2+7 -> 44037 | AV2: =AU2+6 -> 44043 | AW2: =AV2+1 -> 44044 | AX2: =AW2+7 -> 44051 | AY2: =AX2+7 -> 44058 | AZ2: =AY2+7 -> 44065 | BA2: =AZ2+7 -> 44072 | BB2: =BA2+2 -> 44074 | BC2: =BB2+5 -> 44079 | BD2: =BC2+7 -> 44086 | BE2: =BD2+7 -> 44093 | BF2: =BE2+7 -> 44100 | BG2: =BF2+4 -> 44104
A3: 1 | B3: Contract Signature | C3: 43831 | D3: 1 | E3: 43832 | F3: 43831 | G3: 1 | H3: 43832 | L3: =IF(AND($F3<(L$2+7),$F3>L$2),1, IF(AND($H3<L$2+7,$H3>L$2),3, IF(AND($F3<=L$2, $H3>=L$2), 2, "" ))) -> 3 | M3: =IF(AND($F3<(M$2+7),$F3>M$2),1, IF(AND($H3<M$2+7,$H3>M$2),3, IF(AND($F3<=M$2, $H3>=M$2), 2, "" ))) | N3: =IF(AND($F3<(N$2+7),$F3>N$2),1, IF(AND($H3<N$2+7,$H3>N$2),3, IF(AND($F3<=N$2, $H3>=N$2), 2, "" ))) | O3: =IF(AND($F3<(O$2+7),$F3>O$2),1, IF(AND($H3<O$2+7,$H3>O$2),3, IF(AND($F3<=O$2, $H3>=O$2), 2, "" ))) | P3: =IF(AND($F3<(P$2+7),$F3>P$2),1, IF(AND($H3<P$2+7,$H3>P$2),3, IF(AND($F3<=P$2, $H3>=P$2), 2, "" ))) | Q3: =IF(AND($F3<(Q$2+7),$F3>Q$2),1, IF(AND($H3<Q$2+7,$H3>Q$2),3, IF(AND($F3<=Q$2, $H3>=Q$2), 2, "" ))) | R3: =IF(AND($F3<(R$2+7),$F3>R$2),1, IF(AND($H3<R$2+7,$H3>R$2),3, IF(AND($F3<=R$2, $H3>=R$2), 2, "" ))) | S3: =IF(AND($F3<(S$2+7),$F3>S$2),1, IF(AND($H3<S$2+7,$H3>S$2),3, IF(AND($F3<=S$2, $H3>=S$2), 2, "" ))) | ... AQ3: =IF(AND($F3<(AQ$2+7),$F3>AQ$2),1, IF(AND($H3<AQ$2+7,$H3>AQ$2),3, IF(AND($F3<=AQ$2, $H3>=AQ$2), 2, "" )))
A4: A | B4: PAYMENT MILESTONE 1: DEPOSIT | C4: 43832 | D4: 1 | E4: 43833 | F4: 43832 | G4: 1 | H4: 43833 | L4: =IF(AND($F4<(L$2+7),$F4>L$2),1, IF(AND($H4<L$2+7,$H4>L$2),3, IF(AND($F4<=L$2, $H4>=L$2), 2, "" ))) -> 1 | M4: =IF(AND($F4<(M$2+7),$F4>M$2),1, IF(AND($H4<M$2+7,$H4>M$2),3, IF(AND($F4<=M$2, $H4>=M$2), 2, "" ))) | N4: =IF(AND($F4<(N$2+7),$F4>N$2),1, IF(AND($H4<N$2+7,$H4>N$2),3, IF(AND($F4<=N$2, $H4>=N$2), 2, "" ))) | O4: =IF(AND($F4<(O$2+7),$F4>O$2),1, IF(AND($H4<O$2+7,$H4>O$2),3, IF(AND($F4<=O$2, $H4>=O$2), 2, "" ))) | P4: =IF(AND($F4<(P$2+7),$F4>P$2),1, IF(AND($H4<P$2+7,$H4>P$2),3, IF(AND($F4<=P$2, $H4>=P$2), 2, "" ))) | Q4: =IF(AND($F4<(Q$2+7),$F4>Q$2),1, IF(AND($H4<Q$2+7,$H4>Q$2),3, IF(AND($F4<=Q$2, $H4>=Q$2), 2, "" ))) | R4: =IF(AND($F4<(R$2+7),$F4>R$2),1, IF(AND($H4<R$2+7,$H4>R$2),3, IF(AND($F4<=R$2, $H4>=R$2), 2, "" ))) | S4: =IF(AND($F4<(S$2+7),$F4>S$2),1, IF(AND($H4<S$2+7,$H4>S$2),3, IF(AND($F4<=S$2, $H4>=S$2), 2, "" ))) | ... AQ4: =IF(AND($F4<(AQ$2+7),$F4>AQ$2),1, IF(AND($H4<AQ$2+7,$H4>AQ$2),3, IF(AND($F4<=AQ$2, $H4>=AQ$2), 2, "" )))
A5: 2 | B5: Structural and Electrical Due Diligences | C5: 43833 | D5: 5 | E5: 43840 | F5: 43833 | G5: 5 | H5: 43840 | L5: =IF(AND($F5<(L$2+7),$F5>L$2),1, IF(AND($H5<L$2+7,$H5>L$2),3, IF(AND($F5<=L$2, $H5>=L$2), 2, "" ))) -> 1 | M5: =IF(AND($F5<(M$2+7),$F5>M$2),1, IF(AND($H5<M$2+7,$H5>M$2),3, IF(AND($F5<=M$2, $H5>=M$2), 2, "" ))) -> 3 | N5: =IF(AND($F5<(N$2+7),$F5>N$2),1, IF(AND($H5<N$2+7,$H5>N$2),3, IF(AND($F5<=N$2, $H5>=N$2), 2, "" ))) | O5: =IF(AND($F5<(O$2+7),$F5>O$2),1, IF(AND($H5<O$2+7,$H5>O$2),3, IF(AND($F5<=O$2, $H5>=O$2), 2, "" ))) | P5: =IF(AND($F5<(P$2+7),$F5>P$2),1, IF(AND($H5<P$2+7,$H5>P$2),3, IF(AND($F5<=P$2, $H5>=P$2), 2, "" ))) | Q5: =IF(AND($F5<(Q$2+7),$F5>Q$2),1, IF(AND($H5<Q$2+7,$H5>Q$2),3, IF(AND($F5<=Q$2, $H5>=Q$2), 2, "" ))) | R5: =IF(AND($F5<(R$2+7),$F5>R$2),1, IF(AND($H5<R$2+7,$H5>R$2),3, IF(AND($F5<=R$2, $H5>=R$2), 2, "" ))) | S5: =IF(AND($F5<(S$2+7),$F5>S$2),1, IF(AND($H5<S$2+7,$H5>S$2),3, IF(AND($F5<=S$2, $H5>=S$2), 2, "" ))) | ... AQ5: =IF(AND($F5<(AQ$2+7),$F5>AQ$2),1, IF(AND($H5<AQ$2+7,$H5>AQ$2),3, IF(AND($F5<=AQ$2, $H5>=AQ$2), 2, "" )))
A6: 3 | B6: Design Confirmation | C6: 43841 | D6: 2 | E6: 43844 | F6: 43841 | G6: 2 | H6: 43844 | L6: =IF(AND($F6<(L$2+7),$F6>L$2),1, IF(AND($H6<L$2+7,$H6>L$2),3, IF(AND($F6<=L$2, $H6>=L$2), 2, "" ))) | M6: =IF(AND($F6<(M$2+7),$F6>M$2),1, IF(AND($H6<M$2+7,$H6>M$2),3, IF(AND($F6<=M$2, $H6>=M$2), 2, "" ))) | N6: =IF(AND($F6<(N$2+7),$F6>N$2),1, IF(AND($H6<N$2+7,$H6>N$2),3, IF(AND($F6<=N$2, $H6>=N$2), 2, "" ))) -> 3 | O6: =IF(AND($F6<(O$2+7),$F6>O$2),1, IF(AND($H6<O$2+7,$H6>O$2),3, IF(AND($F6<=O$2, $H6>=O$2), 2, "" ))) | P6: =IF(AND($F6<(P$2+7),$F6>P$2),1, IF(AND($H6<P$2+7,$H6>P$2),3, IF(AND($F6<=P$2, $H6>=P$2), 2, "" ))) | Q6: =IF(AND($F6<(Q$2+7),$F6>Q$2),1, IF(AND($H6<Q$2+7,$H6>Q$2),3, IF(AND($F6<=Q$2, $H6>=Q$2), 2, "" ))) | R6: =IF(AND($F6<(R$2+7),$F6>R$2),1, IF(AND($H6<R$2+7,$H6>R$2),3, IF(AND($F6<=R$2, $H6>=R$2), 2, "" ))) | S6: =IF(AND($F6<(S$2+7),$F6>S$2),1, IF(AND($H6<S$2+7,$H6>S$2),3, IF(AND($F6<=S$2, $H6>=S$2), 2, "" ))) | ... AQ6: =IF(AND($F6<(AQ$2+7),$F6>AQ$2),1, IF(AND($H6<AQ$2+7,$H6>AQ$2),3, IF(AND($F6<=AQ$2, $H6>=AQ$2), 2, "" )))
A7: 4 | B7: Equipment Procurement | C7: 43833 | E7: 43949 | F7: 43833 | H7: 43949 | L7: =IF(AND($F7<(L$2+7),$F7>L$2),1, IF(AND($H7<L$2+7,$H7>L$2),3, IF(AND($F7<=L$2, $H7>=L$2), 2, "" ))) -> 1 | M7: =IF(AND($F7<(M$2+7),$F7>M$2),1, IF(AND($H7<M$2+7,$H7>M$2),3, IF(AND($F7<=M$2, $H7>=M$2), 2, "" ))) -> 2 | N7: =IF(AND($F7<(N$2+7),$F7>N$2),1, IF(AND($H7<N$2+7,$H7>N$2),3, IF(AND($F7<=N$2, $H7>=N$2), 2, "" ))) -> 2 | O7: =IF(AND($F7<(O$2+7),$F7>O$2),1, IF(AND($H7<O$2+7,$H7>O$2),3, IF(AND($F7<=O$2, $H7>=O$2), 2, "" ))) -> 2 | P7: =IF(AND($F7<(P$2+7),$F7>P$2),1, IF(AND($H7<P$2+7,$H7>P$2),3, IF(AND($F7<=P$2, $H7>=P$2), 2, "" ))) -> 2 | Q7: =IF(AND($F7<(Q$2+7),$F7>Q$2),1, IF(AND($H7<Q$2+7,$H7>Q$2),3, IF(AND($F7<=Q$2, $H7>=Q$2), 2, "" ))) -> 2 | R7: =IF(AND($F7<(R$2+7),$F7>R$2),1, IF(AND($H7<R$2+7,$H7>R$2),3, IF(AND($F7<=R$2, $H7>=R$2), 2, "" ))) -> 2 | S7: =IF(AND($F7<(S$2+7),$F7>S$2),1, IF(AND($H7<S$2+7,$H7>S$2),3, IF(AND($F7<=S$2, $H7>=S$2), 2, "" ))) -> 2 | ... AQ7: =IF(AND($F7<(AQ$2+7),$F7>AQ$2),1, IF(AND($H7<AQ$2+7,$H7>AQ$2),3, IF(AND($F7<=AQ$2, $H7>=AQ$2), 2, "" )))
B8: Panel Procurement | C8: 43833 | D8: 5 | E8: 43840 | F8: 43833 | G8: 5 | H8: 43840 | L8: =IF(AND($F8<(L$2+7),$F8>L$2),1, IF(AND($H8<L$2+7,$H8>L$2),3, IF(AND($F8<=L$2, $H8>=L$2), 2, "" ))) -> 1 | M8: =IF(AND($F8<(M$2+7),$F8>M$2),1, IF(AND($H8<M$2+7,$H8>M$2),3, IF(AND($F8<=M$2, $H8>=M$2), 2, "" ))) -> 3 | N8: =IF(AND($F8<(N$2+7),$F8>N$2),1, IF(AND($H8<N$2+7,$H8>N$2),3, IF(AND($F8<=N$2, $H8>=N$2), 2, "" ))) | O8: =IF(AND($F8<(O$2+7),$F8>O$2),1, IF(AND($H8<O$2+7,$H8>O$2),3, IF(AND($F8<=O$2, $H8>=O$2), 2, "" ))) | P8: =IF(AND($F8<(P$2+7),$F8>P$2),1, IF(AND($H8<P$2+7,$H8>P$2),3, IF(AND($F8<=P$2, $H8>=P$2), 2, "" ))) | Q8: =IF(AND($F8<(Q$2+7),$F8>Q$2),1, IF(AND($H8<Q$2+7,$H8>Q$2),3, IF(AND($F8<=Q$2, $H8>=Q$2), 2, "" ))) | R8: =IF(AND($F8<(R$2+7),$F8>R$2),1, IF(AND($H8<R$2+7,$H8>R$2),3, IF(AND($F8<=R$2, $H8>=R$2), 2, "" ))) | S8: =IF(AND($F8<(S$2+7),$F8>S$2),1, IF(AND($H8<S$2+7,$H8>S$2),3, IF(AND($F8<=S$2, $H8>=S$2), 2, "" ))) | ... AQ8: =IF(AND($F8<(AQ$2+7),$F8>AQ$2),1, IF(AND($H8<AQ$2+7,$H8>AQ$2),3, IF(AND($F8<=AQ$2, $H8>=AQ$2), 2, "" )))
B9: Inverter Procurement | C9: 43941 | D9: 5 | E9: 43949 | F9: 43941 | G9: 5 | H9: 43949 | L9: =IF(AND($F9<(L$2+7),$F9>L$2),1, IF(AND($H9<L$2+7,$H9>L$2),3, IF(AND($F9<=L$2, $H9>=L$2), 2, "" ))) | M9: =IF(AND($F9<(M$2+7),$F9>M$2),1, IF(AND($H9<M$2+7,$H9>M$2),3, IF(AND($F9<=M$2, $H9>=M$2), 2, "" ))) | N9: =IF(AND($F9<(N$2+7),$F9>N$2),1, IF(AND($H9<N$2+7,$H9>N$2),3, IF(AND($F9<=N$2, $H9>=N$2), 2, "" ))) | O9: =IF(AND($F9<(O$2+7),$F9>O$2),1, IF(AND($H9<O$2+7,$H9>O$2),3, IF(AND($F9<=O$2, $H9>=O$2), 2, "" ))) | P9: =IF(AND($F9<(P$2+7),$F9>P$2),1, IF(AND($H9<P$2+7,$H9>P$2),3, IF(AND($F9<=P$2, $H9>=P$2), 2, "" ))) | Q9: =IF(AND($F9<(Q$2+7),$F9>Q$2),1, IF(AND($H9<Q$2+7,$H9>Q$2),3, IF(AND($F9<=Q$2, $H9>=Q$2), 2, "" ))) | R9: =IF(AND($F9<(R$2+7),$F9>R$2),1, IF(AND($H9<R$2+7,$H9>R$2),3, IF(AND($F9<=R$2, $H9>=R$2), 2, "" ))) | S9: =IF(AND($F9<(S$2+7),$F9>S$2),1, IF(AND($H9<S$2+7,$H9>S$2),3, IF(AND($F9<=S$2, $H9>=S$2), 2, "" ))) | ... AQ9: =IF(AND($F9<(AQ$2+7),$F9>AQ$2),1, IF(AND($H9<AQ$2+7,$H9>AQ$2),3, IF(AND($F9<=AQ$2, $H9>=AQ$2), 2, "" )))
B10: Mounting Structure Procurement | C10: 43941 | D10: 5 | E10: 43949 | F10: 43941 | G10: 5 | H10: 43949 | L10: =IF(AND($F10<(L$2+7),$F10>L$2),1, IF(AND($H10<L$2+7,$H10>L$2),3, IF(AND($F10<=L$2, $H10>=L$2), 2, "" ))) | M10: =IF(AND($F10<(M$2+7),$F10>M$2),1, IF(AND($H10<M$2+7,$H10>M$2),3, IF(AND($F10<=M$2, $H10>=M$2), 2, "" ))) | N10: =IF(AND($F10<(N$2+7),$F10>N$2),1, IF(AND($H10<N$2+7,$H10>N$2),3, IF(AND($F10<=N$2, $H10>=N$2), 2, "" ))) | O10: =IF(AND($F10<(O$2+7),$F10>O$2),1, IF(AND($H10<O$2+7,$H10>O$2),3, IF(AND($F10<=O$2, $H10>=O$2), 2, "" ))) | P10: =IF(AND($F10<(P$2+7),$F10>P$2),1, IF(AND($H10<P$2+7,$H10>P$2),3, IF(AND($F10<=P$2, $H10>=P$2), 2, "" ))) | Q10: =IF(AND($F10<(Q$2+7),$F10>Q$2),1, IF(AND($H10<Q$2+7,$H10>Q$2),3, IF(AND($F10<=Q$2, $H10>=Q$2), 2, "" ))) | R10: =IF(AND($F10<(R$2+7),$F10>R$2),1, IF(AND($H10<R$2+7,$H10>R$2),3, IF(AND($F10<=R$2, $H10>=R$2), 2, "" ))) | S10: =IF(AND($F10<(S$2+7),$F10>S$2),1, IF(AND($H10<S$2+7,$H10>S$2),3, IF(AND($F10<=S$2, $H10>=S$2), 2, "" ))) | ... AQ10: =IF(AND($F10<(AQ$2+7),$F10>AQ$2),1, IF(AND($H10<AQ$2+7,$H10>AQ$2),3, IF(AND($F10<=AQ$2, $H10>=AQ$2), 2, "" )))
B11: BOS Procurement | C11: 43941 | D11: 5 | E11: 43949 | F11: 43941 | G11: 5 | H11: 43949 | L11: =IF(AND($F11<(L$2+7),$F11>L$2),1, IF(AND($H11<L$2+7,$H11>L$2),3, IF(AND($F11<=L$2, $H11>=L$2), 2, "" ))) | M11: =IF(AND($F11<(M$2+7),$F11>M$2),1, IF(AND($H11<M$2+7,$H11>M$2),3, IF(AND($F11<=M$2, $H11>=M$2), 2, "" ))) | N11: =IF(AND($F11<(N$2+7),$F11>N$2),1, IF(AND($H11<N$2+7,$H11>N$2),3, IF(AND($F11<=N$2, $H11>=N$2), 2, "" ))) | O11: =IF(AND($F11<(O$2+7),$F11>O$2),1, IF(AND($H11<O$2+7,$H11>O$2),3, IF(AND($F11<=O$2, $H11>=O$2), 2, "" ))) | P11: =IF(AND($F11<(P$2+7),$F11>P$2),1, IF(AND($H11<P$2+7,$H11>P$2),3, IF(AND($F11<=P$2, $H11>=P$2), 2, "" ))) | Q11: =IF(AND($F11<(Q$2+7),$F11>Q$2),1, IF(AND($H11<Q$2+7,$H11>Q$2),3, IF(AND($F11<=Q$2, $H11>=Q$2), 2, "" ))) | R11: =IF(AND($F11<(R$2+7),$F11>R$2),1, IF(AND($H11<R$2+7,$H11>R$2),3, IF(AND($F11<=R$2, $H11>=R$2), 2, "" ))) | S11: =IF(AND($F11<(S$2+7),$F11>S$2),1, IF(AND($H11<S$2+7,$H11>S$2),3, IF(AND($F11<=S$2, $H11>=S$2), 2, "" ))) | ... AQ11: =IF(AND($F11<(AQ$2+7),$F11>AQ$2),1, IF(AND($H11<AQ$2+7,$H11>AQ$2),3, IF(AND($F11<=AQ$2, $H11>=AQ$2), 2, "" )))
A12: 5 | B12: Internal Project Kick off | C12: 43936 | D12: 5 | E12: 43943 | F12: 43936 | G12: 5 | H12: 43943
A13: 6 | B13: Client Project Kick-off | C13: 43963 | D13: 5 | E13: 43970 | F13: 43963 | G13: 5 | H13: 43970 | L13: =IF(AND($F13<(L$2+7),$F13>L$2),1, IF(AND($H13<L$2+7,$H13>L$2),3, IF(AND($F13<=L$2, $H13>=L$2), 2, "" ))) | M13: =IF(AND($F13<(M$2+7),$F13>M$2),1, IF(AND($H13<M$2+7,$H13>M$2),3, IF(AND($F13<=M$2, $H13>=M$2), 2, "" ))) | N13: =IF(AND($F13<(N$2+7),$F13>N$2),1, IF(AND($H13<N$2+7,$H13>N$2),3, IF(AND($F13<=N$2, $H13>=N$2), 2, "" ))) | O13: =IF(AND($F13<(O$2+7),$F13>O$2),1, IF(AND($H13<O$2+7,$H13>O$2),3, IF(AND($F13<=O$2, $H13>=O$2), 2, "" ))) | P13: =IF(AND($F13<(P$2+7),$F13>P$2),1, IF(AND($H13<P$2+7,$H13>P$2),3, IF(AND($F13<=P$2, $H13>=P$2), 2, "" ))) | Q13: =IF(AND($F13<(Q$2+7),$F13>Q$2),1, IF(AND($H13<Q$2+7,$H13>Q$2),3, IF(AND($F13<=Q$2, $H13>=Q$2), 2, "" ))) | R13: =IF(AND($F13<(R$2+7),$F13>R$2),1, IF(AND($H13<R$2+7,$H13>R$2),3, IF(AND($F13<=R$2, $H13>=R$2), 2, "" ))) | S13: =IF(AND($F13<(S$2+7),$F13>S$2),1, IF(AND($H13<S$2+7,$H13>S$2),3, IF(AND($F13<=S$2, $H13>=S$2), 2, "" ))) | ... AQ13: =IF(AND($F13<(AQ$2+7),$F13>AQ$2),1, IF(AND($H13<AQ$2+7,$H13>AQ$2),3, IF(AND($F13<=AQ$2, $H13>=AQ$2), 2, "" )))
A14: 7 | B14: Equipment Delivery | C14: 43983 | D14: 9 | E14: 43994 | F14: 43983 | G14: 9 | H14: 43994 | L14: =IF(AND($F14<(L$2+7),$F14>L$2),1, IF(AND($H14<L$2+7,$H14>L$2),3, IF(AND($F14<=L$2, $H14>=L$2), 2, "" ))) | M14: =IF(AND($F14<(M$2+7),$F14>M$2),1, IF(AND($H14<M$2+7,$H14>M$2),3, IF(AND($F14<=M$2, $H14>=M$2), 2, "" ))) | N14: =IF(AND($F14<(N$2+7),$F14>N$2),1, IF(AND($H14<N$2+7,$H14>N$2),3, IF(AND($F14<=N$2, $H14>=N$2), 2, "" ))) | O14: =IF(AND($F14<(O$2+7),$F14>O$2),1, IF(AND($H14<O$2+7,$H14>O$2),3, IF(AND($F14<=O$2, $H14>=O$2), 2, "" ))) | P14: =IF(AND($F14<(P$2+7),$F14>P$2),1, IF(AND($H14<P$2+7,$H14>P$2),3, IF(AND($F14<=P$2, $H14>=P$2), 2, "" ))) | Q14: =IF(AND($F14<(Q$2+7),$F14>Q$2),1, IF(AND($H14<Q$2+7,$H14>Q$2),3, IF(AND($F14<=Q$2, $H14>=Q$2), 2, "" ))) | R14: =IF(AND($F14<(R$2+7),$F14>R$2),1, IF(AND($H14<R$2+7,$H14>R$2),3, IF(AND($F14<=R$2, $H14>=R$2), 2, "" ))) | S14: =IF(AND($F14<(S$2+7),$F14>S$2),1, IF(AND($H14<S$2+7,$H14>S$2),3, IF(AND($F14<=S$2, $H14>=S$2), 2, "" ))) | ... AQ14: =IF(AND($F14<(AQ$2+7),$F14>AQ$2),1, IF(AND($H14<AQ$2+7,$H14>AQ$2),3, IF(AND($F14<=AQ$2, $H14>=AQ$2), 2, "" )))
B15: Mounting Structure Delivery | C15: 43983 | D15: 2 | E15: 43985 | F15: 43983 | G15: 2 | H15: 43985
B16: Panel Delivery | C16: 43990 | D16: 2 | E16: 43992 | F16: 43990 | G16: 2 | H16: 43992 | L16: =IF(AND($F16<(L$2+7),$F16>L$2),1, IF(AND($H16<L$2+7,$H16>L$2),3, IF(AND($F16<=L$2, $H16>=L$2), 2, "" ))) | M16: =IF(AND($F16<(M$2+7),$F16>M$2),1, IF(AND($H16<M$2+7,$H16>M$2),3, IF(AND($F16<=M$2, $H16>=M$2), 2, "" ))) | N16: =IF(AND($F16<(N$2+7),$F16>N$2),1, IF(AND($H16<N$2+7,$H16>N$2),3, IF(AND($F16<=N$2, $H16>=N$2), 2, "" ))) | O16: =IF(AND($F16<(O$2+7),$F16>O$2),1, IF(AND($H16<O$2+7,$H16>O$2),3, IF(AND($F16<=O$2, $H16>=O$2), 2, "" ))) | P16: =IF(AND($F16<(P$2+7),$F16>P$2),1, IF(AND($H16<P$2+7,$H16>P$2),3, IF(AND($F16<=P$2, $H16>=P$2), 2, "" ))) | Q16: =IF(AND($F16<(Q$2+7),$F16>Q$2),1, IF(AND($H16<Q$2+7,$H16>Q$2),3, IF(AND($F16<=Q$2, $H16>=Q$2), 2, "" ))) | R16: =IF(AND($F16<(R$2+7),$F16>R$2),1, IF(AND($H16<R$2+7,$H16>R$2),3, IF(AND($F16<=R$2, $H16>=R$2), 2, "" ))) | S16: =IF(AND($F16<(S$2+7),$F16>S$2),1, IF(AND($H16<S$2+7,$H16>S$2),3, IF(AND($F16<=S$2, $H16>=S$2), 2, "" ))) | ... AQ16: =IF(AND($F16<(AQ$2+7),$F16>AQ$2),1, IF(AND($H16<AQ$2+7,$H16>AQ$2),3, IF(AND($F16<=AQ$2, $H16>=AQ$2), 2, "" )))
B17: Generator Delivery | C17: 43983 | D17: 2 | E17: 43985 | F17: 43983 | G17: 2 | H17: 43985
A18: B | B18: PAYMENT MILESTONE 2: DELIVERY OF PV PANELS | C18: 43992 | D18: 2 | E18: 43994 | F18: 43992 | G18: 2 | H18: 43994
B19: Inverter Delivery | C19: 43983 | D19: 2 | E19: 43985 | F19: 43983 | G19: 2 | H19: 43985 | L19: =IF(AND($F19<(L$2+7),$F19>L$2),1, IF(AND($H19<L$2+7,$H19>L$2),3, IF(AND($F19<=L$2, $H19>=L$2), 2, "" ))) | M19: =IF(AND($F19<(M$2+7),$F19>M$2),1, IF(AND($H19<M$2+7,$H19>M$2),3, IF(AND($F19<=M$2, $H19>=M$2), 2, "" ))) | N19: =IF(AND($F19<(N$2+7),$F19>N$2),1, IF(AND($H19<N$2+7,$H19>N$2),3, IF(AND($F19<=N$2, $H19>=N$2), 2, "" ))) | O19: =IF(AND($F19<(O$2+7),$F19>O$2),1, IF(AND($H19<O$2+7,$H19>O$2),3, IF(AND($F19<=O$2, $H19>=O$2), 2, "" ))) | P19: =IF(AND($F19<(P$2+7),$F19>P$2),1, IF(AND($H19<P$2+7,$H19>P$2),3, IF(AND($F19<=P$2, $H19>=P$2), 2, "" ))) | Q19: =IF(AND($F19<(Q$2+7),$F19>Q$2),1, IF(AND($H19<Q$2+7,$H19>Q$2),3, IF(AND($F19<=Q$2, $H19>=Q$2), 2, "" ))) | R19: =IF(AND($F19<(R$2+7),$F19>R$2),1, IF(AND($H19<R$2+7,$H19>R$2),3, IF(AND($F19<=R$2, $H19>=R$2), 2, "" ))) | S19: =IF(AND($F19<(S$2+7),$F19>S$2),1, IF(AND($H19<S$2+7,$H19>S$2),3, IF(AND($F19<=S$2, $H19>=S$2), 2, "" ))) | ... AQ19: =IF(AND($F19<(AQ$2+7),$F19>AQ$2),1, IF(AND($H19<AQ$2+7,$H19>AQ$2),3, IF(AND($F19<=AQ$2, $H19>=AQ$2), 2, "" )))
B20: BOS Delivery | C20: 43983 | D20: 1 | E20: 43984 | F20: 43983 | G20: 1 | H20: 43984 | L20: =IF(AND($F20<(L$2+7),$F20>L$2),1, IF(AND($H20<L$2+7,$H20>L$2),3, IF(AND($F20<=L$2, $H20>=L$2), 2, "" ))) | M20: =IF(AND($F20<(M$2+7),$F20>M$2),1, IF(AND($H20<M$2+7,$H20>M$2),3, IF(AND($F20<=M$2, $H20>=M$2), 2, "" ))) | N20: =IF(AND($F20<(N$2+7),$F20>N$2),1, IF(AND($H20<N$2+7,$H20>N$2),3, IF(AND($F20<=N$2, $H20>=N$2), 2, "" ))) | O20: =IF(AND($F20<(O$2+7),$F20>O$2),1, IF(AND($H20<O$2+7,$H20>O$2),3, IF(AND($F20<=O$2, $H20>=O$2), 2, "" ))) | P20: =IF(AND($F20<(P$2+7),$F20>P$2),1, IF(AND($H20<P$2+7,$H20>P$2),3, IF(AND($F20<=P$2, $H20>=P$2), 2, "" ))) | Q20: =IF(AND($F20<(Q$2+7),$F20>Q$2),1, IF(AND($H20<Q$2+7,$H20>Q$2),3, IF(AND($F20<=Q$2, $H20>=Q$2), 2, "" ))) | R20: =IF(AND($F20<(R$2+7),$F20>R$2),1, IF(AND($H20<R$2+7,$H20>R$2),3, IF(AND($F20<=R$2, $H20>=R$2), 2, "" ))) | S20: =IF(AND($F20<(S$2+7),$F20>S$2),1, IF(AND($H20<S$2+7,$H20>S$2),3, IF(AND($F20<=S$2, $H20>=S$2), 2, "" ))) | ... AQ20: =IF(AND($F20<(AQ$2+7),$F20>AQ$2),1, IF(AND($H20<AQ$2+7,$H20>AQ$2),3, IF(AND($F20<=AQ$2, $H20>=AQ$2), 2, "" )))
A21: C | B21: PAYMENT MILESTONE 3: DELIVERY OF INVERTERS AND BOS | C21: 43985 | D21: 2 | E21: 43987 | F21: 43985 | G21: 2 | H21: 43987
A22: 8 | B22: Installation | C22: 43990 | D22: 22 | E22: 44012 | F22: 43990 | G22: 22 | H22: 44012 | L22: =IF(AND($F22<(L$2+7),$F22>L$2),1, IF(AND($H22<L$2+7,$H22>L$2),3, IF(AND($F22<=L$2, $H22>=L$2), 2, "" ))) | M22: =IF(AND($F22<(M$2+7),$F22>M$2),1, IF(AND($H22<M$2+7,$H22>M$2),3, IF(AND($F22<=M$2, $H22>=M$2), 2, "" ))) | N22: =IF(AND($F22<(N$2+7),$F22>N$2),1, IF(AND($H22<N$2+7,$H22>N$2),3, IF(AND($F22<=N$2, $H22>=N$2), 2, "" ))) | O22: =IF(AND($F22<(O$2+7),$F22>O$2),1, IF(AND($H22<O$2+7,$H22>O$2),3, IF(AND($F22<=O$2, $H22>=O$2), 2, "" ))) | P22: =IF(AND($F22<(P$2+7),$F22>P$2),1, IF(AND($H22<P$2+7,$H22>P$2),3, IF(AND($F22<=P$2, $H22>=P$2), 2, "" ))) | Q22: =IF(AND($F22<(Q$2+7),$F22>Q$2),1, IF(AND($H22<Q$2+7,$H22>Q$2),3, IF(AND($F22<=Q$2, $H22>=Q$2), 2, "" ))) | R22: =IF(AND($F22<(R$2+7),$F22>R$2),1, IF(AND($H22<R$2+7,$H22>R$2),3, IF(AND($F22<=R$2, $H22>=R$2), 2, "" ))) | S22: =IF(AND($F22<(S$2+7),$F22>S$2),1, IF(AND($H22<S$2+7,$H22>S$2),3, IF(AND($F22<=S$2, $H22>=S$2), 2, "" ))) | ... AQ22: =IF(AND($F22<(AQ$2+7),$F22>AQ$2),1, IF(AND($H22<AQ$2+7,$H22>AQ$2),3, IF(AND($F22<=AQ$2, $H22>=AQ$2), 2, "" ))) -> 2
B23: Site Establishment | C23: 43990 | D23: 1 | E23: 43991 | F23: 43990 | G23: 1 | H23: 43991 | J23: Installation placed on hold due to Covid-19 case | L23: =IF(AND($F23<(L$2+7),$F23>L$2),1, IF(AND($H23<L$2+7,$H23>L$2),3, IF(AND($F23<=L$2, $H23>=L$2), 2, "" ))) | M23: =IF(AND($F23<(M$2+7),$F23>M$2),1, IF(AND($H23<M$2+7,$H23>M$2),3, IF(AND($F23<=M$2, $H23>=M$2), 2, "" ))) | N23: =IF(AND($F23<(N$2+7),$F23>N$2),1, IF(AND($H23<N$2+7,$H23>N$2),3, IF(AND($F23<=N$2, $H23>=N$2), 2, "" ))) | O23: =IF(AND($F23<(O$2+7),$F23>O$2),1, IF(AND($H23<O$2+7,$H23>O$2),3, IF(AND($F23<=O$2, $H23>=O$2), 2, "" ))) | P23: =IF(AND($F23<(P$2+7),$F23>P$2),1, IF(AND($H23<P$2+7,$H23>P$2),3, IF(AND($F23<=P$2, $H23>=P$2), 2, "" ))) | Q23: =IF(AND($F23<(Q$2+7),$F23>Q$2),1, IF(AND($H23<Q$2+7,$H23>Q$2),3, IF(AND($F23<=Q$2, $H23>=Q$2), 2, "" ))) | R23: =IF(AND($F23<(R$2+7),$F23>R$2),1, IF(AND($H23<R$2+7,$H23>R$2),3, IF(AND($F23<=R$2, $H23>=R$2), 2, "" ))) | S23: =IF(AND($F23<(S$2+7),$F23>S$2),1, IF(AND($H23<S$2+7,$H23>S$2),3, IF(AND($F23<=S$2, $H23>=S$2), 2, "" ))) | ... AQ23: =IF(AND($F23<(AQ$2+7),$F23>AQ$2),1, IF(AND($H23<AQ$2+7,$H23>AQ$2),3, IF(AND($F23<=AQ$2, $H23>=AQ$2), 2, "" )))
A24: 9 | B24: DC Works | C24: 43991 | D24: 16 | E24: 44012 | F24: 43991 | G24: 16 | H24: 44012 | L24: =IF(AND($F24<(L$2+7),$F24>L$2),1, IF(AND($H24<L$2+7,$H24>L$2),3, IF(AND($F24<=L$2, $H24>=L$2), 2, "" ))) | M24: =IF(AND($F24<(M$2+7),$F24>M$2),1, IF(AND($H24<M$2+7,$H24>M$2),3, IF(AND($F24<=M$2, $H24>=M$2), 2, "" ))) | N24: =IF(AND($F24<(N$2+7),$F24>N$2),1, IF(AND($H24<N$2+7,$H24>N$2),3, IF(AND($F24<=N$2, $H24>=N$2), 2, "" ))) | O24: =IF(AND($F24<(O$2+7),$F24>O$2),1, IF(AND($H24<O$2+7,$H24>O$2),3, IF(AND($F24<=O$2, $H24>=O$2), 2, "" ))) | P24: =IF(AND($F24<(P$2+7),$F24>P$2),1, IF(AND($H24<P$2+7,$H24>P$2),3, IF(AND($F24<=P$2, $H24>=P$2), 2, "" ))) | Q24: =IF(AND($F24<(Q$2+7),$F24>Q$2),1, IF(AND($H24<Q$2+7,$H24>Q$2),3, IF(AND($F24<=Q$2, $H24>=Q$2), 2, "" ))) | R24: =IF(AND($F24<(R$2+7),$F24>R$2),1, IF(AND($H24<R$2+7,$H24>R$2),3, IF(AND($F24<=R$2, $H24>=R$2), 2, "" ))) | S24: =IF(AND($F24<(S$2+7),$F24>S$2),1, IF(AND($H24<S$2+7,$H24>S$2),3, IF(AND($F24<=S$2, $H24>=S$2), 2, "" ))) | ... AQ24: =IF(AND($F24<(AQ$2+7),$F24>AQ$2),1, IF(AND($H24<AQ$2+7,$H24>AQ$2),3, IF(AND($F24<=AQ$2, $H24>=AQ$2), 2, "" ))) -> 2
B25: Mounting structure Installation | C25: 43991 | D25: 4 | E25: 43997 | F25: 43991 | G25: 4 | H25: 43997 | L25: =IF(AND($F25<(L$2+7),$F25>L$2),1, IF(AND($H25<L$2+7,$H25>L$2),3, IF(AND($F25<=L$2, $H25>=L$2), 2, "" ))) | M25: =IF(AND($F25<(M$2+7),$F25>M$2),1, IF(AND($H25<M$2+7,$H25>M$2),3, IF(AND($F25<=M$2, $H25>=M$2), 2, "" ))) | N25: =IF(AND($F25<(N$2+7),$F25>N$2),1, IF(AND($H25<N$2+7,$H25>N$2),3, IF(AND($F25<=N$2, $H25>=N$2), 2, "" ))) | O25: =IF(AND($F25<(O$2+7),$F25>O$2),1, IF(AND($H25<O$2+7,$H25>O$2),3, IF(AND($F25<=O$2, $H25>=O$2), 2, "" ))) | P25: =IF(AND($F25<(P$2+7),$F25>P$2),1, IF(AND($H25<P$2+7,$H25>P$2),3, IF(AND($F25<=P$2, $H25>=P$2), 2, "" ))) | Q25: =IF(AND($F25<(Q$2+7),$F25>Q$2),1, IF(AND($H25<Q$2+7,$H25>Q$2),3, IF(AND($F25<=Q$2, $H25>=Q$2), 2, "" ))) | R25: =IF(AND($F25<(R$2+7),$F25>R$2),1, IF(AND($H25<R$2+7,$H25>R$2),3, IF(AND($F25<=R$2, $H25>=R$2), 2, "" ))) | S25: =IF(AND($F25<(S$2+7),$F25>S$2),1, IF(AND($H25<S$2+7,$H25>S$2),3, IF(AND($F25<=S$2, $H25>=S$2), 2, "" ))) | ... AQ25: =IF(AND($F25<(AQ$2+7),$F25>AQ$2),1, IF(AND($H25<AQ$2+7,$H25>AQ$2),3, IF(AND($F25<=AQ$2, $H25>=AQ$2), 2, "" )))
B26: Cable tray Installation | C26: 43997 | D26: 3 | E26: 44004 | F26: 43997 | G26: 3 | H26: 44004 | L26: =IF(AND($F26<(L$2+7),$F26>L$2),1, IF(AND($H26<L$2+7,$H26>L$2),3, IF(AND($F26<=L$2, $H26>=L$2), 2, "" ))) | M26: =IF(AND($F26<(M$2+7),$F26>M$2),1, IF(AND($H26<M$2+7,$H26>M$2),3, IF(AND($F26<=M$2, $H26>=M$2), 2, "" ))) | N26: =IF(AND($F26<(N$2+7),$F26>N$2),1, IF(AND($H26<N$2+7,$H26>N$2),3, IF(AND($F26<=N$2, $H26>=N$2), 2, "" ))) | O26: =IF(AND($F26<(O$2+7),$F26>O$2),1, IF(AND($H26<O$2+7,$H26>O$2),3, IF(AND($F26<=O$2, $H26>=O$2), 2, "" ))) | P26: =IF(AND($F26<(P$2+7),$F26>P$2),1, IF(AND($H26<P$2+7,$H26>P$2),3, IF(AND($F26<=P$2, $H26>=P$2), 2, "" ))) | Q26: =IF(AND($F26<(Q$2+7),$F26>Q$2),1, IF(AND($H26<Q$2+7,$H26>Q$2),3, IF(AND($F26<=Q$2, $H26>=Q$2), 2, "" ))) | R26: =IF(AND($F26<(R$2+7),$F26>R$2),1, IF(AND($H26<R$2+7,$H26>R$2),3, IF(AND($F26<=R$2, $H26>=R$2), 2, "" ))) | S26: =IF(AND($F26<(S$2+7),$F26>S$2),1, IF(AND($H26<S$2+7,$H26>S$2),3, IF(AND($F26<=S$2, $H26>=S$2), 2, "" ))) | ... AQ26: =IF(AND($F26<(AQ$2+7),$F26>AQ$2),1, IF(AND($H26<AQ$2+7,$H26>AQ$2),3, IF(AND($F26<=AQ$2, $H26>=AQ$2), 2, "" )))
B27: DC Cable Installation | C27: 44004 | D27: 2 | E27: 44006 | F27: 44004 | G27: 2 | H27: 44006 | L27: =IF(AND($F27<(L$2+7),$F27>L$2),1, IF(AND($H27<L$2+7,$H27>L$2),3, IF(AND($F27<=L$2, $H27>=L$2), 2, "" ))) | M27: =IF(AND($F27<(M$2+7),$F27>M$2),1, IF(AND($H27<M$2+7,$H27>M$2),3, IF(AND($F27<=M$2, $H27>=M$2), 2, "" ))) | N27: =IF(AND($F27<(N$2+7),$F27>N$2),1, IF(AND($H27<N$2+7,$H27>N$2),3, IF(AND($F27<=N$2, $H27>=N$2), 2, "" ))) | O27: =IF(AND($F27<(O$2+7),$F27>O$2),1, IF(AND($H27<O$2+7,$H27>O$2),3, IF(AND($F27<=O$2, $H27>=O$2), 2, "" ))) | P27: =IF(AND($F27<(P$2+7),$F27>P$2),1, IF(AND($H27<P$2+7,$H27>P$2),3, IF(AND($F27<=P$2, $H27>=P$2), 2, "" ))) | Q27: =IF(AND($F27<(Q$2+7),$F27>Q$2),1, IF(AND($H27<Q$2+7,$H27>Q$2),3, IF(AND($F27<=Q$2, $H27>=Q$2), 2, "" ))) | R27: =IF(AND($F27<(R$2+7),$F27>R$2),1, IF(AND($H27<R$2+7,$H27>R$2),3, IF(AND($F27<=R$2, $H27>=R$2), 2, "" ))) | S27: =IF(AND($F27<(S$2+7),$F27>S$2),1, IF(AND($H27<S$2+7,$H27>S$2),3, IF(AND($F27<=S$2, $H27>=S$2), 2, "" ))) | ... AQ27: =IF(AND($F27<(AQ$2+7),$F27>AQ$2),1, IF(AND($H27<AQ$2+7,$H27>AQ$2),3, IF(AND($F27<=AQ$2, $H27>=AQ$2), 2, "" )))
B28: Module Installation | C28: 44006 | D28: 4 | E28: 44012 | F28: 44006 | G28: 4 | H28: 44012 | L28: =IF(AND($F28<(L$2+7),$F28>L$2),1, IF(AND($H28<L$2+7,$H28>L$2),3, IF(AND($F28<=L$2, $H28>=L$2), 2, "" ))) | M28: =IF(AND($F28<(M$2+7),$F28>M$2),1, IF(AND($H28<M$2+7,$H28>M$2),3, IF(AND($F28<=M$2, $H28>=M$2), 2, "" ))) | N28: =IF(AND($F28<(N$2+7),$F28>N$2),1, IF(AND($H28<N$2+7,$H28>N$2),3, IF(AND($F28<=N$2, $H28>=N$2), 2, "" ))) | O28: =IF(AND($F28<(O$2+7),$F28>O$2),1, IF(AND($H28<O$2+7,$H28>O$2),3, IF(AND($F28<=O$2, $H28>=O$2), 2, "" ))) | P28: =IF(AND($F28<(P$2+7),$F28>P$2),1, IF(AND($H28<P$2+7,$H28>P$2),3, IF(AND($F28<=P$2, $H28>=P$2), 2, "" ))) | Q28: =IF(AND($F28<(Q$2+7),$F28>Q$2),1, IF(AND($H28<Q$2+7,$H28>Q$2),3, IF(AND($F28<=Q$2, $H28>=Q$2), 2, "" ))) | R28: =IF(AND($F28<(R$2+7),$F28>R$2),1, IF(AND($H28<R$2+7,$H28>R$2),3, IF(AND($F28<=R$2, $H28>=R$2), 2, "" ))) | S28: =IF(AND($F28<(S$2+7),$F28>S$2),1, IF(AND($H28<S$2+7,$H28>S$2),3, IF(AND($F28<=S$2, $H28>=S$2), 2, "" ))) | ... AQ28: =IF(AND($F28<(AQ$2+7),$F28>AQ$2),1, IF(AND($H28<AQ$2+7,$H28>AQ$2),3, IF(AND($F28<=AQ$2, $H28>=AQ$2), 2, "" ))) -> 2
B29: Earth Cable Installation | C29: 44004 | D29: 1 | E29: 44005 | F29: 44004 | G29: 1 | H29: 44005 | L29: =IF(AND($F29<(L$2+7),$F29>L$2),1, IF(AND($H29<L$2+7,$H29>L$2),3, IF(AND($F29<=L$2, $H29>=L$2), 2, "" ))) | M29: =IF(AND($F29<(M$2+7),$F29>M$2),1, IF(AND($H29<M$2+7,$H29>M$2),3, IF(AND($F29<=M$2, $H29>=M$2), 2, "" ))) | N29: =IF(AND($F29<(N$2+7),$F29>N$2),1, IF(AND($H29<N$2+7,$H29>N$2),3, IF(AND($F29<=N$2, $H29>=N$2), 2, "" ))) | O29: =IF(AND($F29<(O$2+7),$F29>O$2),1, IF(AND($H29<O$2+7,$H29>O$2),3, IF(AND($F29<=O$2, $H29>=O$2), 2, "" ))) | P29: =IF(AND($F29<(P$2+7),$F29>P$2),1, IF(AND($H29<P$2+7,$H29>P$2),3, IF(AND($F29<=P$2, $H29>=P$2), 2, "" ))) | Q29: =IF(AND($F29<(Q$2+7),$F29>Q$2),1, IF(AND($H29<Q$2+7,$H29>Q$2),3, IF(AND($F29<=Q$2, $H29>=Q$2), 2, "" ))) | R29: =IF(AND($F29<(R$2+7),$F29>R$2),1, IF(AND($H29<R$2+7,$H29>R$2),3, IF(AND($F29<=R$2, $H29>=R$2), 2, "" ))) | S29: =IF(AND($F29<(S$2+7),$F29>S$2),1, IF(AND($H29<S$2+7,$H29>S$2),3, IF(AND($F29<=S$2, $H29>=S$2), 2, "" ))) | ... AQ29: =IF(AND($F29<(AQ$2+7),$F29>AQ$2),1, IF(AND($H29<AQ$2+7,$H29>AQ$2),3, IF(AND($F29<=AQ$2, $H29>=AQ$2), 2, "" )))
A30: 10 | B30: AC Works | C30: 43991 | D30: 8 | E30: 44000 | F30: 43991 | G30: 8 | H30: 44000
B31: Inverters Installation | C31: 43991 | D31: 2 | E31: 43993 | F31: 43991 | G31: 2 | H31: 43993 | L31: =IF(AND($F31<(L$2+7),$F31>L$2),1, IF(AND($H31<L$2+7,$H31>L$2),3, IF(AND($F31<=L$2, $H31>=L$2), 2, "" ))) | M31: =IF(AND($F31<(M$2+7),$F31>M$2),1, IF(AND($H31<M$2+7,$H31>M$2),3, IF(AND($F31<=M$2, $H31>=M$2), 2, "" ))) | N31: =IF(AND($F31<(N$2+7),$F31>N$2),1, IF(AND($H31<N$2+7,$H31>N$2),3, IF(AND($F31<=N$2, $H31>=N$2), 2, "" ))) | O31: =IF(AND($F31<(O$2+7),$F31>O$2),1, IF(AND($H31<O$2+7,$H31>O$2),3, IF(AND($F31<=O$2, $H31>=O$2), 2, "" ))) | P31: =IF(AND($F31<(P$2+7),$F31>P$2),1, IF(AND($H31<P$2+7,$H31>P$2),3, IF(AND($F31<=P$2, $H31>=P$2), 2, "" ))) | Q31: =IF(AND($F31<(Q$2+7),$F31>Q$2),1, IF(AND($H31<Q$2+7,$H31>Q$2),3, IF(AND($F31<=Q$2, $H31>=Q$2), 2, "" ))) | R31: =IF(AND($F31<(R$2+7),$F31>R$2),1, IF(AND($H31<R$2+7,$H31>R$2),3, IF(AND($F31<=R$2, $H31>=R$2), 2, "" ))) | S31: =IF(AND($F31<(S$2+7),$F31>S$2),1, IF(AND($H31<S$2+7,$H31>S$2),3, IF(AND($F31<=S$2, $H31>=S$2), 2, "" ))) | ... AQ31: =IF(AND($F31<(AQ$2+7),$F31>AQ$2),1, IF(AND($H31<AQ$2+7,$H31>AQ$2),3, IF(AND($F31<=AQ$2, $H31>=AQ$2), 2, "" )))
B32: AC BOS Installation | C32: 43993 | D32: 3 | E32: 44000 | F32: 43993 | G32: 3 | H32: 44000 | L32: =IF(AND($F32<(L$2+7),$F32>L$2),1, IF(AND($H32<L$2+7,$H32>L$2),3, IF(AND($F32<=L$2, $H32>=L$2), 2, "" ))) | M32: =IF(AND($F32<(M$2+7),$F32>M$2),1, IF(AND($H32<M$2+7,$H32>M$2),3, IF(AND($F32<=M$2, $H32>=M$2), 2, "" ))) | N32: =IF(AND($F32<(N$2+7),$F32>N$2),1, IF(AND($H32<N$2+7,$H32>N$2),3, IF(AND($F32<=N$2, $H32>=N$2), 2, "" ))) | O32: =IF(AND($F32<(O$2+7),$F32>O$2),1, IF(AND($H32<O$2+7,$H32>O$2),3, IF(AND($F32<=O$2, $H32>=O$2), 2, "" ))) | P32: =IF(AND($F32<(P$2+7),$F32>P$2),1, IF(AND($H32<P$2+7,$H32>P$2),3, IF(AND($F32<=P$2, $H32>=P$2), 2, "" ))) | Q32: =IF(AND($F32<(Q$2+7),$F32>Q$2),1, IF(AND($H32<Q$2+7,$H32>Q$2),3, IF(AND($F32<=Q$2, $H32>=Q$2), 2, "" ))) | R32: =IF(AND($F32<(R$2+7),$F32>R$2),1, IF(AND($H32<R$2+7,$H32>R$2),3, IF(AND($F32<=R$2, $H32>=R$2), 2, "" ))) | S32: =IF(AND($F32<(S$2+7),$F32>S$2),1, IF(AND($H32<S$2+7,$H32>S$2),3, IF(AND($F32<=S$2, $H32>=S$2), 2, "" ))) | ... AQ32: =IF(AND($F32<(AQ$2+7),$F32>AQ$2),1, IF(AND($H32<AQ$2+7,$H32>AQ$2),3, IF(AND($F32<=AQ$2, $H32>=AQ$2), 2, "" )))
B33: AC Cable/Tie-In | C33: 43992 | D33: 3 | E33: 43997 | F33: 43992 | G33: 3 | H33: 43997 | L33: =IF(AND($F33<(L$2+7),$F33>L$2),1, IF(AND($H33<L$2+7,$H33>L$2),3, IF(AND($F33<=L$2, $H33>=L$2), 2, "" ))) | M33: =IF(AND($F33<(M$2+7),$F33>M$2),1, IF(AND($H33<M$2+7,$H33>M$2),3, IF(AND($F33<=M$2, $H33>=M$2), 2, "" ))) | N33: =IF(AND($F33<(N$2+7),$F33>N$2),1, IF(AND($H33<N$2+7,$H33>N$2),3, IF(AND($F33<=N$2, $H33>=N$2), 2, "" ))) | O33: =IF(AND($F33<(O$2+7),$F33>O$2),1, IF(AND($H33<O$2+7,$H33>O$2),3, IF(AND($F33<=O$2, $H33>=O$2), 2, "" ))) | P33: =IF(AND($F33<(P$2+7),$F33>P$2),1, IF(AND($H33<P$2+7,$H33>P$2),3, IF(AND($F33<=P$2, $H33>=P$2), 2, "" ))) | Q33: =IF(AND($F33<(Q$2+7),$F33>Q$2),1, IF(AND($H33<Q$2+7,$H33>Q$2),3, IF(AND($F33<=Q$2, $H33>=Q$2), 2, "" ))) | R33: =IF(AND($F33<(R$2+7),$F33>R$2),1, IF(AND($H33<R$2+7,$H33>R$2),3, IF(AND($F33<=R$2, $H33>=R$2), 2, "" ))) | S33: =IF(AND($F33<(S$2+7),$F33>S$2),1, IF(AND($H33<S$2+7,$H33>S$2),3, IF(AND($F33<=S$2, $H33>=S$2), 2, "" ))) | ... AQ33: =IF(AND($F33<(AQ$2+7),$F33>AQ$2),1, IF(AND($H33<AQ$2+7,$H33>AQ$2),3, IF(AND($F33<=AQ$2, $H33>=AQ$2), 2, "" )))
B34: Monitoring Platform Installation | C34: 43997 | D34: 1 | E34: 44000 | F34: 43997 | G34: 1 | H34: 44000
A35: 11 | B35: Completion | C35: 44000 | D35: 14 | E35: 44014 | F35: 44000 | G35: 14 | H35: 44014 | L35: =IF(AND($F35<(L$2+7),$F35>L$2),1, IF(AND($H35<L$2+7,$H35>L$2),3, IF(AND($F35<=L$2, $H35>=L$2), 2, "" ))) | M35: =IF(AND($F35<(M$2+7),$F35>M$2),1, IF(AND($H35<M$2+7,$H35>M$2),3, IF(AND($F35<=M$2, $H35>=M$2), 2, "" ))) | N35: =IF(AND($F35<(N$2+7),$F35>N$2),1, IF(AND($H35<N$2+7,$H35>N$2),3, IF(AND($F35<=N$2, $H35>=N$2), 2, "" ))) | O35: =IF(AND($F35<(O$2+7),$F35>O$2),1, IF(AND($H35<O$2+7,$H35>O$2),3, IF(AND($F35<=O$2, $H35>=O$2), 2, "" ))) | P35: =IF(AND($F35<(P$2+7),$F35>P$2),1, IF(AND($H35<P$2+7,$H35>P$2),3, IF(AND($F35<=P$2, $H35>=P$2), 2, "" ))) | Q35: =IF(AND($F35<(Q$2+7),$F35>Q$2),1, IF(AND($H35<Q$2+7,$H35>Q$2),3, IF(AND($F35<=Q$2, $H35>=Q$2), 2, "" ))) | R35: =IF(AND($F35<(R$2+7),$F35>R$2),1, IF(AND($H35<R$2+7,$H35>R$2),3, IF(AND($F35<=R$2, $H35>=R$2), 2, "" ))) | S35: =IF(AND($F35<(S$2+7),$F35>S$2),1, IF(AND($H35<S$2+7,$H35>S$2),3, IF(AND($F35<=S$2, $H35>=S$2), 2, "" ))) | ... AQ35: =IF(AND($F35<(AQ$2+7),$F35>AQ$2),1, IF(AND($H35<AQ$2+7,$H35>AQ$2),3, IF(AND($F35<=AQ$2, $H35>=AQ$2), 2, "" ))) -> 3
B36: DC Works | C36: 44012 | D36: 2 | E36: 44014 | F36: 44012 | G36: 2 | H36: 44014 | L36: =IF(AND($F36<(L$2+7),$F36>L$2),1, IF(AND($H36<L$2+7,$H36>L$2),3, IF(AND($F36<=L$2, $H36>=L$2), 2, "" ))) | M36: =IF(AND($F36<(M$2+7),$F36>M$2),1, IF(AND($H36<M$2+7,$H36>M$2),3, IF(AND($F36<=M$2, $H36>=M$2), 2, "" ))) | N36: =IF(AND($F36<(N$2+7),$F36>N$2),1, IF(AND($H36<N$2+7,$H36>N$2),3, IF(AND($F36<=N$2, $H36>=N$2), 2, "" ))) | O36: =IF(AND($F36<(O$2+7),$F36>O$2),1, IF(AND($H36<O$2+7,$H36>O$2),3, IF(AND($F36<=O$2, $H36>=O$2), 2, "" ))) | P36: =IF(AND($F36<(P$2+7),$F36>P$2),1, IF(AND($H36<P$2+7,$H36>P$2),3, IF(AND($F36<=P$2, $H36>=P$2), 2, "" ))) | Q36: =IF(AND($F36<(Q$2+7),$F36>Q$2),1, IF(AND($H36<Q$2+7,$H36>Q$2),3, IF(AND($F36<=Q$2, $H36>=Q$2), 2, "" ))) | R36: =IF(AND($F36<(R$2+7),$F36>R$2),1, IF(AND($H36<R$2+7,$H36>R$2),3, IF(AND($F36<=R$2, $H36>=R$2), 2, "" ))) | S36: =IF(AND($F36<(S$2+7),$F36>S$2),1, IF(AND($H36<S$2+7,$H36>S$2),3, IF(AND($F36<=S$2, $H36>=S$2), 2, "" ))) | ... AQ36: =IF(AND($F36<(AQ$2+7),$F36>AQ$2),1, IF(AND($H36<AQ$2+7,$H36>AQ$2),3, IF(AND($F36<=AQ$2, $H36>=AQ$2), 2, "" ))) -> 3
B37: AC Works | C37: 44000 | D37: 2 | E37: 44004 | F37: 44000 | G37: 2 | H37: 44004 | L37: =IF(AND($F37<(L$2+7),$F37>L$2),1, IF(AND($H37<L$2+7,$H37>L$2),3, IF(AND($F37<=L$2, $H37>=L$2), 2, "" ))) | M37: =IF(AND($F37<(M$2+7),$F37>M$2),1, IF(AND($H37<M$2+7,$H37>M$2),3, IF(AND($F37<=M$2, $H37>=M$2), 2, "" ))) | N37: =IF(AND($F37<(N$2+7),$F37>N$2),1, IF(AND($H37<N$2+7,$H37>N$2),3, IF(AND($F37<=N$2, $H37>=N$2), 2, "" ))) | O37: =IF(AND($F37<(O$2+7),$F37>O$2),1, IF(AND($H37<O$2+7,$H37>O$2),3, IF(AND($F37<=O$2, $H37>=O$2), 2, "" ))) | P37: =IF(AND($F37<(P$2+7),$F37>P$2),1, IF(AND($H37<P$2+7,$H37>P$2),3, IF(AND($F37<=P$2, $H37>=P$2), 2, "" ))) | Q37: =IF(AND($F37<(Q$2+7),$F37>Q$2),1, IF(AND($H37<Q$2+7,$H37>Q$2),3, IF(AND($F37<=Q$2, $H37>=Q$2), 2, "" ))) | R37: =IF(AND($F37<(R$2+7),$F37>R$2),1, IF(AND($H37<R$2+7,$H37>R$2),3, IF(AND($F37<=R$2, $H37>=R$2), 2, "" ))) | S37: =IF(AND($F37<(S$2+7),$F37>S$2),1, IF(AND($H37<S$2+7,$H37>S$2),3, IF(AND($F37<=S$2, $H37>=S$2), 2, "" ))) | ... AQ37: =IF(AND($F37<(AQ$2+7),$F37>AQ$2),1, IF(AND($H37<AQ$2+7,$H37>AQ$2),3, IF(AND($F37<=AQ$2, $H37>=AQ$2), 2, "" )))
A38: D | B38: PAYMENT MILESTONE 4: PRACTICAL COMPLETION | C38: 44012 | D38: 1 | E38: 44013 | F38: 44012 | G38: 1 | H38: 44013 | L38: =IF(AND($F38<(L$2+7),$F38>L$2),1, IF(AND($H38<L$2+7,$H38>L$2),3, IF(AND($F38<=L$2, $H38>=L$2), 2, "" ))) | M38: =IF(AND($F38<(M$2+7),$F38>M$2),1, IF(AND($H38<M$2+7,$H38>M$2),3, IF(AND($F38<=M$2, $H38>=M$2), 2, "" ))) | N38: =IF(AND($F38<(N$2+7),$F38>N$2),1, IF(AND($H38<N$2+7,$H38>N$2),3, IF(AND($F38<=N$2, $H38>=N$2), 2, "" ))) | O38: =IF(AND($F38<(O$2+7),$F38>O$2),1, IF(AND($H38<O$2+7,$H38>O$2),3, IF(AND($F38<=O$2, $H38>=O$2), 2, "" ))) | P38: =IF(AND($F38<(P$2+7),$F38>P$2),1, IF(AND($H38<P$2+7,$H38>P$2),3, IF(AND($F38<=P$2, $H38>=P$2), 2, "" ))) | Q38: =IF(AND($F38<(Q$2+7),$F38>Q$2),1, IF(AND($H38<Q$2+7,$H38>Q$2),3, IF(AND($F38<=Q$2, $H38>=Q$2), 2, "" ))) | R38: =IF(AND($F38<(R$2+7),$F38>R$2),1, IF(AND($H38<R$2+7,$H38>R$2),3, IF(AND($F38<=R$2, $H38>=R$2), 2, "" ))) | S38: =IF(AND($F38<(S$2+7),$F38>S$2),1, IF(AND($H38<S$2+7,$H38>S$2),3, IF(AND($F38<=S$2, $H38>=S$2), 2, "" ))) | ... AQ38: =IF(AND($F38<(AQ$2+7),$F38>AQ$2),1, IF(AND($H38<AQ$2+7,$H38>AQ$2),3, IF(AND($F38<=AQ$2, $H38>=AQ$2), 2, "" ))) -> 3
A39: 12 | B39: Commissioning | C39: 43997 | D39: 22 | E39: 44019 | F39: 43997 | G39: 22 | H39: 44019 | L39: =IF(AND($F39<(L$2+7),$F39>L$2),1, IF(AND($H39<L$2+7,$H39>L$2),3, IF(AND($F39<=L$2, $H39>=L$2), 2, "" ))) | M39: =IF(AND($F39<(M$2+7),$F39>M$2),1, IF(AND($H39<M$2+7,$H39>M$2),3, IF(AND($F39<=M$2, $H39>=M$2), 2, "" ))) | N39: =IF(AND($F39<(N$2+7),$F39>N$2),1, IF(AND($H39<N$2+7,$H39>N$2),3, IF(AND($F39<=N$2, $H39>=N$2), 2, "" ))) | O39: =IF(AND($F39<(O$2+7),$F39>O$2),1, IF(AND($H39<O$2+7,$H39>O$2),3, IF(AND($F39<=O$2, $H39>=O$2), 2, "" ))) | P39: =IF(AND($F39<(P$2+7),$F39>P$2),1, IF(AND($H39<P$2+7,$H39>P$2),3, IF(AND($F39<=P$2, $H39>=P$2), 2, "" ))) | Q39: =IF(AND($F39<(Q$2+7),$F39>Q$2),1, IF(AND($H39<Q$2+7,$H39>Q$2),3, IF(AND($F39<=Q$2, $H39>=Q$2), 2, "" ))) | R39: =IF(AND($F39<(R$2+7),$F39>R$2),1, IF(AND($H39<R$2+7,$H39>R$2),3, IF(AND($F39<=R$2, $H39>=R$2), 2, "" ))) | S39: =IF(AND($F39<(S$2+7),$F39>S$2),1, IF(AND($H39<S$2+7,$H39>S$2),3, IF(AND($F39<=S$2, $H39>=S$2), 2, "" ))) | ... AQ39: =IF(AND($F39<(AQ$2+7),$F39>AQ$2),1, IF(AND($H39<AQ$2+7,$H39>AQ$2),3, IF(AND($F39<=AQ$2, $H39>=AQ$2), 2, "" ))) -> 2
B40: Snag List | C40: 44014 | D40: 3 | E40: 44019 | F40: 44014 | G40: 3 | H40: 44019
B41: Pre-Commissioning Checks | C41: 44010 | D41: 2 | E41: 44012 | F41: 44010 | G41: 2 | H41: 44012
B42: Issue CoC | C42: 43997 | D42: 2 | E42: 44001 | F42: 43997 | G42: 2 | H42: 44001 | L42: =IF(AND($F42<(L$2+7),$F42>L$2),1, IF(AND($H42<L$2+7,$H42>L$2),3, IF(AND($F42<=L$2, $H42>=L$2), 2, "" ))) | M42: =IF(AND($F42<(M$2+7),$F42>M$2),1, IF(AND($H42<M$2+7,$H42>M$2),3, IF(AND($F42<=M$2, $H42>=M$2), 2, "" ))) | N42: =IF(AND($F42<(N$2+7),$F42>N$2),1, IF(AND($H42<N$2+7,$H42>N$2),3, IF(AND($F42<=N$2, $H42>=N$2), 2, "" ))) | O42: =IF(AND($F42<(O$2+7),$F42>O$2),1, IF(AND($H42<O$2+7,$H42>O$2),3, IF(AND($F42<=O$2, $H42>=O$2), 2, "" ))) | P42: =IF(AND($F42<(P$2+7),$F42>P$2),1, IF(AND($H42<P$2+7,$H42>P$2),3, IF(AND($F42<=P$2, $H42>=P$2), 2, "" ))) | Q42: =IF(AND($F42<(Q$2+7),$F42>Q$2),1, IF(AND($H42<Q$2+7,$H42>Q$2),3, IF(AND($F42<=Q$2, $H42>=Q$2), 2, "" ))) | R42: =IF(AND($F42<(R$2+7),$F42>R$2),1, IF(AND($H42<R$2+7,$H42>R$2),3, IF(AND($F42<=R$2, $H42>=R$2), 2, "" ))) | S42: =IF(AND($F42<(S$2+7),$F42>S$2),1, IF(AND($H42<S$2+7,$H42>S$2),3, IF(AND($F42<=S$2, $H42>=S$2), 2, "" ))) | ... AQ42: =IF(AND($F42<(AQ$2+7),$F42>AQ$2),1, IF(AND($H42<AQ$2+7,$H42>AQ$2),3, IF(AND($F42<=AQ$2, $H42>=AQ$2), 2, "" )))
B43: Cold Commissioning | C43: 44012 | D43: 1 | E43: 44013 | F43: 44012 | G43: 1 | H43: 44013 | L43: =IF(AND($F43<(L$2+7),$F43>L$2),1, IF(AND($H43<L$2+7,$H43>L$2),3, IF(AND($F43<=L$2, $H43>=L$2), 2, "" ))) | M43: =IF(AND($F43<(M$2+7),$F43>M$2),1, IF(AND($H43<M$2+7,$H43>M$2),3, IF(AND($F43<=M$2, $H43>=M$2), 2, "" ))) | N43: =IF(AND($F43<(N$2+7),$F43>N$2),1, IF(AND($H43<N$2+7,$H43>N$2),3, IF(AND($F43<=N$2, $H43>=N$2), 2, "" ))) | O43: =IF(AND($F43<(O$2+7),$F43>O$2),1, IF(AND($H43<O$2+7,$H43>O$2),3, IF(AND($F43<=O$2, $H43>=O$2), 2, "" ))) | P43: =IF(AND($F43<(P$2+7),$F43>P$2),1, IF(AND($H43<P$2+7,$H43>P$2),3, IF(AND($F43<=P$2, $H43>=P$2), 2, "" ))) | Q43: =IF(AND($F43<(Q$2+7),$F43>Q$2),1, IF(AND($H43<Q$2+7,$H43>Q$2),3, IF(AND($F43<=Q$2, $H43>=Q$2), 2, "" ))) | R43: =IF(AND($F43<(R$2+7),$F43>R$2),1, IF(AND($H43<R$2+7,$H43>R$2),3, IF(AND($F43<=R$2, $H43>=R$2), 2, "" ))) | S43: =IF(AND($F43<(S$2+7),$F43>S$2),1, IF(AND($H43<S$2+7,$H43>S$2),3, IF(AND($F43<=S$2, $H43>=S$2), 2, "" ))) | ... AQ43: =IF(AND($F43<(AQ$2+7),$F43>AQ$2),1, IF(AND($H43<AQ$2+7,$H43>AQ$2),3, IF(AND($F43<=AQ$2, $H43>=AQ$2), 2, "" ))) -> 3
B44: Hot Commissioning | C44: 44013 | D44: 2 | E44: 44015 | F44: 44013 | G44: 2 | H44: 44015 | L44: =IF(AND($F44<(L$2+7),$F44>L$2),1, IF(AND($H44<L$2+7,$H44>L$2),3, IF(AND($F44<=L$2, $H44>=L$2), 2, "" ))) | M44: =IF(AND($F44<(M$2+7),$F44>M$2),1, IF(AND($H44<M$2+7,$H44>M$2),3, IF(AND($F44<=M$2, $H44>=M$2), 2, "" ))) | N44: =IF(AND($F44<(N$2+7),$F44>N$2),1, IF(AND($H44<N$2+7,$H44>N$2),3, IF(AND($F44<=N$2, $H44>=N$2), 2, "" ))) | O44: =IF(AND($F44<(O$2+7),$F44>O$2),1, IF(AND($H44<O$2+7,$H44>O$2),3, IF(AND($F44<=O$2, $H44>=O$2), 2, "" ))) | P44: =IF(AND($F44<(P$2+7),$F44>P$2),1, IF(AND($H44<P$2+7,$H44>P$2),3, IF(AND($F44<=P$2, $H44>=P$2), 2, "" ))) | Q44: =IF(AND($F44<(Q$2+7),$F44>Q$2),1, IF(AND($H44<Q$2+7,$H44>Q$2),3, IF(AND($F44<=Q$2, $H44>=Q$2), 2, "" ))) | R44: =IF(AND($F44<(R$2+7),$F44>R$2),1, IF(AND($H44<R$2+7,$H44>R$2),3, IF(AND($F44<=R$2, $H44>=R$2), 2, "" ))) | S44: =IF(AND($F44<(S$2+7),$F44>S$2),1, IF(AND($H44<S$2+7,$H44>S$2),3, IF(AND($F44<=S$2, $H44>=S$2), 2, "" ))) | ... AQ44: =IF(AND($F44<(AQ$2+7),$F44>AQ$2),1, IF(AND($H44<AQ$2+7,$H44>AQ$2),3, IF(AND($F44<=AQ$2, $H44>=AQ$2), 2, "" ))) -> 1
A45: 13 | B45: Handover | C45: 44020 | D45: 1 | E45: 44021 | F45: 44020 | G45: 1 | H45: 44021 | L45: =IF(AND($F45<(L$2+7),$F45>L$2),1, IF(AND($H45<L$2+7,$H45>L$2),3, IF(AND($F45<=L$2, $H45>=L$2), 2, "" ))) | M45: =IF(AND($F45<(M$2+7),$F45>M$2),1, IF(AND($H45<M$2+7,$H45>M$2),3, IF(AND($F45<=M$2, $H45>=M$2), 2, "" ))) | N45: =IF(AND($F45<(N$2+7),$F45>N$2),1, IF(AND($H45<N$2+7,$H45>N$2),3, IF(AND($F45<=N$2, $H45>=N$2), 2, "" ))) | O45: =IF(AND($F45<(O$2+7),$F45>O$2),1, IF(AND($H45<O$2+7,$H45>O$2),3, IF(AND($F45<=O$2, $H45>=O$2), 2, "" ))) | P45: =IF(AND($F45<(P$2+7),$F45>P$2),1, IF(AND($H45<P$2+7,$H45>P$2),3, IF(AND($F45<=P$2, $H45>=P$2), 2, "" ))) | Q45: =IF(AND($F45<(Q$2+7),$F45>Q$2),1, IF(AND($H45<Q$2+7,$H45>Q$2),3, IF(AND($F45<=Q$2, $H45>=Q$2), 2, "" ))) | R45: =IF(AND($F45<(R$2+7),$F45>R$2),1, IF(AND($H45<R$2+7,$H45>R$2),3, IF(AND($F45<=R$2, $H45>=R$2), 2, "" ))) | S45: =IF(AND($F45<(S$2+7),$F45>S$2),1, IF(AND($H45<S$2+7,$H45>S$2),3, IF(AND($F45<=S$2, $H45>=S$2), 2, "" ))) | ... AQ45: =IF(AND($F45<(AQ$2+7),$F45>AQ$2),1, IF(AND($H45<AQ$2+7,$H45>AQ$2),3, IF(AND($F45<=AQ$2, $H45>=AQ$2), 2, "" )))
A46: E | B46: PAYMENT MILESTONE 6: HANDOVER COMPLETE | C46: 44022 | D46: 1 | E46: 44025 | F46: 44022 | G46: 1 | H46: 44025
C47: 43831 | D47: These numbers are used to set the start and end dates on the Gantt Chart
C48: 44014

Sheet Revenue Tracking
B2: HIGH LEVEL PROJECT REVENUE TRACKING
D3: COSTED | F3: ACTUAL | L3: FINANCIAL REVIEW | N3: TIMELINE REVIEW | R3: Allocated in 2025 | S3: Budgeted | T3: Actual | W3: 2025 Actual Revenue | X3: 2025 Actual COS | Y3: 2026 Budget Revenue | Z3: 2026 Budget COS | AA3: 2026 Actual Revenue | AB3: 2026 Actual COS
B4: 1 | C4: Planned Revenue | D4: ='Project Plan'!E6 -> 59995000 | F4: =F23 -> 59995000 | L4: 59995000 | N4: Start Date | P4: Sales | S4: =F4-R4 -> 59995000 | T4: =F4-R4 -> 59995000 | W4: =SUMIFS('Expenditure Breakdown'!$U:$U, 'Expenditure Breakdown'!$T:$T, ">"&DATE(2024,8,31), 'Expenditure Breakdown'!$T:$T, "<="&DATE(2025,8,31), 'Expenditure Breakdown'!$S:$S, "<>") -> 44416314 | X4: =SUMIFS('Expenditure Breakdown'!$Q:$Q, 'Expenditure Breakdown'!$T:$T, ">"&DATE(2024,8,31), 'Expenditure Breakdown'!$T:$T, "<="&DATE(2025,8,31), 'Expenditure Breakdown'!$S:$S, "<>") -> 37030035 | Y4: =SUMIFS('Expenditure Breakdown'!$U:$U, 'Expenditure Breakdown'!$T:$T, ">"&DATE(2025,8,31), 'Expenditure Breakdown'!$T:$T, "<="&DATE(2026,8,31)) -> 13731172 | Z4: =SUMIFS('Expenditure Breakdown'!$Q:$Q, 'Expenditure Breakdown'!$T:$T, ">"&DATE(2025,8,31), 'Expenditure Breakdown'!$T:$T, "<="&DATE(2026,8,31)) -> 11662156 | AA4: =SUMIFS('Expenditure Breakdown'!$U:$U, 'Expenditure Breakdown'!$T:$T, ">"&DATE(2025,8,31), 'Expenditure Breakdown'!$T:$T, "<="&DATE(2026,8,31), 'Expenditure Breakdown'!$S:$S, "<>") -> 12424762 | AB4: =SUMIFS('Expenditure Breakdown'!$Q:$Q, 'Expenditure Breakdown'!$T:$T, ">"&DATE(2025,8,31), 'Expenditure Breakdown'!$T:$T, "<="&DATE(2026,8,31), 'Expenditure Breakdown'!$S:$S, "<>") -> 8578068.9
B5: 2 | C5: Planned Expenditure | D5: =+'Expenditure Tracking'!F5 -> 56096452 | F5: =+'Expenditure Tracking'!H5 -> 48692192 | G5: VO PM Limit | H5: Current VO Total | L5: 46345971 | N5: 45894 | P5: COS | S5: =F5-R5 -> 48692192 | T5: =F5-R5 -> 48692192
B6: 3 | C6: Planned Profit | D6: =+D4-D5 -> 3898547.9 | F6: =+F4-F5 -> 11302808 | G6: =D6*0.05 -> 194927.4 | H6: =SUMIF('Expenditure Breakdown'!N:N,"*VO*",'Expenditure Breakdown'!Q:Q) -> 0 | L6: 13649029 | N6: End Date - PC | P6: GP | R6: =R4-R5 -> 0 | S6: =S4-S5 -> 11302808 | T6: =T4-T5 -> 11302808
B7: 4 | C7: Planned Margin | D7: =+D6/D4 -> 0.064981214 | F7: =+F6/F4 -> 0.18839584 | L7: 0.22750277 | N7: 45982
B10: CONTRACT
B12: No. | C12: PAYMENT MILESTONE | E12: % | F12: VALUE | H12: PLANNED PAYMENT DATE | L12: INVOICE NUMBER | N12: INVOICE RAISED DATE | P12: PAYMENT RECEIVED DATE | R12: MILESTONE NOTES & COMMENTS
B13: 1 | C13: Deposit - Coega Steel | E13: 0.25 | F13: 15000000 | H13: 45808 | L13: 004753 | N13: 45805 | P13: 45828
B14: 2 | C14: Delivery of Panels - Batch 1 | E14: 0.15 | F14: =($D$4*E14)-1250 -> 8998000 | H14: =P14 -> 45898 | L14: 004823 | N14: 45895 | P14: 45898
B15: 3 | C15: Delivery of Panels - Batch 2 | E15: 0.15 | F15: =$D$4*E15 -> 8999250 | H15: 45922 | L15: 004838 | N15: 45912 | P15: 45918
B16: 4 | C16: Delivery of Inverters | E16: 0.3 | F16: =$D$4*E16 -> 17998500 | H16: =P16 -> 45862 | L16: 004783 | N16: 45852 | P16: 45862
B17: 5 | C17: Practical Completion | E17: 0.1 | F17: =33990.72/1.15 -> 29557.148 | H17: ='Project Plan'!G99+7 -> 45980 | L17: 004933 | N17: 46055 | P17: 46002
B18: 5 | C18: Practical Completion | F18: =23326.12/1.15 -> 20283.583 | H18: 45980 | L18: 004933 | N18: 46055 | P18: 46002
B19: 5 | C19: Practical Completion | F19: =5999500-F17-F18 -> 5949659.3 | H19: 45980 | L19: 004933 | N19: 46055 | P19: 46062 | R19: Completion Certificate to be shared
B20: 6 | C20: Handover | E20: 0.05 | F20: =$D$4*E20 -> 2999750 | H20: ='Project Plan'!E122+7 -> 45999 | P20: ='Project Plan'!I122+60 -> 46137
B21: 7 | C21: - | E21: 0 | F21: =$D$4*E21 -> 0
E23: =SUM(E13:E21) -> 1 | F23: =SUM(F13:F21) -> 59995000
B25: KEY: | C25: contains an error (in result or a check has failed)
C26: Red Font - IF TEXT : content not yet confirmed | F26: =F17+F18+F19 -> 5999500
C27: Red Font - IF NUMBER: Negative value
C28: Anything in yellow is a concern or risk for noting or action
C29: confirmed
C30: [ADD INITIALS: comment for noting in square brackets, use colour or red to draw attention if important]
C31: [RT: When adding rows into sheet, ensure you insert between first and last row of each category]
C32: end of sheet - do not insert information below/beyond this

Sheet Data
C2: Public holidays | F2: Drop down list
C3: 45658 | D3: New Years Day | F3: Approved
C4: 45737 | D4: Human Rights day | F4: Pending
C5: 45765 | D5: Good Friday | F5: Declined
C6: 45768 | D6: Family Day | F6: Abanded
C7: 45774 | D7: Freedom Day
C8: 45765 | D8: Freedom DayObserved
C9: 45778 | D9: Workers day
C10: 45824 | D10: Youth Day Holiday
C11: 45878 | D11: Womens Day
C12: 45924 | D12: Heritage Day
H13: Manual dates
C17: 46011 | D17: Builders Break
C18: 46012 | D18: Builders Break
C19: 46013 | D19: Builders Break
C20: 46014 | D20: Builders Break
C21: 46015 | D21: Builders Break
C22: 46016 | D22: Builders Break
C23: 46017 | D23: Builders Break
C24: 46018 | D24: Builders Break
C25: 46019 | D25: Builders Break
C26: 46020 | D26: Builders Break
C27: 46021 | D27: Builders Break
C28: 46022 | D28: Builders Break
... C42: 46017 | D42: Day of Goodwill

Sheet Project Plan
N1: =TODAY() -> 46063 | O1: =TODAY() -> 46063
C2: PROJECT PLAN | E2: Coega Steels Phase 2 | N2: 0 | O2: 1
C3: PROJECT SIZE (kWp) | E3: 7080
C4: PROJECT DEVELOPER | E4: Gordon Upton
C5: PROJECT MANAGERS | E5: Lloyd Brown
C6: CONTRACT VALUE | E6: 59995000
C7: Phase: | E7: QA
B8: No. | C8: HIGH LEVEL PROGRAMME | E8: Planned Start | F8: Duration (work days) | G8: Planned End | I8: Actual Start | J8: Duration (work days) | K8: Actual End | M8: Status | N8: Expected Status | O8: Comment
F9: =G108-E19 -> 160 | J9: =K108-I19 -> 240 | M9: =AVERAGE(M11,M18,M32,M42,M58,M67,M74,M81,M88,M98,M110,M117) -> 0.88194444 | N9: =AVERAGE(N11,N18,N32,N42,N58,N67,N74,N81,N88,N98,N110,N117) -> 0.93781746
B11: 1 | C11: Project Initiation | E11: =MIN(E12:E16) -> 45796 | F11: =G11-E11 -> 74 | G11: =MAX(G12:G16) -> 45870 | I11: =MIN(I12:I16) -> 45796 | J11: =K11-I11 -> 74 | K11: =MAX(K12:K16) -> 45870 | M11: =AVERAGE(M12:M16) -> 1 | N11: =AVERAGE(N12:N16) -> 1
B12: =B11+0.1 -> 1.1 | C12: PD Handover | E12: 45796 | F12: 1 | G12: =WORKDAY.INTL(E12,F12,1,Data!$C$3:$C$41) -> 45797 | I12: 45796 | J12: 1 | K12: =WORKDAY.INTL(I12,J12,1,Data!$C$3:$C$41) -> 45797 | M12: 1 | N12: =_xlfn.LET( _xlpm.s,VALUE(I12), _xlpm.e,VALUE(K12), IF(OR(_xlpm.s="",_xlpm.e=""),"", IF(_xlpm.e<=_xlpm.s, IF(TODAY()>=_xlpm.e,1,0), MAX(0,MIN(1,(TODAY()-_xlpm.s)/(_xlpm.e-_xlpm.s))))) ) -> 1
B13: =B12+0.1 -> 1.2 | C13: Financial Close | E13: =WORKDAY.INTL(E19,0,1,Data!$C$3:$C$41)-7 -> 45808 | F13: 1 | G13: =WORKDAY.INTL(E13,F13,1,Data!$C$3:$C$41) -> 45810 | I13: =WORKDAY.INTL(I19,0,1,Data!$C$3:$C$41)-7 -> 45808 | J13: 1 | K13: =WORKDAY.INTL(I13,J13,1,Data!$C$3:$C$41) -> 45810 | M13: 1 | N13: =_xlfn.LET( _xlpm.s,VALUE(I13), _xlpm.e,VALUE(K13), IF(OR(_xlpm.s="",_xlpm.e=""),"", IF(_xlpm.e<=_xlpm.s, IF(TODAY()>=_xlpm.e,1,0), MAX(0,MIN(1,(TODAY()-_xlpm.s)/(_xlpm.e-_xlpm.s))))) ) -> 1
B14: =B13+0.1 -> 1.3 | C14: Structural Assessment | E14: =E12 -> 45796 | F14: 1 | G14: =WORKDAY.INTL(E14,F14,1,Data!$C$3:$C$41) -> 45797 | I14: =I12 -> 45796 | J14: 1 | K14: =WORKDAY.INTL(I14,J14,1,Data!$C$3:$C$41) -> 45797 | M14: 1 | N14: =_xlfn.LET( _xlpm.s,VALUE(I14), _xlpm.e,VALUE(K14), IF(OR(_xlpm.s="",_xlpm.e=""),"", IF(_xlpm.e<=_xlpm.s, IF(TODAY()>=_xlpm.e,1,0), MAX(0,MIN(1,(TODAY()-_xlpm.s)/(_xlpm.e-_xlpm.s))))) ) -> 1
B15: =B14+0.1 -> 1.4 | C15: Project Introduction | E15: 45867 | F15: 1 | G15: =WORKDAY.INTL(E15,F15,1,Data!$C$3:$C$41) -> 45868 | I15: 45867 | J15: 1 | K15: =WORKDAY.INTL(I15,J15,1,Data!$C$3:$C$41) -> 45868 | M15: 1 | N15: =_xlfn.LET( _xlpm.s,VALUE(I15), _xlpm.e,VALUE(K15), IF(OR(_xlpm.s="",_xlpm.e=""),"", IF(_xlpm.e<=_xlpm.s, IF(TODAY()>=_xlpm.e,1,0), MAX(0,MIN(1,(TODAY()-_xlpm.s)/(_xlpm.e-_xlpm.s))))) ) -> 1 | Y15: 0
B16: =B15+0.1 -> 1.5 | C16: Project Review | E16: 45870 | F16: 0 | G16: =WORKDAY.INTL(E16,F16,1,Data!$C$3:$C$41) -> 45870 | I16: 45870 | J16: 0 | K16: =WORKDAY.INTL(I16,J16,1,Data!$C$3:$C$41) -> 45870 | M16: 1 | N16: =_xlfn.LET( _xlpm.s,VALUE(I16), _xlpm.e,VALUE(K16), IF(OR(_xlpm.s="",_xlpm.e=""),"", IF(_xlpm.e<=_xlpm.s, IF(TODAY()>=_xlpm.e,1,0), MAX(0,MIN(1,(TODAY()-_xlpm.s)/(_xlpm.e-_xlpm.s))))) ) -> 1 | Y16: 1
B18: 2 | C18: Site Establishment Preperation | E18: =MIN(E19:E31) -> 45815 | F18: =G18-E18 -> 6 | G18: =MAX(G19) -> 45821 | I18: =MIN(I19:I31) -> 45815 | J18: =K18-I18 -> 95 | K18: =MAX(K19:K30) -> 45910 | M18: =AVERAGE(M19:M30) -> 1 | N18: =AVERAGE(N19:N30) -> 1 | S18: Milestone | T18: Start Date | U18: Total Duration | V18: Total WorkDays | W18: End Date | X18: Progress Percentage | Y18: Project Overall Progress Percentage
B19: =B18+0.1 -> 2.1 | C19: HSE Requirements | E19: 45815 | F19: 5 | G19: =WORKDAY.INTL(E19,F19,1,Data!$C$3:$C$41) -> 45821 | I19: 45815 | J19: 5 | K19: =WORKDAY.INTL(I19,J19,1,Data!$C$3:$C$41) -> 45821 | M19: 1 | N19: =_xlfn.LET( _xlpm.s,VALUE(I19), _xlpm.e,VALUE(K19), IF(OR(_xlpm.s="",_xlpm.e=""),"", IF(_xlpm.e<=_xlpm.s, IF(TODAY()>=_xlpm.e,1,0), MAX(0,MIN(1,(TODAY()-_xlpm.s)/(_xlpm.e-_xlpm.s))))) ) -> 1 | S19: =C32 -> Procurement & Contracting | T19: =I32 -> 45796 | U19: =J32 -> 193 | V19: =F32 -> 124 | W19: =K32 -> 45989 | X19: =M32 -> 1 | Y19: =M9 -> 0.88194444
B20: =B19+0.1 -> 2.2 | C20: EE File | E20: =WORKDAY.INTL(G18,0,1,Data!$C$3:$C$41) -> 45821 | F20: 17 | G20: =WORKDAY.INTL(E20,F20,1,Data!$C$3:$C$41) -> 45847 | I20: =WORKDAY.INTL(K19,0,1,Data!$C$3:$C$41) -> 45821 | J20: 17 | K20: =WORKDAY.INTL(I20,J20,1,Data!$C$3:$C$41) -> 45847 | M20: 1 | N20: =_xlfn.LET( _xlpm.s,VALUE(I20), _xlpm.e,VALUE(K20), IF(OR(_xlpm.s="",_xlpm.e=""),"", IF(_xlpm.e<=_xlpm.s, IF(TODAY()>=_xlpm.e,1,0), MAX(0,MIN(1,(TODAY()-_xlpm.s)/(_xlpm.e-_xlpm.s))))) ) -> 1 | S20: =C42 -> Extras & Civil Works | T20: =I42 -> 45830 | U20: =J42 -> 212 | V20: =F42 -> 71 | W20: =K42 -> 46042 | X20: =M42 -> 1
B21: =B20+0.1 -> 2.3 | C21: Subcontractor File - Solar Contractor | E21: =WORKDAY.INTL(G20,0,1,Data!$C$3:$C$41) -> 45847 | F21: 8 | G21: =WORKDAY.INTL(E21,F21,1,Data!$C$3:$C$41) -> 45859 | I21: =WORKDAY.INTL(K20,0,1,Data!$C$3:$C$41) -> 45847 | J21: 31 | K21: =WORKDAY.INTL(I21,J21,1,Data!$C$3:$C$41) -> 45890 | M21: 1 | N21: =_xlfn.LET( _xlpm.s,VALUE(I21), _xlpm.e,VALUE(K21), IF(OR(_xlpm.s="",_xlpm.e=""),"", IF(_xlpm.e<=_xlpm.s, IF(TODAY()>=_xlpm.e,1,0), MAX(0,MIN(1,(TODAY()-_xlpm.s)/(_xlpm.e-_xlpm.s))))) ) -> 1 | S21: =C58 -> DC Works - Rooftop | T21: =I58 -> 45894 | U21: =J58 -> 147 | V21: =F58 -> 51 | W21: =K58 -> 46041 | X21: =M58 -> 1 | AE21: =TODAY() -> 46063 | AF21: =TODAY() -> 46063
B22: =B21+0.1 -> 2.4 | C22: Subcontractor File - Civil Contractor (Bay View Construction & Engineering Hub) | I22: 45875 | J22: 25 | K22: =WORKDAY.INTL(I22,J22,1,Data!$C$3:$C$41) -> 45910 | M22: 1 | N22: =_xlfn.LET( _xlpm.s,VALUE(I22), _xlpm.e,VALUE(K22), IF(OR(_xlpm.s="",_xlpm.e=""),"", IF(_xlpm.e<=_xlpm.s, IF(TODAY()>=_xlpm.e,1,0), MAX(0,MIN(1,(TODAY()-_xlpm.s)/(_xlpm.e-_xlpm.s))))) ) -> 1 | O22: Bayview file pending - awaiting Medical approvals | S22: =C67 -> DC Works - Ground Mount | T22: =I67 -> 45938 | U22: =J67 -> 120 | V22: =F67 -> 58 | W22: =K67 -> 46058 | X22: =M67 -> 0.99 | AE22: 1 | AF22: 0
B23: =B22+0.1 -> 2.5 | C23: Subcontractor File - Anchor Point Contractor | E23: =WORKDAY.INTL(G20,0,1,Data!$C$3:$C$41) -> 45847 | F23: 8 | G23: =WORKDAY.INTL(E23,F23,1,Data!$C$3:$C$41) -> 45859 | I23: =WORKDAY.INTL(K20,0,1,Data!$C$3:$C$41) -> 45847 | J23: 31 | K23: =WORKDAY.INTL(I23,J23,1,Data!$C$3:$C$41) -> 45890 | M23: 1 | N23: =_xlfn.LET( _xlpm.s,VALUE(I23), _xlpm.e,VALUE(K23), IF(OR(_xlpm.s="",_xlpm.e=""),"", IF(_xlpm.e<=_xlpm.s, IF(TODAY()>=_xlpm.e,1,0), MAX(0,MIN(1,(TODAY()-_xlpm.s)/(_xlpm.e-_xlpm.s))))) ) -> 1 | S23: =C74 -> AC Installation - Ground Mount | T23: =I74 -> 45990 | U23: =J74 -> 17 | V23: =F74 -> 26 | W23: =K74 -> 46007 | X23: =M74 -> 1
B24: =B23+0.1 -> 2.6 | C24: HSE Permit Issued | I24: 45847 | J24: 33 | K24: =WORKDAY.INTL(I24,J24,1,Data!$C$3:$C$41) -> 45894 | M24: 1 | N24: =_xlfn.LET( _xlpm.s,VALUE(I24), _xlpm.e,VALUE(K24), IF(OR(_xlpm.s="",_xlpm.e=""),"", IF(_xlpm.e<=_xlpm.s, IF(TODAY()>=_xlpm.e,1,0), MAX(0,MIN(1,(TODAY()-_xlpm.s)/(_xlpm.e-_xlpm.s))))) ) -> 1 | O24: CDC/Coega Delays | S24: =C81 -> AC Installation - Rooftop | T24: =I81 -> 45915 | U24: =J81 -> 92 | V24: =F81 -> 21 | W24: =K81 -> 46007 | X24: =M81 -> 1
B25: =B24+0.1 -> 2.7 | C25: Establishment of site entry & Exit points | I25: 45867 | J25: 0 | K25: =WORKDAY.INTL(I25,J25,1,Data!$C$3:$C$41) -> 45867 | M25: 1 | N25: =_xlfn.LET( _xlpm.s,VALUE(I25), _xlpm.e,VALUE(K25), IF(OR(_xlpm.s="",_xlpm.e=""),"", IF(_xlpm.e<=_xlpm.s, IF(TODAY()>=_xlpm.e,1,0), MAX(0,MIN(1,(TODAY()-_xlpm.s)/(_xlpm.e-_xlpm.s))))) ) -> 1 | S25: =C88 -> Transformer Installation | T25: =I88 -> 45986 | U25: =J88 -> 22 | V25: =F88 -> 43 | W25: =K88 -> 46008 | X25: =M88 -> 1
B26: =B25+0.1 -> 2.8 | C26: Laydown Area Demarcated | I26: 45867 | J26: 0 | K26: =WORKDAY.INTL(I26,J26,1,Data!$C$3:$C$41) -> 45867 | M26: 1 | N26: =_xlfn.LET( _xlpm.s,VALUE(I26), _xlpm.e,VALUE(K26), IF(OR(_xlpm.s="",_xlpm.e=""),"", IF(_xlpm.e<=_xlpm.s, IF(TODAY()>=_xlpm.e,1,0), MAX(0,MIN(1,(TODAY()-_xlpm.s)/(_xlpm.e-_xlpm.s))))) ) -> 1 | S26: =C98 -> Commissioning | T26: =I98 -> 46006 | U26: =J98 -> 59 | V26: =F98 -> 4 | W26: =K98 -> 46065 | X26: =M98 -> 0.89
B27: =B26+0.1 -> 2.9 | C27: Ground Mount Demarcated | I27: 45867 | J27: 0 | K27: =WORKDAY.INTL(I27,J27,1,Data!$C$3:$C$41) -> 45867 | M27: 1 | N27: =_xlfn.LET( _xlpm.s,VALUE(I27), _xlpm.e,VALUE(K27), IF(OR(_xlpm.s="",_xlpm.e=""),"", IF(_xlpm.e<=_xlpm.s, IF(TODAY()>=_xlpm.e,1,0), MAX(0,MIN(1,(TODAY()-_xlpm.s)/(_xlpm.e-_xlpm.s))))) ) -> 1 | S27: =C110 -> QA Inspection & Snag Completion | T27: =I110 -> 46048 | U27: =J110 -> 22 | V27: =F110 -> 58 | W27: =K110 -> 46070 | X27: =M110 -> 0.52
B28: 2.1 | C28: Designated area fencing | I28: 45867 | J28: 0 | K28: =WORKDAY.INTL(I28,J28,1,Data!$C$3:$C$41) -> 45867 | M28: 1 | N28: =_xlfn.LET( _xlpm.s,VALUE(I28), _xlpm.e,VALUE(K28), IF(OR(_xlpm.s="",_xlpm.e=""),"", IF(_xlpm.e<=_xlpm.s, IF(TODAY()>=_xlpm.e,1,0), MAX(0,MIN(1,(TODAY()-_xlpm.s)/(_xlpm.e-_xlpm.s))))) ) -> 1 | S28: =C117 -> Project Closure | T28: =I117 -> 46006 | U28: =J117 -> 72 | V28: =F117 -> 70 | W28: =K117 -> 46078 | X28: =M117 -> 0.18333333
B29: 2.11 | C29: Site Ablutions | I29: 45867 | J29: 21 | K29: =WORKDAY.INTL(I29,J29,1,Data!$C$3:$C$41) -> 45896 | M29: 1 | N29: =_xlfn.LET( _xlpm.s,VALUE(I29), _xlpm.e,VALUE(K29), IF(OR(_xlpm.s="",_xlpm.e=""),"", IF(_xlpm.e<=_xlpm.s, IF(TODAY()>=_xlpm.e,1,0), MAX(0,MIN(1,(TODAY()-_xlpm.s)/(_xlpm.e-_xlpm.s))))) ) -> 1 | O29: Appointment finalised by eow
B30: 2.12 | C30: Site Establishment Permit Issued | I30: 45867 | J30: =K30-I30 -> 23 | K30: =K23 -> 45890 | M30: 1 | N30: =_xlfn.LET( _xlpm.s,VALUE(I30), _xlpm.e,VALUE(K30), IF(OR(_xlpm.s="",_xlpm.e=""),"", IF(_xlpm.e<=_xlpm.s, IF(TODAY()>=_xlpm.e,1,0), MAX(0,MIN(1,(TODAY()-_xlpm.s)/(_xlpm.e-_xlpm.s))))) ) -> 1
B32: 3 | C32: Procurement & Contracting | E32: =MIN(E33:E40) -> 45795 | F32: =G32-E32 -> 124 | G32: =MAX(G33:G40) -> 45919 | I32: 45796 | J32: =K32-I32 -> 193 | K32: =MAX(K33:K40) -> 45989 | M32: =AVERAGE(M33:M40) -> 1 | N32: =AVERAGE(N33:N40) -> 1
B33: =B32+0.1 -> 3.1 | C33: Huawei Transformers (16 weeks lead time) | E33: 45795 | F33: 89 | G33: =WORKDAY.INTL(E33,F33,1,Data!$C$3:$C$41) -> 45919 | I33: 45795 | J33: 138 | K33: =WORKDAY.INTL(I33,J33,1,Data!$C$3:$C$41) -> 45989 | M33: 1 | N33: =_xlfn.LET( _xlpm.s,VALUE(I33), _xlpm.e,VALUE(K33), IF(OR(_xlpm.s="",_xlpm.e=""),"", IF(_xlpm.e<=_xlpm.s, IF(TODAY()>=_xlpm.e,1,0), MAX(0,MIN(1,(TODAY()-_xlpm.s)/(_xlpm.e-_xlpm.s))))) ) -> 1 | O33: Delay of shipping as of 14 Oct
B34: =B33+0.1 -> 3.2 | C34: Panels (6 - 8 Weeks) | E34: 45820 | F34: 36 | G34: =WORKDAY.INTL(E34,F34,1,Data!$C$3:$C$41) -> 45873 | I34: 45820 | J34: 93 | K34: =WORKDAY.INTL(I34,J34,1,Data!$C$3:$C$41) -> 45953 | M34: 1 | N34: =_xlfn.LET( _xlpm.s,VALUE(I34), _xlpm.e,VALUE(K34), IF(OR(_xlpm.s="",_xlpm.e=""),"", IF(_xlpm.e<=_xlpm.s, IF(TODAY()>=_xlpm.e,1,0), MAX(0,MIN(1,(TODAY()-_xlpm.s)/(_xlpm.e-_xlpm.s))))) ) -> 1 | O34: 30 pallets deliverd 26/08; 90 pallets 15 Oct; 185 pallets 20 Oct
B35: =B34+0.1 -> 3.3 | C35: Ground Mount Structure (10 Weeks) | E35: 45820 | F35: 58 | G35: =WORKDAY.INTL(E35,F35,1,Data!$C$3:$C$41) -> 45903 | I35: 45820 | J35: 66 | K35: =WORKDAY.INTL(I35,J35,1,Data!$C$3:$C$41) -> 45915 | M35: 1 | N35: =_xlfn.LET( _xlpm.s,VALUE(I35), _xlpm.e,VALUE(K35), IF(OR(_xlpm.s="",_xlpm.e=""),"", IF(_xlpm.e<=_xlpm.s, IF(TODAY()>=_xlpm.e,1,0), MAX(0,MIN(1,(TODAY()-_xlpm.s)/(_xlpm.e-_xlpm.s))))) ) -> 1
B36: =B35+0.1 -> 3.4 | C36: Inverters (8 to 12 weeks) | E36: 45820 | F36: 18 | G36: =WORKDAY.INTL(E36,F36,1,Data!$C$3:$C$41) -> 45847 | I36: 45820 | J36: 18 | K36: =WORKDAY.INTL(I36,J36,1,Data!$C$3:$C$41) -> 45847 | M36: 1 | N36: =_xlfn.LET( _xlpm.s,VALUE(I36), _xlpm.e,VALUE(K36), IF(OR(_xlpm.s="",_xlpm.e=""),"", IF(_xlpm.e<=_xlpm.s, IF(TODAY()>=_xlpm.e,1,0), MAX(0,MIN(1,(TODAY()-_xlpm.s)/(_xlpm.e-_xlpm.s))))) ) -> 1
B37: =B36+0.1 -> 3.5 | C37: DC Cable | E37: 45820 | F37: 18 | G37: =WORKDAY.INTL(E37,F37,1,Data!$C$3:$C$41) -> 45847 | I37: 45820 | J37: 66 | K37: =WORKDAY.INTL(I37,J37,1,Data!$C$3:$C$41) -> 45915 | M37: 1 | N37: =_xlfn.LET( _xlpm.s,VALUE(I37), _xlpm.e,VALUE(K37), IF(OR(_xlpm.s="",_xlpm.e=""),"", IF(_xlpm.e<=_xlpm.s, IF(TODAY()>=_xlpm.e,1,0), MAX(0,MIN(1,(TODAY()-_xlpm.s)/(_xlpm.e-_xlpm.s))))) ) -> 1
B38: =B37+0.1 -> 3.6 | C38: LV Cable (2-4 Weeks) | E38: 45855 | F38: 10 | G38: =WORKDAY.INTL(E38,F38,1,Data!$C$3:$C$41) -> 45869 | I38: 45855 | J38: 10 | K38: =WORKDAY.INTL(I38,J38,1,Data!$C$3:$C$41) -> 45869 | M38: 1 | N38: =_xlfn.LET( _xlpm.s,VALUE(I38), _xlpm.e,VALUE(K38), IF(OR(_xlpm.s="",_xlpm.e=""),"", IF(_xlpm.e<=_xlpm.s, IF(TODAY()>=_xlpm.e,1,0), MAX(0,MIN(1,(TODAY()-_xlpm.s)/(_xlpm.e-_xlpm.s))))) ) -> 1
B39: =B38+0.1 -> 3.7 | C39: MV Cable (2-4 Weeks) | E39: 45855 | F39: 10 | G39: =WORKDAY.INTL(E39,F39,1,Data!$C$3:$C$41) -> 45869 | I39: 45855 | J39: 10 | K39: =WORKDAY.INTL(I39,J39,1,Data!$C$3:$C$41) -> 45869 | M39: 1 | N39: =_xlfn.LET( _xlpm.s,VALUE(I39), _xlpm.e,VALUE(K39), IF(OR(_xlpm.s="",_xlpm.e=""),"", IF(_xlpm.e<=_xlpm.s, IF(TODAY()>=_xlpm.e,1,0), MAX(0,MIN(1,(TODAY()-_xlpm.s)/(_xlpm.e-_xlpm.s))))) ) -> 1
B40: =B39+0.1 -> 3.8 | C40: Distribution Boards (6 - 8 Weeks) | E40: 45848 | F40: 20 | G40: =WORKDAY.INTL(E40,F40,1,Data!$C$3:$C$41) -> 45876 | I40: 45848 | J40: 34 | K40: =WORKDAY.INTL(I40,J40,1,Data!$C$3:$C$41) -> 45896 | M40: 1 | N40: =_xlfn.LET( _xlpm.s,VALUE(I40), _xlpm.e,VALUE(K40), IF(OR(_xlpm.s="",_xlpm.e=""),"", IF(_xlpm.e<=_xlpm.s, IF(TODAY()>=_xlpm.e,1,0), MAX(0,MIN(1,(TODAY()-_xlpm.s)/(_xlpm.e-_xlpm.s))))) ) -> 1 | O40: ABB hold up on the breakers
B42: 4 | C42: Extras & Civil Works | E42: =MIN(E43:E56) -> 45830 | F42: =G42-E42 -> 71 | G42: =MAX(G43:G56) -> 45901 | I42: =MIN(I43:I56) -> 45830 | J42: =K42-I42 -> 212 | K42: =MAX(K43:K56) -> 46042 | M42: =AVERAGE(M43:M56) -> 1 | N42: =AVERAGE(N43:N56) -> 1
B43: =B42+0.1 -> 4.1 | C43: Staircase Installation - Coega Scope | I43: 45830 | J43: 61 | K43: =WORKDAY.INTL(I43,J43,1,Data!$C$3:$C$41) -> 45915 | M43: 1 | N43: =_xlfn.LET( _xlpm.s,VALUE(I43), _xlpm.e,VALUE(K43), IF(OR(_xlpm.s="",_xlpm.e=""),"", IF(_xlpm.e<=_xlpm.s, IF(TODAY()>=_xlpm.e,1,0), MAX(0,MIN(1,(TODAY()-_xlpm.s)/(_xlpm.e-_xlpm.s))))) ) -> 1 | O43: Follow up with Coega
B44: =B43+0.1 -> 4.2 | C44: Ground Mount Fence - Coega Scope | E44: 45830 | F44: 42 | G44: =WORKDAY.INTL(E44,F44,1,Data!$C$3:$C$41) -> 45888 | I44: 45830 | J44: 135 | K44: =WORKDAY.INTL(I44,J44,1,Data!$C$3:$C$41) -> 46042 | M44: 1 | N44: =_xlfn.LET( _xlpm.s,VALUE(I44), _xlpm.e,VALUE(K44), IF(OR(_xlpm.s="",_xlpm.e=""),"", IF(_xlpm.e<=_xlpm.s, IF(TODAY()>=_xlpm.e,1,0), MAX(0,MIN(1,(TODAY()-_xlpm.s)/(_xlpm.e-_xlpm.s))))) ) -> 1 | O44: Resuming 01 Oct
B45: =B44+0.1 -> 4.3 | C45: Catladder Fabrication | E45: 45854 | F45: 15 | G45: =WORKDAY.INTL(E45,F45,1,Data!$C$3:$C$41) -> 45875 | I45: 45854 | J45: 31 | K45: =WORKDAY.INTL(I45,J45,1,Data!$C$3:$C$41) -> 45897 | M45: 1 | N45: =_xlfn.LET( _xlpm.s,VALUE(I45), _xlpm.e,VALUE(K45), IF(OR(_xlpm.s="",_xlpm.e=""),"", IF(_xlpm.e<=_xlpm.s, IF(TODAY()>=_xlpm.e,1,0), MAX(0,MIN(1,(TODAY()-_xlpm.s)/(_xlpm.e-_xlpm.s))))) ) -> 1
B46: =B45+0.1 -> 4.4 | C46: Catladder Installation | E46: =WORKDAY.INTL(G45,0,1,Data!$C$3:$C$41) -> 45875 | F46: 5 | G46: =WORKDAY.INTL(E46,F46,1,Data!$C$3:$C$41) -> 45882 | I46: =K22+3 -> 45913 | J46: 15 | K46: =WORKDAY.INTL(I46,J46,1,Data!$C$3:$C$41) -> 45936 | M46: 1 | N46: =_xlfn.LET( _xlpm.s,VALUE(I46), _xlpm.e,VALUE(K46), IF(OR(_xlpm.s="",_xlpm.e=""),"", IF(_xlpm.e<=_xlpm.s, IF(TODAY()>=_xlpm.e,1,0), MAX(0,MIN(1,(TODAY()-_xlpm.s)/(_xlpm.e-_xlpm.s))))) ) -> 1 | O46: Awaiting sign off form Subbie
B47: =B46+0.1 -> 4.5 | C47: Rooftop Inverter Cage Fabrication | E47: 45873 | F47: 15 | G47: =WORKDAY.INTL(E47,F47,1,Data!$C$3:$C$41) -> 45894 | I47: 45947 | J47: 19 | K47: =WORKDAY.INTL(I47,J47,1,Data!$C$3:$C$41) -> 45974 | M47: 1 | N47: =_xlfn.LET( _xlpm.s,VALUE(I47), _xlpm.e,VALUE(K47), IF(OR(_xlpm.s="",_xlpm.e=""),"", IF(_xlpm.e<=_xlpm.s, IF(TODAY()>=_xlpm.e,1,0), MAX(0,MIN(1,(TODAY()-_xlpm.s)/(_xlpm.e-_xlpm.s))))) ) -> 1
B48: =B47+0.1 -> 4.6 | C48: Rooftop Inverter Cage Installation | E48: =WORKDAY.INTL(G47,0,1,Data!$C$3:$C$41) -> 45894 | F48: 5 | G48: =WORKDAY.INTL(E48,F48,1,Data!$C$3:$C$41) -> 45901 | I48: =WORKDAY.INTL(K47,0,1,Data!$C$3:$C$41) -> 45974 | J48: 5 | K48: =WORKDAY.INTL(I48,J48,1,Data!$C$3:$C$41) -> 45981 | M48: 1 | N48: =_xlfn.LET( _xlpm.s,VALUE(I48), _xlpm.e,VALUE(K48), IF(OR(_xlpm.s="",_xlpm.e=""),"", IF(_xlpm.e<=_xlpm.s, IF(TODAY()>=_xlpm.e,1,0), MAX(0,MIN(1,(TODAY()-_xlpm.s)/(_xlpm.e-_xlpm.s))))) ) -> 1
B49: =B48+0.1 -> 4.7 | C49: Plinths - Casting & Curing | E49: 45880 | F49: 15 | G49: =WORKDAY.INTL(E49,F49,1,Data!$C$3:$C$41) -> 45901 | I49: 45953 | J49: 32 | K49: =WORKDAY.INTL(I49,J49,1,Data!$C$3:$C$41) -> 45999 | M49: 1 | N49: =_xlfn.LET( _xlpm.s,VALUE(I49), _xlpm.e,VALUE(K49), IF(OR(_xlpm.s="",_xlpm.e=""),"", IF(_xlpm.e<=_xlpm.s, IF(TODAY()>=_xlpm.e,1,0), MAX(0,MIN(1,(TODAY()-_xlpm.s)/(_xlpm.e-_xlpm.s))))) ) -> 1
B50: =B49+0.1 -> 4.8 | C50: Walkway Installation | E50: =WORKDAY.INTL(G51,0,1,Data!$C$3:$C$41)-2 -> 45878 | F50: 5 | G50: =WORKDAY.INTL(E50,F50,1,Data!$C$3:$C$41) -> 45884 | I50: =WORKDAY.INTL(I51,0,1,Data!$C$3:$C$41)+5 -> 45899 | J50: 10 | K50: =WORKDAY.INTL(I50,J50,1,Data!$C$3:$C$41) -> 45912 | M50: 1 | N50: =_xlfn.LET( _xlpm.s,VALUE(I50), _xlpm.e,VALUE(K50), IF(OR(_xlpm.s="",_xlpm.e=""),"", IF(_xlpm.e<=_xlpm.s, IF(TODAY()>=_xlpm.e,1,0), MAX(0,MIN(1,(TODAY()-_xlpm.s)/(_xlpm.e-_xlpm.s))))) ) -> 1 | O50: Complete on Furnance, staring on mill
B51: =B50+0.1 -> 4.9 | C51: Anchor Point Installation | E51: 45873 | F51: 5 | G51: =WORKDAY.INTL(E51,F51,1,Data!$C$3:$C$41) -> 45880 | I51: 45894 | J51: 7 | K51: =WORKDAY.INTL(I51,J51,1,Data!$C$3:$C$41) -> 45903 | M51: 1 | N51: =_xlfn.LET( _xlpm.s,VALUE(I51), _xlpm.e,VALUE(K51), IF(OR(_xlpm.s="",_xlpm.e=""),"", IF(_xlpm.e<=_xlpm.s, IF(TODAY()>=_xlpm.e,1,0), MAX(0,MIN(1,(TODAY()-_xlpm.s)/(_xlpm.e-_xlpm.s))))) ) -> 1
B52: 4.1 | C52: Optic Fiber Installation | I52: 45994 | J52: 2 | K52: =WORKDAY.INTL(I52,J52,1,Data!$C$3:$C$41) -> 45996 | M52: 1 | N52: =_xlfn.LET( _xlpm.s,VALUE(I52), _xlpm.e,VALUE(K52), IF(OR(_xlpm.s="",_xlpm.e=""),"", IF(_xlpm.e<=_xlpm.s, IF(TODAY()>=_xlpm.e,1,0), MAX(0,MIN(1,(TODAY()-_xlpm.s)/(_xlpm.e-_xlpm.s))))) ) -> 1
B53: 4.11 | C53: Trenching - Fiber | M53: 1 | N53: =_xlfn.LET( _xlpm.s,VALUE(I53), _xlpm.e,VALUE(K53), IF(OR(_xlpm.s="",_xlpm.e=""),"", IF(_xlpm.e<=_xlpm.s, IF(TODAY()>=_xlpm.e,1,0), MAX(0,MIN(1,(TODAY()-_xlpm.s)/(_xlpm.e-_xlpm.s))))) ) -> 1
B54: 4.12 | C54: Directional Drilling | M54: 1 | N54: =_xlfn.LET( _xlpm.s,VALUE(I54), _xlpm.e,VALUE(K54), IF(OR(_xlpm.s="",_xlpm.e=""),"", IF(_xlpm.e<=_xlpm.s, IF(TODAY()>=_xlpm.e,1,0), MAX(0,MIN(1,(TODAY()-_xlpm.s)/(_xlpm.e-_xlpm.s))))) ) -> 1
B55: 4.13 | C55: Trenching - Ground Mount to Mill | M55: 1 | N55: =_xlfn.LET( _xlpm.s,VALUE(I55), _xlpm.e,VALUE(K55), IF(OR(_xlpm.s="",_xlpm.e=""),"", IF(_xlpm.e<=_xlpm.s, IF(TODAY()>=_xlpm.e,1,0), MAX(0,MIN(1,(TODAY()-_xlpm.s)/(_xlpm.e-_xlpm.s))))) ) -> 1
B56: 4.14 | C56: Trenching - Furnance & Mill - Coega Scope | I56: 45992 | J56: 12 | K56: =WORKDAY.INTL(I56,J56,1,Data!$C$3:$C$41) -> 46008 | M56: 1 | N56: =_xlfn.LET( _xlpm.s,VALUE(I56), _xlpm.e,VALUE(K56), IF(OR(_xlpm.s="",_xlpm.e=""),"", IF(_xlpm.e<=_xlpm.s, IF(TODAY()>=_xlpm.e,1,0), MAX(0,MIN(1,(TODAY()-_xlpm.s)/(_xlpm.e-_xlpm.s))))) ) -> 1 | O56: Direct impact on pulling strings from the furnance to the mill. Impacts approx. 1,6MW
B58: 5 | C58: DC Works - Rooftop | E58: =MIN(E60:E64) -> 45878 | F58: =G58-E58 -> 51 | G58: =MAX(G60:G64) -> 45929 | I58: =MIN(I60:I64) -> 45894 | J58: =K58-I58 -> 147 | K58: =MAX(K60:K64) -> 46041 | M58: =AVERAGE(M59:M64) -> 1 | N58: =AVERAGE(N59:N64) -> 1
B59: 5.1 | C59: Mounting Structure delivered | E59: 45835 | F59: 1 | G59: =WORKDAY.INTL(E59,F59,1,Data!$C$3:$C$41) -> 45838 | I59: 45835 | J59: 1 | K59: =WORKDAY.INTL(I59,J59,1,Data!$C$3:$C$41) -> 45838 | M59: 1 | N59: =_xlfn.LET( _xlpm.s,VALUE(I59), _xlpm.e,VALUE(K59), IF(OR(_xlpm.s="",_xlpm.e=""),"", IF(_xlpm.e<=_xlpm.s, IF(TODAY()>=_xlpm.e,1,0), MAX(0,MIN(1,(TODAY()-_xlpm.s)/(_xlpm.e-_xlpm.s))))) ) -> 1
B60: 5.2 | C60: Mounting Structure installation - Frunance | E60: =WORKDAY.INTL(G51,0,1,Data!$C$3:$C$41)-2 -> 45878 | F60: 12 | G60: =WORKDAY.INTL(E60,F60,1,Data!$C$3:$C$41) -> 45895 | I60: 45894 | J60: 5 | K60: =WORKDAY.INTL(I60,J60,1,Data!$C$3:$C$41) -> 45901 | M60: 1 | N60: =_xlfn.LET( _xlpm.s,VALUE(I60), _xlpm.e,VALUE(K60), IF(OR(_xlpm.s="",_xlpm.e=""),"", IF(_xlpm.e<=_xlpm.s, IF(TODAY()>=_xlpm.e,1,0), MAX(0,MIN(1,(TODAY()-_xlpm.s)/(_xlpm.e-_xlpm.s))))) ) -> 1
B61: 5.3 | C61: Mounting Structure installation - Mill | I61: 45901 | J61: 5 | K61: =WORKDAY.INTL(I61,J61,1,Data!$C$3:$C$41) -> 45908 | M61: 1 | N61: =_xlfn.LET( _xlpm.s,VALUE(I61), _xlpm.e,VALUE(K61), IF(OR(_xlpm.s="",_xlpm.e=""),"", IF(_xlpm.e<=_xlpm.s, IF(TODAY()>=_xlpm.e,1,0), MAX(0,MIN(1,(TODAY()-_xlpm.s)/(_xlpm.e-_xlpm.s))))) ) -> 1
B62: 5.4 | C62: Panel Installation - Furnace | E62: =WORKDAY.INTL(G60,0,1,Data!$C$3:$C$41)+1 -> 45896 | F62: 17 | G62: =WORKDAY.INTL(E62,F62,1,Data!$C$3:$C$41) -> 45919 | I62: 45915 | J62: 24 | K62: =WORKDAY.INTL(I62,J62,1,Data!$C$3:$C$41) -> 45950 | M62: 1 | N62: =_xlfn.LET( _xlpm.s,VALUE(I62), _xlpm.e,VALUE(K62), IF(OR(_xlpm.s="",_xlpm.e=""),"", IF(_xlpm.e<=_xlpm.s, IF(TODAY()>=_xlpm.e,1,0), MAX(0,MIN(1,(TODAY()-_xlpm.s)/(_xlpm.e-_xlpm.s))))) ) -> 1 | O62: Waiting for delivery of panels
B63: 5.5 | C63: Panel Installation - Mill | I63: 45951 | J63: 22 | K63: =WORKDAY.INTL(I63,J63,1,Data!$C$3:$C$41) -> 45981 | M63: 1 | N63: =_xlfn.LET( _xlpm.s,VALUE(I63), _xlpm.e,VALUE(K63), IF(OR(_xlpm.s="",_xlpm.e=""),"", IF(_xlpm.e<=_xlpm.s, IF(TODAY()>=_xlpm.e,1,0), MAX(0,MIN(1,(TODAY()-_xlpm.s)/(_xlpm.e-_xlpm.s))))) ) -> 1 | O63: Roof risk delayed
B64: 5.6 | C64: DC Stringing - Furnace | E64: =WORKDAY.INTL(G62,0,1,Data!$C$3:$C$41)+2 -> 45921 | F64: 5 | G64: =WORKDAY.INTL(E64,F64,1,Data!$C$3:$C$41) -> 45929 | I64: 45940 | J64: 55 | K64: =WORKDAY.INTL(I64,J64,1,Data!$C$3:$C$41) -> 46041 | M64: 1 | N64: =_xlfn.LET( _xlpm.s,VALUE(I64), _xlpm.e,VALUE(K64), IF(OR(_xlpm.s="",_xlpm.e=""),"", IF(_xlpm.e<=_xlpm.s, IF(TODAY()>=_xlpm.e,1,0), MAX(0,MIN(1,(TODAY()-_xlpm.s)/(_xlpm.e-_xlpm.s))))) ) -> 1
B65: 5.7 | C65: DC Stringing - Mill | I65: 45929 | J65: 9 | K65: =WORKDAY.INTL(I65,J65,1,Data!$C$3:$C$41) -> 45940 | M65: 1 | N65: =_xlfn.LET( _xlpm.s,VALUE(I65), _xlpm.e,VALUE(K65), IF(OR(_xlpm.s="",_xlpm.e=""),"", IF(_xlpm.e<=_xlpm.s, IF(TODAY()>=_xlpm.e,1,0), MAX(0,MIN(1,(TODAY()-_xlpm.s)/(_xlpm.e-_xlpm.s))))) ) -> 1
B67: 6 | C67: DC Works - Ground Mount | E67: =MIN(E68:E71) -> 45894 | F67: =G67-E67 -> 58 | G67: =MAX(G68:G71) -> 45952 | I67: =MIN(I68:I71) -> 45938 | J67: =K67-I67 -> 120 | K67: =MAX(K68:K72) -> 46058 | M67: =AVERAGE(M68:M72) -> 0.99 | N67: =AVERAGE(N68:N72) -> 1
B68: 6.1 | C68: Drilling | E68: 45894 | F68: 7 | G68: =WORKDAY.INTL(E68,F68,1,Data!$C$3:$C$41) -> 45903 | I68: 45938 | J68: 34 | K68: =WORKDAY.INTL(I68,J68,1,Data!$C$3:$C$41) -> 45986 | M68: 1 | N68: =_xlfn.LET( _xlpm.s,VALUE(I68), _xlpm.e,VALUE(K68), IF(OR(_xlpm.s="",_xlpm.e=""),"", IF(_xlpm.e<=_xlpm.s, IF(TODAY()>=_xlpm.e,1,0), MAX(0,MIN(1,(TODAY()-_xlpm.s)/(_xlpm.e-_xlpm.s))))) ) -> 1 | O68: 1. Top layer soil was building rubble. 2. Levelling and approval of installation took 4 weeks longer than intially communicated by Coega. 3. Baseline date was 12 Sept 2025, Bayview only started 08 Oct 2025. 4. This has caused a 4 week delay.
B69: 6.2 | C69: Pillar Installation | E69: =WORKDAY.INTL(G68,0,1,Data!$C$3:$C$41) -> 45903 | F69: 7 | G69: =WORKDAY.INTL(E69,F69,1,Data!$C$3:$C$41) -> 45912 | I69: 45956 | J69: 37 | K69: =WORKDAY.INTL(I69,J69,1,Data!$C$3:$C$41) -> 46007 | M69: 1 | N69: =_xlfn.LET( _xlpm.s,VALUE(I69), _xlpm.e,VALUE(K69), IF(OR(_xlpm.s="",_xlpm.e=""),"", IF(_xlpm.e<=_xlpm.s, IF(TODAY()>=_xlpm.e,1,0), MAX(0,MIN(1,(TODAY()-_xlpm.s)/(_xlpm.e-_xlpm.s))))) ) -> 1 | O69: Busy with the north facing pillars
B70: 6.3 | C70: Structure Installation | E70: 45915 | F70: 14 | G70: =WORKDAY.INTL(E70,F70,1,Data!$C$3:$C$41) -> 45936 | I70: 45963 | J70: 42 | K70: =WORKDAY.INTL(I70,J70,1,Data!$C$3:$C$41) -> 46043 | M70: 1 | N70: =_xlfn.LET( _xlpm.s,VALUE(I70), _xlpm.e,VALUE(K70), IF(OR(_xlpm.s="",_xlpm.e=""),"", IF(_xlpm.e<=_xlpm.s, IF(TODAY()>=_xlpm.e,1,0), MAX(0,MIN(1,(TODAY()-_xlpm.s)/(_xlpm.e-_xlpm.s))))) ) -> 1
B71: 6.4 | C71: Panel Installation | E71: =WORKDAY.INTL(G70,0,1,Data!$C$3:$C$41)+2 -> 45938 | F71: 10 | G71: =WORKDAY.INTL(E71,F71,1,Data!$C$3:$C$41) -> 45952 | I71: 45985 | J71: 33 | K71: =WORKDAY.INTL(I71,J71,1,Data!$C$3:$C$41) -> 46052 | M71: 1 | N71: =_xlfn.LET( _xlpm.s,VALUE(I71), _xlpm.e,VALUE(K71), IF(OR(_xlpm.s="",_xlpm.e=""),"", IF(_xlpm.e<=_xlpm.s, IF(TODAY()>=_xlpm.e,1,0), MAX(0,MIN(1,(TODAY()-_xlpm.s)/(_xlpm.e-_xlpm.s))))) ) -> 1
B72: 6.5 | C72: DC Stringing | E72: =WORKDAY.INTL(G71,0,1,Data!$C$3:$C$41)+2 -> 45954 | F72: 10 | G72: =WORKDAY.INTL(E72,F72,1,Data!$C$3:$C$41) -> 45968 | I72: =K70-20 -> 46023 | J72: 18 | K72: =WORKDAY.INTL(I72,J72,1,Data!$C$3:$C$41) -> 46058 | M72: 0.95 | N72: =_xlfn.LET( _xlpm.s,VALUE(I72), _xlpm.e,VALUE(K72), IF(OR(_xlpm.s="",_xlpm.e=""),"", IF(_xlpm.e<=_xlpm.s, IF(TODAY()>=_xlpm.e,1,0), MAX(0,MIN(1,(TODAY()-_xlpm.s)/(_xlpm.e-_xlpm.s))))) ) -> 1
B74: 7 | C74: AC Installation - Ground Mount | E74: =MIN(E76:E79) -> 45945 | F74: =G74-E74 -> 26 | G74: =MAX(G75:G79) -> 45971 | I74: =MIN(I76:I79) -> 45990 | J74: =K74-I74 -> 17 | K74: =MAX(K75:K79) -> 46007 | M74: =AVERAGE(M75:M79) -> 1 | N74: =AVERAGE(N75:N79) -> 1
B75: 7.1 | C75: Inverters Delivered | E75: 45848 | F75: 1 | G75: =E75+F75 -> 45849 | I75: 45848 | J75: 1 | K75: =I75+J75 -> 45849 | M75: 1 | N75: =_xlfn.LET( _xlpm.s,VALUE(I75), _xlpm.e,VALUE(K75), IF(OR(_xlpm.s="",_xlpm.e=""),"", IF(_xlpm.e<=_xlpm.s, IF(TODAY()>=_xlpm.e,1,0), MAX(0,MIN(1,(TODAY()-_xlpm.s)/(_xlpm.e-_xlpm.s))))) ) -> 1
B76: 7.2 | C76: Inverters Mounted | E76: 45945 | F76: 6 | G76: =WORKDAY.INTL(E76,F76,1,Data!$C$3:$C$41) -> 45953 | I76: 45990 | J76: 4 | K76: =WORKDAY.INTL(I76,J76,1,Data!$C$3:$C$41) -> 45995 | M76: 1 | N76: =_xlfn.LET( _xlpm.s,VALUE(I76), _xlpm.e,VALUE(K76), IF(OR(_xlpm.s="",_xlpm.e=""),"", IF(_xlpm.e<=_xlpm.s, IF(TODAY()>=_xlpm.e,1,0), MAX(0,MIN(1,(TODAY()-_xlpm.s)/(_xlpm.e-_xlpm.s))))) ) -> 1
B77: 7.3 | C77: DB Placement | E77: =WORKDAY.INTL(G76,0,1,Data!$C$3:$C$41) -> 45953 | F77: 2 | G77: =WORKDAY.INTL(E77,F77,1,Data!$C$3:$C$41) -> 45957 | I77: =WORKDAY.INTL(I76,0,1,Data!$C$3:$C$41) -> 45990 | J77: 4 | K77: =WORKDAY.INTL(I77,J77,1,Data!$C$3:$C$41) -> 45995 | M77: 1 | N77: =_xlfn.LET( _xlpm.s,VALUE(I77), _xlpm.e,VALUE(K77), IF(OR(_xlpm.s="",_xlpm.e=""),"", IF(_xlpm.e<=_xlpm.s, IF(TODAY()>=_xlpm.e,1,0), MAX(0,MIN(1,(TODAY()-_xlpm.s)/(_xlpm.e-_xlpm.s))))) ) -> 1
B78: 7.4 | C78: Cabling - Inverter to DB | E78: =WORKDAY.INTL(G77,0,1,Data!$C$3:$C$41) -> 45957 | F78: 5 | G78: =WORKDAY.INTL(E78,F78,1,Data!$C$3:$C$41) -> 45964 | I78: =WORKDAY.INTL(K77,0,1,Data!$C$3:$C$41) -> 45995 | J78: 5 | K78: =WORKDAY.INTL(I78,J78,1,Data!$C$3:$C$41) -> 46002 | M78: 1 | N78: =_xlfn.LET( _xlpm.s,VALUE(I78), _xlpm.e,VALUE(K78), IF(OR(_xlpm.s="",_xlpm.e=""),"", IF(_xlpm.e<=_xlpm.s, IF(TODAY()>=_xlpm.e,1,0), MAX(0,MIN(1,(TODAY()-_xlpm.s)/(_xlpm.e-_xlpm.s))))) ) -> 1
B79: 7.5 | C79: Cabling - DB to Transformer | E79: =WORKDAY.INTL(G78,0,1,Data!$C$3:$C$41) -> 45964 | F79: 5 | G79: =WORKDAY.INTL(E79,F79,1,Data!$C$3:$C$41) -> 45971 | I79: =WORKDAY.INTL(K76,0,1,Data!$C$3:$C$41) -> 45995 | J79: 8 | K79: =WORKDAY.INTL(I79,J79,1,Data!$C$3:$C$41) -> 46007 | M79: 1 | N79: =_xlfn.LET( _xlpm.s,VALUE(I79), _xlpm.e,VALUE(K79), IF(OR(_xlpm.s="",_xlpm.e=""),"", IF(_xlpm.e<=_xlpm.s, IF(TODAY()>=_xlpm.e,1,0), MAX(0,MIN(1,(TODAY()-_xlpm.s)/(_xlpm.e-_xlpm.s))))) ) -> 1
B81: 8 | C81: AC Installation - Rooftop | E81: =MIN(E83:E86) -> 45950 | F81: =G81-E81 -> 21 | G81: =MAX(G82:G86) -> 45971 | I81: =MIN(I83:I86) -> 45915 | J81: =K81-I81 -> 92 | K81: =MAX(K82:K86) -> 46007 | M81: =AVERAGE(M82:M86) -> 1 | N81: =AVERAGE(N82:N86) -> 1
B82: 8.1 | C82: Inverters Delivered | E82: 45848 | F82: 1 | G82: =E82+F82 -> 45849 | I82: 45848 | J82: 1 | K82: =I82+J82 -> 45849 | M82: 1 | N82: =_xlfn.LET( _xlpm.s,VALUE(I82), _xlpm.e,VALUE(K82), IF(OR(_xlpm.s="",_xlpm.e=""),"", IF(_xlpm.e<=_xlpm.s, IF(TODAY()>=_xlpm.e,1,0), MAX(0,MIN(1,(TODAY()-_xlpm.s)/(_xlpm.e-_xlpm.s))))) ) -> 1
B83: 8.2 | C83: Inverters Mounted | E83: 45950 | F83: 4 | G83: =WORKDAY.INTL(E83,F83,1,Data!$C$3:$C$41) -> 45954 | I83: 45915 | J83: 3 | K83: =WORKDAY.INTL(I83,J83,1,Data!$C$3:$C$41) -> 45918 | M83: 1 | N83: 1
B84: 8.3 | C84: DB Placement | E84: =WORKDAY.INTL(G83,0,1,Data!$C$3:$C$41) -> 45954 | F84: 2 | G84: =WORKDAY.INTL(E84,F84,1,Data!$C$3:$C$41) -> 45958 | I84: =WORKDAY.INTL(K83,0,1,Data!$C$3:$C$41) -> 45918 | J84: 2 | K84: =WORKDAY.INTL(I84,J84,1,Data!$C$3:$C$41) -> 45922 | M84: 1 | N84: =_xlfn.LET( _xlpm.s,VALUE(I84), _xlpm.e,VALUE(K84), IF(OR(_xlpm.s="",_xlpm.e=""),"", IF(_xlpm.e<=_xlpm.s, IF(TODAY()>=_xlpm.e,1,0), MAX(0,MIN(1,(TODAY()-_xlpm.s)/(_xlpm.e-_xlpm.s))))) ) -> 1
B85: 8.4 | C85: Cabling - Inverter to DB | E85: =WORKDAY.INTL(G84,0,1,Data!$C$3:$C$41) -> 45958 | F85: 4 | G85: =WORKDAY.INTL(E85,F85,1,Data!$C$3:$C$41) -> 45964 | I85: =WORKDAY.INTL(K84,0,1,Data!$C$3:$C$41) -> 45922 | J85: 7 | K85: =WORKDAY.INTL(I85,J85,1,Data!$C$3:$C$41) -> 45932 | M85: 1 | N85: =_xlfn.LET( _xlpm.s,VALUE(I85), _xlpm.e,VALUE(K85), IF(OR(_xlpm.s="",_xlpm.e=""),"", IF(_xlpm.e<=_xlpm.s, IF(TODAY()>=_xlpm.e,1,0), MAX(0,MIN(1,(TODAY()-_xlpm.s)/(_xlpm.e-_xlpm.s))))) ) -> 1
B86: 8.5 | C86: Cabling - DB to Transformer | E86: =WORKDAY.INTL(G85,0,1,Data!$C$3:$C$41) -> 45964 | F86: 5 | G86: =WORKDAY.INTL(E86,F86,1,Data!$C$3:$C$41) -> 45971 | I86: =WORKDAY.INTL(K49,0,1,Data!$C$3:$C$41) -> 45999 | J86: 6 | K86: =WORKDAY.INTL(I86,J86,1,Data!$C$3:$C$41) -> 46007 | M86: 1 | N86: =_xlfn.LET( _xlpm.s,VALUE(I86), _xlpm.e,VALUE(K86), IF(OR(_xlpm.s="",_xlpm.e=""),"", IF(_xlpm.e<=_xlpm.s, IF(TODAY()>=_xlpm.e,1,0), MAX(0,MIN(1,(TODAY()-_xlpm.s)/(_xlpm.e-_xlpm.s))))) ) -> 1
B88: 9 | C88: Transformer Installation | E88: =MIN(E89:E96) -> 45922 | F88: =G88-E88 -> 43 | G88: =MAX(G89:G96) -> 45965 | I88: =MIN(I89:I96) -> 45986 | J88: =K88-I88 -> 22 | K88: =MAX(K89:K96) -> 46008 | M88: =AVERAGE(M89:M96) -> 1 | N88: =AVERAGE(N89:N96) -> 1
B89: 9.1 | C89: Transformer Offloading | E89: 45922 | F89: 2 | G89: =WORKDAY.INTL(E89,F89,1,Data!$C$3:$C$41) -> 45925 | I89: =K33-1 -> 45988 | J89: 1 | K89: =WORKDAY.INTL(I89,J89,1,Data!$C$3:$C$41) -> 45989 | M89: 1 | N89: =_xlfn.LET( _xlpm.s,VALUE(I89), _xlpm.e,VALUE(K89), IF(OR(_xlpm.s="",_xlpm.e=""),"", IF(_xlpm.e<=_xlpm.s, IF(TODAY()>=_xlpm.e,1,0), MAX(0,MIN(1,(TODAY()-_xlpm.s)/(_xlpm.e-_xlpm.s))))) ) -> 1
C90: Transformer Rigging risk assessment and offloading plan | I90: 45986 | J90: 4 | K90: =WORKDAY.INTL(I90,J90,1,Data!$C$3:$C$41) -> 45992 | M90: 1 | N90: =_xlfn.LET( _xlpm.s,VALUE(I90), _xlpm.e,VALUE(K90), IF(OR(_xlpm.s="",_xlpm.e=""),"", IF(_xlpm.e<=_xlpm.s, IF(TODAY()>=_xlpm.e,1,0), MAX(0,MIN(1,(TODAY()-_xlpm.s)/(_xlpm.e-_xlpm.s))))) ) -> 1
B91: =B89+0.1 -> 9.2 | C91: Transformer 1 - MV - Install MV cabling | E91: 45953 | F91: 2 | G91: =WORKDAY.INTL(E91,F91,1,Data!$C$3:$C$41) -> 45957 | I91: =K78-7 -> 45995 | J91: 2 | K91: =WORKDAY.INTL(I91,J91,1,Data!$C$3:$C$41) -> 45999 | M91: 1 | N91: =_xlfn.LET( _xlpm.s,VALUE(I91), _xlpm.e,VALUE(K91), IF(OR(_xlpm.s="",_xlpm.e=""),"", IF(_xlpm.e<=_xlpm.s, IF(TODAY()>=_xlpm.e,1,0), MAX(0,MIN(1,(TODAY()-_xlpm.s)/(_xlpm.e-_xlpm.s))))) ) -> 1
B92: =B91+0.1 -> 9.3 | C92: Transformer 1 - MV - Terminate and connect cabling at RMU - Assuming Coega has the tie in breaker ready | E92: =WORKDAY.INTL(G91,0,1,Data!$C$3:$C$41) -> 45957 | F92: 0 | G92: =WORKDAY.INTL(E92,F92,1,Data!$C$3:$C$41) -> 45957 | I92: 46002 | J92: 0 | K92: =WORKDAY.INTL(I92,J92,1,Data!$C$3:$C$41) -> 46002 | M92: 1 | N92: =_xlfn.LET( _xlpm.s,VALUE(I92), _xlpm.e,VALUE(K92), IF(OR(_xlpm.s="",_xlpm.e=""),"", IF(_xlpm.e<=_xlpm.s, IF(TODAY()>=_xlpm.e,1,0), MAX(0,MIN(1,(TODAY()-_xlpm.s)/(_xlpm.e-_xlpm.s))))) ) -> 1
B93: =B92+0.1 -> 9.4 | C93: Transformer 1 - MV - Cable pressure testing and protection calibrations | E93: =WORKDAY.INTL(G92,0,1,Data!$C$3:$C$41) -> 45957 | F93: 2 | G93: =WORKDAY.INTL(E93,F93,1,Data!$C$3:$C$41) -> 45959 | I93: =WORKDAY.INTL(K92,0,1,Data!$C$3:$C$41) -> 46002 | J93: 2 | K93: =WORKDAY.INTL(I93,J93,1,Data!$C$3:$C$41) -> 46006 | M93: 1 | N93: =_xlfn.LET( _xlpm.s,VALUE(I93), _xlpm.e,VALUE(K93), IF(OR(_xlpm.s="",_xlpm.e=""),"", IF(_xlpm.e<=_xlpm.s, IF(TODAY()>=_xlpm.e,1,0), MAX(0,MIN(1,(TODAY()-_xlpm.s)/(_xlpm.e-_xlpm.s))))) ) -> 1
B94: =B93+0.1 -> 9.5 | C94: Transformer 2 - MV - Install MV cabling | E94: =WORKDAY.INTL(G93,0,1,Data!$C$3:$C$41) -> 45959 | F94: 2 | G94: =WORKDAY.INTL(E94,F94,1,Data!$C$3:$C$41) -> 45961 | I94: =WORKDAY.INTL(K93,0,1,Data!$C$3:$C$41) -> 46006 | J94: 2 | K94: =WORKDAY.INTL(I94,J94,1,Data!$C$3:$C$41) -> 46008 | M94: 1 | N94: =_xlfn.LET( _xlpm.s,VALUE(I94), _xlpm.e,VALUE(K94), IF(OR(_xlpm.s="",_xlpm.e=""),"", IF(_xlpm.e<=_xlpm.s, IF(TODAY()>=_xlpm.e,1,0), MAX(0,MIN(1,(TODAY()-_xlpm.s)/(_xlpm.e-_xlpm.s))))) ) -> 1
B95: =B94+0.1 -> 9.6 | C95: Transformer 2 - MV - Terminate and connect cabling at RMU | E95: =WORKDAY.INTL(G94,0,1,Data!$C$3:$C$41) -> 45961 | F95: 0 | G95: =WORKDAY.INTL(E95,F95,1,Data!$C$3:$C$41) -> 45961 | I95: =WORKDAY.INTL(K94,0,1,Data!$C$3:$C$41)-2 -> 46006 | J95: 0 | K95: =WORKDAY.INTL(I95,J95,1,Data!$C$3:$C$41) -> 46006 | M95: 1 | N95: =_xlfn.LET( _xlpm.s,VALUE(I95), _xlpm.e,VALUE(K95), IF(OR(_xlpm.s="",_xlpm.e=""),"", IF(_xlpm.e<=_xlpm.s, IF(TODAY()>=_xlpm.e,1,0), MAX(0,MIN(1,(TODAY()-_xlpm.s)/(_xlpm.e-_xlpm.s))))) ) -> 1
B96: =B95+0.1 -> 9.7 | C96: Transformer 2 - MV - Cable pressure testing and protection calibrations | E96: =WORKDAY.INTL(G95,0,1,Data!$C$3:$C$41) -> 45961 | F96: 2 | G96: =WORKDAY.INTL(E96,F96,1,Data!$C$3:$C$41) -> 45965 | I96: =WORKDAY.INTL(K95,0,1,Data!$C$3:$C$41) -> 46006 | J96: 2 | K96: =WORKDAY.INTL(I96,J96,1,Data!$C$3:$C$41) -> 46008 | M96: 1 | N96: =_xlfn.LET( _xlpm.s,VALUE(I96), _xlpm.e,VALUE(K96), IF(OR(_xlpm.s="",_xlpm.e=""),"", IF(_xlpm.e<=_xlpm.s, IF(TODAY()>=_xlpm.e,1,0), MAX(0,MIN(1,(TODAY()-_xlpm.s)/(_xlpm.e-_xlpm.s))))) ) -> 1
B98: 10 | C98: Commissioning | E98: =MIN(E99:E108) -> 45971 | F98: =G98-E98 -> 4 | G98: =MAX(G99:G108) -> 45975 | I98: =MIN(I99:I108) -> 46006 | J98: =K98-I98 -> 59 | K98: =MAX(K99:K108) -> 46065 | M98: =AVERAGE(M99:M108) -> 0.89 | N98: =AVERAGE(N99:N108) -> 0.90142857
B99: =B98+0.1 -> 10.1 | C99: MV Signoff and COC | E99: =WORKDAY.INTL(MAX(G88,G81,G74,G67,G58),0,1,Data!$C$3:$C$41) -> 45971 | F99: 2 | G99: =WORKDAY.INTL(E99,F99,1,Data!$C$3:$C$41) -> 45973 | I99: 46006 | J99: 3 | K99: =WORKDAY.INTL(I99,J99,1,Data!$C$3:$C$41) -> 46009 | M99: 1 | N99: =_xlfn.LET( _xlpm.s,VALUE(I99), _xlpm.e,VALUE(K99), IF(OR(_xlpm.s="",_xlpm.e=""),"", IF(_xlpm.e<=_xlpm.s, IF(TODAY()>=_xlpm.e,1,0), MAX(0,MIN(1,(TODAY()-_xlpm.s)/(_xlpm.e-_xlpm.s))))) ) -> 1
B100: 10.2 | C100: Transformer Commissioning | I100: 46006 | J100: 2 | K100: =WORKDAY.INTL(I100,J100,1,Data!$C$3:$C$41) -> 46008 | M100: 1 | N100: =_xlfn.LET( _xlpm.s,VALUE(I100), _xlpm.e,VALUE(K100), IF(OR(_xlpm.s="",_xlpm.e=""),"", IF(_xlpm.e<=_xlpm.s, IF(TODAY()>=_xlpm.e,1,0), MAX(0,MIN(1,(TODAY()-_xlpm.s)/(_xlpm.e-_xlpm.s))))) ) -> 1
B101: 10.3 | C101: Inverter Commissioning | I101: =K100 -> 46008 | J101: 2 | K101: =WORKDAY.INTL(I101,J101,1,Data!$C$3:$C$41) -> 46010 | M101: 1 | N101: =_xlfn.LET( _xlpm.s,VALUE(I101), _xlpm.e,VALUE(K101), IF(OR(_xlpm.s="",_xlpm.e=""),"", IF(_xlpm.e<=_xlpm.s, IF(TODAY()>=_xlpm.e,1,0), MAX(0,MIN(1,(TODAY()-_xlpm.s)/(_xlpm.e-_xlpm.s))))) ) -> 1
B102: 10.4 | C102: Energy Flowing - Partial | I102: =K101-1 -> 46009 | J102: 1 | K102: =WORKDAY.INTL(I102,J102,1,Data!$C$3:$C$41) -> 46010 | M102: 1 | N102: =_xlfn.LET( _xlpm.s,VALUE(I102), _xlpm.e,VALUE(K102), IF(OR(_xlpm.s="",_xlpm.e=""),"", IF(_xlpm.e<=_xlpm.s, IF(TODAY()>=_xlpm.e,1,0), MAX(0,MIN(1,(TODAY()-_xlpm.s)/(_xlpm.e-_xlpm.s))))) ) -> 1 | O102: Furnance strings to be energised
B103: 10.5 | C103: Energy Flowing - Full | I103: 46055 | J103: 3 | K103: =WORKDAY.INTL(I103,J103,1,Data!$C$3:$C$41) -> 46058 | M103: 0.9 | N103: 0.5 | O103: All strings to be energised
B104: 10.6 | C104: Issue Compeltion Certificates | I104: =K103 -> 46058 | J104: 5 | K104: =WORKDAY.INTL(I104,J104,1,Data!$C$3:$C$41) -> 46065 | M104: 0 | N104: =_xlfn.LET( _xlpm.s,VALUE(I104), _xlpm.e,VALUE(K104), IF(OR(_xlpm.s="",_xlpm.e=""),"", IF(_xlpm.e<=_xlpm.s, IF(TODAY()>=_xlpm.e,1,0), MAX(0,MIN(1,(TODAY()-_xlpm.s)/(_xlpm.e-_xlpm.s))))) ) -> 0.71428571
B105: 10.7 | C105: Techsitter Installation | I105: 46048 | J105: 2 | K105: =WORKDAY.INTL(I105,J105,1,Data!$C$3:$C$41) -> 46050 | M105: 1 | N105: =_xlfn.LET( _xlpm.s,VALUE(I105), _xlpm.e,VALUE(K105), IF(OR(_xlpm.s="",_xlpm.e=""),"", IF(_xlpm.e<=_xlpm.s, IF(TODAY()>=_xlpm.e,1,0), MAX(0,MIN(1,(TODAY()-_xlpm.s)/(_xlpm.e-_xlpm.s))))) ) -> 1
B106: 10.8 | C106: Grid Meter Setup | I106: 46034 | J106: 10 | K106: =WORKDAY.INTL(I106,J106,1,Data!$C$3:$C$41) -> 46048 | M106: 1 | N106: =_xlfn.LET( _xlpm.s,VALUE(I106), _xlpm.e,VALUE(K106), IF(OR(_xlpm.s="",_xlpm.e=""),"", IF(_xlpm.e<=_xlpm.s, IF(TODAY()>=_xlpm.e,1,0), MAX(0,MIN(1,(TODAY()-_xlpm.s)/(_xlpm.e-_xlpm.s))))) ) -> 1
B107: 10.9 | C107: Inverter 4 Rolling Mill (Inverter 14) Faulty string | I107: 46048 | J107: 2 | K107: =WORKDAY.INTL(I107,J107,1,Data!$C$3:$C$41) -> 46050 | M107: 1 | N107: 1
B108: 10.1 | C108: Practical Completion | E108: =WORKDAY.INTL(G99,0,1,Data!$C$3:$C$41) -> 45973 | F108: 2 | G108: =WORKDAY.INTL(E108,F108,1,Data!$C$3:$C$41) -> 45975 | I108: 46055 | J108: 0 | K108: =WORKDAY.INTL(I108,J108,1,Data!$C$3:$C$41) -> 46055 | M108: 1 | N108: 0.8
J109: `
B110: 11 | C110: QA Inspection & Snag Completion | E110: =MIN(E111:E115) -> 45929 | F110: =G110-E110 -> 58 | G110: =MAX(G111:G115) -> 45987 | I110: =MIN(I111:I115) -> 46048 | J110: =K110-I110 -> 22 | K110: =MAX(K111:K115) -> 46070 | M110: =AVERAGE(M111:M115) -> 0.52 | N110: =AVERAGE(N111:N115) -> 0.9
...

Sheet Expenditure Tracking
B2: HIGH LEVEL PROJECT EXPENDITURE TRACKING
F4: COSTED | H4: ACTUAL | J4: Difference from costed
B5: EXPENDITURE | F5: =SUM(F9:F23) -> 56096452 | H5: =SUM(H9:H23) -> 48692192 | J5: =SUM(J9:J23) -> 7404260.5
B7: No. | D7: Item | F7: Costed Expenditure | H7: Actual Expenditure | J7: Saving / Overrun | L7: Comments on variations from planned expenditure
B9: ='Expenditure Breakdown'!L6 -> 1 | D9: ='Expenditure Breakdown'!M6 -> 1. Panels | F9: ='Expenditure Breakdown'!I6 -> 14537831 | H9: ='Expenditure Breakdown'!X6 -> 13735976 | J9: =F9-H9 -> 801855.3
B10: ='Expenditure Breakdown'!L21 -> 2 | D10: ='Expenditure Breakdown'!M21 -> 2. Inverters | F10: ='Expenditure Breakdown'!I21 -> 2760000 | H10: ='Expenditure Breakdown'!X21 -> 2495176.2 | J10: =F10-H10 -> 264823.78
B11: ='Expenditure Breakdown'!L29 -> 3 | D11: ='Expenditure Breakdown'!M29 -> 3. Mounting Structures | F11: ='Expenditure Breakdown'!I29 -> 7358785.9 | H11: ='Expenditure Breakdown'!X29 -> 4071044.3 | J11: =F11-H11 -> 3287741.6
B12: ='Expenditure Breakdown'!L49 -> 4 | D12: ='Expenditure Breakdown'!M49 -> 4. DC Equipment | F12: ='Expenditure Breakdown'!I49 -> 8057942 | H12: ='Expenditure Breakdown'!X49 -> 3329187 | J12: =F12-H12 -> 4728755
B13: ='Expenditure Breakdown'!L74 -> 5 | D13: ='Expenditure Breakdown'!M74 -> 5. Monitoring | F13: ='Expenditure Breakdown'!I74 -> 64000 | H13: ='Expenditure Breakdown'!X74 -> 241577.3 | J13: =F13-H13 -> -177577.3
B14: ='Expenditure Breakdown'!L96 -> 6 | D14: ='Expenditure Breakdown'!M96 -> 6. AC Equipment | F14: ='Expenditure Breakdown'!I96 -> 2941866.9 | H14: ='Expenditure Breakdown'!X96 -> 2401487 | J14: =F14-H14 -> 540379.9
B15: ='Expenditure Breakdown'!L122 -> 7 | D15: ='Expenditure Breakdown'!M122 -> 7.MV Substation | F15: ='Expenditure Breakdown'!I122 -> 12030861 | H15: ='Expenditure Breakdown'!X122 -> 7046627.6 | J15: =F15-H15 -> 4984233
B16: ='Expenditure Breakdown'!L161 -> 8 | D16: ='Expenditure Breakdown'!M161 -> 8. Product Add On | F16: ='Expenditure Breakdown'!I161 -> 2015000 | H16: ='Expenditure Breakdown'!X161 -> 2216118.2 | J16: =F16-H16 -> -201118.21
B17: ='Expenditure Breakdown'!L183 -> 9 | D17: ='Expenditure Breakdown'!M183 -> 9. AC & DC installation | F17: ='Expenditure Breakdown'!I183 -> 4360411.2 | H17: ='Expenditure Breakdown'!X183 -> 8055680 | J17: =F17-H17 -> -3695268.8
B18: ='Expenditure Breakdown'!L227 -> 10 | D18: ='Expenditure Breakdown'!M227 -> 10. Site Logistics | F18: ='Expenditure Breakdown'!I227 -> 394304.23 | H18: ='Expenditure Breakdown'!X227 -> 936113.11 | J18: =F18-H18 -> -541808.88
B19: ='Expenditure Breakdown'!L283 -> 11 | D19: ='Expenditure Breakdown'!M283 -> 11. Due Dilligence | F19: ='Expenditure Breakdown'!I283 -> 420000 | H19: ='Expenditure Breakdown'!X283 -> 658656 | J19: =F19-H19 -> -238656
B20: ='Expenditure Breakdown'!L298 -> 12 | D20: ='Expenditure Breakdown'!M298 -> 12. BDP Commission | F20: ='Expenditure Breakdown'!I298 -> 205449.89 | H20: ='Expenditure Breakdown'!X298 -> 0 | J20: =F20-H20 -> 205449.89
B21: ='Expenditure Breakdown'!L301 -> 13 | D21: ='Expenditure Breakdown'!M302 -> 13. Engineering | F21: ='Expenditure Breakdown'!I301 -> 950000 | H21: ='Expenditure Breakdown'!X301 -> 984324.26 | J21: =F21-H21 -> -34324.26
B22: ='Expenditure Breakdown'!L311 -> 14 | D22: ='Expenditure Breakdown'!M311 -> 14. General Expenses | F22: ='Expenditure Breakdown'!I311 -> 0 | H22: ='Expenditure Breakdown'!X311 -> 271181.58 | J22: =F22-H22 -> -271181.58
B23: ='Expenditure Breakdown'!L324 -> 15 | D23: ='Expenditure Breakdown'!M324 -> 15. Service Add On | F23: ='Expenditure Breakdown'!I324 -> 0 | H23: ='Expenditure Breakdown'!X324 -> 2249043 | J23: =F23-H23 -> -2249043
D25: check: | F25: ='Expenditure Breakdown'!I2-'Expenditure Tracking'!F5 -> 0 | G25: =#REF!-G5 -> #REF! | H25: ='Expenditure Breakdown'!X2-H5 -> 0

Sheet Expenditure Breakdown
B2: COSTED EXPENDITURE BREAKDOWN | I2: =SUM(I6:I361) -> 56096452 | J2: =SUM(J6:J361)-5000 -> 59995000 | L2: ACTUAL EXPENDITURE BREAKDOWN | R2: FINANCE ONLY | X2: =SUM(X6:X361) -> 48692192
B4: No. | C4: Product / Service | D4: Description of Work | E4: QTY | F4: Rate / Unit | G4: Budget Total | H4: FINANCE PAYMENT DATE | I4: Total COS | J4: =IF(J2-'Revenue Tracking'!D4>=0, "Total Revenue", "ERROR on REV" ) -> ERROR on REV | L4: No. | M4: Product/ Service | N4: Description of Work | O4: QTY | P4: Rate / Unit | Q4: Actual Total | R4: PO NUMBER | S4: INVOICE NUMBER | T4: INVOICE RAISED DATE | U4: REVENUE RECOGNITION AMOUNT | V4: CHECK | W4: FINANCE PAYMENT DATE | X4: Total COS
B6: 1 | C6: Panels | D6: Panels Budget | G6: =D362 -> 14537831 | H6: 45827 | I6: =SUM(G6:G19) -> 14537831 | J6: =F362 -> 15101046 | L6: 1 | M6: 1. Panels | N6: Jinko 620W - Deposit | O6: 11420 | P6: 0.1 | Q6: =13735976*0.1 -> 1373597.6 | R6: PO3993-CSPH2-20260610 - RV Approved | S6: Menlo INV0003003 | T6: 45869 | U6: 1510104.6 | V6: =J6-SUM(U6:U19) -> 0 | W6: 45827 | X6: =SUM(Q6:Q19) -> 13735976
B7: 1 | D7: Delivery Budget | L7: 1 | M7: 1. Panels | U7: 0
B8: 1 | L8: 1 | M8: 1. Panels | N8: Jinko 620W - Ground Mount | O8: 5112 | P8: 1202.8 | Q8: =1675740.96/1.15 -> 1457166.1 | S8: Menlo INV0003103 | T8: 45869 | U8: 6083790.8 | W8: 45925
L9: 1 | M9: 1. Panels | Q9: =(2000000+237905.06+2243727.74)/1.15 -> 3897072 | S9: Menlo INV0003103 | T9: 45869 | U9: 0 | W9: 45946
L10: 1 | M10: 1. Panels | Q10: =6148713.6-Q8-Q9-614871.36 -> 179604.19 | S10: Menlo INV0003103 | T10: 45869 | U10: 0 | W10: 46031
B11: 1 | L11: 1 | M11: 1. Panels | N11: Jinko 620W - Rooftop | O11: =4032+2268 -> 6300 | P11: 1202.8 | Q11: 869565.22 | S11: Menlo INV0003103 | T11: 45869 | U11: 7497629.5 | W11: 46031
L12: 1 | M12: 1. Panels | Q12: 637461.31 | S12: Menlo INV0003103 | T12: 45869 | U12: 0 | W12: 46031
L13: 1 | M13: 1. Panels | Q13: 1006679.1 | S13: Menlo INV0003103 | T13: 45869 | U13: 0 | W13: 46037
L14: 1 | M14: 1. Panels | Q14: 1277597.2 | S14: Menlo INV0003103 | T14: 45869 | U14: 0 | W14: 46045
L15: 1 | M15: 1. Panels | Q15: 1304347.8 | S15: Menlo INV0003103 | T15: 45869 | U15: 0 | W15: 46051
L16: 1 | M16: 1. Panels | Q16: =6819876-Q11-Q12-Q13-Q14-Q15 -> 1724225.3 | S16: Menlo INV0003103 | T16: 45869 | U16: 0 | W16: 46051
B17: 1 | L17: 1 | M17: 1. Panels | N17: Spare | O17: 8 | P17: 1202.8 | Q17: =13735976*0.9*(O17/$O$6) -> 8660.16 | S17: Menlo INV0003103 | T17: 45869 | U17: 9520.7993 | W17: =W16 -> 46051 | AB17: Luken Solar
B18: 1 | L18: 1 | M18: 1. Panels | N18: Extra Pallet | O18: 1 | P18: 43292.88 | Q18: =P18 -> 43292.88 | S18: Menlo INV0003160 | T18: 45900 | U18: 0 | W18: =W9 -> 45946 | Y18: BUDGET | Z18: Installer Allocation
B19: 1 | L19: 1 | M19: 1. Panels | N19: Extra Pallet | O19: 1 | P19: -43292.88 | Q19: =P19 -> -43292.88 | S19: MSA Energy: CRN0000262 | T19: 45991 | U19: 0 | W19: =W16 -> 46051 | Y19: BUDGET | Z19: Installer Allocation
T20: =IF(W20>1,EOMONTH(W20,0),"") | Y20: AC Equipment | Z20: =G96 -> 2941866.9 | AB20: Installation of 4MW Roof Mount including electrical work, labour and logistics | AC20: 4000000 | AD20: 4MW | AE20: =AC20/4000000 -> 1
B21: 2 | C21: Inverters | D21: Inverter Budget | G21: =D363 -> 2760000 | H21: 45820 | I21: =SUM(G21:G27) -> 2760000 | J21: =F363 -> 2982470.7 | L21: 2 | M21: 2. Inverters | N21: Huawei 330KTL - Deposit 30% | O21: 23 | P21: =6087*17.7457 -> 108018.08 | Q21: =O21*P21*30% -> 745324.72 | R21: PO3991-CSPH2-20250610 - JP Approved | S21: Kathea S19625 | T21: 45869 | U21: 886426.77 | V21: =J21-SUM(U21:U27) -> -0.00028844411 | W21: 45820 | X21: =SUM(Q21:Q27) -> 2495176.2 | Y21: DC Equipment | Z21: =G50 -> 4558110
B22: 2 | L22: 2 | M22: 2. Inverters | N22: Huawei 330KTL - Balance 70% | Q22: 1749851.5 | S22: Kathea - 519704 | T22: 45869 | U22: 2081126.7 | W22: 45855 | Y22: AC Labour | Z22: =G183 -> 1062060 | AA22: =Z22/7080000 -> 0.15000847 | AB22: Special lifting equipment
B23: 2 | L23: 2 | M23: 2. Inverters | T23: =IF(W23>1,EOMONTH(W23,0),"") | U23: =(Q23/$X$21*$J$21) -> 0 | Y23: DC Labour | Z23: =G184 -> 3298351.2 | AA23: =Z23/7080000 -> 0.46586882 | AB23: Elctrical and installation small components (not provided by Emergent) | AC23: 550000
B24: 2 | L24: 2 | M24: 2. Inverters | T24: 45900 | U24: 14917.19 | W24: 45820 | Y24: Offloading | Z24: =G227 -> 85000
B25: 2 | L25: 2 | M25: 2. Inverters | N25: Huawei SUN2000 HAV5-Inverter Accessories - 330KTL Inverters | Q25: 899.72 | S25: Kathea - 500335 | T25: 46022 | U25: 0 | W25: 46053 | Y25: Scaffolding | Z25: =G228 -> 133245.9 | AB25: Installation of Ground Mount system:
B26: 2 | L26: 2 | M26: 2. Inverters | Q26: -899.72 | S26: Kathea - 500335 | T26: 46053 | U26: 0 | W26: 46053 | Y26: Storage | Z26: =G232 -> 176058.33
B27: 2 | L27: 2 | M27: 2. Inverters | T27: =IF(W27>1,EOMONTH(W27,0),"") | U27: =(Q27/$X$21*$J$21) -> 0 | Y27: Telehandler | Z27: 0 | AB27: Installation of 3MW Ground Mount including electrical work, labour and logistics (incl. Structures) | AC27: 2500000 | AD27: 3MW | AE27: =AC27/3000000 -> 0.83333333
T28: =IF(W28>1,EOMONTH(W28,0),"")
B29: 3 | C29: Mounting Structures | D29: Structure Budget | G29: =D364 -> 7358785.9 | H29: 45867 | I29: =SUM(G29:G47) -> 7358785.9 | J29: =F364 -> 7951943.3 | L29: 3 | M29: 3. Mounting Structures | N29: IBR short rail - Rooftop | O29: 19830 | P29: 22.88 | Q29: =O29*P29 -> 453710.4 | R29: PO3994-CSPH2-20260610 - RV Approved | S29: Schletter - INV1895 | T29: 45838 | U29: 870407.92 | V29: =J29-SUM(U29:U47) -> 0 | W29: 45867 | X29: =SUM(Q29:Q47) -> 4071044.3 | Y29: Other | Z29: 0 | AB29: Trenching and pipes
B30: 3 | L30: 3 | M30: 3. Mounting Structures | N30: Screws - Rooftop | O30: 39660 | P30: 5.87 | Q30: =O30*P30 -> 232804.2 | S30: Schletter - INV1895 | T30: 45838 | U30: 446616.65 | W30: 45867 | Y30: Total | Z30: =SUM(Z20:Z29) -> 12254692 | AB30: Elctrical and installation small components (not provided by Emergent) | AC30: 590000
L31: 3 | M31: 3. Mounting Structures | N31: Inner Clamp - 30mm - Rooftop | O31: 18030 | P31: 10.64 | Q31: 197183 | S31: Schletter - INV1895 | T31: 45838 | U31: 378280.17 | W31: 45867 | Y31: Less 15% | Z31: =+Z30*0.85 -> 10416489
L32: 3 | M32: 3. Mounting Structures | N32: End Clamp - 30mm - Rooftop | O32: 1820 | P32: 10.96 | Q32: 20391.2 | S32: Schletter - INV1895 | T32: 45838 | U32: 39118.923 | W32: 45867 | Y32: R/Wp | Z32: =Z31/'Project Plan'!$E$3/1000 -> 1.4712554
L33: 3 | M33: 3. Mounting Structures | U33: 0
L34: 3 | M34: 3. Mounting Structures | N34: IBR Mounting clamps - Cable Trays | O34: =O29*0.1 -> 1983 | P34: 22.88 | Q34: =O34*P34 -> 45371.04 | S34: Schletter - INV1895 | T34: 45838 | U34: 87040.792 | W34: 45867 | Y34: ACTUAL | Z34: Installer Price
L35: 3 | M35: 3. Mounting Structures | N35: Screws - Cable Trays | O35: =O34*2 -> 3966 | P35: 5.87 | Q35: =O35*P35 -> 23280.42 | S35: Schletter - INV1895 | T35: 45838 | U35: 44661.665 | W35: 45867 | Y35: =Y20 -> AC Equipment | Z35: 2941866.9
L36: 3 | M36: 3. Mounting Structures | U36: 0 | Y36: =Y21 -> DC Equipment | Z36: 4558110
L37: 3 | M37: 3. Mounting Structures | N37: Freight Charges | Q37: 17564 | S37: Schletter - INV1895 | T37: 45838 | U37: 33695.161 | W37: 45867 | Y37: =Y22 -> AC Labour | Z37: =AA37*7080000 -> 1770000 | AA37: 0.25
L38: 3 | M38: 3. Mounting Structures | U38: =(Q38/$X$29*$J$29) -> 0 | W38: 45930 | Y38: =Y23 -> DC Labour | Z38: =AA38*7080000 -> 4602000 | AA38: 0.65
L39: 3 | M39: 3. Mounting Structures | U39: =(Q39/$X$29*$J$29) -> 0 | W39: 45930 | Y39: =Y24 -> Offloading | Z39: 85000
L40: 3 | M40: 3. Mounting Structures | T40: =IF(W40>1,EOMONTH(W40,0),"") | U40: =(Q40/$X$29*$J$29) -> 0 | Y40: =Y25 -> Scaffolding | Z40: 133245.9
B41: 3 | L41: 3 | M41: 3. Mounting Structures | N41: Ground mount - Deposit | O41: =O8*620/1000 -> 3169.44 | P41: 0.97201398 | Q41: =O41*P41*1000*0.5 -> 1540370 | R41: PO3992-CSPH2-20250610 - RV Approved | S41: Schletter : INV1887 | T41: 45900 | U41: 2955079.4 | W41: 45827 | Y41: =Y26 -> Storage | Z41: 176058.33
B42: 3 | L42: 3 | M42: 3. Mounting Structures | N42: Ground mount - Balance | Q42: =O41*P41*1000*0.5 -> 1540370 | S42: Schletter: INV2113 | T42: 45900 | U42: 2955079.4 | W42: 45930 | Y42: =Y27 -> Telehandler | Z42: 150000
L43: 3 | M43: 3. Mounting Structures | Q43: -1540370 | S43: Schletter - CRN0271 | T43: 45930 | U43: 0 | W43: 45930
L44: 3 | M44: 3. Mounting Structures | Q44: -1540370 | S44: Schletter - CRN0272 | T44: 45930 | U44: 0 | W44: 45930
L45: 3 | M45: 3. Mounting Structures | Q45: 3006740 | S45: Schletter - INV2231 | T45: 45930 | U45: 0 | W45: 45930
B46: 3 | L46: 3 | M46: 3. Mounting Structures | N46: Engineering Signoff - deposit | Q46: =74000*50% -> 37000 | S46: Schletter : INV1887 | T46: 45838 | U46: 70981.607 | W46: 45827 | Y46: HSE | Z46: 4500
B47: 3 | L47: 3 | M47: 3. Mounting Structures | N47: Engineering Signoff - balance | Q47: =74000*50% -> 37000 | S47: Schletter: INV2113 | T47: 45900 | U47: 70981.607 | W47: =W42 -> 45930 | Y47: Other | Z47: 0
T48: =IF(W48>1,EOMONTH(W48,0),"") | Y48: Other | Z48: 0
B49: 4 | C49: DC Equipment | D49: DC Cable Budget | E49: 249988 | G49: 3499832 | H49: =H50 -> 45901 | I49: =SUM(G49:G72) -> 8057942 | J49: =F365 -> 8707455.1 | L49: 4 | M49: 4. DC Equipment | N49: DC Cable Budget | O49: 24000 | P49: 0 | Q49: =O49*P49 -> 0 | U49: =(Q49/$X$49*$J$49) -> 0 | V49: =J49-SUM(U49:U72) -> -0.0047537833 | X49: =SUM(Q49:Q72) -> 3329187 | Y49: Total | Z49: =SUM(Z35:Z48) -> 14420781
B50: 4 | D50: DC Equipment Budget | G50: =D365-G49 -> 4558110 | H50: 45901 | L50: 4 | M50: 4. DC Equipment | N50: DC Cable - Balance to be delivered | O50: 0.1 | P50: 2376000 | Q50: =O50*P50 -> 237600 | R50: PO3993-CSPH2-20260610 - RV Approved | S50: Menlo INV0003003 | T50: 45838 | U50: 465334.02 | W50: 45901 | Y50: R/Wp | Z50: =Z49/'Project Plan'!$E$3/1000 -> 2.0368335
L51: 4 | M51: 4. DC Equipment | N51: DC Cable | O51: 0.9 | Q51: =O51*P50 -> 2138400 | S51: Menlo INV0003047 | T51: 45838 | U51: 4188006.2 | W51: 45901
B52: 4 | L52: 4 | M52: 4. DC Equipment | N52: Jinko Connectors - Male | O52: 500 | P52: 13 | Q52: =O52*P52 -> 6500 | R52: PO4154-COEGA-20250723 - RV Approved | S52: Menlo INV0003096 | T52: 45869 | U52: 13627.717 | W52: 45925
B53: 4 | L53: 4 | M53: 4. DC Equipment | N53: Jinko Connectors - Female | O53: 500 | P53: 13 | Q53: =O53*P53 -> 6500 | S53: Menlo INV0003096 | T53: 45869 | U53: 13627.717 | W53: =W52 -> 45925
L54: 4 | M54: 4. DC Equipment | T54: =IF(W54>1,EOMONTH(W54,0),"") | U54: =(Q54/$X$49*$J$49) -> 0
L55: 4 | M55: 4. DC Equipment | N55: DC Cable Trays - As Per BOQ | Q55: 370187 | R55: PO4126-CSPH2-20250716 - RV Approved | S55: Advanced Strut INV IN152953 | T55: 45869 | U55: 1724074.2 | W55: 45904
L56: 4 | M56: 4. DC Equipment | U56: =(Q56/$X$49*$J$49) -> 0
L57: 4 | M57: 4. DC Equipment | T57: 45900 | U57: 1117518.2 | W57: 45900
L58: 4 | M58: 4. DC Equipment | T58: =IF(W58>1,EOMONTH(W58,0),"") | U58: =(Q58/$X$49*$J$49) -> 0
L59: 4 | M59: 4. DC Equipment | U59: =(Q59/$X$49*$J$49) -> 0
L60: 4 | M60: 4. DC Equipment | T60: =IF(W60>1,EOMONTH(W60,0),"") | U60: =(Q60/$X$49*$J$49) -> 0
L61: 4 | M61: 4. DC Equipment | T61: =IF(W61>1,EOMONTH(W61,0),"") | U61: =(Q61/$X$49*$J$49) -> 0
B62: 4 | L62: 4 | M62: 4. DC Equipment | N62: Project Kick Off - Rooftop | O62: =AC23/2 -> 275000 | P62: 0.5 | Q62: =$O$62*P62 -> 137500 | R62: PO4029-CSPH2-20250624 - RV Approved | S62: Luken Solar Inv: 0654 | T62: 45838 | U62: 269290.52 | W62: =W67 -> 45834
B63: 4 | L63: 4 | M63: 4. DC Equipment | N63: DC Equipment Onsite - Rooftop | P63: 0.4 | Q63: =$O$62*P63 -> 110000 | S63: Luken Solar Inv: 0660 | T63: =T68 -> 45869 | U63: 230622.91 | W63: =W68 -> 45910
B64: 4 | L64: 4 | M64: 4. DC Equipment | N64: End of Defects Period - Rooftop | P64: 0.1 | Q64: =$O$62*P64 -> 27500 | S64: Luken Solar Inv 0665 | T64: =T69 -> 45900 | U64: 71925.973 | W64: =W203 -> 46100
B65: 4 | L65: 4 | M65: 4. DC Equipment | T65: =IF(W65>1,EOMONTH(W65,0),"") | U65: =(Q65/$X$49*$J$49) -> 0
B66: 4 | L66: 4 | M66: 4. DC Equipment | T66: =IF(W66>1,EOMONTH(W66,0),"") | U66: =(Q66/$X$49*$J$49) -> 0
B67: 4 | L67: 4 | M67: 4. DC Equipment | N67: Project Kick Off - Ground Mount | O67: =AC30/2 -> 295000 | P67: 0.5 | Q67: =$O$67*P67 -> 147500 | S67: Luken Solar Inv: 0654 | T67: 45838 | U67: 288875.28 | W67: =W184 -> 45834
B68: 4 | L68: 4 | M68: 4. DC Equipment | N68: DC Equipment Onsite - Ground Mount | P68: 0.4 | Q68: =$O$67*P68 -> 118000 | S68: Luken Solar Inv: 0660 | T68: 45869 | U68: 247395.48 | W68: 45910
B69: 4 | L69: 4 | M69: 4. DC Equipment | N69: End of Defects Period - Ground Mount | P69: 0.1 | Q69: =$O$67*P69 -> 29500 | S69: Luken Solar Inv 0665 | T69: 45900 | U69: 77156.953 | W69: =W191 -> 46100
B70: 4 | L70: 4 | M70: 4. DC Equipment | T70: =IF(W70>1,EOMONTH(W70,0),"") | U70: =(Q70/$X$49*$J$49) -> 0
B71: 4 | L71: 4 | M71: 4. DC Equipment | T71: =IF(W71>1,EOMONTH(W71,0),"") | U71: =(Q71/$X$49*$J$49) -> 0
B72: 4 | L72: 4 | M72: 4. DC Equipment | T72: =IF(W72>1,EOMONTH(W72,0),"") | U72: =(Q72/$X$49*$J$49) -> 0
T73: =IF(W73>1,EOMONTH(W73,0),"")
B74: 5 | C74: Monitoring | D74: Monitoring Budget | G74: 26000 | H74: =H75 -> 45862 | I74: =SUM(G74:G94) -> 64000 | J74: =F367 -> 69158.741 | L74: 5 | M74: 5. Monitoring | N74: Metering Budget | U74: =(Q74/$X$74*$J$74) -> 0 | V74: =J74-SUM(U74:U94) -> 0.00054425999 | X74: =SUM(Q74:Q94) -> 241577.3
B75: 5 | D75: Comms DB | G75: 8000 | H75: 45862 | L75: 5 | M75: 5. Monitoring | N75: Janitza UMG604 pro | O75: 1 | Q75: 19205.5 | R75: PO4129-CSPH2-2020717 - RV Approved | S75: Harmonious Technical - QU100635 | T75: 45869 | U75: 3006.8452 | W75: 45862
L76: 5 | M76: 5. Monitoring | N76: Delivery of Janitza | Q76: 264.26 | S76: DSV Inv: 180140895 | T76: 45869 | U76: 41.372987 | W76: 45900
B77: 5 | D77: Revenue Grade Meter | G77: 30000 | H77: 45900 | L77: 5 | M77: 5. Monitoring | N77: Techsitter | O77: 1 | Q77: 11169 | S77: Matriarch - INV-4999 | T77: 45900 | U77: 26948.87 | W77: 45900 | Y77: TC: Changed amount - 30k
L78: 5 | M78: 5. Monitoring | N78: Delivery of Techsitter | Q78: 175.56 | S78: DSV Inv: 180140895 | T78: 45869 | U78: 27.485967 | W78: 45900
L79: 5 | M79: 5. Monitoring | N79: Encombi controller complete kit | O79: 1 | Q79: 95374 | R79: PO4128-CSPH2-20250717 - RV Approved | S79: Kathea Inv: 519753 + 519759 + 519762 | T79: 45869 | U79: 14931.913 | W79: 45930
L80: 5 | M80: 5. Monitoring | N80: Router and CTs | Q80: 15921 | R80: PO4125-COEG-20250716 - RV Approved | S80: AccuEnergy - ASAI-005973 | T80: 45869 | U80: 2492.6183 | W80: =T80+30 -> 45899
L81: 5 | M81: 5. Monitoring | N81: Optic Fiber Installation | Q81: 83760 | R81: PO4506-CSPH2-20251128 - RV Approve | S81: Paul van Vuuren Inv: IOG090 | T81: 46022 | U81: 17237.103 | W81: 46037
L82: 5 | M82: 5. Monitoring | Q82: -1980 | S82: Paul van Vuuren - CN000217 | T82: 46053 | W82: 46053
L83: 5 | M83: 5. Monitoring | N83: Meanwell MDR-100-24 | O83: 1 | Q83: 1060 | R83: PO4259-CSHP2-20250821 - RV Approved | S83: Mantech INV1078143 | T83: 45930 | U83: 335.8169 | W83: 45904
L84: 5 | M84: 5. Monitoring | U84: =(Q84/$X$74*$J$74) -> 0
L85: 5 | M85: 5. Monitoring | N85: Techsitter - Ground Mount | Q85: 11169 | S85: Matriarch - INV-5207 | T85: 45961 | U85: 3469.3218 | W85: 45974
L86: 5 | M86: 5. Monitoring | N86: Delivery of Techsitter | Q86: 308.98 | S86: DSV Inv: 180150385 | T86: 45961 | U86: 97.749105 | W86: 45991
L87: 5 | M87: 5. Monitoring | N87: Supply & Delivery - Mode Duplex Fibre Modules | Q87: 1980 | S87: Paul Van Vuuren - IOG122 | T87: 46053 | U87: 562.22433 | W87: 46065
L88: 5 | M88: 5. Monitoring | N88: AcuRev Energy Meter | Q88: 3170 | S88: AccuEnergy - ASAI-007302 | T88: 46053 | U88: 7.42 | W88: 46081
L89: 5 | M89: 5. Monitoring | T89: =IF(W89>1,EOMONTH(W89,0),"") | U89: =(Q89/$X$74*$J$74) -> 0
L90: 5 | M90: 5. Monitoring | T90: =IF(W90>1,EOMONTH(W90,0),"") | U90: =(Q90/$X$74*$J$74) -> 0
B91: 5 | L91: 5 | M91: 5. Monitoring | T91: =IF(W91>1,EOMONTH(W91,0),"") | U91: =(Q91/$X$74*$J$74) -> 0
B92: 5 | L92: 5 | M92: 5. Monitoring | T92: =IF(W92>1,EOMONTH(W92,0),"") | U92: =(Q92/$X$74*$J$74) -> 0
B93: 5 | L93: 5 | M93: 5. Monitoring | T93: =IF(W93>1,EOMONTH(W93,0),"") | U93: =(Q93/$X$74*$J$74) -> 0
B94: 5 | L94: 5 | M94: 5. Monitoring | T94: =IF(W94>1,EOMONTH(W94,0),"") | U94: =(Q94/$X$74*$J$74) -> 0
T95: =IF(W95>1,EOMONTH(W95,0),"")
B96: 6 | C96: AC Equipment | D96: AC Equipment Budget | G96: =D366 -> 2941866.9 | H96: =H97 -> 45901 | I96: =SUM(G96:G120) -> 2941866.9 | J96: =F366 -> 3178997.1 | L96: 6 | M96: 6. AC Equipment | U96: =(Q96/$X$96*$J$96) -> 0 | V96: =J96-SUM(U96:U120) -> 0.0029870779 | X96: =SUM(Q96:Q120) -> 2401487
B97: 6 | H97: 45901 | L97: 6 | M97: 6. AC Equipment | N97: MCCB Boards | P97: =Q97/20 -> 27122.75 | Q97: 542455 | R97: PO4115-COEG-20250710 - RV Approved | S97: Eastern Switchgear: 16889 | T97: 45869 | U97: 819376.53 | W97: 45901
L98: 6 | M98: 6. AC Equipment
L99: 6 | M99: 6. AC Equipment | N99: LV Cable | Q99: 111600 | S99: Herholdts - INV1198397 | T99: 46022 | W99: 46051
L100: 6 | M100: 6. AC Equipment | N100: Contigency | T100: 45900 | U100: 720273.72
L101: 6 | M101: 6. AC Equipment
L102: 6 | M102: 6. AC Equipment | N102: AC - LV/MV/Earthing Cable | P102: =Q102+Q103+Q104 -> 1126388 | Q102: 602839 | R102: PO4131-CSPH2-20250717 - RV Approved | S102: ARB : PLZ-3079494 | T102: 45869 | U102: 586595.34 | W102: 45900
L103: 6 | M103: 6. AC Equipment | N103: AC - LV/MV/Earthing Cable - Delivery 1 | Q103: 517469.18 | S103: ARB : PLZ-3079420 | T103: 45869 | U103: 460970.25 | W103: 45900
...

Sheet Cashflow
D1: [RT: Double Check the first date is always a MONDAY] | F1: 45677 | G1: =F1+7 -> 45684 | H1: =G1+7 -> 45691 | I1: =H1+7 -> 45698 | J1: =I1+7 -> 45705 | K1: =J1+7 -> 45712 | L1: =K1+7 -> 45719 | M1: =L1+7 -> 45726 | N1: =M1+7 -> 45733 | ... LD1: =LC1+7 -> 47847
A2: PLANNED | C2: CHECK | D2: CHECK
B3: Planned Revenue | C3: ='Revenue Tracking'!D4 -> 59995000 | D3: =SUM(F3:LD3) -> 59995000 | F3: =SUMIFS('Revenue Tracking'!$F$13:$F$21, 'Revenue Tracking'!$H$13:$H$21, ">="&F1,'Revenue Tracking'!$H$13:$H$21, "<"&G1) -> 0 | G3: =SUMIFS('Revenue Tracking'!$F$13:$F$21, 'Revenue Tracking'!$H$13:$H$21, ">="&G1,'Revenue Tracking'!$H$13:$H$21, "<"&H1) -> 0 | H3: =SUMIFS('Revenue Tracking'!$F$13:$F$21, 'Revenue Tracking'!$H$13:$H$21, ">="&H1,'Revenue Tracking'!$H$13:$H$21, "<"&I1) -> 0 | I3: =SUMIFS('Revenue Tracking'!$F$13:$F$21, 'Revenue Tracking'!$H$13:$H$21, ">="&I1,'Revenue Tracking'!$H$13:$H$21, "<"&J1) -> 0 | J3: =SUMIFS('Revenue Tracking'!$F$13:$F$21, 'Revenue Tracking'!$H$13:$H$21, ">="&J1,'Revenue Tracking'!$H$13:$H$21, "<"&K1) -> 0 | K3: =SUMIFS('Revenue Tracking'!$F$13:$F$21, 'Revenue Tracking'!$H$13:$H$21, ">="&K1,'Revenue Tracking'!$H$13:$H$21, "<"&L1) -> 0 | L3: =SUMIFS('Revenue Tracking'!$F$13:$F$21, 'Revenue Tracking'!$H$13:$H$21, ">="&L1,'Revenue Tracking'!$H$13:$H$21, "<"&M1) -> 0 | M3: =SUMIFS('Revenue Tracking'!$F$13:$F$21, 'Revenue Tracking'!$H$13:$H$21, ">="&M1,'Revenue Tracking'!$H$13:$H$21, "<"&N1) -> 0 | ... LC3: =SUMIFS('Revenue Tracking'!$F$13:$F$21, 'Revenue Tracking'!$H$13:$H$21, ">="&LC1,'Revenue Tracking'!$H$13:$H$21, "<"&LD1) -> 0 | LD3: =SUMIFS('Revenue Tracking'!$F$13:$F$21, 'Revenue Tracking'!$H$13:$H$21, ">="&LD1,'Revenue Tracking'!$H$13:$H$21, "<"&#REF!) -> 0
B4: Planned Revenue - Cumulative | F4: =F3 -> 0 | G4: =F4+G3 -> 0 | H4: =G4+H3 -> 0 | I4: =H4+I3 -> 0 | J4: =I4+J3 -> 0 | K4: =J4+K3 -> 0 | L4: =K4+L3 -> 0 | M4: =L4+M3 -> 0 | N4: =M4+N3 -> 0 | ... LD4: =LC4+LD3 -> 59995000
B5: Planned Expenditure | C5: ='Revenue Tracking'!D5 -> 56096452 | D5: =SUM(F5:LD5) -> 56096452 | F5: =SUMIFS('Expenditure Breakdown'!$G$6:$G$368, 'Expenditure Breakdown'!$H$6:$H$368, ">="&F1,'Expenditure Breakdown'!$H$6:$H$368, "<"&G1) -> 0 | G5: =SUMIFS('Expenditure Breakdown'!$G$6:$G$368, 'Expenditure Breakdown'!$H$6:$H$368, ">="&G1,'Expenditure Breakdown'!$H$6:$H$368, "<"&H1) -> 0 | H5: =SUMIFS('Expenditure Breakdown'!$G$6:$G$368, 'Expenditure Breakdown'!$H$6:$H$368, ">="&H1,'Expenditure Breakdown'!$H$6:$H$368, "<"&I1) -> 0 | I5: =SUMIFS('Expenditure Breakdown'!$G$6:$G$368, 'Expenditure Breakdown'!$H$6:$H$368, ">="&I1,'Expenditure Breakdown'!$H$6:$H$368, "<"&J1) -> 0 | J5: =SUMIFS('Expenditure Breakdown'!$G$6:$G$368, 'Expenditure Breakdown'!$H$6:$H$368, ">="&J1,'Expenditure Breakdown'!$H$6:$H$368, "<"&K1) -> 0 | K5: =SUMIFS('Expenditure Breakdown'!$G$6:$G$368, 'Expenditure Breakdown'!$H$6:$H$368, ">="&K1,'Expenditure Breakdown'!$H$6:$H$368, "<"&L1) -> 0 | L5: =SUMIFS('Expenditure Breakdown'!$G$6:$G$368, 'Expenditure Breakdown'!$H$6:$H$368, ">="&L1,'Expenditure Breakdown'!$H$6:$H$368, "<"&M1) -> 0 | M5: =SUMIFS('Expenditure Breakdown'!$G$6:$G$368, 'Expenditure Breakdown'!$H$6:$H$368, ">="&M1,'Expenditure Breakdown'!$H$6:$H$368, "<"&N1) -> 0 | ... LC5: =SUMIFS('Expenditure Breakdown'!$G$6:$G$368, 'Expenditure Breakdown'!$H$6:$H$368, ">="&LC1,'Expenditure Breakdown'!$H$6:$H$368, "<"&LD1) -> 0 | LD5: =SUMIFS('Expenditure Breakdown'!$G$6:$G$368, 'Expenditure Breakdown'!$H$6:$H$368, ">="&LD1,'Expenditure Breakdown'!$H$6:$H$368, "<"&#REF!) -> 0
B6: Planned Expenditure - Cumulative | F6: =F5 -> 0 | G6: =F6+G5 -> 0 | H6: =G6+H5 -> 0 | I6: =H6+I5 -> 0 | J6: =I6+J5 -> 0 | K6: =J6+K5 -> 0 | L6: =K6+L5 -> 0 | M6: =L6+M5 -> 0 | N6: =M6+N5 -> 0 | ... LD6: =LC6+LD5 -> 56096452
B7: PLANNED CashFlow | F7: =F4-F6 -> 0 | G7: =G4-G6 -> 0 | H7: =H4-H6 -> 0 | I7: =I4-I6 -> 0 | J7: =J4-J6 -> 0 | K7: =K4-K6 -> 0 | L7: =L4-L6 -> 0 | M7: =M4-M6 -> 0 | ... LD7: =LD4-LD6 -> 3898547.9
A8: ACTUAL | C8: CHECK | D8: CHECK
B9: Actual + Planned Revenue | C9: ='Revenue Tracking'!F4 -> 59995000 | D9: =SUM(F9:LD9) -> 59995000 | F9: =SUMIFS('Revenue Tracking'!$F$13:$F$21, 'Revenue Tracking'!$P$13:$P$21, ">="&F1,'Revenue Tracking'!$P$13:$P$21, "<"&G1) -> 0 | G9: =SUMIFS('Revenue Tracking'!$F$13:$F$21, 'Revenue Tracking'!$P$13:$P$21, ">="&G1,'Revenue Tracking'!$P$13:$P$21, "<"&H1) -> 0 | H9: =SUMIFS('Revenue Tracking'!$F$13:$F$21, 'Revenue Tracking'!$P$13:$P$21, ">="&H1,'Revenue Tracking'!$P$13:$P$21, "<"&I1) -> 0 | I9: =SUMIFS('Revenue Tracking'!$F$13:$F$21, 'Revenue Tracking'!$P$13:$P$21, ">="&I1,'Revenue Tracking'!$P$13:$P$21, "<"&J1) -> 0 | J9: =SUMIFS('Revenue Tracking'!$F$13:$F$21, 'Revenue Tracking'!$P$13:$P$21, ">="&J1,'Revenue Tracking'!$P$13:$P$21, "<"&K1) -> 0 | K9: =SUMIFS('Revenue Tracking'!$F$13:$F$21, 'Revenue Tracking'!$P$13:$P$21, ">="&K1,'Revenue Tracking'!$P$13:$P$21, "<"&L1) -> 0 | L9: =SUMIFS('Revenue Tracking'!$F$13:$F$21, 'Revenue Tracking'!$P$13:$P$21, ">="&L1,'Revenue Tracking'!$P$13:$P$21, "<"&M1) -> 0 | M9: =SUMIFS('Revenue Tracking'!$F$13:$F$21, 'Revenue Tracking'!$P$13:$P$21, ">="&M1,'Revenue Tracking'!$P$13:$P$21, "<"&N1) -> 0 | ... LC9: =SUMIFS('Revenue Tracking'!$F$13:$F$21, 'Revenue Tracking'!$P$13:$P$21, ">="&LC1,'Revenue Tracking'!$P$13:$P$21, "<"&LD1) -> 0 | LD9: =SUMIFS('Revenue Tracking'!$F$13:$F$21, 'Revenue Tracking'!$P$13:$P$21, ">="&LD1,'Revenue Tracking'!$P$13:$P$21, "<"&#REF!) -> 0
B10: Actual + Planned Revenue - Cumulative | F10: =F9 -> 0 | G10: =F10+G9 -> 0 | H10: =G10+H9 -> 0 | I10: =H10+I9 -> 0 | J10: =I10+J9 -> 0 | K10: =J10+K9 -> 0 | L10: =K10+L9 -> 0 | M10: =L10+M9 -> 0 | N10: =M10+N9 -> 0 | ... LD10: =LC10+LD9 -> 59995000
B11: Actual + Planned Expenditure | C11: ='Revenue Tracking'!F5 -> 48692192 | D11: =SUM(F11:LD11) -> 48692192 | F11: =SUMIFS('Expenditure Breakdown'!$Q$6:$Q$368, 'Expenditure Breakdown'!$W$6:$W$368, ">="&F1,'Expenditure Breakdown'!$W$6:$W$368, "<"&G1) -> 0 | G11: =SUMIFS('Expenditure Breakdown'!$Q$6:$Q$368, 'Expenditure Breakdown'!$W$6:$W$368, ">="&G1,'Expenditure Breakdown'!$W$6:$W$368, "<"&H1) -> 0 | H11: =SUMIFS('Expenditure Breakdown'!$Q$6:$Q$368, 'Expenditure Breakdown'!$W$6:$W$368, ">="&H1,'Expenditure Breakdown'!$W$6:$W$368, "<"&I1) -> 0 | I11: =SUMIFS('Expenditure Breakdown'!$Q$6:$Q$368, 'Expenditure Breakdown'!$W$6:$W$368, ">="&I1,'Expenditure Breakdown'!$W$6:$W$368, "<"&J1) -> 0 | J11: =SUMIFS('Expenditure Breakdown'!$Q$6:$Q$368, 'Expenditure Breakdown'!$W$6:$W$368, ">="&J1,'Expenditure Breakdown'!$W$6:$W$368, "<"&K1) -> 0 | K11: =SUMIFS('Expenditure Breakdown'!$Q$6:$Q$368, 'Expenditure Breakdown'!$W$6:$W$368, ">="&K1,'Expenditure Breakdown'!$W$6:$W$368, "<"&L1) -> 0 | L11: =SUMIFS('Expenditure Breakdown'!$Q$6:$Q$368, 'Expenditure Breakdown'!$W$6:$W$368, ">="&L1,'Expenditure Breakdown'!$W$6:$W$368, "<"&M1) -> 0 | M11: =SUMIFS('Expenditure Breakdown'!$Q$6:$Q$368, 'Expenditure Breakdown'!$W$6:$W$368, ">="&M1,'Expenditure Breakdown'!$W$6:$W$368, "<"&N1) -> 0 | ... LD11: =SUMIFS('Expenditure Breakdown'!$Q$6:$Q$368, 'Expenditure Breakdown'!$W$6:$W$368, ">="&LD1,'Expenditure Breakdown'!$W$6:$W$368, "<"&LE1) -> 0
B12: Actual + Planned Expenditure - Cumulative | F12: =F11 -> 0 | G12: =F12+G11 -> 0 | H12: =G12+H11 -> 0 | I12: =H12+I11 -> 0 | J12: =I12+J11 -> 0 | K12: =J12+K11 -> 0 | L12: =K12+L11 -> 0 | M12: =L12+M11 -> 0 | N12: =M12+N11 -> 0 | ... LD12: =LC12+LD11 -> 48692192
B14: ACTUAL CashFlow | F14: =F10-F12 -> 0 | G14: =G10-G12 -> 0 | H14: =H10-H12 -> 0 | I14: =I10-I12 -> 0 | J14: =J10-J12 -> 0 | K14: =K10-K12 -> 0 | L14: =L10-L12 -> 0 | M14: =M10-M12 -> 0 | ... LD14: =LD10-LD12 -> 11302808
C16: CHECK | D16: CHECK
B17: Revenue Recognition | C17: =C3-D17 -> -5195.4807 | D17: =SUM(F17:LD17) -> 60000195 | F17: =SUMIFS('Expenditure Breakdown'!$U$6:$U$368, 'Expenditure Breakdown'!$T$6:$T$368, ">="&F1,'Expenditure Breakdown'!$T$6:$T$368, "<"&G1) -> 0 | G17: =SUMIFS('Expenditure Breakdown'!$U$6:$U$368, 'Expenditure Breakdown'!$T$6:$T$368, ">="&G1,'Expenditure Breakdown'!$T$6:$T$368, "<"&H1) -> 0 | H17: =SUMIFS('Expenditure Breakdown'!$U$6:$U$368, 'Expenditure Breakdown'!$T$6:$T$368, ">="&H1,'Expenditure Breakdown'!$T$6:$T$368, "<"&I1) -> 0 | I17: =SUMIFS('Expenditure Breakdown'!$U$6:$U$368, 'Expenditure Breakdown'!$T$6:$T$368, ">="&I1,'Expenditure Breakdown'!$T$6:$T$368, "<"&J1) -> 0 | J17: =SUMIFS('Expenditure Breakdown'!$U$6:$U$368, 'Expenditure Breakdown'!$T$6:$T$368, ">="&J1,'Expenditure Breakdown'!$T$6:$T$368, "<"&K1) -> 0 | K17: =SUMIFS('Expenditure Breakdown'!$U$6:$U$368, 'Expenditure Breakdown'!$T$6:$T$368, ">="&K1,'Expenditure Breakdown'!$T$6:$T$368, "<"&L1) -> 0 | L17: =SUMIFS('Expenditure Breakdown'!$U$6:$U$368, 'Expenditure Breakdown'!$T$6:$T$368, ">="&L1,'Expenditure Breakdown'!$T$6:$T$368, "<"&M1) -> 0 | M17: =SUMIFS('Expenditure Breakdown'!$U$6:$U$368, 'Expenditure Breakdown'!$T$6:$T$368, ">="&M1,'Expenditure Breakdown'!$T$6:$T$368, "<"&N1) -> 0 | ... LC17: =SUMIFS('Expenditure Breakdown'!$U$6:$U$368, 'Expenditure Breakdown'!$T$6:$T$368, ">="&LC1,'Expenditure Breakdown'!$T$6:$T$368, "<"&LD1) -> 0 | LD17: =SUMIFS('Expenditure Breakdown'!$U$6:$U$368, 'Expenditure Breakdown'!$T$6:$T$368, ">="&LD1,'Expenditure Breakdown'!$T$6:$T$368, "<"&#REF!) -> 0
B18: Revenue Recognition Cumulative | C18: =D17-D18 -> 0 | D18: =MAX(F18:LD18) -> 60000195 | F18: =F17 -> 0 | G18: =F18+G17 -> 0 | H18: =G18+H17 -> 0 | I18: =H18+I17 -> 0 | J18: =I18+J17 -> 0 | K18: =J18+K17 -> 0 | L18: =K18+L17 -> 0 | M18: =L18+M17 -> 0 | N18: =M18+N17 -> 0 | ... LD18: =LC18+LD17 -> 60000195

Sheet Finance - Revenue
A3: Sum of REVENUE RECOGNITION AMOUNT | B3: Column Labels
A4: Row Labels | B4: (blank) | C4: 45808 | D4: 45838 | E4: 45869 | F4: 45900 | G4: 45930 | H4: 45961 | I4: 45991 | J4: 46022 | L4: 46053 | M4: 46081 | N4: 46112 | O4: Grand Total
A5: (blank)
A6: 1. Panels | E6: 15101046 | F6: 0 | I6: 0 | K6: 0 | O6: 15101046
A7: 2. Inverters | E7: 2967553.5 | F7: 14917.19 | J7: 0 | K7: 0 | L7: 0 | O7: 2982470.7
A8: 3. Mounting Structures | B8: 0 | D8: 1970802.9 | F8: 5981140.4 | G8: 0 | K8: 0 | O8: 7951943.3
A9: 4. DC Equipment | B9: 0 | D9: 5211506 | E9: 2229348 | F9: 1266601.1 | K9: 0 | O9: 8707455.1
A10: 5. Monitoring | B10: 0 | E10: 20500.235 | F10: 26948.87 | G10: 335.8169 | H10: 3567.0709 | J10: 17237.103 | K10: 0 | L10: 574.25433 | O10: 69163.351
A11: 6. AC Equipment | B11: 0 | D11: 283072.81 | E11: 2094714.6 | F11: 801209.65 | I11: 0 | K11: 0 | O11: 3178997
A12: 8. Product Add On | D12: 322824.35 | E12: 1106461.4 | F12: 698976.6 | H12: 1352.2372 | K12: 0 | M12: 47805.186 | O12: 2177419.7
A13: 9. AC & DC installation | B13: 0 | D13: 795716.76 | E13: 1384002.1 | F13: 2288695.7 | K13: 0 | L13: 661480.97 | O13: 5129895.6
A14: 10. Site Logistics | B14: 0 | D14: 219100.52 | E14: 182063.65 | F14: 48905.674 | G14: 1258.8741 | H14: 4983.0804 | I14: 5872.3514 | J14: 1703.1875 | K14: 0 | L14: 0 | O14: 463887.33
A15: 11. Due Dilligence | B15: 0 | D15: 12174.422 | E15: 184585.66 | H15: 58776.044 | I15: 21812.498 | M15: 216769.02 | O15: 494117.65
A16: 13. Engineering | F16: 12657.571 | G16: 3164.3928 | H16: 3108.9043 | I16: 3155.1443 | J16: 3118.0251 | K16: 0 | L16: 12700.507 | M16: 1041836.4 | O16: 1079740.9
A17: 14. General Expenses | C17: 0 | D17: 0 | E17: 0 | F17: 0 | G17: 0 | H17: 0 | I17: 0 | J17: 0 | K17: 0 | L17: 0 | M17: 0 | O17: 0
A18: 15. Service Add On
A19: 12. BDP Commission
A20: 7.MV Substation | B20: 0 | F20: 1043498.1 | I20: 11620566 | K20: 0 | O20: 12664064
A21: Grand Total | B21: 0 | C21: 0 | D21: 8815197.7 | E21: 25270275 | F21: 12183551 | G21: 4759.0838 | H21: 71787.337 | I21: 11651406 | J21: 22058.316 | K21: 0 | L21: 674755.73 | M21: 1306410.6 | O21: 60000200
D23: 8815197.7 | E23: 25270275 | F23: 12183551
D24: =GETPIVOTDATA("REVENUE RECOGNITION AMOUNT",$A$3,"INVOICE RAISED DATE",DATE(2025,6,30))-D23 -> -0.00050674379 | E24: =GETPIVOTDATA("REVENUE RECOGNITION AMOUNT",$A$3,"INVOICE RAISED DATE",DATE(2025,7,31))-E23 -> 0.00043057278 | F24: =GETPIVOTDATA("REVENUE RECOGNITION AMOUNT",$A$3,"INVOICE RAISED DATE",DATE(2025,8,31))-F23 -> 0.00043023936

Sheet Finance - COS
A3: Sum of Actual Total | B3: Column Labels
A4: Row Labels | B4: (blank) | C4: 45808 | D4: 45838 | E4: 45869 | F4: 45900 | G4: 45930 | H4: 45961 | I4: 45991 | J4: 46022 | L4: 46053 | M4: 46081 | N4: 46112 | O4: Grand Total
A5: (blank)
A6: 1. Panels | E6: 13735976 | F6: 43292.88 | I6: -43292.88 | O6: 13735976
A7: 2. Inverters | E7: 2495176.2 | J7: 899.72 | L7: -899.72 | O7: 2495176.2
A8: 3. Mounting Structures | D8: 1027304.3 | F8: 3117740 | G8: -74000 | O8: 4071044.3
A9: 4. DC Equipment | B9: 0 | D9: 2661000 | E9: 611187 | F9: 57000 | O9: 3329187
A10: 5. Monitoring | E10: 130940.32 | F10: 11169 | G10: 1060 | H10: 11477.98 | J10: 83760 | L10: 3170 | O10: 241577.3
A11: 6. AC Equipment | D11: 285000 | E11: 1896843 | F11: 57000 | I11: 51044 | J11: 111600 | O11: 2401487
A12: 8. Product Add On | D12: 274155.94 | E12: 1142236 | F12: 748350 | H12: 1376.27 | M12: 50000 | O12: 2216118.2
A13: 9. AC & DC installation | D13: 1023750 | E13: 2272840 | F13: 3720340 | L13: 1038750 | O13: 8055680
A14: 10. Site Logistics | D14: 335650 | E14: 271950 | F14: 164367.17 | G14: 7908.92 | H14: 8636.97 | I14: 49179.8 | J14: 90501.1 | L14: 7919.15 | O14: 936113.11
A15: 11. Due Dilligence | D15: 10400 | E15: 252556 | H15: 79700 | I15: 28400 | M15: 287600 | O15: 658656
A16: 13. Engineering | F16: 11372 | G16: 2843 | H16: 2843 | I16: 2843 | J16: 2843 | L16: 11580.26 | M16: 950000 | O16: 984324.26
A17: 14. General Expenses | C17: 6509.86 | D17: 5770.84 | E17: 21295.98 | F17: 50534.6 | G17: 32154.96 | H17: 20629.91 | I17: 15266.94 | J17: 59700.29 | L17: 28655.7 | M17: 30662.5 | O17: 271181.58
A18: 15. Service Add On | F18: 5983.56 | G18: 3399.75 | H18: 14194.43 | I18: 183718.93 | J18: 1519.09 | L18: 274402.47 | M18: 1158765.8 | N18: 607059 | O18: 2249043
A19: 12. BDP Commission | K19: 0 | O19: 0
A20: 7.MV Substation | F20: 582344.8 | I20: 6464282.8 | O20: 7046627.6
A21: Grand Total | B21: 0 | C21: 6509.86 | D21: 5623031 | E21: 22831001 | F21: 8569494 | G21: -26633.37 | H21: 138858.56 | I21: 6751442.6 | J21: 350823.2 | K21: 0 | L21: 1363577.9 | M21: 2477028.3 | N21: 607059 | O21: 48692192
D23: 4704545
D25: =GETPIVOTDATA("Actual Total ",$A$3,"INVOICE RAISED DATE",DATE(2025,6,30))-D23 -> 918486.04

Sheet Certificate - Financial Close
B2: Emergent Energy – Financial Close Completion Certificate | H2: FINANCIAL CLOSE CERTIFICATE
B4: Project Name: | C4: ='Project Plan'!E2 -> Coega Steels Phase 2
B5: COO: | C5: Johannes Potgieter
B6: Programme Manager: | C6: Roedolph Venter
B7: HoPD: | C7: Natasha Watkins-Baker
B9: Date of Phase Completion:
B10: Phase Deliverables Checklist: (Y/N)
B11: Product Agreement | C11: NA
B12: EPC Agreement | C12: NA
B13: O&M Agreeement | C13: NA
B14: Cost Proposal | C14: Signed
B15: Deposit Received | C15: Yes
B16: Risks / Notes | C16: None
B18: Acknowledgement and Acceptance:
B19: Role | C19: Name | D19: Signature | E19: Date
B20: COO | C20: Johannes | D20: JTP | E20: 45953

Sheet Project Margins
A1: [capture project margins from costing sheet]
A3: Products | D3: 0.32
A4: Services | D4: 0.5
A5: Expenses | D5: 0.15
A6: Subcontractors | D6: 0.2

Sheet Equipment Quotes
B2: Equipment Quote and Budget comparision
B4: Description | D4: Budget | F4: Supplier 1 | H4: Variance | J4: Supplier 2 | L4: Variance | N4: Comments / Notes
F7: >Name< | J7: >Name<
B9: Inverters | D9: =SUM(D10:D11) -> #REF! | F9: =SUM(F10:F13) -> 0 | H9: =$D$9-F9 -> #REF! | J9: =SUM(J10:J13) -> 0 | L9: =$D$9-J9 -> #REF!
B10: Inverters | D10: =#REF! -> #REF!
B11: Optimizers | D11: =#REF! -> #REF!
B12: Warranty
B13: Delivery fee
F15: >Name< | J15: >Name<
B17: Mounting Structure | D17: =SUM(D18:D19) -> #REF! | F17: =SUM(F18:F20) -> 0 | H17: =$D$17- F17 -> #REF! | J17: =SUM(J18:J20) -> 0 | L17: =$D$17- J17 -> #REF!
B18: Mounting Structure | D18: =#REF! -> #REF!
B19: Delivery fee
F21: >Name< | J21: >Name<
B23: DC Cable | D23: =SUM(D24:D25) -> #REF! | F23: =SUM(F24:F25) -> 0 | H23: =$D$23- F23 -> #REF! | J23: =SUM(J24:J25) -> 0 | L23: =$D$23- J23 -> #REF!
B24: DC Cable | D24: =#REF! -> #REF!
B25: Delivery fee
F27: >Name< | J27: >Name<
B29: Monitoring system | D29: =SUM(D30:D32) -> #REF! | F29: =SUM(F30:F42) -> 0 | H29: =$D$29-F29 -> #REF! | J29: =SUM(J30:J32) -> 0 | L29: =$D$29-J29 -> #REF!
B30: =#REF! -> #REF! | D30: =#REF! -> #REF!
B31: =#REF! -> #REF! | D31: =#REF! -> #REF!
B32: Delivery fee
F34: >Name< | J34: >Name<
B36: Additional Scope | D36: =SUM(D37:D41) -> #REF! | F36: =SUM(F37:F41) -> 0 | H36: =$D$29-F36 -> #REF! | J36: =SUM(J37:J41) -> 0 | L36: =$D$29-J36 -> #REF!
B37: SCADA | D37: =#REF! -> #REF!
B38: Inverter cage
B39: Cat ladders
B40: Gen Integration
B41: Lifelines
B43: Totals | D43: =D36+D29+D23+D17+D9 -> #REF! | H43: =SUM(H7:H42) -> #REF! | L43: =SUM(L7:L42) -> #REF!
B47: All amounts are incl VAT

Sheet Installer Quotes
B2: Installer Quote and Budget comparision
B4: Description | D4: Budget | G4: Cosmic Sun | J4: Variance | L4: Matthews Group | O4: Variance
B6: AC Equipment | D6: =#REF! -> #REF! | E6: =D6/(1000*'Project Plan'!$E$3) -> #REF! | G6: 277892.91 | H6: =G6/('Project Plan'!$E$3*1000) -> 0.039250411 | J6: =D6-G6 -> #REF! | M6: =L6/('Project Plan'!$E$3*1000) -> 0 | O6: =D6-L6 -> #REF!
B7: DC Equipment | D7: =#REF! -> #REF! | E7: =D7/(1000*'Project Plan'!$E$3) -> #REF! | G7: 142158.25 | H7: =G7/('Project Plan'!$E$3*1000) -> 0.020078849 | J7: =D7-G7 -> #REF! | M7: =L7/('Project Plan'!$E$3*1000) -> 0 | O7: =D7-L7 -> #REF!
B8: AC Labour | D8: =#REF! -> #REF! | E8: =D8/(1000*'Project Plan'!$E$3) -> #REF! | G8: 96174 | H8: =G8/('Project Plan'!$E$3*1000) -> 0.013583898 | J8: =D8-G8 -> #REF! | M8: =L8/('Project Plan'!$E$3*1000) -> 0 | O8: =D8-L8 -> #REF!
B9: DC Labour | D9: =#REF! -> #REF! | E9: =D9/(1000*'Project Plan'!$E$3) -> #REF! | G9: 230160 | H9: =G9/('Project Plan'!$E$3*1000) -> 0.032508475 | J9: =D9-G9 -> #REF! | M9: =L9/('Project Plan'!$E$3*1000) -> 0 | O9: =D9-L9 -> #REF!
B10: Offloading | D10: =#REF! -> #REF! | G10: 0 | J10: =D10-G10 -> #REF! | O10: =D10-L10 -> #REF!
B11: Roof Access/Scaffolding | D11: =#REF! -> #REF! | G11: 29257.61 | J11: =D11-G11 -> #REF! | O11: =D11-L11 -> #REF!
B12: Storage | D12: =#REF! -> #REF! | J12: =D12-G12 -> #REF! | O12: =D12-L12 -> #REF!
B13: Telehandler | D13: =#REF! -> #REF!
B14: HSE | D14: 0
B15: Totals | D15: =SUM(D6:D13) -> #REF! | G15: =SUM(G6:G13) -> 775642.77 | J15: =SUM(J6:J14) -> #REF! | L15: =SUM(L6:L13) -> 0 | O15: =SUM(O6:O14) -> #REF!
B18: Description | D18: Budget | G18: >Installer Name 3< | J18: Variance | L18: >Installer Name 4< | O18: Variance
B20: AC installation | D20: =#REF! -> #REF! | E20: =D20/(1000*'Project Plan'!$E$3) -> #REF! | H20: =G20/(1000*'Project Plan'!$E$3) -> 0 | J20: =D20-G20 -> #REF! | M20: =L20/(1000*'Project Plan'!$E$3) -> 0 | O20: =D6-L20 -> #REF!
B21: AC equipment | D21: =#REF! -> #REF! | E21: =D21/(1000*'Project Plan'!$E$3) -> #REF! | J21: =D21-G21 -> #REF! | M21: =L21/(1000*'Project Plan'!$E$3) -> 0 | O21: =D7-L21 -> #REF!
B22: DC installation | D22: =#REF! -> #REF! | E22: =D22/(1000*'Project Plan'!$E$3) -> #REF! | H22: =G22/(1000*'Project Plan'!$E$3) -> 0 | J22: =D22-G22 -> #REF! | M22: =L22/(1000*'Project Plan'!$E$3) -> 0 | O22: =D8-L22 -> #REF!
B23: DC equipment | D23: =SUM(#REF!) -> #REF! | E23: =D23/(1000*'Project Plan'!$E$3) -> #REF! | J23: =D23-G23 -> #REF! | O23: =D9-L23 -> #REF!
B24: Storage | D24: =#REF! -> #REF! | J24: =D24-G24 -> #REF! | O24: =D10-L24 -> #REF!
B25: Panel lifting equipment | D25: =SUM(#REF!) -> #REF! | J25: =D25-G25 -> #REF! | O25: =D11-L25 -> #REF!
B26: Offloading | D26: =#REF! -> #REF! | J26: =D26-G26 -> #REF! | O26: =D12-L26 -> #REF!
B29: Totals | D29: =SUM(D20:D27) -> #REF! | G29: =SUM(G20:G27) -> 0 | J29: =SUM(J20:J28) -> #REF! | L29: =SUM(L20:L27) -> 0 | O29: =SUM(O20:O28) -> #REF!
B32: Budget Summary
B34: Budget | D34: =D15 -> #REF!
B35: =G4 -> Cosmic Sun | D35: =G15 -> 775642.77
B36: =L4 -> Matthews Group | D36: =L15 -> 0
B37: =G18 -> >Installer Name 3< | D37: =G29 -> 0
B38: =L18 -> >Installer Name 4< | D38: =L29 -> 0
B40: =IF(D40<D34,"Saving","Loss") -> #REF! | D40: =D34-MIN(D35:D38) -> #REF!
B42: All amounts are exc VAT

Sheet Decision Register
B1: =D15 -> Coega Steels Phase 2 | E1: Decision Register
B3: ID | C3: Decision Description | D3: Decision Impact | E3: Proposed Date | F3: Proposed By | G3: Status | H3: Approved By | I3: Date | J3: Results / Comments
B4: DEC001
B5: DEC002
B6: DEC003
B7: DEC004
B8: DEC005
B9: DEC006
B10: DEC007
B11: DEC008
B12: DEC009
B13: DEC010
D15: {='Project Plan'!E2:H2} -> Coega Steels Phase 2 | E15: 0 | F15: 0 | G15: 0
