Workbook
Name Inverter_Capacity: #REF!
Name Inverter_Supplier: #REF!
Name Project_Size: 'Certificate - Financial Close'!Projectsize
Name Project_Size: 'Change Register'!Projectsize
Name Project_Size: 'Finance - Revenue'!Projectsize
Name Project_Size: Projectsize
Name Projectsize: 'Project Margins'!$K$5
Name Projectsize: #REF!
Name Projectsize: #REF!
Name Projectsize: 'Project Margins'!$K$5
Name Security_Serv: #REF!
Name Security_Serv: #REF!
Name SSS: #REF!
Name SSS: #REF!
Name USD_ZAR: #REF!

Sheet Sheet1
A1: PROJECT PLAN
A2: # | B2: Project Milestone | C2: Planned Start Date | D2: Duration (Work Days) | E2: Planned End Date | F2: Actual Start Date | H2: Actual End Date | J2: Comments | L2: =C3 -> 43831 | M2: =L2+3 -> 43834 | N2: =M2+7 -> 43841 | O2: =N2+7 -> 43848 | P2: =O2+7 -> 43855 | Q2: =P2+6 -> 43861 | R2: =Q2+1 -> 43862 | S2: =R2+7 -> 43869 | T2: =S2+7 -> 43876 | U2: =T2+7 -> 43883 | V2: =U2+6 -> 43889 | W2: =V2+7 -> 43896 | X2: =W2+7 -> 43903 | Y2: =X2+7 -> 43910 | Z2: =Y2+7 -> 43917 | AA2: =Z2+3 -> 43920 | AB2: =AA2+4 -> 43924 | AC2: =AB2+7 -> 43931 | AD2: =AC2+7 -> 43938 | AE2: =AD2+7 -> 43945 | AF2: =AE2+6 -> 43951 | AG2: =AF2+2 -> 43953 | AH2: =AG2+7 -> 43960 | AI2: =AH2+7 -> 43967 | AJ2: =AI2+7 -> 43974 | AK2: =AJ2+7 -> 43981 | AL2: =AK2+1 -> 43982 | AM2: =AL2+6 -> 43988 | AN2: =AM2+7 -> 43995 | AO2: =AN2+7 -> 44002 | AP2: =AO2+7 -> 44009 | AQ2: =AP2+3 -> 44012 | AR2: =AQ2+4 -> 44016 | AS2: =AR2+7 -> 44023 | AT2: =AS2+7 -> 44030 | AU2: =AT2+7 -> 44037 | AV2: =AU2+6 -> 44043 | AW2: =AV2+1 -> 44044 | AX2: =AW2+7 -> 44051 | AY2: =AX2+7 -> 44058 | AZ2: =AY2+7 -> 44065 | BA2: =AZ2+7 -> 44072 | BB2: =BA2+2 -> 44074 | BC2: =BB2+5 -> 44079 | BD2: =BC2+7 -> 44086 | BE2: =BD2+7 -> 44093 | BF2: =BE2+7 -> 44100 | BG2: =BF2+4 -> 44104
A3: 1 | B3: Contract Signature | C3: 43831 | D3: 1 | E3: 43832 | F3: 43831 | G3: 1 | H3: 43832 | L3: =IF(AND($F3<(L$2+7),$F3>L$2),1, IF(AND($H3<L$2+7,$H3>L$2),3, IF(AND($F3<=L$2, $H3>=L$2), 2, "" ))) -> 3 | M3: =IF(AND($F3<(M$2+7),$F3>M$2),1, IF(AND($H3<M$2+7,$H3>M$2),3, IF(AND($F3<=M$2, $H3>=M$2), 2, "" ))) | N3: =IF(AND($F3<(N$2+7),$F3>N$2),1, IF(AND($H3<N$2+7,$H3>N$2),3, IF(AND($F3<=N$2, $H3>=N$2), 2, "" ))) | O3: =IF(AND($F3<(O$2+7),$F3>O$2),1, IF(AND($H3<O$2+7,$H3>O$2),3, IF(AND($F3<=O$2, $H3>=O$2), 2, "" ))) | P3: =IF(AND($F3<(P$2+7),$F3>P$2),1, IF(AND($H3<P$2+7,$H3>P$2),3, IF(AND($F3<=P$2, $H3>=P$2), 2, "" ))) | Q3: =IF(AND($F3<(Q$2+7),$F3>Q$2),1, IF(AND($H3<Q$2+7,$H3>Q$2),3, IF(AND($F3<=Q$2, $H3>=Q$2), 2, "" ))) | R3: =IF(AND($F3<(R$2+7),$F3>R$2),1, IF(AND($H3<R$2+7,$H3>R$2),3, IF(AND($F3<=R$2, $H3>=R$2), 2, "" ))) | S3: =IF(AND($F3<(S$2+7),$F3>S$2),1, IF(AND($H3<S$2+7,$H3>S$2),3, IF(AND($F3<=S$2, $H3>=S$2), 2, "" ))) | ... AQ3: =IF(AND($F3<(AQ$2+7),$F3>AQ$2),1, IF(AND($H3<AQ$2+7,$H3>AQ$2),3, IF(AND($F3<=AQ$2, $H3>=AQ$2), 2, "" )))
A4: A | B4: PAYMENT MILESTONE 1: DEPOSIT | C4: 43832 | D4: 1 | E4: 43833 | F4: 43832 | G4: 1 | H4: 43833 | L4: =IF(AND($F4<(L$2+7),$F4>L$2),1, IF(AND($H4<L$2+7,$H4>L$2),3, IF(AND($F4<=L$2, $H4>=L$2), 2, "" ))) -> 1 | M4: =IF(AND($F4<(M$2+7),$F4>M$2),1, IF(AND($H4<M$2+7,$H4>M$2),3, IF(AND($F4<=M$2, $H4>=M$2), 2, "" ))) | N4: =IF(AND($F4<(N$2+7),$F4>N$2),1, IF(AND($H4<N$2+7,$H4>N$2),3, IF(AND($F4<=N$2, $H4>=N$2), 2, "" ))) | O4: =IF(AND($F4<(O$2+7),$F4>O$2),1, IF(AND($H4<O$2+7,$H4>O$2),3, IF(AND($F4<=O$2, $H4>=O$2), 2, "" ))) | P4: =IF(AND($F4<(P$2+7),$F4>P$2),1, IF(AND($H4<P$2+7,$H4>P$2),3, IF(AND($F4<=P$2, $H4>=P$2), 2, "" ))) | Q4: =IF(AND($F4<(Q$2+7),$F4>Q$2),1, IF(AND($H4<Q$2+7,$H4>Q$2),3, IF(AND($F4<=Q$2, $H4>=Q$2), 2, "" ))) | R4: =IF(AND($F4<(R$2+7),$F4>R$2),1, IF(AND($H4<R$2+7,$H4>R$2),3, IF(AND($F4<=R$2, $H4>=R$2), 2, "" ))) | S4: =IF(AND($F4<(S$2+7),$F4>S$2),1, IF(AND($H4<S$2+7,$H4>S$2),3, IF(AND($F4<=S$2, $H4>=S$2), 2, "" ))) | ... AQ4: =IF(AND($F4<(AQ$2+7),$F4>AQ$2),1, IF(AND($H4<AQ$2+7,$H4>AQ$2),3, IF(AND($F4<=AQ$2, $H4>=AQ$2), 2, "" )))
A5: 2 | B5: Structural and Electrical Due Diligences | C5: 43833 | D5: 5 | E5: 43840 | F5: 43833 | G5: 5 | H5: 43840 | L5: =IF(AND($F5<(L$2+7),$F5>L$2),1, IF(AND($H5<L$2+7,$H5>L$2),3, IF(AND($F5<=L$2, $H5>=L$2), 2, "" ))) -> 1 | M5: =IF(AND($F5<(M$2+7),$F5>M$2),1, IF(AND($H5<M$2+7,$H5>M$2),3, IF(AND($F5<=M$2, $H5>=M$2), 2, "" ))) -> 3 | N5: =IF(AND($F5<(N$2+7),$F5>N$2),1, IF(AND($H5<N$2+7,$H5>N$2),3, IF(AND($F5<=N$2, $H5>=N$2), 2, "" ))) | O5: =IF(AND($F5<(O$2+7),$F5>O$2),1, IF(AND($H5<O$2+7,$H5>O$2),3, IF(AND($F5<=O$2, $H5>=O$2), 2, "" ))) | P5: =IF(AND($F5<(P$2+7),$F5>P$2),1, IF(AND($H5<P$2+7,$H5>P$2),3, IF(AND($F5<=P$2, $H5>=P$2), 2, "" ))) | Q5: =IF(AND($F5<(Q$2+7),$F5>Q$2),1, IF(AND($H5<Q$2+7,$H5>Q$2),3, IF(AND($F5<=Q$2, $H5>=Q$2), 2, "" ))) | R5: =IF(AND($F5<(R$2+7),$F5>R$2),1, IF(AND($H5<R$2+7,$H5>R$2),3, IF(AND($F5<=R$2, $H5>=R$2), 2, "" ))) | S5: =IF(AND($F5<(S$2+7),$F5>S$2),1, IF(AND($H5<S$2+7,$H5>S$2),3, IF(AND($F5<=S$2, $H5>=S$2), 2, "" ))) | ... AQ5: =IF(AND($F5<(AQ$2+7),$F5>AQ$2),1, IF(AND($H5<AQ$2+7,$H5>AQ$2),3, IF(AND($F5<=AQ$2, $H5>=AQ$2), 2, "" )))
A6: 3 | B6: Design Confirmation | C6: 43841 | D6: 2 | E6: 43844 | F6: 43841 | G6: 2 | H6: 43844 | L6: =IF(AND($F6<(L$2+7),$F6>L$2),1, IF(AND($H6<L$2+7,$H6>L$2),3, IF(AND($F6<=L$2, $H6>=L$2), 2, "" ))) | M6: =IF(AND($F6<(M$2+7),$F6>M$2),1, IF(AND($H6<M$2+7,$H6>M$2),3, IF(AND($F6<=M$2, $H6>=M$2), 2, "" ))) | N6: =IF(AND($F6<(N$2+7),$F6>N$2),1, IF(AND($H6<N$2+7,$H6>N$2),3, IF(AND($F6<=N$2, $H6>=N$2), 2, "" ))) -> 3 | O6: =IF(AND($F6<(O$2+7),$F6>O$2),1, IF(AND($H6<O$2+7,$H6>O$2),3, IF(AND($F6<=O$2, $H6>=O$2), 2, "" ))) | P6: =IF(AND($F6<(P$2+7),$F6>P$2),1, IF(AND($H6<P$2+7,$H6>P$2),3, IF(AND($F6<=P$2, $H6>=P$2), 2, "" ))) | Q6: =IF(AND($F6<(Q$2+7),$F6>Q$2),1, IF(AND($H6<Q$2+7,$H6>Q$2),3, IF(AND($F6<=Q$2, $H6>=Q$2), 2, "" ))) | R6: =IF(AND($F6<(R$2+7),$F6>R$2),1, IF(AND($H6<R$2+7,$H6>R$2),3, IF(AND($F6<=R$2, $H6>=R$2), 2, "" ))) | S6: =IF(AND($F6<(S$2+7),$F6>S$2),1, IF(AND($H6<S$2+7,$H6>S$2),3, IF(AND($F6<=S$2, $H6>=S$2), 2, "" ))) | ... AQ6: =IF(AND($F6<(AQ$2+7),$F6>AQ$2),1, IF(AND($H6<AQ$2+7,$H6>AQ$2),3, IF(AND($F6<=AQ$2, $H6>=AQ$2), 2, "" )))
A7: 4 | B7: Equipment Procurement | C7: 43833 | E7: 43949 | F7: 43833 | H7: 43949 | L7: =IF(AND($F7<(L$2+7),$F7>L$2),1, IF(AND($H7<L$2+7,$H7>L$2),3, IF(AND($F7<=L$2, $H7>=L$2), 2, "" ))) -> 1 | M7: =IF(AND($F7<(M$2+7),$F7>M$2),1, IF(AND($H7<M$2+7,$H7>M$2),3, IF(AND($F7<=M$2, $H7>=M$2), 2, "" ))) -> 2 | N7: =IF(AND($F7<(N$2+7),$F7>N$2),1, IF(AND($H7<N$2+7,$H7>N$2),3, IF(AND($F7<=N$2, $H7>=N$2), 2, "" ))) -> 2 | O7: =IF(AND($F7<(O$2+7),$F7>O$2),1, IF(AND($H7<O$2+7,$H7>O$2),3, IF(AND($F7<=O$2, $H7>=O$2), 2, "" ))) -> 2 | P7: =IF(AND($F7<(P$2+7),$F7>P$2),1, IF(AND($H7<P$2+7,$H7>P$2),3, IF(AND($F7<=P$2, $H7>=P$2), 2, "" ))) -> 2 | Q7: =IF(AND($F7<(Q$2+7),$F7>Q$2),1, IF(AND($H7<Q$2+7,$H7>Q$2),3, IF(AND($F7<=Q$2, $H7>=Q$2), 2, "" ))) -> 2 | R7: =IF(AND($F7<(R$2+7),$F7>R$2),1, IF(AND($H7<R$2+7,$H7>R$2),3, IF(AND($F7<=R$2, $H7>=R$2), 2, "" ))) -> 2 | S7: =IF(AND($F7<(S$2+7),$F7>S$2),1, IF(AND($H7<S$2+7,$H7>S$2),3, IF(AND($F7<=S$2, $H7>=S$2), 2, "" ))) -> 2 | ... AQ7: =IF(AND($F7<(AQ$2+7),$F7>AQ$2),1, IF(AND($H7<AQ$2+7,$H7>AQ$2),3, IF(AND($F7<=AQ$2, $H7>=AQ$2), 2, "" )))
B8: Panel Procurement | C8: 43833 | D8: 5 | E8: 43840 | F8: 43833 | G8: 5 | H8: 43840 | L8: =IF(AND($F8<(L$2+7),$F8>L$2),1, IF(AND($H8<L$2+7,$H8>L$2),3, IF(AND($F8<=L$2, $H8>=L$2), 2, "" ))) -> 1 | M8: =IF(AND($F8<(M$2+7),$F8>M$2),1, IF(AND($H8<M$2+7,$H8>M$2),3, IF(AND($F8<=M$2, $H8>=M$2), 2, "" ))) -> 3 | N8: =IF(AND($F8<(N$2+7),$F8>N$2),1, IF(AND($H8<N$2+7,$H8>N$2),3, IF(AND($F8<=N$2, $H8>=N$2), 2, "" ))) | O8: =IF(AND($F8<(O$2+7),$F8>O$2),1, IF(AND($H8<O$2+7,$H8>O$2),3, IF(AND($F8<=O$2, $H8>=O$2), 2, "" ))) | P8: =IF(AND($F8<(P$2+7),$F8>P$2),1, IF(AND($H8<P$2+7,$H8>P$2),3, IF(AND($F8<=P$2, $H8>=P$2), 2, "" ))) | Q8: =IF(AND($F8<(Q$2+7),$F8>Q$2),1, IF(AND($H8<Q$2+7,$H8>Q$2),3, IF(AND($F8<=Q$2, $H8>=Q$2), 2, "" ))) | R8: =IF(AND($F8<(R$2+7),$F8>R$2),1, IF(AND($H8<R$2+7,$H8>R$2),3, IF(AND($F8<=R$2, $H8>=R$2), 2, "" ))) | S8: =IF(AND($F8<(S$2+7),$F8>S$2),1, IF(AND($H8<S$2+7,$H8>S$2),3, IF(AND($F8<=S$2, $H8>=S$2), 2, "" ))) | ... AQ8: =IF(AND($F8<(AQ$2+7),$F8>AQ$2),1, IF(AND($H8<AQ$2+7,$H8>AQ$2),3, IF(AND($F8<=AQ$2, $H8>=AQ$2), 2, "" )))
B9: Inverter Procurement | C9: 43941 | D9: 5 | E9: 43949 | F9: 43941 | G9: 5 | H9: 43949 | L9: =IF(AND($F9<(L$2+7),$F9>L$2),1, IF(AND($H9<L$2+7,$H9>L$2),3, IF(AND($F9<=L$2, $H9>=L$2), 2, "" ))) | M9: =IF(AND($F9<(M$2+7),$F9>M$2),1, IF(AND($H9<M$2+7,$H9>M$2),3, IF(AND($F9<=M$2, $H9>=M$2), 2, "" ))) | N9: =IF(AND($F9<(N$2+7),$F9>N$2),1, IF(AND($H9<N$2+7,$H9>N$2),3, IF(AND($F9<=N$2, $H9>=N$2), 2, "" ))) | O9: =IF(AND($F9<(O$2+7),$F9>O$2),1, IF(AND($H9<O$2+7,$H9>O$2),3, IF(AND($F9<=O$2, $H9>=O$2), 2, "" ))) | P9: =IF(AND($F9<(P$2+7),$F9>P$2),1, IF(AND($H9<P$2+7,$H9>P$2),3, IF(AND($F9<=P$2, $H9>=P$2), 2, "" ))) | Q9: =IF(AND($F9<(Q$2+7),$F9>Q$2),1, IF(AND($H9<Q$2+7,$H9>Q$2),3, IF(AND($F9<=Q$2, $H9>=Q$2), 2, "" ))) | R9: =IF(AND($F9<(R$2+7),$F9>R$2),1, IF(AND($H9<R$2+7,$H9>R$2),3, IF(AND($F9<=R$2, $H9>=R$2), 2, "" ))) | S9: =IF(AND($F9<(S$2+7),$F9>S$2),1, IF(AND($H9<S$2+7,$H9>S$2),3, IF(AND($F9<=S$2, $H9>=S$2), 2, "" ))) | ... AQ9: =IF(AND($F9<(AQ$2+7),$F9>AQ$2),1, IF(AND($H9<AQ$2+7,$H9>AQ$2),3, IF(AND($F9<=AQ$2, $H9>=AQ$2), 2, "" )))
B10: Mounting Structure Procurement | C10: 43941 | D10: 5 | E10: 43949 | F10: 43941 | G10: 5 | H10: 43949 | L10: =IF(AND($F10<(L$2+7),$F10>L$2),1, IF(AND($H10<L$2+7,$H10>L$2),3, IF(AND($F10<=L$2, $H10>=L$2), 2, "" ))) | M10: =IF(AND($F10<(M$2+7),$F10>M$2),1, IF(AND($H10<M$2+7,$H10>M$2),3, IF(AND($F10<=M$2, $H10>=M$2), 2, "" ))) | N10: =IF(AND($F10<(N$2+7),$F10>N$2),1, IF(AND($H10<N$2+7,$H10>N$2),3, IF(AND($F10<=N$2, $H10>=N$2), 2, "" ))) | O10: =IF(AND($F10<(O$2+7),$F10>O$2),1, IF(AND($H10<O$2+7,$H10>O$2),3, IF(AND($F10<=O$2, $H10>=O$2), 2, "" ))) | P10: =IF(AND($F10<(P$2+7),$F10>P$2),1, IF(AND($H10<P$2+7,$H10>P$2),3, IF(AND($F10<=P$2, $H10>=P$2), 2, "" ))) | Q10: =IF(AND($F10<(Q$2+7),$F10>Q$2),1, IF(AND($H10<Q$2+7,$H10>Q$2),3, IF(AND($F10<=Q$2, $H10>=Q$2), 2, "" ))) | R10: =IF(AND($F10<(R$2+7),$F10>R$2),1, IF(AND($H10<R$2+7,$H10>R$2),3, IF(AND($F10<=R$2, $H10>=R$2), 2, "" ))) | S10: =IF(AND($F10<(S$2+7),$F10>S$2),1, IF(AND($H10<S$2+7,$H10>S$2),3, IF(AND($F10<=S$2, $H10>=S$2), 2, "" ))) | ... AQ10: =IF(AND($F10<(AQ$2+7),$F10>AQ$2),1, IF(AND($H10<AQ$2+7,$H10>AQ$2),3, IF(AND($F10<=AQ$2, $H10>=AQ$2), 2, "" )))
B11: BOS Procurement | C11: 43941 | D11: 5 | E11: 43949 | F11: 43941 | G11: 5 | H11: 43949 | L11: =IF(AND($F11<(L$2+7),$F11>L$2),1, IF(AND($H11<L$2+7,$H11>L$2),3, IF(AND($F11<=L$2, $H11>=L$2), 2, "" ))) | M11: =IF(AND($F11<(M$2+7),$F11>M$2),1, IF(AND($H11<M$2+7,$H11>M$2),3, IF(AND($F11<=M$2, $H11>=M$2), 2, "" ))) | N11: =IF(AND($F11<(N$2+7),$F11>N$2),1, IF(AND($H11<N$2+7,$H11>N$2),3, IF(AND($F11<=N$2, $H11>=N$2), 2, "" ))) | O11: =IF(AND($F11<(O$2+7),$F11>O$2),1, IF(AND($H11<O$2+7,$H11>O$2),3, IF(AND($F11<=O$2, $H11>=O$2), 2, "" ))) | P11: =IF(AND($F11<(P$2+7),$F11>P$2),1, IF(AND($H11<P$2+7,$H11>P$2),3, IF(AND($F11<=P$2, $H11>=P$2), 2, "" ))) | Q11: =IF(AND($F11<(Q$2+7),$F11>Q$2),1, IF(AND($H11<Q$2+7,$H11>Q$2),3, IF(AND($F11<=Q$2, $H11>=Q$2), 2, "" ))) | R11: =IF(AND($F11<(R$2+7),$F11>R$2),1, IF(AND($H11<R$2+7,$H11>R$2),3, IF(AND($F11<=R$2, $H11>=R$2), 2, "" ))) | S11: =IF(AND($F11<(S$2+7),$F11>S$2),1, IF(AND($H11<S$2+7,$H11>S$2),3, IF(AND($F11<=S$2, $H11>=S$2), 2, "" ))) | ... AQ11: =IF(AND($F11<(AQ$2+7),$F11>AQ$2),1, IF(AND($H11<AQ$2+7,$H11>AQ$2),3, IF(AND($F11<=AQ$2, $H11>=AQ$2), 2, "" )))
A12: 5 | B12: Internal Project Kick off | C12: 43936 | D12: 5 | E12: 43943 | F12: 43936 | G12: 5 | H12: 43943
A13: 6 | B13: Client Project Kick-off | C13: 43963 | D13: 5 | E13: 43970 | F13: 43963 | G13: 5 | H13: 43970 | L13: =IF(AND($F13<(L$2+7),$F13>L$2),1, IF(AND($H13<L$2+7,$H13>L$2),3, IF(AND($F13<=L$2, $H13>=L$2), 2, "" ))) | M13: =IF(AND($F13<(M$2+7),$F13>M$2),1, IF(AND($H13<M$2+7,$H13>M$2),3, IF(AND($F13<=M$2, $H13>=M$2), 2, "" ))) | N13: =IF(AND($F13<(N$2+7),$F13>N$2),1, IF(AND($H13<N$2+7,$H13>N$2),3, IF(AND($F13<=N$2, $H13>=N$2), 2, "" ))) | O13: =IF(AND($F13<(O$2+7),$F13>O$2),1, IF(AND($H13<O$2+7,$H13>O$2),3, IF(AND($F13<=O$2, $H13>=O$2), 2, "" ))) | P13: =IF(AND($F13<(P$2+7),$F13>P$2),1, IF(AND($H13<P$2+7,$H13>P$2),3, IF(AND($F13<=P$2, $H13>=P$2), 2, "" ))) | Q13: =IF(AND($F13<(Q$2+7),$F13>Q$2),1, IF(AND($H13<Q$2+7,$H13>Q$2),3, IF(AND($F13<=Q$2, $H13>=Q$2), 2, "" ))) | R13: =IF(AND($F13<(R$2+7),$F13>R$2),1, IF(AND($H13<R$2+7,$H13>R$2),3, IF(AND($F13<=R$2, $H13>=R$2), 2, "" ))) | S13: =IF(AND($F13<(S$2+7),$F13>S$2),1, IF(AND($H13<S$2+7,$H13>S$2),3, IF(AND($F13<=S$2, $H13>=S$2), 2, "" ))) | ... AQ13: =IF(AND($F13<(AQ$2+7),$F13>AQ$2),1, IF(AND($H13<AQ$2+7,$H13>AQ$2),3, IF(AND($F13<=AQ$2, $H13>=AQ$2), 2, "" )))
A14: 7 | B14: Equipment Delivery | C14: 43983 | D14: 9 | E14: 43994 | F14: 43983 | G14: 9 | H14: 43994 | L14: =IF(AND($F14<(L$2+7),$F14>L$2),1, IF(AND($H14<L$2+7,$H14>L$2),3, IF(AND($F14<=L$2, $H14>=L$2), 2, "" ))) | M14: =IF(AND($F14<(M$2+7),$F14>M$2),1, IF(AND($H14<M$2+7,$H14>M$2),3, IF(AND($F14<=M$2, $H14>=M$2), 2, "" ))) | N14: =IF(AND($F14<(N$2+7),$F14>N$2),1, IF(AND($H14<N$2+7,$H14>N$2),3, IF(AND($F14<=N$2, $H14>=N$2), 2, "" ))) | O14: =IF(AND($F14<(O$2+7),$F14>O$2),1, IF(AND($H14<O$2+7,$H14>O$2),3, IF(AND($F14<=O$2, $H14>=O$2), 2, "" ))) | P14: =IF(AND($F14<(P$2+7),$F14>P$2),1, IF(AND($H14<P$2+7,$H14>P$2),3, IF(AND($F14<=P$2, $H14>=P$2), 2, "" ))) | Q14: =IF(AND($F14<(Q$2+7),$F14>Q$2),1, IF(AND($H14<Q$2+7,$H14>Q$2),3, IF(AND($F14<=Q$2, $H14>=Q$2), 2, "" ))) | R14: =IF(AND($F14<(R$2+7),$F14>R$2),1, IF(AND($H14<R$2+7,$H14>R$2),3, IF(AND($F14<=R$2, $H14>=R$2), 2, "" ))) | S14: =IF(AND($F14<(S$2+7),$F14>S$2),1, IF(AND($H14<S$2+7,$H14>S$2),3, IF(AND($F14<=S$2, $H14>=S$2), 2, "" ))) | ... AQ14: =IF(AND($F14<(AQ$2+7),$F14>AQ$2),1, IF(AND($H14<AQ$2+7,$H14>AQ$2),3, IF(AND($F14<=AQ$2, $H14>=AQ$2), 2, "" )))
B15: Mounting Structure Delivery | C15: 43983 | D15: 2 | E15: 43985 | F15: 43983 | G15: 2 | H15: 43985
B16: Panel Delivery | C16: 43990 | D16: 2 | E16: 43992 | F16: 43990 | G16: 2 | H16: 43992 | L16: =IF(AND($F16<(L$2+7),$F16>L$2),1, IF(AND($H16<L$2+7,$H16>L$2),3, IF(AND($F16<=L$2, $H16>=L$2), 2, "" ))) | M16: =IF(AND($F16<(M$2+7),$F16>M$2),1, IF(AND($H16<M$2+7,$H16>M$2),3, IF(AND($F16<=M$2, $H16>=M$2), 2, "" ))) | N16: =IF(AND($F16<(N$2+7),$F16>N$2),1, IF(AND($H16<N$2+7,$H16>N$2),3, IF(AND($F16<=N$2, $H16>=N$2), 2, "" ))) | O16: =IF(AND($F16<(O$2+7),$F16>O$2),1, IF(AND($H16<O$2+7,$H16>O$2),3, IF(AND($F16<=O$2, $H16>=O$2), 2, "" ))) | P16: =IF(AND($F16<(P$2+7),$F16>P$2),1, IF(AND($H16<P$2+7,$H16>P$2),3, IF(AND($F16<=P$2, $H16>=P$2), 2, "" ))) | Q16: =IF(AND($F16<(Q$2+7),$F16>Q$2),1, IF(AND($H16<Q$2+7,$H16>Q$2),3, IF(AND($F16<=Q$2, $H16>=Q$2), 2, "" ))) | R16: =IF(AND($F16<(R$2+7),$F16>R$2),1, IF(AND($H16<R$2+7,$H16>R$2),3, IF(AND($F16<=R$2, $H16>=R$2), 2, "" ))) | S16: =IF(AND($F16<(S$2+7),$F16>S$2),1, IF(AND($H16<S$2+7,$H16>S$2),3, IF(AND($F16<=S$2, $H16>=S$2), 2, "" ))) | ... AQ16: =IF(AND($F16<(AQ$2+7),$F16>AQ$2),1, IF(AND($H16<AQ$2+7,$H16>AQ$2),3, IF(AND($F16<=AQ$2, $H16>=AQ$2), 2, "" )))
B17: Generator Delivery | C17: 43983 | D17: 2 | E17: 43985 | F17: 43983 | G17: 2 | H17: 43985
A18: B | B18: PAYMENT MILESTONE 2: DELIVERY OF PV PANELS | C18: 43992 | D18: 2 | E18: 43994 | F18: 43992 | G18: 2 | H18: 43994
B19: Inverter Delivery | C19: 43983 | D19: 2 | E19: 43985 | F19: 43983 | G19: 2 | H19: 43985 | L19: =IF(AND($F19<(L$2+7),$F19>L$2),1, IF(AND($H19<L$2+7,$H19>L$2),3, IF(AND($F19<=L$2, $H19>=L$2), 2, "" ))) | M19: =IF(AND($F19<(M$2+7),$F19>M$2),1, IF(AND($H19<M$2+7,$H19>M$2),3, IF(AND($F19<=M$2, $H19>=M$2), 2, "" ))) | N19: =IF(AND($F19<(N$2+7),$F19>N$2),1, IF(AND($H19<N$2+7,$H19>N$2),3, IF(AND($F19<=N$2, $H19>=N$2), 2, "" ))) | O19: =IF(AND($F19<(O$2+7),$F19>O$2),1, IF(AND($H19<O$2+7,$H19>O$2),3, IF(AND($F19<=O$2, $H19>=O$2), 2, "" ))) | P19: =IF(AND($F19<(P$2+7),$F19>P$2),1, IF(AND($H19<P$2+7,$H19>P$2),3, IF(AND($F19<=P$2, $H19>=P$2), 2, "" ))) | Q19: =IF(AND($F19<(Q$2+7),$F19>Q$2),1, IF(AND($H19<Q$2+7,$H19>Q$2),3, IF(AND($F19<=Q$2, $H19>=Q$2), 2, "" ))) | R19: =IF(AND($F19<(R$2+7),$F19>R$2),1, IF(AND($H19<R$2+7,$H19>R$2),3, IF(AND($F19<=R$2, $H19>=R$2), 2, "" ))) | S19: =IF(AND($F19<(S$2+7),$F19>S$2),1, IF(AND($H19<S$2+7,$H19>S$2),3, IF(AND($F19<=S$2, $H19>=S$2), 2, "" ))) | ... AQ19: =IF(AND($F19<(AQ$2+7),$F19>AQ$2),1, IF(AND($H19<AQ$2+7,$H19>AQ$2),3, IF(AND($F19<=AQ$2, $H19>=AQ$2), 2, "" )))
B20: BOS Delivery | C20: 43983 | D20: 1 | E20: 43984 | F20: 43983 | G20: 1 | H20: 43984 | L20: =IF(AND($F20<(L$2+7),$F20>L$2),1, IF(AND($H20<L$2+7,$H20>L$2),3, IF(AND($F20<=L$2, $H20>=L$2), 2, "" ))) | M20: =IF(AND($F20<(M$2+7),$F20>M$2),1, IF(AND($H20<M$2+7,$H20>M$2),3, IF(AND($F20<=M$2, $H20>=M$2), 2, "" ))) | N20: =IF(AND($F20<(N$2+7),$F20>N$2),1, IF(AND($H20<N$2+7,$H20>N$2),3, IF(AND($F20<=N$2, $H20>=N$2), 2, "" ))) | O20: =IF(AND($F20<(O$2+7),$F20>O$2),1, IF(AND($H20<O$2+7,$H20>O$2),3, IF(AND($F20<=O$2, $H20>=O$2), 2, "" ))) | P20: =IF(AND($F20<(P$2+7),$F20>P$2),1, IF(AND($H20<P$2+7,$H20>P$2),3, IF(AND($F20<=P$2, $H20>=P$2), 2, "" ))) | Q20: =IF(AND($F20<(Q$2+7),$F20>Q$2),1, IF(AND($H20<Q$2+7,$H20>Q$2),3, IF(AND($F20<=Q$2, $H20>=Q$2), 2, "" ))) | R20: =IF(AND($F20<(R$2+7),$F20>R$2),1, IF(AND($H20<R$2+7,$H20>R$2),3, IF(AND($F20<=R$2, $H20>=R$2), 2, "" ))) | S20: =IF(AND($F20<(S$2+7),$F20>S$2),1, IF(AND($H20<S$2+7,$H20>S$2),3, IF(AND($F20<=S$2, $H20>=S$2), 2, "" ))) | ... AQ20: =IF(AND($F20<(AQ$2+7),$F20>AQ$2),1, IF(AND($H20<AQ$2+7,$H20>AQ$2),3, IF(AND($F20<=AQ$2, $H20>=AQ$2), 2, "" )))
A21: C | B21: PAYMENT MILESTONE 3: DELIVERY OF INVERTERS AND BOS | C21: 43985 | D21: 2 | E21: 43987 | F21: 43985 | G21: 2 | H21: 43987
A22: 8 | B22: Installation | C22: 43990 | D22: 22 | E22: 44012 | F22: 43990 | G22: 22 | H22: 44012 | L22: =IF(AND($F22<(L$2+7),$F22>L$2),1, IF(AND($H22<L$2+7,$H22>L$2),3, IF(AND($F22<=L$2, $H22>=L$2), 2, "" ))) | M22: =IF(AND($F22<(M$2+7),$F22>M$2),1, IF(AND($H22<M$2+7,$H22>M$2),3, IF(AND($F22<=M$2, $H22>=M$2), 2, "" ))) | N22: =IF(AND($F22<(N$2+7),$F22>N$2),1, IF(AND($H22<N$2+7,$H22>N$2),3, IF(AND($F22<=N$2, $H22>=N$2), 2, "" ))) | O22: =IF(AND($F22<(O$2+7),$F22>O$2),1, IF(AND($H22<O$2+7,$H22>O$2),3, IF(AND($F22<=O$2, $H22>=O$2), 2, "" ))) | P22: =IF(AND($F22<(P$2+7),$F22>P$2),1, IF(AND($H22<P$2+7,$H22>P$2),3, IF(AND($F22<=P$2, $H22>=P$2), 2, "" ))) | Q22: =IF(AND($F22<(Q$2+7),$F22>Q$2),1, IF(AND($H22<Q$2+7,$H22>Q$2),3, IF(AND($F22<=Q$2, $H22>=Q$2), 2, "" ))) | R22: =IF(AND($F22<(R$2+7),$F22>R$2),1, IF(AND($H22<R$2+7,$H22>R$2),3, IF(AND($F22<=R$2, $H22>=R$2), 2, "" ))) | S22: =IF(AND($F22<(S$2+7),$F22>S$2),1, IF(AND($H22<S$2+7,$H22>S$2),3, IF(AND($F22<=S$2, $H22>=S$2), 2, "" ))) | ... AQ22: =IF(AND($F22<(AQ$2+7),$F22>AQ$2),1, IF(AND($H22<AQ$2+7,$H22>AQ$2),3, IF(AND($F22<=AQ$2, $H22>=AQ$2), 2, "" ))) -> 2
B23: Site Establishment | C23: 43990 | D23: 1 | E23: 43991 | F23: 43990 | G23: 1 | H23: 43991 | J23: Installation placed on hold due to Covid-19 case | L23: =IF(AND($F23<(L$2+7),$F23>L$2),1, IF(AND($H23<L$2+7,$H23>L$2),3, IF(AND($F23<=L$2, $H23>=L$2), 2, "" ))) | M23: =IF(AND($F23<(M$2+7),$F23>M$2),1, IF(AND($H23<M$2+7,$H23>M$2),3, IF(AND($F23<=M$2, $H23>=M$2), 2, "" ))) | N23: =IF(AND($F23<(N$2+7),$F23>N$2),1, IF(AND($H23<N$2+7,$H23>N$2),3, IF(AND($F23<=N$2, $H23>=N$2), 2, "" ))) | O23: =IF(AND($F23<(O$2+7),$F23>O$2),1, IF(AND($H23<O$2+7,$H23>O$2),3, IF(AND($F23<=O$2, $H23>=O$2), 2, "" ))) | P23: =IF(AND($F23<(P$2+7),$F23>P$2),1, IF(AND($H23<P$2+7,$H23>P$2),3, IF(AND($F23<=P$2, $H23>=P$2), 2, "" ))) | Q23: =IF(AND($F23<(Q$2+7),$F23>Q$2),1, IF(AND($H23<Q$2+7,$H23>Q$2),3, IF(AND($F23<=Q$2, $H23>=Q$2), 2, "" ))) | R23: =IF(AND($F23<(R$2+7),$F23>R$2),1, IF(AND($H23<R$2+7,$H23>R$2),3, IF(AND($F23<=R$2, $H23>=R$2), 2, "" ))) | S23: =IF(AND($F23<(S$2+7),$F23>S$2),1, IF(AND($H23<S$2+7,$H23>S$2),3, IF(AND($F23<=S$2, $H23>=S$2), 2, "" ))) | ... AQ23: =IF(AND($F23<(AQ$2+7),$F23>AQ$2),1, IF(AND($H23<AQ$2+7,$H23>AQ$2),3, IF(AND($F23<=AQ$2, $H23>=AQ$2), 2, "" )))
A24: 9 | B24: DC Works | C24: 43991 | D24: 16 | E24: 44012 | F24: 43991 | G24: 16 | H24: 44012 | L24: =IF(AND($F24<(L$2+7),$F24>L$2),1, IF(AND($H24<L$2+7,$H24>L$2),3, IF(AND($F24<=L$2, $H24>=L$2), 2, "" ))) | M24: =IF(AND($F24<(M$2+7),$F24>M$2),1, IF(AND($H24<M$2+7,$H24>M$2),3, IF(AND($F24<=M$2, $H24>=M$2), 2, "" ))) | N24: =IF(AND($F24<(N$2+7),$F24>N$2),1, IF(AND($H24<N$2+7,$H24>N$2),3, IF(AND($F24<=N$2, $H24>=N$2), 2, "" ))) | O24: =IF(AND($F24<(O$2+7),$F24>O$2),1, IF(AND($H24<O$2+7,$H24>O$2),3, IF(AND($F24<=O$2, $H24>=O$2), 2, "" ))) | P24: =IF(AND($F24<(P$2+7),$F24>P$2),1, IF(AND($H24<P$2+7,$H24>P$2),3, IF(AND($F24<=P$2, $H24>=P$2), 2, "" ))) | Q24: =IF(AND($F24<(Q$2+7),$F24>Q$2),1, IF(AND($H24<Q$2+7,$H24>Q$2),3, IF(AND($F24<=Q$2, $H24>=Q$2), 2, "" ))) | R24: =IF(AND($F24<(R$2+7),$F24>R$2),1, IF(AND($H24<R$2+7,$H24>R$2),3, IF(AND($F24<=R$2, $H24>=R$2), 2, "" ))) | S24: =IF(AND($F24<(S$2+7),$F24>S$2),1, IF(AND($H24<S$2+7,$H24>S$2),3, IF(AND($F24<=S$2, $H24>=S$2), 2, "" ))) | ... AQ24: =IF(AND($F24<(AQ$2+7),$F24>AQ$2),1, IF(AND($H24<AQ$2+7,$H24>AQ$2),3, IF(AND($F24<=AQ$2, $H24>=AQ$2), 2, "" ))) -> 2
B25: Mounting structure Installation | C25: 43991 | D25: 4 | E25: 43997 | F25: 43991 | G25: 4 | H25: 43997 | L25: =IF(AND($F25<(L$2+7),$F25>L$2),1, IF(AND($H25<L$2+7,$H25>L$2),3, IF(AND($F25<=L$2, $H25>=L$2), 2, "" ))) | M25: =IF(AND($F25<(M$2+7),$F25>M$2),1, IF(AND($H25<M$2+7,$H25>M$2),3, IF(AND($F25<=M$2, $H25>=M$2), 2, "" ))) | N25: =IF(AND($F25<(N$2+7),$F25>N$2),1, IF(AND($H25<N$2+7,$H25>N$2),3, IF(AND($F25<=N$2, $H25>=N$2), 2, "" ))) | O25: =IF(AND($F25<(O$2+7),$F25>O$2),1, IF(AND($H25<O$2+7,$H25>O$2),3, IF(AND($F25<=O$2, $H25>=O$2), 2, "" ))) | P25: =IF(AND($F25<(P$2+7),$F25>P$2),1, IF(AND($H25<P$2+7,$H25>P$2),3, IF(AND($F25<=P$2, $H25>=P$2), 2, "" ))) | Q25: =IF(AND($F25<(Q$2+7),$F25>Q$2),1, IF(AND($H25<Q$2+7,$H25>Q$2),3, IF(AND($F25<=Q$2, $H25>=Q$2), 2, "" ))) | R25: =IF(AND($F25<(R$2+7),$F25>R$2),1, IF(AND($H25<R$2+7,$H25>R$2),3, IF(AND($F25<=R$2, $H25>=R$2), 2, "" ))) | S25: =IF(AND($F25<(S$2+7),$F25>S$2),1, IF(AND($H25<S$2+7,$H25>S$2),3, IF(AND($F25<=S$2, $H25>=S$2), 2, "" ))) | ... AQ25: =IF(AND($F25<(AQ$2+7),$F25>AQ$2),1, IF(AND($H25<AQ$2+7,$H25>AQ$2),3, IF(AND($F25<=AQ$2, $H25>=AQ$2), 2, "" )))
B26: Cable tray Installation | C26: 43997 | D26: 3 | E26: 44004 | F26: 43997 | G26: 3 | H26: 44004 | L26: =IF(AND($F26<(L$2+7),$F26>L$2),1, IF(AND($H26<L$2+7,$H26>L$2),3, IF(AND($F26<=L$2, $H26>=L$2), 2, "" ))) | M26: =IF(AND($F26<(M$2+7),$F26>M$2),1, IF(AND($H26<M$2+7,$H26>M$2),3, IF(AND($F26<=M$2, $H26>=M$2), 2, "" ))) | N26: =IF(AND($F26<(N$2+7),$F26>N$2),1, IF(AND($H26<N$2+7,$H26>N$2),3, IF(AND($F26<=N$2, $H26>=N$2), 2, "" ))) | O26: =IF(AND($F26<(O$2+7),$F26>O$2),1, IF(AND($H26<O$2+7,$H26>O$2),3, IF(AND($F26<=O$2, $H26>=O$2), 2, "" ))) | P26: =IF(AND($F26<(P$2+7),$F26>P$2),1, IF(AND($H26<P$2+7,$H26>P$2),3, IF(AND($F26<=P$2, $H26>=P$2), 2, "" ))) | Q26: =IF(AND($F26<(Q$2+7),$F26>Q$2),1, IF(AND($H26<Q$2+7,$H26>Q$2),3, IF(AND($F26<=Q$2, $H26>=Q$2), 2, "" ))) | R26: =IF(AND($F26<(R$2+7),$F26>R$2),1, IF(AND($H26<R$2+7,$H26>R$2),3, IF(AND($F26<=R$2, $H26>=R$2), 2, "" ))) | S26: =IF(AND($F26<(S$2+7),$F26>S$2),1, IF(AND($H26<S$2+7,$H26>S$2),3, IF(AND($F26<=S$2, $H26>=S$2), 2, "" ))) | ... AQ26: =IF(AND($F26<(AQ$2+7),$F26>AQ$2),1, IF(AND($H26<AQ$2+7,$H26>AQ$2),3, IF(AND($F26<=AQ$2, $H26>=AQ$2), 2, "" )))
B27: DC Cable Installation | C27: 44004 | D27: 2 | E27: 44006 | F27: 44004 | G27: 2 | H27: 44006 | L27: =IF(AND($F27<(L$2+7),$F27>L$2),1, IF(AND($H27<L$2+7,$H27>L$2),3, IF(AND($F27<=L$2, $H27>=L$2), 2, "" ))) | M27: =IF(AND($F27<(M$2+7),$F27>M$2),1, IF(AND($H27<M$2+7,$H27>M$2),3, IF(AND($F27<=M$2, $H27>=M$2), 2, "" ))) | N27: =IF(AND($F27<(N$2+7),$F27>N$2),1, IF(AND($H27<N$2+7,$H27>N$2),3, IF(AND($F27<=N$2, $H27>=N$2), 2, "" ))) | O27: =IF(AND($F27<(O$2+7),$F27>O$2),1, IF(AND($H27<O$2+7,$H27>O$2),3, IF(AND($F27<=O$2, $H27>=O$2), 2, "" ))) | P27: =IF(AND($F27<(P$2+7),$F27>P$2),1, IF(AND($H27<P$2+7,$H27>P$2),3, IF(AND($F27<=P$2, $H27>=P$2), 2, "" ))) | Q27: =IF(AND($F27<(Q$2+7),$F27>Q$2),1, IF(AND($H27<Q$2+7,$H27>Q$2),3, IF(AND($F27<=Q$2, $H27>=Q$2), 2, "" ))) | R27: =IF(AND($F27<(R$2+7),$F27>R$2),1, IF(AND($H27<R$2+7,$H27>R$2),3, IF(AND($F27<=R$2, $H27>=R$2), 2, "" ))) | S27: =IF(AND($F27<(S$2+7),$F27>S$2),1, IF(AND($H27<S$2+7,$H27>S$2),3, IF(AND($F27<=S$2, $H27>=S$2), 2, "" ))) | ... AQ27: =IF(AND($F27<(AQ$2+7),$F27>AQ$2),1, IF(AND($H27<AQ$2+7,$H27>AQ$2),3, IF(AND($F27<=AQ$2, $H27>=AQ$2), 2, "" )))
B28: Module Installation | C28: 44006 | D28: 4 | E28: 44012 | F28: 44006 | G28: 4 | H28: 44012 | L28: =IF(AND($F28<(L$2+7),$F28>L$2),1, IF(AND($H28<L$2+7,$H28>L$2),3, IF(AND($F28<=L$2, $H28>=L$2), 2, "" ))) | M28: =IF(AND($F28<(M$2+7),$F28>M$2),1, IF(AND($H28<M$2+7,$H28>M$2),3, IF(AND($F28<=M$2, $H28>=M$2), 2, "" ))) | N28: =IF(AND($F28<(N$2+7),$F28>N$2),1, IF(AND($H28<N$2+7,$H28>N$2),3, IF(AND($F28<=N$2, $H28>=N$2), 2, "" ))) | O28: =IF(AND($F28<(O$2+7),$F28>O$2),1, IF(AND($H28<O$2+7,$H28>O$2),3, IF(AND($F28<=O$2, $H28>=O$2), 2, "" ))) | P28: =IF(AND($F28<(P$2+7),$F28>P$2),1, IF(AND($H28<P$2+7,$H28>P$2),3, IF(AND($F28<=P$2, $H28>=P$2), 2, "" ))) | Q28: =IF(AND($F28<(Q$2+7),$F28>Q$2),1, IF(AND($H28<Q$2+7,$H28>Q$2),3, IF(AND($F28<=Q$2, $H28>=Q$2), 2, "" ))) | R28: =IF(AND($F28<(R$2+7),$F28>R$2),1, IF(AND($H28<R$2+7,$H28>R$2),3, IF(AND($F28<=R$2, $H28>=R$2), 2, "" ))) | S28: =IF(AND($F28<(S$2+7),$F28>S$2),1, IF(AND($H28<S$2+7,$H28>S$2),3, IF(AND($F28<=S$2, $H28>=S$2), 2, "" ))) | ... AQ28: =IF(AND($F28<(AQ$2+7),$F28>AQ$2),1, IF(AND($H28<AQ$2+7,$H28>AQ$2),3, IF(AND($F28<=AQ$2, $H28>=AQ$2), 2, "" ))) -> 2
B29: Earth Cable Installation | C29: 44004 | D29: 1 | E29: 44005 | F29: 44004 | G29: 1 | H29: 44005 | L29: =IF(AND($F29<(L$2+7),$F29>L$2),1, IF(AND($H29<L$2+7,$H29>L$2),3, IF(AND($F29<=L$2, $H29>=L$2), 2, "" ))) | M29: =IF(AND($F29<(M$2+7),$F29>M$2),1, IF(AND($H29<M$2+7,$H29>M$2),3, IF(AND($F29<=M$2, $H29>=M$2), 2, "" ))) | N29: =IF(AND($F29<(N$2+7),$F29>N$2),1, IF(AND($H29<N$2+7,$H29>N$2),3, IF(AND($F29<=N$2, $H29>=N$2), 2, "" ))) | O29: =IF(AND($F29<(O$2+7),$F29>O$2),1, IF(AND($H29<O$2+7,$H29>O$2),3, IF(AND($F29<=O$2, $H29>=O$2), 2, "" ))) | P29: =IF(AND($F29<(P$2+7),$F29>P$2),1, IF(AND($H29<P$2+7,$H29>P$2),3, IF(AND($F29<=P$2, $H29>=P$2), 2, "" ))) | Q29: =IF(AND($F29<(Q$2+7),$F29>Q$2),1, IF(AND($H29<Q$2+7,$H29>Q$2),3, IF(AND($F29<=Q$2, $H29>=Q$2), 2, "" ))) | R29: =IF(AND($F29<(R$2+7),$F29>R$2),1, IF(AND($H29<R$2+7,$H29>R$2),3, IF(AND($F29<=R$2, $H29>=R$2), 2, "" ))) | S29: =IF(AND($F29<(S$2+7),$F29>S$2),1, IF(AND($H29<S$2+7,$H29>S$2),3, IF(AND($F29<=S$2, $H29>=S$2), 2, "" ))) | ... AQ29: =IF(AND($F29<(AQ$2+7),$F29>AQ$2),1, IF(AND($H29<AQ$2+7,$H29>AQ$2),3, IF(AND($F29<=AQ$2, $H29>=AQ$2), 2, "" )))
A30: 10 | B30: AC Works | C30: 43991 | D30: 8 | E30: 44000 | F30: 43991 | G30: 8 | H30: 44000
B31: Inverters Installation | C31: 43991 | D31: 2 | E31: 43993 | F31: 43991 | G31: 2 | H31: 43993 | L31: =IF(AND($F31<(L$2+7),$F31>L$2),1, IF(AND($H31<L$2+7,$H31>L$2),3, IF(AND($F31<=L$2, $H31>=L$2), 2, "" ))) | M31: =IF(AND($F31<(M$2+7),$F31>M$2),1, IF(AND($H31<M$2+7,$H31>M$2),3, IF(AND($F31<=M$2, $H31>=M$2), 2, "" ))) | N31: =IF(AND($F31<(N$2+7),$F31>N$2),1, IF(AND($H31<N$2+7,$H31>N$2),3, IF(AND($F31<=N$2, $H31>=N$2), 2, "" ))) | O31: =IF(AND($F31<(O$2+7),$F31>O$2),1, IF(AND($H31<O$2+7,$H31>O$2),3, IF(AND($F31<=O$2, $H31>=O$2), 2, "" ))) | P31: =IF(AND($F31<(P$2+7),$F31>P$2),1, IF(AND($H31<P$2+7,$H31>P$2),3, IF(AND($F31<=P$2, $H31>=P$2), 2, "" ))) | Q31: =IF(AND($F31<(Q$2+7),$F31>Q$2),1, IF(AND($H31<Q$2+7,$H31>Q$2),3, IF(AND($F31<=Q$2, $H31>=Q$2), 2, "" ))) | R31: =IF(AND($F31<(R$2+7),$F31>R$2),1, IF(AND($H31<R$2+7,$H31>R$2),3, IF(AND($F31<=R$2, $H31>=R$2), 2, "" ))) | S31: =IF(AND($F31<(S$2+7),$F31>S$2),1, IF(AND($H31<S$2+7,$H31>S$2),3, IF(AND($F31<=S$2, $H31>=S$2), 2, "" ))) | ... AQ31: =IF(AND($F31<(AQ$2+7),$F31>AQ$2),1, IF(AND($H31<AQ$2+7,$H31>AQ$2),3, IF(AND($F31<=AQ$2, $H31>=AQ$2), 2, "" )))
B32: AC BOS Installation | C32: 43993 | D32: 3 | E32: 44000 | F32: 43993 | G32: 3 | H32: 44000 | L32: =IF(AND($F32<(L$2+7),$F32>L$2),1, IF(AND($H32<L$2+7,$H32>L$2),3, IF(AND($F32<=L$2, $H32>=L$2), 2, "" ))) | M32: =IF(AND($F32<(M$2+7),$F32>M$2),1, IF(AND($H32<M$2+7,$H32>M$2),3, IF(AND($F32<=M$2, $H32>=M$2), 2, "" ))) | N32: =IF(AND($F32<(N$2+7),$F32>N$2),1, IF(AND($H32<N$2+7,$H32>N$2),3, IF(AND($F32<=N$2, $H32>=N$2), 2, "" ))) | O32: =IF(AND($F32<(O$2+7),$F32>O$2),1, IF(AND($H32<O$2+7,$H32>O$2),3, IF(AND($F32<=O$2, $H32>=O$2), 2, "" ))) | P32: =IF(AND($F32<(P$2+7),$F32>P$2),1, IF(AND($H32<P$2+7,$H32>P$2),3, IF(AND($F32<=P$2, $H32>=P$2), 2, "" ))) | Q32: =IF(AND($F32<(Q$2+7),$F32>Q$2),1, IF(AND($H32<Q$2+7,$H32>Q$2),3, IF(AND($F32<=Q$2, $H32>=Q$2), 2, "" ))) | R32: =IF(AND($F32<(R$2+7),$F32>R$2),1, IF(AND($H32<R$2+7,$H32>R$2),3, IF(AND($F32<=R$2, $H32>=R$2), 2, "" ))) | S32: =IF(AND($F32<(S$2+7),$F32>S$2),1, IF(AND($H32<S$2+7,$H32>S$2),3, IF(AND($F32<=S$2, $H32>=S$2), 2, "" ))) | ... AQ32: =IF(AND($F32<(AQ$2+7),$F32>AQ$2),1, IF(AND($H32<AQ$2+7,$H32>AQ$2),3, IF(AND($F32<=AQ$2, $H32>=AQ$2), 2, "" )))
B33: AC Cable/Tie-In | C33: 43992 | D33: 3 | E33: 43997 | F33: 43992 | G33: 3 | H33: 43997 | L33: =IF(AND($F33<(L$2+7),$F33>L$2),1, IF(AND($H33<L$2+7,$H33>L$2),3, IF(AND($F33<=L$2, $H33>=L$2), 2, "" ))) | M33: =IF(AND($F33<(M$2+7),$F33>M$2),1, IF(AND($H33<M$2+7,$H33>M$2),3, IF(AND($F33<=M$2, $H33>=M$2), 2, "" ))) | N33: =IF(AND($F33<(N$2+7),$F33>N$2),1, IF(AND($H33<N$2+7,$H33>N$2),3, IF(AND($F33<=N$2, $H33>=N$2), 2, "" ))) | O33: =IF(AND($F33<(O$2+7),$F33>O$2),1, IF(AND($H33<O$2+7,$H33>O$2),3, IF(AND($F33<=O$2, $H33>=O$2), 2, "" ))) | P33: =IF(AND($F33<(P$2+7),$F33>P$2),1, IF(AND($H33<P$2+7,$H33>P$2),3, IF(AND($F33<=P$2, $H33>=P$2), 2, "" ))) | Q33: =IF(AND($F33<(Q$2+7),$F33>Q$2),1, IF(AND($H33<Q$2+7,$H33>Q$2),3, IF(AND($F33<=Q$2, $H33>=Q$2), 2, "" ))) | R33: =IF(AND($F33<(R$2+7),$F33>R$2),1, IF(AND($H33<R$2+7,$H33>R$2),3, IF(AND($F33<=R$2, $H33>=R$2), 2, "" ))) | S33: =IF(AND($F33<(S$2+7),$F33>S$2),1, IF(AND($H33<S$2+7,$H33>S$2),3, IF(AND($F33<=S$2, $H33>=S$2), 2, "" ))) | ... AQ33: =IF(AND($F33<(AQ$2+7),$F33>AQ$2),1, IF(AND($H33<AQ$2+7,$H33>AQ$2),3, IF(AND($F33<=AQ$2, $H33>=AQ$2), 2, "" )))
B34: Monitoring Platform Installation | C34: 43997 | D34: 1 | E34: 44000 | F34: 43997 | G34: 1 | H34: 44000
A35: 11 | B35: Completion | C35: 44000 | D35: 14 | E35: 44014 | F35: 44000 | G35: 14 | H35: 44014 | L35: =IF(AND($F35<(L$2+7),$F35>L$2),1, IF(AND($H35<L$2+7,$H35>L$2),3, IF(AND($F35<=L$2, $H35>=L$2), 2, "" ))) | M35: =IF(AND($F35<(M$2+7),$F35>M$2),1, IF(AND($H35<M$2+7,$H35>M$2),3, IF(AND($F35<=M$2, $H35>=M$2), 2, "" ))) | N35: =IF(AND($F35<(N$2+7),$F35>N$2),1, IF(AND($H35<N$2+7,$H35>N$2),3, IF(AND($F35<=N$2, $H35>=N$2), 2, "" ))) | O35: =IF(AND($F35<(O$2+7),$F35>O$2),1, IF(AND($H35<O$2+7,$H35>O$2),3, IF(AND($F35<=O$2, $H35>=O$2), 2, "" ))) | P35: =IF(AND($F35<(P$2+7),$F35>P$2),1, IF(AND($H35<P$2+7,$H35>P$2),3, IF(AND($F35<=P$2, $H35>=P$2), 2, "" ))) | Q35: =IF(AND($F35<(Q$2+7),$F35>Q$2),1, IF(AND($H35<Q$2+7,$H35>Q$2),3, IF(AND($F35<=Q$2, $H35>=Q$2), 2, "" ))) | R35: =IF(AND($F35<(R$2+7),$F35>R$2),1, IF(AND($H35<R$2+7,$H35>R$2),3, IF(AND($F35<=R$2, $H35>=R$2), 2, "" ))) | S35: =IF(AND($F35<(S$2+7),$F35>S$2),1, IF(AND($H35<S$2+7,$H35>S$2),3, IF(AND($F35<=S$2, $H35>=S$2), 2, "" ))) | ... AQ35: =IF(AND($F35<(AQ$2+7),$F35>AQ$2),1, IF(AND($H35<AQ$2+7,$H35>AQ$2),3, IF(AND($F35<=AQ$2, $H35>=AQ$2), 2, "" ))) -> 3
B36: DC Works | C36: 44012 | D36: 2 | E36: 44014 | F36: 44012 | G36: 2 | H36: 44014 | L36: =IF(AND($F36<(L$2+7),$F36>L$2),1, IF(AND($H36<L$2+7,$H36>L$2),3, IF(AND($F36<=L$2, $H36>=L$2), 2, "" ))) | M36: =IF(AND($F36<(M$2+7),$F36>M$2),1, IF(AND($H36<M$2+7,$H36>M$2),3, IF(AND($F36<=M$2, $H36>=M$2), 2, "" ))) | N36: =IF(AND($F36<(N$2+7),$F36>N$2),1, IF(AND($H36<N$2+7,$H36>N$2),3, IF(AND($F36<=N$2, $H36>=N$2), 2, "" ))) | O36: =IF(AND($F36<(O$2+7),$F36>O$2),1, IF(AND($H36<O$2+7,$H36>O$2),3, IF(AND($F36<=O$2, $H36>=O$2), 2, "" ))) | P36: =IF(AND($F36<(P$2+7),$F36>P$2),1, IF(AND($H36<P$2+7,$H36>P$2),3, IF(AND($F36<=P$2, $H36>=P$2), 2, "" ))) | Q36: =IF(AND($F36<(Q$2+7),$F36>Q$2),1, IF(AND($H36<Q$2+7,$H36>Q$2),3, IF(AND($F36<=Q$2, $H36>=Q$2), 2, "" ))) | R36: =IF(AND($F36<(R$2+7),$F36>R$2),1, IF(AND($H36<R$2+7,$H36>R$2),3, IF(AND($F36<=R$2, $H36>=R$2), 2, "" ))) | S36: =IF(AND($F36<(S$2+7),$F36>S$2),1, IF(AND($H36<S$2+7,$H36>S$2),3, IF(AND($F36<=S$2, $H36>=S$2), 2, "" ))) | ... AQ36: =IF(AND($F36<(AQ$2+7),$F36>AQ$2),1, IF(AND($H36<AQ$2+7,$H36>AQ$2),3, IF(AND($F36<=AQ$2, $H36>=AQ$2), 2, "" ))) -> 3
B37: AC Works | C37: 44000 | D37: 2 | E37: 44004 | F37: 44000 | G37: 2 | H37: 44004 | L37: =IF(AND($F37<(L$2+7),$F37>L$2),1, IF(AND($H37<L$2+7,$H37>L$2),3, IF(AND($F37<=L$2, $H37>=L$2), 2, "" ))) | M37: =IF(AND($F37<(M$2+7),$F37>M$2),1, IF(AND($H37<M$2+7,$H37>M$2),3, IF(AND($F37<=M$2, $H37>=M$2), 2, "" ))) | N37: =IF(AND($F37<(N$2+7),$F37>N$2),1, IF(AND($H37<N$2+7,$H37>N$2),3, IF(AND($F37<=N$2, $H37>=N$2), 2, "" ))) | O37: =IF(AND($F37<(O$2+7),$F37>O$2),1, IF(AND($H37<O$2+7,$H37>O$2),3, IF(AND($F37<=O$2, $H37>=O$2), 2, "" ))) | P37: =IF(AND($F37<(P$2+7),$F37>P$2),1, IF(AND($H37<P$2+7,$H37>P$2),3, IF(AND($F37<=P$2, $H37>=P$2), 2, "" ))) | Q37: =IF(AND($F37<(Q$2+7),$F37>Q$2),1, IF(AND($H37<Q$2+7,$H37>Q$2),3, IF(AND($F37<=Q$2, $H37>=Q$2), 2, "" ))) | R37: =IF(AND($F37<(R$2+7),$F37>R$2),1, IF(AND($H37<R$2+7,$H37>R$2),3, IF(AND($F37<=R$2, $H37>=R$2), 2, "" ))) | S37: =IF(AND($F37<(S$2+7),$F37>S$2),1, IF(AND($H37<S$2+7,$H37>S$2),3, IF(AND($F37<=S$2, $H37>=S$2), 2, "" ))) | ... AQ37: =IF(AND($F37<(AQ$2+7),$F37>AQ$2),1, IF(AND($H37<AQ$2+7,$H37>AQ$2),3, IF(AND($F37<=AQ$2, $H37>=AQ$2), 2, "" )))
A38: D | B38: PAYMENT MILESTONE 4: PRACTICAL COMPLETION | C38: 44012 | D38: 1 | E38: 44013 | F38: 44012 | G38: 1 | H38: 44013 | L38: =IF(AND($F38<(L$2+7),$F38>L$2),1, IF(AND($H38<L$2+7,$H38>L$2),3, IF(AND($F38<=L$2, $H38>=L$2), 2, "" ))) | M38: =IF(AND($F38<(M$2+7),$F38>M$2),1, IF(AND($H38<M$2+7,$H38>M$2),3, IF(AND($F38<=M$2, $H38>=M$2), 2, "" ))) | N38: =IF(AND($F38<(N$2+7),$F38>N$2),1, IF(AND($H38<N$2+7,$H38>N$2),3, IF(AND($F38<=N$2, $H38>=N$2), 2, "" ))) | O38: =IF(AND($F38<(O$2+7),$F38>O$2),1, IF(AND($H38<O$2+7,$H38>O$2),3, IF(AND($F38<=O$2, $H38>=O$2), 2, "" ))) | P38: =IF(AND($F38<(P$2+7),$F38>P$2),1, IF(AND($H38<P$2+7,$H38>P$2),3, IF(AND($F38<=P$2, $H38>=P$2), 2, "" ))) | Q38: =IF(AND($F38<(Q$2+7),$F38>Q$2),1, IF(AND($H38<Q$2+7,$H38>Q$2),3, IF(AND($F38<=Q$2, $H38>=Q$2), 2, "" ))) | R38: =IF(AND($F38<(R$2+7),$F38>R$2),1, IF(AND($H38<R$2+7,$H38>R$2),3, IF(AND($F38<=R$2, $H38>=R$2), 2, "" ))) | S38: =IF(AND($F38<(S$2+7),$F38>S$2),1, IF(AND($H38<S$2+7,$H38>S$2),3, IF(AND($F38<=S$2, $H38>=S$2), 2, "" ))) | ... AQ38: =IF(AND($F38<(AQ$2+7),$F38>AQ$2),1, IF(AND($H38<AQ$2+7,$H38>AQ$2),3, IF(AND($F38<=AQ$2, $H38>=AQ$2), 2, "" ))) -> 3
A39: 12 | B39: Commissioning | C39: 43997 | D39: 22 | E39: 44019 | F39: 43997 | G39: 22 | H39: 44019 | L39: =IF(AND($F39<(L$2+7),$F39>L$2),1, IF(AND($H39<L$2+7,$H39>L$2),3, IF(AND($F39<=L$2, $H39>=L$2), 2, "" ))) | M39: =IF(AND($F39<(M$2+7),$F39>M$2),1, IF(AND($H39<M$2+7,$H39>M$2),3, IF(AND($F39<=M$2, $H39>=M$2), 2, "" ))) | N39: =IF(AND($F39<(N$2+7),$F39>N$2),1, IF(AND($H39<N$2+7,$H39>N$2),3, IF(AND($F39<=N$2, $H39>=N$2), 2, "" ))) | O39: =IF(AND($F39<(O$2+7),$F39>O$2),1, IF(AND($H39<O$2+7,$H39>O$2),3, IF(AND($F39<=O$2, $H39>=O$2), 2, "" ))) | P39: =IF(AND($F39<(P$2+7),$F39>P$2),1, IF(AND($H39<P$2+7,$H39>P$2),3, IF(AND($F39<=P$2, $H39>=P$2), 2, "" ))) | Q39: =IF(AND($F39<(Q$2+7),$F39>Q$2),1, IF(AND($H39<Q$2+7,$H39>Q$2),3, IF(AND($F39<=Q$2, $H39>=Q$2), 2, "" ))) | R39: =IF(AND($F39<(R$2+7),$F39>R$2),1, IF(AND($H39<R$2+7,$H39>R$2),3, IF(AND($F39<=R$2, $H39>=R$2), 2, "" ))) | S39: =IF(AND($F39<(S$2+7),$F39>S$2),1, IF(AND($H39<S$2+7,$H39>S$2),3, IF(AND($F39<=S$2, $H39>=S$2), 2, "" ))) | ... AQ39: =IF(AND($F39<(AQ$2+7),$F39>AQ$2),1, IF(AND($H39<AQ$2+7,$H39>AQ$2),3, IF(AND($F39<=AQ$2, $H39>=AQ$2), 2, "" ))) -> 2
B40: Snag List | C40: 44014 | D40: 3 | E40: 44019 | F40: 44014 | G40: 3 | H40: 44019
B41: Pre-Commissioning Checks | C41: 44010 | D41: 2 | E41: 44012 | F41: 44010 | G41: 2 | H41: 44012
B42: Issue CoC | C42: 43997 | D42: 2 | E42: 44001 | F42: 43997 | G42: 2 | H42: 44001 | L42: =IF(AND($F42<(L$2+7),$F42>L$2),1, IF(AND($H42<L$2+7,$H42>L$2),3, IF(AND($F42<=L$2, $H42>=L$2), 2, "" ))) | M42: =IF(AND($F42<(M$2+7),$F42>M$2),1, IF(AND($H42<M$2+7,$H42>M$2),3, IF(AND($F42<=M$2, $H42>=M$2), 2, "" ))) | N42: =IF(AND($F42<(N$2+7),$F42>N$2),1, IF(AND($H42<N$2+7,$H42>N$2),3, IF(AND($F42<=N$2, $H42>=N$2), 2, "" ))) | O42: =IF(AND($F42<(O$2+7),$F42>O$2),1, IF(AND($H42<O$2+7,$H42>O$2),3, IF(AND($F42<=O$2, $H42>=O$2), 2, "" ))) | P42: =IF(AND($F42<(P$2+7),$F42>P$2),1, IF(AND($H42<P$2+7,$H42>P$2),3, IF(AND($F42<=P$2, $H42>=P$2), 2, "" ))) | Q42: =IF(AND($F42<(Q$2+7),$F42>Q$2),1, IF(AND($H42<Q$2+7,$H42>Q$2),3, IF(AND($F42<=Q$2, $H42>=Q$2), 2, "" ))) | R42: =IF(AND($F42<(R$2+7),$F42>R$2),1, IF(AND($H42<R$2+7,$H42>R$2),3, IF(AND($F42<=R$2, $H42>=R$2), 2, "" ))) | S42: =IF(AND($F42<(S$2+7),$F42>S$2),1, IF(AND($H42<S$2+7,$H42>S$2),3, IF(AND($F42<=S$2, $H42>=S$2), 2, "" ))) | ... AQ42: =IF(AND($F42<(AQ$2+7),$F42>AQ$2),1, IF(AND($H42<AQ$2+7,$H42>AQ$2),3, IF(AND($F42<=AQ$2, $H42>=AQ$2), 2, "" )))
B43: Cold Commissioning | C43: 44012 | D43: 1 | E43: 44013 | F43: 44012 | G43: 1 | H43: 44013 | L43: =IF(AND($F43<(L$2+7),$F43>L$2),1, IF(AND($H43<L$2+7,$H43>L$2),3, IF(AND($F43<=L$2, $H43>=L$2), 2, "" ))) | M43: =IF(AND($F43<(M$2+7),$F43>M$2),1, IF(AND($H43<M$2+7,$H43>M$2),3, IF(AND($F43<=M$2, $H43>=M$2), 2, "" ))) | N43: =IF(AND($F43<(N$2+7),$F43>N$2),1, IF(AND($H43<N$2+7,$H43>N$2),3, IF(AND($F43<=N$2, $H43>=N$2), 2, "" ))) | O43: =IF(AND($F43<(O$2+7),$F43>O$2),1, IF(AND($H43<O$2+7,$H43>O$2),3, IF(AND($F43<=O$2, $H43>=O$2), 2, "" ))) | P43: =IF(AND($F43<(P$2+7),$F43>P$2),1, IF(AND($H43<P$2+7,$H43>P$2),3, IF(AND($F43<=P$2, $H43>=P$2), 2, "" ))) | Q43: =IF(AND($F43<(Q$2+7),$F43>Q$2),1, IF(AND($H43<Q$2+7,$H43>Q$2),3, IF(AND($F43<=Q$2, $H43>=Q$2), 2, "" ))) | R43: =IF(AND($F43<(R$2+7),$F43>R$2),1, IF(AND($H43<R$2+7,$H43>R$2),3, IF(AND($F43<=R$2, $H43>=R$2), 2, "" ))) | S43: =IF(AND($F43<(S$2+7),$F43>S$2),1, IF(AND($H43<S$2+7,$H43>S$2),3, IF(AND($F43<=S$2, $H43>=S$2), 2, "" ))) | ... AQ43: =IF(AND($F43<(AQ$2+7),$F43>AQ$2),1, IF(AND($H43<AQ$2+7,$H43>AQ$2),3, IF(AND($F43<=AQ$2, $H43>=AQ$2), 2, "" ))) -> 3
B44: Hot Commissioning | C44: 44013 | D44: 2 | E44: 44015 | F44: 44013 | G44: 2 | H44: 44015 | L44: =IF(AND($F44<(L$2+7),$F44>L$2),1, IF(AND($H44<L$2+7,$H44>L$2),3, IF(AND($F44<=L$2, $H44>=L$2), 2, "" ))) | M44: =IF(AND($F44<(M$2+7),$F44>M$2),1, IF(AND($H44<M$2+7,$H44>M$2),3, IF(AND($F44<=M$2, $H44>=M$2), 2, "" ))) | N44: =IF(AND($F44<(N$2+7),$F44>N$2),1, IF(AND($H44<N$2+7,$H44>N$2),3, IF(AND($F44<=N$2, $H44>=N$2), 2, "" ))) | O44: =IF(AND($F44<(O$2+7),$F44>O$2),1, IF(AND($H44<O$2+7,$H44>O$2),3, IF(AND($F44<=O$2, $H44>=O$2), 2, "" ))) | P44: =IF(AND($F44<(P$2+7),$F44>P$2),1, IF(AND($H44<P$2+7,$H44>P$2),3, IF(AND($F44<=P$2, $H44>=P$2), 2, "" ))) | Q44: =IF(AND($F44<(Q$2+7),$F44>Q$2),1, IF(AND($H44<Q$2+7,$H44>Q$2),3, IF(AND($F44<=Q$2, $H44>=Q$2), 2, "" ))) | R44: =IF(AND($F44<(R$2+7),$F44>R$2),1, IF(AND($H44<R$2+7,$H44>R$2),3, IF(AND($F44<=R$2, $H44>=R$2), 2, "" ))) | S44: =IF(AND($F44<(S$2+7),$F44>S$2),1, IF(AND($H44<S$2+7,$H44>S$2),3, IF(AND($F44<=S$2, $H44>=S$2), 2, "" ))) | ... AQ44: =IF(AND($F44<(AQ$2+7),$F44>AQ$2),1, IF(AND($H44<AQ$2+7,$H44>AQ$2),3, IF(AND($F44<=AQ$2, $H44>=AQ$2), 2, "" ))) -> 1
A45: 13 | B45: Handover | C45: 44020 | D45: 1 | E45: 44021 | F45: 44020 | G45: 1 | H45: 44021 | L45: =IF(AND($F45<(L$2+7),$F45>L$2),1, IF(AND($H45<L$2+7,$H45>L$2),3, IF(AND($F45<=L$2, $H45>=L$2), 2, "" ))) | M45: =IF(AND($F45<(M$2+7),$F45>M$2),1, IF(AND($H45<M$2+7,$H45>M$2),3, IF(AND($F45<=M$2, $H45>=M$2), 2, "" ))) | N45: =IF(AND($F45<(N$2+7),$F45>N$2),1, IF(AND($H45<N$2+7,$H45>N$2),3, IF(AND($F45<=N$2, $H45>=N$2), 2, "" ))) | O45: =IF(AND($F45<(O$2+7),$F45>O$2),1, IF(AND($H45<O$2+7,$H45>O$2),3, IF(AND($F45<=O$2, $H45>=O$2), 2, "" ))) | P45: =IF(AND($F45<(P$2+7),$F45>P$2),1, IF(AND($H45<P$2+7,$H45>P$2),3, IF(AND($F45<=P$2, $H45>=P$2), 2, "" ))) | Q45: =IF(AND($F45<(Q$2+7),$F45>Q$2),1, IF(AND($H45<Q$2+7,$H45>Q$2),3, IF(AND($F45<=Q$2, $H45>=Q$2), 2, "" ))) | R45: =IF(AND($F45<(R$2+7),$F45>R$2),1, IF(AND($H45<R$2+7,$H45>R$2),3, IF(AND($F45<=R$2, $H45>=R$2), 2, "" ))) | S45: =IF(AND($F45<(S$2+7),$F45>S$2),1, IF(AND($H45<S$2+7,$H45>S$2),3, IF(AND($F45<=S$2, $H45>=S$2), 2, "" ))) | ... AQ45: =IF(AND($F45<(AQ$2+7),$F45>AQ$2),1, IF(AND($H45<AQ$2+7,$H45>AQ$2),3, IF(AND($F45<=AQ$2, $H45>=AQ$2), 2, "" )))
A46: E | B46: PAYMENT MILESTONE 6: HANDOVER COMPLETE | C46: 44022 | D46: 1 | E46: 44025 | F46: 44022 | G46: 1 | H46: 44025
C47: 43831 | D47: These numbers are used to set the start and end dates on the Gantt Chart
C48: 44014

Sheet Certificate - Financial Close
B2: Emergent Energy – Financial Close Completion Certificate | H2: FINANCIAL CLOSE CERTIFICATE
B4: Project Name: | C4: ='Project Plan'!E2 -> 1 Bolt Ave
B5: COO: | C5: Johannes Potgieter
B6: Programme Manager: | C6: Roedolph Venter
B7: HoPD: | C7: Natasha Watkins-Baker
B9: Date of Phase Completion:
B10: Phase Deliverables Checklist: (Y/N)
B11: Product Agreement | C11: NA
B12: EPC Agreement | C12: NA
B13: O&M Agreeement | C13: NA
B14: Cost Proposal | C14: Signed
B15: Deposit Received | C15: Yes
B16: Risks / Notes | C16: None
B18: Acknowledgement and Acceptance:
B19: Role | C19: Name | D19: Signature | E19: Date
B20: COO | C20: Johannes | D20: JTP | E20: 45953

Sheet Certificate - Planning
B2: Emergent Energy – Planning Phase Completion Certificate | H2: PLANNING CERTIFICATE
B4: Project Name: | C4: ='Project Plan'!E2 -> 1 Bolt Ave
B5: Client Representative:
B6: Programme Manager: | C6: Roedolph Venter
B7: Project Manager: | C7: Peet Verreynne
B8: Project Engineer:
B10: Date of Phase Completion:
B11: Phase Deliverables Checklist: (Y/N)
B12: Project Introduction Presentation
B13: Project Brief
B14: Engineering Pack
B15: BOQ
B16: PO – Material & Equipment
B17: PO - Contractors
B18: HSE – NOC
B19: HSE – EE File
B20: HSE – Contractor File
... B24: Acknowledgement and Acceptance:
B25: Role | C25: Name | D25: Signature | E25: Date

Sheet Change Register
E1: Change Register
B3: ID | C3: Description | D3: Impact | E3: Proposed Date | F3: Proposed By | G3: Status | H3: Approved By | I3: Date | J3: Results / Comments
B4: DEC001
B5: DEC002
B6: DEC003
B7: DEC004
B8: DEC005
B9: DEC006
B10: DEC007
B11: DEC008
B12: DEC009
B13: DEC010

Sheet Data
C2: Public holidays | F2: Drop down list
C3: 45658 | D3: New Years Day | F3: Approved
C4: 45737 | D4: Human Rights day | F4: Pending
C5: 45765 | D5: Good Friday | F5: Declined
C6: 45768 | D6: Family Day | F6: Abanded
C7: 45774 | D7: Freedom Day
C8: 45765 | D8: Freedom DayObserved
C9: 45778 | D9: Workers day
C10: 45824 | D10: Youth Day Holiday
C11: 45878 | D11: Womens Day
C12: 45924 | D12: Heritage Day
C13: 46007 | D13: Day of Reconciliation | H13: Manual dates
C14: 46016 | D14: Christmas Day
C15: 46017 | D15: Day of Goodwill

Sheet BOQ
B2: Item | C2: Supplier | D2: Description | E2: Quantity | F2: Comments
B3: PV Module
B4: Mounting Structure
B5: DC Cable Red & Black
B6: Inverters
B7: Current Transformers (Production)
B8: Current Transformers (Consumption)
B9: Solar Production Meter
B10: Solar Consumption Meter
B11: Wi-Fi Router & Sim
B12: Switch
B13: Back Up Battery
B14: PVDB
... B30: Techsitter

Sheet Revenue Tracking
B2: HIGH LEVEL PROJECT REVENUE TRACKING
D3: COSTED | F3: ACTUAL | L3: FINANCIAL REVIEW | N3: TIMELINE REVIEW | U3: 2026 Budget Revenue | V3: 2026 Budget COS | W3: 2026 Actual Revenue | X3: 2026 Actual COS
B4: 1 | C4: Planned Revenue | D4: ='Project Plan'!E6 -> 3283810.5 | F4: =F21 -> 3377404.8 | N4: Start Date | U4: =SUMIFS('Expenditure Breakdown'!$U:$U, 'Expenditure Breakdown'!$T:$T, ">"&DATE(2025,8,31), 'Expenditure Breakdown'!$T:$T, "<="&DATE(2026,8,31)) -> 3283810.5 | V4: =SUMIFS('Expenditure Breakdown'!$Q:$Q, 'Expenditure Breakdown'!$T:$T, ">"&DATE(2025,8,31), 'Expenditure Breakdown'!$T:$T, "<="&DATE(2026,8,31)) -> 2217962.2 | W4: =SUMIFS('Expenditure Breakdown'!$U:$U, 'Expenditure Breakdown'!$T:$T, ">"&DATE(2025,8,31), 'Expenditure Breakdown'!$T:$T, "<="&DATE(2026,8,31), 'Expenditure Breakdown'!$S:$S, "<>") -> 3192804.2 | X4: =SUMIFS('Expenditure Breakdown'!$Q:$Q, 'Expenditure Breakdown'!$T:$T, ">"&DATE(2025,8,31), 'Expenditure Breakdown'!$T:$T, "<="&DATE(2026,8,31), 'Expenditure Breakdown'!$S:$S, "<>") -> 2169914.5
B5: 2 | C5: Planned Expenditure | D5: =+'Expenditure Tracking'!F5 -> 2763016.5 | F5: =+'Expenditure Tracking'!H5 -> 2217962.2 | G5: VO PM Limit | H5: Current VO Total
B6: 3 | C6: Planned Profit | D6: =+D4-D5 -> 520794.02 | F6: =+F4-F5 -> 1159442.6 | G6: =D6*0.05 -> 26039.701 | H6: =SUMIF('Expenditure Breakdown'!N:N,"*VO*",'Expenditure Breakdown'!Q:Q) -> 0 | N6: End Date - PC
B7: 4 | C7: Planned Margin | D7: =+D6/D4 -> 0.15859442 | F7: =+F6/F4 -> 0.34329394
B10: CONTRACT
B12: No. | C12: PAYMENT MILESTONE | E12: % | F12: VALUE | H12: PLANNED PAYMENT DATE | L12: INVOICE NUMBER | N12: INVOICE RAISED DATE | P12: PAYMENT RECEIVED DATE | R12: MILESTONE REQUIREMENTS & COMMENTS | S12: MILESTONE DOCUMENTS RECEIVED
B13: 1 | C13: Acceptance and Initial Deposit | E13: 0.35 | F13: =$D$4*E13 -> 1149333.7 | H13: 45908 | L13: 004830 | N13: 45904 | P13: 45905 | S13: TRUE | AN13: ='Decision Register'!$P$14+ 7 -> 7
B14: 2 | C14: Delivery of Panels | E14: 0.3 | F14: =$D$4*E14 -> 985143.16 | H14: ='Project Plan'!E36+7 -> 45951 | L14: 004853 | N14: 45950 | P14: 45951 | S14: TRUE
B15: 3 | C15: Delivery of Inverters | E15: 0.2 | F15: =$D$4*E15 -> 656762.11 | H15: ='Project Plan'!E22+7 -> 45951 | L15: 004853 | N15: 45950 | P15: 45971 | S15: TRUE
B16: 4 | C16: Practical Completion | E16: 0.1 | F16: =$D$4*E16 -> 328381.05 | H16: ='Project Plan'!G39+7 -> 45986 | L16: 004907 | N16: 46015 | P16: 16/01/2026 | S16: TRUE
B17: 5 | C17: Handover | E17: 0.05 | F17: =$D$4*E17 -> 164190.53 | H17: ='Project Plan'!E51+7 -> 45995 | P17: ='Project Plan'!K51+7 -> 46071 | R17: awaiting HO meeting date | S17: TRUE
B18: 6 | C18: Client VO - Walkways | E18: 0 | F18: 93594.2 | H18: =H16 -> 45986 | L18: 004908 | N18: 46015 | P18: =P16 -> 16/01/2026 | S18: TRUE
B19: 7 | C19: - | E19: 0 | F19: =$D$4*E19 -> 0 | S19: FALSE
E21: =SUM(E13:E19) -> 1 | F21: =SUM(F13:F19) -> 3377404.8
B23: KEY: | C23: contains an error (in result or a check has failed)
C24: Red Font - IF TEXT : content not yet confirmed
C25: Red Font - IF NUMBER: Negative value
C26: Anything in yellow is a concern or risk for noting or action
C27: confirmed
C28: [ADD INITIALS: comment for noting in square brackets, use colour or red to draw attention if important]
C29: [RT: When adding rows into sheet, ensure you insert between first and last row of each category]
C30: end of sheet - do not insert information below/beyond this
B40: No. | C40: PAYMENT MILESTONE | E40: % | F40: VALUE
B41: 1 | C41: Deposit - Project commencement | E41: 0.35 | F41: =$F$47*E41 -> 1182091.7
B42: 2 | C42: Delivery of Panels | E42: 0.3 | F42: =$F$47*E42 -> 1013221.4
B43: 3 | C43: Delivery of Inverters | E43: 0.2 | F43: =$F$47*E43 -> 675480.95
B44: 4 | C44: Practical Completion | E44: 0.1 | F44: =$F$47*E44 -> 337740.48
B45: 5 | C45: Handover | E45: 0.05 | F45: =$F$47*E45 -> 168870.24
C46: Total | E46: =SUM(E41:E45) -> 1 | F46: =SUM(F41:F45) -> 3377404.8
E47: =SUM(E41:E45) -> 1 | F47: =F21 -> 3377404.8

Sheet Compliance
B2: HSE
B4: Description | C4: Status | D4: Approved By | E4: Date | F4: Results / Comments
B5: NOC | C5: Approved | D5: DOL
B6: 7.1 Agreement | C6: Approved | D6: EE
B7: 13.2 Agreement | C7: Approved | D7: EE
B8: EE File | C8: Approved | D8: Client
B9: Subbie File | C9: Approved | D9: Client
B16: SSEG
B18: Description | C18: Status | D18: Approved By | E18: Date | F18: Results / Comments
B19: SSEG Application | C19: In Process | F19: Awaiting signed BQ, ESA, LPU from client
B20: PTI | C20: In Process | F20: NERSA letter from ESKOM
B21: Commissioning Approval
B22: NERSA Registration

Sheet Project Plan
N1: =TODAY() -> 46056 | O1: =TODAY() -> 46056
C2: PROJECT PLAN | E2: 1 Bolt Ave | I2: Net Work Days | K2: =NETWORKDAYS(I19,K41,Data!C3:C15) -> 71 | N2: 0 | O2: 1
C3: PROJECT SIZE (kWp) | E3: 366 | I3: Total Weeks | K3: =K2/5 -> 14.2
C4: PROJECT DEVELOPER | E4: Peet Verreynne | I4: kW/Week Installation Rate | K4: =E3/K3 -> 25.774648
C5: PROJECT MANAGERS | E5: Peet Verreynne
C6: CONTRACT VALUE | E6: 3283810.5
C7: Phase: | E7: Handover
B8: No. | C8: HIGH LEVEL PROGRAMME | E8: Planned Start | F8: Duration (days) | G8: Planned End | I8: Actual Start | J8: Duration (days) | K8: Actual End | M8: Status | N8: Status | O8: Comment
F9: =G41-E19 -> 35 | J9: =K41-I19 -> 101 | M9: =AVERAGE(M11,M18,M21,M28,M35,M39,M46,M43) -> 0.95997537 | N9: =AVERAGE(N11,N18,N21,N28,N35,N39,N46,N43) -> 0.95401409
B11: 1 | C11: Project Initiation | E11: =MIN(E12:E16) -> 45909 | F11: =G11-E11 -> 30 | G11: =MAX(G12:G16) -> 45939 | I11: =MIN(I12:I16) -> 45909 | J11: =K11-I11 -> 43 | K11: =MAX(K12:K16) -> 45952 | M11: =(J12*M12+J13*M13+J14*M14+J15*M15+J16*M16)/SUM(J12:J16) -> 1 | N11: =(K12*N12+K13*N13+K14*N14+K15*N15+K16*N16)/SUM(K12:K16) -> 1
B12: 1.1 | C12: BD Handover | E12: 45909 | F12: 1 | G12: =WORKDAY.INTL(E12,F12,1,Data!$C$3:$C$14) -> 45910 | I12: 45909 | J12: 1 | K12: =WORKDAY.INTL(I12,J12,1,Data!$C$3:$C$14) -> 45910 | M12: 1 | N12: =_xlfn.LET( _xlpm.s,VALUE($I12), _xlpm.e,VALUE($K12), IF(OR(_xlpm.s="",_xlpm.e=""),"", IF(_xlpm.e<=_xlpm.s, IF(TODAY()>=_xlpm.e,1,0), MAX(0,MIN(1,(TODAY()-_xlpm.s)/(_xlpm.e-_xlpm.s))))) ) -> 1 | S12: Milestone | T12: Start Date | U12: Duration | V12: End Date | X12: =TODAY() -> 46056 | Y12: =TODAY() -> 46056
B13: 1.2 | C13: Project Introduction | E13: =WORKDAY.INTL(E19,0,1,Data!$C$3:$C$14)-14 -> 45930 | F13: 1 | G13: =WORKDAY.INTL(E13,F13,1,Data!$C$3:$C$14) -> 45931 | I13: =WORKDAY.INTL(I19,0,1,Data!$C$3:$C$14)-14 -> 45930 | J13: 1 | K13: =WORKDAY.INTL(I13,J13,1,Data!$C$3:$C$14) -> 45931 | M13: 1 | N13: =_xlfn.LET( _xlpm.s,VALUE($I13), _xlpm.e,VALUE($K13), IF(OR(_xlpm.s="",_xlpm.e=""),"", IF(_xlpm.e<=_xlpm.s, IF(TODAY()>=_xlpm.e,1,0), MAX(0,MIN(1,(TODAY()-_xlpm.s)/(_xlpm.e-_xlpm.s))))) ) -> 1 | S13: =C11 -> Project Initiation | T13: =I11 -> 45909 | U13: =J11 -> 43 | V13: =K11 -> 45952 | X13: 1 | Y13: 0
B14: 1.3 | C14: HSE | E14: =E13 -> 45930 | F14: 7 | G14: =WORKDAY.INTL(E14,F14,1,Data!$C$3:$C$14) -> 45939 | I14: 45946 | J14: 7 | K14: 45952 | M14: 1 | N14: =_xlfn.LET( _xlpm.s,VALUE($I14), _xlpm.e,VALUE($K14), IF(OR(_xlpm.s="",_xlpm.e=""),"", IF(_xlpm.e<=_xlpm.s, IF(TODAY()>=_xlpm.e,1,0), MAX(0,MIN(1,(TODAY()-_xlpm.s)/(_xlpm.e-_xlpm.s))))) ) -> 1 | O14: Meeting with Client HSE was today 22/10/2025 | S14: =C18 -> Site Establishment | T14: =I18 -> 45944 | U14: =J18 -> 1 | V14: =K18 -> 45945
B15: 1.4 | C15: Installer Kick Off | E15: =WORKDAY.INTL(E19,0,1,Data!$C$3:$C$14)-14 -> 45930 | F15: 1 | G15: =WORKDAY.INTL(E15,F15,1,Data!$C$3:$C$14) -> 45931 | I15: =WORKDAY.INTL(I19,0,1,Data!$C$3:$C$14)-14 -> 45930 | J15: 1 | K15: =WORKDAY.INTL(I15,J15,1,Data!$C$3:$C$14) -> 45931 | M15: 1 | N15: =_xlfn.LET( _xlpm.s,VALUE($I15), _xlpm.e,VALUE($K15), IF(OR(_xlpm.s="",_xlpm.e=""),"", IF(_xlpm.e<=_xlpm.s, IF(TODAY()>=_xlpm.e,1,0), MAX(0,MIN(1,(TODAY()-_xlpm.s)/(_xlpm.e-_xlpm.s))))) ) -> 1 | S15: =C21 -> AC Installation | T15: =I21 -> 45930 | U15: =J21 -> 62 | V15: =K21 -> 45992
B16: 1.5 | C16: Project Review | E16: =WORKDAY.INTL(E19,0,1,Data!$C$3:$C$14)-7 -> 45937 | F16: 1 | G16: =WORKDAY.INTL(E16,F16,1,Data!$C$3:$C$14) -> 45938 | I16: =WORKDAY.INTL(I19,0,1,Data!$C$3:$C$14)-7 -> 45937 | J16: 1 | K16: =WORKDAY.INTL(I16,J16,1,Data!$C$3:$C$14) -> 45938 | M16: 1 | N16: =_xlfn.LET( _xlpm.s,VALUE($I16), _xlpm.e,VALUE($K16), IF(OR(_xlpm.s="",_xlpm.e=""),"", IF(_xlpm.e<=_xlpm.s, IF(TODAY()>=_xlpm.e,1,0), MAX(0,MIN(1,(TODAY()-_xlpm.s)/(_xlpm.e-_xlpm.s))))) ) -> 1 | S16: =C28 -> DC Works | T16: =I28 -> 45944 | U16: =J28 -> 62 | V16: =K28 -> 46006
S17: =C35 -> Module installation | T17: =I35 -> 45944 | U17: =J35 -> 62 | V17: =K35 -> 46006
B18: 2 | C18: Site Establishment | E18: =MIN(E19:E20) -> 45944 | F18: =G18-E18 -> 1 | G18: =MAX(G19) -> 45945 | I18: =MIN(I19:I20) -> 45944 | J18: =K18-I18 -> 1 | K18: =MAX(K19) -> 45945 | M18: =(J19*M19)/J18 -> 1 | N18: =(K19*N19)/K18 -> 1 | S18: =C39 -> Commissioning | T18: =I39 -> 46006 | U18: =J39 -> 39 | V18: =K39 -> 46045
B19: 2.1 | C19: Solar Contractor Establishment | E19: 45944 | F19: 1 | G19: =E19+F19 -> 45945 | I19: 45944 | J19: 1 | K19: =I19+J19 -> 45945 | M19: 1 | N19: =_xlfn.LET( _xlpm.s,VALUE($I19), _xlpm.e,VALUE($K19), IF(OR(_xlpm.s="",_xlpm.e=""),"", IF(_xlpm.e<=_xlpm.s, IF(TODAY()>=_xlpm.e,1,0), MAX(0,MIN(1,(TODAY()-_xlpm.s)/(_xlpm.e-_xlpm.s))))) ) -> 1 | S19: =C43 -> QA Inspections | T19: =I43 -> 46043 | U19: =J43 -> 1 | V19: =K43 -> 46044
S20: =C46 -> Project Closure | T20: =I46 -> 46044 | U20: =J46 -> 22 | V20: =K46 -> 46066
B21: 3 | C21: AC Installation | E21: =MIN(E22:E26) -> 45930 | F21: =G21-E21 -> 42 | G21: =MAX(G22:G26) -> 45972 | I21: =MIN(I22:I26) -> 45930 | J21: =K21-I21 -> 62 | K21: =MAX(K22:K26) -> 45992 | M21: =(J22*M22+J23*M23+J24*M24+J25*M25+J26*M26)/SUM(J22:J26) -> 1 | N21: =(J22*N22+J23*N23+J24*N24+J25*N25+J26*N26)/SUM(J22:J26) -> 1
B22: 3.1 | C22: Inverters delivered | E22: =WORKDAY.INTL(E19,0,1,Data!$C$3:$C$14) -> 45944 | F22: 1 | G22: =WORKDAY.INTL(E22,F22,1,Data!$C$3:$C$14) -> 45945 | I22: =WORKDAY.INTL(I19,0,1,Data!$C$3:$C$14) -> 45944 | J22: 1 | K22: =WORKDAY.INTL(I22,J22,1,Data!$C$3:$C$14) -> 45945 | M22: 1 | N22: =_xlfn.LET( _xlpm.s,VALUE($I22), _xlpm.e,VALUE($K22), IF(OR(_xlpm.s="",_xlpm.e=""),"", IF(_xlpm.e<=_xlpm.s, IF(TODAY()>=_xlpm.e,1,0), MAX(0,MIN(1,(TODAY()-_xlpm.s)/(_xlpm.e-_xlpm.s))))) ) -> 1
B23: 3.2 | C23: Inverters Mounted | E23: =WORKDAY.INTL(G22,0,1,Data!$C$3:$C$14)+7 -> 45952 | F23: 2 | G23: =WORKDAY.INTL(E23,F23,1,Data!$C$3:$C$14) -> 45954 | I23: =WORKDAY.INTL(K22,0,1,Data!$C$3:$C$14)+7+7 -> 45959 | J23: 2 | K23: =WORKDAY.INTL(I23,J23,1,Data!$C$3:$C$14) -> 45961 | M23: 1 | N23: =_xlfn.LET( _xlpm.s,VALUE($I23), _xlpm.e,VALUE($K23), IF(OR(_xlpm.s="",_xlpm.e=""),"", IF(_xlpm.e<=_xlpm.s, IF(TODAY()>=_xlpm.e,1,0), MAX(0,MIN(1,(TODAY()-_xlpm.s)/(_xlpm.e-_xlpm.s))))) ) -> 1 | O23: Waiting on iverter rack + 7
B24: 3.3 | C24: Solar DB Lead Time | E24: =WORKDAY.INTL(E19,0,1,Data!$C$3:$C$14)-14 -> 45930 | F24: 25 | G24: =WORKDAY.INTL(E24,F24,1,Data!$C$3:$C$14) -> 45965 | I24: =WORKDAY.INTL(I19,0,1,Data!$C$3:$C$14)-14 -> 45930 | J24: 33 | K24: =WORKDAY.INTL(I24,J24,1,Data!$C$3:$C$14) -> 45975 | M24: 1 | N24: =_xlfn.LET( _xlpm.s,VALUE($I24), _xlpm.e,VALUE($K24), IF(OR(_xlpm.s="",_xlpm.e=""),"", IF(_xlpm.e<=_xlpm.s, IF(TODAY()>=_xlpm.e,1,0), MAX(0,MIN(1,(TODAY()-_xlpm.s)/(_xlpm.e-_xlpm.s))))) ) -> 1
B25: 3.4 | C25: AC Works | E25: =WORKDAY.INTL(G24,0,1,Data!$C$3:$C$14) -> 45965 | F25: 5 | G25: =WORKDAY.INTL(E25,F25,1,Data!$C$3:$C$14) -> 45972 | I25: =WORKDAY.INTL(K24,0,1,Data!$C$3:$C$14)-5 -> 45970 | J25: 15 | K25: =WORKDAY.INTL(I25,J25,1,Data!$C$3:$C$14) -> 45989 | M25: 1 | N25: 1
B26: 3.5 | C26: AC Tie-In | E26: =WORKDAY.INTL(E25,0,1,Data!$C$3:$C$14) -> 45965 | F26: 1 | G26: =WORKDAY.INTL(E26,F26,1,Data!$C$3:$C$14) -> 45966 | I26: =WORKDAY.INTL(K25,0,1,Data!$C$3:$C$14) -> 45989 | J26: 1 | K26: =WORKDAY.INTL(I26,J26,1,Data!$C$3:$C$14) -> 45992 | M26: 1 | N26: 1
B28: 4 | C28: DC Works | E28: =MIN(E30:E33) -> 45944 | F28: =G28-E28 -> 31 | G28: =MAX(G30:G33) -> 45975 | I28: =MIN(I30:I33) -> 45944 | J28: =K28-I28 -> 62 | K28: =MAX(K30:K33) -> 46006 | M28: =(J30*M30+J31*M31+J33*M33)/SUM(J30:J33) -> 0.96551724 | N28: =(J30*N30+J31*N31+J33*N33)/SUM(J30:J33) -> 0.96551724
B30: 4.1 | C30: Mounting Structure delivered | E30: =E19 -> 45944 | F30: 1 | G30: =WORKDAY.INTL(E30,F30,1,Data!$C$3:$C$14) -> 45945 | I30: =I19 -> 45944 | J30: 1 | K30: =WORKDAY.INTL(I30,J30,1,Data!$C$3:$C$14) -> 45945 | M30: 1 | N30: =_xlfn.LET( _xlpm.s,VALUE($I30), _xlpm.e,VALUE($K30), IF(OR(_xlpm.s="",_xlpm.e=""),"", IF(_xlpm.e<=_xlpm.s, IF(TODAY()>=_xlpm.e,1,0), MAX(0,MIN(1,(TODAY()-_xlpm.s)/(_xlpm.e-_xlpm.s))))) ) -> 1
B31: 4.2 | C31: Mounting Structure installation | E31: =WORKDAY.INTL(G30,0,1,Data!$C$3:$C$14) -> 45945 | F31: 6 | G31: =WORKDAY.INTL(E31,F31,1,Data!$C$3:$C$14) -> 45953 | I31: =WORKDAY.INTL(K30,0,1,Data!$C$3:$C$14) -> 45945 | J31: 19 | K31: =WORKDAY.INTL(I31,J31,1,Data!$C$3:$C$14) -> 45972 | M31: 1 | N31: =_xlfn.LET( _xlpm.s,VALUE($I31), _xlpm.e,VALUE($K31), IF(OR(_xlpm.s="",_xlpm.e=""),"", IF(_xlpm.e<=_xlpm.s, IF(TODAY()>=_xlpm.e,1,0), MAX(0,MIN(1,(TODAY()-_xlpm.s)/(_xlpm.e-_xlpm.s))))) ) -> 1 | O31: Roof inspection and fixes caused + 3 days
B32: 4.3 | C32: DC Cable delivered | E32: =E30 -> 45944 | F32: 1 | G32: =WORKDAY.INTL(E32,F32,1,Data!$C$3:$C$14) -> 45945 | I32: =I30 -> 45944 | J32: 1 | K32: =WORKDAY.INTL(I32,J32,1,Data!$C$3:$C$14) -> 45945 | M32: 1 | N32: =_xlfn.LET( _xlpm.s,VALUE($I32), _xlpm.e,VALUE($K32), IF(OR(_xlpm.s="",_xlpm.e=""),"", IF(_xlpm.e<=_xlpm.s, IF(TODAY()>=_xlpm.e,1,0), MAX(0,MIN(1,(TODAY()-_xlpm.s)/(_xlpm.e-_xlpm.s))))) ) -> 1
B33: 4.4 | C33: DC Stringing | E33: =WORKDAY.INTL(G37,0,1,Data!$C$3:$C$14)-3 -> 45963 | F33: 10 | G33: =WORKDAY.INTL(E33,F33,1,Data!$C$3:$C$14) -> 45975 | I33: =I37+2 -> 45995 | J33: 8 | K33: 46006 | M33: 1 | N33: =_xlfn.LET( _xlpm.s,VALUE($I33), _xlpm.e,VALUE($K33), IF(OR(_xlpm.s="",_xlpm.e=""),"", IF(_xlpm.e<=_xlpm.s, IF(TODAY()>=_xlpm.e,1,0), MAX(0,MIN(1,(TODAY()-_xlpm.s)/(_xlpm.e-_xlpm.s))))) ) -> 1
B35: 5 | C35: Module installation | E35: =MIN(E36:E37) -> 45944 | F35: =G35-E35 -> 22 | G35: =MAX(G36:G37) -> 45966 | I35: =MIN(I36:I37) -> 45944 | J35: =K35-I35 -> 62 | K35: =MAX(K36:K37) -> 46006 | M35: =(J36*M36+J37*M37)/SUM(J36:J37) -> 1 | N35: =(J36*N36+J37*N37)/SUM(J36:J37) -> 1
B36: 5.1 | C36: Module delivery | E36: =WORKDAY.INTL(E19,0,1,Data!$C$3:$C$14) -> 45944 | F36: 1 | G36: =WORKDAY.INTL(E36,F36,1,Data!$C$3:$C$14) -> 45945 | I36: =WORKDAY.INTL(I19,0,1,Data!$C$3:$C$14) -> 45944 | J36: 1 | K36: =WORKDAY.INTL(I36,J36,1,Data!$C$3:$C$14) -> 45945 | M36: 1 | N36: =_xlfn.LET( _xlpm.s,VALUE($I36), _xlpm.e,VALUE($K36), IF(OR(_xlpm.s="",_xlpm.e=""),"", IF(_xlpm.e<=_xlpm.s, IF(TODAY()>=_xlpm.e,1,0), MAX(0,MIN(1,(TODAY()-_xlpm.s)/(_xlpm.e-_xlpm.s))))) ) -> 1
B37: 5.2 | C37: Module mounting | E37: =G31 -> 45953 | F37: 9 | G37: =WORKDAY.INTL(E37,F37,1,Data!$C$3:$C$14) -> 45966 | I37: 45993 | J37: 9 | K37: =WORKDAY.INTL(I37,J37,1,Data!$C$3:$C$14) -> 46006 | M37: 1 | N37: =_xlfn.LET( _xlpm.s,VALUE($I37), _xlpm.e,VALUE($K37), IF(OR(_xlpm.s="",_xlpm.e=""),"", IF(_xlpm.e<=_xlpm.s, IF(TODAY()>=_xlpm.e,1,0), MAX(0,MIN(1,(TODAY()-_xlpm.s)/(_xlpm.e-_xlpm.s))))) ) -> 1
B39: 6 | C39: Commissioning | E39: =MIN(E40:E41) -> 45975 | F39: =G39-E39 -> 4 | G39: =MAX(G40:G41) -> 45979 | I39: =MIN(I40:I41) -> 46006 | J39: =K39-I39 -> 39 | K39: =MAX(K40:K41) -> 46045 | M39: =(J40*M40+J41*M41)/SUM(J40:J41) -> 1 | N39: =(K40*N40+K41*N41)/SUM(K40:K41) -> 1
B40: 6.1 | C40: Commissioning | E40: =WORKDAY.INTL(MAX(G21,G28,G35),0,1,Data!$C$3:$C$14) -> 45975 | F40: 1 | G40: =WORKDAY.INTL(E40,F40,1,Data!$C$3:$C$14) -> 45978 | I40: 46006 | J40: 5 | K40: =WORKDAY.INTL(I40,J40,1,Data!$C$3:$C$14) -> 46014 | M40: 1 | N40: =_xlfn.LET( _xlpm.s,VALUE($I40), _xlpm.e,VALUE($K40), IF(OR(_xlpm.s="",_xlpm.e=""),"", IF(_xlpm.e<=_xlpm.s, IF(TODAY()>=_xlpm.e,1,0), MAX(0,MIN(1,(TODAY()-_xlpm.s)/(_xlpm.e-_xlpm.s))))) ) -> 1
B41: 6.2 | C41: Practical Completion | E41: =WORKDAY.INTL(G40,0,1,Data!$C$3:$C$14) -> 45978 | F41: 1 | G41: =WORKDAY.INTL(E41,F41,1,Data!$C$3:$C$14) -> 45979 | I41: 46044 | J41: 1 | K41: =WORKDAY.INTL(I41,J41,1,Data!$C$3:$C$14) -> 46045 | M41: 1 | N41: =_xlfn.LET( _xlpm.s,VALUE($I41), _xlpm.e,VALUE($K41), IF(OR(_xlpm.s="",_xlpm.e=""),"", IF(_xlpm.e<=_xlpm.s, IF(TODAY()>=_xlpm.e,1,0), MAX(0,MIN(1,(TODAY()-_xlpm.s)/(_xlpm.e-_xlpm.s))))) ) -> 1
B43: 7 | C43: QA Inspections | E43: =MIN(E44) -> 45975 | F43: =G43-E43 -> 5 | G43: =MAX(G44) -> 45980 | I43: =MIN(I44) -> 46043 | J43: =K43-I43 -> 1 | K43: =MAX(K44) -> 46044 | M43: =(J44*M44)/SUM(J44) -> 1 | N43: =(K44*N44)/SUM(K44) -> 1
B44: 7.1 | C44: Red-Team Inspection | E44: =WORKDAY.INTL(E40,0,1,Data!$C$3:$C$14) -> 45975 | F44: 3 | G44: =WORKDAY.INTL(E44,F44,1,Data!$C$3:$C$14) -> 45980 | I44: 46043 | J44: 1 | K44: =WORKDAY.INTL(I44,J44,1,Data!$C$3:$C$14) -> 46044 | M44: 1 | N44: =_xlfn.LET( _xlpm.s,VALUE($I44), _xlpm.e,VALUE($K44), IF(OR(_xlpm.s="",_xlpm.e=""),"", IF(_xlpm.e<=_xlpm.s, IF(TODAY()>=_xlpm.e,1,0), MAX(0,MIN(1,(TODAY()-_xlpm.s)/(_xlpm.e-_xlpm.s))))) ) -> 1
B46: 8 | C46: Project Closure | E46: =MIN(E47:E52) -> 45979 | F46: =G46-E46 -> 16 | G46: =MAX(G47:G52) -> 45995 | I46: =MIN(I47:I52) -> 46044 | J46: =K46-I46 -> 22 | K46: =MAX(K47:K52) -> 46066 | M46: =(J47*M47+J48*M48+J49*M49+J50*M50+J51*M51+J52*M52)/SUM(J47:J52) -> 0.71428571 | N46: =(K47*N47+K48*N48+K49*N49+K50*N50+K51*N51+K52*N52)/SUM(K47:K52) -> 0.6665955
B47: 8.1 | C47: Equipment serial numbers | E47: =G44 -> 45980 | F47: 1 | G47: =WORKDAY.INTL(E47,F47,1,Data!$C$3:$C$14) -> 45981 | I47: 46049 | J47: 2 | K47: =WORKDAY.INTL(I47,J47,1,Data!$C$3:$C$14) -> 46051 | M47: 1 | N47: =_xlfn.LET( _xlpm.s,VALUE($I47), _xlpm.e,VALUE($K47), IF(OR(_xlpm.s="",_xlpm.e=""),"", IF(_xlpm.e<=_xlpm.s, IF(TODAY()>=_xlpm.e,1,0), MAX(0,MIN(1,(TODAY()-_xlpm.s)/(_xlpm.e-_xlpm.s))))) ) -> 1
B48: 8.2 | C48: Snags completion | E48: =G44 -> 45980 | F48: 5 | G48: =WORKDAY.INTL(E48,F48,1,Data!$C$3:$C$14) -> 45987 | I48: =K44 -> 46044 | J48: 3 | K48: =WORKDAY.INTL(I48,J48,1,Data!$C$3:$C$14) -> 46049 | M48: 1 | N48: =_xlfn.LET( _xlpm.s,VALUE($I48), _xlpm.e,VALUE($K48), IF(OR(_xlpm.s="",_xlpm.e=""),"", IF(_xlpm.e<=_xlpm.s, IF(TODAY()>=_xlpm.e,1,0), MAX(0,MIN(1,(TODAY()-_xlpm.s)/(_xlpm.e-_xlpm.s))))) ) -> 1
B49: 8.3 | C49: System Performance Monitoring | E49: =WORKDAY.INTL(G39,0,1,Data!$C$3:$C$14) -> 45979 | F49: 5 | G49: =WORKDAY.INTL(E49,F49,1,Data!$C$3:$C$14) -> 45986 | I49: =WORKDAY.INTL(K39,0,1,Data!$C$3:$C$14) -> 46045 | J49: 3 | K49: =WORKDAY.INTL(I49,J49,1,Data!$C$3:$C$14) -> 46050 | M49: 1 | N49: =_xlfn.LET( _xlpm.s,VALUE($I49), _xlpm.e,VALUE($K49), IF(OR(_xlpm.s="",_xlpm.e=""),"", IF(_xlpm.e<=_xlpm.s, IF(TODAY()>=_xlpm.e,1,0), MAX(0,MIN(1,(TODAY()-_xlpm.s)/(_xlpm.e-_xlpm.s))))) ) -> 1
B50: 8.4 | C50: Handover documentation | E50: =WORKDAY.INTL(G48,0,1,Data!$C$3:$C$14) -> 45987 | F50: 1 | G50: =WORKDAY.INTL(E50,F50,1,Data!$C$3:$C$14) -> 45988 | I50: 46049 | J50: 2 | K50: =WORKDAY.INTL(I50,J50,1,Data!$C$3:$C$14) -> 46051 | M50: 1 | N50: =_xlfn.LET( _xlpm.s,VALUE($I50), _xlpm.e,VALUE($K50), IF(OR(_xlpm.s="",_xlpm.e=""),"", IF(_xlpm.e<=_xlpm.s, IF(TODAY()>=_xlpm.e,1,0), MAX(0,MIN(1,(TODAY()-_xlpm.s)/(_xlpm.e-_xlpm.s))))) ) -> 1
B51: 8.5 | C51: Handover to Client | E51: =WORKDAY.INTL(G50,0,1,Data!$C$3:$C$14) -> 45988 | F51: 1 | G51: =WORKDAY.INTL(E51,F51,1,Data!$C$3:$C$14) -> 45989 | I51: 46063 | J51: 1 | K51: =WORKDAY.INTL(I51,J51,1,Data!$C$3:$C$14) -> 46064 | M51: 0 | N51: =_xlfn.LET( _xlpm.s,VALUE($I51), _xlpm.e,VALUE($K51), IF(OR(_xlpm.s="",_xlpm.e=""),"", IF(_xlpm.e<=_xlpm.s, IF(TODAY()>=_xlpm.e,1,0), MAX(0,MIN(1,(TODAY()-_xlpm.s)/(_xlpm.e-_xlpm.s))))) ) -> 0
B52: 8.6 | C52: Handover to Matriarch | E52: =WORKDAY.INTL(E51,0,1,Data!$C$3:$C$14) -> 45988 | F52: 5 | G52: =WORKDAY.INTL(E52,F52,1,Data!$C$3:$C$14) -> 45995 | I52: =WORKDAY.INTL(I51,0,1,Data!$C$3:$C$14) -> 46063 | J52: 3 | K52: =WORKDAY.INTL(I52,J52,1,Data!$C$3:$C$14) -> 46066 | M52: 0 | N52: =_xlfn.LET( _xlpm.s,VALUE($I52), _xlpm.e,VALUE($K52), IF(OR(_xlpm.s="",_xlpm.e=""),"", IF(_xlpm.e<=_xlpm.s, IF(TODAY()>=_xlpm.e,1,0), MAX(0,MIN(1,(TODAY()-_xlpm.s)/(_xlpm.e-_xlpm.s))))) ) -> 0 | O52: Date TBC

Sheet Expenditure Tracking
B2: HIGH LEVEL PROJECT EXPENDITURE TRACKING
F4: COSTED | H4: ACTUAL | J4: Difference from costed
B5: EXPENDITURE | F5: =SUM(F9:F23) -> 2763016.5 | H5: =SUM(H9:H23) -> 2217962.2 | J5: =SUM(J9:J23) -> 545054.36
B7: No. | D7: Item | F7: Costed Expenditure | H7: Actual Expenditure | J7: Saving / Overrun | L7: Comments on variations from planned expenditure
B9: ='Expenditure Breakdown'!L6 -> 1 | D9: ='Expenditure Breakdown'!M6 -> 1. Panels | F9: ='Expenditure Breakdown'!I6 -> 838063 | H9: ='Expenditure Breakdown'!X6 -> 706622.74 | J9: =F9-H9 -> 131440.26
B10: ='Expenditure Breakdown'!L13 -> 2 | D10: ='Expenditure Breakdown'!M13 -> 2. Inverters | F10: ='Expenditure Breakdown'!I13 -> 210000 | H10: ='Expenditure Breakdown'!X13 -> 195738 | J10: =F10-H10 -> 14262
B11: ='Expenditure Breakdown'!L21 -> 3 | D11: ='Expenditure Breakdown'!M21 -> 3. Mounting Structures | F11: ='Expenditure Breakdown'!I21 -> 146400 | H11: ='Expenditure Breakdown'!X21 -> 69250 | J11: =F11-H11 -> 77150
B12: ='Expenditure Breakdown'!L28 -> 4 | D12: ='Expenditure Breakdown'!M28 -> 4. DC Equipment | F12: ='Expenditure Breakdown'!I28 -> 286300 | H12: ='Expenditure Breakdown'!X28 -> 257154.9 | J12: =F12-H12 -> 29145.1
B13: ='Expenditure Breakdown'!L44 -> 5 | D13: ='Expenditure Breakdown'!M44 -> 5. Monitoring | F13: ='Expenditure Breakdown'!I44 -> 49000 | H13: ='Expenditure Breakdown'!X44 -> 44864.75 | J13: =F13-H13 -> 4135.25
B14: ='Expenditure Breakdown'!L53 -> 6 | D14: ='Expenditure Breakdown'!M53 -> 6. AC Equipment | F14: ='Expenditure Breakdown'!I53 -> 497053.6 | H14: ='Expenditure Breakdown'!X53 -> 247722.28 | J14: =F14-H14 -> 249331.32
B15: ='Expenditure Breakdown'!L71 -> 7 | D15: ='Expenditure Breakdown'!M71 -> 7.BESS | F15: ='Expenditure Breakdown'!I71 -> 0 | H15: ='Expenditure Breakdown'!X71 -> 0 | J15: =F15-H15 -> 0
B16: ='Expenditure Breakdown'!L80 -> 8 | D16: ='Expenditure Breakdown'!M80 -> 8. Product Add On | F16: ='Expenditure Breakdown'!I80 -> 208000 | H16: ='Expenditure Breakdown'!X80 -> 226006.5 | J16: =F16-H16 -> -18006.5
B17: ='Expenditure Breakdown'!L91 -> 9 | D17: ='Expenditure Breakdown'!M91 -> 9. AC & DC installation | F17: ='Expenditure Breakdown'!I91 -> 291000 | H17: ='Expenditure Breakdown'!X91 -> 321250 | J17: =F17-H17 -> -30250
B18: ='Expenditure Breakdown'!L104 -> 10 | D18: ='Expenditure Breakdown'!M104 -> 10. Site Logistics | F18: ='Expenditure Breakdown'!I104 -> 76945.467 | H18: ='Expenditure Breakdown'!X104 -> 92395.69 | J18: =F18-H18 -> -15450.223
B19: ='Expenditure Breakdown'!L120 -> 11 | D19: ='Expenditure Breakdown'!M120 -> 11. Due Dilligence | F19: ='Expenditure Breakdown'!I120 -> 109300 | H19: ='Expenditure Breakdown'!X120 -> 14750 | J19: =F19-H19 -> 94550
B20: ='Expenditure Breakdown'!L126 -> 12 | D20: ='Expenditure Breakdown'!M126 -> 12. BDP Commission | F20: ='Expenditure Breakdown'!I126 -> 13353.69 | H20: ='Expenditure Breakdown'!X126 -> 0 | J20: =F20-H20 -> 13353.69
B21: ='Expenditure Breakdown'!L129 -> 13 | D21: ='Expenditure Breakdown'!M130 -> 13. Engineering | F21: ='Expenditure Breakdown'!I129 -> 31300.776 | H21: ='Expenditure Breakdown'!X129 -> 41047.632 | J21: =F21-H21 -> -9746.8561
B22: ='Expenditure Breakdown'!L136 -> 14 | D22: ='Expenditure Breakdown'!M136 -> 14. General Expenses | F22: ='Expenditure Breakdown'!I136 -> 6300 | H22: ='Expenditure Breakdown'!X136 -> 1159.68 | J22: =F22-H22 -> 5140.32
B23: ='Expenditure Breakdown'!L149 -> 15 | D23: ='Expenditure Breakdown'!M149 -> 15. Service Add On | F23: ='Expenditure Breakdown'!I149 -> 0 | H23: ='Expenditure Breakdown'!X149 -> 0 | J23: =F23-H23 -> 0
D25: check: | F25: ='Expenditure Breakdown'!I2-'Expenditure Tracking'!F5 -> 0 | G25: =#REF!-G5 -> #REF! | H25: ='Expenditure Breakdown'!X2-H5 -> 0

Sheet Expenditure Breakdown
B2: COSTED EXPENDITURE BREAKDOWN | I2: =SUM(I6:I163) -> 2763016.5 | J2: =SUM(J6:J163) -> 3283810.6 | L2: ACTUAL EXPENDITURE BREAKDOWN | R2: FINANCE ONLY | X2: =SUM(X6:X163) -> 2217962.2
B4: No. | C4: Product / Service | D4: Description of Work | E4: QTY | F4: Rate / Unit | G4: Budget Total | H4: FORECASTED PAYMENT DATE | I4: Total COS | J4: =IF(J2-'Revenue Tracking'!D4>=0, "Total Revenue", "ERROR on REV" ) -> Total Revenue | L4: No. | M4: Product/ Service | N4: Description of Work | O4: QTY | P4: Rate / Unit | Q4: Actual Total | R4: PO NUMBER | S4: INVOICE NUMBER | T4: INVOICE RAISED DATE | U4: REVENUE RECOGNITION AMOUNT | V4: CHECK | W4: FINANCE PAYMENT DATE | X4: Total COS
B6: 1 | C6: Panels | D6: Panels Budget | G6: =D164 -> 838063 | H6: ='Project Plan'!E36+60 -> 46004 | I6: =SUM(G6:G11) -> 838063 | J6: =F164 -> 1022028 | L6: 1 | M6: 1. Panels | N6: Panels Budget - Assume 610W - Longi 610 (Krannich) | O6: ='Project Plan'!$E$3*1000/610 -> 600 | P6: =1.85*610 -> 1128.5 | Q6: =O6*P6 -> 677100 | S6: Krannich - 15-10014113 | T6: 45961 | U6: 982465.72 | V6: =J6-SUM(U6:U11) -> 0 | W6: 46009 | X6: =SUM(Q6:Q11) -> 706622.74
B7: 1 | D7: Delivery Budget | L7: 1 | M7: 1. Panels | N7: EPR Fees | Q7: 14365.74 | S7: Krannich - 15-10014113 | T7: 45961 | U7: 20844.553 | W7: =W6 -> 46009
B8: 1 | L8: 1 | M8: 1. Panels | N8: Delivery | Q8: 12900 | S8: Krannich - 15-10014113 | T8: 45961 | U8: 18717.778 | W8: =W6 -> 46009
B9: 1 | L9: 1 | M9: 1. Panels | N9: Panels from stock (Ziegler) | O9: 2 | P9: 1128.5 | Q9: =O9*P9 -> 2257 | S9: Allocated from Cpt Storeroom | T9: 46022 | U9: 0 | W9: 46022
B10: 1 | L10: 1 | M10: 1. Panels | T10: =IF(W10>1,EOMONTH(W10,0),"") | U10: 0
B11: 1 | L11: 1 | M11: 1. Panels | T11: =IF(W11>1,EOMONTH(W11,0),"") | U11: 0 | Y11: BUDGET | Z11: Installer Allocation
T12: =IF(W12>1,EOMONTH(W12,0),"") | Y12: AC Equipment | Z12: =G53 -> 497053.6
B13: 2 | C13: Inverters | D13: Inverter Budget | G13: =D165 -> 210000 | H13: ='Project Plan'!E22+60 -> 46004 | I13: =SUM(G13:G19) -> 210000 | J13: =F165 -> 256097.56 | L13: 2 | M13: 2. Inverters | N13: Huawei 100KTL (Krannich) | O13: 3 | P13: 65246 | Q13: =O13*P13 -> 195738 | S13: Krannich - 15-10014113 | T13: 45961 | U13: 256097.56 | V13: =J13-SUM(U13:U19) -> 0 | W13: =W6 -> 46009 | X13: =SUM(Q13:Q19) -> 195738 | Y13: DC Equipment | Z13: =G29 -> 169260
B14: 2 | L14: 2 | M14: 2. Inverters | T14: =IF(W14>1,EOMONTH(W14,0),"") | U14: 0 | Y14: AC Labour | Z14: =G91 -> 91500
B15: 2 | L15: 2 | M15: 2. Inverters | T15: =IF(W15>1,EOMONTH(W15,0),"") | U15: 0 | Y15: DC Labour | Z15: =G92 -> 199500
B16: 2 | L16: 2 | M16: 2. Inverters | T16: =IF(W16>1,EOMONTH(W16,0),"") | U16: 0 | Y16: Offloading | Z16: =G104 -> 8500
B17: 2 | L17: 2 | M17: 2. Inverters | T17: =IF(W17>1,EOMONTH(W17,0),"") | U17: 0 | Y17: Scaffolding | Z17: =G105 -> 22285.467
B18: 2 | L18: 2 | M18: 2. Inverters | T18: =IF(W18>1,EOMONTH(W18,0),"") | U18: 0 | Y18: Storage | Z18: =G107 -> 2960
B19: 2 | L19: 2 | M19: 2. Inverters | T19: =IF(W19>1,EOMONTH(W19,0),"") | U19: 0 | Y19: Telehandler | Z19: 0
T20: =IF(W20>1,EOMONTH(W20,0),"")
B21: 3 | C21: Mounting Structures | D21: Structure Budget | G21: =D166 -> 146400 | H21: ='Project Plan'!E30+30 -> 45974 | I21: =SUM(G21:G26) -> 146400 | J21: =F166 -> 178536.59 | L21: 3 | M21: 3. Mounting Structures | N21: Schletter Structure | Q21: 69250 | R21: PO4324-BOLT-20250925 - RV Approved | S21: Schletter - INV2244 | T21: 45930 | U21: 178536.59 | V21: =J21-SUM(U21:U26) -> 0 | W21: =T21+30 -> 45960 | X21: =SUM(Q21:Q26) -> 69250 | Y21: Other | Z21: 0
B22: 3 | L22: 3 | M22: 3. Mounting Structures | T22: =IF(W22>1,EOMONTH(W22,0),"") | U22: 0 | Y22: Total | Z22: =SUM(Z12:Z21) -> 991059.06
B23: 3 | L23: 3 | M23: 3. Mounting Structures | T23: =IF(W23>1,EOMONTH(W23,0),"") | U23: 0 | Y23: Less 15% | Z23: =+Z22*0.85 -> 842400.2
B24: 3 | L24: 3 | M24: 3. Mounting Structures | T24: =IF(W24>1,EOMONTH(W24,0),"") | U24: 0 | Y24: R/Wp | Z24: =Z23/'Project Plan'!$E$3/1000 -> 2.3016399
B25: 3 | L25: 3 | M25: 3. Mounting Structures | T25: =IF(W25>1,EOMONTH(W25,0),"") | U25: 0
B26: 3 | L26: 3 | M26: 3. Mounting Structures | T26: =IF(W26>1,EOMONTH(W26,0),"") | U26: 0 | Y26: ACTUAL | Z26: Installer Price
T27: =IF(W27>1,EOMONTH(W27,0),"") | Y27: AC Equipment | Z27: 116890.33
B28: 4 | C28: DC Equipment | D28: DC Cable Budget | E28: =G28/14*1.15 -> 9614 | G28: 117040 | H28: =H13 -> 46004 | I28: =SUM(G28:G42) -> 286300 | J28: =F167 -> 349146.34 | L28: 4 | M28: 4. DC Equipment | N28: DC Cable - Menlo SO0003713 | O28: 8000 | P28: 13.65 | Q28: =O28*P28 -> 109200 | S28: Menlo - INV0003329 | T28: 45961 | U28: 148263.87 | V28: =J28-SUM(U28:U42) -> 0 | W28: 46003 | X28: =SUM(Q28:Q42) -> 257154.9 | Y28: DC Equipment | Z28: 147954.9
B29: 4 | D29: DC Equipment Budget | G29: =D167-G28 -> 169260 | H29: =H28 -> 46004 | L29: 4 | M29: 4. DC Equipment | T29: =IF(W29>1,EOMONTH(W29,0),"") | U29: =(Q29/$X$28*$J$28) -> 0 | Y29: AC Labour | Z29: 93937.5
B30: 4 | L30: 4 | M30: 4. DC Equipment | T30: =IF(W30>1,EOMONTH(W30,0),"") | U30: =(Q30/$X$28*$J$28) -> 0 | Y30: DC Labour | Z30: 227312.5
B31: 4 | L31: 4 | M31: 4. DC Equipment | T31: =IF(W31>1,EOMONTH(W31,0),"") | U31: =(Q31/$X$28*$J$28) -> 0 | Y31: OffLoading | Z31: 12000
B32: 4 | L32: 4 | M32: 4. DC Equipment | N32: Project Kick Off | O32: =Z28 -> 147954.9 | P32: 0.15 | Q32: =$O$32*P32 -> 22193.235 | R32: PO4349-BOLT-20251001 - RV Approved | S32: Leading Edge - INV-0158 | T32: =T92 -> 45961 | U32: 30132.371 | W32: =W92 -> 45939 | Y32: Storage | Z32: 11440
B33: 4 | L33: 4 | M33: 4. DC Equipment | N33: Site Establishment | P33: 0.15 | Q33: =$O$32*P33 -> 22193.235 | S33: Leading Edge - INV-0159 | T33: =T93 -> 45961 | U33: 30132.371 | W33: =W93 -> 45939 | Y33: Geda | Z33: 37455.8
B34: 4 | L34: 4 | M34: 4. DC Equipment | N34: AC Installation Complete | P34: 0.2 | Q34: =$O$32*P34 -> 29590.98 | S34: Leading Edge - INV-0172 | T34: =T94 -> 45991 | U34: 40176.494 | W34: =W94 -> 45999 | Y34: Travel | Z34: 19549.89
B35: 4 | L35: 4 | M35: 4. DC Equipment | N35: DC Installation Complete | P35: 0.2 | Q35: =$O$32*P35 -> 29590.98 | S35: =S95 -> Leading Edge - INV-0176 | T35: =T95 -> 46022 | U35: 40176.494 | W35: =W95 -> 46015 | Y35: COC's | Z35: 4000
B36: 4 | L36: 4 | M36: 4. DC Equipment | N36: Commissioning Complete | P36: 0.1 | Q36: =$O$32*P36 -> 14795.49 | S36: =S96 -> Leading Edge - INV-0177 | T36: =T96 -> 46022 | U36: 20088.247 | W36: =W96 -> 46015 | Y36: HSE | Z36: 7950
B37: 4 | L37: 4 | M37: 4. DC Equipment | N37: Site De-establisment | P37: 0.1 | Q37: =$O$32*P37 -> 14795.49 | S37: Leading Edge - INV-0178 | T37: 46022 | U37: 20088.247 | W37: =W97 -> 46052 | Y37: Other | Z37: 0
B38: 4 | L38: 4 | M38: 4. DC Equipment | N38: Handover Document Complete | P38: 0.05 | Q38: =$O$32*P38 -> 7397.745 | S38: Leading Edge - INV-0179 | T38: 46022 | U38: 10044.124 | W38: =W98 -> 46058 | Y38: Total | Z38: =SUM(Z27:Z37) -> 678490.92
B39: 4 | L39: 4 | M39: 4. DC Equipment | N39: End of Defects Period | P39: 0.05 | Q39: =$O$32*P39 -> 7397.745 | S39: Leading Edge - INV-0180 | T39: 46022 | U39: 10044.124 | W39: =W99 -> 46109 | Y39: R/Wp | Z39: =Z38/'Project Plan'!$E$3/1000 -> 1.8538003
B40: 4 | L40: 4 | M40: 4. DC Equipment | T40: =IF(W40>1,EOMONTH(W40,0),"") | U40: =(Q40/$X$28*$J$28) -> 0
B41: 4 | L41: 4 | M41: 4. DC Equipment | T41: =IF(W41>1,EOMONTH(W41,0),"") | U41: =(Q41/$X$28*$J$28) -> 0
B42: 4 | L42: 4 | M42: 4. DC Equipment | T42: =IF(W42>1,EOMONTH(W42,0),"") | U42: =(Q42/$X$28*$J$28) -> 0
T43: =IF(W43>1,EOMONTH(W43,0),"")
B44: 5 | C44: Monitoring | D44: Monitoring Budget | G44: =D169-G45 -> 34000 | H44: =H13 -> 46004 | I44: =SUM(G44:G51) -> 49000 | J44: =F169 -> 59756.098 | L44: 5 | M44: 5. Monitoring | N44: Smartlogger - Menlo SO0003713 | Q44: 8598.34 | S44: Menlo - INV0003329 | T44: 45961 | U44: 11639.593 | V44: =J44-SUM(U44:U51) -> 0.001976382 | W44: =H44 -> 46004 | X44: =SUM(Q44:Q51) -> 44864.75
B45: 5 | D45: Revenue Metering | G45: 15000 | H45: 45961 | L45: 5 | M45: 5. Monitoring | N45: CTs & Meters | Q45: 22615.5 | R45: PO4325-BOLT-20250925 - RV Approved | S45: Accuenergy - ASAI-006478 | T45: 45930 | U45: 31168.85 | W45: =T45+30 -> 45960
B46: 5 | L46: 5 | M46: 5. Monitoring | N46: Techsitter | Q46: 11169 | S46: Matriarch - INV-5207 | T46: 45961 | U46: 15320.089 | W46: 45974
L47: 5 | M47: 5. Monitoring | N47: Courier of Techsitter | Q47: 206.91 | S47: DSV Inv: 180150385 | T47: 45961 | U47: 283.81052 | W47: 45991
B48: 5 | L48: 5 | M48: 5. Monitoring | N48: Lithium Battery | Q48: 975 | S48: Red Pole - SO-35912 | T48: 45930 | U48: 1343.7523 | W48: 45939
B49: 5 | L49: 5 | M49: 5. Monitoring | N49: Power Supply | Q49: 1300 | S49: Allocated from Cpt Storeroom | T49: 46022 | U49: 0 | W49: 46022
B50: 5 | L50: 5 | M50: 5. Monitoring | T50: =IF(W50>1,EOMONTH(W50,0),"") | U50: =(Q50/$X$44*$J$44) -> 0
B51: 5 | L51: 5 | M51: 5. Monitoring | T51: =IF(W51>1,EOMONTH(W51,0),"") | U51: =(Q51/$X$44*$J$44) -> 0
T52: =IF(W52>1,EOMONTH(W52,0),"")
B53: 6 | C53: AC Equipment | D53: AC Equipment Budget | G53: =D168 -> 497053.6 | H53: 45961 | I53: =SUM(G53:G69) -> 497053.6 | J53: =F168 -> 606162.92 | L53: 6 | M53: 6. AC Equipment | T53: =IF(W53>1,EOMONTH(W53,0),"") | U53: =(Q53/$X$53*$J$53) -> 0 | V53: =J53-SUM(U53:U69) -> 0 | X53: =SUM(Q53:Q69) -> 247722.28
B54: 6 | L54: 6 | M54: 6. AC Equipment | N54: PVDB | Q54: 130831.95 | R54: PO4329-BOLT-20250925 - MI Approved | S54: Switchboard - 2-SOI002605 | T54: 45991 | U54: 320138.65 | W54: =T54+30 -> 46021
B55: 6 | L55: 6 | M55: 6. AC Equipment | T55: =IF(W55>1,EOMONTH(W55,0),"") | U55: =(Q55/$X$53*$J$53) -> 0
B56: 6 | L56: 6 | M56: 6. AC Equipment | T56: =IF(W56>1,EOMONTH(W56,0),"") | U56: =(Q56/$X$53*$J$53) -> 0
B57: 6 | L57: 6 | M57: 6. AC Equipment | T57: =IF(W57>1,EOMONTH(W57,0),"") | U57: =(Q57/$X$53*$J$53) -> 0
B58: 6 | L58: 6 | M58: 6. AC Equipment | T58: =IF(W58>1,EOMONTH(W58,0),"") | U58: =(Q58/$X$53*$J$53) -> 0
B59: 6 | L59: 6 | M59: 6. AC Equipment | N59: Project Kick Off | O59: =Z27 -> 116890.33 | P59: 0.15 | Q59: =$O$59*P59 -> 17533.55 | R59: PO4349-BOLT-20251001 - RV Approved | S59: Leading Edge - INV-0158 | T59: =T92 -> 45961 | U59: 42903.64 | W59: =W92 -> 45939
B60: 6 | L60: 6 | M60: 6. AC Equipment | N60: Site Establishment | P60: 0.15 | Q60: =$O$59*P60 -> 17533.55 | S60: Leading Edge - INV-0159 | T60: =T93 -> 45961 | U60: 42903.64 | W60: =W93 -> 45939
B61: 6 | L61: 6 | M61: 6. AC Equipment | N61: AC Installation Complete | P61: 0.2 | Q61: =$O$59*P61 -> 23378.066 | S61: Leading Edge - INV-0172 | T61: =T94 -> 45991 | U61: 57204.854 | W61: =W94 -> 45999
B62: 6 | L62: 6 | M62: 6. AC Equipment | N62: DC Installation Complete | P62: 0.2 | Q62: =$O$59*P62 -> 23378.066 | S62: =S95 -> Leading Edge - INV-0176 | T62: =T95 -> 46022 | U62: 57204.854 | W62: =W95 -> 46015
B63: 6 | L63: 6 | M63: 6. AC Equipment | N63: Commissioning Complete | P63: 0.1 | Q63: =$O$59*P63 -> 11689.033 | S63: =S96 -> Leading Edge - INV-0177 | T63: =T96 -> 46022 | U63: 28602.427 | W63: =W96 -> 46015
B64: 6 | L64: 6 | M64: 6. AC Equipment | N64: Site De-establisment | P64: 0.1 | Q64: =$O$59*P64 -> 11689.033 | S64: Leading Edge - INV-0178 | T64: 46022 | U64: 28602.427 | W64: =W97 -> 46052
B65: 6 | L65: 6 | M65: 6. AC Equipment | N65: Handover Document Complete | P65: 0.05 | Q65: =$O$59*P65 -> 5844.5165 | S65: Leading Edge - INV-0179 | T65: 46022 | U65: 14301.213 | W65: =W98 -> 46058
B66: 6 | L66: 6 | M66: 6. AC Equipment | N66: End of Defects Period | P66: 0.05 | Q66: =$O$59*P66 -> 5844.5165 | S66: Leading Edge - INV-0180 | T66: 46022 | U66: 14301.213 | W66: =W99 -> 46109
B67: 6 | L67: 6 | M67: 6. AC Equipment | T67: =IF(W67>1,EOMONTH(W67,0),"") | U67: =(Q67/$X$53*$J$53) -> 0
B68: 6 | L68: 6 | M68: 6. AC Equipment | T68: =IF(W68>1,EOMONTH(W68,0),"") | U68: =(Q68/$X$53*$J$53) -> 0
B69: 6 | L69: 6 | M69: 6. AC Equipment | T69: =IF(W69>1,EOMONTH(W69,0),"") | U69: =(Q69/$X$53*$J$53) -> 0
T70: =IF(W70>1,EOMONTH(W70,0),"")
B71: 7 | C71: BESS | I71: =SUM(G71:G78) -> 0 | J71: =F173 -> 0 | L71: 7 | M71: 7.BESS | V71: =J71-SUM(U71:U78) -> 0 | X71: =SUM(Q71:Q78) -> 0
B72: 7 | L72: 7 | M72: 7.BESS
B73: 7 | L73: 7 | M73: 7.BESS
B74: 7 | L74: 7 | M74: 7.BESS
B75: 7 | L75: 7 | M75: 7.BESS
B76: 7 | L76: 7 | M76: 7.BESS
B77: 7 | L77: 7 | M77: 7.BESS
B78: 7 | L78: 7 | M78: 7.BESS
B80: 8 | C80: Product Add On | I80: =SUM(G80:G89) -> 208000 | J80: =F170+F172 -> 239241.19 | L80: 8 | M80: 8. Product Add On | U80: 0 | V80: =J80-SUM(U80:U89) -> 0 | X80: =SUM(Q80:Q89) -> 226006.5
B81: 8 | D81: Inverter Rack | G81: 48000 | H81: =H92 -> 45937 | L81: 8 | M81: 8. Product Add On | U81: 0
B82: 8 | L82: 8 | M82: 8. Product Add On | N82: APEX & Emulator | Q82: 44000 | R82: PO4326-BOLT-20250925 - RV Approved | S82: Rbicon - INVWCRE-0070990 | T82: 45930 | U82: 87904.906 | W82: 45960
B83: 8 | L83: 8 | M83: 8. Product Add On | U83: 0
B84: 8 | D84: MV Metering Emulator | G84: 85000 | H84: =H81 -> 45937 | L84: 8 | M84: 8. Product Add On | N84: Catladder & Inverter Rack | O84: 75750 | P84: 0.5 | Q84: 37875 | R84: PO4347-BOLT-20250930 - RV Approved | S84: Barrier Projects - 497 | T84: 45961 | U84: 75668.143 | W84: 45939
B85: 8 | L85: 8 | M85: 8. Product Add On | P85: 0.5 | Q85: 37875 | S85: Barrier Projects - 497 | T85: 45961 | U85: 75668.143 | W85: 45974
B86: 8 | L86: 8 | M86: 8. Product Add On | N86: Walkway Installation | Q86: 29500 | R86: PO4465-BOLT-20251111 - RV Approved | S86: Leading Edge - INV-0169 | T86: 45991 | U86: 0 | W86: 45980
B87: 8 | D87: Catladder | G87: 75000 | H87: =H81 -> 45937 | L87: 8 | M87: 8. Product Add On | N87: Walkway Material | Q87: 71592.3 | R87: PO4462-BOLT-20251111 - RV Approved | S87: Onvlee Engineering PO4662-Bolt-20251111 | T87: 45991 | U87: 0 | W87: 45974
L88: 8 | M88: 8. Product Add On | N88: Walkway Clamps | Q88: -5272.5 | S88: Onvlee Engineering - CN 01001981 | T88: 46053 | W88: 46043
B89: 8 | L89: 8 | M89: 8. Product Add On | N89: Walkway Clamps | Q89: 10436.7 | S89: Onvlee Engineering - ONV1702 | T89: 46053 | U89: 0 | W89: 46031
K90: Only services to be capture below, products above | T90: =IF(W90>1,EOMONTH(W90,0),"")
B91: 9 | C91: AC & DC Installation | D91: AC Installation Budget | G91: =D177 -> 91500 | H91: =H92 -> 45937 | I91: =SUM(G91:G102) -> 291000 | J91: =F177+F178 -> 323333.33 | L91: 9 | M91: 9. AC & DC installation | T91: =IF(W91>1,EOMONTH(W91,0),"") | U91: =(Q91/$X$91*$J$91) -> 0 | V91: =J91-SUM(U91:U102) -> 0 | X91: =SUM(Q91:Q102) -> 321250
B92: 9 | D92: DC Installation Budget | G92: =D178 -> 199500 | H92: ='Project Plan'!E19-7 -> 45937 | L92: 9 | M92: 9. AC & DC installation | N92: Project Kick Off | O92: =Z30+Z29 -> 321250 | P92: 0.15 | Q92: =$O$92*P92 -> 48187.5 | R92: PO4349-BOLT-20251001 - RV Approved | S92: Leading Edge - INV-0158 | T92: 45961 | U92: 48500 | W92: 45939
B93: 9 | L93: 9 | M93: 9. AC & DC installation | N93: Site Establishment | P93: 0.15 | Q93: =$O$92*P93 -> 48187.5 | S93: Leading Edge - INV-0159 | T93: =IF(W93>1,EOMONTH(W93,0),"") -> 45961 | U93: 48500 | W93: 45939
B94: 9 | L94: 9 | M94: 9. AC & DC installation | N94: AC Installation Complete | P94: 0.2 | Q94: =$O$92*P94 -> 64250 | S94: Leading Edge - INV-0172 | T94: 45991 | U94: 64666.667 | W94: ='Project Plan'!K21+7 -> 45999
B95: 9 | L95: 9 | M95: 9. AC & DC installation | N95: DC Installation Complete | P95: 0.2 | Q95: =$O$92*P95 -> 64250 | S95: Leading Edge - INV-0176 | T95: 46022 | U95: 64666.667 | W95: 46015
B96: 9 | L96: 9 | M96: 9. AC & DC installation | N96: Commissioning Complete | P96: 0.1 | Q96: =$O$92*P96 -> 32125 | S96: Leading Edge - INV-0177 | T96: 46022 | U96: 32333.333 | W96: 46015
B97: 9 | L97: 9 | M97: 9. AC & DC installation | N97: Site De-establisment | P97: 0.1 | Q97: =$O$92*P97 -> 32125 | S97: Leading Edge - INV-0178 | T97: 46022 | U97: 32333.333 | W97: ='Project Plan'!K41+7 -> 46052
B98: 9 | L98: 9 | M98: 9. AC & DC installation | N98: Handover Document Complete | P98: 0.05 | Q98: =$O$92*P98 -> 16062.5 | S98: Leading Edge - INV-0179 | T98: 46022 | U98: 16166.667 | W98: ='Project Plan'!K48+9 -> 46058
B99: 9 | L99: 9 | M99: 9. AC & DC installation | N99: End of Defects Period | P99: 0.05 | Q99: =$O$92*P99 -> 16062.5 | S99: Leading Edge - INV-0180 | T99: 46022 | U99: 16166.667 | W99: ='Project Plan'!K48+60 -> 46109
B100: 9 | L100: 9 | M100: 9. AC & DC installation | T100: =IF(W100>1,EOMONTH(W100,0),"") | U100: =(Q100/$X$91*$J$91) -> 0
B101: 9 | L101: 9 | M101: 9. AC & DC installation | U101: =(Q101/$X$91*$J$91) -> 0
B102: 9 | L102: 9 | M102: 9. AC & DC installation | T102: =IF(W102>1,EOMONTH(W102,0),"") | U102: =(Q102/$X$91*$J$91) -> 0
T103: =IF(W103>1,EOMONTH(W103,0),"")
B104: 10 | C104: Site Logistics | D104: Offloading | G104: =D181 -> 8500 | H104: 45991 | I104: =SUM(G104:G118) -> 76945.467 | J104: =F181+F184+F185+F183+F182 -> 85494.963 | L104: 10 | M104: 10. Site Logistics | U104: =(Q104/$X$104*$J$104) -> 0 | V104: =J104-SUM(U104:U118) -> 0 | X104: =SUM(Q104:Q118) -> 92395.69
...

Sheet Cashflow
D1: [RT: Double Check the first date is always a MONDAY] | F1: 45845 | G1: =F1+7 -> 45852 | H1: =G1+7 -> 45859 | I1: =H1+7 -> 45866 | J1: =I1+7 -> 45873 | K1: =J1+7 -> 45880 | L1: =K1+7 -> 45887 | M1: =L1+7 -> 45894 | N1: =M1+7 -> 45901 | ... AZG1: =AZF1+7 -> 55316
A2: PLANNED | C2: CHECK | D2: CHECK
B3: Planned Revenue | C3: ='Revenue Tracking'!D4 -> 3283810.5 | D3: =SUM(F3:AZG3) -> 3377404.7 | F3: =SUMIFS('Revenue Tracking'!$F$13:$F$19, 'Revenue Tracking'!$H$13:$H$19, ">="&F1,'Revenue Tracking'!$H$13:$H$19, "<"&G1) -> 0 | G3: =SUMIFS('Revenue Tracking'!$F$13:$F$19, 'Revenue Tracking'!$H$13:$H$19, ">="&G1,'Revenue Tracking'!$H$13:$H$19, "<"&H1) -> 0 | H3: =SUMIFS('Revenue Tracking'!$F$13:$F$19, 'Revenue Tracking'!$H$13:$H$19, ">="&H1,'Revenue Tracking'!$H$13:$H$19, "<"&I1) -> 0 | I3: =SUMIFS('Revenue Tracking'!$F$13:$F$19, 'Revenue Tracking'!$H$13:$H$19, ">="&I1,'Revenue Tracking'!$H$13:$H$19, "<"&J1) -> 0 | J3: =SUMIFS('Revenue Tracking'!$F$13:$F$19, 'Revenue Tracking'!$H$13:$H$19, ">="&J1,'Revenue Tracking'!$H$13:$H$19, "<"&K1) -> 0 | K3: =SUMIFS('Revenue Tracking'!$F$13:$F$19, 'Revenue Tracking'!$H$13:$H$19, ">="&K1,'Revenue Tracking'!$H$13:$H$19, "<"&L1) -> 0 | L3: =SUMIFS('Revenue Tracking'!$F$13:$F$19, 'Revenue Tracking'!$H$13:$H$19, ">="&L1,'Revenue Tracking'!$H$13:$H$19, "<"&M1) -> 0 | M3: =SUMIFS('Revenue Tracking'!$F$13:$F$19, 'Revenue Tracking'!$H$13:$H$19, ">="&M1,'Revenue Tracking'!$H$13:$H$19, "<"&N1) -> 0 | ... AZG3: =SUMIFS('Revenue Tracking'!$F$13:$F$19, 'Revenue Tracking'!$H$13:$H$19, ">="&AZG1,'Revenue Tracking'!$H$13:$H$19, "<"&AZH1) -> 0
B4: Planned Revenue - Cumulative | F4: =F3 -> 0 | G4: =F4+G3 -> 0 | H4: =G4+H3 -> 0 | I4: =H4+I3 -> 0 | J4: =I4+J3 -> 0 | K4: =J4+K3 -> 0 | L4: =K4+L3 -> 0 | M4: =L4+M3 -> 0 | N4: =M4+N3 -> 0 | ... AZG4: =AZF4+AZG3 -> 3377404.7
B5: Planned Expenditure | C5: ='Revenue Tracking'!D5 -> 2763016.5 | D5: =SUM(F5:AZG5) -> 2763016.5 | F5: =SUMIFS('Expenditure Breakdown'!$G$6:$G$170, 'Expenditure Breakdown'!$H$6:$H$170, ">="&F1,'Expenditure Breakdown'!$H$6:$H$170, "<"&G1) -> 0 | G5: =SUMIFS('Expenditure Breakdown'!$G$6:$G$170, 'Expenditure Breakdown'!$H$6:$H$170, ">="&G1,'Expenditure Breakdown'!$H$6:$H$170, "<"&H1) -> 0 | H5: =SUMIFS('Expenditure Breakdown'!$G$6:$G$170, 'Expenditure Breakdown'!$H$6:$H$170, ">="&H1,'Expenditure Breakdown'!$H$6:$H$170, "<"&I1) -> 0 | I5: =SUMIFS('Expenditure Breakdown'!$G$6:$G$170, 'Expenditure Breakdown'!$H$6:$H$170, ">="&I1,'Expenditure Breakdown'!$H$6:$H$170, "<"&J1) -> 0 | J5: =SUMIFS('Expenditure Breakdown'!$G$6:$G$170, 'Expenditure Breakdown'!$H$6:$H$170, ">="&J1,'Expenditure Breakdown'!$H$6:$H$170, "<"&K1) -> 0 | K5: =SUMIFS('Expenditure Breakdown'!$G$6:$G$170, 'Expenditure Breakdown'!$H$6:$H$170, ">="&K1,'Expenditure Breakdown'!$H$6:$H$170, "<"&L1) -> 0 | L5: =SUMIFS('Expenditure Breakdown'!$G$6:$G$170, 'Expenditure Breakdown'!$H$6:$H$170, ">="&L1,'Expenditure Breakdown'!$H$6:$H$170, "<"&M1) -> 0 | M5: =SUMIFS('Expenditure Breakdown'!$G$6:$G$170, 'Expenditure Breakdown'!$H$6:$H$170, ">="&M1,'Expenditure Breakdown'!$H$6:$H$170, "<"&N1) -> 0 | ... AZG5: =SUMIFS('Expenditure Breakdown'!$G$6:$G$170, 'Expenditure Breakdown'!$H$6:$H$170, ">="&AZG1,'Expenditure Breakdown'!$H$6:$H$170, "<"&AZH1) -> 0
B6: Planned Expenditure - Cumulative | F6: =F5 -> 0 | G6: =F6+G5 -> 0 | H6: =G6+H5 -> 0 | I6: =H6+I5 -> 0 | J6: =I6+J5 -> 0 | K6: =J6+K5 -> 0 | L6: =K6+L5 -> 0 | M6: =L6+M5 -> 0 | N6: =M6+N5 -> 0 | ... AZG6: =AZF6+AZG5 -> 2763016.5
B7: PLANNED CashFlow | F7: =F4-F6 -> 0 | G7: =G4-G6 -> 0 | H7: =H4-H6 -> 0 | I7: =I4-I6 -> 0 | J7: =J4-J6 -> 0 | K7: =K4-K6 -> 0 | L7: =L4-L6 -> 0 | M7: =M4-M6 -> 0 | ... AZG7: =AZG4-AZG6 -> 614388.22
A8: ACTUAL | C8: CHECK | D8: CHECK
B9: Actual + Planned Revenue | C9: ='Revenue Tracking'!F4 -> 3377404.8 | D9: =SUM(F9:AZG9) -> 2955429.5 | F9: =SUMIFS('Revenue Tracking'!$F$13:$F$19, 'Revenue Tracking'!$P$13:$P$19, ">="&F1,'Revenue Tracking'!$P$13:$P$19, "<"&G1) -> 0 | G9: =SUMIFS('Revenue Tracking'!$F$13:$F$19, 'Revenue Tracking'!$P$13:$P$19, ">="&G1,'Revenue Tracking'!$P$13:$P$19, "<"&H1) -> 0 | H9: =SUMIFS('Revenue Tracking'!$F$13:$F$19, 'Revenue Tracking'!$P$13:$P$19, ">="&H1,'Revenue Tracking'!$P$13:$P$19, "<"&I1) -> 0 | I9: =SUMIFS('Revenue Tracking'!$F$13:$F$19, 'Revenue Tracking'!$P$13:$P$19, ">="&I1,'Revenue Tracking'!$P$13:$P$19, "<"&J1) -> 0 | J9: =SUMIFS('Revenue Tracking'!$F$13:$F$19, 'Revenue Tracking'!$P$13:$P$19, ">="&J1,'Revenue Tracking'!$P$13:$P$19, "<"&K1) -> 0 | K9: =SUMIFS('Revenue Tracking'!$F$13:$F$19, 'Revenue Tracking'!$P$13:$P$19, ">="&K1,'Revenue Tracking'!$P$13:$P$19, "<"&L1) -> 0 | L9: =SUMIFS('Revenue Tracking'!$F$13:$F$19, 'Revenue Tracking'!$P$13:$P$19, ">="&L1,'Revenue Tracking'!$P$13:$P$19, "<"&M1) -> 0 | M9: =SUMIFS('Revenue Tracking'!$F$13:$F$19, 'Revenue Tracking'!$P$13:$P$19, ">="&M1,'Revenue Tracking'!$P$13:$P$19, "<"&N1) -> 0 | ... AZG9: =SUMIFS('Revenue Tracking'!$F$13:$F$19, 'Revenue Tracking'!$P$13:$P$19, ">="&AZG1,'Revenue Tracking'!$P$13:$P$19, "<"&AZH1) -> 0
B10: Actual + Planned Revenue - Cumulative | F10: =F9 -> 0 | G10: =F10+G9 -> 0 | H10: =G10+H9 -> 0 | I10: =H10+I9 -> 0 | J10: =I10+J9 -> 0 | K10: =J10+K9 -> 0 | L10: =K10+L9 -> 0 | M10: =L10+M9 -> 0 | N10: =M10+N9 -> 1149333.7 | ... AZG10: =AZF10+AZG9 -> 2955429.5
B11: Actual + Planned Expenditure | C11: ='Revenue Tracking'!F5 -> 2217962.2 | D11: =SUM(F11:AZG11) -> 2217962.2 | F11: =SUMIFS('Expenditure Breakdown'!$Q$6:$Q$170, 'Expenditure Breakdown'!$W$6:$W$170, ">="&F1,'Expenditure Breakdown'!$W$6:$W$170, "<"&G1) -> 0 | G11: =SUMIFS('Expenditure Breakdown'!$Q$6:$Q$170, 'Expenditure Breakdown'!$W$6:$W$170, ">="&G1,'Expenditure Breakdown'!$W$6:$W$170, "<"&H1) -> 0 | H11: =SUMIFS('Expenditure Breakdown'!$Q$6:$Q$170, 'Expenditure Breakdown'!$W$6:$W$170, ">="&H1,'Expenditure Breakdown'!$W$6:$W$170, "<"&I1) -> 0 | I11: =SUMIFS('Expenditure Breakdown'!$Q$6:$Q$170, 'Expenditure Breakdown'!$W$6:$W$170, ">="&I1,'Expenditure Breakdown'!$W$6:$W$170, "<"&J1) -> 0 | J11: =SUMIFS('Expenditure Breakdown'!$Q$6:$Q$170, 'Expenditure Breakdown'!$W$6:$W$170, ">="&J1,'Expenditure Breakdown'!$W$6:$W$170, "<"&K1) -> 0 | K11: =SUMIFS('Expenditure Breakdown'!$Q$6:$Q$170, 'Expenditure Breakdown'!$W$6:$W$170, ">="&K1,'Expenditure Breakdown'!$W$6:$W$170, "<"&L1) -> 0 | L11: =SUMIFS('Expenditure Breakdown'!$Q$6:$Q$170, 'Expenditure Breakdown'!$W$6:$W$170, ">="&L1,'Expenditure Breakdown'!$W$6:$W$170, "<"&M1) -> 0 | M11: =SUMIFS('Expenditure Breakdown'!$Q$6:$Q$170, 'Expenditure Breakdown'!$W$6:$W$170, ">="&M1,'Expenditure Breakdown'!$W$6:$W$170, "<"&N1) -> 0 | ... AZG11: =SUMIFS('Expenditure Breakdown'!$Q$6:$Q$170, 'Expenditure Breakdown'!$W$6:$W$170, ">="&AZG1,'Expenditure Breakdown'!$W$6:$W$170, "<"&AZH1) -> 0
B12: Actual + Planned Expenditure - Cumulative | F12: =F11 -> 0 | G12: =F12+G11 -> 0 | H12: =G12+H11 -> 0 | I12: =H12+I11 -> 0 | J12: =I12+J11 -> 0 | K12: =J12+K11 -> 0 | L12: =K12+L11 -> 0 | M12: =L12+M11 -> 0 | N12: =M12+N11 -> 0 | ... AZG12: =AZF12+AZG11 -> 2217962.2
B14: ACTUAL CashFlow | F14: =F10-F12 -> 0 | G14: =G10-G12 -> 0 | H14: =H10-H12 -> 0 | I14: =I10-I12 -> 0 | J14: =J10-J12 -> 0 | K14: =K10-K12 -> 0 | L14: =L10-L12 -> 0 | M14: =M10-M12 -> 0 | ... AZG14: =AZG10-AZG12 -> 737467.32
C16: CHECK | D16: CHECK
B17: Revenue Recognition | C17: =C3-D17 -> 0.00035144528 | D17: =SUM(F17:AZG17) -> 3283810.5 | F17: =SUMIFS('Expenditure Breakdown'!$U$6:$U$170, 'Expenditure Breakdown'!$T$6:$T$170, ">="&F1,'Expenditure Breakdown'!$T$6:$T$170, "<"&G1) -> 0 | G17: =SUMIFS('Expenditure Breakdown'!$U$6:$U$170, 'Expenditure Breakdown'!$T$6:$T$170, ">="&G1,'Expenditure Breakdown'!$T$6:$T$170, "<"&H1) -> 0 | H17: =SUMIFS('Expenditure Breakdown'!$U$6:$U$170, 'Expenditure Breakdown'!$T$6:$T$170, ">="&H1,'Expenditure Breakdown'!$T$6:$T$170, "<"&I1) -> 0 | I17: =SUMIFS('Expenditure Breakdown'!$U$6:$U$170, 'Expenditure Breakdown'!$T$6:$T$170, ">="&I1,'Expenditure Breakdown'!$T$6:$T$170, "<"&J1) -> 0 | J17: =SUMIFS('Expenditure Breakdown'!$U$6:$U$170, 'Expenditure Breakdown'!$T$6:$T$170, ">="&J1,'Expenditure Breakdown'!$T$6:$T$170, "<"&K1) -> 0 | K17: =SUMIFS('Expenditure Breakdown'!$U$6:$U$170, 'Expenditure Breakdown'!$T$6:$T$170, ">="&K1,'Expenditure Breakdown'!$T$6:$T$170, "<"&L1) -> 0 | L17: =SUMIFS('Expenditure Breakdown'!$U$6:$U$170, 'Expenditure Breakdown'!$T$6:$T$170, ">="&L1,'Expenditure Breakdown'!$T$6:$T$170, "<"&M1) -> 0 | M17: =SUMIFS('Expenditure Breakdown'!$U$6:$U$170, 'Expenditure Breakdown'!$T$6:$T$170, ">="&M1,'Expenditure Breakdown'!$T$6:$T$170, "<"&N1) -> 0 | ... AZG17: =SUMIFS('Expenditure Breakdown'!$U$6:$U$170, 'Expenditure Breakdown'!$T$6:$T$170, ">="&AZG1,'Expenditure Breakdown'!$T$6:$T$170, "<"&AZH1) -> 0
B18: Revenue Recognition Cumulative | C18: =D17-D18 -> 0 | D18: =MAX(F18:AZG18) -> 3283810.5 | F18: =F17 -> 0 | G18: =F18+G17 -> 0 | H18: =G18+H17 -> 0 | I18: =H18+I17 -> 0 | J18: =I18+J17 -> 0 | K18: =J18+K17 -> 0 | L18: =K18+L17 -> 0 | M18: =L18+M17 -> 0 | N18: =M18+N17 -> 0 | ... AZG18: =AZF18+AZG17 -> 3283810.5

Sheet Finance - Revenue
A3: Sum of REVENUE RECOGNITION AMOUNT | B3: Column Labels
A4: Row Labels | B4: (blank) | C4: 45930 | D4: 45961 | E4: 45991 | F4: 46022 | H4: 46053 | I4: 46081 | J4: Grand Total
A5: (blank)
A6: 1. Panels | D6: 1022028 | F6: 0 | G6: 0 | J6: 1022028
A7: 2. Inverters | D7: 256097.56 | G7: 0 | J7: 256097.56
A8: 3. Mounting Structures | C8: 178536.59 | G8: 0 | J8: 178536.59
A9: 4. DC Equipment | D9: 208528.61 | E9: 40176.494 | F9: 100441.24 | G9: 0 | J9: 349146.34
A10: 5. Monitoring | C10: 32512.603 | D10: 27243.493 | F10: 0 | G10: 0 | J10: 59756.096
A11: 6. AC Equipment | D11: 85807.281 | E11: 377343.51 | F11: 143012.13 | G11: 0 | J11: 606162.92
A12: 8. Product Add On | B12: 0 | C12: 87904.906 | D12: 151336.29 | E12: 0 | H12: 0 | J12: 239241.19
A13: 9. AC & DC installation | B13: 0 | D13: 97000 | E13: 64666.667 | F13: 161666.67 | G13: 0 | J13: 323333.33
A14: 10. Site Logistics | B14: 0 | D14: 25648.489 | E14: 17098.993 | F14: 42747.481 | G14: 0 | J14: 85494.963
A15: 11. Due Dilligence | B15: 0 | E15: 0 | G15: 0 | H15: 121444.44 | J15: 121444.44
A16: 13. Engineering | B16: 0 | H16: 35569.063 | J16: 35569.063
A17: 14. General Expenses | C17: 62.896406 | D17: 299.72249 | E17: 234.90785 | F17: 366.32477 | G17: 0 | H17: 3018.074 | I17: 3018.074 | J17: 6999.9994
A18: 15. Service Add On
A19: 12. BDP Commission
A20: 7.BESS
A21: 16. VO - XXX
A22: Grand Total | B22: 0 | C22: 299016.99 | D22: 1873989.5 | E22: 499520.57 | F22: 448233.84 | G22: 0 | H22: 160031.58 | I22: 3018.074 | J22: 3283810.5

Sheet Finance - COS
A3: Sum of Actual Total | B3: Column Labels
A4: Row Labels | B4: (blank) | C4: 45930 | D4: 45961 | E4: 45991 | F4: 46022 | H4: 46053 | I4: 46081 | J4: Grand Total
A5: (blank)
A6: 1. Panels | D6: 704365.74 | F6: 2257 | J6: 706622.74
A7: 2. Inverters | D7: 195738 | J7: 195738
A8: 3. Mounting Structures | C8: 69250 | J8: 69250
A9: 4. DC Equipment | D9: 153586.47 | E9: 29590.98 | F9: 73977.45 | J9: 257154.9
A10: 5. Monitoring | C10: 23590.5 | D10: 19974.25 | F10: 1300 | J10: 44864.75
A11: 6. AC Equipment | D11: 35067.099 | E11: 154210.02 | F11: 58445.165 | J11: 247722.28
A12: 8. Product Add On | C12: 44000 | D12: 75750 | E12: 101092.3 | H12: 10436.7 | J12: 231279
A13: 9. AC & DC installation | D13: 96375 | E13: 64250 | F13: 160625 | J13: 321250
A14: 10. Site Logistics | D14: 27718.707 | E14: 18479.138 | F14: 46197.845 | J14: 92395.69
A15: 11. Due Dilligence | B15: 0 | E15: 0 | H15: 18577.5 | J15: 18577.5
A16: 13. Engineering | H16: 41047.632 | J16: 41047.632
A17: 14. General Expenses | C17: 28.56 | D17: 37 | E17: 37 | F17: 57.12 | H17: 500 | I17: 500 | J17: 1159.68
A18: 15. Service Add On
A19: 12. BDP Commission | B19: 0 | J19: 0
A20: 7.BESS
A21: 16. VO - XXX
A22: Grand Total | B22: 0 | C22: 136869.06 | D22: 1308612.3 | E22: 367659.43 | F22: 342859.58 | H22: 70561.832 | I22: 500 | J22: 2227062.2

Sheet Project Margins
A1: [capture project margins from costing sheet]
A3: Products | D3: 0.32
A4: Services | D4: 0.5
A5: Expenses | D5: 0.15
A6: Subcontractors | D6: 0.2

Sheet Equipment Quotes
B2: Equipment Quote and Budget comparision
B4: Description | D4: Budget | F4: Supplier 1 | H4: Variance | J4: Supplier 2 | L4: Variance | N4: Comments / Notes
F7: >Name< | J7: >Name<
B9: Inverters | D9: =SUM(D10:D11) -> #REF! | F9: =SUM(F10:F13) -> 0 | H9: =$D$9-F9 -> #REF! | J9: =SUM(J10:J13) -> 0 | L9: =$D$9-J9 -> #REF!
B10: Inverters | D10: =#REF! -> #REF!
B11: Optimizers | D11: =#REF! -> #REF!
B12: Warranty
B13: Delivery fee
F15: >Name< | J15: >Name<
B17: Mounting Structure | D17: =SUM(D18:D19) -> #REF! | F17: =SUM(F18:F20) -> 0 | H17: =$D$17- F17 -> #REF! | J17: =SUM(J18:J20) -> 0 | L17: =$D$17- J17 -> #REF!
B18: Mounting Structure | D18: =#REF! -> #REF!
B19: Delivery fee
F21: >Name< | J21: >Name<
B23: DC Cable | D23: =SUM(D24:D25) -> #REF! | F23: =SUM(F24:F25) -> 0 | H23: =$D$23- F23 -> #REF! | J23: =SUM(J24:J25) -> 0 | L23: =$D$23- J23 -> #REF!
B24: DC Cable | D24: =#REF! -> #REF!
B25: Delivery fee
F27: >Name< | J27: >Name<
B29: Monitoring system | D29: =SUM(D30:D32) -> #REF! | F29: =SUM(F30:F42) -> 0 | H29: =$D$29-F29 -> #REF! | J29: =SUM(J30:J32) -> 0 | L29: =$D$29-J29 -> #REF!
B30: =#REF! -> #REF! | D30: =#REF! -> #REF!
B31: =#REF! -> #REF! | D31: =#REF! -> #REF!
B32: Delivery fee
F34: >Name< | J34: >Name<
B36: Additional Scope | D36: =SUM(D37:D41) -> #REF! | F36: =SUM(F37:F41) -> 0 | H36: =$D$29-F36 -> #REF! | J36: =SUM(J37:J41) -> 0 | L36: =$D$29-J36 -> #REF!
B37: SCADA | D37: =#REF! -> #REF!
B38: Inverter cage
B39: Cat ladders
B40: Gen Integration
B41: Lifelines
B43: Totals | D43: =D36+D29+D23+D17+D9 -> #REF! | H43: =SUM(H7:H42) -> #REF! | L43: =SUM(L7:L42) -> #REF!
B47: All amounts are incl VAT

Sheet Installer Quotes
B2: Installer Quote and Budget comparision
B4: Description | D4: Budget | G4: Cosmic Sun | J4: Variance | L4: Matthews Group | O4: Variance
B6: AC Equipment | D6: =#REF! -> #REF! | E6: =D6/(1000*'Project Plan'!$E$3) -> #REF! | G6: 277892.91 | H6: =G6/('Project Plan'!$E$3*1000) -> 0.75927025 | J6: =D6-G6 -> #REF! | M6: =L6/('Project Plan'!$E$3*1000) -> 0 | O6: =D6-L6 -> #REF!
B7: DC Equipment | D7: =#REF! -> #REF! | E7: =D7/(1000*'Project Plan'!$E$3) -> #REF! | G7: 142158.25 | H7: =G7/('Project Plan'!$E$3*1000) -> 0.38841052 | J7: =D7-G7 -> #REF! | M7: =L7/('Project Plan'!$E$3*1000) -> 0 | O7: =D7-L7 -> #REF!
B8: AC Labour | D8: =#REF! -> #REF! | E8: =D8/(1000*'Project Plan'!$E$3) -> #REF! | G8: 96174 | H8: =G8/('Project Plan'!$E$3*1000) -> 0.26277049 | J8: =D8-G8 -> #REF! | M8: =L8/('Project Plan'!$E$3*1000) -> 0 | O8: =D8-L8 -> #REF!
B9: DC Labour | D9: =#REF! -> #REF! | E9: =D9/(1000*'Project Plan'!$E$3) -> #REF! | G9: 230160 | H9: =G9/('Project Plan'!$E$3*1000) -> 0.62885246 | J9: =D9-G9 -> #REF! | M9: =L9/('Project Plan'!$E$3*1000) -> 0 | O9: =D9-L9 -> #REF!
B10: Offloading | D10: =#REF! -> #REF! | G10: 0 | J10: =D10-G10 -> #REF! | O10: =D10-L10 -> #REF!
B11: Roof Access/Scaffolding | D11: =#REF! -> #REF! | G11: 29257.61 | J11: =D11-G11 -> #REF! | O11: =D11-L11 -> #REF!
B12: Storage | D12: =#REF! -> #REF! | J12: =D12-G12 -> #REF! | O12: =D12-L12 -> #REF!
B13: Telehandler | D13: =#REF! -> #REF!
B14: HSE | D14: 0
B15: Totals | D15: =SUM(D6:D13) -> #REF! | G15: =SUM(G6:G13) -> 775642.77 | J15: =SUM(J6:J14) -> #REF! | L15: =SUM(L6:L13) -> 0 | O15: =SUM(O6:O14) -> #REF!
B18: Description | D18: Budget | G18: >Installer Name 3< | J18: Variance | L18: >Installer Name 4< | O18: Variance
B20: AC installation | D20: =#REF! -> #REF! | E20: =D20/(1000*'Project Plan'!$E$3) -> #REF! | H20: =G20/(1000*'Project Plan'!$E$3) -> 0 | J20: =D20-G20 -> #REF! | M20: =L20/(1000*'Project Plan'!$E$3) -> 0 | O20: =D6-L20 -> #REF!
B21: AC equipment | D21: =#REF! -> #REF! | E21: =D21/(1000*'Project Plan'!$E$3) -> #REF! | J21: =D21-G21 -> #REF! | M21: =L21/(1000*'Project Plan'!$E$3) -> 0 | O21: =D7-L21 -> #REF!
B22: DC installation | D22: =#REF! -> #REF! | E22: =D22/(1000*'Project Plan'!$E$3) -> #REF! | H22: =G22/(1000*'Project Plan'!$E$3) -> 0 | J22: =D22-G22 -> #REF! | M22: =L22/(1000*'Project Plan'!$E$3) -> 0 | O22: =D8-L22 -> #REF!
B23: DC equipment | D23: =SUM(#REF!) -> #REF! | E23: =D23/(1000*'Project Plan'!$E$3) -> #REF! | J23: =D23-G23 -> #REF! | O23: =D9-L23 -> #REF!
B24: Storage | D24: =#REF! -> #REF! | J24: =D24-G24 -> #REF! | O24: =D10-L24 -> #REF!
B25: Panel lifting equipment | D25: =SUM(#REF!) -> #REF! | J25: =D25-G25 -> #REF! | O25: =D11-L25 -> #REF!
B26: Offloading | D26: =#REF! -> #REF! | J26: =D26-G26 -> #REF! | O26: =D12-L26 -> #REF!
B29: Totals | D29: =SUM(D20:D27) -> #REF! | G29: =SUM(G20:G27) -> 0 | J29: =SUM(J20:J28) -> #REF! | L29: =SUM(L20:L27) -> 0 | O29: =SUM(O20:O28) -> #REF!
B32: Budget Summary
B34: Budget | D34: =D15 -> #REF!
B35: =G4 -> Cosmic Sun | D35: =G15 -> 775642.77
B36: =L4 -> Matthews Group | D36: =L15 -> 0
B37: =G18 -> >Installer Name 3< | D37: =G29 -> 0
B38: =L18 -> >Installer Name 4< | D38: =L29 -> 0
B40: =IF(D40<D34,"Saving","Loss") -> #REF! | D40: =D34-MIN(D35:D38) -> #REF!
B42: All amounts are exc VAT

Sheet Decision Register
B1: =D15 -> 1 Bolt Ave | E1: Decision Register
B3: ID | C3: Decision Description | D3: Decision Impact | E3: Proposed Date | F3: Proposed By | G3: Status | H3: Approved By | I3: Date | J3: Results / Comments
B4: DEC001
B5: DEC002
B6: DEC003
B7: DEC004
B8: DEC005
B9: DEC006
B10: DEC007
B11: DEC008
B12: DEC009
B13: DEC010
D15: {='Project Plan'!E2:H2} -> 1 Bolt Ave | E15: 0 | F15: 0 | G15: 0
