Workbook
Name Inverter_Capacity: #REF!
Name Inverter_Supplier: #REF!
Name Project_Size: Compliance!Projectsize
Name Project_Size: 'Finance - Revenue'!Projectsize
Name Project_Size: Projectsize
Name Projectsize: #REF!
Name Projectsize: #REF!
Name Projectsize: 'Project Margins'!$K$5
Name Security_Serv: #REF!
Name Security_Serv: #REF!
Name SSS: #REF!
Name SSS: #REF!
Name USD_ZAR: #REF!

Sheet Sheet1
A1: PROJECT PLAN
A2: # | B2: Project Milestone | C2: Planned Start Date | D2: Duration (Work Days) | E2: Planned End Date | F2: Actual Start Date | H2: Actual End Date | J2: Comments | L2: =C3 -> 43831 | M2: =L2+3 -> 43834 | N2: =M2+7 -> 43841 | O2: =N2+7 -> 43848 | P2: =O2+7 -> 43855 | Q2: =P2+6 -> 43861 | R2: =Q2+1 -> 43862 | S2: =R2+7 -> 43869 | T2: =S2+7 -> 43876 | U2: =T2+7 -> 43883 | V2: =U2+6 -> 43889 | W2: =V2+7 -> 43896 | X2: =W2+7 -> 43903 | Y2: =X2+7 -> 43910 | Z2: =Y2+7 -> 43917 | AA2: =Z2+3 -> 43920 | AB2: =AA2+4 -> 43924 | AC2: =AB2+7 -> 43931 | AD2: =AC2+7 -> 43938 | AE2: =AD2+7 -> 43945 | AF2: =AE2+6 -> 43951 | AG2: =AF2+2 -> 43953 | AH2: =AG2+7 -> 43960 | AI2: =AH2+7 -> 43967 | AJ2: =AI2+7 -> 43974 | AK2: =AJ2+7 -> 43981 | AL2: =AK2+1 -> 43982 | AM2: =AL2+6 -> 43988 | AN2: =AM2+7 -> 43995 | AO2: =AN2+7 -> 44002 | AP2: =AO2+7 -> 44009 | AQ2: =AP2+3 -> 44012 | AR2: =AQ2+4 -> 44016 | AS2: =AR2+7 -> 44023 | AT2: =AS2+7 -> 44030 | AU2: =AT2+7 -> 44037 | AV2: =AU2+6 -> 44043 | AW2: =AV2+1 -> 44044 | AX2: =AW2+7 -> 44051 | AY2: =AX2+7 -> 44058 | AZ2: =AY2+7 -> 44065 | BA2: =AZ2+7 -> 44072 | BB2: =BA2+2 -> 44074 | BC2: =BB2+5 -> 44079 | BD2: =BC2+7 -> 44086 | BE2: =BD2+7 -> 44093 | BF2: =BE2+7 -> 44100 | BG2: =BF2+4 -> 44104
A3: 1 | B3: Contract Signature | C3: 43831 | D3: 1 | E3: 43832 | F3: 43831 | G3: 1 | H3: 43832 | L3: =IF(AND($F3<(L$2+7),$F3>L$2),1, IF(AND($H3<L$2+7,$H3>L$2),3, IF(AND($F3<=L$2, $H3>=L$2), 2, "" ))) -> 3 | M3: =IF(AND($F3<(M$2+7),$F3>M$2),1, IF(AND($H3<M$2+7,$H3>M$2),3, IF(AND($F3<=M$2, $H3>=M$2), 2, "" ))) | N3: =IF(AND($F3<(N$2+7),$F3>N$2),1, IF(AND($H3<N$2+7,$H3>N$2),3, IF(AND($F3<=N$2, $H3>=N$2), 2, "" ))) | O3: =IF(AND($F3<(O$2+7),$F3>O$2),1, IF(AND($H3<O$2+7,$H3>O$2),3, IF(AND($F3<=O$2, $H3>=O$2), 2, "" ))) | P3: =IF(AND($F3<(P$2+7),$F3>P$2),1, IF(AND($H3<P$2+7,$H3>P$2),3, IF(AND($F3<=P$2, $H3>=P$2), 2, "" ))) | Q3: =IF(AND($F3<(Q$2+7),$F3>Q$2),1, IF(AND($H3<Q$2+7,$H3>Q$2),3, IF(AND($F3<=Q$2, $H3>=Q$2), 2, "" ))) | R3: =IF(AND($F3<(R$2+7),$F3>R$2),1, IF(AND($H3<R$2+7,$H3>R$2),3, IF(AND($F3<=R$2, $H3>=R$2), 2, "" ))) | S3: =IF(AND($F3<(S$2+7),$F3>S$2),1, IF(AND($H3<S$2+7,$H3>S$2),3, IF(AND($F3<=S$2, $H3>=S$2), 2, "" ))) | ... AQ3: =IF(AND($F3<(AQ$2+7),$F3>AQ$2),1, IF(AND($H3<AQ$2+7,$H3>AQ$2),3, IF(AND($F3<=AQ$2, $H3>=AQ$2), 2, "" )))
A4: A | B4: PAYMENT MILESTONE 1: DEPOSIT | C4: 43832 | D4: 1 | E4: 43833 | F4: 43832 | G4: 1 | H4: 43833 | L4: =IF(AND($F4<(L$2+7),$F4>L$2),1, IF(AND($H4<L$2+7,$H4>L$2),3, IF(AND($F4<=L$2, $H4>=L$2), 2, "" ))) -> 1 | M4: =IF(AND($F4<(M$2+7),$F4>M$2),1, IF(AND($H4<M$2+7,$H4>M$2),3, IF(AND($F4<=M$2, $H4>=M$2), 2, "" ))) | N4: =IF(AND($F4<(N$2+7),$F4>N$2),1, IF(AND($H4<N$2+7,$H4>N$2),3, IF(AND($F4<=N$2, $H4>=N$2), 2, "" ))) | O4: =IF(AND($F4<(O$2+7),$F4>O$2),1, IF(AND($H4<O$2+7,$H4>O$2),3, IF(AND($F4<=O$2, $H4>=O$2), 2, "" ))) | P4: =IF(AND($F4<(P$2+7),$F4>P$2),1, IF(AND($H4<P$2+7,$H4>P$2),3, IF(AND($F4<=P$2, $H4>=P$2), 2, "" ))) | Q4: =IF(AND($F4<(Q$2+7),$F4>Q$2),1, IF(AND($H4<Q$2+7,$H4>Q$2),3, IF(AND($F4<=Q$2, $H4>=Q$2), 2, "" ))) | R4: =IF(AND($F4<(R$2+7),$F4>R$2),1, IF(AND($H4<R$2+7,$H4>R$2),3, IF(AND($F4<=R$2, $H4>=R$2), 2, "" ))) | S4: =IF(AND($F4<(S$2+7),$F4>S$2),1, IF(AND($H4<S$2+7,$H4>S$2),3, IF(AND($F4<=S$2, $H4>=S$2), 2, "" ))) | ... AQ4: =IF(AND($F4<(AQ$2+7),$F4>AQ$2),1, IF(AND($H4<AQ$2+7,$H4>AQ$2),3, IF(AND($F4<=AQ$2, $H4>=AQ$2), 2, "" )))
A5: 2 | B5: Structural and Electrical Due Diligences | C5: 43833 | D5: 5 | E5: 43840 | F5: 43833 | G5: 5 | H5: 43840 | L5: =IF(AND($F5<(L$2+7),$F5>L$2),1, IF(AND($H5<L$2+7,$H5>L$2),3, IF(AND($F5<=L$2, $H5>=L$2), 2, "" ))) -> 1 | M5: =IF(AND($F5<(M$2+7),$F5>M$2),1, IF(AND($H5<M$2+7,$H5>M$2),3, IF(AND($F5<=M$2, $H5>=M$2), 2, "" ))) -> 3 | N5: =IF(AND($F5<(N$2+7),$F5>N$2),1, IF(AND($H5<N$2+7,$H5>N$2),3, IF(AND($F5<=N$2, $H5>=N$2), 2, "" ))) | O5: =IF(AND($F5<(O$2+7),$F5>O$2),1, IF(AND($H5<O$2+7,$H5>O$2),3, IF(AND($F5<=O$2, $H5>=O$2), 2, "" ))) | P5: =IF(AND($F5<(P$2+7),$F5>P$2),1, IF(AND($H5<P$2+7,$H5>P$2),3, IF(AND($F5<=P$2, $H5>=P$2), 2, "" ))) | Q5: =IF(AND($F5<(Q$2+7),$F5>Q$2),1, IF(AND($H5<Q$2+7,$H5>Q$2),3, IF(AND($F5<=Q$2, $H5>=Q$2), 2, "" ))) | R5: =IF(AND($F5<(R$2+7),$F5>R$2),1, IF(AND($H5<R$2+7,$H5>R$2),3, IF(AND($F5<=R$2, $H5>=R$2), 2, "" ))) | S5: =IF(AND($F5<(S$2+7),$F5>S$2),1, IF(AND($H5<S$2+7,$H5>S$2),3, IF(AND($F5<=S$2, $H5>=S$2), 2, "" ))) | ... AQ5: =IF(AND($F5<(AQ$2+7),$F5>AQ$2),1, IF(AND($H5<AQ$2+7,$H5>AQ$2),3, IF(AND($F5<=AQ$2, $H5>=AQ$2), 2, "" )))
A6: 3 | B6: Design Confirmation | C6: 43841 | D6: 2 | E6: 43844 | F6: 43841 | G6: 2 | H6: 43844 | L6: =IF(AND($F6<(L$2+7),$F6>L$2),1, IF(AND($H6<L$2+7,$H6>L$2),3, IF(AND($F6<=L$2, $H6>=L$2), 2, "" ))) | M6: =IF(AND($F6<(M$2+7),$F6>M$2),1, IF(AND($H6<M$2+7,$H6>M$2),3, IF(AND($F6<=M$2, $H6>=M$2), 2, "" ))) | N6: =IF(AND($F6<(N$2+7),$F6>N$2),1, IF(AND($H6<N$2+7,$H6>N$2),3, IF(AND($F6<=N$2, $H6>=N$2), 2, "" ))) -> 3 | O6: =IF(AND($F6<(O$2+7),$F6>O$2),1, IF(AND($H6<O$2+7,$H6>O$2),3, IF(AND($F6<=O$2, $H6>=O$2), 2, "" ))) | P6: =IF(AND($F6<(P$2+7),$F6>P$2),1, IF(AND($H6<P$2+7,$H6>P$2),3, IF(AND($F6<=P$2, $H6>=P$2), 2, "" ))) | Q6: =IF(AND($F6<(Q$2+7),$F6>Q$2),1, IF(AND($H6<Q$2+7,$H6>Q$2),3, IF(AND($F6<=Q$2, $H6>=Q$2), 2, "" ))) | R6: =IF(AND($F6<(R$2+7),$F6>R$2),1, IF(AND($H6<R$2+7,$H6>R$2),3, IF(AND($F6<=R$2, $H6>=R$2), 2, "" ))) | S6: =IF(AND($F6<(S$2+7),$F6>S$2),1, IF(AND($H6<S$2+7,$H6>S$2),3, IF(AND($F6<=S$2, $H6>=S$2), 2, "" ))) | ... AQ6: =IF(AND($F6<(AQ$2+7),$F6>AQ$2),1, IF(AND($H6<AQ$2+7,$H6>AQ$2),3, IF(AND($F6<=AQ$2, $H6>=AQ$2), 2, "" )))
A7: 4 | B7: Equipment Procurement | C7: 43833 | E7: 43949 | F7: 43833 | H7: 43949 | L7: =IF(AND($F7<(L$2+7),$F7>L$2),1, IF(AND($H7<L$2+7,$H7>L$2),3, IF(AND($F7<=L$2, $H7>=L$2), 2, "" ))) -> 1 | M7: =IF(AND($F7<(M$2+7),$F7>M$2),1, IF(AND($H7<M$2+7,$H7>M$2),3, IF(AND($F7<=M$2, $H7>=M$2), 2, "" ))) -> 2 | N7: =IF(AND($F7<(N$2+7),$F7>N$2),1, IF(AND($H7<N$2+7,$H7>N$2),3, IF(AND($F7<=N$2, $H7>=N$2), 2, "" ))) -> 2 | O7: =IF(AND($F7<(O$2+7),$F7>O$2),1, IF(AND($H7<O$2+7,$H7>O$2),3, IF(AND($F7<=O$2, $H7>=O$2), 2, "" ))) -> 2 | P7: =IF(AND($F7<(P$2+7),$F7>P$2),1, IF(AND($H7<P$2+7,$H7>P$2),3, IF(AND($F7<=P$2, $H7>=P$2), 2, "" ))) -> 2 | Q7: =IF(AND($F7<(Q$2+7),$F7>Q$2),1, IF(AND($H7<Q$2+7,$H7>Q$2),3, IF(AND($F7<=Q$2, $H7>=Q$2), 2, "" ))) -> 2 | R7: =IF(AND($F7<(R$2+7),$F7>R$2),1, IF(AND($H7<R$2+7,$H7>R$2),3, IF(AND($F7<=R$2, $H7>=R$2), 2, "" ))) -> 2 | S7: =IF(AND($F7<(S$2+7),$F7>S$2),1, IF(AND($H7<S$2+7,$H7>S$2),3, IF(AND($F7<=S$2, $H7>=S$2), 2, "" ))) -> 2 | ... AQ7: =IF(AND($F7<(AQ$2+7),$F7>AQ$2),1, IF(AND($H7<AQ$2+7,$H7>AQ$2),3, IF(AND($F7<=AQ$2, $H7>=AQ$2), 2, "" )))
B8: Panel Procurement | C8: 43833 | D8: 5 | E8: 43840 | F8: 43833 | G8: 5 | H8: 43840 | L8: =IF(AND($F8<(L$2+7),$F8>L$2),1, IF(AND($H8<L$2+7,$H8>L$2),3, IF(AND($F8<=L$2, $H8>=L$2), 2, "" ))) -> 1 | M8: =IF(AND($F8<(M$2+7),$F8>M$2),1, IF(AND($H8<M$2+7,$H8>M$2),3, IF(AND($F8<=M$2, $H8>=M$2), 2, "" ))) -> 3 | N8: =IF(AND($F8<(N$2+7),$F8>N$2),1, IF(AND($H8<N$2+7,$H8>N$2),3, IF(AND($F8<=N$2, $H8>=N$2), 2, "" ))) | O8: =IF(AND($F8<(O$2+7),$F8>O$2),1, IF(AND($H8<O$2+7,$H8>O$2),3, IF(AND($F8<=O$2, $H8>=O$2), 2, "" ))) | P8: =IF(AND($F8<(P$2+7),$F8>P$2),1, IF(AND($H8<P$2+7,$H8>P$2),3, IF(AND($F8<=P$2, $H8>=P$2), 2, "" ))) | Q8: =IF(AND($F8<(Q$2+7),$F8>Q$2),1, IF(AND($H8<Q$2+7,$H8>Q$2),3, IF(AND($F8<=Q$2, $H8>=Q$2), 2, "" ))) | R8: =IF(AND($F8<(R$2+7),$F8>R$2),1, IF(AND($H8<R$2+7,$H8>R$2),3, IF(AND($F8<=R$2, $H8>=R$2), 2, "" ))) | S8: =IF(AND($F8<(S$2+7),$F8>S$2),1, IF(AND($H8<S$2+7,$H8>S$2),3, IF(AND($F8<=S$2, $H8>=S$2), 2, "" ))) | ... AQ8: =IF(AND($F8<(AQ$2+7),$F8>AQ$2),1, IF(AND($H8<AQ$2+7,$H8>AQ$2),3, IF(AND($F8<=AQ$2, $H8>=AQ$2), 2, "" )))
B9: Inverter Procurement | C9: 43941 | D9: 5 | E9: 43949 | F9: 43941 | G9: 5 | H9: 43949 | L9: =IF(AND($F9<(L$2+7),$F9>L$2),1, IF(AND($H9<L$2+7,$H9>L$2),3, IF(AND($F9<=L$2, $H9>=L$2), 2, "" ))) | M9: =IF(AND($F9<(M$2+7),$F9>M$2),1, IF(AND($H9<M$2+7,$H9>M$2),3, IF(AND($F9<=M$2, $H9>=M$2), 2, "" ))) | N9: =IF(AND($F9<(N$2+7),$F9>N$2),1, IF(AND($H9<N$2+7,$H9>N$2),3, IF(AND($F9<=N$2, $H9>=N$2), 2, "" ))) | O9: =IF(AND($F9<(O$2+7),$F9>O$2),1, IF(AND($H9<O$2+7,$H9>O$2),3, IF(AND($F9<=O$2, $H9>=O$2), 2, "" ))) | P9: =IF(AND($F9<(P$2+7),$F9>P$2),1, IF(AND($H9<P$2+7,$H9>P$2),3, IF(AND($F9<=P$2, $H9>=P$2), 2, "" ))) | Q9: =IF(AND($F9<(Q$2+7),$F9>Q$2),1, IF(AND($H9<Q$2+7,$H9>Q$2),3, IF(AND($F9<=Q$2, $H9>=Q$2), 2, "" ))) | R9: =IF(AND($F9<(R$2+7),$F9>R$2),1, IF(AND($H9<R$2+7,$H9>R$2),3, IF(AND($F9<=R$2, $H9>=R$2), 2, "" ))) | S9: =IF(AND($F9<(S$2+7),$F9>S$2),1, IF(AND($H9<S$2+7,$H9>S$2),3, IF(AND($F9<=S$2, $H9>=S$2), 2, "" ))) | ... AQ9: =IF(AND($F9<(AQ$2+7),$F9>AQ$2),1, IF(AND($H9<AQ$2+7,$H9>AQ$2),3, IF(AND($F9<=AQ$2, $H9>=AQ$2), 2, "" )))
B10: Mounting Structure Procurement | C10: 43941 | D10: 5 | E10: 43949 | F10: 43941 | G10: 5 | H10: 43949 | L10: =IF(AND($F10<(L$2+7),$F10>L$2),1, IF(AND($H10<L$2+7,$H10>L$2),3, IF(AND($F10<=L$2, $H10>=L$2), 2, "" ))) | M10: =IF(AND($F10<(M$2+7),$F10>M$2),1, IF(AND($H10<M$2+7,$H10>M$2),3, IF(AND($F10<=M$2, $H10>=M$2), 2, "" ))) | N10: =IF(AND($F10<(N$2+7),$F10>N$2),1, IF(AND($H10<N$2+7,$H10>N$2),3, IF(AND($F10<=N$2, $H10>=N$2), 2, "" ))) | O10: =IF(AND($F10<(O$2+7),$F10>O$2),1, IF(AND($H10<O$2+7,$H10>O$2),3, IF(AND($F10<=O$2, $H10>=O$2), 2, "" ))) | P10: =IF(AND($F10<(P$2+7),$F10>P$2),1, IF(AND($H10<P$2+7,$H10>P$2),3, IF(AND($F10<=P$2, $H10>=P$2), 2, "" ))) | Q10: =IF(AND($F10<(Q$2+7),$F10>Q$2),1, IF(AND($H10<Q$2+7,$H10>Q$2),3, IF(AND($F10<=Q$2, $H10>=Q$2), 2, "" ))) | R10: =IF(AND($F10<(R$2+7),$F10>R$2),1, IF(AND($H10<R$2+7,$H10>R$2),3, IF(AND($F10<=R$2, $H10>=R$2), 2, "" ))) | S10: =IF(AND($F10<(S$2+7),$F10>S$2),1, IF(AND($H10<S$2+7,$H10>S$2),3, IF(AND($F10<=S$2, $H10>=S$2), 2, "" ))) | ... AQ10: =IF(AND($F10<(AQ$2+7),$F10>AQ$2),1, IF(AND($H10<AQ$2+7,$H10>AQ$2),3, IF(AND($F10<=AQ$2, $H10>=AQ$2), 2, "" )))
B11: BOS Procurement | C11: 43941 | D11: 5 | E11: 43949 | F11: 43941 | G11: 5 | H11: 43949 | L11: =IF(AND($F11<(L$2+7),$F11>L$2),1, IF(AND($H11<L$2+7,$H11>L$2),3, IF(AND($F11<=L$2, $H11>=L$2), 2, "" ))) | M11: =IF(AND($F11<(M$2+7),$F11>M$2),1, IF(AND($H11<M$2+7,$H11>M$2),3, IF(AND($F11<=M$2, $H11>=M$2), 2, "" ))) | N11: =IF(AND($F11<(N$2+7),$F11>N$2),1, IF(AND($H11<N$2+7,$H11>N$2),3, IF(AND($F11<=N$2, $H11>=N$2), 2, "" ))) | O11: =IF(AND($F11<(O$2+7),$F11>O$2),1, IF(AND($H11<O$2+7,$H11>O$2),3, IF(AND($F11<=O$2, $H11>=O$2), 2, "" ))) | P11: =IF(AND($F11<(P$2+7),$F11>P$2),1, IF(AND($H11<P$2+7,$H11>P$2),3, IF(AND($F11<=P$2, $H11>=P$2), 2, "" ))) | Q11: =IF(AND($F11<(Q$2+7),$F11>Q$2),1, IF(AND($H11<Q$2+7,$H11>Q$2),3, IF(AND($F11<=Q$2, $H11>=Q$2), 2, "" ))) | R11: =IF(AND($F11<(R$2+7),$F11>R$2),1, IF(AND($H11<R$2+7,$H11>R$2),3, IF(AND($F11<=R$2, $H11>=R$2), 2, "" ))) | S11: =IF(AND($F11<(S$2+7),$F11>S$2),1, IF(AND($H11<S$2+7,$H11>S$2),3, IF(AND($F11<=S$2, $H11>=S$2), 2, "" ))) | ... AQ11: =IF(AND($F11<(AQ$2+7),$F11>AQ$2),1, IF(AND($H11<AQ$2+7,$H11>AQ$2),3, IF(AND($F11<=AQ$2, $H11>=AQ$2), 2, "" )))
A12: 5 | B12: Internal Project Kick off | C12: 43936 | D12: 5 | E12: 43943 | F12: 43936 | G12: 5 | H12: 43943
A13: 6 | B13: Client Project Kick-off | C13: 43963 | D13: 5 | E13: 43970 | F13: 43963 | G13: 5 | H13: 43970 | L13: =IF(AND($F13<(L$2+7),$F13>L$2),1, IF(AND($H13<L$2+7,$H13>L$2),3, IF(AND($F13<=L$2, $H13>=L$2), 2, "" ))) | M13: =IF(AND($F13<(M$2+7),$F13>M$2),1, IF(AND($H13<M$2+7,$H13>M$2),3, IF(AND($F13<=M$2, $H13>=M$2), 2, "" ))) | N13: =IF(AND($F13<(N$2+7),$F13>N$2),1, IF(AND($H13<N$2+7,$H13>N$2),3, IF(AND($F13<=N$2, $H13>=N$2), 2, "" ))) | O13: =IF(AND($F13<(O$2+7),$F13>O$2),1, IF(AND($H13<O$2+7,$H13>O$2),3, IF(AND($F13<=O$2, $H13>=O$2), 2, "" ))) | P13: =IF(AND($F13<(P$2+7),$F13>P$2),1, IF(AND($H13<P$2+7,$H13>P$2),3, IF(AND($F13<=P$2, $H13>=P$2), 2, "" ))) | Q13: =IF(AND($F13<(Q$2+7),$F13>Q$2),1, IF(AND($H13<Q$2+7,$H13>Q$2),3, IF(AND($F13<=Q$2, $H13>=Q$2), 2, "" ))) | R13: =IF(AND($F13<(R$2+7),$F13>R$2),1, IF(AND($H13<R$2+7,$H13>R$2),3, IF(AND($F13<=R$2, $H13>=R$2), 2, "" ))) | S13: =IF(AND($F13<(S$2+7),$F13>S$2),1, IF(AND($H13<S$2+7,$H13>S$2),3, IF(AND($F13<=S$2, $H13>=S$2), 2, "" ))) | ... AQ13: =IF(AND($F13<(AQ$2+7),$F13>AQ$2),1, IF(AND($H13<AQ$2+7,$H13>AQ$2),3, IF(AND($F13<=AQ$2, $H13>=AQ$2), 2, "" )))
A14: 7 | B14: Equipment Delivery | C14: 43983 | D14: 9 | E14: 43994 | F14: 43983 | G14: 9 | H14: 43994 | L14: =IF(AND($F14<(L$2+7),$F14>L$2),1, IF(AND($H14<L$2+7,$H14>L$2),3, IF(AND($F14<=L$2, $H14>=L$2), 2, "" ))) | M14: =IF(AND($F14<(M$2+7),$F14>M$2),1, IF(AND($H14<M$2+7,$H14>M$2),3, IF(AND($F14<=M$2, $H14>=M$2), 2, "" ))) | N14: =IF(AND($F14<(N$2+7),$F14>N$2),1, IF(AND($H14<N$2+7,$H14>N$2),3, IF(AND($F14<=N$2, $H14>=N$2), 2, "" ))) | O14: =IF(AND($F14<(O$2+7),$F14>O$2),1, IF(AND($H14<O$2+7,$H14>O$2),3, IF(AND($F14<=O$2, $H14>=O$2), 2, "" ))) | P14: =IF(AND($F14<(P$2+7),$F14>P$2),1, IF(AND($H14<P$2+7,$H14>P$2),3, IF(AND($F14<=P$2, $H14>=P$2), 2, "" ))) | Q14: =IF(AND($F14<(Q$2+7),$F14>Q$2),1, IF(AND($H14<Q$2+7,$H14>Q$2),3, IF(AND($F14<=Q$2, $H14>=Q$2), 2, "" ))) | R14: =IF(AND($F14<(R$2+7),$F14>R$2),1, IF(AND($H14<R$2+7,$H14>R$2),3, IF(AND($F14<=R$2, $H14>=R$2), 2, "" ))) | S14: =IF(AND($F14<(S$2+7),$F14>S$2),1, IF(AND($H14<S$2+7,$H14>S$2),3, IF(AND($F14<=S$2, $H14>=S$2), 2, "" ))) | ... AQ14: =IF(AND($F14<(AQ$2+7),$F14>AQ$2),1, IF(AND($H14<AQ$2+7,$H14>AQ$2),3, IF(AND($F14<=AQ$2, $H14>=AQ$2), 2, "" )))
B15: Mounting Structure Delivery | C15: 43983 | D15: 2 | E15: 43985 | F15: 43983 | G15: 2 | H15: 43985
B16: Panel Delivery | C16: 43990 | D16: 2 | E16: 43992 | F16: 43990 | G16: 2 | H16: 43992 | L16: =IF(AND($F16<(L$2+7),$F16>L$2),1, IF(AND($H16<L$2+7,$H16>L$2),3, IF(AND($F16<=L$2, $H16>=L$2), 2, "" ))) | M16: =IF(AND($F16<(M$2+7),$F16>M$2),1, IF(AND($H16<M$2+7,$H16>M$2),3, IF(AND($F16<=M$2, $H16>=M$2), 2, "" ))) | N16: =IF(AND($F16<(N$2+7),$F16>N$2),1, IF(AND($H16<N$2+7,$H16>N$2),3, IF(AND($F16<=N$2, $H16>=N$2), 2, "" ))) | O16: =IF(AND($F16<(O$2+7),$F16>O$2),1, IF(AND($H16<O$2+7,$H16>O$2),3, IF(AND($F16<=O$2, $H16>=O$2), 2, "" ))) | P16: =IF(AND($F16<(P$2+7),$F16>P$2),1, IF(AND($H16<P$2+7,$H16>P$2),3, IF(AND($F16<=P$2, $H16>=P$2), 2, "" ))) | Q16: =IF(AND($F16<(Q$2+7),$F16>Q$2),1, IF(AND($H16<Q$2+7,$H16>Q$2),3, IF(AND($F16<=Q$2, $H16>=Q$2), 2, "" ))) | R16: =IF(AND($F16<(R$2+7),$F16>R$2),1, IF(AND($H16<R$2+7,$H16>R$2),3, IF(AND($F16<=R$2, $H16>=R$2), 2, "" ))) | S16: =IF(AND($F16<(S$2+7),$F16>S$2),1, IF(AND($H16<S$2+7,$H16>S$2),3, IF(AND($F16<=S$2, $H16>=S$2), 2, "" ))) | ... AQ16: =IF(AND($F16<(AQ$2+7),$F16>AQ$2),1, IF(AND($H16<AQ$2+7,$H16>AQ$2),3, IF(AND($F16<=AQ$2, $H16>=AQ$2), 2, "" )))
B17: Generator Delivery | C17: 43983 | D17: 2 | E17: 43985 | F17: 43983 | G17: 2 | H17: 43985
A18: B | B18: PAYMENT MILESTONE 2: DELIVERY OF PV PANELS | C18: 43992 | D18: 2 | E18: 43994 | F18: 43992 | G18: 2 | H18: 43994
B19: Inverter Delivery | C19: 43983 | D19: 2 | E19: 43985 | F19: 43983 | G19: 2 | H19: 43985 | L19: =IF(AND($F19<(L$2+7),$F19>L$2),1, IF(AND($H19<L$2+7,$H19>L$2),3, IF(AND($F19<=L$2, $H19>=L$2), 2, "" ))) | M19: =IF(AND($F19<(M$2+7),$F19>M$2),1, IF(AND($H19<M$2+7,$H19>M$2),3, IF(AND($F19<=M$2, $H19>=M$2), 2, "" ))) | N19: =IF(AND($F19<(N$2+7),$F19>N$2),1, IF(AND($H19<N$2+7,$H19>N$2),3, IF(AND($F19<=N$2, $H19>=N$2), 2, "" ))) | O19: =IF(AND($F19<(O$2+7),$F19>O$2),1, IF(AND($H19<O$2+7,$H19>O$2),3, IF(AND($F19<=O$2, $H19>=O$2), 2, "" ))) | P19: =IF(AND($F19<(P$2+7),$F19>P$2),1, IF(AND($H19<P$2+7,$H19>P$2),3, IF(AND($F19<=P$2, $H19>=P$2), 2, "" ))) | Q19: =IF(AND($F19<(Q$2+7),$F19>Q$2),1, IF(AND($H19<Q$2+7,$H19>Q$2),3, IF(AND($F19<=Q$2, $H19>=Q$2), 2, "" ))) | R19: =IF(AND($F19<(R$2+7),$F19>R$2),1, IF(AND($H19<R$2+7,$H19>R$2),3, IF(AND($F19<=R$2, $H19>=R$2), 2, "" ))) | S19: =IF(AND($F19<(S$2+7),$F19>S$2),1, IF(AND($H19<S$2+7,$H19>S$2),3, IF(AND($F19<=S$2, $H19>=S$2), 2, "" ))) | ... AQ19: =IF(AND($F19<(AQ$2+7),$F19>AQ$2),1, IF(AND($H19<AQ$2+7,$H19>AQ$2),3, IF(AND($F19<=AQ$2, $H19>=AQ$2), 2, "" )))
B20: BOS Delivery | C20: 43983 | D20: 1 | E20: 43984 | F20: 43983 | G20: 1 | H20: 43984 | L20: =IF(AND($F20<(L$2+7),$F20>L$2),1, IF(AND($H20<L$2+7,$H20>L$2),3, IF(AND($F20<=L$2, $H20>=L$2), 2, "" ))) | M20: =IF(AND($F20<(M$2+7),$F20>M$2),1, IF(AND($H20<M$2+7,$H20>M$2),3, IF(AND($F20<=M$2, $H20>=M$2), 2, "" ))) | N20: =IF(AND($F20<(N$2+7),$F20>N$2),1, IF(AND($H20<N$2+7,$H20>N$2),3, IF(AND($F20<=N$2, $H20>=N$2), 2, "" ))) | O20: =IF(AND($F20<(O$2+7),$F20>O$2),1, IF(AND($H20<O$2+7,$H20>O$2),3, IF(AND($F20<=O$2, $H20>=O$2), 2, "" ))) | P20: =IF(AND($F20<(P$2+7),$F20>P$2),1, IF(AND($H20<P$2+7,$H20>P$2),3, IF(AND($F20<=P$2, $H20>=P$2), 2, "" ))) | Q20: =IF(AND($F20<(Q$2+7),$F20>Q$2),1, IF(AND($H20<Q$2+7,$H20>Q$2),3, IF(AND($F20<=Q$2, $H20>=Q$2), 2, "" ))) | R20: =IF(AND($F20<(R$2+7),$F20>R$2),1, IF(AND($H20<R$2+7,$H20>R$2),3, IF(AND($F20<=R$2, $H20>=R$2), 2, "" ))) | S20: =IF(AND($F20<(S$2+7),$F20>S$2),1, IF(AND($H20<S$2+7,$H20>S$2),3, IF(AND($F20<=S$2, $H20>=S$2), 2, "" ))) | ... AQ20: =IF(AND($F20<(AQ$2+7),$F20>AQ$2),1, IF(AND($H20<AQ$2+7,$H20>AQ$2),3, IF(AND($F20<=AQ$2, $H20>=AQ$2), 2, "" )))
A21: C | B21: PAYMENT MILESTONE 3: DELIVERY OF INVERTERS AND BOS | C21: 43985 | D21: 2 | E21: 43987 | F21: 43985 | G21: 2 | H21: 43987
A22: 8 | B22: Installation | C22: 43990 | D22: 22 | E22: 44012 | F22: 43990 | G22: 22 | H22: 44012 | L22: =IF(AND($F22<(L$2+7),$F22>L$2),1, IF(AND($H22<L$2+7,$H22>L$2),3, IF(AND($F22<=L$2, $H22>=L$2), 2, "" ))) | M22: =IF(AND($F22<(M$2+7),$F22>M$2),1, IF(AND($H22<M$2+7,$H22>M$2),3, IF(AND($F22<=M$2, $H22>=M$2), 2, "" ))) | N22: =IF(AND($F22<(N$2+7),$F22>N$2),1, IF(AND($H22<N$2+7,$H22>N$2),3, IF(AND($F22<=N$2, $H22>=N$2), 2, "" ))) | O22: =IF(AND($F22<(O$2+7),$F22>O$2),1, IF(AND($H22<O$2+7,$H22>O$2),3, IF(AND($F22<=O$2, $H22>=O$2), 2, "" ))) | P22: =IF(AND($F22<(P$2+7),$F22>P$2),1, IF(AND($H22<P$2+7,$H22>P$2),3, IF(AND($F22<=P$2, $H22>=P$2), 2, "" ))) | Q22: =IF(AND($F22<(Q$2+7),$F22>Q$2),1, IF(AND($H22<Q$2+7,$H22>Q$2),3, IF(AND($F22<=Q$2, $H22>=Q$2), 2, "" ))) | R22: =IF(AND($F22<(R$2+7),$F22>R$2),1, IF(AND($H22<R$2+7,$H22>R$2),3, IF(AND($F22<=R$2, $H22>=R$2), 2, "" ))) | S22: =IF(AND($F22<(S$2+7),$F22>S$2),1, IF(AND($H22<S$2+7,$H22>S$2),3, IF(AND($F22<=S$2, $H22>=S$2), 2, "" ))) | ... AQ22: =IF(AND($F22<(AQ$2+7),$F22>AQ$2),1, IF(AND($H22<AQ$2+7,$H22>AQ$2),3, IF(AND($F22<=AQ$2, $H22>=AQ$2), 2, "" ))) -> 2
B23: Site Establishment | C23: 43990 | D23: 1 | E23: 43991 | F23: 43990 | G23: 1 | H23: 43991 | J23: Installation placed on hold due to Covid-19 case | L23: =IF(AND($F23<(L$2+7),$F23>L$2),1, IF(AND($H23<L$2+7,$H23>L$2),3, IF(AND($F23<=L$2, $H23>=L$2), 2, "" ))) | M23: =IF(AND($F23<(M$2+7),$F23>M$2),1, IF(AND($H23<M$2+7,$H23>M$2),3, IF(AND($F23<=M$2, $H23>=M$2), 2, "" ))) | N23: =IF(AND($F23<(N$2+7),$F23>N$2),1, IF(AND($H23<N$2+7,$H23>N$2),3, IF(AND($F23<=N$2, $H23>=N$2), 2, "" ))) | O23: =IF(AND($F23<(O$2+7),$F23>O$2),1, IF(AND($H23<O$2+7,$H23>O$2),3, IF(AND($F23<=O$2, $H23>=O$2), 2, "" ))) | P23: =IF(AND($F23<(P$2+7),$F23>P$2),1, IF(AND($H23<P$2+7,$H23>P$2),3, IF(AND($F23<=P$2, $H23>=P$2), 2, "" ))) | Q23: =IF(AND($F23<(Q$2+7),$F23>Q$2),1, IF(AND($H23<Q$2+7,$H23>Q$2),3, IF(AND($F23<=Q$2, $H23>=Q$2), 2, "" ))) | R23: =IF(AND($F23<(R$2+7),$F23>R$2),1, IF(AND($H23<R$2+7,$H23>R$2),3, IF(AND($F23<=R$2, $H23>=R$2), 2, "" ))) | S23: =IF(AND($F23<(S$2+7),$F23>S$2),1, IF(AND($H23<S$2+7,$H23>S$2),3, IF(AND($F23<=S$2, $H23>=S$2), 2, "" ))) | ... AQ23: =IF(AND($F23<(AQ$2+7),$F23>AQ$2),1, IF(AND($H23<AQ$2+7,$H23>AQ$2),3, IF(AND($F23<=AQ$2, $H23>=AQ$2), 2, "" )))
A24: 9 | B24: DC Works | C24: 43991 | D24: 16 | E24: 44012 | F24: 43991 | G24: 16 | H24: 44012 | L24: =IF(AND($F24<(L$2+7),$F24>L$2),1, IF(AND($H24<L$2+7,$H24>L$2),3, IF(AND($F24<=L$2, $H24>=L$2), 2, "" ))) | M24: =IF(AND($F24<(M$2+7),$F24>M$2),1, IF(AND($H24<M$2+7,$H24>M$2),3, IF(AND($F24<=M$2, $H24>=M$2), 2, "" ))) | N24: =IF(AND($F24<(N$2+7),$F24>N$2),1, IF(AND($H24<N$2+7,$H24>N$2),3, IF(AND($F24<=N$2, $H24>=N$2), 2, "" ))) | O24: =IF(AND($F24<(O$2+7),$F24>O$2),1, IF(AND($H24<O$2+7,$H24>O$2),3, IF(AND($F24<=O$2, $H24>=O$2), 2, "" ))) | P24: =IF(AND($F24<(P$2+7),$F24>P$2),1, IF(AND($H24<P$2+7,$H24>P$2),3, IF(AND($F24<=P$2, $H24>=P$2), 2, "" ))) | Q24: =IF(AND($F24<(Q$2+7),$F24>Q$2),1, IF(AND($H24<Q$2+7,$H24>Q$2),3, IF(AND($F24<=Q$2, $H24>=Q$2), 2, "" ))) | R24: =IF(AND($F24<(R$2+7),$F24>R$2),1, IF(AND($H24<R$2+7,$H24>R$2),3, IF(AND($F24<=R$2, $H24>=R$2), 2, "" ))) | S24: =IF(AND($F24<(S$2+7),$F24>S$2),1, IF(AND($H24<S$2+7,$H24>S$2),3, IF(AND($F24<=S$2, $H24>=S$2), 2, "" ))) | ... AQ24: =IF(AND($F24<(AQ$2+7),$F24>AQ$2),1, IF(AND($H24<AQ$2+7,$H24>AQ$2),3, IF(AND($F24<=AQ$2, $H24>=AQ$2), 2, "" ))) -> 2
B25: Mounting structure Installation | C25: 43991 | D25: 4 | E25: 43997 | F25: 43991 | G25: 4 | H25: 43997 | L25: =IF(AND($F25<(L$2+7),$F25>L$2),1, IF(AND($H25<L$2+7,$H25>L$2),3, IF(AND($F25<=L$2, $H25>=L$2), 2, "" ))) | M25: =IF(AND($F25<(M$2+7),$F25>M$2),1, IF(AND($H25<M$2+7,$H25>M$2),3, IF(AND($F25<=M$2, $H25>=M$2), 2, "" ))) | N25: =IF(AND($F25<(N$2+7),$F25>N$2),1, IF(AND($H25<N$2+7,$H25>N$2),3, IF(AND($F25<=N$2, $H25>=N$2), 2, "" ))) | O25: =IF(AND($F25<(O$2+7),$F25>O$2),1, IF(AND($H25<O$2+7,$H25>O$2),3, IF(AND($F25<=O$2, $H25>=O$2), 2, "" ))) | P25: =IF(AND($F25<(P$2+7),$F25>P$2),1, IF(AND($H25<P$2+7,$H25>P$2),3, IF(AND($F25<=P$2, $H25>=P$2), 2, "" ))) | Q25: =IF(AND($F25<(Q$2+7),$F25>Q$2),1, IF(AND($H25<Q$2+7,$H25>Q$2),3, IF(AND($F25<=Q$2, $H25>=Q$2), 2, "" ))) | R25: =IF(AND($F25<(R$2+7),$F25>R$2),1, IF(AND($H25<R$2+7,$H25>R$2),3, IF(AND($F25<=R$2, $H25>=R$2), 2, "" ))) | S25: =IF(AND($F25<(S$2+7),$F25>S$2),1, IF(AND($H25<S$2+7,$H25>S$2),3, IF(AND($F25<=S$2, $H25>=S$2), 2, "" ))) | ... AQ25: =IF(AND($F25<(AQ$2+7),$F25>AQ$2),1, IF(AND($H25<AQ$2+7,$H25>AQ$2),3, IF(AND($F25<=AQ$2, $H25>=AQ$2), 2, "" )))
B26: Cable tray Installation | C26: 43997 | D26: 3 | E26: 44004 | F26: 43997 | G26: 3 | H26: 44004 | L26: =IF(AND($F26<(L$2+7),$F26>L$2),1, IF(AND($H26<L$2+7,$H26>L$2),3, IF(AND($F26<=L$2, $H26>=L$2), 2, "" ))) | M26: =IF(AND($F26<(M$2+7),$F26>M$2),1, IF(AND($H26<M$2+7,$H26>M$2),3, IF(AND($F26<=M$2, $H26>=M$2), 2, "" ))) | N26: =IF(AND($F26<(N$2+7),$F26>N$2),1, IF(AND($H26<N$2+7,$H26>N$2),3, IF(AND($F26<=N$2, $H26>=N$2), 2, "" ))) | O26: =IF(AND($F26<(O$2+7),$F26>O$2),1, IF(AND($H26<O$2+7,$H26>O$2),3, IF(AND($F26<=O$2, $H26>=O$2), 2, "" ))) | P26: =IF(AND($F26<(P$2+7),$F26>P$2),1, IF(AND($H26<P$2+7,$H26>P$2),3, IF(AND($F26<=P$2, $H26>=P$2), 2, "" ))) | Q26: =IF(AND($F26<(Q$2+7),$F26>Q$2),1, IF(AND($H26<Q$2+7,$H26>Q$2),3, IF(AND($F26<=Q$2, $H26>=Q$2), 2, "" ))) | R26: =IF(AND($F26<(R$2+7),$F26>R$2),1, IF(AND($H26<R$2+7,$H26>R$2),3, IF(AND($F26<=R$2, $H26>=R$2), 2, "" ))) | S26: =IF(AND($F26<(S$2+7),$F26>S$2),1, IF(AND($H26<S$2+7,$H26>S$2),3, IF(AND($F26<=S$2, $H26>=S$2), 2, "" ))) | ... AQ26: =IF(AND($F26<(AQ$2+7),$F26>AQ$2),1, IF(AND($H26<AQ$2+7,$H26>AQ$2),3, IF(AND($F26<=AQ$2, $H26>=AQ$2), 2, "" )))
B27: DC Cable Installation | C27: 44004 | D27: 2 | E27: 44006 | F27: 44004 | G27: 2 | H27: 44006 | L27: =IF(AND($F27<(L$2+7),$F27>L$2),1, IF(AND($H27<L$2+7,$H27>L$2),3, IF(AND($F27<=L$2, $H27>=L$2), 2, "" ))) | M27: =IF(AND($F27<(M$2+7),$F27>M$2),1, IF(AND($H27<M$2+7,$H27>M$2),3, IF(AND($F27<=M$2, $H27>=M$2), 2, "" ))) | N27: =IF(AND($F27<(N$2+7),$F27>N$2),1, IF(AND($H27<N$2+7,$H27>N$2),3, IF(AND($F27<=N$2, $H27>=N$2), 2, "" ))) | O27: =IF(AND($F27<(O$2+7),$F27>O$2),1, IF(AND($H27<O$2+7,$H27>O$2),3, IF(AND($F27<=O$2, $H27>=O$2), 2, "" ))) | P27: =IF(AND($F27<(P$2+7),$F27>P$2),1, IF(AND($H27<P$2+7,$H27>P$2),3, IF(AND($F27<=P$2, $H27>=P$2), 2, "" ))) | Q27: =IF(AND($F27<(Q$2+7),$F27>Q$2),1, IF(AND($H27<Q$2+7,$H27>Q$2),3, IF(AND($F27<=Q$2, $H27>=Q$2), 2, "" ))) | R27: =IF(AND($F27<(R$2+7),$F27>R$2),1, IF(AND($H27<R$2+7,$H27>R$2),3, IF(AND($F27<=R$2, $H27>=R$2), 2, "" ))) | S27: =IF(AND($F27<(S$2+7),$F27>S$2),1, IF(AND($H27<S$2+7,$H27>S$2),3, IF(AND($F27<=S$2, $H27>=S$2), 2, "" ))) | ... AQ27: =IF(AND($F27<(AQ$2+7),$F27>AQ$2),1, IF(AND($H27<AQ$2+7,$H27>AQ$2),3, IF(AND($F27<=AQ$2, $H27>=AQ$2), 2, "" )))
B28: Module Installation | C28: 44006 | D28: 4 | E28: 44012 | F28: 44006 | G28: 4 | H28: 44012 | L28: =IF(AND($F28<(L$2+7),$F28>L$2),1, IF(AND($H28<L$2+7,$H28>L$2),3, IF(AND($F28<=L$2, $H28>=L$2), 2, "" ))) | M28: =IF(AND($F28<(M$2+7),$F28>M$2),1, IF(AND($H28<M$2+7,$H28>M$2),3, IF(AND($F28<=M$2, $H28>=M$2), 2, "" ))) | N28: =IF(AND($F28<(N$2+7),$F28>N$2),1, IF(AND($H28<N$2+7,$H28>N$2),3, IF(AND($F28<=N$2, $H28>=N$2), 2, "" ))) | O28: =IF(AND($F28<(O$2+7),$F28>O$2),1, IF(AND($H28<O$2+7,$H28>O$2),3, IF(AND($F28<=O$2, $H28>=O$2), 2, "" ))) | P28: =IF(AND($F28<(P$2+7),$F28>P$2),1, IF(AND($H28<P$2+7,$H28>P$2),3, IF(AND($F28<=P$2, $H28>=P$2), 2, "" ))) | Q28: =IF(AND($F28<(Q$2+7),$F28>Q$2),1, IF(AND($H28<Q$2+7,$H28>Q$2),3, IF(AND($F28<=Q$2, $H28>=Q$2), 2, "" ))) | R28: =IF(AND($F28<(R$2+7),$F28>R$2),1, IF(AND($H28<R$2+7,$H28>R$2),3, IF(AND($F28<=R$2, $H28>=R$2), 2, "" ))) | S28: =IF(AND($F28<(S$2+7),$F28>S$2),1, IF(AND($H28<S$2+7,$H28>S$2),3, IF(AND($F28<=S$2, $H28>=S$2), 2, "" ))) | ... AQ28: =IF(AND($F28<(AQ$2+7),$F28>AQ$2),1, IF(AND($H28<AQ$2+7,$H28>AQ$2),3, IF(AND($F28<=AQ$2, $H28>=AQ$2), 2, "" ))) -> 2
B29: Earth Cable Installation | C29: 44004 | D29: 1 | E29: 44005 | F29: 44004 | G29: 1 | H29: 44005 | L29: =IF(AND($F29<(L$2+7),$F29>L$2),1, IF(AND($H29<L$2+7,$H29>L$2),3, IF(AND($F29<=L$2, $H29>=L$2), 2, "" ))) | M29: =IF(AND($F29<(M$2+7),$F29>M$2),1, IF(AND($H29<M$2+7,$H29>M$2),3, IF(AND($F29<=M$2, $H29>=M$2), 2, "" ))) | N29: =IF(AND($F29<(N$2+7),$F29>N$2),1, IF(AND($H29<N$2+7,$H29>N$2),3, IF(AND($F29<=N$2, $H29>=N$2), 2, "" ))) | O29: =IF(AND($F29<(O$2+7),$F29>O$2),1, IF(AND($H29<O$2+7,$H29>O$2),3, IF(AND($F29<=O$2, $H29>=O$2), 2, "" ))) | P29: =IF(AND($F29<(P$2+7),$F29>P$2),1, IF(AND($H29<P$2+7,$H29>P$2),3, IF(AND($F29<=P$2, $H29>=P$2), 2, "" ))) | Q29: =IF(AND($F29<(Q$2+7),$F29>Q$2),1, IF(AND($H29<Q$2+7,$H29>Q$2),3, IF(AND($F29<=Q$2, $H29>=Q$2), 2, "" ))) | R29: =IF(AND($F29<(R$2+7),$F29>R$2),1, IF(AND($H29<R$2+7,$H29>R$2),3, IF(AND($F29<=R$2, $H29>=R$2), 2, "" ))) | S29: =IF(AND($F29<(S$2+7),$F29>S$2),1, IF(AND($H29<S$2+7,$H29>S$2),3, IF(AND($F29<=S$2, $H29>=S$2), 2, "" ))) | ... AQ29: =IF(AND($F29<(AQ$2+7),$F29>AQ$2),1, IF(AND($H29<AQ$2+7,$H29>AQ$2),3, IF(AND($F29<=AQ$2, $H29>=AQ$2), 2, "" )))
A30: 10 | B30: AC Works | C30: 43991 | D30: 8 | E30: 44000 | F30: 43991 | G30: 8 | H30: 44000
B31: Inverters Installation | C31: 43991 | D31: 2 | E31: 43993 | F31: 43991 | G31: 2 | H31: 43993 | L31: =IF(AND($F31<(L$2+7),$F31>L$2),1, IF(AND($H31<L$2+7,$H31>L$2),3, IF(AND($F31<=L$2, $H31>=L$2), 2, "" ))) | M31: =IF(AND($F31<(M$2+7),$F31>M$2),1, IF(AND($H31<M$2+7,$H31>M$2),3, IF(AND($F31<=M$2, $H31>=M$2), 2, "" ))) | N31: =IF(AND($F31<(N$2+7),$F31>N$2),1, IF(AND($H31<N$2+7,$H31>N$2),3, IF(AND($F31<=N$2, $H31>=N$2), 2, "" ))) | O31: =IF(AND($F31<(O$2+7),$F31>O$2),1, IF(AND($H31<O$2+7,$H31>O$2),3, IF(AND($F31<=O$2, $H31>=O$2), 2, "" ))) | P31: =IF(AND($F31<(P$2+7),$F31>P$2),1, IF(AND($H31<P$2+7,$H31>P$2),3, IF(AND($F31<=P$2, $H31>=P$2), 2, "" ))) | Q31: =IF(AND($F31<(Q$2+7),$F31>Q$2),1, IF(AND($H31<Q$2+7,$H31>Q$2),3, IF(AND($F31<=Q$2, $H31>=Q$2), 2, "" ))) | R31: =IF(AND($F31<(R$2+7),$F31>R$2),1, IF(AND($H31<R$2+7,$H31>R$2),3, IF(AND($F31<=R$2, $H31>=R$2), 2, "" ))) | S31: =IF(AND($F31<(S$2+7),$F31>S$2),1, IF(AND($H31<S$2+7,$H31>S$2),3, IF(AND($F31<=S$2, $H31>=S$2), 2, "" ))) | ... AQ31: =IF(AND($F31<(AQ$2+7),$F31>AQ$2),1, IF(AND($H31<AQ$2+7,$H31>AQ$2),3, IF(AND($F31<=AQ$2, $H31>=AQ$2), 2, "" )))
B32: AC BOS Installation | C32: 43993 | D32: 3 | E32: 44000 | F32: 43993 | G32: 3 | H32: 44000 | L32: =IF(AND($F32<(L$2+7),$F32>L$2),1, IF(AND($H32<L$2+7,$H32>L$2),3, IF(AND($F32<=L$2, $H32>=L$2), 2, "" ))) | M32: =IF(AND($F32<(M$2+7),$F32>M$2),1, IF(AND($H32<M$2+7,$H32>M$2),3, IF(AND($F32<=M$2, $H32>=M$2), 2, "" ))) | N32: =IF(AND($F32<(N$2+7),$F32>N$2),1, IF(AND($H32<N$2+7,$H32>N$2),3, IF(AND($F32<=N$2, $H32>=N$2), 2, "" ))) | O32: =IF(AND($F32<(O$2+7),$F32>O$2),1, IF(AND($H32<O$2+7,$H32>O$2),3, IF(AND($F32<=O$2, $H32>=O$2), 2, "" ))) | P32: =IF(AND($F32<(P$2+7),$F32>P$2),1, IF(AND($H32<P$2+7,$H32>P$2),3, IF(AND($F32<=P$2, $H32>=P$2), 2, "" ))) | Q32: =IF(AND($F32<(Q$2+7),$F32>Q$2),1, IF(AND($H32<Q$2+7,$H32>Q$2),3, IF(AND($F32<=Q$2, $H32>=Q$2), 2, "" ))) | R32: =IF(AND($F32<(R$2+7),$F32>R$2),1, IF(AND($H32<R$2+7,$H32>R$2),3, IF(AND($F32<=R$2, $H32>=R$2), 2, "" ))) | S32: =IF(AND($F32<(S$2+7),$F32>S$2),1, IF(AND($H32<S$2+7,$H32>S$2),3, IF(AND($F32<=S$2, $H32>=S$2), 2, "" ))) | ... AQ32: =IF(AND($F32<(AQ$2+7),$F32>AQ$2),1, IF(AND($H32<AQ$2+7,$H32>AQ$2),3, IF(AND($F32<=AQ$2, $H32>=AQ$2), 2, "" )))
B33: AC Cable/Tie-In | C33: 43992 | D33: 3 | E33: 43997 | F33: 43992 | G33: 3 | H33: 43997 | L33: =IF(AND($F33<(L$2+7),$F33>L$2),1, IF(AND($H33<L$2+7,$H33>L$2),3, IF(AND($F33<=L$2, $H33>=L$2), 2, "" ))) | M33: =IF(AND($F33<(M$2+7),$F33>M$2),1, IF(AND($H33<M$2+7,$H33>M$2),3, IF(AND($F33<=M$2, $H33>=M$2), 2, "" ))) | N33: =IF(AND($F33<(N$2+7),$F33>N$2),1, IF(AND($H33<N$2+7,$H33>N$2),3, IF(AND($F33<=N$2, $H33>=N$2), 2, "" ))) | O33: =IF(AND($F33<(O$2+7),$F33>O$2),1, IF(AND($H33<O$2+7,$H33>O$2),3, IF(AND($F33<=O$2, $H33>=O$2), 2, "" ))) | P33: =IF(AND($F33<(P$2+7),$F33>P$2),1, IF(AND($H33<P$2+7,$H33>P$2),3, IF(AND($F33<=P$2, $H33>=P$2), 2, "" ))) | Q33: =IF(AND($F33<(Q$2+7),$F33>Q$2),1, IF(AND($H33<Q$2+7,$H33>Q$2),3, IF(AND($F33<=Q$2, $H33>=Q$2), 2, "" ))) | R33: =IF(AND($F33<(R$2+7),$F33>R$2),1, IF(AND($H33<R$2+7,$H33>R$2),3, IF(AND($F33<=R$2, $H33>=R$2), 2, "" ))) | S33: =IF(AND($F33<(S$2+7),$F33>S$2),1, IF(AND($H33<S$2+7,$H33>S$2),3, IF(AND($F33<=S$2, $H33>=S$2), 2, "" ))) | ... AQ33: =IF(AND($F33<(AQ$2+7),$F33>AQ$2),1, IF(AND($H33<AQ$2+7,$H33>AQ$2),3, IF(AND($F33<=AQ$2, $H33>=AQ$2), 2, "" )))
B34: Monitoring Platform Installation | C34: 43997 | D34: 1 | E34: 44000 | F34: 43997 | G34: 1 | H34: 44000
A35: 11 | B35: Completion | C35: 44000 | D35: 14 | E35: 44014 | F35: 44000 | G35: 14 | H35: 44014 | L35: =IF(AND($F35<(L$2+7),$F35>L$2),1, IF(AND($H35<L$2+7,$H35>L$2),3, IF(AND($F35<=L$2, $H35>=L$2), 2, "" ))) | M35: =IF(AND($F35<(M$2+7),$F35>M$2),1, IF(AND($H35<M$2+7,$H35>M$2),3, IF(AND($F35<=M$2, $H35>=M$2), 2, "" ))) | N35: =IF(AND($F35<(N$2+7),$F35>N$2),1, IF(AND($H35<N$2+7,$H35>N$2),3, IF(AND($F35<=N$2, $H35>=N$2), 2, "" ))) | O35: =IF(AND($F35<(O$2+7),$F35>O$2),1, IF(AND($H35<O$2+7,$H35>O$2),3, IF(AND($F35<=O$2, $H35>=O$2), 2, "" ))) | P35: =IF(AND($F35<(P$2+7),$F35>P$2),1, IF(AND($H35<P$2+7,$H35>P$2),3, IF(AND($F35<=P$2, $H35>=P$2), 2, "" ))) | Q35: =IF(AND($F35<(Q$2+7),$F35>Q$2),1, IF(AND($H35<Q$2+7,$H35>Q$2),3, IF(AND($F35<=Q$2, $H35>=Q$2), 2, "" ))) | R35: =IF(AND($F35<(R$2+7),$F35>R$2),1, IF(AND($H35<R$2+7,$H35>R$2),3, IF(AND($F35<=R$2, $H35>=R$2), 2, "" ))) | S35: =IF(AND($F35<(S$2+7),$F35>S$2),1, IF(AND($H35<S$2+7,$H35>S$2),3, IF(AND($F35<=S$2, $H35>=S$2), 2, "" ))) | ... AQ35: =IF(AND($F35<(AQ$2+7),$F35>AQ$2),1, IF(AND($H35<AQ$2+7,$H35>AQ$2),3, IF(AND($F35<=AQ$2, $H35>=AQ$2), 2, "" ))) -> 3
B36: DC Works | C36: 44012 | D36: 2 | E36: 44014 | F36: 44012 | G36: 2 | H36: 44014 | L36: =IF(AND($F36<(L$2+7),$F36>L$2),1, IF(AND($H36<L$2+7,$H36>L$2),3, IF(AND($F36<=L$2, $H36>=L$2), 2, "" ))) | M36: =IF(AND($F36<(M$2+7),$F36>M$2),1, IF(AND($H36<M$2+7,$H36>M$2),3, IF(AND($F36<=M$2, $H36>=M$2), 2, "" ))) | N36: =IF(AND($F36<(N$2+7),$F36>N$2),1, IF(AND($H36<N$2+7,$H36>N$2),3, IF(AND($F36<=N$2, $H36>=N$2), 2, "" ))) | O36: =IF(AND($F36<(O$2+7),$F36>O$2),1, IF(AND($H36<O$2+7,$H36>O$2),3, IF(AND($F36<=O$2, $H36>=O$2), 2, "" ))) | P36: =IF(AND($F36<(P$2+7),$F36>P$2),1, IF(AND($H36<P$2+7,$H36>P$2),3, IF(AND($F36<=P$2, $H36>=P$2), 2, "" ))) | Q36: =IF(AND($F36<(Q$2+7),$F36>Q$2),1, IF(AND($H36<Q$2+7,$H36>Q$2),3, IF(AND($F36<=Q$2, $H36>=Q$2), 2, "" ))) | R36: =IF(AND($F36<(R$2+7),$F36>R$2),1, IF(AND($H36<R$2+7,$H36>R$2),3, IF(AND($F36<=R$2, $H36>=R$2), 2, "" ))) | S36: =IF(AND($F36<(S$2+7),$F36>S$2),1, IF(AND($H36<S$2+7,$H36>S$2),3, IF(AND($F36<=S$2, $H36>=S$2), 2, "" ))) | ... AQ36: =IF(AND($F36<(AQ$2+7),$F36>AQ$2),1, IF(AND($H36<AQ$2+7,$H36>AQ$2),3, IF(AND($F36<=AQ$2, $H36>=AQ$2), 2, "" ))) -> 3
B37: AC Works | C37: 44000 | D37: 2 | E37: 44004 | F37: 44000 | G37: 2 | H37: 44004 | L37: =IF(AND($F37<(L$2+7),$F37>L$2),1, IF(AND($H37<L$2+7,$H37>L$2),3, IF(AND($F37<=L$2, $H37>=L$2), 2, "" ))) | M37: =IF(AND($F37<(M$2+7),$F37>M$2),1, IF(AND($H37<M$2+7,$H37>M$2),3, IF(AND($F37<=M$2, $H37>=M$2), 2, "" ))) | N37: =IF(AND($F37<(N$2+7),$F37>N$2),1, IF(AND($H37<N$2+7,$H37>N$2),3, IF(AND($F37<=N$2, $H37>=N$2), 2, "" ))) | O37: =IF(AND($F37<(O$2+7),$F37>O$2),1, IF(AND($H37<O$2+7,$H37>O$2),3, IF(AND($F37<=O$2, $H37>=O$2), 2, "" ))) | P37: =IF(AND($F37<(P$2+7),$F37>P$2),1, IF(AND($H37<P$2+7,$H37>P$2),3, IF(AND($F37<=P$2, $H37>=P$2), 2, "" ))) | Q37: =IF(AND($F37<(Q$2+7),$F37>Q$2),1, IF(AND($H37<Q$2+7,$H37>Q$2),3, IF(AND($F37<=Q$2, $H37>=Q$2), 2, "" ))) | R37: =IF(AND($F37<(R$2+7),$F37>R$2),1, IF(AND($H37<R$2+7,$H37>R$2),3, IF(AND($F37<=R$2, $H37>=R$2), 2, "" ))) | S37: =IF(AND($F37<(S$2+7),$F37>S$2),1, IF(AND($H37<S$2+7,$H37>S$2),3, IF(AND($F37<=S$2, $H37>=S$2), 2, "" ))) | ... AQ37: =IF(AND($F37<(AQ$2+7),$F37>AQ$2),1, IF(AND($H37<AQ$2+7,$H37>AQ$2),3, IF(AND($F37<=AQ$2, $H37>=AQ$2), 2, "" )))
A38: D | B38: PAYMENT MILESTONE 4: PRACTICAL COMPLETION | C38: 44012 | D38: 1 | E38: 44013 | F38: 44012 | G38: 1 | H38: 44013 | L38: =IF(AND($F38<(L$2+7),$F38>L$2),1, IF(AND($H38<L$2+7,$H38>L$2),3, IF(AND($F38<=L$2, $H38>=L$2), 2, "" ))) | M38: =IF(AND($F38<(M$2+7),$F38>M$2),1, IF(AND($H38<M$2+7,$H38>M$2),3, IF(AND($F38<=M$2, $H38>=M$2), 2, "" ))) | N38: =IF(AND($F38<(N$2+7),$F38>N$2),1, IF(AND($H38<N$2+7,$H38>N$2),3, IF(AND($F38<=N$2, $H38>=N$2), 2, "" ))) | O38: =IF(AND($F38<(O$2+7),$F38>O$2),1, IF(AND($H38<O$2+7,$H38>O$2),3, IF(AND($F38<=O$2, $H38>=O$2), 2, "" ))) | P38: =IF(AND($F38<(P$2+7),$F38>P$2),1, IF(AND($H38<P$2+7,$H38>P$2),3, IF(AND($F38<=P$2, $H38>=P$2), 2, "" ))) | Q38: =IF(AND($F38<(Q$2+7),$F38>Q$2),1, IF(AND($H38<Q$2+7,$H38>Q$2),3, IF(AND($F38<=Q$2, $H38>=Q$2), 2, "" ))) | R38: =IF(AND($F38<(R$2+7),$F38>R$2),1, IF(AND($H38<R$2+7,$H38>R$2),3, IF(AND($F38<=R$2, $H38>=R$2), 2, "" ))) | S38: =IF(AND($F38<(S$2+7),$F38>S$2),1, IF(AND($H38<S$2+7,$H38>S$2),3, IF(AND($F38<=S$2, $H38>=S$2), 2, "" ))) | ... AQ38: =IF(AND($F38<(AQ$2+7),$F38>AQ$2),1, IF(AND($H38<AQ$2+7,$H38>AQ$2),3, IF(AND($F38<=AQ$2, $H38>=AQ$2), 2, "" ))) -> 3
A39: 12 | B39: Commissioning | C39: 43997 | D39: 22 | E39: 44019 | F39: 43997 | G39: 22 | H39: 44019 | L39: =IF(AND($F39<(L$2+7),$F39>L$2),1, IF(AND($H39<L$2+7,$H39>L$2),3, IF(AND($F39<=L$2, $H39>=L$2), 2, "" ))) | M39: =IF(AND($F39<(M$2+7),$F39>M$2),1, IF(AND($H39<M$2+7,$H39>M$2),3, IF(AND($F39<=M$2, $H39>=M$2), 2, "" ))) | N39: =IF(AND($F39<(N$2+7),$F39>N$2),1, IF(AND($H39<N$2+7,$H39>N$2),3, IF(AND($F39<=N$2, $H39>=N$2), 2, "" ))) | O39: =IF(AND($F39<(O$2+7),$F39>O$2),1, IF(AND($H39<O$2+7,$H39>O$2),3, IF(AND($F39<=O$2, $H39>=O$2), 2, "" ))) | P39: =IF(AND($F39<(P$2+7),$F39>P$2),1, IF(AND($H39<P$2+7,$H39>P$2),3, IF(AND($F39<=P$2, $H39>=P$2), 2, "" ))) | Q39: =IF(AND($F39<(Q$2+7),$F39>Q$2),1, IF(AND($H39<Q$2+7,$H39>Q$2),3, IF(AND($F39<=Q$2, $H39>=Q$2), 2, "" ))) | R39: =IF(AND($F39<(R$2+7),$F39>R$2),1, IF(AND($H39<R$2+7,$H39>R$2),3, IF(AND($F39<=R$2, $H39>=R$2), 2, "" ))) | S39: =IF(AND($F39<(S$2+7),$F39>S$2),1, IF(AND($H39<S$2+7,$H39>S$2),3, IF(AND($F39<=S$2, $H39>=S$2), 2, "" ))) | ... AQ39: =IF(AND($F39<(AQ$2+7),$F39>AQ$2),1, IF(AND($H39<AQ$2+7,$H39>AQ$2),3, IF(AND($F39<=AQ$2, $H39>=AQ$2), 2, "" ))) -> 2
B40: Snag List | C40: 44014 | D40: 3 | E40: 44019 | F40: 44014 | G40: 3 | H40: 44019
B41: Pre-Commissioning Checks | C41: 44010 | D41: 2 | E41: 44012 | F41: 44010 | G41: 2 | H41: 44012
B42: Issue CoC | C42: 43997 | D42: 2 | E42: 44001 | F42: 43997 | G42: 2 | H42: 44001 | L42: =IF(AND($F42<(L$2+7),$F42>L$2),1, IF(AND($H42<L$2+7,$H42>L$2),3, IF(AND($F42<=L$2, $H42>=L$2), 2, "" ))) | M42: =IF(AND($F42<(M$2+7),$F42>M$2),1, IF(AND($H42<M$2+7,$H42>M$2),3, IF(AND($F42<=M$2, $H42>=M$2), 2, "" ))) | N42: =IF(AND($F42<(N$2+7),$F42>N$2),1, IF(AND($H42<N$2+7,$H42>N$2),3, IF(AND($F42<=N$2, $H42>=N$2), 2, "" ))) | O42: =IF(AND($F42<(O$2+7),$F42>O$2),1, IF(AND($H42<O$2+7,$H42>O$2),3, IF(AND($F42<=O$2, $H42>=O$2), 2, "" ))) | P42: =IF(AND($F42<(P$2+7),$F42>P$2),1, IF(AND($H42<P$2+7,$H42>P$2),3, IF(AND($F42<=P$2, $H42>=P$2), 2, "" ))) | Q42: =IF(AND($F42<(Q$2+7),$F42>Q$2),1, IF(AND($H42<Q$2+7,$H42>Q$2),3, IF(AND($F42<=Q$2, $H42>=Q$2), 2, "" ))) | R42: =IF(AND($F42<(R$2+7),$F42>R$2),1, IF(AND($H42<R$2+7,$H42>R$2),3, IF(AND($F42<=R$2, $H42>=R$2), 2, "" ))) | S42: =IF(AND($F42<(S$2+7),$F42>S$2),1, IF(AND($H42<S$2+7,$H42>S$2),3, IF(AND($F42<=S$2, $H42>=S$2), 2, "" ))) | ... AQ42: =IF(AND($F42<(AQ$2+7),$F42>AQ$2),1, IF(AND($H42<AQ$2+7,$H42>AQ$2),3, IF(AND($F42<=AQ$2, $H42>=AQ$2), 2, "" )))
B43: Cold Commissioning | C43: 44012 | D43: 1 | E43: 44013 | F43: 44012 | G43: 1 | H43: 44013 | L43: =IF(AND($F43<(L$2+7),$F43>L$2),1, IF(AND($H43<L$2+7,$H43>L$2),3, IF(AND($F43<=L$2, $H43>=L$2), 2, "" ))) | M43: =IF(AND($F43<(M$2+7),$F43>M$2),1, IF(AND($H43<M$2+7,$H43>M$2),3, IF(AND($F43<=M$2, $H43>=M$2), 2, "" ))) | N43: =IF(AND($F43<(N$2+7),$F43>N$2),1, IF(AND($H43<N$2+7,$H43>N$2),3, IF(AND($F43<=N$2, $H43>=N$2), 2, "" ))) | O43: =IF(AND($F43<(O$2+7),$F43>O$2),1, IF(AND($H43<O$2+7,$H43>O$2),3, IF(AND($F43<=O$2, $H43>=O$2), 2, "" ))) | P43: =IF(AND($F43<(P$2+7),$F43>P$2),1, IF(AND($H43<P$2+7,$H43>P$2),3, IF(AND($F43<=P$2, $H43>=P$2), 2, "" ))) | Q43: =IF(AND($F43<(Q$2+7),$F43>Q$2),1, IF(AND($H43<Q$2+7,$H43>Q$2),3, IF(AND($F43<=Q$2, $H43>=Q$2), 2, "" ))) | R43: =IF(AND($F43<(R$2+7),$F43>R$2),1, IF(AND($H43<R$2+7,$H43>R$2),3, IF(AND($F43<=R$2, $H43>=R$2), 2, "" ))) | S43: =IF(AND($F43<(S$2+7),$F43>S$2),1, IF(AND($H43<S$2+7,$H43>S$2),3, IF(AND($F43<=S$2, $H43>=S$2), 2, "" ))) | ... AQ43: =IF(AND($F43<(AQ$2+7),$F43>AQ$2),1, IF(AND($H43<AQ$2+7,$H43>AQ$2),3, IF(AND($F43<=AQ$2, $H43>=AQ$2), 2, "" ))) -> 3
B44: Hot Commissioning | C44: 44013 | D44: 2 | E44: 44015 | F44: 44013 | G44: 2 | H44: 44015 | L44: =IF(AND($F44<(L$2+7),$F44>L$2),1, IF(AND($H44<L$2+7,$H44>L$2),3, IF(AND($F44<=L$2, $H44>=L$2), 2, "" ))) | M44: =IF(AND($F44<(M$2+7),$F44>M$2),1, IF(AND($H44<M$2+7,$H44>M$2),3, IF(AND($F44<=M$2, $H44>=M$2), 2, "" ))) | N44: =IF(AND($F44<(N$2+7),$F44>N$2),1, IF(AND($H44<N$2+7,$H44>N$2),3, IF(AND($F44<=N$2, $H44>=N$2), 2, "" ))) | O44: =IF(AND($F44<(O$2+7),$F44>O$2),1, IF(AND($H44<O$2+7,$H44>O$2),3, IF(AND($F44<=O$2, $H44>=O$2), 2, "" ))) | P44: =IF(AND($F44<(P$2+7),$F44>P$2),1, IF(AND($H44<P$2+7,$H44>P$2),3, IF(AND($F44<=P$2, $H44>=P$2), 2, "" ))) | Q44: =IF(AND($F44<(Q$2+7),$F44>Q$2),1, IF(AND($H44<Q$2+7,$H44>Q$2),3, IF(AND($F44<=Q$2, $H44>=Q$2), 2, "" ))) | R44: =IF(AND($F44<(R$2+7),$F44>R$2),1, IF(AND($H44<R$2+7,$H44>R$2),3, IF(AND($F44<=R$2, $H44>=R$2), 2, "" ))) | S44: =IF(AND($F44<(S$2+7),$F44>S$2),1, IF(AND($H44<S$2+7,$H44>S$2),3, IF(AND($F44<=S$2, $H44>=S$2), 2, "" ))) | ... AQ44: =IF(AND($F44<(AQ$2+7),$F44>AQ$2),1, IF(AND($H44<AQ$2+7,$H44>AQ$2),3, IF(AND($F44<=AQ$2, $H44>=AQ$2), 2, "" ))) -> 1
A45: 13 | B45: Handover | C45: 44020 | D45: 1 | E45: 44021 | F45: 44020 | G45: 1 | H45: 44021 | L45: =IF(AND($F45<(L$2+7),$F45>L$2),1, IF(AND($H45<L$2+7,$H45>L$2),3, IF(AND($F45<=L$2, $H45>=L$2), 2, "" ))) | M45: =IF(AND($F45<(M$2+7),$F45>M$2),1, IF(AND($H45<M$2+7,$H45>M$2),3, IF(AND($F45<=M$2, $H45>=M$2), 2, "" ))) | N45: =IF(AND($F45<(N$2+7),$F45>N$2),1, IF(AND($H45<N$2+7,$H45>N$2),3, IF(AND($F45<=N$2, $H45>=N$2), 2, "" ))) | O45: =IF(AND($F45<(O$2+7),$F45>O$2),1, IF(AND($H45<O$2+7,$H45>O$2),3, IF(AND($F45<=O$2, $H45>=O$2), 2, "" ))) | P45: =IF(AND($F45<(P$2+7),$F45>P$2),1, IF(AND($H45<P$2+7,$H45>P$2),3, IF(AND($F45<=P$2, $H45>=P$2), 2, "" ))) | Q45: =IF(AND($F45<(Q$2+7),$F45>Q$2),1, IF(AND($H45<Q$2+7,$H45>Q$2),3, IF(AND($F45<=Q$2, $H45>=Q$2), 2, "" ))) | R45: =IF(AND($F45<(R$2+7),$F45>R$2),1, IF(AND($H45<R$2+7,$H45>R$2),3, IF(AND($F45<=R$2, $H45>=R$2), 2, "" ))) | S45: =IF(AND($F45<(S$2+7),$F45>S$2),1, IF(AND($H45<S$2+7,$H45>S$2),3, IF(AND($F45<=S$2, $H45>=S$2), 2, "" ))) | ... AQ45: =IF(AND($F45<(AQ$2+7),$F45>AQ$2),1, IF(AND($H45<AQ$2+7,$H45>AQ$2),3, IF(AND($F45<=AQ$2, $H45>=AQ$2), 2, "" )))
A46: E | B46: PAYMENT MILESTONE 6: HANDOVER COMPLETE | C46: 44022 | D46: 1 | E46: 44025 | F46: 44022 | G46: 1 | H46: 44025
C47: 43831 | D47: These numbers are used to set the start and end dates on the Gantt Chart
C48: 44014

Sheet Compliance
B2: HSE
B4: Description | C4: Status | D4: Approved By | E4: Date | F4: Results / Comments
B5: NOC
B6: 7.1 Agreement
B7: 13.2 Agreement
B8: EE File
B9: Subbie File
B16: SSEG
B18: Description | C18: Status | D18: Approved By | E18: Date | F18: Results / Comments
B19: SSEG Application
B20: PTI
B21: Commissioning Approval

Sheet Revenue Tracking
B2: HIGH LEVEL PROJECT REVENUE TRACKING
D3: PLANNED | F3: ACTUAL | L3: FINANCIAL REVIEW | N3: TIMELINE REVIEW | R3: Allocated in 2024 | S3: Budgeted | T3: Acutal
B4: 1 | C4: Planned Revenue | D4: ='Project Plan'!E6 -> 2462259 | F4: =F21 -> 2505210.5 | L4: 2462259 | N4: Start Date | P4: Sales | R4: =GETPIVOTDATA("REVENUE RECOGNITION AMOUNT",'Finance - Revenue'!$A$3,"INVOICE RAISED DATE",DATE(2024,7,31))+GETPIVOTDATA("REVENUE RECOGNITION AMOUNT",'Finance - Revenue'!$A$3,"INVOICE RAISED DATE",DATE(2024,8,31)) -> 848045.34 | S4: 1614213.7 | T4: =F4-R4 -> 1657165.1
B5: 2 | C5: Planned Expenditure | D5: =+'Expenditure Tracking'!F5 -> 2105194.2 | F5: =+'Expenditure Tracking'!J5 -> 2103862.1 | L5: 2040967.7 | N5: 45560 | P5: COS | R5: =GETPIVOTDATA("Actual Total ",'Finance - COS'!$A$3,"INVOICE RAISED DATE",DATE(2024,7,31))+GETPIVOTDATA("Actual Total ",'Finance - COS'!$A$3,"INVOICE RAISED DATE",DATE(2024,8,31)) -> 730147.42 | S5: 1301474.2 | T5: =F5-R5 -> 1373714.7
B6: 3 | C6: Planned Profit | D6: =+D4-D5 -> 357064.85 | F6: =+F4-F5 -> 401348.36 | L6: 421291.35 | N6: End Date - PC | P6: GP | R6: =R4-R5 -> 117897.92 | S6: =S4-S5 -> 312739.45 | T6: =T4-T5 -> 283450.44
B7: 4 | C7: Planned Margin | D7: =+D6/D4 -> 0.14501515 | F7: =+F6/F4 -> 0.16020545 | L7: 0.17109952 | N7: 45600
B10: CONTRACT
B12: No. | C12: PAYMENT MILESTONE | E12: % | F12: VALUE | H12: PLANNED PAYMENT DATE | L12: INVOICE NUMBER | N12: INVOICE RAISED DATE | P12: PAYMENT RECEIVED DATE | R12: MILESTONE NOTES & COMMENTS
B13: 1 | C13: Acceptance and Initial Deposit | E13: 0.35 | F13: =$D$4*E13 -> 861790.65 | H13: 45491 | L13: 004471 | N13: 45488 | P13: 45490
B14: 2 | C14: Delivery of Inverters | E14: 0.25 | F14: =$D$4*E14 -> 615564.75 | H14: ='Project Plan'!E22+7 -> 45567 | L14: 004555 | N14: 45567 | P14: =N14+7 -> 45574
B15: 3 | C15: Delivery of Panels | E15: 0.25 | F15: =$D$4*E15 -> 615564.75 | H15: ='Project Plan'!E35+7 -> 45583 | L15: 004576 | N15: 45586 | P15: =N15+38 -> 45624
B16: 4 | C16: Practical Completion | E16: 0.1 | F16: =$D$4*E16 -> 246225.9 | H16: ='Project Plan'!E39+7 -> 45616 | L16: 004608 | N16: 45610 | P16: =N16+14 -> 45624
B17: 5 | C17: Handover | E17: 0.05 | F17: =$D$4*E17 -> 123112.95 | H17: ='Project Plan'!E50+7 -> 45642 | L17: 004693 | N17: 45714 | P17: 45946
B18: 6 | C18: VO - Walkways | E18: 0 | F18: ='Expenditure Breakdown'!R68+'Expenditure Breakdown'!R69+'Expenditure Breakdown'!R70+'Expenditure Breakdown'!R72 -> 52281.12 | H18: =H17 -> 45642 | L18: 004693 | N18: 45714 | P18: 45946
B19: 7 | C19: Credit Note - Walkways | E19: 0 | F19: -9329.65 | L19: 004931 | N19: 46045 | P19: 46081
E21: =SUM(E13:E19) -> 1 | F21: =SUM(F13:F19) -> 2505210.5
B23: KEY: | C23: contains an error (in result or a check has failed)
C24: Red Font - IF TEXT : content not yet confirmed
C25: Red Font - IF NUMBER: Negative value
C26: Anything in yellow is a concern or risk for noting or action
C27: confirmed
C28: [ADD INITIALS: comment for noting in square brackets, use colour or red to draw attention if important]
C29: [RT: When adding rows into sheet, ensure you insert between first and last row of each category]
C30: end of sheet - do not insert information below/beyond this
B40: No. | C40: PAYMENT MILESTONE | E40: % | F40: VALUE
B41: 1 | C41: Deposit - Project commencement | E41: 0.35 | F41: =$F$47*E41 -> 876823.67
B42: 2 | C42: Delivery of Panels | E42: 0.3 | F42: =$F$47*E42 -> 751563.14
B43: 3 | C43: Delivery of Inverters | E43: 0.2 | F43: =$F$47*E43 -> 501042.09
B44: 4 | C44: Practical Completion | E44: 0.1 | F44: =$F$47*E44 -> 250521.05
B45: 5 | C45: Handover | E45: 0.05 | F45: =$F$47*E45 -> 125260.52
C46: Total | E46: =SUM(E41:E45) -> 1 | F46: =SUM(F41:F45) -> 2505210.5
E47: =SUM(E41:E45) -> 1 | F47: =F21 -> 2505210.5

Sheet Project Plan
N1: 45943 | O1: 45943
C2: PROJECT PLAN | E2: SA Metal - 22 Christiaan | N2: 0 | O2: 1
C3: PROJECT SIZE (kWp) | E3: 250
C4: BUSINESS DEVELOPER | E4: Peet
C5: PROJECT MANAGER | E5: Lloyd
C6: CONTRACT VALUE | E6: 2462259
C7: Phase: | E7: Compliance Handover
B8: No. | C8: HIGH LEVEL PROGRAMME | E8: Planned Start | F8: Duration (days) | G8: Planned End | I8: Actual Start | J8: Duration (days) | K8: Actual End | M8: Status | O8: Comment
F9: 55 | J9: 55 | M9: 1 | N9: 1
B11: 1 | C11: Project Initiation | E11: 45518 | F11: 37 | G11: 45555 | I11: 45518 | J11: 37 | K11: 45555 | M11: 1 | N11: 1
B12: 1.1 | C12: BD Handover | E12: 45518 | F12: 1 | G12: 45519 | I12: 45518 | J12: 1 | K12: 45519 | M12: 1 | N12: 1
B13: 1.2 | C13: Project Introduction | E13: 45540 | F13: 1 | G13: 45541 | I13: 45540 | J13: 1 | K13: 45541 | M13: 1 | N13: 1
B14: 1.3 | C14: HSE | E14: 45540 | F14: 15 | G14: 45555 | I14: 45540 | J14: 15 | K14: 45555 | M14: 1 | N14: 1
B15: 1.4 | C15: Installer Kick Off | E15: 45548 | F15: 1 | G15: 45551 | I15: 45548 | J15: 1 | K15: 45551 | M15: 1 | N15: 1
B16: 1.5 | C16: Project Review | E16: 45547 | F16: 1 | G16: 45548 | I16: 45547 | J16: 1 | K16: 45548 | M16: 1 | N16: 1
B18: 2 | C18: Site Establishment | E18: 45560 | F18: 1 | G18: 45561 | I18: 45560 | J18: 1 | K18: 45561 | M18: 1 | N18: 1
B19: 2.1 | C19: Installer on site & Roof Assessment | E19: 45560 | F19: 1 | G19: 45561 | I19: 45560 | J19: 1 | K19: 45561 | M19: 1 | N19: 1 | S19: 88 | T19: Net working Days
B21: 3 | C21: AC Installation | E21: 45562 | F21: 35 | G21: 45597 | I21: 45562 | J21: 35 | K21: 45597 | M21: 1 | N21: 1 | S21: 17.6 | T21: Net Working Weeks
B22: 3.1 | C22: Inverters delivered | E22: 45560 | F22: 1 | G22: 45561 | I22: 45565 | J22: 1 | K22: 45566 | M22: 1 | N22: 1 | S22: 14.204545 | T22: kW/Week Installationn Speed
B23: 3.2 | C23: Inverters Mounted | E23: 45561 | F23: 1 | G23: 45562 | I23: 45566 | J23: 1 | K23: 45567 | M23: 1 | N23: 1
B24: 3.3 | C24: Solar DB lead time | E24: 45560 | F24: 30 | G24: 45602 | I24: 45560 | J24: 30 | K24: 45602 | M24: 1 | N24: 1
B25: 3.4 | C25: AC Works | E25: 45561 | F25: 10 | G25: 45575 | I25: 45566 | J25: 10 | K25: 45580 | M25: 1 | N25: 1
B26: 3.5 | C26: AC Tie - in | E26: 45569 | F26: 1 | G26: 45572 | I26: 45574 | J26: 1 | K26: 45575 | M26: 1 | N26: 1
B28: 4 | C28: DC Works | E28: 45560 | F28: 37 | G28: 45597 | I28: 45560 | J28: 37 | K28: 45597 | M28: 1 | N28: 1
B29: 4.1 | C29: Mounting Structure delivered | E29: 45560 | F29: 1 | G29: 45561 | I29: 45560 | J29: 1 | K29: 45561 | M29: 1 | N29: 1
B30: 4.2 | C30: Mounting Structure installation | E30: 45560 | F30: 8 | G30: 45572 | I30: 45560 | J30: 8 | K30: 45572 | M30: 1 | N30: 1
B31: 4.3 | C31: DC Cable delivered | E31: 45560 | F31: 1 | G31: 45561 | I31: 45560 | J31: 1 | K31: 45561 | M31: 1 | N31: 1
B32: 4.3 | C32: DC Stringing | E32: 45597 | F32: 5 | G32: 45604 | I32: 45597 | J32: 5 | K32: 45604 | M32: 1 | N32: 1
B34: 5 | C34: Module installation | E34: 45576 | F34: 33 | G34: 45609 | I34: 45576 | J34: 33 | K34: 45609 | M34: 1 | N34: 1
B35: 5.1 | C35: Module delivery | E35: 45576 | F35: 1 | G35: 45579 | I35: 45576 | J35: 1 | K35: 45579 | M35: 1 | N35: 1
B36: 5.2 | C36: Module mounting | E36: 45576 | F36: 15 | G36: 45597 | I36: 45576 | J36: 15 | K36: 45597 | M36: 1 | N36: 1
B38: 6 | C38: Commissioning | E38: 45604 | F38: 5 | G38: 45609 | I38: 45604 | J38: 5 | K38: 45609 | M38: 1 | N38: 1
B39: 6.1 | C39: Commissioning | E39: 45609 | F39: 1 | G39: 45610 | I39: 45609 | J39: 1 | K39: 45610 | M39: 1 | N39: 1
B40: 6.2 | C40: Practical Completion | E40: 45609 | F40: 4 | G40: 45615 | I40: 45609 | J40: 4 | K40: 45615 | M40: 1 | N40: 1
B42: 7 | C42: QA Inspections | E42: 45609 | F42: 28 | G42: 45637 | I42: 45609 | J42: 28 | K42: 45637 | M42: 1 | N42: 1
B43: 7.1 | C43: Red-Team Inspection | E43: 45615 | F43: 3 | G43: 45618 | I43: 45632 | J43: 3 | K43: 45637 | M43: 1 | N43: 1
B45: 8 | C45: Project Closure | E45: 45634 | F45: 52 | G45: 45686 | I45: 45634 | J45: 52 | K45: 45686 | M45: 1 | N45: 1
B46: 8.1 | C46: Equipment serial numbers | E46: 45618 | F46: 1 | G46: 45621 | I46: 45637 | J46: 1 | K46: 45638 | M46: 1 | N46: 1
B47: 8.2 | C47: Snags completion | E47: 45621 | F47: 5 | G47: 45628 | I47: 45638 | J47: 28 | K47: 45681 | M47: 1 | N47: 1
B48: 8.3 | C48: System Performance Monitoring | E48: 45628 | F48: 5 | G48: 45635 | I48: 45646 | J48: 10 | K48: 45664 | M48: 1 | N48: 1
B49: 8.4 | C49: Handover documentation | E49: 45628 | F49: 5 | G49: 45635 | I49: 45646 | J49: 20 | K49: 45678 | M49: 1 | N49: 1
B50: 8.5 | C50: Handover to Client | E50: 45635 | F50: 1 | G50: 45636 | I50: 45708 | J50: 1 | K50: 45898 | M50: 1 | N50: 1
B51: 8.6 | C51: Handover to Matriarch | E51: 45617 | F51: 1 | G51: 45618 | I51: 45776 | J51: 1 | K51: 45777 | M51: 1 | N51: 1

Sheet Data
C2: Public holidays | F2: Drop down list
C3: 45292 | D3: New Years Day | F3: Approved
C4: 45372 | D4: Human Rights day | F4: Pending
C5: 45380 | D5: Good Friday | F5: Declined
C6: 45383 | D6: Family Day | F6: Abanded
C7: 45413 | D7: Workers day
C8: 45460 | D8: Youth Day Holiday
C9: 45513 | D9: Womens Day
C10: 45559 | D10: Heritage Day
C11: 45642 | D11: Day of Reconciliation
C12: 45651 | D12: Christmas Day
C13: 45652 | D13: Day of Goodwill | H13: Manual dates

Sheet Expenditure Tracking
B2: HIGH LEVEL PROJECT EXPENDITURE TRACKING
F4: COSTED | H4: PLANNED | J4: ACTUAL | L4: Difference from costed | N4: Difference from planned
B5: EXPENDITURE | F5: =SUM(F9:F23) -> 2105194.2 | H5: =SUM(H9:H23) -> 2040967.7 | J5: =SUM(J9:J23) -> 2103862.1 | L5: =SUM(L9:L23) -> 1332.043 | N5: =SUM(N9:N23) -> -62894.452
B7: No. | D7: Item | F7: Costed Expenditure | H7: Planned Expenditure | J7: Actual Expenditure | L7: Saving / Overrun | N7: Saving / Overrun | P7: Comments on variations from planned expenditure
B9: ='Expenditure Breakdown'!B6 -> 1 | D9: ='Expenditure Breakdown'!C6 -> Panels | F9: ='Expenditure Breakdown'!J6 -> 690973.73 | H9: 736862.5 | J9: ='Expenditure Breakdown'!X6 -> 647765.5 | L9: =F9-J9 -> 43208.233 | N9: =H9-J9 -> 89097
B10: ='Expenditure Breakdown'!B13 -> 2 | D10: ='Expenditure Breakdown'!C13 -> Inverters | F10: =+'Expenditure Breakdown'!J13 -> 157796 | H10: 151514 | J10: =+'Expenditure Breakdown'!X13 -> 138845.23 | L10: =F10-J10 -> 18950.77 | N10: =H10-J10 -> 12668.77
B11: ='Expenditure Breakdown'!B18 -> 3 | D11: ='Expenditure Breakdown'!C18 -> Mounting Structures | F11: =+'Expenditure Breakdown'!J18 -> 99864 | H11: 58349.4 | J11: =+'Expenditure Breakdown'!X18 -> 169924.22 | L11: =F11-J11 -> -70060.22 | N11: =H11-J11 -> -111574.82
B12: ='Expenditure Breakdown'!B26 -> 4 | D12: ='Expenditure Breakdown'!C26 -> DC Equipment | F12: =+'Expenditure Breakdown'!J26 -> 237064.3 | H12: 242250 | J12: =+'Expenditure Breakdown'!X26 -> 242250 | L12: =F12-J12 -> -5185.7 | N12: =H12-J12 -> 0
B13: ='Expenditure Breakdown'!B37 -> 5 | D13: ='Expenditure Breakdown'!C37 -> Monitoring | F13: =+'Expenditure Breakdown'!J37 -> 49000 | H13: 80720.5 | J13: =+'Expenditure Breakdown'!X37 -> 71452.01 | L13: =F13-J13 -> -22452.01 | N13: =H13-J13 -> 9268.49
B14: ='Expenditure Breakdown'!B44 -> 6 | D14: ='Expenditure Breakdown'!C44 -> AC Equipment | F14: =+'Expenditure Breakdown'!J44 -> 304429.82 | H14: 212432 | J14: =+'Expenditure Breakdown'!X44 -> 212863.6 | L14: =F14-J14 -> 91566.22 | N14: =H14-J14 -> -431.6
B15: ='Expenditure Breakdown'!B59 -> 7 | D15: ='Expenditure Breakdown'!C59 -> Battery Systems | F15: =+'Expenditure Breakdown'!J59 -> 0 | H15: 0 | J15: ='Expenditure Breakdown'!X59 -> 0 | L15: =F15-J15 -> 0 | N15: =H15-J15 -> 0
B16: ='Expenditure Breakdown'!B68 -> 8 | D16: ='Expenditure Breakdown'!C68 -> Product Add On | F16: ='Expenditure Breakdown'!J68 -> 0 | H16: 0 | J16: ='Expenditure Breakdown'!X68 -> 158729.52 | L16: =F16-J16 -> -158729.52 | N16: =H16-J16 -> -158729.52
B17: ='Expenditure Breakdown'!M77 -> 9 | D17: ='Expenditure Breakdown'!C77 -> AC & DC Installation | F17: =+'Expenditure Breakdown'!J77 -> 208050 | H17: 175013.8 | J17: =+'Expenditure Breakdown'!X77 -> 175013.8 | L17: =F17-J17 -> 33036.2 | N17: =H17-J17 -> 0
B18: ='Expenditure Breakdown'!B86 -> 10 | D18: ='Expenditure Breakdown'!C86 -> Site Logistics | F18: =+'Expenditure Breakdown'!J86 -> 38356.3 | H18: 122767 | J18: =+'Expenditure Breakdown'!X86 -> 107767 | L18: =F18-J18 -> -69410.7 | N18: =H18-J18 -> 15000
B19: ='Expenditure Breakdown'!B101 -> 11 | D19: ='Expenditure Breakdown'!C101 -> Due Dilligence | F19: ='Expenditure Breakdown'!J101 -> 89000 | H19: 23020 | J19: ='Expenditure Breakdown'!X101 -> 14174.76 | L19: =F19-J19 -> 74825.24 | N19: =H19-J19 -> 8845.24
B20: ='Expenditure Breakdown'!B109 -> 12 | D20: ='Expenditure Breakdown'!C109 -> BDP Commission | F20: ='Expenditure Breakdown'!G107 -> 63011.44 | H20: 63043.34 | J20: ='Expenditure Breakdown'!X107 -> 63043.34 | L20: =F20-J20 -> -31.9 | N20: =H20-J20 -> 0
B21: ='Expenditure Breakdown'!B111 -> 13 | D21: ='Expenditure Breakdown'!C111 -> Engineering | F21: =+'Expenditure Breakdown'!J111 -> 163448.56 | H21: 170795.12 | J21: =+'Expenditure Breakdown'!X111 -> 62400 | L21: =F21-J21 -> 101048.56 | N21: =H21-J21 -> 108395.12 | P21: RV: Matriarch defects percentage 1.25%
B22: ='Expenditure Breakdown'!B119 -> 14 | D22: ='Expenditure Breakdown'!C119 -> General Expenses | F22: =+'Expenditure Breakdown'!J119 -> 4200 | H22: 4200 | J22: =+'Expenditure Breakdown'!X119 -> 7385.64 | L22: =F22-J22 -> -3185.64 | N22: =H22-J22 -> -3185.64
B23: ='Expenditure Breakdown'!B128 -> 15 | D23: ='Expenditure Breakdown'!C128 -> Service Add On | F23: =+'Expenditure Breakdown'!J128 -> 0 | H23: 0 | J23: =+'Expenditure Breakdown'!X128 -> 32247.49 | L23: =F23-J23 -> -32247.49 | N23: =H23-J23 -> -32247.49
D25: check: | F25: ='Expenditure Breakdown'!J2-'Expenditure Tracking'!F5 -> 0 | G25: ='Expenditure Breakdown'!#REF!-G5 -> #REF! | H25: ='Expenditure Breakdown'!X2-J5 -> 0 | I25: ='Expenditure Breakdown'!#REF!-I5 -> #REF! | J25: ='Expenditure Breakdown'!X2-J5 -> 0
A27: Copy amounts in column H and paste as values at Project review.

Sheet Expenditure Breakdown
B2: COSTED EXPENDITURE BREAKDOWN | J2: =SUM(J6:J132) -> 2105194.2 | K2: =SUM(K6:K132) -> 2506224.1 | M2: ACTUAL EXPENDITURE BREAKDOWN | S2: FINANCE ONLY | X2: =SUM(X6:X132) -> 2103862.1
B4: No. | C4: Product / Service | D4: Description of Work | E4: QTY | F4: Rate / Unit | G4: Budget Total | H4: Project Related date | J4: Total COS | K4: =IF(K2-'Revenue Tracking'!D4>=0, "Total Revenue", "ERROR on REV" ) -> Total Revenue | M4: No. | N4: Product/ Service | O4: Description of Work | P4: QTY | Q4: Rate / Unit | R4: Actual Total | S4: INVOICE NUMBER | T4: INVOICE RAISED DATE | U4: REVENUE RECOGNITION AMOUNT | V4: CHECK | W4: FINANCE PAYMENT DATE | X4: Total COS | Y4: PO NUMBER | Z4: COMMENTS
B6: 1 | C6: Panels | D6: Longi 570W - Costing Sheet | E6: 438 | F6: 1531.9035 | G6: =E6*F6 -> 670973.73 | H6: ='Project Plan'!E35+60 -> 45636 | J6: =SUM(G6:G11) -> 690973.73 | K6: 842650.89 | M6: 1 | N6: 1. Panels | O6: Canadian Solar 555W - Deposit - Herholdts | P6: 450 | Q6: 1415.25 | R6: =P6*Q6*0.5 -> 318431.25 | S6: Herholdts Inv: INV875402 | T6: 45504 | U6: 396426.72 | V6: =K6-SUM(U6:U11) -> -0.00044532667 | W6: 45562 | X6: =SUM(R6:R11) -> 647765.5 | Y6: PO3244-SAM-20240719 - RV Approved | AA6: 19
B7: 1 | D7: Jinko Solar 575W | M7: 1 | N7: 1. Panels | R7: =P6*Q6*0.5 -> 318431.25 | S7: Herholdts Inv: INV875402 | T7: 45504 | U7: 396426.72 | W7: 45596 | AA7: BUDGET | AB7: Installer Allocation
B8: 1 | M8: 1 | N8: 1. Panels | O8: Storage handling Fee | R8: 1300 | S8: Supply Chain: Inv SCO04502 | T8: 45596 | U8: 1691.1153 | W8: 45625 | AA8: AC Equipment | AB8: =C51 -> 304429.82
B9: 1 | D9: Delivery | G9: 20000 | H9: =H6 -> 45636 | M9: 1 | N9: 1. Panels | O9: Delivery | R9: 8550 | S9: Supply Chain: Inv SCO04533 | T9: 45596 | U9: 11122.335 | W9: 45625 | AA9: DC Equipment | AB9: =SUM(G28:G35) -> 116936.3
B10: 1 | M10: 1 | N10: 1. Panels | O10: Storage | R10: 1053 | S10: Supply Chain: Inv SCO04502 | T10: =T9 -> 45596 | U10: 1369.8034 | W10: 45625 | AA10: AC Labour | AB10: =C79 -> 145635
B11: 1 | M11: 1 | N11: 1. Panels | O11: Delivery and storage budget | T11: 45626 | U11: 35614.21 | AA11: DC Labour | AB11: =C78 -> 62415
AA12: Offloading | AB12: =G96 -> 8500
B13: 2 | C13: Inverters | D13: Huawei 100KTL | E13: 2 | F13: 78898 | G13: =E13*F13 -> 157796 | H13: ='Project Plan'!E22+30 -> 45590 | J13: =SUM(G13:G16) -> 157796 | K13: 192434.15 | M13: 2 | N13: 2. Inverters | O13: Huawei 100KTL | P13: 2 | Q13: 68870 | R13: =P13*Q13 -> 137740 | S13: Kathea Inv518635 | T13: 45565 | U13: 190902.34 | V13: =K13-SUM(U13:U16) -> 0 | W13: =T13+30 -> 45595 | X13: =SUM(R13:R16) -> 138845.23 | Z13: MI: Kathea quote | AA13: Telehandler | AB13: =G86 -> 0
B14: 2 | M14: 2 | N14: 2. Inverters | U14: =(R14/$X$13*$K$13) -> 0 | AA14: Storage | AB14: =G97 -> 0
B15: 2 | M15: 2 | N15: 2. Inverters | O15: Delivery | R15: 1105.23 | S15: Kathea Inv518635 | T15: 45565 | U15: 1531.8063 | W15: =W13 -> 45595 | AA15: =D99 -> Scaffolding | AB15: =G99 -> 29856.3
B16: 2 | M16: 2 | N16: 2. Inverters | U16: =(R16/$X$13*$K$13) -> 0 | AA16: Other | AB16: 0
AA17: Total | AB17: =SUM(AB8:AB16) -> 667772.42
B18: 3 | C18: Mounting Structures | D18: KlipLok Roof | E18: ='Project Plan'!E3*1000 -> 250000 | F18: 0.45 | G18: 99864 | H18: ='Project Plan'!E19+30 -> 45590 | J18: =SUM(G18:G24) -> 99864 | K18: 121785.37 | M18: 3 | N18: 3. Mounting Structures | O18: MS | P18: 1 | Q18: 56499.4 | R18: =P18*Q18 -> 56499.4 | S18: Schletter Inv0891 | T18: 45565 | U18: 117065.68 | V18: =K18-SUM(U18:U24) -> 0 | W18: 45558 | X18: =SUM(R18:R24) -> 169924.22 | Y18: PO3364-SAM22-20240918 - RV Approved | AA18: Less 15% | AB18: =+AB17*0.85 -> 567606.56 | AF18: 62178.86
B19: 3 | M19: 3 | N19: 3. Mounting Structures | R19: -56499.4 | S19: Schletter Inv0891 | T19: 45657 | U19: 0 | W19: 45657 | AA19: R/Wp | AB19: =+AB18/'Project Plan'!$E$3/1000 -> 2.2704262
M20: 3 | N20: 3. Mounting Structures | R20: 44229.04 | S20: Schletter Inv0891 | T20: 45657 | W20: 45657
B21: 3 | M21: 3 | N21: 3. Mounting Structures | O21: Delivery | R21: 1850 | S21: Schletter Inv0893 | T21: 45565 | U21: 3833.1648 | W21: =W18 -> 45558
M22: 3 | N22: 3. Mounting Structures | O22: Seam Clamps | R22: 155413 | S22: Schletter Inv: INV1051 | T22: 45626 | U22: 0 | W22: 45645
M23: 3 | N23: 3. Mounting Structures | O23: Seam Clamp Returned | R23: -31995.68 | S23: Schletter Credit: CRN0160 | T23: 45626 | W23: 45645
B24: 3 | M24: 3 | N24: 3. Mounting Structures | R24: 427.86 | S24: DSV Inv: 180099596 | T24: 45596 | U24: 886.51779 | W24: 45625 | AA24: ACTUAL - Cosmic Sun | AB24: Installer Price | AE24: ACTUAL - Thula Moya | AF24: Installer Price | AH24: ACTUAL - CornerStone | AI24: Installer Price
T25: =IF(W25>1,EOMONTH(W25,-1),"") | AA25: AC Equipment | AB25: 79400 | AE25: AC Equipment | AF25: 146732 | AH25: AC Equipment | AI25: =55724.24+6662.03 -> 62386.27 | AJ25: *Removed 6 Comms Metering R25976,34
B26: 4 | C26: DC Equipment | D26: DC Cable | E26: 6133 | F26: 16 | G26: =E26*F26 -> 98128 | H26: ='Project Plan'!E31+30 -> 45590 | J26: =SUM(G26:G35) -> 237064.3 | K26: 289102.8 | M26: 4 | N26: 4. DC Equipment | O26: DC Cable | P26: 8000 | Q26: 13.5 | R26: =P26*Q26 -> 108000 | S26: Herholdts Inv: INV922149 | T26: 45596 | U26: 128887.94 | V26: =K26-SUM(U26:U35) -> 0 | W26: 45596 | X26: =SUM(R26:R35) -> 242250 | Y26: PO3315-MUL-20240823 - RV Approved | Z26: MI: Herholdts quote | AA26: DC Equipment | AB26: 84262.4 | AE26: DC Equipment | AF26: 134250 | AH26: DC Equipment | AI26: 145954.74
B27: 4 | D27: DC Surge Arrestor | E27: 4 | F27: 5500 | G27: =E27*F27 -> 22000 | H27: =H28 -> 45606 | M27: 4 | N27: 4. DC Equipment | O27: Delivery | R27: 0 | U27: =(R27/$X$26*$K$26) -> 0 | AA27: AC Labour | AB27: 62500 | AE27: AC Labour | AF27: 62504 | AH27: AC Labour | AI27: 15154.29
B28: 4 | D28: DC Cable Tray | E28: 220 | F28: 152 | G28: =E28*F28 -> 33440 | H28: ='Project Plan'!E34+30 -> 45606 | M28: 4 | N28: 4. DC Equipment | O28: Project Kick Off | P28: =AF26 -> 134250 | Q28: 0.1 | R28: =$P$28*Q28 -> 13425 | S28: Thula Moya Inv04436 | T28: =T77 -> 45565 | U28: 16021.487 | W28: =W77 -> 45560 | Y28: PO3367-SAM22-20240924 - RV Approved | AA28: DC Labour | AB28: 149000 | AC28: =SUM(AB27:AB28)/250000 -> 0.846 | AE28: DC Labour | AF28: 112509.8 | AG28: =SUM(AF27:AF28)/250000 -> 0.7000552 | AH28: DC Labour | AI28: 191994.01 | AJ28: =SUM(AI27:AI28)/250000 -> 0.8285932
B29: 4 | D29: Earth Cable | E29: =E26 -> 6133 | F29: 13.5 | G29: =E29*F29 -> 82795.5 | H29: =H18 -> 45590 | M29: 4 | N29: 4. DC Equipment | O29: Site Establishment | Q29: 0.15 | R29: =$P$28*Q29 -> 20137.5 | S29: Thula Moya Inv04439 | T29: =T78 -> 45565 | U29: 24032.23 | W29: =W78 -> 45575 | AA29: Offloading | AB29: 8500 | AE29: Site Logistics | AF29: 47669 | AH29: Site Logistics | AI29: =76775.4+15381.6 -> 92157
B30: 4 | D30: Earth clamp | E30: 43.8 | F30: 16 | G30: =E30*F30 -> 700.8 | H30: ='Project Plan'!E35 -> 45576 | M30: 4 | N30: 4. DC Equipment | O30: AC Installation Complete | Q30: 0.2 | R30: =$P$28*Q30 -> 26850 | S30: Thula Moya IN04473 | T30: =T79 -> 45596 | U30: 32042.973 | W30: =W79 -> 45596 | AA30: Roof Access | AB30: 15000 | AE30: Sundries | AF30: 14986 | AH30: HSE | AI30: 7027.8
B31: 4 | M31: 4 | N31: 4. DC Equipment | O31: DC Installation Complete | Q31: 0.25 | R31: =$P$28*Q31 -> 33562.5 | S31: Thula Moya IN04474 | T31: =T80 -> 45596 | U31: 40053.717 | W31: =W80 -> 45596 | AA31: Container | AB31: 8500 | AE31: Accomodation | AF31: 45112 | AH31: COC | AI31: 3978
B32: 4 | M32: 4 | N32: 4. DC Equipment | O32: Commissioning Complete | Q32: 0.1 | R32: =$P$28*Q32 -> 13425 | S32: Thula Moya IN04475 | T32: 45596 | U32: 16021.487 | W32: =W81 -> 45610 | AA32: HSE | AB32: 4500 | AE32: Scaffolding | AF32: 0 | AH32: Travel | AI32: 17801.55
B33: 4 | M33: 4 | N33: 4. DC Equipment | O33: Site De-establisment | Q33: 0.1 | R33: =$P$28*Q33 -> 13425 | S33: Thula Moya IN04476 | T33: 45596 | U33: 16021.487 | W33: =W82 -> 45631 | AA33: Other | AB33: 0 | AE33: Other | AF33: 0 | AH33: Other | AI33: 0
B34: 4 | M34: 4 | N34: 4. DC Equipment | O34: Handover Document Complete | Q34: 0.05 | R34: =$P$28*Q34 -> 6712.5 | S34: =S83 -> Thula Moya IN04598 | T34: =T83 -> 45688 | U34: 8010.7434 | W34: =W83 -> 45701 | AA34: Other | AB34: 0 | AE34: Other | AF34: 0 | AH34: Other | AI34: 0
B35: 4 | M35: 4 | N35: 4. DC Equipment | O35: End of Defects Period | Q35: 0.05 | R35: =$P$28*Q35 -> 6712.5 | S35: =S84 -> Thula Moya IN04599 | T35: =T84 -> 45688 | U35: 8010.7434 | W35: =W84 -> 45722 | AA35: Other | AB35: 0 | AE35: Other | AF35: 0 | AH35: Other | AI35: 0
T36: =IF(W36>1,EOMONTH(W36,-1),"") | AA36: Total | AB36: =SUM(AB25:AB35) -> 411662.4 | AE36: Total | AF36: =SUM(AF25:AF35) -> 563762.8 | AH36: Total | AI36: =SUM(AI25:AI35) -> 536453.66
B37: 5 | C37: Monitoring | D37: Smartlogger 3000 | E37: 1 | F37: 26000 | G37: =F37*E37 -> 26000 | H37: =H13 -> 45590 | J37: =SUM(G37:G42) -> 49000 | K37: 59756.098 | M37: 5 | N37: 5. Monitoring | O37: Smartlogger 3000 | P37: 1 | Q37: 8000 | R37: =Q37*P37 -> 8000 | S37: Solarworld SASIV-24-00517 | T37: 45535 | U37: 5922.2723 | V37: =K37-SUM(U37:U42) -> 0.00081832578 | W37: =T37+30 -> 45565 | X37: =SUM(R37:R42) -> 71452.01 | Z37: MI: Kathea quote | AA37: R/Wp | AB37: =+AB36/'Project Plan'!$E$3/1000 -> 1.6466496 | AE37: R/Wp | AF37: =+AF36/'Project Plan'!$E$3/1000 -> 2.2550512 | AH37: R/Wp | AI37: =+AI36/'Project Plan'!$E$3/1000 -> 2.1458146
B38: 5 | D38: Comms DB | G38: 8000 | H38: =H37 -> 45590 | M38: 5 | N38: 5. Monitoring | O38: CTs | R38: 13970.5 | S38: AccuEnergy ASAI-003743 | T38: 45535 | U38: 10342.138 | W38: =T38+30 -> 45565
B39: 5 | D39: Revenue Grade Meter | E39: 1 | F39: 15000 | G39: =F39*E39 -> 15000 | H39: ='Project Plan'!G51 -> 45618 | M39: 5 | N39: 5. Monitoring | O39: Revenue Grade Meter | P39: 1 | Q39: 11169 | R39: =Q39*P39 -> 11169 | S39: MATRIARCH - INV-3278 | T39: 45626 | U39: 11797.237 | W39: 45626
B40: 5 | M40: 5 | N40: 5. Monitoring | O40: SCADA | R40: 35750 | S40: Rubicon INVWCRE-0060133 | T40: 45535 | U40: 26465.154 | W40: 45562
B41: 5 | M41: 5 | N41: 5. Monitoring | O41: Frontline Comms Equipment | R41: =12812.55/5 -> 2562.51 | S41: Frontline Electrical: INV697940 | T41: 45596 | U41: 5229.2951 | W41: 45575 | Y41: PO3387-SAM-20241007 - RV Approved | Z41: PO split across the portfolio
B42: 5 | M42: 5 | N42: 5. Monitoring | T42: =IF(W42>1,EOMONTH(W42,-1),"") | U42: =(R42/$X$37*$K$37) -> 0
T43: =IF(W43>1,EOMONTH(W43,-1),"")
B44: 6 | C44: AC Equipment | J44: =SUM(G44:G57) -> 304429.82 | K44: 371255.87 | M44: 6 | N44: 6. AC Equipment | T44: =IF(W44>1,EOMONTH(W44,-1),"") | U44: =(R44/$X$44*$K$44) -> 0 | V44: =K44-SUM(U44:U57) -> -0.0027590452 | X44: =SUM(R44:R57) -> 212863.6
M45: 1 | N45: 6. AC Equipment | O45: AC & Comms Board - Deposit | P45: 0.4 | Q45: 65700 | R45: =Q45*P45 -> 26280 | S45: Cosmic Sun CS_SAMPVDB_001 | T45: 45565 | U45: 45928.238 | W45: 45562 | Y45: PO3375-SAMPort-20240930 - RV Approved
M46: 2 | N46: 6. AC Equipment | O46: AC & Comms Board - Balance | P46: 0.6 | R46: =Q45*P46 -> 39420 | S46: Cosmic Sun CS_SAMPVDB_002 | T46: 45596 | U46: =(R46/$X$44*$K$44) -> 68752.509 | W46: 45596
M47: 3 | N47: 6. AC Equipment | O47: Copper Stub Fabrication | R47: 0 | U47: 0 | Y47: PO3845-SAM14B-20250430 - RV Approved
M48: 4 | N48: 6. AC Equipment | O48: AC Cable | R48: 432.1 | S48: Gerhard Exp Claim | T48: 45808 | U48: 139.85 | W48: 45817
M49: 5 | N49: 6. AC Equipment | T49: =T76 | U49: =(R49/$X$44*$K$44) -> 0
B50: 6 | D50: Project Kick Off | F50: 0.1 | G50: =$C$51*F50 -> 30442.982 | H50: =H83 -> 45635 | M50: 6 | N50: 6. AC Equipment | O50: Project Kick Off | P50: =AF25 -> 146732 | Q50: 0.1 | R50: =$P$50*Q50 -> 14673.2 | S50: Thula Moya Inv04436 | T50: 45565 | U50: 25643.615 | W50: 45560 | Y50: PO3367-SAM22-20240924 - RV Approved
B51: 6 | C51: 304429.82 | D51: Site Establishment | F51: 0.15 | G51: =$C$51*F51 -> 45664.473 | H51: =H78 -> 45560 | M51: 6 | N51: 6. AC Equipment | O51: Site Establishment | Q51: 0.15 | R51: 22009.3 | S51: Thula Moya Inv04439 | T51: =T78 -> 45565 | U51: 38464.549 | W51: =W78 -> 45575
B52: 6 | D52: AC Installation Complete | F52: 0.2 | G52: =$C$51*F52 -> 60885.964 | H52: =H79 -> 45597 | M52: 6 | N52: 6. AC Equipment | O52: AC Installation Complete | Q52: 0.2 | R52: =$P$50*Q52 -> 29346.4 | S52: Thula Moya IN04473 | T52: =T79 -> 45596 | U52: 51287.231 | W52: =W79 -> 45596
B53: 6 | D53: DC Installation Complete | F53: 0.25 | G53: =$C$51*F53 -> 76107.455 | H53: =H80 -> 45597 | M53: 6 | N53: 6. AC Equipment | O53: DC Installation Complete | Q53: 0.25 | R53: =$P$50*Q53 -> 36683 | S53: Thula Moya IN04474 | T53: 45596 | U53: 64109.039 | W53: =W80 -> 45596
B54: 6 | D54: Commissioning Complete | F54: 0.1 | G54: =$C$51*F54 -> 30442.982 | H54: =H81 -> 45609 | M54: 6 | N54: 6. AC Equipment | O54: Commissioning Complete | Q54: 0.1 | R54: =$P$50*Q54 -> 14673.2 | S54: Thula Moya IN04475 | T54: 45596 | U54: 25643.615 | W54: =W81 -> 45610
B55: 6 | D55: Site De-establisment | F55: 0.1 | G55: =$C$51*F55 -> 30442.982 | H55: =H82 -> 45628 | M55: 6 | N55: 6. AC Equipment | O55: Site De-establisment | Q55: 0.1 | R55: =$P$50*Q55 -> 14673.2 | S55: Thula Moya IN04476 | T55: 45596 | U55: 25643.615 | W55: =W82 -> 45631
B56: 6 | D56: Handover Document Complete | F56: 0.05 | G56: =$C$51*F56 -> 15221.491 | H56: =H83 -> 45635 | M56: 6 | N56: 6. AC Equipment | O56: Handover Document Complete | Q56: 0.05 | R56: =$P$50*Q56 -> 7336.6 | S56: =S83 -> Thula Moya IN04598 | T56: =T83 -> 45688 | U56: 12821.808 | W56: =W83 -> 45701
B57: 6 | D57: End of Defects Period | F57: 0.05 | G57: =$C$51*F57 -> 15221.491 | H57: =H84 -> 45665 | M57: 6 | N57: 6. AC Equipment | O57: End of Defects Period | Q57: 0.05 | R57: =$P$50*Q57 -> 7336.6 | S57: =S95 -> Thula Moya IN04599 | T57: =T84 -> 45688 | U57: 12821.808 | W57: =W84 -> 45722
T58: =IF(W58>1,EOMONTH(W58,-1),"")
B59: 7 | C59: Battery Systems | J59: =SUM(G59:G66) -> 0 | K59: 0 | M59: 7 | N59: Battery Systems | T59: =IF(W59>1,EOMONTH(W59,-1),"") | V59: =K59-SUM(U59:U66) -> 0 | X59: =SUM(R59:R66) -> 0
B60: 7 | M60: 7 | T60: =IF(W60>1,EOMONTH(W60,-1),"")
B61: 7 | M61: 7 | T61: =IF(W61>1,EOMONTH(W61,-1),"")
B62: 7 | M62: 7 | T62: =IF(W62>1,EOMONTH(W62,-1),"")
B63: 7 | M63: 7 | T63: =IF(W63>1,EOMONTH(W63,-1),"")
B64: 7 | M64: 7 | T64: =IF(W64>1,EOMONTH(W64,-1),"")
B65: 7 | M65: 7 | T65: =IF(W65>1,EOMONTH(W65,-1),"")
B66: 7 | M66: 7 | T66: =IF(W66>1,EOMONTH(W66,-1),"")
T67: =IF(W67>1,EOMONTH(W67,-1),"")
B68: 8 | C68: Product Add On | J68: =SUM(G68:G75) -> 0 | K68: 43965.12 | M68: 8 | N68: 8. Product Add On | O68: Walkways transport | R68: 4025 | S68: Onvlee Engineering:Inv 01048652 | T68: 45596 | U68: 0 | V68: =K68-SUM(U68:U75) -> 0 | W68: 45575 | X68: =SUM(R68:R75) -> 158729.52
B69: 8 | M69: 8 | N69: 8. Product Add On | O69: Mounting Structure for Walkways | R69: =21221.6/5 -> 4244.32 | S69: Schletter INV0951 | T69: 45596 | U69: 0 | W69: =T69+29 -> 45625 | Y69: PO3389-SAM-20241008 - RV Approved
B70: 8 | M70: 8 | N70: 8. Product Add On | O70: Walkways | R70: 35695.8 | S70: Onvlee Engineering:Inv 01048652 | T70: =T69 -> 45596 | U70: 0 | W70: 45575 | Y70: PO3390-SAM-20241008 - RV Approved
M71: 8 | N71: 8. Product Add On | T71: 45626 | U71: 43965.12 | W71: 45626
M72: 8 | N72: 8. Product Add On | O72: Installation of walkways | R72: 8316 | S72: Thula Moya IN04600 | T72: 45688 | W72: 45869
B73: 8 | M73: 8 | N73: 8. Product Add On | O73: Manufacture Cages Housing Inverters & DB | R73: 72608.7 | S73: Thula Moya Inv IN04471 | T73: 45596 | U73: 0 | W73: 45596
M74: 8 | N74: 8. Product Add On | O74: Additional walkways | R74: 9538.74 | S74: Onvlee Engineering ONV1485 | T74: 45900 | W74: 45890
B75: 8 | M75: 8 | N75: 8. Product Add On | O75: Supply and install Tie in Breaker - Thula Moya | R75: 24300.96 | S75: Thula Moya IN04486 | T75: 45596 | U75: 0 | W75: 45596 | Y75: PO3434-SAM-20241029 - RV Approved
L76: Only services to be capture below, products above | T76: =IF(W76>1,EOMONTH(W76,-1),"")
B77: 9 | C77: AC & DC Installation | D77: Project Kick Off | F77: 0.1 | G77: =SUM($C$78:$C$79)*F77 -> 20805 | H77: ='Project Plan'!E19-7 -> 45553 | J77: =SUM(G77:G84) -> 208050 | K77: =73429.41176+171335.2941 -> 244764.71 | M77: 9 | N77: 9. AC & DC installation | O77: Project Kick Off | P77: =AF27+AF28 -> 175013.8 | Q77: 0.1 | R77: =$P$77*Q77 -> 17501.38 | S77: Thula Moya Inv04436 | T77: 45565 | U77: 24476.471 | V77: 0 | W77: 45560 | X77: =SUM(R77:R84) -> 175013.8 | Y77: PO3367-SAM22-20240924 - RV Approved
B78: 9 | C78: 62415 | D78: Site Establishment | F78: 0.15 | G78: =SUM($C$78:$C$79)*F78 -> 31207.5 | H78: ='Project Plan'!I19 -> 45560 | M78: 9 | N78: 9. AC & DC installation | O78: Site Establishment | Q78: 0.15 | R78: =$P$77*Q78 -> 26252.07 | S78: Thula Moya Inv04439 | T78: 45565 | U78: 36714.706 | W78: 45575
B79: 9 | C79: 145635 | D79: AC Installation Complete | F79: 0.2 | G79: =SUM($C$78:$C$79)*F79 -> 41610 | H79: ='Project Plan'!G21 -> 45597 | M79: 9 | N79: 9. AC & DC installation | O79: AC Installation Complete | Q79: 0.2 | R79: =$P$77*Q79 -> 35002.76 | S79: Thula Moya IN04473 | T79: 45596 | U79: 48952.941 | W79: 45596
B80: 9 | D80: DC Installation Complete | F80: 0.25 | G80: =SUM($C$78:$C$79)*F80 -> 52012.5 | H80: ='Project Plan'!G28 -> 45597 | M80: 9 | N80: 9. AC & DC installation | O80: DC Installation Complete | Q80: 0.25 | R80: =$P$77*Q80 -> 43753.45 | S80: Thula Moya IN04474 | T80: 45596 | U80: 61191.176 | W80: =W79 -> 45596
B81: 9 | D81: Commissioning Complete | F81: 0.1 | G81: =SUM($C$78:$C$79)*F81 -> 20805 | H81: ='Project Plan'!G38 -> 45609 | M81: 9 | N81: 9. AC & DC installation | O81: Commissioning Complete | Q81: 0.1 | R81: =$P$77*Q81 -> 17501.38 | S81: Thula Moya IN04475 | T81: 45596 | U81: 24476.471 | W81: 45610
B82: 9 | D82: Site De-establisment | F82: 0.1 | G82: =SUM($C$78:$C$79)*F82 -> 20805 | H82: ='Project Plan'!G47 -> 45628 | M82: 9 | N82: 9. AC & DC installation | O82: Site De-establisment | Q82: 0.1 | R82: =$P$77*Q82 -> 17501.38 | S82: Thula Moya IN04476 | T82: 45596 | U82: 24476.471 | W82: 45631
B83: 9 | D83: Handover Document Complete | F83: 0.05 | G83: =SUM($C$78:$C$79)*F83 -> 10402.5 | H83: ='Project Plan'!G49 -> 45635 | M83: 9 | N83: 9. AC & DC installation | O83: Handover Document Complete | Q83: 0.05 | R83: =$P$77*Q83 -> 8750.69 | S83: Thula Moya IN04598 | T83: 45688 | U83: 12238.235 | W83: 45701
B84: 9 | D84: End of Defects Period | F84: 0.05 | G84: =SUM($C$78:$C$79)*F84 -> 10402.5 | H84: =H83+30 -> 45665 | M84: 9 | N84: 9. AC & DC installation | O84: End of Defects Period | Q84: 0.05 | R84: =$P$77*Q84 -> 8750.69 | S84: Thula Moya IN04599 | T84: 45688 | U84: 12238.235 | W84: 45722
T85: =IF(W85>1,EOMONTH(W85,-1),"")
B86: 10 | C86: Site Logistics | J86: =SUM(G86:G99) -> 38356.3 | K86: =10000+35125.05882 -> 45125.059 | M86: 10 | N86: 10. Site Logistics | O86: Security | U86: =R86/$X$86*$K$86 -> 0 | V86: =K86-SUM(U86:U99) -> -0.0049433887 | X86: =SUM(R86:R99) -> 107767
M87: 10 | N87: 10. Site Logistics | T87: =IF(W87>1,EOMONTH(W87,-1),"") | U87: =R87/$X$86*$K$86 -> 0
M88: 10 | N88: 10. Site Logistics | O88: Project Kick Off | P88: =AF29+AF30+AF31 -> 107767 | Q88: 0.1 | R88: =$P$88*Q88 -> 10776.7 | S88: Thula Moya Inv04436 | T88: 45565 | U88: 3961.1559 | W88: 45560 | Y88: PO3367-SAM22-20240924 - RV Approved
M89: 10 | N89: 10. Site Logistics | O89: Site Establishment | Q89: 0.15 | R89: =$P$88*Q89 -> 16165.05 | S89: Thula Moya Inv04439 | T89: =T78 -> 45565 | U89: 5941.7338 | W89: =W78 -> 45575
M90: 10 | N90: 10. Site Logistics | O90: AC Installation Complete | Q90: 0.2 | R90: =$P$88*Q90 -> 21553.4 | S90: Thula Moya IN04473 | T90: =T79 -> 45596 | U90: 10403.392 | W90: =W79 -> 45596
M91: 10 | N91: 10. Site Logistics | O91: DC Installation Complete | Q91: 0.25 | R91: =$P$88*Q91 -> 26941.75 | S91: Thula Moya IN04474 | T91: 45596 | U91: 11281.265 | W91: =W80 -> 45596
M92: 10 | N92: 10. Site Logistics | O92: Commissioning Complete | Q92: 0.1 | R92: =$P$88*Q92 -> 10776.7 | S92: Thula Moya IN04475 | T92: 45596 | U92: 4512.5059 | W92: =W81 -> 45610
M93: 10 | N93: 10. Site Logistics | O93: Site De-establisment | Q93: 0.1 | R93: =$P$88*Q93 -> 10776.7 | S93: Thula Moya IN04476 | T93: 45596 | U93: =R93/$X$86*$K$86 -> 4512.5059 | W93: =W82 -> 45631
M94: 10 | N94: 10. Site Logistics | O94: Handover Document Complete | Q94: 0.05 | R94: =$P$88*Q94 -> 5388.35 | S94: =S83 -> Thula Moya IN04598 | T94: =T83 -> 45688 | U94: 2256.2529 | W94: =W83 -> 45701
M95: 10 | N95: 10. Site Logistics | O95: End of Defects Period | Q95: 0.05 | R95: =$P$88*Q95 -> 5388.35 | S95: =S84 -> Thula Moya IN04599 | T95: =T84 -> 45688 | U95: 2256.2529 | W95: =W84 -> 45722
B96: 10 | D96: Offloading | G96: 8500 | H96: =H81 -> 45609 | M96: 10 | N96: 10. Site Logistics | T96: =IF(W96>1,EOMONTH(W96,-1),"") | U96: =R96/$X$86*$K$86 -> 0
B97: 10 | M97: 10 | N97: 10. Site Logistics | T97: =IF(W97>1,EOMONTH(W97,-1),"") | U97: =R97/$X$86*$K$86 -> 0
B98: 10 | M98: 10 | N98: 10. Site Logistics | T98: =IF(W98>1,EOMONTH(W98,-1),"") | U98: =R98/$X$86*$K$86 -> 0
B99: 10 | D99: Scaffolding | G99: 29856.3 | H99: =H96 -> 45609 | M99: 10 | N99: 10. Site Logistics | T99: =IF(W99>1,EOMONTH(W99,-1),"") | U99: =R99/$X$86*$K$86 -> 0
T100: =IF(W100>1,EOMONTH(W100,-1),"")
B101: 11 | C101: Due Dilligence | D101: Electrical PrEng sign off | G101: 11000 | H101: ='Project Plan'!E51 -> 45617 | J101: =SUM(G101:G105) -> 89000 | K101: 104705.88 | M101: 11 | N101: 11. Due Dilligence | O101: Electrical PrEng sign off | R101: 5654.76 | S101: Sun Spot Inv E005 | T101: 45626 | U101: 48923.028 | V101: =K101-SUM(U101:U105) -> -0.0014126527 | W101: 45673 | X101: =SUM(R101:R105) -> 14174.76
B102: 11 | D102: Structural sign off | G102: 18000 | H102: ='Project Plan'!E19 -> 45560 | M102: 11 | N102: 11. Due Dilligence | O102: Structural sign off | R102: 2520 | S102: L&B Consulting Inv1742 | T102: 45535 | U102: 11462.156 | W102: 45537
B103: 11 | D103: SCADA - COCT | G103: 60000 | H103: =H102+30 -> 45590 | M103: 11 | N103: 11. Due Dilligence | T103: =IF(W103>1,EOMONTH(W103,-1),"") | U103: =R103/$X$101*$K$101 -> 0
...

Sheet Cashflow
D1: [RT: Double Check the first date is always a MONDAY] | F1: 45488 | G1: =F1+7 -> 45495 | H1: =G1+7 -> 45502 | I1: =H1+7 -> 45509 | J1: =I1+7 -> 45516 | K1: =J1+7 -> 45523 | L1: =K1+7 -> 45530 | M1: =L1+7 -> 45537 | N1: =M1+7 -> 45544 | ... CC1: =CB1+7 -> 46013
A2: PLANNED | C2: CHECK | D2: CHECK
B3: Planned Revenue | C3: ='Revenue Tracking'!D4 -> 2462259 | D3: =SUM(F3:CC3) -> 2514540.1 | F3: =SUMIFS('Revenue Tracking'!$F$13:$F$19, 'Revenue Tracking'!$H$13:$H$19, ">="&F1,'Revenue Tracking'!$H$13:$H$19, "<"&G1) -> 861790.65 | G3: =SUMIFS('Revenue Tracking'!$F$13:$F$19, 'Revenue Tracking'!$H$13:$H$19, ">="&G1,'Revenue Tracking'!$H$13:$H$19, "<"&H1) -> 0 | H3: =SUMIFS('Revenue Tracking'!$F$13:$F$19, 'Revenue Tracking'!$H$13:$H$19, ">="&H1,'Revenue Tracking'!$H$13:$H$19, "<"&I1) -> 0 | I3: =SUMIFS('Revenue Tracking'!$F$13:$F$19, 'Revenue Tracking'!$H$13:$H$19, ">="&I1,'Revenue Tracking'!$H$13:$H$19, "<"&J1) -> 0 | J3: =SUMIFS('Revenue Tracking'!$F$13:$F$19, 'Revenue Tracking'!$H$13:$H$19, ">="&J1,'Revenue Tracking'!$H$13:$H$19, "<"&K1) -> 0 | K3: =SUMIFS('Revenue Tracking'!$F$13:$F$19, 'Revenue Tracking'!$H$13:$H$19, ">="&K1,'Revenue Tracking'!$H$13:$H$19, "<"&L1) -> 0 | L3: =SUMIFS('Revenue Tracking'!$F$13:$F$19, 'Revenue Tracking'!$H$13:$H$19, ">="&L1,'Revenue Tracking'!$H$13:$H$19, "<"&M1) -> 0 | M3: =SUMIFS('Revenue Tracking'!$F$13:$F$19, 'Revenue Tracking'!$H$13:$H$19, ">="&M1,'Revenue Tracking'!$H$13:$H$19, "<"&N1) -> 0 | ... CA3: =SUMIFS('Revenue Tracking'!$F$13:$F$19, 'Revenue Tracking'!$H$13:$H$19, ">="&CA1,'Revenue Tracking'!$H$13:$H$19, "<"&CB1) -> 0 | CB3: =SUMIFS('Revenue Tracking'!$F$13:$F$19, 'Revenue Tracking'!$H$13:$H$19, ">="&CB1,'Revenue Tracking'!$H$13:$H$19, "<"&CD1) -> 0 | CC3: =SUMIFS('Revenue Tracking'!$F$13:$F$19, 'Revenue Tracking'!$H$13:$H$19, ">="&CC1,'Revenue Tracking'!$H$13:$H$19, "<"&CE1) -> 0
B4: Planned Revenue - Cumulative | F4: =F3 -> 861790.65 | G4: =F4+G3 -> 861790.65 | H4: =G4+H3 -> 861790.65 | I4: =H4+I3 -> 861790.65 | J4: =I4+J3 -> 861790.65 | K4: =J4+K3 -> 861790.65 | L4: =K4+L3 -> 861790.65 | M4: =L4+M3 -> 861790.65 | N4: =M4+N3 -> 861790.65 | ... CC4: =CB4+CC3 -> 2514540.1
B5: Planned Expenditure | C5: ='Revenue Tracking'!D5 -> 2105194.2 | D5: =SUM(F5:CC5) -> 2105194.2 | F5: =SUMIFS('Expenditure Breakdown'!$G$6:$G$131, 'Expenditure Breakdown'!$H$6:$H$131, ">="&F1,'Expenditure Breakdown'!$H$6:$H$131, "<"&G1) -> 0 | G5: =SUMIFS('Expenditure Breakdown'!$G$6:$G$131, 'Expenditure Breakdown'!$H$6:$H$131, ">="&G1,'Expenditure Breakdown'!$H$6:$H$131, "<"&H1) -> 0 | H5: =SUMIFS('Expenditure Breakdown'!$G$6:$G$131, 'Expenditure Breakdown'!$H$6:$H$131, ">="&H1,'Expenditure Breakdown'!$H$6:$H$131, "<"&I1) -> 0 | I5: =SUMIFS('Expenditure Breakdown'!$G$6:$G$131, 'Expenditure Breakdown'!$H$6:$H$131, ">="&I1,'Expenditure Breakdown'!$H$6:$H$131, "<"&J1) -> 0 | J5: =SUMIFS('Expenditure Breakdown'!$G$6:$G$131, 'Expenditure Breakdown'!$H$6:$H$131, ">="&J1,'Expenditure Breakdown'!$H$6:$H$131, "<"&K1) -> 0 | K5: =SUMIFS('Expenditure Breakdown'!$G$6:$G$131, 'Expenditure Breakdown'!$H$6:$H$131, ">="&K1,'Expenditure Breakdown'!$H$6:$H$131, "<"&L1) -> 0 | L5: =SUMIFS('Expenditure Breakdown'!$G$6:$G$131, 'Expenditure Breakdown'!$H$6:$H$131, ">="&L1,'Expenditure Breakdown'!$H$6:$H$131, "<"&M1) -> 0 | M5: =SUMIFS('Expenditure Breakdown'!$G$6:$G$131, 'Expenditure Breakdown'!$H$6:$H$131, ">="&M1,'Expenditure Breakdown'!$H$6:$H$131, "<"&N1) -> 0 | ... CA5: =SUMIFS('Expenditure Breakdown'!$G$6:$G$131, 'Expenditure Breakdown'!$H$6:$H$131, ">="&CA1,'Expenditure Breakdown'!$H$6:$H$131, "<"&CB1) -> 0 | CB5: =SUMIFS('Expenditure Breakdown'!$G$6:$G$131, 'Expenditure Breakdown'!$H$6:$H$131, ">="&CB1,'Expenditure Breakdown'!$H$6:$H$131, "<"&CD1) -> 0 | CC5: =SUMIFS('Expenditure Breakdown'!$G$6:$G$131, 'Expenditure Breakdown'!$H$6:$H$131, ">="&CC1,'Expenditure Breakdown'!$H$6:$H$131, "<"&CE1) -> 0
B6: Planned Expenditure - Cumulative | F6: =F5 -> 0 | G6: =F6+G5 -> 0 | H6: =G6+H5 -> 0 | I6: =H6+I5 -> 0 | J6: =I6+J5 -> 0 | K6: =J6+K5 -> 0 | L6: =K6+L5 -> 0 | M6: =L6+M5 -> 0 | N6: =M6+N5 -> 0 | ... CC6: =CB6+CC5 -> 2105194.2
B7: PLANNED CashFlow | F7: =F4-F6 -> 861790.65 | G7: =G4-G6 -> 861790.65 | H7: =H4-H6 -> 861790.65 | I7: =I4-I6 -> 861790.65 | J7: =J4-J6 -> 861790.65 | K7: =K4-K6 -> 861790.65 | L7: =L4-L6 -> 861790.65 | M7: =M4-M6 -> 861790.65 | ... CC7: =CC4-CC6 -> 409345.97
A8: ACTUAL | C8: CHECK | D8: CHECK
B9: Actual + Planned Revenue | C9: ='Revenue Tracking'!F4 -> 2505210.5 | D9: =SUM(F9:BR9) -> 2339146.1 | F9: =SUMIFS('Revenue Tracking'!$F$13:$F$19, 'Revenue Tracking'!$P$13:$P$19, ">="&F1,'Revenue Tracking'!$P$13:$P$19, "<"&G1) -> 861790.65 | G9: =SUMIFS('Revenue Tracking'!$F$13:$F$19, 'Revenue Tracking'!$P$13:$P$19, ">="&G1,'Revenue Tracking'!$P$13:$P$19, "<"&H1) -> 0 | H9: =SUMIFS('Revenue Tracking'!$F$13:$F$19, 'Revenue Tracking'!$P$13:$P$19, ">="&H1,'Revenue Tracking'!$P$13:$P$19, "<"&I1) -> 0 | I9: =SUMIFS('Revenue Tracking'!$F$13:$F$19, 'Revenue Tracking'!$P$13:$P$19, ">="&I1,'Revenue Tracking'!$P$13:$P$19, "<"&J1) -> 0 | J9: =SUMIFS('Revenue Tracking'!$F$13:$F$19, 'Revenue Tracking'!$P$13:$P$19, ">="&J1,'Revenue Tracking'!$P$13:$P$19, "<"&K1) -> 0 | K9: =SUMIFS('Revenue Tracking'!$F$13:$F$19, 'Revenue Tracking'!$P$13:$P$19, ">="&K1,'Revenue Tracking'!$P$13:$P$19, "<"&L1) -> 0 | L9: =SUMIFS('Revenue Tracking'!$F$13:$F$19, 'Revenue Tracking'!$P$13:$P$19, ">="&L1,'Revenue Tracking'!$P$13:$P$19, "<"&M1) -> 0 | M9: =SUMIFS('Revenue Tracking'!$F$13:$F$19, 'Revenue Tracking'!$P$13:$P$19, ">="&M1,'Revenue Tracking'!$P$13:$P$19, "<"&N1) -> 0 | ... CA9: =SUMIFS('Revenue Tracking'!$F$13:$F$19, 'Revenue Tracking'!$P$13:$P$19, ">="&CA1,'Revenue Tracking'!$P$13:$P$19, "<"&CB1) -> 0 | CB9: =SUMIFS('Revenue Tracking'!$F$13:$F$19, 'Revenue Tracking'!$P$13:$P$19, ">="&CB1,'Revenue Tracking'!$P$13:$P$19, "<"&CD1) -> 0 | CC9: =SUMIFS('Revenue Tracking'!$F$13:$F$19, 'Revenue Tracking'!$P$13:$P$19, ">="&CC1,'Revenue Tracking'!$P$13:$P$19, "<"&CE1) -> 0
B10: Actual + Planned Revenue - Cumulative | F10: =F9 -> 861790.65 | G10: =F10+G9 -> 861790.65 | H10: =G10+H9 -> 861790.65 | I10: =H10+I9 -> 861790.65 | J10: =I10+J9 -> 861790.65 | K10: =J10+K9 -> 861790.65 | L10: =K10+L9 -> 861790.65 | M10: =L10+M9 -> 861790.65 | N10: =M10+N9 -> 861790.65 | ... CC10: =CB10+CC9 -> 2514540.1
B11: Actual + Planned Expenditure | C11: ='Revenue Tracking'!F5 -> 2103862.1 | D11: =SUM(F11:BR11) -> 2103862.1 | F11: =SUMIFS('Expenditure Breakdown'!$R$6:$R$131, 'Expenditure Breakdown'!$W$6:$W$131, ">="&F1,'Expenditure Breakdown'!$W$6:$W$131, "<"&G1) -> 0 | G11: =SUMIFS('Expenditure Breakdown'!$R$6:$R$131, 'Expenditure Breakdown'!$W$6:$W$131, ">="&G1,'Expenditure Breakdown'!$W$6:$W$131, "<"&H1) -> 0 | H11: =SUMIFS('Expenditure Breakdown'!$R$6:$R$131, 'Expenditure Breakdown'!$W$6:$W$131, ">="&H1,'Expenditure Breakdown'!$W$6:$W$131, "<"&I1) -> 0 | I11: =SUMIFS('Expenditure Breakdown'!$R$6:$R$131, 'Expenditure Breakdown'!$W$6:$W$131, ">="&I1,'Expenditure Breakdown'!$W$6:$W$131, "<"&J1) -> 0 | J11: =SUMIFS('Expenditure Breakdown'!$R$6:$R$131, 'Expenditure Breakdown'!$W$6:$W$131, ">="&J1,'Expenditure Breakdown'!$W$6:$W$131, "<"&K1) -> 0 | K11: =SUMIFS('Expenditure Breakdown'!$R$6:$R$131, 'Expenditure Breakdown'!$W$6:$W$131, ">="&K1,'Expenditure Breakdown'!$W$6:$W$131, "<"&L1) -> 0 | L11: =SUMIFS('Expenditure Breakdown'!$R$6:$R$131, 'Expenditure Breakdown'!$W$6:$W$131, ">="&L1,'Expenditure Breakdown'!$W$6:$W$131, "<"&M1) -> 0 | M11: =SUMIFS('Expenditure Breakdown'!$R$6:$R$131, 'Expenditure Breakdown'!$W$6:$W$131, ">="&M1,'Expenditure Breakdown'!$W$6:$W$131, "<"&N1) -> 35564.42 | ... CA11: =SUMIFS('Expenditure Breakdown'!$R$6:$R$131, 'Expenditure Breakdown'!$W$6:$W$131, ">="&CA1,'Expenditure Breakdown'!$W$6:$W$131, "<"&CB1) -> 0 | CB11: =SUMIFS('Expenditure Breakdown'!$R$6:$R$131, 'Expenditure Breakdown'!$W$6:$W$131, ">="&CB1,'Expenditure Breakdown'!$W$6:$W$131, "<"&CD1) -> 0 | CC11: =SUMIFS('Expenditure Breakdown'!$R$6:$R$131, 'Expenditure Breakdown'!$W$6:$W$131, ">="&CC1,'Expenditure Breakdown'!$W$6:$W$131, "<"&CE1) -> 0
B12: Actual + Planned Expenditure - Cumulative | F12: =F11 -> 0 | G12: =F12+G11 -> 0 | H12: =G12+H11 -> 0 | I12: =H12+I11 -> 0 | J12: =I12+J11 -> 0 | K12: =J12+K11 -> 0 | L12: =K12+L11 -> 0 | M12: =L12+M11 -> 35564.42 | N12: =M12+N11 -> 35564.42 | ... CC12: =CB12+CC11 -> 2103862.1
B14: ACTUAL CashFlow | F14: =F10-F12 -> 861790.65 | G14: =G10-G12 -> 861790.65 | H14: =H10-H12 -> 861790.65 | I14: =I10-I12 -> 861790.65 | J14: =J10-J12 -> 861790.65 | K14: =K10-K12 -> 861790.65 | L14: =L10-L12 -> 861790.65 | M14: =M10-M12 -> 826226.23 | ... CC14: =CC10-CC12 -> 410678.01
C16: CHECK | D16: CHECK
B17: Revenue Recognition | C17: =C3-D17 -> -43924.244 | D17: =SUM(F17:BE17) -> 2506183.2 | F17: =SUMIFS('Expenditure Breakdown'!$U$6:$U$131, 'Expenditure Breakdown'!$T$6:$T$131, ">="&F1,'Expenditure Breakdown'!$T$6:$T$131, "<"&G1) -> 0 | G17: =SUMIFS('Expenditure Breakdown'!$U$6:$U$131, 'Expenditure Breakdown'!$T$6:$T$131, ">="&G1,'Expenditure Breakdown'!$T$6:$T$131, "<"&H1) -> 0 | H17: =SUMIFS('Expenditure Breakdown'!$U$6:$U$131, 'Expenditure Breakdown'!$T$6:$T$131, ">="&H1,'Expenditure Breakdown'!$T$6:$T$131, "<"&I1) -> 792853.43 | I17: =SUMIFS('Expenditure Breakdown'!$U$6:$U$131, 'Expenditure Breakdown'!$T$6:$T$131, ">="&I1,'Expenditure Breakdown'!$T$6:$T$131, "<"&J1) -> 0 | J17: =SUMIFS('Expenditure Breakdown'!$U$6:$U$131, 'Expenditure Breakdown'!$T$6:$T$131, ">="&J1,'Expenditure Breakdown'!$T$6:$T$131, "<"&K1) -> 0 | K17: =SUMIFS('Expenditure Breakdown'!$U$6:$U$131, 'Expenditure Breakdown'!$T$6:$T$131, ">="&K1,'Expenditure Breakdown'!$T$6:$T$131, "<"&L1) -> 0 | L17: =SUMIFS('Expenditure Breakdown'!$U$6:$U$131, 'Expenditure Breakdown'!$T$6:$T$131, ">="&L1,'Expenditure Breakdown'!$T$6:$T$131, "<"&M1) -> 55191.91 | M17: =SUMIFS('Expenditure Breakdown'!$U$6:$U$131, 'Expenditure Breakdown'!$T$6:$T$131, ">="&M1,'Expenditure Breakdown'!$T$6:$T$131, "<"&N1) -> 0 | ... CA17: =SUMIFS('Expenditure Breakdown'!$U$6:$U$131, 'Expenditure Breakdown'!$T$6:$T$131, ">="&CA1,'Expenditure Breakdown'!$T$6:$T$131, "<"&CB1) -> 0 | CB17: =SUMIFS('Expenditure Breakdown'!$U$6:$U$131, 'Expenditure Breakdown'!$T$6:$T$131, ">="&CB1,'Expenditure Breakdown'!$T$6:$T$131, "<"&CD1) -> 0 | CC17: =SUMIFS('Expenditure Breakdown'!$U$6:$U$131, 'Expenditure Breakdown'!$T$6:$T$131, ">="&CC1,'Expenditure Breakdown'!$T$6:$T$131, "<"&CE1) -> 0
B18: Revenue Recognition Cumulative | C18: =D17-D18 -> 0 | D18: =MAX(F18:BE18) -> 2506183.2 | F18: =F17 -> 0 | G18: =F18+G17 -> 0 | H18: =G18+H17 -> 792853.43 | I18: =H18+I17 -> 792853.43 | J18: =I18+J17 -> 792853.43 | K18: =J18+K17 -> 792853.43 | L18: =K18+L17 -> 848045.34 | M18: =L18+M17 -> 848045.34 | N18: =M18+N17 -> 848045.34 | ... CC18: =CB18+CC17 -> 2506183.2
B20: Installer Expenditure | D20: =SUM(F20:BE20) -> 455995.3 | F20: =SUMIFS('Expenditure Breakdown'!$R$28:$R$35, 'Expenditure Breakdown'!$W$28:$W$35, ">="&F1,'Expenditure Breakdown'!$W$28:$W$35, "<"&G1)+SUMIFS('Expenditure Breakdown'!$R$50:$R$57, 'Expenditure Breakdown'!$W$50:$W$57, ">="&F1,'Expenditure Breakdown'!$W$50:$W$57, "<"&G1)+SUMIFS('Expenditure Breakdown'!$R$77:$R$84, 'Expenditure Breakdown'!$W$77:$W$84, ">="&F1,'Expenditure Breakdown'!$W$77:$W$84, "<"&G1) -> 0 | G20: =SUMIFS('Expenditure Breakdown'!$R$28:$R$35, 'Expenditure Breakdown'!$W$28:$W$35, ">="&G1,'Expenditure Breakdown'!$W$28:$W$35, "<"&H1)+SUMIFS('Expenditure Breakdown'!$R$50:$R$57, 'Expenditure Breakdown'!$W$50:$W$57, ">="&G1,'Expenditure Breakdown'!$W$50:$W$57, "<"&H1)+SUMIFS('Expenditure Breakdown'!$R$77:$R$84, 'Expenditure Breakdown'!$W$77:$W$84, ">="&G1,'Expenditure Breakdown'!$W$77:$W$84, "<"&H1) -> 0 | H20: =SUMIFS('Expenditure Breakdown'!$R$28:$R$35, 'Expenditure Breakdown'!$W$28:$W$35, ">="&H1,'Expenditure Breakdown'!$W$28:$W$35, "<"&I1)+SUMIFS('Expenditure Breakdown'!$R$50:$R$57, 'Expenditure Breakdown'!$W$50:$W$57, ">="&H1,'Expenditure Breakdown'!$W$50:$W$57, "<"&I1)+SUMIFS('Expenditure Breakdown'!$R$77:$R$84, 'Expenditure Breakdown'!$W$77:$W$84, ">="&H1,'Expenditure Breakdown'!$W$77:$W$84, "<"&I1) -> 0 | I20: =SUMIFS('Expenditure Breakdown'!$R$28:$R$35, 'Expenditure Breakdown'!$W$28:$W$35, ">="&I1,'Expenditure Breakdown'!$W$28:$W$35, "<"&J1)+SUMIFS('Expenditure Breakdown'!$R$50:$R$57, 'Expenditure Breakdown'!$W$50:$W$57, ">="&I1,'Expenditure Breakdown'!$W$50:$W$57, "<"&J1)+SUMIFS('Expenditure Breakdown'!$R$77:$R$84, 'Expenditure Breakdown'!$W$77:$W$84, ">="&I1,'Expenditure Breakdown'!$W$77:$W$84, "<"&J1) -> 0 | J20: =SUMIFS('Expenditure Breakdown'!$R$28:$R$35, 'Expenditure Breakdown'!$W$28:$W$35, ">="&J1,'Expenditure Breakdown'!$W$28:$W$35, "<"&K1)+SUMIFS('Expenditure Breakdown'!$R$50:$R$57, 'Expenditure Breakdown'!$W$50:$W$57, ">="&J1,'Expenditure Breakdown'!$W$50:$W$57, "<"&K1)+SUMIFS('Expenditure Breakdown'!$R$77:$R$84, 'Expenditure Breakdown'!$W$77:$W$84, ">="&J1,'Expenditure Breakdown'!$W$77:$W$84, "<"&K1) -> 0 | K20: =SUMIFS('Expenditure Breakdown'!$R$28:$R$35, 'Expenditure Breakdown'!$W$28:$W$35, ">="&K1,'Expenditure Breakdown'!$W$28:$W$35, "<"&L1)+SUMIFS('Expenditure Breakdown'!$R$50:$R$57, 'Expenditure Breakdown'!$W$50:$W$57, ">="&K1,'Expenditure Breakdown'!$W$50:$W$57, "<"&L1)+SUMIFS('Expenditure Breakdown'!$R$77:$R$84, 'Expenditure Breakdown'!$W$77:$W$84, ">="&K1,'Expenditure Breakdown'!$W$77:$W$84, "<"&L1) -> 0 | L20: =SUMIFS('Expenditure Breakdown'!$R$28:$R$35, 'Expenditure Breakdown'!$W$28:$W$35, ">="&L1,'Expenditure Breakdown'!$W$28:$W$35, "<"&M1)+SUMIFS('Expenditure Breakdown'!$R$50:$R$57, 'Expenditure Breakdown'!$W$50:$W$57, ">="&L1,'Expenditure Breakdown'!$W$50:$W$57, "<"&M1)+SUMIFS('Expenditure Breakdown'!$R$77:$R$84, 'Expenditure Breakdown'!$W$77:$W$84, ">="&L1,'Expenditure Breakdown'!$W$77:$W$84, "<"&M1) -> 0 | M20: =SUMIFS('Expenditure Breakdown'!$R$28:$R$35, 'Expenditure Breakdown'!$W$28:$W$35, ">="&M1,'Expenditure Breakdown'!$W$28:$W$35, "<"&N1)+SUMIFS('Expenditure Breakdown'!$R$50:$R$57, 'Expenditure Breakdown'!$W$50:$W$57, ">="&M1,'Expenditure Breakdown'!$W$50:$W$57, "<"&N1)+SUMIFS('Expenditure Breakdown'!$R$77:$R$84, 'Expenditure Breakdown'!$W$77:$W$84, ">="&M1,'Expenditure Breakdown'!$W$77:$W$84, "<"&N1) -> 0 | ... CA20: =SUMIFS('Expenditure Breakdown'!$R$28:$R$35, 'Expenditure Breakdown'!$W$28:$W$35, ">="&CA1,'Expenditure Breakdown'!$W$28:$W$35, "<"&CB1)+SUMIFS('Expenditure Breakdown'!$R$50:$R$57, 'Expenditure Breakdown'!$W$50:$W$57, ">="&CA1,'Expenditure Breakdown'!$W$50:$W$57, "<"&CB1)+SUMIFS('Expenditure Breakdown'!$R$77:$R$84, 'Expenditure Breakdown'!$W$77:$W$84, ">="&CA1,'Expenditure Breakdown'!$W$77:$W$84, "<"&CB1) -> 0 | CB20: =SUMIFS('Expenditure Breakdown'!$R$28:$R$35, 'Expenditure Breakdown'!$W$28:$W$35, ">="&CB1,'Expenditure Breakdown'!$W$28:$W$35, "<"&CD1)+SUMIFS('Expenditure Breakdown'!$R$50:$R$57, 'Expenditure Breakdown'!$W$50:$W$57, ">="&CB1,'Expenditure Breakdown'!$W$50:$W$57, "<"&CD1)+SUMIFS('Expenditure Breakdown'!$R$77:$R$84, 'Expenditure Breakdown'!$W$77:$W$84, ">="&CB1,'Expenditure Breakdown'!$W$77:$W$84, "<"&CD1) -> 0 | CC20: =SUMIFS('Expenditure Breakdown'!$R$28:$R$35, 'Expenditure Breakdown'!$W$28:$W$35, ">="&CC1,'Expenditure Breakdown'!$W$28:$W$35, "<"&CE1)+SUMIFS('Expenditure Breakdown'!$R$50:$R$57, 'Expenditure Breakdown'!$W$50:$W$57, ">="&CC1,'Expenditure Breakdown'!$W$50:$W$57, "<"&CE1)+SUMIFS('Expenditure Breakdown'!$R$77:$R$84, 'Expenditure Breakdown'!$W$77:$W$84, ">="&CC1,'Expenditure Breakdown'!$W$77:$W$84, "<"&CE1) -> 0
B21: Installer Expenditure - Cumulative | F21: =F20 -> 0 | G21: =G20+F21 -> 0 | H21: =H20+G21 -> 0 | I21: =I20+H21 -> 0 | J21: =J20+I21 -> 0 | K21: =K20+J21 -> 0 | L21: =L20+K21 -> 0 | M21: =M20+L21 -> 0 | N21: =N20+M21 -> 0 | ... CC21: =CC20+CB21 -> 455995.3

Sheet Finance - Revenue
A1: REVENUE RECOGNITION AMOUNT | B1: (All)
A3: Sum of REVENUE RECOGNITION AMOUNT | B3: Column Labels
A4: Row Labels | C4: (blank) | D4: 45504 | E4: 45535 | F4: 45565 | G4: 45596 | H4: 45626 | I4: 45657 | J4: 45688 | K4: 45716 | L4: 45808 | M4: 45777 | N4: 45869 | O4: 45900 | P4: Grand Total
A5: (blank)
A6: Battery Systems
A7: BDP Commission
A8: 1. Panels | D8: 792853.43 | G8: 14183.254 | H8: 35614.21 | P8: 842650.89 | Q8: =SUM(F8:O8) -> 49797.464
A9: 2. Inverters | B9: 0 | F9: 192434.15 | P9: 192434.15 | Q9: =SUM(F9:O9) -> 192434.15
A10: 3. Mounting Structures | F10: 120898.85 | G10: 886.51779 | H10: 0 | I10: 0 | P10: 121785.37 | Q10: =SUM(F10:O10) -> 121785.37
A11: 4. DC Equipment | C11: 0 | F11: 40053.717 | G11: 233027.6 | J11: 16021.487 | P11: 289102.8 | Q11: =SUM(F11:O11) -> 289102.8
A12: 5. Monitoring | B12: 0 | E12: 42729.565 | G12: 5229.2951 | H12: 11797.237 | P12: 59756.097 | Q12: =SUM(F12:O12) -> 17026.532
A13: 6. AC Equipment | B13: 0 | C13: 0 | F13: 110036.4 | G13: 235436.01 | J13: 25643.615 | L13: 139.85 | P13: 371255.88 | Q13: =SUM(F13:O13) -> 371255.88
A14: 8. Product Add On | G14: 0 | H14: 43965.12 | P14: 43965.12 | Q14: =SUM(F14:O14) -> 43965.12
A15: 9. AC & DC installation | F15: 61191.176 | G15: 159097.06 | J15: 24476.471 | P15: 244764.71 | Q15: =SUM(F15:O15) -> 244764.71
A16: 10. Site Logistics | B16: 0 | C16: 0 | F16: 9902.8896 | G16: 30709.668 | J16: 4512.5059 | P16: 45125.064 | Q16: =SUM(F16:O16) -> 45125.064
A17: 11. Due Dilligence | B17: 0 | E17: 11462.156 | H17: 93243.728 | P17: 104705.88 | Q17: =SUM(F17:O17) -> 93243.728
A18: 13. Engineering | H18: 185737 | P18: 185737 | Q18: =SUM(F18:O18) -> 185737
A19: 14. General Expenses | E19: 1000.1896 | F19: 1154.7593 | G19: 1393.1129 | H19: 0 | J19: 654.76884 | K19: 697.46059 | P19: 4900.2913 | Q19: =SUM(F19:O19) -> 3900.1016
A20: 15. Service Add On | Q20: =SUM(F20:O20) -> 0
A21: Grand Total | B21: 0 | C21: 0 | D21: 792853.43 | E21: 55191.91 | F21: 535671.94 | G21: 679962.52 | H21: 370357.29 | I21: 0 | J21: 71308.848 | K21: 697.46059 | L21: 139.85 | P21: 2506183.2 | Q21: =SUM(Q8:Q20) -> 1658137.9
D23: =SUM(D21:E21) -> 848045.34

Sheet Finance - COS
A3: Sum of Actual Total | B3: Column Labels
A4: Row Labels | B4: (blank) | D4: 45504 | E4: 45535 | F4: 45565 | G4: 45596 | H4: 45626 | I4: 45657 | J4: 45688 | K4: 45716 | L4: 45777 | M4: 45808 | N4: 45869 | O4: 45900 | P4: 46053 | Q4: Grand Total
A5: Battery Systems
A6: BDP Commission | E6: 31521.67 | H6: 31521.67 | Q6: 63043.34
A7: (blank)
A8: 1. Panels | D8: 636862.5 | G8: 10903 | Q8: 647765.5
A9: 2. Inverters | F9: 138845.23 | Q9: 138845.23
A10: 3. Mounting Structures | F10: 58349.4 | G10: 427.86 | H10: 123417.32 | I10: -12270.36 | Q10: 169924.22
A11: 4. DC Equipment | B11: 0 | F11: 33562.5 | G11: 195262.5 | J11: 13425 | Q11: 242250
A12: 5. Monitoring | E12: 57720.5 | G12: 2562.51 | H12: 11169 | Q12: 71452.01
A13: 6. AC Equipment | B13: 0 | F13: 62962.5 | G13: 134795.8 | J13: 14673.2 | M13: 432.1 | Q13: 212863.6
A14: 8. Product Add On | G14: 140874.78 | J14: 8316 | O14: 9538.74 | Q14: 158729.52
A15: 9. AC & DC installation | F15: 43753.45 | G15: 113758.97 | J15: 17501.38 | Q15: 175013.8
A16: 10. Site Logistics | F16: 26941.75 | G16: 70048.55 | J16: 10776.7 | Q16: 107767
A17: 11. Due Dilligence | E17: 2520 | H17: 11654.76 | Q17: 14174.76
A18: 13. Engineering | H18: 30778.238 | O18: 31621.762 | Q18: 62400
A19: 14. General Expenses | E19: 1522.75 | F19: 1570.97 | G19: 1671 | H19: 0 | J19: 1109.72 | K19: 423.22 | L19: 1087.98 | Q19: 7385.64
A20: 15. Service Add On | M20: 32247.49 | N20: 9731.71 | P20: -9731.71 | Q20: 32247.49
A21: Grand Total | B21: 0 | D21: 636862.5 | E21: 93284.92 | F21: 365985.8 | G21: 670304.97 | H21: 208540.99 | I21: -12270.36 | J21: 65802 | K21: 423.22 | L21: 1087.98 | M21: 32679.59 | N21: 9731.71 | O21: 41160.502 | P21: -9731.71 | Q21: 2103862.1

Sheet Project Margins
A1: [capture project margins from costing sheet]
A3: Products | D3: 0.32
A4: Services | D4: 0.5
A5: Expenses | D5: 0.15
A6: Subcontractors | D6: 0.2

Sheet Equipment Quotes
B2: Equipment Quote and Budget comparision
B4: Description | D4: Budget | F4: Supplier 1 | H4: Variance | J4: Supplier 2 | L4: Variance | N4: Comments / Notes
F7: >Name< | J7: >Name<
B9: Inverters | D9: =SUM(D10:D11) -> 157796 | F9: =SUM(F10:F13) -> 0 | H9: =$D$9-F9 -> 157796 | J9: =SUM(J10:J13) -> 0 | L9: =$D$9-J9 -> 157796
B10: Inverters | D10: ='Expenditure Breakdown'!G13 -> 157796
B11: Optimizers | D11: ='Expenditure Breakdown'!G14 -> 0
B12: Warranty
B13: Delivery fee
F15: >Name< | J15: >Name<
B17: Mounting Structure | D17: =SUM(D18:D19) -> 99864 | F17: =SUM(F18:F20) -> 0 | H17: =$D$17- F17 -> 99864 | J17: =SUM(J18:J20) -> 0 | L17: =$D$17- J17 -> 99864
B18: Mounting Structure | D18: ='Expenditure Breakdown'!G18 -> 99864
B19: Delivery fee
F21: >Name< | J21: >Name<
B23: DC Cable | D23: =SUM(D24:D25) -> 98128 | F23: =SUM(F24:F25) -> 0 | H23: =$D$23- F23 -> 98128 | J23: =SUM(J24:J25) -> 0 | L23: =$D$23- J23 -> 98128
B24: DC Cable | D24: ='Expenditure Breakdown'!G26 -> 98128
B25: Delivery fee
F27: >Name< | J27: >Name<
B29: Monitoring system | D29: =SUM(D30:D32) -> #REF! | F29: =SUM(F30:F42) -> 0 | H29: =$D$29-F29 -> #REF! | J29: =SUM(J30:J32) -> 0 | L29: =$D$29-J29 -> #REF!
B30: ='Expenditure Breakdown'!D37 -> Smartlogger 3000 | D30: ='Expenditure Breakdown'!G37 -> 26000
B31: ='Expenditure Breakdown'!#REF! -> #REF! | D31: ='Expenditure Breakdown'!#REF! -> #REF!
B32: Delivery fee
F34: >Name< | J34: >Name<
B36: Additional Scope | D36: =SUM(D37:D41) -> 0 | F36: =SUM(F37:F41) -> 0 | H36: =$D$29-F36 -> #REF! | J36: =SUM(J37:J41) -> 0 | L36: =$D$29-J36 -> #REF!
B37: SCADA | D37: ='Expenditure Breakdown'!G68 -> 0
B38: Inverter cage
B39: Cat ladders
B40: Gen Integration
B41: Lifelines
B43: Totals | D43: =D36+D29+D23+D17+D9 -> #REF! | H43: =SUM(H7:H42) -> #REF! | L43: =SUM(L7:L42) -> #REF!
B47: All amounts are incl VAT

Sheet Installer Quotes
B2: Installer Quote and Budget comparision
B4: Description | D4: Budget | G4: Cosmic Sun | J4: Variance | L4: Matthews Group | O4: Variance
B6: AC Equipment | D6: ='Expenditure Breakdown'!AB8 -> 304429.82 | E6: =D6/(1000*'Project Plan'!$E$3) -> 1.2177193 | G6: 277892.91 | H6: =G6/('Project Plan'!$E$3*1000) -> 1.1115716 | J6: =D6-G6 -> 26536.91 | M6: =L6/('Project Plan'!$E$3*1000) -> 0 | O6: =D6-L6 -> 304429.82
B7: DC Equipment | D7: ='Expenditure Breakdown'!AB9 -> 116936.3 | E7: =D7/(1000*'Project Plan'!$E$3) -> 0.4677452 | G7: 142158.25 | H7: =G7/('Project Plan'!$E$3*1000) -> 0.568633 | J7: =D7-G7 -> -25221.95 | M7: =L7/('Project Plan'!$E$3*1000) -> 0 | O7: =D7-L7 -> 116936.3
B8: AC Labour | D8: ='Expenditure Breakdown'!AB10 -> 145635 | E8: =D8/(1000*'Project Plan'!$E$3) -> 0.58254 | G8: 96174 | H8: =G8/('Project Plan'!$E$3*1000) -> 0.384696 | J8: =D8-G8 -> 49461 | M8: =L8/('Project Plan'!$E$3*1000) -> 0 | O8: =D8-L8 -> 145635
B9: DC Labour | D9: ='Expenditure Breakdown'!AB11 -> 62415 | E9: =D9/(1000*'Project Plan'!$E$3) -> 0.24966 | G9: 230160 | H9: =G9/('Project Plan'!$E$3*1000) -> 0.92064 | J9: =D9-G9 -> -167745 | M9: =L9/('Project Plan'!$E$3*1000) -> 0 | O9: =D9-L9 -> 62415
B10: Offloading | D10: ='Expenditure Breakdown'!AB12 -> 8500 | G10: 0 | J10: =D10-G10 -> 8500 | O10: =D10-L10 -> 8500
B11: Roof Access/Scaffolding | D11: ='Expenditure Breakdown'!AB13 -> 0 | G11: 29257.61 | J11: =D11-G11 -> -29257.61 | O11: =D11-L11 -> 0
B12: Storage | D12: ='Expenditure Breakdown'!AB14 -> 0 | J12: =D12-G12 -> 0 | O12: =D12-L12 -> 0
B13: Telehandler | D13: ='Expenditure Breakdown'!AB15 -> 29856.3
B14: HSE | D14: 0
B15: Totals | D15: =SUM(D6:D13) -> 667772.42 | G15: =SUM(G6:G13) -> 775642.77 | J15: =SUM(J6:J14) -> -137726.65 | L15: =SUM(L6:L13) -> 0 | O15: =SUM(O6:O14) -> 637916.12
B18: Description | D18: Budget | G18: >Installer Name 3< | J18: Variance | L18: >Installer Name 4< | O18: Variance
B20: AC installation | D20: ='Expenditure Breakdown'!#REF! -> #REF! | E20: =D20/(1000*'Project Plan'!$E$3) -> #REF! | H20: =G20/(1000*'Project Plan'!$E$3) -> 0 | J20: =D20-G20 -> #REF! | M20: =L20/(1000*'Project Plan'!$E$3) -> 0 | O20: =D6-L20 -> 304429.82
B21: AC equipment | D21: ='Expenditure Breakdown'!C57 -> 0 | E21: =D21/(1000*'Project Plan'!$E$3) -> 0 | J21: =D21-G21 -> 0 | M21: =L21/(1000*'Project Plan'!$E$3) -> 0 | O21: =D7-L21 -> 116936.3
B22: DC installation | D22: ='Expenditure Breakdown'!#REF! -> #REF! | E22: =D22/(1000*'Project Plan'!$E$3) -> #REF! | H22: =G22/(1000*'Project Plan'!$E$3) -> 0 | J22: =D22-G22 -> #REF! | M22: =L22/(1000*'Project Plan'!$E$3) -> 0 | O22: =D8-L22 -> 145635
B23: DC equipment | D23: =SUM('Expenditure Breakdown'!G33:G34) -> 0 | E23: =D23/(1000*'Project Plan'!$E$3) -> 0 | J23: =D23-G23 -> 0 | O23: =D9-L23 -> 62415
B24: Storage | D24: ='Expenditure Breakdown'!G105 -> 0 | J24: =D24-G24 -> 0 | O24: =D10-L24 -> 8500
B25: Panel lifting equipment | D25: =SUM('Expenditure Breakdown'!G86:G97) -> 8500 | J25: =D25-G25 -> 8500 | O25: =D11-L25 -> 0
B26: Offloading | D26: ='Expenditure Breakdown'!G99 -> 29856.3 | J26: =D26-G26 -> 29856.3 | O26: =D12-L26 -> 0
B29: Totals | D29: =SUM(D20:D27) -> #REF! | G29: =SUM(G20:G27) -> 0 | J29: =SUM(J20:J28) -> #REF! | L29: =SUM(L20:L27) -> 0 | O29: =SUM(O20:O28) -> 637916.12
B32: Budget Summary
B34: Budget | D34: =D15 -> 667772.42
B35: =G4 -> Cosmic Sun | D35: =G15 -> 775642.77
B36: =L4 -> Matthews Group | D36: =L15 -> 0
B37: =G18 -> >Installer Name 3< | D37: =G29 -> 0
B38: =L18 -> >Installer Name 4< | D38: =L29 -> 0
B40: =IF(D40<D34,"Saving","Loss") -> Loss | D40: =D34-MIN(D35:D38) -> 667772.42
B42: All amounts are exc VAT

Sheet Decision Register
B1: =D15 -> SA Metal - 22 Christiaan | E1: Decision Register
B3: ID | C3: Decision Description | D3: Decision Impact | E3: Proposed Date | F3: Proposed By | G3: Status | H3: Approved By | I3: Date | J3: Results / Comments
B4: DEC001
B5: DEC002
B6: DEC003
B7: DEC004
B8: DEC005
B9: DEC006
B10: DEC007
B11: DEC008
B12: DEC009
B13: DEC010
D15: {='Project Plan'!E2:H2} -> SA Metal - 22 Christiaan | E15: 0 | F15: 0 | G15: 0
