Workbook
Name Inverter_Capacity: #REF!
Name Inverter_Supplier: #REF!
Name Project_Size: 'Certificate - Financial Close'!Projectsize
Name Project_Size: 'Finance - Revenue'!Projectsize
Name Project_Size: Projectsize
Name Projectsize: #REF!
Name Projectsize: #REF!
Name Projectsize: 'Project Margins'!$K$5
Name Security_Serv: #REF!
Name Security_Serv: #REF!
Name SSS: #REF!
Name SSS: #REF!
Name USD_ZAR: #REF!

Sheet Sheet1
A1: PROJECT PLAN
A2: # | B2: Project Milestone | C2: Planned Start Date | D2: Duration (Work Days) | E2: Planned End Date | F2: Actual Start Date | H2: Actual End Date | J2: Comments | L2: =C3 -> 43831 | M2: =L2+3 -> 43834 | N2: =M2+7 -> 43841 | O2: =N2+7 -> 43848 | P2: =O2+7 -> 43855 | Q2: =P2+6 -> 43861 | R2: =Q2+1 -> 43862 | S2: =R2+7 -> 43869 | T2: =S2+7 -> 43876 | U2: =T2+7 -> 43883 | V2: =U2+6 -> 43889 | W2: =V2+7 -> 43896 | X2: =W2+7 -> 43903 | Y2: =X2+7 -> 43910 | Z2: =Y2+7 -> 43917 | AA2: =Z2+3 -> 43920 | AB2: =AA2+4 -> 43924 | AC2: =AB2+7 -> 43931 | AD2: =AC2+7 -> 43938 | AE2: =AD2+7 -> 43945 | AF2: =AE2+6 -> 43951 | AG2: =AF2+2 -> 43953 | AH2: =AG2+7 -> 43960 | AI2: =AH2+7 -> 43967 | AJ2: =AI2+7 -> 43974 | AK2: =AJ2+7 -> 43981 | AL2: =AK2+1 -> 43982 | AM2: =AL2+6 -> 43988 | AN2: =AM2+7 -> 43995 | AO2: =AN2+7 -> 44002 | AP2: =AO2+7 -> 44009 | AQ2: =AP2+3 -> 44012 | AR2: =AQ2+4 -> 44016 | AS2: =AR2+7 -> 44023 | AT2: =AS2+7 -> 44030 | AU2: =AT2+7 -> 44037 | AV2: =AU2+6 -> 44043 | AW2: =AV2+1 -> 44044 | AX2: =AW2+7 -> 44051 | AY2: =AX2+7 -> 44058 | AZ2: =AY2+7 -> 44065 | BA2: =AZ2+7 -> 44072 | BB2: =BA2+2 -> 44074 | BC2: =BB2+5 -> 44079 | BD2: =BC2+7 -> 44086 | BE2: =BD2+7 -> 44093 | BF2: =BE2+7 -> 44100 | BG2: =BF2+4 -> 44104
A3: 1 | B3: Contract Signature | C3: 43831 | D3: 1 | E3: 43832 | F3: 43831 | G3: 1 | H3: 43832 | L3: =IF(AND($F3<(L$2+7),$F3>L$2),1, IF(AND($H3<L$2+7,$H3>L$2),3, IF(AND($F3<=L$2, $H3>=L$2), 2, "" ))) -> 3 | M3: =IF(AND($F3<(M$2+7),$F3>M$2),1, IF(AND($H3<M$2+7,$H3>M$2),3, IF(AND($F3<=M$2, $H3>=M$2), 2, "" ))) | N3: =IF(AND($F3<(N$2+7),$F3>N$2),1, IF(AND($H3<N$2+7,$H3>N$2),3, IF(AND($F3<=N$2, $H3>=N$2), 2, "" ))) | O3: =IF(AND($F3<(O$2+7),$F3>O$2),1, IF(AND($H3<O$2+7,$H3>O$2),3, IF(AND($F3<=O$2, $H3>=O$2), 2, "" ))) | P3: =IF(AND($F3<(P$2+7),$F3>P$2),1, IF(AND($H3<P$2+7,$H3>P$2),3, IF(AND($F3<=P$2, $H3>=P$2), 2, "" ))) | Q3: =IF(AND($F3<(Q$2+7),$F3>Q$2),1, IF(AND($H3<Q$2+7,$H3>Q$2),3, IF(AND($F3<=Q$2, $H3>=Q$2), 2, "" ))) | R3: =IF(AND($F3<(R$2+7),$F3>R$2),1, IF(AND($H3<R$2+7,$H3>R$2),3, IF(AND($F3<=R$2, $H3>=R$2), 2, "" ))) | S3: =IF(AND($F3<(S$2+7),$F3>S$2),1, IF(AND($H3<S$2+7,$H3>S$2),3, IF(AND($F3<=S$2, $H3>=S$2), 2, "" ))) | ... AQ3: =IF(AND($F3<(AQ$2+7),$F3>AQ$2),1, IF(AND($H3<AQ$2+7,$H3>AQ$2),3, IF(AND($F3<=AQ$2, $H3>=AQ$2), 2, "" )))
A4: A | B4: PAYMENT MILESTONE 1: DEPOSIT | C4: 43832 | D4: 1 | E4: 43833 | F4: 43832 | G4: 1 | H4: 43833 | L4: =IF(AND($F4<(L$2+7),$F4>L$2),1, IF(AND($H4<L$2+7,$H4>L$2),3, IF(AND($F4<=L$2, $H4>=L$2), 2, "" ))) -> 1 | M4: =IF(AND($F4<(M$2+7),$F4>M$2),1, IF(AND($H4<M$2+7,$H4>M$2),3, IF(AND($F4<=M$2, $H4>=M$2), 2, "" ))) | N4: =IF(AND($F4<(N$2+7),$F4>N$2),1, IF(AND($H4<N$2+7,$H4>N$2),3, IF(AND($F4<=N$2, $H4>=N$2), 2, "" ))) | O4: =IF(AND($F4<(O$2+7),$F4>O$2),1, IF(AND($H4<O$2+7,$H4>O$2),3, IF(AND($F4<=O$2, $H4>=O$2), 2, "" ))) | P4: =IF(AND($F4<(P$2+7),$F4>P$2),1, IF(AND($H4<P$2+7,$H4>P$2),3, IF(AND($F4<=P$2, $H4>=P$2), 2, "" ))) | Q4: =IF(AND($F4<(Q$2+7),$F4>Q$2),1, IF(AND($H4<Q$2+7,$H4>Q$2),3, IF(AND($F4<=Q$2, $H4>=Q$2), 2, "" ))) | R4: =IF(AND($F4<(R$2+7),$F4>R$2),1, IF(AND($H4<R$2+7,$H4>R$2),3, IF(AND($F4<=R$2, $H4>=R$2), 2, "" ))) | S4: =IF(AND($F4<(S$2+7),$F4>S$2),1, IF(AND($H4<S$2+7,$H4>S$2),3, IF(AND($F4<=S$2, $H4>=S$2), 2, "" ))) | ... AQ4: =IF(AND($F4<(AQ$2+7),$F4>AQ$2),1, IF(AND($H4<AQ$2+7,$H4>AQ$2),3, IF(AND($F4<=AQ$2, $H4>=AQ$2), 2, "" )))
A5: 2 | B5: Structural and Electrical Due Diligences | C5: 43833 | D5: 5 | E5: 43840 | F5: 43833 | G5: 5 | H5: 43840 | L5: =IF(AND($F5<(L$2+7),$F5>L$2),1, IF(AND($H5<L$2+7,$H5>L$2),3, IF(AND($F5<=L$2, $H5>=L$2), 2, "" ))) -> 1 | M5: =IF(AND($F5<(M$2+7),$F5>M$2),1, IF(AND($H5<M$2+7,$H5>M$2),3, IF(AND($F5<=M$2, $H5>=M$2), 2, "" ))) -> 3 | N5: =IF(AND($F5<(N$2+7),$F5>N$2),1, IF(AND($H5<N$2+7,$H5>N$2),3, IF(AND($F5<=N$2, $H5>=N$2), 2, "" ))) | O5: =IF(AND($F5<(O$2+7),$F5>O$2),1, IF(AND($H5<O$2+7,$H5>O$2),3, IF(AND($F5<=O$2, $H5>=O$2), 2, "" ))) | P5: =IF(AND($F5<(P$2+7),$F5>P$2),1, IF(AND($H5<P$2+7,$H5>P$2),3, IF(AND($F5<=P$2, $H5>=P$2), 2, "" ))) | Q5: =IF(AND($F5<(Q$2+7),$F5>Q$2),1, IF(AND($H5<Q$2+7,$H5>Q$2),3, IF(AND($F5<=Q$2, $H5>=Q$2), 2, "" ))) | R5: =IF(AND($F5<(R$2+7),$F5>R$2),1, IF(AND($H5<R$2+7,$H5>R$2),3, IF(AND($F5<=R$2, $H5>=R$2), 2, "" ))) | S5: =IF(AND($F5<(S$2+7),$F5>S$2),1, IF(AND($H5<S$2+7,$H5>S$2),3, IF(AND($F5<=S$2, $H5>=S$2), 2, "" ))) | ... AQ5: =IF(AND($F5<(AQ$2+7),$F5>AQ$2),1, IF(AND($H5<AQ$2+7,$H5>AQ$2),3, IF(AND($F5<=AQ$2, $H5>=AQ$2), 2, "" )))
A6: 3 | B6: Design Confirmation | C6: 43841 | D6: 2 | E6: 43844 | F6: 43841 | G6: 2 | H6: 43844 | L6: =IF(AND($F6<(L$2+7),$F6>L$2),1, IF(AND($H6<L$2+7,$H6>L$2),3, IF(AND($F6<=L$2, $H6>=L$2), 2, "" ))) | M6: =IF(AND($F6<(M$2+7),$F6>M$2),1, IF(AND($H6<M$2+7,$H6>M$2),3, IF(AND($F6<=M$2, $H6>=M$2), 2, "" ))) | N6: =IF(AND($F6<(N$2+7),$F6>N$2),1, IF(AND($H6<N$2+7,$H6>N$2),3, IF(AND($F6<=N$2, $H6>=N$2), 2, "" ))) -> 3 | O6: =IF(AND($F6<(O$2+7),$F6>O$2),1, IF(AND($H6<O$2+7,$H6>O$2),3, IF(AND($F6<=O$2, $H6>=O$2), 2, "" ))) | P6: =IF(AND($F6<(P$2+7),$F6>P$2),1, IF(AND($H6<P$2+7,$H6>P$2),3, IF(AND($F6<=P$2, $H6>=P$2), 2, "" ))) | Q6: =IF(AND($F6<(Q$2+7),$F6>Q$2),1, IF(AND($H6<Q$2+7,$H6>Q$2),3, IF(AND($F6<=Q$2, $H6>=Q$2), 2, "" ))) | R6: =IF(AND($F6<(R$2+7),$F6>R$2),1, IF(AND($H6<R$2+7,$H6>R$2),3, IF(AND($F6<=R$2, $H6>=R$2), 2, "" ))) | S6: =IF(AND($F6<(S$2+7),$F6>S$2),1, IF(AND($H6<S$2+7,$H6>S$2),3, IF(AND($F6<=S$2, $H6>=S$2), 2, "" ))) | ... AQ6: =IF(AND($F6<(AQ$2+7),$F6>AQ$2),1, IF(AND($H6<AQ$2+7,$H6>AQ$2),3, IF(AND($F6<=AQ$2, $H6>=AQ$2), 2, "" )))
A7: 4 | B7: Equipment Procurement | C7: 43833 | E7: 43949 | F7: 43833 | H7: 43949 | L7: =IF(AND($F7<(L$2+7),$F7>L$2),1, IF(AND($H7<L$2+7,$H7>L$2),3, IF(AND($F7<=L$2, $H7>=L$2), 2, "" ))) -> 1 | M7: =IF(AND($F7<(M$2+7),$F7>M$2),1, IF(AND($H7<M$2+7,$H7>M$2),3, IF(AND($F7<=M$2, $H7>=M$2), 2, "" ))) -> 2 | N7: =IF(AND($F7<(N$2+7),$F7>N$2),1, IF(AND($H7<N$2+7,$H7>N$2),3, IF(AND($F7<=N$2, $H7>=N$2), 2, "" ))) -> 2 | O7: =IF(AND($F7<(O$2+7),$F7>O$2),1, IF(AND($H7<O$2+7,$H7>O$2),3, IF(AND($F7<=O$2, $H7>=O$2), 2, "" ))) -> 2 | P7: =IF(AND($F7<(P$2+7),$F7>P$2),1, IF(AND($H7<P$2+7,$H7>P$2),3, IF(AND($F7<=P$2, $H7>=P$2), 2, "" ))) -> 2 | Q7: =IF(AND($F7<(Q$2+7),$F7>Q$2),1, IF(AND($H7<Q$2+7,$H7>Q$2),3, IF(AND($F7<=Q$2, $H7>=Q$2), 2, "" ))) -> 2 | R7: =IF(AND($F7<(R$2+7),$F7>R$2),1, IF(AND($H7<R$2+7,$H7>R$2),3, IF(AND($F7<=R$2, $H7>=R$2), 2, "" ))) -> 2 | S7: =IF(AND($F7<(S$2+7),$F7>S$2),1, IF(AND($H7<S$2+7,$H7>S$2),3, IF(AND($F7<=S$2, $H7>=S$2), 2, "" ))) -> 2 | ... AQ7: =IF(AND($F7<(AQ$2+7),$F7>AQ$2),1, IF(AND($H7<AQ$2+7,$H7>AQ$2),3, IF(AND($F7<=AQ$2, $H7>=AQ$2), 2, "" )))
B8: Panel Procurement | C8: 43833 | D8: 5 | E8: 43840 | F8: 43833 | G8: 5 | H8: 43840 | L8: =IF(AND($F8<(L$2+7),$F8>L$2),1, IF(AND($H8<L$2+7,$H8>L$2),3, IF(AND($F8<=L$2, $H8>=L$2), 2, "" ))) -> 1 | M8: =IF(AND($F8<(M$2+7),$F8>M$2),1, IF(AND($H8<M$2+7,$H8>M$2),3, IF(AND($F8<=M$2, $H8>=M$2), 2, "" ))) -> 3 | N8: =IF(AND($F8<(N$2+7),$F8>N$2),1, IF(AND($H8<N$2+7,$H8>N$2),3, IF(AND($F8<=N$2, $H8>=N$2), 2, "" ))) | O8: =IF(AND($F8<(O$2+7),$F8>O$2),1, IF(AND($H8<O$2+7,$H8>O$2),3, IF(AND($F8<=O$2, $H8>=O$2), 2, "" ))) | P8: =IF(AND($F8<(P$2+7),$F8>P$2),1, IF(AND($H8<P$2+7,$H8>P$2),3, IF(AND($F8<=P$2, $H8>=P$2), 2, "" ))) | Q8: =IF(AND($F8<(Q$2+7),$F8>Q$2),1, IF(AND($H8<Q$2+7,$H8>Q$2),3, IF(AND($F8<=Q$2, $H8>=Q$2), 2, "" ))) | R8: =IF(AND($F8<(R$2+7),$F8>R$2),1, IF(AND($H8<R$2+7,$H8>R$2),3, IF(AND($F8<=R$2, $H8>=R$2), 2, "" ))) | S8: =IF(AND($F8<(S$2+7),$F8>S$2),1, IF(AND($H8<S$2+7,$H8>S$2),3, IF(AND($F8<=S$2, $H8>=S$2), 2, "" ))) | ... AQ8: =IF(AND($F8<(AQ$2+7),$F8>AQ$2),1, IF(AND($H8<AQ$2+7,$H8>AQ$2),3, IF(AND($F8<=AQ$2, $H8>=AQ$2), 2, "" )))
B9: Inverter Procurement | C9: 43941 | D9: 5 | E9: 43949 | F9: 43941 | G9: 5 | H9: 43949 | L9: =IF(AND($F9<(L$2+7),$F9>L$2),1, IF(AND($H9<L$2+7,$H9>L$2),3, IF(AND($F9<=L$2, $H9>=L$2), 2, "" ))) | M9: =IF(AND($F9<(M$2+7),$F9>M$2),1, IF(AND($H9<M$2+7,$H9>M$2),3, IF(AND($F9<=M$2, $H9>=M$2), 2, "" ))) | N9: =IF(AND($F9<(N$2+7),$F9>N$2),1, IF(AND($H9<N$2+7,$H9>N$2),3, IF(AND($F9<=N$2, $H9>=N$2), 2, "" ))) | O9: =IF(AND($F9<(O$2+7),$F9>O$2),1, IF(AND($H9<O$2+7,$H9>O$2),3, IF(AND($F9<=O$2, $H9>=O$2), 2, "" ))) | P9: =IF(AND($F9<(P$2+7),$F9>P$2),1, IF(AND($H9<P$2+7,$H9>P$2),3, IF(AND($F9<=P$2, $H9>=P$2), 2, "" ))) | Q9: =IF(AND($F9<(Q$2+7),$F9>Q$2),1, IF(AND($H9<Q$2+7,$H9>Q$2),3, IF(AND($F9<=Q$2, $H9>=Q$2), 2, "" ))) | R9: =IF(AND($F9<(R$2+7),$F9>R$2),1, IF(AND($H9<R$2+7,$H9>R$2),3, IF(AND($F9<=R$2, $H9>=R$2), 2, "" ))) | S9: =IF(AND($F9<(S$2+7),$F9>S$2),1, IF(AND($H9<S$2+7,$H9>S$2),3, IF(AND($F9<=S$2, $H9>=S$2), 2, "" ))) | ... AQ9: =IF(AND($F9<(AQ$2+7),$F9>AQ$2),1, IF(AND($H9<AQ$2+7,$H9>AQ$2),3, IF(AND($F9<=AQ$2, $H9>=AQ$2), 2, "" )))
B10: Mounting Structure Procurement | C10: 43941 | D10: 5 | E10: 43949 | F10: 43941 | G10: 5 | H10: 43949 | L10: =IF(AND($F10<(L$2+7),$F10>L$2),1, IF(AND($H10<L$2+7,$H10>L$2),3, IF(AND($F10<=L$2, $H10>=L$2), 2, "" ))) | M10: =IF(AND($F10<(M$2+7),$F10>M$2),1, IF(AND($H10<M$2+7,$H10>M$2),3, IF(AND($F10<=M$2, $H10>=M$2), 2, "" ))) | N10: =IF(AND($F10<(N$2+7),$F10>N$2),1, IF(AND($H10<N$2+7,$H10>N$2),3, IF(AND($F10<=N$2, $H10>=N$2), 2, "" ))) | O10: =IF(AND($F10<(O$2+7),$F10>O$2),1, IF(AND($H10<O$2+7,$H10>O$2),3, IF(AND($F10<=O$2, $H10>=O$2), 2, "" ))) | P10: =IF(AND($F10<(P$2+7),$F10>P$2),1, IF(AND($H10<P$2+7,$H10>P$2),3, IF(AND($F10<=P$2, $H10>=P$2), 2, "" ))) | Q10: =IF(AND($F10<(Q$2+7),$F10>Q$2),1, IF(AND($H10<Q$2+7,$H10>Q$2),3, IF(AND($F10<=Q$2, $H10>=Q$2), 2, "" ))) | R10: =IF(AND($F10<(R$2+7),$F10>R$2),1, IF(AND($H10<R$2+7,$H10>R$2),3, IF(AND($F10<=R$2, $H10>=R$2), 2, "" ))) | S10: =IF(AND($F10<(S$2+7),$F10>S$2),1, IF(AND($H10<S$2+7,$H10>S$2),3, IF(AND($F10<=S$2, $H10>=S$2), 2, "" ))) | ... AQ10: =IF(AND($F10<(AQ$2+7),$F10>AQ$2),1, IF(AND($H10<AQ$2+7,$H10>AQ$2),3, IF(AND($F10<=AQ$2, $H10>=AQ$2), 2, "" )))
B11: BOS Procurement | C11: 43941 | D11: 5 | E11: 43949 | F11: 43941 | G11: 5 | H11: 43949 | L11: =IF(AND($F11<(L$2+7),$F11>L$2),1, IF(AND($H11<L$2+7,$H11>L$2),3, IF(AND($F11<=L$2, $H11>=L$2), 2, "" ))) | M11: =IF(AND($F11<(M$2+7),$F11>M$2),1, IF(AND($H11<M$2+7,$H11>M$2),3, IF(AND($F11<=M$2, $H11>=M$2), 2, "" ))) | N11: =IF(AND($F11<(N$2+7),$F11>N$2),1, IF(AND($H11<N$2+7,$H11>N$2),3, IF(AND($F11<=N$2, $H11>=N$2), 2, "" ))) | O11: =IF(AND($F11<(O$2+7),$F11>O$2),1, IF(AND($H11<O$2+7,$H11>O$2),3, IF(AND($F11<=O$2, $H11>=O$2), 2, "" ))) | P11: =IF(AND($F11<(P$2+7),$F11>P$2),1, IF(AND($H11<P$2+7,$H11>P$2),3, IF(AND($F11<=P$2, $H11>=P$2), 2, "" ))) | Q11: =IF(AND($F11<(Q$2+7),$F11>Q$2),1, IF(AND($H11<Q$2+7,$H11>Q$2),3, IF(AND($F11<=Q$2, $H11>=Q$2), 2, "" ))) | R11: =IF(AND($F11<(R$2+7),$F11>R$2),1, IF(AND($H11<R$2+7,$H11>R$2),3, IF(AND($F11<=R$2, $H11>=R$2), 2, "" ))) | S11: =IF(AND($F11<(S$2+7),$F11>S$2),1, IF(AND($H11<S$2+7,$H11>S$2),3, IF(AND($F11<=S$2, $H11>=S$2), 2, "" ))) | ... AQ11: =IF(AND($F11<(AQ$2+7),$F11>AQ$2),1, IF(AND($H11<AQ$2+7,$H11>AQ$2),3, IF(AND($F11<=AQ$2, $H11>=AQ$2), 2, "" )))
A12: 5 | B12: Internal Project Kick off | C12: 43936 | D12: 5 | E12: 43943 | F12: 43936 | G12: 5 | H12: 43943
A13: 6 | B13: Client Project Kick-off | C13: 43963 | D13: 5 | E13: 43970 | F13: 43963 | G13: 5 | H13: 43970 | L13: =IF(AND($F13<(L$2+7),$F13>L$2),1, IF(AND($H13<L$2+7,$H13>L$2),3, IF(AND($F13<=L$2, $H13>=L$2), 2, "" ))) | M13: =IF(AND($F13<(M$2+7),$F13>M$2),1, IF(AND($H13<M$2+7,$H13>M$2),3, IF(AND($F13<=M$2, $H13>=M$2), 2, "" ))) | N13: =IF(AND($F13<(N$2+7),$F13>N$2),1, IF(AND($H13<N$2+7,$H13>N$2),3, IF(AND($F13<=N$2, $H13>=N$2), 2, "" ))) | O13: =IF(AND($F13<(O$2+7),$F13>O$2),1, IF(AND($H13<O$2+7,$H13>O$2),3, IF(AND($F13<=O$2, $H13>=O$2), 2, "" ))) | P13: =IF(AND($F13<(P$2+7),$F13>P$2),1, IF(AND($H13<P$2+7,$H13>P$2),3, IF(AND($F13<=P$2, $H13>=P$2), 2, "" ))) | Q13: =IF(AND($F13<(Q$2+7),$F13>Q$2),1, IF(AND($H13<Q$2+7,$H13>Q$2),3, IF(AND($F13<=Q$2, $H13>=Q$2), 2, "" ))) | R13: =IF(AND($F13<(R$2+7),$F13>R$2),1, IF(AND($H13<R$2+7,$H13>R$2),3, IF(AND($F13<=R$2, $H13>=R$2), 2, "" ))) | S13: =IF(AND($F13<(S$2+7),$F13>S$2),1, IF(AND($H13<S$2+7,$H13>S$2),3, IF(AND($F13<=S$2, $H13>=S$2), 2, "" ))) | ... AQ13: =IF(AND($F13<(AQ$2+7),$F13>AQ$2),1, IF(AND($H13<AQ$2+7,$H13>AQ$2),3, IF(AND($F13<=AQ$2, $H13>=AQ$2), 2, "" )))
A14: 7 | B14: Equipment Delivery | C14: 43983 | D14: 9 | E14: 43994 | F14: 43983 | G14: 9 | H14: 43994 | L14: =IF(AND($F14<(L$2+7),$F14>L$2),1, IF(AND($H14<L$2+7,$H14>L$2),3, IF(AND($F14<=L$2, $H14>=L$2), 2, "" ))) | M14: =IF(AND($F14<(M$2+7),$F14>M$2),1, IF(AND($H14<M$2+7,$H14>M$2),3, IF(AND($F14<=M$2, $H14>=M$2), 2, "" ))) | N14: =IF(AND($F14<(N$2+7),$F14>N$2),1, IF(AND($H14<N$2+7,$H14>N$2),3, IF(AND($F14<=N$2, $H14>=N$2), 2, "" ))) | O14: =IF(AND($F14<(O$2+7),$F14>O$2),1, IF(AND($H14<O$2+7,$H14>O$2),3, IF(AND($F14<=O$2, $H14>=O$2), 2, "" ))) | P14: =IF(AND($F14<(P$2+7),$F14>P$2),1, IF(AND($H14<P$2+7,$H14>P$2),3, IF(AND($F14<=P$2, $H14>=P$2), 2, "" ))) | Q14: =IF(AND($F14<(Q$2+7),$F14>Q$2),1, IF(AND($H14<Q$2+7,$H14>Q$2),3, IF(AND($F14<=Q$2, $H14>=Q$2), 2, "" ))) | R14: =IF(AND($F14<(R$2+7),$F14>R$2),1, IF(AND($H14<R$2+7,$H14>R$2),3, IF(AND($F14<=R$2, $H14>=R$2), 2, "" ))) | S14: =IF(AND($F14<(S$2+7),$F14>S$2),1, IF(AND($H14<S$2+7,$H14>S$2),3, IF(AND($F14<=S$2, $H14>=S$2), 2, "" ))) | ... AQ14: =IF(AND($F14<(AQ$2+7),$F14>AQ$2),1, IF(AND($H14<AQ$2+7,$H14>AQ$2),3, IF(AND($F14<=AQ$2, $H14>=AQ$2), 2, "" )))
B15: Mounting Structure Delivery | C15: 43983 | D15: 2 | E15: 43985 | F15: 43983 | G15: 2 | H15: 43985
B16: Panel Delivery | C16: 43990 | D16: 2 | E16: 43992 | F16: 43990 | G16: 2 | H16: 43992 | L16: =IF(AND($F16<(L$2+7),$F16>L$2),1, IF(AND($H16<L$2+7,$H16>L$2),3, IF(AND($F16<=L$2, $H16>=L$2), 2, "" ))) | M16: =IF(AND($F16<(M$2+7),$F16>M$2),1, IF(AND($H16<M$2+7,$H16>M$2),3, IF(AND($F16<=M$2, $H16>=M$2), 2, "" ))) | N16: =IF(AND($F16<(N$2+7),$F16>N$2),1, IF(AND($H16<N$2+7,$H16>N$2),3, IF(AND($F16<=N$2, $H16>=N$2), 2, "" ))) | O16: =IF(AND($F16<(O$2+7),$F16>O$2),1, IF(AND($H16<O$2+7,$H16>O$2),3, IF(AND($F16<=O$2, $H16>=O$2), 2, "" ))) | P16: =IF(AND($F16<(P$2+7),$F16>P$2),1, IF(AND($H16<P$2+7,$H16>P$2),3, IF(AND($F16<=P$2, $H16>=P$2), 2, "" ))) | Q16: =IF(AND($F16<(Q$2+7),$F16>Q$2),1, IF(AND($H16<Q$2+7,$H16>Q$2),3, IF(AND($F16<=Q$2, $H16>=Q$2), 2, "" ))) | R16: =IF(AND($F16<(R$2+7),$F16>R$2),1, IF(AND($H16<R$2+7,$H16>R$2),3, IF(AND($F16<=R$2, $H16>=R$2), 2, "" ))) | S16: =IF(AND($F16<(S$2+7),$F16>S$2),1, IF(AND($H16<S$2+7,$H16>S$2),3, IF(AND($F16<=S$2, $H16>=S$2), 2, "" ))) | ... AQ16: =IF(AND($F16<(AQ$2+7),$F16>AQ$2),1, IF(AND($H16<AQ$2+7,$H16>AQ$2),3, IF(AND($F16<=AQ$2, $H16>=AQ$2), 2, "" )))
B17: Generator Delivery | C17: 43983 | D17: 2 | E17: 43985 | F17: 43983 | G17: 2 | H17: 43985
A18: B | B18: PAYMENT MILESTONE 2: DELIVERY OF PV PANELS | C18: 43992 | D18: 2 | E18: 43994 | F18: 43992 | G18: 2 | H18: 43994
B19: Inverter Delivery | C19: 43983 | D19: 2 | E19: 43985 | F19: 43983 | G19: 2 | H19: 43985 | L19: =IF(AND($F19<(L$2+7),$F19>L$2),1, IF(AND($H19<L$2+7,$H19>L$2),3, IF(AND($F19<=L$2, $H19>=L$2), 2, "" ))) | M19: =IF(AND($F19<(M$2+7),$F19>M$2),1, IF(AND($H19<M$2+7,$H19>M$2),3, IF(AND($F19<=M$2, $H19>=M$2), 2, "" ))) | N19: =IF(AND($F19<(N$2+7),$F19>N$2),1, IF(AND($H19<N$2+7,$H19>N$2),3, IF(AND($F19<=N$2, $H19>=N$2), 2, "" ))) | O19: =IF(AND($F19<(O$2+7),$F19>O$2),1, IF(AND($H19<O$2+7,$H19>O$2),3, IF(AND($F19<=O$2, $H19>=O$2), 2, "" ))) | P19: =IF(AND($F19<(P$2+7),$F19>P$2),1, IF(AND($H19<P$2+7,$H19>P$2),3, IF(AND($F19<=P$2, $H19>=P$2), 2, "" ))) | Q19: =IF(AND($F19<(Q$2+7),$F19>Q$2),1, IF(AND($H19<Q$2+7,$H19>Q$2),3, IF(AND($F19<=Q$2, $H19>=Q$2), 2, "" ))) | R19: =IF(AND($F19<(R$2+7),$F19>R$2),1, IF(AND($H19<R$2+7,$H19>R$2),3, IF(AND($F19<=R$2, $H19>=R$2), 2, "" ))) | S19: =IF(AND($F19<(S$2+7),$F19>S$2),1, IF(AND($H19<S$2+7,$H19>S$2),3, IF(AND($F19<=S$2, $H19>=S$2), 2, "" ))) | ... AQ19: =IF(AND($F19<(AQ$2+7),$F19>AQ$2),1, IF(AND($H19<AQ$2+7,$H19>AQ$2),3, IF(AND($F19<=AQ$2, $H19>=AQ$2), 2, "" )))
B20: BOS Delivery | C20: 43983 | D20: 1 | E20: 43984 | F20: 43983 | G20: 1 | H20: 43984 | L20: =IF(AND($F20<(L$2+7),$F20>L$2),1, IF(AND($H20<L$2+7,$H20>L$2),3, IF(AND($F20<=L$2, $H20>=L$2), 2, "" ))) | M20: =IF(AND($F20<(M$2+7),$F20>M$2),1, IF(AND($H20<M$2+7,$H20>M$2),3, IF(AND($F20<=M$2, $H20>=M$2), 2, "" ))) | N20: =IF(AND($F20<(N$2+7),$F20>N$2),1, IF(AND($H20<N$2+7,$H20>N$2),3, IF(AND($F20<=N$2, $H20>=N$2), 2, "" ))) | O20: =IF(AND($F20<(O$2+7),$F20>O$2),1, IF(AND($H20<O$2+7,$H20>O$2),3, IF(AND($F20<=O$2, $H20>=O$2), 2, "" ))) | P20: =IF(AND($F20<(P$2+7),$F20>P$2),1, IF(AND($H20<P$2+7,$H20>P$2),3, IF(AND($F20<=P$2, $H20>=P$2), 2, "" ))) | Q20: =IF(AND($F20<(Q$2+7),$F20>Q$2),1, IF(AND($H20<Q$2+7,$H20>Q$2),3, IF(AND($F20<=Q$2, $H20>=Q$2), 2, "" ))) | R20: =IF(AND($F20<(R$2+7),$F20>R$2),1, IF(AND($H20<R$2+7,$H20>R$2),3, IF(AND($F20<=R$2, $H20>=R$2), 2, "" ))) | S20: =IF(AND($F20<(S$2+7),$F20>S$2),1, IF(AND($H20<S$2+7,$H20>S$2),3, IF(AND($F20<=S$2, $H20>=S$2), 2, "" ))) | ... AQ20: =IF(AND($F20<(AQ$2+7),$F20>AQ$2),1, IF(AND($H20<AQ$2+7,$H20>AQ$2),3, IF(AND($F20<=AQ$2, $H20>=AQ$2), 2, "" )))
A21: C | B21: PAYMENT MILESTONE 3: DELIVERY OF INVERTERS AND BOS | C21: 43985 | D21: 2 | E21: 43987 | F21: 43985 | G21: 2 | H21: 43987
A22: 8 | B22: Installation | C22: 43990 | D22: 22 | E22: 44012 | F22: 43990 | G22: 22 | H22: 44012 | L22: =IF(AND($F22<(L$2+7),$F22>L$2),1, IF(AND($H22<L$2+7,$H22>L$2),3, IF(AND($F22<=L$2, $H22>=L$2), 2, "" ))) | M22: =IF(AND($F22<(M$2+7),$F22>M$2),1, IF(AND($H22<M$2+7,$H22>M$2),3, IF(AND($F22<=M$2, $H22>=M$2), 2, "" ))) | N22: =IF(AND($F22<(N$2+7),$F22>N$2),1, IF(AND($H22<N$2+7,$H22>N$2),3, IF(AND($F22<=N$2, $H22>=N$2), 2, "" ))) | O22: =IF(AND($F22<(O$2+7),$F22>O$2),1, IF(AND($H22<O$2+7,$H22>O$2),3, IF(AND($F22<=O$2, $H22>=O$2), 2, "" ))) | P22: =IF(AND($F22<(P$2+7),$F22>P$2),1, IF(AND($H22<P$2+7,$H22>P$2),3, IF(AND($F22<=P$2, $H22>=P$2), 2, "" ))) | Q22: =IF(AND($F22<(Q$2+7),$F22>Q$2),1, IF(AND($H22<Q$2+7,$H22>Q$2),3, IF(AND($F22<=Q$2, $H22>=Q$2), 2, "" ))) | R22: =IF(AND($F22<(R$2+7),$F22>R$2),1, IF(AND($H22<R$2+7,$H22>R$2),3, IF(AND($F22<=R$2, $H22>=R$2), 2, "" ))) | S22: =IF(AND($F22<(S$2+7),$F22>S$2),1, IF(AND($H22<S$2+7,$H22>S$2),3, IF(AND($F22<=S$2, $H22>=S$2), 2, "" ))) | ... AQ22: =IF(AND($F22<(AQ$2+7),$F22>AQ$2),1, IF(AND($H22<AQ$2+7,$H22>AQ$2),3, IF(AND($F22<=AQ$2, $H22>=AQ$2), 2, "" ))) -> 2
B23: Site Establishment | C23: 43990 | D23: 1 | E23: 43991 | F23: 43990 | G23: 1 | H23: 43991 | J23: Installation placed on hold due to Covid-19 case | L23: =IF(AND($F23<(L$2+7),$F23>L$2),1, IF(AND($H23<L$2+7,$H23>L$2),3, IF(AND($F23<=L$2, $H23>=L$2), 2, "" ))) | M23: =IF(AND($F23<(M$2+7),$F23>M$2),1, IF(AND($H23<M$2+7,$H23>M$2),3, IF(AND($F23<=M$2, $H23>=M$2), 2, "" ))) | N23: =IF(AND($F23<(N$2+7),$F23>N$2),1, IF(AND($H23<N$2+7,$H23>N$2),3, IF(AND($F23<=N$2, $H23>=N$2), 2, "" ))) | O23: =IF(AND($F23<(O$2+7),$F23>O$2),1, IF(AND($H23<O$2+7,$H23>O$2),3, IF(AND($F23<=O$2, $H23>=O$2), 2, "" ))) | P23: =IF(AND($F23<(P$2+7),$F23>P$2),1, IF(AND($H23<P$2+7,$H23>P$2),3, IF(AND($F23<=P$2, $H23>=P$2), 2, "" ))) | Q23: =IF(AND($F23<(Q$2+7),$F23>Q$2),1, IF(AND($H23<Q$2+7,$H23>Q$2),3, IF(AND($F23<=Q$2, $H23>=Q$2), 2, "" ))) | R23: =IF(AND($F23<(R$2+7),$F23>R$2),1, IF(AND($H23<R$2+7,$H23>R$2),3, IF(AND($F23<=R$2, $H23>=R$2), 2, "" ))) | S23: =IF(AND($F23<(S$2+7),$F23>S$2),1, IF(AND($H23<S$2+7,$H23>S$2),3, IF(AND($F23<=S$2, $H23>=S$2), 2, "" ))) | ... AQ23: =IF(AND($F23<(AQ$2+7),$F23>AQ$2),1, IF(AND($H23<AQ$2+7,$H23>AQ$2),3, IF(AND($F23<=AQ$2, $H23>=AQ$2), 2, "" )))
A24: 9 | B24: DC Works | C24: 43991 | D24: 16 | E24: 44012 | F24: 43991 | G24: 16 | H24: 44012 | L24: =IF(AND($F24<(L$2+7),$F24>L$2),1, IF(AND($H24<L$2+7,$H24>L$2),3, IF(AND($F24<=L$2, $H24>=L$2), 2, "" ))) | M24: =IF(AND($F24<(M$2+7),$F24>M$2),1, IF(AND($H24<M$2+7,$H24>M$2),3, IF(AND($F24<=M$2, $H24>=M$2), 2, "" ))) | N24: =IF(AND($F24<(N$2+7),$F24>N$2),1, IF(AND($H24<N$2+7,$H24>N$2),3, IF(AND($F24<=N$2, $H24>=N$2), 2, "" ))) | O24: =IF(AND($F24<(O$2+7),$F24>O$2),1, IF(AND($H24<O$2+7,$H24>O$2),3, IF(AND($F24<=O$2, $H24>=O$2), 2, "" ))) | P24: =IF(AND($F24<(P$2+7),$F24>P$2),1, IF(AND($H24<P$2+7,$H24>P$2),3, IF(AND($F24<=P$2, $H24>=P$2), 2, "" ))) | Q24: =IF(AND($F24<(Q$2+7),$F24>Q$2),1, IF(AND($H24<Q$2+7,$H24>Q$2),3, IF(AND($F24<=Q$2, $H24>=Q$2), 2, "" ))) | R24: =IF(AND($F24<(R$2+7),$F24>R$2),1, IF(AND($H24<R$2+7,$H24>R$2),3, IF(AND($F24<=R$2, $H24>=R$2), 2, "" ))) | S24: =IF(AND($F24<(S$2+7),$F24>S$2),1, IF(AND($H24<S$2+7,$H24>S$2),3, IF(AND($F24<=S$2, $H24>=S$2), 2, "" ))) | ... AQ24: =IF(AND($F24<(AQ$2+7),$F24>AQ$2),1, IF(AND($H24<AQ$2+7,$H24>AQ$2),3, IF(AND($F24<=AQ$2, $H24>=AQ$2), 2, "" ))) -> 2
B25: Mounting structure Installation | C25: 43991 | D25: 4 | E25: 43997 | F25: 43991 | G25: 4 | H25: 43997 | L25: =IF(AND($F25<(L$2+7),$F25>L$2),1, IF(AND($H25<L$2+7,$H25>L$2),3, IF(AND($F25<=L$2, $H25>=L$2), 2, "" ))) | M25: =IF(AND($F25<(M$2+7),$F25>M$2),1, IF(AND($H25<M$2+7,$H25>M$2),3, IF(AND($F25<=M$2, $H25>=M$2), 2, "" ))) | N25: =IF(AND($F25<(N$2+7),$F25>N$2),1, IF(AND($H25<N$2+7,$H25>N$2),3, IF(AND($F25<=N$2, $H25>=N$2), 2, "" ))) | O25: =IF(AND($F25<(O$2+7),$F25>O$2),1, IF(AND($H25<O$2+7,$H25>O$2),3, IF(AND($F25<=O$2, $H25>=O$2), 2, "" ))) | P25: =IF(AND($F25<(P$2+7),$F25>P$2),1, IF(AND($H25<P$2+7,$H25>P$2),3, IF(AND($F25<=P$2, $H25>=P$2), 2, "" ))) | Q25: =IF(AND($F25<(Q$2+7),$F25>Q$2),1, IF(AND($H25<Q$2+7,$H25>Q$2),3, IF(AND($F25<=Q$2, $H25>=Q$2), 2, "" ))) | R25: =IF(AND($F25<(R$2+7),$F25>R$2),1, IF(AND($H25<R$2+7,$H25>R$2),3, IF(AND($F25<=R$2, $H25>=R$2), 2, "" ))) | S25: =IF(AND($F25<(S$2+7),$F25>S$2),1, IF(AND($H25<S$2+7,$H25>S$2),3, IF(AND($F25<=S$2, $H25>=S$2), 2, "" ))) | ... AQ25: =IF(AND($F25<(AQ$2+7),$F25>AQ$2),1, IF(AND($H25<AQ$2+7,$H25>AQ$2),3, IF(AND($F25<=AQ$2, $H25>=AQ$2), 2, "" )))
B26: Cable tray Installation | C26: 43997 | D26: 3 | E26: 44004 | F26: 43997 | G26: 3 | H26: 44004 | L26: =IF(AND($F26<(L$2+7),$F26>L$2),1, IF(AND($H26<L$2+7,$H26>L$2),3, IF(AND($F26<=L$2, $H26>=L$2), 2, "" ))) | M26: =IF(AND($F26<(M$2+7),$F26>M$2),1, IF(AND($H26<M$2+7,$H26>M$2),3, IF(AND($F26<=M$2, $H26>=M$2), 2, "" ))) | N26: =IF(AND($F26<(N$2+7),$F26>N$2),1, IF(AND($H26<N$2+7,$H26>N$2),3, IF(AND($F26<=N$2, $H26>=N$2), 2, "" ))) | O26: =IF(AND($F26<(O$2+7),$F26>O$2),1, IF(AND($H26<O$2+7,$H26>O$2),3, IF(AND($F26<=O$2, $H26>=O$2), 2, "" ))) | P26: =IF(AND($F26<(P$2+7),$F26>P$2),1, IF(AND($H26<P$2+7,$H26>P$2),3, IF(AND($F26<=P$2, $H26>=P$2), 2, "" ))) | Q26: =IF(AND($F26<(Q$2+7),$F26>Q$2),1, IF(AND($H26<Q$2+7,$H26>Q$2),3, IF(AND($F26<=Q$2, $H26>=Q$2), 2, "" ))) | R26: =IF(AND($F26<(R$2+7),$F26>R$2),1, IF(AND($H26<R$2+7,$H26>R$2),3, IF(AND($F26<=R$2, $H26>=R$2), 2, "" ))) | S26: =IF(AND($F26<(S$2+7),$F26>S$2),1, IF(AND($H26<S$2+7,$H26>S$2),3, IF(AND($F26<=S$2, $H26>=S$2), 2, "" ))) | ... AQ26: =IF(AND($F26<(AQ$2+7),$F26>AQ$2),1, IF(AND($H26<AQ$2+7,$H26>AQ$2),3, IF(AND($F26<=AQ$2, $H26>=AQ$2), 2, "" )))
B27: DC Cable Installation | C27: 44004 | D27: 2 | E27: 44006 | F27: 44004 | G27: 2 | H27: 44006 | L27: =IF(AND($F27<(L$2+7),$F27>L$2),1, IF(AND($H27<L$2+7,$H27>L$2),3, IF(AND($F27<=L$2, $H27>=L$2), 2, "" ))) | M27: =IF(AND($F27<(M$2+7),$F27>M$2),1, IF(AND($H27<M$2+7,$H27>M$2),3, IF(AND($F27<=M$2, $H27>=M$2), 2, "" ))) | N27: =IF(AND($F27<(N$2+7),$F27>N$2),1, IF(AND($H27<N$2+7,$H27>N$2),3, IF(AND($F27<=N$2, $H27>=N$2), 2, "" ))) | O27: =IF(AND($F27<(O$2+7),$F27>O$2),1, IF(AND($H27<O$2+7,$H27>O$2),3, IF(AND($F27<=O$2, $H27>=O$2), 2, "" ))) | P27: =IF(AND($F27<(P$2+7),$F27>P$2),1, IF(AND($H27<P$2+7,$H27>P$2),3, IF(AND($F27<=P$2, $H27>=P$2), 2, "" ))) | Q27: =IF(AND($F27<(Q$2+7),$F27>Q$2),1, IF(AND($H27<Q$2+7,$H27>Q$2),3, IF(AND($F27<=Q$2, $H27>=Q$2), 2, "" ))) | R27: =IF(AND($F27<(R$2+7),$F27>R$2),1, IF(AND($H27<R$2+7,$H27>R$2),3, IF(AND($F27<=R$2, $H27>=R$2), 2, "" ))) | S27: =IF(AND($F27<(S$2+7),$F27>S$2),1, IF(AND($H27<S$2+7,$H27>S$2),3, IF(AND($F27<=S$2, $H27>=S$2), 2, "" ))) | ... AQ27: =IF(AND($F27<(AQ$2+7),$F27>AQ$2),1, IF(AND($H27<AQ$2+7,$H27>AQ$2),3, IF(AND($F27<=AQ$2, $H27>=AQ$2), 2, "" )))
B28: Module Installation | C28: 44006 | D28: 4 | E28: 44012 | F28: 44006 | G28: 4 | H28: 44012 | L28: =IF(AND($F28<(L$2+7),$F28>L$2),1, IF(AND($H28<L$2+7,$H28>L$2),3, IF(AND($F28<=L$2, $H28>=L$2), 2, "" ))) | M28: =IF(AND($F28<(M$2+7),$F28>M$2),1, IF(AND($H28<M$2+7,$H28>M$2),3, IF(AND($F28<=M$2, $H28>=M$2), 2, "" ))) | N28: =IF(AND($F28<(N$2+7),$F28>N$2),1, IF(AND($H28<N$2+7,$H28>N$2),3, IF(AND($F28<=N$2, $H28>=N$2), 2, "" ))) | O28: =IF(AND($F28<(O$2+7),$F28>O$2),1, IF(AND($H28<O$2+7,$H28>O$2),3, IF(AND($F28<=O$2, $H28>=O$2), 2, "" ))) | P28: =IF(AND($F28<(P$2+7),$F28>P$2),1, IF(AND($H28<P$2+7,$H28>P$2),3, IF(AND($F28<=P$2, $H28>=P$2), 2, "" ))) | Q28: =IF(AND($F28<(Q$2+7),$F28>Q$2),1, IF(AND($H28<Q$2+7,$H28>Q$2),3, IF(AND($F28<=Q$2, $H28>=Q$2), 2, "" ))) | R28: =IF(AND($F28<(R$2+7),$F28>R$2),1, IF(AND($H28<R$2+7,$H28>R$2),3, IF(AND($F28<=R$2, $H28>=R$2), 2, "" ))) | S28: =IF(AND($F28<(S$2+7),$F28>S$2),1, IF(AND($H28<S$2+7,$H28>S$2),3, IF(AND($F28<=S$2, $H28>=S$2), 2, "" ))) | ... AQ28: =IF(AND($F28<(AQ$2+7),$F28>AQ$2),1, IF(AND($H28<AQ$2+7,$H28>AQ$2),3, IF(AND($F28<=AQ$2, $H28>=AQ$2), 2, "" ))) -> 2
B29: Earth Cable Installation | C29: 44004 | D29: 1 | E29: 44005 | F29: 44004 | G29: 1 | H29: 44005 | L29: =IF(AND($F29<(L$2+7),$F29>L$2),1, IF(AND($H29<L$2+7,$H29>L$2),3, IF(AND($F29<=L$2, $H29>=L$2), 2, "" ))) | M29: =IF(AND($F29<(M$2+7),$F29>M$2),1, IF(AND($H29<M$2+7,$H29>M$2),3, IF(AND($F29<=M$2, $H29>=M$2), 2, "" ))) | N29: =IF(AND($F29<(N$2+7),$F29>N$2),1, IF(AND($H29<N$2+7,$H29>N$2),3, IF(AND($F29<=N$2, $H29>=N$2), 2, "" ))) | O29: =IF(AND($F29<(O$2+7),$F29>O$2),1, IF(AND($H29<O$2+7,$H29>O$2),3, IF(AND($F29<=O$2, $H29>=O$2), 2, "" ))) | P29: =IF(AND($F29<(P$2+7),$F29>P$2),1, IF(AND($H29<P$2+7,$H29>P$2),3, IF(AND($F29<=P$2, $H29>=P$2), 2, "" ))) | Q29: =IF(AND($F29<(Q$2+7),$F29>Q$2),1, IF(AND($H29<Q$2+7,$H29>Q$2),3, IF(AND($F29<=Q$2, $H29>=Q$2), 2, "" ))) | R29: =IF(AND($F29<(R$2+7),$F29>R$2),1, IF(AND($H29<R$2+7,$H29>R$2),3, IF(AND($F29<=R$2, $H29>=R$2), 2, "" ))) | S29: =IF(AND($F29<(S$2+7),$F29>S$2),1, IF(AND($H29<S$2+7,$H29>S$2),3, IF(AND($F29<=S$2, $H29>=S$2), 2, "" ))) | ... AQ29: =IF(AND($F29<(AQ$2+7),$F29>AQ$2),1, IF(AND($H29<AQ$2+7,$H29>AQ$2),3, IF(AND($F29<=AQ$2, $H29>=AQ$2), 2, "" )))
A30: 10 | B30: AC Works | C30: 43991 | D30: 8 | E30: 44000 | F30: 43991 | G30: 8 | H30: 44000
B31: Inverters Installation | C31: 43991 | D31: 2 | E31: 43993 | F31: 43991 | G31: 2 | H31: 43993 | L31: =IF(AND($F31<(L$2+7),$F31>L$2),1, IF(AND($H31<L$2+7,$H31>L$2),3, IF(AND($F31<=L$2, $H31>=L$2), 2, "" ))) | M31: =IF(AND($F31<(M$2+7),$F31>M$2),1, IF(AND($H31<M$2+7,$H31>M$2),3, IF(AND($F31<=M$2, $H31>=M$2), 2, "" ))) | N31: =IF(AND($F31<(N$2+7),$F31>N$2),1, IF(AND($H31<N$2+7,$H31>N$2),3, IF(AND($F31<=N$2, $H31>=N$2), 2, "" ))) | O31: =IF(AND($F31<(O$2+7),$F31>O$2),1, IF(AND($H31<O$2+7,$H31>O$2),3, IF(AND($F31<=O$2, $H31>=O$2), 2, "" ))) | P31: =IF(AND($F31<(P$2+7),$F31>P$2),1, IF(AND($H31<P$2+7,$H31>P$2),3, IF(AND($F31<=P$2, $H31>=P$2), 2, "" ))) | Q31: =IF(AND($F31<(Q$2+7),$F31>Q$2),1, IF(AND($H31<Q$2+7,$H31>Q$2),3, IF(AND($F31<=Q$2, $H31>=Q$2), 2, "" ))) | R31: =IF(AND($F31<(R$2+7),$F31>R$2),1, IF(AND($H31<R$2+7,$H31>R$2),3, IF(AND($F31<=R$2, $H31>=R$2), 2, "" ))) | S31: =IF(AND($F31<(S$2+7),$F31>S$2),1, IF(AND($H31<S$2+7,$H31>S$2),3, IF(AND($F31<=S$2, $H31>=S$2), 2, "" ))) | ... AQ31: =IF(AND($F31<(AQ$2+7),$F31>AQ$2),1, IF(AND($H31<AQ$2+7,$H31>AQ$2),3, IF(AND($F31<=AQ$2, $H31>=AQ$2), 2, "" )))
B32: AC BOS Installation | C32: 43993 | D32: 3 | E32: 44000 | F32: 43993 | G32: 3 | H32: 44000 | L32: =IF(AND($F32<(L$2+7),$F32>L$2),1, IF(AND($H32<L$2+7,$H32>L$2),3, IF(AND($F32<=L$2, $H32>=L$2), 2, "" ))) | M32: =IF(AND($F32<(M$2+7),$F32>M$2),1, IF(AND($H32<M$2+7,$H32>M$2),3, IF(AND($F32<=M$2, $H32>=M$2), 2, "" ))) | N32: =IF(AND($F32<(N$2+7),$F32>N$2),1, IF(AND($H32<N$2+7,$H32>N$2),3, IF(AND($F32<=N$2, $H32>=N$2), 2, "" ))) | O32: =IF(AND($F32<(O$2+7),$F32>O$2),1, IF(AND($H32<O$2+7,$H32>O$2),3, IF(AND($F32<=O$2, $H32>=O$2), 2, "" ))) | P32: =IF(AND($F32<(P$2+7),$F32>P$2),1, IF(AND($H32<P$2+7,$H32>P$2),3, IF(AND($F32<=P$2, $H32>=P$2), 2, "" ))) | Q32: =IF(AND($F32<(Q$2+7),$F32>Q$2),1, IF(AND($H32<Q$2+7,$H32>Q$2),3, IF(AND($F32<=Q$2, $H32>=Q$2), 2, "" ))) | R32: =IF(AND($F32<(R$2+7),$F32>R$2),1, IF(AND($H32<R$2+7,$H32>R$2),3, IF(AND($F32<=R$2, $H32>=R$2), 2, "" ))) | S32: =IF(AND($F32<(S$2+7),$F32>S$2),1, IF(AND($H32<S$2+7,$H32>S$2),3, IF(AND($F32<=S$2, $H32>=S$2), 2, "" ))) | ... AQ32: =IF(AND($F32<(AQ$2+7),$F32>AQ$2),1, IF(AND($H32<AQ$2+7,$H32>AQ$2),3, IF(AND($F32<=AQ$2, $H32>=AQ$2), 2, "" )))
B33: AC Cable/Tie-In | C33: 43992 | D33: 3 | E33: 43997 | F33: 43992 | G33: 3 | H33: 43997 | L33: =IF(AND($F33<(L$2+7),$F33>L$2),1, IF(AND($H33<L$2+7,$H33>L$2),3, IF(AND($F33<=L$2, $H33>=L$2), 2, "" ))) | M33: =IF(AND($F33<(M$2+7),$F33>M$2),1, IF(AND($H33<M$2+7,$H33>M$2),3, IF(AND($F33<=M$2, $H33>=M$2), 2, "" ))) | N33: =IF(AND($F33<(N$2+7),$F33>N$2),1, IF(AND($H33<N$2+7,$H33>N$2),3, IF(AND($F33<=N$2, $H33>=N$2), 2, "" ))) | O33: =IF(AND($F33<(O$2+7),$F33>O$2),1, IF(AND($H33<O$2+7,$H33>O$2),3, IF(AND($F33<=O$2, $H33>=O$2), 2, "" ))) | P33: =IF(AND($F33<(P$2+7),$F33>P$2),1, IF(AND($H33<P$2+7,$H33>P$2),3, IF(AND($F33<=P$2, $H33>=P$2), 2, "" ))) | Q33: =IF(AND($F33<(Q$2+7),$F33>Q$2),1, IF(AND($H33<Q$2+7,$H33>Q$2),3, IF(AND($F33<=Q$2, $H33>=Q$2), 2, "" ))) | R33: =IF(AND($F33<(R$2+7),$F33>R$2),1, IF(AND($H33<R$2+7,$H33>R$2),3, IF(AND($F33<=R$2, $H33>=R$2), 2, "" ))) | S33: =IF(AND($F33<(S$2+7),$F33>S$2),1, IF(AND($H33<S$2+7,$H33>S$2),3, IF(AND($F33<=S$2, $H33>=S$2), 2, "" ))) | ... AQ33: =IF(AND($F33<(AQ$2+7),$F33>AQ$2),1, IF(AND($H33<AQ$2+7,$H33>AQ$2),3, IF(AND($F33<=AQ$2, $H33>=AQ$2), 2, "" )))
B34: Monitoring Platform Installation | C34: 43997 | D34: 1 | E34: 44000 | F34: 43997 | G34: 1 | H34: 44000
A35: 11 | B35: Completion | C35: 44000 | D35: 14 | E35: 44014 | F35: 44000 | G35: 14 | H35: 44014 | L35: =IF(AND($F35<(L$2+7),$F35>L$2),1, IF(AND($H35<L$2+7,$H35>L$2),3, IF(AND($F35<=L$2, $H35>=L$2), 2, "" ))) | M35: =IF(AND($F35<(M$2+7),$F35>M$2),1, IF(AND($H35<M$2+7,$H35>M$2),3, IF(AND($F35<=M$2, $H35>=M$2), 2, "" ))) | N35: =IF(AND($F35<(N$2+7),$F35>N$2),1, IF(AND($H35<N$2+7,$H35>N$2),3, IF(AND($F35<=N$2, $H35>=N$2), 2, "" ))) | O35: =IF(AND($F35<(O$2+7),$F35>O$2),1, IF(AND($H35<O$2+7,$H35>O$2),3, IF(AND($F35<=O$2, $H35>=O$2), 2, "" ))) | P35: =IF(AND($F35<(P$2+7),$F35>P$2),1, IF(AND($H35<P$2+7,$H35>P$2),3, IF(AND($F35<=P$2, $H35>=P$2), 2, "" ))) | Q35: =IF(AND($F35<(Q$2+7),$F35>Q$2),1, IF(AND($H35<Q$2+7,$H35>Q$2),3, IF(AND($F35<=Q$2, $H35>=Q$2), 2, "" ))) | R35: =IF(AND($F35<(R$2+7),$F35>R$2),1, IF(AND($H35<R$2+7,$H35>R$2),3, IF(AND($F35<=R$2, $H35>=R$2), 2, "" ))) | S35: =IF(AND($F35<(S$2+7),$F35>S$2),1, IF(AND($H35<S$2+7,$H35>S$2),3, IF(AND($F35<=S$2, $H35>=S$2), 2, "" ))) | ... AQ35: =IF(AND($F35<(AQ$2+7),$F35>AQ$2),1, IF(AND($H35<AQ$2+7,$H35>AQ$2),3, IF(AND($F35<=AQ$2, $H35>=AQ$2), 2, "" ))) -> 3
B36: DC Works | C36: 44012 | D36: 2 | E36: 44014 | F36: 44012 | G36: 2 | H36: 44014 | L36: =IF(AND($F36<(L$2+7),$F36>L$2),1, IF(AND($H36<L$2+7,$H36>L$2),3, IF(AND($F36<=L$2, $H36>=L$2), 2, "" ))) | M36: =IF(AND($F36<(M$2+7),$F36>M$2),1, IF(AND($H36<M$2+7,$H36>M$2),3, IF(AND($F36<=M$2, $H36>=M$2), 2, "" ))) | N36: =IF(AND($F36<(N$2+7),$F36>N$2),1, IF(AND($H36<N$2+7,$H36>N$2),3, IF(AND($F36<=N$2, $H36>=N$2), 2, "" ))) | O36: =IF(AND($F36<(O$2+7),$F36>O$2),1, IF(AND($H36<O$2+7,$H36>O$2),3, IF(AND($F36<=O$2, $H36>=O$2), 2, "" ))) | P36: =IF(AND($F36<(P$2+7),$F36>P$2),1, IF(AND($H36<P$2+7,$H36>P$2),3, IF(AND($F36<=P$2, $H36>=P$2), 2, "" ))) | Q36: =IF(AND($F36<(Q$2+7),$F36>Q$2),1, IF(AND($H36<Q$2+7,$H36>Q$2),3, IF(AND($F36<=Q$2, $H36>=Q$2), 2, "" ))) | R36: =IF(AND($F36<(R$2+7),$F36>R$2),1, IF(AND($H36<R$2+7,$H36>R$2),3, IF(AND($F36<=R$2, $H36>=R$2), 2, "" ))) | S36: =IF(AND($F36<(S$2+7),$F36>S$2),1, IF(AND($H36<S$2+7,$H36>S$2),3, IF(AND($F36<=S$2, $H36>=S$2), 2, "" ))) | ... AQ36: =IF(AND($F36<(AQ$2+7),$F36>AQ$2),1, IF(AND($H36<AQ$2+7,$H36>AQ$2),3, IF(AND($F36<=AQ$2, $H36>=AQ$2), 2, "" ))) -> 3
B37: AC Works | C37: 44000 | D37: 2 | E37: 44004 | F37: 44000 | G37: 2 | H37: 44004 | L37: =IF(AND($F37<(L$2+7),$F37>L$2),1, IF(AND($H37<L$2+7,$H37>L$2),3, IF(AND($F37<=L$2, $H37>=L$2), 2, "" ))) | M37: =IF(AND($F37<(M$2+7),$F37>M$2),1, IF(AND($H37<M$2+7,$H37>M$2),3, IF(AND($F37<=M$2, $H37>=M$2), 2, "" ))) | N37: =IF(AND($F37<(N$2+7),$F37>N$2),1, IF(AND($H37<N$2+7,$H37>N$2),3, IF(AND($F37<=N$2, $H37>=N$2), 2, "" ))) | O37: =IF(AND($F37<(O$2+7),$F37>O$2),1, IF(AND($H37<O$2+7,$H37>O$2),3, IF(AND($F37<=O$2, $H37>=O$2), 2, "" ))) | P37: =IF(AND($F37<(P$2+7),$F37>P$2),1, IF(AND($H37<P$2+7,$H37>P$2),3, IF(AND($F37<=P$2, $H37>=P$2), 2, "" ))) | Q37: =IF(AND($F37<(Q$2+7),$F37>Q$2),1, IF(AND($H37<Q$2+7,$H37>Q$2),3, IF(AND($F37<=Q$2, $H37>=Q$2), 2, "" ))) | R37: =IF(AND($F37<(R$2+7),$F37>R$2),1, IF(AND($H37<R$2+7,$H37>R$2),3, IF(AND($F37<=R$2, $H37>=R$2), 2, "" ))) | S37: =IF(AND($F37<(S$2+7),$F37>S$2),1, IF(AND($H37<S$2+7,$H37>S$2),3, IF(AND($F37<=S$2, $H37>=S$2), 2, "" ))) | ... AQ37: =IF(AND($F37<(AQ$2+7),$F37>AQ$2),1, IF(AND($H37<AQ$2+7,$H37>AQ$2),3, IF(AND($F37<=AQ$2, $H37>=AQ$2), 2, "" )))
A38: D | B38: PAYMENT MILESTONE 4: PRACTICAL COMPLETION | C38: 44012 | D38: 1 | E38: 44013 | F38: 44012 | G38: 1 | H38: 44013 | L38: =IF(AND($F38<(L$2+7),$F38>L$2),1, IF(AND($H38<L$2+7,$H38>L$2),3, IF(AND($F38<=L$2, $H38>=L$2), 2, "" ))) | M38: =IF(AND($F38<(M$2+7),$F38>M$2),1, IF(AND($H38<M$2+7,$H38>M$2),3, IF(AND($F38<=M$2, $H38>=M$2), 2, "" ))) | N38: =IF(AND($F38<(N$2+7),$F38>N$2),1, IF(AND($H38<N$2+7,$H38>N$2),3, IF(AND($F38<=N$2, $H38>=N$2), 2, "" ))) | O38: =IF(AND($F38<(O$2+7),$F38>O$2),1, IF(AND($H38<O$2+7,$H38>O$2),3, IF(AND($F38<=O$2, $H38>=O$2), 2, "" ))) | P38: =IF(AND($F38<(P$2+7),$F38>P$2),1, IF(AND($H38<P$2+7,$H38>P$2),3, IF(AND($F38<=P$2, $H38>=P$2), 2, "" ))) | Q38: =IF(AND($F38<(Q$2+7),$F38>Q$2),1, IF(AND($H38<Q$2+7,$H38>Q$2),3, IF(AND($F38<=Q$2, $H38>=Q$2), 2, "" ))) | R38: =IF(AND($F38<(R$2+7),$F38>R$2),1, IF(AND($H38<R$2+7,$H38>R$2),3, IF(AND($F38<=R$2, $H38>=R$2), 2, "" ))) | S38: =IF(AND($F38<(S$2+7),$F38>S$2),1, IF(AND($H38<S$2+7,$H38>S$2),3, IF(AND($F38<=S$2, $H38>=S$2), 2, "" ))) | ... AQ38: =IF(AND($F38<(AQ$2+7),$F38>AQ$2),1, IF(AND($H38<AQ$2+7,$H38>AQ$2),3, IF(AND($F38<=AQ$2, $H38>=AQ$2), 2, "" ))) -> 3
A39: 12 | B39: Commissioning | C39: 43997 | D39: 22 | E39: 44019 | F39: 43997 | G39: 22 | H39: 44019 | L39: =IF(AND($F39<(L$2+7),$F39>L$2),1, IF(AND($H39<L$2+7,$H39>L$2),3, IF(AND($F39<=L$2, $H39>=L$2), 2, "" ))) | M39: =IF(AND($F39<(M$2+7),$F39>M$2),1, IF(AND($H39<M$2+7,$H39>M$2),3, IF(AND($F39<=M$2, $H39>=M$2), 2, "" ))) | N39: =IF(AND($F39<(N$2+7),$F39>N$2),1, IF(AND($H39<N$2+7,$H39>N$2),3, IF(AND($F39<=N$2, $H39>=N$2), 2, "" ))) | O39: =IF(AND($F39<(O$2+7),$F39>O$2),1, IF(AND($H39<O$2+7,$H39>O$2),3, IF(AND($F39<=O$2, $H39>=O$2), 2, "" ))) | P39: =IF(AND($F39<(P$2+7),$F39>P$2),1, IF(AND($H39<P$2+7,$H39>P$2),3, IF(AND($F39<=P$2, $H39>=P$2), 2, "" ))) | Q39: =IF(AND($F39<(Q$2+7),$F39>Q$2),1, IF(AND($H39<Q$2+7,$H39>Q$2),3, IF(AND($F39<=Q$2, $H39>=Q$2), 2, "" ))) | R39: =IF(AND($F39<(R$2+7),$F39>R$2),1, IF(AND($H39<R$2+7,$H39>R$2),3, IF(AND($F39<=R$2, $H39>=R$2), 2, "" ))) | S39: =IF(AND($F39<(S$2+7),$F39>S$2),1, IF(AND($H39<S$2+7,$H39>S$2),3, IF(AND($F39<=S$2, $H39>=S$2), 2, "" ))) | ... AQ39: =IF(AND($F39<(AQ$2+7),$F39>AQ$2),1, IF(AND($H39<AQ$2+7,$H39>AQ$2),3, IF(AND($F39<=AQ$2, $H39>=AQ$2), 2, "" ))) -> 2
B40: Snag List | C40: 44014 | D40: 3 | E40: 44019 | F40: 44014 | G40: 3 | H40: 44019
B41: Pre-Commissioning Checks | C41: 44010 | D41: 2 | E41: 44012 | F41: 44010 | G41: 2 | H41: 44012
B42: Issue CoC | C42: 43997 | D42: 2 | E42: 44001 | F42: 43997 | G42: 2 | H42: 44001 | L42: =IF(AND($F42<(L$2+7),$F42>L$2),1, IF(AND($H42<L$2+7,$H42>L$2),3, IF(AND($F42<=L$2, $H42>=L$2), 2, "" ))) | M42: =IF(AND($F42<(M$2+7),$F42>M$2),1, IF(AND($H42<M$2+7,$H42>M$2),3, IF(AND($F42<=M$2, $H42>=M$2), 2, "" ))) | N42: =IF(AND($F42<(N$2+7),$F42>N$2),1, IF(AND($H42<N$2+7,$H42>N$2),3, IF(AND($F42<=N$2, $H42>=N$2), 2, "" ))) | O42: =IF(AND($F42<(O$2+7),$F42>O$2),1, IF(AND($H42<O$2+7,$H42>O$2),3, IF(AND($F42<=O$2, $H42>=O$2), 2, "" ))) | P42: =IF(AND($F42<(P$2+7),$F42>P$2),1, IF(AND($H42<P$2+7,$H42>P$2),3, IF(AND($F42<=P$2, $H42>=P$2), 2, "" ))) | Q42: =IF(AND($F42<(Q$2+7),$F42>Q$2),1, IF(AND($H42<Q$2+7,$H42>Q$2),3, IF(AND($F42<=Q$2, $H42>=Q$2), 2, "" ))) | R42: =IF(AND($F42<(R$2+7),$F42>R$2),1, IF(AND($H42<R$2+7,$H42>R$2),3, IF(AND($F42<=R$2, $H42>=R$2), 2, "" ))) | S42: =IF(AND($F42<(S$2+7),$F42>S$2),1, IF(AND($H42<S$2+7,$H42>S$2),3, IF(AND($F42<=S$2, $H42>=S$2), 2, "" ))) | ... AQ42: =IF(AND($F42<(AQ$2+7),$F42>AQ$2),1, IF(AND($H42<AQ$2+7,$H42>AQ$2),3, IF(AND($F42<=AQ$2, $H42>=AQ$2), 2, "" )))
B43: Cold Commissioning | C43: 44012 | D43: 1 | E43: 44013 | F43: 44012 | G43: 1 | H43: 44013 | L43: =IF(AND($F43<(L$2+7),$F43>L$2),1, IF(AND($H43<L$2+7,$H43>L$2),3, IF(AND($F43<=L$2, $H43>=L$2), 2, "" ))) | M43: =IF(AND($F43<(M$2+7),$F43>M$2),1, IF(AND($H43<M$2+7,$H43>M$2),3, IF(AND($F43<=M$2, $H43>=M$2), 2, "" ))) | N43: =IF(AND($F43<(N$2+7),$F43>N$2),1, IF(AND($H43<N$2+7,$H43>N$2),3, IF(AND($F43<=N$2, $H43>=N$2), 2, "" ))) | O43: =IF(AND($F43<(O$2+7),$F43>O$2),1, IF(AND($H43<O$2+7,$H43>O$2),3, IF(AND($F43<=O$2, $H43>=O$2), 2, "" ))) | P43: =IF(AND($F43<(P$2+7),$F43>P$2),1, IF(AND($H43<P$2+7,$H43>P$2),3, IF(AND($F43<=P$2, $H43>=P$2), 2, "" ))) | Q43: =IF(AND($F43<(Q$2+7),$F43>Q$2),1, IF(AND($H43<Q$2+7,$H43>Q$2),3, IF(AND($F43<=Q$2, $H43>=Q$2), 2, "" ))) | R43: =IF(AND($F43<(R$2+7),$F43>R$2),1, IF(AND($H43<R$2+7,$H43>R$2),3, IF(AND($F43<=R$2, $H43>=R$2), 2, "" ))) | S43: =IF(AND($F43<(S$2+7),$F43>S$2),1, IF(AND($H43<S$2+7,$H43>S$2),3, IF(AND($F43<=S$2, $H43>=S$2), 2, "" ))) | ... AQ43: =IF(AND($F43<(AQ$2+7),$F43>AQ$2),1, IF(AND($H43<AQ$2+7,$H43>AQ$2),3, IF(AND($F43<=AQ$2, $H43>=AQ$2), 2, "" ))) -> 3
B44: Hot Commissioning | C44: 44013 | D44: 2 | E44: 44015 | F44: 44013 | G44: 2 | H44: 44015 | L44: =IF(AND($F44<(L$2+7),$F44>L$2),1, IF(AND($H44<L$2+7,$H44>L$2),3, IF(AND($F44<=L$2, $H44>=L$2), 2, "" ))) | M44: =IF(AND($F44<(M$2+7),$F44>M$2),1, IF(AND($H44<M$2+7,$H44>M$2),3, IF(AND($F44<=M$2, $H44>=M$2), 2, "" ))) | N44: =IF(AND($F44<(N$2+7),$F44>N$2),1, IF(AND($H44<N$2+7,$H44>N$2),3, IF(AND($F44<=N$2, $H44>=N$2), 2, "" ))) | O44: =IF(AND($F44<(O$2+7),$F44>O$2),1, IF(AND($H44<O$2+7,$H44>O$2),3, IF(AND($F44<=O$2, $H44>=O$2), 2, "" ))) | P44: =IF(AND($F44<(P$2+7),$F44>P$2),1, IF(AND($H44<P$2+7,$H44>P$2),3, IF(AND($F44<=P$2, $H44>=P$2), 2, "" ))) | Q44: =IF(AND($F44<(Q$2+7),$F44>Q$2),1, IF(AND($H44<Q$2+7,$H44>Q$2),3, IF(AND($F44<=Q$2, $H44>=Q$2), 2, "" ))) | R44: =IF(AND($F44<(R$2+7),$F44>R$2),1, IF(AND($H44<R$2+7,$H44>R$2),3, IF(AND($F44<=R$2, $H44>=R$2), 2, "" ))) | S44: =IF(AND($F44<(S$2+7),$F44>S$2),1, IF(AND($H44<S$2+7,$H44>S$2),3, IF(AND($F44<=S$2, $H44>=S$2), 2, "" ))) | ... AQ44: =IF(AND($F44<(AQ$2+7),$F44>AQ$2),1, IF(AND($H44<AQ$2+7,$H44>AQ$2),3, IF(AND($F44<=AQ$2, $H44>=AQ$2), 2, "" ))) -> 1
A45: 13 | B45: Handover | C45: 44020 | D45: 1 | E45: 44021 | F45: 44020 | G45: 1 | H45: 44021 | L45: =IF(AND($F45<(L$2+7),$F45>L$2),1, IF(AND($H45<L$2+7,$H45>L$2),3, IF(AND($F45<=L$2, $H45>=L$2), 2, "" ))) | M45: =IF(AND($F45<(M$2+7),$F45>M$2),1, IF(AND($H45<M$2+7,$H45>M$2),3, IF(AND($F45<=M$2, $H45>=M$2), 2, "" ))) | N45: =IF(AND($F45<(N$2+7),$F45>N$2),1, IF(AND($H45<N$2+7,$H45>N$2),3, IF(AND($F45<=N$2, $H45>=N$2), 2, "" ))) | O45: =IF(AND($F45<(O$2+7),$F45>O$2),1, IF(AND($H45<O$2+7,$H45>O$2),3, IF(AND($F45<=O$2, $H45>=O$2), 2, "" ))) | P45: =IF(AND($F45<(P$2+7),$F45>P$2),1, IF(AND($H45<P$2+7,$H45>P$2),3, IF(AND($F45<=P$2, $H45>=P$2), 2, "" ))) | Q45: =IF(AND($F45<(Q$2+7),$F45>Q$2),1, IF(AND($H45<Q$2+7,$H45>Q$2),3, IF(AND($F45<=Q$2, $H45>=Q$2), 2, "" ))) | R45: =IF(AND($F45<(R$2+7),$F45>R$2),1, IF(AND($H45<R$2+7,$H45>R$2),3, IF(AND($F45<=R$2, $H45>=R$2), 2, "" ))) | S45: =IF(AND($F45<(S$2+7),$F45>S$2),1, IF(AND($H45<S$2+7,$H45>S$2),3, IF(AND($F45<=S$2, $H45>=S$2), 2, "" ))) | ... AQ45: =IF(AND($F45<(AQ$2+7),$F45>AQ$2),1, IF(AND($H45<AQ$2+7,$H45>AQ$2),3, IF(AND($F45<=AQ$2, $H45>=AQ$2), 2, "" )))
A46: E | B46: PAYMENT MILESTONE 6: HANDOVER COMPLETE | C46: 44022 | D46: 1 | E46: 44025 | F46: 44022 | G46: 1 | H46: 44025
C47: 43831 | D47: These numbers are used to set the start and end dates on the Gantt Chart
C48: 44014

Sheet Certificate - Financial Close
B2: Emergent Energy – Financial Close Completion Certificate | H2: FINANCIAL CLOSE CERTIFICATE
B4: Project Name: | C4: ='Project Plan'!E2 -> BMG Fluid Tech
B5: COO: | C5: Johannes Potgieter
B6: Programme Manager: | C6: Roedolph Venter
B7: HoPD: | C7: Natasha Watkins-Baker
B9: Date of Phase Completion:
B10: Phase Deliverables Checklist: (Y/N)
B11: Product Agreement | C11: NA
B12: EPC Agreement | C12: NA
B13: O&M Agreeement | C13: NA
B14: Cost Proposal | C14: Signed
B15: Deposit Received | C15: Yes
B16: Risks / Notes | C16: None
B18: Acknowledgement and Acceptance:
B19: Role | C19: Name | D19: Signature | E19: Date
B20: COO | C20: Johannes | D20: JTP | E20: 45953

Sheet Change Register
F1: Change Register
B3: ID | C3: Description | D3: Folder URL | E3: Impact | F3: Proposed Date | G3: Proposed By | H3: Status | I3: Approved By | J3: Date | K3: Results / Comments
B4: DEC001 | C4: Carport Single Row redesign from south face to North. | D4: https://emergy.sharepoint.com/:f:/s/Emergent_Energy/IgAEhud4kKKoSbGrY_3Epw1qAUy8KJZITDPiWcKbL-Mlzgc?e=mtZGfR | E4: 4 week delay/extension to PC due for new strut manufacturing lead times. | F4: 45946 | G4: JT and Schletter | H4: Approved | I4: Client Signed off | J4: 45967 | K4: Multiple reitarations occurred from intial V1 to V4 being the final one.
B5: DEC002
B6: DEC003
B7: DEC004
B8: DEC005
B9: DEC006
B10: DEC007
B11: DEC008
B12: DEC009
B13: DEC010

Sheet BOQ
B2: Item | C2: Supplier | D2: Description | E2: Quantity | F2: Comments
B3: PV Module
B4: Mounting Structure
B5: DC Cable Red & Black
B6: Inverters
B7: Current Transformers (Production)
B8: Current Transformers (Consumption)
B9: Solar Production Meter
B10: Solar Consumption Meter
B11: Wi-Fi Router & Sim
B12: Switch
B13: Back Up Battery
B14: PVDB
... B30: Techsitter

Sheet Compliance
B2: HSE
B4: Description | C4: Status | D4: Approved By | E4: Date | F4: Results / Comments
B5: NOC
B6: 7.1 Agreement
B7: 13.2 Agreement
B8: EE File
B9: Subbie File
B16: SSEG
B18: Description | C18: Status | D18: Approved By | E18: Date | F18: Results / Comments
B19: SSEG Application
B20: PTI
B21: Commissioning Approval

Sheet Revenue Tracking
B2: HIGH LEVEL PROJECT REVENUE TRACKING
D3: COSTED | F3: ACTUAL | L3: FINANCIAL REVIEW | N3: TIMELINE REVIEW | P3: 2025 Actual Revenue | Q3: 2025 Actual COS | R3: 2026 Budget Revenue | S3: 2026 Budget COS | T3: 2026 Actual Revenue | U3: 2026 Actual COS
B4: 1 | C4: Planned Revenue | D4: ='Project Plan'!E6 -> 3984069.2 | F4: =F21 -> 3984069.2 | L4: 3984069.2 | N4: Start Date | P4: =SUMIFS('Expenditure Breakdown'!$U:$U, 'Expenditure Breakdown'!$T:$T, ">"&DATE(2024,8,31), 'Expenditure Breakdown'!$T:$T, "<="&DATE(2025,8,31), 'Expenditure Breakdown'!$S:$S, "<>") -> 2930458.9 | Q4: =SUMIFS('Expenditure Breakdown'!$Q:$Q, 'Expenditure Breakdown'!$T:$T, ">"&DATE(2024,8,31), 'Expenditure Breakdown'!$T:$T, "<="&DATE(2025,8,31), 'Expenditure Breakdown'!$S:$S, "<>") -> 2867100.4 | R4: =SUMIFS('Expenditure Breakdown'!$U:$U, 'Expenditure Breakdown'!$T:$T, ">"&DATE(2025,8,31), 'Expenditure Breakdown'!$T:$T, "<="&DATE(2026,8,31)) -> 265580.76 | S4: =SUMIFS('Expenditure Breakdown'!$Q:$Q, 'Expenditure Breakdown'!$T:$T, ">"&DATE(2025,8,31), 'Expenditure Breakdown'!$T:$T, "<="&DATE(2026,8,31)) -> 409781.67 | T4: =SUMIFS('Expenditure Breakdown'!$U:$U, 'Expenditure Breakdown'!$T:$T, ">"&DATE(2025,8,31), 'Expenditure Breakdown'!$T:$T, "<="&DATE(2026,8,31), 'Expenditure Breakdown'!$S:$S, "<>") -> 186463.76 | U4: =SUMIFS('Expenditure Breakdown'!$Q:$Q, 'Expenditure Breakdown'!$T:$T, ">"&DATE(2025,8,31), 'Expenditure Breakdown'!$T:$T, "<="&DATE(2026,8,31), 'Expenditure Breakdown'!$S:$S, "<>") -> 348464.8
B5: 2 | C5: Planned Expenditure | D5: =+'Expenditure Tracking'!F5 -> 3079187 | F5: =+'Expenditure Tracking'!H5 -> 3276882 | G5: VO PM Limit | H5: Current VO Total | L5: 3164175.2 | N5: 45868
B6: 3 | C6: Planned Profit | D6: =+D4-D5 -> 904882.2 | F6: =+F4-F5 -> 707187.22 | G6: =D6*0.05 -> 45244.11 | H6: =SUMIF('Expenditure Breakdown'!N:N,"*VO*",'Expenditure Breakdown'!Q:Q) -> 66149.26 | L6: 819894.07 | N6: End Date - PC
B7: 4 | C7: Planned Margin | D7: =+D6/D4 -> 0.22712512 | F7: =+F6/F4 -> 0.17750375 | L7: 0.20579313 | N7: 45950
B10: CONTRACT
B12: No. | C12: PAYMENT MILESTONE | E12: % | F12: VALUE | H12: PLANNED PAYMENT DATE | L12: INVOICE NUMBER | N12: INVOICE RAISED DATE | P12: PAYMENT RECEIVED DATE | R12: MILESTONE NOTES & COMMENTS
B13: 1 | C13: Acceptance and Initial Deposit | E13: 0.5 | F13: =$D$4*E13 -> 1992034.6 | H13: 45808 | L13: 004769 | N13: 45826 | P13: 45833
B14: 2 | C14: Delivery of Panels | E14: 0.25 | F14: =$D$4*E14 -> 996017.31 | H14: ='Project Plan'!E41+7 -> 45903 | L14: 004827 | N14: 45900 | P14: 45908
B15: 3 | C15: Delivery of Inverters | E15: 0.1 | F15: =$D$4*E15 -> 398406.92 | H15: ='Project Plan'!E22+7 -> 45907 | L15: 004804 | N15: 45869 | P15: 45888
B16: 4 | C16: Practical Completion | E16: 0.1 | F16: =$D$4*E16 -> 398406.92 | H16: 45981 | L16: 004928 | N16: 46044 | P16: 46064 | R16: Site achieved PC today - 22 Jan - Invoice Sent
B17: 5 | C17: Handover | E17: 0.05 | F17: =$D$4*E17 -> 199203.46 | H17: 45996 | P17: ='Project Plan'!I56+14 -> 46083
B18: 6 | C18: - | E18: 0 | F18: =$D$4*E18 -> 0
B19: 7 | C19: - | E19: 0 | F19: =$D$4*E19 -> 0
E21: =SUM(E13:E19) -> 1 | F21: =SUM(F13:F19) -> 3984069.2
B23: KEY: | C23: contains an error (in result or a check has failed)
C24: Red Font - IF TEXT : content not yet confirmed
C25: Red Font - IF NUMBER: Negative value
C26: Anything in yellow is a concern or risk for noting or action
C27: confirmed
C28: [ADD INITIALS: comment for noting in square brackets, use colour or red to draw attention if important]
C29: [RT: When adding rows into sheet, ensure you insert between first and last row of each category]
C30: end of sheet - do not insert information below/beyond this
B40: No. | C40: PAYMENT MILESTONE | E40: % | F40: VALUE
B41: 1 | C41: Deposit - Project commencement | E41: 0.35 | F41: =$F$47*E41 -> 1394424.2
B42: 2 | C42: Delivery of Panels | E42: 0.3 | F42: =$F$47*E42 -> 1195220.8
B43: 3 | C43: Delivery of Inverters | E43: 0.2 | F43: =$F$47*E43 -> 796813.85
B44: 4 | C44: Practical Completion | E44: 0.1 | F44: =$F$47*E44 -> 398406.92
B45: 5 | C45: Handover | E45: 0.05 | F45: =$F$47*E45 -> 199203.46
C46: Total | E46: =SUM(E41:E45) -> 1 | F46: =SUM(F41:F45) -> 3984069.2
E47: =SUM(E41:E45) -> 1 | F47: =F21 -> 3984069.2

Sheet Project Plan
N1: =TODAY() -> 46065 | O1: =TODAY() -> 46065
C2: PROJECT PLAN | E2: BMG Fluid Tech | I2: Net Work Days | K2: =NETWORKDAYS(I19,K46,Data!C3:C15) -> 100 | N2: 0 | O2: QC snags shared with installer
C3: PROJECT SIZE (kWp) | E3: 144 | I3: Total Weeks | K3: =K2/5 -> 20
C4: PROJECT DEVELOPER | E4: Cole Bisset | I4: kW/Week Installation Rate | K4: =E3/K3 -> 7.2
C5: PROJECT MANAGERS | E5: JT Moorosi
C6: CONTRACT VALUE | E6: 3984069.2
C7: Phase: | E7: QA
B8: No. | C8: HIGH LEVEL PROGRAMME | E8: Planned Start | F8: Duration (days) | G8: Planned End | I8: Actual Start | J8: Duration (days) | K8: Actual End | M8: Status | N8: Expected Status | O8: Comment
F9: =G46-E19 -> 75 | J9: =K46-I19 -> 145 | M9: =AVERAGE(M11,M18,M21,M30,M40,M44,M51,M48) -> 0.88547554 | N9: =AVERAGE(N11,N18,N21,N30,N40,N44,N51,N48) -> 0.9042299
B11: 1 | C11: Project Initiation | E11: 45785 | F11: 113 | G11: 45898 | I11: =MIN(I12:I16) -> 45785 | J11: =K11-I11 -> 113 | K11: =MAX(K12:K16) -> 45898 | M11: =(J12*M12+J13*M13+J14*M14+J15*M15+J16*M16)/SUM(J12:J16) -> 1 | N11: =(K12*N12+K13*N13+K14*N14+K15*N15+K16*N16)/SUM(K12:K16) -> 1
B12: 1.1 | C12: BD Handover | E12: 45785 | F12: 1 | G12: 45786 | I12: 45785 | J12: 1 | K12: =WORKDAY.INTL(I12,J12,1,Data!$C$3:$C$14) -> 45786 | M12: 1 | N12: =_xlfn.LET( _xlpm.s,VALUE($I12), _xlpm.e,VALUE($K12), IF(OR(_xlpm.s="",_xlpm.e=""),"", IF(_xlpm.e<=_xlpm.s, IF(TODAY()>=_xlpm.e,1,0), MAX(0,MIN(1,(TODAY()-_xlpm.s)/(_xlpm.e-_xlpm.s))))) ) -> 1
B13: 1.2 | C13: Project Introduction | E13: 45885 | F13: 1 | G13: 45887 | I13: =WORKDAY.INTL(I19,0,1,Data!$C$3:$C$14)-14 -> 45885 | J13: 1 | K13: =WORKDAY.INTL(I13,J13,1,Data!$C$3:$C$14) -> 45887 | M13: 1 | N13: =_xlfn.LET( _xlpm.s,VALUE($I13), _xlpm.e,VALUE($K13), IF(OR(_xlpm.s="",_xlpm.e=""),"", IF(_xlpm.e<=_xlpm.s, IF(TODAY()>=_xlpm.e,1,0), MAX(0,MIN(1,(TODAY()-_xlpm.s)/(_xlpm.e-_xlpm.s))))) ) -> 1
B14: 1.3 | C14: HSE | E14: 45885 | F14: 10 | G14: 45898 | I14: =I13 -> 45885 | J14: 10 | K14: =WORKDAY.INTL(I14,J14,1,Data!$C$3:$C$14) -> 45898 | M14: 1 | N14: =_xlfn.LET( _xlpm.s,VALUE($I14), _xlpm.e,VALUE($K14), IF(OR(_xlpm.s="",_xlpm.e=""),"", IF(_xlpm.e<=_xlpm.s, IF(TODAY()>=_xlpm.e,1,0), MAX(0,MIN(1,(TODAY()-_xlpm.s)/(_xlpm.e-_xlpm.s))))) ) -> 1
B15: 1.4 | C15: Installer Kick Off | E15: 45885 | F15: 1 | G15: 45887 | I15: =WORKDAY.INTL(I19,0,1,Data!$C$3:$C$14)-14 -> 45885 | J15: 1 | K15: =WORKDAY.INTL(I15,J15,1,Data!$C$3:$C$14) -> 45887 | M15: 1 | N15: =_xlfn.LET( _xlpm.s,VALUE($I15), _xlpm.e,VALUE($K15), IF(OR(_xlpm.s="",_xlpm.e=""),"", IF(_xlpm.e<=_xlpm.s, IF(TODAY()>=_xlpm.e,1,0), MAX(0,MIN(1,(TODAY()-_xlpm.s)/(_xlpm.e-_xlpm.s))))) ) -> 1
B16: 1.5 | C16: Project Review | E16: 45855 | F16: 1 | G16: 45856 | I16: 45855 | J16: 1 | K16: =WORKDAY.INTL(I16,J16,1,Data!$C$3:$C$14) -> 45856 | M16: 1 | N16: =_xlfn.LET( _xlpm.s,VALUE($I16), _xlpm.e,VALUE($K16), IF(OR(_xlpm.s="",_xlpm.e=""),"", IF(_xlpm.e<=_xlpm.s, IF(TODAY()>=_xlpm.e,1,0), MAX(0,MIN(1,(TODAY()-_xlpm.s)/(_xlpm.e-_xlpm.s))))) ) -> 1
B18: 2 | C18: Site Establishment | E18: 45899 | F18: 1 | G18: 45900 | I18: =MIN(I19:I20) -> 45899 | J18: =K18-I18 -> 1 | K18: =MAX(K19) -> 45900 | M18: =(J19*M19)/J18 -> 1 | N18: =(K19*N19)/K18 -> 1
B19: 2.1 | C19: Solar Contractor Establishment | E19: 45899 | F19: 1 | G19: 45900 | I19: 45899 | J19: 1 | K19: =I19+J19 -> 45900 | M19: 1 | N19: =_xlfn.LET( _xlpm.s,VALUE($I19), _xlpm.e,VALUE($K19), IF(OR(_xlpm.s="",_xlpm.e=""),"", IF(_xlpm.e<=_xlpm.s, IF(TODAY()>=_xlpm.e,1,0), MAX(0,MIN(1,(TODAY()-_xlpm.s)/(_xlpm.e-_xlpm.s))))) ) -> 1
B21: 3 | C21: AC Installation | E21: 45880 | F21: 79 | G21: 45959 | I21: =MIN(I22:I28) -> 45880 | J21: =K21-I21 -> 102 | K21: =MAX(K22:K28) -> 45982 | M21: =(J22*M22+J23*M23+J24*M24+J27*M27+J28*M28)/SUM(J22:J28) -> 0.64130435 | N21: =(J22*N22+J23*N23+J24*N24+J27*N27+J28*N28)/SUM(J22:J28) -> 0.64130435
B22: 3.1 | C22: Inverters delivered | E22: 45900 | F22: 1 | G22: 45901 | I22: =WORKDAY.INTL(K19,0,1,Data!$C$3:$C$14) -> 45900 | J22: 1 | K22: =WORKDAY.INTL(I22,J22,1,Data!$C$3:$C$14) -> 45901 | M22: 1 | N22: =_xlfn.LET( _xlpm.s,VALUE($I22), _xlpm.e,VALUE($K22), IF(OR(_xlpm.s="",_xlpm.e=""),"", IF(_xlpm.e<=_xlpm.s, IF(TODAY()>=_xlpm.e,1,0), MAX(0,MIN(1,(TODAY()-_xlpm.s)/(_xlpm.e-_xlpm.s))))) ) -> 1
B23: 3.2 | C23: Inverters Mounted | E23: 45943 | F23: 5 | G23: 45950 | I23: =K25+1 -> 45943 | J23: 5 | K23: =WORKDAY.INTL(I23,J23,1,Data!$C$3:$C$14) -> 45950 | M23: 1 | N23: =_xlfn.LET( _xlpm.s,VALUE($I23), _xlpm.e,VALUE($K23), IF(OR(_xlpm.s="",_xlpm.e=""),"", IF(_xlpm.e<=_xlpm.s, IF(TODAY()>=_xlpm.e,1,0), MAX(0,MIN(1,(TODAY()-_xlpm.s)/(_xlpm.e-_xlpm.s))))) ) -> 1
B24: 3.3 | C24: Container Assembly and Delivery - Solar DB | E24: 45880 | F24: 40 | G24: 45937 | I24: =WORKDAY.INTL(I19,0,1,Data!$C$3:$C$14)-19 -> 45880 | J24: 40 | K24: =WORKDAY.INTL(I24,J24,1,Data!$C$3:$C$14) -> 45937 | M24: =_xlfn.LET( _xlpm.s,VALUE($I24), _xlpm.e,VALUE($K24), IF(OR(_xlpm.s="",_xlpm.e=""),"", IF(_xlpm.e<=_xlpm.s, IF(TODAY()>=_xlpm.e,1,0), MAX(0,MIN(1,(TODAY()-_xlpm.s)/(_xlpm.e-_xlpm.s))))) ) -> 1 | N24: =_xlfn.LET( _xlpm.s,VALUE($I24), _xlpm.e,VALUE($K24), IF(OR(_xlpm.s="",_xlpm.e=""),"", IF(_xlpm.e<=_xlpm.s, IF(TODAY()>=_xlpm.e,1,0), MAX(0,MIN(1,(TODAY()-_xlpm.s)/(_xlpm.e-_xlpm.s))))) ) -> 1 | O24: AC Junction Box to be delivered at the container manufacturer to pre-fit/install on week ending 19th Sep and the rest of the boards Week of the 25th Sep.
B25: 3.4 | C25: Trench to BESS | E25: 45938 | F25: 4 | G25: 45942 | I25: =WORKDAY.INTL(K24,0,1,Data!$C$3:$C$14)+1 -> 45938 | J25: 4 | K25: =I25+J25 -> 45942 | M25: 1 | N25: =_xlfn.LET( _xlpm.s,VALUE($I25), _xlpm.e,VALUE($K25), IF(OR(_xlpm.s="",_xlpm.e=""),"", IF(_xlpm.e<=_xlpm.s, IF(TODAY()>=_xlpm.e,1,0), MAX(0,MIN(1,(TODAY()-_xlpm.s)/(_xlpm.e-_xlpm.s))))) ) -> 1
B26: 3.5 | C26: AC Cabling | E26: 45944 | F26: 12 | G26: 45956 | I26: =K25+8 -> 45950 | J26: 29 | K26: =I26+J26 -> 45979 | M26: 1 | N26: =_xlfn.LET( _xlpm.s,VALUE($I26), _xlpm.e,VALUE($K26), IF(OR(_xlpm.s="",_xlpm.e=""),"", IF(_xlpm.e<=_xlpm.s, IF(TODAY()>=_xlpm.e,1,0), MAX(0,MIN(1,(TODAY()-_xlpm.s)/(_xlpm.e-_xlpm.s))))) ) -> 1
B27: 3.6 | C27: Container Plinths | E27: 45911 | F27: 10 | G27: 45926 | I27: 45911 | J27: 10 | K27: =WORKDAY.INTL(I27,J27,1,Data!$C$3:$C$14) -> 45926 | M27: 1 | N27: =_xlfn.LET( _xlpm.s,VALUE($I27), _xlpm.e,VALUE($K27), IF(OR(_xlpm.s="",_xlpm.e=""),"", IF(_xlpm.e<=_xlpm.s, IF(TODAY()>=_xlpm.e,1,0), MAX(0,MIN(1,(TODAY()-_xlpm.s)/(_xlpm.e-_xlpm.s))))) ) -> 1 | O27: Curing will take up to 10 days
B28: 3.7 | C28: AC Tie-In | E28: 45956 | F28: 3 | G28: 45959 | I28: =WORKDAY.INTL(K26,0,1,Data!$C$3:$C$14) -> 45979 | J28: 3 | K28: =WORKDAY.INTL(I28,J28,1,Data!$C$3:$C$14) -> 45982 | M28: 1 | N28: =_xlfn.LET( _xlpm.s,VALUE($I28), _xlpm.e,VALUE($K28), IF(OR(_xlpm.s="",_xlpm.e=""),"", IF(_xlpm.e<=_xlpm.s, IF(TODAY()>=_xlpm.e,1,0), MAX(0,MIN(1,(TODAY()-_xlpm.s)/(_xlpm.e-_xlpm.s))))) ) -> 1
B30: 4 | C30: DC Works | E30: 45869 | F30: 103 | G30: 45972 | I30: =MIN(I31:I38) -> 45869 | J30: =K30-I30 -> 133 | K30: =MAX(K31:K38) -> 46002 | M30: =AVERAGE(M31:M38) -> 1 | N30: =AVERAGE(N31:N38) -> 1
B31: 4.1 | C31: Base Prep | E31: 45908 | F31: 4 | G31: 45912 | I31: 45908 | J31: 4 | K31: =WORKDAY.INTL(I31,J31,1,Data!$C$3:$C$14) -> 45912 | M31: 1 | N31: =_xlfn.LET( _xlpm.s,VALUE($I31), _xlpm.e,VALUE($K31), IF(OR(_xlpm.s="",_xlpm.e=""),"", IF(_xlpm.e<=_xlpm.s, IF(TODAY()>=_xlpm.e,1,0), MAX(0,MIN(1,(TODAY()-_xlpm.s)/(_xlpm.e-_xlpm.s))))) ) -> 1
B32: 4.2 | C32: Rebar and Concrete | E32: 45918 | F32: 4 | G32: 45925 | I32: 45918 | J32: 4 | K32: =WORKDAY.INTL(I32,J32,1,Data!$C$3:$C$14) -> 45925 | M32: 1 | N32: =_xlfn.LET( _xlpm.s,VALUE($I32), _xlpm.e,VALUE($K32), IF(OR(_xlpm.s="",_xlpm.e=""),"", IF(_xlpm.e<=_xlpm.s, IF(TODAY()>=_xlpm.e,1,0), MAX(0,MIN(1,(TODAY()-_xlpm.s)/(_xlpm.e-_xlpm.s))))) ) -> 1 | O32: Only started pouring concrete 18 september
B33: 4.3 | C33: Trenches and re-instatement | E33: 45926 | F33: 4 | G33: 45932 | I33: =K32+1 -> 45926 | J33: 4 | K33: =WORKDAY.INTL(I33,J33,1,Data!$C$3:$C$14) -> 45932 | M33: 1 | N33: =_xlfn.LET( _xlpm.s,VALUE($I33), _xlpm.e,VALUE($K33), IF(OR(_xlpm.s="",_xlpm.e=""),"", IF(_xlpm.e<=_xlpm.s, IF(TODAY()>=_xlpm.e,1,0), MAX(0,MIN(1,(TODAY()-_xlpm.s)/(_xlpm.e-_xlpm.s))))) ) -> 1
B34: 4.4 | C34: Structures | E34: 45933 | F34: 10 | G34: 45947 | I34: =K33+1 -> 45933 | J34: 17 | K34: =WORKDAY.INTL(I34,J34,1,Data!$C$3:$C$14) -> 45958 | M34: 1 | N34: =_xlfn.LET( _xlpm.s,VALUE($I34), _xlpm.e,VALUE($K34), IF(OR(_xlpm.s="",_xlpm.e=""),"", IF(_xlpm.e<=_xlpm.s, IF(TODAY()>=_xlpm.e,1,0), MAX(0,MIN(1,(TODAY()-_xlpm.s)/(_xlpm.e-_xlpm.s))))) ) -> 1
B35: 4.5 | C35: New Structure lead time | I35: 45957 | J35: 30 | K35: =WORKDAY.INTL(I35,J35,1,Data!$C$3:$C$14) -> 45999 | M35: 1 | N35: =_xlfn.LET( _xlpm.s,VALUE($I35), _xlpm.e,VALUE($K35), IF(OR(_xlpm.s="",_xlpm.e=""),"", IF(_xlpm.e<=_xlpm.s, IF(TODAY()>=_xlpm.e,1,0), MAX(0,MIN(1,(TODAY()-_xlpm.s)/(_xlpm.e-_xlpm.s))))) ) -> 1
B36: 4.6 | C36: New Strucutre Installation | I36: =K35 -> 45999 | J36: 3 | K36: =WORKDAY.INTL(I36,J36,1,Data!$C$3:$C$14) -> 46002 | M36: 1 | N36: =_xlfn.LET( _xlpm.s,VALUE($I36), _xlpm.e,VALUE($K36), IF(OR(_xlpm.s="",_xlpm.e=""),"", IF(_xlpm.e<=_xlpm.s, IF(TODAY()>=_xlpm.e,1,0), MAX(0,MIN(1,(TODAY()-_xlpm.s)/(_xlpm.e-_xlpm.s))))) ) -> 1
B37: 4.7 | C37: DC Cable delivered | E37: 45869 | F37: 1 | G37: 45870 | I37: 45869 | J37: 1 | K37: =WORKDAY.INTL(I37,J37,1,Data!$C$3:$C$14) -> 45870 | M37: 1 | N37: =_xlfn.LET( _xlpm.s,VALUE($I37), _xlpm.e,VALUE($K37), IF(OR(_xlpm.s="",_xlpm.e=""),"", IF(_xlpm.e<=_xlpm.s, IF(TODAY()>=_xlpm.e,1,0), MAX(0,MIN(1,(TODAY()-_xlpm.s)/(_xlpm.e-_xlpm.s))))) ) -> 1
B38: 4.8 | C38: DC Stringing | E38: 45958 | F38: 10 | G38: 45972 | I38: =WORKDAY.INTL(K42,0,1,Data!$C$3:$C$14)-3 -> 45971 | J38: 10 | K38: =WORKDAY.INTL(I38,J38,1,Data!$C$3:$C$14) -> 45985 | M38: 1 | N38: =_xlfn.LET( _xlpm.s,VALUE($I38), _xlpm.e,VALUE($K38), IF(OR(_xlpm.s="",_xlpm.e=""),"", IF(_xlpm.e<=_xlpm.s, IF(TODAY()>=_xlpm.e,1,0), MAX(0,MIN(1,(TODAY()-_xlpm.s)/(_xlpm.e-_xlpm.s))))) ) -> 1
B40: 5 | C40: Module installation | E40: 45896 | F40: 65 | G40: 45961 | I40: =MIN(I41:I42) -> 45896 | J40: =K40-I40 -> 78 | K40: =MAX(K41:K42) -> 45974 | M40: =(J41*M41+J42*M42)/SUM(J41:J42) -> 1 | N40: =(K41*N41+K42*N42)/SUM(K41:K42) -> 1
B41: 5.1 | C41: Module delivery | E41: 45896 | F41: 1 | G41: 45897 | I41: 45896 | J41: 1 | K41: =WORKDAY.INTL(I41,J41,1,Data!$C$3:$C$14) -> 45897 | M41: 1 | N41: =_xlfn.LET( _xlpm.s,VALUE($I41), _xlpm.e,VALUE($K41), IF(OR(_xlpm.s="",_xlpm.e=""),"", IF(_xlpm.e<=_xlpm.s, IF(TODAY()>=_xlpm.e,1,0), MAX(0,MIN(1,(TODAY()-_xlpm.s)/(_xlpm.e-_xlpm.s))))) ) -> 1
B42: 5.2 | C42: Module mounting | E42: 45950 | F42: 9 | G42: 45961 | I42: =K34+3 -> 45961 | J42: 9 | K42: =WORKDAY.INTL(I42,J42,1,Data!$C$3:$C$14) -> 45974 | M42: 1 | N42: =_xlfn.LET( _xlpm.s,VALUE($I42), _xlpm.e,VALUE($K42), IF(OR(_xlpm.s="",_xlpm.e=""),"", IF(_xlpm.e<=_xlpm.s, IF(TODAY()>=_xlpm.e,1,0), MAX(0,MIN(1,(TODAY()-_xlpm.s)/(_xlpm.e-_xlpm.s))))) ) -> 1
B44: 6 | C44: Commissioning | E44: 45972 | F44: 2 | G44: 45974 | I44: =MIN(I45:I46) -> 46002 | J44: =K44-I44 -> 42 | K44: =MAX(K45:K46) -> 46044 | M44: =(J45*M45+J46*M46)/SUM(J45:J46) -> 1 | N44: =(K45*N45+K46*N46)/SUM(K45:K46) -> 1
B45: 6.1 | C45: Commissioning - Partial | E45: 45972 | F45: 1 | G45: 45973 | I45: =K30 -> 46002 | J45: 1 | K45: =WORKDAY.INTL(I45,J45,1,Data!$C$3:$C$14) -> 46003 | M45: 1 | N45: =_xlfn.LET( _xlpm.s,VALUE($I45), _xlpm.e,VALUE($K45), IF(OR(_xlpm.s="",_xlpm.e=""),"", IF(_xlpm.e<=_xlpm.s, IF(TODAY()>=_xlpm.e,1,0), MAX(0,MIN(1,(TODAY()-_xlpm.s)/(_xlpm.e-_xlpm.s))))) ) -> 1
B46: 6.2 | C46: Commissioning - Full | E46: 45973 | F46: 1 | G46: 45974 | I46: 46043 | J46: 1 | K46: =WORKDAY.INTL(I46,J46,1,Data!$C$3:$C$14) -> 46044 | M46: 1 | N46: =_xlfn.LET( _xlpm.s,VALUE($I46), _xlpm.e,VALUE($K46), IF(OR(_xlpm.s="",_xlpm.e=""),"", IF(_xlpm.e<=_xlpm.s, IF(TODAY()>=_xlpm.e,1,0), MAX(0,MIN(1,(TODAY()-_xlpm.s)/(_xlpm.e-_xlpm.s))))) ) -> 1
B48: 7 | C48: QA Inspections | E48: 45974 | F48: 1 | G48: 45975 | I48: =MIN(I49) -> 46003 | J48: =K48-I48 -> 3 | K48: =MAX(K49) -> 46006 | M48: =(J49*M49)/SUM(J49) -> 1 | N48: =(K49*N49)/SUM(K49) -> 1
B49: 7.1 | C49: Red-Team Inspection | E49: 45974 | F49: 1 | G49: 45975 | I49: =K45 -> 46003 | J49: 1 | K49: =WORKDAY.INTL(I49,J49,1,Data!$C$3:$C$14) -> 46006 | M49: 1 | N49: =_xlfn.LET( _xlpm.s,VALUE($I49), _xlpm.e,VALUE($K49), IF(OR(_xlpm.s="",_xlpm.e=""),"", IF(_xlpm.e<=_xlpm.s, IF(TODAY()>=_xlpm.e,1,0), MAX(0,MIN(1,(TODAY()-_xlpm.s)/(_xlpm.e-_xlpm.s))))) ) -> 1
B51: 8 | C51: Project Closure | E51: 45975 | F51: 14 | G51: 45989 | I51: =MIN(I52:I57) -> 46042 | J51: =K51-I51 -> 34 | K51: =MAX(K52:K57) -> 46076 | M51: =(J52*M52+J53*M53+J54*M54+J55*M55+J56*M56+J57*M57)/SUM(J52:J57) -> 0.4425 | N51: =(K52*N52+K53*N53+K54*N54+K55*N55+K56*N56+K57*N57)/SUM(K52:K57) -> 0.59253487
B52: 8.1 | C52: Equipment serial numbers | E52: 45975 | F52: 2 | G52: 45979 | I52: 46044 | J52: 18 | K52: =WORKDAY.INTL(I52,J52,1,Data!$C$3:$C$14) -> 46070 | M52: 0.4 | N52: =_xlfn.LET( _xlpm.s,VALUE($I52), _xlpm.e,VALUE($K52), IF(OR(_xlpm.s="",_xlpm.e=""),"", IF(_xlpm.e<=_xlpm.s, IF(TODAY()>=_xlpm.e,1,0), MAX(0,MIN(1,(TODAY()-_xlpm.s)/(_xlpm.e-_xlpm.s))))) ) -> 0.80769231
B53: 8.2 | C53: Snags completion | E53: 45975 | F53: 5 | G53: 45982 | I53: 46042 | J53: 18 | K53: =WORKDAY.INTL(I53,J53,1,Data!$C$3:$C$14) -> 46066 | M53: 0.5 | N53: =_xlfn.LET( _xlpm.s,VALUE($I53), _xlpm.e,VALUE($K53), IF(OR(_xlpm.s="",_xlpm.e=""),"", IF(_xlpm.e<=_xlpm.s, IF(TODAY()>=_xlpm.e,1,0), MAX(0,MIN(1,(TODAY()-_xlpm.s)/(_xlpm.e-_xlpm.s))))) ) -> 0.95833333 | O53: qc snags shared 4 feb
B54: 8.3 | C54: System Performance Monitoring | E54: 45982 | F54: 5 | G54: 45989 | I54: 46043 | J54: 5 | K54: =WORKDAY.INTL(I54,J54,1,Data!$C$3:$C$14) -> 46050 | M54: 0.9 | N54: =_xlfn.LET( _xlpm.s,VALUE($I54), _xlpm.e,VALUE($K54), IF(OR(_xlpm.s="",_xlpm.e=""),"", IF(_xlpm.e<=_xlpm.s, IF(TODAY()>=_xlpm.e,1,0), MAX(0,MIN(1,(TODAY()-_xlpm.s)/(_xlpm.e-_xlpm.s))))) ) -> 1
B55: 8.4 | C55: Handover documentation | E55: 45975 | F55: 5 | G55: 45982 | I55: =K54 -> 46050 | J55: 13 | K55: =WORKDAY.INTL(I55,J55,1,Data!$C$3:$C$14) -> 46069 | M55: 0.45 | N55: =_xlfn.LET( _xlpm.s,VALUE($I55), _xlpm.e,VALUE($K55), IF(OR(_xlpm.s="",_xlpm.e=""),"", IF(_xlpm.e<=_xlpm.s, IF(TODAY()>=_xlpm.e,1,0), MAX(0,MIN(1,(TODAY()-_xlpm.s)/(_xlpm.e-_xlpm.s))))) ) -> 0.78947368
B56: 8.5 | C56: Handover to Client | E56: 45982 | F56: 1 | G56: 45985 | I56: 46069 | J56: 1 | K56: =WORKDAY.INTL(I56,J56,1,Data!$C$3:$C$14) -> 46070 | M56: 0 | N56: =_xlfn.LET( _xlpm.s,VALUE($I56), _xlpm.e,VALUE($K56), IF(OR(_xlpm.s="",_xlpm.e=""),"", IF(_xlpm.e<=_xlpm.s, IF(TODAY()>=_xlpm.e,1,0), MAX(0,MIN(1,(TODAY()-_xlpm.s)/(_xlpm.e-_xlpm.s))))) ) -> 0
B57: 8.6 | C57: Handover to Matriarch | E57: 45977 | F57: 5 | G57: 45982 | I57: =K55 -> 46069 | J57: 5 | K57: =WORKDAY.INTL(I57,J57,1,Data!$C$3:$C$14) -> 46076 | M57: 0 | N57: =_xlfn.LET( _xlpm.s,VALUE($I57), _xlpm.e,VALUE($K57), IF(OR(_xlpm.s="",_xlpm.e=""),"", IF(_xlpm.e<=_xlpm.s, IF(TODAY()>=_xlpm.e,1,0), MAX(0,MIN(1,(TODAY()-_xlpm.s)/(_xlpm.e-_xlpm.s))))) ) -> 0

Sheet Data
C2: Public holidays | F2: Drop down list
C3: 45658 | D3: New Years Day | F3: Approved
C4: 45737 | D4: Human Rights day | F4: Pending
C5: 45765 | D5: Good Friday | F5: Declined
C6: 45768 | D6: Family Day | F6: Abanded
C7: 45774 | D7: Freedom Day
C8: 45765 | D8: Freedom DayObserved
C9: 45778 | D9: Workers day
C10: 45824 | D10: Youth Day Holiday
C11: 45878 | D11: Womens Day
C12: 45924 | D12: Heritage Day
C13: 46007 | D13: Day of Reconciliation | H13: Manual dates
C14: 46016 | D14: Christmas Day
C15: 46017 | D15: Day of Goodwill

Sheet Expenditure Tracking
B2: HIGH LEVEL PROJECT EXPENDITURE TRACKING
F4: COSTED | H4: ACTUAL | J4: Difference from costed
B5: EXPENDITURE | F5: =SUM(F9:F23) -> 3079187 | H5: =SUM(H9:H23) -> 3276882 | J5: =SUM(J9:J23) -> -197694.98
B7: No. | D7: Item | F7: Costed Expenditure | H7: Actual Expenditure | J7: Saving / Overrun | L7: Comments on variations from planned expenditure
B9: ='Expenditure Breakdown'!L6 -> 1 | D9: ='Expenditure Breakdown'!M6 -> 1. Panels | F9: ='Expenditure Breakdown'!I6 -> 370402.24 | H9: ='Expenditure Breakdown'!X6 -> 280023.2 | J9: =F9-H9 -> 90379.039
B10: ='Expenditure Breakdown'!L13 -> 2 | D10: ='Expenditure Breakdown'!M13 -> 2. Inverters | F10: ='Expenditure Breakdown'!I13 -> 140000 | H10: ='Expenditure Breakdown'!X13 -> 137740.7 | J10: =F10-H10 -> 2259.3
B11: ='Expenditure Breakdown'!L21 -> 3 | D11: ='Expenditure Breakdown'!M21 -> 3. Mounting Structures | F11: ='Expenditure Breakdown'!I21 -> 518256 | H11: ='Expenditure Breakdown'!X21 -> 1247029.4 | J11: =F11-H11 -> -728773.42 | L11: Look at costing for carport
B12: ='Expenditure Breakdown'!L42 -> 4 | D12: ='Expenditure Breakdown'!M42 -> 4. DC Equipment | F12: ='Expenditure Breakdown'!I42 -> 140380.1 | H12: ='Expenditure Breakdown'!X42 -> 259295 | J12: =F12-H12 -> -118914.9 | L12: DC run spec is inaccurate, DC run much longer then expected
B13: ='Expenditure Breakdown'!L58 -> 5 | D13: ='Expenditure Breakdown'!M58 -> 5. Monitoring | F13: ='Expenditure Breakdown'!I58 -> 174000 | H13: ='Expenditure Breakdown'!X58 -> 41389.35 | J13: =F13-H13 -> 132610.65
B14: ='Expenditure Breakdown'!L67 -> 6 | D14: ='Expenditure Breakdown'!M67 -> 6. AC Equipment | F14: ='Expenditure Breakdown'!I67 -> 236614.82 | H14: ='Expenditure Breakdown'!X67 -> 416739.86 | J14: =F14-H14 -> -180125.04
B15: ='Expenditure Breakdown'!L86 -> 7 | D15: ='Expenditure Breakdown'!M86 -> 7.BESS | F15: ='Expenditure Breakdown'!I86 -> 710967.83 | H15: ='Expenditure Breakdown'!X86 -> 0 | J15: =F15-H15 -> 710967.83
B16: ='Expenditure Breakdown'!L95 -> 8 | D16: ='Expenditure Breakdown'!M95 -> 8. Product Add On | F16: ='Expenditure Breakdown'!I95 -> 536231.13 | H16: ='Expenditure Breakdown'!X95 -> 516856.72 | J16: =F16-H16 -> 19374.41
B17: ='Expenditure Breakdown'!L117 -> 9 | D17: ='Expenditure Breakdown'!M117 -> 9. AC & DC installation | F17: ='Expenditure Breakdown'!I117 -> 141305 | H17: ='Expenditure Breakdown'!X117 -> 220320 | J17: =F17-H17 -> -79015
B18: ='Expenditure Breakdown'!L130 -> 10 | D18: ='Expenditure Breakdown'!M130 -> 10. Site Logistics | F18: ='Expenditure Breakdown'!I130 -> 25300 | H18: ='Expenditure Breakdown'!X130 -> 80250 | J18: =F18-H18 -> -54950
B19: ='Expenditure Breakdown'!L146 -> 11 | D19: ='Expenditure Breakdown'!M146 -> 11. Due Dilligence | F19: ='Expenditure Breakdown'!I146 -> 29000 | H19: ='Expenditure Breakdown'!X146 -> 19950 | J19: =F19-H19 -> 9050
B20: ='Expenditure Breakdown'!L152 -> 12 | D20: ='Expenditure Breakdown'!M152 -> 12. BDP Commission | F20: ='Expenditure Breakdown'!I152 -> 23202.108 | H20: ='Expenditure Breakdown'!X152 -> 0 | J20: =F20-H20 -> 23202.108
B21: ='Expenditure Breakdown'!L155 -> 13 | D21: ='Expenditure Breakdown'!M156 -> 13. Engineering | F21: ='Expenditure Breakdown'!I155 -> 31077.825 | H21: ='Expenditure Breakdown'!X155 -> 49800.866 | J21: =F21-H21 -> -18723.041
B22: ='Expenditure Breakdown'!L162 -> 14 | D22: ='Expenditure Breakdown'!M162 -> 14. General Expenses | F22: ='Expenditure Breakdown'!I162 -> 2450 | H22: ='Expenditure Breakdown'!X162 -> 7486.91 | J22: =F22-H22 -> -5036.91
B23: ='Expenditure Breakdown'!L175 -> 15 | D23: ='Expenditure Breakdown'!M175 -> 15. Service Add On | F23: ='Expenditure Breakdown'!I175 -> 0 | H23: ='Expenditure Breakdown'!X175 -> 0 | J23: =F23-H23 -> 0
D25: check: | F25: ='Expenditure Breakdown'!I2-'Expenditure Tracking'!F5 -> 0 | G25: =#REF!-G5 -> #REF! | H25: ='Expenditure Breakdown'!X2-H5 -> 0

Sheet Expenditure Breakdown
B2: COSTED EXPENDITURE BREAKDOWN | I2: =SUM(I6:I187) -> 3079187 | J2: =SUM(J6:J187) -> 3984069.2 | L2: ACTUAL EXPENDITURE BREAKDOWN | R2: FINANCE ONLY | X2: =SUM(X6:X187) -> 3276882
B4: No. | C4: Product / Service | D4: Description of Work | E4: QTY | F4: Rate / Unit | G4: Budget Total | H4: FORECASTED PAYMENT DATE | I4: Total COS | J4: =IF(J2-'Revenue Tracking'!D4>=0, "Total Revenue", "ERROR on REV" ) -> Total Revenue | L4: No. | M4: Product/ Service | N4: Description of Work | O4: QTY | P4: Rate / Unit | Q4: Actual Total | R4: PO NUMBER | S4: INVOICE NUMBER | T4: INVOICE RAISED DATE | U4: REVENUE RECOGNITION AMOUNT | V4: CHECK | W4: FINANCE PAYMENT DATE | X4: Total COS
B6: 1 | C6: Panels | D6: Panels Budget | G6: =D188 -> 370402.24 | H6: ='Project Plan'!G41+60 -> 45957 | I6: =SUM(G6:G11) -> 370402.24 | J6: =F188 -> 514447.55 | L6: 1 | M6: 1. Panels | N6: JA Solar 615 | O6: 235 | P6: 1156.4 | Q6: =O6*P6 -> 271754 | S6: Menlo INV0003177 | T6: 45900 | U6: 507353.12 | V6: =J6-SUM(U6:U11) -> 0 | W6: 45954 | X6: =SUM(Q6:Q11) -> 280023.2
B7: 1 | D7: Delivery Budget | L7: 1 | M7: 1. Panels | N7: Transport - Futile trip | Q7: 3800 | S7: Menlo INV0003177 | T7: 45900 | U7: 7094.4378 | W7: 45954
B8: 1 | L8: 1 | M8: 1. Panels | N8: JA Solar 615 | Q8: 3469.2 | S8: Menlo INV0003504 | T8: 46022 | U8: - | W8: 46058
B9: 1 | L9: 1 | M9: 1. Panels | N9: Transport | Q9: 1000 | S9: Menlo INV0003504 | T9: 46022 | U9: - | W9: 46058
B10: 1 | L10: 1 | M10: 1. Panels | U10: =(Q10/$X$6*$J$6) -> 0
B11: 1 | L11: 1 | M11: 1. Panels | T11: =IF(W11>1,EOMONTH(W11,0),"") | U11: =(Q11/$X$6*$J$6) -> 0 | Y11: BUDGET | Z11: Installer Allocation
T12: =IF(W12>1,EOMONTH(W12,0),"") | Y12: AC Equipment | Z12: =G67 -> 236614.82
B13: 2 | C13: Inverters | D13: Inverter Budget | G13: 140000 | H13: =EOMONTH('Project Plan'!E22+30,0) -> 45930 | I13: =SUM(G13:G19) -> 140000 | J13: 194444.44 | L13: 2 | M13: 2. Inverters | N13: Huawei 100KTL | O13: 2 | P13: 68870 | Q13: 137740.7 | S13: Menlo - INV0003112 | T13: 45869 | U13: 194444.44 | V13: =J13-SUM(U13:U19) -> 0 | W13: 45876 | X13: =SUM(Q13:Q19) -> 137740.7 | Y13: DC Equipment | Z13: =G43 -> 93410.1
B14: 2 | L14: 2 | M14: 2. Inverters | T14: =IF(W14>1,EOMONTH(W14,0),"") | U14: 0 | Y14: AC Labour | Z14: =G117 -> 50386
B15: 2 | L15: 2 | M15: 2. Inverters | T15: =IF(W15>1,EOMONTH(W15,0),"") | U15: 0 | Y15: DC Labour | Z15: =G118 -> 90919
B16: 2 | L16: 2 | M16: 2. Inverters | T16: =IF(W16>1,EOMONTH(W16,0),"") | U16: 0 | Y16: Offloading | Z16: =G130 -> 8500
B17: 2 | L17: 2 | M17: 2. Inverters | T17: =IF(W17>1,EOMONTH(W17,0),"") | U17: 0 | Y17: Scaffolding | Z17: =G131 -> 0
B18: 2 | L18: 2 | M18: 2. Inverters | T18: =IF(W18>1,EOMONTH(W18,0),"") | U18: 0 | Y18: Storage | Z18: =G133 -> 0
B19: 2 | L19: 2 | M19: 2. Inverters | T19: =IF(W19>1,EOMONTH(W19,0),"") | U19: 0 | Y19: Telehandler | Z19: 0
T20: =IF(W20>1,EOMONTH(W20,0),"") | Y20: HSE | Z20: 0
B21: 3 | C21: Mounting Structures | D21: Structure Budget | G21: =D190 -> 518256 | H21: =H13 -> 45930 | I21: =SUM(G21:G40) -> 518256 | J21: =F190 -> 719800 | L21: 3 | M21: 3. Mounting Structures | N21: Schletter Structure - Deposit | P21: 689400 | Q21: =P21*50% -> 344700 | R21: PO4094-BMGFT-20250707 | S21: Schletter - INV1971 | T21: 45869 | U21: 192541.23 | V21: =J21-SUM(U21:U40) -> 0.0042397808 | W21: 45855 | X21: =SUM(Q21:Q40) -> 1247029.4 | Y21: BESS Installation & Equipment | Z21: =832272.28*0.85 -> 707431.44
B22: 3 | L22: 3 | M22: 3. Mounting Structures | N22: Schletter - Balance | Q22: =P21*50% -> 344700 | S22: Schletter - INVQ0135 | T22: 45900 | U22: 192541.23 | W22: 45930 | Y22: Total | Z22: =SUM(Z12:Z21) -> 1187261.4
L23: 3 | M23: 3. Mounting Structures | Q23: -344700 | S23: Schletter - INVQ0135 | T23: 45930 | U23: 0 | W23: 45930
L24: 3 | M24: 3. Mounting Structures | Q24: -344700 | S24: Schletter - CRN0273 | T24: 45930 | U24: 0 | W24: 45930
L25: 3 | M25: 3. Mounting Structures | Q25: 694199.98 | S25: Schletter - INV2238 | T25: 45930 | W25: 45930
B26: 3 | L26: 3 | M26: 3. Mounting Structures | N26: Delivery Charge | Q26: 4800 | S26: Schletter - INV2416 | T26: 45991 | U26: 0 | W26: 46021 | Y26: Less 15% | Z26: =+Z22*0.85 -> 1009172.2
L27: 3 | M27: 3. Mounting Structures | N27: CT Struts | Q27: 12832.45 | S27: Schletter - INV2528 | T27: 46022 | U27: 0 | W27: 46051
L28: 3 | M28: 3. Mounting Structures
B29: 3 | L29: 3 | M29: 3. Mounting Structures | N29: Civil Engineering Services - Schletter | Q29: 25790.99 | R29: PO4139-BMGFT-20250721 | S29: Schletter INVQ0136 | T29: 45900 | U29: 14406.234 | W29: =T29+30 -> 45930 | Y29: R/Wp | Z29: =Z26/'Project Plan'!$E$3/1000 -> 7.0081399
L30: 3 | M30: 3. Mounting Structures | Q30: -25790.99 | S30: Schletter INVQ0136 | T30: 45930 | U30: 0 | W30: =T30+30 -> 45960
L31: 3 | M31: 3. Mounting Structures | Q31: 25790.99 | S31: Schletter - INV2518 | T31: 46022 | U31: 0 | W31: 46051
L32: 3 | M32: 3. Mounting Structures
L33: 3 | M33: 3. Mounting Structures | N33: Carport Installation - iEco Solar | O33: =AL52 -> 509406 | P33: 0.6 | Q33: =$O$33*P33 -> 305643.6 | R33: PO4207-BMGFT-20250807 - RV Approved | S33: Ieco Solar InvEME01 | T33: 45900 | U33: 170725.25 | W33: 45883
L34: 3 | M34: 3. Mounting Structures | P34: 0.2 | Q34: =$O$33*P34 -> 101881.2 | S34: Ieco Solar InvEME02 | T34: 45900 | U34: 56908.418 | W34: 45961
L35: 3 | M35: 3. Mounting Structures | P35: 0.15 | Q35: =$O$33*P35 -> 76410.9 | S35: Ieco Solar InvEME02 | T35: 45900 | U35: 42681.314 | W35: 45974
L36: 3 | M36: 3. Mounting Structures | P36: 0.05 | Q36: =$O$33*P36 -> 25470.3 | S36: Ieco Solar InvEME02 | T36: 45900 | U36: 14227.105 | W36: 46072
L37: 3 | M37: 3. Mounting Structures | U37: =(Q37/$X$21*$J$21) -> 0
L38: 3 | M38: 3. Mounting Structures | N38: Re-establishment Cost - Carport Variation - Cost TBC (RV Approved) - VO | Q38: 0 | U38: 0
B39: 3 | L39: 3 | M39: 3. Mounting Structures | T39: =IF(W39>1,EOMONTH(W39,0),"") | U39: =(Q39/$X$21*$J$21) -> 0
B40: 3 | L40: 3 | M40: 3. Mounting Structures | N40: Carport Contigency | T40: 45961 | U40: 35769.208 | Y40: ACTUAL - MG | Z40: Installer Price | AB40: ACTUAL - MG | AC40: Installer Price | AE40: ACTUAL - CS AC/DC Only | AF40: Installer Price | AH40: ACTUAL - CS Carport | AI40: Installer Price | AK40: ACTUAL - IECO | AL40: Installer Price
T41: =IF(W41>1,EOMONTH(W41,0),"") | Y41: =Y12 -> AC Equipment | Z41: =453255.25+197822.25 -> 651077.5 | AB41: Carport Install | AC41: 0 | AE41: AC Equipment | AF41: 350590.6 | AH41: Carport Assembly | AI41: 110400 | AK41: Carport Scope | AL41: 372600 | AM41: =AL41*1.2 -> 447120
B42: 4 | C42: DC Equipment | D42: DC Cable Budget | G42: 46970 | H42: =H13 -> 45930 | I42: =SUM(G42:G56) -> 140380.1 | J42: =F191 -> 194972.36 | L42: 4 | M42: 4. DC Equipment | N42: DC Cable | O42: 12000 | P42: 13.5 | Q42: 134446.46 | R42: PO4182-BMGFT-2025073 - RV Approved | S42: Rubicon INVWCRE-0069699 | T42: 45869 | U42: 121813.08 | V42: =J42-SUM(U42:U56) -> 0 | W42: 45900 | X42: =SUM(Q42:Q56) -> 259295 | Y42: =Y13 -> DC Equipment | Z42: 86573.26 | AB42: DC Equipment | AC42: 0 | AE42: DC Equipment | AF42: 97295 | AH42: Civils Works (Provisional) | AI42: 639500 | AK42: Spoil Removal | AL42: 7700 | AM42: =AL42*1.2 -> 9240
B43: 4 | D43: DC Equipment Budget | G43: =D191-G42 -> 93410.1 | H43: =H42 -> 45930 | L43: 4 | M43: 4. DC Equipment | Q43: =162000-Q42 -> 27553.54 | R43: PO4182-BMGFT-2025073 - RV Approved | S43: Rubicon INVWCRE-0069699 | T43: 45869 | U43: 0 | W43: 45901 | Y43: =Y14 -> AC Labour | Z43: =38575+28812 -> 67387 | AB43: AC Labour | AC43: 0 | AE43: AC Labour | AF43: 112320 | AG43: =AF43/600000 -> 0.1872 | AH43: Trenching | AI43: 0 | AK43: Reinstate Bases | AL43: 13000
B44: 4 | L44: 4 | M44: 4. DC Equipment | T44: =IF(W44>1,EOMONTH(W44,0),"") | U44: 0 | Y44: =Y15 -> DC Labour | Z44: 93600 | AB44: DC Labour | AC44: 0 | AE44: DC Labour | AF44: 108000 | AG44: =AF44/600000 -> 0.18 | AH44: Scanning | AI44: 14950 | AK44: Site Establish - PGs | AL44: 77706
B45: 4 | L45: 4 | M45: 4. DC Equipment | T45: =IF(W45>1,EOMONTH(W45,0),"") | U45: 0 | Y45: =Y16 -> Offloading | Z45: 7290 | AB45: Offloading | AC45: 0 | AE45: Offloading | AF45: =4950+11950 -> 16900 | AH45: Offloading | AI45: 0 | AK45: Sleeves | AL45: 1575
B46: 4 | L46: 4 | M46: 4. DC Equipment | N46: Project Kick Off | O46: =AF42 -> 97295 | P46: 0.1 | Q46: =$O$46*P46 -> 9729.5 | R46: PO4166-BMGFT-20250728 - RV Approved | S46: Cosmic Sun: CS_BMG_001_AC DC | T46: 45869 | U46: 7315.9281 | W46: =W118 -> 45869 | Y46: =Y17 -> Scaffolding | Z46: 0 | AB46: Scaffolding | AC46: 0 | AE46: Scaffolding | AF46: 0 | AH46: Scaffolding | AI46: 0 | AK46: Trenching | AL46: 16975
B47: 4 | L47: 4 | M47: 4. DC Equipment | N47: Site Establishment | P47: 0.15 | Q47: =$O$46*P47 -> 14594.25 | S47: Cosmic Sun - CS_BMG_002_AC DC | T47: 45869 | U47: 10973.892 | W47: =W119 -> 45932 | Y47: =Y18 -> Storage | Z47: 0 | AB47: Storage | AC47: 0 | AE47: Storage | AF47: 6600 | AH47: Storage | AI47: 0 | AK47: Scanning | AL47: 19850
B48: 4 | L48: 4 | M48: 4. DC Equipment | N48: AC Installation Complete | P48: 0.2 | Q48: =$O$46*P48 -> 19459 | S48: Cosmic Sun - CS_BMG_002_AC DC | T48: 45869 | U48: 14631.856 | W48: =W120 -> 46003 | Y48: =Y19 -> Telehandler | Z48: 0 | AB48: Telehandler | AC48: 0 | AE48: Telehandler | AF48: 0 | AH48: Telehandler | AI48: 0 | AK48: Telehandler | AL48: 0
B49: 4 | L49: 4 | M49: 4. DC Equipment | N49: DC Installation Complete | P49: 0.25 | Q49: =$O$46*P49 -> 24323.75 | S49: Cosmic Sun - CS_BMG_002_AC DC | T49: 45869 | U49: 18289.82 | W49: 46009 | Y49: HSE | Z49: 5720 | AB49: HSE | AC49: 0 | AE49: HSE | AF49: 1500 | AH49: HSE | AI49: 4500 | AK49: HSE | AL49: 0
B50: 4 | L50: 4 | M50: 4. DC Equipment | N50: Commissioning Complete | P50: 0.1 | Q50: =$O$46*P50 -> 9729.5 | S50: Cosmic Sun - CS_BMG_002_AC DC | T50: 45869 | U50: 7315.9281 | W50: 46051 | Y50: Trench | Z50: 28795 | AB50: Other | AC50: 0 | AE50: Trenching | AF50: 55250 | AH50: Other | AI50: 0 | AK50: Other | AL50: 0
B51: 4 | L51: 4 | M51: 4. DC Equipment | N51: Site De-establisment | P51: 0.1 | Q51: =$O$46*P51 -> 9729.5 | S51: Cosmic Sun - CS_BMG_002_AC DC | T51: 45869 | U51: 7315.9281 | W51: 46051 | Y51: PnGs | Z51: =35811+4350 -> 40161 | AB51: PnGs | AC51: 0 | AE51: Other | AF51: 0 | AH51: Other | AI51: 0 | AK51: Other | AL51: 0
B52: 4 | L52: 4 | M52: 4. DC Equipment | N52: Handover Document Complete | P52: 0.05 | Q52: =$O$46*P52 -> 4864.75 | S52: Cosmic Sun - CS_BMG_002_AC DC | T52: 45869 | U52: 3657.9641 | W52: 46051 | Y52: Total | Z52: =SUM(Z41:Z51) -> 980603.76 | AB52: Total | AC52: =SUM(AC41:AC51) -> 0 | AE52: Total | AF52: =SUM(AF41:AF51) -> 748455.6 | AH52: Total | AI52: =SUM(AI41:AI51) -> 769350 | AK52: Total | AL52: =SUM(AL41:AL51) -> 509406 | AM52: 369680
B53: 4 | L53: 4 | M53: 4. DC Equipment | N53: End of Defects Period | P53: 0.05 | Q53: =$O$46*P53 -> 4864.75 | S53: Cosmic Sun - CS_BMG_002_AC DC | T53: 45869 | U53: 3657.9641 | W53: =W125 -> 46081 | Y53: R/Wp | Z53: =Z52/'Project Plan'!$E$3/1000 -> 6.8097483 | AB53: R/Wp | AC53: =AC52/'Project Plan'!$E$3/1000 -> 0 | AE53: R/Wp | AF53: =AF52/'Project Plan'!$E$3/1000 -> 5.1976083 | AH53: R/Wp | AI53: =AI52/'Project Plan'!$E$3/1000 -> 5.3427083 | AK53: R/Wp | AL53: =AL52/'Project Plan'!$E$3/1000 -> 3.5375417
B54: 4 | L54: 4 | M54: 4. DC Equipment | T54: =IF(W54>1,EOMONTH(W54,0),"") | U54: =(Q54/$X$42*$J$42) -> 0 | Y54: R/kWh | Z54: =Z52/600000 -> 1.6343396 | AB54: R/kWh | AC54: =AC52/600000 -> 0 | AE54: R/kWh | AF54: =AF52/600000 -> 1.247426 | AH54: R/kWh | AI54: =AI52/600000 -> 1.28225 | AK54: R/kWh | AL54: =AL52/600000 -> 0.84901
B55: 4 | L55: 4 | M55: 4. DC Equipment | T55: =IF(W55>1,EOMONTH(W55,0),"") | U55: =(Q55/$X$42*$J$42) -> 0
B56: 4 | L56: 4 | M56: 4. DC Equipment | T56: =IF(W56>1,EOMONTH(W56,0),"") | U56: =(Q56/$X$42*$J$42) -> 0
T57: =IF(W57>1,EOMONTH(W57,0),"") | AE57: CS Total | AF57: =AF52+AI52 -> 1517805.6
B58: 5 | C58: Monitoring | D58: Monitoring Budget | G58: =D193-G59 -> 159000 | H58: =H13 -> 45930 | I58: =SUM(G58:G65) -> 174000 | J58: =F193 -> 241666.67 | L58: 5 | M58: 5. Monitoring | U58: =(Q58/$X$58*$J$58) -> 0 | V58: =J58-SUM(U58:U65) -> 0 | X58: =SUM(Q58:Q65) -> 41389.35 | AE58: R/Wp | AF58: =AF53+AI53 -> 10.540317
B59: 5 | D59: Revenue Metering | G59: 15000 | H59: 45808 | L59: 5 | M59: 5. Monitoring | N59: CTs Techsitter, Router and Switch | Q59: 7642 | R59: PO4080-BMG-20250701 - RV Approved | S59: Accuenergy - ASAI-006262 | T59: 45900 | U59: 98177.485 | W59: =T59+30 -> 45930 | AE59: R/kWh | AF59: =AF54+AI54 -> 2.529676
B60: 5 | L60: 5 | M60: 5. Monitoring | N60: Techsitter | Q60: 11169 | S60: Matriarch - INV-4999 | T60: 45900 | U60: 143489.18 | W60: 45900
B61: 5 | L61: 5 | M61: 5. Monitoring | N61: Smartlogger- RMA from Kroonstad | Q61: 8598.35 | S61: Allocated from Kroonstad | T61: 45991 | U61: 0 | W61: 45991
B62: 5 | L62: 5 | M62: 5. Monitoring | N62: Grid meter and CTs | Q62: 6900 | R62: PO4525-BMGFT-20251208 - RV Approved | S62: Accuenergy - ASAI-007074 | T62: 46022 | U62: 0 | W62: 46029
B63: 5 | L63: 5 | M63: 5. Monitoring | N63: Rogowski Coils | Q63: 4110 | S63: Accuenergy - ASAI-006969 | T63: 45991 | U63: 0 | W63: 46029
L64: 5 | M64: 5. Monitoring | N64: Energy Meter | Q64: 2970 | S64: Accuenergy - ASAI-006969 | T64: 45991 | U64: 0 | W64: 46029
B65: 5 | L65: 5 | M65: 5. Monitoring | T65: =IF(W65>1,EOMONTH(W65,0),"") | U65: =(Q65/$X$58*$J$58) -> 0
T66: =IF(W66>1,EOMONTH(W66,0),"")
B67: 6 | C67: AC Equipment | D67: AC Equipment Budget | G67: =D192 -> 236614.82 | H67: =H58 -> 45930 | I67: =SUM(G67:G84) -> 236614.82 | J67: =F192 -> 328631.69 | L67: 6 | M67: 6. AC Equipment | U67: =(Q67/$X$67*$J$67) -> 0 | V67: =J67-SUM(U67:U84) -> 0 | X67: =SUM(Q67:Q84) -> 416739.86
B68: 6 | L68: 6 | M68: 6. AC Equipment | U68: =(Q68/$X$67*$J$67) -> 0
B69: 6 | L69: 6 | M69: 6. AC Equipment | T69: =IF(W69>1,EOMONTH(W69,0),"") | U69: =(Q69/$X$67*$J$67) -> 0
B70: 6 | L70: 6 | M70: 6. AC Equipment | T70: =IF(W70>1,EOMONTH(W70,0),"") | U70: =(Q70/$X$67*$J$67) -> 0
B71: 6 | L71: 6 | M71: 6. AC Equipment | T71: =IF(W71>1,EOMONTH(W71,0),"") | U71: =(Q71/$X$67*$J$67) -> 0
B72: 6 | L72: 6 | M72: 6. AC Equipment | T72: =IF(W72>1,EOMONTH(W72,0),"") | U72: =(Q72/$X$67*$J$67) -> 0
B73: 6 | L73: 6 | M73: 6. AC Equipment | N73: Project Kick Off | O73: =AF41 -> 350590.6 | P73: 0.1 | Q73: =$O$73*P73 -> 35059.06 | R73: PO4166-BMGFT-20250728 - RV Approved | S73: Cosmic Sun: CS_BMG_001_AC DC | T73: 45869 | U73: 32863.169 | W73: =W118 -> 45869
B74: 6 | L74: 6 | M74: 6. AC Equipment | N74: Site Establishment | P74: 0.15 | Q74: =$O$73*P74 -> 52588.59 | S74: Cosmic Sun - CS_BMG_002_AC DC | T74: 45869 | U74: 49294.754 | W74: =W119 -> 45932
B75: 6 | L75: 6 | M75: 6. AC Equipment | N75: AC Installation Complete | P75: 0.2 | Q75: =$O$73*P75 -> 70118.12 | S75: Cosmic Sun - CS_BMG_002_AC DC | T75: 45869 | U75: 65726.338 | W75: =W120 -> 46003
B76: 6 | L76: 6 | M76: 6. AC Equipment | N76: DC Installation Complete | P76: 0.25 | Q76: =$O$73*P76 -> 87647.65 | S76: Cosmic Sun - CS_BMG_002_AC DC | T76: 45869 | U76: 82157.923 | W76: 46009
B77: 6 | L77: 6 | M77: 6. AC Equipment | N77: Commissioning Complete | P77: 0.1 | Q77: =$O$73*P77 -> 35059.06 | S77: Cosmic Sun - CS_BMG_002_AC DC | T77: 45869 | U77: 32863.169 | W77: =W50 -> 46051
B78: 6 | L78: 6 | M78: 6. AC Equipment | N78: Site De-establisment | P78: 0.1 | Q78: =$O$73*P78 -> 35059.06 | S78: Cosmic Sun - CS_BMG_002_AC DC | T78: 45869 | U78: 32863.169 | W78: 46051
B79: 6 | L79: 6 | M79: 6. AC Equipment | N79: Handover Document Complete | P79: 0.05 | Q79: =$O$73*P79 -> 17529.53 | S79: Cosmic Sun - CS_BMG_002_AC DC | T79: 45869 | U79: 16431.585 | W79: 46051
B80: 6 | L80: 6 | M80: 6. AC Equipment | N80: End of Defects Period | P80: 0.05 | Q80: =$O$73*P80 -> 17529.53 | S80: Cosmic Sun - CS_BMG_002_AC DC | T80: 45869 | U80: 16431.585 | W80: =W125 -> 46081
B81: 6 | L81: 6 | M81: 6. AC Equipment | T81: =IF(W81>1,EOMONTH(W81,0),"") | U81: =(Q81/$X$67*$J$67) -> 0
B82: 6 | L82: 6 | M82: 6. AC Equipment | N82: Variation Breaker and Delivery - Cosmic Sun - VO | Q82: 17891.32 | R82: PO4313-BMGFT-20250916 - RV Approved | S82: CS_BMG_005_VO | T82: 45961 | U82: 0 | W82: 45967
L83: 6 | M83: 6. AC Equipment | N83: Variation Additional AC cable excluding 95mm - Cosmic Sun - VO | Q83: 32171.96 | S83: CS_BMG_005_VO | T83: 45961 | W83: 45967
B84: 6 | L84: 6 | M84: 6. AC Equipment | N84: Variation Additional AC cable 95mm - Cosmic Sun - VO | Q84: 16085.98 | S84: CS_BMG_006_VO | T84: 45991 | U84: 0 | W84: 45995
T85: =IF(W85>1,EOMONTH(W85,0),"")
B86: 7 | C86: BESS | D86: Battery Inverter + Battery Bank | G86: 0 | I86: =SUM(G86:G93) -> 710967.83 | J86: =F197 -> 789964.25 | L86: 7 | M86: 7.BESS | T86: =IF(W86>1,EOMONTH(W86,0),"") | U86: 0 | V86: =J86-SUM(U86:U93) -> 0 | X86: =SUM(Q86:Q93) -> 0
B87: 7 | D87: Ps and Gs | G87: 67400 | H87: 45991 | L87: 7 | M87: 7.BESS | N87: BESS Supply & Install | T87: 45900 | U87: 789964.25
B88: 7 | D88: Installation | G88: 197200 | H88: 45991 | L88: 7 | M88: 7.BESS | N88: Installation | P88: 197200 | U88: 0
B89: 7 | D89: AC+DC Equipment | G89: 112400 | H89: 45991 | L89: 7 | M89: 7.BESS | N89: AC+DC Equipment | P89: 112400 | U89: 0
B90: 7 | D90: Inverter Cables | G90: 37500 | H90: 45991 | L90: 7 | M90: 7.BESS | N90: Inverter Cables | P90: 37500 | U90: 0
B91: 7 | D91: Main Gateway Cable (Tie-In) | G91: 296467.83 | H91: 45991 | L91: 7 | M91: 7.BESS | N91: Main Gateway Cable (Tie-In) | P91: 296467.83 | U91: 0
B92: 7 | L92: 7 | M92: 7.BESS | T92: =IF(W92>1,EOMONTH(W92,0),"") | U92: 0
B93: 7 | L93: 7 | M93: 7.BESS | T93: =IF(W93>1,EOMONTH(W93,0),"") | U93: 0
T94: =IF(W94>1,EOMONTH(W94,0),"")
B95: 8 | C95: Product Add On | D95: DC Combiner Cabinet | G95: 121304.45 | H95: =H90 -> 45991 | I95: =SUM(G95:G115) -> 536231.13 | J95: =F196 -> 744765.46 | L95: 8 | M95: 8. Product Add On | N95: DC Combiner Cabinet | P95: 121304.45 | T95: =IF(W95>1,EOMONTH(W95,0),"") | U95: =(Q95/$X$95*$J$95) -> 0 | V95: =J95-SUM(U95:U115) -> 0.004084682 | X95: =SUM(Q95:Q115) -> 516856.72
B96: 8 | D96: Trenching cost | G96: 18000 | H96: =H88 -> 45991 | L96: 8 | M96: 8. Product Add On | N96: Trenching cost | P96: 18000 | T96: =IF(W96>1,EOMONTH(W96,0),"") | U96: =(Q96/$X$95*$J$95) -> 0
B97: 8 | D97: Battery Storage Container with HVAC systems | G97: 348926.68 | H97: 45869 | L97: 8 | M97: 8. Product Add On | U97: =(Q97/$X$95*$J$95) -> 0
B98: 8 | D98: Delivery of BESS Storage | G98: 48000 | H98: 45838 | L98: 8 | M98: 8. Product Add On | N98: Delivery of BESS Storage | U98: =(Q98/$X$95*$J$95) -> 0
L99: 8 | M99: 8. Product Add On | T99: =IF(W99>1,EOMONTH(W99,0),"") | U99: =(Q99/$X$95*$J$95) -> 0
L100: 8 | M100: 8. Product Add On | N100: Battery Storage Container with HVAC systems | O100: 400000 | P100: 0.5 | Q100: =O100*P100 -> 200000 | S100: GivEnergy INV-0012 | T100: 45869 | U100: 332484.58 | W100: 45862
L101: 8 | M101: 8. Product Add On | P101: 0.5 | Q101: =O100*P101 -> 200000 | S101: GivEnergy INV-0012 | T101: 45869 | U101: 332484.58 | W101: 45867
L102: 8 | M102: 8. Product Add On | T102: =IF(W102>1,EOMONTH(W102,0),"") | U102: =(Q102/$X$95*$J$95) -> 0
L103: 8 | M103: 8. Product Add On | N103: Changeover DB & Boards Customization - Cosmic Sun | Q103: 63955.72 | R103: PO4247-BMGFT-20250820 - RV Approved | S103: Cosmic Sun - CS_BMG_004_VO | T103: 45900 | U103: 38322.387 | W103: 45890
...

Sheet Cashflow
D1: [RT: Double Check the first date is always a MONDAY] | F1: 45754 | G1: =F1+7 -> 45761 | H1: =G1+7 -> 45768 | I1: =H1+7 -> 45775 | J1: =I1+7 -> 45782 | K1: =J1+7 -> 45789 | L1: =K1+7 -> 45796 | M1: =L1+7 -> 45803 | N1: =M1+7 -> 45810 | ... AZG1: =AZF1+7 -> 55225
A2: PLANNED | C2: CHECK | D2: CHECK
B3: Planned Revenue | C3: ='Revenue Tracking'!D4 -> 3984069.2 | D3: =SUM(F3:AZG3) -> 3984069.2 | F3: =SUMIFS('Revenue Tracking'!$F$13:$F$19, 'Revenue Tracking'!$H$13:$H$19, ">="&F1,'Revenue Tracking'!$H$13:$H$19, "<"&G1) -> 0 | G3: =SUMIFS('Revenue Tracking'!$F$13:$F$19, 'Revenue Tracking'!$H$13:$H$19, ">="&G1,'Revenue Tracking'!$H$13:$H$19, "<"&H1) -> 0 | H3: =SUMIFS('Revenue Tracking'!$F$13:$F$19, 'Revenue Tracking'!$H$13:$H$19, ">="&H1,'Revenue Tracking'!$H$13:$H$19, "<"&I1) -> 0 | I3: =SUMIFS('Revenue Tracking'!$F$13:$F$19, 'Revenue Tracking'!$H$13:$H$19, ">="&I1,'Revenue Tracking'!$H$13:$H$19, "<"&J1) -> 0 | J3: =SUMIFS('Revenue Tracking'!$F$13:$F$19, 'Revenue Tracking'!$H$13:$H$19, ">="&J1,'Revenue Tracking'!$H$13:$H$19, "<"&K1) -> 0 | K3: =SUMIFS('Revenue Tracking'!$F$13:$F$19, 'Revenue Tracking'!$H$13:$H$19, ">="&K1,'Revenue Tracking'!$H$13:$H$19, "<"&L1) -> 0 | L3: =SUMIFS('Revenue Tracking'!$F$13:$F$19, 'Revenue Tracking'!$H$13:$H$19, ">="&L1,'Revenue Tracking'!$H$13:$H$19, "<"&M1) -> 0 | M3: =SUMIFS('Revenue Tracking'!$F$13:$F$19, 'Revenue Tracking'!$H$13:$H$19, ">="&M1,'Revenue Tracking'!$H$13:$H$19, "<"&N1) -> 1992034.6 | ... AZG3: =SUMIFS('Revenue Tracking'!$F$13:$F$19, 'Revenue Tracking'!$H$13:$H$19, ">="&AZG1,'Revenue Tracking'!$H$13:$H$19, "<"&AZH1) -> 0
B4: Planned Revenue - Cumulative | F4: =F3 -> 0 | G4: =F4+G3 -> 0 | H4: =G4+H3 -> 0 | I4: =H4+I3 -> 0 | J4: =I4+J3 -> 0 | K4: =J4+K3 -> 0 | L4: =K4+L3 -> 0 | M4: =L4+M3 -> 1992034.6 | N4: =M4+N3 -> 1992034.6 | ... AZG4: =AZF4+AZG3 -> 3984069.2
B5: Planned Expenditure | C5: ='Revenue Tracking'!D5 -> 3079187 | D5: =SUM(F5:AZG5) -> 3079187 | F5: =SUMIFS('Expenditure Breakdown'!$G$6:$G$194, 'Expenditure Breakdown'!$H$6:$H$194, ">="&F1,'Expenditure Breakdown'!$H$6:$H$194, "<"&G1) -> 0 | G5: =SUMIFS('Expenditure Breakdown'!$G$6:$G$194, 'Expenditure Breakdown'!$H$6:$H$194, ">="&G1,'Expenditure Breakdown'!$H$6:$H$194, "<"&H1) -> 0 | H5: =SUMIFS('Expenditure Breakdown'!$G$6:$G$194, 'Expenditure Breakdown'!$H$6:$H$194, ">="&H1,'Expenditure Breakdown'!$H$6:$H$194, "<"&I1) -> 0 | I5: =SUMIFS('Expenditure Breakdown'!$G$6:$G$194, 'Expenditure Breakdown'!$H$6:$H$194, ">="&I1,'Expenditure Breakdown'!$H$6:$H$194, "<"&J1) -> 0 | J5: =SUMIFS('Expenditure Breakdown'!$G$6:$G$194, 'Expenditure Breakdown'!$H$6:$H$194, ">="&J1,'Expenditure Breakdown'!$H$6:$H$194, "<"&K1) -> 0 | K5: =SUMIFS('Expenditure Breakdown'!$G$6:$G$194, 'Expenditure Breakdown'!$H$6:$H$194, ">="&K1,'Expenditure Breakdown'!$H$6:$H$194, "<"&L1) -> 0 | L5: =SUMIFS('Expenditure Breakdown'!$G$6:$G$194, 'Expenditure Breakdown'!$H$6:$H$194, ">="&L1,'Expenditure Breakdown'!$H$6:$H$194, "<"&M1) -> 0 | M5: =SUMIFS('Expenditure Breakdown'!$G$6:$G$194, 'Expenditure Breakdown'!$H$6:$H$194, ">="&M1,'Expenditure Breakdown'!$H$6:$H$194, "<"&N1) -> 15000 | ... AZG5: =SUMIFS('Expenditure Breakdown'!$G$6:$G$194, 'Expenditure Breakdown'!$H$6:$H$194, ">="&AZG1,'Expenditure Breakdown'!$H$6:$H$194, "<"&AZH1) -> 0
B6: Planned Expenditure - Cumulative | F6: =F5 -> 0 | G6: =F6+G5 -> 0 | H6: =G6+H5 -> 0 | I6: =H6+I5 -> 0 | J6: =I6+J5 -> 0 | K6: =J6+K5 -> 0 | L6: =K6+L5 -> 0 | M6: =L6+M5 -> 15000 | N6: =M6+N5 -> 15000 | ... AZG6: =AZF6+AZG5 -> 3079187
B7: PLANNED CashFlow | F7: =F4-F6 -> 0 | G7: =G4-G6 -> 0 | H7: =H4-H6 -> 0 | I7: =I4-I6 -> 0 | J7: =J4-J6 -> 0 | K7: =K4-K6 -> 0 | L7: =L4-L6 -> 0 | M7: =M4-M6 -> 1977034.6 | ... AZG7: =AZG4-AZG6 -> 904882.2
A8: ACTUAL | C8: CHECK | D8: CHECK
B9: Actual + Planned Revenue | C9: ='Revenue Tracking'!F4 -> 3984069.2 | D9: =SUM(F9:AZG9) -> 3984069.2 | F9: =SUMIFS('Revenue Tracking'!$F$13:$F$19, 'Revenue Tracking'!$P$13:$P$19, ">="&F1,'Revenue Tracking'!$P$13:$P$19, "<"&G1) -> 0 | G9: =SUMIFS('Revenue Tracking'!$F$13:$F$19, 'Revenue Tracking'!$P$13:$P$19, ">="&G1,'Revenue Tracking'!$P$13:$P$19, "<"&H1) -> 0 | H9: =SUMIFS('Revenue Tracking'!$F$13:$F$19, 'Revenue Tracking'!$P$13:$P$19, ">="&H1,'Revenue Tracking'!$P$13:$P$19, "<"&I1) -> 0 | I9: =SUMIFS('Revenue Tracking'!$F$13:$F$19, 'Revenue Tracking'!$P$13:$P$19, ">="&I1,'Revenue Tracking'!$P$13:$P$19, "<"&J1) -> 0 | J9: =SUMIFS('Revenue Tracking'!$F$13:$F$19, 'Revenue Tracking'!$P$13:$P$19, ">="&J1,'Revenue Tracking'!$P$13:$P$19, "<"&K1) -> 0 | K9: =SUMIFS('Revenue Tracking'!$F$13:$F$19, 'Revenue Tracking'!$P$13:$P$19, ">="&K1,'Revenue Tracking'!$P$13:$P$19, "<"&L1) -> 0 | L9: =SUMIFS('Revenue Tracking'!$F$13:$F$19, 'Revenue Tracking'!$P$13:$P$19, ">="&L1,'Revenue Tracking'!$P$13:$P$19, "<"&M1) -> 0 | M9: =SUMIFS('Revenue Tracking'!$F$13:$F$19, 'Revenue Tracking'!$P$13:$P$19, ">="&M1,'Revenue Tracking'!$P$13:$P$19, "<"&N1) -> 0 | ... AZG9: =SUMIFS('Revenue Tracking'!$F$13:$F$19, 'Revenue Tracking'!$P$13:$P$19, ">="&AZG1,'Revenue Tracking'!$P$13:$P$19, "<"&AZH1) -> 0
B10: Actual + Planned Revenue - Cumulative | F10: =F9 -> 0 | G10: =F10+G9 -> 0 | H10: =G10+H9 -> 0 | I10: =H10+I9 -> 0 | J10: =I10+J9 -> 0 | K10: =J10+K9 -> 0 | L10: =K10+L9 -> 0 | M10: =L10+M9 -> 0 | N10: =M10+N9 -> 0 | ... AZG10: =AZF10+AZG9 -> 3984069.2
B11: Actual + Planned Expenditure | C11: ='Revenue Tracking'!F5 -> 3276882 | D11: =SUM(F11:AZG11) -> 3276882 | F11: =SUMIFS('Expenditure Breakdown'!$Q$6:$Q$194, 'Expenditure Breakdown'!$W$6:$W$194, ">="&F1,'Expenditure Breakdown'!$W$6:$W$194, "<"&G1) -> 0 | G11: =SUMIFS('Expenditure Breakdown'!$Q$6:$Q$194, 'Expenditure Breakdown'!$W$6:$W$194, ">="&G1,'Expenditure Breakdown'!$W$6:$W$194, "<"&H1) -> 0 | H11: =SUMIFS('Expenditure Breakdown'!$Q$6:$Q$194, 'Expenditure Breakdown'!$W$6:$W$194, ">="&H1,'Expenditure Breakdown'!$W$6:$W$194, "<"&I1) -> 0 | I11: =SUMIFS('Expenditure Breakdown'!$Q$6:$Q$194, 'Expenditure Breakdown'!$W$6:$W$194, ">="&I1,'Expenditure Breakdown'!$W$6:$W$194, "<"&J1) -> 0 | J11: =SUMIFS('Expenditure Breakdown'!$Q$6:$Q$194, 'Expenditure Breakdown'!$W$6:$W$194, ">="&J1,'Expenditure Breakdown'!$W$6:$W$194, "<"&K1) -> 0 | K11: =SUMIFS('Expenditure Breakdown'!$Q$6:$Q$194, 'Expenditure Breakdown'!$W$6:$W$194, ">="&K1,'Expenditure Breakdown'!$W$6:$W$194, "<"&L1) -> 0 | L11: =SUMIFS('Expenditure Breakdown'!$Q$6:$Q$194, 'Expenditure Breakdown'!$W$6:$W$194, ">="&L1,'Expenditure Breakdown'!$W$6:$W$194, "<"&M1) -> 0 | M11: =SUMIFS('Expenditure Breakdown'!$Q$6:$Q$194, 'Expenditure Breakdown'!$W$6:$W$194, ">="&M1,'Expenditure Breakdown'!$W$6:$W$194, "<"&N1) -> 0 | ... AZG11: =SUMIFS('Expenditure Breakdown'!$Q$6:$Q$194, 'Expenditure Breakdown'!$W$6:$W$194, ">="&AZG1,'Expenditure Breakdown'!$W$6:$W$194, "<"&AZH1) -> 0
B12: Actual + Planned Expenditure - Cumulative | F12: =F11 -> 0 | G12: =F12+G11 -> 0 | H12: =G12+H11 -> 0 | I12: =H12+I11 -> 0 | J12: =I12+J11 -> 0 | K12: =J12+K11 -> 0 | L12: =K12+L11 -> 0 | M12: =L12+M11 -> 0 | N12: =M12+N11 -> 0 | ... AZG12: =AZF12+AZG11 -> 3276882
B14: ACTUAL CashFlow | F14: =F10-F12 -> 0 | G14: =G10-G12 -> 0 | H14: =H10-H12 -> 0 | I14: =I10-I12 -> 0 | J14: =J10-J12 -> 0 | K14: =K10-K12 -> 0 | L14: =L10-L12 -> 0 | M14: =M10-M12 -> 0 | ... AZG14: =AZG10-AZG12 -> 707187.22
C16: CHECK | D16: CHECK
B17: Revenue Recognition | C17: =C3-D17 -> -1934.7081 | D17: =SUM(F17:AZG17) -> 3986004 | F17: =SUMIFS('Expenditure Breakdown'!$U$6:$U$194, 'Expenditure Breakdown'!$T$6:$T$194, ">="&F1,'Expenditure Breakdown'!$T$6:$T$194, "<"&G1) -> 0 | G17: =SUMIFS('Expenditure Breakdown'!$U$6:$U$194, 'Expenditure Breakdown'!$T$6:$T$194, ">="&G1,'Expenditure Breakdown'!$T$6:$T$194, "<"&H1) -> 0 | H17: =SUMIFS('Expenditure Breakdown'!$U$6:$U$194, 'Expenditure Breakdown'!$T$6:$T$194, ">="&H1,'Expenditure Breakdown'!$T$6:$T$194, "<"&I1) -> 0 | I17: =SUMIFS('Expenditure Breakdown'!$U$6:$U$194, 'Expenditure Breakdown'!$T$6:$T$194, ">="&I1,'Expenditure Breakdown'!$T$6:$T$194, "<"&J1) -> 0 | J17: =SUMIFS('Expenditure Breakdown'!$U$6:$U$194, 'Expenditure Breakdown'!$T$6:$T$194, ">="&J1,'Expenditure Breakdown'!$T$6:$T$194, "<"&K1) -> 0 | K17: =SUMIFS('Expenditure Breakdown'!$U$6:$U$194, 'Expenditure Breakdown'!$T$6:$T$194, ">="&K1,'Expenditure Breakdown'!$T$6:$T$194, "<"&L1) -> 0 | L17: =SUMIFS('Expenditure Breakdown'!$U$6:$U$194, 'Expenditure Breakdown'!$T$6:$T$194, ">="&L1,'Expenditure Breakdown'!$T$6:$T$194, "<"&M1) -> 0 | M17: =SUMIFS('Expenditure Breakdown'!$U$6:$U$194, 'Expenditure Breakdown'!$T$6:$T$194, ">="&M1,'Expenditure Breakdown'!$T$6:$T$194, "<"&N1) -> 0 | ... AZG17: =SUMIFS('Expenditure Breakdown'!$U$6:$U$194, 'Expenditure Breakdown'!$T$6:$T$194, ">="&AZG1,'Expenditure Breakdown'!$T$6:$T$194, "<"&AZH1) -> 0
B18: Revenue Recognition Cumulative | C18: =D17-D18 -> 0 | D18: =MAX(F18:AZG18) -> 3986004 | F18: =F17 -> 0 | G18: =F18+G17 -> 0 | H18: =G18+H17 -> 0 | I18: =H18+I17 -> 0 | J18: =I18+J17 -> 0 | K18: =J18+K17 -> 0 | L18: =K18+L17 -> 0 | M18: =L18+M17 -> 0 | N18: =M18+N17 -> 0 | ... AZG18: =AZF18+AZG17 -> 3986004

Sheet Finance - Revenue
A3: Sum of REVENUE RECOGNITION AMOUNT | B3: Column Labels
A4: Row Labels | B4: (blank) | C4: 45777 | D4: 45808 | E4: 45838 | F4: 45869 | G4: 45900 | H4: 45930 | I4: 45961 | J4: 45991 | K4: 46022 | M4: 46053 | N4: 46081 | O4: Grand Total
A5: (blank)
A6: 1. Panels | B6: 0 | G6: 514447.55 | K6: 0 | L6: 0 | O6: 514447.55
A7: 2. Inverters | F7: 194444.44 | L7: 0 | O7: 194444.44
A8: 3. Mounting Structures | B8: 0 | F8: 192541.23 | G8: 491489.56 | H8: 0 | I8: 35769.208 | J8: 0 | K8: 0 | L8: 0 | O8: 719800
A9: 4. DC Equipment | F9: 194972.36 | L9: 0 | O9: 194972.36
A10: 5. Monitoring | B10: 0 | G10: 241666.67 | J10: 0 | K10: 0 | L10: 0 | O10: 241666.67
A11: 6. AC Equipment | B11: 0 | F11: 328631.69 | I11: 0 | J11: 0 | L11: 0 | O11: 328631.69
A12: 8. Product Add On | B12: 0 | F12: 664969.16 | G12: 38322.387 | H12: 41473.908 | J12: 0 | L12: 0 | O12: 744765.45
A13: 9. AC & DC installation | F13: 39251.389 | J13: 31401.111 | K13: 54951.944 | L13: 0 | M13: 23550.833 | N13: 7850.2778 | O13: 157005.56
A14: 10. Site Logistics | F14: 28111.111 | L14: 0 | O14: 28111.111
A15: 11. Due Dilligence | B15: 0 | K15: 22531.328 | L15: 0 | M15: 9690.8939 | O15: 32222.222
A16: 13. Engineering | L16: 0 | N16: 35315.71 | O16: 35315.71
A17: 14. General Expenses | B17: 0 | C17: 0 | D17: 0 | E17: 647.08873 | F17: 583.73621 | G17: 380.56947 | H17: 820.19754 | I17: 1633.5093 | J17: 170.15157 | K17: 0 | M17: 239.88713 | N17: 181.79878 | O17: 4656.9387
A18: 15. Service Add On | L18: 0 | O18: 0
A19: 12. BDP Commission
A20: 7.BESS | B20: 0 | G20: 789964.25 | L20: 0 | O20: 789964.25
A21: Grand Total | B21: 0 | C21: 0 | D21: 0 | E21: 647.08873 | F21: 1643505.1 | G21: 2076271 | H21: 42294.105 | I21: 37402.717 | J21: 31571.263 | K21: 77483.273 | L21: 0 | M21: 33481.614 | N21: 43347.787 | O21: 3986004
E23: 647.09 | F23: 1643505.1 | G23: 2076271
E24: =GETPIVOTDATA("REVENUE RECOGNITION AMOUNT",$A$3,"INVOICE RAISED DATE",DATE(2025,6,30))-E23 -> -0.0012656442 | F24: =GETPIVOTDATA("REVENUE RECOGNITION AMOUNT",$A$3,"INVOICE RAISED DATE",DATE(2025,7,31))-F23 -> 0.0034237755 | G24: =GETPIVOTDATA("REVENUE RECOGNITION AMOUNT",$A$3,"INVOICE RAISED DATE",DATE(2025,8,31))-G23 -> -0.0048611069

Sheet Finance - COS
A3: Sum of Actual Total | B3: Column Labels
A4: Row Labels | B4: (blank) | C4: 45777 | D4: 45808 | E4: 45838 | F4: 45869 | G4: 45900 | H4: 45930 | I4: 45961 | J4: 45991 | K4: 46022 | M4: 46053 | N4: 46081 | O4: Grand Total
A5: (blank)
A6: 1. Panels | G6: 275554 | K6: 4469.2 | O6: 280023.2
A7: 2. Inverters | F7: 137740.7 | O7: 137740.7
A8: 3. Mounting Structures | B8: 0 | F8: 344700 | G8: 879896.99 | H8: -20991.01 | J8: 4800 | K8: 38623.44 | O8: 1247029.4
A9: 4. DC Equipment | F9: 259295 | O9: 259295
A10: 5. Monitoring | G10: 18811 | J10: 15678.35 | K10: 6900 | O10: 41389.35
A11: 6. AC Equipment | F11: 350590.6 | I11: 50063.28 | J11: 16085.98 | O11: 416739.86
A12: 8. Product Add On | F12: 400000 | G12: 63955.72 | H12: 27360 | J12: 18931 | K12: 6610 | O12: 516856.72
A13: 9. AC & DC installation | F13: 55080 | J13: 44064 | K13: 77112 | M13: 33048 | N13: 11016 | O13: 220320
A14: 10. Site Logistics | F14: 80250 | O14: 80250
A15: 11. Due Dilligence | K15: 13950 | M15: 6000 | O15: 19950
A16: 13. Engineering | N16: 49800.866 | O16: 49800.866
A17: 14. General Expenses | C17: 0 | D17: 0 | E17: 458.39 | F17: 459.51 | G17: 308.45 | H17: 845.78 | I17: 3844.23 | J17: 410.79 | K17: 0 | M17: 659.76 | N17: 500 | O17: 7486.91
A18: 15. Service Add On
A19: 12. BDP Commission | L19: 0 | O19: 0
A20: 7.BESS
A21: Grand Total | B21: 0 | C21: 0 | D21: 0 | E21: 458.39 | F21: 1628115.8 | G21: 1238526.2 | H21: 7214.77 | I21: 53907.51 | J21: 99970.12 | K21: 147664.64 | L21: 0 | M21: 39707.76 | N21: 61316.866 | O21: 3276882

Sheet Project Margins
A1: [capture project margins from costing sheet]
A3: Products | D3: 0.32
A4: Services | D4: 0.5
A5: Expenses | D5: 0.15
A6: Subcontractors | D6: 0.2

Sheet Equipment Quotes
B2: Equipment Quote and Budget comparision
B4: Description | D4: Budget | F4: Supplier 1 | H4: Variance | J4: Supplier 2 | L4: Variance | N4: Comments / Notes
F7: >Name< | J7: >Name<
B9: Inverters | D9: =SUM(D10:D11) -> #REF! | F9: =SUM(F10:F13) -> 0 | H9: =$D$9-F9 -> #REF! | J9: =SUM(J10:J13) -> 0 | L9: =$D$9-J9 -> #REF!
B10: Inverters | D10: =#REF! -> #REF!
B11: Optimizers | D11: =#REF! -> #REF!
B12: Warranty
B13: Delivery fee
F15: >Name< | J15: >Name<
B17: Mounting Structure | D17: =SUM(D18:D19) -> #REF! | F17: =SUM(F18:F20) -> 0 | H17: =$D$17- F17 -> #REF! | J17: =SUM(J18:J20) -> 0 | L17: =$D$17- J17 -> #REF!
B18: Mounting Structure | D18: =#REF! -> #REF!
B19: Delivery fee
F21: >Name< | J21: >Name<
B23: DC Cable | D23: =SUM(D24:D25) -> #REF! | F23: =SUM(F24:F25) -> 0 | H23: =$D$23- F23 -> #REF! | J23: =SUM(J24:J25) -> 0 | L23: =$D$23- J23 -> #REF!
B24: DC Cable | D24: =#REF! -> #REF!
B25: Delivery fee
F27: >Name< | J27: >Name<
B29: Monitoring system | D29: =SUM(D30:D32) -> #REF! | F29: =SUM(F30:F42) -> 0 | H29: =$D$29-F29 -> #REF! | J29: =SUM(J30:J32) -> 0 | L29: =$D$29-J29 -> #REF!
B30: =#REF! -> #REF! | D30: =#REF! -> #REF!
B31: =#REF! -> #REF! | D31: =#REF! -> #REF!
B32: Delivery fee
F34: >Name< | J34: >Name<
B36: Additional Scope | D36: =SUM(D37:D41) -> #REF! | F36: =SUM(F37:F41) -> 0 | H36: =$D$29-F36 -> #REF! | J36: =SUM(J37:J41) -> 0 | L36: =$D$29-J36 -> #REF!
B37: SCADA | D37: =#REF! -> #REF!
B38: Inverter cage
B39: Cat ladders
B40: Gen Integration
B41: Lifelines
B43: Totals | D43: =D36+D29+D23+D17+D9 -> #REF! | H43: =SUM(H7:H42) -> #REF! | L43: =SUM(L7:L42) -> #REF!
B47: All amounts are incl VAT

Sheet Installer Quotes
B2: Installer Quote and Budget comparision
B4: Description | D4: Budget | G4: Cosmic Sun | J4: Variance | L4: Matthews Group | O4: Variance
B6: AC Equipment | D6: =#REF! -> #REF! | E6: =D6/(1000*'Project Plan'!$E$3) -> #REF! | G6: 277892.91 | H6: =G6/('Project Plan'!$E$3*1000) -> 1.9298119 | J6: =D6-G6 -> #REF! | M6: =L6/('Project Plan'!$E$3*1000) -> 0 | O6: =D6-L6 -> #REF!
B7: DC Equipment | D7: =#REF! -> #REF! | E7: =D7/(1000*'Project Plan'!$E$3) -> #REF! | G7: 142158.25 | H7: =G7/('Project Plan'!$E$3*1000) -> 0.98721007 | J7: =D7-G7 -> #REF! | M7: =L7/('Project Plan'!$E$3*1000) -> 0 | O7: =D7-L7 -> #REF!
B8: AC Labour | D8: =#REF! -> #REF! | E8: =D8/(1000*'Project Plan'!$E$3) -> #REF! | G8: 96174 | H8: =G8/('Project Plan'!$E$3*1000) -> 0.667875 | J8: =D8-G8 -> #REF! | M8: =L8/('Project Plan'!$E$3*1000) -> 0 | O8: =D8-L8 -> #REF!
B9: DC Labour | D9: =#REF! -> #REF! | E9: =D9/(1000*'Project Plan'!$E$3) -> #REF! | G9: 230160 | H9: =G9/('Project Plan'!$E$3*1000) -> 1.5983333 | J9: =D9-G9 -> #REF! | M9: =L9/('Project Plan'!$E$3*1000) -> 0 | O9: =D9-L9 -> #REF!
B10: Offloading | D10: =#REF! -> #REF! | G10: 0 | J10: =D10-G10 -> #REF! | O10: =D10-L10 -> #REF!
B11: Roof Access/Scaffolding | D11: =#REF! -> #REF! | G11: 29257.61 | J11: =D11-G11 -> #REF! | O11: =D11-L11 -> #REF!
B12: Storage | D12: =#REF! -> #REF! | J12: =D12-G12 -> #REF! | O12: =D12-L12 -> #REF!
B13: Telehandler | D13: =#REF! -> #REF!
B14: HSE | D14: 0
B15: Totals | D15: =SUM(D6:D13) -> #REF! | G15: =SUM(G6:G13) -> 775642.77 | J15: =SUM(J6:J14) -> #REF! | L15: =SUM(L6:L13) -> 0 | O15: =SUM(O6:O14) -> #REF!
B18: Description | D18: Budget | G18: >Installer Name 3< | J18: Variance | L18: >Installer Name 4< | O18: Variance
B20: AC installation | D20: =#REF! -> #REF! | E20: =D20/(1000*'Project Plan'!$E$3) -> #REF! | H20: =G20/(1000*'Project Plan'!$E$3) -> 0 | J20: =D20-G20 -> #REF! | M20: =L20/(1000*'Project Plan'!$E$3) -> 0 | O20: =D6-L20 -> #REF!
B21: AC equipment | D21: =#REF! -> #REF! | E21: =D21/(1000*'Project Plan'!$E$3) -> #REF! | J21: =D21-G21 -> #REF! | M21: =L21/(1000*'Project Plan'!$E$3) -> 0 | O21: =D7-L21 -> #REF!
B22: DC installation | D22: =#REF! -> #REF! | E22: =D22/(1000*'Project Plan'!$E$3) -> #REF! | H22: =G22/(1000*'Project Plan'!$E$3) -> 0 | J22: =D22-G22 -> #REF! | M22: =L22/(1000*'Project Plan'!$E$3) -> 0 | O22: =D8-L22 -> #REF!
B23: DC equipment | D23: =SUM(#REF!) -> #REF! | E23: =D23/(1000*'Project Plan'!$E$3) -> #REF! | J23: =D23-G23 -> #REF! | O23: =D9-L23 -> #REF!
B24: Storage | D24: =#REF! -> #REF! | J24: =D24-G24 -> #REF! | O24: =D10-L24 -> #REF!
B25: Panel lifting equipment | D25: =SUM(#REF!) -> #REF! | J25: =D25-G25 -> #REF! | O25: =D11-L25 -> #REF!
B26: Offloading | D26: =#REF! -> #REF! | J26: =D26-G26 -> #REF! | O26: =D12-L26 -> #REF!
B29: Totals | D29: =SUM(D20:D27) -> #REF! | G29: =SUM(G20:G27) -> 0 | J29: =SUM(J20:J28) -> #REF! | L29: =SUM(L20:L27) -> 0 | O29: =SUM(O20:O28) -> #REF!
B32: Budget Summary
B34: Budget | D34: =D15 -> #REF!
B35: =G4 -> Cosmic Sun | D35: =G15 -> 775642.77
B36: =L4 -> Matthews Group | D36: =L15 -> 0
B37: =G18 -> >Installer Name 3< | D37: =G29 -> 0
B38: =L18 -> >Installer Name 4< | D38: =L29 -> 0
B40: =IF(D40<D34,"Saving","Loss") -> #REF! | D40: =D34-MIN(D35:D38) -> #REF!
B42: All amounts are exc VAT

Sheet Decision Register
B1: =D15 -> BMG Fluid Tech | E1: Decision Register
B3: ID | C3: Decision Description | D3: Decision Impact | E3: Proposed Date | F3: Proposed By | G3: Status | H3: Approved By | I3: Date | J3: Results / Comments
B4: DEC001
B5: DEC002
B6: DEC003
B7: DEC004
B8: DEC005
B9: DEC006
B10: DEC007
B11: DEC008
B12: DEC009
B13: DEC010
D15: {='Project Plan'!E2:H2} -> BMG Fluid Tech | E15: 0 | F15: 0 | G15: 0
