Workbook
Name Inverter_Capacity: #REF!
Name Inverter_Supplier: #REF!
Name Project_Size: 'Finance - Revenue'!Projectsize
Name Project_Size: Projectsize
Name Projectsize: #REF!
Name Projectsize: #REF!
Name Security_Serv: #REF!
Name Security_Serv: #REF!
Name SSS: #REF!
Name SSS: #REF!
Name USD_ZAR: #REF!

Sheet Certificate - Financial Close
B2: Emergent Energy – Financial Close Completion Certificate | H2: FINANCIAL CLOSE CERTIFICATE
B4: Project Name: | C4: ='Project Plan'!E2 -> PnP Bethal
B5: COO: | C5: Johannes Potgieter
B6: Programme Manager: | C6: Roedolph Venter
B7: HoPD: | C7: Natasha Watkins-Baker
B9: Date of Phase Completion:
B10: Phase Deliverables Checklist: (Y/N)
B11: Product Agreement
B12: EPC Agreement
B13: O&M Agreeement
B14: Cost Proposal
B15: Deposit Received
B16: Risks / Notes
B18: Acknowledgement and Acceptance:
B19: Role | C19: Name | D19: Signature | E19: Date

Sheet Certificate - Planning
B2: Emergent Energy – Planning Phase Completion Certificate | H2: PLANNING CERTIFICATE
B4: Project Name: | C4: ='Project Plan'!E2 -> PnP Bethal
B5: Client Representative:
B6: Programme Manager: | C6: Roedolph Venter
B7: Project Manager: | C7: ='Project Plan'!E5 -> Eon Van Rensburg
B8: Project Engineer:
B10: Date of Phase Completion:
B11: Phase Deliverables Checklist: (Y/N)
B12: Project Introduction Presentation
B13: Project Brief
B14: Engineering Pack
B15: BOQ
B16: PO – Material & Equipment
B17: PO - Contractors
B18: HSE – NOC
B19: HSE – EE File
B20: HSE – Contractor File
... B24: Acknowledgement and Acceptance:
B25: Role | C25: Name | D25: Signature | E25: Date

Sheet Change Register
F1: Change Register
B3: ID | C3: Description | D3: Supporting Image (If Applicable) | E3: Impact | F3: Proposed Date | G3: Proposed By | H3: Status | I3: Approved By | J3: Approved Date | K3: Results / Comments
B4: DEC001
B5: DEC002
B6: DEC003
B7: DEC004
B8: DEC005
B9: DEC006
B10: DEC007
B11: DEC008
B12: DEC009
B13: DEC010
B14: DEC011
B15: DEC012
... B33: DEC030

Sheet BOQ
B2: Item | C2: Supplier | D2: Description | E2: Quantity | F2: Comments
B3: PV Module
B4: DC Cable Red & Black
B5: Inverters
B6: Mounting Structure
B7: Current Transformers (Production)
B8: Current Transformers (Consumption)
B9: Solar Production Meter (Techistter)
B10: Grid Consumption Meter
B11: Wi-Fi Router & Sim
B12: Switch
B13: Back Up Battery
B14: PVDB
... B30: Techsitter

Sheet Compliance
B2: HSE
B4: Description | C4: Status | D4: Approved By | E4: Date | F4: Results / Comments
B5: NOC | F5: In progress
B6: 7.1 Agreement | F6: In progress
B7: 13.2 Agreement | F7: In progress
B8: EE File | F8: In progress
B9: Subbie File | F9: Not appointed yet
B16: SSEG
B18: Description | C18: Status | D18: Approved By | E18: Date | F18: Results / Comments
B19: SSEG Application
B20: PTI
B21: Commissioning Approval

Sheet Project Plan
N1: =TODAY() -> 46056 | O1: =TODAY() -> 46056
C2: PROJECT PLAN | E2: PnP Bethal | I2: Net Work Days | K2: =NETWORKDAYS(I19,K43,Data!C3:C60) -> 31 | N2: 0 | O2: 1
C3: PROJECT SIZE (kWp) | E3: 420 | I3: Total Weeks | K3: =K2/5 -> 6.2
C4: PROJECT DEVELOPER | E4: Megan Moore | I4: kW/Week Installation Rate | K4: =E3/K3 -> 67.741935
C5: PROJECT MANAGERS | E5: Eon Van Rensburg
C6: CONTRACT VALUE | E6: 4119606.9
C7: Phase: | E7: Planning
B8: No. | C8: HIGH LEVEL PROGRAMME | E8: Planned Start | F8: Duration | G8: Planned End | I8: Actual Start | J8: Duration | K8: Actual End | M8: Status | N8: Expected Status | O8: Comment
F9: =G43-E20 -> 46 | J9: =K43-I20 -> 46 | M9: =AVERAGE(M11,M19,M22,M32,M39,M43,M52,M48) -> 0.0032051282 | N9: =AVERAGE(N11,N19,N22,N32,N39,N43,N52,N48) -> 0.042959311 | S9: =TODAY() -> 46056 | T9: =TODAY() -> 46056
S10: 1 | T10: 0
B11: 1 | C11: Project Initiation | E11: =MIN(E12:E18) -> 46043 | F11: =G11-E11 -> 28 | G11: =MAX(G12:G18) -> 46071 | I11: =MIN(I12:I18) -> 46043 | J11: =K11-I11 -> 28 | K11: =MAX(K12:K18) -> 46071 | M11: =(J12*M12+J14*M14+J15*M15+J16*M16+J17*M17)/SUM(J12:J17) -> 0.025641026 | N11: =(K12*N12+K14*N14+K15*N15+K16*N16+K17*N17)/SUM(K12:K17) -> 0.26978286
B12: 1.1 | C12: Project Charter Handover | E12: 46043 | F12: 1 | G12: 46043 | I12: 46043 | J12: 1 | K12: 46043 | M12: 1 | N12: =_xlfn.LET( _xlpm.s,VALUE($I12), _xlpm.e,VALUE($K12), IF(OR(_xlpm.s="",_xlpm.e=""),"", IF(_xlpm.e<=_xlpm.s, IF(TODAY()>=_xlpm.e,1,0), MAX(0,MIN(1,(TODAY()-_xlpm.s)/(_xlpm.e-_xlpm.s))))) ) -> 1 | S12: Milestone | T12: Start Date | U12: Duration | V12: End Date
C13: Deposit | I13: =I12 -> 46043 | J13: 16 | K13: =WORKDAY.INTL(I13,J13,1,Data!$C$3:$C$60) -> 46065
B14: 1.2 | C14: HSE Readiness and Signoff | E14: =G12 -> 46043 | F14: 15 | G14: =WORKDAY.INTL(E14,F14,1,Data!$C$3:$C$60) -> 46064 | I14: =K12 -> 46043 | J14: 15 | K14: =WORKDAY.INTL(I14,J14,1,Data!$C$3:$C$60) -> 46064 | M14: 0 | N14: =_xlfn.LET( _xlpm.s,VALUE($I14), _xlpm.e,VALUE($K14), IF(OR(_xlpm.s="",_xlpm.e=""),"", IF(_xlpm.e<=_xlpm.s, IF(TODAY()>=_xlpm.e,1,0), MAX(0,MIN(1,(TODAY()-_xlpm.s)/(_xlpm.e-_xlpm.s))))) ) -> 0.61904762 | S14: =C11 -> Project Initiation | T14: =I11 -> 46043 | U14: =J11 -> 28 | V14: =K11 -> 46071
B15: 1.3 | C15: Project Introduction | E15: =WORKDAY.INTL(G14,0,1,Data!$C$3:$C$60) -> 46064 | F15: 1 | G15: =WORKDAY.INTL(E15,F15,1,Data!$C$3:$C$60) -> 46065 | I15: =WORKDAY.INTL(K14,0,1,Data!$C$3:$C$60) -> 46064 | J15: 1 | K15: =WORKDAY.INTL(I15,J15,1,Data!$C$3:$C$60) -> 46065 | M15: 0 | N15: =_xlfn.LET( _xlpm.s,VALUE($I15), _xlpm.e,VALUE($K15), IF(OR(_xlpm.s="",_xlpm.e=""),"", IF(_xlpm.e<=_xlpm.s, IF(TODAY()>=_xlpm.e,1,0), MAX(0,MIN(1,(TODAY()-_xlpm.s)/(_xlpm.e-_xlpm.s))))) ) -> 0 | S15: =C19 -> Site Establishment | T15: =I19 -> 46081 | U15: =J19 -> 1 | V15: =K19 -> 46082
B16: 1.4 | C16: Installer Kick Off | E16: =WORKDAY.INTL(E14,0,1,Data!$C$3:$C$60)+14 -> 46057 | F16: 1 | G16: =WORKDAY.INTL(E16,F16,1,Data!$C$3:$C$60) -> 46058 | I16: =WORKDAY.INTL(I14,0,1,Data!$C$3:$C$60)+14 -> 46057 | J16: 1 | K16: =WORKDAY.INTL(I16,J16,1,Data!$C$3:$C$60) -> 46058 | M16: 0 | N16: =_xlfn.LET( _xlpm.s,VALUE($I16), _xlpm.e,VALUE($K16), IF(OR(_xlpm.s="",_xlpm.e=""),"", IF(_xlpm.e<=_xlpm.s, IF(TODAY()>=_xlpm.e,1,0), MAX(0,MIN(1,(TODAY()-_xlpm.s)/(_xlpm.e-_xlpm.s))))) ) -> 0 | S16: =C22 -> AC Installation | T16: =I22 -> 46050 | U16: =J22 -> 61 | V16: =K22 -> 46111
B17: 1.5 | C17: Project Review | E17: =WORKDAY.INTL(G14,0,1,Data!$C$3:$C$60) -> 46064 | F17: 5 | G17: =WORKDAY.INTL(E17,F17,1,Data!$C$3:$C$60) -> 46071 | I17: =WORKDAY.INTL(K14,0,1,Data!$C$3:$C$60) -> 46064 | J17: 5 | K17: =WORKDAY.INTL(I17,J17,1,Data!$C$3:$C$60) -> 46071 | M17: 0 | N17: =_xlfn.LET( _xlpm.s,VALUE($I17), _xlpm.e,VALUE($K17), IF(OR(_xlpm.s="",_xlpm.e=""),"", IF(_xlpm.e<=_xlpm.s, IF(TODAY()>=_xlpm.e,1,0), MAX(0,MIN(1,(TODAY()-_xlpm.s)/(_xlpm.e-_xlpm.s))))) ) -> 0 | S17: =C32 -> DC Works | T17: =I32 -> 46057 | U17: =J32 -> 48 | V17: =K32 -> 46105
S18: =C39 -> Module installation | T18: =I39 -> 46081 | U18: =J39 -> 18 | V18: =K39 -> 46099
B19: 2 | C19: Site Establishment | E19: =MIN(E20:E21) -> 46076 | F19: =G19-E19 -> 1 | G19: =MAX(G20:G21) -> 46077 | I19: =MIN(I20:I21) -> 46081 | J19: =K19-I19 -> 1 | K19: =MAX(K20:K21) -> 46082 | M19: =(J20*M20)/J19 -> 0 | N19: =(K20*N20)/K19 -> 0 | S19: =C43 -> Commissioning | T19: =I43 -> 46111 | U19: =J43 -> 16 | V19: =K43 -> 46127
B20: 2.1 | C20: Solar Contractor Establishment | E20: 46076 | F20: 1 | G20: =E20+F20 -> 46077 | I20: =K11+10 -> 46081 | J20: 1 | K20: =I20+J20 -> 46082 | M20: 0 | N20: =_xlfn.LET( _xlpm.s,VALUE($I20), _xlpm.e,VALUE($K20), IF(OR(_xlpm.s="",_xlpm.e=""),"", IF(_xlpm.e<=_xlpm.s, IF(TODAY()>=_xlpm.e,1,0), MAX(0,MIN(1,(TODAY()-_xlpm.s)/(_xlpm.e-_xlpm.s))))) ) -> 0 | S20: =C48 -> QA Inspections | T20: =I48 -> 46120 | U20: =J48 -> 8 | V20: =K48 -> 46128
S21: =C52 -> Project Closure | T21: =I52 -> 46125 | U21: =J52 -> 11 | V21: =K52 -> 46136
B22: 3 | C22: AC Installation | E22: =MIN(E23:E31) -> 46050 | F22: =G22-E22 -> 54 | G22: =MAX(G23:G31) -> 46104 | I22: =MIN(I23:I31) -> 46050 | J22: =K22-I22 -> 61 | K22: =MAX(K23:K31) -> 46111 | M22: =(J23*M23+J24*M24+J25*M25+J27*M27+J30*M30)/SUM(J23:J30) -> 0 | N22: =(J23*N23+J24*N24+J25*N25+J27*N27+J30*N30)/SUM(J23:J30) -> 0.073891626
B23: 3.1 | C23: Inverters delivered | E23: =WORKDAY.INTL(E20,0,1,Data!$C$3:$C$60) -> 46076 | F23: 1 | G23: =WORKDAY.INTL(E23,F23,1,Data!$C$3:$C$60) -> 46077 | I23: =WORKDAY.INTL(I20,0,1,Data!$C$3:$C$60) -> 46081 | J23: 1 | K23: =WORKDAY.INTL(I23,J23,1,Data!$C$3:$C$60) -> 46083 | M23: 0 | N23: =_xlfn.LET( _xlpm.s,VALUE($I23), _xlpm.e,VALUE($K23), IF(OR(_xlpm.s="",_xlpm.e=""),"", IF(_xlpm.e<=_xlpm.s, IF(TODAY()>=_xlpm.e,1,0), MAX(0,MIN(1,(TODAY()-_xlpm.s)/(_xlpm.e-_xlpm.s))))) ) -> 0
B24: 3.2 | C24: Inverters Mounted | E24: =WORKDAY.INTL(G23,0,1,Data!$C$3:$C$60) -> 46077 | F24: 1 | G24: =WORKDAY.INTL(E24,F24,1,Data!$C$3:$C$60) -> 46078 | I24: =WORKDAY.INTL(K23,0,1,Data!$C$3:$C$60) -> 46083 | J24: 1 | K24: =WORKDAY.INTL(I24,J24,1,Data!$C$3:$C$60) -> 46084 | M24: 0 | N24: =_xlfn.LET( _xlpm.s,VALUE($I24), _xlpm.e,VALUE($K24), IF(OR(_xlpm.s="",_xlpm.e=""),"", IF(_xlpm.e<=_xlpm.s, IF(TODAY()>=_xlpm.e,1,0), MAX(0,MIN(1,(TODAY()-_xlpm.s)/(_xlpm.e-_xlpm.s))))) ) -> 0
B25: 3.3 | C25: Solar DB Lead Time | E25: =WORKDAY.INTL(E15,0,1,Data!$C$3:$C$60)-14 -> 46050 | F25: 30 | G25: =WORKDAY.INTL(E25,F25,1,Data!$C$3:$C$60) -> 46092 | I25: =WORKDAY.INTL(I15,0,1,Data!$C$3:$C$60)-14 -> 46050 | J25: 30 | K25: =WORKDAY.INTL(I25,J25,1,Data!$C$3:$C$60) -> 46092 | M25: 0 | N25: =_xlfn.LET( _xlpm.s,VALUE($I25), _xlpm.e,VALUE($K25), IF(OR(_xlpm.s="",_xlpm.e=""),"", IF(_xlpm.e<=_xlpm.s, IF(TODAY()>=_xlpm.e,1,0), MAX(0,MIN(1,(TODAY()-_xlpm.s)/(_xlpm.e-_xlpm.s))))) ) -> 0.14285714
B26: 3.4 | C26: BESS Delivery | E26: =E24 -> 46077 | F26: 1 | G26: =G23 -> 46077 | I26: =I24 -> 46083 | J26: 1 | K26: =K23 -> 46083 | M26: 0 | N26: =_xlfn.LET( _xlpm.s,VALUE($I26), _xlpm.e,VALUE($K26), IF(OR(_xlpm.s="",_xlpm.e=""),"", IF(_xlpm.e<=_xlpm.s, IF(TODAY()>=_xlpm.e,1,0), MAX(0,MIN(1,(TODAY()-_xlpm.s)/(_xlpm.e-_xlpm.s))))) ) -> 0
B27: 3.5 | C27: AC Works - BESS | E27: =WORKDAY.INTL(G25,0,1,Data!$C$3:$C$60) -> 46092 | F27: 8 | G27: =WORKDAY.INTL(E27,F27,1,Data!$C$3:$C$60) -> 46104 | I27: =WORKDAY.INTL(K25,0,1,Data!$C$3:$C$60) -> 46092 | J27: 10 | K27: =WORKDAY.INTL(I27,J27,1,Data!$C$3:$C$60) -> 46106 | M27: 0 | N27: =_xlfn.LET( _xlpm.s,VALUE($I27), _xlpm.e,VALUE($K27), IF(OR(_xlpm.s="",_xlpm.e=""),"", IF(_xlpm.e<=_xlpm.s, IF(TODAY()>=_xlpm.e,1,0), MAX(0,MIN(1,(TODAY()-_xlpm.s)/(_xlpm.e-_xlpm.s))))) ) -> 0
B28: 3.6 | C28: AC Tie-In - BESS | I28: =WORKDAY.INTL(K27,0,1,Data!$C$3:$C$60) -> 46106 | J28: 2 | K28: =WORKDAY.INTL(I28,J28,1,Data!$C$3:$C$60) -> 46108 | M28: 0 | N28: =_xlfn.LET( _xlpm.s,VALUE($I28), _xlpm.e,VALUE($K28), IF(OR(_xlpm.s="",_xlpm.e=""),"", IF(_xlpm.e<=_xlpm.s, IF(TODAY()>=_xlpm.e,1,0), MAX(0,MIN(1,(TODAY()-_xlpm.s)/(_xlpm.e-_xlpm.s))))) ) -> 0
B29: 3.7 | C29: AC Works - Solar | I29: =K25 -> 46092 | J29: 12 | K29: =WORKDAY.INTL(I29,J29,1,Data!$C$3:$C$60) -> 46108 | M29: 0 | N29: =_xlfn.LET( _xlpm.s,VALUE($I29), _xlpm.e,VALUE($K29), IF(OR(_xlpm.s="",_xlpm.e=""),"", IF(_xlpm.e<=_xlpm.s, IF(TODAY()>=_xlpm.e,1,0), MAX(0,MIN(1,(TODAY()-_xlpm.s)/(_xlpm.e-_xlpm.s))))) ) -> 0
B30: 3.8 | C30: AC Tie-In - Solar | E30: =WORKDAY.INTL(E27,0,1,Data!$C$3:$C$60) -> 46092 | F30: 1 | G30: =WORKDAY.INTL(E30,F30,1,Data!$C$3:$C$60) -> 46093 | I30: =K29 -> 46108 | J30: 1 | K30: =WORKDAY.INTL(I30,J30,1,Data!$C$3:$C$60) -> 46111 | M30: 0 | N30: =_xlfn.LET( _xlpm.s,VALUE($I30), _xlpm.e,VALUE($K30), IF(OR(_xlpm.s="",_xlpm.e=""),"", IF(_xlpm.e<=_xlpm.s, IF(TODAY()>=_xlpm.e,1,0), MAX(0,MIN(1,(TODAY()-_xlpm.s)/(_xlpm.e-_xlpm.s))))) ) -> 0
B32: 4 | C32: DC Works | E32: =MIN(E34:E38) -> 46076 | F32: =G32-E32 -> 23 | G32: =MAX(G34:G38) -> 46099 | I32: =MIN(I34:I38) -> 46057 | J32: =K32-I32 -> 48 | K32: =MAX(K34:K38) -> 46105 | M32: =(J34*M34+J35*M35+J37*M37)/SUM(J34:J37) -> 0 | N32: =(K34*N34+K35*N35+K37*N37)/SUM(K34:K37) -> 0
B34: 4.1 | C34: Mounting Structure delivered | E34: =E20 -> 46076 | F34: 1 | G34: =WORKDAY.INTL(E34,F34,1,Data!$C$3:$C$60) -> 46077 | I34: =I20 -> 46081 | J34: 1 | K34: =WORKDAY.INTL(I34,J34,1,Data!$C$3:$C$60) -> 46083 | M34: 0 | N34: =_xlfn.LET( _xlpm.s,VALUE($I34), _xlpm.e,VALUE($K34), IF(OR(_xlpm.s="",_xlpm.e=""),"", IF(_xlpm.e<=_xlpm.s, IF(TODAY()>=_xlpm.e,1,0), MAX(0,MIN(1,(TODAY()-_xlpm.s)/(_xlpm.e-_xlpm.s))))) ) -> 0
B35: 4.2 | C35: Mounting Structure installation | E35: =WORKDAY.INTL(G34,0,1,Data!$C$3:$C$60) -> 46077 | F35: 3 | G35: =WORKDAY.INTL(E35,F35,1,Data!$C$3:$C$60) -> 46080 | I35: =WORKDAY.INTL(K34,0,1,Data!$C$3:$C$60) -> 46083 | J35: 3 | K35: =WORKDAY.INTL(I35,J35,1,Data!$C$3:$C$60) -> 46086 | M35: 0 | N35: =_xlfn.LET( _xlpm.s,VALUE($I35), _xlpm.e,VALUE($K35), IF(OR(_xlpm.s="",_xlpm.e=""),"", IF(_xlpm.e<=_xlpm.s, IF(TODAY()>=_xlpm.e,1,0), MAX(0,MIN(1,(TODAY()-_xlpm.s)/(_xlpm.e-_xlpm.s))))) ) -> 0
B36: 4.3 | C36: DC Cable delivered | E36: =E34 -> 46076 | F36: 1 | G36: =WORKDAY.INTL(E36,F36,1,Data!$C$3:$C$60) -> 46077 | I36: 46057 | J36: 1 | K36: =WORKDAY.INTL(I36,J36,1,Data!$C$3:$C$60) -> 46058 | M36: 0 | N36: =_xlfn.LET( _xlpm.s,VALUE($I36), _xlpm.e,VALUE($K36), IF(OR(_xlpm.s="",_xlpm.e=""),"", IF(_xlpm.e<=_xlpm.s, IF(TODAY()>=_xlpm.e,1,0), MAX(0,MIN(1,(TODAY()-_xlpm.s)/(_xlpm.e-_xlpm.s))))) ) -> 0
B37: 4.4 | C37: DC Stringing | E37: =WORKDAY.INTL(G41,0,1,Data!$C$3:$C$60)-3 -> 46090 | F37: 7 | G37: =WORKDAY.INTL(E37,F37,1,Data!$C$3:$C$60) -> 46099 | I37: =WORKDAY.INTL(K41,0,1,Data!$C$3:$C$60)-3 -> 46096 | J37: 7 | K37: =WORKDAY.INTL(I37,J37,1,Data!$C$3:$C$60) -> 46105 | M37: 0 | N37: =_xlfn.LET( _xlpm.s,VALUE($I37), _xlpm.e,VALUE($K37), IF(OR(_xlpm.s="",_xlpm.e=""),"", IF(_xlpm.e<=_xlpm.s, IF(TODAY()>=_xlpm.e,1,0), MAX(0,MIN(1,(TODAY()-_xlpm.s)/(_xlpm.e-_xlpm.s))))) ) -> 0
B39: 5 | C39: Module installation | E39: =MIN(E40:E42) -> 46076 | F39: =G39-E39 -> 17 | G39: =MAX(G40:G42) -> 46093 | I39: =MIN(I40:I42) -> 46081 | J39: =K39-I39 -> 18 | K39: =MAX(K40:K42) -> 46099 | M39: =(J40*M40+J41*M41)/SUM(J40:J41) -> 0 | N39: =(K40*N40+K41*N41)/SUM(K40:K41) -> 0
B40: 5.1 | C40: Module delivery | E40: =WORKDAY.INTL(E20,0,1,Data!$C$3:$C$60) -> 46076 | F40: 1 | G40: =WORKDAY.INTL(E40,F40,1,Data!$C$3:$C$60) -> 46077 | I40: =WORKDAY.INTL(I20,0,1,Data!$C$3:$C$60) -> 46081 | J40: 1 | K40: =WORKDAY.INTL(I40,J40,1,Data!$C$3:$C$60) -> 46083 | M40: 0 | N40: =_xlfn.LET( _xlpm.s,VALUE($I40), _xlpm.e,VALUE($K40), IF(OR(_xlpm.s="",_xlpm.e=""),"", IF(_xlpm.e<=_xlpm.s, IF(TODAY()>=_xlpm.e,1,0), MAX(0,MIN(1,(TODAY()-_xlpm.s)/(_xlpm.e-_xlpm.s))))) ) -> 0
B41: 5.2 | C41: Module mounting | E41: =G35 -> 46080 | F41: 9 | G41: =WORKDAY.INTL(E41,F41,1,Data!$C$3:$C$60) -> 46093 | I41: =K35 -> 46086 | J41: 9 | K41: =WORKDAY.INTL(I41,J41,1,Data!$C$3:$C$60) -> 46099 | M41: 0 | N41: =_xlfn.LET( _xlpm.s,VALUE($I41), _xlpm.e,VALUE($K41), IF(OR(_xlpm.s="",_xlpm.e=""),"", IF(_xlpm.e<=_xlpm.s, IF(TODAY()>=_xlpm.e,1,0), MAX(0,MIN(1,(TODAY()-_xlpm.s)/(_xlpm.e-_xlpm.s))))) ) -> 0
B43: 6 | C43: Commissioning | E43: =MIN(E44:E47) -> 46104 | F43: =G43-E43 -> 18 | G43: =MAX(G44:G47) -> 46122 | I43: =MIN(I44:I47) -> 46111 | J43: =K43-I43 -> 16 | K43: =MAX(K44:K47) -> 46127 | M43: =(J44*M44+J45*M45+J46*M46)/SUM(J44:J46) -> 0 | N43: =(K44*N44+K45*N45)/SUM(K44:K45) -> 0
B44: 6.1 | C44: Solar Commissioning | E44: =WORKDAY.INTL(MAX(G22,G32,G39),0,1,Data!$C$3:$C$60) -> 46104 | F44: 1 | G44: =WORKDAY.INTL(E44,F44,1,Data!$C$3:$C$60) -> 46105 | I44: =WORKDAY.INTL(MAX(K22,K32,K39),0,1,Data!$C$3:$C$60) -> 46111 | J44: 1 | K44: =WORKDAY.INTL(I44,J44,1,Data!$C$3:$C$60) -> 46112 | M44: 0 | N44: =_xlfn.LET( _xlpm.s,VALUE($I44), _xlpm.e,VALUE($K44), IF(OR(_xlpm.s="",_xlpm.e=""),"", IF(_xlpm.e<=_xlpm.s, IF(TODAY()>=_xlpm.e,1,0), MAX(0,MIN(1,(TODAY()-_xlpm.s)/(_xlpm.e-_xlpm.s))))) ) -> 0
B45: 6.2 | C45: BESS Commissioning | E45: =WORKDAY.INTL(G44,0,1,Data!$C$3:$C$60)+7 -> 46112 | F45: 1 | G45: =WORKDAY.INTL(E45,F45,1,Data!$C$3:$C$60) -> 46113 | I45: =WORKDAY.INTL(K44,0,1,Data!$C$3:$C$60)+7 -> 46119 | J45: 1 | K45: =WORKDAY.INTL(I45,J45,1,Data!$C$3:$C$60) -> 46120 | M45: 0 | N45: =_xlfn.LET( _xlpm.s,VALUE($I45), _xlpm.e,VALUE($K45), IF(OR(_xlpm.s="",_xlpm.e=""),"", IF(_xlpm.e<=_xlpm.s, IF(TODAY()>=_xlpm.e,1,0), MAX(0,MIN(1,(TODAY()-_xlpm.s)/(_xlpm.e-_xlpm.s))))) ) -> 0
B46: 6.3 | C46: System Performance Monitoring | E46: =WORKDAY.INTL(G45,0,1,Data!$C$3:$C$60) -> 46113 | F46: 5 | G46: =WORKDAY.INTL(E46,F46,1,Data!$C$3:$C$60) -> 46122 | I46: =WORKDAY.INTL(K45,0,1,Data!$C$3:$C$60) -> 46120 | J46: 5 | K46: =WORKDAY.INTL(I46,J46,1,Data!$C$3:$C$60) -> 46127 | M46: 0 | N46: =_xlfn.LET( _xlpm.s,VALUE($I46), _xlpm.e,VALUE($K46), IF(OR(_xlpm.s="",_xlpm.e=""),"", IF(_xlpm.e<=_xlpm.s, IF(TODAY()>=_xlpm.e,1,0), MAX(0,MIN(1,(TODAY()-_xlpm.s)/(_xlpm.e-_xlpm.s))))) ) -> 0
B48: 7 | C48: QA Inspections | E48: =MIN(E49:E51) -> 46113 | F48: =G48-E48 -> 12 | G48: =MAX(G49:G51) -> 46125 | I48: =MIN(I49:I51) -> 46120 | J48: =K48-I48 -> 8 | K48: =MAX(K49:K51) -> 46128 | M48: =(J49*M49+J50*M50)/SUM(J49:J50) -> 0 | N48: =(K49*N49)/SUM(K49) -> 0
B49: 7.1 | C49: Red-Team Inspection | E49: =WORKDAY.INTL(E46,0,1,Data!$C$3:$C$60) -> 46113 | F49: 3 | G49: =WORKDAY.INTL(E49,F49,1,Data!$C$3:$C$60) -> 46120 | I49: =WORKDAY.INTL(I46,0,1,Data!$C$3:$C$60) -> 46120 | J49: 3 | K49: =WORKDAY.INTL(I49,J49,1,Data!$C$3:$C$60) -> 46125 | M49: 0 | N49: =_xlfn.LET( _xlpm.s,VALUE($I49), _xlpm.e,VALUE($K49), IF(OR(_xlpm.s="",_xlpm.e=""),"", IF(_xlpm.e<=_xlpm.s, IF(TODAY()>=_xlpm.e,1,0), MAX(0,MIN(1,(TODAY()-_xlpm.s)/(_xlpm.e-_xlpm.s))))) ) -> 0
B50: 7.2 | C50: Snags completion | E50: =G49 -> 46120 | F50: 3 | G50: =WORKDAY.INTL(E50,F50,1,Data!$C$3:$C$60) -> 46125 | I50: =K49 -> 46125 | J50: 3 | K50: =WORKDAY.INTL(I50,J50,1,Data!$C$3:$C$60) -> 46128 | M50: 0 | N50: =_xlfn.LET( _xlpm.s,VALUE($I50), _xlpm.e,VALUE($K50), IF(OR(_xlpm.s="",_xlpm.e=""),"", IF(_xlpm.e<=_xlpm.s, IF(TODAY()>=_xlpm.e,1,0), MAX(0,MIN(1,(TODAY()-_xlpm.s)/(_xlpm.e-_xlpm.s))))) ) -> 0
B52: 8 | C52: Project Closure | E52: =MIN(E53:E55) -> 46120 | F52: =G52-E52 -> 13 | G52: =MAX(G53:G55) -> 46133 | I52: =MIN(I53:I55) -> 46125 | J52: =K52-I52 -> 11 | K52: =MAX(K53:K55) -> 46136 | M52: =(J53*M53+J54*M54+J55*M55)/SUM(J53:J55) -> 0 | N52: =(K50*N50+K46*N46+K53*N53+K54*N54+K55*N55)/SUM(K50:K55) -> 0
B53: 8.1 | C53: Handover documentation | E53: =WORKDAY.INTL(E50,0,1,Data!$C$3:$C$60) -> 46120 | F53: 4 | G53: =WORKDAY.INTL(E53,F53,1,Data!$C$3:$C$60) -> 46126 | I53: =WORKDAY.INTL(I50,0,1,Data!$C$3:$C$60) -> 46125 | J53: 4 | K53: =WORKDAY.INTL(I53,J53,1,Data!$C$3:$C$60) -> 46129 | M53: 0 | N53: =_xlfn.LET( _xlpm.s,VALUE($I53), _xlpm.e,VALUE($K53), IF(OR(_xlpm.s="",_xlpm.e=""),"", IF(_xlpm.e<=_xlpm.s, IF(TODAY()>=_xlpm.e,1,0), MAX(0,MIN(1,(TODAY()-_xlpm.s)/(_xlpm.e-_xlpm.s))))) ) -> 0
B54: 8.2 | C54: Handover to Client | E54: =WORKDAY.INTL(G53,0,1,Data!$C$3:$C$60) -> 46126 | F54: 1 | G54: =WORKDAY.INTL(E54,F54,1,Data!$C$3:$C$60) -> 46127 | I54: =WORKDAY.INTL(K53,0,1,Data!$C$3:$C$60) -> 46129 | J54: 1 | K54: =WORKDAY.INTL(I54,J54,1,Data!$C$3:$C$60) -> 46132 | M54: 0 | N54: =_xlfn.LET( _xlpm.s,VALUE($I54), _xlpm.e,VALUE($K54), IF(OR(_xlpm.s="",_xlpm.e=""),"", IF(_xlpm.e<=_xlpm.s, IF(TODAY()>=_xlpm.e,1,0), MAX(0,MIN(1,(TODAY()-_xlpm.s)/(_xlpm.e-_xlpm.s))))) ) -> 0
B55: 8.3 | C55: Handover to Matriarch | E55: =WORKDAY.INTL(G53,0,1,Data!$C$3:$C$60) -> 46126 | F55: 5 | G55: =WORKDAY.INTL(E55,F55,1,Data!$C$3:$C$60) -> 46133 | I55: =WORKDAY.INTL(K53,0,1,Data!$C$3:$C$60) -> 46129 | J55: 5 | K55: =WORKDAY.INTL(I55,J55,1,Data!$C$3:$C$60) -> 46136 | M55: 0 | N55: =_xlfn.LET( _xlpm.s,VALUE($I55), _xlpm.e,VALUE($K55), IF(OR(_xlpm.s="",_xlpm.e=""),"", IF(_xlpm.e<=_xlpm.s, IF(TODAY()>=_xlpm.e,1,0), MAX(0,MIN(1,(TODAY()-_xlpm.s)/(_xlpm.e-_xlpm.s))))) ) -> 0

Sheet Revenue Tracking
B2: HIGH LEVEL PROJECT REVENUE TRACKING | T2: 2026 Budget Revenue | U2: 2026 Budget COS | V2: 2026 Actual Revenue | W2: 2026 Actual COS
D3: COSTED | F3: ACTUAL | L3: FINANCIAL REVIEW | N3: TIMELINE REVIEW | T3: =SUMIFS('Expenditure Breakdown'!$U:$U, 'Expenditure Breakdown'!$T:$T, ">"&DATE(2025,8,31), 'Expenditure Breakdown'!$T:$T, "<="&DATE(2026,8,31)) -> 4119606.9 | U3: =SUMIFS('Expenditure Breakdown'!$Q:$Q, 'Expenditure Breakdown'!$T:$T, ">"&DATE(2025,8,31), 'Expenditure Breakdown'!$T:$T, "<="&DATE(2026,8,31)) -> 3300331.8 | V3: =SUMIFS('Expenditure Breakdown'!$U:$U, 'Expenditure Breakdown'!$T:$T, ">"&DATE(2025,8,31), 'Expenditure Breakdown'!$T:$T, "<="&DATE(2026,8,31), 'Expenditure Breakdown'!$S:$S, "<>") -> 0 | W3: =SUMIFS('Expenditure Breakdown'!$Q:$Q, 'Expenditure Breakdown'!$T:$T, ">"&DATE(2025,8,31), 'Expenditure Breakdown'!$T:$T, "<="&DATE(2026,8,31), 'Expenditure Breakdown'!$S:$S, "<>") -> 0
B4: 1 | C4: Planned Revenue | D4: ='Project Plan'!E6 -> 4119606.9 | F4: =F26 -> 5149508.6 | N4: Start Date
B5: 2 | C5: Planned Expenditure | D5: =+'Expenditure Tracking'!F5 -> 3462114.9 | F5: =+'Expenditure Tracking'!H5 -> 3300331.8 | G5: VO PM LIMIT | H5: CURRENT VO Total
B6: 3 | C6: Planned Profit | D6: =+D4-D5 -> 657491.96 | F6: =+F4-F5 -> 1849176.8 | G6: =D6*0.05 -> 32874.598 | H6: =SUMIF('Expenditure Breakdown'!N:N,"*VO*",'Expenditure Breakdown'!Q:Q) -> 0 | N6: End Date - PC
B7: 4 | C7: Planned Margin | D7: =+D6/D4 -> 0.15960066 | F7: =+F6/F4 -> 0.35909772
B10: CONTRACT
B12: No. | C12: PAYMENT MILESTONE | E12: % | F12: VALUE | H12: PLANNED PAYMENT DATE | L12: INVOICE NUMBER | N12: INVOICE RAISED DATE | P12: PAYMENT RECEIVED DATE | R12: MILESTONE NOTES & COMMENTS
B13: 1 | C13: Acceptance and Initial Deposit | E13: 0.4 | F13: =$D$4*E13 -> 1647842.7 | H13: 46062 | P13: 46062 | AO13: ='Change Register'!$Q$14+ 7 -> 7
B14: 2 | C14: Delivery of Panels | E14: 0.2 | F14: =$D$4*E14 -> 823921.37 | H14: ='Project Plan'!E40+7 -> 46083 | P14: ='Project Plan'!I40+7 -> 46088
B15: 3 | C15: Delivery of Inverters | E15: 0.1 | F15: =$D$4*E15 -> 411960.69 | H15: ='Project Plan'!E23+7 -> 46083 | P15: ='Project Plan'!I24+7 -> 46090
B16: 4 | C16: Delivery of BESS | E16: 0.05 | F16: =$D$4*E16 -> 205980.34 | H16: ='Project Plan'!E26+7 -> 46084 | P16: ='Project Plan'!I26+7 -> 46090
B17: 5 | C17: Practical Completion Solar | E17: 0.4 | F17: =$D$4*E17 -> 1647842.7 | H17: ='Project Plan'!E44+7 -> 46111 | P17: ='Project Plan'!I44+7 -> 46118
B18: 6 | C18: Practical Completion BESS | E18: 0.025 | F18: =$D$4*E18 -> 102990.17 | H18: ='Project Plan'!E45+7 -> 46119 | P18: ='Project Plan'!I45+7 -> 46126
B19: 7 | C19: Handover Solar | E19: 0.05 | F19: =$D$4*E19 -> 205980.34 | H19: ='Project Plan'!G54+7 -> 46134 | P19: ='Project Plan'!K52+7 -> 46143
B20: 8 | C20: Handover BESS | E20: 0.025 | F20: =$D$4*E20 -> 102990.17 | H20: =H19 -> 46134 | P20: =P19 -> 46143
B21: 9 | C21: - | E21: 0 | F21: =$D$4*E21 -> 0
B22: 10 | C22: - | E22: 0 | F22: =$D$4*E22 -> 0
B23: 11 | C23: - | E23: 0 | F23: =$D$4*E23 -> 0
B24: 12 | C24: - | E24: 0 | F24: =$D$4*E24 -> 0
E26: =SUM(E13:E24) -> 1.25 | F26: =SUM(F13:F24) -> 5149508.6
B28: KEY: | C28: contains an error (in result or a check has failed)
C29: Red Font - IF TEXT : content not yet confirmed
C30: Red Font - IF NUMBER: Negative value
C31: Anything in yellow is a concern or risk for noting or action
C32: confirmed
C33: [ADD INITIALS: comment for noting in square brackets, use colour or red to draw attention if important]
C34: [RT: When adding rows into sheet, ensure you insert between first and last row of each category]
C35: end of sheet - do not insert information below/beyond this
B45: No. | C45: PAYMENT MILESTONE | E45: % | F45: VALUE
B46: 1 | C46: Deposit - Project commencement | E46: 0.35 | F46: =$F$52*E46 -> 1802328
B47: 2 | C47: Delivery of Panels | E47: 0.3 | F47: =$F$52*E47 -> 1544852.6
B48: 3 | C48: Delivery of Inverters | E48: 0.2 | F48: =$F$52*E48 -> 1029901.7
B49: 4 | C49: Practical Completion | E49: 0.1 | F49: =$F$52*E49 -> 514950.86
B50: 5 | C50: Handover | E50: 0.05 | F50: =$F$52*E50 -> 257475.43
C51: Total | E51: =SUM(E46:E50) -> 1 | F51: =SUM(F46:F50) -> 5149508.6
E52: =SUM(E46:E50) -> 1 | F52: =F26 -> 5149508.6

Sheet Expenditure Tracking
B2: HIGH LEVEL PROJECT EXPENDITURE TRACKING
F4: COSTED | H4: ACTUAL | J4: Difference from Costed
B5: EXPENDITURE | F5: =SUM(F9:F23) -> 3462114.9 | H5: =SUM(H9:H23) -> 3300331.8 | J5: =SUM(J9:J23) -> 161783.11
B7: No. | D7: Item | F7: Costed Expenditure | H7: Actual Expenditure | J7: Saving / Overrun | L7: Comments on variations from planned expenditure
B9: ='Expenditure Breakdown'!L6 -> 1 | D9: ='Expenditure Breakdown'!M6 -> 1. Panels | F9: ='Expenditure Breakdown'!I6 -> 934547.92 | H9: ='Expenditure Breakdown'!X6 -> 987000 | J9: =F9-H9 -> -52452.08
B10: ='Expenditure Breakdown'!L13 -> 2 | D10: ='Expenditure Breakdown'!M13 -> 2. Inverters | F10: ='Expenditure Breakdown'!I13 -> 204150 | H10: ='Expenditure Breakdown'!X13 -> 252150.6 | J10: =F10-H10 -> -48000.6
B11: ='Expenditure Breakdown'!L21 -> 3 | D11: ='Expenditure Breakdown'!M21 -> 3. Mounting Structures | F11: ='Expenditure Breakdown'!I21 -> 188856 | H11: ='Expenditure Breakdown'!X21 -> 111074 | J11: =F11-H11 -> 77782
B12: ='Expenditure Breakdown'!L28 -> 4 | D12: ='Expenditure Breakdown'!M28 -> 4. DC Equipment | F12: ='Expenditure Breakdown'!I28 -> 223700.8 | H12: ='Expenditure Breakdown'!X28 -> 219321.68 | J12: =F12-H12 -> 4379.12
B13: ='Expenditure Breakdown'!L44 -> 5 | D13: ='Expenditure Breakdown'!M44 -> 5. Monitoring | F13: ='Expenditure Breakdown'!I44 -> 174000 | H13: ='Expenditure Breakdown'!X44 -> 156000 | J13: =F13-H13 -> 18000
B14: ='Expenditure Breakdown'!L52 -> 6 | D14: ='Expenditure Breakdown'!M52 -> 6. AC Equipment | F14: ='Expenditure Breakdown'!I52 -> 413396.73 | H14: ='Expenditure Breakdown'!X52 -> 392097.38 | J14: =F14-H14 -> 21299.35
B15: ='Expenditure Breakdown'!L70 -> 7 | D15: ='Expenditure Breakdown'!M70 -> 7.BESS | F15: ='Expenditure Breakdown'!I70 -> 531293.91 | H15: ='Expenditure Breakdown'!X70 -> 446453 | J15: =F15-H15 -> 84840.913
B16: ='Expenditure Breakdown'!L79 -> 8 | D16: ='Expenditure Breakdown'!M79 -> 8. Product Add On | F16: ='Expenditure Breakdown'!I79 -> 245040.6 | H16: ='Expenditure Breakdown'!X79 -> 204500 | J16: =F16-H16 -> 40540.6
B17: ='Expenditure Breakdown'!L95 -> 9 | D17: ='Expenditure Breakdown'!M95 -> 9. AC & DC installation | F17: ='Expenditure Breakdown'!I95 -> 333680 | H17: ='Expenditure Breakdown'!X95 -> 343628 | J17: =F17-H17 -> -9948
B18: ='Expenditure Breakdown'!L108 -> 10 | D18: ='Expenditure Breakdown'!M108 -> 10. Site Logistics | F18: ='Expenditure Breakdown'!I108 -> 49217.111 | H18: ='Expenditure Breakdown'!X108 -> 45434.544 | J18: =F18-H18 -> 3782.5667
B19: ='Expenditure Breakdown'!L124 -> 11 | D19: ='Expenditure Breakdown'!M124 -> 11. Due Dilligence | F19: ='Expenditure Breakdown'!I124 -> 118984 | H19: ='Expenditure Breakdown'!X124 -> 85577.5 | J19: =F19-H19 -> 33406.5
B20: ='Expenditure Breakdown'!L130 -> 12 | D20: ='Expenditure Breakdown'!M130 -> 12. BDP Commission | F20: ='Expenditure Breakdown'!I130 -> 0 | H20: ='Expenditure Breakdown'!X130 -> 0 | J20: =F20-H20 -> 0
B21: ='Expenditure Breakdown'!L133 -> 13 | D21: ='Expenditure Breakdown'!M134 -> 13. Engineering | F21: ='Expenditure Breakdown'!I133 -> 39647.831 | H21: ='Expenditure Breakdown'!X133 -> 51495.086 | J21: =F21-H21 -> -11847.255
B22: ='Expenditure Breakdown'!L140 -> 14 | D22: ='Expenditure Breakdown'!M140 -> 14. General Expenses | F22: ='Expenditure Breakdown'!I140 -> 5600 | H22: ='Expenditure Breakdown'!X140 -> 5600 | J22: =F22-H22 -> 0
B23: ='Expenditure Breakdown'!L153 -> 15 | D23: ='Expenditure Breakdown'!M153 -> 15. Service Add On | F23: ='Expenditure Breakdown'!I153 -> 0 | H23: ='Expenditure Breakdown'!X153 -> 0 | J23: =F23-H23 -> 0
D25: check: | F25: ='Expenditure Breakdown'!I2-'Expenditure Tracking'!F5 -> 0 | G25: =#REF!-G5 -> #REF! | H25: ='Expenditure Breakdown'!X2-H5 -> 0

Sheet Expenditure Breakdown
B2: COSTED EXPENDITURE BREAKDOWN | I2: =SUM(I6:I165) -> 3462114.9 | J2: =SUM(J6:J165) -> 4119606.9 | L2: ACTUAL EXPENDITURE BREAKDOWN | R2: FINANCE ONLY | X2: =SUM(X6:X165) -> 3300331.8
B4: No. | C4: Product / Service | D4: Description of Work | E4: QTY | F4: Rate / Unit | G4: Budget Total | H4: FORECASTED PAYMENT DATE | I4: Total COS | J4: =IF(J2-'Revenue Tracking'!D4>=0, "Total Revenue", "ERROR on REV" ) -> Total Revenue | L4: No. | M4: Product/ Service | N4: Description of Work | O4: QTY | P4: Rate / Unit | Q4: Actual Total | R4: PO NUMBER | S4: INVOICE NUMBER | T4: INVOICE RAISED DATE | U4: REVENUE RECOGNITION AMOUNT | V4: CHECK | W4: FINANCE PAYMENT DATE | X4: Total COS
B6: 1 | C6: Panels | D6: Panels Budget | G6: =D166 -> 934547.92 | H6: ='Project Plan'!E40+60 -> 46136 | I6: =SUM(G6:G11) -> 934547.92 | J6: =F166 -> 1139692.6 | L6: 1 | M6: 1. Panels | N6: Panels TBC - 610W as placeholder | O6: ='Project Plan'!E3*1000/610 -> 688.52459 | P6: =2.35*610 -> 1433.5 | Q6: =O6*P6 -> 987000 | T6: 46081 | U6: =(Q6/$X$6*$J$6) -> 1139692.6 | V6: =J6-SUM(U6:U11) -> 0 | W6: ='Project Plan'!I40+60 -> 46141 | X6: =SUM(Q6:Q11) -> 987000
B7: 1 | D7: Delivery Budget | L7: 1 | M7: 1. Panels | Q7: =O7*P7 -> 0 | U7: =(Q7/$X$6*$J$6) -> 0
B8: 1 | L8: 1 | M8: 1. Panels | T8: =IF(W8>1,EOMONTH(W8,0),"") | U8: =(Q8/$X$6*$J$6) -> 0
B9: 1 | L9: 1 | M9: 1. Panels | T9: =IF(W9>1,EOMONTH(W9,0),"") | U9: =(Q9/$X$6*$J$6) -> 0
B10: 1 | L10: 1 | M10: 1. Panels | T10: =IF(W10>1,EOMONTH(W10,0),"") | U10: =(Q10/$X$6*$J$6) -> 0
B11: 1 | L11: 1 | M11: 1. Panels | T11: =IF(W11>1,EOMONTH(W11,0),"") | U11: =(Q11/$X$6*$J$6) -> 0 | Y11: BUDGET | Z11: Installer Allocation
T12: =IF(W12>1,EOMONTH(W12,0),"") | Y12: AC Equipment | Z12: =G52 -> 413396.73
B13: 2 | C13: Inverters | D13: Inverter Budget - Sungrow 125kW | G13: =D167 -> 204150 | H13: ='Project Plan'!E23+60 -> 46136 | I13: =SUM(G13:G19) -> 204150 | J13: =F167 -> 248963.41 | L13: 2 | M13: 2. Inverters | U13: =(Q13/$X$13*$J$13) -> 0 | V13: =J13-SUM(U13:U19) -> 0 | X13: =SUM(Q13:Q19) -> 252150.6 | Y13: DC Equipment | Z13: =G29 -> 126260.8
B14: 2 | L14: 2 | M14: 2. Inverters | N14: Sungrow 125kW | O14: 3 | P14: 68870 | Q14: =O14*P14 -> 206610 | T14: 46081 | U14: =(Q14/$X$13*$J$13) -> 203998.45 | W14: =T14+30 -> 46111 | Y14: AC Labour | Z14: =G95 -> 104920
B15: 2 | L15: 2 | M15: 2. Inverters | N15: Sungrow Wifi Comunication Module For Battery Inverter | Q15: 3900 | T15: =IF(W15>1,EOMONTH(W15,0),"") -> 46112 | U15: =(Q15/$X$13*$J$13) -> 3850.704 | W15: =W14 -> 46111 | Y15: DC Labour | Z15: =G96 -> 228760
B16: 2 | L16: 2 | M16: 2. Inverters | T16: =IF(W16>1,EOMONTH(W16,0),"") | U16: =(Q16/$X$13*$J$13) -> 0 | Y16: Offloading | Z16: =G108 -> 8500
B17: 2 | L17: 2 | M17: 2. Inverters | N17: Sungrow warranty extension to 10 years on the 125kW string inverter and the 25kW hybrid inverter | Q17: 41640.6 | T17: =IF(W17>1,EOMONTH(W17,0),"") -> 46112 | U17: =(Q17/$X$13*$J$13) -> 41114.263 | W17: =W15 -> 46111 | Y17: Scaffolding | Z17: =G109 -> 15072.667
B18: 2 | L18: 2 | M18: 2. Inverters | T18: =IF(W18>1,EOMONTH(W18,0),"") | U18: =(Q18/$X$13*$J$13) -> 0 | Y18: Storage | Z18: =G111 -> 1644.4444
B19: 2 | L19: 2 | M19: 2. Inverters | T19: =IF(W19>1,EOMONTH(W19,0),"") | U19: =(Q19/$X$13*$J$13) -> 0 | Y19: Telehandler | Z19: 0
T20: =IF(W20>1,EOMONTH(W20,0),"") | Y20: Trenching | Z20: 0
B21: 3 | C21: Mounting Structures | D21: Structure Budget | G21: =D168 -> 188856 | H21: ='Project Plan'!E34+30 -> 46106 | I21: =SUM(G21:G26) -> 188856 | J21: =F168 -> 230312.2 | L21: 3 | M21: 3. Mounting Structures | N21: Schletter Structure | Q21: 111074 | T21: 46081 | U21: =(Q21/$X$21*$J$21) -> 230312.2 | V21: =J21-SUM(U21:U26) -> 0 | W21: =T21+30 -> 46111 | X21: =SUM(Q21:Q26) -> 111074 | Y21: Other | Z21: 0
B22: 3 | L22: 3 | M22: 3. Mounting Structures | T22: =IF(W22>1,EOMONTH(W22,0),"") | U22: =(Q22/$X$21*$J$21) -> 0 | Y22: Total | Z22: =SUM(Z12:Z21) -> 898554.64
B23: 3 | L23: 3 | M23: 3. Mounting Structures | T23: =IF(W23>1,EOMONTH(W23,0),"") | U23: =(Q23/$X$21*$J$21) -> 0 | Y23: Less 15% | Z23: =+Z22*0.85 -> 763771.44
B24: 3 | L24: 3 | M24: 3. Mounting Structures | T24: =IF(W24>1,EOMONTH(W24,0),"") | U24: =(Q24/$X$21*$J$21) -> 0 | Y24: R/Wp | Z24: =Z23/'Project Plan'!$E$3/1000 -> 1.8185034
B25: 3 | L25: 3 | M25: 3. Mounting Structures | T25: =IF(W25>1,EOMONTH(W25,0),"") | U25: =(Q25/$X$21*$J$21) -> 0
B26: 3 | L26: 3 | M26: 3. Mounting Structures | T26: =IF(W26>1,EOMONTH(W26,0),"") | U26: =(Q26/$X$21*$J$21) -> 0 | Y26: ACTUAL | Z26: Installer Price
T27: =IF(W27>1,EOMONTH(W27,0),"") | Y27: =Y12 -> AC Equipment | Z27: =121265.426086957+40000 -> 161265.43
B28: 4 | C28: DC Equipment | D28: DC Cable Budget | E28: 6960 | G28: 97440 | H28: ='Project Plan'!E36+60 -> 46136 | I28: =SUM(G28:G42) -> 223700.8 | J28: =F169 -> 272805.85 | L28: 4 | M28: 4. DC Equipment | N28: DC Cable | O28: 8000 | P28: 14 | Q28: =O28*P28 -> 112000 | T28: 46081 | U28: =(Q28/$X$28*$J$28) -> 139312.52 | V28: =J28-SUM(U28:U42) -> 0 | W28: =T28+30 -> 46111 | X28: =SUM(Q28:Q42) -> 219321.68 | Y28: =Y13 -> DC Equipment | Z28: =Z13*0.85 -> 107321.68
B29: 4 | D29: DC Equipment Budget | G29: =D169-G28 -> 126260.8 | H29: ='Project Plan'!G32 -> 46099 | L29: 4 | M29: 4. DC Equipment | T29: =IF(W29>1,EOMONTH(W29,0),"") | U29: =(Q29/$X$28*$J$28) -> 0 | Y29: =Y14 -> AC Labour | Z29: =Z14*0.85 -> 89182
B30: 4 | L30: 4 | M30: 4. DC Equipment | T30: =IF(W30>1,EOMONTH(W30,0),"") | U30: =(Q30/$X$28*$J$28) -> 0 | Y30: =Y15 -> DC Labour | Z30: =Z15*0.85 -> 194446
B31: 4 | L31: 4 | M31: 4. DC Equipment | T31: =IF(W31>1,EOMONTH(W31,0),"") | U31: =(Q31/$X$28*$J$28) -> 0 | Y31: Lifelines | Z31: =Z16*0.85 -> 7225
B32: 4 | L32: 4 | M32: 4. DC Equipment | N32: Project Kick Off | O32: =Z28 -> 107321.68 | P32: 0.1 | Q32: =$O$32*P32 -> 10732.168 | T32: =T96 -> 46081 | U32: =(Q32/$X$28*$J$28) -> 13349.334 | W32: =W96 -> 46081 | Y32: Forklift | Z32: =Z17*0.85 -> 12811.767
B33: 4 | L33: 4 | M33: 4. DC Equipment | N33: Site Establishment | P33: 0.15 | Q33: =$O$32*P33 -> 16098.252 | T33: =T97 -> 46081 | U33: =(Q33/$X$28*$J$28) -> 20024 | W33: =W97 -> 46081 | Y33: Geda | Z33: =Z18*0.85 -> 1397.7778
B34: 4 | L34: 4 | M34: 4. DC Equipment | N34: AC Installation Complete | P34: 0.2 | Q34: =$O$32*P34 -> 21464.336 | T34: =T98 -> 46142 | U34: =(Q34/$X$28*$J$28) -> 26698.667 | W34: =W98 -> 46118 | Y34: BESS Installation | Z34: 60000
B35: 4 | L35: 4 | M35: 4. DC Equipment | N35: DC Installation Complete | P35: 0.25 | Q35: =$O$32*P35 -> 26830.42 | T35: =T99 -> 46112 | U35: =(Q35/$X$28*$J$28) -> 33373.334 | W35: =W99 -> 46112 | Y35: Trenching | Z35: 0
B36: 4 | L36: 4 | M36: 4. DC Equipment | N36: Commissioning Complete | P36: 0.1 | Q36: =$O$32*P36 -> 10732.168 | T36: =T100 -> 46142 | U36: =(Q36/$X$28*$J$28) -> 13349.334 | W36: =W100 -> 46134 | Y36: Other | Z36: 0
B37: 4 | L37: 4 | M37: 4. DC Equipment | N37: Site De-establisment | P37: 0.1 | Q37: =$O$32*P37 -> 10732.168 | T37: =T101 -> 46142 | U37: =(Q37/$X$28*$J$28) -> 13349.334 | W37: =W101 -> 46135 | Y37: Other | Z37: 0
B38: 4 | L38: 4 | M38: 4. DC Equipment | N38: Handover Document Complete | P38: 0.05 | Q38: =$O$32*P38 -> 5366.084 | T38: =T102 -> 46142 | U38: =(Q38/$X$28*$J$28) -> 6674.6668 | W38: =W102 -> 46135 | Y38: Total | Z38: =SUM(Z27:Z37) -> 633649.65
B39: 4 | L39: 4 | M39: 4. DC Equipment | N39: End of Defects Period | P39: 0.05 | Q39: =$O$32*P39 -> 5366.084 | T39: =T103 -> 46173 | U39: =(Q39/$X$28*$J$28) -> 6674.6668 | W39: =W103 -> 46158 | Y39: R/Wp | Z39: =Z38/'Project Plan'!$E$3/1000 -> 1.5086896
B40: 4 | L40: 4 | M40: 4. DC Equipment | T40: =IF(W40>1,EOMONTH(W40,0),"") | U40: =(Q40/$X$28*$J$28) -> 0
B41: 4 | L41: 4 | M41: 4. DC Equipment | T41: =IF(W41>1,EOMONTH(W41,0),"") | U41: =(Q41/$X$28*$J$28) -> 0
B42: 4 | L42: 4 | M42: 4. DC Equipment | T42: =IF(W42>1,EOMONTH(W42,0),"") | U42: =(Q42/$X$28*$J$28) -> 0
T43: =IF(W43>1,EOMONTH(W43,0),"")
B44: 5 | C44: Monitoring | D44: Smartlogger 3000 | G44: 26000 | H44: =H52 -> 46122 | I44: =D171 -> 174000 | J44: =F171 -> 212195.12 | L44: 5 | M44: 5. Monitoring | U44: =(Q44/$X$44*$J$44) -> 0 | V44: =J44-SUM(U44:U50) -> 0 | X44: =SUM(Q44:Q50) -> 156000
B45: 5 | D45: Comms DB | G45: 8000 | H45: =H44 -> 46122 | L45: 5 | M45: 5. Monitoring | N45: Comms DB | Q45: 26000 | T45: =IF(W45>1,EOMONTH(W45,0),"") -> 46081 | U45: =(Q45/$X$44*$J$44) -> 35365.854 | W45: 46081
B46: 5 | D46: Revenue Grade Meter | G46: 15000 | H46: =H45 -> 46122 | L46: 5 | M46: 5. Monitoring | N46: Revenue Grade Meter | Q46: 15000 | T46: =IF(W46>1,EOMONTH(W46,0),"") -> 46081 | U46: =(Q46/$X$44*$J$44) -> 20403.377 | W46: =W45 -> 46081
B47: 5 | D47: Generator Integration | G47: 125000 | H47: =H46 -> 46122 | L47: 5 | M47: 5. Monitoring | N47: APEX Controller | Q47: 90000 | T47: 46081 | U47: =(Q47/$X$44*$J$44) -> 122420.26 | W47: =T47+30 -> 46111
B48: 5 | L48: 5 | M48: 5. Monitoring | N48: Sungrow Wifi Comunication Module For Battery Inverter | Q48: 25000 | T48: 46081 | U48: =(Q48/$X$44*$J$44) -> 34005.629 | W48: =T48+30 -> 46111
B49: 5 | L49: 5 | M49: 5. Monitoring | T49: =IF(W49>1,EOMONTH(W49,0),"") | U49: =(Q49/$X$44*$J$44) -> 0
B50: 5 | L50: 5 | M50: 5. Monitoring | T50: =IF(W50>1,EOMONTH(W50,0),"") | U50: =(Q50/$X$44*$J$44) -> 0
T51: =IF(W51>1,EOMONTH(W51,0),"")
B52: 6 | C52: AC Equipment | D52: AC Equipment Budget | G52: =D170 -> 413396.73 | H52: ='Project Plan'!G25+30 -> 46122 | I52: =SUM(G52:G68) -> 413396.73 | J52: =F170 -> 504142.35 | L52: 6 | M52: 6. AC Equipment | T52: =IF(W52>1,EOMONTH(W52,0),"") | U52: =(Q52/$X$52*$J$52) -> 0 | V52: =J52-SUM(U52:U68) -> 0 | X52: =SUM(Q52:Q68) -> 392097.38
B53: 6 | L53: 6 | M53: 6. AC Equipment | N53: PVDB | Q53: 190831.95 | T53: 46081 | U53: =(Q53/$X$52*$J$52) -> 245363.71 | W53: =T53+30 -> 46111
B54: 6 | L54: 6 | M54: 6. AC Equipment | T54: =IF(W54>1,EOMONTH(W54,0),"") | U54: =(Q54/$X$52*$J$52) -> 0
B55: 6 | L55: 6 | M55: 6. AC Equipment | N55: Auto Change over Switch | Q55: 40000 | T55: =T53 -> 46081 | U55: =(Q55/$X$52*$J$52) -> 51430.321 | W55: =W53 -> 46111
B56: 6 | L56: 6 | M56: 6. AC Equipment | T56: =IF(W56>1,EOMONTH(W56,0),"") | U56: =(Q56/$X$52*$J$52) -> 0
B57: 6 | L57: 6 | M57: 6. AC Equipment | T57: =IF(W57>1,EOMONTH(W57,0),"") | U57: =(Q57/$X$52*$J$52) -> 0
B58: 6 | L58: 6 | M58: 6. AC Equipment | N58: Project Kick Off | O58: =Z27 -> 161265.43 | P58: 0.1 | Q58: =$O$58*P58 -> 16126.543 | T58: =T96 -> 46081 | U58: =(Q58/$X$52*$J$52) -> 20734.832 | W58: =W96 -> 46081
B59: 6 | L59: 6 | M59: 6. AC Equipment | N59: Site Establishment | P59: 0.15 | Q59: =$O$58*P59 -> 24189.814 | T59: =IF(W59>1,EOMONTH(W59,0),"") -> 46081 | U59: =(Q59/$X$52*$J$52) -> 31102.247 | W59: =W97 -> 46081
B60: 6 | L60: 6 | M60: 6. AC Equipment | N60: AC Installation Complete | P60: 0.2 | Q60: =$O$58*P60 -> 32253.085 | T60: =IF(W60>1,EOMONTH(W60,0),"") -> 46142 | U60: =(Q60/$X$52*$J$52) -> 41469.663 | W60: =W98 -> 46118
B61: 6 | L61: 6 | M61: 6. AC Equipment | N61: DC Installation Complete | P61: 0.25 | Q61: =$O$58*P61 -> 40316.357 | T61: =IF(W61>1,EOMONTH(W61,0),"") -> 46112 | U61: =(Q61/$X$52*$J$52) -> 51837.079 | W61: =W99 -> 46112
B62: 6 | L62: 6 | M62: 6. AC Equipment | N62: Commissioning Complete | P62: 0.1 | Q62: =$O$58*P62 -> 16126.543 | T62: =IF(W62>1,EOMONTH(W62,0),"") -> 46142 | U62: =(Q62/$X$52*$J$52) -> 20734.832 | W62: =W100 -> 46134
B63: 6 | L63: 6 | M63: 6. AC Equipment | N63: Site De-establisment | P63: 0.1 | Q63: =$O$58*P63 -> 16126.543 | T63: =IF(W63>1,EOMONTH(W63,0),"") -> 46142 | U63: =(Q63/$X$52*$J$52) -> 20734.832 | W63: =W101 -> 46135
B64: 6 | L64: 6 | M64: 6. AC Equipment | N64: Handover Document Complete | P64: 0.05 | Q64: =$O$58*P64 -> 8063.2713 | T64: =IF(W64>1,EOMONTH(W64,0),"") -> 46142 | U64: =(Q64/$X$52*$J$52) -> 10367.416 | W64: =W102 -> 46135
B65: 6 | L65: 6 | M65: 6. AC Equipment | N65: End of Defects Period | P65: 0.05 | Q65: =$O$58*P65 -> 8063.2713 | T65: =IF(W65>1,EOMONTH(W65,0),"") -> 46173 | U65: =(Q65/$X$52*$J$52) -> 10367.416 | W65: =W103 -> 46158
B66: 6 | L66: 6 | M66: 6. AC Equipment | T66: =IF(W66>1,EOMONTH(W66,0),"") | U66: =(Q66/$X$52*$J$52) -> 0
B67: 6 | L67: 6 | M67: 6. AC Equipment | T67: =IF(W67>1,EOMONTH(W67,0),"") | U67: =(Q67/$X$52*$J$52) -> 0
B68: 6 | L68: 6 | M68: 6. AC Equipment | T68: =IF(W68>1,EOMONTH(W68,0),"") | U68: =(Q68/$X$52*$J$52) -> 0
T69: =IF(W69>1,EOMONTH(W69,0),"")
B70: 7 | C70: BESS | D70: Sungrow 50kW with104kWh | G70: 372400 | H70: 46112 | I70: =SUM(G70:G77) -> 531293.91 | J70: 603743.08 | L70: 7 | M70: 7.BESS | N70: Sungrow 50kW with104kWh | Q70: =372400*1.15 -> 428260 | T70: 46081 | U70: =(Q70/$X$70*$J$70) -> 579140.5 | V70: =J70-SUM(U70:U77) -> 0 | W70: =T70+30 -> 46111 | X70: =SUM(Q70:Q77) -> 446453
B71: 7 | D71: Sungrow SBH Battery Parallel box + Acessory Box | G71: 15820 | H71: 46112 | L71: 7 | M71: 7.BESS | N71: Sungrow SBH Battery Parallel box + Acessory Box | Q71: =15820*1.15 -> 18193 | T71: 46081 | U71: =(Q71/$X$70*$J$70) -> 24602.585 | W71: =T71+30 -> 46111
B72: 7 | D72: Ps and Gs | G72: 15000 | H72: 46112 | L72: 7 | M72: 7.BESS | T72: =IF(W72>1,EOMONTH(W72,0),"") | U72: =(Q72/$X$70*$J$70) -> 0
B73: 7 | D73: Installation | G73: 40000 | H73: 46112 | L73: 7 | M73: 7.BESS | T73: =IF(W73>1,EOMONTH(W73,0),"") | U73: =(Q73/$X$70*$J$70) -> 0
B74: 7 | D74: AC+DC Equipment | G74: 60000 | H74: 46112 | L74: 7 | M74: 7.BESS | T74: =IF(W74>1,EOMONTH(W74,0),"") | U74: =(Q74/$X$70*$J$70) -> 0
B75: 7 | D75: Inverter Cables | G75: 7500 | H75: 46112 | L75: 7 | M75: 7.BESS | T75: =IF(W75>1,EOMONTH(W75,0),"") | U75: =(Q75/$X$70*$J$70) -> 0
B76: 7 | D76: Main Gateway Cable (Tie-In) | G76: 20573.913 | H76: 46142 | L76: 7 | M76: 7.BESS | T76: =IF(W76>1,EOMONTH(W76,0),"") | U76: =(Q76/$X$70*$J$70) -> 0
B77: 7 | L77: 7 | M77: 7.BESS | T77: =IF(W77>1,EOMONTH(W77,0),"") | U77: =(Q77/$X$70*$J$70) -> 0
T78: =IF(W78>1,EOMONTH(W78,0),"")
B79: 8 | C79: Product Add On | D79: Walkways | G79: 82500 | H79: 46081 | I79: =SUM(G79:G93) -> 245040.6 | J79: =151829.268292683+147000.731707317 -> 298830 | L79: 8 | M79: 8. Product Add On | N79: Walkways | O79: 82500 | P79: 1 | Q79: =O79*P79 -> 82500 | T79: 46081 | U79: =(Q79/$X$79*$J$79) -> 120554.89 | V79: =J79-SUM(U79:U93) -> 0 | W79: =T79-14 -> 46067 | X79: =SUM(Q79:Q93) -> 204500
B80: 8 | D80: Water Points | G80: 12000 | H80: 46112 | L80: 8 | M80: 8. Product Add On | U80: =(Q80/$X$79*$J$79) -> 0
L81: 8 | M81: 8. Product Add On | N81: Water Points - Deposit | O81: 12000 | P81: 0.5 | Q81: =O81*P81 -> 6000 | T81: 46112 | U81: =(Q81/$X$79*$J$79) -> 8767.6284 | W81: =T81-14 -> 46098
L82: 8 | M82: 8. Product Add On | N82: Water Points - Balance | P82: 0.5 | Q82: =O81*P82 -> 6000 | T82: 46112 | U82: =(Q82/$X$79*$J$79) -> 8767.6284 | W82: 46112
B83: 8 | D83: Cat Ladders | G83: 30000 | H83: 46112 | L83: 8 | M83: 8. Product Add On | N83: Cat Ladders - Deposit | O83: 55000 | P83: 0.5 | Q83: =O83*P83 -> 27500 | T83: 46112 | U83: =(Q83/$X$79*$J$79) -> 40184.963 | W83: =T83-14 -> 46098
L84: 8 | M84: 8. Product Add On | N84: Cat Ladders - Balance | P84: 0.5 | Q84: =O83*P84 -> 27500 | T84: 46112 | U84: =(Q84/$X$79*$J$79) -> 40184.963 | W84: 46112
B85: 8 | D85: Aircon for the inverter room x 2 (battery room + Grid-tied room) | G85: 35000 | H85: 46112 | L85: 8 | M85: 8. Product Add On | N85: Aircon for the inverter room x 2 (battery room + Grid-tied room) - Deposit | O85: 55000 | P85: 0.5 | Q85: =O85*P85 -> 27500 | T85: 46112 | U85: =(Q85/$X$79*$J$79) -> 40184.963 | W85: =T85-14 -> 46098
L86: 8 | M86: 8. Product Add On | N86: Aircon for the inverter room x 2 (battery room + Grid-tied room) - Balance | P86: 0.5 | Q86: =O85*P86 -> 27500 | T86: 46112 | U86: =(Q86/$X$79*$J$79) -> 40184.963 | W86: 46112
B87: 8 | D87: Automatic change over switch | G87: 40000 | H87: 46112 | L87: 8 | M87: 8. Product Add On | T87: =IF(W87>1,EOMONTH(W87,0),"") | U87: =(Q87/$X$79*$J$79) -> 0
L88: 8 | M88: 8. Product Add On | U88: =(Q88/$X$79*$J$79) -> 0
B89: 8 | D89: Sungrow Wifi Comunication Module For Battery Inverter | G89: 3900 | H89: 46112 | L89: 8 | M89: 8. Product Add On | U89: =(Q89/$X$79*$J$79) -> 0
L90: 8 | M90: 8. Product Add On | U90: =(Q90/$X$79*$J$79) -> 0
B91: 8 | D91: Sungrow warranty extension to 10 years on the 125kW string inverter and the 25kW hybrid inverter. | G91: 41640.6 | H91: 46142 | L91: 8 | M91: 8. Product Add On | T91: =IF(W91>1,EOMONTH(W91,0),"") | U91: =(Q91/$X$79*$J$79) -> 0
B92: 8 | L92: 8 | M92: 8. Product Add On | T92: =IF(W92>1,EOMONTH(W92,0),"") | U92: =(Q92/$X$79*$J$79) -> 0
B93: 8 | L93: 8 | M93: 8. Product Add On | T93: =IF(W93>1,EOMONTH(W93,0),"") | U93: =(Q93/$X$79*$J$79) -> 0
K94: Only services to be capture below, products above | T94: =IF(W94>1,EOMONTH(W94,0),"")
B95: 9 | C95: AC & DC Installation | D95: AC Installation Budget | G95: =D179 -> 104920 | H95: ='Project Plan'!G22+7 -> 46111 | I95: =SUM(G95:G106) -> 333680 | J95: =F179+F180 -> 370755.56 | L95: 9 | M95: 9. AC & DC installation | T95: =IF(W95>1,EOMONTH(W95,0),"") | U95: =(Q95/$X$95*$J$95) -> 0 | V95: =J95-SUM(U95:U106) -> 0 | X95: =SUM(Q95:Q106) -> 343628
B96: 9 | D96: DC Installation Budget | G96: =D180 -> 228760 | H96: ='Project Plan'!G32+7 -> 46106 | L96: 9 | M96: 9. AC & DC installation | N96: Project Kick Off | O96: =Z30+Z29+Z34 -> 343628 | P96: 0.1 | Q96: =$O$96*P96 -> 34362.8 | T96: =IF(W96>1,EOMONTH(W96,0),"") -> 46081 | U96: =(Q96/$X$95*$J$95) -> 37075.556 | W96: ='Project Plan'!I20 -> 46081
B97: 9 | L97: 9 | M97: 9. AC & DC installation | N97: Site Establishment | P97: 0.15 | Q97: =$O$96*P97 -> 51544.2 | T97: =IF(W97>1,EOMONTH(W97,0),"") -> 46081 | U97: =(Q97/$X$95*$J$95) -> 55613.333 | W97: ='Project Plan'!I20 -> 46081
B98: 9 | L98: 9 | M98: 9. AC & DC installation | N98: AC Installation Complete | P98: 0.2 | Q98: =$O$96*P98 -> 68725.6 | T98: =IF(W98>1,EOMONTH(W98,0),"") -> 46142 | U98: =(Q98/$X$95*$J$95) -> 74151.111 | W98: ='Project Plan'!K22+7 -> 46118
B99: 9 | L99: 9 | M99: 9. AC & DC installation | N99: DC Installation Complete | P99: 0.25 | Q99: =$O$96*P99 -> 85907 | T99: =IF(W99>1,EOMONTH(W99,0),"") -> 46112 | U99: =(Q99/$X$95*$J$95) -> 92688.889 | W99: ='Project Plan'!K32+7 -> 46112
B100: 9 | L100: 9 | M100: 9. AC & DC installation | N100: Commissioning Complete | P100: 0.1 | Q100: =$O$96*P100 -> 34362.8 | T100: =IF(W100>1,EOMONTH(W100,0),"") -> 46142 | U100: =(Q100/$X$95*$J$95) -> 37075.556 | W100: ='Project Plan'!K43+7 -> 46134
B101: 9 | L101: 9 | M101: 9. AC & DC installation | N101: Site De-establisment | P101: 0.1 | Q101: =$O$96*P101 -> 34362.8 | T101: =IF(W101>1,EOMONTH(W101,0),"") -> 46142 | U101: =(Q101/$X$95*$J$95) -> 37075.556 | W101: ='Project Plan'!K50+7 -> 46135
B102: 9 | L102: 9 | M102: 9. AC & DC installation | N102: Handover Document Complete | P102: 0.05 | Q102: =$O$96*P102 -> 17181.4 | T102: =IF(W102>1,EOMONTH(W102,0),"") -> 46142 | U102: =(Q102/$X$95*$J$95) -> 18537.778 | W102: ='Project Plan'!K50+7 -> 46135
B103: 9 | L103: 9 | M103: 9. AC & DC installation | N103: End of Defects Period | P103: 0.05 | Q103: =$O$96*P103 -> 17181.4 | T103: =IF(W103>1,EOMONTH(W103,0),"") -> 46173 | U103: =(Q103/$X$95*$J$95) -> 18537.778 | W103: ='Project Plan'!K50+30 -> 46158
...

Sheet Cashflow
D1: [RT: Double Check the first date is always a MONDAY] | F1: 46034 | G1: =F1+7 -> 46041 | H1: =G1+7 -> 46048 | I1: =H1+7 -> 46055 | J1: =I1+7 -> 46062 | K1: =J1+7 -> 46069 | L1: =K1+7 -> 46076 | M1: =L1+7 -> 46083 | N1: =M1+7 -> 46090 | ... KF1: =KE1+7 -> 48036
A2: PLANNED | C2: CHECK | D2: CHECK
B3: Planned Revenue | C3: ='Revenue Tracking'!D4 -> 4119606.9 | D3: =SUM(F3:KF3) -> 5149508.6 | F3: =SUMIFS('Revenue Tracking'!$F$13:$F$24, 'Revenue Tracking'!$H$13:$H$24, ">="&F1,'Revenue Tracking'!$H$13:$H$24, "<"&G1) -> 0 | G3: =SUMIFS('Revenue Tracking'!$F$13:$F$24, 'Revenue Tracking'!$H$13:$H$24, ">="&G1,'Revenue Tracking'!$H$13:$H$24, "<"&H1) -> 0 | H3: =SUMIFS('Revenue Tracking'!$F$13:$F$24, 'Revenue Tracking'!$H$13:$H$24, ">="&H1,'Revenue Tracking'!$H$13:$H$24, "<"&I1) -> 0 | I3: =SUMIFS('Revenue Tracking'!$F$13:$F$24, 'Revenue Tracking'!$H$13:$H$24, ">="&I1,'Revenue Tracking'!$H$13:$H$24, "<"&J1) -> 0 | J3: =SUMIFS('Revenue Tracking'!$F$13:$F$24, 'Revenue Tracking'!$H$13:$H$24, ">="&J1,'Revenue Tracking'!$H$13:$H$24, "<"&K1) -> 1647842.7 | K3: =SUMIFS('Revenue Tracking'!$F$13:$F$24, 'Revenue Tracking'!$H$13:$H$24, ">="&K1,'Revenue Tracking'!$H$13:$H$24, "<"&L1) -> 0 | L3: =SUMIFS('Revenue Tracking'!$F$13:$F$24, 'Revenue Tracking'!$H$13:$H$24, ">="&L1,'Revenue Tracking'!$H$13:$H$24, "<"&M1) -> 0 | M3: =SUMIFS('Revenue Tracking'!$F$13:$F$24, 'Revenue Tracking'!$H$13:$H$24, ">="&M1,'Revenue Tracking'!$H$13:$H$24, "<"&N1) -> 1441862.4 | ... KE3: =SUMIFS('Revenue Tracking'!$F$13:$F$24, 'Revenue Tracking'!$H$13:$H$24, ">="&KE1,'Revenue Tracking'!$H$13:$H$24, "<"&KF1) -> 0 | KF3: =SUMIFS('Revenue Tracking'!$F$13:$F$24, 'Revenue Tracking'!$H$13:$H$24, ">="&KF1,'Revenue Tracking'!$H$13:$H$24, "<"&#REF!) -> 0
B4: Planned Revenue - Cumulative | F4: =F3 -> 0 | G4: =F4+G3 -> 0 | H4: =G4+H3 -> 0 | I4: =H4+I3 -> 0 | J4: =I4+J3 -> 1647842.7 | K4: =J4+K3 -> 1647842.7 | L4: =K4+L3 -> 1647842.7 | M4: =L4+M3 -> 3089705.1 | N4: =M4+N3 -> 3089705.1 | ... KF4: =KE4+KF3 -> 5149508.6
B5: Planned Expenditure | C5: ='Revenue Tracking'!D5 -> 3462114.9 | D5: =SUM(F5:KF5) -> 3462114.9 | F5: =SUMIFS('Expenditure Breakdown'!$G$6:$G$172, 'Expenditure Breakdown'!$H$6:$H$172, ">="&F1,'Expenditure Breakdown'!$H$6:$H$172, "<"&G1) -> 0 | G5: =SUMIFS('Expenditure Breakdown'!$G$6:$G$172, 'Expenditure Breakdown'!$H$6:$H$172, ">="&G1,'Expenditure Breakdown'!$H$6:$H$172, "<"&H1) -> 0 | H5: =SUMIFS('Expenditure Breakdown'!$G$6:$G$172, 'Expenditure Breakdown'!$H$6:$H$172, ">="&H1,'Expenditure Breakdown'!$H$6:$H$172, "<"&I1) -> 0 | I5: =SUMIFS('Expenditure Breakdown'!$G$6:$G$172, 'Expenditure Breakdown'!$H$6:$H$172, ">="&I1,'Expenditure Breakdown'!$H$6:$H$172, "<"&J1) -> 0 | J5: =SUMIFS('Expenditure Breakdown'!$G$6:$G$172, 'Expenditure Breakdown'!$H$6:$H$172, ">="&J1,'Expenditure Breakdown'!$H$6:$H$172, "<"&K1) -> 0 | K5: =SUMIFS('Expenditure Breakdown'!$G$6:$G$172, 'Expenditure Breakdown'!$H$6:$H$172, ">="&K1,'Expenditure Breakdown'!$H$6:$H$172, "<"&L1) -> 0 | L5: =SUMIFS('Expenditure Breakdown'!$G$6:$G$172, 'Expenditure Breakdown'!$H$6:$H$172, ">="&L1,'Expenditure Breakdown'!$H$6:$H$172, "<"&M1) -> 89500 | M5: =SUMIFS('Expenditure Breakdown'!$G$6:$G$172, 'Expenditure Breakdown'!$H$6:$H$172, ">="&M1,'Expenditure Breakdown'!$H$6:$H$172, "<"&N1) -> 0 | ... KE5: =SUMIFS('Expenditure Breakdown'!$G$6:$G$172, 'Expenditure Breakdown'!$H$6:$H$172, ">="&KE1,'Expenditure Breakdown'!$H$6:$H$172, "<"&KF1) -> 0 | KF5: =SUMIFS('Expenditure Breakdown'!$G$6:$G$172, 'Expenditure Breakdown'!$H$6:$H$172, ">="&KF1,'Expenditure Breakdown'!$H$6:$H$172, "<"&#REF!) -> 0
B6: Planned Expenditure - Cumulative | F6: =F5 -> 0 | G6: =F6+G5 -> 0 | H6: =G6+H5 -> 0 | I6: =H6+I5 -> 0 | J6: =I6+J5 -> 0 | K6: =J6+K5 -> 0 | L6: =K6+L5 -> 89500 | M6: =L6+M5 -> 89500 | N6: =M6+N5 -> 89500 | ... KF6: =KE6+KF5 -> 3462114.9
B7: PLANNED CashFlow | F7: =F4-F6 -> 0 | G7: =G4-G6 -> 0 | H7: =H4-H6 -> 0 | I7: =I4-I6 -> 0 | J7: =J4-J6 -> 1647842.7 | K7: =K4-K6 -> 1647842.7 | L7: =L4-L6 -> 1558342.7 | M7: =M4-M6 -> 3000205.1 | ... KF7: =KF4-KF6 -> 1687393.7
A8: ACTUAL | C8: CHECK | D8: CHECK
B9: Actual + Planned Revenue | C9: ='Revenue Tracking'!F4 -> 5149508.6 | D9: =SUM(F9:KF9) -> 5149508.6 | F9: =SUMIFS('Revenue Tracking'!$F$13:$F$24, 'Revenue Tracking'!$P$13:$P$24, ">="&F1,'Revenue Tracking'!$P$13:$P$24, "<"&G1) -> 0 | G9: =SUMIFS('Revenue Tracking'!$F$13:$F$24, 'Revenue Tracking'!$P$13:$P$24, ">="&G1,'Revenue Tracking'!$P$13:$P$24, "<"&H1) -> 0 | H9: =SUMIFS('Revenue Tracking'!$F$13:$F$24, 'Revenue Tracking'!$P$13:$P$24, ">="&H1,'Revenue Tracking'!$P$13:$P$24, "<"&I1) -> 0 | I9: =SUMIFS('Revenue Tracking'!$F$13:$F$24, 'Revenue Tracking'!$P$13:$P$24, ">="&I1,'Revenue Tracking'!$P$13:$P$24, "<"&J1) -> 0 | J9: =SUMIFS('Revenue Tracking'!$F$13:$F$24, 'Revenue Tracking'!$P$13:$P$24, ">="&J1,'Revenue Tracking'!$P$13:$P$24, "<"&K1) -> 1647842.7 | K9: =SUMIFS('Revenue Tracking'!$F$13:$F$24, 'Revenue Tracking'!$P$13:$P$24, ">="&K1,'Revenue Tracking'!$P$13:$P$24, "<"&L1) -> 0 | L9: =SUMIFS('Revenue Tracking'!$F$13:$F$24, 'Revenue Tracking'!$P$13:$P$24, ">="&L1,'Revenue Tracking'!$P$13:$P$24, "<"&M1) -> 0 | M9: =SUMIFS('Revenue Tracking'!$F$13:$F$24, 'Revenue Tracking'!$P$13:$P$24, ">="&M1,'Revenue Tracking'!$P$13:$P$24, "<"&N1) -> 823921.37 | ... KE9: =SUMIFS('Revenue Tracking'!$F$13:$F$24, 'Revenue Tracking'!$P$13:$P$24, ">="&KE1,'Revenue Tracking'!$P$13:$P$24, "<"&KF1) -> 0 | KF9: =SUMIFS('Revenue Tracking'!$F$13:$F$24, 'Revenue Tracking'!$P$13:$P$24, ">="&KF1,'Revenue Tracking'!$P$13:$P$24, "<"&#REF!) -> 0
B10: Actual + Planned Revenue - Cumulative | F10: =F9 -> 0 | G10: =F10+G9 -> 0 | H10: =G10+H9 -> 0 | I10: =H10+I9 -> 0 | J10: =I10+J9 -> 1647842.7 | K10: =J10+K9 -> 1647842.7 | L10: =K10+L9 -> 1647842.7 | M10: =L10+M9 -> 2471764.1 | N10: =M10+N9 -> 3089705.1 | ... KF10: =KE10+KF9 -> 5149508.6
B11: Actual + Planned Expenditure | C11: ='Revenue Tracking'!F5 -> 3300331.8 | D11: =SUM(F11:KF11) -> 3300331.8 | F11: =SUMIFS('Expenditure Breakdown'!$Q$6:$Q$172, 'Expenditure Breakdown'!$W$6:$W$172, ">="&F1,'Expenditure Breakdown'!$W$6:$W$172, "<"&G1) -> 0 | G11: =SUMIFS('Expenditure Breakdown'!$Q$6:$Q$172, 'Expenditure Breakdown'!$W$6:$W$172, ">="&G1,'Expenditure Breakdown'!$W$6:$W$172, "<"&H1) -> 0 | H11: =SUMIFS('Expenditure Breakdown'!$Q$6:$Q$172, 'Expenditure Breakdown'!$W$6:$W$172, ">="&H1,'Expenditure Breakdown'!$W$6:$W$172, "<"&I1) -> 0 | I11: =SUMIFS('Expenditure Breakdown'!$Q$6:$Q$172, 'Expenditure Breakdown'!$W$6:$W$172, ">="&I1,'Expenditure Breakdown'!$W$6:$W$172, "<"&J1) -> 1400 | J11: =SUMIFS('Expenditure Breakdown'!$Q$6:$Q$172, 'Expenditure Breakdown'!$W$6:$W$172, ">="&J1,'Expenditure Breakdown'!$W$6:$W$172, "<"&K1) -> 82500 | K11: =SUMIFS('Expenditure Breakdown'!$Q$6:$Q$172, 'Expenditure Breakdown'!$W$6:$W$172, ">="&K1,'Expenditure Breakdown'!$W$6:$W$172, "<"&L1) -> 0 | L11: =SUMIFS('Expenditure Breakdown'!$Q$6:$Q$172, 'Expenditure Breakdown'!$W$6:$W$172, ">="&L1,'Expenditure Breakdown'!$W$6:$W$172, "<"&M1) -> 230412.41 | M11: =SUMIFS('Expenditure Breakdown'!$Q$6:$Q$172, 'Expenditure Breakdown'!$W$6:$W$172, ">="&M1,'Expenditure Breakdown'!$W$6:$W$172, "<"&N1) -> 1400 | ... KE11: =SUMIFS('Expenditure Breakdown'!$Q$6:$Q$172, 'Expenditure Breakdown'!$W$6:$W$172, ">="&KE1,'Expenditure Breakdown'!$W$6:$W$172, "<"&KF1) -> 0 | KF11: =SUMIFS('Expenditure Breakdown'!$Q$6:$Q$172, 'Expenditure Breakdown'!$W$6:$W$172, ">="&KF1,'Expenditure Breakdown'!$W$6:$W$172, "<"&#REF!) -> 0
B12: Actual + Planned Expenditure - Cumulative | F12: =F11 -> 0 | G12: =F12+G11 -> 0 | H12: =G12+H11 -> 0 | I12: =H12+I11 -> 1400 | J12: =I12+J11 -> 83900 | K12: =J12+K11 -> 83900 | L12: =K12+L11 -> 314312.41 | M12: =L12+M11 -> 315712.41 | N12: =M12+N11 -> 315712.41 | ... KF12: =KE12+KF11 -> 3300331.8
B14: ACTUAL CashFlow | F14: =F10-F12 -> 0 | G14: =G10-G12 -> 0 | H14: =H10-H12 -> 0 | I14: =I10-I12 -> -1400 | J14: =J10-J12 -> 1563942.7 | K14: =K10-K12 -> 1563942.7 | L14: =L10-L12 -> 1333530.3 | M14: =M10-M12 -> 2156051.7 | ... KF14: =KF10-KF12 -> 1849176.8
C16: CHECK | D16: CHECK
B17: Revenue Recognition | C17: =C3-D17 -> 0 | D17: =SUM(F17:KF17) -> 4119606.9 | F17: =SUMIFS('Expenditure Breakdown'!$U$6:$U$172, 'Expenditure Breakdown'!$T$6:$T$172, ">="&F1,'Expenditure Breakdown'!$T$6:$T$172, "<"&G1) -> 0 | G17: =SUMIFS('Expenditure Breakdown'!$U$6:$U$172, 'Expenditure Breakdown'!$T$6:$T$172, ">="&G1,'Expenditure Breakdown'!$T$6:$T$172, "<"&H1) -> 0 | H17: =SUMIFS('Expenditure Breakdown'!$U$6:$U$172, 'Expenditure Breakdown'!$T$6:$T$172, ">="&H1,'Expenditure Breakdown'!$T$6:$T$172, "<"&I1) -> 1555.5556 | I17: =SUMIFS('Expenditure Breakdown'!$U$6:$U$172, 'Expenditure Breakdown'!$T$6:$T$172, ">="&I1,'Expenditure Breakdown'!$T$6:$T$172, "<"&J1) -> 0 | J17: =SUMIFS('Expenditure Breakdown'!$U$6:$U$172, 'Expenditure Breakdown'!$T$6:$T$172, ">="&J1,'Expenditure Breakdown'!$T$6:$T$172, "<"&K1) -> 0 | K17: =SUMIFS('Expenditure Breakdown'!$U$6:$U$172, 'Expenditure Breakdown'!$T$6:$T$172, ">="&K1,'Expenditure Breakdown'!$T$6:$T$172, "<"&L1) -> 0 | L17: =SUMIFS('Expenditure Breakdown'!$U$6:$U$172, 'Expenditure Breakdown'!$T$6:$T$172, ">="&L1,'Expenditure Breakdown'!$T$6:$T$172, "<"&M1) -> 3172208.2 | M17: =SUMIFS('Expenditure Breakdown'!$U$6:$U$172, 'Expenditure Breakdown'!$T$6:$T$172, ">="&M1,'Expenditure Breakdown'!$T$6:$T$172, "<"&N1) -> 0 | ... KE17: =SUMIFS('Expenditure Breakdown'!$U$6:$U$172, 'Expenditure Breakdown'!$T$6:$T$172, ">="&KE1,'Expenditure Breakdown'!$T$6:$T$172, "<"&KF1) -> 0 | KF17: =SUMIFS('Expenditure Breakdown'!$U$6:$U$172, 'Expenditure Breakdown'!$T$6:$T$172, ">="&KF1,'Expenditure Breakdown'!$T$6:$T$172, "<"&#REF!) -> 0
B18: Revenue Recognition Cumulative | C18: =D17-D18 -> 0 | D18: =MAX(F18:KF18) -> 4119606.9 | F18: =F17 -> 0 | G18: =F18+G17 -> 0 | H18: =G18+H17 -> 1555.5556 | I18: =H18+I17 -> 1555.5556 | J18: =I18+J17 -> 1555.5556 | K18: =J18+K17 -> 1555.5556 | L18: =K18+L17 -> 3173763.7 | M18: =L18+M17 -> 3173763.7 | N18: =M18+N17 -> 3173763.7 | ... KF18: =KE18+KF17 -> 4119606.9

Sheet Finance - Revenue
A3: Sum of REVENUE RECOGNITION AMOUNT | B3: Column Labels
A4: Row Labels | B4: (blank) | C4: 46022 | E4: 46053 | F4: 46081 | G4: 46112 | H4: 46142 | I4: 46111 | J4: Grand Total
A5: (blank)
A6: 1. Panels | B6: 0 | D6: 0 | E6: 577060.68 | J6: 577060.68
A7: 2. Inverters | B7: 0 | D7: 0 | E7: 175000 | J7: 175000
A8: 3. Mounting Structures | D8: 0 | E8: 188842.5 | J8: 188842.5
A9: 4. DC Equipment | D9: 0 | E9: 21928.216 | F9: 100913.8 | G9: 21928.216 | H9: 4385.6431 | J9: 149155.87
A10: 5. Monitoring | D10: 0 | E10: 10517.677 | F10: 50732.323 | J10: 61250
A11: 6. AC Equipment | D11: 0 | E11: 30740.993 | F11: 196451.6 | G11: 30740.993 | H11: 6148.1987 | J11: 264081.78
A12: 8. Product Add On | B12: 0 | D12: 0 | F12: 144498.77 | I12: 18670.539 | J12: 163169.31
A13: 9. AC & DC installation | D13: 0 | E13: 37919.444 | F13: 68255 | G13: 37919.444 | H13: 7583.8889 | J13: 151677.78
A14: 10. Site Logistics | D14: 0 | E14: 7089.9731 | F14: 12761.952 | G14: 7089.9731 | H14: 1417.9946 | J14: 28359.892
A15: 11. Due Dilligence | C15: 11164.109 | D15: 0 | G15: 87724.78 | J15: 98888.889
A16: 13. Engineering | D16: 0 | G16: 19649.809 | J16: 19649.809
A17: 14. General Expenses | C17: 534.72222 | D17: 0 | E17: 534.72222 | F17: 534.72222 | G17: 534.72222 | J17: 2138.8889
A18: 15. Service Add On
A19: 12. BDP Commission
A20: 7.BESS
A21: Grand Total | B21: 0 | C21: 11698.831 | D21: 0 | E21: 1049634.2 | F21: 574148.16 | G21: 205587.94 | H21: 19535.725 | I21: 18670.539 | J21: 1879275.4

Sheet Finance - COS
A3: Sum of Actual Total | B3: Column Labels
A4: Row Labels | B4: (blank) | C4: 46022 | E4: 46053 | F4: 46081 | G4: 46112 | H4: 46142 | I4: 46111 | J4: Grand Total
A5: (blank)
A6: 1. Panels | B6: 0 | E6: 356240 | J6: 356240
A7: 2. Inverters | E7: 137740 | J7: 137740
A8: 3. Mounting Structures | E8: 151074 | J8: 151074
A9: 4. DC Equipment | E9: 19985.675 | F9: 91974.215 | G9: 19985.675 | H9: 3997.135 | J9: 135942.7
A10: 5. Monitoring | E10: 8500 | F10: 41000 | J10: 49500
A11: 6. AC Equipment | E11: 17608.369 | F11: 112527.01 | G11: 17608.369 | H11: 3521.6738 | J11: 151265.43
A12: 8. Product Add On | F12: 116091 | I12: 15000 | J12: 131091
A13: 9. AC & DC installation | E13: 34127.5 | F13: 61429.5 | G13: 34127.5 | H13: 6825.5 | J13: 136510
A14: 10. Site Logistics | E14: 6828.0591 | F14: 12290.506 | G14: 6828.0591 | H14: 1365.6118 | J14: 27312.236
A15: 11. Due Dilligence | C15: 10000 | G15: 78577.5 | J15: 88577.5
A16: 13. Engineering | G16: 23490.942 | J16: 23490.942
A17: 14. General Expenses | C17: 481.25 | E17: 481.25 | F17: 481.25 | G17: 481.25 | J17: 1925
A18: 15. Service Add On
A19: 12. BDP Commission | D19: 0 | J19: 0
A20: 7.BESS
A21: Grand Total | B21: 0 | C21: 10481.25 | D21: 0 | E21: 732584.85 | F21: 435793.49 | G21: 181099.3 | H21: 15709.921 | I21: 15000 | J21: 1390668.8

Sheet Data
C2: Public holidays | F2: Drop down list
C3: 45658 | D3: New Years Day | F3: Approved
C4: 45737 | D4: Human Rights day | F4: Pending
C5: 45765 | D5: Good Friday | F5: Declined
C6: 45768 | D6: Family Day | F6: Abanded
C7: 45774 | D7: Freedom Day
C8: 45765 | D8: Freedom DayObserved
C9: 45778 | D9: Workers day
C10: 45824 | D10: Youth Day Holiday
C11: 45878 | D11: Womens Day
C12: 45924 | D12: Heritage Day
C13: 46007 | D13: Day of Reconciliation | H13: Manual dates
C14: 46016 | D14: Christmas Day
C15: 46017 | D15: Day of Goodwill
C16: 46006 | D16: Builders Break
C17: 46007 | D17: Builders Break
C18: 46008 | D18: Builders Break
C19: 46009 | D19: Builders Break
C20: 46010 | D20: Builders Break
C21: 46011 | D21: Builders Break
C22: 46012 | D22: Builders Break
C23: 46013 | D23: Builders Break
C24: 46014 | D24: Builders Break
C25: 46015 | D25: Builders Break
... C40: 46030 | D40: Builders Break
D41: Builders Break
D42: Builders Break
D43: Builders Break
D44: Builders Break
D45: Builders Break
D46: Builders Break
D47: Builders Break
D48: Builders Break
C49: 46102 | D49: Human Rights day
C50: 46115 | D50: Good Friday
C51: 46118 | D51: Family Day
C52: 46139 | D52: Freedom Day
C53: 46143 | D53: Workers day
C54: 46189 | D54: Youth Day Holiday
C55: 46243 | D55: Womens Day
C56: 46244 | D56: Womens Day Observerd
C57: 46289 | D57: Heritage Day
C58: 46372 | D58: Day of Reconciliation
C59: 46381 | D59: Christmas Day
C60: 46382 | D60: Day of Goodwill
