Workbook
Name AC_Equipment_Product: #REF!
Name AC_Installation_Services: #REF!
Name Civil___Electrical_Due_Dilligence_Services: #REF!
Name DC_Equipment_Product: #REF!
Name Engineering___Project_Management_Services: #REF!
Name Installation_Services: #REF!
Name Inverter_Capacity: #REF!
Name Inverter_Supplier: #REF!
Name Material_Roof_access: #REF!
Name Mounting_Structures_Product: #REF!
Name Offloading_service: #REF!
Name Project_Size: 'Finance - Revenue'!Projectsize
Name Project_Size: Projectsize
Name Projectsize: #REF!
Name Projectsize: 'Project Margins'!$K$5
Name PV_Modules_Product: #REF!
Name Security_Serv: #REF!
Name Security_Serv: #REF!
Name Site_Storage_services: #REF!
Name SSS: #REF!
Name SSS: #REF!
Name Travel: #REF!
Name USD_ZAR: #REF!

Sheet Sheet1
A1: PROJECT PLAN
A2: # | B2: Project Milestone | C2: Planned Start Date | D2: Duration (Work Days) | E2: Planned End Date | F2: Actual Start Date | H2: Actual End Date | J2: Comments | L2: =C3 -> 43831 | M2: =L2+3 -> 43834 | N2: =M2+7 -> 43841 | O2: =N2+7 -> 43848 | P2: =O2+7 -> 43855 | Q2: =P2+6 -> 43861 | R2: =Q2+1 -> 43862 | S2: =R2+7 -> 43869 | T2: =S2+7 -> 43876 | U2: =T2+7 -> 43883 | V2: =U2+6 -> 43889 | W2: =V2+7 -> 43896 | X2: =W2+7 -> 43903 | Y2: =X2+7 -> 43910 | Z2: =Y2+7 -> 43917 | AA2: =Z2+3 -> 43920 | AB2: =AA2+4 -> 43924 | AC2: =AB2+7 -> 43931 | AD2: =AC2+7 -> 43938 | AE2: =AD2+7 -> 43945 | AF2: =AE2+6 -> 43951 | AG2: =AF2+2 -> 43953 | AH2: =AG2+7 -> 43960 | AI2: =AH2+7 -> 43967 | AJ2: =AI2+7 -> 43974 | AK2: =AJ2+7 -> 43981 | AL2: =AK2+1 -> 43982 | AM2: =AL2+6 -> 43988 | AN2: =AM2+7 -> 43995 | AO2: =AN2+7 -> 44002 | AP2: =AO2+7 -> 44009 | AQ2: =AP2+3 -> 44012 | AR2: =AQ2+4 -> 44016 | AS2: =AR2+7 -> 44023 | AT2: =AS2+7 -> 44030 | AU2: =AT2+7 -> 44037 | AV2: =AU2+6 -> 44043 | AW2: =AV2+1 -> 44044 | AX2: =AW2+7 -> 44051 | AY2: =AX2+7 -> 44058 | AZ2: =AY2+7 -> 44065 | BA2: =AZ2+7 -> 44072 | BB2: =BA2+2 -> 44074 | BC2: =BB2+5 -> 44079 | BD2: =BC2+7 -> 44086 | BE2: =BD2+7 -> 44093 | BF2: =BE2+7 -> 44100 | BG2: =BF2+4 -> 44104
A3: 1 | B3: Contract Signature | C3: 43831 | D3: 1 | E3: 43832 | F3: 43831 | G3: 1 | H3: 43832 | L3: =IF(AND($F3<(L$2+7),$F3>L$2),1, IF(AND($H3<L$2+7,$H3>L$2),3, IF(AND($F3<=L$2, $H3>=L$2), 2, "" ))) -> 3 | M3: =IF(AND($F3<(M$2+7),$F3>M$2),1, IF(AND($H3<M$2+7,$H3>M$2),3, IF(AND($F3<=M$2, $H3>=M$2), 2, "" ))) | N3: =IF(AND($F3<(N$2+7),$F3>N$2),1, IF(AND($H3<N$2+7,$H3>N$2),3, IF(AND($F3<=N$2, $H3>=N$2), 2, "" ))) | O3: =IF(AND($F3<(O$2+7),$F3>O$2),1, IF(AND($H3<O$2+7,$H3>O$2),3, IF(AND($F3<=O$2, $H3>=O$2), 2, "" ))) | P3: =IF(AND($F3<(P$2+7),$F3>P$2),1, IF(AND($H3<P$2+7,$H3>P$2),3, IF(AND($F3<=P$2, $H3>=P$2), 2, "" ))) | Q3: =IF(AND($F3<(Q$2+7),$F3>Q$2),1, IF(AND($H3<Q$2+7,$H3>Q$2),3, IF(AND($F3<=Q$2, $H3>=Q$2), 2, "" ))) | R3: =IF(AND($F3<(R$2+7),$F3>R$2),1, IF(AND($H3<R$2+7,$H3>R$2),3, IF(AND($F3<=R$2, $H3>=R$2), 2, "" ))) | S3: =IF(AND($F3<(S$2+7),$F3>S$2),1, IF(AND($H3<S$2+7,$H3>S$2),3, IF(AND($F3<=S$2, $H3>=S$2), 2, "" ))) | ... AQ3: =IF(AND($F3<(AQ$2+7),$F3>AQ$2),1, IF(AND($H3<AQ$2+7,$H3>AQ$2),3, IF(AND($F3<=AQ$2, $H3>=AQ$2), 2, "" )))
A4: A | B4: PAYMENT MILESTONE 1: DEPOSIT | C4: 43832 | D4: 1 | E4: 43833 | F4: 43832 | G4: 1 | H4: 43833 | L4: =IF(AND($F4<(L$2+7),$F4>L$2),1, IF(AND($H4<L$2+7,$H4>L$2),3, IF(AND($F4<=L$2, $H4>=L$2), 2, "" ))) -> 1 | M4: =IF(AND($F4<(M$2+7),$F4>M$2),1, IF(AND($H4<M$2+7,$H4>M$2),3, IF(AND($F4<=M$2, $H4>=M$2), 2, "" ))) | N4: =IF(AND($F4<(N$2+7),$F4>N$2),1, IF(AND($H4<N$2+7,$H4>N$2),3, IF(AND($F4<=N$2, $H4>=N$2), 2, "" ))) | O4: =IF(AND($F4<(O$2+7),$F4>O$2),1, IF(AND($H4<O$2+7,$H4>O$2),3, IF(AND($F4<=O$2, $H4>=O$2), 2, "" ))) | P4: =IF(AND($F4<(P$2+7),$F4>P$2),1, IF(AND($H4<P$2+7,$H4>P$2),3, IF(AND($F4<=P$2, $H4>=P$2), 2, "" ))) | Q4: =IF(AND($F4<(Q$2+7),$F4>Q$2),1, IF(AND($H4<Q$2+7,$H4>Q$2),3, IF(AND($F4<=Q$2, $H4>=Q$2), 2, "" ))) | R4: =IF(AND($F4<(R$2+7),$F4>R$2),1, IF(AND($H4<R$2+7,$H4>R$2),3, IF(AND($F4<=R$2, $H4>=R$2), 2, "" ))) | S4: =IF(AND($F4<(S$2+7),$F4>S$2),1, IF(AND($H4<S$2+7,$H4>S$2),3, IF(AND($F4<=S$2, $H4>=S$2), 2, "" ))) | ... AQ4: =IF(AND($F4<(AQ$2+7),$F4>AQ$2),1, IF(AND($H4<AQ$2+7,$H4>AQ$2),3, IF(AND($F4<=AQ$2, $H4>=AQ$2), 2, "" )))
A5: 2 | B5: Structural and Electrical Due Diligences | C5: 43833 | D5: 5 | E5: 43840 | F5: 43833 | G5: 5 | H5: 43840 | L5: =IF(AND($F5<(L$2+7),$F5>L$2),1, IF(AND($H5<L$2+7,$H5>L$2),3, IF(AND($F5<=L$2, $H5>=L$2), 2, "" ))) -> 1 | M5: =IF(AND($F5<(M$2+7),$F5>M$2),1, IF(AND($H5<M$2+7,$H5>M$2),3, IF(AND($F5<=M$2, $H5>=M$2), 2, "" ))) -> 3 | N5: =IF(AND($F5<(N$2+7),$F5>N$2),1, IF(AND($H5<N$2+7,$H5>N$2),3, IF(AND($F5<=N$2, $H5>=N$2), 2, "" ))) | O5: =IF(AND($F5<(O$2+7),$F5>O$2),1, IF(AND($H5<O$2+7,$H5>O$2),3, IF(AND($F5<=O$2, $H5>=O$2), 2, "" ))) | P5: =IF(AND($F5<(P$2+7),$F5>P$2),1, IF(AND($H5<P$2+7,$H5>P$2),3, IF(AND($F5<=P$2, $H5>=P$2), 2, "" ))) | Q5: =IF(AND($F5<(Q$2+7),$F5>Q$2),1, IF(AND($H5<Q$2+7,$H5>Q$2),3, IF(AND($F5<=Q$2, $H5>=Q$2), 2, "" ))) | R5: =IF(AND($F5<(R$2+7),$F5>R$2),1, IF(AND($H5<R$2+7,$H5>R$2),3, IF(AND($F5<=R$2, $H5>=R$2), 2, "" ))) | S5: =IF(AND($F5<(S$2+7),$F5>S$2),1, IF(AND($H5<S$2+7,$H5>S$2),3, IF(AND($F5<=S$2, $H5>=S$2), 2, "" ))) | ... AQ5: =IF(AND($F5<(AQ$2+7),$F5>AQ$2),1, IF(AND($H5<AQ$2+7,$H5>AQ$2),3, IF(AND($F5<=AQ$2, $H5>=AQ$2), 2, "" )))
A6: 3 | B6: Design Confirmation | C6: 43841 | D6: 2 | E6: 43844 | F6: 43841 | G6: 2 | H6: 43844 | L6: =IF(AND($F6<(L$2+7),$F6>L$2),1, IF(AND($H6<L$2+7,$H6>L$2),3, IF(AND($F6<=L$2, $H6>=L$2), 2, "" ))) | M6: =IF(AND($F6<(M$2+7),$F6>M$2),1, IF(AND($H6<M$2+7,$H6>M$2),3, IF(AND($F6<=M$2, $H6>=M$2), 2, "" ))) | N6: =IF(AND($F6<(N$2+7),$F6>N$2),1, IF(AND($H6<N$2+7,$H6>N$2),3, IF(AND($F6<=N$2, $H6>=N$2), 2, "" ))) -> 3 | O6: =IF(AND($F6<(O$2+7),$F6>O$2),1, IF(AND($H6<O$2+7,$H6>O$2),3, IF(AND($F6<=O$2, $H6>=O$2), 2, "" ))) | P6: =IF(AND($F6<(P$2+7),$F6>P$2),1, IF(AND($H6<P$2+7,$H6>P$2),3, IF(AND($F6<=P$2, $H6>=P$2), 2, "" ))) | Q6: =IF(AND($F6<(Q$2+7),$F6>Q$2),1, IF(AND($H6<Q$2+7,$H6>Q$2),3, IF(AND($F6<=Q$2, $H6>=Q$2), 2, "" ))) | R6: =IF(AND($F6<(R$2+7),$F6>R$2),1, IF(AND($H6<R$2+7,$H6>R$2),3, IF(AND($F6<=R$2, $H6>=R$2), 2, "" ))) | S6: =IF(AND($F6<(S$2+7),$F6>S$2),1, IF(AND($H6<S$2+7,$H6>S$2),3, IF(AND($F6<=S$2, $H6>=S$2), 2, "" ))) | ... AQ6: =IF(AND($F6<(AQ$2+7),$F6>AQ$2),1, IF(AND($H6<AQ$2+7,$H6>AQ$2),3, IF(AND($F6<=AQ$2, $H6>=AQ$2), 2, "" )))
A7: 4 | B7: Equipment Procurement | C7: 43833 | E7: 43949 | F7: 43833 | H7: 43949 | L7: =IF(AND($F7<(L$2+7),$F7>L$2),1, IF(AND($H7<L$2+7,$H7>L$2),3, IF(AND($F7<=L$2, $H7>=L$2), 2, "" ))) -> 1 | M7: =IF(AND($F7<(M$2+7),$F7>M$2),1, IF(AND($H7<M$2+7,$H7>M$2),3, IF(AND($F7<=M$2, $H7>=M$2), 2, "" ))) -> 2 | N7: =IF(AND($F7<(N$2+7),$F7>N$2),1, IF(AND($H7<N$2+7,$H7>N$2),3, IF(AND($F7<=N$2, $H7>=N$2), 2, "" ))) -> 2 | O7: =IF(AND($F7<(O$2+7),$F7>O$2),1, IF(AND($H7<O$2+7,$H7>O$2),3, IF(AND($F7<=O$2, $H7>=O$2), 2, "" ))) -> 2 | P7: =IF(AND($F7<(P$2+7),$F7>P$2),1, IF(AND($H7<P$2+7,$H7>P$2),3, IF(AND($F7<=P$2, $H7>=P$2), 2, "" ))) -> 2 | Q7: =IF(AND($F7<(Q$2+7),$F7>Q$2),1, IF(AND($H7<Q$2+7,$H7>Q$2),3, IF(AND($F7<=Q$2, $H7>=Q$2), 2, "" ))) -> 2 | R7: =IF(AND($F7<(R$2+7),$F7>R$2),1, IF(AND($H7<R$2+7,$H7>R$2),3, IF(AND($F7<=R$2, $H7>=R$2), 2, "" ))) -> 2 | S7: =IF(AND($F7<(S$2+7),$F7>S$2),1, IF(AND($H7<S$2+7,$H7>S$2),3, IF(AND($F7<=S$2, $H7>=S$2), 2, "" ))) -> 2 | ... AQ7: =IF(AND($F7<(AQ$2+7),$F7>AQ$2),1, IF(AND($H7<AQ$2+7,$H7>AQ$2),3, IF(AND($F7<=AQ$2, $H7>=AQ$2), 2, "" )))
B8: Panel Procurement | C8: 43833 | D8: 5 | E8: 43840 | F8: 43833 | G8: 5 | H8: 43840 | L8: =IF(AND($F8<(L$2+7),$F8>L$2),1, IF(AND($H8<L$2+7,$H8>L$2),3, IF(AND($F8<=L$2, $H8>=L$2), 2, "" ))) -> 1 | M8: =IF(AND($F8<(M$2+7),$F8>M$2),1, IF(AND($H8<M$2+7,$H8>M$2),3, IF(AND($F8<=M$2, $H8>=M$2), 2, "" ))) -> 3 | N8: =IF(AND($F8<(N$2+7),$F8>N$2),1, IF(AND($H8<N$2+7,$H8>N$2),3, IF(AND($F8<=N$2, $H8>=N$2), 2, "" ))) | O8: =IF(AND($F8<(O$2+7),$F8>O$2),1, IF(AND($H8<O$2+7,$H8>O$2),3, IF(AND($F8<=O$2, $H8>=O$2), 2, "" ))) | P8: =IF(AND($F8<(P$2+7),$F8>P$2),1, IF(AND($H8<P$2+7,$H8>P$2),3, IF(AND($F8<=P$2, $H8>=P$2), 2, "" ))) | Q8: =IF(AND($F8<(Q$2+7),$F8>Q$2),1, IF(AND($H8<Q$2+7,$H8>Q$2),3, IF(AND($F8<=Q$2, $H8>=Q$2), 2, "" ))) | R8: =IF(AND($F8<(R$2+7),$F8>R$2),1, IF(AND($H8<R$2+7,$H8>R$2),3, IF(AND($F8<=R$2, $H8>=R$2), 2, "" ))) | S8: =IF(AND($F8<(S$2+7),$F8>S$2),1, IF(AND($H8<S$2+7,$H8>S$2),3, IF(AND($F8<=S$2, $H8>=S$2), 2, "" ))) | ... AQ8: =IF(AND($F8<(AQ$2+7),$F8>AQ$2),1, IF(AND($H8<AQ$2+7,$H8>AQ$2),3, IF(AND($F8<=AQ$2, $H8>=AQ$2), 2, "" )))
B9: Inverter Procurement | C9: 43941 | D9: 5 | E9: 43949 | F9: 43941 | G9: 5 | H9: 43949 | L9: =IF(AND($F9<(L$2+7),$F9>L$2),1, IF(AND($H9<L$2+7,$H9>L$2),3, IF(AND($F9<=L$2, $H9>=L$2), 2, "" ))) | M9: =IF(AND($F9<(M$2+7),$F9>M$2),1, IF(AND($H9<M$2+7,$H9>M$2),3, IF(AND($F9<=M$2, $H9>=M$2), 2, "" ))) | N9: =IF(AND($F9<(N$2+7),$F9>N$2),1, IF(AND($H9<N$2+7,$H9>N$2),3, IF(AND($F9<=N$2, $H9>=N$2), 2, "" ))) | O9: =IF(AND($F9<(O$2+7),$F9>O$2),1, IF(AND($H9<O$2+7,$H9>O$2),3, IF(AND($F9<=O$2, $H9>=O$2), 2, "" ))) | P9: =IF(AND($F9<(P$2+7),$F9>P$2),1, IF(AND($H9<P$2+7,$H9>P$2),3, IF(AND($F9<=P$2, $H9>=P$2), 2, "" ))) | Q9: =IF(AND($F9<(Q$2+7),$F9>Q$2),1, IF(AND($H9<Q$2+7,$H9>Q$2),3, IF(AND($F9<=Q$2, $H9>=Q$2), 2, "" ))) | R9: =IF(AND($F9<(R$2+7),$F9>R$2),1, IF(AND($H9<R$2+7,$H9>R$2),3, IF(AND($F9<=R$2, $H9>=R$2), 2, "" ))) | S9: =IF(AND($F9<(S$2+7),$F9>S$2),1, IF(AND($H9<S$2+7,$H9>S$2),3, IF(AND($F9<=S$2, $H9>=S$2), 2, "" ))) | ... AQ9: =IF(AND($F9<(AQ$2+7),$F9>AQ$2),1, IF(AND($H9<AQ$2+7,$H9>AQ$2),3, IF(AND($F9<=AQ$2, $H9>=AQ$2), 2, "" )))
B10: Mounting Structure Procurement | C10: 43941 | D10: 5 | E10: 43949 | F10: 43941 | G10: 5 | H10: 43949 | L10: =IF(AND($F10<(L$2+7),$F10>L$2),1, IF(AND($H10<L$2+7,$H10>L$2),3, IF(AND($F10<=L$2, $H10>=L$2), 2, "" ))) | M10: =IF(AND($F10<(M$2+7),$F10>M$2),1, IF(AND($H10<M$2+7,$H10>M$2),3, IF(AND($F10<=M$2, $H10>=M$2), 2, "" ))) | N10: =IF(AND($F10<(N$2+7),$F10>N$2),1, IF(AND($H10<N$2+7,$H10>N$2),3, IF(AND($F10<=N$2, $H10>=N$2), 2, "" ))) | O10: =IF(AND($F10<(O$2+7),$F10>O$2),1, IF(AND($H10<O$2+7,$H10>O$2),3, IF(AND($F10<=O$2, $H10>=O$2), 2, "" ))) | P10: =IF(AND($F10<(P$2+7),$F10>P$2),1, IF(AND($H10<P$2+7,$H10>P$2),3, IF(AND($F10<=P$2, $H10>=P$2), 2, "" ))) | Q10: =IF(AND($F10<(Q$2+7),$F10>Q$2),1, IF(AND($H10<Q$2+7,$H10>Q$2),3, IF(AND($F10<=Q$2, $H10>=Q$2), 2, "" ))) | R10: =IF(AND($F10<(R$2+7),$F10>R$2),1, IF(AND($H10<R$2+7,$H10>R$2),3, IF(AND($F10<=R$2, $H10>=R$2), 2, "" ))) | S10: =IF(AND($F10<(S$2+7),$F10>S$2),1, IF(AND($H10<S$2+7,$H10>S$2),3, IF(AND($F10<=S$2, $H10>=S$2), 2, "" ))) | ... AQ10: =IF(AND($F10<(AQ$2+7),$F10>AQ$2),1, IF(AND($H10<AQ$2+7,$H10>AQ$2),3, IF(AND($F10<=AQ$2, $H10>=AQ$2), 2, "" )))
B11: BOS Procurement | C11: 43941 | D11: 5 | E11: 43949 | F11: 43941 | G11: 5 | H11: 43949 | L11: =IF(AND($F11<(L$2+7),$F11>L$2),1, IF(AND($H11<L$2+7,$H11>L$2),3, IF(AND($F11<=L$2, $H11>=L$2), 2, "" ))) | M11: =IF(AND($F11<(M$2+7),$F11>M$2),1, IF(AND($H11<M$2+7,$H11>M$2),3, IF(AND($F11<=M$2, $H11>=M$2), 2, "" ))) | N11: =IF(AND($F11<(N$2+7),$F11>N$2),1, IF(AND($H11<N$2+7,$H11>N$2),3, IF(AND($F11<=N$2, $H11>=N$2), 2, "" ))) | O11: =IF(AND($F11<(O$2+7),$F11>O$2),1, IF(AND($H11<O$2+7,$H11>O$2),3, IF(AND($F11<=O$2, $H11>=O$2), 2, "" ))) | P11: =IF(AND($F11<(P$2+7),$F11>P$2),1, IF(AND($H11<P$2+7,$H11>P$2),3, IF(AND($F11<=P$2, $H11>=P$2), 2, "" ))) | Q11: =IF(AND($F11<(Q$2+7),$F11>Q$2),1, IF(AND($H11<Q$2+7,$H11>Q$2),3, IF(AND($F11<=Q$2, $H11>=Q$2), 2, "" ))) | R11: =IF(AND($F11<(R$2+7),$F11>R$2),1, IF(AND($H11<R$2+7,$H11>R$2),3, IF(AND($F11<=R$2, $H11>=R$2), 2, "" ))) | S11: =IF(AND($F11<(S$2+7),$F11>S$2),1, IF(AND($H11<S$2+7,$H11>S$2),3, IF(AND($F11<=S$2, $H11>=S$2), 2, "" ))) | ... AQ11: =IF(AND($F11<(AQ$2+7),$F11>AQ$2),1, IF(AND($H11<AQ$2+7,$H11>AQ$2),3, IF(AND($F11<=AQ$2, $H11>=AQ$2), 2, "" )))
A12: 5 | B12: Internal Project Kick off | C12: 43936 | D12: 5 | E12: 43943 | F12: 43936 | G12: 5 | H12: 43943
A13: 6 | B13: Client Project Kick-off | C13: 43963 | D13: 5 | E13: 43970 | F13: 43963 | G13: 5 | H13: 43970 | L13: =IF(AND($F13<(L$2+7),$F13>L$2),1, IF(AND($H13<L$2+7,$H13>L$2),3, IF(AND($F13<=L$2, $H13>=L$2), 2, "" ))) | M13: =IF(AND($F13<(M$2+7),$F13>M$2),1, IF(AND($H13<M$2+7,$H13>M$2),3, IF(AND($F13<=M$2, $H13>=M$2), 2, "" ))) | N13: =IF(AND($F13<(N$2+7),$F13>N$2),1, IF(AND($H13<N$2+7,$H13>N$2),3, IF(AND($F13<=N$2, $H13>=N$2), 2, "" ))) | O13: =IF(AND($F13<(O$2+7),$F13>O$2),1, IF(AND($H13<O$2+7,$H13>O$2),3, IF(AND($F13<=O$2, $H13>=O$2), 2, "" ))) | P13: =IF(AND($F13<(P$2+7),$F13>P$2),1, IF(AND($H13<P$2+7,$H13>P$2),3, IF(AND($F13<=P$2, $H13>=P$2), 2, "" ))) | Q13: =IF(AND($F13<(Q$2+7),$F13>Q$2),1, IF(AND($H13<Q$2+7,$H13>Q$2),3, IF(AND($F13<=Q$2, $H13>=Q$2), 2, "" ))) | R13: =IF(AND($F13<(R$2+7),$F13>R$2),1, IF(AND($H13<R$2+7,$H13>R$2),3, IF(AND($F13<=R$2, $H13>=R$2), 2, "" ))) | S13: =IF(AND($F13<(S$2+7),$F13>S$2),1, IF(AND($H13<S$2+7,$H13>S$2),3, IF(AND($F13<=S$2, $H13>=S$2), 2, "" ))) | ... AQ13: =IF(AND($F13<(AQ$2+7),$F13>AQ$2),1, IF(AND($H13<AQ$2+7,$H13>AQ$2),3, IF(AND($F13<=AQ$2, $H13>=AQ$2), 2, "" )))
A14: 7 | B14: Equipment Delivery | C14: 43983 | D14: 9 | E14: 43994 | F14: 43983 | G14: 9 | H14: 43994 | L14: =IF(AND($F14<(L$2+7),$F14>L$2),1, IF(AND($H14<L$2+7,$H14>L$2),3, IF(AND($F14<=L$2, $H14>=L$2), 2, "" ))) | M14: =IF(AND($F14<(M$2+7),$F14>M$2),1, IF(AND($H14<M$2+7,$H14>M$2),3, IF(AND($F14<=M$2, $H14>=M$2), 2, "" ))) | N14: =IF(AND($F14<(N$2+7),$F14>N$2),1, IF(AND($H14<N$2+7,$H14>N$2),3, IF(AND($F14<=N$2, $H14>=N$2), 2, "" ))) | O14: =IF(AND($F14<(O$2+7),$F14>O$2),1, IF(AND($H14<O$2+7,$H14>O$2),3, IF(AND($F14<=O$2, $H14>=O$2), 2, "" ))) | P14: =IF(AND($F14<(P$2+7),$F14>P$2),1, IF(AND($H14<P$2+7,$H14>P$2),3, IF(AND($F14<=P$2, $H14>=P$2), 2, "" ))) | Q14: =IF(AND($F14<(Q$2+7),$F14>Q$2),1, IF(AND($H14<Q$2+7,$H14>Q$2),3, IF(AND($F14<=Q$2, $H14>=Q$2), 2, "" ))) | R14: =IF(AND($F14<(R$2+7),$F14>R$2),1, IF(AND($H14<R$2+7,$H14>R$2),3, IF(AND($F14<=R$2, $H14>=R$2), 2, "" ))) | S14: =IF(AND($F14<(S$2+7),$F14>S$2),1, IF(AND($H14<S$2+7,$H14>S$2),3, IF(AND($F14<=S$2, $H14>=S$2), 2, "" ))) | ... AQ14: =IF(AND($F14<(AQ$2+7),$F14>AQ$2),1, IF(AND($H14<AQ$2+7,$H14>AQ$2),3, IF(AND($F14<=AQ$2, $H14>=AQ$2), 2, "" )))
B15: Mounting Structure Delivery | C15: 43983 | D15: 2 | E15: 43985 | F15: 43983 | G15: 2 | H15: 43985
B16: Panel Delivery | C16: 43990 | D16: 2 | E16: 43992 | F16: 43990 | G16: 2 | H16: 43992 | L16: =IF(AND($F16<(L$2+7),$F16>L$2),1, IF(AND($H16<L$2+7,$H16>L$2),3, IF(AND($F16<=L$2, $H16>=L$2), 2, "" ))) | M16: =IF(AND($F16<(M$2+7),$F16>M$2),1, IF(AND($H16<M$2+7,$H16>M$2),3, IF(AND($F16<=M$2, $H16>=M$2), 2, "" ))) | N16: =IF(AND($F16<(N$2+7),$F16>N$2),1, IF(AND($H16<N$2+7,$H16>N$2),3, IF(AND($F16<=N$2, $H16>=N$2), 2, "" ))) | O16: =IF(AND($F16<(O$2+7),$F16>O$2),1, IF(AND($H16<O$2+7,$H16>O$2),3, IF(AND($F16<=O$2, $H16>=O$2), 2, "" ))) | P16: =IF(AND($F16<(P$2+7),$F16>P$2),1, IF(AND($H16<P$2+7,$H16>P$2),3, IF(AND($F16<=P$2, $H16>=P$2), 2, "" ))) | Q16: =IF(AND($F16<(Q$2+7),$F16>Q$2),1, IF(AND($H16<Q$2+7,$H16>Q$2),3, IF(AND($F16<=Q$2, $H16>=Q$2), 2, "" ))) | R16: =IF(AND($F16<(R$2+7),$F16>R$2),1, IF(AND($H16<R$2+7,$H16>R$2),3, IF(AND($F16<=R$2, $H16>=R$2), 2, "" ))) | S16: =IF(AND($F16<(S$2+7),$F16>S$2),1, IF(AND($H16<S$2+7,$H16>S$2),3, IF(AND($F16<=S$2, $H16>=S$2), 2, "" ))) | ... AQ16: =IF(AND($F16<(AQ$2+7),$F16>AQ$2),1, IF(AND($H16<AQ$2+7,$H16>AQ$2),3, IF(AND($F16<=AQ$2, $H16>=AQ$2), 2, "" )))
B17: Generator Delivery | C17: 43983 | D17: 2 | E17: 43985 | F17: 43983 | G17: 2 | H17: 43985
A18: B | B18: PAYMENT MILESTONE 2: DELIVERY OF PV PANELS | C18: 43992 | D18: 2 | E18: 43994 | F18: 43992 | G18: 2 | H18: 43994
B19: Inverter Delivery | C19: 43983 | D19: 2 | E19: 43985 | F19: 43983 | G19: 2 | H19: 43985 | L19: =IF(AND($F19<(L$2+7),$F19>L$2),1, IF(AND($H19<L$2+7,$H19>L$2),3, IF(AND($F19<=L$2, $H19>=L$2), 2, "" ))) | M19: =IF(AND($F19<(M$2+7),$F19>M$2),1, IF(AND($H19<M$2+7,$H19>M$2),3, IF(AND($F19<=M$2, $H19>=M$2), 2, "" ))) | N19: =IF(AND($F19<(N$2+7),$F19>N$2),1, IF(AND($H19<N$2+7,$H19>N$2),3, IF(AND($F19<=N$2, $H19>=N$2), 2, "" ))) | O19: =IF(AND($F19<(O$2+7),$F19>O$2),1, IF(AND($H19<O$2+7,$H19>O$2),3, IF(AND($F19<=O$2, $H19>=O$2), 2, "" ))) | P19: =IF(AND($F19<(P$2+7),$F19>P$2),1, IF(AND($H19<P$2+7,$H19>P$2),3, IF(AND($F19<=P$2, $H19>=P$2), 2, "" ))) | Q19: =IF(AND($F19<(Q$2+7),$F19>Q$2),1, IF(AND($H19<Q$2+7,$H19>Q$2),3, IF(AND($F19<=Q$2, $H19>=Q$2), 2, "" ))) | R19: =IF(AND($F19<(R$2+7),$F19>R$2),1, IF(AND($H19<R$2+7,$H19>R$2),3, IF(AND($F19<=R$2, $H19>=R$2), 2, "" ))) | S19: =IF(AND($F19<(S$2+7),$F19>S$2),1, IF(AND($H19<S$2+7,$H19>S$2),3, IF(AND($F19<=S$2, $H19>=S$2), 2, "" ))) | ... AQ19: =IF(AND($F19<(AQ$2+7),$F19>AQ$2),1, IF(AND($H19<AQ$2+7,$H19>AQ$2),3, IF(AND($F19<=AQ$2, $H19>=AQ$2), 2, "" )))
B20: BOS Delivery | C20: 43983 | D20: 1 | E20: 43984 | F20: 43983 | G20: 1 | H20: 43984 | L20: =IF(AND($F20<(L$2+7),$F20>L$2),1, IF(AND($H20<L$2+7,$H20>L$2),3, IF(AND($F20<=L$2, $H20>=L$2), 2, "" ))) | M20: =IF(AND($F20<(M$2+7),$F20>M$2),1, IF(AND($H20<M$2+7,$H20>M$2),3, IF(AND($F20<=M$2, $H20>=M$2), 2, "" ))) | N20: =IF(AND($F20<(N$2+7),$F20>N$2),1, IF(AND($H20<N$2+7,$H20>N$2),3, IF(AND($F20<=N$2, $H20>=N$2), 2, "" ))) | O20: =IF(AND($F20<(O$2+7),$F20>O$2),1, IF(AND($H20<O$2+7,$H20>O$2),3, IF(AND($F20<=O$2, $H20>=O$2), 2, "" ))) | P20: =IF(AND($F20<(P$2+7),$F20>P$2),1, IF(AND($H20<P$2+7,$H20>P$2),3, IF(AND($F20<=P$2, $H20>=P$2), 2, "" ))) | Q20: =IF(AND($F20<(Q$2+7),$F20>Q$2),1, IF(AND($H20<Q$2+7,$H20>Q$2),3, IF(AND($F20<=Q$2, $H20>=Q$2), 2, "" ))) | R20: =IF(AND($F20<(R$2+7),$F20>R$2),1, IF(AND($H20<R$2+7,$H20>R$2),3, IF(AND($F20<=R$2, $H20>=R$2), 2, "" ))) | S20: =IF(AND($F20<(S$2+7),$F20>S$2),1, IF(AND($H20<S$2+7,$H20>S$2),3, IF(AND($F20<=S$2, $H20>=S$2), 2, "" ))) | ... AQ20: =IF(AND($F20<(AQ$2+7),$F20>AQ$2),1, IF(AND($H20<AQ$2+7,$H20>AQ$2),3, IF(AND($F20<=AQ$2, $H20>=AQ$2), 2, "" )))
A21: C | B21: PAYMENT MILESTONE 3: DELIVERY OF INVERTERS AND BOS | C21: 43985 | D21: 2 | E21: 43987 | F21: 43985 | G21: 2 | H21: 43987
A22: 8 | B22: Installation | C22: 43990 | D22: 22 | E22: 44012 | F22: 43990 | G22: 22 | H22: 44012 | L22: =IF(AND($F22<(L$2+7),$F22>L$2),1, IF(AND($H22<L$2+7,$H22>L$2),3, IF(AND($F22<=L$2, $H22>=L$2), 2, "" ))) | M22: =IF(AND($F22<(M$2+7),$F22>M$2),1, IF(AND($H22<M$2+7,$H22>M$2),3, IF(AND($F22<=M$2, $H22>=M$2), 2, "" ))) | N22: =IF(AND($F22<(N$2+7),$F22>N$2),1, IF(AND($H22<N$2+7,$H22>N$2),3, IF(AND($F22<=N$2, $H22>=N$2), 2, "" ))) | O22: =IF(AND($F22<(O$2+7),$F22>O$2),1, IF(AND($H22<O$2+7,$H22>O$2),3, IF(AND($F22<=O$2, $H22>=O$2), 2, "" ))) | P22: =IF(AND($F22<(P$2+7),$F22>P$2),1, IF(AND($H22<P$2+7,$H22>P$2),3, IF(AND($F22<=P$2, $H22>=P$2), 2, "" ))) | Q22: =IF(AND($F22<(Q$2+7),$F22>Q$2),1, IF(AND($H22<Q$2+7,$H22>Q$2),3, IF(AND($F22<=Q$2, $H22>=Q$2), 2, "" ))) | R22: =IF(AND($F22<(R$2+7),$F22>R$2),1, IF(AND($H22<R$2+7,$H22>R$2),3, IF(AND($F22<=R$2, $H22>=R$2), 2, "" ))) | S22: =IF(AND($F22<(S$2+7),$F22>S$2),1, IF(AND($H22<S$2+7,$H22>S$2),3, IF(AND($F22<=S$2, $H22>=S$2), 2, "" ))) | ... AQ22: =IF(AND($F22<(AQ$2+7),$F22>AQ$2),1, IF(AND($H22<AQ$2+7,$H22>AQ$2),3, IF(AND($F22<=AQ$2, $H22>=AQ$2), 2, "" ))) -> 2
B23: Site Establishment | C23: 43990 | D23: 1 | E23: 43991 | F23: 43990 | G23: 1 | H23: 43991 | J23: Installation placed on hold due to Covid-19 case | L23: =IF(AND($F23<(L$2+7),$F23>L$2),1, IF(AND($H23<L$2+7,$H23>L$2),3, IF(AND($F23<=L$2, $H23>=L$2), 2, "" ))) | M23: =IF(AND($F23<(M$2+7),$F23>M$2),1, IF(AND($H23<M$2+7,$H23>M$2),3, IF(AND($F23<=M$2, $H23>=M$2), 2, "" ))) | N23: =IF(AND($F23<(N$2+7),$F23>N$2),1, IF(AND($H23<N$2+7,$H23>N$2),3, IF(AND($F23<=N$2, $H23>=N$2), 2, "" ))) | O23: =IF(AND($F23<(O$2+7),$F23>O$2),1, IF(AND($H23<O$2+7,$H23>O$2),3, IF(AND($F23<=O$2, $H23>=O$2), 2, "" ))) | P23: =IF(AND($F23<(P$2+7),$F23>P$2),1, IF(AND($H23<P$2+7,$H23>P$2),3, IF(AND($F23<=P$2, $H23>=P$2), 2, "" ))) | Q23: =IF(AND($F23<(Q$2+7),$F23>Q$2),1, IF(AND($H23<Q$2+7,$H23>Q$2),3, IF(AND($F23<=Q$2, $H23>=Q$2), 2, "" ))) | R23: =IF(AND($F23<(R$2+7),$F23>R$2),1, IF(AND($H23<R$2+7,$H23>R$2),3, IF(AND($F23<=R$2, $H23>=R$2), 2, "" ))) | S23: =IF(AND($F23<(S$2+7),$F23>S$2),1, IF(AND($H23<S$2+7,$H23>S$2),3, IF(AND($F23<=S$2, $H23>=S$2), 2, "" ))) | ... AQ23: =IF(AND($F23<(AQ$2+7),$F23>AQ$2),1, IF(AND($H23<AQ$2+7,$H23>AQ$2),3, IF(AND($F23<=AQ$2, $H23>=AQ$2), 2, "" )))
A24: 9 | B24: DC Works | C24: 43991 | D24: 16 | E24: 44012 | F24: 43991 | G24: 16 | H24: 44012 | L24: =IF(AND($F24<(L$2+7),$F24>L$2),1, IF(AND($H24<L$2+7,$H24>L$2),3, IF(AND($F24<=L$2, $H24>=L$2), 2, "" ))) | M24: =IF(AND($F24<(M$2+7),$F24>M$2),1, IF(AND($H24<M$2+7,$H24>M$2),3, IF(AND($F24<=M$2, $H24>=M$2), 2, "" ))) | N24: =IF(AND($F24<(N$2+7),$F24>N$2),1, IF(AND($H24<N$2+7,$H24>N$2),3, IF(AND($F24<=N$2, $H24>=N$2), 2, "" ))) | O24: =IF(AND($F24<(O$2+7),$F24>O$2),1, IF(AND($H24<O$2+7,$H24>O$2),3, IF(AND($F24<=O$2, $H24>=O$2), 2, "" ))) | P24: =IF(AND($F24<(P$2+7),$F24>P$2),1, IF(AND($H24<P$2+7,$H24>P$2),3, IF(AND($F24<=P$2, $H24>=P$2), 2, "" ))) | Q24: =IF(AND($F24<(Q$2+7),$F24>Q$2),1, IF(AND($H24<Q$2+7,$H24>Q$2),3, IF(AND($F24<=Q$2, $H24>=Q$2), 2, "" ))) | R24: =IF(AND($F24<(R$2+7),$F24>R$2),1, IF(AND($H24<R$2+7,$H24>R$2),3, IF(AND($F24<=R$2, $H24>=R$2), 2, "" ))) | S24: =IF(AND($F24<(S$2+7),$F24>S$2),1, IF(AND($H24<S$2+7,$H24>S$2),3, IF(AND($F24<=S$2, $H24>=S$2), 2, "" ))) | ... AQ24: =IF(AND($F24<(AQ$2+7),$F24>AQ$2),1, IF(AND($H24<AQ$2+7,$H24>AQ$2),3, IF(AND($F24<=AQ$2, $H24>=AQ$2), 2, "" ))) -> 2
B25: Mounting structure Installation | C25: 43991 | D25: 4 | E25: 43997 | F25: 43991 | G25: 4 | H25: 43997 | L25: =IF(AND($F25<(L$2+7),$F25>L$2),1, IF(AND($H25<L$2+7,$H25>L$2),3, IF(AND($F25<=L$2, $H25>=L$2), 2, "" ))) | M25: =IF(AND($F25<(M$2+7),$F25>M$2),1, IF(AND($H25<M$2+7,$H25>M$2),3, IF(AND($F25<=M$2, $H25>=M$2), 2, "" ))) | N25: =IF(AND($F25<(N$2+7),$F25>N$2),1, IF(AND($H25<N$2+7,$H25>N$2),3, IF(AND($F25<=N$2, $H25>=N$2), 2, "" ))) | O25: =IF(AND($F25<(O$2+7),$F25>O$2),1, IF(AND($H25<O$2+7,$H25>O$2),3, IF(AND($F25<=O$2, $H25>=O$2), 2, "" ))) | P25: =IF(AND($F25<(P$2+7),$F25>P$2),1, IF(AND($H25<P$2+7,$H25>P$2),3, IF(AND($F25<=P$2, $H25>=P$2), 2, "" ))) | Q25: =IF(AND($F25<(Q$2+7),$F25>Q$2),1, IF(AND($H25<Q$2+7,$H25>Q$2),3, IF(AND($F25<=Q$2, $H25>=Q$2), 2, "" ))) | R25: =IF(AND($F25<(R$2+7),$F25>R$2),1, IF(AND($H25<R$2+7,$H25>R$2),3, IF(AND($F25<=R$2, $H25>=R$2), 2, "" ))) | S25: =IF(AND($F25<(S$2+7),$F25>S$2),1, IF(AND($H25<S$2+7,$H25>S$2),3, IF(AND($F25<=S$2, $H25>=S$2), 2, "" ))) | ... AQ25: =IF(AND($F25<(AQ$2+7),$F25>AQ$2),1, IF(AND($H25<AQ$2+7,$H25>AQ$2),3, IF(AND($F25<=AQ$2, $H25>=AQ$2), 2, "" )))
B26: Cable tray Installation | C26: 43997 | D26: 3 | E26: 44004 | F26: 43997 | G26: 3 | H26: 44004 | L26: =IF(AND($F26<(L$2+7),$F26>L$2),1, IF(AND($H26<L$2+7,$H26>L$2),3, IF(AND($F26<=L$2, $H26>=L$2), 2, "" ))) | M26: =IF(AND($F26<(M$2+7),$F26>M$2),1, IF(AND($H26<M$2+7,$H26>M$2),3, IF(AND($F26<=M$2, $H26>=M$2), 2, "" ))) | N26: =IF(AND($F26<(N$2+7),$F26>N$2),1, IF(AND($H26<N$2+7,$H26>N$2),3, IF(AND($F26<=N$2, $H26>=N$2), 2, "" ))) | O26: =IF(AND($F26<(O$2+7),$F26>O$2),1, IF(AND($H26<O$2+7,$H26>O$2),3, IF(AND($F26<=O$2, $H26>=O$2), 2, "" ))) | P26: =IF(AND($F26<(P$2+7),$F26>P$2),1, IF(AND($H26<P$2+7,$H26>P$2),3, IF(AND($F26<=P$2, $H26>=P$2), 2, "" ))) | Q26: =IF(AND($F26<(Q$2+7),$F26>Q$2),1, IF(AND($H26<Q$2+7,$H26>Q$2),3, IF(AND($F26<=Q$2, $H26>=Q$2), 2, "" ))) | R26: =IF(AND($F26<(R$2+7),$F26>R$2),1, IF(AND($H26<R$2+7,$H26>R$2),3, IF(AND($F26<=R$2, $H26>=R$2), 2, "" ))) | S26: =IF(AND($F26<(S$2+7),$F26>S$2),1, IF(AND($H26<S$2+7,$H26>S$2),3, IF(AND($F26<=S$2, $H26>=S$2), 2, "" ))) | ... AQ26: =IF(AND($F26<(AQ$2+7),$F26>AQ$2),1, IF(AND($H26<AQ$2+7,$H26>AQ$2),3, IF(AND($F26<=AQ$2, $H26>=AQ$2), 2, "" )))
B27: DC Cable Installation | C27: 44004 | D27: 2 | E27: 44006 | F27: 44004 | G27: 2 | H27: 44006 | L27: =IF(AND($F27<(L$2+7),$F27>L$2),1, IF(AND($H27<L$2+7,$H27>L$2),3, IF(AND($F27<=L$2, $H27>=L$2), 2, "" ))) | M27: =IF(AND($F27<(M$2+7),$F27>M$2),1, IF(AND($H27<M$2+7,$H27>M$2),3, IF(AND($F27<=M$2, $H27>=M$2), 2, "" ))) | N27: =IF(AND($F27<(N$2+7),$F27>N$2),1, IF(AND($H27<N$2+7,$H27>N$2),3, IF(AND($F27<=N$2, $H27>=N$2), 2, "" ))) | O27: =IF(AND($F27<(O$2+7),$F27>O$2),1, IF(AND($H27<O$2+7,$H27>O$2),3, IF(AND($F27<=O$2, $H27>=O$2), 2, "" ))) | P27: =IF(AND($F27<(P$2+7),$F27>P$2),1, IF(AND($H27<P$2+7,$H27>P$2),3, IF(AND($F27<=P$2, $H27>=P$2), 2, "" ))) | Q27: =IF(AND($F27<(Q$2+7),$F27>Q$2),1, IF(AND($H27<Q$2+7,$H27>Q$2),3, IF(AND($F27<=Q$2, $H27>=Q$2), 2, "" ))) | R27: =IF(AND($F27<(R$2+7),$F27>R$2),1, IF(AND($H27<R$2+7,$H27>R$2),3, IF(AND($F27<=R$2, $H27>=R$2), 2, "" ))) | S27: =IF(AND($F27<(S$2+7),$F27>S$2),1, IF(AND($H27<S$2+7,$H27>S$2),3, IF(AND($F27<=S$2, $H27>=S$2), 2, "" ))) | ... AQ27: =IF(AND($F27<(AQ$2+7),$F27>AQ$2),1, IF(AND($H27<AQ$2+7,$H27>AQ$2),3, IF(AND($F27<=AQ$2, $H27>=AQ$2), 2, "" )))
B28: Module Installation | C28: 44006 | D28: 4 | E28: 44012 | F28: 44006 | G28: 4 | H28: 44012 | L28: =IF(AND($F28<(L$2+7),$F28>L$2),1, IF(AND($H28<L$2+7,$H28>L$2),3, IF(AND($F28<=L$2, $H28>=L$2), 2, "" ))) | M28: =IF(AND($F28<(M$2+7),$F28>M$2),1, IF(AND($H28<M$2+7,$H28>M$2),3, IF(AND($F28<=M$2, $H28>=M$2), 2, "" ))) | N28: =IF(AND($F28<(N$2+7),$F28>N$2),1, IF(AND($H28<N$2+7,$H28>N$2),3, IF(AND($F28<=N$2, $H28>=N$2), 2, "" ))) | O28: =IF(AND($F28<(O$2+7),$F28>O$2),1, IF(AND($H28<O$2+7,$H28>O$2),3, IF(AND($F28<=O$2, $H28>=O$2), 2, "" ))) | P28: =IF(AND($F28<(P$2+7),$F28>P$2),1, IF(AND($H28<P$2+7,$H28>P$2),3, IF(AND($F28<=P$2, $H28>=P$2), 2, "" ))) | Q28: =IF(AND($F28<(Q$2+7),$F28>Q$2),1, IF(AND($H28<Q$2+7,$H28>Q$2),3, IF(AND($F28<=Q$2, $H28>=Q$2), 2, "" ))) | R28: =IF(AND($F28<(R$2+7),$F28>R$2),1, IF(AND($H28<R$2+7,$H28>R$2),3, IF(AND($F28<=R$2, $H28>=R$2), 2, "" ))) | S28: =IF(AND($F28<(S$2+7),$F28>S$2),1, IF(AND($H28<S$2+7,$H28>S$2),3, IF(AND($F28<=S$2, $H28>=S$2), 2, "" ))) | ... AQ28: =IF(AND($F28<(AQ$2+7),$F28>AQ$2),1, IF(AND($H28<AQ$2+7,$H28>AQ$2),3, IF(AND($F28<=AQ$2, $H28>=AQ$2), 2, "" ))) -> 2
B29: Earth Cable Installation | C29: 44004 | D29: 1 | E29: 44005 | F29: 44004 | G29: 1 | H29: 44005 | L29: =IF(AND($F29<(L$2+7),$F29>L$2),1, IF(AND($H29<L$2+7,$H29>L$2),3, IF(AND($F29<=L$2, $H29>=L$2), 2, "" ))) | M29: =IF(AND($F29<(M$2+7),$F29>M$2),1, IF(AND($H29<M$2+7,$H29>M$2),3, IF(AND($F29<=M$2, $H29>=M$2), 2, "" ))) | N29: =IF(AND($F29<(N$2+7),$F29>N$2),1, IF(AND($H29<N$2+7,$H29>N$2),3, IF(AND($F29<=N$2, $H29>=N$2), 2, "" ))) | O29: =IF(AND($F29<(O$2+7),$F29>O$2),1, IF(AND($H29<O$2+7,$H29>O$2),3, IF(AND($F29<=O$2, $H29>=O$2), 2, "" ))) | P29: =IF(AND($F29<(P$2+7),$F29>P$2),1, IF(AND($H29<P$2+7,$H29>P$2),3, IF(AND($F29<=P$2, $H29>=P$2), 2, "" ))) | Q29: =IF(AND($F29<(Q$2+7),$F29>Q$2),1, IF(AND($H29<Q$2+7,$H29>Q$2),3, IF(AND($F29<=Q$2, $H29>=Q$2), 2, "" ))) | R29: =IF(AND($F29<(R$2+7),$F29>R$2),1, IF(AND($H29<R$2+7,$H29>R$2),3, IF(AND($F29<=R$2, $H29>=R$2), 2, "" ))) | S29: =IF(AND($F29<(S$2+7),$F29>S$2),1, IF(AND($H29<S$2+7,$H29>S$2),3, IF(AND($F29<=S$2, $H29>=S$2), 2, "" ))) | ... AQ29: =IF(AND($F29<(AQ$2+7),$F29>AQ$2),1, IF(AND($H29<AQ$2+7,$H29>AQ$2),3, IF(AND($F29<=AQ$2, $H29>=AQ$2), 2, "" )))
A30: 10 | B30: AC Works | C30: 43991 | D30: 8 | E30: 44000 | F30: 43991 | G30: 8 | H30: 44000
B31: Inverters Installation | C31: 43991 | D31: 2 | E31: 43993 | F31: 43991 | G31: 2 | H31: 43993 | L31: =IF(AND($F31<(L$2+7),$F31>L$2),1, IF(AND($H31<L$2+7,$H31>L$2),3, IF(AND($F31<=L$2, $H31>=L$2), 2, "" ))) | M31: =IF(AND($F31<(M$2+7),$F31>M$2),1, IF(AND($H31<M$2+7,$H31>M$2),3, IF(AND($F31<=M$2, $H31>=M$2), 2, "" ))) | N31: =IF(AND($F31<(N$2+7),$F31>N$2),1, IF(AND($H31<N$2+7,$H31>N$2),3, IF(AND($F31<=N$2, $H31>=N$2), 2, "" ))) | O31: =IF(AND($F31<(O$2+7),$F31>O$2),1, IF(AND($H31<O$2+7,$H31>O$2),3, IF(AND($F31<=O$2, $H31>=O$2), 2, "" ))) | P31: =IF(AND($F31<(P$2+7),$F31>P$2),1, IF(AND($H31<P$2+7,$H31>P$2),3, IF(AND($F31<=P$2, $H31>=P$2), 2, "" ))) | Q31: =IF(AND($F31<(Q$2+7),$F31>Q$2),1, IF(AND($H31<Q$2+7,$H31>Q$2),3, IF(AND($F31<=Q$2, $H31>=Q$2), 2, "" ))) | R31: =IF(AND($F31<(R$2+7),$F31>R$2),1, IF(AND($H31<R$2+7,$H31>R$2),3, IF(AND($F31<=R$2, $H31>=R$2), 2, "" ))) | S31: =IF(AND($F31<(S$2+7),$F31>S$2),1, IF(AND($H31<S$2+7,$H31>S$2),3, IF(AND($F31<=S$2, $H31>=S$2), 2, "" ))) | ... AQ31: =IF(AND($F31<(AQ$2+7),$F31>AQ$2),1, IF(AND($H31<AQ$2+7,$H31>AQ$2),3, IF(AND($F31<=AQ$2, $H31>=AQ$2), 2, "" )))
B32: AC BOS Installation | C32: 43993 | D32: 3 | E32: 44000 | F32: 43993 | G32: 3 | H32: 44000 | L32: =IF(AND($F32<(L$2+7),$F32>L$2),1, IF(AND($H32<L$2+7,$H32>L$2),3, IF(AND($F32<=L$2, $H32>=L$2), 2, "" ))) | M32: =IF(AND($F32<(M$2+7),$F32>M$2),1, IF(AND($H32<M$2+7,$H32>M$2),3, IF(AND($F32<=M$2, $H32>=M$2), 2, "" ))) | N32: =IF(AND($F32<(N$2+7),$F32>N$2),1, IF(AND($H32<N$2+7,$H32>N$2),3, IF(AND($F32<=N$2, $H32>=N$2), 2, "" ))) | O32: =IF(AND($F32<(O$2+7),$F32>O$2),1, IF(AND($H32<O$2+7,$H32>O$2),3, IF(AND($F32<=O$2, $H32>=O$2), 2, "" ))) | P32: =IF(AND($F32<(P$2+7),$F32>P$2),1, IF(AND($H32<P$2+7,$H32>P$2),3, IF(AND($F32<=P$2, $H32>=P$2), 2, "" ))) | Q32: =IF(AND($F32<(Q$2+7),$F32>Q$2),1, IF(AND($H32<Q$2+7,$H32>Q$2),3, IF(AND($F32<=Q$2, $H32>=Q$2), 2, "" ))) | R32: =IF(AND($F32<(R$2+7),$F32>R$2),1, IF(AND($H32<R$2+7,$H32>R$2),3, IF(AND($F32<=R$2, $H32>=R$2), 2, "" ))) | S32: =IF(AND($F32<(S$2+7),$F32>S$2),1, IF(AND($H32<S$2+7,$H32>S$2),3, IF(AND($F32<=S$2, $H32>=S$2), 2, "" ))) | ... AQ32: =IF(AND($F32<(AQ$2+7),$F32>AQ$2),1, IF(AND($H32<AQ$2+7,$H32>AQ$2),3, IF(AND($F32<=AQ$2, $H32>=AQ$2), 2, "" )))
B33: AC Cable/Tie-In | C33: 43992 | D33: 3 | E33: 43997 | F33: 43992 | G33: 3 | H33: 43997 | L33: =IF(AND($F33<(L$2+7),$F33>L$2),1, IF(AND($H33<L$2+7,$H33>L$2),3, IF(AND($F33<=L$2, $H33>=L$2), 2, "" ))) | M33: =IF(AND($F33<(M$2+7),$F33>M$2),1, IF(AND($H33<M$2+7,$H33>M$2),3, IF(AND($F33<=M$2, $H33>=M$2), 2, "" ))) | N33: =IF(AND($F33<(N$2+7),$F33>N$2),1, IF(AND($H33<N$2+7,$H33>N$2),3, IF(AND($F33<=N$2, $H33>=N$2), 2, "" ))) | O33: =IF(AND($F33<(O$2+7),$F33>O$2),1, IF(AND($H33<O$2+7,$H33>O$2),3, IF(AND($F33<=O$2, $H33>=O$2), 2, "" ))) | P33: =IF(AND($F33<(P$2+7),$F33>P$2),1, IF(AND($H33<P$2+7,$H33>P$2),3, IF(AND($F33<=P$2, $H33>=P$2), 2, "" ))) | Q33: =IF(AND($F33<(Q$2+7),$F33>Q$2),1, IF(AND($H33<Q$2+7,$H33>Q$2),3, IF(AND($F33<=Q$2, $H33>=Q$2), 2, "" ))) | R33: =IF(AND($F33<(R$2+7),$F33>R$2),1, IF(AND($H33<R$2+7,$H33>R$2),3, IF(AND($F33<=R$2, $H33>=R$2), 2, "" ))) | S33: =IF(AND($F33<(S$2+7),$F33>S$2),1, IF(AND($H33<S$2+7,$H33>S$2),3, IF(AND($F33<=S$2, $H33>=S$2), 2, "" ))) | ... AQ33: =IF(AND($F33<(AQ$2+7),$F33>AQ$2),1, IF(AND($H33<AQ$2+7,$H33>AQ$2),3, IF(AND($F33<=AQ$2, $H33>=AQ$2), 2, "" )))
B34: Monitoring Platform Installation | C34: 43997 | D34: 1 | E34: 44000 | F34: 43997 | G34: 1 | H34: 44000
A35: 11 | B35: Completion | C35: 44000 | D35: 14 | E35: 44014 | F35: 44000 | G35: 14 | H35: 44014 | L35: =IF(AND($F35<(L$2+7),$F35>L$2),1, IF(AND($H35<L$2+7,$H35>L$2),3, IF(AND($F35<=L$2, $H35>=L$2), 2, "" ))) | M35: =IF(AND($F35<(M$2+7),$F35>M$2),1, IF(AND($H35<M$2+7,$H35>M$2),3, IF(AND($F35<=M$2, $H35>=M$2), 2, "" ))) | N35: =IF(AND($F35<(N$2+7),$F35>N$2),1, IF(AND($H35<N$2+7,$H35>N$2),3, IF(AND($F35<=N$2, $H35>=N$2), 2, "" ))) | O35: =IF(AND($F35<(O$2+7),$F35>O$2),1, IF(AND($H35<O$2+7,$H35>O$2),3, IF(AND($F35<=O$2, $H35>=O$2), 2, "" ))) | P35: =IF(AND($F35<(P$2+7),$F35>P$2),1, IF(AND($H35<P$2+7,$H35>P$2),3, IF(AND($F35<=P$2, $H35>=P$2), 2, "" ))) | Q35: =IF(AND($F35<(Q$2+7),$F35>Q$2),1, IF(AND($H35<Q$2+7,$H35>Q$2),3, IF(AND($F35<=Q$2, $H35>=Q$2), 2, "" ))) | R35: =IF(AND($F35<(R$2+7),$F35>R$2),1, IF(AND($H35<R$2+7,$H35>R$2),3, IF(AND($F35<=R$2, $H35>=R$2), 2, "" ))) | S35: =IF(AND($F35<(S$2+7),$F35>S$2),1, IF(AND($H35<S$2+7,$H35>S$2),3, IF(AND($F35<=S$2, $H35>=S$2), 2, "" ))) | ... AQ35: =IF(AND($F35<(AQ$2+7),$F35>AQ$2),1, IF(AND($H35<AQ$2+7,$H35>AQ$2),3, IF(AND($F35<=AQ$2, $H35>=AQ$2), 2, "" ))) -> 3
B36: DC Works | C36: 44012 | D36: 2 | E36: 44014 | F36: 44012 | G36: 2 | H36: 44014 | L36: =IF(AND($F36<(L$2+7),$F36>L$2),1, IF(AND($H36<L$2+7,$H36>L$2),3, IF(AND($F36<=L$2, $H36>=L$2), 2, "" ))) | M36: =IF(AND($F36<(M$2+7),$F36>M$2),1, IF(AND($H36<M$2+7,$H36>M$2),3, IF(AND($F36<=M$2, $H36>=M$2), 2, "" ))) | N36: =IF(AND($F36<(N$2+7),$F36>N$2),1, IF(AND($H36<N$2+7,$H36>N$2),3, IF(AND($F36<=N$2, $H36>=N$2), 2, "" ))) | O36: =IF(AND($F36<(O$2+7),$F36>O$2),1, IF(AND($H36<O$2+7,$H36>O$2),3, IF(AND($F36<=O$2, $H36>=O$2), 2, "" ))) | P36: =IF(AND($F36<(P$2+7),$F36>P$2),1, IF(AND($H36<P$2+7,$H36>P$2),3, IF(AND($F36<=P$2, $H36>=P$2), 2, "" ))) | Q36: =IF(AND($F36<(Q$2+7),$F36>Q$2),1, IF(AND($H36<Q$2+7,$H36>Q$2),3, IF(AND($F36<=Q$2, $H36>=Q$2), 2, "" ))) | R36: =IF(AND($F36<(R$2+7),$F36>R$2),1, IF(AND($H36<R$2+7,$H36>R$2),3, IF(AND($F36<=R$2, $H36>=R$2), 2, "" ))) | S36: =IF(AND($F36<(S$2+7),$F36>S$2),1, IF(AND($H36<S$2+7,$H36>S$2),3, IF(AND($F36<=S$2, $H36>=S$2), 2, "" ))) | ... AQ36: =IF(AND($F36<(AQ$2+7),$F36>AQ$2),1, IF(AND($H36<AQ$2+7,$H36>AQ$2),3, IF(AND($F36<=AQ$2, $H36>=AQ$2), 2, "" ))) -> 3
B37: AC Works | C37: 44000 | D37: 2 | E37: 44004 | F37: 44000 | G37: 2 | H37: 44004 | L37: =IF(AND($F37<(L$2+7),$F37>L$2),1, IF(AND($H37<L$2+7,$H37>L$2),3, IF(AND($F37<=L$2, $H37>=L$2), 2, "" ))) | M37: =IF(AND($F37<(M$2+7),$F37>M$2),1, IF(AND($H37<M$2+7,$H37>M$2),3, IF(AND($F37<=M$2, $H37>=M$2), 2, "" ))) | N37: =IF(AND($F37<(N$2+7),$F37>N$2),1, IF(AND($H37<N$2+7,$H37>N$2),3, IF(AND($F37<=N$2, $H37>=N$2), 2, "" ))) | O37: =IF(AND($F37<(O$2+7),$F37>O$2),1, IF(AND($H37<O$2+7,$H37>O$2),3, IF(AND($F37<=O$2, $H37>=O$2), 2, "" ))) | P37: =IF(AND($F37<(P$2+7),$F37>P$2),1, IF(AND($H37<P$2+7,$H37>P$2),3, IF(AND($F37<=P$2, $H37>=P$2), 2, "" ))) | Q37: =IF(AND($F37<(Q$2+7),$F37>Q$2),1, IF(AND($H37<Q$2+7,$H37>Q$2),3, IF(AND($F37<=Q$2, $H37>=Q$2), 2, "" ))) | R37: =IF(AND($F37<(R$2+7),$F37>R$2),1, IF(AND($H37<R$2+7,$H37>R$2),3, IF(AND($F37<=R$2, $H37>=R$2), 2, "" ))) | S37: =IF(AND($F37<(S$2+7),$F37>S$2),1, IF(AND($H37<S$2+7,$H37>S$2),3, IF(AND($F37<=S$2, $H37>=S$2), 2, "" ))) | ... AQ37: =IF(AND($F37<(AQ$2+7),$F37>AQ$2),1, IF(AND($H37<AQ$2+7,$H37>AQ$2),3, IF(AND($F37<=AQ$2, $H37>=AQ$2), 2, "" )))
A38: D | B38: PAYMENT MILESTONE 4: PRACTICAL COMPLETION | C38: 44012 | D38: 1 | E38: 44013 | F38: 44012 | G38: 1 | H38: 44013 | L38: =IF(AND($F38<(L$2+7),$F38>L$2),1, IF(AND($H38<L$2+7,$H38>L$2),3, IF(AND($F38<=L$2, $H38>=L$2), 2, "" ))) | M38: =IF(AND($F38<(M$2+7),$F38>M$2),1, IF(AND($H38<M$2+7,$H38>M$2),3, IF(AND($F38<=M$2, $H38>=M$2), 2, "" ))) | N38: =IF(AND($F38<(N$2+7),$F38>N$2),1, IF(AND($H38<N$2+7,$H38>N$2),3, IF(AND($F38<=N$2, $H38>=N$2), 2, "" ))) | O38: =IF(AND($F38<(O$2+7),$F38>O$2),1, IF(AND($H38<O$2+7,$H38>O$2),3, IF(AND($F38<=O$2, $H38>=O$2), 2, "" ))) | P38: =IF(AND($F38<(P$2+7),$F38>P$2),1, IF(AND($H38<P$2+7,$H38>P$2),3, IF(AND($F38<=P$2, $H38>=P$2), 2, "" ))) | Q38: =IF(AND($F38<(Q$2+7),$F38>Q$2),1, IF(AND($H38<Q$2+7,$H38>Q$2),3, IF(AND($F38<=Q$2, $H38>=Q$2), 2, "" ))) | R38: =IF(AND($F38<(R$2+7),$F38>R$2),1, IF(AND($H38<R$2+7,$H38>R$2),3, IF(AND($F38<=R$2, $H38>=R$2), 2, "" ))) | S38: =IF(AND($F38<(S$2+7),$F38>S$2),1, IF(AND($H38<S$2+7,$H38>S$2),3, IF(AND($F38<=S$2, $H38>=S$2), 2, "" ))) | ... AQ38: =IF(AND($F38<(AQ$2+7),$F38>AQ$2),1, IF(AND($H38<AQ$2+7,$H38>AQ$2),3, IF(AND($F38<=AQ$2, $H38>=AQ$2), 2, "" ))) -> 3
A39: 12 | B39: Commissioning | C39: 43997 | D39: 22 | E39: 44019 | F39: 43997 | G39: 22 | H39: 44019 | L39: =IF(AND($F39<(L$2+7),$F39>L$2),1, IF(AND($H39<L$2+7,$H39>L$2),3, IF(AND($F39<=L$2, $H39>=L$2), 2, "" ))) | M39: =IF(AND($F39<(M$2+7),$F39>M$2),1, IF(AND($H39<M$2+7,$H39>M$2),3, IF(AND($F39<=M$2, $H39>=M$2), 2, "" ))) | N39: =IF(AND($F39<(N$2+7),$F39>N$2),1, IF(AND($H39<N$2+7,$H39>N$2),3, IF(AND($F39<=N$2, $H39>=N$2), 2, "" ))) | O39: =IF(AND($F39<(O$2+7),$F39>O$2),1, IF(AND($H39<O$2+7,$H39>O$2),3, IF(AND($F39<=O$2, $H39>=O$2), 2, "" ))) | P39: =IF(AND($F39<(P$2+7),$F39>P$2),1, IF(AND($H39<P$2+7,$H39>P$2),3, IF(AND($F39<=P$2, $H39>=P$2), 2, "" ))) | Q39: =IF(AND($F39<(Q$2+7),$F39>Q$2),1, IF(AND($H39<Q$2+7,$H39>Q$2),3, IF(AND($F39<=Q$2, $H39>=Q$2), 2, "" ))) | R39: =IF(AND($F39<(R$2+7),$F39>R$2),1, IF(AND($H39<R$2+7,$H39>R$2),3, IF(AND($F39<=R$2, $H39>=R$2), 2, "" ))) | S39: =IF(AND($F39<(S$2+7),$F39>S$2),1, IF(AND($H39<S$2+7,$H39>S$2),3, IF(AND($F39<=S$2, $H39>=S$2), 2, "" ))) | ... AQ39: =IF(AND($F39<(AQ$2+7),$F39>AQ$2),1, IF(AND($H39<AQ$2+7,$H39>AQ$2),3, IF(AND($F39<=AQ$2, $H39>=AQ$2), 2, "" ))) -> 2
B40: Snag List | C40: 44014 | D40: 3 | E40: 44019 | F40: 44014 | G40: 3 | H40: 44019
B41: Pre-Commissioning Checks | C41: 44010 | D41: 2 | E41: 44012 | F41: 44010 | G41: 2 | H41: 44012
B42: Issue CoC | C42: 43997 | D42: 2 | E42: 44001 | F42: 43997 | G42: 2 | H42: 44001 | L42: =IF(AND($F42<(L$2+7),$F42>L$2),1, IF(AND($H42<L$2+7,$H42>L$2),3, IF(AND($F42<=L$2, $H42>=L$2), 2, "" ))) | M42: =IF(AND($F42<(M$2+7),$F42>M$2),1, IF(AND($H42<M$2+7,$H42>M$2),3, IF(AND($F42<=M$2, $H42>=M$2), 2, "" ))) | N42: =IF(AND($F42<(N$2+7),$F42>N$2),1, IF(AND($H42<N$2+7,$H42>N$2),3, IF(AND($F42<=N$2, $H42>=N$2), 2, "" ))) | O42: =IF(AND($F42<(O$2+7),$F42>O$2),1, IF(AND($H42<O$2+7,$H42>O$2),3, IF(AND($F42<=O$2, $H42>=O$2), 2, "" ))) | P42: =IF(AND($F42<(P$2+7),$F42>P$2),1, IF(AND($H42<P$2+7,$H42>P$2),3, IF(AND($F42<=P$2, $H42>=P$2), 2, "" ))) | Q42: =IF(AND($F42<(Q$2+7),$F42>Q$2),1, IF(AND($H42<Q$2+7,$H42>Q$2),3, IF(AND($F42<=Q$2, $H42>=Q$2), 2, "" ))) | R42: =IF(AND($F42<(R$2+7),$F42>R$2),1, IF(AND($H42<R$2+7,$H42>R$2),3, IF(AND($F42<=R$2, $H42>=R$2), 2, "" ))) | S42: =IF(AND($F42<(S$2+7),$F42>S$2),1, IF(AND($H42<S$2+7,$H42>S$2),3, IF(AND($F42<=S$2, $H42>=S$2), 2, "" ))) | ... AQ42: =IF(AND($F42<(AQ$2+7),$F42>AQ$2),1, IF(AND($H42<AQ$2+7,$H42>AQ$2),3, IF(AND($F42<=AQ$2, $H42>=AQ$2), 2, "" )))
B43: Cold Commissioning | C43: 44012 | D43: 1 | E43: 44013 | F43: 44012 | G43: 1 | H43: 44013 | L43: =IF(AND($F43<(L$2+7),$F43>L$2),1, IF(AND($H43<L$2+7,$H43>L$2),3, IF(AND($F43<=L$2, $H43>=L$2), 2, "" ))) | M43: =IF(AND($F43<(M$2+7),$F43>M$2),1, IF(AND($H43<M$2+7,$H43>M$2),3, IF(AND($F43<=M$2, $H43>=M$2), 2, "" ))) | N43: =IF(AND($F43<(N$2+7),$F43>N$2),1, IF(AND($H43<N$2+7,$H43>N$2),3, IF(AND($F43<=N$2, $H43>=N$2), 2, "" ))) | O43: =IF(AND($F43<(O$2+7),$F43>O$2),1, IF(AND($H43<O$2+7,$H43>O$2),3, IF(AND($F43<=O$2, $H43>=O$2), 2, "" ))) | P43: =IF(AND($F43<(P$2+7),$F43>P$2),1, IF(AND($H43<P$2+7,$H43>P$2),3, IF(AND($F43<=P$2, $H43>=P$2), 2, "" ))) | Q43: =IF(AND($F43<(Q$2+7),$F43>Q$2),1, IF(AND($H43<Q$2+7,$H43>Q$2),3, IF(AND($F43<=Q$2, $H43>=Q$2), 2, "" ))) | R43: =IF(AND($F43<(R$2+7),$F43>R$2),1, IF(AND($H43<R$2+7,$H43>R$2),3, IF(AND($F43<=R$2, $H43>=R$2), 2, "" ))) | S43: =IF(AND($F43<(S$2+7),$F43>S$2),1, IF(AND($H43<S$2+7,$H43>S$2),3, IF(AND($F43<=S$2, $H43>=S$2), 2, "" ))) | ... AQ43: =IF(AND($F43<(AQ$2+7),$F43>AQ$2),1, IF(AND($H43<AQ$2+7,$H43>AQ$2),3, IF(AND($F43<=AQ$2, $H43>=AQ$2), 2, "" ))) -> 3
B44: Hot Commissioning | C44: 44013 | D44: 2 | E44: 44015 | F44: 44013 | G44: 2 | H44: 44015 | L44: =IF(AND($F44<(L$2+7),$F44>L$2),1, IF(AND($H44<L$2+7,$H44>L$2),3, IF(AND($F44<=L$2, $H44>=L$2), 2, "" ))) | M44: =IF(AND($F44<(M$2+7),$F44>M$2),1, IF(AND($H44<M$2+7,$H44>M$2),3, IF(AND($F44<=M$2, $H44>=M$2), 2, "" ))) | N44: =IF(AND($F44<(N$2+7),$F44>N$2),1, IF(AND($H44<N$2+7,$H44>N$2),3, IF(AND($F44<=N$2, $H44>=N$2), 2, "" ))) | O44: =IF(AND($F44<(O$2+7),$F44>O$2),1, IF(AND($H44<O$2+7,$H44>O$2),3, IF(AND($F44<=O$2, $H44>=O$2), 2, "" ))) | P44: =IF(AND($F44<(P$2+7),$F44>P$2),1, IF(AND($H44<P$2+7,$H44>P$2),3, IF(AND($F44<=P$2, $H44>=P$2), 2, "" ))) | Q44: =IF(AND($F44<(Q$2+7),$F44>Q$2),1, IF(AND($H44<Q$2+7,$H44>Q$2),3, IF(AND($F44<=Q$2, $H44>=Q$2), 2, "" ))) | R44: =IF(AND($F44<(R$2+7),$F44>R$2),1, IF(AND($H44<R$2+7,$H44>R$2),3, IF(AND($F44<=R$2, $H44>=R$2), 2, "" ))) | S44: =IF(AND($F44<(S$2+7),$F44>S$2),1, IF(AND($H44<S$2+7,$H44>S$2),3, IF(AND($F44<=S$2, $H44>=S$2), 2, "" ))) | ... AQ44: =IF(AND($F44<(AQ$2+7),$F44>AQ$2),1, IF(AND($H44<AQ$2+7,$H44>AQ$2),3, IF(AND($F44<=AQ$2, $H44>=AQ$2), 2, "" ))) -> 1
A45: 13 | B45: Handover | C45: 44020 | D45: 1 | E45: 44021 | F45: 44020 | G45: 1 | H45: 44021 | L45: =IF(AND($F45<(L$2+7),$F45>L$2),1, IF(AND($H45<L$2+7,$H45>L$2),3, IF(AND($F45<=L$2, $H45>=L$2), 2, "" ))) | M45: =IF(AND($F45<(M$2+7),$F45>M$2),1, IF(AND($H45<M$2+7,$H45>M$2),3, IF(AND($F45<=M$2, $H45>=M$2), 2, "" ))) | N45: =IF(AND($F45<(N$2+7),$F45>N$2),1, IF(AND($H45<N$2+7,$H45>N$2),3, IF(AND($F45<=N$2, $H45>=N$2), 2, "" ))) | O45: =IF(AND($F45<(O$2+7),$F45>O$2),1, IF(AND($H45<O$2+7,$H45>O$2),3, IF(AND($F45<=O$2, $H45>=O$2), 2, "" ))) | P45: =IF(AND($F45<(P$2+7),$F45>P$2),1, IF(AND($H45<P$2+7,$H45>P$2),3, IF(AND($F45<=P$2, $H45>=P$2), 2, "" ))) | Q45: =IF(AND($F45<(Q$2+7),$F45>Q$2),1, IF(AND($H45<Q$2+7,$H45>Q$2),3, IF(AND($F45<=Q$2, $H45>=Q$2), 2, "" ))) | R45: =IF(AND($F45<(R$2+7),$F45>R$2),1, IF(AND($H45<R$2+7,$H45>R$2),3, IF(AND($F45<=R$2, $H45>=R$2), 2, "" ))) | S45: =IF(AND($F45<(S$2+7),$F45>S$2),1, IF(AND($H45<S$2+7,$H45>S$2),3, IF(AND($F45<=S$2, $H45>=S$2), 2, "" ))) | ... AQ45: =IF(AND($F45<(AQ$2+7),$F45>AQ$2),1, IF(AND($H45<AQ$2+7,$H45>AQ$2),3, IF(AND($F45<=AQ$2, $H45>=AQ$2), 2, "" )))
A46: E | B46: PAYMENT MILESTONE 6: HANDOVER COMPLETE | C46: 44022 | D46: 1 | E46: 44025 | F46: 44022 | G46: 1 | H46: 44025
C47: 43831 | D47: These numbers are used to set the start and end dates on the Gantt Chart
C48: 44014

Sheet Certificate - Financial Close
B2: Emergent Energy – Financial Close Completion Certificate | H2: FINANCIAL CLOSE CERTIFICATE
B4: Project Name: | C4: ='Project Plan'!E2 -> Seshego Circle
B5: COO: | C5: Johannes Potgieter
B6: Programme Manager: | C6: Roedolph Venter
B7: HoPD: | C7: Natasha Watkins-Baker
B9: Date of Phase Completion:
B10: Phase Deliverables Checklist: (Y/N)
B11: Product Agreement
B12: EPC Agreement
B13: O&M Agreeement
B14: Cost Proposal
B15: Deposit Received
B16: Risks / Notes
B18: Acknowledgement and Acceptance:
B19: Role | C19: Name | D19: Signature | E19: Date

Sheet Certificate - Planning
B2: Emergent Energy – Planning Phase Completion Certificate | H2: PLANNING CERTIFICATE
B4: Project Name: | C4: ='Project Plan'!E2 -> Seshego Circle
B5: Client Representative:
B6: Programme Manager: | C6: Roedolph Venter
B7: Project Manager: | C7: ='Project Plan'!E5 -> Eon Van Rensburg
B8: Project Engineer:
B10: Date of Phase Completion:
B11: Phase Deliverables Checklist: (Y/N)
B12: Project Introduction Presentation
B13: Project Brief
B14: Engineering Pack
B15: BOQ
B16: PO – Material & Equipment
B17: PO - Contractors
B18: HSE – NOC
B19: HSE – EE File
B20: HSE – Contractor File
... B24: Acknowledgement and Acceptance:
B25: Role | C25: Name | D25: Signature | E25: Date

Sheet Change Register
F1: Change Register
B3: ID | C3: Description | D3: Supporting Image (If Applicable) | E3: Impact | F3: Proposed Date | G3: Proposed By | H3: Status | I3: Approved By | J3: Approved Date | K3: Results / Comments
B4: DEC001
B5: DEC002
B6: DEC003
B7: DEC004
B8: DEC005
B9: DEC006
B10: DEC007
B11: DEC008
B12: DEC009
B13: DEC010
B14: DEC011
B15: DEC012
... B33: DEC030

Sheet BOQ
B2: Item | C2: Supplier | D2: Description | E2: Quantity | F2: Comments
B3: PV Module
B4: DC Cable Red & Black
B5: Inverters
B6: Mounting Structure
B7: Current Transformers (Production)
B8: Current Transformers (Consumption)
B9: Solar Production Meter (Techistter)
B10: Grid Consumption Meter
B11: Wi-Fi Router & Sim
B12: Switch
B13: Back Up Battery
B14: PVDB
... B30: Techsitter

Sheet Compliance
B2: HSE
B4: Description | C4: Status | D4: Approved By | E4: Date | F4: Results / Comments
B5: NOC
B6: 7.1 Agreement
B7: 13.2 Agreement
B8: EE File
B9: Subbie File
B16: SSEG
B18: Description | C18: Status | D18: Approved By | E18: Date | F18: Results / Comments
B19: SSEG Application
B20: PTI
B21: Commissioning Approval

Sheet Project Plan
N1: =TODAY() -> 46055 | O1: =TODAY() -> 46055
C2: PROJECT PLAN | E2: Seshego Circle | N2: 0 | O2: 1
C3: PROJECT SIZE (kWp) | E3: 1360
C4: PROJECT DEVELOPER | E4: Dayne Sage | J4: Target Month | K4: 45961
C5: PROJECT MANAGERS | E5: Eon Van Rensburg
C6: CONTRACT VALUE | E6: 10428344
C7: Phase: | E7: Construction
B8: No. | C8: HIGH LEVEL PROGRAMME | E8: Planned Start | F8: Duration (days) | G8: Planned End | I8: Actual Start | J8: Duration (days) | K8: Actual End | M8: Status | N8: Status | O8: Comment
F9: =G49-E19 -> 60 | J9: =K49-I19 -> 123 | M9: =AVERAGE(M11,M18,M23,M32,M41,M46,M54,M51) -> 0.55776907 | N9: =AVERAGE(N11,N18,N23,N32,N41,N46,N54,N51) -> 0.53062263
B11: 1 | C11: Project Initiation | E11: =MIN(E12:E16) -> 45845 | F11: =G11-E11 -> 94 | G11: =MAX(G12:G16) -> 45939 | I11: =MIN(I12:I16) -> 45845 | J11: =K11-I11 -> 94 | K11: =MAX(K12:K16) -> 45939 | M11: =(J12*M12+J13*M13+J14*M14+J15*M15+J16*M16)/SUM(J12:J16) -> 1 | N11: =(K12*N12+K13*N13+K14*N14+K15*N15+K16*N16)/SUM(K12:K16) -> 1
B12: 1.1 | C12: BD Handover | E12: 45845 | F12: 5 | G12: =WORKDAY.INTL(E12,F12,1,Data!$C$3:$C$45) -> 45852 | I12: 45845 | J12: 5 | K12: =WORKDAY.INTL(I12,J12,1,Data!$C$3:$C$45) -> 45852 | M12: 1 | N12: =_xlfn.LET( _xlpm.s,VALUE($I12), _xlpm.e,VALUE($K12), IF(OR(_xlpm.s="",_xlpm.e=""),"", IF(_xlpm.e<=_xlpm.s, IF(TODAY()>=_xlpm.e,1,0), MAX(0,MIN(1,(TODAY()-_xlpm.s)/(_xlpm.e-_xlpm.s))))) ) -> 1
B13: 1.2 | C13: Project Introduction | E13: =WORKDAY.INTL(E19,0,1,Data!$C$3:$C$45)-14 -> 45929 | F13: 1 | G13: =WORKDAY.INTL(E13,F13,1,Data!$C$3:$C$45) -> 45930 | I13: =WORKDAY.INTL(I19,0,1,Data!$C$3:$C$45)-14 -> 45929 | J13: 1 | K13: =WORKDAY.INTL(I13,J13,1,Data!$C$3:$C$45) -> 45930 | M13: 1 | N13: =_xlfn.LET( _xlpm.s,VALUE($I13), _xlpm.e,VALUE($K13), IF(OR(_xlpm.s="",_xlpm.e=""),"", IF(_xlpm.e<=_xlpm.s, IF(TODAY()>=_xlpm.e,1,0), MAX(0,MIN(1,(TODAY()-_xlpm.s)/(_xlpm.e-_xlpm.s))))) ) -> 1
B14: 1.3 | C14: HSE | E14: =E13 -> 45929 | F14: 8 | G14: =WORKDAY.INTL(E14,F14,1,Data!$C$3:$C$45) -> 45939 | I14: =I13 -> 45929 | J14: 8 | K14: =WORKDAY.INTL(I14,J14,1,Data!$C$3:$C$45) -> 45939 | M14: 1 | N14: =_xlfn.LET( _xlpm.s,VALUE($I14), _xlpm.e,VALUE($K14), IF(OR(_xlpm.s="",_xlpm.e=""),"", IF(_xlpm.e<=_xlpm.s, IF(TODAY()>=_xlpm.e,1,0), MAX(0,MIN(1,(TODAY()-_xlpm.s)/(_xlpm.e-_xlpm.s))))) ) -> 1
B15: 1.4 | C15: Installer Kick Off | E15: =WORKDAY.INTL(E19,0,1,Data!$C$3:$C$45)-14 -> 45929 | F15: 1 | G15: =WORKDAY.INTL(E15,F15,1,Data!$C$3:$C$45) -> 45930 | I15: =WORKDAY.INTL(I19,0,1,Data!$C$3:$C$45)-14 -> 45929 | J15: 1 | K15: =WORKDAY.INTL(I15,J15,1,Data!$C$3:$C$45) -> 45930 | M15: 1 | N15: =_xlfn.LET( _xlpm.s,VALUE($I15), _xlpm.e,VALUE($K15), IF(OR(_xlpm.s="",_xlpm.e=""),"", IF(_xlpm.e<=_xlpm.s, IF(TODAY()>=_xlpm.e,1,0), MAX(0,MIN(1,(TODAY()-_xlpm.s)/(_xlpm.e-_xlpm.s))))) ) -> 1
B16: 1.5 | C16: Project Review | E16: =WORKDAY.INTL(E19,0,1,Data!$C$3:$C$45)-14 -> 45929 | F16: 1 | G16: =WORKDAY.INTL(E16,F16,1,Data!$C$3:$C$45) -> 45930 | I16: =WORKDAY.INTL(I19,0,1,Data!$C$3:$C$45)-14 -> 45929 | J16: 1 | K16: =WORKDAY.INTL(I16,J16,1,Data!$C$3:$C$45) -> 45930 | M16: 1 | N16: =_xlfn.LET( _xlpm.s,VALUE($I16), _xlpm.e,VALUE($K16), IF(OR(_xlpm.s="",_xlpm.e=""),"", IF(_xlpm.e<=_xlpm.s, IF(TODAY()>=_xlpm.e,1,0), MAX(0,MIN(1,(TODAY()-_xlpm.s)/(_xlpm.e-_xlpm.s))))) ) -> 1
B18: 2 | C18: Site Establishment | E18: =MIN(E19:E22) -> 45943 | F18: =G18-E18 -> 1 | G18: =MAX(G19) -> 45944 | I18: =MIN(I19:I22) -> 45943 | J18: =K18-I18 -> 1 | K18: =MAX(K19) -> 45944 | M18: =(J19*M19)/J18 -> 1 | N18: =(K19*N19)/K18 -> 1
B19: 2.1 | C19: Solar Contractor Establishment | E19: 45943 | F19: 1 | G19: =E19+F19 -> 45944 | I19: 45943 | J19: 1 | K19: =I19+J19 -> 45944 | M19: 1 | N19: =_xlfn.LET( _xlpm.s,VALUE($I19), _xlpm.e,VALUE($K19), IF(OR(_xlpm.s="",_xlpm.e=""),"", IF(_xlpm.e<=_xlpm.s, IF(TODAY()>=_xlpm.e,1,0), MAX(0,MIN(1,(TODAY()-_xlpm.s)/(_xlpm.e-_xlpm.s))))) ) -> 1 | S19: =NETWORKDAYS(I19,K49,Data!C3:C46) -> 66 | T19: Net Work Days
B20: 2.2 | C20: Civil Works | I20: 45957 | J20: 36 | K20: =I20+J20 -> 45993 | M20: 1 | N20: =_xlfn.LET( _xlpm.s,VALUE($I20), _xlpm.e,VALUE($K20), IF(OR(_xlpm.s="",_xlpm.e=""),"", IF(_xlpm.e<=_xlpm.s, IF(TODAY()>=_xlpm.e,1,0), MAX(0,MIN(1,(TODAY()-_xlpm.s)/(_xlpm.e-_xlpm.s))))) ) -> 1 | O20: Inverter stands
B21: 2.2 | C21: Roof Remedial Work | I21: 45950 | J21: 10 | K21: =I21+J21 -> 45960 | M21: 1 | N21: =_xlfn.LET( _xlpm.s,VALUE($I21), _xlpm.e,VALUE($K21), IF(OR(_xlpm.s="",_xlpm.e=""),"", IF(_xlpm.e<=_xlpm.s, IF(TODAY()>=_xlpm.e,1,0), MAX(0,MIN(1,(TODAY()-_xlpm.s)/(_xlpm.e-_xlpm.s))))) ) -> 1
B23: 3 | C23: AC Installation | E23: =MIN(E24:E30) -> 45929 | F23: =G23-E23 -> 52 | G23: =MAX(G24:G30) -> 45981 | I23: =MIN(I24:I30) -> 45929 | J23: =K23-I23 -> 133 | K23: =MAX(K24:K30) -> 46062 | M23: =(J24*M24+J25*M25+J26*M26+J27*M27+J30*M30)/SUM(J24:J30) -> 0.83606557 | N23: =(K24*N24+K25*N25+K26*N26+K27*N27+K30*N30)/SUM(K24:K30) -> 0.57106803 | S23: =S19/5 -> 13.2 | T23: Total Weeks
B24: 3.1 | C24: Inverters delivered | E24: =E19 -> 45943 | F24: 1 | G24: =WORKDAY.INTL(E24,F24,1,Data!$C$3:$C$45) -> 45944 | I24: =I19 -> 45943 | J24: 1 | K24: =WORKDAY.INTL(I24,J24,1,Data!$C$3:$C$45) -> 45944 | M24: 1 | N24: =_xlfn.LET( _xlpm.s,VALUE($I24), _xlpm.e,VALUE($K24), IF(OR(_xlpm.s="",_xlpm.e=""),"", IF(_xlpm.e<=_xlpm.s, IF(TODAY()>=_xlpm.e,1,0), MAX(0,MIN(1,(TODAY()-_xlpm.s)/(_xlpm.e-_xlpm.s))))) ) -> 1 | S24: =E3/S23 -> 103.0303 | T24: kW/Week Installation Rate
B25: 3.2 | C25: Inverters Mounted | E25: =WORKDAY.INTL(G24,0,1,Data!$C$3:$C$45)+21 -> 45965 | F25: 1 | G25: =WORKDAY.INTL(E25,F25,1,Data!$C$3:$C$45) -> 45966 | I25: =WORKDAY.INTL(K20,0,1,Data!$C$3:$C$45) -> 45993 | J25: 1 | K25: =WORKDAY.INTL(I25,J25,1,Data!$C$3:$C$45) -> 45994 | M25: 1 | N25: =_xlfn.LET( _xlpm.s,VALUE($I25), _xlpm.e,VALUE($K25), IF(OR(_xlpm.s="",_xlpm.e=""),"", IF(_xlpm.e<=_xlpm.s, IF(TODAY()>=_xlpm.e,1,0), MAX(0,MIN(1,(TODAY()-_xlpm.s)/(_xlpm.e-_xlpm.s))))) ) -> 1
B26: 3.3 | C26: Solar DB Lead Time | E26: =WORKDAY.INTL(E19,0,1,Data!$C$3:$C$45)-14 -> 45929 | F26: 30 | G26: =WORKDAY.INTL(E26,F26,1,Data!$C$3:$C$45) -> 45971 | I26: =WORKDAY.INTL(I19,0,1,Data!$C$3:$C$45)-14 -> 45929 | J26: 34 | K26: =WORKDAY.INTL(I26,J26,1,Data!$C$3:$C$45) -> 45975 | M26: 1 | N26: =_xlfn.LET( _xlpm.s,VALUE($I26), _xlpm.e,VALUE($K26), IF(OR(_xlpm.s="",_xlpm.e=""),"", IF(_xlpm.e<=_xlpm.s, IF(TODAY()>=_xlpm.e,1,0), MAX(0,MIN(1,(TODAY()-_xlpm.s)/(_xlpm.e-_xlpm.s))))) ) -> 1
B27: 3.4 | C27: AC Works - Tie In 1 | E27: =WORKDAY.INTL(G26,0,1,Data!$C$3:$C$45) -> 45971 | F27: 8 | G27: =WORKDAY.INTL(E27,F27,1,Data!$C$3:$C$45) -> 45981 | I27: =WORKDAY.INTL(K20,0,1,Data!$C$3:$C$45) -> 45993 | J27: 15 | K27: =WORKDAY.INTL(I27,J27,1,Data!$C$3:$C$45) -> 46048 | M27: 1 | N27: =_xlfn.LET( _xlpm.s,VALUE($I27), _xlpm.e,VALUE($K27), IF(OR(_xlpm.s="",_xlpm.e=""),"", IF(_xlpm.e<=_xlpm.s, IF(TODAY()>=_xlpm.e,1,0), MAX(0,MIN(1,(TODAY()-_xlpm.s)/(_xlpm.e-_xlpm.s))))) ) -> 1
B28: 3.5 | C28: AC Works - Tie In 2 | I28: 46034 | J28: 8 | K28: =WORKDAY.INTL(I28,J28,1,Data!$C$3:$C$45) -> 46050 | M28: 1 | N28: =_xlfn.LET( _xlpm.s,VALUE($I28), _xlpm.e,VALUE($K28), IF(OR(_xlpm.s="",_xlpm.e=""),"", IF(_xlpm.e<=_xlpm.s, IF(TODAY()>=_xlpm.e,1,0), MAX(0,MIN(1,(TODAY()-_xlpm.s)/(_xlpm.e-_xlpm.s))))) ) -> 1
B29: 3.6 | C29: AC Tie In 1 | I29: 46059 | J29: 1 | K29: =WORKDAY.INTL(I29,J29,1,Data!$C$3:$C$45) -> 46062 | M29: 0 | N29: =_xlfn.LET( _xlpm.s,VALUE($I29), _xlpm.e,VALUE($K29), IF(OR(_xlpm.s="",_xlpm.e=""),"", IF(_xlpm.e<=_xlpm.s, IF(TODAY()>=_xlpm.e,1,0), MAX(0,MIN(1,(TODAY()-_xlpm.s)/(_xlpm.e-_xlpm.s))))) ) -> 0
B30: 3.7 | C30: AC Tie-In 2 | E30: =WORKDAY.INTL(E27,0,1,Data!$C$3:$C$45) -> 45971 | F30: 2 | G30: =WORKDAY.INTL(E30,F30,1,Data!$C$3:$C$45) -> 45973 | I30: 46059 | J30: 1 | K30: =WORKDAY.INTL(I30,J30,1,Data!$C$3:$C$45) -> 46062 | M30: 0 | N30: =_xlfn.LET( _xlpm.s,VALUE($I30), _xlpm.e,VALUE($K30), IF(OR(_xlpm.s="",_xlpm.e=""),"", IF(_xlpm.e<=_xlpm.s, IF(TODAY()>=_xlpm.e,1,0), MAX(0,MIN(1,(TODAY()-_xlpm.s)/(_xlpm.e-_xlpm.s))))) ) -> 0
B32: 4 | C32: DC Works | E32: =MIN(E34:E39) -> 45943 | F32: =G32-E32 -> 53 | G32: =MAX(G34:G39) -> 45996 | I32: =MIN(I34:I39) -> 45943 | J32: =K32-I32 -> 100 | K32: =MAX(K34:K39) -> 46043 | M32: =(J34*M34+J35*M35+J39*M39)/SUM(J34:J39) -> 0.62608696 | N32: =(J34*N34+J35*N35+J39*N39)/SUM(J34:J39) -> 0.67391304
B33: 4.1 | C33: Lifeline Installation (If Applicable) | M33: 0 | N33: 0
B34: 4.1 | C34: Mounting Structure delivered | E34: =E24 -> 45943 | F34: 1 | G34: =WORKDAY.INTL(E34,F34,1,Data!$C$3:$C$45) -> 45944 | I34: =I24 -> 45943 | J34: 1 | K34: =WORKDAY.INTL(I34,J34,1,Data!$C$3:$C$45) -> 45944 | M34: 1 | N34: =_xlfn.LET( _xlpm.s,VALUE($I34), _xlpm.e,VALUE($K34), IF(OR(_xlpm.s="",_xlpm.e=""),"", IF(_xlpm.e<=_xlpm.s, IF(TODAY()>=_xlpm.e,1,0), MAX(0,MIN(1,(TODAY()-_xlpm.s)/(_xlpm.e-_xlpm.s))))) ) -> 1
B35: 4.2 | C35: Mounting Structure installation -Tie In 1 | E35: =WORKDAY.INTL(G34,0,1,Data!$C$3:$C$45) -> 45944 | F35: 10 | G35: =WORKDAY.INTL(E35,F35,1,Data!$C$3:$C$45) -> 45958 | I35: =WORKDAY.INTL(K21,0,1,Data!$C$3:$C$45)-3 -> 45957 | J35: 8 | K35: =WORKDAY.INTL(I35,J35,1,Data!$C$3:$C$45) -> 45967 | M35: 1 | N35: =_xlfn.LET( _xlpm.s,VALUE($I35), _xlpm.e,VALUE($K35), IF(OR(_xlpm.s="",_xlpm.e=""),"", IF(_xlpm.e<=_xlpm.s, IF(TODAY()>=_xlpm.e,1,0), MAX(0,MIN(1,(TODAY()-_xlpm.s)/(_xlpm.e-_xlpm.s))))) ) -> 1
B36: 4.3 | C36: Mounting Structure installation -Tie In 2 | I36: =WORKDAY.INTL(K35,0,1,Data!$C$3:$C$45)+7 -> 45974 | J36: 8 | K36: =WORKDAY.INTL(I36,J36,1,Data!$C$3:$C$45) -> 45986 | M36: 1 | N36: =_xlfn.LET( _xlpm.s,VALUE($I36), _xlpm.e,VALUE($K36), IF(OR(_xlpm.s="",_xlpm.e=""),"", IF(_xlpm.e<=_xlpm.s, IF(TODAY()>=_xlpm.e,1,0), MAX(0,MIN(1,(TODAY()-_xlpm.s)/(_xlpm.e-_xlpm.s))))) ) -> 1
B37: 4.4 | C37: DC Cable delivered | E37: =E24 -> 45943 | F37: 1 | G37: =WORKDAY.INTL(E37,F37,1,Data!$C$3:$C$45) -> 45944 | I37: =I24 -> 45943 | J37: 1 | K37: =WORKDAY.INTL(I37,J37,1,Data!$C$3:$C$45) -> 45944 | M37: 1 | N37: =_xlfn.LET( _xlpm.s,VALUE($I37), _xlpm.e,VALUE($K37), IF(OR(_xlpm.s="",_xlpm.e=""),"", IF(_xlpm.e<=_xlpm.s, IF(TODAY()>=_xlpm.e,1,0), MAX(0,MIN(1,(TODAY()-_xlpm.s)/(_xlpm.e-_xlpm.s))))) ) -> 1
B38: 4.5 | C38: DC Stringing Tie In 1 | I38: =K43-5 -> 45976 | J38: 6 | K38: =WORKDAY.INTL(I38,J38,1,Data!$C$3:$C$45) -> 45985 | M38: 1 | N38: =_xlfn.LET( _xlpm.s,VALUE($I38), _xlpm.e,VALUE($K38), IF(OR(_xlpm.s="",_xlpm.e=""),"", IF(_xlpm.e<=_xlpm.s, IF(TODAY()>=_xlpm.e,1,0), MAX(0,MIN(1,(TODAY()-_xlpm.s)/(_xlpm.e-_xlpm.s))))) ) -> 1
B39: 4.6 | C39: DC Stringing Tie In 2 | E39: =WORKDAY.INTL(G43,0,1,Data!$C$3:$C$45)-3 -> 45976 | F39: 15 | G39: =WORKDAY.INTL(E39,F39,1,Data!$C$3:$C$45) -> 45996 | I39: =WORKDAY.INTL(K44,0,1,Data!$C$3:$C$45)-14 -> 45979 | J39: 22 | K39: =WORKDAY.INTL(I39,J39,1,Data!$C$3:$C$45) -> 46043 | M39: 0.9 | N39: =_xlfn.LET( _xlpm.s,VALUE($I39), _xlpm.e,VALUE($K39), IF(OR(_xlpm.s="",_xlpm.e=""),"", IF(_xlpm.e<=_xlpm.s, IF(TODAY()>=_xlpm.e,1,0), MAX(0,MIN(1,(TODAY()-_xlpm.s)/(_xlpm.e-_xlpm.s))))) ) -> 1
B41: 5 | C41: Module installation | E41: =MIN(E42:E43) -> 45943 | F41: =G41-E41 -> 36 | G41: =MAX(G42:G43) -> 45979 | I41: =MIN(I42:I43) -> 45943 | J41: =K41-I41 -> 38 | K41: =MAX(K42:K43) -> 45981 | M41: =(J42*M42+J43*M43)/SUM(J42:J43) -> 1 | N41: =(J42*N42+J43*N43)/SUM(J42:J43) -> 1
B42: 5.1 | C42: Module delivery | E42: =E24 -> 45943 | F42: 1 | G42: =WORKDAY.INTL(E42,F42,1,Data!$C$3:$C$45) -> 45944 | I42: =I24 -> 45943 | J42: 1 | K42: =WORKDAY.INTL(I42,J42,1,Data!$C$3:$C$45) -> 45944 | M42: 1 | N42: =_xlfn.LET( _xlpm.s,VALUE($I42), _xlpm.e,VALUE($K42), IF(OR(_xlpm.s="",_xlpm.e=""),"", IF(_xlpm.e<=_xlpm.s, IF(TODAY()>=_xlpm.e,1,0), MAX(0,MIN(1,(TODAY()-_xlpm.s)/(_xlpm.e-_xlpm.s))))) ) -> 1
B43: 5.2 | C43: Module mounting - Tie In 1 | E43: =G35-7 -> 45951 | F43: 20 | G43: =WORKDAY.INTL(E43,F43,1,Data!$C$3:$C$45) -> 45979 | I43: =K35-2 -> 45965 | J43: 12 | K43: =WORKDAY.INTL(I43,J43,1,Data!$C$3:$C$45) -> 45981 | M43: 1 | N43: =_xlfn.LET( _xlpm.s,VALUE($I43), _xlpm.e,VALUE($K43), IF(OR(_xlpm.s="",_xlpm.e=""),"", IF(_xlpm.e<=_xlpm.s, IF(TODAY()>=_xlpm.e,1,0), MAX(0,MIN(1,(TODAY()-_xlpm.s)/(_xlpm.e-_xlpm.s))))) ) -> 1
B44: 5.2 | C44: Module mounting - Tie In 2 | E44: =G35-7 -> 45951 | F44: 20 | G44: =WORKDAY.INTL(E44,F44,1,Data!$C$3:$C$45) -> 45979 | I44: =K43-2 -> 45979 | J44: 10 | K44: =WORKDAY.INTL(I44,J44,1,Data!$C$3:$C$45) -> 45993 | M44: 1 | N44: =_xlfn.LET( _xlpm.s,VALUE($I44), _xlpm.e,VALUE($K44), IF(OR(_xlpm.s="",_xlpm.e=""),"", IF(_xlpm.e<=_xlpm.s, IF(TODAY()>=_xlpm.e,1,0), MAX(0,MIN(1,(TODAY()-_xlpm.s)/(_xlpm.e-_xlpm.s))))) ) -> 1
B46: 6 | C46: Commissioning | E46: =MIN(E47:E49) -> 45996 | F46: =G46-E46 -> 7 | G46: =MAX(G47:G49) -> 46003 | I46: =MIN(I47:I49) -> 46062 | J46: =K46-I46 -> 4 | K46: =MAX(K47:K49) -> 46066 | M46: =(J47*M47+J49*M49)/SUM(J47:J49) -> 0 | N46: =(K47*N47+K49*N49)/SUM(K47:K49) -> 0
B47: 6.1 | C47: Commissioning - Tie In 1 | E47: =WORKDAY.INTL(MAX(G23,G32,G41),0,1,Data!$C$3:$C$45) -> 45996 | F47: 2 | G47: =WORKDAY.INTL(E47,F47,1,Data!$C$3:$C$45) -> 46000 | I47: =WORKDAY.INTL(K23,0,1,Data!$C$3:$C$45) -> 46062 | J47: 1 | K47: =WORKDAY.INTL(I47,J47,1,Data!$C$3:$C$45) -> 46063 | M47: 0 | N47: =_xlfn.LET( _xlpm.s,VALUE($I47), _xlpm.e,VALUE($K47), IF(OR(_xlpm.s="",_xlpm.e=""),"", IF(_xlpm.e<=_xlpm.s, IF(TODAY()>=_xlpm.e,1,0), MAX(0,MIN(1,(TODAY()-_xlpm.s)/(_xlpm.e-_xlpm.s))))) ) -> 0
B48: 6.2 | C48: Commissioning - Tie In 2 | I48: 46062 | J48: 1 | K48: =WORKDAY.INTL(I48,J48,1,Data!$C$3:$C$45) -> 46063 | M48: 0 | N48: =_xlfn.LET( _xlpm.s,VALUE($I48), _xlpm.e,VALUE($K48), IF(OR(_xlpm.s="",_xlpm.e=""),"", IF(_xlpm.e<=_xlpm.s, IF(TODAY()>=_xlpm.e,1,0), MAX(0,MIN(1,(TODAY()-_xlpm.s)/(_xlpm.e-_xlpm.s))))) ) -> 0
B49: 6.3 | C49: Practical Completion | E49: =WORKDAY.INTL(G47,0,1,Data!$C$3:$C$45) -> 46000 | F49: 3 | G49: =WORKDAY.INTL(E49,F49,1,Data!$C$3:$C$45) -> 46003 | I49: =WORKDAY.INTL(K48,0,1,Data!$C$3:$C$45) -> 46063 | J49: 3 | K49: =WORKDAY.INTL(I49,J49,1,Data!$C$3:$C$45) -> 46066 | M49: 0 | N49: =_xlfn.LET( _xlpm.s,VALUE($I49), _xlpm.e,VALUE($K49), IF(OR(_xlpm.s="",_xlpm.e=""),"", IF(_xlpm.e<=_xlpm.s, IF(TODAY()>=_xlpm.e,1,0), MAX(0,MIN(1,(TODAY()-_xlpm.s)/(_xlpm.e-_xlpm.s))))) ) -> 0
B51: 7 | C51: QA Inspections | E51: =MIN(E52) -> 45996 | F51: =G51-E51 -> 3 | G51: =MAX(G52) -> 45999 | I51: =MIN(I52) -> 46066 | J51: =K51-I51 -> 5 | K51: =MAX(K52) -> 46071 | M51: =(J52*M52)/SUM(J52) -> 0 | N51: =(K52*N52)/SUM(K52) -> 0
B52: 7.1 | C52: Red-Team Inspection | E52: =WORKDAY.INTL(E47,0,1,Data!$C$3:$C$45) -> 45996 | F52: 1 | G52: =WORKDAY.INTL(E52,F52,1,Data!$C$3:$C$45) -> 45999 | I52: =WORKDAY.INTL(K49,0,1,Data!$C$3:$C$45) -> 46066 | J52: 3 | K52: =WORKDAY.INTL(I52,J52,1,Data!$C$3:$C$45) -> 46071 | M52: 0 | N52: =_xlfn.LET( _xlpm.s,VALUE($I52), _xlpm.e,VALUE($K52), IF(OR(_xlpm.s="",_xlpm.e=""),"", IF(_xlpm.e<=_xlpm.s, IF(TODAY()>=_xlpm.e,1,0), MAX(0,MIN(1,(TODAY()-_xlpm.s)/(_xlpm.e-_xlpm.s))))) ) -> 0
B54: 8 | C54: Project Closure | E54: =MIN(E55:E60) -> 45996 | F54: =G54-E54 -> 48 | G54: =MAX(G55:G60) -> 46044 | I54: =MIN(I55:I60) -> 46066 | J54: =K54-I54 -> 20 | K54: =MAX(K55:K60) -> 46086 | M54: =(J55*M55+J56*M56+J57*M57+J58*M58+J59*M59+J60*M60)/SUM(J55:J60) -> 0 | N54: =(K55*N55+K56*N56+K57*N57+K58*N58+K59*N59+K60*N60)/SUM(K55:K60) -> 0
B55: 8.1 | C55: Equipment serial numbers | E55: =E52 -> 45996 | F55: 1 | G55: =WORKDAY.INTL(E55,F55,1,Data!$C$3:$C$45) -> 45999 | I55: =I52 -> 46066 | J55: 1 | K55: =WORKDAY.INTL(I55,J55,1,Data!$C$3:$C$45) -> 46069 | M55: 0 | N55: =_xlfn.LET( _xlpm.s,VALUE($I55), _xlpm.e,VALUE($K55), IF(OR(_xlpm.s="",_xlpm.e=""),"", IF(_xlpm.e<=_xlpm.s, IF(TODAY()>=_xlpm.e,1,0), MAX(0,MIN(1,(TODAY()-_xlpm.s)/(_xlpm.e-_xlpm.s))))) ) -> 0
B56: 8.2 | C56: Snags completion | E56: =G52 -> 45999 | F56: 5 | G56: =WORKDAY.INTL(E56,F56,1,Data!$C$3:$C$45) -> 46006 | I56: =K52 -> 46071 | J56: 5 | K56: =WORKDAY.INTL(I56,J56,1,Data!$C$3:$C$45) -> 46078 | M56: 0 | N56: =_xlfn.LET( _xlpm.s,VALUE($I56), _xlpm.e,VALUE($K56), IF(OR(_xlpm.s="",_xlpm.e=""),"", IF(_xlpm.e<=_xlpm.s, IF(TODAY()>=_xlpm.e,1,0), MAX(0,MIN(1,(TODAY()-_xlpm.s)/(_xlpm.e-_xlpm.s))))) ) -> 0
B57: 8.3 | C57: System Performance Monitoring | E57: =WORKDAY.INTL(G46,0,1,Data!$C$3:$C$45) -> 46003 | F57: 5 | G57: =WORKDAY.INTL(E57,F57,1,Data!$C$3:$C$45) -> 46044 | I57: =WORKDAY.INTL(K46,0,1,Data!$C$3:$C$45) -> 46066 | J57: 5 | K57: =WORKDAY.INTL(I57,J57,1,Data!$C$3:$C$45) -> 46073 | M57: 0 | N57: =_xlfn.LET( _xlpm.s,VALUE($I57), _xlpm.e,VALUE($K57), IF(OR(_xlpm.s="",_xlpm.e=""),"", IF(_xlpm.e<=_xlpm.s, IF(TODAY()>=_xlpm.e,1,0), MAX(0,MIN(1,(TODAY()-_xlpm.s)/(_xlpm.e-_xlpm.s))))) ) -> 0
B58: 8.4 | C58: Handover documentation | E58: =WORKDAY.INTL(G56,0,1,Data!$C$3:$C$45) -> 46006 | F58: 1 | G58: =WORKDAY.INTL(E58,F58,1,Data!$C$3:$C$45) -> 46041 | I58: =WORKDAY.INTL(K56,0,1,Data!$C$3:$C$45) -> 46078 | J58: 1 | K58: =WORKDAY.INTL(I58,J58,1,Data!$C$3:$C$45) -> 46079 | M58: 0 | N58: =_xlfn.LET( _xlpm.s,VALUE($I58), _xlpm.e,VALUE($K58), IF(OR(_xlpm.s="",_xlpm.e=""),"", IF(_xlpm.e<=_xlpm.s, IF(TODAY()>=_xlpm.e,1,0), MAX(0,MIN(1,(TODAY()-_xlpm.s)/(_xlpm.e-_xlpm.s))))) ) -> 0
B59: 8.5 | C59: Handover to Client | E59: =WORKDAY.INTL(G58,0,1,Data!$C$3:$C$45) -> 46041 | F59: 1 | G59: =WORKDAY.INTL(E59,F59,1,Data!$C$3:$C$45) -> 46042 | I59: =WORKDAY.INTL(K58,0,1,Data!$C$3:$C$45) -> 46079 | J59: 1 | K59: =WORKDAY.INTL(I59,J59,1,Data!$C$3:$C$45) -> 46080 | M59: 0 | N59: =_xlfn.LET( _xlpm.s,VALUE($I59), _xlpm.e,VALUE($K59), IF(OR(_xlpm.s="",_xlpm.e=""),"", IF(_xlpm.e<=_xlpm.s, IF(TODAY()>=_xlpm.e,1,0), MAX(0,MIN(1,(TODAY()-_xlpm.s)/(_xlpm.e-_xlpm.s))))) ) -> 0
B60: 8.6 | C60: Handover to Matriarch | E60: =WORKDAY.INTL(E59,0,1,Data!$C$3:$C$45) -> 46041 | F60: 1 | G60: =WORKDAY.INTL(E60,F60,1,Data!$C$3:$C$45) -> 46042 | I60: =WORKDAY.INTL(I59,0,1,Data!$C$3:$C$45) -> 46079 | J60: 5 | K60: =WORKDAY.INTL(I60,J60,1,Data!$C$3:$C$45) -> 46086 | M60: 0 | N60: =_xlfn.LET( _xlpm.s,VALUE($I60), _xlpm.e,VALUE($K60), IF(OR(_xlpm.s="",_xlpm.e=""),"", IF(_xlpm.e<=_xlpm.s, IF(TODAY()>=_xlpm.e,1,0), MAX(0,MIN(1,(TODAY()-_xlpm.s)/(_xlpm.e-_xlpm.s))))) ) -> 0

Sheet Revenue Tracking
B2: HIGH LEVEL PROJECT REVENUE TRACKING
D3: COSTED | F3: ACTUAL | L3: FINANCIAL REVIEW | N3: TIMELINE REVIEW
B4: 1 | C4: Planned Revenue | D4: ='Project Plan'!E6 -> 10428344 | F4: =F22 -> 10428344 | N4: Start Date
B5: 2 | C5: Planned Expenditure | D5: =+'Expenditure Tracking'!F5 -> 9590676.1 | F5: =+'Expenditure Tracking'!H5 -> 7349211.2
B6: 3 | C6: Planned Profit | D6: =+D4-D5 -> 837668.22 | F6: =+F4-F5 -> 3079133.1 | N6: End Date - PC
B7: 4 | C7: Planned Margin | D7: =+D6/D4 -> 0.080326098 | F7: =+F6/F4 -> 0.29526577
B10: CONTRACT
B12: No. | C12: PAYMENT MILESTONE | E12: % | F12: VALUE | H12: PLANNED PAYMENT DATE | L12: INVOICE NUMBER | N12: INVOICE RAISED DATE | P12: PAYMENT RECEIVED DATE | R12: MILESTONE NOTES & COMMENTS
B13: 1 | C13: Claim 1 | E13: =F13/$D$4 -> 0.28831062 | F13: =6013204.76-F14 -> 3006602.4 | H13: 45986 | L13: 004866 | N13: 45958 | P13: 45999
B14: 1 | C14: Claim 1 | E14: 0.29 | F14: 3006602.4 | H14: 45986 | L14: 004866 | N14: 45958 | P14: 45994
B15: 2 | C15: Claim 2 | E15: =F15/$D$4 -> 0.21341537 | F15: 2225569 | H15: 46016 | L15: 004903 | N15: 46008 | P15: 46034
B16: 3 | C16: Claim 3 | E16: 0 | F16: 0
B17: 4 | C17: Claim 4 | E17: 0.21 | F17: 2189570.6 | H17: 46078 | P17: 46078
B18: 5 | E18: 0 | F18: =$D$4*E18 -> 0
B19: 6 | E19: 0 | F19: =$D$4*E19 -> 0
B20: 7 | C20: - | E20: 0 | F20: =$D$4*E20 -> 0
E22: =SUM(E13:E20) -> 1.001726 | F22: =SUM(F13:F20) -> 10428344
B24: KEY: | C24: contains an error (in result or a check has failed)
C25: Red Font - IF TEXT : content not yet confirmed
C26: Red Font - IF NUMBER: Negative value
C27: Anything in yellow is a concern or risk for noting or action
C28: confirmed
C29: [ADD INITIALS: comment for noting in square brackets, use colour or red to draw attention if important]
C30: [RT: When adding rows into sheet, ensure you insert between first and last row of each category]
C31: end of sheet - do not insert information below/beyond this
B41: No. | C41: PAYMENT MILESTONE | E41: % | F41: VALUE
B42: 1 | C42: Deposit - Project commencement | E42: 0.35 | F42: =$F$48*E42 -> 3649920.5
B43: 2 | C43: Delivery of Panels | E43: 0.3 | F43: =$F$48*E43 -> 3128503.3
B44: 3 | C44: Delivery of Inverters | E44: 0.2 | F44: =$F$48*E44 -> 2085668.9
B45: 4 | C45: Practical Completion | E45: 0.1 | F45: =$F$48*E45 -> 1042834.4
B46: 5 | C46: Handover | E46: 0.05 | F46: =$F$48*E46 -> 521417.22
C47: Total | E47: =SUM(E42:E46) -> 1 | F47: =SUM(F42:F46) -> 10428344
E48: =SUM(E42:E46) -> 1 | F48: =F22 -> 10428344

Sheet Data
C2: Public holidays | F2: Drop down list
C3: 45658 | D3: New Years Day | F3: Approved
C4: 45737 | D4: Human Rights day | F4: Pending
C5: 45765 | D5: Good Friday | F5: Declined
C6: 45768 | D6: Family Day | F6: Abanded
C7: 45774 | D7: Freedom Day
C8: 45765 | D8: Freedom DayObserved
C9: 45778 | D9: Workers day
C10: 45824 | D10: Youth Day Holiday
C11: 45878 | D11: Womens Day
C12: 45924 | D12: Heritage Day
C13: 46007 | D13: Day of Reconciliation | H13: Manual dates
C14: 46008 | D14: Builders Holiday
C15: 46009 | D15: Builders Holiday
C16: 46010 | D16: Builders Holiday
C17: 46011 | D17: Builders Holiday
C18: 46012 | D18: Builders Holiday
C19: 46013 | D19: Builders Holiday
C20: 46014 | D20: Builders Holiday
C21: 46015 | D21: Builders Holiday
C22: 46016 | D22: Builders Holiday
C23: 46017 | D23: Builders Holiday
C24: 46018 | D24: Builders Holiday
C25: 46019 | D25: Builders Holiday
... C46: 46017 | D46: Day of Goodwill

Sheet Expenditure Breakdown
B2: COSTED EXPENDITURE BREAKDOWN | I2: =SUM(I6:I177) -> 9590676.1 | J2: =SUM(J6:J177) -> 12428344 | L2: ACTUAL EXPENDITURE BREAKDOWN | R2: FINANCE ONLY | X2: =SUM(X6:X177) -> 7349211.2
B4: No. | C4: Product / Service | D4: Description of Work | E4: QTY | F4: Rate / Unit | G4: Budget Total | H4: FINANCE PAYMENT DATE | I4: Total COS | J4: =IF(J2-'Revenue Tracking'!D4>=0, "Total Revenue", "ERROR on REV" ) -> Total Revenue | L4: No. | M4: Product/ Service | N4: Description of Work | O4: QTY | P4: Rate / Unit | Q4: Actual Total | R4: PO NUMBER | S4: INVOICE NUMBER | T4: INVOICE RAISED DATE | U4: REVENUE RECOGNITION AMOUNT | V4: CHECK | W4: FINANCE PAYMENT DATE | X4: Total COS
B6: 1 | C6: Panels | D6: Panels Budget | G6: =D178 -> 2857717.2 | H6: 46022 | I6: =SUM(G6:G11) -> 2857717.2 | J6: =F178 -> 3072814.2 | L6: 1 | M6: 1. Panels | N6: Jinko 590 | O6: 1298 | P6: 1150.5 | Q6: =O6*P6 -> 1493349 | S6: Menlo - INV0003320 | T6: 45961 | U6: 1729623.9 | V6: =J6-SUM(U6:U11) -> 0 | W6: 46003 | X6: =SUM(Q6:Q11) -> 2657189.4
B7: 1 | D7: Delivery Budget | L7: 1 | M7: 1. Panels | N7: Jinko 590 balance | O7: =2306-O6 -> 1008 | P7: 1150.5 | Q7: =O7*P7 -> 1159704 | S7: Menlo - INV0003319 | T7: 45961 | U7: 1343190.2 | W7: 46009
B8: 1 | L8: 1 | M8: 1. Panels | T8: =IF(W8>1,EOMONTH(W8,0),"") | U8: 0
B9: 1 | L9: 1 | M9: 1. Panels | N9: Replacement Panels - Damaged due to weather | O9: 2 | Q9: 4136.4 | R9: PO4556-DSHC-20260119 - RV Approved | S9: MSA Energy - INV0003547 | T9: 46053 | U9: 0 | W9: =T9+60 -> 46113
B10: 1 | L10: 1 | M10: 1. Panels | T10: =IF(W10>1,EOMONTH(W10,0),"") | U10: 0
B11: 1 | L11: 1 | M11: 1. Panels | T11: =IF(W11>1,EOMONTH(W11,0),"") | U11: 0 | Y11: BUDGET | Z11: Installer Allocation
T12: =IF(W12>1,EOMONTH(W12,0),"") | Y12: AC Equipment | Z12: =G60 -> 1511034.3
B13: 2 | C13: Inverters | D13: Inverter Budget | E13: 11 | G13: =D179 -> 770000 | H13: =H6 -> 46022 | I13: =SUM(G13:G19) -> 770000 | J13: =F179 -> 827956.99 | L13: 2 | M13: 2. Inverters | N13: Huawei 100KTL | O13: 11 | P13: 68870.358 | Q13: =O13*P13 -> 757573.94 | S13: =S6 -> Menlo - INV0003320 | T13: 45961 | U13: 827956.99 | V13: =J13-SUM(U13:U19) -> 0 | W13: =W6 -> 46003 | X13: =SUM(Q13:Q19) -> 757573.94 | Y13: DC Equipment | Z13: =G31 -> 675888.1
B14: 2 | L14: 2 | M14: 2. Inverters | T14: =IF(W14>1,EOMONTH(W14,0),"") | U14: 0 | Y14: AC Labour | Z14: =G99 -> 340042.5
B15: 2 | L15: 2 | M15: 2. Inverters | T15: =IF(W15>1,EOMONTH(W15,0),"") | U15: 0 | Y15: DC Labour | Z15: =G100 -> 720090
B16: 2 | L16: 2 | M16: 2. Inverters | T16: =IF(W16>1,EOMONTH(W16,0),"") | U16: 0 | Y16: Offloading | Z16: =G114 -> 8500
B17: 2 | L17: 2 | M17: 2. Inverters | T17: =IF(W17>1,EOMONTH(W17,0),"") | U17: 0 | Y17: Scaffolding | Z17: =G115 -> 70393.8
B18: 2 | L18: 2 | M18: 2. Inverters | T18: =IF(W18>1,EOMONTH(W18,0),"") | U18: 0 | Y18: Storage | Z18: =G121 -> 33546.667
B19: 2 | L19: 2 | M19: 2. Inverters | T19: =IF(W19>1,EOMONTH(W19,0),"") | U19: 0 | Y19: Telehandler | Z19: 0
T20: =IF(W20>1,EOMONTH(W20,0),"")
B21: 3 | C21: Mounting Structures | D21: Structure Budget | G21: =D180 -> 1105818.2 | H21: =E21+30 -> 30 | I21: =SUM(G21:G28) -> 1105818.2 | J21: =F180 -> 1189051.8 | L21: 3 | M21: 3. Mounting Structures | N21: K2 Structure | Q21: 40621.45 | R21: PO4364-DSHC-20251009 - RV Approved | S21: Krannich - 15-10014095 | T21: 45961 | U21: 142264.22 | V21: =J21-SUM(U21:U28) -> 0 | W21: 46003 | X21: =SUM(Q21:Q28) -> 363159.38 | Y21: Other | Z21: 0
B22: 3 | L22: 3 | M22: 3. Mounting Structures | Q22: 45778.95 | S22: krannich - 15-10014122 | T22: 45961 | U22: 160326.79 | W22: 46009 | Y22: Total | Z22: =SUM(Z12:Z21) -> 3359495.4
B23: 3 | L23: 3 | M23: 3. Mounting Structures | Q23: 50931.2 | S23: krannich - 15-10014093 | T23: 45961 | U23: 178370.97 | W23: 46003 | Y23: Less 15% | Z23: =+Z22*0.85 -> 2855571.1
B24: 3 | L24: 3 | M24: 3. Mounting Structures | Q24: 202184.62 | S24: Krannich - 15-10014094 | T24: 45961 | U24: 708089.86 | W24: 46003 | Y24: R/Wp | Z24: =Z23/'Project Plan'!$E$3/1000 -> 2.0996846
B25: 3 | L25: 3 | M25: 3. Mounting Structures | N25: Earthing plates | Q25: 71394.92 | R25: PO4490-DSHC-20251125 - RV Approved | S25: K2 Systems - Inv139402 | T25: 45991 | U25: 0 | W25: 45989
L26: 3 | M26: 3. Mounting Structures | Q26: -67046.2 | S26: K2 Systems - Credit SACN42026 | T26: 46053 | U26: 0 | W26: 46059
L27: 3 | M27: 3. Mounting Structures | N27: Terragriff (254 clamps short returned) to be deducted from subbie | Q27: 3737.49 | T27: 46081 | W27: =T27 -> 46081
B28: 3 | L28: 3 | M28: 3. Mounting Structures | N28: Universal KL-Clamp | Q28: 15556.95 | R28: PO4553-DSHC-20260116 - RV Approved | S28: K2 Systems - InvSAI672026 | T28: 46053 | U28: 0 | W28: 46045 | Y28: ACTUAL - JA Electrical | Z28: Installer Price
T29: =IF(W29>1,EOMONTH(W29,0),"") | Y29: =Y12 -> AC Equipment | Z29: 231508.8
B30: 4 | C30: DC Equipment | D30: DC Cable Budget | E30: =G30/14*1.15 -> 36274.45 | G30: 441602 | H30: =H6 -> 46022 | I30: =SUM(G30:G46) -> 1117490.1 | J30: =F181 -> 1201602.3 | L30: 4 | M30: 4. DC Equipment | N30: DC Cable - old price | O30: 14000 | P30: 13.5 | Q30: =O30*P30 -> 189000 | S30: =S13 -> Menlo - INV0003320 | T30: 45961 | U30: 318265 | V30: =J30-SUM(U30:U46) -> 0 | W30: =W6 -> 46003 | X30: =SUM(Q30:Q46) -> 713565.2 | Y30: =Y13 -> DC Equipment | Z30: 169665.2
B31: 4 | D31: DC Equipment Budget | G31: =D181-G30 -> 675888.1 | H31: 46022 | L31: 4 | M31: 4. DC Equipment | O31: =40000-O30 -> 26000 | P31: 13.65 | Q31: =P31*O31 -> 354900 | S31: =S6 -> Menlo - INV0003320 | T31: 45961 | U31: 597630.94 | W31: =W7 -> 46009 | Y31: =Y14 -> AC Labour | Z31: 142795.4
B32: 4 | L32: 4 | M32: 4. DC Equipment | T32: =IF(W32>1,EOMONTH(W32,0),"") | U32: =(Q32/$X$30*$J$30) -> 0 | Y32: =Y15 -> DC Labour | Z32: 962496.8
B33: 4 | L33: 4 | M33: 4. DC Equipment | T33: =IF(W33>1,EOMONTH(W33,0),"") | U33: =(Q33/$X$30*$J$30) -> 0 | Y33: =Y16 -> Offloading | Z33: 55490
B34: 4 | H34: =H100 -> 45900 | L34: 4 | M34: 4. DC Equipment | N34: Project Kick Off | O34: =Z30 -> 169665.2 | P34: 0.1 | Q34: =$O$34*P34 -> 16966.52 | S34: =S100 -> JA Electrical - Inv 1104 | T34: =T100 -> 45961 | U34: 28570.632 | W34: =W100 -> 45967 | Y34: =Y17 -> Scaffolding | Z34: 75760
B35: 4 | H35: =H101 -> #REF! | L35: 4 | M35: 4. DC Equipment | N35: Site Establishment | P35: 0.15 | Q35: =$O$34*P35 -> 25449.78 | S35: =S101 -> JA Electrical - Inv 1105 | T35: =T101 -> 45961 | U35: 42855.948 | W35: =W101 -> 45967 | Y35: =Y18 -> Storage | Z35: 11407
B36: 4 | H36: =H102 -> #REF! | L36: 4 | M36: 4. DC Equipment | N36: AC Installation Complete | P36: 0.1 | Q36: =$O$34*P36 -> 16966.52 | S36: JA ElectricalInv 1142 | T36: =T102 -> 46022 | U36: 28570.632 | W36: =W102 -> 46003 | Y36: Site Ablutions | Z36: 17072
L37: 4 | M37: 4. DC Equipment | N37: AC Installation Complete | P37: 0.1 | Q37: =$O$34*P37 -> 16966.52 | T37: =T103 -> 46053 | U37: =(Q37/$X$30*$J$30) -> 28570.632 | W37: =W103 -> 46067
B38: 4 | H38: =H104 -> #REF! | L38: 4 | M38: 4. DC Equipment | N38: DC Installation Complete | P38: 0.2 | Q38: =$O$34*P38 -> 33933.04 | S38: JA ElectricalInv 1142 | T38: =T104 -> 46022 | U38: 57141.264 | W38: =W104 -> 46003 | Y38: Return of excess material | Z38: 14195
L39: 4 | M39: 4. DC Equipment | N39: DC Installation Complete | P39: 0.05 | Q39: =$O$34*P39 -> 8483.26 | T39: =T105 -> 46053 | U39: =(Q39/$X$30*$J$30) -> 14285.316 | W39: =W105 -> 46067
B40: 4 | H40: =H106 -> #REF! | L40: 4 | M40: 4. DC Equipment | N40: Commissioning Complete | P40: 0.1 | Q40: =$O$34*P40 -> 16966.52 | T40: =T106 -> 46081 | U40: =(Q40/$X$30*$J$30) -> 28570.632 | W40: =W106 -> 46073 | Y40: Waste Skip | Z40: 22620
B41: 4 | H41: =H107 -> #REF! | L41: 4 | M41: 4. DC Equipment | N41: Site De-establisment | P41: 0.1 | Q41: =$O$34*P41 -> 16966.52 | T41: =T107 -> 46112 | U41: =(Q41/$X$30*$J$30) -> 28570.632 | W41: =W107 -> 46085 | Y41: Other | Z41: 0
B42: 4 | H42: =H108 -> #REF! | L42: 4 | M42: 4. DC Equipment | N42: Handover Document Complete | P42: 0.05 | Q42: =$O$34*P42 -> 8483.26 | T42: =T108 -> 46112 | U42: =(Q42/$X$30*$J$30) -> 14285.316 | W42: =W108 -> 46085 | Y42: Total | Z42: =SUM(Z29:Z41) -> 1703010.2
B43: 4 | H43: =H109 -> #REF! | L43: 4 | M43: 4. DC Equipment | N43: End of Defects Period | P43: 0.05 | Q43: =$O$34*P43 -> 8483.26 | T43: =T109 -> 46081 | U43: =(Q43/$X$30*$J$30) -> 14285.316 | W43: =W109 -> 46108 | Y43: R/Wp | Z43: =Z42/'Project Plan'!$E$3/1000 -> 1.2522134
B44: 4 | L44: 4 | M44: 4. DC Equipment | T44: =IF(W44>1,EOMONTH(W44,0),"") | U44: =(Q44/$X$30*$J$30) -> 0
B45: 4 | L45: 4 | M45: 4. DC Equipment | T45: =IF(W45>1,EOMONTH(W45,0),"") | U45: =(Q45/$X$30*$J$30) -> 0
B46: 4 | L46: 4 | M46: 4. DC Equipment | T46: =IF(W46>1,EOMONTH(W46,0),"") | U46: =(Q46/$X$30*$J$30) -> 0
T47: =IF(W47>1,EOMONTH(W47,0),"")
B48: 5 | C48: Monitoring | D48: Monitoring Budget | G48: =D183-G49 -> 34000 | H48: 45900 | I48: =SUM(G48:G58) -> 49000 | J48: =F183 -> 52688.172 | L48: 5 | M48: 5. Monitoring | N48: Smartlogger | Q48: 8598.34 | S48: =S6 -> Menlo - INV0003320 | T48: 45961 | U48: 5015.4617 | V48: =J48-SUM(U48:U58) -> 0.0040393824 | W48: =W6 -> 46003 | X48: =SUM(Q48:Q58) -> 91265.29
B49: 5 | D49: Revenue Metering | G49: 15000 | H49: 45900 | L49: 5 | M49: 5. Monitoring | N49: CTs & Meters | Q49: 27301 | R49: PO4416-DSHC-20251028 - RV Approved | S49: Accuenergy Inv :ASAI-006727 | T49: 45961 | U49: 9478.94 | W49: 45989
B50: 5 | H50: 45900 | L50: 5 | M50: 5. Monitoring | N50: Techsitter | Q50: 11169 | S50: Matriarch - INV-4742 | T50: 45930 | U50: 7261.7211 | W50: 45900
L51: 5 | M51: 5. Monitoring | N51: DElivery of Techsitter | Q51: 335.86 | S51: DSV Inv:180156930 | T51: 45991 | U51: 0 | W51: 46022
B52: 5 | H52: 45900 | L52: 5 | M52: 5. Monitoring | N52: Apex Device and Licenses | Q52: 44000 | R52: PO4077-DSHC-20250630 - RV Approved | S52: Rubicon INVWCRE-0069079 | T52: 45930 | U52: 28607.371 | W52: 45900
L53: 5 | M53: 5. Monitoring | N53: Above Apex allocated to Corporate Park | Q53: =-1*Q52 -> -44000 | S53: Allocated to Corporate Park | T53: 45961 | U53: 0 | W53: =T53 -> 45961
L54: 5 | M54: 5. Monitoring | N54: New Apex device | Q54: 40000 | R54: PO4420-DSHC-20251029 - RV Approved | S54: Rubicon - INVWCRE-0072121 | T54: 45991 | U54: 0 | W54: 46021
L55: 5 | M55: 5. Monitoring | N55: Delivery of Apex | Q55: 285.59 | S55: DSV Inv:180155155 | T55: 45991 | U55: 0 | W55: 46021
B56: 5 | H56: 45876 | L56: 5 | M56: 5. Monitoring | N56: UPS | Q56: 3575.5 | R56: PO4070-DSHC-20250630 - RV Approved | S56: Frontiline QTE107313 | T56: 45930 | U56: 2324.674 | W56: 45876
B57: 5 | L57: 5 | M57: 5. Monitoring | T57: =IF(W57>1,EOMONTH(W57,0),"") | U57: =(Q57/$X$48*$J$48) -> 0
B58: 5 | L58: 5 | M58: 5. Monitoring | T58: =IF(W58>1,EOMONTH(W58,0),"") | U58: =(Q58/$X$48*$J$48) -> 0
T59: =IF(W59>1,EOMONTH(W59,0),"")
B60: 6 | C60: AC Equipment | D60: AC Equipment Budget | G60: =D182 -> 1511034.3 | H60: 45900 | I60: =SUM(G60:G78) -> 1511034.3 | J60: =F182 -> 1624768.1 | L60: 6 | M60: 6. AC Equipment | T60: =IF(W60>1,EOMONTH(W60,0),"") | U60: =(Q60/$X$60*$J$60) -> 0 | V60: =J60-SUM(U60:U78) -> 5.3090509e-05 | X60: =SUM(Q60:Q78) -> 586437.82
B61: 6 | H61: =E61+30 -> 30 | L61: 6 | M61: 6. AC Equipment | N61: PVDB | Q61: 354929.22 | R61: PO4330-DSHC-20250925 - MI Approved | S61: Switchboard - 2-SOI002604 | T61: 45991 | U61: 983356.54 | W61: =T61+30 -> 46021
B62: 6 | L62: 6 | M62: 6. AC Equipment | T62: =IF(W62>1,EOMONTH(W62,0),"") | U62: =(Q62/$X$60*$J$60) -> 0
B63: 6 | L63: 6 | M63: 6. AC Equipment | T63: =IF(W63>1,EOMONTH(W63,0),"") | U63: =(Q63/$X$60*$J$60) -> 0
B64: 6 | L64: 6 | M64: 6. AC Equipment | T64: =IF(W64>1,EOMONTH(W64,0),"") | U64: =(Q64/$X$60*$J$60) -> 0
B65: 6 | L65: 6 | M65: 6. AC Equipment | T65: =IF(W65>1,EOMONTH(W65,0),"") | U65: =(Q65/$X$60*$J$60) -> 0
B66: 6 | H66: =H100 -> 45900 | L66: 6 | M66: 6. AC Equipment | N66: Project Kick Off | O66: =Z29 -> 231508.8 | P66: 0.1 | Q66: =$O$66*P66 -> 23150.88 | S66: =S100 -> JA Electrical - Inv 1104 | T66: =T100 -> 45961 | U66: 64141.153 | W66: =W100 -> 45967
B67: 6 | H67: =H101 -> #REF! | L67: 6 | M67: 6. AC Equipment | N67: Site Establishment | P67: 0.15 | Q67: =$O$66*P67 -> 34726.32 | S67: =S101 -> JA Electrical - Inv 1105 | T67: =T101 -> 45961 | U67: 96211.729 | W67: =W101 -> 45967
B68: 6 | H68: =H102 -> #REF! | L68: 6 | M68: 6. AC Equipment | N68: AC Installation Complete | P68: 0.1 | Q68: 23150.78 | S68: JA ElectricalInv 1142 | T68: =T102 -> 46022 | U68: 64141.287 | W68: =W102 -> 46003
L69: 6. | M69: 6. AC Equipment | N69: AC Installation Complete | P69: 0.1 | Q69: =$O$66*P69 -> 23150.88 | T69: =T103 -> 46053 | U69: =(Q69/$X$60*$J$60) -> 64141.174 | W69: =W103 -> 46067
B70: 6 | H70: =H104 -> #REF! | L70: 6 | M70: 6. AC Equipment | N70: DC Installation Complete | P70: 0.2 | Q70: 46301.66 | S70: JA ElectricalInv 1142 | T70: =T104 -> 46022 | U70: 128282.07 | W70: =W104 -> 46003
L71: 6 | M71: 6. AC Equipment | N71: DC Installation Complete | P71: 0.05 | Q71: =$O$66*P71 -> 11575.44 | T71: =T105 -> 46053 | U71: =(Q71/$X$60*$J$60) -> 32070.587 | W71: =W105 -> 46067
B72: 6 | H72: =H106 -> #REF! | L72: 6 | M72: 6. AC Equipment | N72: Commissioning Complete | P72: 0.1 | Q72: =$O$66*P72 -> 23150.88 | T72: =T106 -> 46081 | U72: =(Q72/$X$60*$J$60) -> 64141.174 | W72: =W106 -> 46073
B73: 6 | H73: =H107 -> #REF! | L73: 6 | M73: 6. AC Equipment | N73: Site De-establisment | P73: 0.1 | Q73: =$O$66*P73 -> 23150.88 | T73: =T107 -> 46112 | U73: =(Q73/$X$60*$J$60) -> 64141.174 | W73: =W107 -> 46085
B74: 6 | H74: =H108 -> #REF! | L74: 6 | M74: 6. AC Equipment | N74: Handover Document Complete | P74: 0.05 | Q74: =$O$66*P74 -> 11575.44 | T74: =T108 -> 46112 | U74: =(Q74/$X$60*$J$60) -> 32070.587 | W74: =W108 -> 46085
B75: 6 | H75: =H109 -> #REF! | L75: 6 | M75: 6. AC Equipment | N75: End of Defects Period | P75: 0.05 | Q75: =$O$66*P75 -> 11575.44 | T75: =T109 -> 46081 | U75: =(Q75/$X$60*$J$60) -> 32070.587 | W75: =W109 -> 46108
B76: 6 | L76: 6 | M76: 6. AC Equipment | T76: =IF(W76>1,EOMONTH(W76,0),"") | U76: =(Q76/$X$60*$J$60) -> 0
B77: 6 | L77: 6 | M77: 6. AC Equipment | T77: =IF(W77>1,EOMONTH(W77,0),"") | U77: =(Q77/$X$60*$J$60) -> 0
B78: 6 | L78: 6 | M78: 6. AC Equipment | T78: =IF(W78>1,EOMONTH(W78,0),"") | U78: =(Q78/$X$60*$J$60) -> 0
T79: =IF(W79>1,EOMONTH(W79,0),"")
B80: 7 | C80: BESS | I80: =SUM(G80:G87) -> 0 | J80: =F187 -> 0 | L80: 7 | M80: 7.BESS | V80: =J80-SUM(U80:U87) -> 0 | X80: =SUM(Q80:Q87) -> 0
B81: 7 | L81: 7 | M81: 7.BESS
B82: 7 | L82: 7 | M82: 7.BESS
B83: 7 | L83: 7 | M83: 7.BESS
B84: 7 | L84: 7 | M84: 7.BESS
B85: 7 | L85: 7 | M85: 7.BESS
B86: 7 | L86: 7 | M86: 7.BESS
B87: 7 | L87: 7 | M87: 7.BESS
T88: =IF(W88>1,EOMONTH(W88,0),"")
B89: 8 | C89: Product Add On | I89: =SUM(G89:G97) -> 300000 | J89: =F185+F186 -> 322580.65 | L89: 8 | M89: 8. Product Add On | T89: =IF(W89>1,EOMONTH(W89,0),"") | U89: =(Q89/$X$89*$J$89) -> 0 | V89: =J89-SUM(U89:U97) -> 9818.0735 | X89: =SUM(Q89:Q97) -> 341826
B90: 8 | D90: Transformer | G90: 300000 | H90: 45900 | L90: 8 | M90: 8. Product Add On | N90: Tie In Kiosk | O90: 2 | P90: 25000 | Q90: =O90*P90 -> 50000 | T90: 46081 | U90: 0 | W90: =T90-14 -> 46067
B91: 8 | L91: 8 | M91: 8. Product Add On | T91: =IF(W91>1,EOMONTH(W91,0),"") | U91: =(Q91/$X$89*$J$89) -> 0
B92: 8 | H92: =E92+30 -> 30 | L92: 8 | M92: 8. Product Add On | N92: Brick Face Inverter Rooms | O92: 232956 | P92: 0.75 | Q92: =$O$92*P92 -> 174717 | R92: PO4365-DSHC-20251013 - RV Approved | S92: Van Staden Three : Inv 3021 | T92: 45961 | U92: 200089.19 | W92: 45946
B93: 8 | L93: 8 | M93: 8. Product Add On | P93: 0.25 | Q93: =$O$92*P93 -> 58239 | S93: Van Staden Three : Inv 3037 | T93: 45961 | U93: 66696.397 | W93: 46009
B94: 8 | L94: 8 | M94: 8. Product Add On | N94: Inverter stand | Q94: 48720 | R94: PO4450-DSHC-20251107 - RV Approved | T94: 46053 | U94: =(Q94/$X$89*$J$89) -> 45976.985 | W94: =T94 -> 46053
B95: 8 | L95: 8 | M95: 8. Product Add On | T95: =IF(W95>1,EOMONTH(W95,0),"") | U95: =(Q95/$X$89*$J$89) -> 0
B96: 8 | L96: 8 | M96: 8. Product Add On | N96: Grounding Washers | Q96: 10150 | R96: PO4571-DSHC-20260123 - RV Approved | T96: 46081 | U96: 0 | W96: =T96 -> 46081
B97: 8 | L97: 8 | M97: 8. Product Add On | T97: =IF(W97>1,EOMONTH(W97,0),"") | U97: =(Q97/$X$89*$J$89) -> 0
K98: Only services to be capture below, products above | T98: =IF(W98>1,EOMONTH(W98,0),"")
B99: 9 | C99: AC & DC Installation | D99: AC Installation Budget | G99: =D191 -> 340042.5 | H99: 45900 | I99: =SUM(G99:G112) -> 1060132.5 | J99: =F191+F192 -> 1204696 | L99: 9 | M99: 9. AC & DC installation | T99: =IF(W99>1,EOMONTH(W99,0),"") | U99: =(Q99/$X$99*$J$99) -> 0 | V99: =J99-SUM(U99:U112) -> 0 | X99: =SUM(Q99:Q112) -> 1105292.2
B100: 9 | D100: DC Installation Budget | G100: =D192 -> 720090 | H100: 45900 | L100: 9 | M100: 9. AC & DC installation | N100: Project Kick Off | O100: =Z32+Z31 -> 1105292.2 | P100: 0.1 | Q100: =$O$100*P100 -> 110529.22 | S100: JA Electrical - Inv 1104 | T100: 45961 | U100: 120469.6 | W100: 45967
B101: 9 | H101: ='Project Plan'!#REF!+14 -> #REF! | L101: 9 | M101: 9. AC & DC installation | N101: Site Establishment | P101: 0.15 | Q101: =$O$100*P101 -> 165793.83 | S101: JA Electrical - Inv 1105 | T101: 45961 | U101: 180704.4 | W101: 45967
B102: 9 | H102: ='Project Plan'!#REF!+7 -> #REF! | L102: 9 | M102: 9. AC & DC installation | N102: AC Installation Complete | P102: 0.1 | Q102: =$O$100*P102 -> 110529.22 | S102: JA ElectricalInv 1142 | T102: 46022 | U102: 120469.6 | W102: 46003
L103: 9 | M103: 9. AC & DC installation | N103: AC Installation Complete | P103: 0.1 | Q103: =$O$100*P103 -> 110529.22 | T103: 46053 | U103: =(Q103/$X$99*$J$99) -> 120469.6 | W103: 46067
...

Sheet Expenditure Tracking
B2: HIGH LEVEL PROJECT EXPENDITURE TRACKING
F4: COSTED | H4: ACTUAL | J4: Difference from costed
B5: EXPENDITURE | F5: =SUM(F9:F23) -> 9590676.1 | H5: =SUM(H9:H23) -> 7349211.2 | J5: =SUM(J9:J23) -> 2241464.9
B7: No. | D7: Item | F7: Costed Expenditure | H7: Actual Expenditure | J7: Saving / Overrun | L7: Comments on variations from planned expenditure
B9: ='Expenditure Breakdown'!L6 -> 1 | D9: ='Expenditure Breakdown'!M6 -> 1. Panels | F9: ='Expenditure Breakdown'!I6 -> 2857717.2 | H9: ='Expenditure Breakdown'!X6 -> 2657189.4 | J9: =F9-H9 -> 200527.77
B10: ='Expenditure Breakdown'!L13 -> 2 | D10: ='Expenditure Breakdown'!M13 -> 2. Inverters | F10: ='Expenditure Breakdown'!I13 -> 770000 | H10: ='Expenditure Breakdown'!X13 -> 757573.94 | J10: =F10-H10 -> 12426.062
B11: ='Expenditure Breakdown'!L21 -> 3 | D11: ='Expenditure Breakdown'!M21 -> 3. Mounting Structures | F11: ='Expenditure Breakdown'!I21 -> 1105818.2 | H11: ='Expenditure Breakdown'!X21 -> 363159.38 | J11: =F11-H11 -> 742658.83
B12: ='Expenditure Breakdown'!L30 -> 4 | D12: ='Expenditure Breakdown'!M30 -> 4. DC Equipment | F12: ='Expenditure Breakdown'!I30 -> 1117490.1 | H12: ='Expenditure Breakdown'!X30 -> 713565.2 | J12: =F12-H12 -> 403924.9
B13: ='Expenditure Breakdown'!L48 -> 5 | D13: ='Expenditure Breakdown'!M48 -> 5. Monitoring | F13: ='Expenditure Breakdown'!I48 -> 49000 | H13: ='Expenditure Breakdown'!X48 -> 91265.29 | J13: =F13-H13 -> -42265.29
B14: ='Expenditure Breakdown'!L60 -> 6 | D14: ='Expenditure Breakdown'!M60 -> 6. AC Equipment | F14: ='Expenditure Breakdown'!I60 -> 1511034.3 | H14: ='Expenditure Breakdown'!X60 -> 586437.82 | J14: =F14-H14 -> 924596.48
B15: ='Expenditure Breakdown'!L80 -> 7 | D15: ='Expenditure Breakdown'!M80 -> 7.BESS | F15: ='Expenditure Breakdown'!I80 -> 0 | H15: ='Expenditure Breakdown'!X80 -> 0 | J15: =F15-H15 -> 0
B16: ='Expenditure Breakdown'!L89 -> 8 | D16: ='Expenditure Breakdown'!M89 -> 8. Product Add On | F16: ='Expenditure Breakdown'!I89 -> 300000 | H16: ='Expenditure Breakdown'!X89 -> 341826 | J16: =F16-H16 -> -41826
B17: ='Expenditure Breakdown'!L99 -> 9 | D17: ='Expenditure Breakdown'!M99 -> 9. AC & DC installation | F17: ='Expenditure Breakdown'!I99 -> 1060132.5 | H17: ='Expenditure Breakdown'!X99 -> 1105292.2 | J17: =F17-H17 -> -45159.7
B18: ='Expenditure Breakdown'!L114 -> 10 | D18: ='Expenditure Breakdown'!M114 -> 10. Site Logistics | F18: ='Expenditure Breakdown'!I114 -> 184440.47 | H18: ='Expenditure Breakdown'!X114 -> 302543.9 | J18: =F18-H18 -> -118103.43
B19: ='Expenditure Breakdown'!L136 -> 11 | D19: ='Expenditure Breakdown'!M136 -> 11. Due Dilligence | F19: ='Expenditure Breakdown'!I136 -> 182012.75 | H19: ='Expenditure Breakdown'!X136 -> 142343.85 | J19: =F19-H19 -> 39668.9
B20: ='Expenditure Breakdown'!L142 -> 12 | D20: ='Expenditure Breakdown'!M142 -> 12. BDP Commission | F20: ='Expenditure Breakdown'!I142 -> 0 | H20: ='Expenditure Breakdown'!X142 -> 0 | J20: =F20-H20 -> 0
B21: ='Expenditure Breakdown'!L145 -> 13 | D21: ='Expenditure Breakdown'!M146 -> 13. Engineering | F21: ='Expenditure Breakdown'!I145 -> 429230.63 | H21: ='Expenditure Breakdown'!X145 -> 130354.3 | J21: =F21-H21 -> 298876.33
B22: ='Expenditure Breakdown'!L152 -> 14 | D22: ='Expenditure Breakdown'!M152 -> 14. General Expenses | F22: ='Expenditure Breakdown'!I152 -> 23800 | H22: ='Expenditure Breakdown'!X152 -> 47089.8 | J22: =F22-H22 -> -23289.8
B23: ='Expenditure Breakdown'!L165 -> 15 | D23: ='Expenditure Breakdown'!M165 -> 15. Service Add On | F23: ='Expenditure Breakdown'!I165 -> 0 | H23: ='Expenditure Breakdown'!X165 -> 110570.16 | J23: =F23-H23 -> -110570.16
D25: check: | F25: ='Expenditure Breakdown'!I2-'Expenditure Tracking'!F5 -> 0 | G25: =#REF!-G5 -> #REF! | H25: ='Expenditure Breakdown'!X2-H5 -> 0

Sheet Cashflow
D1: [RT: Double Check the first date is always a MONDAY] | F1: 45677 | G1: =F1+7 -> 45684 | H1: =G1+7 -> 45691 | I1: =H1+7 -> 45698 | J1: =I1+7 -> 45705 | K1: =J1+7 -> 45712 | L1: =K1+7 -> 45719 | M1: =L1+7 -> 45726 | N1: =M1+7 -> 45733 | ... LD1: =LC1+7 -> 47847
A2: PLANNED | C2: CHECK | D2: CHECK
B3: Planned Revenue | C3: ='Revenue Tracking'!D4 -> 10428344 | D3: =SUM(F3:LD3) -> 10428344 | F3: =SUMIFS('Revenue Tracking'!$F$13:$F$20, 'Revenue Tracking'!$H$13:$H$20, ">="&F1,'Revenue Tracking'!$H$13:$H$20, "<"&G1) -> 0 | G3: =SUMIFS('Revenue Tracking'!$F$13:$F$20, 'Revenue Tracking'!$H$13:$H$20, ">="&G1,'Revenue Tracking'!$H$13:$H$20, "<"&H1) -> 0 | H3: =SUMIFS('Revenue Tracking'!$F$13:$F$20, 'Revenue Tracking'!$H$13:$H$20, ">="&H1,'Revenue Tracking'!$H$13:$H$20, "<"&I1) -> 0 | I3: =SUMIFS('Revenue Tracking'!$F$13:$F$20, 'Revenue Tracking'!$H$13:$H$20, ">="&I1,'Revenue Tracking'!$H$13:$H$20, "<"&J1) -> 0 | J3: =SUMIFS('Revenue Tracking'!$F$13:$F$20, 'Revenue Tracking'!$H$13:$H$20, ">="&J1,'Revenue Tracking'!$H$13:$H$20, "<"&K1) -> 0 | K3: =SUMIFS('Revenue Tracking'!$F$13:$F$20, 'Revenue Tracking'!$H$13:$H$20, ">="&K1,'Revenue Tracking'!$H$13:$H$20, "<"&L1) -> 0 | L3: =SUMIFS('Revenue Tracking'!$F$13:$F$20, 'Revenue Tracking'!$H$13:$H$20, ">="&L1,'Revenue Tracking'!$H$13:$H$20, "<"&M1) -> 0 | M3: =SUMIFS('Revenue Tracking'!$F$13:$F$20, 'Revenue Tracking'!$H$13:$H$20, ">="&M1,'Revenue Tracking'!$H$13:$H$20, "<"&N1) -> 0 | ... LC3: =SUMIFS('Revenue Tracking'!$F$13:$F$20, 'Revenue Tracking'!$H$13:$H$20, ">="&LC1,'Revenue Tracking'!$H$13:$H$20, "<"&LD1) -> 0 | LD3: =SUMIFS('Revenue Tracking'!$F$13:$F$20, 'Revenue Tracking'!$H$13:$H$20, ">="&LD1,'Revenue Tracking'!$H$13:$H$20, "<"&#REF!) -> 0
B4: Planned Revenue - Cumulative | F4: =F3 -> 0 | G4: =F4+G3 -> 0 | H4: =G4+H3 -> 0 | I4: =H4+I3 -> 0 | J4: =I4+J3 -> 0 | K4: =J4+K3 -> 0 | L4: =K4+L3 -> 0 | M4: =L4+M3 -> 0 | N4: =M4+N3 -> 0 | ... LD4: =LC4+LD3 -> 10428344
B5: Planned Expenditure | C5: ='Revenue Tracking'!D5 -> 9590676.1 | D5: =SUM(F5:LD5) -> 8484857.9 | F5: =SUMIFS('Expenditure Breakdown'!$G$6:$G$215, 'Expenditure Breakdown'!$H$6:$H$215, ">="&F1,'Expenditure Breakdown'!$H$6:$H$215, "<"&G1) -> 0 | G5: =SUMIFS('Expenditure Breakdown'!$G$6:$G$215, 'Expenditure Breakdown'!$H$6:$H$215, ">="&G1,'Expenditure Breakdown'!$H$6:$H$215, "<"&H1) -> 0 | H5: =SUMIFS('Expenditure Breakdown'!$G$6:$G$215, 'Expenditure Breakdown'!$H$6:$H$215, ">="&H1,'Expenditure Breakdown'!$H$6:$H$215, "<"&I1) -> 0 | I5: =SUMIFS('Expenditure Breakdown'!$G$6:$G$215, 'Expenditure Breakdown'!$H$6:$H$215, ">="&I1,'Expenditure Breakdown'!$H$6:$H$215, "<"&J1) -> 0 | J5: =SUMIFS('Expenditure Breakdown'!$G$6:$G$215, 'Expenditure Breakdown'!$H$6:$H$215, ">="&J1,'Expenditure Breakdown'!$H$6:$H$215, "<"&K1) -> 0 | K5: =SUMIFS('Expenditure Breakdown'!$G$6:$G$215, 'Expenditure Breakdown'!$H$6:$H$215, ">="&K1,'Expenditure Breakdown'!$H$6:$H$215, "<"&L1) -> 0 | L5: =SUMIFS('Expenditure Breakdown'!$G$6:$G$215, 'Expenditure Breakdown'!$H$6:$H$215, ">="&L1,'Expenditure Breakdown'!$H$6:$H$215, "<"&M1) -> 0 | M5: =SUMIFS('Expenditure Breakdown'!$G$6:$G$215, 'Expenditure Breakdown'!$H$6:$H$215, ">="&M1,'Expenditure Breakdown'!$H$6:$H$215, "<"&N1) -> 0 | ... LC5: =SUMIFS('Expenditure Breakdown'!$G$6:$G$215, 'Expenditure Breakdown'!$H$6:$H$215, ">="&LC1,'Expenditure Breakdown'!$H$6:$H$215, "<"&LD1) -> 0 | LD5: =SUMIFS('Expenditure Breakdown'!$G$6:$G$215, 'Expenditure Breakdown'!$H$6:$H$215, ">="&LD1,'Expenditure Breakdown'!$H$6:$H$215, "<"&#REF!) -> 0
B6: Planned Expenditure - Cumulative | F6: =F5 -> 0 | G6: =F6+G5 -> 0 | H6: =G6+H5 -> 0 | I6: =H6+I5 -> 0 | J6: =I6+J5 -> 0 | K6: =J6+K5 -> 0 | L6: =K6+L5 -> 0 | M6: =L6+M5 -> 0 | N6: =M6+N5 -> 0 | ... LD6: =LC6+LD5 -> 8484857.9
B7: PLANNED CashFlow | F7: =F4-F6 -> 0 | G7: =G4-G6 -> 0 | H7: =H4-H6 -> 0 | I7: =I4-I6 -> 0 | J7: =J4-J6 -> 0 | K7: =K4-K6 -> 0 | L7: =L4-L6 -> 0 | M7: =M4-M6 -> 0 | ... LD7: =LD4-LD6 -> 1943486.4
A8: ACTUAL | C8: CHECK | D8: CHECK
B9: Actual + Planned Revenue | C9: ='Revenue Tracking'!F4 -> 10428344 | D9: =SUM(F9:LD9) -> 10428344 | F9: =SUMIFS('Revenue Tracking'!$F$13:$F$20, 'Revenue Tracking'!$P$13:$P$20, ">="&F1,'Revenue Tracking'!$P$13:$P$20, "<"&G1) -> 0 | G9: =SUMIFS('Revenue Tracking'!$F$13:$F$20, 'Revenue Tracking'!$P$13:$P$20, ">="&G1,'Revenue Tracking'!$P$13:$P$20, "<"&H1) -> 0 | H9: =SUMIFS('Revenue Tracking'!$F$13:$F$20, 'Revenue Tracking'!$P$13:$P$20, ">="&H1,'Revenue Tracking'!$P$13:$P$20, "<"&I1) -> 0 | I9: =SUMIFS('Revenue Tracking'!$F$13:$F$20, 'Revenue Tracking'!$P$13:$P$20, ">="&I1,'Revenue Tracking'!$P$13:$P$20, "<"&J1) -> 0 | J9: =SUMIFS('Revenue Tracking'!$F$13:$F$20, 'Revenue Tracking'!$P$13:$P$20, ">="&J1,'Revenue Tracking'!$P$13:$P$20, "<"&K1) -> 0 | K9: =SUMIFS('Revenue Tracking'!$F$13:$F$20, 'Revenue Tracking'!$P$13:$P$20, ">="&K1,'Revenue Tracking'!$P$13:$P$20, "<"&L1) -> 0 | L9: =SUMIFS('Revenue Tracking'!$F$13:$F$20, 'Revenue Tracking'!$P$13:$P$20, ">="&L1,'Revenue Tracking'!$P$13:$P$20, "<"&M1) -> 0 | M9: =SUMIFS('Revenue Tracking'!$F$13:$F$20, 'Revenue Tracking'!$P$13:$P$20, ">="&M1,'Revenue Tracking'!$P$13:$P$20, "<"&N1) -> 0 | ... LC9: =SUMIFS('Revenue Tracking'!$F$13:$F$20, 'Revenue Tracking'!$P$13:$P$20, ">="&LC1,'Revenue Tracking'!$P$13:$P$20, "<"&LD1) -> 0 | LD9: =SUMIFS('Revenue Tracking'!$F$13:$F$20, 'Revenue Tracking'!$P$13:$P$20, ">="&LD1,'Revenue Tracking'!$P$13:$P$20, "<"&#REF!) -> 0
B10: Actual + Planned Revenue - Cumulative | F10: =F9 -> 0 | G10: =F10+G9 -> 0 | H10: =G10+H9 -> 0 | I10: =H10+I9 -> 0 | J10: =I10+J9 -> 0 | K10: =J10+K9 -> 0 | L10: =K10+L9 -> 0 | M10: =L10+M9 -> 0 | N10: =M10+N9 -> 0 | ... LD10: =LC10+LD9 -> 10428344
B11: Actual + Planned Expenditure | C11: ='Revenue Tracking'!F5 -> 7349211.2 | D11: =SUM(F11:LD11) -> 7349211.2 | F11: =SUMIFS('Expenditure Breakdown'!$Q$6:$Q$184, 'Expenditure Breakdown'!$W$6:$W$184, ">="&F1,'Expenditure Breakdown'!$W$6:$W$184, "<"&G1) -> 0 | G11: =SUMIFS('Expenditure Breakdown'!$Q$6:$Q$184, 'Expenditure Breakdown'!$W$6:$W$184, ">="&G1,'Expenditure Breakdown'!$W$6:$W$184, "<"&H1) -> 0 | H11: =SUMIFS('Expenditure Breakdown'!$Q$6:$Q$184, 'Expenditure Breakdown'!$W$6:$W$184, ">="&H1,'Expenditure Breakdown'!$W$6:$W$184, "<"&I1) -> 0 | I11: =SUMIFS('Expenditure Breakdown'!$Q$6:$Q$184, 'Expenditure Breakdown'!$W$6:$W$184, ">="&I1,'Expenditure Breakdown'!$W$6:$W$184, "<"&J1) -> 0 | J11: =SUMIFS('Expenditure Breakdown'!$Q$6:$Q$184, 'Expenditure Breakdown'!$W$6:$W$184, ">="&J1,'Expenditure Breakdown'!$W$6:$W$184, "<"&K1) -> 0 | K11: =SUMIFS('Expenditure Breakdown'!$Q$6:$Q$184, 'Expenditure Breakdown'!$W$6:$W$184, ">="&K1,'Expenditure Breakdown'!$W$6:$W$184, "<"&L1) -> 79700 | L11: =SUMIFS('Expenditure Breakdown'!$Q$6:$Q$184, 'Expenditure Breakdown'!$W$6:$W$184, ">="&L1,'Expenditure Breakdown'!$W$6:$W$184, "<"&M1) -> 9620 | M11: =SUMIFS('Expenditure Breakdown'!$Q$6:$Q$184, 'Expenditure Breakdown'!$W$6:$W$184, ">="&M1,'Expenditure Breakdown'!$W$6:$W$184, "<"&N1) -> 0 | ... LC11: =SUMIFS('Expenditure Breakdown'!$Q$6:$Q$184, 'Expenditure Breakdown'!$W$6:$W$184, ">="&LC1,'Expenditure Breakdown'!$W$6:$W$184, "<"&LD1) -> 0 | LD11: =SUMIFS('Expenditure Breakdown'!$Q$6:$Q$184, 'Expenditure Breakdown'!$W$6:$W$184, ">="&LD1,'Expenditure Breakdown'!$W$6:$W$184, "<"&#REF!) -> 0
B12: Actual + Planned Expenditure - Cumulative | F12: =F11 -> 0 | G12: =F12+G11 -> 0 | H12: =G12+H11 -> 0 | I12: =H12+I11 -> 0 | J12: =I12+J11 -> 0 | K12: =J12+K11 -> 79700 | L12: =K12+L11 -> 89320 | M12: =L12+M11 -> 89320 | N12: =M12+N11 -> 89320 | ... LD12: =LC12+LD11 -> 7349211.2
B14: ACTUAL CashFlow | F14: =F10-F12 -> 0 | G14: =G10-G12 -> 0 | H14: =H10-H12 -> 0 | I14: =I10-I12 -> 0 | J14: =J10-J12 -> 0 | K14: =K10-K12 -> -79700 | L14: =L10-L12 -> -89320 | M14: =M10-M12 -> -89320 | ... LD14: =LD10-LD12 -> 3079133.1
C16: CHECK | D16: CHECK
B17: Revenue Recognition | C17: =C3-D17 -> 9818.0797 | D17: =SUM(F17:LD17) -> 10418526 | F17: =SUMIFS('Expenditure Breakdown'!$U$6:$U$184, 'Expenditure Breakdown'!$T$6:$T$184, ">="&F1,'Expenditure Breakdown'!$T$6:$T$184, "<"&G1) -> 0 | G17: =SUMIFS('Expenditure Breakdown'!$U$6:$U$184, 'Expenditure Breakdown'!$T$6:$T$184, ">="&G1,'Expenditure Breakdown'!$T$6:$T$184, "<"&H1) -> 0 | H17: =SUMIFS('Expenditure Breakdown'!$U$6:$U$184, 'Expenditure Breakdown'!$T$6:$T$184, ">="&H1,'Expenditure Breakdown'!$T$6:$T$184, "<"&I1) -> 0 | I17: =SUMIFS('Expenditure Breakdown'!$U$6:$U$184, 'Expenditure Breakdown'!$T$6:$T$184, ">="&I1,'Expenditure Breakdown'!$T$6:$T$184, "<"&J1) -> 0 | J17: =SUMIFS('Expenditure Breakdown'!$U$6:$U$184, 'Expenditure Breakdown'!$T$6:$T$184, ">="&J1,'Expenditure Breakdown'!$T$6:$T$184, "<"&K1) -> 0 | K17: =SUMIFS('Expenditure Breakdown'!$U$6:$U$184, 'Expenditure Breakdown'!$T$6:$T$184, ">="&K1,'Expenditure Breakdown'!$T$6:$T$184, "<"&L1) -> 0 | L17: =SUMIFS('Expenditure Breakdown'!$U$6:$U$184, 'Expenditure Breakdown'!$T$6:$T$184, ">="&L1,'Expenditure Breakdown'!$T$6:$T$184, "<"&M1) -> 0 | M17: =SUMIFS('Expenditure Breakdown'!$U$6:$U$184, 'Expenditure Breakdown'!$T$6:$T$184, ">="&M1,'Expenditure Breakdown'!$T$6:$T$184, "<"&N1) -> 0 | ... LC17: =SUMIFS('Expenditure Breakdown'!$U$6:$U$184, 'Expenditure Breakdown'!$T$6:$T$184, ">="&LC1,'Expenditure Breakdown'!$T$6:$T$184, "<"&LD1) -> 0 | LD17: =SUMIFS('Expenditure Breakdown'!$U$6:$U$184, 'Expenditure Breakdown'!$T$6:$T$184, ">="&LD1,'Expenditure Breakdown'!$T$6:$T$184, "<"&#REF!) -> 0
B18: Revenue Recognition Cumulative | C18: =D17-D18 -> 0 | D18: =MAX(F18:LD18) -> 10418526 | F18: =F17 -> 0 | G18: =F18+G17 -> 0 | H18: =G18+H17 -> 0 | I18: =H18+I17 -> 0 | J18: =I18+J17 -> 0 | K18: =J18+K17 -> 0 | L18: =K18+L17 -> 0 | M18: =L18+M17 -> 0 | N18: =M18+N17 -> 0 | ... LD18: =LC18+LD17 -> 10418526

Sheet Finance - Revenue
A3: Sum of REVENUE RECOGNITION AMOUNT | B3: Column Labels
A4: Row Labels | B4: (blank) | C4: 45930 | D4: 45961 | E4: 45991 | F4: 46022 | H4: 46053 | I4: 46081 | J4: Grand Total
A5: (blank)
A6: 1. Panels | D6: 3072814.2 | G6: 0 | H6: 0 | J6: 3072814.2
A7: 2. Inverters | D7: 827956.99 | G7: 0 | J7: 827956.99
A8: 3. Mounting Structures | D8: 1189051.8 | E8: 0 | H8: 0 | J8: 1189051.8
A9: 4. DC Equipment | D9: 987322.52 | F9: 85711.896 | G9: 0 | H9: 42855.948 | I9: 85711.896 | J9: 1201602.3
A10: 5. Monitoring | C10: 38193.766 | D10: 14494.402 | E10: 0 | G10: 0 | J10: 52688.168
A11: 6. AC Equipment | D11: 160352.88 | E11: 983356.54 | F11: 192423.36 | G11: 0 | H11: 96211.762 | I11: 192423.52 | J11: 1624768.1
A12: 8. Product Add On | B12: 0 | D12: 266785.59 | G12: 0 | H12: 55795.059 | J12: 322580.65
A13: 9. AC & DC installation | D13: 301174.01 | F13: 361408.81 | G13: 0 | H13: 180704.4 | I13: 361408.81 | J13: 1204696
A14: 10. Site Logistics | B14: 0 | D14: 58979.113 | E14: 38348.821 | F14: 50992.154 | G14: 0 | H14: 20423.783 | I14: 40847.566 | J14: 209591.44
A15: 11. Due Dilligence | C15: 152536.78 | I15: 54295.887 | J15: 206832.67
A16: 13. Engineering | B16: 0 | G16: 0 | I16: 487762.08 | J16: 487762.08
A17: 14. General Expenses | C17: 16326.888 | D17: 3732.1067 | E17: 3279.4745 | F17: 0 | G17: 0 | H17: 2330.7655 | I17: 2330.7655 | J17: 28000
A18: 15. Service Add On
A19: 12. BDP Commission
A20: 7.BESS
A21: Grand Total | B21: 0 | C21: 207057.44 | D21: 6882663.6 | E21: 1024984.8 | F21: 690536.22 | G21: 0 | H21: 398321.72 | I21: 1224780.5 | J21: 10428344

Sheet Finance - COS
A3: Sum of Actual Total | B3: Column Labels
A4: Row Labels | B4: (blank) | C4: 45930 | D4: 45961 | E4: 45991 | F4: 46022 | H4: 46053 | I4: 46081 | J4: Grand Total
A5: (blank)
A6: 1. Panels | D6: 2653053 | H6: 4136.4 | J6: 2657189.4
A7: 2. Inverters | D7: 757573.94 | J7: 757573.94
A8: 3. Mounting Structures | D8: 339516.22 | E8: 71394.92 | H8: 15556.95 | J8: 426468.09
A9: 4. DC Equipment | D9: 586316.3 | F9: 50899.56 | H9: 25449.78 | I9: 50899.56 | J9: 713565.2
A10: 5. Monitoring | C10: 58744.5 | D10: -8100.66 | E10: 40621.45 | J10: 91265.29
A11: 6. AC Equipment | D11: 57877.2 | E11: 354929.22 | F11: 69452.44 | H11: 34726.32 | I11: 69452.64 | J11: 586437.82
A12: 8. Product Add On | D12: 232956 | H12: 48720 | J12: 281676
A13: 9. AC & DC installation | D13: 276323.05 | F13: 331587.66 | H13: 165793.83 | I13: 331587.66 | J13: 1105292.2
A14: 10. Site Logistics | D14: 85136 | E14: 60000 | F14: 68963.1 | H14: 29481.6 | I14: 58963.2 | J14: 302543.9
A15: 11. Due Dilligence | C15: 98339.6 | I15: 44004.25 | J15: 142343.85
A16: 13. Engineering | I16: 130354.3 | J16: 130354.3
A17: 14. General Expenses | C17: 13986.75 | D17: 10587.7 | E17: 5515.35 | F17: 0 | H17: 8500 | I17: 8500 | J17: 47089.8
A18: 15. Service Add On | F18: 104852.72 | H18: 5717.44 | J18: 110570.16
A19: 12. BDP Commission
A20: 7.BESS
A21: Grand Total | C21: 171070.85 | D21: 4991238.7 | E21: 532460.94 | F21: 625755.48 | H21: 338082.32 | I21: 693761.61 | J21: 7352370

Sheet Project Margins
A1: [capture project margins from costing sheet]
A3: Products | D3: 0.32
A4: Services | D4: 0.5
A5: Expenses | D5: 0.15
A6: Subcontractors | D6: 0.2

Sheet Equipment Quotes
B2: Equipment Quote and Budget comparision
B4: Description | D4: Budget | F4: Supplier 1 | H4: Variance | J4: Supplier 2 | L4: Variance | N4: Comments / Notes
F7: >Name< | J7: >Name<
B9: Inverters | D9: =SUM(D10:D11) -> #REF! | F9: =SUM(F10:F13) -> 0 | H9: =$D$9-F9 -> #REF! | J9: =SUM(J10:J13) -> 0 | L9: =$D$9-J9 -> #REF!
B10: Inverters | D10: =#REF! -> #REF!
B11: Optimizers | D11: =#REF! -> #REF!
B12: Warranty
B13: Delivery fee
F15: >Name< | J15: >Name<
B17: Mounting Structure | D17: =SUM(D18:D19) -> #REF! | F17: =SUM(F18:F20) -> 0 | H17: =$D$17- F17 -> #REF! | J17: =SUM(J18:J20) -> 0 | L17: =$D$17- J17 -> #REF!
B18: Mounting Structure | D18: =#REF! -> #REF!
B19: Delivery fee
F21: >Name< | J21: >Name<
B23: DC Cable | D23: =SUM(D24:D25) -> #REF! | F23: =SUM(F24:F25) -> 0 | H23: =$D$23- F23 -> #REF! | J23: =SUM(J24:J25) -> 0 | L23: =$D$23- J23 -> #REF!
B24: DC Cable | D24: =#REF! -> #REF!
B25: Delivery fee
F27: >Name< | J27: >Name<
B29: Monitoring system | D29: =SUM(D30:D32) -> #REF! | F29: =SUM(F30:F42) -> 0 | H29: =$D$29-F29 -> #REF! | J29: =SUM(J30:J32) -> 0 | L29: =$D$29-J29 -> #REF!
B30: =#REF! -> #REF! | D30: =#REF! -> #REF!
B31: =#REF! -> #REF! | D31: =#REF! -> #REF!
B32: Delivery fee
F34: >Name< | J34: >Name<
B36: Additional Scope | D36: =SUM(D37:D41) -> #REF! | F36: =SUM(F37:F41) -> 0 | H36: =$D$29-F36 -> #REF! | J36: =SUM(J37:J41) -> 0 | L36: =$D$29-J36 -> #REF!
B37: SCADA | D37: =#REF! -> #REF!
B38: Inverter cage
B39: Cat ladders
B40: Gen Integration
B41: Lifelines
B43: Totals | D43: =D36+D29+D23+D17+D9 -> #REF! | H43: =SUM(H7:H42) -> #REF! | L43: =SUM(L7:L42) -> #REF!
B47: All amounts are incl VAT

Sheet Installer Quotes
B2: Installer Quote and Budget comparision
B4: Description | D4: Budget | G4: Cosmic Sun | J4: Variance | L4: Matthews Group | O4: Variance
B6: AC Equipment | D6: =#REF! -> #REF! | E6: =D6/(1000*'Project Plan'!$E$3) -> #REF! | G6: 277892.91 | H6: =G6/('Project Plan'!$E$3*1000) -> 0.20433302 | J6: =D6-G6 -> #REF! | M6: =L6/('Project Plan'!$E$3*1000) -> 0 | O6: =D6-L6 -> #REF!
B7: DC Equipment | D7: =#REF! -> #REF! | E7: =D7/(1000*'Project Plan'!$E$3) -> #REF! | G7: 142158.25 | H7: =G7/('Project Plan'!$E$3*1000) -> 0.10452812 | J7: =D7-G7 -> #REF! | M7: =L7/('Project Plan'!$E$3*1000) -> 0 | O7: =D7-L7 -> #REF!
B8: AC Labour | D8: =#REF! -> #REF! | E8: =D8/(1000*'Project Plan'!$E$3) -> #REF! | G8: 96174 | H8: =G8/('Project Plan'!$E$3*1000) -> 0.070716176 | J8: =D8-G8 -> #REF! | M8: =L8/('Project Plan'!$E$3*1000) -> 0 | O8: =D8-L8 -> #REF!
B9: DC Labour | D9: =#REF! -> #REF! | E9: =D9/(1000*'Project Plan'!$E$3) -> #REF! | G9: 230160 | H9: =G9/('Project Plan'!$E$3*1000) -> 0.16923529 | J9: =D9-G9 -> #REF! | M9: =L9/('Project Plan'!$E$3*1000) -> 0 | O9: =D9-L9 -> #REF!
B10: Offloading | D10: =#REF! -> #REF! | G10: 0 | J10: =D10-G10 -> #REF! | O10: =D10-L10 -> #REF!
B11: Roof Access/Scaffolding | D11: =#REF! -> #REF! | G11: 29257.61 | J11: =D11-G11 -> #REF! | O11: =D11-L11 -> #REF!
B12: Storage | D12: =#REF! -> #REF! | J12: =D12-G12 -> #REF! | O12: =D12-L12 -> #REF!
B13: Telehandler | D13: =#REF! -> #REF!
B14: HSE | D14: 0
B15: Totals | D15: =SUM(D6:D13) -> #REF! | G15: =SUM(G6:G13) -> 775642.77 | J15: =SUM(J6:J14) -> #REF! | L15: =SUM(L6:L13) -> 0 | O15: =SUM(O6:O14) -> #REF!
B18: Description | D18: Budget | G18: >Installer Name 3< | J18: Variance | L18: >Installer Name 4< | O18: Variance
B20: AC installation | D20: =#REF! -> #REF! | E20: =D20/(1000*'Project Plan'!$E$3) -> #REF! | H20: =G20/(1000*'Project Plan'!$E$3) -> 0 | J20: =D20-G20 -> #REF! | M20: =L20/(1000*'Project Plan'!$E$3) -> 0 | O20: =D6-L20 -> #REF!
B21: AC equipment | D21: =#REF! -> #REF! | E21: =D21/(1000*'Project Plan'!$E$3) -> #REF! | J21: =D21-G21 -> #REF! | M21: =L21/(1000*'Project Plan'!$E$3) -> 0 | O21: =D7-L21 -> #REF!
B22: DC installation | D22: =#REF! -> #REF! | E22: =D22/(1000*'Project Plan'!$E$3) -> #REF! | H22: =G22/(1000*'Project Plan'!$E$3) -> 0 | J22: =D22-G22 -> #REF! | M22: =L22/(1000*'Project Plan'!$E$3) -> 0 | O22: =D8-L22 -> #REF!
B23: DC equipment | D23: =SUM(#REF!) -> #REF! | E23: =D23/(1000*'Project Plan'!$E$3) -> #REF! | J23: =D23-G23 -> #REF! | O23: =D9-L23 -> #REF!
B24: Storage | D24: =#REF! -> #REF! | J24: =D24-G24 -> #REF! | O24: =D10-L24 -> #REF!
B25: Panel lifting equipment | D25: =SUM(#REF!) -> #REF! | J25: =D25-G25 -> #REF! | O25: =D11-L25 -> #REF!
B26: Offloading | D26: =#REF! -> #REF! | J26: =D26-G26 -> #REF! | O26: =D12-L26 -> #REF!
B29: Totals | D29: =SUM(D20:D27) -> #REF! | G29: =SUM(G20:G27) -> 0 | J29: =SUM(J20:J28) -> #REF! | L29: =SUM(L20:L27) -> 0 | O29: =SUM(O20:O28) -> #REF!
B32: Budget Summary
B34: Budget | D34: =D15 -> #REF!
B35: =G4 -> Cosmic Sun | D35: =G15 -> 775642.77
B36: =L4 -> Matthews Group | D36: =L15 -> 0
B37: =G18 -> >Installer Name 3< | D37: =G29 -> 0
B38: =L18 -> >Installer Name 4< | D38: =L29 -> 0
B40: =IF(D40<D34,"Saving","Loss") -> #REF! | D40: =D34-MIN(D35:D38) -> #REF!
B42: All amounts are exc VAT

Sheet Decision Register
B1: =D15 -> Seshego Circle | E1: Decision Register
B3: ID | C3: Decision Description | D3: Decision Impact | E3: Proposed Date | F3: Proposed By | G3: Status | H3: Approved By | I3: Date | J3: Results / Comments
B4: DEC001
B5: DEC002
B6: DEC003
B7: DEC004
B8: DEC005
B9: DEC006
B10: DEC007
B11: DEC008
B12: DEC009
B13: DEC010
D15: {='Project Plan'!E2:H2} -> Seshego Circle | E15: 0 | F15: 0 | G15: 0
