Workbook
Name Inverter_Capacity: #REF!
Name Inverter_Supplier: #REF!
Name Inverter_Supplier: #REF!
Name Inverter_Supplier: #REF!
Name Project_Size: 'Certificate - Financial Close'!Projectsize
Name Project_Size: Compliance!Projectsize
Name Project_Size: 'Finance - Revenue'!Projectsize
Name Project_Size: Projectsize
Name Projectsize: #REF!
Name Projectsize: #REF!
Name Projectsize: #REF!
Name Projectsize: 'Project Margins'!$K$5
Name Security_Serv: #REF!
Name Security_Serv: #REF!
Name SSS: #REF!
Name SSS: #REF!
Name USD_ZAR: #REF!
Name USD_ZAR: #REF!
Name USD_ZAR: #REF!

Sheet Sheet1
A1: PROJECT PLAN
A2: # | B2: Project Milestone | C2: Planned Start Date | D2: Duration (Work Days) | E2: Planned End Date | F2: Actual Start Date | H2: Actual End Date | J2: Comments | L2: =C3 -> 43831 | M2: =L2+3 -> 43834 | N2: =M2+7 -> 43841 | O2: =N2+7 -> 43848 | P2: =O2+7 -> 43855 | Q2: =P2+6 -> 43861 | R2: =Q2+1 -> 43862 | S2: =R2+7 -> 43869 | T2: =S2+7 -> 43876 | U2: =T2+7 -> 43883 | V2: =U2+6 -> 43889 | W2: =V2+7 -> 43896 | X2: =W2+7 -> 43903 | Y2: =X2+7 -> 43910 | Z2: =Y2+7 -> 43917 | AA2: =Z2+3 -> 43920 | AB2: =AA2+4 -> 43924 | AC2: =AB2+7 -> 43931 | AD2: =AC2+7 -> 43938 | AE2: =AD2+7 -> 43945 | AF2: =AE2+6 -> 43951 | AG2: =AF2+2 -> 43953 | AH2: =AG2+7 -> 43960 | AI2: =AH2+7 -> 43967 | AJ2: =AI2+7 -> 43974 | AK2: =AJ2+7 -> 43981 | AL2: =AK2+1 -> 43982 | AM2: =AL2+6 -> 43988 | AN2: =AM2+7 -> 43995 | AO2: =AN2+7 -> 44002 | AP2: =AO2+7 -> 44009 | AQ2: =AP2+3 -> 44012 | AR2: =AQ2+4 -> 44016 | AS2: =AR2+7 -> 44023 | AT2: =AS2+7 -> 44030 | AU2: =AT2+7 -> 44037 | AV2: =AU2+6 -> 44043 | AW2: =AV2+1 -> 44044 | AX2: =AW2+7 -> 44051 | AY2: =AX2+7 -> 44058 | AZ2: =AY2+7 -> 44065 | BA2: =AZ2+7 -> 44072 | BB2: =BA2+2 -> 44074 | BC2: =BB2+5 -> 44079 | BD2: =BC2+7 -> 44086 | BE2: =BD2+7 -> 44093 | BF2: =BE2+7 -> 44100 | BG2: =BF2+4 -> 44104
A3: 1 | B3: Contract Signature | C3: 43831 | D3: 1 | E3: 43832 | F3: 43831 | G3: 1 | H3: 43832 | L3: =IF(AND($F3<(L$2+7),$F3>L$2),1, IF(AND($H3<L$2+7,$H3>L$2),3, IF(AND($F3<=L$2, $H3>=L$2), 2, "" ))) -> 3 | M3: =IF(AND($F3<(M$2+7),$F3>M$2),1, IF(AND($H3<M$2+7,$H3>M$2),3, IF(AND($F3<=M$2, $H3>=M$2), 2, "" ))) | N3: =IF(AND($F3<(N$2+7),$F3>N$2),1, IF(AND($H3<N$2+7,$H3>N$2),3, IF(AND($F3<=N$2, $H3>=N$2), 2, "" ))) | O3: =IF(AND($F3<(O$2+7),$F3>O$2),1, IF(AND($H3<O$2+7,$H3>O$2),3, IF(AND($F3<=O$2, $H3>=O$2), 2, "" ))) | P3: =IF(AND($F3<(P$2+7),$F3>P$2),1, IF(AND($H3<P$2+7,$H3>P$2),3, IF(AND($F3<=P$2, $H3>=P$2), 2, "" ))) | Q3: =IF(AND($F3<(Q$2+7),$F3>Q$2),1, IF(AND($H3<Q$2+7,$H3>Q$2),3, IF(AND($F3<=Q$2, $H3>=Q$2), 2, "" ))) | R3: =IF(AND($F3<(R$2+7),$F3>R$2),1, IF(AND($H3<R$2+7,$H3>R$2),3, IF(AND($F3<=R$2, $H3>=R$2), 2, "" ))) | S3: =IF(AND($F3<(S$2+7),$F3>S$2),1, IF(AND($H3<S$2+7,$H3>S$2),3, IF(AND($F3<=S$2, $H3>=S$2), 2, "" ))) | ... AQ3: =IF(AND($F3<(AQ$2+7),$F3>AQ$2),1, IF(AND($H3<AQ$2+7,$H3>AQ$2),3, IF(AND($F3<=AQ$2, $H3>=AQ$2), 2, "" )))
A4: A | B4: PAYMENT MILESTONE 1: DEPOSIT | C4: 43832 | D4: 1 | E4: 43833 | F4: 43832 | G4: 1 | H4: 43833 | L4: =IF(AND($F4<(L$2+7),$F4>L$2),1, IF(AND($H4<L$2+7,$H4>L$2),3, IF(AND($F4<=L$2, $H4>=L$2), 2, "" ))) -> 1 | M4: =IF(AND($F4<(M$2+7),$F4>M$2),1, IF(AND($H4<M$2+7,$H4>M$2),3, IF(AND($F4<=M$2, $H4>=M$2), 2, "" ))) | N4: =IF(AND($F4<(N$2+7),$F4>N$2),1, IF(AND($H4<N$2+7,$H4>N$2),3, IF(AND($F4<=N$2, $H4>=N$2), 2, "" ))) | O4: =IF(AND($F4<(O$2+7),$F4>O$2),1, IF(AND($H4<O$2+7,$H4>O$2),3, IF(AND($F4<=O$2, $H4>=O$2), 2, "" ))) | P4: =IF(AND($F4<(P$2+7),$F4>P$2),1, IF(AND($H4<P$2+7,$H4>P$2),3, IF(AND($F4<=P$2, $H4>=P$2), 2, "" ))) | Q4: =IF(AND($F4<(Q$2+7),$F4>Q$2),1, IF(AND($H4<Q$2+7,$H4>Q$2),3, IF(AND($F4<=Q$2, $H4>=Q$2), 2, "" ))) | R4: =IF(AND($F4<(R$2+7),$F4>R$2),1, IF(AND($H4<R$2+7,$H4>R$2),3, IF(AND($F4<=R$2, $H4>=R$2), 2, "" ))) | S4: =IF(AND($F4<(S$2+7),$F4>S$2),1, IF(AND($H4<S$2+7,$H4>S$2),3, IF(AND($F4<=S$2, $H4>=S$2), 2, "" ))) | ... AQ4: =IF(AND($F4<(AQ$2+7),$F4>AQ$2),1, IF(AND($H4<AQ$2+7,$H4>AQ$2),3, IF(AND($F4<=AQ$2, $H4>=AQ$2), 2, "" )))
A5: 2 | B5: Structural and Electrical Due Diligences | C5: 43833 | D5: 5 | E5: 43840 | F5: 43833 | G5: 5 | H5: 43840 | L5: =IF(AND($F5<(L$2+7),$F5>L$2),1, IF(AND($H5<L$2+7,$H5>L$2),3, IF(AND($F5<=L$2, $H5>=L$2), 2, "" ))) -> 1 | M5: =IF(AND($F5<(M$2+7),$F5>M$2),1, IF(AND($H5<M$2+7,$H5>M$2),3, IF(AND($F5<=M$2, $H5>=M$2), 2, "" ))) -> 3 | N5: =IF(AND($F5<(N$2+7),$F5>N$2),1, IF(AND($H5<N$2+7,$H5>N$2),3, IF(AND($F5<=N$2, $H5>=N$2), 2, "" ))) | O5: =IF(AND($F5<(O$2+7),$F5>O$2),1, IF(AND($H5<O$2+7,$H5>O$2),3, IF(AND($F5<=O$2, $H5>=O$2), 2, "" ))) | P5: =IF(AND($F5<(P$2+7),$F5>P$2),1, IF(AND($H5<P$2+7,$H5>P$2),3, IF(AND($F5<=P$2, $H5>=P$2), 2, "" ))) | Q5: =IF(AND($F5<(Q$2+7),$F5>Q$2),1, IF(AND($H5<Q$2+7,$H5>Q$2),3, IF(AND($F5<=Q$2, $H5>=Q$2), 2, "" ))) | R5: =IF(AND($F5<(R$2+7),$F5>R$2),1, IF(AND($H5<R$2+7,$H5>R$2),3, IF(AND($F5<=R$2, $H5>=R$2), 2, "" ))) | S5: =IF(AND($F5<(S$2+7),$F5>S$2),1, IF(AND($H5<S$2+7,$H5>S$2),3, IF(AND($F5<=S$2, $H5>=S$2), 2, "" ))) | ... AQ5: =IF(AND($F5<(AQ$2+7),$F5>AQ$2),1, IF(AND($H5<AQ$2+7,$H5>AQ$2),3, IF(AND($F5<=AQ$2, $H5>=AQ$2), 2, "" )))
A6: 3 | B6: Design Confirmation | C6: 43841 | D6: 2 | E6: 43844 | F6: 43841 | G6: 2 | H6: 43844 | L6: =IF(AND($F6<(L$2+7),$F6>L$2),1, IF(AND($H6<L$2+7,$H6>L$2),3, IF(AND($F6<=L$2, $H6>=L$2), 2, "" ))) | M6: =IF(AND($F6<(M$2+7),$F6>M$2),1, IF(AND($H6<M$2+7,$H6>M$2),3, IF(AND($F6<=M$2, $H6>=M$2), 2, "" ))) | N6: =IF(AND($F6<(N$2+7),$F6>N$2),1, IF(AND($H6<N$2+7,$H6>N$2),3, IF(AND($F6<=N$2, $H6>=N$2), 2, "" ))) -> 3 | O6: =IF(AND($F6<(O$2+7),$F6>O$2),1, IF(AND($H6<O$2+7,$H6>O$2),3, IF(AND($F6<=O$2, $H6>=O$2), 2, "" ))) | P6: =IF(AND($F6<(P$2+7),$F6>P$2),1, IF(AND($H6<P$2+7,$H6>P$2),3, IF(AND($F6<=P$2, $H6>=P$2), 2, "" ))) | Q6: =IF(AND($F6<(Q$2+7),$F6>Q$2),1, IF(AND($H6<Q$2+7,$H6>Q$2),3, IF(AND($F6<=Q$2, $H6>=Q$2), 2, "" ))) | R6: =IF(AND($F6<(R$2+7),$F6>R$2),1, IF(AND($H6<R$2+7,$H6>R$2),3, IF(AND($F6<=R$2, $H6>=R$2), 2, "" ))) | S6: =IF(AND($F6<(S$2+7),$F6>S$2),1, IF(AND($H6<S$2+7,$H6>S$2),3, IF(AND($F6<=S$2, $H6>=S$2), 2, "" ))) | ... AQ6: =IF(AND($F6<(AQ$2+7),$F6>AQ$2),1, IF(AND($H6<AQ$2+7,$H6>AQ$2),3, IF(AND($F6<=AQ$2, $H6>=AQ$2), 2, "" )))
A7: 4 | B7: Equipment Procurement | C7: 43833 | E7: 43949 | F7: 43833 | H7: 43949 | L7: =IF(AND($F7<(L$2+7),$F7>L$2),1, IF(AND($H7<L$2+7,$H7>L$2),3, IF(AND($F7<=L$2, $H7>=L$2), 2, "" ))) -> 1 | M7: =IF(AND($F7<(M$2+7),$F7>M$2),1, IF(AND($H7<M$2+7,$H7>M$2),3, IF(AND($F7<=M$2, $H7>=M$2), 2, "" ))) -> 2 | N7: =IF(AND($F7<(N$2+7),$F7>N$2),1, IF(AND($H7<N$2+7,$H7>N$2),3, IF(AND($F7<=N$2, $H7>=N$2), 2, "" ))) -> 2 | O7: =IF(AND($F7<(O$2+7),$F7>O$2),1, IF(AND($H7<O$2+7,$H7>O$2),3, IF(AND($F7<=O$2, $H7>=O$2), 2, "" ))) -> 2 | P7: =IF(AND($F7<(P$2+7),$F7>P$2),1, IF(AND($H7<P$2+7,$H7>P$2),3, IF(AND($F7<=P$2, $H7>=P$2), 2, "" ))) -> 2 | Q7: =IF(AND($F7<(Q$2+7),$F7>Q$2),1, IF(AND($H7<Q$2+7,$H7>Q$2),3, IF(AND($F7<=Q$2, $H7>=Q$2), 2, "" ))) -> 2 | R7: =IF(AND($F7<(R$2+7),$F7>R$2),1, IF(AND($H7<R$2+7,$H7>R$2),3, IF(AND($F7<=R$2, $H7>=R$2), 2, "" ))) -> 2 | S7: =IF(AND($F7<(S$2+7),$F7>S$2),1, IF(AND($H7<S$2+7,$H7>S$2),3, IF(AND($F7<=S$2, $H7>=S$2), 2, "" ))) -> 2 | ... AQ7: =IF(AND($F7<(AQ$2+7),$F7>AQ$2),1, IF(AND($H7<AQ$2+7,$H7>AQ$2),3, IF(AND($F7<=AQ$2, $H7>=AQ$2), 2, "" )))
B8: Panel Procurement | C8: 43833 | D8: 5 | E8: 43840 | F8: 43833 | G8: 5 | H8: 43840 | L8: =IF(AND($F8<(L$2+7),$F8>L$2),1, IF(AND($H8<L$2+7,$H8>L$2),3, IF(AND($F8<=L$2, $H8>=L$2), 2, "" ))) -> 1 | M8: =IF(AND($F8<(M$2+7),$F8>M$2),1, IF(AND($H8<M$2+7,$H8>M$2),3, IF(AND($F8<=M$2, $H8>=M$2), 2, "" ))) -> 3 | N8: =IF(AND($F8<(N$2+7),$F8>N$2),1, IF(AND($H8<N$2+7,$H8>N$2),3, IF(AND($F8<=N$2, $H8>=N$2), 2, "" ))) | O8: =IF(AND($F8<(O$2+7),$F8>O$2),1, IF(AND($H8<O$2+7,$H8>O$2),3, IF(AND($F8<=O$2, $H8>=O$2), 2, "" ))) | P8: =IF(AND($F8<(P$2+7),$F8>P$2),1, IF(AND($H8<P$2+7,$H8>P$2),3, IF(AND($F8<=P$2, $H8>=P$2), 2, "" ))) | Q8: =IF(AND($F8<(Q$2+7),$F8>Q$2),1, IF(AND($H8<Q$2+7,$H8>Q$2),3, IF(AND($F8<=Q$2, $H8>=Q$2), 2, "" ))) | R8: =IF(AND($F8<(R$2+7),$F8>R$2),1, IF(AND($H8<R$2+7,$H8>R$2),3, IF(AND($F8<=R$2, $H8>=R$2), 2, "" ))) | S8: =IF(AND($F8<(S$2+7),$F8>S$2),1, IF(AND($H8<S$2+7,$H8>S$2),3, IF(AND($F8<=S$2, $H8>=S$2), 2, "" ))) | ... AQ8: =IF(AND($F8<(AQ$2+7),$F8>AQ$2),1, IF(AND($H8<AQ$2+7,$H8>AQ$2),3, IF(AND($F8<=AQ$2, $H8>=AQ$2), 2, "" )))
B9: Inverter Procurement | C9: 43941 | D9: 5 | E9: 43949 | F9: 43941 | G9: 5 | H9: 43949 | L9: =IF(AND($F9<(L$2+7),$F9>L$2),1, IF(AND($H9<L$2+7,$H9>L$2),3, IF(AND($F9<=L$2, $H9>=L$2), 2, "" ))) | M9: =IF(AND($F9<(M$2+7),$F9>M$2),1, IF(AND($H9<M$2+7,$H9>M$2),3, IF(AND($F9<=M$2, $H9>=M$2), 2, "" ))) | N9: =IF(AND($F9<(N$2+7),$F9>N$2),1, IF(AND($H9<N$2+7,$H9>N$2),3, IF(AND($F9<=N$2, $H9>=N$2), 2, "" ))) | O9: =IF(AND($F9<(O$2+7),$F9>O$2),1, IF(AND($H9<O$2+7,$H9>O$2),3, IF(AND($F9<=O$2, $H9>=O$2), 2, "" ))) | P9: =IF(AND($F9<(P$2+7),$F9>P$2),1, IF(AND($H9<P$2+7,$H9>P$2),3, IF(AND($F9<=P$2, $H9>=P$2), 2, "" ))) | Q9: =IF(AND($F9<(Q$2+7),$F9>Q$2),1, IF(AND($H9<Q$2+7,$H9>Q$2),3, IF(AND($F9<=Q$2, $H9>=Q$2), 2, "" ))) | R9: =IF(AND($F9<(R$2+7),$F9>R$2),1, IF(AND($H9<R$2+7,$H9>R$2),3, IF(AND($F9<=R$2, $H9>=R$2), 2, "" ))) | S9: =IF(AND($F9<(S$2+7),$F9>S$2),1, IF(AND($H9<S$2+7,$H9>S$2),3, IF(AND($F9<=S$2, $H9>=S$2), 2, "" ))) | ... AQ9: =IF(AND($F9<(AQ$2+7),$F9>AQ$2),1, IF(AND($H9<AQ$2+7,$H9>AQ$2),3, IF(AND($F9<=AQ$2, $H9>=AQ$2), 2, "" )))
B10: Mounting Structure Procurement | C10: 43941 | D10: 5 | E10: 43949 | F10: 43941 | G10: 5 | H10: 43949 | L10: =IF(AND($F10<(L$2+7),$F10>L$2),1, IF(AND($H10<L$2+7,$H10>L$2),3, IF(AND($F10<=L$2, $H10>=L$2), 2, "" ))) | M10: =IF(AND($F10<(M$2+7),$F10>M$2),1, IF(AND($H10<M$2+7,$H10>M$2),3, IF(AND($F10<=M$2, $H10>=M$2), 2, "" ))) | N10: =IF(AND($F10<(N$2+7),$F10>N$2),1, IF(AND($H10<N$2+7,$H10>N$2),3, IF(AND($F10<=N$2, $H10>=N$2), 2, "" ))) | O10: =IF(AND($F10<(O$2+7),$F10>O$2),1, IF(AND($H10<O$2+7,$H10>O$2),3, IF(AND($F10<=O$2, $H10>=O$2), 2, "" ))) | P10: =IF(AND($F10<(P$2+7),$F10>P$2),1, IF(AND($H10<P$2+7,$H10>P$2),3, IF(AND($F10<=P$2, $H10>=P$2), 2, "" ))) | Q10: =IF(AND($F10<(Q$2+7),$F10>Q$2),1, IF(AND($H10<Q$2+7,$H10>Q$2),3, IF(AND($F10<=Q$2, $H10>=Q$2), 2, "" ))) | R10: =IF(AND($F10<(R$2+7),$F10>R$2),1, IF(AND($H10<R$2+7,$H10>R$2),3, IF(AND($F10<=R$2, $H10>=R$2), 2, "" ))) | S10: =IF(AND($F10<(S$2+7),$F10>S$2),1, IF(AND($H10<S$2+7,$H10>S$2),3, IF(AND($F10<=S$2, $H10>=S$2), 2, "" ))) | ... AQ10: =IF(AND($F10<(AQ$2+7),$F10>AQ$2),1, IF(AND($H10<AQ$2+7,$H10>AQ$2),3, IF(AND($F10<=AQ$2, $H10>=AQ$2), 2, "" )))
B11: BOS Procurement | C11: 43941 | D11: 5 | E11: 43949 | F11: 43941 | G11: 5 | H11: 43949 | L11: =IF(AND($F11<(L$2+7),$F11>L$2),1, IF(AND($H11<L$2+7,$H11>L$2),3, IF(AND($F11<=L$2, $H11>=L$2), 2, "" ))) | M11: =IF(AND($F11<(M$2+7),$F11>M$2),1, IF(AND($H11<M$2+7,$H11>M$2),3, IF(AND($F11<=M$2, $H11>=M$2), 2, "" ))) | N11: =IF(AND($F11<(N$2+7),$F11>N$2),1, IF(AND($H11<N$2+7,$H11>N$2),3, IF(AND($F11<=N$2, $H11>=N$2), 2, "" ))) | O11: =IF(AND($F11<(O$2+7),$F11>O$2),1, IF(AND($H11<O$2+7,$H11>O$2),3, IF(AND($F11<=O$2, $H11>=O$2), 2, "" ))) | P11: =IF(AND($F11<(P$2+7),$F11>P$2),1, IF(AND($H11<P$2+7,$H11>P$2),3, IF(AND($F11<=P$2, $H11>=P$2), 2, "" ))) | Q11: =IF(AND($F11<(Q$2+7),$F11>Q$2),1, IF(AND($H11<Q$2+7,$H11>Q$2),3, IF(AND($F11<=Q$2, $H11>=Q$2), 2, "" ))) | R11: =IF(AND($F11<(R$2+7),$F11>R$2),1, IF(AND($H11<R$2+7,$H11>R$2),3, IF(AND($F11<=R$2, $H11>=R$2), 2, "" ))) | S11: =IF(AND($F11<(S$2+7),$F11>S$2),1, IF(AND($H11<S$2+7,$H11>S$2),3, IF(AND($F11<=S$2, $H11>=S$2), 2, "" ))) | ... AQ11: =IF(AND($F11<(AQ$2+7),$F11>AQ$2),1, IF(AND($H11<AQ$2+7,$H11>AQ$2),3, IF(AND($F11<=AQ$2, $H11>=AQ$2), 2, "" )))
A12: 5 | B12: Internal Project Kick off | C12: 43936 | D12: 5 | E12: 43943 | F12: 43936 | G12: 5 | H12: 43943
A13: 6 | B13: Client Project Kick-off | C13: 43963 | D13: 5 | E13: 43970 | F13: 43963 | G13: 5 | H13: 43970 | L13: =IF(AND($F13<(L$2+7),$F13>L$2),1, IF(AND($H13<L$2+7,$H13>L$2),3, IF(AND($F13<=L$2, $H13>=L$2), 2, "" ))) | M13: =IF(AND($F13<(M$2+7),$F13>M$2),1, IF(AND($H13<M$2+7,$H13>M$2),3, IF(AND($F13<=M$2, $H13>=M$2), 2, "" ))) | N13: =IF(AND($F13<(N$2+7),$F13>N$2),1, IF(AND($H13<N$2+7,$H13>N$2),3, IF(AND($F13<=N$2, $H13>=N$2), 2, "" ))) | O13: =IF(AND($F13<(O$2+7),$F13>O$2),1, IF(AND($H13<O$2+7,$H13>O$2),3, IF(AND($F13<=O$2, $H13>=O$2), 2, "" ))) | P13: =IF(AND($F13<(P$2+7),$F13>P$2),1, IF(AND($H13<P$2+7,$H13>P$2),3, IF(AND($F13<=P$2, $H13>=P$2), 2, "" ))) | Q13: =IF(AND($F13<(Q$2+7),$F13>Q$2),1, IF(AND($H13<Q$2+7,$H13>Q$2),3, IF(AND($F13<=Q$2, $H13>=Q$2), 2, "" ))) | R13: =IF(AND($F13<(R$2+7),$F13>R$2),1, IF(AND($H13<R$2+7,$H13>R$2),3, IF(AND($F13<=R$2, $H13>=R$2), 2, "" ))) | S13: =IF(AND($F13<(S$2+7),$F13>S$2),1, IF(AND($H13<S$2+7,$H13>S$2),3, IF(AND($F13<=S$2, $H13>=S$2), 2, "" ))) | ... AQ13: =IF(AND($F13<(AQ$2+7),$F13>AQ$2),1, IF(AND($H13<AQ$2+7,$H13>AQ$2),3, IF(AND($F13<=AQ$2, $H13>=AQ$2), 2, "" )))
A14: 7 | B14: Equipment Delivery | C14: 43983 | D14: 9 | E14: 43994 | F14: 43983 | G14: 9 | H14: 43994 | L14: =IF(AND($F14<(L$2+7),$F14>L$2),1, IF(AND($H14<L$2+7,$H14>L$2),3, IF(AND($F14<=L$2, $H14>=L$2), 2, "" ))) | M14: =IF(AND($F14<(M$2+7),$F14>M$2),1, IF(AND($H14<M$2+7,$H14>M$2),3, IF(AND($F14<=M$2, $H14>=M$2), 2, "" ))) | N14: =IF(AND($F14<(N$2+7),$F14>N$2),1, IF(AND($H14<N$2+7,$H14>N$2),3, IF(AND($F14<=N$2, $H14>=N$2), 2, "" ))) | O14: =IF(AND($F14<(O$2+7),$F14>O$2),1, IF(AND($H14<O$2+7,$H14>O$2),3, IF(AND($F14<=O$2, $H14>=O$2), 2, "" ))) | P14: =IF(AND($F14<(P$2+7),$F14>P$2),1, IF(AND($H14<P$2+7,$H14>P$2),3, IF(AND($F14<=P$2, $H14>=P$2), 2, "" ))) | Q14: =IF(AND($F14<(Q$2+7),$F14>Q$2),1, IF(AND($H14<Q$2+7,$H14>Q$2),3, IF(AND($F14<=Q$2, $H14>=Q$2), 2, "" ))) | R14: =IF(AND($F14<(R$2+7),$F14>R$2),1, IF(AND($H14<R$2+7,$H14>R$2),3, IF(AND($F14<=R$2, $H14>=R$2), 2, "" ))) | S14: =IF(AND($F14<(S$2+7),$F14>S$2),1, IF(AND($H14<S$2+7,$H14>S$2),3, IF(AND($F14<=S$2, $H14>=S$2), 2, "" ))) | ... AQ14: =IF(AND($F14<(AQ$2+7),$F14>AQ$2),1, IF(AND($H14<AQ$2+7,$H14>AQ$2),3, IF(AND($F14<=AQ$2, $H14>=AQ$2), 2, "" )))
B15: Mounting Structure Delivery | C15: 43983 | D15: 2 | E15: 43985 | F15: 43983 | G15: 2 | H15: 43985
B16: Panel Delivery | C16: 43990 | D16: 2 | E16: 43992 | F16: 43990 | G16: 2 | H16: 43992 | L16: =IF(AND($F16<(L$2+7),$F16>L$2),1, IF(AND($H16<L$2+7,$H16>L$2),3, IF(AND($F16<=L$2, $H16>=L$2), 2, "" ))) | M16: =IF(AND($F16<(M$2+7),$F16>M$2),1, IF(AND($H16<M$2+7,$H16>M$2),3, IF(AND($F16<=M$2, $H16>=M$2), 2, "" ))) | N16: =IF(AND($F16<(N$2+7),$F16>N$2),1, IF(AND($H16<N$2+7,$H16>N$2),3, IF(AND($F16<=N$2, $H16>=N$2), 2, "" ))) | O16: =IF(AND($F16<(O$2+7),$F16>O$2),1, IF(AND($H16<O$2+7,$H16>O$2),3, IF(AND($F16<=O$2, $H16>=O$2), 2, "" ))) | P16: =IF(AND($F16<(P$2+7),$F16>P$2),1, IF(AND($H16<P$2+7,$H16>P$2),3, IF(AND($F16<=P$2, $H16>=P$2), 2, "" ))) | Q16: =IF(AND($F16<(Q$2+7),$F16>Q$2),1, IF(AND($H16<Q$2+7,$H16>Q$2),3, IF(AND($F16<=Q$2, $H16>=Q$2), 2, "" ))) | R16: =IF(AND($F16<(R$2+7),$F16>R$2),1, IF(AND($H16<R$2+7,$H16>R$2),3, IF(AND($F16<=R$2, $H16>=R$2), 2, "" ))) | S16: =IF(AND($F16<(S$2+7),$F16>S$2),1, IF(AND($H16<S$2+7,$H16>S$2),3, IF(AND($F16<=S$2, $H16>=S$2), 2, "" ))) | ... AQ16: =IF(AND($F16<(AQ$2+7),$F16>AQ$2),1, IF(AND($H16<AQ$2+7,$H16>AQ$2),3, IF(AND($F16<=AQ$2, $H16>=AQ$2), 2, "" )))
B17: Generator Delivery | C17: 43983 | D17: 2 | E17: 43985 | F17: 43983 | G17: 2 | H17: 43985
A18: B | B18: PAYMENT MILESTONE 2: DELIVERY OF PV PANELS | C18: 43992 | D18: 2 | E18: 43994 | F18: 43992 | G18: 2 | H18: 43994
B19: Inverter Delivery | C19: 43983 | D19: 2 | E19: 43985 | F19: 43983 | G19: 2 | H19: 43985 | L19: =IF(AND($F19<(L$2+7),$F19>L$2),1, IF(AND($H19<L$2+7,$H19>L$2),3, IF(AND($F19<=L$2, $H19>=L$2), 2, "" ))) | M19: =IF(AND($F19<(M$2+7),$F19>M$2),1, IF(AND($H19<M$2+7,$H19>M$2),3, IF(AND($F19<=M$2, $H19>=M$2), 2, "" ))) | N19: =IF(AND($F19<(N$2+7),$F19>N$2),1, IF(AND($H19<N$2+7,$H19>N$2),3, IF(AND($F19<=N$2, $H19>=N$2), 2, "" ))) | O19: =IF(AND($F19<(O$2+7),$F19>O$2),1, IF(AND($H19<O$2+7,$H19>O$2),3, IF(AND($F19<=O$2, $H19>=O$2), 2, "" ))) | P19: =IF(AND($F19<(P$2+7),$F19>P$2),1, IF(AND($H19<P$2+7,$H19>P$2),3, IF(AND($F19<=P$2, $H19>=P$2), 2, "" ))) | Q19: =IF(AND($F19<(Q$2+7),$F19>Q$2),1, IF(AND($H19<Q$2+7,$H19>Q$2),3, IF(AND($F19<=Q$2, $H19>=Q$2), 2, "" ))) | R19: =IF(AND($F19<(R$2+7),$F19>R$2),1, IF(AND($H19<R$2+7,$H19>R$2),3, IF(AND($F19<=R$2, $H19>=R$2), 2, "" ))) | S19: =IF(AND($F19<(S$2+7),$F19>S$2),1, IF(AND($H19<S$2+7,$H19>S$2),3, IF(AND($F19<=S$2, $H19>=S$2), 2, "" ))) | ... AQ19: =IF(AND($F19<(AQ$2+7),$F19>AQ$2),1, IF(AND($H19<AQ$2+7,$H19>AQ$2),3, IF(AND($F19<=AQ$2, $H19>=AQ$2), 2, "" )))
B20: BOS Delivery | C20: 43983 | D20: 1 | E20: 43984 | F20: 43983 | G20: 1 | H20: 43984 | L20: =IF(AND($F20<(L$2+7),$F20>L$2),1, IF(AND($H20<L$2+7,$H20>L$2),3, IF(AND($F20<=L$2, $H20>=L$2), 2, "" ))) | M20: =IF(AND($F20<(M$2+7),$F20>M$2),1, IF(AND($H20<M$2+7,$H20>M$2),3, IF(AND($F20<=M$2, $H20>=M$2), 2, "" ))) | N20: =IF(AND($F20<(N$2+7),$F20>N$2),1, IF(AND($H20<N$2+7,$H20>N$2),3, IF(AND($F20<=N$2, $H20>=N$2), 2, "" ))) | O20: =IF(AND($F20<(O$2+7),$F20>O$2),1, IF(AND($H20<O$2+7,$H20>O$2),3, IF(AND($F20<=O$2, $H20>=O$2), 2, "" ))) | P20: =IF(AND($F20<(P$2+7),$F20>P$2),1, IF(AND($H20<P$2+7,$H20>P$2),3, IF(AND($F20<=P$2, $H20>=P$2), 2, "" ))) | Q20: =IF(AND($F20<(Q$2+7),$F20>Q$2),1, IF(AND($H20<Q$2+7,$H20>Q$2),3, IF(AND($F20<=Q$2, $H20>=Q$2), 2, "" ))) | R20: =IF(AND($F20<(R$2+7),$F20>R$2),1, IF(AND($H20<R$2+7,$H20>R$2),3, IF(AND($F20<=R$2, $H20>=R$2), 2, "" ))) | S20: =IF(AND($F20<(S$2+7),$F20>S$2),1, IF(AND($H20<S$2+7,$H20>S$2),3, IF(AND($F20<=S$2, $H20>=S$2), 2, "" ))) | ... AQ20: =IF(AND($F20<(AQ$2+7),$F20>AQ$2),1, IF(AND($H20<AQ$2+7,$H20>AQ$2),3, IF(AND($F20<=AQ$2, $H20>=AQ$2), 2, "" )))
A21: C | B21: PAYMENT MILESTONE 3: DELIVERY OF INVERTERS AND BOS | C21: 43985 | D21: 2 | E21: 43987 | F21: 43985 | G21: 2 | H21: 43987
A22: 8 | B22: Installation | C22: 43990 | D22: 22 | E22: 44012 | F22: 43990 | G22: 22 | H22: 44012 | L22: =IF(AND($F22<(L$2+7),$F22>L$2),1, IF(AND($H22<L$2+7,$H22>L$2),3, IF(AND($F22<=L$2, $H22>=L$2), 2, "" ))) | M22: =IF(AND($F22<(M$2+7),$F22>M$2),1, IF(AND($H22<M$2+7,$H22>M$2),3, IF(AND($F22<=M$2, $H22>=M$2), 2, "" ))) | N22: =IF(AND($F22<(N$2+7),$F22>N$2),1, IF(AND($H22<N$2+7,$H22>N$2),3, IF(AND($F22<=N$2, $H22>=N$2), 2, "" ))) | O22: =IF(AND($F22<(O$2+7),$F22>O$2),1, IF(AND($H22<O$2+7,$H22>O$2),3, IF(AND($F22<=O$2, $H22>=O$2), 2, "" ))) | P22: =IF(AND($F22<(P$2+7),$F22>P$2),1, IF(AND($H22<P$2+7,$H22>P$2),3, IF(AND($F22<=P$2, $H22>=P$2), 2, "" ))) | Q22: =IF(AND($F22<(Q$2+7),$F22>Q$2),1, IF(AND($H22<Q$2+7,$H22>Q$2),3, IF(AND($F22<=Q$2, $H22>=Q$2), 2, "" ))) | R22: =IF(AND($F22<(R$2+7),$F22>R$2),1, IF(AND($H22<R$2+7,$H22>R$2),3, IF(AND($F22<=R$2, $H22>=R$2), 2, "" ))) | S22: =IF(AND($F22<(S$2+7),$F22>S$2),1, IF(AND($H22<S$2+7,$H22>S$2),3, IF(AND($F22<=S$2, $H22>=S$2), 2, "" ))) | ... AQ22: =IF(AND($F22<(AQ$2+7),$F22>AQ$2),1, IF(AND($H22<AQ$2+7,$H22>AQ$2),3, IF(AND($F22<=AQ$2, $H22>=AQ$2), 2, "" ))) -> 2
B23: Site Establishment | C23: 43990 | D23: 1 | E23: 43991 | F23: 43990 | G23: 1 | H23: 43991 | J23: Installation placed on hold due to Covid-19 case | L23: =IF(AND($F23<(L$2+7),$F23>L$2),1, IF(AND($H23<L$2+7,$H23>L$2),3, IF(AND($F23<=L$2, $H23>=L$2), 2, "" ))) | M23: =IF(AND($F23<(M$2+7),$F23>M$2),1, IF(AND($H23<M$2+7,$H23>M$2),3, IF(AND($F23<=M$2, $H23>=M$2), 2, "" ))) | N23: =IF(AND($F23<(N$2+7),$F23>N$2),1, IF(AND($H23<N$2+7,$H23>N$2),3, IF(AND($F23<=N$2, $H23>=N$2), 2, "" ))) | O23: =IF(AND($F23<(O$2+7),$F23>O$2),1, IF(AND($H23<O$2+7,$H23>O$2),3, IF(AND($F23<=O$2, $H23>=O$2), 2, "" ))) | P23: =IF(AND($F23<(P$2+7),$F23>P$2),1, IF(AND($H23<P$2+7,$H23>P$2),3, IF(AND($F23<=P$2, $H23>=P$2), 2, "" ))) | Q23: =IF(AND($F23<(Q$2+7),$F23>Q$2),1, IF(AND($H23<Q$2+7,$H23>Q$2),3, IF(AND($F23<=Q$2, $H23>=Q$2), 2, "" ))) | R23: =IF(AND($F23<(R$2+7),$F23>R$2),1, IF(AND($H23<R$2+7,$H23>R$2),3, IF(AND($F23<=R$2, $H23>=R$2), 2, "" ))) | S23: =IF(AND($F23<(S$2+7),$F23>S$2),1, IF(AND($H23<S$2+7,$H23>S$2),3, IF(AND($F23<=S$2, $H23>=S$2), 2, "" ))) | ... AQ23: =IF(AND($F23<(AQ$2+7),$F23>AQ$2),1, IF(AND($H23<AQ$2+7,$H23>AQ$2),3, IF(AND($F23<=AQ$2, $H23>=AQ$2), 2, "" )))
A24: 9 | B24: DC Works | C24: 43991 | D24: 16 | E24: 44012 | F24: 43991 | G24: 16 | H24: 44012 | L24: =IF(AND($F24<(L$2+7),$F24>L$2),1, IF(AND($H24<L$2+7,$H24>L$2),3, IF(AND($F24<=L$2, $H24>=L$2), 2, "" ))) | M24: =IF(AND($F24<(M$2+7),$F24>M$2),1, IF(AND($H24<M$2+7,$H24>M$2),3, IF(AND($F24<=M$2, $H24>=M$2), 2, "" ))) | N24: =IF(AND($F24<(N$2+7),$F24>N$2),1, IF(AND($H24<N$2+7,$H24>N$2),3, IF(AND($F24<=N$2, $H24>=N$2), 2, "" ))) | O24: =IF(AND($F24<(O$2+7),$F24>O$2),1, IF(AND($H24<O$2+7,$H24>O$2),3, IF(AND($F24<=O$2, $H24>=O$2), 2, "" ))) | P24: =IF(AND($F24<(P$2+7),$F24>P$2),1, IF(AND($H24<P$2+7,$H24>P$2),3, IF(AND($F24<=P$2, $H24>=P$2), 2, "" ))) | Q24: =IF(AND($F24<(Q$2+7),$F24>Q$2),1, IF(AND($H24<Q$2+7,$H24>Q$2),3, IF(AND($F24<=Q$2, $H24>=Q$2), 2, "" ))) | R24: =IF(AND($F24<(R$2+7),$F24>R$2),1, IF(AND($H24<R$2+7,$H24>R$2),3, IF(AND($F24<=R$2, $H24>=R$2), 2, "" ))) | S24: =IF(AND($F24<(S$2+7),$F24>S$2),1, IF(AND($H24<S$2+7,$H24>S$2),3, IF(AND($F24<=S$2, $H24>=S$2), 2, "" ))) | ... AQ24: =IF(AND($F24<(AQ$2+7),$F24>AQ$2),1, IF(AND($H24<AQ$2+7,$H24>AQ$2),3, IF(AND($F24<=AQ$2, $H24>=AQ$2), 2, "" ))) -> 2
B25: Mounting structure Installation | C25: 43991 | D25: 4 | E25: 43997 | F25: 43991 | G25: 4 | H25: 43997 | L25: =IF(AND($F25<(L$2+7),$F25>L$2),1, IF(AND($H25<L$2+7,$H25>L$2),3, IF(AND($F25<=L$2, $H25>=L$2), 2, "" ))) | M25: =IF(AND($F25<(M$2+7),$F25>M$2),1, IF(AND($H25<M$2+7,$H25>M$2),3, IF(AND($F25<=M$2, $H25>=M$2), 2, "" ))) | N25: =IF(AND($F25<(N$2+7),$F25>N$2),1, IF(AND($H25<N$2+7,$H25>N$2),3, IF(AND($F25<=N$2, $H25>=N$2), 2, "" ))) | O25: =IF(AND($F25<(O$2+7),$F25>O$2),1, IF(AND($H25<O$2+7,$H25>O$2),3, IF(AND($F25<=O$2, $H25>=O$2), 2, "" ))) | P25: =IF(AND($F25<(P$2+7),$F25>P$2),1, IF(AND($H25<P$2+7,$H25>P$2),3, IF(AND($F25<=P$2, $H25>=P$2), 2, "" ))) | Q25: =IF(AND($F25<(Q$2+7),$F25>Q$2),1, IF(AND($H25<Q$2+7,$H25>Q$2),3, IF(AND($F25<=Q$2, $H25>=Q$2), 2, "" ))) | R25: =IF(AND($F25<(R$2+7),$F25>R$2),1, IF(AND($H25<R$2+7,$H25>R$2),3, IF(AND($F25<=R$2, $H25>=R$2), 2, "" ))) | S25: =IF(AND($F25<(S$2+7),$F25>S$2),1, IF(AND($H25<S$2+7,$H25>S$2),3, IF(AND($F25<=S$2, $H25>=S$2), 2, "" ))) | ... AQ25: =IF(AND($F25<(AQ$2+7),$F25>AQ$2),1, IF(AND($H25<AQ$2+7,$H25>AQ$2),3, IF(AND($F25<=AQ$2, $H25>=AQ$2), 2, "" )))
B26: Cable tray Installation | C26: 43997 | D26: 3 | E26: 44004 | F26: 43997 | G26: 3 | H26: 44004 | L26: =IF(AND($F26<(L$2+7),$F26>L$2),1, IF(AND($H26<L$2+7,$H26>L$2),3, IF(AND($F26<=L$2, $H26>=L$2), 2, "" ))) | M26: =IF(AND($F26<(M$2+7),$F26>M$2),1, IF(AND($H26<M$2+7,$H26>M$2),3, IF(AND($F26<=M$2, $H26>=M$2), 2, "" ))) | N26: =IF(AND($F26<(N$2+7),$F26>N$2),1, IF(AND($H26<N$2+7,$H26>N$2),3, IF(AND($F26<=N$2, $H26>=N$2), 2, "" ))) | O26: =IF(AND($F26<(O$2+7),$F26>O$2),1, IF(AND($H26<O$2+7,$H26>O$2),3, IF(AND($F26<=O$2, $H26>=O$2), 2, "" ))) | P26: =IF(AND($F26<(P$2+7),$F26>P$2),1, IF(AND($H26<P$2+7,$H26>P$2),3, IF(AND($F26<=P$2, $H26>=P$2), 2, "" ))) | Q26: =IF(AND($F26<(Q$2+7),$F26>Q$2),1, IF(AND($H26<Q$2+7,$H26>Q$2),3, IF(AND($F26<=Q$2, $H26>=Q$2), 2, "" ))) | R26: =IF(AND($F26<(R$2+7),$F26>R$2),1, IF(AND($H26<R$2+7,$H26>R$2),3, IF(AND($F26<=R$2, $H26>=R$2), 2, "" ))) | S26: =IF(AND($F26<(S$2+7),$F26>S$2),1, IF(AND($H26<S$2+7,$H26>S$2),3, IF(AND($F26<=S$2, $H26>=S$2), 2, "" ))) | ... AQ26: =IF(AND($F26<(AQ$2+7),$F26>AQ$2),1, IF(AND($H26<AQ$2+7,$H26>AQ$2),3, IF(AND($F26<=AQ$2, $H26>=AQ$2), 2, "" )))
B27: DC Cable Installation | C27: 44004 | D27: 2 | E27: 44006 | F27: 44004 | G27: 2 | H27: 44006 | L27: =IF(AND($F27<(L$2+7),$F27>L$2),1, IF(AND($H27<L$2+7,$H27>L$2),3, IF(AND($F27<=L$2, $H27>=L$2), 2, "" ))) | M27: =IF(AND($F27<(M$2+7),$F27>M$2),1, IF(AND($H27<M$2+7,$H27>M$2),3, IF(AND($F27<=M$2, $H27>=M$2), 2, "" ))) | N27: =IF(AND($F27<(N$2+7),$F27>N$2),1, IF(AND($H27<N$2+7,$H27>N$2),3, IF(AND($F27<=N$2, $H27>=N$2), 2, "" ))) | O27: =IF(AND($F27<(O$2+7),$F27>O$2),1, IF(AND($H27<O$2+7,$H27>O$2),3, IF(AND($F27<=O$2, $H27>=O$2), 2, "" ))) | P27: =IF(AND($F27<(P$2+7),$F27>P$2),1, IF(AND($H27<P$2+7,$H27>P$2),3, IF(AND($F27<=P$2, $H27>=P$2), 2, "" ))) | Q27: =IF(AND($F27<(Q$2+7),$F27>Q$2),1, IF(AND($H27<Q$2+7,$H27>Q$2),3, IF(AND($F27<=Q$2, $H27>=Q$2), 2, "" ))) | R27: =IF(AND($F27<(R$2+7),$F27>R$2),1, IF(AND($H27<R$2+7,$H27>R$2),3, IF(AND($F27<=R$2, $H27>=R$2), 2, "" ))) | S27: =IF(AND($F27<(S$2+7),$F27>S$2),1, IF(AND($H27<S$2+7,$H27>S$2),3, IF(AND($F27<=S$2, $H27>=S$2), 2, "" ))) | ... AQ27: =IF(AND($F27<(AQ$2+7),$F27>AQ$2),1, IF(AND($H27<AQ$2+7,$H27>AQ$2),3, IF(AND($F27<=AQ$2, $H27>=AQ$2), 2, "" )))
B28: Module Installation | C28: 44006 | D28: 4 | E28: 44012 | F28: 44006 | G28: 4 | H28: 44012 | L28: =IF(AND($F28<(L$2+7),$F28>L$2),1, IF(AND($H28<L$2+7,$H28>L$2),3, IF(AND($F28<=L$2, $H28>=L$2), 2, "" ))) | M28: =IF(AND($F28<(M$2+7),$F28>M$2),1, IF(AND($H28<M$2+7,$H28>M$2),3, IF(AND($F28<=M$2, $H28>=M$2), 2, "" ))) | N28: =IF(AND($F28<(N$2+7),$F28>N$2),1, IF(AND($H28<N$2+7,$H28>N$2),3, IF(AND($F28<=N$2, $H28>=N$2), 2, "" ))) | O28: =IF(AND($F28<(O$2+7),$F28>O$2),1, IF(AND($H28<O$2+7,$H28>O$2),3, IF(AND($F28<=O$2, $H28>=O$2), 2, "" ))) | P28: =IF(AND($F28<(P$2+7),$F28>P$2),1, IF(AND($H28<P$2+7,$H28>P$2),3, IF(AND($F28<=P$2, $H28>=P$2), 2, "" ))) | Q28: =IF(AND($F28<(Q$2+7),$F28>Q$2),1, IF(AND($H28<Q$2+7,$H28>Q$2),3, IF(AND($F28<=Q$2, $H28>=Q$2), 2, "" ))) | R28: =IF(AND($F28<(R$2+7),$F28>R$2),1, IF(AND($H28<R$2+7,$H28>R$2),3, IF(AND($F28<=R$2, $H28>=R$2), 2, "" ))) | S28: =IF(AND($F28<(S$2+7),$F28>S$2),1, IF(AND($H28<S$2+7,$H28>S$2),3, IF(AND($F28<=S$2, $H28>=S$2), 2, "" ))) | ... AQ28: =IF(AND($F28<(AQ$2+7),$F28>AQ$2),1, IF(AND($H28<AQ$2+7,$H28>AQ$2),3, IF(AND($F28<=AQ$2, $H28>=AQ$2), 2, "" ))) -> 2
B29: Earth Cable Installation | C29: 44004 | D29: 1 | E29: 44005 | F29: 44004 | G29: 1 | H29: 44005 | L29: =IF(AND($F29<(L$2+7),$F29>L$2),1, IF(AND($H29<L$2+7,$H29>L$2),3, IF(AND($F29<=L$2, $H29>=L$2), 2, "" ))) | M29: =IF(AND($F29<(M$2+7),$F29>M$2),1, IF(AND($H29<M$2+7,$H29>M$2),3, IF(AND($F29<=M$2, $H29>=M$2), 2, "" ))) | N29: =IF(AND($F29<(N$2+7),$F29>N$2),1, IF(AND($H29<N$2+7,$H29>N$2),3, IF(AND($F29<=N$2, $H29>=N$2), 2, "" ))) | O29: =IF(AND($F29<(O$2+7),$F29>O$2),1, IF(AND($H29<O$2+7,$H29>O$2),3, IF(AND($F29<=O$2, $H29>=O$2), 2, "" ))) | P29: =IF(AND($F29<(P$2+7),$F29>P$2),1, IF(AND($H29<P$2+7,$H29>P$2),3, IF(AND($F29<=P$2, $H29>=P$2), 2, "" ))) | Q29: =IF(AND($F29<(Q$2+7),$F29>Q$2),1, IF(AND($H29<Q$2+7,$H29>Q$2),3, IF(AND($F29<=Q$2, $H29>=Q$2), 2, "" ))) | R29: =IF(AND($F29<(R$2+7),$F29>R$2),1, IF(AND($H29<R$2+7,$H29>R$2),3, IF(AND($F29<=R$2, $H29>=R$2), 2, "" ))) | S29: =IF(AND($F29<(S$2+7),$F29>S$2),1, IF(AND($H29<S$2+7,$H29>S$2),3, IF(AND($F29<=S$2, $H29>=S$2), 2, "" ))) | ... AQ29: =IF(AND($F29<(AQ$2+7),$F29>AQ$2),1, IF(AND($H29<AQ$2+7,$H29>AQ$2),3, IF(AND($F29<=AQ$2, $H29>=AQ$2), 2, "" )))
A30: 10 | B30: AC Works | C30: 43991 | D30: 8 | E30: 44000 | F30: 43991 | G30: 8 | H30: 44000
B31: Inverters Installation | C31: 43991 | D31: 2 | E31: 43993 | F31: 43991 | G31: 2 | H31: 43993 | L31: =IF(AND($F31<(L$2+7),$F31>L$2),1, IF(AND($H31<L$2+7,$H31>L$2),3, IF(AND($F31<=L$2, $H31>=L$2), 2, "" ))) | M31: =IF(AND($F31<(M$2+7),$F31>M$2),1, IF(AND($H31<M$2+7,$H31>M$2),3, IF(AND($F31<=M$2, $H31>=M$2), 2, "" ))) | N31: =IF(AND($F31<(N$2+7),$F31>N$2),1, IF(AND($H31<N$2+7,$H31>N$2),3, IF(AND($F31<=N$2, $H31>=N$2), 2, "" ))) | O31: =IF(AND($F31<(O$2+7),$F31>O$2),1, IF(AND($H31<O$2+7,$H31>O$2),3, IF(AND($F31<=O$2, $H31>=O$2), 2, "" ))) | P31: =IF(AND($F31<(P$2+7),$F31>P$2),1, IF(AND($H31<P$2+7,$H31>P$2),3, IF(AND($F31<=P$2, $H31>=P$2), 2, "" ))) | Q31: =IF(AND($F31<(Q$2+7),$F31>Q$2),1, IF(AND($H31<Q$2+7,$H31>Q$2),3, IF(AND($F31<=Q$2, $H31>=Q$2), 2, "" ))) | R31: =IF(AND($F31<(R$2+7),$F31>R$2),1, IF(AND($H31<R$2+7,$H31>R$2),3, IF(AND($F31<=R$2, $H31>=R$2), 2, "" ))) | S31: =IF(AND($F31<(S$2+7),$F31>S$2),1, IF(AND($H31<S$2+7,$H31>S$2),3, IF(AND($F31<=S$2, $H31>=S$2), 2, "" ))) | ... AQ31: =IF(AND($F31<(AQ$2+7),$F31>AQ$2),1, IF(AND($H31<AQ$2+7,$H31>AQ$2),3, IF(AND($F31<=AQ$2, $H31>=AQ$2), 2, "" )))
B32: AC BOS Installation | C32: 43993 | D32: 3 | E32: 44000 | F32: 43993 | G32: 3 | H32: 44000 | L32: =IF(AND($F32<(L$2+7),$F32>L$2),1, IF(AND($H32<L$2+7,$H32>L$2),3, IF(AND($F32<=L$2, $H32>=L$2), 2, "" ))) | M32: =IF(AND($F32<(M$2+7),$F32>M$2),1, IF(AND($H32<M$2+7,$H32>M$2),3, IF(AND($F32<=M$2, $H32>=M$2), 2, "" ))) | N32: =IF(AND($F32<(N$2+7),$F32>N$2),1, IF(AND($H32<N$2+7,$H32>N$2),3, IF(AND($F32<=N$2, $H32>=N$2), 2, "" ))) | O32: =IF(AND($F32<(O$2+7),$F32>O$2),1, IF(AND($H32<O$2+7,$H32>O$2),3, IF(AND($F32<=O$2, $H32>=O$2), 2, "" ))) | P32: =IF(AND($F32<(P$2+7),$F32>P$2),1, IF(AND($H32<P$2+7,$H32>P$2),3, IF(AND($F32<=P$2, $H32>=P$2), 2, "" ))) | Q32: =IF(AND($F32<(Q$2+7),$F32>Q$2),1, IF(AND($H32<Q$2+7,$H32>Q$2),3, IF(AND($F32<=Q$2, $H32>=Q$2), 2, "" ))) | R32: =IF(AND($F32<(R$2+7),$F32>R$2),1, IF(AND($H32<R$2+7,$H32>R$2),3, IF(AND($F32<=R$2, $H32>=R$2), 2, "" ))) | S32: =IF(AND($F32<(S$2+7),$F32>S$2),1, IF(AND($H32<S$2+7,$H32>S$2),3, IF(AND($F32<=S$2, $H32>=S$2), 2, "" ))) | ... AQ32: =IF(AND($F32<(AQ$2+7),$F32>AQ$2),1, IF(AND($H32<AQ$2+7,$H32>AQ$2),3, IF(AND($F32<=AQ$2, $H32>=AQ$2), 2, "" )))
B33: AC Cable/Tie-In | C33: 43992 | D33: 3 | E33: 43997 | F33: 43992 | G33: 3 | H33: 43997 | L33: =IF(AND($F33<(L$2+7),$F33>L$2),1, IF(AND($H33<L$2+7,$H33>L$2),3, IF(AND($F33<=L$2, $H33>=L$2), 2, "" ))) | M33: =IF(AND($F33<(M$2+7),$F33>M$2),1, IF(AND($H33<M$2+7,$H33>M$2),3, IF(AND($F33<=M$2, $H33>=M$2), 2, "" ))) | N33: =IF(AND($F33<(N$2+7),$F33>N$2),1, IF(AND($H33<N$2+7,$H33>N$2),3, IF(AND($F33<=N$2, $H33>=N$2), 2, "" ))) | O33: =IF(AND($F33<(O$2+7),$F33>O$2),1, IF(AND($H33<O$2+7,$H33>O$2),3, IF(AND($F33<=O$2, $H33>=O$2), 2, "" ))) | P33: =IF(AND($F33<(P$2+7),$F33>P$2),1, IF(AND($H33<P$2+7,$H33>P$2),3, IF(AND($F33<=P$2, $H33>=P$2), 2, "" ))) | Q33: =IF(AND($F33<(Q$2+7),$F33>Q$2),1, IF(AND($H33<Q$2+7,$H33>Q$2),3, IF(AND($F33<=Q$2, $H33>=Q$2), 2, "" ))) | R33: =IF(AND($F33<(R$2+7),$F33>R$2),1, IF(AND($H33<R$2+7,$H33>R$2),3, IF(AND($F33<=R$2, $H33>=R$2), 2, "" ))) | S33: =IF(AND($F33<(S$2+7),$F33>S$2),1, IF(AND($H33<S$2+7,$H33>S$2),3, IF(AND($F33<=S$2, $H33>=S$2), 2, "" ))) | ... AQ33: =IF(AND($F33<(AQ$2+7),$F33>AQ$2),1, IF(AND($H33<AQ$2+7,$H33>AQ$2),3, IF(AND($F33<=AQ$2, $H33>=AQ$2), 2, "" )))
B34: Monitoring Platform Installation | C34: 43997 | D34: 1 | E34: 44000 | F34: 43997 | G34: 1 | H34: 44000
A35: 11 | B35: Completion | C35: 44000 | D35: 14 | E35: 44014 | F35: 44000 | G35: 14 | H35: 44014 | L35: =IF(AND($F35<(L$2+7),$F35>L$2),1, IF(AND($H35<L$2+7,$H35>L$2),3, IF(AND($F35<=L$2, $H35>=L$2), 2, "" ))) | M35: =IF(AND($F35<(M$2+7),$F35>M$2),1, IF(AND($H35<M$2+7,$H35>M$2),3, IF(AND($F35<=M$2, $H35>=M$2), 2, "" ))) | N35: =IF(AND($F35<(N$2+7),$F35>N$2),1, IF(AND($H35<N$2+7,$H35>N$2),3, IF(AND($F35<=N$2, $H35>=N$2), 2, "" ))) | O35: =IF(AND($F35<(O$2+7),$F35>O$2),1, IF(AND($H35<O$2+7,$H35>O$2),3, IF(AND($F35<=O$2, $H35>=O$2), 2, "" ))) | P35: =IF(AND($F35<(P$2+7),$F35>P$2),1, IF(AND($H35<P$2+7,$H35>P$2),3, IF(AND($F35<=P$2, $H35>=P$2), 2, "" ))) | Q35: =IF(AND($F35<(Q$2+7),$F35>Q$2),1, IF(AND($H35<Q$2+7,$H35>Q$2),3, IF(AND($F35<=Q$2, $H35>=Q$2), 2, "" ))) | R35: =IF(AND($F35<(R$2+7),$F35>R$2),1, IF(AND($H35<R$2+7,$H35>R$2),3, IF(AND($F35<=R$2, $H35>=R$2), 2, "" ))) | S35: =IF(AND($F35<(S$2+7),$F35>S$2),1, IF(AND($H35<S$2+7,$H35>S$2),3, IF(AND($F35<=S$2, $H35>=S$2), 2, "" ))) | ... AQ35: =IF(AND($F35<(AQ$2+7),$F35>AQ$2),1, IF(AND($H35<AQ$2+7,$H35>AQ$2),3, IF(AND($F35<=AQ$2, $H35>=AQ$2), 2, "" ))) -> 3
B36: DC Works | C36: 44012 | D36: 2 | E36: 44014 | F36: 44012 | G36: 2 | H36: 44014 | L36: =IF(AND($F36<(L$2+7),$F36>L$2),1, IF(AND($H36<L$2+7,$H36>L$2),3, IF(AND($F36<=L$2, $H36>=L$2), 2, "" ))) | M36: =IF(AND($F36<(M$2+7),$F36>M$2),1, IF(AND($H36<M$2+7,$H36>M$2),3, IF(AND($F36<=M$2, $H36>=M$2), 2, "" ))) | N36: =IF(AND($F36<(N$2+7),$F36>N$2),1, IF(AND($H36<N$2+7,$H36>N$2),3, IF(AND($F36<=N$2, $H36>=N$2), 2, "" ))) | O36: =IF(AND($F36<(O$2+7),$F36>O$2),1, IF(AND($H36<O$2+7,$H36>O$2),3, IF(AND($F36<=O$2, $H36>=O$2), 2, "" ))) | P36: =IF(AND($F36<(P$2+7),$F36>P$2),1, IF(AND($H36<P$2+7,$H36>P$2),3, IF(AND($F36<=P$2, $H36>=P$2), 2, "" ))) | Q36: =IF(AND($F36<(Q$2+7),$F36>Q$2),1, IF(AND($H36<Q$2+7,$H36>Q$2),3, IF(AND($F36<=Q$2, $H36>=Q$2), 2, "" ))) | R36: =IF(AND($F36<(R$2+7),$F36>R$2),1, IF(AND($H36<R$2+7,$H36>R$2),3, IF(AND($F36<=R$2, $H36>=R$2), 2, "" ))) | S36: =IF(AND($F36<(S$2+7),$F36>S$2),1, IF(AND($H36<S$2+7,$H36>S$2),3, IF(AND($F36<=S$2, $H36>=S$2), 2, "" ))) | ... AQ36: =IF(AND($F36<(AQ$2+7),$F36>AQ$2),1, IF(AND($H36<AQ$2+7,$H36>AQ$2),3, IF(AND($F36<=AQ$2, $H36>=AQ$2), 2, "" ))) -> 3
B37: AC Works | C37: 44000 | D37: 2 | E37: 44004 | F37: 44000 | G37: 2 | H37: 44004 | L37: =IF(AND($F37<(L$2+7),$F37>L$2),1, IF(AND($H37<L$2+7,$H37>L$2),3, IF(AND($F37<=L$2, $H37>=L$2), 2, "" ))) | M37: =IF(AND($F37<(M$2+7),$F37>M$2),1, IF(AND($H37<M$2+7,$H37>M$2),3, IF(AND($F37<=M$2, $H37>=M$2), 2, "" ))) | N37: =IF(AND($F37<(N$2+7),$F37>N$2),1, IF(AND($H37<N$2+7,$H37>N$2),3, IF(AND($F37<=N$2, $H37>=N$2), 2, "" ))) | O37: =IF(AND($F37<(O$2+7),$F37>O$2),1, IF(AND($H37<O$2+7,$H37>O$2),3, IF(AND($F37<=O$2, $H37>=O$2), 2, "" ))) | P37: =IF(AND($F37<(P$2+7),$F37>P$2),1, IF(AND($H37<P$2+7,$H37>P$2),3, IF(AND($F37<=P$2, $H37>=P$2), 2, "" ))) | Q37: =IF(AND($F37<(Q$2+7),$F37>Q$2),1, IF(AND($H37<Q$2+7,$H37>Q$2),3, IF(AND($F37<=Q$2, $H37>=Q$2), 2, "" ))) | R37: =IF(AND($F37<(R$2+7),$F37>R$2),1, IF(AND($H37<R$2+7,$H37>R$2),3, IF(AND($F37<=R$2, $H37>=R$2), 2, "" ))) | S37: =IF(AND($F37<(S$2+7),$F37>S$2),1, IF(AND($H37<S$2+7,$H37>S$2),3, IF(AND($F37<=S$2, $H37>=S$2), 2, "" ))) | ... AQ37: =IF(AND($F37<(AQ$2+7),$F37>AQ$2),1, IF(AND($H37<AQ$2+7,$H37>AQ$2),3, IF(AND($F37<=AQ$2, $H37>=AQ$2), 2, "" )))
A38: D | B38: PAYMENT MILESTONE 4: PRACTICAL COMPLETION | C38: 44012 | D38: 1 | E38: 44013 | F38: 44012 | G38: 1 | H38: 44013 | L38: =IF(AND($F38<(L$2+7),$F38>L$2),1, IF(AND($H38<L$2+7,$H38>L$2),3, IF(AND($F38<=L$2, $H38>=L$2), 2, "" ))) | M38: =IF(AND($F38<(M$2+7),$F38>M$2),1, IF(AND($H38<M$2+7,$H38>M$2),3, IF(AND($F38<=M$2, $H38>=M$2), 2, "" ))) | N38: =IF(AND($F38<(N$2+7),$F38>N$2),1, IF(AND($H38<N$2+7,$H38>N$2),3, IF(AND($F38<=N$2, $H38>=N$2), 2, "" ))) | O38: =IF(AND($F38<(O$2+7),$F38>O$2),1, IF(AND($H38<O$2+7,$H38>O$2),3, IF(AND($F38<=O$2, $H38>=O$2), 2, "" ))) | P38: =IF(AND($F38<(P$2+7),$F38>P$2),1, IF(AND($H38<P$2+7,$H38>P$2),3, IF(AND($F38<=P$2, $H38>=P$2), 2, "" ))) | Q38: =IF(AND($F38<(Q$2+7),$F38>Q$2),1, IF(AND($H38<Q$2+7,$H38>Q$2),3, IF(AND($F38<=Q$2, $H38>=Q$2), 2, "" ))) | R38: =IF(AND($F38<(R$2+7),$F38>R$2),1, IF(AND($H38<R$2+7,$H38>R$2),3, IF(AND($F38<=R$2, $H38>=R$2), 2, "" ))) | S38: =IF(AND($F38<(S$2+7),$F38>S$2),1, IF(AND($H38<S$2+7,$H38>S$2),3, IF(AND($F38<=S$2, $H38>=S$2), 2, "" ))) | ... AQ38: =IF(AND($F38<(AQ$2+7),$F38>AQ$2),1, IF(AND($H38<AQ$2+7,$H38>AQ$2),3, IF(AND($F38<=AQ$2, $H38>=AQ$2), 2, "" ))) -> 3
A39: 12 | B39: Commissioning | C39: 43997 | D39: 22 | E39: 44019 | F39: 43997 | G39: 22 | H39: 44019 | L39: =IF(AND($F39<(L$2+7),$F39>L$2),1, IF(AND($H39<L$2+7,$H39>L$2),3, IF(AND($F39<=L$2, $H39>=L$2), 2, "" ))) | M39: =IF(AND($F39<(M$2+7),$F39>M$2),1, IF(AND($H39<M$2+7,$H39>M$2),3, IF(AND($F39<=M$2, $H39>=M$2), 2, "" ))) | N39: =IF(AND($F39<(N$2+7),$F39>N$2),1, IF(AND($H39<N$2+7,$H39>N$2),3, IF(AND($F39<=N$2, $H39>=N$2), 2, "" ))) | O39: =IF(AND($F39<(O$2+7),$F39>O$2),1, IF(AND($H39<O$2+7,$H39>O$2),3, IF(AND($F39<=O$2, $H39>=O$2), 2, "" ))) | P39: =IF(AND($F39<(P$2+7),$F39>P$2),1, IF(AND($H39<P$2+7,$H39>P$2),3, IF(AND($F39<=P$2, $H39>=P$2), 2, "" ))) | Q39: =IF(AND($F39<(Q$2+7),$F39>Q$2),1, IF(AND($H39<Q$2+7,$H39>Q$2),3, IF(AND($F39<=Q$2, $H39>=Q$2), 2, "" ))) | R39: =IF(AND($F39<(R$2+7),$F39>R$2),1, IF(AND($H39<R$2+7,$H39>R$2),3, IF(AND($F39<=R$2, $H39>=R$2), 2, "" ))) | S39: =IF(AND($F39<(S$2+7),$F39>S$2),1, IF(AND($H39<S$2+7,$H39>S$2),3, IF(AND($F39<=S$2, $H39>=S$2), 2, "" ))) | ... AQ39: =IF(AND($F39<(AQ$2+7),$F39>AQ$2),1, IF(AND($H39<AQ$2+7,$H39>AQ$2),3, IF(AND($F39<=AQ$2, $H39>=AQ$2), 2, "" ))) -> 2
B40: Snag List | C40: 44014 | D40: 3 | E40: 44019 | F40: 44014 | G40: 3 | H40: 44019
B41: Pre-Commissioning Checks | C41: 44010 | D41: 2 | E41: 44012 | F41: 44010 | G41: 2 | H41: 44012
B42: Issue CoC | C42: 43997 | D42: 2 | E42: 44001 | F42: 43997 | G42: 2 | H42: 44001 | L42: =IF(AND($F42<(L$2+7),$F42>L$2),1, IF(AND($H42<L$2+7,$H42>L$2),3, IF(AND($F42<=L$2, $H42>=L$2), 2, "" ))) | M42: =IF(AND($F42<(M$2+7),$F42>M$2),1, IF(AND($H42<M$2+7,$H42>M$2),3, IF(AND($F42<=M$2, $H42>=M$2), 2, "" ))) | N42: =IF(AND($F42<(N$2+7),$F42>N$2),1, IF(AND($H42<N$2+7,$H42>N$2),3, IF(AND($F42<=N$2, $H42>=N$2), 2, "" ))) | O42: =IF(AND($F42<(O$2+7),$F42>O$2),1, IF(AND($H42<O$2+7,$H42>O$2),3, IF(AND($F42<=O$2, $H42>=O$2), 2, "" ))) | P42: =IF(AND($F42<(P$2+7),$F42>P$2),1, IF(AND($H42<P$2+7,$H42>P$2),3, IF(AND($F42<=P$2, $H42>=P$2), 2, "" ))) | Q42: =IF(AND($F42<(Q$2+7),$F42>Q$2),1, IF(AND($H42<Q$2+7,$H42>Q$2),3, IF(AND($F42<=Q$2, $H42>=Q$2), 2, "" ))) | R42: =IF(AND($F42<(R$2+7),$F42>R$2),1, IF(AND($H42<R$2+7,$H42>R$2),3, IF(AND($F42<=R$2, $H42>=R$2), 2, "" ))) | S42: =IF(AND($F42<(S$2+7),$F42>S$2),1, IF(AND($H42<S$2+7,$H42>S$2),3, IF(AND($F42<=S$2, $H42>=S$2), 2, "" ))) | ... AQ42: =IF(AND($F42<(AQ$2+7),$F42>AQ$2),1, IF(AND($H42<AQ$2+7,$H42>AQ$2),3, IF(AND($F42<=AQ$2, $H42>=AQ$2), 2, "" )))
B43: Cold Commissioning | C43: 44012 | D43: 1 | E43: 44013 | F43: 44012 | G43: 1 | H43: 44013 | L43: =IF(AND($F43<(L$2+7),$F43>L$2),1, IF(AND($H43<L$2+7,$H43>L$2),3, IF(AND($F43<=L$2, $H43>=L$2), 2, "" ))) | M43: =IF(AND($F43<(M$2+7),$F43>M$2),1, IF(AND($H43<M$2+7,$H43>M$2),3, IF(AND($F43<=M$2, $H43>=M$2), 2, "" ))) | N43: =IF(AND($F43<(N$2+7),$F43>N$2),1, IF(AND($H43<N$2+7,$H43>N$2),3, IF(AND($F43<=N$2, $H43>=N$2), 2, "" ))) | O43: =IF(AND($F43<(O$2+7),$F43>O$2),1, IF(AND($H43<O$2+7,$H43>O$2),3, IF(AND($F43<=O$2, $H43>=O$2), 2, "" ))) | P43: =IF(AND($F43<(P$2+7),$F43>P$2),1, IF(AND($H43<P$2+7,$H43>P$2),3, IF(AND($F43<=P$2, $H43>=P$2), 2, "" ))) | Q43: =IF(AND($F43<(Q$2+7),$F43>Q$2),1, IF(AND($H43<Q$2+7,$H43>Q$2),3, IF(AND($F43<=Q$2, $H43>=Q$2), 2, "" ))) | R43: =IF(AND($F43<(R$2+7),$F43>R$2),1, IF(AND($H43<R$2+7,$H43>R$2),3, IF(AND($F43<=R$2, $H43>=R$2), 2, "" ))) | S43: =IF(AND($F43<(S$2+7),$F43>S$2),1, IF(AND($H43<S$2+7,$H43>S$2),3, IF(AND($F43<=S$2, $H43>=S$2), 2, "" ))) | ... AQ43: =IF(AND($F43<(AQ$2+7),$F43>AQ$2),1, IF(AND($H43<AQ$2+7,$H43>AQ$2),3, IF(AND($F43<=AQ$2, $H43>=AQ$2), 2, "" ))) -> 3
B44: Hot Commissioning | C44: 44013 | D44: 2 | E44: 44015 | F44: 44013 | G44: 2 | H44: 44015 | L44: =IF(AND($F44<(L$2+7),$F44>L$2),1, IF(AND($H44<L$2+7,$H44>L$2),3, IF(AND($F44<=L$2, $H44>=L$2), 2, "" ))) | M44: =IF(AND($F44<(M$2+7),$F44>M$2),1, IF(AND($H44<M$2+7,$H44>M$2),3, IF(AND($F44<=M$2, $H44>=M$2), 2, "" ))) | N44: =IF(AND($F44<(N$2+7),$F44>N$2),1, IF(AND($H44<N$2+7,$H44>N$2),3, IF(AND($F44<=N$2, $H44>=N$2), 2, "" ))) | O44: =IF(AND($F44<(O$2+7),$F44>O$2),1, IF(AND($H44<O$2+7,$H44>O$2),3, IF(AND($F44<=O$2, $H44>=O$2), 2, "" ))) | P44: =IF(AND($F44<(P$2+7),$F44>P$2),1, IF(AND($H44<P$2+7,$H44>P$2),3, IF(AND($F44<=P$2, $H44>=P$2), 2, "" ))) | Q44: =IF(AND($F44<(Q$2+7),$F44>Q$2),1, IF(AND($H44<Q$2+7,$H44>Q$2),3, IF(AND($F44<=Q$2, $H44>=Q$2), 2, "" ))) | R44: =IF(AND($F44<(R$2+7),$F44>R$2),1, IF(AND($H44<R$2+7,$H44>R$2),3, IF(AND($F44<=R$2, $H44>=R$2), 2, "" ))) | S44: =IF(AND($F44<(S$2+7),$F44>S$2),1, IF(AND($H44<S$2+7,$H44>S$2),3, IF(AND($F44<=S$2, $H44>=S$2), 2, "" ))) | ... AQ44: =IF(AND($F44<(AQ$2+7),$F44>AQ$2),1, IF(AND($H44<AQ$2+7,$H44>AQ$2),3, IF(AND($F44<=AQ$2, $H44>=AQ$2), 2, "" ))) -> 1
A45: 13 | B45: Handover | C45: 44020 | D45: 1 | E45: 44021 | F45: 44020 | G45: 1 | H45: 44021 | L45: =IF(AND($F45<(L$2+7),$F45>L$2),1, IF(AND($H45<L$2+7,$H45>L$2),3, IF(AND($F45<=L$2, $H45>=L$2), 2, "" ))) | M45: =IF(AND($F45<(M$2+7),$F45>M$2),1, IF(AND($H45<M$2+7,$H45>M$2),3, IF(AND($F45<=M$2, $H45>=M$2), 2, "" ))) | N45: =IF(AND($F45<(N$2+7),$F45>N$2),1, IF(AND($H45<N$2+7,$H45>N$2),3, IF(AND($F45<=N$2, $H45>=N$2), 2, "" ))) | O45: =IF(AND($F45<(O$2+7),$F45>O$2),1, IF(AND($H45<O$2+7,$H45>O$2),3, IF(AND($F45<=O$2, $H45>=O$2), 2, "" ))) | P45: =IF(AND($F45<(P$2+7),$F45>P$2),1, IF(AND($H45<P$2+7,$H45>P$2),3, IF(AND($F45<=P$2, $H45>=P$2), 2, "" ))) | Q45: =IF(AND($F45<(Q$2+7),$F45>Q$2),1, IF(AND($H45<Q$2+7,$H45>Q$2),3, IF(AND($F45<=Q$2, $H45>=Q$2), 2, "" ))) | R45: =IF(AND($F45<(R$2+7),$F45>R$2),1, IF(AND($H45<R$2+7,$H45>R$2),3, IF(AND($F45<=R$2, $H45>=R$2), 2, "" ))) | S45: =IF(AND($F45<(S$2+7),$F45>S$2),1, IF(AND($H45<S$2+7,$H45>S$2),3, IF(AND($F45<=S$2, $H45>=S$2), 2, "" ))) | ... AQ45: =IF(AND($F45<(AQ$2+7),$F45>AQ$2),1, IF(AND($H45<AQ$2+7,$H45>AQ$2),3, IF(AND($F45<=AQ$2, $H45>=AQ$2), 2, "" )))
A46: E | B46: PAYMENT MILESTONE 6: HANDOVER COMPLETE | C46: 44022 | D46: 1 | E46: 44025 | F46: 44022 | G46: 1 | H46: 44025
C47: 43831 | D47: These numbers are used to set the start and end dates on the Gantt Chart
C48: 44014

Sheet Certificate - Financial Close
B2: Emergent Energy – Financial Close Completion Certificate | H2: FINANCIAL CLOSE CERTIFICATE
B4: Project Name: | C4: ='Project Plan'!E2 -> Trident Steel GP
B5: COO: | C5: Johannes Potgieter
B6: Programme Manager: | C6: Roedolph Venter
B7: HoPD: | C7: Natasha Watkins-Baker
B9: Date of Phase Completion:
B10: Phase Deliverables Checklist: (Y/N)
B11: Product Agreement | C11: NA
B12: EPC Agreement | C12: NA
B13: O&M Agreeement | C13: NA
B14: Cost Proposal | C14: Signed
B15: Deposit Received | C15: Yes
B16: Risks / Notes | C16: None
B18: Acknowledgement and Acceptance:
B19: Role | C19: Name | D19: Signature | E19: Date
B20: COO | C20: Johannes | D20: JTP | E20: 45953

Sheet Compliance
B2: HSE
B4: Description | C4: Status | D4: Approved By | E4: Date | F4: Results / Comments
B5: NOC
B6: 7.1 Agreement
B7: 13.2 Agreement
B8: EE File
B9: Subbie File
B16: SSEG
B18: Description | C18: Status | D18: Approved By | E18: Date | F18: Results / Comments
B19: SSEG Application
B20: PTI
B21: Commissioning Approval

Sheet Project Plan
N1: =TODAY() -> 46064 | O1: =TODAY() -> 46064
C2: PROJECT PLAN | E2: Trident Steel GP | N2: 0 | O2: 1
C3: PROJECT SIZE (kWp) | E3: 1875 | O3: What is required next? Johannes mentioned SSEG approval
C4: PROJECT DEVELOPER | E4: Natasha Watkins-Baker
C5: PROJECT MANAGERS | E5: JT Moorosi
C6: CONTRACT VALUE | E6: 16024329
C7: Phase: | E7: Handover
B8: No. | C8: HIGH LEVEL PROGRAMME | E8: Planned Start | F8: Duration (days) | G8: Planned End | I8: Actual Start | J8: Duration (days) | K8: Actual End | M8: Status | N8: Expected Status | O8: Comment
F9: =G78-E19 -> 53 | J9: =K78-I19 -> 85 | M9: =AVERAGE(M11,M18,M22,M47,M63,M76,M86,M82,M27) -> 1 | N9: =AVERAGE(N11,N18,N22,N47,N63,N76,N86,N82,N27) -> 1
B11: 1 | C11: Project Initiation | E11: =MIN(E12:E16) -> 45594 | F11: =G11-E11 -> 25 | G11: =MAX(G12:G16) -> 45619 | I11: =MIN(I12:I16) -> 45594 | J11: =K11-I11 -> 25 | K11: =MAX(K12:K16) -> 45619 | M11: =(J12*M12+J13*M13+J14*M14+J15*M15+J16*M16)/SUM(J12:J16) -> 1 | N11: =(K12*N12+K13*N13+K14*N14+K15*N15+K16*N16)/SUM(K12:K16) -> 1
B12: 1.1 | C12: Handover | E12: 45594 | F12: 1 | G12: =WORKDAY.INTL(E12,F12,1,Data!$C$3:$C$14) -> 45595 | I12: 45594 | J12: 1 | K12: =WORKDAY.INTL(I12,J12,1,Data!$C$3:$C$14) -> 45595 | M12: 1 | N12: 1
B13: 1.2 | C13: Project Introduction | E13: 45604 | F13: 1 | G13: =WORKDAY.INTL(E13,F13,1,Data!$C$3:$C$14) -> 45607 | I13: 45604 | J13: 1 | K13: =WORKDAY.INTL(I13,J13,1,Data!$C$3:$C$14) -> 45607 | M13: 1 | N13: 1
B14: 1.3 | C14: HSE | E14: =E13 -> 45604 | F14: 15 | G14: =E14+F14 -> 45619 | I14: =I13 -> 45604 | J14: 15 | K14: =I14+J14 -> 45619 | M14: 1 | N14: 1
B15: 1.4 | C15: Installer Kick Off | E15: =G14-7 -> 45612 | F15: 1 | G15: =WORKDAY.INTL(E15,F15,1,Data!$C$3:$C$14) -> 45614 | I15: =K14-7 -> 45612 | J15: 1 | K15: =WORKDAY.INTL(I15,J15,1,Data!$C$3:$C$14) -> 45614 | M15: 1 | N15: 1
B16: 1.5 | C16: Project Review | E16: =E15 -> 45612 | F16: 1 | G16: =WORKDAY.INTL(E16,F16,1,Data!$C$3:$C$14) -> 45614 | I16: =I15 -> 45612 | J16: 1 | K16: =WORKDAY.INTL(I16,J16,1,Data!$C$3:$C$14) -> 45614 | M16: 1 | N16: 1
B18: 2 | C18: Site Establishment | E18: =MIN(E19:E20) -> 45663 | F18: =G18-E18 -> 8 | G18: =MAX(G19:G20) -> 45671 | I18: =MIN(I19:I20) -> 45663 | J18: =K18-I18 -> 36 | K18: =MAX(K19:K20) -> 45699 | M18: =(J19*M19+J20*M20)/SUM(J19:J20) -> 1 | N18: =(K19*N19+K20*N20)/SUM(K19:K20) -> 1
B19: 2.1 | C19: TSS - Roof Assessment | E19: 45663 | F19: 1 | G19: =E19+F19 -> 45664 | I19: 45663 | J19: 1 | K19: =I19+J19 -> 45664 | M19: 1 | N19: 1 | S19: =NETWORKDAYS(I19,K80) -> 134
B20: 2.2 | C20: CPD1 - Roof Assessment | E20: =E19+7 -> 45670 | F20: 1 | G20: =E20+F20 -> 45671 | I20: 45698 | J20: 1 | K20: =I20+J20 -> 45699 | M20: 1 | N20: 1 | S20: =NETWORKDAYS(I20,K89) -> 139
B22: 3 | C22: Roof Replacement - Paul | E22: =MIN(E23:E25) -> 45607 | F22: =G22-E22 -> 46 | G22: =MAX(G23:G25) -> 45653 | I22: =MIN(I23:I25) -> 45607 | J22: =K22-I22 -> 95 | K22: =MAX(K23:K25) -> 45702 | M22: =(J23*M23+J24*M24+J25*M25)/SUM(J23:J25) -> 1 | N22: =(K23*N23+K24*N24+K25*N25)/SUM(K23:K25) -> 1 | S22: =S19/5 -> 26.8
B23: 3.1 | C23: Activity Start Date | E23: 45607 | F23: 1 | G23: =WORKDAY.INTL(E23,F23,1,Data!$C$3:$C$14) -> 45608 | I23: 45607 | J23: 1 | K23: =WORKDAY.INTL(I23,J23,1,Data!$C$3:$C$14) -> 45608 | M23: 1 | N23: 1
B24: 3.2 | C24: First Phase | D24: {=_xlfn.LET(_xlpm.w,$B$10:$B$54,_xlpm.r,$M$10:$M$54,_xlpm.v,IF(ISNUMBER(_xlpm.r),_xlpm.r,IFERROR(VALUE(SUBSTITUTE(_xlpm.r,"%",""))/100,0)),_xlpm.g,IFERROR(VALUE(LEFT(_xlpm.w,1)),0),_xlpm.bdOnly,(SUMPRODUCT((_xlpm.w="1.1")*(_xlpm.v>0))>0)*(SUMPRODUCT((_xlpm.w<>"1.1")*(_xlpm.v>0))=0),_xlpm.anyConstr,SUMPRODUCT((_xlpm.g>=2)*(_xlpm.g<=6)*(_xlpm.v>0))>0,_xlpm.anyQA,SUMPRODUCT((_xlpm.g=7)*(_xlpm.v>0))>0,_xlpm.anyHO,SUMPRODUCT((_xlpm.g=8)*(_xlpm.v>0))>0,_xlpm.anyPlan,SUMPRODUCT((_xlpm.g=1)*(_xlpm.v>0))>0,IF(_xlpm.bdOnly,"1. Financial Close",IF(_xlpm.anyConstr,"3. Construction",IF(_xlpm.anyQA,"4. QA",IF(_xlpm.anyHO,"5. Handover",IF(_xlpm.anyPlan,"2. Planning","1. Financial Close"))))))} -> 3. Construction | E24: =WORKDAY.INTL(G23,0,1,Data!$C$3:$C$14) -> 45608 | F24: 15 | G24: =WORKDAY.INTL(E24,F24,1,Data!$C$3:$C$14) -> 45629 | I24: =WORKDAY.INTL(K23,0,1,Data!$C$3:$C$14) -> 45608 | J24: 15 | K24: =WORKDAY.INTL(I24,J24,1,Data!$C$3:$C$14) -> 45629 | M24: 1 | N24: 1 | S24: =E3/S22 -> 69.962687
B25: 3.3 | C25: Second Phase | E25: =WORKDAY.INTL(G24,0,1,Data!$C$3:$C$14) -> 45629 | F25: 15 | G25: =WORKDAY.INTL(E25,F25,1,Data!$C$3:$C$14) -> 45653 | I25: =WORKDAY.INTL(K24,0,1,Data!$C$3:$C$14) -> 45629 | J25: 50 | K25: =WORKDAY.INTL(I25,J25,1,Data!$C$3:$C$14) -> 45702 | M25: 1 | N25: 1
B27: 4 | C27: AC Installation | E27: =MIN(E28:E45) -> 45666 | F27: =G27-E27 -> 1 | G27: =MAX(G28:G45) -> 45667 | I27: =MIN(I28:I45) -> 45638 | J27: =K27-I27 -> 118 | K27: =MAX(K28:K41) -> 45756 | M27: =(J28*M28+J29*M29+J30*M30+J31*M31+J32*M32+J33*M33+J34*M34+J35*M35+J36*M36+J37*M37+J38*M38+J39*M39+J40*M40+J41*M41+J42*M42+J43*M43+J44*M44+J45*M45)/SUM(J28:J45) -> 1 | N27: =(K28*N28+K29*N29+K30*N30+K31*N31+K32*N32+K33*N33+K34*N34+K35*N35+K36*N36+K37*N37+K38*N38+K39*N39+K40*N40+K41*N41+K42*N42+K43*N43+K44*N44+K45*N45)/SUM(K28:K45) -> 1
B28: 4.1 | C28: Inverters delivered - TSS & CPD | E28: =E19+3 -> 45666 | F28: 1 | G28: =WORKDAY.INTL(E28,F28,1,Data!$C$3:$C$14) -> 45667 | I28: 45692 | J28: 1 | K28: =WORKDAY.INTL(I28,J28,1,Data!$C$3:$C$14) -> 45693 | M28: 1 | N28: 1
B29: 4.2 | C29: Steel Structure - TSS | I29: 45677 | J29: 35 | K29: =WORKDAY.INTL(I29,J29,1,Data!$C$3:$C$14) -> 45726 | M29: 1 | N29: 1
B30: 4.3 | C30: Steel Structure - CPD | I30: 45677 | J30: 42 | K30: =WORKDAY.INTL(I30,J30,1,Data!$C$3:$C$14) -> 45735 | M30: 1 | N30: 1
B31: 4.4 | C31: Mounting Inverters - TSS | I31: =WORKDAY.INTL(K29,0,1,Data!$C$3:$C$14)+5 -> 45731 | J31: 5 | K31: =WORKDAY.INTL(I31,J31,1,Data!$C$3:$C$14) -> 45737 | M31: 1 | N31: 1
B32: 4.5 | C32: Mounting Inverters - CPD1 | I32: =WORKDAY.INTL(K30,0,1,Data!$C$3:$C$14)+5 -> 45740 | J32: 6 | K32: =WORKDAY.INTL(I32,J32,1,Data!$C$3:$C$14) -> 45748 | M32: 1 | N32: 1
B33: 4.6 | C33: Mounting Cable Trays - TSS | I33: =WORKDAY.INTL(K31,0,1,Data!$C$3:$C$14) -> 45737 | J33: 2 | K33: =WORKDAY.INTL(I33,J33,1,Data!$C$3:$C$14) -> 45741 | M33: 1 | N33: 1
B34: 4.7 | C34: Mounting Cable Trays - CPD | I34: =WORKDAY.INTL(K32,0,1,Data!$C$3:$C$14) -> 45748 | J34: 4 | K34: =WORKDAY.INTL(I34,J34,1,Data!$C$3:$C$14) -> 45754 | M34: 1 | N34: 1
B35: 4.8 | C35: Solar DB Lead Time - TSS & CPD | I35: 45638 | J35: 46 | K35: =WORKDAY.INTL(I35,J35,1,Data!$C$3:$C$14) -> 45707 | M35: 1 | N35: 1
B36: 4.9 | C36: Installing Solar DB - TSS | I36: =WORKDAY.INTL(K35,0,1,Data!$C$3:$C$14) -> 45707 | J36: 2 | K36: =WORKDAY.INTL(I36,J36,1,Data!$C$3:$C$14) -> 45709 | M36: 1 | N36: 1
B37: 4.10 | C37: Installing Solar DB - CPD | I37: =WORKDAY.INTL(K35,0,1,Data!$C$3:$C$14) -> 45707 | J37: 2 | K37: =WORKDAY.INTL(I37,J37,1,Data!$C$3:$C$14) -> 45709 | M37: 1 | N37: 1
B38: 4.11 | C38: AC Cabling (DB to Inverter) - TSS | I38: =WORKDAY.INTL(K33,0,1,Data!$C$3:$C$14) -> 45741 | J38: 4 | K38: =WORKDAY.INTL(I38,J38,1,Data!$C$3:$C$14) -> 45747 | M38: 1 | N38: 1
B39: 4.12 | C39: AC Cabling (DB to Inverter) - CPD | I39: =WORKDAY.INTL(K34,0,1,Data!$C$3:$C$14)-3 -> 45751 | J39: 3 | K39: =WORKDAY.INTL(I39,J39,1,Data!$C$3:$C$14) -> 45756 | M39: 1 | N39: 1
B40: 4.13 | C40: AC Cabling (DB to Tie In) - TSS | I40: =WORKDAY.INTL(I42,0,1,Data!$C$3:$C$14) -> 45710 | J40: 12 | K40: =WORKDAY.INTL(I40,J40,1,Data!$C$3:$C$14) -> 45727 | M40: 1 | N40: 1
B41: 4.14 | C41: AC Cabling (DB to Tie In) - CPD | I41: =K43 -> 45710 | J41: 2 | K41: =WORKDAY.INTL(I41,J41,1,Data!$C$3:$C$14) -> 45713 | M41: 1 | N41: 1
B42: 4.15 | C42: Tie In Breaker Installation - TSS | I42: 45710 | J42: 11 | K42: =WORKDAY.INTL(I42,J42,1,Data!$C$3:$C$14) -> 45726 | M42: 1 | N42: 1
B43: 4.16 | C43: Tie In Breaker Installation - CPD | I43: 45710 | J43: 1 | K43: =I43 -> 45710 | M43: 1 | N43: 1
B44: 4.17 | C44: AC Commissioning - TSS | I44: =WORKDAY.INTL(K40,0,1,Data!$C$3:$C$14) -> 45727 | J44: 4 | K44: =WORKDAY.INTL(I44,J44,1,Data!$C$3:$C$14) -> 45733 | M44: 1 | N44: 1
B45: 4.18 | C45: AC Commissioning - CPD | I45: =WORKDAY.INTL(K41,0,1,Data!$C$3:$C$14) -> 45713 | J45: 10 | K45: =WORKDAY.INTL(I45,J45,1,Data!$C$3:$C$14) -> 45727 | M45: 1 | N45: 1
B47: 5 | C47: DC Works - TSS | E47: =MIN(E48:E53) -> 45663 | F47: =G47-E47 -> 49 | G47: =MAX(G48:G53) -> 45712 | I47: =MIN(I48:I53) -> 45671 | J47: =K47-I47 -> 64 | K47: =MAX(K48:K53) -> 45735 | M47: =(J48*M48+J49*M49+J50*M50+J51*M51+J52*M52+J53*M53)/SUM(J48:J53) -> 1 | N47: =(K48*N48+K49*N49+K50*N50+K51*N51+K52*N52+K53*N53)/SUM(K48:K53) -> 1
B48: 5.1 | C48: Mounting Structure Delivered | E48: =E19 -> 45663 | F48: 1 | G48: =WORKDAY.INTL(E48,F48,1,Data!$C$3:$C$14) -> 45664 | I48: 45671 | J48: 1 | K48: =WORKDAY.INTL(I48,J48,1,Data!$C$3:$C$14) -> 45672 | M48: 1 | N48: 1 | O48: Optimiser Delivery early Dec
B49: 5.2 | C49: DC Cable Delivered | E49: =E19 -> 45663 | F49: 35 | G49: =WORKDAY.INTL(E49,F49,1,Data!$C$3:$C$14) -> 45712 | I49: 45722 | J49: 1 | K49: =WORKDAY.INTL(I49,J49,1,Data!$C$3:$C$14) -> 45723 | M49: 1 | N49: 1
B50: 5.3 | C50: TSS - Module Delivery | E50: =E48+8 -> 45671 | F50: 1 | G50: =WORKDAY.INTL(E50,F50,1,Data!$C$3:$C$14) -> 45672 | I50: 45685 | J50: 3 | K50: =WORKDAY.INTL(I50,J50,1,Data!$C$3:$C$14) -> 45688 | M50: 1 | N50: 1
B51: 5.4 | C51: TSS - Mounting Structure installation | E51: =E19 -> 45663 | F51: 20 | G51: =WORKDAY.INTL(E51,F51,1,Data!$C$3:$C$14) -> 45691 | I51: 45672 | J51: 4 | K51: =WORKDAY.INTL(I51,J51,1,Data!$C$3:$C$14) -> 45678 | M51: 1 | N51: 1
B52: 5.5 | C52: TSS - Module Lifting | E52: =WORKDAY.INTL(G51,0,1,Data!$C$3:$C$14)-7 -> 45684 | F52: 7 | G52: =WORKDAY.INTL(E52,F52,1,Data!$C$3:$C$14) -> 45693 | I52: =I53 -> 45686 | J52: 35 | K52: =K53 -> 45735 | M52: 1 | N52: 1
B53: 5.6 | C53: TSS - Module Mounting | E53: 45663 | F53: 35 | G53: =WORKDAY.INTL(E53,F53,1,Data!$C$3:$C$14) -> 45712 | I53: 45686 | J53: 35 | K53: =WORKDAY.INTL(I53,J53,1,Data!$C$3:$C$14) -> 45735 | M53: 1 | N53: 1 | O53: 1400 on 11 Mar of 1400
B55: 6 | C55: DC Works - CPD1 | E55: =MIN(E56:E61) -> #REF! | F55: =G55-E55 -> #REF! | G55: =MAX(G56:G61) -> #REF! | I55: =MIN(I56:I61) -> 45671 | J55: =K55-I55 -> 87 | K55: =MAX(K56:K61) -> 45758 | M55: =(J56*M56+J57*M57+J58*M58+J59*M59+J60*M60+J61*M61)/SUM(J56:J61) -> 1 | N55: =(K56*N56+K57*N57+K58*N58+K59*N59+K60*N60+K61*N61)/SUM(K56:K61) -> 1
B56: 6.1 | C56: Mounting Structure Delivered | E56: =#REF! -> #REF! | F56: 1 | G56: =WORKDAY.INTL(E56,F56,1,Data!$C$3:$C$14) -> #REF! | I56: =I48 -> 45671 | J56: 1 | K56: =WORKDAY.INTL(I56,J56,1,Data!$C$3:$C$14) -> 45672 | M56: 1 | N56: 1
B57: 6.2 | C57: DC Cable Delivered | E57: =#REF! -> #REF! | F57: 35 | G57: =WORKDAY.INTL(E57,F57,1,Data!$C$3:$C$14) -> #REF! | I57: =I49 -> 45722 | J57: 1 | K57: =WORKDAY.INTL(I57,J57,1,Data!$C$3:$C$14) -> 45723 | M57: 1 | N57: 1
B58: 6.3 | C58: CPD1 - Module Delivery | E58: =E50+7 -> 45678 | F58: 1 | G58: =WORKDAY.INTL(E58,F58,1,Data!$C$3:$C$14) -> 45679 | I58: =I50 -> 45685 | J58: 3 | K58: =WORKDAY.INTL(I58,J58,1,Data!$C$3:$C$14) -> 45688 | M58: 1 | N58: 1
B59: 6.4 | C59: CPD1 - Mounting Structure installation | E59: =WORKDAY.INTL(G24,0,1,Data!$C$3:$C$14) -> 45629 | F59: 45 | G59: =WORKDAY.INTL(E59,F59,1,Data!$C$3:$C$14) -> 45695 | I59: =WORKDAY.INTL(K25,0,1,Data!$C$3:$C$14)-7 -> 45695 | J59: 11 | K59: =WORKDAY.INTL(I59,J59,1,Data!$C$3:$C$14) -> 45712 | M59: 1 | N59: 1
B60: 6.5 | C60: CPD1 - Module Lifting | E60: 45671 | F60: 10 | G60: =WORKDAY.INTL(E60,F60,1,Data!$C$3:$C$14) -> 45685 | I60: =I61 -> 45708 | J60: 36 | K60: =K61 -> 45758 | M60: 1 | N60: 1
B61: 6.6 | C61: CPD1 - Module Mounting | E61: =WORKDAY.INTL(E60,0,1,Data!$C$3:$C$14) -> 45671 | F61: 45 | G61: =WORKDAY.INTL(E61,F61,1,Data!$C$3:$C$14) -> 45734 | I61: 45708 | J61: 36 | K61: =WORKDAY.INTL(I61,J61,1,Data!$C$3:$C$14) -> 45758 | M61: 1 | N61: 1 | O61: 1483 on 17 Mar of 1800
B63: 7 | C63: Extras | E63: =MIN(E64:E74) -> 0 | F63: =G63-E63 -> 0 | G63: =MAX(G64:G74) -> 0 | I63: 45705 | J63: =K63-I63 -> 62 | K63: 45767 | M63: 1 | N63: 1
B64: 7.1 | C64: TSS - Fixed Anchor Point & Lifeline Approvals | I64: 45715 | J64: 1 | K64: =WORKDAY.INTL(I64,J64,1,Data!$C$3:$C$14) -> 45716 | M64: 1 | N64: 1 | S64: =N11 -> 1
B65: 7.2 | C65: TSS - Fixed Anchor Point & Lifeline Installation | I65: 45882 | J65: 5 | K65: =WORKDAY.INTL(I65,J65,1,Data!$C$3:$C$14) -> 45889 | M65: 1 | N65: 1 | O65: Awaiting Mauro to feedback, contact he said he'll advise tomorrow latest - 03/07/25 | S65: =N18 -> 1
B66: 7.3 | C66: TSS - Fixed Anchor Point & Lifeline Sign Off | I66: =K65 -> 45889 | J66: 1 | K66: =WORKDAY.INTL(I66,J66,1,Data!$C$3:$C$14) -> 45890 | M66: 1 | N66: 1 | S66: =N22 -> 1
B67: 7.4 | C67: CPD1 - Fixed Anchor Point & Lifeline Approvals | I67: 45715 | J67: 1 | K67: =WORKDAY.INTL(I67,J67,1,Data!$C$3:$C$14) -> 45716 | M67: 1 | N67: 1 | S67: =N27 -> 1
B68: 7.5 | C68: CPD1 - Fixed Anchor Point & Lifeline Installation | I68: =K65 -> 45889 | J68: 5 | K68: =WORKDAY.INTL(I68,J68,1,Data!$C$3:$C$14) -> 45896 | M68: 1 | N68: 1 | O68: Awaiting Mauro to feedback, contact he said he'll advise tomorrow latest - 03/07/25 | S68: =N47 -> 1
B69: 7.6 | C69: CPD1 - Fixed Anchor Point & Lifeline Sign Off | I69: =K68 -> 45896 | J69: 1 | K69: =WORKDAY.INTL(I69,J69,1,Data!$C$3:$C$14) -> 45897 | M69: 1 | N69: 1 | S69: =N55 -> 1
B70: 7.7 | C70: TSS - Walkway Installation | I70: =K61 -> 45758 | J70: 10 | K70: =WORKDAY.INTL(I70,J70,1,Data!$C$3:$C$14)+70 -> 45842 | M70: 1 | N70: 1 | O70: Pending sign off, works completed. | S70: =N63 -> 1
B71: 7.8 | C71: CPD1 - Walkway Installation | I71: =I70 -> 45758 | J71: 10 | K71: =WORKDAY.INTL(I71,J71,1,Data!$C$3:$C$14)+70 -> 45842 | M71: 1 | N71: 1 | O71: Pending sign off, works completed. | S71: =N76 -> 1
B72: 7.9 | C72: TSS - Waterpoint Installation | I72: 45861 | J72: 2 | K72: =WORKDAY.INTL(I72,J72,1,Data!$C$3:$C$14) -> 45863 | M72: 1 | N72: 1 | O72: Awaiting LOG for the Subby to submit for approval then commence works | S72: =N82 -> 1
B73: 7.10 | C73: CPD1 - Waterpoint Installation | I73: 45884 | J73: 5 | K73: =WORKDAY.INTL(I73,J73,1,Data!$C$3:$C$14) -> 45891 | M73: 1 | N73: 1 | O73: Awaiting LOG for the Subby to submit for approval then commence works | S73: =N86 -> 1
B74: 7.11 | C74: MV Metering | I74: 45765 | J74: 7 | K74: =I74+J74 -> 45772 | M74: 1 | N74: 1
B76: 8 | C76: Commissioning | E76: =MIN(E77:E80) -> #REF! | F76: =G76-E76 -> #REF! | G76: =MAX(G77:G80) -> #REF! | I76: =MIN(I77:I80) -> 45735 | J76: =K76-I76 -> 113 | K76: =MAX(K77:K80) -> 45848 | M76: =(J77*M77+J78*M78+J79*M79+J80*M80)/SUM(J77:J80) -> 1 | N76: =(K77*N77+K78*N78+K79*N79+K80*N80)/SUM(K77:K80) -> 1
B77: 8.1 | C77: TSS - Practical Completion | E77: =WORKDAY.INTL(G47,0,1,Data!$C$3:$C$14) -> 45712 | F77: 3 | G77: =WORKDAY.INTL(E77,F77,1,Data!$C$3:$C$14) -> 45715 | I77: =WORKDAY.INTL(K47,0,1,Data!$C$3:$C$14) -> 45735 | J77: 4 | K77: =WORKDAY.INTL(I77,J77,1,Data!$C$3:$C$14) -> 45741 | M77: 1 | N77: 1
B78: 8.2 | C78: TSS - Commissioning | E78: =WORKDAY.INTL(G77,0,1,Data!$C$3:$C$14) -> 45715 | F78: 1 | G78: =WORKDAY.INTL(E78,F78,1,Data!$C$3:$C$14) -> 45716 | I78: =WORKDAY.INTL(K77,0,1,Data!$C$3:$C$14) -> 45741 | J78: 5 | K78: =WORKDAY.INTL(I78,J78,1,Data!$C$3:$C$14) -> 45748 | M78: 1 | N78: 1
B79: 8.3 | C79: CPD1 - Commissioning | E79: =WORKDAY.INTL(G55,0,1,Data!$C$3:$C$14) -> #REF! | F79: 3 | G79: =WORKDAY.INTL(E79,F79,1,Data!$C$3:$C$14) -> #REF! | I79: =WORKDAY.INTL(K39,0,1,Data!$C$3:$C$14) -> 45756 | J79: 4 | K79: =WORKDAY.INTL(I79,J79,1,Data!$C$3:$C$14) -> 45762 | M79: 1 | N79: 1
B80: 8.4 | C80: CPD1 - Practical Completion | E80: =WORKDAY.INTL(G79,0,1,Data!$C$3:$C$14) -> #REF! | F80: 1 | G80: =WORKDAY.INTL(E80,F80,1,Data!$C$3:$C$14) -> #REF! | I80: =WORKDAY.INTL(K79,0,1,Data!$C$3:$C$14) -> 45762 | J80: 62 | K80: =WORKDAY.INTL(I80,J80,1,Data!$C$3:$C$14) -> 45848 | M80: 1 | N80: 1
B82: 9 | C82: QA Inspections | E82: =MIN(E83:E84) -> #REF! | F82: =G82-E82 -> #REF! | G82: =MAX(G83:G84) -> #REF! | I82: =MIN(I83:I84) -> 45749 | J82: =K82-I82 -> 113 | K82: =MAX(K83:K84) -> 45862 | M82: =(J83*M83+J84*M84)/SUM(J83:J84) -> 1 | N82: =(K83*N83+K84*N84)/SUM(K83:K84) -> 1
B83: 9.1 | C83: TSS - Red-Team Inspection & Snag Completion | E83: =WORKDAY.INTL(E77,0,1,Data!$C$3:$C$14) -> 45712 | F83: 15 | G83: =WORKDAY.INTL(E83,F83,1,Data!$C$3:$C$14) -> 45733 | I83: =WORKDAY.INTL(I77,0,1,Data!$C$3:$C$14)+14 -> 45749 | J83: 15 | K83: =WORKDAY.INTL(I83,J83,1,Data!$C$3:$C$14) -> 45770 | M83: 1 | N83: 1
B84: 9.2 | C84: CPD1 - Red-Team Inspection & Snag Completion | E84: =WORKDAY.INTL(E79,0,1,Data!$C$3:$C$14) -> #REF! | F84: 15 | G84: =WORKDAY.INTL(E84,F84,1,Data!$C$3:$C$14) -> #REF! | I84: =WORKDAY.INTL(K80,0,1,Data!$C$3:$C$14) -> 45848 | J84: 10 | K84: =WORKDAY.INTL(I84,J84,1,Data!$C$3:$C$14) -> 45862 | M84: 1 | N84: 1
B86: 10 | C86: Project Closure | E86: =MIN(E87:E92) -> #REF! | F86: =G86-E86 -> #REF! | G86: =MAX(G87:G92) -> #REF! | I86: =MIN(I87:I92) -> 45735 | J86: =K86-I86 -> 190 | K86: =MAX(K87:K92) -> 45925 | M86: =(J87*M87+J88*M88+J89*M89+J90*M90+J91*M91+J92*M92)/SUM(J87:J92) -> 1 | N86: =(K87*N87+K88*N88+K89*N89+K90*N90+K91*N91+K92*N92)/SUM(K87:K92) -> 1
B87: 10.1 | C87: Equipment serial numbers | E87: =E76 -> #REF! | F87: 2 | G87: =WORKDAY.INTL(E87,F87,1,Data!$C$3:$C$14) -> #REF! | I87: =I76 -> 45735 | J87: 2 | K87: =WORKDAY.INTL(I87,J87,1,Data!$C$3:$C$14) -> 45737 | M87: 1 | N87: 1
B88: 10.2 | C88: Client Snag completion | E88: =G84 -> #REF! | F88: 10 | G88: =WORKDAY.INTL(E88,F88,1,Data!$C$3:$C$14) -> #REF! | I88: =K76 -> 45848 | J88: 35 | K88: =WORKDAY.INTL(I88,J88,1,Data!$C$3:$C$14) -> 45897 | M88: 1 | N88: 1
B89: 10.3 | C89: System Performance Monitoring | E89: =WORKDAY.INTL(G80,0,1,Data!$C$3:$C$14) -> #REF! | F89: 10 | G89: =WORKDAY.INTL(E89,F89,1,Data!$C$3:$C$14) -> #REF! | I89: =WORKDAY.INTL(K80,0,1,Data!$C$3:$C$14) -> 45848 | J89: 30 | K89: =WORKDAY.INTL(I89,J89,1,Data!$C$3:$C$14) -> 45890 | M89: 1 | N89: 1
B90: 10.4 | C90: Handover documentation | E90: =WORKDAY.INTL(E88,0,1,Data!$C$3:$C$14) -> #REF! | F90: 10 | G90: =WORKDAY.INTL(E90,F90,1,Data!$C$3:$C$14) -> #REF! | I90: =WORKDAY.INTL(I88,0,1,Data!$C$3:$C$14) -> 45848 | J90: 55 | K90: =WORKDAY.INTL(I90,J90,1,Data!$C$3:$C$14) -> 45925 | M90: 1 | N90: 1
B91: 10.5 | C91: Handover to Client | E91: =WORKDAY.INTL(G90,0,1,Data!$C$3:$C$14) -> #REF! | F91: 1 | G91: =WORKDAY.INTL(E91,F91,1,Data!$C$3:$C$14) -> #REF! | I91: 45887 | J91: 20 | K91: =WORKDAY.INTL(I91,J91,1,Data!$C$3:$C$14) -> 45915 | M91: 1 | N91: 1
B92: 10.6 | C92: Handover to Matriarch | E92: =WORKDAY.INTL(G84,0,1,Data!$C$3:$C$14) -> #REF! | F92: 5 | G92: =WORKDAY.INTL(E92,F92,1,Data!$C$3:$C$14) -> #REF! | I92: =WORKDAY.INTL(K84,0,1,Data!$C$3:$C$14) -> 45862 | J92: 45 | K92: =WORKDAY.INTL(I92,J92,1,Data!$C$3:$C$14) -> 45925 | M92: 1 | N92: 1

Sheet Revenue Tracking
B2: HIGH LEVEL PROJECT REVENUE TRACKING
D3: PLANNED | F3: ACTUAL | L3: FINANCIAL REVIEW | N3: TIMELINE REVIEW
B4: 1 | C4: Planned Revenue | D4: ='Project Plan'!E6 -> 16024329 | F4: =F30 -> 16024329 | L4: 16024329 | N4: Start Date
B5: 2 | C5: Planned Expenditure | D5: =+'Expenditure Tracking'!F5 -> 13780794 | F5: =+'Expenditure Tracking'!J5 -> 14799894 | L5: 15134527 | N5: 45663
B6: 3 | C6: Planned Profit | D6: =+D4-D5 -> 2243535.2 | F6: =+F4-F5 -> 1224435.1 | L6: 889801.96 | N6: End Date - PC
B7: 4 | C7: Planned Margin | D7: =+D6/D4 -> 0.14000806 | F7: =+F6/F4 -> 0.076411004 | L7: 0.055528189 | N7: 45798
B10: CONTRACT
B11: No. | C11: PAYMENT MILESTONE TSS | E11: % | F11: VALUE | H11: PLANNED PAYMENT DATE | L11: INVOICE NUMBER | N11: INVOICE RAISED DATE | P11: PAYMENT RECEIVED DATE | R11: MILESTONE NOTES & COMMENTS
B12: 1 | C12: Acceptance and initial Deposit | E12: 0.35 | F12: =$D$4*E12 / 2 -> 2804257.6 | H12: 45614 | L12: 004644 | N12: 45609 | P12: 45643
B13: 2 | C13: Delivery of Inverters | E13: 0.2 | F13: =$D$4*E13 / 2 -> 1602432.9 | H13: ='Project Plan'!E13+7 -> 45611 | L13: 004648 | N13: 45695 | P13: =N13+7 -> 45702 | R13: Receipt of solar panels on site
B14: 3 | C14: Delivery of Panels | E14: 0.3 | F14: =$D$4*E14 / 2 -> 2403649.3 | H14: =P14 -> 45693 | L14: 004657 | N14: 45687 | P14: 45693 | R14: Receipt of inverters of site
B15: 4 | C15: Practical Completion | E15: 0.1 | F15: =$D$4*E15 / 2 -> 801216.45 | H15: =P15 -> 45772 | L15: 004697 | N15: 45715 | P15: 45772 | R15: All provisional test successfully finalised
B16: 5 | C16: Handover Partial | E16: 0.025 | F16: =$D$4*E16 / 2 -> 200304.11 | H16: =P16 -> 46081 | L16: 004697 | N16: 45715 | P16: 46081 | R16: All documentation provided
B17: 6 | C17: Handover Partial | E17: 0.025 | F17: =$D$4*E17 / 2 -> 200304.11 | H17: 46081 | L17: 004697 | N17: 45715 | P17: 46081
B18: 7 | C18: - | E18: 0 | F18: =$D$4*E18 -> 0
B21: No. | C21: PAYMENT MILESTONE CDP | E21: % | F21: VALUE | H21: PLANNED PAYMENT DATE | L21: INVOICE NUMBER | N21: INVOICE RAISED DATE | P21: PAYMENT RECEIVED DATE | R21: MILESTONE NOTES & COMMENTS
B22: 1 | C22: Acceptance and initial Deposit | E22: 0.35 | F22: =$D$4*E22/ 2 -> 2804257.6 | H22: 45614 | L22: 004631 | N22: 45609 | P22: 45643
B23: 2 | C23: Delivery of Inverters | E23: 0.2 | F23: =$D$4*E23 / 2 -> 1602432.9 | H23: ='Project Plan'!E23+7 -> 45614 | L23: 004649 | N23: 45695 | P23: =N23+7 -> 45702 | R23: Receipt of solar panels on site
B24: 3 | C24: Delivery of Panels | E24: 0.3 | F24: =$D$4*E24 / 2 -> 2403649.3 | H24: =H14 -> 45693 | L24: 004658 | N24: 45687 | P24: =P14 -> 45693 | R24: Receipt of inverters of site
B25: 4 | C25: Practical Completion | E25: 0.1 | F25: =$D$4*E25 / 2 -> 801216.45 | H25: ='Project Plan'!E77+7 -> 45719 | L25: 004696 | N25: 45715 | P25: 45964 | R25: All provisional test successfully finalised
B26: 5 | C26: Handover | E26: 0.025 | F26: =$D$4*E26 / 2 -> 200304.11 | H26: =H16 -> 46081 | L26: 004696 | N26: 45715 | P26: =P16 -> 46081 | R26: All documentation provided
B27: 6 | C27: Handover Partial | E27: 0.025 | F27: =$D$4*E27 / 2 -> 200304.11 | H27: 46081 | L27: 004696 | N27: 45715 | P27: 46081
B28: 7 | C28: - | E28: 0 | F28: =$D$4*E28 -> 0
E30: =SUM(E22:E28) -> 1 | F30: =SUM(F22:F28)+SUM(F12:F18) -> 16024329
B32: KEY: | C32: contains an error (in result or a check has failed)
C33: Red Font - IF TEXT : content not yet confirmed
C34: Red Font - IF NUMBER: Negative value
C35: Anything in yellow is a concern or risk for noting or action
C36: confirmed
C37: [ADD INITIALS: comment for noting in square brackets, use colour or red to draw attention if important]
C38: [RT: When adding rows into sheet, ensure you insert between first and last row of each category]
C39: end of sheet - do not insert information below/beyond this
B49: No. | C49: PAYMENT MILESTONE | E49: % | F49: VALUE
B50: 1 | C50: Deposit - Project commencement | E50: 0.35 | F50: =$F$56*E50 -> 5608515.1
B51: 2 | C51: Delivery of Panels | E51: 0.3 | F51: =$F$56*E51 -> 4807298.7
B52: 3 | C52: Delivery of Inverters | E52: 0.2 | F52: =$F$56*E52 -> 3204865.8
B53: 4 | C53: Practical Completion | E53: 0.1 | F53: =$F$56*E53 -> 1602432.9
B54: 5 | C54: Handover | E54: 0.05 | F54: =$F$56*E54 -> 801216.45
C55: Total | E55: =SUM(E50:E54) -> 1 | F55: =SUM(F50:F54) -> 16024329
E56: =SUM(E50:E54) -> 1 | F56: =F30 -> 16024329

Sheet Data
C2: Public holidays | F2: Drop down list
C3: 45292 | D3: New Years Day | F3: Approved
C4: 45372 | D4: Human Rights day | F4: Pending
C5: 45380 | D5: Good Friday | F5: Declined
C6: 45383 | D6: Family Day | F6: Abanded
C7: 45413 | D7: Workers day
C8: 45460 | D8: Youth Day Holiday
C9: 45513 | D9: Womens Day
C10: 45559 | D10: Heritage Day
C11: 45642 | D11: Day of Reconciliation
C12: 45651 | D12: Christmas Day
C13: 45652 | D13: Day of Goodwill | H13: Manual dates

Sheet Expenditure Tracking
B2: HIGH LEVEL PROJECT EXPENDITURE TRACKING
F4: COSTED | H4: PLANNED | J4: ACTUAL | L4: Difference from costed | N4: Difference from planned
B5: EXPENDITURE | F5: =SUM(F9:F23) -> 13780794 | H5: =SUM(H9:H23) -> 15134527 | J5: =SUM(J9:J23) -> 14799894 | L5: =SUM(L9:L23) -> -1019100.1 | N5: =SUM(N9:N23) -> 334633.1
B7: No. | D7: Item | F7: Costed Expenditure | H7: Planned Expenditure | J7: Actual Expenditure | L7: Saving / Overrun | N7: Saving / Overrun | P7: Comments on variations from planned expenditure
B9: ='Expenditure Breakdown'!B6 -> 1 | D9: ='Expenditure Breakdown'!C6 -> Panels | F9: ='Expenditure Breakdown'!I6 -> 4370925.6 | H9: 4254751.8 | J9: ='Expenditure Breakdown'!X6 -> 4255658.9 | L9: =F9-J9 -> 115266.69 | N9: =H9-J9 -> -907.14
B10: ='Expenditure Breakdown'!B14 -> 2 | D10: ='Expenditure Breakdown'!C14 -> Inverters | F10: =+'Expenditure Breakdown'!I14 -> 3000818 | H10: 3103440 | J10: =+'Expenditure Breakdown'!X14 -> 3159240 | L10: =F10-J10 -> -158422 | N10: =H10-J10 -> -55800
B11: ='Expenditure Breakdown'!B21 -> 3 | D11: ='Expenditure Breakdown'!C21 -> Mounting Structures | F11: =+'Expenditure Breakdown'!I21 -> 656096 | H11: 346295 | J11: =+'Expenditure Breakdown'!X21 -> 385343 | L11: =F11-J11 -> 270753 | N11: =H11-J11 -> -39048
B12: ='Expenditure Breakdown'!B26 -> 4 | D12: ='Expenditure Breakdown'!C26 -> DC Equipment | F12: =+'Expenditure Breakdown'!I26 -> 1512771.2 | H12: 1835752.5 | J12: =+'Expenditure Breakdown'!X26 -> 1702752.5 | L12: =F12-J12 -> -189981.3 | N12: =H12-J12 -> 133000
B13: ='Expenditure Breakdown'!B40 -> 5 | D13: ='Expenditure Breakdown'!C40 -> Monitoring | F13: =+'Expenditure Breakdown'!I40 -> 550800 | H13: 403365.26 | J13: =+'Expenditure Breakdown'!X40 -> 419582.98 | L13: =F13-J13 -> 131217.02 | N13: =H13-J13 -> -16217.72
B14: ='Expenditure Breakdown'!B57 -> 6 | D14: ='Expenditure Breakdown'!C57 -> AC Equipment | F14: =+'Expenditure Breakdown'!I57 -> 978811.02 | H14: 1388068.9 | J14: =+'Expenditure Breakdown'!X57 -> 1529166.9 | L14: =F14-J14 -> -550355.85 | N14: =H14-J14 -> -141098
B15: ='Expenditure Breakdown'!B73 -> 7 | D15: ='Expenditure Breakdown'!C73 -> Battery Systems | F15: =+'Expenditure Breakdown'!I73 -> 0 | H15: 0 | J15: ='Expenditure Breakdown'!X73 -> 0 | L15: =F15-J15 -> 0 | N15: =H15-J15 -> 0
B16: ='Expenditure Breakdown'!B82 -> 8 | D16: ='Expenditure Breakdown'!C82 -> Product Add On | F16: ='Expenditure Breakdown'!I82 -> 608000 | H16: 890823 | J16: ='Expenditure Breakdown'!X82 -> 492321.82 | L16: =F16-J16 -> 115678.18 | N16: =H16-J16 -> 398501.18
B17: ='Expenditure Breakdown'!L105 -> 9 | D17: ='Expenditure Breakdown'!C105 -> AC & DC Installation | F17: =+'Expenditure Breakdown'!I105 -> 1003132 | H17: 2052500 | J17: =+'Expenditure Breakdown'!X105 -> 2052500 | L17: =F17-J17 -> -1049368 | N17: =H17-J17 -> 0
B18: ='Expenditure Breakdown'!B117 -> 10 | D18: ='Expenditure Breakdown'!C117 -> Site Logistics | F18: =+'Expenditure Breakdown'!I117 -> 234820.18 | H18: 462630 | J18: =+'Expenditure Breakdown'!X117 -> 424330 | L18: =F18-J18 -> -189509.82 | N18: =H18-J18 -> 38300
B19: ='Expenditure Breakdown'!B139 -> 11 | D19: ='Expenditure Breakdown'!C139 -> Due Dilligence | F19: ='Expenditure Breakdown'!I139 -> 167000 | H19: 161100 | J19: ='Expenditure Breakdown'!X139 -> 120447.39 | L19: =F19-J19 -> 46552.61 | N19: =H19-J19 -> 40652.61
B20: ='Expenditure Breakdown'!B147 -> 12 | D20: ='Expenditure Breakdown'!C147 -> BDP Commission | F20: ='Expenditure Breakdown'!G146 -> 0 | H20: 0 | J20: ='Expenditure Breakdown'!X146 -> 0 | L20: =F20-J20 -> 0 | N20: =H20-J20 -> 0
B21: ='Expenditure Breakdown'!B149 -> 13 | D21: ='Expenditure Breakdown'!C149 -> Engineering | F21: =+'Expenditure Breakdown'!I149 -> 664894.72 | H21: 200304.11 | J21: =+'Expenditure Breakdown'!X149 -> 165600 | L21: =F21-J21 -> 499294.71 | N21: =H21-J21 -> 34704.11 | P21: RV: Matriarch defects percentage 1.25%
B22: ='Expenditure Breakdown'!B157 -> 14 | D22: ='Expenditure Breakdown'!C157 -> General Expenses | F22: =+'Expenditure Breakdown'!I157 -> 32725 | H22: 35496.43 | J22: =+'Expenditure Breakdown'!X157 -> 37052.37 | L22: =F22-J22 -> -4327.37 | N22: =H22-J22 -> -1555.94
B23: ='Expenditure Breakdown'!B168 -> 15 | D23: ='Expenditure Breakdown'!C168 -> Service Add On | F23: =+'Expenditure Breakdown'!I168 -> 0 | H23: 0 | J23: =+'Expenditure Breakdown'!X168 -> 55898 | L23: =F23-J23 -> -55898 | N23: =H23-J23 -> -55898
D25: check: | F25: ='Expenditure Breakdown'!I2-'Expenditure Tracking'!F5 -> 0 | G25: ='Expenditure Breakdown'!#REF!-G5 -> #REF! | H25: ='Expenditure Breakdown'!X2-J5 -> 0 | I25: ='Expenditure Breakdown'!#REF!-I5 -> #REF! | J25: ='Expenditure Breakdown'!X2-J5 -> 0
A27: Copy amounts in column H and paste as values at Project review.

Sheet Expenditure Breakdown
B2: COSTED EXPENDITURE BREAKDOWN | I2: =SUM(I6:I174) -> 13780794 | J2: =SUM(J6:J174) -> 16024329 | L2: ACTUAL EXPENDITURE BREAKDOWN | S2: FINANCE ONLY | X2: =SUM(X6:X174) -> 14799894
B4: No. | C4: Product / Service | D4: Description of Work | E4: QTY | F4: Rate / Unit | G4: Budget Total | H4: Project Related date | I4: Total COS | J4: =IF(J2-'Revenue Tracking'!D4>=0, "Total Revenue", "ERROR on REV" ) -> ERROR on REV | L4: No. | M4: Product/ Service | N4: Description of Work | O4: QTY | P4: Rate / Unit | Q4: Actual Total | R4: PO NUMBER | S4: INVOICE NUMBER | T4: INVOICE RAISED DATE | U4: REVENUE RECOGNITION AMOUNT | V4: CHECK | W4: FINANCE PAYMENT DATE | X4: Total COS | Y4: COMMENTS
B6: 1 | C6: Panels | D6: Jinko 580W | E6: 3232 | F6: 1333.826 | G6: =E6*F6 -> 4310925.6 | H6: =H14 -> 45637 | I6: =SUM(G6:G12) -> 4370925.6 | J6: 4699920 | L6: 1 | M6: 1. Panels | N6: Jinko 585W - TSS (1400) | O6: 1602 | P6: 1327.95 | Q6: =O6*P6 -> 2127375.9 | S6: Menlo Inv IN0002290 | T6: 45657 | U6: 2349960 | V6: =J6-SUM(U6:U12) -> 0 | W6: 45695 | X6: =SUM(Q6:Q12) -> 4255658.9 | Y6: Menlo quote | Z6: 19
B7: 1 | L7: 1 | M7: 1. Panels | N7: Jinko 585W - CPD1 (1804) | O7: 1602 | Q7: =P6*O7 -> 2127375.9 | S7: Menlo Inv IN0002363 | T7: 45657 | U7: 2349960 | W7: 45708 | Z7: BUDGET - Solar | AA7: Installer Allocation
B8: 1 | D8: Module delivery to site | G8: 60000 | H8: =H6 -> 45637 | L8: 1 | M8: 1. Panels | T8: =IF(W8>1,EOMONTH(W8,0),"") | U8: 0 | Z8: AC Equipment | AA8: =C62 -> 1505863.1
B9: 1 | L9: 1 | M9: 1. Panels | U9: 0 | Z9: DC Equipment | AA9: =SUM(G27:G38) -> 955571.2
B10: 1 | L10: 1 | M10: 1. Panels | N10: Storage | Q10: 685.71 | S10: Supply Chain - Inv SCO05052 | T10: 45808 | U10: 0 | W10: 45835 | Y10: TC: Added cost | Z10: AC Labour | AA10: =C107 -> 1074640 | AC10: =AA10/140000 -> 7.676
L11: 1 | M11: 1. Panels | W11: 45930
B12: 1 | L12: 1 | M12: 1. Panels | Q12: 221.43 | S12: Supply Chain - SCO05164 | T12: 45869 | U12: 0 | W12: 45899 | Z12: DC Labour | AA12: =C106 -> 468640 | AC12: =AA12/140000 -> 3.3474286
T13: =IF(W13>1,EOMONTH(W13,0),"") | Z13: Offloading | AA13: =G118 -> 8500
B14: 2 | C14: Inverters | D14: SolarEdge 100kW | E14: 18 | F14: 66161 | G14: =E14*F14 -> 1190898 | H14: ='Project Plan'!E23+30 -> 45637 | I14: =SUM(G14:G19) -> 3000818 | J14: 3226686 | L14: 2 | M14: 2. Inverters | N14: SolarEdge 100kW | O14: 18 | P14: 18950 | Q14: =O14*P14 -> 341100 | R14: PO3553-TSD-20250121 - RV Approved | S14: HERHOLDT'S - INV995250 | T14: 45716 | U14: 354646.01 | V14: =J14-SUM(U14:U19) -> 0 | W14: 45744 | X14: =SUM(Q14:Q19) -> 3159240 | Y14: Herholdts quote | Z14: Roof Access/Scaffolding | AA14: =G126 -> 74707.68
L15: 2 | M15: 2. Inverters | N15: Solar Edge Synergy unit | O15: 54 | P15: 15710 | Q15: =O15*P15 -> 848340 | S15: HERHOLDT'S - INV995250 | T15: 45716 | U15: 882029.88 | W15: =W14 -> 45744
B16: 2 | L16: 2 | M16: 2. Inverters | N16: S1200 Optimiser - TSS | O16: 825 | P16: 1160 | Q16: =O16*P16 -> 957000 | R16: PO3554-TSD-20250121 | S16: HERHOLDT'S - INV987265 | T16: 45688 | U16: 995005.07 | W16: 45715 | Z16: Storage | AA16: =G125 -> 51892.5
B17: 2 | D17: S1200 Optimiser | E17: 1616 | F17: 1120 | G17: =E17*F17 -> 1809920 | H17: =H14 -> 45637 | L17: 2 | M17: 2. Inverters | N17: S1200 Optimiser - CPD1 | O17: 825 | P17: 1160 | Q17: =O17*P17 -> 957000 | S17: HERHOLDT'S - INV987265 | T17: 45688 | U17: 995005.07 | W17: 45715 | Y17: Delivery early Dec Herholdts quote | Z17: Telehandler | AA17: =G117 -> 32400
L18: 2 | M18: 2. Inverters | N18: Spare Optimizer 1200W/80V | O18: 60 | Q18: 55800 | R18: PO4193-TSG-20250804 - RV Approved | S18: Herholdts - INV1113245 | T18: 45900 | U18: 0 | W18: 45930
B19: 2 | L19: 2 | M19: 2. Inverters | Q19: 0 | U19: =(Q19/$X$14*$J$14) -> 0 | Z19: Other | AA19: 0
T20: =IF(W20>1,EOMONTH(W20,0),"") | Z20: Total | AA20: =SUM(AA8:AA19) -> 4172214.5
B21: 3 | C21: Mounting Structures | D21: IBR Roof | G21: 656096 | H21: ='Project Plan'!E19+30 -> 45693 | I21: =SUM(G21:G24) -> 656096 | J21: 705479.57 | L21: 3 | M21: 3. Mounting Structures | N21: IBR Roof | Q21: 346295 | R21: PO3465-TRID-20241115 - RV Approved | S21: SCHLETTER - INV1261 | T21: 45688 | U21: 705479.57 | V21: =J21-SUM(U21:U24) -> 0 | W21: 45714 | X21: =SUM(Q21:Q24) -> 385343 | Z21: Less 15% | AA21: =+AA20*0.85 -> 3546382.3 | AC21: [SM: Target Installation Price]
B22: 3 | L22: 3 | M22: 3. Mounting Structures | N22: Delivery | Q22: 0 | U22: 0 | Z22: R/Wp | AA22: =+AA21/'Project Plan'!$E$3/1000 -> 1.8914039
B23: 3 | L23: 3 | M23: 3. Mounting Structures | N23: MS Top Up - Trunking Incl - Schletter | Q23: 39048 | R23: PO3774-TSG-20250328 - RV Approved | S23: Schletter - INV1643 | T23: 45777 | W23: 45777
B24: 3 | L24: 3 | M24: 3. Mounting Structures | T24: =IF(W24>1,EOMONTH(W24,0),"") | Z24: ACTUAL | AA24: Installer Price
T25: =IF(W25>1,EOMONTH(W25,0),"") | Z25: AC Equipment | AA25: 1388068.9
B26: 4 | C26: DC Equipment | D26: DC Cable | E26: 39800 | F26: 14 | G26: =E26*F26 -> 557200 | H26: ='Project Plan'!E50+30 -> 45701 | I26: =SUM(G26:G38) -> 1512771.2 | J26: 1626635.7 | L26: 4 | M26: 4. DC Equipment | N26: DC Cable | O26: 46000 | P26: 13.3 | Q26: =O26*P26 -> 611800 | S26: Menlo Inv IN0002363 | T26: 45657 | U26: 542107.78 | V26: =J26-SUM(U26:U38) -> 0.002779156 | W26: 45708 | X26: =SUM(Q26:Q38) -> 1702752.5 | Y26: Menlo quote | Z26: DC Equipment | AA26: 1090952.5
B27: 4 | L27: 4 | M27: 4. DC Equipment | N27: DC Cable Budget | O27: 10000 | P27: 13.3 | Q27: 0 | U27: =(Q27/$X$26*$J$26) -> 0 | Z27: AC Labour | AA27: 633750 | AC27: =AA27/1875000 -> 0.338
B28: 4 | D28: DC Cable Tray | E28: 270 | F28: 1530 | G28: =E28*F28 -> 413100 | H28: =H26 -> 45701 | L28: 4 | M28: 4. DC Equipment | N28: Deposit - TSS | O28: 484867.78 | P28: =P105 -> 0.3 | Q28: =$O$28*P28 -> 145460.33 | R28: PO3527-TSG-20241212 | S28: Cosmic Sun CS_TRS_001 | T28: =T105 -> 45688 | U28: 290003.52 | W28: =W105 -> 45666 | Z28: DC Labour | AA28: 1418750 | AC28: =AA28/1875000 -> 0.75666667
B29: 4 | L29: 4 | M29: 4. DC Equipment | N29: All AC & DC Equipment Onsite | P29: =P106 -> 0.2 | Q29: =$O$28*P29 -> 96973.556 | S29: Cosmic Sun CS_TRS_003 | T29: =T106 -> 45716 | U29: 193335.68 | W29: =W106 -> 45708 | Z29: =Z13 -> Offloading | AA29: 39600
B30: 4 | L30: 4 | M30: 4. DC Equipment | N30: Pracitcal Completion - TSS | P30: =P63 -> 0.3 | Q30: =$O$28*P30 -> 145460.33 | S30: =S107 -> Cosmic Sun CS_TRS_008 | T30: =T107 -> 45747 | U30: 128890.45 | W30: =W107 -> 45757 | Z30: =Z14 -> Roof Access/Scaffolding | AA30: 194150
B31: 4 | L31: 4 | M31: 4. DC Equipment | N31: Site Fully Commissioned - TSS | P31: =P108 -> 0.15 | Q31: =$O$28*P31 -> 72730.167 | S31: =S108 -> Cosmic Sun CS_TRS_009 | T31: =T108 -> 45777 | U31: 159642.91 | W31: =W108 -> 45764 | Z31: Trenching | AA31: 15000
B32: 4 | D32: Earth Cable | E32: =E26 -> 39800 | F32: 13.5 | G32: =E32*F32 -> 537300 | H32: =H26 -> 45701 | L32: 4 | M32: 4. DC Equipment | N32: Retention | P32: =P109 -> 0.05 | Q32: =$O$28*P32 -> 24243.389 | S32: Cosmic Sun CS_TRS_013 | T32: =T109 -> 45838 | U32: 23159.656 | W32: =W109 -> 45890 | Z32: HSE | AA32: 18800
L33: 4 | M33: 4. DC Equipment | N33: CPD1
L34: 4 | M34: 4. DC Equipment | N34: Deposit - CPD1 | O34: 606084.72 | P34: =P111 -> 0.3 | Q34: =O34*P34 -> 181825.42 | S34: Cosmic Sun CS_TRS_001 | T34: =T111 -> 45688 | W34: =W105 -> 45666
L35: 4 | M35: 4. DC Equipment | N35: All AC & DC Equipment Onsite | P35: =P112 -> 0.2 | Q35: =O34*P35 -> 121216.94 | S35: Cosmic Sun CS_TRS_003 | T35: =T112 -> 45716 | W35: =W112 -> 45708
L36: 4 | M36: 4. DC Equipment | N36: Practical Completion | P36: =P113 -> 0.3 | Q36: =O34*P36 -> 181825.42 | S36: Cosmic Sun CS_TRS_010 | T36: 45777 | U36: 173697.42 | W36: =W113 -> 45785
L37: 4 | M37: 4. DC Equipment | N37: Site Fully Commissioned | P37: =P114 -> 0.15 | Q37: =O34*P37 -> 90912.708 | S37: Cosmic Sun CS_TRS_010 | T37: 45777 | U37: 86848.709 | W37: 45785
B38: 4 | D38: Earth clamp | E38: 323.2 | F38: 16 | G38: =E38*F38 -> 5171.2 | H38: ='Project Plan'!E78 -> 45715 | L38: 4 | M38: 4. DC Equipment | N38: Retention | P38: =P115 -> 0.05 | Q38: =O34*P38 -> 30304.236 | S38: Cosmic Sun CS_TRS_012 | T38: 45838 | U38: 28949.57 | W38: =W115 -> 45890 | Z38: Other | AA38: 0
T39: =IF(W39>1,EOMONTH(W39,0),"") | Z39: Total | AA39: =SUM(AA25:AA32) -> 4799071.4
B40: 5 | C40: Monitoring | D40: SolarEdge Gateway | G40: 4300 | H40: =H14 -> 45637 | I40: =SUM(G40:G55) -> 550800 | J40: =516989.247311828+75268.8172043011 -> 592258.06 | L40: 5 | M40: 5. Monitoring | N40: SolarEdge Energy Meter | O40: 2 | P40: 1740 | Q40: =P40*O40 -> 3480 | R40: PO3553-TSD-20250121 - RV Approved | S40: HERHOLDT'S - INV995250 | T40: 45716 | U40: 5722.9894 | V40: =J40-SUM(U40:U55) -> -0.0025618575 | W40: 45744 | X40: =SUM(Q40:Q55) -> 419582.98 | Z40: R/Wp | AA40: =+AA39/'Project Plan'!$E$3/1000 -> 2.5595047
B41: 5 | D41: Comms DB | G41: 64000 | H41: =H42 -> 45637 | L41: 5 | M41: 5. Monitoring | N41: CTs & Router: TSS & CPD - AccuEnergy | Q41: 21463 | R41: PO3565-TSG-20250127 - RV Approved | S41: Accuenergy - Inv ASAI-004650 | T41: 45688 | U41: 31475.096 | W41: 45715
B42: 5 | D42: Fibre run | G42: 162500 | H42: =H43 -> 45637 | L42: 5 | M42: 5. Monitoring | N42: Revenue Grade Meter - Techsitter | O42: 2 | P42: 14934 | Q42: =P42*O42 -> 29868 | S42: Matriarch INV-3710 | T42: 45688 | U42: =43800.8742636499 -> 43800.874 | W42: 45688
B43: 5 | D43: Generator Integration SEDG | G43: 250000 | H43: =H14 -> 45637 | L43: 5 | M43: 5. Monitoring | N43: Fibre - Volkirk Deposit | Q43: 40101 | R43: PO3696-TSG-20250226 - RV Approved | S43: Volkirk Fibre INV0001116 | T43: 45716 | U43: 62163.262 | W43: 45722 | AA43: 4272214.5
L44: 5 | M44: 5. Monitoring | N44: Fibre - Volkirk - Balance | Q44: 40101 | S44: Volkirk Fibre - INV0001138 | T44: 45747 | U44: 62163.262 | W44: 45750
B45: 5 | D45: Janitza UMG 604 pro (MV Metering) | E45: 2 | G45: 70000 | H45: =H43 -> 45637 | L45: 5 | M45: 5. Monitoring | N45: Solar Edge PPC-DG | Q45: 61210 | R45: PO3553-TSD-20250121 - RV Approved | S45: HERHOLDT'S - INV995250 | T45: 45716 | U45: 125742.79 | W45: 45744
L46: 5 | M46: 5. Monitoring | N46: 24V PSU | Q46: 1460 | R46: PO3648-TSG-20250211 - RV Approved | S46: Accuenergy - Inv ASAI-004783 | T46: 45716 | U46: 2401.0243 | W46: 45744
L47: 5 | M47: 5. Monitoring | N47: Janitza UMG 604 (moved from Trident PE) | Q47: 18571.36 | S47: Harmonius Technical Inv: INV21620 | T47: 45716 | U47: 30541.292 | W47: 45715
L48: 5 | M48: 5. Monitoring | N48: Shipping of Janitza | Q48: 559.63 | S48: DSV Inv: 180121124 | T48: 45747 | U48: 0 | W48: 45777
L49: 5 | M49: 5. Monitoring | N49: Janitza UMG 604 - Harmonious | Q49: 18571.36 | R49: PO3738-TSG-20250312 - RV Approved | S49: Harmonius Technical QU100577 | T49: 45747 | U49: 0 | W49: 45729
L50: 5 | M50: 5. Monitoring | N50: Delivery of Janitza | Q50: 559.63 | S50: DSV Inv: 180121124 | T50: 45808 | U50: 822.17993
L51: 5 | M51: 5. Monitoring | N51: Fibre - Volkirk : Main Sub - Deposit | Q51: =47235/2 -> 23617.5 | R51: PO3752-TSG-20250317 - RV Approved | S51: Volkirk Properties INV0001127 | T51: 45747 | U51: 36619.658 | W51: 45744
L52: 5 | M52: 5. Monitoring | N52: Fibre - Volkirk : Main Sub - Balance | Q52: =47235/2 -> 23617.5 | S52: Volkirk Properties INV0001139 | T52: 45747 | U52: 36611.078 | W52: 45750
L53: 5 | M53: 5. Monitoring | N53: SE Hark EMS Package - Herholdts | O53: 1 | P53: 97750 | Q53: =O53*P53 -> 97750 | R53: PO3952-TSG-20250523 - RV Approved | S53: Herholdts - INV1071481 | T53: 45808 | U53: 121579.45 | W53: 45835
L54: 5 | M54: 5. Monitoring | N54: Commisioning - Solar Edge Hours | O54: 4 | P54: 5550 | Q54: =O54*P54 -> 22200 | R54: PO3861-TSG-20250509 - RV Approved | S54: Herholdts - INV1058643 | T54: 45808 | U54: 32615.111 | W54: 45835
B55: 5 | L55: 5 | M55: 5. Monitoring | N55: Fiber - Gensets | Q55: 16453 | R55: PO4074-TSG-20250630 - RV Approved | S55: VP Fibre - INV0001201 | T55: 45838 | U55: 0 | W55: 45849 | AA55: =AA43-AA39 -> -526856.89
T56: =IF(W56>1,EOMONTH(W56,0),"")
B57: 6 | C57: AC Equipment | D57: Project Kick Off | F57: 0.1 | G57: =$C$62*F57 -> 150586.31 | H57: =H105 -> 45656 | I57: =SUM(G57:G71) -> 978811.02 | J57: 1619207.6 | L57: 6 | M57: 6. AC Equipment | T57: =IF(W57>1,EOMONTH(W57,0),"") | U57: =(Q57/$X$57*$J$57) -> 0 | V57: =J57-SUM(U57:U71) -> 0.001318333 | X57: =SUM(Q57:Q71) -> 1529166.9
B58: 6 | L58: 6 | M58: 6. AC Equipment | N58: DB Board Fast Track Fee | Q58: 14956 | R58: PO3612-TRID-20210131 - RV Approved | S58: CS_TRS_002 | T58: 45716 | U58: 15836.643 | W58: 45701
B59: 6 | L59: 6 | M59: 6. AC Equipment | T59: =IF(W59>1,EOMONTH(W59,0),"") | U59: =(Q59/$X$57*$J$57) -> 0
B60: 6 | L60: 6 | M60: 6. AC Equipment | N60: VO - AC Cable : Cosmic Sun | Q60: 126142 | R60: PO3675-TSG-20250219 - RV Approved | S60: Cosmic Sun CS_TRS_005 | T60: 45716 | U60: 93925.813 | W60: 45708
B61: 6 | L61: 6 | M61: 6. AC Equipment | N61: Deposit - TSS | O61: 616919.5 | P61: =P105 -> 0.3 | Q61: =$O$61*P61 -> 185075.85 | R61: PO3527-TSG-20241212 | S61: Cosmic Sun CS_TRS_001 | T61: 45688 | U61: 480584.15 | W61: 45666
B62: 6 | C62: 1505863.1 | D62: Site Establishment | F62: 0.15 | G62: =$C$62*F62 -> 225879.47 | H62: =H106 -> 45663 | L62: 6 | M62: 6. AC Equipment | N62: All AC & DC Equipment Onsite | P62: =P106 -> 0.2 | Q62: =$O$61*P62 -> 123383.9 | S62: Cosmic Sun CS_TRS_003 | T62: =T106 -> 45716 | U62: 293960.29 | W62: =W106 -> 45708
B63: 6 | D63: AC Installation Complete | F63: 0.2 | G63: =$C$62*F63 -> 301172.62 | H63: =H107 -> 45653 | L63: 6 | M63: 6. AC Equipment | N63: Pracitcal Completion - TSS | P63: =P107 -> 0.3 | Q63: =$O$61*P63 -> 185075.85 | S63: =S107 -> Cosmic Sun CS_TRS_008 | T63: =T107 -> 45747 | U63: 195973.53 | W63: =W107 -> 45757
B64: 6 | D64: Commissioning Complete | F64: 0.1 | G64: =$C$62*F64 -> 150586.31 | H64: =#REF! -> #REF! | L64: 6 | M64: 6. AC Equipment | N64: Site Fully Commissioned - TSS | P64: =P108 -> 0.15 | Q64: =$O$61*P64 -> 92537.925 | S64: =S108 -> Cosmic Sun CS_TRS_009 | T64: =T108 -> 45777 | U64: 97986.765 | W64: =W108 -> 45764
B65: 6 | D65: Handover Document Complete | F65: 0.05 | G65: =$C$62*F65 -> 75293.155 | H65: =#REF! -> #REF! | L65: 6 | M65: 6. AC Equipment | N65: Retention | P65: =P109 -> 0.05 | Q65: =$O$61*P65 -> 30845.975 | S65: Cosmic Sun CS_TRS_013 | T65: =T109 -> 45838 | U65: 32662.255 | W65: =W109 -> 45890
L66: 6 | M66: 6. AC Equipment | N66: CPD1
L67: 6 | M67: 6. AC Equipment | N67: Deposit - CPD1 | O67: 771149.37 | P67: =P111 -> 0.3 | Q67: =O67*P67 -> 231344.81 | S67: Cosmic Sun CS_TRS_001 | T67: =T111 -> 45688 | W67: =W111 -> 45666
L68: 6 | M68: 6. AC Equipment | N68: All AC & DC Equipment Onsite | P68: =P112 -> 0.2 | Q68: =O67*P68 -> 154229.87 | S68: Cosmic Sun CS_TRS_003 | T68: =T112 -> 45716 | W68: =W112 -> 45708
L69: 6 | M69: 6. AC Equipment | N69: Practical Completion | P69: =P113 -> 0.3 | Q69: =O67*P69 -> 231344.81 | S69: Cosmic Sun CS_TRS_010 | T69: =T113 -> 45777 | U69: 244966.91 | W69: =W113 -> 45785
L70: 6 | M70: 6. AC Equipment | N70: Site Fully Commissioned | P70: =P114 -> 0.15 | Q70: =O67*P70 -> 115672.41 | S70: Cosmic Sun CS_TRS_010 | T70: =T114 -> 45777 | U70: 122483.46 | W70: 45785
B71: 6 | D71: End of Defects Period | F71: 0.05 | G71: =$C$62*F71 -> 75293.155 | H71: =H65 -> #REF! | L71: 6 | M71: 6. AC Equipment | N71: Retention | P71: =P115 -> 0.05 | Q71: =O67*P71 -> 38557.469 | S71: Cosmic Sun CS_TRS_012 | T71: 45838 | U71: 40827.819 | W71: =W115 -> 45890
T72: =IF(W72>1,EOMONTH(W72,0),"")
B73: 7 | C73: Battery Systems | I73: =SUM(G73:G80) -> 0 | J73: 0 | L73: 7 | M73: Battery Systems | T73: =IF(W73>1,EOMONTH(W73,0),"") | V73: =J73-SUM(U73:U80) -> 0 | X73: =SUM(Q73:Q80) -> 0
B74: 7 | L74: 7 | T74: =IF(W74>1,EOMONTH(W74,0),"")
B75: 7 | L75: 7 | T75: =IF(W75>1,EOMONTH(W75,0),"")
B76: 7 | L76: 7 | T76: =IF(W76>1,EOMONTH(W76,0),"")
B77: 7 | L77: 7 | T77: =IF(W77>1,EOMONTH(W77,0),"")
B78: 7 | L78: 7 | T78: =IF(W78>1,EOMONTH(W78,0),"")
B79: 7 | L79: 7 | T79: =IF(W79>1,EOMONTH(W79,0),"")
B80: 7 | L80: 7 | T80: =IF(W80>1,EOMONTH(W80,0),"")
T81: =IF(W81>1,EOMONTH(W81,0),"")
B82: 8 | C82: Product Add On | D82: Inverter cages (1 close to TSS transformer, 1 at CPD1) | G82: 100000 | H82: =H71 -> #REF! | I82: =SUM(G82:G103) -> 608000 | J82: =277419.35483871+368421.052631579 -> 645840.41 | L82: 8 | M82: 8. Product Add On | N82: RUT Power Supply - AccuEnergy | Q82: 99 | R82: PO3858-TSG-20250508 | S82: ASAI - 005420 | T82: 45808 | U82: 132.70616 | V82: =J82-SUM(U82:U103) -> 0.0031841852 | W82: 45835 | X82: =SUM(Q82:Q103) -> 492321.82 | Y82: Team lost power supply somehow.
B83: 8 | D83: Permanent anchors and temporary/permanent lifelines | G83: 250000 | H83: =H82 -> #REF! | L83: 8 | M83: 8. Product Add On | N83: Plug point Fibre and Comms at Sub - Cosmic Sun | Q83: 1500 | R83: PO3939-TSG-20250520 - RV Approved | S83: Cosmic Sun: CS_TRS_011 | T83: 45808 | U83: 2010.6993 | W83: 45806
B84: 8 | D84: Walkways | E84: 120 | F84: 750 | G84: =E84*F84 -> 90000 | H84: =H83 -> #REF! | L84: 8 | M84: 8. Product Add On | N84: Permanent Anchor Points - ATS Africa | O84: 171800 | P84: 0.5 | Q84: =O84*P84 -> 85900 | R84: PO3803-TSG-20250414 - RV Approved | S84: ATS AFRICA - INV-0386 | T84: 45777 | U84: 172789.3 | W84: 45785
L85: 8 | M85: 8. Product Add On | P85: 0.5 | Q85: =O84*P85 -> 85900 | S85: ATS AFRICA - INV-0386 | T85: 45777 | U85: 172789.3 | W85: 45827
B86: 8 | D86: Water Points | E86: 4 | F86: 12000 | G86: =E86*F86 -> 48000 | H86: =H84 -> #REF! | L86: 8 | M86: 8. Product Add On | N86: Walkways- Cosmic Sun = 120m | Q86: 16800 | R86: PO3676-TSG-20250219 - RV Approved | S86: Cosmic Sun CS_TRS_006 | T86: 45716 | U86: 39344.387 | W86: 45820
B87: 8 | D87: Cat Ladders | E87: 4 | F87: 30000 | G87: =E87*F87 -> 120000 | H87: =H86 -> #REF! | L87: 8 | M87: 8. Product Add On | N87: Walkways - Onvlee | O87: =120/5.7 -> 21.052632 | P87: 2974.66 | Q87: 62467.86 | R87: PO3697-TSG-20250226 - RV Approved | S87: Onvlee PO-3697-TSG-20250226 | T87: 45747 | U87: 39459.63 | W87: 45729 | Y87: Must place order before 25 Nov, delivery must be set for 4 Dec - Cash payment
B88: 8 | L88: 8 | M88: 8. Product Add On | N88: Walkways Fastners | O88: 23 | P88: 94.8 | Q88: =P88*O88 -> 2180.4 | S88: Onvlee PO-3697-TSG-20250226 | T88: =T87 -> 45747 | U88: 1377.3127 | W88: =W87 -> 45729
B89: 8 | L89: 8 | M89: 8. Product Add On | N89: Delivery | Q89: 5175 | S89: Onvlee PO-3697-TSG-20250226 | T89: =T88 -> 45747 | U89: 3268.9384 | W89: =W87 -> 45729
B90: 8 | L90: 8 | M90: 8. Product Add On | N90: Cat6 Cable - Cosmic Sun | Q90: 10519 | R90: PO4086-TSG-20250702 - RV Approved | S90: Cosmic Sun CS_TRS_014 | T90: 45838 | U90: 0 | W90: 45841
B91: 8 | L91: 8 | M91: 8. Product Add On | N91: Lifting & Rigging | T91: =IF(W91>1,EOMONTH(W91,0),"") | U91: =(Q91/$X$82*$J$82) -> 0
B92: 8 | L92: 8 | M92: 8. Product Add On | N92: Additional Courier | Q92: 1100 | R92: PO3923-TSG-20250516 - RV Approved | S92: Supply Chain - INV SCO05026 | T92: 45808 | U92: 0 | W92: 45827
B93: 8 | L93: 8 | M93: 8. Product Add On | N93: Temp Fence Transport & Labour | Q93: 12000 | R93: PO3552-TRID-20250121 - RV Approved | S93: Supply Chain Optimiser Inv SCO04728 | T93: 45688 | U93: 8098.8322 | W93: 45708
B94: 8 | L94: 8 | M94: 8. Product Add On | N94: Waterpoints - Deposit | O94: 0.5 | P94: 47900 | Q94: =O94*P94 -> 23950 | R94: PO3621-TSG-20250205 - RV Approved | S94: Plumbryt INV 3621-250314/01 | T94: 45747 | U94: 0 | W94: 45736
L95: 8 | M95: 8. Product Add On | N95: Waterpoints - Balance | O95: 0.5 | Q95: =P94*O95 -> 23950 | S95: Plumbryt INV 3621-250314/01 | T95: 45747 | U95: 0 | W95: 45876
B96: 8 | L96: 8 | M96: 8. Product Add On | N96: MV Shutdown | Q96: 0 | U96: =(Q96/$X$82*$J$82) -> 0
L97: 8 | M97: 8. Product Add On | N97: VO - Inverter Stands, Fence works: Cosmic Sun | O97: 0.6 | P97: 106215.56 | Q97: =O97*P97 -> 63729.336 | R97: PO3661-TSG-20250214 - RV Approved | S97: Cosmic Sun CS_TRS_004 | T97: 45716 | U97: 41161.592 | W97: 45708
L98: 8 | M98: 8. Product Add On | O98: 0.4 | Q98: =O98*P97 -> 42486.224 | S98: Cosmic Sun CS_TRS_007 | T98: 45747 | U98: 26939.092 | W98: 45750
L99: 8 | M99: 8. Product Add On | N99: MV Metering - Malaysian Swittchgear | O99: 0.75 | P99: 44655 | Q99: =O99*P99 -> 33491.25 | R99: PO3725-TSG-20250306 - RV Approved | S99: Malaysian Inv SJ-11558 | T99: 45777 | U99: 39856.733 | W99: 45757
L100: 8 | M100: 8. Product Add On | O100: 0.25 | Q100: =O100*P99 -> 11163.75 | S100: Malaysian Inv SJ-11558 | T100: 45777 | U100: 13285.578 | W100: 45792
L101: 8 | M101: 8. Product Add On | N101: Domestic Transport | Q101: 3500 | R101: PO3865-TSG-20250509 - RV Approved | S101: Supply Chain - INV SCO05008 | T101: 45808 | U101: 76733.912 | W101: 45820
L102: 8 | M102: 8. Product Add On | N102: Walkways Mount Kits Top Up - Onvlee | O102: 50 | P102: 94.8 | Q102: =O102*P102 -> 4740 | R102: PO3914-TSG-20250515 - RV Approved | S102: Onvlee INV01050372 | T102: 45808 | U102: 6353.8099 | W102: 45806
B103: 8 | L103: 8 | M103: 8. Product Add On | N103: Walkways Mount Kits Top Up Delivery - Onvlee | O103: 1 | P103: 1670 | Q103: =O103*P103 -> 1670 | S103: Onvlee INV01050372 | T103: 45808 | U103: 2238.5786 | W103: 45806
...

Sheet Cashflow
D1: [RT: Double Check the first date is always a MONDAY] | F1: 45600 | G1: =F1+7 -> 45607 | H1: =G1+7 -> 45614 | I1: =H1+7 -> 45621 | J1: =I1+7 -> 45628 | K1: =J1+7 -> 45635 | L1: =K1+7 -> 45642 | M1: =L1+7 -> 45649 | N1: =M1+7 -> 45656 | ... CP1: =CO1+7 -> 46216
A2: PLANNED | C2: CHECK | D2: CHECK
B3: Planned Revenue | C3: ='Revenue Tracking'!D4 -> 16024329 | D3: =SUM(F3:CP3) -> 16024329 | F3: =SUMIFS('Revenue Tracking'!$F$12:$F$28, 'Revenue Tracking'!$H$12:$H$28, ">="&F1,'Revenue Tracking'!$H$12:$H$28, "<"&G1) -> 0 | G3: =SUMIFS('Revenue Tracking'!$F$12:$F$28, 'Revenue Tracking'!$H$12:$H$28, ">="&G1,'Revenue Tracking'!$H$12:$H$28, "<"&H1) -> 1602432.9 | H3: =SUMIFS('Revenue Tracking'!$F$12:$F$28, 'Revenue Tracking'!$H$12:$H$28, ">="&H1,'Revenue Tracking'!$H$12:$H$28, "<"&I1) -> 7210948 | I3: =SUMIFS('Revenue Tracking'!$F$12:$F$28, 'Revenue Tracking'!$H$12:$H$28, ">="&I1,'Revenue Tracking'!$H$12:$H$28, "<"&J1) -> 0 | J3: =SUMIFS('Revenue Tracking'!$F$12:$F$28, 'Revenue Tracking'!$H$12:$H$28, ">="&J1,'Revenue Tracking'!$H$12:$H$28, "<"&K1) -> 0 | K3: =SUMIFS('Revenue Tracking'!$F$12:$F$28, 'Revenue Tracking'!$H$12:$H$28, ">="&K1,'Revenue Tracking'!$H$12:$H$28, "<"&L1) -> 0 | L3: =SUMIFS('Revenue Tracking'!$F$12:$F$28, 'Revenue Tracking'!$H$12:$H$28, ">="&L1,'Revenue Tracking'!$H$12:$H$28, "<"&M1) -> 0 | M3: =SUMIFS('Revenue Tracking'!$F$12:$F$28, 'Revenue Tracking'!$H$12:$H$28, ">="&M1,'Revenue Tracking'!$H$12:$H$28, "<"&N1) -> 0 | ... CP3: =SUMIFS('Revenue Tracking'!$F$12:$F$28, 'Revenue Tracking'!$H$12:$H$28, ">="&CP1,'Revenue Tracking'!$H$12:$H$28, "<"&CQ1) -> 0
B4: Planned Revenue - Cumulative | F4: =F3 -> 0 | G4: =F4+G3 -> 1602432.9 | H4: =G4+H3 -> 8813380.9 | I4: =H4+I3 -> 8813380.9 | J4: =I4+J3 -> 8813380.9 | K4: =J4+K3 -> 8813380.9 | L4: =K4+L3 -> 8813380.9 | M4: =L4+M3 -> 8813380.9 | N4: =M4+N3 -> 8813380.9 | ... CP4: =CO4+CP3 -> 16024329
B5: Planned Expenditure | C5: ='Revenue Tracking'!D5 -> 13780794 | D5: =SUM(F5:CP5) -> 12360545 | F5: =SUMIFS('Expenditure Breakdown'!$G$6:$G$173, 'Expenditure Breakdown'!$H$6:$H$173, ">="&F1,'Expenditure Breakdown'!$H$6:$H$173, "<"&G1) -> 0 | G5: =SUMIFS('Expenditure Breakdown'!$G$6:$G$173, 'Expenditure Breakdown'!$H$6:$H$173, ">="&G1,'Expenditure Breakdown'!$H$6:$H$173, "<"&H1) -> 0 | H5: =SUMIFS('Expenditure Breakdown'!$G$6:$G$173, 'Expenditure Breakdown'!$H$6:$H$173, ">="&H1,'Expenditure Breakdown'!$H$6:$H$173, "<"&I1) -> 0 | I5: =SUMIFS('Expenditure Breakdown'!$G$6:$G$173, 'Expenditure Breakdown'!$H$6:$H$173, ">="&I1,'Expenditure Breakdown'!$H$6:$H$173, "<"&J1) -> 0 | J5: =SUMIFS('Expenditure Breakdown'!$G$6:$G$173, 'Expenditure Breakdown'!$H$6:$H$173, ">="&J1,'Expenditure Breakdown'!$H$6:$H$173, "<"&K1) -> 0 | K5: =SUMIFS('Expenditure Breakdown'!$G$6:$G$173, 'Expenditure Breakdown'!$H$6:$H$173, ">="&K1,'Expenditure Breakdown'!$H$6:$H$173, "<"&L1) -> 7922543.6 | L5: =SUMIFS('Expenditure Breakdown'!$G$6:$G$173, 'Expenditure Breakdown'!$H$6:$H$173, ">="&L1,'Expenditure Breakdown'!$H$6:$H$173, "<"&M1) -> 0 | M5: =SUMIFS('Expenditure Breakdown'!$G$6:$G$173, 'Expenditure Breakdown'!$H$6:$H$173, ">="&M1,'Expenditure Breakdown'!$H$6:$H$173, "<"&N1) -> 609828.62 | ... CP5: =SUMIFS('Expenditure Breakdown'!$G$6:$G$173, 'Expenditure Breakdown'!$H$6:$H$173, ">="&CP1,'Expenditure Breakdown'!$H$6:$H$173, "<"&CQ1) -> 0
B6: Planned Expenditure - Cumulative | F6: =F5 -> 0 | G6: =F6+G5 -> 0 | H6: =G6+H5 -> 0 | I6: =H6+I5 -> 0 | J6: =I6+J5 -> 0 | K6: =J6+K5 -> 7922543.6 | L6: =K6+L5 -> 7922543.6 | M6: =L6+M5 -> 8532372.3 | N6: =M6+N5 -> 8837286.6 | ... CP6: =CO6+CP5 -> 12360545
B7: PLANNED CashFlow | F7: =F4-F6 -> 0 | G7: =G4-G6 -> 1602432.9 | H7: =H4-H6 -> 8813380.9 | I7: =I4-I6 -> 8813380.9 | J7: =J4-J6 -> 8813380.9 | K7: =K4-K6 -> 890837.28 | L7: =L4-L6 -> 890837.28 | M7: =M4-M6 -> 281008.66 | ... CP7: =CP4-CP6 -> 3663784
A8: ACTUAL | C8: CHECK | D8: CHECK
B9: Actual + Planned Revenue | C9: ='Revenue Tracking'!F4 -> 16024329 | D9: =SUM(F9:CP9) -> 16024329 | F9: =SUMIFS('Revenue Tracking'!$F$12:$F$28, 'Revenue Tracking'!$P12:$P$28, ">="&F1,'Revenue Tracking'!$P$12:$P$28, "<"&G1) -> 0 | G9: =SUMIFS('Revenue Tracking'!$F$12:$F$28, 'Revenue Tracking'!$P12:$P$28, ">="&G1,'Revenue Tracking'!$P$12:$P$28, "<"&H1) -> 0 | H9: =SUMIFS('Revenue Tracking'!$F$12:$F$28, 'Revenue Tracking'!$P12:$P$28, ">="&H1,'Revenue Tracking'!$P$12:$P$28, "<"&I1) -> 0 | I9: =SUMIFS('Revenue Tracking'!$F$12:$F$28, 'Revenue Tracking'!$P12:$P$28, ">="&I1,'Revenue Tracking'!$P$12:$P$28, "<"&J1) -> 0 | J9: =SUMIFS('Revenue Tracking'!$F$12:$F$28, 'Revenue Tracking'!$P12:$P$28, ">="&J1,'Revenue Tracking'!$P$12:$P$28, "<"&K1) -> 0 | K9: =SUMIFS('Revenue Tracking'!$F$12:$F$28, 'Revenue Tracking'!$P12:$P$28, ">="&K1,'Revenue Tracking'!$P$12:$P$28, "<"&L1) -> 0 | L9: =SUMIFS('Revenue Tracking'!$F$12:$F$28, 'Revenue Tracking'!$P12:$P$28, ">="&L1,'Revenue Tracking'!$P$12:$P$28, "<"&M1) -> 5608515.1 | M9: =SUMIFS('Revenue Tracking'!$F$12:$F$28, 'Revenue Tracking'!$P12:$P$28, ">="&M1,'Revenue Tracking'!$P$12:$P$28, "<"&N1) -> 0 | ... CP9: =SUMIFS('Revenue Tracking'!$F$12:$F$28, 'Revenue Tracking'!$P12:$P$28, ">="&CP1,'Revenue Tracking'!$P$12:$P$28, "<"&CQ1) -> 0
B10: Actual + Planned Revenue - Cumulative | F10: =F9 -> 0 | G10: =F10+G9 -> 0 | H10: =G10+H9 -> 0 | I10: =H10+I9 -> 0 | J10: =I10+J9 -> 0 | K10: =J10+K9 -> 0 | L10: =K10+L9 -> 5608515.1 | M10: =L10+M9 -> 5608515.1 | N10: =M10+N9 -> 5608515.1 | ... CP10: =CO10+CP9 -> 16024329
B11: Actual + Planned Expenditure | C11: ='Revenue Tracking'!F5 -> 14799894 | D11: =SUM(F11:CP11) -> 14799334 | F11: =SUMIFS('Expenditure Breakdown'!$Q$6:$Q$173, 'Expenditure Breakdown'!$W$6:$W$173, ">="&F1,'Expenditure Breakdown'!$W$6:$W$173, "<"&G1) -> 0 | G11: =SUMIFS('Expenditure Breakdown'!$Q$6:$Q$173, 'Expenditure Breakdown'!$W$6:$W$173, ">="&G1,'Expenditure Breakdown'!$W$6:$W$173, "<"&H1) -> 0 | H11: =SUMIFS('Expenditure Breakdown'!$Q$6:$Q$173, 'Expenditure Breakdown'!$W$6:$W$173, ">="&H1,'Expenditure Breakdown'!$W$6:$W$173, "<"&I1) -> 0 | I11: =SUMIFS('Expenditure Breakdown'!$Q$6:$Q$173, 'Expenditure Breakdown'!$W$6:$W$173, ">="&I1,'Expenditure Breakdown'!$W$6:$W$173, "<"&J1) -> 0 | J11: =SUMIFS('Expenditure Breakdown'!$Q$6:$Q$173, 'Expenditure Breakdown'!$W$6:$W$173, ">="&J1,'Expenditure Breakdown'!$W$6:$W$173, "<"&K1) -> 0 | K11: =SUMIFS('Expenditure Breakdown'!$Q$6:$Q$173, 'Expenditure Breakdown'!$W$6:$W$173, ">="&K1,'Expenditure Breakdown'!$W$6:$W$173, "<"&L1) -> 0 | L11: =SUMIFS('Expenditure Breakdown'!$Q$6:$Q$173, 'Expenditure Breakdown'!$W$6:$W$173, ">="&L1,'Expenditure Breakdown'!$W$6:$W$173, "<"&M1) -> 0 | M11: =SUMIFS('Expenditure Breakdown'!$Q$6:$Q$173, 'Expenditure Breakdown'!$W$6:$W$173, ">="&M1,'Expenditure Breakdown'!$W$6:$W$173, "<"&N1) -> 0 | ... CP11: =SUMIFS('Expenditure Breakdown'!$Q$6:$Q$173, 'Expenditure Breakdown'!$W$6:$W$173, ">="&CP1,'Expenditure Breakdown'!$W$6:$W$173, "<"&CQ1) -> 0
B12: Actual + Planned Expenditure - Cumulative | F12: =F11 -> 0 | G12: =F12+G11 -> 0 | H12: =G12+H11 -> 0 | I12: =H12+I11 -> 0 | J12: =I12+J11 -> 0 | K12: =J12+K11 -> 0 | L12: =K12+L11 -> 0 | M12: =L12+M11 -> 0 | N12: =M12+N11 -> 0 | ... CP12: =CO12+CP11 -> 14799334
B14: ACTUAL CashFlow | F14: =F10-F12 -> 0 | G14: =G10-G12 -> 0 | H14: =H10-H12 -> 0 | I14: =I10-I12 -> 0 | J14: =J10-J12 -> 0 | K14: =K10-K12 -> 0 | L14: =L10-L12 -> 5608515.1 | M14: =M10-M12 -> 5608515.1 | ... CP14: =CP10-CP12 -> 1224994.7
C16: CHECK | D16: CHECK
B17: Revenue Recognition | C17: =C3-D17 -> 0.013926148 | D17: =SUM(F17:CP17) -> 16024329 | F17: =SUMIFS('Expenditure Breakdown'!$U$6:$U$173, 'Expenditure Breakdown'!$T$6:$T$173, ">="&F1,'Expenditure Breakdown'!$T$6:$T$173, "<"&G1) -> 0 | G17: =SUMIFS('Expenditure Breakdown'!$U$6:$U$173, 'Expenditure Breakdown'!$T$6:$T$173, ">="&G1,'Expenditure Breakdown'!$T$6:$T$173, "<"&H1) -> 0 | H17: =SUMIFS('Expenditure Breakdown'!$U$6:$U$173, 'Expenditure Breakdown'!$T$6:$T$173, ">="&H1,'Expenditure Breakdown'!$T$6:$T$173, "<"&I1) -> 0 | I17: =SUMIFS('Expenditure Breakdown'!$U$6:$U$173, 'Expenditure Breakdown'!$T$6:$T$173, ">="&I1,'Expenditure Breakdown'!$T$6:$T$173, "<"&J1) -> 0 | J17: =SUMIFS('Expenditure Breakdown'!$U$6:$U$173, 'Expenditure Breakdown'!$T$6:$T$173, ">="&J1,'Expenditure Breakdown'!$T$6:$T$173, "<"&K1) -> 0 | K17: =SUMIFS('Expenditure Breakdown'!$U$6:$U$173, 'Expenditure Breakdown'!$T$6:$T$173, ">="&K1,'Expenditure Breakdown'!$T$6:$T$173, "<"&L1) -> 0 | L17: =SUMIFS('Expenditure Breakdown'!$U$6:$U$173, 'Expenditure Breakdown'!$T$6:$T$173, ">="&L1,'Expenditure Breakdown'!$T$6:$T$173, "<"&M1) -> 0 | M17: =SUMIFS('Expenditure Breakdown'!$U$6:$U$173, 'Expenditure Breakdown'!$T$6:$T$173, ">="&M1,'Expenditure Breakdown'!$T$6:$T$173, "<"&N1) -> 0 | ... CP17: =SUMIFS('Expenditure Breakdown'!$U$6:$U$173, 'Expenditure Breakdown'!$T$6:$T$173, ">="&CP1,'Expenditure Breakdown'!$T$6:$T$173, "<"&CQ1) -> 0
B18: Revenue Recognition Cumulative | C18: =D17-D18 -> 0 | D18: =MAX(F18:CP18) -> 16024329 | F18: =F17 -> 0 | G18: =F18+G17 -> 0 | H18: =G18+H17 -> 0 | I18: =H18+I17 -> 0 | J18: =I18+J17 -> 0 | K18: =J18+K17 -> 0 | L18: =K18+L17 -> 0 | M18: =L18+M17 -> 0 | N18: =M18+N17 -> 5250104.3 | ... CP18: =CO18+CP17 -> 16024329

Sheet Finance - Revenue
A1: REVENUE RECOGNITION AMOUNT | B1: (All)
A3: Sum of REVENUE RECOGNITION AMOUNT | B3: Column Labels
A4: Row Labels | C4: (blank) | D4: 45657 | E4: 45688 | F4: 45716 | G4: 45747 | H4: 45777 | I4: 45808 | J4: 45838 | K4: 45869 | L4: 45900 | M4: Grand Total
A5: (blank)
A6: Battery Systems
A7: BDP Commission
A8: 1. Panels | B8: 0 | C8: 0 | D8: 4699920 | I8: 0 | K8: 0 | M8: 4699920
A9: 2. Inverters | C9: 0 | E9: 1990010.1 | F9: 1236675.9 | L9: 0 | M9: 3226686
A10: 3. Mounting Structures | C10: 0 | E10: 705479.57 | M10: 705479.57
A11: 4. DC Equipment | C11: 0 | D11: 542107.78 | E11: 290003.52 | F11: 193335.68 | G11: 128890.45 | H11: 420189.03 | J11: 52109.226 | M11: 1626635.7
A12: 5. Monitoring | E12: 75275.97 | F12: 226571.36 | G12: 135394 | I12: 155016.74 | J12: 0 | M12: 592258.07
A13: 6. AC Equipment | B13: 0 | E13: 480584.15 | F13: 403722.75 | G13: 195973.53 | H13: 465437.13 | J13: 73490.074 | M13: 1619207.6
A14: 8. Product Add On | B14: 0 | C14: 0 | E14: 8098.8322 | F14: 80505.979 | G14: 71044.973 | H14: 398720.91 | I14: 87469.706 | J14: 0 | M14: 645840.4
A15: 9. AC & DC installation | E15: 503243.48 | F15: 335495.65 | G15: 223663.77 | H15: 531201.45 | J15: 83873.913 | M15: 1677478.3
A16: 10. Site Logistics | B16: 0 | C16: 0 | E16: 81701.035 | F16: 45331.254 | G16: 48227.475 | H16: 69073.256 | J16: 10906.304 | M16: 255239.32
A17: 11. Due Dilligence | D17: 0 | E17: 5746.4983 | H17: 111937.32 | I17: 63837.923 | M17: 181521.74
A18: 13. Engineering | I18: 755562.18 | L18: 0 | M18: 755562.18
A19: 14. General Expenses | D19: 8076.518 | E19: 3343.2704 | F19: 9543.7985 | G19: 4057.1696 | H19: 1505.0668 | I19: 1495.2011 | J19: 239.05988 | K19: 2704.8743 | L19: 7535.0364 | M19: 38499.995
A20: 15. Service Add On
A21: Grand Total | B21: 0 | C21: 0 | D21: 5250104.3 | E21: 4143486.5 | F21: 2531182.4 | G21: 807251.37 | H21: 1998064.2 | I21: 1063381.7 | J21: 220618.58 | K21: 2704.8743 | L21: 7535.0364 | M21: 16024329
D23: 5306329.5 | E23: 4143486.5 | F23: 2534966.7 | G23: 807251.37 | H23: 1998064.2 | I23: 1063381.8 | J23: =220618.58-60009.45 -> 160609.13
D25: =GETPIVOTDATA("REVENUE RECOGNITION AMOUNT",$A$3,"INVOICE RAISED DATE",DATE(2024,12,31))-D23 -> -56225.113 | E25: =GETPIVOTDATA("REVENUE RECOGNITION AMOUNT",$A$3,"INVOICE RAISED DATE",DATE(2025,1,31))-E23 -> -0.0044445312 | F25: =GETPIVOTDATA("REVENUE RECOGNITION AMOUNT",$A$3,"INVOICE RAISED DATE",DATE(2025,2,28))-F23 -> -3784.3287 | G25: =GETPIVOTDATA("REVENUE RECOGNITION AMOUNT",$A$3,"INVOICE RAISED DATE",DATE(2025,3,31))-G23 -> -0.0029091191 | H25: =GETPIVOTDATA("REVENUE RECOGNITION AMOUNT",$A$3,"INVOICE RAISED DATE",DATE(2025,4,30))-H23 -> 0.0010520364 | I25: =GETPIVOTDATA("REVENUE RECOGNITION AMOUNT",$A$3,"INVOICE RAISED DATE",DATE(2025,5,31))-I23 -> -0.0026663046 | J25: =GETPIVOTDATA("REVENUE RECOGNITION AMOUNT",$A$3,"INVOICE RAISED DATE",DATE(2025,6,30))-J23 -> 60009.446 | M25: =SUM(D25:L25) -> -0.0049547798

Sheet Finance - COS
A3: Sum of Actual Total | B3: Column Labels
A4: Row Labels | B4: (blank) | D4: 45657 | E4: 45688 | F4: 45716 | G4: 45747 | H4: 45777 | I4: 45808 | J4: 45838 | K4: 45869 | L4: 45900 | M4: 46053 | N4: Grand Total
A5: Battery Systems
A6: BDP Commission | C6: 0 | N6: 0
A7: (blank)
A8: 1. Panels | D8: 4254751.8 | I8: 685.71 | K8: 221.43 | N8: 4255658.9
A9: 2. Inverters | B9: 0 | E9: 1914000 | F9: 1189440 | L9: 55800 | N9: 3159240
A10: 3. Mounting Structures | B10: 0 | E10: 346295 | H10: 39048 | N10: 385343
A11: 4. DC Equipment | B11: 0 | D11: 611800 | E11: 327285.75 | F11: 218190.5 | G11: 145460.33 | H11: 345468.29 | J11: 54547.625 | N11: 1702752.5
A12: 5. Monitoring | E12: 51331 | F12: 124822.36 | G12: 106466.99 | I12: 120509.63 | J12: 16453 | N12: 419582.98
A13: 6. AC Equipment | E13: 416420.66 | F13: 418711.77 | G13: 185075.85 | H13: 439555.14 | J13: 69403.444 | N13: 1529166.9
A14: 8. Product Add On | B14: 0 | E14: 12000 | F14: 80529.336 | G14: 160209.48 | H14: 216455 | I14: 12609 | J14: 10519 | N14: 492321.82
A15: 9. AC & DC installation | E15: 615750 | F15: 410500 | G15: 273666.67 | H15: 649958.33 | J15: 102625 | N15: 2052500
A16: 10. Site Logistics | E16: 138339 | F16: 72526 | G16: 79850.667 | H16: 115482.83 | J16: 18131.5 | N16: 424330
A17: 11. Due Dilligence | D17: 0 | E17: 5100 | H17: 79700 | I17: 35647.39 | N17: 120447.39
A18: 13. Engineering | I18: 200304.11 | L18: -34704.11 | N18: 165600
A19: 14. General Expenses | D19: 7446.43 | E19: 2931 | F19: 12977.95 | G19: 3958.29 | H19: 1491.59 | I19: 1352.79 | J19: 194.68 | K19: 2331.4 | L19: 4368.24 | N19: 37052.37
A20: 15. Service Add On | K20: 33238 | L20: 5500 | M20: 17160 | N20: 55898
A21: Grand Total | B21: 0 | C21: 0 | D21: 4873998.2 | E21: 3829452.4 | F21: 2527697.9 | G21: 954688.28 | H21: 1887159.2 | I21: 371108.63 | J21: 271874.25 | K21: 35790.83 | L21: 30964.13 | M21: 17160 | N21: 14799894

Sheet Project Margins
A1: [capture project margins from costing sheet]
A3: Products | D3: 0.32
A4: Services | D4: 0.5
A5: Expenses | D5: 0.15
A6: Subcontractors | D6: 0.2

Sheet Equipment Quotes
B2: Equipment Quote and Budget comparision
B4: Description | D4: Budget | F4: Supplier 1 | H4: Variance | J4: Supplier 2 | L4: Variance | N4: Comments / Notes
F7: >Name< | J7: >Name<
B9: Inverters | D9: =SUM(D10:D11) -> 1190898 | F9: =SUM(F10:F13) -> 0 | H9: =$D$9-F9 -> 1190898 | J9: =SUM(J10:J13) -> 0 | L9: =$D$9-J9 -> 1190898
B10: Inverters | D10: ='Expenditure Breakdown'!G14 -> 1190898
B11: Optimizers | D11: ='Expenditure Breakdown'!G16 -> 0
B12: Warranty
B13: Delivery fee
F15: >Name< | J15: >Name<
B17: Mounting Structure | D17: =SUM(D18:D19) -> 656096 | F17: =SUM(F18:F20) -> 0 | H17: =$D$17- F17 -> 656096 | J17: =SUM(J18:J20) -> 0 | L17: =$D$17- J17 -> 656096
B18: Mounting Structure | D18: ='Expenditure Breakdown'!G21 -> 656096
B19: Delivery fee
F21: >Name< | J21: >Name<
B23: DC Cable | D23: =SUM(D24:D25) -> 557200 | F23: =SUM(F24:F25) -> 0 | H23: =$D$23- F23 -> 557200 | J23: =SUM(J24:J25) -> 0 | L23: =$D$23- J23 -> 557200
B24: DC Cable | D24: ='Expenditure Breakdown'!G26 -> 557200
B25: Delivery fee
F27: >Name< | J27: >Name<
B29: Monitoring system | D29: =SUM(D30:D32) -> #REF! | F29: =SUM(F30:F42) -> 0 | H29: =$D$29-F29 -> #REF! | J29: =SUM(J30:J32) -> 0 | L29: =$D$29-J29 -> #REF!
B30: ='Expenditure Breakdown'!D40 -> SolarEdge Gateway | D30: ='Expenditure Breakdown'!G40 -> 4300
B31: ='Expenditure Breakdown'!#REF! -> #REF! | D31: ='Expenditure Breakdown'!#REF! -> #REF!
B32: Delivery fee
F34: >Name< | J34: >Name<
B36: Additional Scope | D36: =SUM(D37:D41) -> 100000 | F36: =SUM(F37:F41) -> 0 | H36: =$D$29-F36 -> #REF! | J36: =SUM(J37:J41) -> 0 | L36: =$D$29-J36 -> #REF!
B37: SCADA | D37: ='Expenditure Breakdown'!G82 -> 100000
B38: Inverter cage
B39: Cat ladders
B40: Gen Integration
B41: Lifelines
B43: Totals | D43: =D36+D29+D23+D17+D9 -> #REF! | H43: =SUM(H7:H42) -> #REF! | L43: =SUM(L7:L42) -> #REF!
B47: All amounts are incl VAT

Sheet Installer Quotes
B2: Installer Quote and Budget comparision
B4: Description | D4: Budget | G4: Cosmic Sun | J4: Variance | L4: Matthews Group | O4: Variance
B6: AC Equipment | D6: ='Expenditure Breakdown'!AA8 -> 1505863.1 | E6: =D6/(1000*'Project Plan'!$E$3) -> 0.80312699 | G6: 277892.91 | H6: =G6/('Project Plan'!$E$3*1000) -> 0.14820955 | J6: =D6-G6 -> 1227970.2 | M6: =L6/('Project Plan'!$E$3*1000) -> 0 | O6: =D6-L6 -> 1505863.1
B7: DC Equipment | D7: ='Expenditure Breakdown'!AA9 -> 955571.2 | E7: =D7/(1000*'Project Plan'!$E$3) -> 0.50963797 | G7: 142158.25 | H7: =G7/('Project Plan'!$E$3*1000) -> 0.075817733 | J7: =D7-G7 -> 813412.95 | M7: =L7/('Project Plan'!$E$3*1000) -> 0 | O7: =D7-L7 -> 955571.2
B8: AC Labour | D8: ='Expenditure Breakdown'!AA10 -> 1074640 | E8: =D8/(1000*'Project Plan'!$E$3) -> 0.57314133 | G8: 96174 | H8: =G8/('Project Plan'!$E$3*1000) -> 0.0512928 | J8: =D8-G8 -> 978466 | M8: =L8/('Project Plan'!$E$3*1000) -> 0 | O8: =D8-L8 -> 1074640
B9: DC Labour | D9: ='Expenditure Breakdown'!AA12 -> 468640 | E9: =D9/(1000*'Project Plan'!$E$3) -> 0.24994133 | G9: 230160 | H9: =G9/('Project Plan'!$E$3*1000) -> 0.122752 | J9: =D9-G9 -> 238480 | M9: =L9/('Project Plan'!$E$3*1000) -> 0 | O9: =D9-L9 -> 468640
B10: Offloading | D10: ='Expenditure Breakdown'!AA13 -> 8500 | G10: 0 | J10: =D10-G10 -> 8500 | O10: =D10-L10 -> 8500
B11: Roof Access/Scaffolding | D11: ='Expenditure Breakdown'!AA14 -> 74707.68 | G11: 29257.61 | J11: =D11-G11 -> 45450.07 | O11: =D11-L11 -> 74707.68
B12: Storage | D12: ='Expenditure Breakdown'!AA16 -> 51892.5 | J12: =D12-G12 -> 51892.5 | O12: =D12-L12 -> 51892.5
B13: Telehandler | D13: ='Expenditure Breakdown'!AA17 -> 32400
B14: HSE | D14: 0
B15: Totals | D15: =SUM(D6:D13) -> 4172214.5 | G15: =SUM(G6:G13) -> 775642.77 | J15: =SUM(J6:J14) -> 3364171.7 | L15: =SUM(L6:L13) -> 0 | O15: =SUM(O6:O14) -> 4139814.5
B18: Description | D18: Budget | G18: >Installer Name 3< | J18: Variance | L18: >Installer Name 4< | O18: Variance
B20: AC installation | D20: ='Expenditure Breakdown'!#REF! -> #REF! | E20: =D20/(1000*'Project Plan'!$E$3) -> #REF! | H20: =G20/(1000*'Project Plan'!$E$3) -> 0 | J20: =D20-G20 -> #REF! | M20: =L20/(1000*'Project Plan'!$E$3) -> 0 | O20: =D6-L20 -> 1505863.1
B21: AC equipment | D21: ='Expenditure Breakdown'!C71 -> 0 | E21: =D21/(1000*'Project Plan'!$E$3) -> 0 | J21: =D21-G21 -> 0 | M21: =L21/(1000*'Project Plan'!$E$3) -> 0 | O21: =D7-L21 -> 955571.2
B22: DC installation | D22: ='Expenditure Breakdown'!#REF! -> #REF! | E22: =D22/(1000*'Project Plan'!$E$3) -> #REF! | H22: =G22/(1000*'Project Plan'!$E$3) -> 0 | J22: =D22-G22 -> #REF! | M22: =L22/(1000*'Project Plan'!$E$3) -> 0 | O22: =D8-L22 -> 1074640
B23: DC equipment | D23: =SUM('Expenditure Breakdown'!G32:G32) -> 537300 | E23: =D23/(1000*'Project Plan'!$E$3) -> 0.28656 | J23: =D23-G23 -> 537300 | O23: =D9-L23 -> 468640
B24: Storage | D24: ='Expenditure Breakdown'!G144 -> 0 | J24: =D24-G24 -> 0 | O24: =D10-L24 -> 8500
B25: Panel lifting equipment | D25: =SUM('Expenditure Breakdown'!G117:G125) -> 92792.5 | J25: =D25-G25 -> 92792.5 | O25: =D11-L25 -> 74707.68
B26: Offloading | D26: ='Expenditure Breakdown'!G137 -> 0 | J26: =D26-G26 -> 0 | O26: =D12-L26 -> 51892.5
B29: Totals | D29: =SUM(D20:D27) -> #REF! | G29: =SUM(G20:G27) -> 0 | J29: =SUM(J20:J28) -> #REF! | L29: =SUM(L20:L27) -> 0 | O29: =SUM(O20:O28) -> 4139814.5
B32: Budget Summary
B34: Budget | D34: =D15 -> 4172214.5
B35: =G4 -> Cosmic Sun | D35: =G15 -> 775642.77
B36: =L4 -> Matthews Group | D36: =L15 -> 0
B37: =G18 -> >Installer Name 3< | D37: =G29 -> 0
B38: =L18 -> >Installer Name 4< | D38: =L29 -> 0
B40: =IF(D40<D34,"Saving","Loss") -> Loss | D40: =D34-MIN(D35:D38) -> 4172214.5
B42: All amounts are exc VAT

Sheet Decision Register
B1: =D15 -> Trident Steel GP | E1: Decision Register
B3: ID | C3: Decision Description | D3: Decision Impact | E3: Proposed Date | F3: Proposed By | G3: Status | H3: Approved By | I3: Date | J3: Results / Comments
B4: DEC001
B5: DEC002
B6: DEC003
B7: DEC004
B8: DEC005
B9: DEC006
B10: DEC007
B11: DEC008
B12: DEC009
B13: DEC010
D15: {='Project Plan'!E2:H2} -> Trident Steel GP | E15: 0 | F15: 0 | G15: 0
