Workbook
Name Inverter_Capacity: #REF!
Name Inverter_Supplier: #REF!
Name Project_Size: 'Certificate - Financial Close'!Projectsize
Name Project_Size: Compliance!Projectsize
Name Project_Size: 'Finance - Rev'!Projectsize
Name Project_Size: Projectsize
Name Projectsize: #REF!
Name Projectsize: #REF!
Name Projectsize: #REF!
Name Projectsize: 'Project Margins'!$K$5
Name Security_Serv: #REF!
Name Security_Serv: #REF!
Name SSS: #REF!
Name SSS: #REF!
Name USD_ZAR: #REF!

Sheet Sheet1
A1: PROJECT PLAN
A2: # | B2: Project Milestone | C2: Planned Start Date | D2: Duration (Work Days) | E2: Planned End Date | F2: Actual Start Date | H2: Actual End Date | J2: Comments | L2: =C3 -> 43831 | M2: =L2+3 -> 43834 | N2: =M2+7 -> 43841 | O2: =N2+7 -> 43848 | P2: =O2+7 -> 43855 | Q2: =P2+6 -> 43861 | R2: =Q2+1 -> 43862 | S2: =R2+7 -> 43869 | T2: =S2+7 -> 43876 | U2: =T2+7 -> 43883 | V2: =U2+6 -> 43889 | W2: =V2+7 -> 43896 | X2: =W2+7 -> 43903 | Y2: =X2+7 -> 43910 | Z2: =Y2+7 -> 43917 | AA2: =Z2+3 -> 43920 | AB2: =AA2+4 -> 43924 | AC2: =AB2+7 -> 43931 | AD2: =AC2+7 -> 43938 | AE2: =AD2+7 -> 43945 | AF2: =AE2+6 -> 43951 | AG2: =AF2+2 -> 43953 | AH2: =AG2+7 -> 43960 | AI2: =AH2+7 -> 43967 | AJ2: =AI2+7 -> 43974 | AK2: =AJ2+7 -> 43981 | AL2: =AK2+1 -> 43982 | AM2: =AL2+6 -> 43988 | AN2: =AM2+7 -> 43995 | AO2: =AN2+7 -> 44002 | AP2: =AO2+7 -> 44009 | AQ2: =AP2+3 -> 44012 | AR2: =AQ2+4 -> 44016 | AS2: =AR2+7 -> 44023 | AT2: =AS2+7 -> 44030 | AU2: =AT2+7 -> 44037 | AV2: =AU2+6 -> 44043 | AW2: =AV2+1 -> 44044 | AX2: =AW2+7 -> 44051 | AY2: =AX2+7 -> 44058 | AZ2: =AY2+7 -> 44065 | BA2: =AZ2+7 -> 44072 | BB2: =BA2+2 -> 44074 | BC2: =BB2+5 -> 44079 | BD2: =BC2+7 -> 44086 | BE2: =BD2+7 -> 44093 | BF2: =BE2+7 -> 44100 | BG2: =BF2+4 -> 44104
A3: 1 | B3: Contract Signature | C3: 43831 | D3: 1 | E3: 43832 | F3: 43831 | G3: 1 | H3: 43832 | L3: =IF(AND($F3<(L$2+7),$F3>L$2),1, IF(AND($H3<L$2+7,$H3>L$2),3, IF(AND($F3<=L$2, $H3>=L$2), 2, "" ))) -> 3 | M3: =IF(AND($F3<(M$2+7),$F3>M$2),1, IF(AND($H3<M$2+7,$H3>M$2),3, IF(AND($F3<=M$2, $H3>=M$2), 2, "" ))) | N3: =IF(AND($F3<(N$2+7),$F3>N$2),1, IF(AND($H3<N$2+7,$H3>N$2),3, IF(AND($F3<=N$2, $H3>=N$2), 2, "" ))) | O3: =IF(AND($F3<(O$2+7),$F3>O$2),1, IF(AND($H3<O$2+7,$H3>O$2),3, IF(AND($F3<=O$2, $H3>=O$2), 2, "" ))) | P3: =IF(AND($F3<(P$2+7),$F3>P$2),1, IF(AND($H3<P$2+7,$H3>P$2),3, IF(AND($F3<=P$2, $H3>=P$2), 2, "" ))) | Q3: =IF(AND($F3<(Q$2+7),$F3>Q$2),1, IF(AND($H3<Q$2+7,$H3>Q$2),3, IF(AND($F3<=Q$2, $H3>=Q$2), 2, "" ))) | R3: =IF(AND($F3<(R$2+7),$F3>R$2),1, IF(AND($H3<R$2+7,$H3>R$2),3, IF(AND($F3<=R$2, $H3>=R$2), 2, "" ))) | S3: =IF(AND($F3<(S$2+7),$F3>S$2),1, IF(AND($H3<S$2+7,$H3>S$2),3, IF(AND($F3<=S$2, $H3>=S$2), 2, "" ))) | ... AQ3: =IF(AND($F3<(AQ$2+7),$F3>AQ$2),1, IF(AND($H3<AQ$2+7,$H3>AQ$2),3, IF(AND($F3<=AQ$2, $H3>=AQ$2), 2, "" )))
A4: A | B4: PAYMENT MILESTONE 1: DEPOSIT | C4: 43832 | D4: 1 | E4: 43833 | F4: 43832 | G4: 1 | H4: 43833 | L4: =IF(AND($F4<(L$2+7),$F4>L$2),1, IF(AND($H4<L$2+7,$H4>L$2),3, IF(AND($F4<=L$2, $H4>=L$2), 2, "" ))) -> 1 | M4: =IF(AND($F4<(M$2+7),$F4>M$2),1, IF(AND($H4<M$2+7,$H4>M$2),3, IF(AND($F4<=M$2, $H4>=M$2), 2, "" ))) | N4: =IF(AND($F4<(N$2+7),$F4>N$2),1, IF(AND($H4<N$2+7,$H4>N$2),3, IF(AND($F4<=N$2, $H4>=N$2), 2, "" ))) | O4: =IF(AND($F4<(O$2+7),$F4>O$2),1, IF(AND($H4<O$2+7,$H4>O$2),3, IF(AND($F4<=O$2, $H4>=O$2), 2, "" ))) | P4: =IF(AND($F4<(P$2+7),$F4>P$2),1, IF(AND($H4<P$2+7,$H4>P$2),3, IF(AND($F4<=P$2, $H4>=P$2), 2, "" ))) | Q4: =IF(AND($F4<(Q$2+7),$F4>Q$2),1, IF(AND($H4<Q$2+7,$H4>Q$2),3, IF(AND($F4<=Q$2, $H4>=Q$2), 2, "" ))) | R4: =IF(AND($F4<(R$2+7),$F4>R$2),1, IF(AND($H4<R$2+7,$H4>R$2),3, IF(AND($F4<=R$2, $H4>=R$2), 2, "" ))) | S4: =IF(AND($F4<(S$2+7),$F4>S$2),1, IF(AND($H4<S$2+7,$H4>S$2),3, IF(AND($F4<=S$2, $H4>=S$2), 2, "" ))) | ... AQ4: =IF(AND($F4<(AQ$2+7),$F4>AQ$2),1, IF(AND($H4<AQ$2+7,$H4>AQ$2),3, IF(AND($F4<=AQ$2, $H4>=AQ$2), 2, "" )))
A5: 2 | B5: Structural and Electrical Due Diligences | C5: 43833 | D5: 5 | E5: 43840 | F5: 43833 | G5: 5 | H5: 43840 | L5: =IF(AND($F5<(L$2+7),$F5>L$2),1, IF(AND($H5<L$2+7,$H5>L$2),3, IF(AND($F5<=L$2, $H5>=L$2), 2, "" ))) -> 1 | M5: =IF(AND($F5<(M$2+7),$F5>M$2),1, IF(AND($H5<M$2+7,$H5>M$2),3, IF(AND($F5<=M$2, $H5>=M$2), 2, "" ))) -> 3 | N5: =IF(AND($F5<(N$2+7),$F5>N$2),1, IF(AND($H5<N$2+7,$H5>N$2),3, IF(AND($F5<=N$2, $H5>=N$2), 2, "" ))) | O5: =IF(AND($F5<(O$2+7),$F5>O$2),1, IF(AND($H5<O$2+7,$H5>O$2),3, IF(AND($F5<=O$2, $H5>=O$2), 2, "" ))) | P5: =IF(AND($F5<(P$2+7),$F5>P$2),1, IF(AND($H5<P$2+7,$H5>P$2),3, IF(AND($F5<=P$2, $H5>=P$2), 2, "" ))) | Q5: =IF(AND($F5<(Q$2+7),$F5>Q$2),1, IF(AND($H5<Q$2+7,$H5>Q$2),3, IF(AND($F5<=Q$2, $H5>=Q$2), 2, "" ))) | R5: =IF(AND($F5<(R$2+7),$F5>R$2),1, IF(AND($H5<R$2+7,$H5>R$2),3, IF(AND($F5<=R$2, $H5>=R$2), 2, "" ))) | S5: =IF(AND($F5<(S$2+7),$F5>S$2),1, IF(AND($H5<S$2+7,$H5>S$2),3, IF(AND($F5<=S$2, $H5>=S$2), 2, "" ))) | ... AQ5: =IF(AND($F5<(AQ$2+7),$F5>AQ$2),1, IF(AND($H5<AQ$2+7,$H5>AQ$2),3, IF(AND($F5<=AQ$2, $H5>=AQ$2), 2, "" )))
A6: 3 | B6: Design Confirmation | C6: 43841 | D6: 2 | E6: 43844 | F6: 43841 | G6: 2 | H6: 43844 | L6: =IF(AND($F6<(L$2+7),$F6>L$2),1, IF(AND($H6<L$2+7,$H6>L$2),3, IF(AND($F6<=L$2, $H6>=L$2), 2, "" ))) | M6: =IF(AND($F6<(M$2+7),$F6>M$2),1, IF(AND($H6<M$2+7,$H6>M$2),3, IF(AND($F6<=M$2, $H6>=M$2), 2, "" ))) | N6: =IF(AND($F6<(N$2+7),$F6>N$2),1, IF(AND($H6<N$2+7,$H6>N$2),3, IF(AND($F6<=N$2, $H6>=N$2), 2, "" ))) -> 3 | O6: =IF(AND($F6<(O$2+7),$F6>O$2),1, IF(AND($H6<O$2+7,$H6>O$2),3, IF(AND($F6<=O$2, $H6>=O$2), 2, "" ))) | P6: =IF(AND($F6<(P$2+7),$F6>P$2),1, IF(AND($H6<P$2+7,$H6>P$2),3, IF(AND($F6<=P$2, $H6>=P$2), 2, "" ))) | Q6: =IF(AND($F6<(Q$2+7),$F6>Q$2),1, IF(AND($H6<Q$2+7,$H6>Q$2),3, IF(AND($F6<=Q$2, $H6>=Q$2), 2, "" ))) | R6: =IF(AND($F6<(R$2+7),$F6>R$2),1, IF(AND($H6<R$2+7,$H6>R$2),3, IF(AND($F6<=R$2, $H6>=R$2), 2, "" ))) | S6: =IF(AND($F6<(S$2+7),$F6>S$2),1, IF(AND($H6<S$2+7,$H6>S$2),3, IF(AND($F6<=S$2, $H6>=S$2), 2, "" ))) | ... AQ6: =IF(AND($F6<(AQ$2+7),$F6>AQ$2),1, IF(AND($H6<AQ$2+7,$H6>AQ$2),3, IF(AND($F6<=AQ$2, $H6>=AQ$2), 2, "" )))
A7: 4 | B7: Equipment Procurement | C7: 43833 | E7: 43949 | F7: 43833 | H7: 43949 | L7: =IF(AND($F7<(L$2+7),$F7>L$2),1, IF(AND($H7<L$2+7,$H7>L$2),3, IF(AND($F7<=L$2, $H7>=L$2), 2, "" ))) -> 1 | M7: =IF(AND($F7<(M$2+7),$F7>M$2),1, IF(AND($H7<M$2+7,$H7>M$2),3, IF(AND($F7<=M$2, $H7>=M$2), 2, "" ))) -> 2 | N7: =IF(AND($F7<(N$2+7),$F7>N$2),1, IF(AND($H7<N$2+7,$H7>N$2),3, IF(AND($F7<=N$2, $H7>=N$2), 2, "" ))) -> 2 | O7: =IF(AND($F7<(O$2+7),$F7>O$2),1, IF(AND($H7<O$2+7,$H7>O$2),3, IF(AND($F7<=O$2, $H7>=O$2), 2, "" ))) -> 2 | P7: =IF(AND($F7<(P$2+7),$F7>P$2),1, IF(AND($H7<P$2+7,$H7>P$2),3, IF(AND($F7<=P$2, $H7>=P$2), 2, "" ))) -> 2 | Q7: =IF(AND($F7<(Q$2+7),$F7>Q$2),1, IF(AND($H7<Q$2+7,$H7>Q$2),3, IF(AND($F7<=Q$2, $H7>=Q$2), 2, "" ))) -> 2 | R7: =IF(AND($F7<(R$2+7),$F7>R$2),1, IF(AND($H7<R$2+7,$H7>R$2),3, IF(AND($F7<=R$2, $H7>=R$2), 2, "" ))) -> 2 | S7: =IF(AND($F7<(S$2+7),$F7>S$2),1, IF(AND($H7<S$2+7,$H7>S$2),3, IF(AND($F7<=S$2, $H7>=S$2), 2, "" ))) -> 2 | ... AQ7: =IF(AND($F7<(AQ$2+7),$F7>AQ$2),1, IF(AND($H7<AQ$2+7,$H7>AQ$2),3, IF(AND($F7<=AQ$2, $H7>=AQ$2), 2, "" )))
B8: Panel Procurement | C8: 43833 | D8: 5 | E8: 43840 | F8: 43833 | G8: 5 | H8: 43840 | L8: =IF(AND($F8<(L$2+7),$F8>L$2),1, IF(AND($H8<L$2+7,$H8>L$2),3, IF(AND($F8<=L$2, $H8>=L$2), 2, "" ))) -> 1 | M8: =IF(AND($F8<(M$2+7),$F8>M$2),1, IF(AND($H8<M$2+7,$H8>M$2),3, IF(AND($F8<=M$2, $H8>=M$2), 2, "" ))) -> 3 | N8: =IF(AND($F8<(N$2+7),$F8>N$2),1, IF(AND($H8<N$2+7,$H8>N$2),3, IF(AND($F8<=N$2, $H8>=N$2), 2, "" ))) | O8: =IF(AND($F8<(O$2+7),$F8>O$2),1, IF(AND($H8<O$2+7,$H8>O$2),3, IF(AND($F8<=O$2, $H8>=O$2), 2, "" ))) | P8: =IF(AND($F8<(P$2+7),$F8>P$2),1, IF(AND($H8<P$2+7,$H8>P$2),3, IF(AND($F8<=P$2, $H8>=P$2), 2, "" ))) | Q8: =IF(AND($F8<(Q$2+7),$F8>Q$2),1, IF(AND($H8<Q$2+7,$H8>Q$2),3, IF(AND($F8<=Q$2, $H8>=Q$2), 2, "" ))) | R8: =IF(AND($F8<(R$2+7),$F8>R$2),1, IF(AND($H8<R$2+7,$H8>R$2),3, IF(AND($F8<=R$2, $H8>=R$2), 2, "" ))) | S8: =IF(AND($F8<(S$2+7),$F8>S$2),1, IF(AND($H8<S$2+7,$H8>S$2),3, IF(AND($F8<=S$2, $H8>=S$2), 2, "" ))) | ... AQ8: =IF(AND($F8<(AQ$2+7),$F8>AQ$2),1, IF(AND($H8<AQ$2+7,$H8>AQ$2),3, IF(AND($F8<=AQ$2, $H8>=AQ$2), 2, "" )))
B9: Inverter Procurement | C9: 43941 | D9: 5 | E9: 43949 | F9: 43941 | G9: 5 | H9: 43949 | L9: =IF(AND($F9<(L$2+7),$F9>L$2),1, IF(AND($H9<L$2+7,$H9>L$2),3, IF(AND($F9<=L$2, $H9>=L$2), 2, "" ))) | M9: =IF(AND($F9<(M$2+7),$F9>M$2),1, IF(AND($H9<M$2+7,$H9>M$2),3, IF(AND($F9<=M$2, $H9>=M$2), 2, "" ))) | N9: =IF(AND($F9<(N$2+7),$F9>N$2),1, IF(AND($H9<N$2+7,$H9>N$2),3, IF(AND($F9<=N$2, $H9>=N$2), 2, "" ))) | O9: =IF(AND($F9<(O$2+7),$F9>O$2),1, IF(AND($H9<O$2+7,$H9>O$2),3, IF(AND($F9<=O$2, $H9>=O$2), 2, "" ))) | P9: =IF(AND($F9<(P$2+7),$F9>P$2),1, IF(AND($H9<P$2+7,$H9>P$2),3, IF(AND($F9<=P$2, $H9>=P$2), 2, "" ))) | Q9: =IF(AND($F9<(Q$2+7),$F9>Q$2),1, IF(AND($H9<Q$2+7,$H9>Q$2),3, IF(AND($F9<=Q$2, $H9>=Q$2), 2, "" ))) | R9: =IF(AND($F9<(R$2+7),$F9>R$2),1, IF(AND($H9<R$2+7,$H9>R$2),3, IF(AND($F9<=R$2, $H9>=R$2), 2, "" ))) | S9: =IF(AND($F9<(S$2+7),$F9>S$2),1, IF(AND($H9<S$2+7,$H9>S$2),3, IF(AND($F9<=S$2, $H9>=S$2), 2, "" ))) | ... AQ9: =IF(AND($F9<(AQ$2+7),$F9>AQ$2),1, IF(AND($H9<AQ$2+7,$H9>AQ$2),3, IF(AND($F9<=AQ$2, $H9>=AQ$2), 2, "" )))
B10: Mounting Structure Procurement | C10: 43941 | D10: 5 | E10: 43949 | F10: 43941 | G10: 5 | H10: 43949 | L10: =IF(AND($F10<(L$2+7),$F10>L$2),1, IF(AND($H10<L$2+7,$H10>L$2),3, IF(AND($F10<=L$2, $H10>=L$2), 2, "" ))) | M10: =IF(AND($F10<(M$2+7),$F10>M$2),1, IF(AND($H10<M$2+7,$H10>M$2),3, IF(AND($F10<=M$2, $H10>=M$2), 2, "" ))) | N10: =IF(AND($F10<(N$2+7),$F10>N$2),1, IF(AND($H10<N$2+7,$H10>N$2),3, IF(AND($F10<=N$2, $H10>=N$2), 2, "" ))) | O10: =IF(AND($F10<(O$2+7),$F10>O$2),1, IF(AND($H10<O$2+7,$H10>O$2),3, IF(AND($F10<=O$2, $H10>=O$2), 2, "" ))) | P10: =IF(AND($F10<(P$2+7),$F10>P$2),1, IF(AND($H10<P$2+7,$H10>P$2),3, IF(AND($F10<=P$2, $H10>=P$2), 2, "" ))) | Q10: =IF(AND($F10<(Q$2+7),$F10>Q$2),1, IF(AND($H10<Q$2+7,$H10>Q$2),3, IF(AND($F10<=Q$2, $H10>=Q$2), 2, "" ))) | R10: =IF(AND($F10<(R$2+7),$F10>R$2),1, IF(AND($H10<R$2+7,$H10>R$2),3, IF(AND($F10<=R$2, $H10>=R$2), 2, "" ))) | S10: =IF(AND($F10<(S$2+7),$F10>S$2),1, IF(AND($H10<S$2+7,$H10>S$2),3, IF(AND($F10<=S$2, $H10>=S$2), 2, "" ))) | ... AQ10: =IF(AND($F10<(AQ$2+7),$F10>AQ$2),1, IF(AND($H10<AQ$2+7,$H10>AQ$2),3, IF(AND($F10<=AQ$2, $H10>=AQ$2), 2, "" )))
B11: BOS Procurement | C11: 43941 | D11: 5 | E11: 43949 | F11: 43941 | G11: 5 | H11: 43949 | L11: =IF(AND($F11<(L$2+7),$F11>L$2),1, IF(AND($H11<L$2+7,$H11>L$2),3, IF(AND($F11<=L$2, $H11>=L$2), 2, "" ))) | M11: =IF(AND($F11<(M$2+7),$F11>M$2),1, IF(AND($H11<M$2+7,$H11>M$2),3, IF(AND($F11<=M$2, $H11>=M$2), 2, "" ))) | N11: =IF(AND($F11<(N$2+7),$F11>N$2),1, IF(AND($H11<N$2+7,$H11>N$2),3, IF(AND($F11<=N$2, $H11>=N$2), 2, "" ))) | O11: =IF(AND($F11<(O$2+7),$F11>O$2),1, IF(AND($H11<O$2+7,$H11>O$2),3, IF(AND($F11<=O$2, $H11>=O$2), 2, "" ))) | P11: =IF(AND($F11<(P$2+7),$F11>P$2),1, IF(AND($H11<P$2+7,$H11>P$2),3, IF(AND($F11<=P$2, $H11>=P$2), 2, "" ))) | Q11: =IF(AND($F11<(Q$2+7),$F11>Q$2),1, IF(AND($H11<Q$2+7,$H11>Q$2),3, IF(AND($F11<=Q$2, $H11>=Q$2), 2, "" ))) | R11: =IF(AND($F11<(R$2+7),$F11>R$2),1, IF(AND($H11<R$2+7,$H11>R$2),3, IF(AND($F11<=R$2, $H11>=R$2), 2, "" ))) | S11: =IF(AND($F11<(S$2+7),$F11>S$2),1, IF(AND($H11<S$2+7,$H11>S$2),3, IF(AND($F11<=S$2, $H11>=S$2), 2, "" ))) | ... AQ11: =IF(AND($F11<(AQ$2+7),$F11>AQ$2),1, IF(AND($H11<AQ$2+7,$H11>AQ$2),3, IF(AND($F11<=AQ$2, $H11>=AQ$2), 2, "" )))
A12: 5 | B12: Internal Project Kick off | C12: 43936 | D12: 5 | E12: 43943 | F12: 43936 | G12: 5 | H12: 43943
A13: 6 | B13: Client Project Kick-off | C13: 43963 | D13: 5 | E13: 43970 | F13: 43963 | G13: 5 | H13: 43970 | L13: =IF(AND($F13<(L$2+7),$F13>L$2),1, IF(AND($H13<L$2+7,$H13>L$2),3, IF(AND($F13<=L$2, $H13>=L$2), 2, "" ))) | M13: =IF(AND($F13<(M$2+7),$F13>M$2),1, IF(AND($H13<M$2+7,$H13>M$2),3, IF(AND($F13<=M$2, $H13>=M$2), 2, "" ))) | N13: =IF(AND($F13<(N$2+7),$F13>N$2),1, IF(AND($H13<N$2+7,$H13>N$2),3, IF(AND($F13<=N$2, $H13>=N$2), 2, "" ))) | O13: =IF(AND($F13<(O$2+7),$F13>O$2),1, IF(AND($H13<O$2+7,$H13>O$2),3, IF(AND($F13<=O$2, $H13>=O$2), 2, "" ))) | P13: =IF(AND($F13<(P$2+7),$F13>P$2),1, IF(AND($H13<P$2+7,$H13>P$2),3, IF(AND($F13<=P$2, $H13>=P$2), 2, "" ))) | Q13: =IF(AND($F13<(Q$2+7),$F13>Q$2),1, IF(AND($H13<Q$2+7,$H13>Q$2),3, IF(AND($F13<=Q$2, $H13>=Q$2), 2, "" ))) | R13: =IF(AND($F13<(R$2+7),$F13>R$2),1, IF(AND($H13<R$2+7,$H13>R$2),3, IF(AND($F13<=R$2, $H13>=R$2), 2, "" ))) | S13: =IF(AND($F13<(S$2+7),$F13>S$2),1, IF(AND($H13<S$2+7,$H13>S$2),3, IF(AND($F13<=S$2, $H13>=S$2), 2, "" ))) | ... AQ13: =IF(AND($F13<(AQ$2+7),$F13>AQ$2),1, IF(AND($H13<AQ$2+7,$H13>AQ$2),3, IF(AND($F13<=AQ$2, $H13>=AQ$2), 2, "" )))
A14: 7 | B14: Equipment Delivery | C14: 43983 | D14: 9 | E14: 43994 | F14: 43983 | G14: 9 | H14: 43994 | L14: =IF(AND($F14<(L$2+7),$F14>L$2),1, IF(AND($H14<L$2+7,$H14>L$2),3, IF(AND($F14<=L$2, $H14>=L$2), 2, "" ))) | M14: =IF(AND($F14<(M$2+7),$F14>M$2),1, IF(AND($H14<M$2+7,$H14>M$2),3, IF(AND($F14<=M$2, $H14>=M$2), 2, "" ))) | N14: =IF(AND($F14<(N$2+7),$F14>N$2),1, IF(AND($H14<N$2+7,$H14>N$2),3, IF(AND($F14<=N$2, $H14>=N$2), 2, "" ))) | O14: =IF(AND($F14<(O$2+7),$F14>O$2),1, IF(AND($H14<O$2+7,$H14>O$2),3, IF(AND($F14<=O$2, $H14>=O$2), 2, "" ))) | P14: =IF(AND($F14<(P$2+7),$F14>P$2),1, IF(AND($H14<P$2+7,$H14>P$2),3, IF(AND($F14<=P$2, $H14>=P$2), 2, "" ))) | Q14: =IF(AND($F14<(Q$2+7),$F14>Q$2),1, IF(AND($H14<Q$2+7,$H14>Q$2),3, IF(AND($F14<=Q$2, $H14>=Q$2), 2, "" ))) | R14: =IF(AND($F14<(R$2+7),$F14>R$2),1, IF(AND($H14<R$2+7,$H14>R$2),3, IF(AND($F14<=R$2, $H14>=R$2), 2, "" ))) | S14: =IF(AND($F14<(S$2+7),$F14>S$2),1, IF(AND($H14<S$2+7,$H14>S$2),3, IF(AND($F14<=S$2, $H14>=S$2), 2, "" ))) | ... AQ14: =IF(AND($F14<(AQ$2+7),$F14>AQ$2),1, IF(AND($H14<AQ$2+7,$H14>AQ$2),3, IF(AND($F14<=AQ$2, $H14>=AQ$2), 2, "" )))
B15: Mounting Structure Delivery | C15: 43983 | D15: 2 | E15: 43985 | F15: 43983 | G15: 2 | H15: 43985
B16: Panel Delivery | C16: 43990 | D16: 2 | E16: 43992 | F16: 43990 | G16: 2 | H16: 43992 | L16: =IF(AND($F16<(L$2+7),$F16>L$2),1, IF(AND($H16<L$2+7,$H16>L$2),3, IF(AND($F16<=L$2, $H16>=L$2), 2, "" ))) | M16: =IF(AND($F16<(M$2+7),$F16>M$2),1, IF(AND($H16<M$2+7,$H16>M$2),3, IF(AND($F16<=M$2, $H16>=M$2), 2, "" ))) | N16: =IF(AND($F16<(N$2+7),$F16>N$2),1, IF(AND($H16<N$2+7,$H16>N$2),3, IF(AND($F16<=N$2, $H16>=N$2), 2, "" ))) | O16: =IF(AND($F16<(O$2+7),$F16>O$2),1, IF(AND($H16<O$2+7,$H16>O$2),3, IF(AND($F16<=O$2, $H16>=O$2), 2, "" ))) | P16: =IF(AND($F16<(P$2+7),$F16>P$2),1, IF(AND($H16<P$2+7,$H16>P$2),3, IF(AND($F16<=P$2, $H16>=P$2), 2, "" ))) | Q16: =IF(AND($F16<(Q$2+7),$F16>Q$2),1, IF(AND($H16<Q$2+7,$H16>Q$2),3, IF(AND($F16<=Q$2, $H16>=Q$2), 2, "" ))) | R16: =IF(AND($F16<(R$2+7),$F16>R$2),1, IF(AND($H16<R$2+7,$H16>R$2),3, IF(AND($F16<=R$2, $H16>=R$2), 2, "" ))) | S16: =IF(AND($F16<(S$2+7),$F16>S$2),1, IF(AND($H16<S$2+7,$H16>S$2),3, IF(AND($F16<=S$2, $H16>=S$2), 2, "" ))) | ... AQ16: =IF(AND($F16<(AQ$2+7),$F16>AQ$2),1, IF(AND($H16<AQ$2+7,$H16>AQ$2),3, IF(AND($F16<=AQ$2, $H16>=AQ$2), 2, "" )))
B17: Generator Delivery | C17: 43983 | D17: 2 | E17: 43985 | F17: 43983 | G17: 2 | H17: 43985
A18: B | B18: PAYMENT MILESTONE 2: DELIVERY OF PV PANELS | C18: 43992 | D18: 2 | E18: 43994 | F18: 43992 | G18: 2 | H18: 43994
B19: Inverter Delivery | C19: 43983 | D19: 2 | E19: 43985 | F19: 43983 | G19: 2 | H19: 43985 | L19: =IF(AND($F19<(L$2+7),$F19>L$2),1, IF(AND($H19<L$2+7,$H19>L$2),3, IF(AND($F19<=L$2, $H19>=L$2), 2, "" ))) | M19: =IF(AND($F19<(M$2+7),$F19>M$2),1, IF(AND($H19<M$2+7,$H19>M$2),3, IF(AND($F19<=M$2, $H19>=M$2), 2, "" ))) | N19: =IF(AND($F19<(N$2+7),$F19>N$2),1, IF(AND($H19<N$2+7,$H19>N$2),3, IF(AND($F19<=N$2, $H19>=N$2), 2, "" ))) | O19: =IF(AND($F19<(O$2+7),$F19>O$2),1, IF(AND($H19<O$2+7,$H19>O$2),3, IF(AND($F19<=O$2, $H19>=O$2), 2, "" ))) | P19: =IF(AND($F19<(P$2+7),$F19>P$2),1, IF(AND($H19<P$2+7,$H19>P$2),3, IF(AND($F19<=P$2, $H19>=P$2), 2, "" ))) | Q19: =IF(AND($F19<(Q$2+7),$F19>Q$2),1, IF(AND($H19<Q$2+7,$H19>Q$2),3, IF(AND($F19<=Q$2, $H19>=Q$2), 2, "" ))) | R19: =IF(AND($F19<(R$2+7),$F19>R$2),1, IF(AND($H19<R$2+7,$H19>R$2),3, IF(AND($F19<=R$2, $H19>=R$2), 2, "" ))) | S19: =IF(AND($F19<(S$2+7),$F19>S$2),1, IF(AND($H19<S$2+7,$H19>S$2),3, IF(AND($F19<=S$2, $H19>=S$2), 2, "" ))) | ... AQ19: =IF(AND($F19<(AQ$2+7),$F19>AQ$2),1, IF(AND($H19<AQ$2+7,$H19>AQ$2),3, IF(AND($F19<=AQ$2, $H19>=AQ$2), 2, "" )))
B20: BOS Delivery | C20: 43983 | D20: 1 | E20: 43984 | F20: 43983 | G20: 1 | H20: 43984 | L20: =IF(AND($F20<(L$2+7),$F20>L$2),1, IF(AND($H20<L$2+7,$H20>L$2),3, IF(AND($F20<=L$2, $H20>=L$2), 2, "" ))) | M20: =IF(AND($F20<(M$2+7),$F20>M$2),1, IF(AND($H20<M$2+7,$H20>M$2),3, IF(AND($F20<=M$2, $H20>=M$2), 2, "" ))) | N20: =IF(AND($F20<(N$2+7),$F20>N$2),1, IF(AND($H20<N$2+7,$H20>N$2),3, IF(AND($F20<=N$2, $H20>=N$2), 2, "" ))) | O20: =IF(AND($F20<(O$2+7),$F20>O$2),1, IF(AND($H20<O$2+7,$H20>O$2),3, IF(AND($F20<=O$2, $H20>=O$2), 2, "" ))) | P20: =IF(AND($F20<(P$2+7),$F20>P$2),1, IF(AND($H20<P$2+7,$H20>P$2),3, IF(AND($F20<=P$2, $H20>=P$2), 2, "" ))) | Q20: =IF(AND($F20<(Q$2+7),$F20>Q$2),1, IF(AND($H20<Q$2+7,$H20>Q$2),3, IF(AND($F20<=Q$2, $H20>=Q$2), 2, "" ))) | R20: =IF(AND($F20<(R$2+7),$F20>R$2),1, IF(AND($H20<R$2+7,$H20>R$2),3, IF(AND($F20<=R$2, $H20>=R$2), 2, "" ))) | S20: =IF(AND($F20<(S$2+7),$F20>S$2),1, IF(AND($H20<S$2+7,$H20>S$2),3, IF(AND($F20<=S$2, $H20>=S$2), 2, "" ))) | ... AQ20: =IF(AND($F20<(AQ$2+7),$F20>AQ$2),1, IF(AND($H20<AQ$2+7,$H20>AQ$2),3, IF(AND($F20<=AQ$2, $H20>=AQ$2), 2, "" )))
A21: C | B21: PAYMENT MILESTONE 3: DELIVERY OF INVERTERS AND BOS | C21: 43985 | D21: 2 | E21: 43987 | F21: 43985 | G21: 2 | H21: 43987
A22: 8 | B22: Installation | C22: 43990 | D22: 22 | E22: 44012 | F22: 43990 | G22: 22 | H22: 44012 | L22: =IF(AND($F22<(L$2+7),$F22>L$2),1, IF(AND($H22<L$2+7,$H22>L$2),3, IF(AND($F22<=L$2, $H22>=L$2), 2, "" ))) | M22: =IF(AND($F22<(M$2+7),$F22>M$2),1, IF(AND($H22<M$2+7,$H22>M$2),3, IF(AND($F22<=M$2, $H22>=M$2), 2, "" ))) | N22: =IF(AND($F22<(N$2+7),$F22>N$2),1, IF(AND($H22<N$2+7,$H22>N$2),3, IF(AND($F22<=N$2, $H22>=N$2), 2, "" ))) | O22: =IF(AND($F22<(O$2+7),$F22>O$2),1, IF(AND($H22<O$2+7,$H22>O$2),3, IF(AND($F22<=O$2, $H22>=O$2), 2, "" ))) | P22: =IF(AND($F22<(P$2+7),$F22>P$2),1, IF(AND($H22<P$2+7,$H22>P$2),3, IF(AND($F22<=P$2, $H22>=P$2), 2, "" ))) | Q22: =IF(AND($F22<(Q$2+7),$F22>Q$2),1, IF(AND($H22<Q$2+7,$H22>Q$2),3, IF(AND($F22<=Q$2, $H22>=Q$2), 2, "" ))) | R22: =IF(AND($F22<(R$2+7),$F22>R$2),1, IF(AND($H22<R$2+7,$H22>R$2),3, IF(AND($F22<=R$2, $H22>=R$2), 2, "" ))) | S22: =IF(AND($F22<(S$2+7),$F22>S$2),1, IF(AND($H22<S$2+7,$H22>S$2),3, IF(AND($F22<=S$2, $H22>=S$2), 2, "" ))) | ... AQ22: =IF(AND($F22<(AQ$2+7),$F22>AQ$2),1, IF(AND($H22<AQ$2+7,$H22>AQ$2),3, IF(AND($F22<=AQ$2, $H22>=AQ$2), 2, "" ))) -> 2
B23: Site Establishment | C23: 43990 | D23: 1 | E23: 43991 | F23: 43990 | G23: 1 | H23: 43991 | J23: Installation placed on hold due to Covid-19 case | L23: =IF(AND($F23<(L$2+7),$F23>L$2),1, IF(AND($H23<L$2+7,$H23>L$2),3, IF(AND($F23<=L$2, $H23>=L$2), 2, "" ))) | M23: =IF(AND($F23<(M$2+7),$F23>M$2),1, IF(AND($H23<M$2+7,$H23>M$2),3, IF(AND($F23<=M$2, $H23>=M$2), 2, "" ))) | N23: =IF(AND($F23<(N$2+7),$F23>N$2),1, IF(AND($H23<N$2+7,$H23>N$2),3, IF(AND($F23<=N$2, $H23>=N$2), 2, "" ))) | O23: =IF(AND($F23<(O$2+7),$F23>O$2),1, IF(AND($H23<O$2+7,$H23>O$2),3, IF(AND($F23<=O$2, $H23>=O$2), 2, "" ))) | P23: =IF(AND($F23<(P$2+7),$F23>P$2),1, IF(AND($H23<P$2+7,$H23>P$2),3, IF(AND($F23<=P$2, $H23>=P$2), 2, "" ))) | Q23: =IF(AND($F23<(Q$2+7),$F23>Q$2),1, IF(AND($H23<Q$2+7,$H23>Q$2),3, IF(AND($F23<=Q$2, $H23>=Q$2), 2, "" ))) | R23: =IF(AND($F23<(R$2+7),$F23>R$2),1, IF(AND($H23<R$2+7,$H23>R$2),3, IF(AND($F23<=R$2, $H23>=R$2), 2, "" ))) | S23: =IF(AND($F23<(S$2+7),$F23>S$2),1, IF(AND($H23<S$2+7,$H23>S$2),3, IF(AND($F23<=S$2, $H23>=S$2), 2, "" ))) | ... AQ23: =IF(AND($F23<(AQ$2+7),$F23>AQ$2),1, IF(AND($H23<AQ$2+7,$H23>AQ$2),3, IF(AND($F23<=AQ$2, $H23>=AQ$2), 2, "" )))
A24: 9 | B24: DC Works | C24: 43991 | D24: 16 | E24: 44012 | F24: 43991 | G24: 16 | H24: 44012 | L24: =IF(AND($F24<(L$2+7),$F24>L$2),1, IF(AND($H24<L$2+7,$H24>L$2),3, IF(AND($F24<=L$2, $H24>=L$2), 2, "" ))) | M24: =IF(AND($F24<(M$2+7),$F24>M$2),1, IF(AND($H24<M$2+7,$H24>M$2),3, IF(AND($F24<=M$2, $H24>=M$2), 2, "" ))) | N24: =IF(AND($F24<(N$2+7),$F24>N$2),1, IF(AND($H24<N$2+7,$H24>N$2),3, IF(AND($F24<=N$2, $H24>=N$2), 2, "" ))) | O24: =IF(AND($F24<(O$2+7),$F24>O$2),1, IF(AND($H24<O$2+7,$H24>O$2),3, IF(AND($F24<=O$2, $H24>=O$2), 2, "" ))) | P24: =IF(AND($F24<(P$2+7),$F24>P$2),1, IF(AND($H24<P$2+7,$H24>P$2),3, IF(AND($F24<=P$2, $H24>=P$2), 2, "" ))) | Q24: =IF(AND($F24<(Q$2+7),$F24>Q$2),1, IF(AND($H24<Q$2+7,$H24>Q$2),3, IF(AND($F24<=Q$2, $H24>=Q$2), 2, "" ))) | R24: =IF(AND($F24<(R$2+7),$F24>R$2),1, IF(AND($H24<R$2+7,$H24>R$2),3, IF(AND($F24<=R$2, $H24>=R$2), 2, "" ))) | S24: =IF(AND($F24<(S$2+7),$F24>S$2),1, IF(AND($H24<S$2+7,$H24>S$2),3, IF(AND($F24<=S$2, $H24>=S$2), 2, "" ))) | ... AQ24: =IF(AND($F24<(AQ$2+7),$F24>AQ$2),1, IF(AND($H24<AQ$2+7,$H24>AQ$2),3, IF(AND($F24<=AQ$2, $H24>=AQ$2), 2, "" ))) -> 2
B25: Mounting structure Installation | C25: 43991 | D25: 4 | E25: 43997 | F25: 43991 | G25: 4 | H25: 43997 | L25: =IF(AND($F25<(L$2+7),$F25>L$2),1, IF(AND($H25<L$2+7,$H25>L$2),3, IF(AND($F25<=L$2, $H25>=L$2), 2, "" ))) | M25: =IF(AND($F25<(M$2+7),$F25>M$2),1, IF(AND($H25<M$2+7,$H25>M$2),3, IF(AND($F25<=M$2, $H25>=M$2), 2, "" ))) | N25: =IF(AND($F25<(N$2+7),$F25>N$2),1, IF(AND($H25<N$2+7,$H25>N$2),3, IF(AND($F25<=N$2, $H25>=N$2), 2, "" ))) | O25: =IF(AND($F25<(O$2+7),$F25>O$2),1, IF(AND($H25<O$2+7,$H25>O$2),3, IF(AND($F25<=O$2, $H25>=O$2), 2, "" ))) | P25: =IF(AND($F25<(P$2+7),$F25>P$2),1, IF(AND($H25<P$2+7,$H25>P$2),3, IF(AND($F25<=P$2, $H25>=P$2), 2, "" ))) | Q25: =IF(AND($F25<(Q$2+7),$F25>Q$2),1, IF(AND($H25<Q$2+7,$H25>Q$2),3, IF(AND($F25<=Q$2, $H25>=Q$2), 2, "" ))) | R25: =IF(AND($F25<(R$2+7),$F25>R$2),1, IF(AND($H25<R$2+7,$H25>R$2),3, IF(AND($F25<=R$2, $H25>=R$2), 2, "" ))) | S25: =IF(AND($F25<(S$2+7),$F25>S$2),1, IF(AND($H25<S$2+7,$H25>S$2),3, IF(AND($F25<=S$2, $H25>=S$2), 2, "" ))) | ... AQ25: =IF(AND($F25<(AQ$2+7),$F25>AQ$2),1, IF(AND($H25<AQ$2+7,$H25>AQ$2),3, IF(AND($F25<=AQ$2, $H25>=AQ$2), 2, "" )))
B26: Cable tray Installation | C26: 43997 | D26: 3 | E26: 44004 | F26: 43997 | G26: 3 | H26: 44004 | L26: =IF(AND($F26<(L$2+7),$F26>L$2),1, IF(AND($H26<L$2+7,$H26>L$2),3, IF(AND($F26<=L$2, $H26>=L$2), 2, "" ))) | M26: =IF(AND($F26<(M$2+7),$F26>M$2),1, IF(AND($H26<M$2+7,$H26>M$2),3, IF(AND($F26<=M$2, $H26>=M$2), 2, "" ))) | N26: =IF(AND($F26<(N$2+7),$F26>N$2),1, IF(AND($H26<N$2+7,$H26>N$2),3, IF(AND($F26<=N$2, $H26>=N$2), 2, "" ))) | O26: =IF(AND($F26<(O$2+7),$F26>O$2),1, IF(AND($H26<O$2+7,$H26>O$2),3, IF(AND($F26<=O$2, $H26>=O$2), 2, "" ))) | P26: =IF(AND($F26<(P$2+7),$F26>P$2),1, IF(AND($H26<P$2+7,$H26>P$2),3, IF(AND($F26<=P$2, $H26>=P$2), 2, "" ))) | Q26: =IF(AND($F26<(Q$2+7),$F26>Q$2),1, IF(AND($H26<Q$2+7,$H26>Q$2),3, IF(AND($F26<=Q$2, $H26>=Q$2), 2, "" ))) | R26: =IF(AND($F26<(R$2+7),$F26>R$2),1, IF(AND($H26<R$2+7,$H26>R$2),3, IF(AND($F26<=R$2, $H26>=R$2), 2, "" ))) | S26: =IF(AND($F26<(S$2+7),$F26>S$2),1, IF(AND($H26<S$2+7,$H26>S$2),3, IF(AND($F26<=S$2, $H26>=S$2), 2, "" ))) | ... AQ26: =IF(AND($F26<(AQ$2+7),$F26>AQ$2),1, IF(AND($H26<AQ$2+7,$H26>AQ$2),3, IF(AND($F26<=AQ$2, $H26>=AQ$2), 2, "" )))
B27: DC Cable Installation | C27: 44004 | D27: 2 | E27: 44006 | F27: 44004 | G27: 2 | H27: 44006 | L27: =IF(AND($F27<(L$2+7),$F27>L$2),1, IF(AND($H27<L$2+7,$H27>L$2),3, IF(AND($F27<=L$2, $H27>=L$2), 2, "" ))) | M27: =IF(AND($F27<(M$2+7),$F27>M$2),1, IF(AND($H27<M$2+7,$H27>M$2),3, IF(AND($F27<=M$2, $H27>=M$2), 2, "" ))) | N27: =IF(AND($F27<(N$2+7),$F27>N$2),1, IF(AND($H27<N$2+7,$H27>N$2),3, IF(AND($F27<=N$2, $H27>=N$2), 2, "" ))) | O27: =IF(AND($F27<(O$2+7),$F27>O$2),1, IF(AND($H27<O$2+7,$H27>O$2),3, IF(AND($F27<=O$2, $H27>=O$2), 2, "" ))) | P27: =IF(AND($F27<(P$2+7),$F27>P$2),1, IF(AND($H27<P$2+7,$H27>P$2),3, IF(AND($F27<=P$2, $H27>=P$2), 2, "" ))) | Q27: =IF(AND($F27<(Q$2+7),$F27>Q$2),1, IF(AND($H27<Q$2+7,$H27>Q$2),3, IF(AND($F27<=Q$2, $H27>=Q$2), 2, "" ))) | R27: =IF(AND($F27<(R$2+7),$F27>R$2),1, IF(AND($H27<R$2+7,$H27>R$2),3, IF(AND($F27<=R$2, $H27>=R$2), 2, "" ))) | S27: =IF(AND($F27<(S$2+7),$F27>S$2),1, IF(AND($H27<S$2+7,$H27>S$2),3, IF(AND($F27<=S$2, $H27>=S$2), 2, "" ))) | ... AQ27: =IF(AND($F27<(AQ$2+7),$F27>AQ$2),1, IF(AND($H27<AQ$2+7,$H27>AQ$2),3, IF(AND($F27<=AQ$2, $H27>=AQ$2), 2, "" )))
B28: Module Installation | C28: 44006 | D28: 4 | E28: 44012 | F28: 44006 | G28: 4 | H28: 44012 | L28: =IF(AND($F28<(L$2+7),$F28>L$2),1, IF(AND($H28<L$2+7,$H28>L$2),3, IF(AND($F28<=L$2, $H28>=L$2), 2, "" ))) | M28: =IF(AND($F28<(M$2+7),$F28>M$2),1, IF(AND($H28<M$2+7,$H28>M$2),3, IF(AND($F28<=M$2, $H28>=M$2), 2, "" ))) | N28: =IF(AND($F28<(N$2+7),$F28>N$2),1, IF(AND($H28<N$2+7,$H28>N$2),3, IF(AND($F28<=N$2, $H28>=N$2), 2, "" ))) | O28: =IF(AND($F28<(O$2+7),$F28>O$2),1, IF(AND($H28<O$2+7,$H28>O$2),3, IF(AND($F28<=O$2, $H28>=O$2), 2, "" ))) | P28: =IF(AND($F28<(P$2+7),$F28>P$2),1, IF(AND($H28<P$2+7,$H28>P$2),3, IF(AND($F28<=P$2, $H28>=P$2), 2, "" ))) | Q28: =IF(AND($F28<(Q$2+7),$F28>Q$2),1, IF(AND($H28<Q$2+7,$H28>Q$2),3, IF(AND($F28<=Q$2, $H28>=Q$2), 2, "" ))) | R28: =IF(AND($F28<(R$2+7),$F28>R$2),1, IF(AND($H28<R$2+7,$H28>R$2),3, IF(AND($F28<=R$2, $H28>=R$2), 2, "" ))) | S28: =IF(AND($F28<(S$2+7),$F28>S$2),1, IF(AND($H28<S$2+7,$H28>S$2),3, IF(AND($F28<=S$2, $H28>=S$2), 2, "" ))) | ... AQ28: =IF(AND($F28<(AQ$2+7),$F28>AQ$2),1, IF(AND($H28<AQ$2+7,$H28>AQ$2),3, IF(AND($F28<=AQ$2, $H28>=AQ$2), 2, "" ))) -> 2
B29: Earth Cable Installation | C29: 44004 | D29: 1 | E29: 44005 | F29: 44004 | G29: 1 | H29: 44005 | L29: =IF(AND($F29<(L$2+7),$F29>L$2),1, IF(AND($H29<L$2+7,$H29>L$2),3, IF(AND($F29<=L$2, $H29>=L$2), 2, "" ))) | M29: =IF(AND($F29<(M$2+7),$F29>M$2),1, IF(AND($H29<M$2+7,$H29>M$2),3, IF(AND($F29<=M$2, $H29>=M$2), 2, "" ))) | N29: =IF(AND($F29<(N$2+7),$F29>N$2),1, IF(AND($H29<N$2+7,$H29>N$2),3, IF(AND($F29<=N$2, $H29>=N$2), 2, "" ))) | O29: =IF(AND($F29<(O$2+7),$F29>O$2),1, IF(AND($H29<O$2+7,$H29>O$2),3, IF(AND($F29<=O$2, $H29>=O$2), 2, "" ))) | P29: =IF(AND($F29<(P$2+7),$F29>P$2),1, IF(AND($H29<P$2+7,$H29>P$2),3, IF(AND($F29<=P$2, $H29>=P$2), 2, "" ))) | Q29: =IF(AND($F29<(Q$2+7),$F29>Q$2),1, IF(AND($H29<Q$2+7,$H29>Q$2),3, IF(AND($F29<=Q$2, $H29>=Q$2), 2, "" ))) | R29: =IF(AND($F29<(R$2+7),$F29>R$2),1, IF(AND($H29<R$2+7,$H29>R$2),3, IF(AND($F29<=R$2, $H29>=R$2), 2, "" ))) | S29: =IF(AND($F29<(S$2+7),$F29>S$2),1, IF(AND($H29<S$2+7,$H29>S$2),3, IF(AND($F29<=S$2, $H29>=S$2), 2, "" ))) | ... AQ29: =IF(AND($F29<(AQ$2+7),$F29>AQ$2),1, IF(AND($H29<AQ$2+7,$H29>AQ$2),3, IF(AND($F29<=AQ$2, $H29>=AQ$2), 2, "" )))
A30: 10 | B30: AC Works | C30: 43991 | D30: 8 | E30: 44000 | F30: 43991 | G30: 8 | H30: 44000
B31: Inverters Installation | C31: 43991 | D31: 2 | E31: 43993 | F31: 43991 | G31: 2 | H31: 43993 | L31: =IF(AND($F31<(L$2+7),$F31>L$2),1, IF(AND($H31<L$2+7,$H31>L$2),3, IF(AND($F31<=L$2, $H31>=L$2), 2, "" ))) | M31: =IF(AND($F31<(M$2+7),$F31>M$2),1, IF(AND($H31<M$2+7,$H31>M$2),3, IF(AND($F31<=M$2, $H31>=M$2), 2, "" ))) | N31: =IF(AND($F31<(N$2+7),$F31>N$2),1, IF(AND($H31<N$2+7,$H31>N$2),3, IF(AND($F31<=N$2, $H31>=N$2), 2, "" ))) | O31: =IF(AND($F31<(O$2+7),$F31>O$2),1, IF(AND($H31<O$2+7,$H31>O$2),3, IF(AND($F31<=O$2, $H31>=O$2), 2, "" ))) | P31: =IF(AND($F31<(P$2+7),$F31>P$2),1, IF(AND($H31<P$2+7,$H31>P$2),3, IF(AND($F31<=P$2, $H31>=P$2), 2, "" ))) | Q31: =IF(AND($F31<(Q$2+7),$F31>Q$2),1, IF(AND($H31<Q$2+7,$H31>Q$2),3, IF(AND($F31<=Q$2, $H31>=Q$2), 2, "" ))) | R31: =IF(AND($F31<(R$2+7),$F31>R$2),1, IF(AND($H31<R$2+7,$H31>R$2),3, IF(AND($F31<=R$2, $H31>=R$2), 2, "" ))) | S31: =IF(AND($F31<(S$2+7),$F31>S$2),1, IF(AND($H31<S$2+7,$H31>S$2),3, IF(AND($F31<=S$2, $H31>=S$2), 2, "" ))) | ... AQ31: =IF(AND($F31<(AQ$2+7),$F31>AQ$2),1, IF(AND($H31<AQ$2+7,$H31>AQ$2),3, IF(AND($F31<=AQ$2, $H31>=AQ$2), 2, "" )))
B32: AC BOS Installation | C32: 43993 | D32: 3 | E32: 44000 | F32: 43993 | G32: 3 | H32: 44000 | L32: =IF(AND($F32<(L$2+7),$F32>L$2),1, IF(AND($H32<L$2+7,$H32>L$2),3, IF(AND($F32<=L$2, $H32>=L$2), 2, "" ))) | M32: =IF(AND($F32<(M$2+7),$F32>M$2),1, IF(AND($H32<M$2+7,$H32>M$2),3, IF(AND($F32<=M$2, $H32>=M$2), 2, "" ))) | N32: =IF(AND($F32<(N$2+7),$F32>N$2),1, IF(AND($H32<N$2+7,$H32>N$2),3, IF(AND($F32<=N$2, $H32>=N$2), 2, "" ))) | O32: =IF(AND($F32<(O$2+7),$F32>O$2),1, IF(AND($H32<O$2+7,$H32>O$2),3, IF(AND($F32<=O$2, $H32>=O$2), 2, "" ))) | P32: =IF(AND($F32<(P$2+7),$F32>P$2),1, IF(AND($H32<P$2+7,$H32>P$2),3, IF(AND($F32<=P$2, $H32>=P$2), 2, "" ))) | Q32: =IF(AND($F32<(Q$2+7),$F32>Q$2),1, IF(AND($H32<Q$2+7,$H32>Q$2),3, IF(AND($F32<=Q$2, $H32>=Q$2), 2, "" ))) | R32: =IF(AND($F32<(R$2+7),$F32>R$2),1, IF(AND($H32<R$2+7,$H32>R$2),3, IF(AND($F32<=R$2, $H32>=R$2), 2, "" ))) | S32: =IF(AND($F32<(S$2+7),$F32>S$2),1, IF(AND($H32<S$2+7,$H32>S$2),3, IF(AND($F32<=S$2, $H32>=S$2), 2, "" ))) | ... AQ32: =IF(AND($F32<(AQ$2+7),$F32>AQ$2),1, IF(AND($H32<AQ$2+7,$H32>AQ$2),3, IF(AND($F32<=AQ$2, $H32>=AQ$2), 2, "" )))
B33: AC Cable/Tie-In | C33: 43992 | D33: 3 | E33: 43997 | F33: 43992 | G33: 3 | H33: 43997 | L33: =IF(AND($F33<(L$2+7),$F33>L$2),1, IF(AND($H33<L$2+7,$H33>L$2),3, IF(AND($F33<=L$2, $H33>=L$2), 2, "" ))) | M33: =IF(AND($F33<(M$2+7),$F33>M$2),1, IF(AND($H33<M$2+7,$H33>M$2),3, IF(AND($F33<=M$2, $H33>=M$2), 2, "" ))) | N33: =IF(AND($F33<(N$2+7),$F33>N$2),1, IF(AND($H33<N$2+7,$H33>N$2),3, IF(AND($F33<=N$2, $H33>=N$2), 2, "" ))) | O33: =IF(AND($F33<(O$2+7),$F33>O$2),1, IF(AND($H33<O$2+7,$H33>O$2),3, IF(AND($F33<=O$2, $H33>=O$2), 2, "" ))) | P33: =IF(AND($F33<(P$2+7),$F33>P$2),1, IF(AND($H33<P$2+7,$H33>P$2),3, IF(AND($F33<=P$2, $H33>=P$2), 2, "" ))) | Q33: =IF(AND($F33<(Q$2+7),$F33>Q$2),1, IF(AND($H33<Q$2+7,$H33>Q$2),3, IF(AND($F33<=Q$2, $H33>=Q$2), 2, "" ))) | R33: =IF(AND($F33<(R$2+7),$F33>R$2),1, IF(AND($H33<R$2+7,$H33>R$2),3, IF(AND($F33<=R$2, $H33>=R$2), 2, "" ))) | S33: =IF(AND($F33<(S$2+7),$F33>S$2),1, IF(AND($H33<S$2+7,$H33>S$2),3, IF(AND($F33<=S$2, $H33>=S$2), 2, "" ))) | ... AQ33: =IF(AND($F33<(AQ$2+7),$F33>AQ$2),1, IF(AND($H33<AQ$2+7,$H33>AQ$2),3, IF(AND($F33<=AQ$2, $H33>=AQ$2), 2, "" )))
B34: Monitoring Platform Installation | C34: 43997 | D34: 1 | E34: 44000 | F34: 43997 | G34: 1 | H34: 44000
A35: 11 | B35: Completion | C35: 44000 | D35: 14 | E35: 44014 | F35: 44000 | G35: 14 | H35: 44014 | L35: =IF(AND($F35<(L$2+7),$F35>L$2),1, IF(AND($H35<L$2+7,$H35>L$2),3, IF(AND($F35<=L$2, $H35>=L$2), 2, "" ))) | M35: =IF(AND($F35<(M$2+7),$F35>M$2),1, IF(AND($H35<M$2+7,$H35>M$2),3, IF(AND($F35<=M$2, $H35>=M$2), 2, "" ))) | N35: =IF(AND($F35<(N$2+7),$F35>N$2),1, IF(AND($H35<N$2+7,$H35>N$2),3, IF(AND($F35<=N$2, $H35>=N$2), 2, "" ))) | O35: =IF(AND($F35<(O$2+7),$F35>O$2),1, IF(AND($H35<O$2+7,$H35>O$2),3, IF(AND($F35<=O$2, $H35>=O$2), 2, "" ))) | P35: =IF(AND($F35<(P$2+7),$F35>P$2),1, IF(AND($H35<P$2+7,$H35>P$2),3, IF(AND($F35<=P$2, $H35>=P$2), 2, "" ))) | Q35: =IF(AND($F35<(Q$2+7),$F35>Q$2),1, IF(AND($H35<Q$2+7,$H35>Q$2),3, IF(AND($F35<=Q$2, $H35>=Q$2), 2, "" ))) | R35: =IF(AND($F35<(R$2+7),$F35>R$2),1, IF(AND($H35<R$2+7,$H35>R$2),3, IF(AND($F35<=R$2, $H35>=R$2), 2, "" ))) | S35: =IF(AND($F35<(S$2+7),$F35>S$2),1, IF(AND($H35<S$2+7,$H35>S$2),3, IF(AND($F35<=S$2, $H35>=S$2), 2, "" ))) | ... AQ35: =IF(AND($F35<(AQ$2+7),$F35>AQ$2),1, IF(AND($H35<AQ$2+7,$H35>AQ$2),3, IF(AND($F35<=AQ$2, $H35>=AQ$2), 2, "" ))) -> 3
B36: DC Works | C36: 44012 | D36: 2 | E36: 44014 | F36: 44012 | G36: 2 | H36: 44014 | L36: =IF(AND($F36<(L$2+7),$F36>L$2),1, IF(AND($H36<L$2+7,$H36>L$2),3, IF(AND($F36<=L$2, $H36>=L$2), 2, "" ))) | M36: =IF(AND($F36<(M$2+7),$F36>M$2),1, IF(AND($H36<M$2+7,$H36>M$2),3, IF(AND($F36<=M$2, $H36>=M$2), 2, "" ))) | N36: =IF(AND($F36<(N$2+7),$F36>N$2),1, IF(AND($H36<N$2+7,$H36>N$2),3, IF(AND($F36<=N$2, $H36>=N$2), 2, "" ))) | O36: =IF(AND($F36<(O$2+7),$F36>O$2),1, IF(AND($H36<O$2+7,$H36>O$2),3, IF(AND($F36<=O$2, $H36>=O$2), 2, "" ))) | P36: =IF(AND($F36<(P$2+7),$F36>P$2),1, IF(AND($H36<P$2+7,$H36>P$2),3, IF(AND($F36<=P$2, $H36>=P$2), 2, "" ))) | Q36: =IF(AND($F36<(Q$2+7),$F36>Q$2),1, IF(AND($H36<Q$2+7,$H36>Q$2),3, IF(AND($F36<=Q$2, $H36>=Q$2), 2, "" ))) | R36: =IF(AND($F36<(R$2+7),$F36>R$2),1, IF(AND($H36<R$2+7,$H36>R$2),3, IF(AND($F36<=R$2, $H36>=R$2), 2, "" ))) | S36: =IF(AND($F36<(S$2+7),$F36>S$2),1, IF(AND($H36<S$2+7,$H36>S$2),3, IF(AND($F36<=S$2, $H36>=S$2), 2, "" ))) | ... AQ36: =IF(AND($F36<(AQ$2+7),$F36>AQ$2),1, IF(AND($H36<AQ$2+7,$H36>AQ$2),3, IF(AND($F36<=AQ$2, $H36>=AQ$2), 2, "" ))) -> 3
B37: AC Works | C37: 44000 | D37: 2 | E37: 44004 | F37: 44000 | G37: 2 | H37: 44004 | L37: =IF(AND($F37<(L$2+7),$F37>L$2),1, IF(AND($H37<L$2+7,$H37>L$2),3, IF(AND($F37<=L$2, $H37>=L$2), 2, "" ))) | M37: =IF(AND($F37<(M$2+7),$F37>M$2),1, IF(AND($H37<M$2+7,$H37>M$2),3, IF(AND($F37<=M$2, $H37>=M$2), 2, "" ))) | N37: =IF(AND($F37<(N$2+7),$F37>N$2),1, IF(AND($H37<N$2+7,$H37>N$2),3, IF(AND($F37<=N$2, $H37>=N$2), 2, "" ))) | O37: =IF(AND($F37<(O$2+7),$F37>O$2),1, IF(AND($H37<O$2+7,$H37>O$2),3, IF(AND($F37<=O$2, $H37>=O$2), 2, "" ))) | P37: =IF(AND($F37<(P$2+7),$F37>P$2),1, IF(AND($H37<P$2+7,$H37>P$2),3, IF(AND($F37<=P$2, $H37>=P$2), 2, "" ))) | Q37: =IF(AND($F37<(Q$2+7),$F37>Q$2),1, IF(AND($H37<Q$2+7,$H37>Q$2),3, IF(AND($F37<=Q$2, $H37>=Q$2), 2, "" ))) | R37: =IF(AND($F37<(R$2+7),$F37>R$2),1, IF(AND($H37<R$2+7,$H37>R$2),3, IF(AND($F37<=R$2, $H37>=R$2), 2, "" ))) | S37: =IF(AND($F37<(S$2+7),$F37>S$2),1, IF(AND($H37<S$2+7,$H37>S$2),3, IF(AND($F37<=S$2, $H37>=S$2), 2, "" ))) | ... AQ37: =IF(AND($F37<(AQ$2+7),$F37>AQ$2),1, IF(AND($H37<AQ$2+7,$H37>AQ$2),3, IF(AND($F37<=AQ$2, $H37>=AQ$2), 2, "" )))
A38: D | B38: PAYMENT MILESTONE 4: PRACTICAL COMPLETION | C38: 44012 | D38: 1 | E38: 44013 | F38: 44012 | G38: 1 | H38: 44013 | L38: =IF(AND($F38<(L$2+7),$F38>L$2),1, IF(AND($H38<L$2+7,$H38>L$2),3, IF(AND($F38<=L$2, $H38>=L$2), 2, "" ))) | M38: =IF(AND($F38<(M$2+7),$F38>M$2),1, IF(AND($H38<M$2+7,$H38>M$2),3, IF(AND($F38<=M$2, $H38>=M$2), 2, "" ))) | N38: =IF(AND($F38<(N$2+7),$F38>N$2),1, IF(AND($H38<N$2+7,$H38>N$2),3, IF(AND($F38<=N$2, $H38>=N$2), 2, "" ))) | O38: =IF(AND($F38<(O$2+7),$F38>O$2),1, IF(AND($H38<O$2+7,$H38>O$2),3, IF(AND($F38<=O$2, $H38>=O$2), 2, "" ))) | P38: =IF(AND($F38<(P$2+7),$F38>P$2),1, IF(AND($H38<P$2+7,$H38>P$2),3, IF(AND($F38<=P$2, $H38>=P$2), 2, "" ))) | Q38: =IF(AND($F38<(Q$2+7),$F38>Q$2),1, IF(AND($H38<Q$2+7,$H38>Q$2),3, IF(AND($F38<=Q$2, $H38>=Q$2), 2, "" ))) | R38: =IF(AND($F38<(R$2+7),$F38>R$2),1, IF(AND($H38<R$2+7,$H38>R$2),3, IF(AND($F38<=R$2, $H38>=R$2), 2, "" ))) | S38: =IF(AND($F38<(S$2+7),$F38>S$2),1, IF(AND($H38<S$2+7,$H38>S$2),3, IF(AND($F38<=S$2, $H38>=S$2), 2, "" ))) | ... AQ38: =IF(AND($F38<(AQ$2+7),$F38>AQ$2),1, IF(AND($H38<AQ$2+7,$H38>AQ$2),3, IF(AND($F38<=AQ$2, $H38>=AQ$2), 2, "" ))) -> 3
A39: 12 | B39: Commissioning | C39: 43997 | D39: 22 | E39: 44019 | F39: 43997 | G39: 22 | H39: 44019 | L39: =IF(AND($F39<(L$2+7),$F39>L$2),1, IF(AND($H39<L$2+7,$H39>L$2),3, IF(AND($F39<=L$2, $H39>=L$2), 2, "" ))) | M39: =IF(AND($F39<(M$2+7),$F39>M$2),1, IF(AND($H39<M$2+7,$H39>M$2),3, IF(AND($F39<=M$2, $H39>=M$2), 2, "" ))) | N39: =IF(AND($F39<(N$2+7),$F39>N$2),1, IF(AND($H39<N$2+7,$H39>N$2),3, IF(AND($F39<=N$2, $H39>=N$2), 2, "" ))) | O39: =IF(AND($F39<(O$2+7),$F39>O$2),1, IF(AND($H39<O$2+7,$H39>O$2),3, IF(AND($F39<=O$2, $H39>=O$2), 2, "" ))) | P39: =IF(AND($F39<(P$2+7),$F39>P$2),1, IF(AND($H39<P$2+7,$H39>P$2),3, IF(AND($F39<=P$2, $H39>=P$2), 2, "" ))) | Q39: =IF(AND($F39<(Q$2+7),$F39>Q$2),1, IF(AND($H39<Q$2+7,$H39>Q$2),3, IF(AND($F39<=Q$2, $H39>=Q$2), 2, "" ))) | R39: =IF(AND($F39<(R$2+7),$F39>R$2),1, IF(AND($H39<R$2+7,$H39>R$2),3, IF(AND($F39<=R$2, $H39>=R$2), 2, "" ))) | S39: =IF(AND($F39<(S$2+7),$F39>S$2),1, IF(AND($H39<S$2+7,$H39>S$2),3, IF(AND($F39<=S$2, $H39>=S$2), 2, "" ))) | ... AQ39: =IF(AND($F39<(AQ$2+7),$F39>AQ$2),1, IF(AND($H39<AQ$2+7,$H39>AQ$2),3, IF(AND($F39<=AQ$2, $H39>=AQ$2), 2, "" ))) -> 2
B40: Snag List | C40: 44014 | D40: 3 | E40: 44019 | F40: 44014 | G40: 3 | H40: 44019
B41: Pre-Commissioning Checks | C41: 44010 | D41: 2 | E41: 44012 | F41: 44010 | G41: 2 | H41: 44012
B42: Issue CoC | C42: 43997 | D42: 2 | E42: 44001 | F42: 43997 | G42: 2 | H42: 44001 | L42: =IF(AND($F42<(L$2+7),$F42>L$2),1, IF(AND($H42<L$2+7,$H42>L$2),3, IF(AND($F42<=L$2, $H42>=L$2), 2, "" ))) | M42: =IF(AND($F42<(M$2+7),$F42>M$2),1, IF(AND($H42<M$2+7,$H42>M$2),3, IF(AND($F42<=M$2, $H42>=M$2), 2, "" ))) | N42: =IF(AND($F42<(N$2+7),$F42>N$2),1, IF(AND($H42<N$2+7,$H42>N$2),3, IF(AND($F42<=N$2, $H42>=N$2), 2, "" ))) | O42: =IF(AND($F42<(O$2+7),$F42>O$2),1, IF(AND($H42<O$2+7,$H42>O$2),3, IF(AND($F42<=O$2, $H42>=O$2), 2, "" ))) | P42: =IF(AND($F42<(P$2+7),$F42>P$2),1, IF(AND($H42<P$2+7,$H42>P$2),3, IF(AND($F42<=P$2, $H42>=P$2), 2, "" ))) | Q42: =IF(AND($F42<(Q$2+7),$F42>Q$2),1, IF(AND($H42<Q$2+7,$H42>Q$2),3, IF(AND($F42<=Q$2, $H42>=Q$2), 2, "" ))) | R42: =IF(AND($F42<(R$2+7),$F42>R$2),1, IF(AND($H42<R$2+7,$H42>R$2),3, IF(AND($F42<=R$2, $H42>=R$2), 2, "" ))) | S42: =IF(AND($F42<(S$2+7),$F42>S$2),1, IF(AND($H42<S$2+7,$H42>S$2),3, IF(AND($F42<=S$2, $H42>=S$2), 2, "" ))) | ... AQ42: =IF(AND($F42<(AQ$2+7),$F42>AQ$2),1, IF(AND($H42<AQ$2+7,$H42>AQ$2),3, IF(AND($F42<=AQ$2, $H42>=AQ$2), 2, "" )))
B43: Cold Commissioning | C43: 44012 | D43: 1 | E43: 44013 | F43: 44012 | G43: 1 | H43: 44013 | L43: =IF(AND($F43<(L$2+7),$F43>L$2),1, IF(AND($H43<L$2+7,$H43>L$2),3, IF(AND($F43<=L$2, $H43>=L$2), 2, "" ))) | M43: =IF(AND($F43<(M$2+7),$F43>M$2),1, IF(AND($H43<M$2+7,$H43>M$2),3, IF(AND($F43<=M$2, $H43>=M$2), 2, "" ))) | N43: =IF(AND($F43<(N$2+7),$F43>N$2),1, IF(AND($H43<N$2+7,$H43>N$2),3, IF(AND($F43<=N$2, $H43>=N$2), 2, "" ))) | O43: =IF(AND($F43<(O$2+7),$F43>O$2),1, IF(AND($H43<O$2+7,$H43>O$2),3, IF(AND($F43<=O$2, $H43>=O$2), 2, "" ))) | P43: =IF(AND($F43<(P$2+7),$F43>P$2),1, IF(AND($H43<P$2+7,$H43>P$2),3, IF(AND($F43<=P$2, $H43>=P$2), 2, "" ))) | Q43: =IF(AND($F43<(Q$2+7),$F43>Q$2),1, IF(AND($H43<Q$2+7,$H43>Q$2),3, IF(AND($F43<=Q$2, $H43>=Q$2), 2, "" ))) | R43: =IF(AND($F43<(R$2+7),$F43>R$2),1, IF(AND($H43<R$2+7,$H43>R$2),3, IF(AND($F43<=R$2, $H43>=R$2), 2, "" ))) | S43: =IF(AND($F43<(S$2+7),$F43>S$2),1, IF(AND($H43<S$2+7,$H43>S$2),3, IF(AND($F43<=S$2, $H43>=S$2), 2, "" ))) | ... AQ43: =IF(AND($F43<(AQ$2+7),$F43>AQ$2),1, IF(AND($H43<AQ$2+7,$H43>AQ$2),3, IF(AND($F43<=AQ$2, $H43>=AQ$2), 2, "" ))) -> 3
B44: Hot Commissioning | C44: 44013 | D44: 2 | E44: 44015 | F44: 44013 | G44: 2 | H44: 44015 | L44: =IF(AND($F44<(L$2+7),$F44>L$2),1, IF(AND($H44<L$2+7,$H44>L$2),3, IF(AND($F44<=L$2, $H44>=L$2), 2, "" ))) | M44: =IF(AND($F44<(M$2+7),$F44>M$2),1, IF(AND($H44<M$2+7,$H44>M$2),3, IF(AND($F44<=M$2, $H44>=M$2), 2, "" ))) | N44: =IF(AND($F44<(N$2+7),$F44>N$2),1, IF(AND($H44<N$2+7,$H44>N$2),3, IF(AND($F44<=N$2, $H44>=N$2), 2, "" ))) | O44: =IF(AND($F44<(O$2+7),$F44>O$2),1, IF(AND($H44<O$2+7,$H44>O$2),3, IF(AND($F44<=O$2, $H44>=O$2), 2, "" ))) | P44: =IF(AND($F44<(P$2+7),$F44>P$2),1, IF(AND($H44<P$2+7,$H44>P$2),3, IF(AND($F44<=P$2, $H44>=P$2), 2, "" ))) | Q44: =IF(AND($F44<(Q$2+7),$F44>Q$2),1, IF(AND($H44<Q$2+7,$H44>Q$2),3, IF(AND($F44<=Q$2, $H44>=Q$2), 2, "" ))) | R44: =IF(AND($F44<(R$2+7),$F44>R$2),1, IF(AND($H44<R$2+7,$H44>R$2),3, IF(AND($F44<=R$2, $H44>=R$2), 2, "" ))) | S44: =IF(AND($F44<(S$2+7),$F44>S$2),1, IF(AND($H44<S$2+7,$H44>S$2),3, IF(AND($F44<=S$2, $H44>=S$2), 2, "" ))) | ... AQ44: =IF(AND($F44<(AQ$2+7),$F44>AQ$2),1, IF(AND($H44<AQ$2+7,$H44>AQ$2),3, IF(AND($F44<=AQ$2, $H44>=AQ$2), 2, "" ))) -> 1
A45: 13 | B45: Handover | C45: 44020 | D45: 1 | E45: 44021 | F45: 44020 | G45: 1 | H45: 44021 | L45: =IF(AND($F45<(L$2+7),$F45>L$2),1, IF(AND($H45<L$2+7,$H45>L$2),3, IF(AND($F45<=L$2, $H45>=L$2), 2, "" ))) | M45: =IF(AND($F45<(M$2+7),$F45>M$2),1, IF(AND($H45<M$2+7,$H45>M$2),3, IF(AND($F45<=M$2, $H45>=M$2), 2, "" ))) | N45: =IF(AND($F45<(N$2+7),$F45>N$2),1, IF(AND($H45<N$2+7,$H45>N$2),3, IF(AND($F45<=N$2, $H45>=N$2), 2, "" ))) | O45: =IF(AND($F45<(O$2+7),$F45>O$2),1, IF(AND($H45<O$2+7,$H45>O$2),3, IF(AND($F45<=O$2, $H45>=O$2), 2, "" ))) | P45: =IF(AND($F45<(P$2+7),$F45>P$2),1, IF(AND($H45<P$2+7,$H45>P$2),3, IF(AND($F45<=P$2, $H45>=P$2), 2, "" ))) | Q45: =IF(AND($F45<(Q$2+7),$F45>Q$2),1, IF(AND($H45<Q$2+7,$H45>Q$2),3, IF(AND($F45<=Q$2, $H45>=Q$2), 2, "" ))) | R45: =IF(AND($F45<(R$2+7),$F45>R$2),1, IF(AND($H45<R$2+7,$H45>R$2),3, IF(AND($F45<=R$2, $H45>=R$2), 2, "" ))) | S45: =IF(AND($F45<(S$2+7),$F45>S$2),1, IF(AND($H45<S$2+7,$H45>S$2),3, IF(AND($F45<=S$2, $H45>=S$2), 2, "" ))) | ... AQ45: =IF(AND($F45<(AQ$2+7),$F45>AQ$2),1, IF(AND($H45<AQ$2+7,$H45>AQ$2),3, IF(AND($F45<=AQ$2, $H45>=AQ$2), 2, "" )))
A46: E | B46: PAYMENT MILESTONE 6: HANDOVER COMPLETE | C46: 44022 | D46: 1 | E46: 44025 | F46: 44022 | G46: 1 | H46: 44025
C47: 43831 | D47: These numbers are used to set the start and end dates on the Gantt Chart
C48: 44014

Sheet Certificate - Financial Close
B2: Emergent Energy – Financial Close Completion Certificate | H2: FINANCIAL CLOSE CERTIFICATE
B4: Project Name: | C4: ='Project Plan'!E2 -> BMG World, 28 Droste Crescent, JHB
B5: COO: | C5: Johannes Potgieter
B6: Programme Manager: | C6: Roedolph Venter
B7: HoPD: | C7: Natasha Watkins-Baker
B9: Date of Phase Completion:
B10: Phase Deliverables Checklist: (Y/N)
B11: Product Agreement | C11: NA
B12: EPC Agreement | C12: NA
B13: O&M Agreeement | C13: NA
B14: Cost Proposal | C14: Signed
B15: Deposit Received | C15: Yes
B16: Risks / Notes | C16: None
B18: Acknowledgement and Acceptance:
B19: Role | C19: Name | D19: Signature | E19: Date
B20: COO | C20: Johannes | D20: JTP | E20: 45953

Sheet Compliance
B2: HSE
B4: Description | C4: Status | D4: Approved By | E4: Date | F4: Results / Comments
B5: NOC
B6: 7.1 Agreement
B7: 13.2 Agreement
B8: EE File
B9: Subbie File
B16: SSEG
B18: Description | C18: Status | D18: Approved By | E18: Date | F18: Results / Comments
B19: SSEG Application
B20: PTI
B21: Commissioning Approval

Sheet Revenue Tracking
B2: HIGH LEVEL PROJECT REVENUE TRACKING
D3: PLANNED | F3: ACTUAL | L3: FINANCIAL REVIEW | N3: TIMELINE REVIEW | P3: 2023 Rev & COS RECOGNISED | Q3: PLANNED | R3: ACTUAL
B4: 1 | C4: Planned Revenue | D4: ='Project Plan'!E8 -> 14953088 | F4: =F22 -> 15251088 | L4: 15251088 | N4: START DATE | P4: 1669614.5 | Q4: =F4-P4 -> 13581474 | R4: =F4-P4 -> 13581474
B5: 2 | C5: Planned Expenditure | D5: =+'Expenditure Tracking'!F5 -> 13282858 | F5: =+'Expenditure Tracking'!J5 -> 14161976 | L5: 13983270 | N5: 45299 | P5: 1171761.6 | Q5: =F5-P5 -> 12990214 | R5: =F5-P5 -> 12990214
B6: 3 | C6: Planned Profit | D6: =+D4-D5 -> 1670230.6 | F6: =+F4-F5-G6 -> 1089112.8 | L6: 1267818 | N6: FINISH DATE | P6: =P4-P5 -> 497852.87 | Q6: =Q4-Q5 -> 591259.88 | R6: =R4-R5 -> 591259.88
B7: 4 | C7: Planned Margin | D7: =+D6/D4 -> 0.11169804 | F7: =+F6/F4 -> 0.071412133 | L7: 0.083129677 | N7: 45364
B10: CONTRACT
B12: No. | C12: PAYMENT MILESTONE | E12: % | F12: VALUE | H12: PLANNED PAYMENT DATE | L12: INVOICE NUMBER | N12: INVOICE RAISED DATE | P12: PAYMENT RECEIVED DATE | R12: MILESTONE NOTES & COMMENTS
B13: 1 | C13: Acceptance and Initial Deposit | E13: 0.6 | F13: =$D$4*E13 -> 8971853 | H13: 45169 | L13: 004139 | M13: 45078 | N13: 45139 | P13: 45140
B14: 2 | C14: Delivery of Batteries | E14: 0.25 | F14: =$D$4*E14 -> 3738272.1 | H14: ='Project Plan'!G39+7 -> 45279 | L14: 004274 | N14: 45273 | P14: 45278
B15: 3 | C15: Delivery of Inverters | E15: 0.1 | F15: =$D$4*E15 -> 1495308.8 | H15: ='Project Plan'!E30+7 -> 45278 | L15: 004274 | N15: 45273 | P15: 45278
B16: 4 | C16: Handover | E16: 0.025 | F16: =$D$4*E16 -> 373827.21 | H16: ='Project Plan'!E62 -> 45372 | L16: 004505 | N16: 45527 | P16: =N16+7 -> 45534
B17: 4 | C17: Handover | E17: 0.025 | F17: =$D$4*E17 -> 373827.21 | H17: 45372 | L17: 004663 | N17: 45691 | P17: 46052 | R17: Wimpie requested invoice to be resent
B18: 5 | C18: VO - Increase in Inverter Size | E18: 0 | F18: 298000 | H18: =H15 -> 45278 | L18: 004275 | N18: 45273 | P18: 45274
B19: 6 | E19: 0 | F19: 0
B20: 7 | C20: - | E20: 0 | F20: =$D$4*E20 -> 0
E22: =SUM(E13:E20) -> 1 | F22: =SUM(F13:F20) -> 15251088
B24: KEY: | C24: contains an error (in result or a check has failed)
C25: Red Font - IF TEXT : content not yet confirmed
C26: Red Font - IF NUMBER: Negative value
C27: Anything in yellow is a concern or risk for noting or action
C28: confirmed
C29: [ADD INITIALS: comment for noting in square brackets, use colour or red to draw attention if important]
C30: [RT: When adding rows into sheet, ensure you insert between first and last row of each category]
C31: end of sheet - do not insert information below/beyond this
B41: No. | C41: PAYMENT MILESTONE | E41: % | F41: VALUE
B42: 1 | C42: Deposit - Project commencement | E42: 0.35 | F42: =$F$48*E42 -> 5337880.9
B43: 2 | C43: Delivery of Panels | E43: 0.3 | F43: =$F$48*E43 -> 4575326.5
B44: 3 | C44: Delivery of Inverters | E44: 0.2 | F44: =$F$48*E44 -> 3050217.7
B45: 4 | C45: Practical Completion | E45: 0.1 | F45: =$F$48*E45 -> 1525108.8
B46: 5 | C46: Handover | E46: 0.05 | F46: =$F$48*E46 -> 762554.42
C47: Total | E47: =SUM(E42:E46) -> 1 | F47: =SUM(F42:F46) -> 15251088
E48: =SUM(E42:E46) -> 1 | F48: =F22 -> 15251088

Sheet Data
C2: Public holidays | F2: Drop down list
C3: 44197 | F3: Approved
C4: 44277 | F4: Pending
C5: 44288 | F5: Declined
C6: 44291 | F6: Abanded
C7: 44313
C8: 44317
C9: 44363
C10: 44417
C11: 44463
C12: 44546
C13: 44555 | H13: Manual dates
C14: 44556

Sheet Project Plan
N1: =TODAY() -> 46063 | O1: =TODAY() -> 46063
C2: PROJECT PLAN | E2: BMG World, 28 Droste Crescent, JHB | N2: 0 | O2: 1
C3: PROJECT SIZE (kWp) | E3: 350 | F3: 1800kWh, 500kVA
C4: SITE ADDRESS | E4: BMG World, 28 Droste Crescent, JHB
C5: BUSINESS DEVELOPER | E5: Peter
C6: PROJECT MANAGERS | E6: Lloyd Brown
C7: INSTALLER | E7: TBC
C8: CONTRACT VALUE | E8: 14953088
C9: Phase: | E9: Compliance Handover
B10: No. | C10: HIGH LEVEL PROGRAMME | E10: Planned Start | F10: Duration (days) | G10: Planned End | I10: Actual Start | J10: Duration (days) | K10: Actual End | M10: Status | O10: Comment
F11: =G51-E27 -> 84 | J11: =K51-I27 -> 102 | M11: =AVERAGE(M13,M26,M29,M36,M45,M49,M57,M54,M19) -> 1 | N11: =AVERAGE(N13,N26,N29,N36,N45,N49,N57,N54,N19) -> 1
B13: 1 | C13: Project Initiation | E13: =MIN(E14:E17) -> 45138 | F13: =G13-E13 -> 38 | G13: =MAX(G14:G17) -> 45176 | I13: =MIN(I14:I17) -> 45138 | J13: =K13-I13 -> 126 | K13: =MAX(K14:K17) -> 45264 | M13: =(J14*M14+J15*M15+J16*M16+J17*M17)/SUM(J14:J17) -> 1 | N13: =(K14*N14+K15*N15+K16*N16+K17*N17)/SUM(K14:K17) -> 1
B14: 1.1 | C14: BD Handover | E14: 45138 | F14: 1 | G14: =WORKDAY.INTL(E14,F14,1,Data!$C$3:$C$14) -> 45139 | I14: 45138 | J14: 1 | K14: =WORKDAY.INTL(I14,J14,1,Data!$C$3:$C$14) -> 45139 | M14: 1 | N14: 1
B15: 1.2 | C15: Project Introduction | E15: =E14+14 -> 45152 | F15: 1 | G15: =WORKDAY.INTL(E15,F15,1,Data!$C$3:$C$14) -> 45153 | I15: =I14+14 -> 45152 | J15: 1 | K15: =WORKDAY.INTL(I15,J15,1,Data!$C$3:$C$14) -> 45153 | M15: 1 | N15: 1
B16: 1.3 | C16: Financial Review | E16: =G15+21 -> 45174 | F16: 1 | G16: =WORKDAY.INTL(E16,F16,1,Data!$C$3:$C$14) -> 45175 | I16: 45261 | J16: 1 | K16: =WORKDAY.INTL(I16,J16,1,Data!$C$3:$C$14) -> 45264 | M16: 1 | N16: 1
B17: 1.4 | C17: Client kick off | E17: =E16+1 -> 45175 | F17: 1 | G17: =WORKDAY.INTL(E17,F17,1,Data!$C$3:$C$14) -> 45176 | I17: =I16+1 -> 45262 | J17: 1 | K17: =WORKDAY.INTL(I17,J17,1,Data!$C$3:$C$14) -> 45264 | M17: 1 | N17: 1
B19: 2 | C19: BESS - Prep Work | E19: =MIN(E20:E24) -> 45152 | F19: =G19-E19 -> 59 | G19: =MAX(G20:G24) -> 45211 | I19: =MIN(I20:I24) -> 45152 | J19: =K19-I19 -> 114 | K19: =MAX(K20:K24) -> 45266 | M19: =(J20*M20+J21*M21+J22*M22+J23*M23+J24*M24)/SUM(J20:J24) -> 1 | N19: =(K20*N20+K21*N21+K22*N22+K23*N23+K24*N24)/SUM(K20:K24) -> 1
B20: 2.1 | C20: Pre-Installation Prepping | E20: =WORKDAY.INTL(E15,0,1,Data!$C$3:$C$14) -> 45152 | F20: 10 | G20: =WORKDAY.INTL(E20,F20,1,Data!$C$3:$C$14) -> 45166 | I20: =WORKDAY.INTL(I15,0,1,Data!$C$3:$C$14) -> 45152 | J20: 10 | K20: =WORKDAY.INTL(I20,J20,1,Data!$C$3:$C$14) -> 45166 | M20: 1 | N20: 1
B21: 2.2 | C21: Plinth Installation | E21: =WORKDAY.INTL(G20,0,1,Data!$C$3:$C$14) -> 45166 | F21: 10 | G21: =WORKDAY.INTL(E21,F21,1,Data!$C$3:$C$14) -> 45180 | I21: =WORKDAY.INTL(K20,0,1,Data!$C$3:$C$14) -> 45166 | J21: 10 | K21: =WORKDAY.INTL(I21,J21,1,Data!$C$3:$C$14) -> 45180 | M21: 1 | N21: 1
B22: 2.3 | C22: Housing Prep | E22: =WORKDAY.INTL(E20,0,1,Data!$C$3:$C$14) -> 45152 | F22: 36 | G22: =WORKDAY.INTL(E22,F22,1,Data!$C$3:$C$14) -> 45202 | I22: =WORKDAY.INTL(I20,0,1,Data!$C$3:$C$14) -> 45152 | J22: 36 | K22: =WORKDAY.INTL(I22,J22,1,Data!$C$3:$C$14) -> 45202 | M22: 1 | N22: 1
B23: 2.4 | C23: Setup of rigger and placement | E23: =WORKDAY.INTL(G22,0,1,Data!$C$3:$C$14) -> 45202 | F23: 3 | G23: =WORKDAY.INTL(E23,F23,1,Data!$C$3:$C$14) -> 45205 | I23: =WORKDAY.INTL(K22,0,1,Data!$C$3:$C$14) -> 45202 | J23: 3 | K23: =WORKDAY.INTL(I23,J23,1,Data!$C$3:$C$14) -> 45205 | M23: 1 | N23: 1
B24: 2.5 | C24: Housing Completed | E24: =WORKDAY.INTL(G23,0,1,Data!$C$3:$C$14) -> 45205 | F24: 4 | G24: =WORKDAY.INTL(E24,F24,1,Data!$C$3:$C$14) -> 45211 | I24: =WORKDAY.INTL(K23,0,1,Data!$C$3:$C$14) -> 45205 | J24: 43 | K24: =WORKDAY.INTL(I24,J24,1,Data!$C$3:$C$14) -> 45266 | M24: 1 | N24: 1
B26: 3 | C26: Site Establishment | E26: =MIN(E27:E28) -> 45271 | F26: =G26-E26 -> 1 | G26: =MAX(G27) -> 45272 | I26: =MIN(I27:I28) -> 45299 | J26: =K26-I26 -> 1 | K26: =MAX(K27) -> 45300 | M26: =(J27*M27)/J26 -> 1 | N26: =(K27*N27)/K26 -> 1
B27: 3.1 | C27: Installer on site and roof assessment | E27: 45271 | F27: 1 | G27: =WORKDAY.INTL(E27,F27,1,Data!$C$3:$C$14) -> 45272 | I27: 45299 | J27: 1 | K27: =WORKDAY.INTL(I27,J27,1,Data!$C$3:$C$14) -> 45300 | M27: 1 | N27: 1
B29: 4 | C29: AC Installation | E29: =MIN(E30:E34) -> 45271 | F29: =G29-E29 -> 74 | G29: =MAX(G30:G34) -> 45345 | I29: =MIN(I30:I34) -> 45299 | J29: =K29-I29 -> 78 | K29: =MAX(K30:K34) -> 45377 | M29: =(J30*M30+J31*M31+J32*M32+J33*M33+J34*M34)/SUM(J30:J34) -> 1 | N29: =(K30*N30+K31*N31+K32*N32+K33*N33+K34*N34)/SUM(K30:K34) -> 1
B30: 4.1 | C30: Inverters delivered | E30: =E27 -> 45271 | F30: 1 | G30: =WORKDAY.INTL(E30,F30,1,Data!$C$3:$C$14) -> 45272 | I30: =I27 -> 45299 | J30: 1 | K30: =WORKDAY.INTL(I30,J30,1,Data!$C$3:$C$14) -> 45300 | M30: 1 | N30: 1
B31: 4.2 | C31: Inverters Mounted | E31: =WORKDAY.INTL(G30,0,1,Data!$C$3:$C$14)+1 -> 45273 | F31: 1 | G31: =WORKDAY.INTL(E31,F31,1,Data!$C$3:$C$14) -> 45274 | I31: =I32+4 -> 45303 | J31: 1 | K31: =WORKDAY.INTL(I31,J31,1,Data!$C$3:$C$14) -> 45306 | M31: 1 | N31: 1
B32: 4.3 | C32: Solar DB lead time | E32: =WORKDAY.INTL(E27,0,1,Data!$C$3:$C$14)+33 -> 45304 | F32: 30 | G32: =WORKDAY.INTL(E32,F32,1,Data!$C$3:$C$14) -> 45345 | I32: =WORKDAY.INTL(I27,0,1,Data!$C$3:$C$14) -> 45299 | J32: 35 | K32: =WORKDAY.INTL(I32,J32,1,Data!$C$3:$C$14)+5 -> 45353 | M32: 1 | N32: 1
B33: 4.4 | C33: AC Works | E33: =WORKDAY.INTL(E32,0,1,Data!$C$3:$C$14)+7 -> 45311 | F33: 25 | G33: =WORKDAY.INTL(E33,F33,1,Data!$C$3:$C$14) -> 45345 | I33: =WORKDAY.INTL(I32,0,1,Data!$C$3:$C$14)+7 -> 45306 | J33: 30 | K33: =WORKDAY.INTL(I33,J33,1,Data!$C$3:$C$14)+28 -> 45376 | M33: 1 | N33: 1
B34: 4.5 | C34: AC Tie - in | E34: =WORKDAY.INTL(G40,0,1,Data!$C$3:$C$14)+1 -> 45322 | F34: 2 | G34: =WORKDAY.INTL(E34,F34,1,Data!$C$3:$C$14) -> 45324 | I34: 45374 | J34: 2 | K34: =WORKDAY.INTL(I34,J34,1,Data!$C$3:$C$14) -> 45377 | M34: 1 | N34: 1
B36: 5 | C36: DC Works | E36: =MIN(E37:E43) -> 45271 | F36: =G36-E36 -> 63 | G36: =MAX(G37:G43) -> 45334 | I36: =MIN(I37:I43) -> 45271 | J36: =K36-I36 -> 63 | K36: =MAX(K37:K43) -> 45334 | M36: =(J37*M37+J38*M38+J39*M39+J40*M40+J41*M41+J42*M42+J43*M43)/SUM(J37:J43) -> 1 | N36: =(K37*N37+K38*N38+K39*N39+K40*N40+K41*N41+K42*N42+K43*N43)/SUM(K37:K43) -> 1
B37: 5.1 | C37: Mounting Structure delivered | E37: 45299 | F37: 1 | G37: =WORKDAY.INTL(E37,F37,1,Data!$C$3:$C$14) -> 45300 | I37: 45301 | J37: 1 | K37: =WORKDAY.INTL(I37,J37,1,Data!$C$3:$C$14) -> 45302 | M37: 1 | N37: 1
B38: 5.2 | C38: Mounting Structure installation | E38: =WORKDAY.INTL(G37,0,1,Data!$C$3:$C$14) -> 45300 | F38: 10 | G38: =WORKDAY.INTL(E38,F38,1,Data!$C$3:$C$14) -> 45314 | I38: =WORKDAY.INTL(K37,0,1,Data!$C$3:$C$14) -> 45302 | J38: 3 | K38: =WORKDAY.INTL(I38,J38,1,Data!$C$3:$C$14) -> 45307 | M38: 1 | N38: 1
B39: 5.3 | C39: Battery Delivery | E39: 45271 | F39: 1 | G39: =WORKDAY.INTL(E39,F39,1,Data!$C$3:$C$14) -> 45272 | I39: 45271 | J39: 1 | K39: =WORKDAY.INTL(I39,J39,1,Data!$C$3:$C$14) -> 45272 | M39: 1 | N39: 1
B40: 5.4 | C40: Battery Installation | E40: =WORKDAY.INTL(G39,0,1,Data!$C$3:$C$14) -> 45272 | F40: 35 | G40: =WORKDAY.INTL(E40,F40,1,Data!$C$3:$C$14) -> 45321 | I40: =WORKDAY.INTL(K39,0,1,Data!$C$3:$C$14) -> 45272 | J40: 35 | K40: =WORKDAY.INTL(I40,J40,1,Data!$C$3:$C$14) -> 45321 | M40: 1 | N40: 1
B41: 5.5 | C41: DC Cable delivered | E41: 45308 | F41: 1 | G41: =WORKDAY.INTL(E41,F41,1,Data!$C$3:$C$14) -> 45309 | I41: 45307 | J41: 1 | K41: =WORKDAY.INTL(I41,J41,1,Data!$C$3:$C$14) -> 45308 | M41: 1 | N41: 1
B42: 5.6 | C42: DC Cable Trays installation | E42: =+G38 -> 45314 | F42: 7 | G42: =WORKDAY.INTL(E42,F42,1,Data!$C$3:$C$14) -> 45323 | I42: =+K38 -> 45307 | J42: 7 | K42: =WORKDAY.INTL(I42,J42,1,Data!$C$3:$C$14) -> 45316 | M42: 1 | N42: 1
B43: 5.7 | C43: DC Cabling | E43: =+G42 -> 45323 | F43: 7 | G43: =WORKDAY.INTL(E43,F43,1,Data!$C$3:$C$14) -> 45334 | I43: =+K42 -> 45316 | J43: 10 | K43: =WORKDAY.INTL(I43,J43,1,Data!$C$3:$C$14)+4 -> 45334 | M43: 1 | N43: 1
B45: 6 | C45: Module installation | E45: =MIN(E46:E47) -> 45314 | F45: =G45-E45 -> 15 | G45: =MAX(G46:G47) -> 45329 | I45: =MIN(I46:I47) -> 45355 | J45: =K45-I45 -> 17 | K45: =MAX(K46:K47) -> 45372 | M45: =(J46*M46+J47*M47)/SUM(J46:J47) -> 1 | N45: =(K46*N46+K47*N47)/SUM(K46:K47) -> 1
B46: 6.1 | C46: Module delivery | E46: 45314 | F46: 1 | G46: =WORKDAY.INTL(E46,F46,1,Data!$C$3:$C$14) -> 45315 | I46: 45355 | J46: 1 | K46: =WORKDAY.INTL(I46,J46,1,Data!$C$3:$C$14) -> 45356 | M46: 1 | N46: 1
B47: 6.2 | C47: Module mounting | E47: =WORKDAY.INTL(G46,0,1,Data!$C$3:$C$14) -> 45315 | F47: 10 | G47: =WORKDAY.INTL(E47,F47,1,Data!$C$3:$C$14) -> 45329 | I47: =WORKDAY.INTL(K46,0,1,Data!$C$3:$C$14) -> 45356 | J47: 12 | K47: =WORKDAY.INTL(I47,J47,1,Data!$C$3:$C$14) -> 45372 | M47: 1 | N47: 1 | O47: Team prep for hoisting and mounting.
B49: 7 | C49: Commissioning | E49: =MIN(E50:E51) -> 45345 | F49: =G49-E49 -> 10 | G49: =MAX(G50:G51) -> 45355 | I49: =MIN(I50:I51) -> 45391 | J49: =K49-I49 -> 10 | K49: =MAX(K50:K51) -> 45401 | M49: =(J50*M50+J51*M51)/SUM(J50:J51) -> 1 | N49: =(K50*N50+K51*N51)/SUM(K50:K51) -> 1
B50: 7.1 | C50: Cold commissioning | E50: =WORKDAY.INTL(MAX(G29,G36,G45),0,1,Data!$C$3:$C$14) -> 45345 | F50: 3 | G50: =WORKDAY.INTL(E50,F50,1,Data!$C$3:$C$14) -> 45350 | I50: =WORKDAY.INTL(MAX(K29,K36,K45),0,1,Data!$C$3:$C$14)+14 -> 45391 | J50: 3 | K50: =WORKDAY.INTL(I50,J50,1,Data!$C$3:$C$14) -> 45394 | M50: 1 | N50: 1
B51: 7.2 | C51: Hot commissioning | E51: =WORKDAY.INTL(G50,0,1,Data!$C$3:$C$14) -> 45350 | F51: 3 | G51: =WORKDAY.INTL(E51,F51,1,Data!$C$3:$C$14) -> 45355 | I51: =WORKDAY.INTL(K50,0,1,Data!$C$3:$C$14) -> 45394 | J51: 5 | K51: =WORKDAY.INTL(I51,J51,1,Data!$C$3:$C$14) -> 45401 | M51: 1 | N51: 1
B52: 7.3 | C52: Final Commissioning | I52: 45446 | J52: 35 | K52: =WORKDAY.INTL(I52,J52,1,Data!$C$3:$C$14) -> 45495 | M52: 1 | N52: 1 | O52: Elum to update the firmware
B54: 8 | C54: QA Inspections | E54: =MIN(E55) -> 45360 | F54: =G54-E54 -> 4 | G54: =MAX(G55) -> 45364 | I54: =MIN(I55) -> 45495 | J54: =K54-I54 -> 3 | K54: =MAX(K55) -> 45498 | M54: =(J55*M55)/SUM(J55) -> 1 | N54: =(K55*N55)/SUM(K55) -> 1
B55: 8.1 | C55: Red-Team Inspection | E55: =WORKDAY.INTL(G51,0,1,Data!$C$3:$C$14)+5 -> 45360 | F55: 3 | G55: =WORKDAY.INTL(E55,F55,1,Data!$C$3:$C$14) -> 45364 | I55: =WORKDAY.INTL(K52,0,1,Data!$C$3:$C$14) -> 45495 | J55: 3 | K55: =WORKDAY.INTL(I55,J55,1,Data!$C$3:$C$14) -> 45498 | M55: 1 | N55: 1
B57: 9 | C57: Project Closure | E57: =MIN(E58:E63) -> 45350 | F57: =G57-E57 -> 26 | G57: =MAX(G58:G63) -> 45376 | I57: =MIN(I58:I63) -> 45394 | J57: =K57-I57 -> 515 | K57: =MAX(K58:K63) -> 45909 | M57: =(J58*M58+J59*M59+J60*M60+J61*M61+J62*M62+J63*M63)/SUM(J58:J63) -> 1 | N57: =(K58*N58+K59*N59+K60*N60+K61*N61+K62*N62+K63*N63)/SUM(K58:K63) -> 1
B58: 9.1 | C58: Equipment serial numbers | E58: =WORKDAY.INTL(E51,0,1,Data!$C$3:$C$14) -> 45350 | F58: 1 | G58: =WORKDAY.INTL(E58,F58,1,Data!$C$3:$C$14) -> 45351 | I58: =WORKDAY.INTL(I51,0,1,Data!$C$3:$C$14) -> 45394 | J58: 1 | K58: =WORKDAY.INTL(I58,J58,1,Data!$C$3:$C$14) -> 45397 | M58: 1 | N58: 1
B59: 9.2 | C59: Snags completion | E59: =WORKDAY.INTL(G55,0,1,Data!$C$3:$C$14) -> 45364 | F59: 3 | G59: =WORKDAY.INTL(E59,F59,1,Data!$C$3:$C$14) -> 45369 | I59: =WORKDAY.INTL(K52,0,1,Data!$C$3:$C$14) -> 45495 | J59: 19 | K59: =WORKDAY.INTL(I59,J59,1,Data!$C$3:$C$14) -> 45520 | M59: 1 | N59: 1
B60: 9.3 | C60: System Performance Monitoring | E60: =WORKDAY.INTL(G59,0,1,Data!$C$3:$C$14) -> 45369 | F60: 5 | G60: =WORKDAY.INTL(E60,F60,1,Data!$C$3:$C$14) -> 45376 | I60: =WORKDAY.INTL(K59,0,1,Data!$C$3:$C$14) -> 45520 | J60: 5 | K60: =WORKDAY.INTL(I60,J60,1,Data!$C$3:$C$14) -> 45527 | M60: 1 | N60: 1
B61: 9.4 | C61: Handover documentation | E61: =WORKDAY.INTL(G59,0,1,Data!$C$3:$C$14) -> 45369 | F61: 3 | G61: =WORKDAY.INTL(E61,F61,1,Data!$C$3:$C$14) -> 45372 | I61: 45586 | J61: 1 | K61: =WORKDAY.INTL(I61,J61,1,Data!$C$3:$C$14) -> 45587 | M61: 1 | N61: 1
B62: 9.5 | C62: Handover to Client | E62: =WORKDAY.INTL(G61,0,1,Data!$C$3:$C$14) -> 45372 | F62: 1 | G62: =WORKDAY.INTL(E62,F62,1,Data!$C$3:$C$14) -> 45373 | I62: =WORKDAY.INTL(K61,0,1,Data!$C$3:$C$14) -> 45587 | J62: 1 | K62: 45909 | M62: 1 | N62: 1
B63: 9.6 | C63: Handover to Matriarch | E63: =WORKDAY.INTL(G62,0,1,Data!$C$3:$C$14) -> 45373 | F63: 1 | G63: =WORKDAY.INTL(E63,F63,1,Data!$C$3:$C$14) -> 45376 | I63: =WORKDAY.INTL(I60,0,1,Data!$C$3:$C$14)+2 -> 45522 | J63: 1 | K63: =WORKDAY.INTL(I63,J63,1,Data!$C$3:$C$14) -> 45523 | M63: 1 | N63: 1

Sheet Expenditure Tracking
B2: HIGH LEVEL PROJECT EXPENDITURE TRACKING
F4: COSTED | H4: PLANNED | J4: ACTUAL | L4: Difference from costed | N4: Difference from planned
B5: EXPENDITURE | F5: =SUM(F9:F23) -> 13282858 | H5: =SUM(H9:H23) -> 14016971 | J5: =SUM(J9:J23) -> 14161976 | L5: =SUM(L9:L23) -> -734113.76 | N5: =SUM(N9:N23) -> -145004.1
B7: No. | D7: Item | F7: Costed Expenditure | H7: Planned Expenditure | J7: Actual Expenditure | L7: Saving / Overrun | N7: Saving / Overrun | P7: Comments on variations from planned expenditure
B9: ='Expenditure Breakdown'!B6 -> 1 | D9: ='Expenditure Breakdown'!C6 -> Panels | F9: ='Expenditure Breakdown'!J6 -> 1502096.4 | H9: 1188829 | J9: ='Expenditure Breakdown'!X6 -> 1165914.2 | L9: =F9-H9 -> 313267.38 | N9: =H9-J9 -> 22914.784
B10: ='Expenditure Breakdown'!B13 -> 2 | D10: ='Expenditure Breakdown'!C13 -> Inverters | F10: =+'Expenditure Breakdown'!J13 -> 216000 | H10: 253411.45 | J10: =+'Expenditure Breakdown'!X13 -> 243184.47 | L10: =F10-H10 -> -37411.455 | N10: =H10-J10 -> 10226.985
B11: ='Expenditure Breakdown'!B18 -> 3 | D11: ='Expenditure Breakdown'!C18 -> Mounting Structures | F11: =+'Expenditure Breakdown'!J18 -> 132867 | H11: 71033.82 | J11: =+'Expenditure Breakdown'!X18 -> 78280 | L11: =F11-H11 -> 61833.18 | N11: =H11-J11 -> -7246.18
B12: ='Expenditure Breakdown'!B25 -> 4 | D12: ='Expenditure Breakdown'!C25 -> DC Equipment | F12: =+'Expenditure Breakdown'!J25 -> 350217.5 | H12: 440470.35 | J12: =+'Expenditure Breakdown'!X25 -> 478379.14 | L12: =F12-H12 -> -90252.85 | N12: =H12-J12 -> -37908.795 | P12: KN: Additional 5000m required.
B13: ='Expenditure Breakdown'!B34 -> 5 | D13: ='Expenditure Breakdown'!C34 -> Monitoring | F13: =+'Expenditure Breakdown'!J34 -> 49000 | H13: 419120.31 | J13: =+'Expenditure Breakdown'!X34 -> 438053.51 | L13: =F13-H13 -> -370120.31 | N13: =H13-J13 -> -18933.2 | P13: KN: Elum controller- RE: order through Krannich - Forex payment issue to Elum
B14: ='Expenditure Breakdown'!B48 -> 6 | D14: ='Expenditure Breakdown'!C48 -> AC Equipment | F14: =+'Expenditure Breakdown'!J48 -> 250335.42 | H14: 1308958.7 | J14: =+'Expenditure Breakdown'!X48 -> 1186079.8 | L14: =F14-H14 -> -1058623.3 | N14: =H14-J14 -> 122878.88 | P14: KN: AC cable, Awaiting amended quote from MG
B15: ='Expenditure Breakdown'!B55 -> 7 | D15: ='Expenditure Breakdown'!C55 -> Battery Systems | F15: =+'Expenditure Breakdown'!J55 -> 10380642 | H15: 9658092 | J15: ='Expenditure Breakdown'!X55 -> 9684222 | L15: =F15-H15 -> 722550.33 | N15: =H15-J15 -> -26130
B16: ='Expenditure Breakdown'!B76 -> 8 | D16: ='Expenditure Breakdown'!C76 -> Product Add On | F16: ='Expenditure Breakdown'!J76 -> 0 | H16: 34671.6 | J16: ='Expenditure Breakdown'!X76 -> 291094.63 | L16: =F16-H16 -> -34671.6 | N16: =H16-J16 -> -256423.03 | P16: KN: Inverter VO & Trenching
B17: ='Expenditure Breakdown'!B86 -> 9 | D17: ='Expenditure Breakdown'!C86 -> AC & DC installation | F17: =+'Expenditure Breakdown'!J86 -> 209475 | H17: 284553.2 | J17: =+'Expenditure Breakdown'!X86 -> 254553.2 | L17: =F17-H17 -> -75078.2 | N17: =H17-J17 -> 30000
B18: ='Expenditure Breakdown'!B95 -> 10 | D18: ='Expenditure Breakdown'!C95 -> Site Logistics | F18: =+'Expenditure Breakdown'!J95 -> 60622.9 | H18: 143314.22 | J18: =+'Expenditure Breakdown'!X95 -> 143314.22 | L18: =F18-H18 -> -82691.32 | N18: =H18-J18 -> 0
B19: ='Expenditure Breakdown'!B104 -> 11 | D19: ='Expenditure Breakdown'!C104 -> Due Dilligence | F19: ='Expenditure Breakdown'!J104 -> 19000 | H19: 16500 | J19: ='Expenditure Breakdown'!X104 -> 11683.16 | L19: =F19-H19 -> 2500 | N19: =H19-J19 -> 4816.84
B20: ='Expenditure Breakdown'!B110 -> 12 | D20: ='Expenditure Breakdown'!C110 -> BDP Commission | F20: =+'Expenditure Breakdown'!J110 -> 0 | H20: 0 | J20: =+'Expenditure Breakdown'!X110 -> 0 | L20: =F20-H20 -> 0 | N20: =H20-J20 -> 0
B21: ='Expenditure Breakdown'!B112 -> 13 | D21: ='Expenditure Breakdown'!C112 -> Engineering | F21: =+'Expenditure Breakdown'!J112 -> 109626.14 | H21: 194292.17 | J21: =+'Expenditure Breakdown'!X112 -> 154048.41 | L21: =F21-H21 -> -84666.031 | N21: =H21-J21 -> 40243.76 | P21: RV: Matriarch defects percentage 1.25%
B22: ='Expenditure Breakdown'!B121 -> 14 | D22: ='Expenditure Breakdown'!C121 -> General Expenses | F22: =+'Expenditure Breakdown'!J121 -> 2975 | H22: 3724.57 | J22: =+'Expenditure Breakdown'!X121 -> 33168.71 | L22: =F22-H22 -> -749.57 | N22: =H22-J22 -> -29444.14
B23: ='Expenditure Breakdown'!B135 -> 15 | D23: ='Expenditure Breakdown'!C135 -> Service Add On | F23: =+'Expenditure Breakdown'!J135 -> 0 | H23: 0 | J23: =+'Expenditure Breakdown'!X135 -> 0 | L23: =F23-H23 -> 0 | N23: =H23-J23 -> 0
D25: check: | F25: ='Expenditure Breakdown'!J2-'Expenditure Tracking'!F5 -> 0 | G25: ='Expenditure Breakdown'!#REF!-G5 -> #REF! | H25: ='Expenditure Breakdown'!X2-J5 -> 0 | I25: ='Expenditure Breakdown'!#REF!-I5 -> #REF! | J25: ='Expenditure Breakdown'!X2-J5 -> 0
A27: Copy amounts in column H and paste as values at Financial review.

Sheet Expenditure Breakdown
B2: PLANNED EXPENDITURE BREAKDOWN | J2: =SUM(J6:J139) -> 13282858 | K2: =SUM(K6:K139) -> 14953089 | M2: ACTUAL EXPENDITURE BREAKDOWN | S2: FINANCE ONLY | X2: =SUM(X6:X139) -> 14161976
B4: No. | C4: Product / Service | D4: Description of Work | E4: QTY | F4: Rate / Unit | G4: Budget Total | H4: Project Related date | J4: Total COS | K4: =IF(K2-'Revenue Tracking'!D4>=0, "Total Revenue", "ERROR on REV" ) -> Total Revenue | M4: No. | N4: Product/ Service | O4: Description of Work | P4: QTY | Q4: Rate / Unit | R4: Actual Total | S4: INVOICE NUMBER | T4: INVOICE RAISED DATE | U4: REVENUE RECOGNITION AMOUNT | V4: CHECK | W4: FINANCE PAYMENT DATE | X4: Total COS | Y4: PO NUMBER | Z4: COMMENTS
B6: 1 | C6: Panels | D6: 555W Solar Panel | E6: 630 | F6: 2384.28 | G6: =F6*E6 -> 1502096.4 | H6: ='Project Plan'!G46+31 -> 45346 | J6: =SUM(G6:G11) -> 1502096.4 | K6: 1675592.2 | M6: 1 | N6: 1. Panels | O6: Jinko 555W | P6: 638 | Q6: =1526.25*P6 -> 973747.5 | S6: MENLO DISTRIBUTION INV0001192 | T6: 45382 | U6: 0 | V6: =K6-SUM(U6:U11) -> 0.0044139633 | W6: 45148 | X6: =SUM(R6:R11) -> 1165914.2 | Y6: PO2982-BMG2-20240227 | AA6: 19
B7: 1 | M7: 1 | N7: 1. Panels | S7: MENLO DISTRIBUTION INV0001192 | T7: 45382 | U7: 0 | W7: 45384 | AA7: BUDGET | AB7: Installer Allocation
B8: 1 | M8: 1 | N8: 1. Panels | P8: 637 | R8: 1165914.2 | S8: Jinko: MCSSRJQ3047 | T8: 45169 | U8: 1675592.2 | W8: 45384 | AA8: AC Equipment | AB8: =+J48 -> 250335.42
B9: 1 | M9: 1 | N9: 1. Panels | U9: 0 | AA9: DC Equipment | AB9: =+G30+G31 -> 142285.5
B10: 1 | M10: 1 | N10: 1. Panels | U10: 0 | AA10: AC Labour | AB10: =+C87 -> 0
B11: 1 | M11: 1 | U11: 0 | AA11: DC Labour | AB11: =+C88 -> 209475
AA12: Offloading | AB12: =+G98 -> 8500
B13: 2 | C13: Inverters | D13: Huawei 100KTL | E13: 3 | G13: 216000 | H13: ='Project Plan'!G30+30 -> 45302 | J13: =SUM(G13:G16) -> 216000 | K13: 240948.52 | M13: 2 | N13: 2. Inverters | O13: Kathea- Huawei 100KTL | P13: 3 | Q13: 80833 | R13: =33565.93/1.15 -> 29187.765 | S13: Kathea Inv 516781 | T13: 45291 | U13: 240948.52 | V13: =K13-SUM(U13:U16) -> -298000 | W13: 45334 | X13: =SUM(R13:R16) -> 243184.47 | AA13: Roof Access | AB13: =+G95+G96 -> 25122.9
B14: 2 | M14: 2 | N14: 2. Inverters | O14: Delivery | R14: =243184.47-R13 -> 213996.7 | S14: Kathea Inv 516781 | T14: 45291 | U14: 0 | W14: 45345 | AA14: =O67 -> 0 | AB14: =R67 -> 0
B15: 2 | M15: 2 | N15: 2. Inverters | T15: 45382 | U15: 298000 | AA15: =O68 -> Data Guru (Cost removed) | AB15: =R68 -> 0
B16: 2 | M16: 2 | N16: 2. Inverters | U16: 0 | AA16: Other | AB16: 0
AA17: Total | AB17: =SUM(AB8:AB16) -> 635718.82
B18: 3 | C18: Mounting Structures | D18: Roof Type TBC | G18: 132867 | H18: ='Project Plan'!E38+30 -> 45330 | J18: =SUM(G18:G23) -> 132867 | K18: 148213.46 | M18: 3 | N18: 3. Mounting Structures | O18: Schlette IBR | R18: =56141-1250 -> 54891 | S18: Schletter Inv: INV0005 | T18: 45322 | U18: 103929.29 | V18: =K18-SUM(U18:U23) -> 0 | W18: 45351 | X18: =SUM(R18:R23) -> 78280 | Y18: PO2908-BMGP2-20231213 | AA18: Less 15% | AB18: =+AB17*0.85 -> 540360.99 | AD18: [SM: Target Installation Price]
M19: 3 | N19: 3. Mounting Structures
B20: 3 | M20: 3 | N20: 3. Mounting Structures | O20: Delivery | R20: 1250 | S20: Schletter Inv: INV0005 | T20: 45322 | U20: 2366.7198 | W20: 45351 | AA20: R/Wp | AB20: =+AB18/'Project Plan'!E3/1000 -> 1.5438886
B21: 3 | M21: 3 | N21: 3. Mounting Structures | O21: Lumax Screws | R21: 19920 | S21: Lumax Inv: INV0040280 | T21: 45322 | U21: 37716.047 | W21: 45351 | AB21: MG | AE21: Cosmic Sun - DC Only
M22: 3 | N22: 3. Mounting Structures | O22: Lumax Screws | R22: 381 | S22: Lumax Inv: INV0040623 | T22: 45322 | U22: 721.37619 | W22: 45351
B23: 3 | M23: 3 | N23: 3. Mounting Structures | O23: Lumax - Clamps | R23: 1838 | S23: lLumax INV0040527 | T23: 45322 | U23: 3480.0248 | W23: 45351 | Y23: PO2936-BMGP2-20240118 | AA23: ACTUAL | AB23: Installer Price | AD23: ACTUAL | AE23: Installer Price
AA24: AC Equipment | AB24: =302612.75+160357.75+628755.61+64674.24+29679.5 -> 1186079.8 | AD24: AC Equipment | AE24: =AE8 -> 0 | AG24: =AB24*0.4 -> 474431.94
B25: 4 | C25: DC Equipment | D25: DC Cable | E25: 10465 | F25: 14.8 | G25: =E25*F25 -> 154882 | H25: ='Project Plan'!E41+45 -> 45353 | J25: =SUM(G25:G32) -> 350217.5 | K25: 390668.47 | M25: 4 | N25: 4. DC Equipment | O25: DC Cable Red | P25: 10000 | Q25: 14.36 | R25: =Q25*P25 -> 143600 | S25: Rubicon Inv: INVWCRE-0052509 | T25: 45322 | U25: 117270.98 | V25: =K25-SUM(U25:U32) -> -0.0016314493 | W25: 45351 | X25: =SUM(R25:R32) -> 478379.14 | AA25: DC Equipment | AB25: 0 | AD25: DC Equipment | AE25: 133659.15
N26: 4. DC Equipment | O26: DC Cable Black | P26: 10000 | Q26: 14.3 | R26: =Q26*P26 -> 143000 | S26: Rubicon Inv: INVWCRE-0052509 | T26: 45322 | U26: 116780.99 | W26: 45351
N27: 4. DC Equipment | O27: Extra DC cable red (Rubicon) | P27: 2000 | Q27: 14.36 | R27: 28720 | S27: Rubicon : Inv INVWCRE-0052851 | T27: 45322 | U27: 23454.196 | W27: 45351
N28: 4. DC Equipment | O28: Extra DC cable black (Rubicon) | P28: 2000 | Q28: 14.3 | R28: 28600 | S28: Rubicon : Inv INVWCRE-0052851 | T28: 45322 | U28: 23356.198 | W28: 45351
B29: 4 | D29: DC Surge Arrestor | E29: 4 | F29: 5500 | G29: =E29*F29 -> 22000 | H29: =H25 -> 45353 | M29: 4 | N29: 4. DC Equipment | O29: Delivery | R29: 800 | S29: Rubicon Inv: INVWCRE-0052509 | T29: 45322 | U29: 653.32023 | W29: 45351 | AA29: AC Labour | AB29: 64553.2 | AD29: AC Labour | AE29: 0
B30: 4 | D30: Earth Cable | E30: 10465 | F30: 13.5 | G30: =E30*F30 -> 141277.5 | H30: =H48 -> 45264 | M30: 4 | N30: 4. DC Equipment | O30: DC Equipment - Deposit | P30: 0.5 | Q30: =AE25 -> 133659.15 | R30: 66829.57 | S30: Cosmic Sun Inv: CS_BMG_001 | T30: 45291 | U30: 62006.03 | W30: 45281 | AA30: DC Labour | AB30: 0 | AD30: DC Labour | AE30: 190000
B31: 4 | D31: Earth clamp | E31: 63 | F31: 16 | G31: =E31*F31 -> 1008 | H31: =H49 -> 45352 | M31: 4 | N31: 4. DC Equipment | O31: DC Equipment - Onsite | P31: 0.4 | R31: =P31*$Q$30 -> 53463.66 | S31: Cosmic Sun Inv: CS_BMG_003 | T31: 45351 | U31: 43661.114 | W31: ='Project Plan'!K42+7 -> 45323 | AA31: Offloading | AB31: 0 | AD31: Offloading | AE31: 0
B32: 4 | D32: DC Cable Tray | E32: 230 | F32: 135 | G32: =E32*F32 -> 31050 | H32: =H50 -> 45352 | M32: 4 | N32: 4. DC Equipment | O32: DC Equipment - Retention | P32: 0.1 | R32: =P32*$Q$30 -> 13365.915 | S32: Cosmic Sun Inv: CS_BMG_006 | T32: 45412 | U32: 3485.6384 | W32: 45407 | AA32: Roof Access | AB32: 0 | AD32: Roof Access | AE32: 71843.09
AA33: Logistics | AB33: 4570 | AD33: Anchor Points | AE33: 50251.13
B34: 5 | C34: Monitoring | D34: Solarlog | G34: 26000 | H34: =H13 -> 45302 | J34: =SUM(G34:G46) -> 49000 | K34: 54659.619 | M34: 5 | N34: 5. Monitoring | O34: Additional Meter | U34: 0 | V34: =K34-SUM(U34:U46) -> 0.0021696851 | X34: =SUM(R34:R46) -> 438053.51 | AA34: P&G | AB34: 12150 | AD34: HSE | AE34: 4500
B35: 5 | M35: 5 | N35: 5. Monitoring | O35: CTs - To be removed (EE Stock 1000A Rogowski Coils with Integrator kit) | R35: 11604 | S35: Accuenergy Inv: ASAI-003146 | T35: 45443 | U35: 1232.3902 | W35: 45473 | Y35: PO3133-BMG-20240528 | Z35: Request Tax Invoice from Accu | AA35: DC Busbar DB Not included - Est 94k | AD35: Other | AE35: 0
M36: 5 | N36: 5. Monitoring | O36: CTs - To be removed (EE Stock 1000A Rogowski Coils with Integrator kit) | R36: -11604 | S36: Allocated to Nampak | T36: 45504 | U36: 0 | W36: 45504 | Z36: KN: This was sent to Roedolph
B37: 5 | D37: Comms DB | G37: 8000 | H37: =H30 -> 45264 | M37: 5 | N37: 5. Monitoring | O37: CTs | R37: =1680+3240 -> 4920 | S37: Accuenergy Inv: ASAI-002374 | T37: 45322 | U37: 622.67188 | W37: 45351 | Y37: PO2914-BMGP2-20231218 | AA37: Other | AB37: 0 | AD37: Other | AE37: 0
B38: 5 | D38: Revenue Grade Meter | G38: 15000 | H38: =H37 -> 45264 | M38: 5 | N38: 5. Monitoring | O38: Ferite Core for Comms Cable | R38: 125.66 | S38: Tanaka's Exp Claim | T38: 45412 | U38: 0 | W38: 45421 | Z38: TC: Added cost | AA38: Total | AB38: =SUM(AB24:AB35) -> 1267353 | AD38: Total | AE38: =SUM(AE24:AE35) -> 450253.37
B39: 5 | M39: 5 | N39: 5. Monitoring | O39: techsitter | R39: 11169 | S39: Techsitter Inv: MN8940230 | T39: 45322 | U39: 1413.5411 | W39: 45351 | AA39: R/Wp | AB39: =+AB38/'Project Plan'!E3/1000 -> 3.6210087 | AD39: R/Wp | AE39: =+AE38/'Project Plan'!E3/1000 -> 1.2864382
B40: 5 | M40: 5 | N40: 5. Monitoring | O40: Network Switch | R40: =1950+100+540 -> 2590 | S40: Accuenergy Inv: ASAI-002374 | T40: 45322 | U40: 327.78865 | W40: 45351 | Y40: PO2914-BMGP2-20231218
B41: 5 | M41: 5 | N41: 5. Monitoring | O41: Delivery | R41: 150 | S41: Accuenergy Inv: ASAI-002374 | T41: =T40 -> 45322 | U41: 18.983899 | W41: 45351 | Y41: PO2914-BMGP2-20231218
B42: 5 | M42: 5 | N42: 5. Monitoring | O42: Elum Controller- Krannich order | R42: 403848.42 | S42: Krannich Inv: 15-10009002 | T42: 45412 | U42: 50730.33 | W42: 45443 | Y42: PO3005-BMG-P2-20240314
B43: 5 | M43: 5 | N43: 5. Monitoring | O43: Power Supply | R43: 2388 | S43: Mantech Inv: SOR947028 | T43: 45291 | U43: 313.91038 | W43: 45281
M44: 5 | N44: 5. Monitoring | O44: Additional Meter | T44: 45716 | W44: 45744 | Y44: PO3628-BMG-20250205 - RV Approved
M45: 5 | N45: 5. Monitoring | O45: Additional CTs and Meter - AccuEnergy | R45: 7080 | S45: Accuenergy Inv: ASAI-006969 | T45: 45991 | W45: 46022 | Y45: PO4502-BMGP2-20251127
B46: 5 | M46: 5 | N46: 5. Monitoring | O46: Meter | R46: 5782.43 | S46: Allocated from Stock | T46: 45535 | W46: 45535 | Z46: This can be removed: KN
B48: 6 | C48: AC Equipment | D48: AC Equipment Deposit | F48: 0.5 | G48: =F48*C49 -> 125167.71 | H48: ='Project Plan'!E27-7 -> 45264 | J48: =SUM(G48:G53) -> 250335.42 | K48: 279249.76 | M48: 6 | N48: 6. AC Equipment | O48: AC Equipment Deposit | P48: 0.5 | Q48: =AB24-302612.75 -> 883467.1 | R48: =P48*$Q$48 -> 441733.55 | S48: Matthews Group: INV-1144 | T48: 45291 | U48: 104001.42 | V48: =K48-SUM(U48:U53) -> 0 | W48: 45303 | X48: =SUM(R48:R53) -> 1186079.8
B49: 6 | C49: 250335.42 | D49: AC Equipment On site | F49: 0.4 | G49: =F49*C49 -> 100134.17 | H49: ='Project Plan'!G32+7 -> 45352 | M49: 6 | N49: 6. AC Equipment | O49: AC Equipment On site | P49: 0.4 | R49: =P49*$Q$48 -> 353386.84 | S49: Matthews Group: INV-1167 | T49: 45382 | U49: 83201.137 | W49: 45373
B50: 6 | D50: Retention | F50: 0.1 | G50: =F50*C49 -> 25033.542 | H50: =H49 -> 45352 | M50: 6 | N50: 6. AC Equipment | O50: Retention | P50: 0.1 | R50: =P50*$Q$48 -> 88346.71 | S50: Matthews Group: INV-1293 | T50: 45504 | U50: 20800.284 | W50: 45540
M51: 6 | N51: 6. AC Equipment | O51: AC Board Deposit | Q51: 302612.75 | R51: =302612.75*0.5 -> 151306.38 | S51: Matthews Group: INV-1144 | T51: 45291 | U51: 35623.461 | W51: 45278
M52: 6 | N52: 6. AC Equipment | O52: AC Board Balance | R52: =302612.75*0.5 -> 151306.38 | S52: Matthews Group: INV-1167 | T52: 45382 | U52: 35623.461 | W52: =W49 -> 45373
B53: 6 | M53: 6 | N53: 6. AC Equipment | O53: DC Busbar - Removed Cost | U53: =R53/$X$48*$K$48 -> 0
B55: 7 | C55: Battery Systems | D55: Battery Inverter + Battery Bank | G55: 9564809 | H55: ='Project Plan'!I33+14 -> 45320 | J55: =SUM(G55:G74) -> 10380642 | K55: 11579632 | M55: 7 | N55: 7. Battery Systems | O55: Freedom Won Battery 300/240kWh HV | P55: 6 | Q55: 1391200 | R55: =1000000/1.15 -> 869565.22 | S55: Herholdt's Inv: INV720872 | T55: 45260 | U55: 1039087.1 | V55: =K55-SUM(U55:U74) -> 0.0022428036 | W55: 45203 | X55: =SUM(R55:R74) -> 9684222
N56: 7. Battery Systems | O56: Freedom Won Battery 300/240kWh HV | R56: =2314898/1.15 -> 2012954.8 | S56: Herholdt's Inv: INV720872 | T56: 45260 | U56: 2405380.8 | W56: 45219
N57: 7. Battery Systems | O57: Freedom Won Battery 300/240kWh HV | R57: =500000/1.15 -> 434782.61 | S57: Herholdt's Inv: INV720872 | T57: 45260 | U57: 519543.57 | W57: 45233
N58: 7. Battery Systems | O58: Freedom Won Battery 300/240kWh HV | R58: =4400000/1.15 -> 3826087 | S58: Herholdt's Inv: INV720872 | T58: 45260 | U58: 4571983.4 | W58: 45240
N59: 7. Battery Systems | O59: Freedom Won Battery 300/240kWh HV | R59: =8347200-R55-R56-R57-R58 -> 1203810.4 | S59: Herholdt's Inv: INV720872 | T59: 45260 | U59: 1438493.5 | W59: 45240
B60: 7 | M60: 7 | N60: 7. Battery Systems | O60: Atess-PCS630 | R60: 545000 | S60: Herholdt's Inv: INV720872 | T60: 45260 | U60: 651247.87 | W60: 45253
B61: 7 | M61: 7 | N61: 7. Battery Systems | O61: Atess 630kW Bypass Cabinet | R61: 380800 | S61: Herholdt's Inv: INV720872 | T61: 45260 | U61: 455037.04 | W61: 45253
B62: 7 | M62: 7 | N62: 7. Battery Systems | O62: Atess 630kW Isolation Transformer | R62: 311600 | S62: Herholdt's Inv: INV720872 | T62: 45260 | U62: 372346.49 | W62: 45253
B63: 7 | M63: 7 | N63: 7. Battery Systems | O63: Atess Enerlog Monitoring Module | R63: 11900 | S63: Herholdt's Inv: INV720872 | T63: 45260 | U63: 14219.908 | W63: 45253
N64: 7. Battery Systems | O64: Atess Enerlog Monitoring Module - Credit | R64: -10710 | S64: Herholdt's CN070484 | T64: 45291 | U64: -12783.999 | W64: 45260
B65: 7 | M65: 7 | N65: 7. Battery Systems | O65: Atess PV Combiner Box 16 Input 1 Output | R65: 11900 | S65: Herholdt's Inv: INV720872 | T65: 45260 | U65: 14219.908 | W65: 45253
B66: 7 | M66: 7 | N66: 7. Battery Systems | O66: Atess PV Combiner Box 16 Input 1 Output - Credit | R66: -10710 | S66: Herholdt's CN070484 | T66: 45291 | U66: -12783.999 | W66: 45260
B67: 7 | D67: Installation | G67: 382500 | H67: =H86 -> 45264 | M67: 7 | N67: 7. Battery Systems | U67: 0
B68: 7 | D68: AC+DC Equipment | G68: 433333.33 | H68: =H89 -> 45357 | M68: 7 | N68: 7. Battery Systems | O68: Data Guru (Cost removed) | U68: 0
B69: 7 | M69: 7 | N69: 7. Battery Systems | O69: Delivery And Rigging | R69: =31192 -> 31192 | S69: E&M Plant Inv: IN111028 | T69: 45291 | U69: 37232.352 | W69: 45268
M70: 7 | N70: 7. Battery Systems | O70: Safety File | R70: 3000 | S70: E&M Plant Inv: IN111028 | T70: 45291 | U70: 3580.9521 | W70: 45268
M71: 7 | N71: 7. Battery Systems | O71: Delivery And Rigging - Additional cost | R71: 15100 | S71: E&M Plant Inv: IN111062 | T71: 45291 | U71: 18024.125 | W71: 45282 | Y71: PO2916-BMGP2-20231219 | Z71: Incorrect Dimensions supplied to the Company
N72: 7. Battery Systems | O72: Delivery And Rigging - Additional cost | R72: -7550 | S72: E&M Plant Credit Note: IC100085 | T72: 45291 | U72: 0 | W72: 45271
N73: 7. Battery Systems | O73: Rigging - shift batteries to install battery cable | R73: 55500 | S73: E&M Plant - Inv IO103047 | T73: 45412 | U73: 64802.52 | W73: 45397 | Y73: PO3045-BMG-P2-20240408
B74: 7 | M74: 7 | N74: 7. Battery Systems | Z74: RV: Removed 60k
B76: 8 | C76: Product Add On | J76: =SUM(G76:G84) -> 0 | K76: 0 | M76: 8 | N76: 8. Product Add On | O76: AC Tie-in breaker | R76: 32856.48 | S76: MG INV-1232 | T76: 45443 | U76: 0 | V76: =K76-SUM(U76:U84) -> 0 | W76: 45449 | X76: =SUM(R76:R84) -> 291094.63
B77: 8 | M77: 8 | N77: 8. Product Add On | O77: Trenching - Deposit | R77: 16045.8 | S77: Mkholo Inv: MP /EE/150124 | T77: 45322 | U77: 0 | W77: 45330
B78: 8 | M78: 8 | N78: 8. Product Add On | O78: Trenching - Balance | R78: 15045.8 | S78: Mkholo Inv: MP /EE/260224 | T78: 45351 | U78: 0 | W78: 45351
M79: 8 | N79: 8. Product Add On | O79: Ring Cores | R79: 267.15 | S79: Tanaka's Exp Claim | T79: 45443 | U79: 0 | W79: 45449
M80: 8 | N80: 8. Product Add On | O80: Steel Covers | R80: 21890 | S80: Mkholo Projects: InvMP/EE?240724 | T80: 45504 | U80: 0 | W80: 45497 | Y80: PO3257-BMGP2-20240724 - RV Approved
M81: 8 | N81: 8. Product Add On | O81: Re-Routing of cables | P81: 0.5 | Q81: 202189.4 | R81: =P81*Q81 -> 101094.7 | S81: MG INV-1291 | T81: 45504 | U81: 0 | W81: 45505 | Y81: VO approved by Johannes e-mail 29 July
M82: 8 | N82: 8. Product Add On | O82: Re-Routing of cables | P82: 0.5 | R82: =Q81*P82 -> 101094.7 | S82: MG INV-1291 | T82: 45504 | U82: 0 | W82: 45533
N83: 8. Product Add On | O83: Repairs on steel covers
B84: 8 | M84: 8 | N84: 8. Product Add On | O84: Man Hole | R84: 2800 | S84: Mkholo Inv: MP/EE/080424 | T84: 45412 | U84: 0 | W84: 45400
L85: Only services to be capture below, products above
B86: 9 | C86: AC & DC installation | D86: Installation Deposit | F86: 0.2 | G86: =SUM(C87:C88)*F86 -> 41895 | H86: ='Project Plan'!E27-7 -> 45264 | J86: =SUM(G86:G93) -> 209475 | K86: 261843.75 | M86: 9 | N86: 9. AC installation | O86: Deposit | P86: 0.25 | R86: 16138.3 | S86: Matthews Group Inv: 1144 | T86: 45291 | U86: 16600.51 | V86: =K86-SUM(U86:U93) -> 0 | W86: 45303 | X86: =SUM(R86:R93) -> 254553.2
B87: 9 | D87: MS Complete | F87: 0.15 | G87: =SUM($C$87:$C$88)*F87 -> 31421.25 | H87: ='Project Plan'!G33+7 -> 45352 | M87: 9 | N87: 9. AC installation | O87: AC Tie-in | P87: 0.25 | R87: 16138.3 | S87: Matthews Group Inv 1238 | T87: 45443 | U87: 16600.51 | W87: 45449
B88: 9 | C88: 209475 | D88: AC Tie-in Complete | F88: 0.15 | G88: =SUM($C$87:$C$88)*F88 -> 31421.25 | H88: ='Project Plan'!G43+7 -> 45341 | M88: 9 | N88: 9. AC installation | O88: Practical Completion | P88: 0.25 | R88: 16138.3 | S88: Matthews Group Inv 1279 | T88: 45504 | U88: 16600.51 | W88: 45492
B89: 9 | C89: 0 | D89: Panels Complete | F89: 0.15 | G89: =SUM($C$87:$C$88)*F89 -> 31421.25 | H89: ='Project Plan'!G50+7 -> 45357 | M89: 9 | N89: 9. AC installation | O89: Retention | P89: 0.25 | R89: 16138.3 | S89: Matthews Group: INV-1293 | T89: 45504 | U89: 16600.51 | W89: 45540
B90: 9 | D90: Practical Completion | F90: 0.2 | G90: =SUM($C$87:$C$88)*F90 -> 41895 | H90: ='Project Plan'!G59+14 -> 45383 | M90: 9 | N90: 9. DC installation | O90: Deposit | P90: 0.25 | R90: 47500 | S90: Cosmic Sun Inv: CS_BMG_001 | T90: 45291 | U90: 48860.427 | W90: 45282
B91: 9 | D91: Retention | F91: 0.15 | G91: =SUM($C$87:$C$88)*F91 -> 31421.25 | H91: =H90 -> 45383 | M91: 9 | N91: 9. DC installation | O91: MS Complete | P91: 0.25 | R91: 47500 | S91: Cosmic Sun Inv: CS_BMG_002 | T91: 45382 | U91: 48860.427 | W91: 45407
N92: 9. DC installation | O92: Panels Complete | P92: 0.25 | R92: 47500 | S92: Cosmic Sun Inv. CS_BMG_005 | T92: 45382 | U92: 48860.427 | W92: 45386
B93: 9 | M93: 9 | N93: 9. DC installation | O93: Retention | P93: 0.25 | R93: 47500 | S93: Cosmic Sun Inv. CS_BMG_006 | T93: 45412 | U93: 48860.427 | W93: 45407
B95: 10 | C95: Site Logistics | D95: Scaffolding | G95: 25122.9 | H95: =H86 -> 45264 | J95: =SUM(G95:G102) -> 60622.9 | K95: 75779 | M95: 10 | N95: 10. Site Logistics - AC | O95: Logistics Deposit | P95: 0.5 | Q95: =AB33+AB34 -> 16720 | R95: =P95*$Q$95 -> 8360 | S95: Matthews Group Inv: 1144 | T95: 45291 | U95: 4420.4437 | V95: =K95-SUM(U95:U102) -> 0 | W95: 45303 | X95: =SUM(R95:R102) -> 143314.22
B96: 10 | M96: 10 | N96: 10. Site Logistics - AC | O96: Logistics - Equipment Onsite | P96: 0.4 | R96: =P96*$Q$95 -> 6688 | S96: Matthews Group Inv: 1167 | T96: 45382 | U96: 3536.355 | W96: =W52 -> 45373
B97: 10 | M97: 10 | N97: 10. Site Logistics - AC | O97: Logistics - Retention | P97: 0.1 | R97: =P97*$Q$95 -> 1672 | S97: Matthews Group: INV-1293 | T97: 45504 | U97: 884.08874 | W97: =W89 -> 45540
B98: 10 | D98: Offloading | G98: 8500 | H98: =H86 -> 45264 | M98: 10 | U98: =R98/$X$95*$K$95 -> 0
B99: 10 | M99: 10 | N99: 10. Site Logistics - DC | O99: Logistics Deposit | P99: 0.5 | Q99: =AE32+AE33+AE34 -> 126594.22 | R99: =$Q$99*P99 -> 63297.11 | S99: Cosmic Sun Inv: CS_BMG_001 | T99: 45291 | U99: 33469.056 | W99: 45282
B100: 10 | D100: Telehandler | G100: 27000 | H100: =H98 -> 45264 | M100: 10 | N100: 10. Site Logistics - DC | O100: Logistics - Equipment Onsite | P100: 0.4 | R100: =$Q$99*P100 -> 50637.688 | S100: Cosmic Sun Inv: CS_BMG_004 | T100: 45382 | U100: 26775.245 | W100: 45323
B101: 10 | M101: 10 | N101: 10. Site Logistics - DC | O101: Logistics - Retention | P101: 0.1 | R101: =$Q$99*P101 -> 12659.422 | S101: Cosmic Sun Inv. CS_BMG_006 | T101: 45412 | U101: 6693.8113 | W101: 45407
B102: 10 | M102: 10 | U102: =R102/$X$95*$K$95 -> 0
B104: 11 | C104: Due Dilligence | D104: Structural sign off | G104: 8000 | H104: ='Project Plan'!E27 -> 45271 | J104: =SUM(G104:G108) -> 19000 | K104: 23750 | M104: 11 | N104: 11. Due Dilligence | O104: Structural sign off | R104: 5500 | S104: L&B INV-1448 | T104: 45230 | U104: 7916.6667 | V104: =K104-SUM(U104:U108) -> -0.0043007999 | W104: 45205 | X104: =SUM(R104:R108) -> 11683.16 | Z104: Changed amount it was 8k -TC
B105: 11 | D105: Electrical PrEng sign off | G105: 11000 | H105: ='Project Plan'!G59+14 -> 45383 | M105: 11 | N105: 11. Due Dilligence | O105: Electrical Sign off | R105: 6183.16 | S105: MJ Bleloch Inv: 1216 | T105: 45443 | U105: 15833.338 | W105: 45449
B106: 11 | M106: 11 | U106: =R106/$X$104*$K$104 -> 0
B107: 11 | M107: 11 | U107: =R107/$X$104*$K$104 -> 0
B108: 11 | M108: 11 | U108: =R108/$X$104*$K$104 -> 0
...

Sheet Cashflow
D1: [RT: Double Check the first date is always a MONDAY] | F1: 45138 | G1: =F1+7 -> 45145 | H1: =G1+7 -> 45152 | I1: =H1+7 -> 45159 | J1: =I1+7 -> 45166 | K1: =J1+7 -> 45173 | L1: =K1+7 -> 45180 | M1: =L1+7 -> 45187 | N1: =M1+7 -> 45194 | ... GF1: =GE1+7 -> 46412
A2: PLANNED | C2: CHECK | D2: CHECK
B3: Planned Revenue | C3: ='Revenue Tracking'!D4 -> 14953088 | D3: =SUM(F3:BE3) -> 15251088 | F3: =SUMIFS('Revenue Tracking'!$F$13:$F$20, 'Revenue Tracking'!$H$13:$H$20, ">="&F1,'Revenue Tracking'!$H$13:$H$20, "<"&G1) -> 0 | G3: =SUMIFS('Revenue Tracking'!$F$13:$F$20, 'Revenue Tracking'!$H$13:$H$20, ">="&G1,'Revenue Tracking'!$H$13:$H$20, "<"&H1) -> 0 | H3: =SUMIFS('Revenue Tracking'!$F$13:$F$20, 'Revenue Tracking'!$H$13:$H$20, ">="&H1,'Revenue Tracking'!$H$13:$H$20, "<"&I1) -> 0 | I3: =SUMIFS('Revenue Tracking'!$F$13:$F$20, 'Revenue Tracking'!$H$13:$H$20, ">="&I1,'Revenue Tracking'!$H$13:$H$20, "<"&J1) -> 0 | J3: =SUMIFS('Revenue Tracking'!$F$13:$F$20, 'Revenue Tracking'!$H$13:$H$20, ">="&J1,'Revenue Tracking'!$H$13:$H$20, "<"&K1) -> 8971853 | K3: =SUMIFS('Revenue Tracking'!$F$13:$F$20, 'Revenue Tracking'!$H$13:$H$20, ">="&K1,'Revenue Tracking'!$H$13:$H$20, "<"&L1) -> 0 | L3: =SUMIFS('Revenue Tracking'!$F$13:$F$20, 'Revenue Tracking'!$H$13:$H$20, ">="&L1,'Revenue Tracking'!$H$13:$H$20, "<"&M1) -> 0 | M3: =SUMIFS('Revenue Tracking'!$F$13:$F$20, 'Revenue Tracking'!$H$13:$H$20, ">="&M1,'Revenue Tracking'!$H$13:$H$20, "<"&N1) -> 0 | ... BD3: =SUMIFS('Revenue Tracking'!$F$13:$F$20, 'Revenue Tracking'!$H$13:$H$20, ">="&BD1,'Revenue Tracking'!$H$13:$H$20, "<"&BE1) -> 0 | BE3: =SUMIFS('Revenue Tracking'!$F$13:$F$20, 'Revenue Tracking'!$H$13:$H$20, ">="&BE1,'Revenue Tracking'!$H$13:$H$20, "<"&GG1) -> 0 | BF3: =SUMIFS('Revenue Tracking'!$F$13:$F$20, 'Revenue Tracking'!$H$13:$H$20, ">="&BF1,'Revenue Tracking'!$H$13:$H$20, "<"&GH1) -> 0 | BG3: =SUMIFS('Revenue Tracking'!$F$13:$F$20, 'Revenue Tracking'!$H$13:$H$20, ">="&BG1,'Revenue Tracking'!$H$13:$H$20, "<"&GI1) -> 0 | BH3: =SUMIFS('Revenue Tracking'!$F$13:$F$20, 'Revenue Tracking'!$H$13:$H$20, ">="&BH1,'Revenue Tracking'!$H$13:$H$20, "<"&GJ1) -> 0 | BI3: =SUMIFS('Revenue Tracking'!$F$13:$F$20, 'Revenue Tracking'!$H$13:$H$20, ">="&BI1,'Revenue Tracking'!$H$13:$H$20, "<"&GK1) -> 0 | BJ3: =SUMIFS('Revenue Tracking'!$F$13:$F$20, 'Revenue Tracking'!$H$13:$H$20, ">="&BJ1,'Revenue Tracking'!$H$13:$H$20, "<"&GL1) -> 0 | BK3: =SUMIFS('Revenue Tracking'!$F$13:$F$20, 'Revenue Tracking'!$H$13:$H$20, ">="&BK1,'Revenue Tracking'!$H$13:$H$20, "<"&GM1) -> 0 | BL3: =SUMIFS('Revenue Tracking'!$F$13:$F$20, 'Revenue Tracking'!$H$13:$H$20, ">="&BL1,'Revenue Tracking'!$H$13:$H$20, "<"&GN1) -> 0 | ... GF3: =SUMIFS('Revenue Tracking'!$F$13:$F$20, 'Revenue Tracking'!$H$13:$H$20, ">="&GF1,'Revenue Tracking'!$H$13:$H$20, "<"&LH1) -> 0
B4: Planned Revenue - Cumulative | F4: =F3 -> 0 | G4: =F4+G3 -> 0 | H4: =G4+H3 -> 0 | I4: =H4+I3 -> 0 | J4: =I4+J3 -> 8971853 | K4: =J4+K3 -> 8971853 | L4: =K4+L3 -> 8971853 | M4: =L4+M3 -> 8971853 | N4: =M4+N3 -> 8971853 | ... GF4: =GE4+GF3 -> 15251088
B5: Planned Expenditure | C5: ='Revenue Tracking'!D5 -> 13282858 | D5: =SUM(F5:BE5) -> 13282858 | F5: =SUMIFS('Expenditure Breakdown'!$G$6:$G$138, 'Expenditure Breakdown'!$H$6:$H$138, ">="&F1,'Expenditure Breakdown'!$H$6:$H$138, "<"&G1) -> 0 | G5: =SUMIFS('Expenditure Breakdown'!$G$6:$G$138, 'Expenditure Breakdown'!$H$6:$H$138, ">="&G1,'Expenditure Breakdown'!$H$6:$H$138, "<"&H1) -> 0 | H5: =SUMIFS('Expenditure Breakdown'!$G$6:$G$138, 'Expenditure Breakdown'!$H$6:$H$138, ">="&H1,'Expenditure Breakdown'!$H$6:$H$138, "<"&I1) -> 0 | I5: =SUMIFS('Expenditure Breakdown'!$G$6:$G$138, 'Expenditure Breakdown'!$H$6:$H$138, ">="&I1,'Expenditure Breakdown'!$H$6:$H$138, "<"&J1) -> 0 | J5: =SUMIFS('Expenditure Breakdown'!$G$6:$G$138, 'Expenditure Breakdown'!$H$6:$H$138, ">="&J1,'Expenditure Breakdown'!$H$6:$H$138, "<"&K1) -> 0 | K5: =SUMIFS('Expenditure Breakdown'!$G$6:$G$138, 'Expenditure Breakdown'!$H$6:$H$138, ">="&K1,'Expenditure Breakdown'!$H$6:$H$138, "<"&L1) -> 0 | L5: =SUMIFS('Expenditure Breakdown'!$G$6:$G$138, 'Expenditure Breakdown'!$H$6:$H$138, ">="&L1,'Expenditure Breakdown'!$H$6:$H$138, "<"&M1) -> 0 | M5: =SUMIFS('Expenditure Breakdown'!$G$6:$G$138, 'Expenditure Breakdown'!$H$6:$H$138, ">="&M1,'Expenditure Breakdown'!$H$6:$H$138, "<"&N1) -> 0 | ... BD5: =SUMIFS('Expenditure Breakdown'!$G$6:$G$138, 'Expenditure Breakdown'!$H$6:$H$138, ">="&BD1,'Expenditure Breakdown'!$H$6:$H$138, "<"&BE1) -> 0 | BE5: =SUMIFS('Expenditure Breakdown'!$G$6:$G$138, 'Expenditure Breakdown'!$H$6:$H$138, ">="&BE1,'Expenditure Breakdown'!$H$6:$H$138, "<"&GG1) -> 0 | BF5: =SUMIFS('Expenditure Breakdown'!$G$6:$G$138, 'Expenditure Breakdown'!$H$6:$H$138, ">="&BF1,'Expenditure Breakdown'!$H$6:$H$138, "<"&GH1) -> 0 | BG5: =SUMIFS('Expenditure Breakdown'!$G$6:$G$138, 'Expenditure Breakdown'!$H$6:$H$138, ">="&BG1,'Expenditure Breakdown'!$H$6:$H$138, "<"&GI1) -> 0 | BH5: =SUMIFS('Expenditure Breakdown'!$G$6:$G$138, 'Expenditure Breakdown'!$H$6:$H$138, ">="&BH1,'Expenditure Breakdown'!$H$6:$H$138, "<"&GJ1) -> 0 | BI5: =SUMIFS('Expenditure Breakdown'!$G$6:$G$138, 'Expenditure Breakdown'!$H$6:$H$138, ">="&BI1,'Expenditure Breakdown'!$H$6:$H$138, "<"&GK1) -> 0 | BJ5: =SUMIFS('Expenditure Breakdown'!$G$6:$G$138, 'Expenditure Breakdown'!$H$6:$H$138, ">="&BJ1,'Expenditure Breakdown'!$H$6:$H$138, "<"&GL1) -> 0 | BK5: =SUMIFS('Expenditure Breakdown'!$G$6:$G$138, 'Expenditure Breakdown'!$H$6:$H$138, ">="&BK1,'Expenditure Breakdown'!$H$6:$H$138, "<"&GM1) -> 0 | BL5: =SUMIFS('Expenditure Breakdown'!$G$6:$G$138, 'Expenditure Breakdown'!$H$6:$H$138, ">="&BL1,'Expenditure Breakdown'!$H$6:$H$138, "<"&GN1) -> 0 | ... GF5: =SUMIFS('Expenditure Breakdown'!$G$6:$G$138, 'Expenditure Breakdown'!$H$6:$H$138, ">="&GF1,'Expenditure Breakdown'!$H$6:$H$138, "<"&LH1) -> 0
B6: Planned Expenditure - Cumulative | F6: =F5 -> 0 | G6: =F6+G5 -> 0 | H6: =G6+H5 -> 0 | I6: =H6+I5 -> 0 | J6: =I6+J5 -> 0 | K6: =J6+K5 -> 0 | L6: =K6+L5 -> 0 | M6: =L6+M5 -> 0 | N6: =M6+N5 -> 0 | ... GF6: =GE6+GF5 -> 13282858
B7: PLANNED CashFlow | F7: =F4-F6 -> 0 | G7: =G4-G6 -> 0 | H7: =H4-H6 -> 0 | I7: =I4-I6 -> 0 | J7: =J4-J6 -> 8971853 | K7: =K4-K6 -> 8971853 | L7: =L4-L6 -> 8971853 | M7: =M4-M6 -> 8971853 | ... GF7: =GF4-GF6 -> 1968230.6
A8: ACTUAL | C8: CHECK | D8: CHECK
B9: Actual + Planned Revenue | C9: ='Revenue Tracking'!F4 -> 15251088 | D9: =SUM(F9:GF9) -> 15251088 | F9: =SUMIFS('Revenue Tracking'!$F$13:$F$20, 'Revenue Tracking'!$P$13:$P$20, ">="&F1,'Revenue Tracking'!$P$13:$P$20, "<"&G1) -> 8971853 | G9: =SUMIFS('Revenue Tracking'!$F$13:$F$20, 'Revenue Tracking'!$P$13:$P$20, ">="&G1,'Revenue Tracking'!$P$13:$P$20, "<"&H1) -> 0 | H9: =SUMIFS('Revenue Tracking'!$F$13:$F$20, 'Revenue Tracking'!$P$13:$P$20, ">="&H1,'Revenue Tracking'!$P$13:$P$20, "<"&I1) -> 0 | I9: =SUMIFS('Revenue Tracking'!$F$13:$F$20, 'Revenue Tracking'!$P$13:$P$20, ">="&I1,'Revenue Tracking'!$P$13:$P$20, "<"&J1) -> 0 | J9: =SUMIFS('Revenue Tracking'!$F$13:$F$20, 'Revenue Tracking'!$P$13:$P$20, ">="&J1,'Revenue Tracking'!$P$13:$P$20, "<"&K1) -> 0 | K9: =SUMIFS('Revenue Tracking'!$F$13:$F$20, 'Revenue Tracking'!$P$13:$P$20, ">="&K1,'Revenue Tracking'!$P$13:$P$20, "<"&L1) -> 0 | L9: =SUMIFS('Revenue Tracking'!$F$13:$F$20, 'Revenue Tracking'!$P$13:$P$20, ">="&L1,'Revenue Tracking'!$P$13:$P$20, "<"&M1) -> 0 | M9: =SUMIFS('Revenue Tracking'!$F$13:$F$20, 'Revenue Tracking'!$P$13:$P$20, ">="&M1,'Revenue Tracking'!$P$13:$P$20, "<"&N1) -> 0 | ... GF9: =SUMIFS('Revenue Tracking'!$F$13:$F$20, 'Revenue Tracking'!$P$13:$P$20, ">="&GF1,'Revenue Tracking'!$P$13:$P$20, "<"&GG1) -> 0
B10: Actual + Planned Revenue - Cumulative | F10: =F9 -> 8971853 | G10: =F10+G9 -> 8971853 | H10: =G10+H9 -> 8971853 | I10: =H10+I9 -> 8971853 | J10: =I10+J9 -> 8971853 | K10: =J10+K9 -> 8971853 | L10: =K10+L9 -> 8971853 | M10: =L10+M9 -> 8971853 | N10: =M10+N9 -> 8971853 | ... GF10: =GE10+GF9 -> 15251088
B11: Actual + Planned Expenditure | C11: ='Revenue Tracking'!F5 -> 14161976 | D11: =SUM(F11:BE11) -> 13850081 | F11: =SUMIFS('Expenditure Breakdown'!$R$6:$R$138, 'Expenditure Breakdown'!$W$6:$W$138, ">="&F1,'Expenditure Breakdown'!$W$6:$W$138, "<"&G1) -> 0 | G11: =SUMIFS('Expenditure Breakdown'!$R$6:$R$138, 'Expenditure Breakdown'!$W$6:$W$138, ">="&G1,'Expenditure Breakdown'!$W$6:$W$138, "<"&H1) -> 0 | H11: =SUMIFS('Expenditure Breakdown'!$R$6:$R$138, 'Expenditure Breakdown'!$W$6:$W$138, ">="&H1,'Expenditure Breakdown'!$W$6:$W$138, "<"&I1) -> 0 | I11: =SUMIFS('Expenditure Breakdown'!$R$6:$R$138, 'Expenditure Breakdown'!$W$6:$W$138, ">="&I1,'Expenditure Breakdown'!$W$6:$W$138, "<"&J1) -> 0 | J11: =SUMIFS('Expenditure Breakdown'!$R$6:$R$138, 'Expenditure Breakdown'!$W$6:$W$138, ">="&J1,'Expenditure Breakdown'!$W$6:$W$138, "<"&K1) -> 5847.36 | K11: =SUMIFS('Expenditure Breakdown'!$R$6:$R$138, 'Expenditure Breakdown'!$W$6:$W$138, ">="&K1,'Expenditure Breakdown'!$W$6:$W$138, "<"&L1) -> 0 | L11: =SUMIFS('Expenditure Breakdown'!$R$6:$R$138, 'Expenditure Breakdown'!$W$6:$W$138, ">="&L1,'Expenditure Breakdown'!$W$6:$W$138, "<"&M1) -> 0 | M11: =SUMIFS('Expenditure Breakdown'!$R$6:$R$138, 'Expenditure Breakdown'!$W$6:$W$138, ">="&M1,'Expenditure Breakdown'!$W$6:$W$138, "<"&N1) -> 0 | ... CJ11: =SUMIFS('Expenditure Breakdown'!$R$6:$R$138, 'Expenditure Breakdown'!$W$6:$W$138, ">="&CJ1,'Expenditure Breakdown'!$W$6:$W$138, "<"&CK1) -> 0 | CK11: =SUMIFS('Expenditure Breakdown'!$R$6:$R$138, 'Expenditure Breakdown'!$W$6:$W$138, ">="&CK1,'Expenditure Breakdown'!$W$6:$W$138, "<"&GG1) -> 0 | CL11: =SUMIFS('Expenditure Breakdown'!$R$6:$R$138, 'Expenditure Breakdown'!$W$6:$W$138, ">="&CL1,'Expenditure Breakdown'!$W$6:$W$138, "<"&GH1) -> 0 | CM11: =SUMIFS('Expenditure Breakdown'!$R$6:$R$138, 'Expenditure Breakdown'!$W$6:$W$138, ">="&CM1,'Expenditure Breakdown'!$W$6:$W$138, "<"&GI1) -> 0 | CN11: =SUMIFS('Expenditure Breakdown'!$R$6:$R$138, 'Expenditure Breakdown'!$W$6:$W$138, ">="&CN1,'Expenditure Breakdown'!$W$6:$W$138, "<"&GJ1) -> 0 | CO11: =SUMIFS('Expenditure Breakdown'!$R$6:$R$138, 'Expenditure Breakdown'!$W$6:$W$138, ">="&CO1,'Expenditure Breakdown'!$W$6:$W$138, "<"&GK1) -> 0 | CP11: =SUMIFS('Expenditure Breakdown'!$R$6:$R$138, 'Expenditure Breakdown'!$W$6:$W$138, ">="&CP1,'Expenditure Breakdown'!$W$6:$W$138, "<"&GL1) -> 0 | CQ11: =SUMIFS('Expenditure Breakdown'!$R$6:$R$138, 'Expenditure Breakdown'!$W$6:$W$138, ">="&CQ1,'Expenditure Breakdown'!$W$6:$W$138, "<"&GM1) -> 0 | CR11: =SUMIFS('Expenditure Breakdown'!$R$6:$R$138, 'Expenditure Breakdown'!$W$6:$W$138, ">="&CR1,'Expenditure Breakdown'!$W$6:$W$138, "<"&GN1) -> 0 | ... GF11: =SUMIFS('Expenditure Breakdown'!$R$6:$R$138, 'Expenditure Breakdown'!$W$6:$W$138, ">="&GF1,'Expenditure Breakdown'!$W$6:$W$138, "<"&KB1) -> 0
B12: Actual + Planned Expenditure - Cumulative | F12: =F11 -> 0 | G12: =F12+G11 -> 0 | H12: =G12+H11 -> 0 | I12: =H12+I11 -> 0 | J12: =I12+J11 -> 5847.36 | K12: =J12+K11 -> 5847.36 | L12: =K12+L11 -> 5847.36 | M12: =L12+M11 -> 5847.36 | N12: =M12+N11 -> 5847.36 | ... GF12: =GE12+GF11 -> 14154896
B14: ACTUAL CashFlow | F14: =F10-F12 -> 8971853 | G14: =G10-G12 -> 8971853 | H14: =H10-H12 -> 8971853 | I14: =I10-I12 -> 8971853 | J14: =J10-J12 -> 8966005.6 | K14: =K10-K12 -> 8966005.6 | L14: =L10-L12 -> 8966005.6 | M14: =M10-M12 -> 8966005.6 | ... GF14: =GF10-GF12 -> 1096192.8
C16: CHECK | D16: CHECK
B17: Revenue Recognition | C17: =C3-D17 -> -243114.98 | D17: =SUM(F17:BE17) -> 15196203 | F17: =SUMIFS('Expenditure Breakdown'!$U$6:$U$138, 'Expenditure Breakdown'!$T$6:$T$138, ">="&F1,'Expenditure Breakdown'!$T$6:$T$138, "<"&G1) -> 0 | G17: =SUMIFS('Expenditure Breakdown'!$U$6:$U$138, 'Expenditure Breakdown'!$T$6:$T$138, ">="&G1,'Expenditure Breakdown'!$T$6:$T$138, "<"&H1) -> 0 | H17: =SUMIFS('Expenditure Breakdown'!$U$6:$U$138, 'Expenditure Breakdown'!$T$6:$T$138, ">="&H1,'Expenditure Breakdown'!$T$6:$T$138, "<"&I1) -> 0 | I17: =SUMIFS('Expenditure Breakdown'!$U$6:$U$138, 'Expenditure Breakdown'!$T$6:$T$138, ">="&I1,'Expenditure Breakdown'!$T$6:$T$138, "<"&J1) -> 0 | J17: =SUMIFS('Expenditure Breakdown'!$U$6:$U$138, 'Expenditure Breakdown'!$T$6:$T$138, ">="&J1,'Expenditure Breakdown'!$T$6:$T$138, "<"&K1) -> 1680912.5 | K17: =SUMIFS('Expenditure Breakdown'!$U$6:$U$138, 'Expenditure Breakdown'!$T$6:$T$138, ">="&K1,'Expenditure Breakdown'!$T$6:$T$138, "<"&L1) -> 0 | L17: =SUMIFS('Expenditure Breakdown'!$U$6:$U$138, 'Expenditure Breakdown'!$T$6:$T$138, ">="&L1,'Expenditure Breakdown'!$T$6:$T$138, "<"&M1) -> 0 | M17: =SUMIFS('Expenditure Breakdown'!$U$6:$U$138, 'Expenditure Breakdown'!$T$6:$T$138, ">="&M1,'Expenditure Breakdown'!$T$6:$T$138, "<"&N1) -> 0 | ... BD17: =SUMIFS('Expenditure Breakdown'!$U$6:$U$138, 'Expenditure Breakdown'!$T$6:$T$138, ">="&BD1,'Expenditure Breakdown'!$T$6:$T$138, "<"&BE1) -> 0 | BE17: =SUMIFS('Expenditure Breakdown'!$U$6:$U$138, 'Expenditure Breakdown'!$T$6:$T$138, ">="&BE1,'Expenditure Breakdown'!$T$6:$T$138, "<"&GG1) -> 0 | BF17: =SUMIFS('Expenditure Breakdown'!$U$6:$U$138, 'Expenditure Breakdown'!$T$6:$T$138, ">="&BF1,'Expenditure Breakdown'!$T$6:$T$138, "<"&GH1) -> 0 | BG17: =SUMIFS('Expenditure Breakdown'!$U$6:$U$138, 'Expenditure Breakdown'!$T$6:$T$138, ">="&BG1,'Expenditure Breakdown'!$T$6:$T$138, "<"&GI1) -> 0 | BH17: =SUMIFS('Expenditure Breakdown'!$U$6:$U$138, 'Expenditure Breakdown'!$T$6:$T$138, ">="&BH1,'Expenditure Breakdown'!$T$6:$T$138, "<"&GJ1) -> 0 | BI17: =SUMIFS('Expenditure Breakdown'!$U$6:$U$138, 'Expenditure Breakdown'!$T$6:$T$138, ">="&BI1,'Expenditure Breakdown'!$T$6:$T$138, "<"&GK1) -> 0 | BJ17: =SUMIFS('Expenditure Breakdown'!$U$6:$U$138, 'Expenditure Breakdown'!$T$6:$T$138, ">="&BJ1,'Expenditure Breakdown'!$T$6:$T$138, "<"&GL1) -> 0 | BK17: =SUMIFS('Expenditure Breakdown'!$U$6:$U$138, 'Expenditure Breakdown'!$T$6:$T$138, ">="&BK1,'Expenditure Breakdown'!$T$6:$T$138, "<"&GM1) -> 0 | BL17: =SUMIFS('Expenditure Breakdown'!$U$6:$U$138, 'Expenditure Breakdown'!$T$6:$T$138, ">="&BL1,'Expenditure Breakdown'!$T$6:$T$138, "<"&GN1) -> 0 | ... GF17: =SUMIFS('Expenditure Breakdown'!$U$6:$U$138, 'Expenditure Breakdown'!$T$6:$T$138, ">="&GF1,'Expenditure Breakdown'!$T$6:$T$138, "<"&LH1) -> 0
B18: Revenue Recognition Cumulative | C18: =D17-D18 -> 1010351.9 | D18: =MAX(F18:AI18) -> 14185851 | F18: =F17 -> 0 | G18: =F18+G17 -> 0 | H18: =G18+H17 -> 0 | I18: =H18+I17 -> 0 | J18: =I18+J17 -> 1680912.5 | K18: =J18+K17 -> 1680912.5 | L18: =K18+L17 -> 1680912.5 | M18: =L18+M17 -> 1680912.5 | N18: =M18+N17 -> 1680912.5 | ... GF18: =GE18+GF17 -> 15196203
B20: Installer Expenditure | D20: =SUM(F20:BE20) -> 1484855.2 | F20: =SUMIFS('Expenditure Breakdown'!$R$30:$R$33, 'Expenditure Breakdown'!$W$30:$W$33, ">="&F1,'Expenditure Breakdown'!$W$30:$W$33, "<"&G1)+SUMIFS('Expenditure Breakdown'!$R$48:$R$54, 'Expenditure Breakdown'!$W$48:$W$54, ">="&F1,'Expenditure Breakdown'!$W$48:$W$54, "<"&G1)+SUMIFS('Expenditure Breakdown'!$R$86:$R$98, 'Expenditure Breakdown'!$W$86:$W$98, ">="&F1,'Expenditure Breakdown'!$W$86:$W$98, "<"&G1) -> 0 | G20: =SUMIFS('Expenditure Breakdown'!$R$30:$R$33, 'Expenditure Breakdown'!$W$30:$W$33, ">="&G1,'Expenditure Breakdown'!$W$30:$W$33, "<"&H1)+SUMIFS('Expenditure Breakdown'!$R$48:$R$54, 'Expenditure Breakdown'!$W$48:$W$54, ">="&G1,'Expenditure Breakdown'!$W$48:$W$54, "<"&H1)+SUMIFS('Expenditure Breakdown'!$R$86:$R$98, 'Expenditure Breakdown'!$W$86:$W$98, ">="&G1,'Expenditure Breakdown'!$W$86:$W$98, "<"&H1) -> 0 | H20: =SUMIFS('Expenditure Breakdown'!$R$30:$R$33, 'Expenditure Breakdown'!$W$30:$W$33, ">="&H1,'Expenditure Breakdown'!$W$30:$W$33, "<"&I1)+SUMIFS('Expenditure Breakdown'!$R$48:$R$54, 'Expenditure Breakdown'!$W$48:$W$54, ">="&H1,'Expenditure Breakdown'!$W$48:$W$54, "<"&I1)+SUMIFS('Expenditure Breakdown'!$R$86:$R$98, 'Expenditure Breakdown'!$W$86:$W$98, ">="&H1,'Expenditure Breakdown'!$W$86:$W$98, "<"&I1) -> 0 | I20: =SUMIFS('Expenditure Breakdown'!$R$30:$R$33, 'Expenditure Breakdown'!$W$30:$W$33, ">="&I1,'Expenditure Breakdown'!$W$30:$W$33, "<"&J1)+SUMIFS('Expenditure Breakdown'!$R$48:$R$54, 'Expenditure Breakdown'!$W$48:$W$54, ">="&I1,'Expenditure Breakdown'!$W$48:$W$54, "<"&J1)+SUMIFS('Expenditure Breakdown'!$R$86:$R$98, 'Expenditure Breakdown'!$W$86:$W$98, ">="&I1,'Expenditure Breakdown'!$W$86:$W$98, "<"&J1) -> 0 | J20: =SUMIFS('Expenditure Breakdown'!$R$30:$R$33, 'Expenditure Breakdown'!$W$30:$W$33, ">="&J1,'Expenditure Breakdown'!$W$30:$W$33, "<"&K1)+SUMIFS('Expenditure Breakdown'!$R$48:$R$54, 'Expenditure Breakdown'!$W$48:$W$54, ">="&J1,'Expenditure Breakdown'!$W$48:$W$54, "<"&K1)+SUMIFS('Expenditure Breakdown'!$R$86:$R$98, 'Expenditure Breakdown'!$W$86:$W$98, ">="&J1,'Expenditure Breakdown'!$W$86:$W$98, "<"&K1) -> 0 | K20: =SUMIFS('Expenditure Breakdown'!$R$30:$R$33, 'Expenditure Breakdown'!$W$30:$W$33, ">="&K1,'Expenditure Breakdown'!$W$30:$W$33, "<"&L1)+SUMIFS('Expenditure Breakdown'!$R$48:$R$54, 'Expenditure Breakdown'!$W$48:$W$54, ">="&K1,'Expenditure Breakdown'!$W$48:$W$54, "<"&L1)+SUMIFS('Expenditure Breakdown'!$R$86:$R$98, 'Expenditure Breakdown'!$W$86:$W$98, ">="&K1,'Expenditure Breakdown'!$W$86:$W$98, "<"&L1) -> 0 | L20: =SUMIFS('Expenditure Breakdown'!$R$30:$R$33, 'Expenditure Breakdown'!$W$30:$W$33, ">="&L1,'Expenditure Breakdown'!$W$30:$W$33, "<"&M1)+SUMIFS('Expenditure Breakdown'!$R$48:$R$54, 'Expenditure Breakdown'!$W$48:$W$54, ">="&L1,'Expenditure Breakdown'!$W$48:$W$54, "<"&M1)+SUMIFS('Expenditure Breakdown'!$R$86:$R$98, 'Expenditure Breakdown'!$W$86:$W$98, ">="&L1,'Expenditure Breakdown'!$W$86:$W$98, "<"&M1) -> 0 | M20: =SUMIFS('Expenditure Breakdown'!$R$30:$R$33, 'Expenditure Breakdown'!$W$30:$W$33, ">="&M1,'Expenditure Breakdown'!$W$30:$W$33, "<"&N1)+SUMIFS('Expenditure Breakdown'!$R$48:$R$54, 'Expenditure Breakdown'!$W$48:$W$54, ">="&M1,'Expenditure Breakdown'!$W$48:$W$54, "<"&N1)+SUMIFS('Expenditure Breakdown'!$R$86:$R$98, 'Expenditure Breakdown'!$W$86:$W$98, ">="&M1,'Expenditure Breakdown'!$W$86:$W$98, "<"&N1) -> 0 | ... BD20: =SUMIFS('Expenditure Breakdown'!$R$30:$R$33, 'Expenditure Breakdown'!$W$30:$W$33, ">="&BD1,'Expenditure Breakdown'!$W$30:$W$33, "<"&BE1)+SUMIFS('Expenditure Breakdown'!$R$48:$R$54, 'Expenditure Breakdown'!$W$48:$W$54, ">="&BD1,'Expenditure Breakdown'!$W$48:$W$54, "<"&BE1)+SUMIFS('Expenditure Breakdown'!$R$86:$R$98, 'Expenditure Breakdown'!$W$86:$W$98, ">="&BD1,'Expenditure Breakdown'!$W$86:$W$98, "<"&BE1) -> 16138.3 | BE20: =SUMIFS('Expenditure Breakdown'!$R$30:$R$33, 'Expenditure Breakdown'!$W$30:$W$33, ">="&BE1,'Expenditure Breakdown'!$W$30:$W$33, "<"&GG1)+SUMIFS('Expenditure Breakdown'!$R$48:$R$54, 'Expenditure Breakdown'!$W$48:$W$54, ">="&BE1,'Expenditure Breakdown'!$W$48:$W$54, "<"&GG1)+SUMIFS('Expenditure Breakdown'!$R$86:$R$98, 'Expenditure Breakdown'!$W$86:$W$98, ">="&BE1,'Expenditure Breakdown'!$W$86:$W$98, "<"&GG1) -> 0 | BF20: =SUMIFS('Expenditure Breakdown'!$R$30:$R$33, 'Expenditure Breakdown'!$W$30:$W$33, ">="&BF1,'Expenditure Breakdown'!$W$30:$W$33, "<"&GH1)+SUMIFS('Expenditure Breakdown'!$R$48:$R$54, 'Expenditure Breakdown'!$W$48:$W$54, ">="&BF1,'Expenditure Breakdown'!$W$48:$W$54, "<"&GH1)+SUMIFS('Expenditure Breakdown'!$R$86:$R$98, 'Expenditure Breakdown'!$W$86:$W$98, ">="&BF1,'Expenditure Breakdown'!$W$86:$W$98, "<"&GH1) -> 0 | BG20: =SUMIFS('Expenditure Breakdown'!$R$30:$R$33, 'Expenditure Breakdown'!$W$30:$W$33, ">="&BG1,'Expenditure Breakdown'!$W$30:$W$33, "<"&GI1)+SUMIFS('Expenditure Breakdown'!$R$48:$R$54, 'Expenditure Breakdown'!$W$48:$W$54, ">="&BG1,'Expenditure Breakdown'!$W$48:$W$54, "<"&GI1)+SUMIFS('Expenditure Breakdown'!$R$86:$R$98, 'Expenditure Breakdown'!$W$86:$W$98, ">="&BG1,'Expenditure Breakdown'!$W$86:$W$98, "<"&GI1) -> 0 | BH20: =SUMIFS('Expenditure Breakdown'!$R$30:$R$33, 'Expenditure Breakdown'!$W$30:$W$33, ">="&BH1,'Expenditure Breakdown'!$W$30:$W$33, "<"&GJ1)+SUMIFS('Expenditure Breakdown'!$R$48:$R$54, 'Expenditure Breakdown'!$W$48:$W$54, ">="&BH1,'Expenditure Breakdown'!$W$48:$W$54, "<"&GJ1)+SUMIFS('Expenditure Breakdown'!$R$86:$R$98, 'Expenditure Breakdown'!$W$86:$W$98, ">="&BH1,'Expenditure Breakdown'!$W$86:$W$98, "<"&GJ1) -> 0 | BI20: =SUMIFS('Expenditure Breakdown'!$R$30:$R$33, 'Expenditure Breakdown'!$W$30:$W$33, ">="&BI1,'Expenditure Breakdown'!$W$30:$W$33, "<"&GK1)+SUMIFS('Expenditure Breakdown'!$R$48:$R$54, 'Expenditure Breakdown'!$W$48:$W$54, ">="&BI1,'Expenditure Breakdown'!$W$48:$W$54, "<"&GK1)+SUMIFS('Expenditure Breakdown'!$R$86:$R$98, 'Expenditure Breakdown'!$W$86:$W$98, ">="&BI1,'Expenditure Breakdown'!$W$86:$W$98, "<"&GK1) -> 0 | BJ20: =SUMIFS('Expenditure Breakdown'!$R$30:$R$33, 'Expenditure Breakdown'!$W$30:$W$33, ">="&BJ1,'Expenditure Breakdown'!$W$30:$W$33, "<"&GL1)+SUMIFS('Expenditure Breakdown'!$R$48:$R$54, 'Expenditure Breakdown'!$W$48:$W$54, ">="&BJ1,'Expenditure Breakdown'!$W$48:$W$54, "<"&GL1)+SUMIFS('Expenditure Breakdown'!$R$86:$R$98, 'Expenditure Breakdown'!$W$86:$W$98, ">="&BJ1,'Expenditure Breakdown'!$W$86:$W$98, "<"&GL1) -> 0 | BK20: =SUMIFS('Expenditure Breakdown'!$R$30:$R$33, 'Expenditure Breakdown'!$W$30:$W$33, ">="&BK1,'Expenditure Breakdown'!$W$30:$W$33, "<"&GM1)+SUMIFS('Expenditure Breakdown'!$R$48:$R$54, 'Expenditure Breakdown'!$W$48:$W$54, ">="&BK1,'Expenditure Breakdown'!$W$48:$W$54, "<"&GM1)+SUMIFS('Expenditure Breakdown'!$R$86:$R$98, 'Expenditure Breakdown'!$W$86:$W$98, ">="&BK1,'Expenditure Breakdown'!$W$86:$W$98, "<"&GM1) -> 0 | BL20: =SUMIFS('Expenditure Breakdown'!$R$30:$R$33, 'Expenditure Breakdown'!$W$30:$W$33, ">="&BL1,'Expenditure Breakdown'!$W$30:$W$33, "<"&GN1)+SUMIFS('Expenditure Breakdown'!$R$48:$R$54, 'Expenditure Breakdown'!$W$48:$W$54, ">="&BL1,'Expenditure Breakdown'!$W$48:$W$54, "<"&GN1)+SUMIFS('Expenditure Breakdown'!$R$86:$R$98, 'Expenditure Breakdown'!$W$86:$W$98, ">="&BL1,'Expenditure Breakdown'!$W$86:$W$98, "<"&GN1) -> 0 | ... GF20: =SUMIFS('Expenditure Breakdown'!$R$30:$R$33, 'Expenditure Breakdown'!$W$30:$W$33, ">="&GF1,'Expenditure Breakdown'!$W$30:$W$33, "<"&LH1)+SUMIFS('Expenditure Breakdown'!$R$48:$R$54, 'Expenditure Breakdown'!$W$48:$W$54, ">="&GF1,'Expenditure Breakdown'!$W$48:$W$54, "<"&LH1)+SUMIFS('Expenditure Breakdown'!$R$86:$R$98, 'Expenditure Breakdown'!$W$86:$W$98, ">="&GF1,'Expenditure Breakdown'!$W$86:$W$98, "<"&LH1) -> 0
B21: Installer Expenditure - Cumulative | F21: =F20 -> 0 | G21: =G20+F21 -> 0 | H21: =H20+G21 -> 0 | I21: =I20+H21 -> 0 | J21: =J20+I21 -> 0 | K21: =K20+J21 -> 0 | L21: =L20+K21 -> 0 | M21: =M20+L21 -> 0 | N21: =N20+M21 -> 0 | ... GF21: =GF20+GE21 -> 1484855.2
D26: =C11-D11 -> 311894.11

Sheet Finance - Rev
A1: REVENUE RECOGNITION AMOUNT | B1: (All)
A3: Sum of REVENUE RECOGNITION AMOUNT
B4: 45169 | C4: 45199 | D4: 45230 | E4: 45260 | F4: 45291 | G4: 45322 | H4: 45351 | I4: 45382 | J4: 45412 | K4: 45443 | L4: (blank) | M4: 45473 | N4: 45504 | O4: 45535 | P4: 45716 | Q4: 45991 | R4: Grand Total
A5: (blank) | L5: 0 | O5: 0 | R5: 0
A6: 1. Panels | B6: 1675592.2 | I6: 0 | L6: 0 | R6: 1675592.2
A7: 2. Inverters | F7: 240948.52 | I7: 298000 | L7: 0 | R7: 538948.52
A8: 3. Mounting Structures | G8: 148213.46 | R8: 148213.46
A9: 4. DC Equipment | F9: 62006.03 | G9: 281515.69 | H9: 43661.114 | J9: 3485.6384 | R9: 390668.47
A10: 5. Monitoring | F10: 313.91038 | G10: 2382.9855 | J10: 50730.33 | K10: 1232.3902 | L10: 0 | N10: 0 | R10: 54659.616
A11: 6. AC Equipment | F11: 139624.88 | I11: 118824.6 | L11: 0 | N11: 20800.284 | R11: 279249.76
A12: 7. Battery Systems | E12: 11481560 | F12: 33269.432 | J12: 64802.52 | L12: 0 | R12: 11579632
A13: 8. Product Add On | G13: 0 | H13: 0 | J13: 0 | K13: 0 | N13: 0 | R13: 0
A14: 11. Due Dilligence | D14: 7916.6667 | K14: 15833.338 | R14: 23750.004
A15: 12. BDP Commission | L15: 0 | R15: 0
A16: 13. Engineering | B16: 3721.0132 | C16: 0 | D16: 0 | E16: 0 | F16: 0 | G16: 1936.5339 | J16: 213594.74 | R16: 219252.28
A17: 14. General Expenses | B17: 1599.3136 | C17: 0 | D17: 141.89557 | E17: 0 | F17: 1758.79 | G17: 0 | H17: 0 | I17: 0 | R17: 3499.9992
A18: 15. Service Add On | L18: 0 | R18: 0
A19: 10. Site Logistics - AC | F19: 4420.4437 | I19: 3536.355 | N19: 884.08874 | R19: 8840.8874
A20: 10. Site Logistics - DC | F20: 33469.056 | I20: 26775.245 | J20: 6693.8113 | R20: 66938.113
A21: 9. AC installation | F21: 16600.51 | K21: 16600.51 | N21: 33201.02 | R21: 66402.041
A22: 9. DC installation | F22: 48860.427 | I22: 97720.855 | J22: 48860.427 | R22: 195441.71
A23: Grand Total | B23: 1680912.5 | C23: 0 | D23: 8058.5622 | E23: 11481560 | F23: 581272 | G23: 434048.67 | H23: 43661.114 | I23: 544857.05 | J23: 388167.46 | K23: 33666.238 | L23: 0 | N23: 54885.393 | O23: 0 | R23: 15251089
B24: 1669614.5 | E24: 11489618 | F24: 581272 | G24: 434048.67 | H24: 43661.11
B25: =GETPIVOTDATA("REVENUE RECOGNITION AMOUNT",$A$3,"INVOICE RAISED DATE",DATE(2023,8,31))-B24 -> 11298.021 | C25: =GETPIVOTDATA("REVENUE RECOGNITION AMOUNT",$A$3,"INVOICE RAISED DATE",DATE(2023,9,30))-C24 -> 0 | D25: =GETPIVOTDATA("REVENUE RECOGNITION AMOUNT",$A$3,"INVOICE RAISED DATE",DATE(2023,10,31))-D24 -> 8058.5622 | E25: =GETPIVOTDATA("REVENUE RECOGNITION AMOUNT",$A$3,"INVOICE RAISED DATE",DATE(2023,11,30))-E24 -> -8058.5557 | F25: =GETPIVOTDATA("REVENUE RECOGNITION AMOUNT",$A$3,"INVOICE RAISED DATE",DATE(2023,12,31))-F24 -> 0.0040173361 | G25: =GETPIVOTDATA("REVENUE RECOGNITION AMOUNT",$A$3,"INVOICE RAISED DATE",DATE(2024,1,31))-G24 -> -0.0018340216 | H25: =GETPIVOTDATA("REVENUE RECOGNITION AMOUNT",$A$3,"INVOICE RAISED DATE",DATE(2024,2,29))-H24 -> 0.0035665931
C26: =SUM(C23:P23) -> 13570176
A27: Inv
B29: ='Revenue Tracking'!F4-'Finance - Rev'!B24 -> 13581474
B30: =C26 -> 13570176
B31: =B29-B30 -> 11297.652

Sheet Finance - COS
A3: Sum of Actual Total | B3: Column Labels
A4: Row Labels | B4: 45169 | C4: 45199 | D4: 45230 | E4: 45260 | F4: 45291 | G4: 45322 | H4: 45351 | I4: 45382 | J4: 45412 | K4: 45443 | L4: (blank) | M4: 45473 | N4: 45504 | O4: 45535 | P4: 45716 | Q4: 45991 | R4: Grand Total
A5: 1. Panels | B5: 1165914.2 | R5: 1165914.2
A6: 10. Site Logistics - AC | F6: 8360 | I6: 6688 | N6: 1672 | R6: 16720
A7: 10. Site Logistics - DC | F7: 63297.11 | I7: 50637.688 | J7: 12659.422 | R7: 126594.22
A8: 11. Due Dilligence | D8: 5500 | K8: 6183.16 | R8: 11683.16
A9: 12. BDP Commission | L9: 0 | R9: 0
A10: 13. Engineering | B10: 3761.29 | C10: 0 | D10: 0 | E10: 0 | F10: 0 | G10: 756.24 | J10: 149530.88 | R10: 154048.41
A11: 14. General Expenses | B11: 2086.07 | C11: 0 | D11: 151 | E11: 0 | F11: 2774.58 | G11: 1366.01 | H11: 679.5 | I11: 373.65 | J11: 20535.43 | K11: 1573.48 | M11: 1339.72 | R11: 30879.44
A12: 15. Service Add On | L12: 0 | R12: 0
A13: 2. Inverters | F13: 243184.47 | R13: 243184.47
A14: 3. Mounting Structures | G14: 78280 | R14: 78280
A15: 4. DC Equipment | F15: 66829.57 | G15: 344720 | H15: 53463.66 | J15: 13365.915 | R15: 478379.14
A16: 5. Monitoring | F16: 2388 | G16: 18829 | J16: 403974.08 | K16: 11604 | N16: -11604 | O16: 5782.43 | Q16: 7080 | R16: 438053.51
A17: 6. AC Equipment | F17: 593039.92 | I17: 504693.21 | N17: 88346.71 | R17: 1186079.8
A18: 7. Battery Systems | E18: 9608400 | F18: 20322 | J18: 55500 | R18: 9684222
A19: 8. Product Add On | G19: 16045.8 | H19: 15045.8 | J19: 2800 | K19: 33123.63 | N19: 224079.4 | R19: 291094.63
A20: 9. AC installation | F20: 16138.3 | K20: 16138.3 | N20: 32276.6 | R20: 64553.2
A21: 9. DC installation | F21: 47500 | I21: 95000 | J21: 47500 | R21: 190000
A22: (blank) | L22: 0 | N22: 1250.66 | O22: 1038.61 | R22: 2289.27
A23: Grand Total | B23: 1171761.6 | C23: 0 | D23: 5651 | E23: 9608400 | F23: 1063834 | G23: 459997.05 | H23: 69188.96 | I23: 657392.55 | J23: 705865.73 | K23: 68622.57 | L23: 0 | M23: 1339.72 | N23: 336021.37 | O23: 6821.04 | Q23: 7080 | R23: 14161976

Sheet Project Margins
A1: [capture project margins from costing sheet]
A3: Products | D3: 0.32
A4: Services | D4: 0.5
A5: Expenses | D5: 0.15
A6: Subcontractors | D6: 0.2

Sheet Equipment Quotes
B2: Equipment Quote and Budget comparision
B4: Description | D4: Budget | F4: Supplier 1 | H4: Variance | J4: Supplier 2 | L4: Variance | N4: Comments / Notes
F7: >Name< | J7: >Name<
B9: Inverters | D9: =SUM(D10:D11) -> 216000 | F9: =SUM(F10:F13) -> 0 | H9: =$D$9-F9 -> 216000 | J9: =SUM(J10:J13) -> 0 | L9: =$D$9-J9 -> 216000
B10: Inverters | D10: ='Expenditure Breakdown'!G13 -> 216000
B11: Optimizers | D11: ='Expenditure Breakdown'!G14 -> 0
B12: Warranty
B13: Delivery fee
F15: >Name< | J15: >Name<
B17: Mounting Structure | D17: =SUM(D18:D19) -> 132867 | F17: =SUM(F18:F20) -> 0 | H17: =$D$17- F17 -> 132867 | J17: =SUM(J18:J20) -> 0 | L17: =$D$17- J17 -> 132867
B18: Mounting Structure | D18: ='Expenditure Breakdown'!G18 -> 132867
B19: Delivery fee
F21: >Name< | J21: >Name<
B23: DC Cable | D23: =SUM(D24:D25) -> 154882 | F23: =SUM(F24:F25) -> 0 | H23: =$D$23- F23 -> 154882 | J23: =SUM(J24:J25) -> 0 | L23: =$D$23- J23 -> 154882
B24: DC Cable | D24: ='Expenditure Breakdown'!G25 -> 154882
B25: Delivery fee
F27: >Name< | J27: >Name<
B29: Monitoring system | D29: =SUM(D30:D32) -> #REF! | F29: =SUM(F30:F42) -> 0 | H29: =$D$29-F29 -> #REF! | J29: =SUM(J30:J32) -> 0 | L29: =$D$29-J29 -> #REF!
B30: ='Expenditure Breakdown'!D34 -> Solarlog | D30: ='Expenditure Breakdown'!G34 -> 26000
B31: ='Expenditure Breakdown'!#REF! -> #REF! | D31: ='Expenditure Breakdown'!#REF! -> #REF!
B32: Delivery fee
F34: >Name< | J34: >Name<
B36: Additional Scope | D36: =SUM(D37:D41) -> 0 | F36: =SUM(F37:F41) -> 0 | H36: =$D$29-F36 -> #REF! | J36: =SUM(J37:J41) -> 0 | L36: =$D$29-J36 -> #REF!
B37: SCADA | D37: ='Expenditure Breakdown'!G76 -> 0
B38: Inverter cage
B39: Cat ladders
B40: Gen Integration
B41: Lifelines
B43: Totals | D43: =D36+D29+D23+D17+D9 -> #REF! | H43: =SUM(H7:H42) -> #REF! | L43: =SUM(L7:L42) -> #REF!
B47: All amounts are incl VAT

Sheet Installer Quotes
B2: Installer Quote and Budget comparision
B4: Description | D4: Budget | G4: Cosmic Sun | J4: Variance | L4: >Installer Name 2< | O4: Variance
B6: AC installation | D6: ='Expenditure Breakdown'!C87 -> 0 | E6: =D6/(1000*'Project Plan'!$E$3) -> 0 | H6: =G6/('Project Plan'!$E$3*1000) -> 0 | J6: =D6-G6 -> 0 | M6: =L6/('Project Plan'!$E$3*1000) -> 0 | O6: =D6-L6 -> 0
B7: AC equipment | D7: ='Expenditure Breakdown'!C88 -> 209475 | E7: =D7/(1000*'Project Plan'!$E$3) -> 0.5985 | H7: =G7/('Project Plan'!$E$3*1000) -> 0 | J7: =D7-G7 -> 209475 | M7: =L7/('Project Plan'!$E$3*1000) -> 0 | O7: =D7-L7 -> 209475
B8: DC installation | D8: ='Expenditure Breakdown'!C53 -> 0 | E8: =D8/(1000*'Project Plan'!$E$3) -> 0 | H8: =G8/('Project Plan'!$E$3*1000) -> 0 | J8: =D8-G8 -> 0 | M8: =L8/('Project Plan'!$E$3*1000) -> 0 | O8: =D8-L8 -> 0
B9: DC equipment | D9: =SUM('Expenditure Breakdown'!G30:G31) -> 142285.5 | E9: =D9/(1000*'Project Plan'!$E$3) -> 0.40653 | H9: =G9/('Project Plan'!$E$3*1000) -> 0 | J9: =D9-G9 -> 142285.5 | M9: =L9/('Project Plan'!$E$3*1000) -> 0 | O9: =D9-L9 -> 142285.5
B10: Storage | D10: ='Expenditure Breakdown'!G108 -> 0 | J10: =D10-G10 -> 0 | O10: =D10-L10 -> 0
B11: Panel lifting equipment | D11: =SUM('Expenditure Breakdown'!G95:G100) -> 60622.9 | J11: =D11-G11 -> 60622.9 | O11: =D11-L11 -> 60622.9
B12: Offloading | D12: ='Expenditure Breakdown'!G102 -> 0 | J12: =D12-G12 -> 0 | O12: =D12-L12 -> 0
B15: Totals | D15: =SUM(D6:D13) -> 412383.4 | G15: =SUM(G6:G13) -> 0 | J15: =SUM(J6:J14) -> 412383.4 | L15: =SUM(L6:L13) -> 0 | O15: =SUM(O6:O14) -> 412383.4
B18: Description | D18: Budget | G18: >Installer Name 3< | J18: Variance | L18: >Installer Name 4< | O18: Variance
B20: AC installation | D20: ='Expenditure Breakdown'!C87 -> 0 | E20: =D20/(1000*'Project Plan'!$E$3) -> 0 | H20: =G20/(1000*'Project Plan'!$E$3) -> 0 | J20: =D20-G20 -> 0 | M20: =L20/(1000*'Project Plan'!$E$3) -> 0 | O20: =D6-L20 -> 0
B21: AC equipment | D21: ='Expenditure Breakdown'!C53 -> 0 | E21: =D21/(1000*'Project Plan'!$E$3) -> 0 | J21: =D21-G21 -> 0 | M21: =L21/(1000*'Project Plan'!$E$3) -> 0 | O21: =D7-L21 -> 209475
B22: DC installation | D22: ='Expenditure Breakdown'!C88 -> 209475 | E22: =D22/(1000*'Project Plan'!$E$3) -> 0.5985 | H22: =G22/(1000*'Project Plan'!$E$3) -> 0 | J22: =D22-G22 -> 209475 | M22: =L22/(1000*'Project Plan'!$E$3) -> 0 | O22: =D8-L22 -> 0
B23: DC equipment | D23: =SUM('Expenditure Breakdown'!G30:G31) -> 142285.5 | E23: =D23/(1000*'Project Plan'!$E$3) -> 0.40653 | J23: =D23-G23 -> 142285.5 | O23: =D9-L23 -> 142285.5
B24: Storage | D24: ='Expenditure Breakdown'!G108 -> 0 | J24: =D24-G24 -> 0 | O24: =D10-L24 -> 0
B25: Panel lifting equipment | D25: =SUM('Expenditure Breakdown'!G95:G100) -> 60622.9 | J25: =D25-G25 -> 60622.9 | O25: =D11-L25 -> 60622.9
B26: Offloading | D26: ='Expenditure Breakdown'!G102 -> 0 | J26: =D26-G26 -> 0 | O26: =D12-L26 -> 0
B29: Totals | D29: =SUM(D20:D27) -> 412383.4 | G29: =SUM(G20:G27) -> 0 | J29: =SUM(J20:J28) -> 412383.4 | L29: =SUM(L20:L27) -> 0 | O29: =SUM(O20:O28) -> 412383.4
B32: Budget Summary
B34: Budget | D34: =D15 -> 412383.4
B35: =G4 -> Cosmic Sun | D35: =G15 -> 0
B36: =L4 -> >Installer Name 2< | D36: =L15 -> 0
B37: =G18 -> >Installer Name 3< | D37: =G29 -> 0
B38: =L18 -> >Installer Name 4< | D38: =L29 -> 0
B40: =IF(D40<D34,"Saving","Loss") -> Loss | D40: =D34-MIN(D35:D38) -> 412383.4
B42: All amounts are exc VAT
G45: LR | H45: JKM | J45: LR
G46: Aarden | H46: Menlo | J46: Krannich
G47: =1815/550 -> 3.3 | H47: =(987483.75/674)/555 -> 2.6398368 | J47: =1487.4/555 -> 2.68

Sheet Project Plan-Volvo
N1: =TODAY() -> 46063 | O1: =TODAY() -> 46063
C2: PROJECT PLAN | E2: Warne House | N2: 0 | O2: 1
C3: PROJECT SIZE (kWp) | E3: 350 | F3: 1800kWh, 500kVA
C4: SITE ADDRESS | E4: BMG World, 28 Droste Crescent, JHB
C5: BUSINESS DEVELOPER | E5: Peter
C6: PROJECT MANAGERS | E6: Kerusha/ Kholisa
C7: INSTALLER | E7: TBC
C8: CONTRACT VALUE | E8: 14953088
B10: No. | C10: HIGH LEVEL PROGRAMME | E10: Planned Start | F10: Duration (days) | G10: Planned End | I10: Actual Start | J10: Duration (days) | K10: Actual End | M10: Status | O10: Comment
F11: =G50-E26 -> 25 | J11: =K50-I26 -> 102 | M11: =AVERAGE(M13,M25,M28,M35,M44,M48,M56,M53,M18) -> 0.9047619
B13: 1 | C13: Project Initiation | E13: =MIN(E14:E17) -> 45138 | F13: =G13-E13 -> 38 | G13: =MAX(G14:G17) -> 45176 | I13: =MIN(I14:I17) -> 45138 | J13: =K13-I13 -> 126 | K13: =MAX(K14:K17) -> 45264 | M13: =(J14*M14+J15*M15+J16*M16+J17*M17)/SUM(J14:J17) -> 1 | N13: =M13*J13 -> 126
B14: 1.1 | C14: BD Handover | E14: 45138 | F14: 1 | G14: =WORKDAY.INTL(E14,F14,1,Data!$C$3:$C$14) -> 45139 | I14: 45138 | J14: 1 | K14: =WORKDAY.INTL(I14,J14,1,Data!$C$3:$C$14) -> 45139 | M14: 1
B15: 1.2 | C15: Project Introduction | E15: =E14+14 -> 45152 | F15: 1 | G15: =WORKDAY.INTL(E15,F15,1,Data!$C$3:$C$14) -> 45153 | I15: =I14+14 -> 45152 | J15: 1 | K15: =WORKDAY.INTL(I15,J15,1,Data!$C$3:$C$14) -> 45153 | M15: 1
B16: 1.3 | C16: Financial Review | E16: =G15+21 -> 45174 | F16: 1 | G16: =WORKDAY.INTL(E16,F16,1,Data!$C$3:$C$14) -> 45175 | I16: 45261 | J16: 1 | K16: =WORKDAY.INTL(I16,J16,1,Data!$C$3:$C$14) -> 45264 | M16: 1
B17: 1.4 | C17: Client kick off | E17: =E16+1 -> 45175 | F17: 1 | G17: =WORKDAY.INTL(E17,F17,1,Data!$C$3:$C$14) -> 45176 | I17: =I16+1 -> 45262 | J17: 1 | K17: =WORKDAY.INTL(I17,J17,1,Data!$C$3:$C$14) -> 45264 | M17: 1
B18: 2 | C18: BESS - Prep Work (If Applicable) | E18: =MIN(E19:E23) -> 45474 | F18: =G18-E18 -> 9 | G18: =MAX(G19:G23) -> 45483 | I18: =MIN(I19:I23) -> 45152 | J18: =K18-I18 -> 114 | K18: =MAX(K19:K23) -> 45266 | M18: =(J19*M19+J20*M20+J21*M21+J22*M22+J23*M23)/SUM(J19:J23) -> 1 | N18: =J18*M18 -> 114
B19: 2.1 | C19: Pre-Installation Prepping | E19: 45474 | F19: 2 | G19: =WORKDAY.INTL(E19,F19,1,Data!$C$3:$C$14) -> 45476 | I19: =WORKDAY.INTL(I15,0,1,Data!$C$3:$C$14) -> 45152 | J19: 10 | K19: =WORKDAY.INTL(I19,J19,1,Data!$C$3:$C$14) -> 45166 | M19: 1
B20: 2.2 | C20: Plinth Installation | E20: =WORKDAY.INTL(G19,0,1,Data!$C$3:$C$14) -> 45476 | F20: 5 | G20: =WORKDAY.INTL(E20,F20,1,Data!$C$3:$C$14) -> 45483 | I20: =WORKDAY.INTL(K19,0,1,Data!$C$3:$C$14) -> 45166 | J20: 10 | K20: =WORKDAY.INTL(I20,J20,1,Data!$C$3:$C$14) -> 45180 | M20: 1
B21: 2.3 | C21: Housing Prep | E21: =WORKDAY.INTL(E19,0,1,Data!$C$3:$C$14) -> 45474 | F21: 7 | G21: =WORKDAY.INTL(E21,F21,1,Data!$C$3:$C$14) -> 45483 | I21: =WORKDAY.INTL(I19,0,1,Data!$C$3:$C$14) -> 45152 | J21: 36 | K21: =WORKDAY.INTL(I21,J21,1,Data!$C$3:$C$14) -> 45202 | M21: 1
B22: 2.4 | C22: Setup of rigger and placement | E22: =WORKDAY.INTL(G21,0,1,Data!$C$3:$C$14)-2 -> 45481 | F22: 1 | G22: =WORKDAY.INTL(E22,F22,1,Data!$C$3:$C$14) -> 45482 | I22: =WORKDAY.INTL(K21,0,1,Data!$C$3:$C$14) -> 45202 | J22: 3 | K22: =WORKDAY.INTL(I22,J22,1,Data!$C$3:$C$14) -> 45205 | M22: 1
B23: 2.5 | C23: Housing Completed | E23: =WORKDAY.INTL(G22,0,1,Data!$C$3:$C$14) -> 45482 | F23: 1 | G23: =WORKDAY.INTL(E23,F23,1,Data!$C$3:$C$14) -> 45483 | I23: =WORKDAY.INTL(K22,0,1,Data!$C$3:$C$14) -> 45205 | J23: 43 | K23: =WORKDAY.INTL(I23,J23,1,Data!$C$3:$C$14) -> 45266 | M23: 1
B25: 3 | C25: Site Establishment | E25: =MIN(E26:E27) -> 45474 | F25: =G25-E25 -> 1 | G25: =MAX(G26) -> 45475 | I25: =MIN(I26:I27) -> 45299 | J25: =K25-I25 -> 1 | K25: =MAX(K26) -> 45300 | M25: =(J26*M26)/J25 -> 1 | N25: =J25*M25 -> 1
B26: 3.1 | C26: Installer on site and roof assessment | E26: 45474 | F26: 1 | G26: =WORKDAY.INTL(E26,F26,1,Data!$C$3:$C$14) -> 45475 | I26: 45299 | J26: 1 | K26: =WORKDAY.INTL(I26,J26,1,Data!$C$3:$C$14) -> 45300 | M26: 1
B28: 4 | C28: AC Installation | E28: =MIN(E29:E33) -> 45467 | F28: =G28-E28 -> 30 | G28: =MAX(G29:G33) -> 45497 | I28: =MIN(I29:I33) -> 45299 | J28: =K28-I28 -> 78 | K28: =MAX(K29:K33) -> 45377 | M28: =(J29*M29+J30*M30+J31*M31+J32*M32+J33*M33)/SUM(J29:J33) -> 1 | N28: =J28*M28 -> 78
B29: 4.1 | C29: Inverters delivered | E29: =E26 -> 45474 | F29: 1 | G29: =WORKDAY.INTL(E29,F29,1,Data!$C$3:$C$14) -> 45475 | I29: =I26 -> 45299 | J29: 1 | K29: =WORKDAY.INTL(I29,J29,1,Data!$C$3:$C$14) -> 45300 | M29: 1
B30: 4.2 | C30: Inverters Mounted | E30: =WORKDAY.INTL(G29,0,1,Data!$C$3:$C$14) -> 45475 | F30: 1 | G30: =WORKDAY.INTL(E30,F30,1,Data!$C$3:$C$14) -> 45476 | I30: =I31+4 -> 45303 | J30: 1 | K30: =WORKDAY.INTL(I30,J30,1,Data!$C$3:$C$14) -> 45306 | M30: 1
B31: 4.3 | C31: Solar DB lead time | E31: =WORKDAY.INTL(E26,0,1,Data!$C$3:$C$14)-7 -> 45467 | F31: 20 | G31: =WORKDAY.INTL(E31,F31,1,Data!$C$3:$C$14) -> 45495 | I31: =WORKDAY.INTL(I26,0,1,Data!$C$3:$C$14) -> 45299 | J31: 35 | K31: =WORKDAY.INTL(I31,J31,1,Data!$C$3:$C$14)+5 -> 45353 | M31: 1
B32: 4.4 | C32: AC Works | E32: =WORKDAY.INTL(G31,0,1,Data!$C$3:$C$14)-7 -> 45488 | F32: 5 | G32: =WORKDAY.INTL(E32,F32,1,Data!$C$3:$C$14) -> 45495 | I32: =WORKDAY.INTL(I31,0,1,Data!$C$3:$C$14)+7 -> 45306 | J32: 30 | K32: =WORKDAY.INTL(I32,J32,1,Data!$C$3:$C$14)+28 -> 45376 | M32: 1
B33: 4.5 | C33: AC Tie - in | E33: =WORKDAY.INTL(G31,0,1,Data!$C$3:$C$14) -> 45495 | F33: 2 | G33: =WORKDAY.INTL(E33,F33,1,Data!$C$3:$C$14) -> 45497 | I33: 45374 | J33: 2 | K33: =WORKDAY.INTL(I33,J33,1,Data!$C$3:$C$14) -> 45377 | M33: 1
B35: 5 | C35: DC Works | E35: =MIN(E36:E42) -> 45474 | F35: =G35-E35 -> 18 | G35: =MAX(G36:G42) -> 45492 | I35: =MIN(I36:I42) -> 45271 | J35: =K35-I35 -> 63 | K35: =MAX(K36:K42) -> 45334 | M35: =(J36*M36+J37*M37+J38*M38+J39*M39+J40*M40+J41*M41+J42*M42)/SUM(J36:J42) -> 1 | N35: =J35*M35 -> 63
B36: 5.1 | C36: Mounting Structure delivered | E36: =WORKDAY.INTL(E26,0,1,Data!$C$3:$C$14) -> 45474 | F36: 1 | G36: =WORKDAY.INTL(E36,F36,1,Data!$C$3:$C$14) -> 45475 | I36: 45301 | J36: 1 | K36: =WORKDAY.INTL(I36,J36,1,Data!$C$3:$C$14) -> 45302 | M36: 1
B37: 5.2 | C37: Mounting Structure installation | E37: =WORKDAY.INTL(G36,0,1,Data!$C$3:$C$14) -> 45475 | F37: 6 | G37: =WORKDAY.INTL(E37,F37,1,Data!$C$3:$C$14) -> 45483 | I37: =WORKDAY.INTL(K36,0,1,Data!$C$3:$C$14) -> 45302 | J37: 3 | K37: =WORKDAY.INTL(I37,J37,1,Data!$C$3:$C$14) -> 45307 | M37: 1
B38: 5.3 | C38: Battery Delivery | E38: =WORKDAY.INTL(G23,0,1,Data!$C$3:$C$14) -> 45483 | F38: 1 | G38: =WORKDAY.INTL(E38,F38,1,Data!$C$3:$C$14) -> 45484 | I38: 45271 | J38: 1 | K38: =WORKDAY.INTL(I38,J38,1,Data!$C$3:$C$14) -> 45272 | M38: 1
B39: 5.4 | C39: Battery Installation | E39: =WORKDAY.INTL(G38,0,1,Data!$C$3:$C$14) -> 45484 | F39: 5 | G39: =WORKDAY.INTL(E39,F39,1,Data!$C$3:$C$14) -> 45491 | I39: =WORKDAY.INTL(K38,0,1,Data!$C$3:$C$14) -> 45272 | J39: 35 | K39: =WORKDAY.INTL(I39,J39,1,Data!$C$3:$C$14) -> 45321 | M39: 1
B40: 5.5 | C40: DC Cable delivered | E40: =WORKDAY.INTL(E26,0,1,Data!$C$3:$C$14) -> 45474 | F40: 1 | G40: =WORKDAY.INTL(E40,F40,1,Data!$C$3:$C$14) -> 45475 | I40: 45307 | J40: 1 | K40: =WORKDAY.INTL(I40,J40,1,Data!$C$3:$C$14) -> 45308 | M40: 1
B41: 5.6 | C41: DC Cable Trays installation | E41: =WORKDAY.INTL(E37,0,1,Data!$C$3:$C$14) -> 45475 | F41: 6 | G41: =WORKDAY.INTL(E41,F41,1,Data!$C$3:$C$14) -> 45483 | I41: =+K37 -> 45307 | J41: 7 | K41: =WORKDAY.INTL(I41,J41,1,Data!$C$3:$C$14) -> 45316 | M41: 1
B42: 5.7 | C42: DC Cabling | E42: =WORKDAY.INTL(G37,0,1,Data!$C$3:$C$14) -> 45483 | F42: 7 | G42: =WORKDAY.INTL(E42,F42,1,Data!$C$3:$C$14) -> 45492 | I42: =+K41 -> 45316 | J42: 10 | K42: =WORKDAY.INTL(I42,J42,1,Data!$C$3:$C$14)+4 -> 45334 | M42: 1
B44: 6 | C44: Module installation | E44: =MIN(E45:E46) -> 45481 | F44: =G44-E44 -> 10 | G44: =MAX(G45:G46) -> 45491 | I44: =MIN(I45:I46) -> 45355 | J44: =K44-I44 -> 17 | K44: =MAX(K45:K46) -> 45372 | M44: =(J45*M45+J46*M46)/SUM(J45:J46) -> 1 | N44: =J44*M44 -> 17
B45: 6.1 | C45: Module delivery | E45: =WORKDAY.INTL(G37,0,1,Data!$C$3:$C$14)-2 -> 45481 | F45: 1 | G45: =WORKDAY.INTL(E45,F45,1,Data!$C$3:$C$14) -> 45482 | I45: 45355 | J45: 1 | K45: =WORKDAY.INTL(I45,J45,1,Data!$C$3:$C$14) -> 45356 | M45: 1
B46: 6.2 | C46: Module mounting | E46: =WORKDAY.INTL(G45,0,1,Data!$C$3:$C$14) -> 45482 | F46: 7 | G46: =WORKDAY.INTL(E46,F46,1,Data!$C$3:$C$14) -> 45491 | I46: =WORKDAY.INTL(K45,0,1,Data!$C$3:$C$14) -> 45356 | J46: 12 | K46: =WORKDAY.INTL(I46,J46,1,Data!$C$3:$C$14) -> 45372 | M46: 1 | O46: Team prep for hoisting and mounting.
B48: 7 | C48: Commissioning | E48: =MIN(E49:E50) -> 45497 | F48: =G48-E48 -> 2 | G48: =MAX(G49:G50) -> 45499 | I48: =MIN(I49:I50) -> 45391 | J48: =K48-I48 -> 10 | K48: =MAX(K49:K50) -> 45401 | M48: =(J49*M49+J50*M50)/SUM(J49:J50) -> 1 | N48: =J48*M48 -> 10
B49: 7.1 | C49: Cold commissioning | E49: =WORKDAY.INTL(MAX(G28,G35,G44),0,1,Data!$C$3:$C$14) -> 45497 | F49: 1 | G49: =WORKDAY.INTL(E49,F49,1,Data!$C$3:$C$14) -> 45498 | I49: =WORKDAY.INTL(MAX(K28,K35,K44),0,1,Data!$C$3:$C$14)+14 -> 45391 | J49: 3 | K49: =WORKDAY.INTL(I49,J49,1,Data!$C$3:$C$14) -> 45394 | M49: 1
B50: 7.2 | C50: Hot commissioning | E50: =WORKDAY.INTL(G49,0,1,Data!$C$3:$C$14) -> 45498 | F50: 1 | G50: =WORKDAY.INTL(E50,F50,1,Data!$C$3:$C$14) -> 45499 | I50: =WORKDAY.INTL(K49,0,1,Data!$C$3:$C$14) -> 45394 | J50: 5 | K50: =WORKDAY.INTL(I50,J50,1,Data!$C$3:$C$14) -> 45401 | M50: 1
B51: 7.3 | C51: Final Commissioning | E51: =WORKDAY.INTL(G50,0,1,Data!$C$3:$C$14) -> 45499 | F51: 2 | G51: =WORKDAY.INTL(E51,F51,1,Data!$C$3:$C$14) -> 45503 | I51: 45446 | J51: 15 | K51: =WORKDAY.INTL(I51,J51,1,Data!$C$3:$C$14) -> 45467 | M51: 0.8 | O51: Awaiting Atess Technician
B53: 8 | C53: QA Inspections | E53: =MIN(E54) -> 45504 | F53: =G53-E53 -> 5 | G53: =MAX(G54) -> 45509 | I53: =MIN(I54) -> 45467 | J53: =K53-I53 -> 3 | K53: =MAX(K54) -> 45470 | M53: =(J54*M54)/SUM(J54) -> 0.9 | N53: =J53*M53 -> 2.7
B54: 8.1 | C54: Red-Team Inspection | E54: =WORKDAY.INTL(G50,0,1,Data!$C$3:$C$14)+5 -> 45504 | F54: 3 | G54: =WORKDAY.INTL(E54,F54,1,Data!$C$3:$C$14) -> 45509 | I54: =WORKDAY.INTL(K51,0,1,Data!$C$3:$C$14) -> 45467 | J54: 3 | K54: =WORKDAY.INTL(I54,J54,1,Data!$C$3:$C$14) -> 45470 | M54: 0.9
B56: 9 | C56: Project Closure | E56: =MIN(E57:E62) -> 45498 | F56: =G56-E56 -> 26 | G56: =MAX(G57:G62) -> 45524 | I56: =MIN(I57:I62) -> 45394 | J56: =K56-I56 -> 83 | K56: =MAX(K57:K62) -> 45477 | M56: =(J57*M57+J58*M58+J59*M59+J60*M60+J61*M61+J62*M62)/SUM(J57:J62) -> 0.24285714 | N56: =J56*M56 -> 20.157143
B57: 9.1 | C57: Equipment serial numbers | E57: =WORKDAY.INTL(E50,0,1,Data!$C$3:$C$14) -> 45498 | F57: 1 | G57: =WORKDAY.INTL(E57,F57,1,Data!$C$3:$C$14) -> 45499 | I57: =WORKDAY.INTL(I50,0,1,Data!$C$3:$C$14) -> 45394 | J57: 1 | K57: =WORKDAY.INTL(I57,J57,1,Data!$C$3:$C$14) -> 45397 | M57: 1
B58: 9.2 | C58: Snags completion | E58: =WORKDAY.INTL(G54,0,1,Data!$C$3:$C$14) -> 45509 | F58: 5 | G58: =WORKDAY.INTL(E58,F58,1,Data!$C$3:$C$14) -> 45516 | I58: =WORKDAY.INTL(K51,0,1,Data!$C$3:$C$14) -> 45467 | J58: 3 | K58: =WORKDAY.INTL(I58,J58,1,Data!$C$3:$C$14) -> 45470 | M58: 0.8
B59: 9.3 | C59: System Performance Monitoring | E59: =WORKDAY.INTL(G58,0,1,Data!$C$3:$C$14) -> 45516 | F59: 4 | G59: =WORKDAY.INTL(E59,F59,1,Data!$C$3:$C$14) -> 45520 | I59: =WORKDAY.INTL(K51,0,1,Data!$C$3:$C$14) -> 45467 | J59: 5 | K59: =WORKDAY.INTL(I59,J59,1,Data!$C$3:$C$14) -> 45474 | M59: 0
B60: 9.4 | C60: Handover documentation | E60: =WORKDAY.INTL(G58,0,1,Data!$C$3:$C$14) -> 45516 | F60: 5 | G60: =WORKDAY.INTL(E60,F60,1,Data!$C$3:$C$14) -> 45523 | I60: =WORKDAY.INTL(K58,0,1,Data!$C$3:$C$14) -> 45470 | J60: 3 | K60: =WORKDAY.INTL(I60,J60,1,Data!$C$3:$C$14) -> 45475 | M60: 0
B61: 9.5 | C61: Handover to Client | E61: =WORKDAY.INTL(G60,0,1,Data!$C$3:$C$14) -> 45523 | F61: 1 | G61: =WORKDAY.INTL(E61,F61,1,Data!$C$3:$C$14) -> 45524 | I61: =WORKDAY.INTL(K60,0,1,Data!$C$3:$C$14) -> 45475 | J61: 1 | K61: =WORKDAY.INTL(I61,J61,1,Data!$C$3:$C$14) -> 45476 | M61: 0
B62: 9.6 | C62: Handover to Matriarch | E62: =WORKDAY.INTL(G58,0,1,Data!$C$3:$C$14) -> 45516 | F62: 1 | G62: =WORKDAY.INTL(E62,F62,1,Data!$C$3:$C$14) -> 45517 | I62: =WORKDAY.INTL(K61,0,1,Data!$C$3:$C$14) -> 45476 | J62: 1 | K62: =WORKDAY.INTL(I62,J62,1,Data!$C$3:$C$14) -> 45477 | M62: 0

Sheet Decision Register
B1: =D15 -> BMG World, 28 Droste Crescent, JHB | E1: Decision Register
B3: ID | C3: Decision Description | D3: Decision Impact | E3: Proposed Date | F3: Proposed By | G3: Status | H3: Approved By | I3: Date | J3: Results / Comments
B4: DEC001
B5: DEC002
B6: DEC003
B7: DEC004
B8: DEC005
B9: DEC006
B10: DEC007
B11: DEC008
B12: DEC009
B13: DEC010
D15: {='Project Plan'!E2:H2} -> BMG World, 28 Droste Crescent, JHB | E15: 0 | F15: 0 | G15: 0
