Workbook
Name Inverter_Capacity: #REF!
Name Inverter_Supplier: #REF!
Name Project_Size: 'Certificate - Financial Close'!Projectsize
Name Project_Size: Compliance!Projectsize
Name Project_Size: 'Finance - Revenue'!Projectsize
Name Project_Size: Projectsize
Name Projectsize: '[1]Project Margins'!$K$5
Name Projectsize: #REF!
Name Projectsize: #REF!
Name Projectsize: 'Project Margins'!$K$5
Name Security_Serv: #REF!
Name Security_Serv: #REF!
Name SSS: #REF!
Name SSS: #REF!
Name USD_ZAR: #REF!

Sheet Sheet1
A1: PROJECT PLAN
A2: # | B2: Project Milestone | C2: Planned Start Date | D2: Duration (Work Days) | E2: Planned End Date | F2: Actual Start Date | H2: Actual End Date | J2: Comments | L2: =C3 -> 43831 | M2: =L2+3 -> 43834 | N2: =M2+7 -> 43841 | O2: =N2+7 -> 43848 | P2: =O2+7 -> 43855 | Q2: =P2+6 -> 43861 | R2: =Q2+1 -> 43862 | S2: =R2+7 -> 43869 | T2: =S2+7 -> 43876 | U2: =T2+7 -> 43883 | V2: =U2+6 -> 43889 | W2: =V2+7 -> 43896 | X2: =W2+7 -> 43903 | Y2: =X2+7 -> 43910 | Z2: =Y2+7 -> 43917 | AA2: =Z2+3 -> 43920 | AB2: =AA2+4 -> 43924 | AC2: =AB2+7 -> 43931 | AD2: =AC2+7 -> 43938 | AE2: =AD2+7 -> 43945 | AF2: =AE2+6 -> 43951 | AG2: =AF2+2 -> 43953 | AH2: =AG2+7 -> 43960 | AI2: =AH2+7 -> 43967 | AJ2: =AI2+7 -> 43974 | AK2: =AJ2+7 -> 43981 | AL2: =AK2+1 -> 43982 | AM2: =AL2+6 -> 43988 | AN2: =AM2+7 -> 43995 | AO2: =AN2+7 -> 44002 | AP2: =AO2+7 -> 44009 | AQ2: =AP2+3 -> 44012 | AR2: =AQ2+4 -> 44016 | AS2: =AR2+7 -> 44023 | AT2: =AS2+7 -> 44030 | AU2: =AT2+7 -> 44037 | AV2: =AU2+6 -> 44043 | AW2: =AV2+1 -> 44044 | AX2: =AW2+7 -> 44051 | AY2: =AX2+7 -> 44058 | AZ2: =AY2+7 -> 44065 | BA2: =AZ2+7 -> 44072 | BB2: =BA2+2 -> 44074 | BC2: =BB2+5 -> 44079 | BD2: =BC2+7 -> 44086 | BE2: =BD2+7 -> 44093 | BF2: =BE2+7 -> 44100 | BG2: =BF2+4 -> 44104
A3: 1 | B3: Contract Signature | C3: 43831 | D3: 1 | E3: 43832 | F3: 43831 | G3: 1 | H3: 43832 | L3: =IF(AND($F3<(L$2+7),$F3>L$2),1, IF(AND($H3<L$2+7,$H3>L$2),3, IF(AND($F3<=L$2, $H3>=L$2), 2, "" ))) -> 3 | M3: =IF(AND($F3<(M$2+7),$F3>M$2),1, IF(AND($H3<M$2+7,$H3>M$2),3, IF(AND($F3<=M$2, $H3>=M$2), 2, "" ))) | N3: =IF(AND($F3<(N$2+7),$F3>N$2),1, IF(AND($H3<N$2+7,$H3>N$2),3, IF(AND($F3<=N$2, $H3>=N$2), 2, "" ))) | O3: =IF(AND($F3<(O$2+7),$F3>O$2),1, IF(AND($H3<O$2+7,$H3>O$2),3, IF(AND($F3<=O$2, $H3>=O$2), 2, "" ))) | P3: =IF(AND($F3<(P$2+7),$F3>P$2),1, IF(AND($H3<P$2+7,$H3>P$2),3, IF(AND($F3<=P$2, $H3>=P$2), 2, "" ))) | Q3: =IF(AND($F3<(Q$2+7),$F3>Q$2),1, IF(AND($H3<Q$2+7,$H3>Q$2),3, IF(AND($F3<=Q$2, $H3>=Q$2), 2, "" ))) | R3: =IF(AND($F3<(R$2+7),$F3>R$2),1, IF(AND($H3<R$2+7,$H3>R$2),3, IF(AND($F3<=R$2, $H3>=R$2), 2, "" ))) | S3: =IF(AND($F3<(S$2+7),$F3>S$2),1, IF(AND($H3<S$2+7,$H3>S$2),3, IF(AND($F3<=S$2, $H3>=S$2), 2, "" ))) | ... AQ3: =IF(AND($F3<(AQ$2+7),$F3>AQ$2),1, IF(AND($H3<AQ$2+7,$H3>AQ$2),3, IF(AND($F3<=AQ$2, $H3>=AQ$2), 2, "" )))
A4: A | B4: PAYMENT MILESTONE 1: DEPOSIT | C4: 43832 | D4: 1 | E4: 43833 | F4: 43832 | G4: 1 | H4: 43833 | L4: =IF(AND($F4<(L$2+7),$F4>L$2),1, IF(AND($H4<L$2+7,$H4>L$2),3, IF(AND($F4<=L$2, $H4>=L$2), 2, "" ))) -> 1 | M4: =IF(AND($F4<(M$2+7),$F4>M$2),1, IF(AND($H4<M$2+7,$H4>M$2),3, IF(AND($F4<=M$2, $H4>=M$2), 2, "" ))) | N4: =IF(AND($F4<(N$2+7),$F4>N$2),1, IF(AND($H4<N$2+7,$H4>N$2),3, IF(AND($F4<=N$2, $H4>=N$2), 2, "" ))) | O4: =IF(AND($F4<(O$2+7),$F4>O$2),1, IF(AND($H4<O$2+7,$H4>O$2),3, IF(AND($F4<=O$2, $H4>=O$2), 2, "" ))) | P4: =IF(AND($F4<(P$2+7),$F4>P$2),1, IF(AND($H4<P$2+7,$H4>P$2),3, IF(AND($F4<=P$2, $H4>=P$2), 2, "" ))) | Q4: =IF(AND($F4<(Q$2+7),$F4>Q$2),1, IF(AND($H4<Q$2+7,$H4>Q$2),3, IF(AND($F4<=Q$2, $H4>=Q$2), 2, "" ))) | R4: =IF(AND($F4<(R$2+7),$F4>R$2),1, IF(AND($H4<R$2+7,$H4>R$2),3, IF(AND($F4<=R$2, $H4>=R$2), 2, "" ))) | S4: =IF(AND($F4<(S$2+7),$F4>S$2),1, IF(AND($H4<S$2+7,$H4>S$2),3, IF(AND($F4<=S$2, $H4>=S$2), 2, "" ))) | ... AQ4: =IF(AND($F4<(AQ$2+7),$F4>AQ$2),1, IF(AND($H4<AQ$2+7,$H4>AQ$2),3, IF(AND($F4<=AQ$2, $H4>=AQ$2), 2, "" )))
A5: 2 | B5: Structural and Electrical Due Diligences | C5: 43833 | D5: 5 | E5: 43840 | F5: 43833 | G5: 5 | H5: 43840 | L5: =IF(AND($F5<(L$2+7),$F5>L$2),1, IF(AND($H5<L$2+7,$H5>L$2),3, IF(AND($F5<=L$2, $H5>=L$2), 2, "" ))) -> 1 | M5: =IF(AND($F5<(M$2+7),$F5>M$2),1, IF(AND($H5<M$2+7,$H5>M$2),3, IF(AND($F5<=M$2, $H5>=M$2), 2, "" ))) -> 3 | N5: =IF(AND($F5<(N$2+7),$F5>N$2),1, IF(AND($H5<N$2+7,$H5>N$2),3, IF(AND($F5<=N$2, $H5>=N$2), 2, "" ))) | O5: =IF(AND($F5<(O$2+7),$F5>O$2),1, IF(AND($H5<O$2+7,$H5>O$2),3, IF(AND($F5<=O$2, $H5>=O$2), 2, "" ))) | P5: =IF(AND($F5<(P$2+7),$F5>P$2),1, IF(AND($H5<P$2+7,$H5>P$2),3, IF(AND($F5<=P$2, $H5>=P$2), 2, "" ))) | Q5: =IF(AND($F5<(Q$2+7),$F5>Q$2),1, IF(AND($H5<Q$2+7,$H5>Q$2),3, IF(AND($F5<=Q$2, $H5>=Q$2), 2, "" ))) | R5: =IF(AND($F5<(R$2+7),$F5>R$2),1, IF(AND($H5<R$2+7,$H5>R$2),3, IF(AND($F5<=R$2, $H5>=R$2), 2, "" ))) | S5: =IF(AND($F5<(S$2+7),$F5>S$2),1, IF(AND($H5<S$2+7,$H5>S$2),3, IF(AND($F5<=S$2, $H5>=S$2), 2, "" ))) | ... AQ5: =IF(AND($F5<(AQ$2+7),$F5>AQ$2),1, IF(AND($H5<AQ$2+7,$H5>AQ$2),3, IF(AND($F5<=AQ$2, $H5>=AQ$2), 2, "" )))
A6: 3 | B6: Design Confirmation | C6: 43841 | D6: 2 | E6: 43844 | F6: 43841 | G6: 2 | H6: 43844 | L6: =IF(AND($F6<(L$2+7),$F6>L$2),1, IF(AND($H6<L$2+7,$H6>L$2),3, IF(AND($F6<=L$2, $H6>=L$2), 2, "" ))) | M6: =IF(AND($F6<(M$2+7),$F6>M$2),1, IF(AND($H6<M$2+7,$H6>M$2),3, IF(AND($F6<=M$2, $H6>=M$2), 2, "" ))) | N6: =IF(AND($F6<(N$2+7),$F6>N$2),1, IF(AND($H6<N$2+7,$H6>N$2),3, IF(AND($F6<=N$2, $H6>=N$2), 2, "" ))) -> 3 | O6: =IF(AND($F6<(O$2+7),$F6>O$2),1, IF(AND($H6<O$2+7,$H6>O$2),3, IF(AND($F6<=O$2, $H6>=O$2), 2, "" ))) | P6: =IF(AND($F6<(P$2+7),$F6>P$2),1, IF(AND($H6<P$2+7,$H6>P$2),3, IF(AND($F6<=P$2, $H6>=P$2), 2, "" ))) | Q6: =IF(AND($F6<(Q$2+7),$F6>Q$2),1, IF(AND($H6<Q$2+7,$H6>Q$2),3, IF(AND($F6<=Q$2, $H6>=Q$2), 2, "" ))) | R6: =IF(AND($F6<(R$2+7),$F6>R$2),1, IF(AND($H6<R$2+7,$H6>R$2),3, IF(AND($F6<=R$2, $H6>=R$2), 2, "" ))) | S6: =IF(AND($F6<(S$2+7),$F6>S$2),1, IF(AND($H6<S$2+7,$H6>S$2),3, IF(AND($F6<=S$2, $H6>=S$2), 2, "" ))) | ... AQ6: =IF(AND($F6<(AQ$2+7),$F6>AQ$2),1, IF(AND($H6<AQ$2+7,$H6>AQ$2),3, IF(AND($F6<=AQ$2, $H6>=AQ$2), 2, "" )))
A7: 4 | B7: Equipment Procurement | C7: 43833 | E7: 43949 | F7: 43833 | H7: 43949 | L7: =IF(AND($F7<(L$2+7),$F7>L$2),1, IF(AND($H7<L$2+7,$H7>L$2),3, IF(AND($F7<=L$2, $H7>=L$2), 2, "" ))) -> 1 | M7: =IF(AND($F7<(M$2+7),$F7>M$2),1, IF(AND($H7<M$2+7,$H7>M$2),3, IF(AND($F7<=M$2, $H7>=M$2), 2, "" ))) -> 2 | N7: =IF(AND($F7<(N$2+7),$F7>N$2),1, IF(AND($H7<N$2+7,$H7>N$2),3, IF(AND($F7<=N$2, $H7>=N$2), 2, "" ))) -> 2 | O7: =IF(AND($F7<(O$2+7),$F7>O$2),1, IF(AND($H7<O$2+7,$H7>O$2),3, IF(AND($F7<=O$2, $H7>=O$2), 2, "" ))) -> 2 | P7: =IF(AND($F7<(P$2+7),$F7>P$2),1, IF(AND($H7<P$2+7,$H7>P$2),3, IF(AND($F7<=P$2, $H7>=P$2), 2, "" ))) -> 2 | Q7: =IF(AND($F7<(Q$2+7),$F7>Q$2),1, IF(AND($H7<Q$2+7,$H7>Q$2),3, IF(AND($F7<=Q$2, $H7>=Q$2), 2, "" ))) -> 2 | R7: =IF(AND($F7<(R$2+7),$F7>R$2),1, IF(AND($H7<R$2+7,$H7>R$2),3, IF(AND($F7<=R$2, $H7>=R$2), 2, "" ))) -> 2 | S7: =IF(AND($F7<(S$2+7),$F7>S$2),1, IF(AND($H7<S$2+7,$H7>S$2),3, IF(AND($F7<=S$2, $H7>=S$2), 2, "" ))) -> 2 | ... AQ7: =IF(AND($F7<(AQ$2+7),$F7>AQ$2),1, IF(AND($H7<AQ$2+7,$H7>AQ$2),3, IF(AND($F7<=AQ$2, $H7>=AQ$2), 2, "" )))
B8: Panel Procurement | C8: 43833 | D8: 5 | E8: 43840 | F8: 43833 | G8: 5 | H8: 43840 | L8: =IF(AND($F8<(L$2+7),$F8>L$2),1, IF(AND($H8<L$2+7,$H8>L$2),3, IF(AND($F8<=L$2, $H8>=L$2), 2, "" ))) -> 1 | M8: =IF(AND($F8<(M$2+7),$F8>M$2),1, IF(AND($H8<M$2+7,$H8>M$2),3, IF(AND($F8<=M$2, $H8>=M$2), 2, "" ))) -> 3 | N8: =IF(AND($F8<(N$2+7),$F8>N$2),1, IF(AND($H8<N$2+7,$H8>N$2),3, IF(AND($F8<=N$2, $H8>=N$2), 2, "" ))) | O8: =IF(AND($F8<(O$2+7),$F8>O$2),1, IF(AND($H8<O$2+7,$H8>O$2),3, IF(AND($F8<=O$2, $H8>=O$2), 2, "" ))) | P8: =IF(AND($F8<(P$2+7),$F8>P$2),1, IF(AND($H8<P$2+7,$H8>P$2),3, IF(AND($F8<=P$2, $H8>=P$2), 2, "" ))) | Q8: =IF(AND($F8<(Q$2+7),$F8>Q$2),1, IF(AND($H8<Q$2+7,$H8>Q$2),3, IF(AND($F8<=Q$2, $H8>=Q$2), 2, "" ))) | R8: =IF(AND($F8<(R$2+7),$F8>R$2),1, IF(AND($H8<R$2+7,$H8>R$2),3, IF(AND($F8<=R$2, $H8>=R$2), 2, "" ))) | S8: =IF(AND($F8<(S$2+7),$F8>S$2),1, IF(AND($H8<S$2+7,$H8>S$2),3, IF(AND($F8<=S$2, $H8>=S$2), 2, "" ))) | ... AQ8: =IF(AND($F8<(AQ$2+7),$F8>AQ$2),1, IF(AND($H8<AQ$2+7,$H8>AQ$2),3, IF(AND($F8<=AQ$2, $H8>=AQ$2), 2, "" )))
B9: Inverter Procurement | C9: 43941 | D9: 5 | E9: 43949 | F9: 43941 | G9: 5 | H9: 43949 | L9: =IF(AND($F9<(L$2+7),$F9>L$2),1, IF(AND($H9<L$2+7,$H9>L$2),3, IF(AND($F9<=L$2, $H9>=L$2), 2, "" ))) | M9: =IF(AND($F9<(M$2+7),$F9>M$2),1, IF(AND($H9<M$2+7,$H9>M$2),3, IF(AND($F9<=M$2, $H9>=M$2), 2, "" ))) | N9: =IF(AND($F9<(N$2+7),$F9>N$2),1, IF(AND($H9<N$2+7,$H9>N$2),3, IF(AND($F9<=N$2, $H9>=N$2), 2, "" ))) | O9: =IF(AND($F9<(O$2+7),$F9>O$2),1, IF(AND($H9<O$2+7,$H9>O$2),3, IF(AND($F9<=O$2, $H9>=O$2), 2, "" ))) | P9: =IF(AND($F9<(P$2+7),$F9>P$2),1, IF(AND($H9<P$2+7,$H9>P$2),3, IF(AND($F9<=P$2, $H9>=P$2), 2, "" ))) | Q9: =IF(AND($F9<(Q$2+7),$F9>Q$2),1, IF(AND($H9<Q$2+7,$H9>Q$2),3, IF(AND($F9<=Q$2, $H9>=Q$2), 2, "" ))) | R9: =IF(AND($F9<(R$2+7),$F9>R$2),1, IF(AND($H9<R$2+7,$H9>R$2),3, IF(AND($F9<=R$2, $H9>=R$2), 2, "" ))) | S9: =IF(AND($F9<(S$2+7),$F9>S$2),1, IF(AND($H9<S$2+7,$H9>S$2),3, IF(AND($F9<=S$2, $H9>=S$2), 2, "" ))) | ... AQ9: =IF(AND($F9<(AQ$2+7),$F9>AQ$2),1, IF(AND($H9<AQ$2+7,$H9>AQ$2),3, IF(AND($F9<=AQ$2, $H9>=AQ$2), 2, "" )))
B10: Mounting Structure Procurement | C10: 43941 | D10: 5 | E10: 43949 | F10: 43941 | G10: 5 | H10: 43949 | L10: =IF(AND($F10<(L$2+7),$F10>L$2),1, IF(AND($H10<L$2+7,$H10>L$2),3, IF(AND($F10<=L$2, $H10>=L$2), 2, "" ))) | M10: =IF(AND($F10<(M$2+7),$F10>M$2),1, IF(AND($H10<M$2+7,$H10>M$2),3, IF(AND($F10<=M$2, $H10>=M$2), 2, "" ))) | N10: =IF(AND($F10<(N$2+7),$F10>N$2),1, IF(AND($H10<N$2+7,$H10>N$2),3, IF(AND($F10<=N$2, $H10>=N$2), 2, "" ))) | O10: =IF(AND($F10<(O$2+7),$F10>O$2),1, IF(AND($H10<O$2+7,$H10>O$2),3, IF(AND($F10<=O$2, $H10>=O$2), 2, "" ))) | P10: =IF(AND($F10<(P$2+7),$F10>P$2),1, IF(AND($H10<P$2+7,$H10>P$2),3, IF(AND($F10<=P$2, $H10>=P$2), 2, "" ))) | Q10: =IF(AND($F10<(Q$2+7),$F10>Q$2),1, IF(AND($H10<Q$2+7,$H10>Q$2),3, IF(AND($F10<=Q$2, $H10>=Q$2), 2, "" ))) | R10: =IF(AND($F10<(R$2+7),$F10>R$2),1, IF(AND($H10<R$2+7,$H10>R$2),3, IF(AND($F10<=R$2, $H10>=R$2), 2, "" ))) | S10: =IF(AND($F10<(S$2+7),$F10>S$2),1, IF(AND($H10<S$2+7,$H10>S$2),3, IF(AND($F10<=S$2, $H10>=S$2), 2, "" ))) | ... AQ10: =IF(AND($F10<(AQ$2+7),$F10>AQ$2),1, IF(AND($H10<AQ$2+7,$H10>AQ$2),3, IF(AND($F10<=AQ$2, $H10>=AQ$2), 2, "" )))
B11: BOS Procurement | C11: 43941 | D11: 5 | E11: 43949 | F11: 43941 | G11: 5 | H11: 43949 | L11: =IF(AND($F11<(L$2+7),$F11>L$2),1, IF(AND($H11<L$2+7,$H11>L$2),3, IF(AND($F11<=L$2, $H11>=L$2), 2, "" ))) | M11: =IF(AND($F11<(M$2+7),$F11>M$2),1, IF(AND($H11<M$2+7,$H11>M$2),3, IF(AND($F11<=M$2, $H11>=M$2), 2, "" ))) | N11: =IF(AND($F11<(N$2+7),$F11>N$2),1, IF(AND($H11<N$2+7,$H11>N$2),3, IF(AND($F11<=N$2, $H11>=N$2), 2, "" ))) | O11: =IF(AND($F11<(O$2+7),$F11>O$2),1, IF(AND($H11<O$2+7,$H11>O$2),3, IF(AND($F11<=O$2, $H11>=O$2), 2, "" ))) | P11: =IF(AND($F11<(P$2+7),$F11>P$2),1, IF(AND($H11<P$2+7,$H11>P$2),3, IF(AND($F11<=P$2, $H11>=P$2), 2, "" ))) | Q11: =IF(AND($F11<(Q$2+7),$F11>Q$2),1, IF(AND($H11<Q$2+7,$H11>Q$2),3, IF(AND($F11<=Q$2, $H11>=Q$2), 2, "" ))) | R11: =IF(AND($F11<(R$2+7),$F11>R$2),1, IF(AND($H11<R$2+7,$H11>R$2),3, IF(AND($F11<=R$2, $H11>=R$2), 2, "" ))) | S11: =IF(AND($F11<(S$2+7),$F11>S$2),1, IF(AND($H11<S$2+7,$H11>S$2),3, IF(AND($F11<=S$2, $H11>=S$2), 2, "" ))) | ... AQ11: =IF(AND($F11<(AQ$2+7),$F11>AQ$2),1, IF(AND($H11<AQ$2+7,$H11>AQ$2),3, IF(AND($F11<=AQ$2, $H11>=AQ$2), 2, "" )))
A12: 5 | B12: Internal Project Kick off | C12: 43936 | D12: 5 | E12: 43943 | F12: 43936 | G12: 5 | H12: 43943
A13: 6 | B13: Client Project Kick-off | C13: 43963 | D13: 5 | E13: 43970 | F13: 43963 | G13: 5 | H13: 43970 | L13: =IF(AND($F13<(L$2+7),$F13>L$2),1, IF(AND($H13<L$2+7,$H13>L$2),3, IF(AND($F13<=L$2, $H13>=L$2), 2, "" ))) | M13: =IF(AND($F13<(M$2+7),$F13>M$2),1, IF(AND($H13<M$2+7,$H13>M$2),3, IF(AND($F13<=M$2, $H13>=M$2), 2, "" ))) | N13: =IF(AND($F13<(N$2+7),$F13>N$2),1, IF(AND($H13<N$2+7,$H13>N$2),3, IF(AND($F13<=N$2, $H13>=N$2), 2, "" ))) | O13: =IF(AND($F13<(O$2+7),$F13>O$2),1, IF(AND($H13<O$2+7,$H13>O$2),3, IF(AND($F13<=O$2, $H13>=O$2), 2, "" ))) | P13: =IF(AND($F13<(P$2+7),$F13>P$2),1, IF(AND($H13<P$2+7,$H13>P$2),3, IF(AND($F13<=P$2, $H13>=P$2), 2, "" ))) | Q13: =IF(AND($F13<(Q$2+7),$F13>Q$2),1, IF(AND($H13<Q$2+7,$H13>Q$2),3, IF(AND($F13<=Q$2, $H13>=Q$2), 2, "" ))) | R13: =IF(AND($F13<(R$2+7),$F13>R$2),1, IF(AND($H13<R$2+7,$H13>R$2),3, IF(AND($F13<=R$2, $H13>=R$2), 2, "" ))) | S13: =IF(AND($F13<(S$2+7),$F13>S$2),1, IF(AND($H13<S$2+7,$H13>S$2),3, IF(AND($F13<=S$2, $H13>=S$2), 2, "" ))) | ... AQ13: =IF(AND($F13<(AQ$2+7),$F13>AQ$2),1, IF(AND($H13<AQ$2+7,$H13>AQ$2),3, IF(AND($F13<=AQ$2, $H13>=AQ$2), 2, "" )))
A14: 7 | B14: Equipment Delivery | C14: 43983 | D14: 9 | E14: 43994 | F14: 43983 | G14: 9 | H14: 43994 | L14: =IF(AND($F14<(L$2+7),$F14>L$2),1, IF(AND($H14<L$2+7,$H14>L$2),3, IF(AND($F14<=L$2, $H14>=L$2), 2, "" ))) | M14: =IF(AND($F14<(M$2+7),$F14>M$2),1, IF(AND($H14<M$2+7,$H14>M$2),3, IF(AND($F14<=M$2, $H14>=M$2), 2, "" ))) | N14: =IF(AND($F14<(N$2+7),$F14>N$2),1, IF(AND($H14<N$2+7,$H14>N$2),3, IF(AND($F14<=N$2, $H14>=N$2), 2, "" ))) | O14: =IF(AND($F14<(O$2+7),$F14>O$2),1, IF(AND($H14<O$2+7,$H14>O$2),3, IF(AND($F14<=O$2, $H14>=O$2), 2, "" ))) | P14: =IF(AND($F14<(P$2+7),$F14>P$2),1, IF(AND($H14<P$2+7,$H14>P$2),3, IF(AND($F14<=P$2, $H14>=P$2), 2, "" ))) | Q14: =IF(AND($F14<(Q$2+7),$F14>Q$2),1, IF(AND($H14<Q$2+7,$H14>Q$2),3, IF(AND($F14<=Q$2, $H14>=Q$2), 2, "" ))) | R14: =IF(AND($F14<(R$2+7),$F14>R$2),1, IF(AND($H14<R$2+7,$H14>R$2),3, IF(AND($F14<=R$2, $H14>=R$2), 2, "" ))) | S14: =IF(AND($F14<(S$2+7),$F14>S$2),1, IF(AND($H14<S$2+7,$H14>S$2),3, IF(AND($F14<=S$2, $H14>=S$2), 2, "" ))) | ... AQ14: =IF(AND($F14<(AQ$2+7),$F14>AQ$2),1, IF(AND($H14<AQ$2+7,$H14>AQ$2),3, IF(AND($F14<=AQ$2, $H14>=AQ$2), 2, "" )))
B15: Mounting Structure Delivery | C15: 43983 | D15: 2 | E15: 43985 | F15: 43983 | G15: 2 | H15: 43985
B16: Panel Delivery | C16: 43990 | D16: 2 | E16: 43992 | F16: 43990 | G16: 2 | H16: 43992 | L16: =IF(AND($F16<(L$2+7),$F16>L$2),1, IF(AND($H16<L$2+7,$H16>L$2),3, IF(AND($F16<=L$2, $H16>=L$2), 2, "" ))) | M16: =IF(AND($F16<(M$2+7),$F16>M$2),1, IF(AND($H16<M$2+7,$H16>M$2),3, IF(AND($F16<=M$2, $H16>=M$2), 2, "" ))) | N16: =IF(AND($F16<(N$2+7),$F16>N$2),1, IF(AND($H16<N$2+7,$H16>N$2),3, IF(AND($F16<=N$2, $H16>=N$2), 2, "" ))) | O16: =IF(AND($F16<(O$2+7),$F16>O$2),1, IF(AND($H16<O$2+7,$H16>O$2),3, IF(AND($F16<=O$2, $H16>=O$2), 2, "" ))) | P16: =IF(AND($F16<(P$2+7),$F16>P$2),1, IF(AND($H16<P$2+7,$H16>P$2),3, IF(AND($F16<=P$2, $H16>=P$2), 2, "" ))) | Q16: =IF(AND($F16<(Q$2+7),$F16>Q$2),1, IF(AND($H16<Q$2+7,$H16>Q$2),3, IF(AND($F16<=Q$2, $H16>=Q$2), 2, "" ))) | R16: =IF(AND($F16<(R$2+7),$F16>R$2),1, IF(AND($H16<R$2+7,$H16>R$2),3, IF(AND($F16<=R$2, $H16>=R$2), 2, "" ))) | S16: =IF(AND($F16<(S$2+7),$F16>S$2),1, IF(AND($H16<S$2+7,$H16>S$2),3, IF(AND($F16<=S$2, $H16>=S$2), 2, "" ))) | ... AQ16: =IF(AND($F16<(AQ$2+7),$F16>AQ$2),1, IF(AND($H16<AQ$2+7,$H16>AQ$2),3, IF(AND($F16<=AQ$2, $H16>=AQ$2), 2, "" )))
B17: Generator Delivery | C17: 43983 | D17: 2 | E17: 43985 | F17: 43983 | G17: 2 | H17: 43985
A18: B | B18: PAYMENT MILESTONE 2: DELIVERY OF PV PANELS | C18: 43992 | D18: 2 | E18: 43994 | F18: 43992 | G18: 2 | H18: 43994
B19: Inverter Delivery | C19: 43983 | D19: 2 | E19: 43985 | F19: 43983 | G19: 2 | H19: 43985 | L19: =IF(AND($F19<(L$2+7),$F19>L$2),1, IF(AND($H19<L$2+7,$H19>L$2),3, IF(AND($F19<=L$2, $H19>=L$2), 2, "" ))) | M19: =IF(AND($F19<(M$2+7),$F19>M$2),1, IF(AND($H19<M$2+7,$H19>M$2),3, IF(AND($F19<=M$2, $H19>=M$2), 2, "" ))) | N19: =IF(AND($F19<(N$2+7),$F19>N$2),1, IF(AND($H19<N$2+7,$H19>N$2),3, IF(AND($F19<=N$2, $H19>=N$2), 2, "" ))) | O19: =IF(AND($F19<(O$2+7),$F19>O$2),1, IF(AND($H19<O$2+7,$H19>O$2),3, IF(AND($F19<=O$2, $H19>=O$2), 2, "" ))) | P19: =IF(AND($F19<(P$2+7),$F19>P$2),1, IF(AND($H19<P$2+7,$H19>P$2),3, IF(AND($F19<=P$2, $H19>=P$2), 2, "" ))) | Q19: =IF(AND($F19<(Q$2+7),$F19>Q$2),1, IF(AND($H19<Q$2+7,$H19>Q$2),3, IF(AND($F19<=Q$2, $H19>=Q$2), 2, "" ))) | R19: =IF(AND($F19<(R$2+7),$F19>R$2),1, IF(AND($H19<R$2+7,$H19>R$2),3, IF(AND($F19<=R$2, $H19>=R$2), 2, "" ))) | S19: =IF(AND($F19<(S$2+7),$F19>S$2),1, IF(AND($H19<S$2+7,$H19>S$2),3, IF(AND($F19<=S$2, $H19>=S$2), 2, "" ))) | ... AQ19: =IF(AND($F19<(AQ$2+7),$F19>AQ$2),1, IF(AND($H19<AQ$2+7,$H19>AQ$2),3, IF(AND($F19<=AQ$2, $H19>=AQ$2), 2, "" )))
B20: BOS Delivery | C20: 43983 | D20: 1 | E20: 43984 | F20: 43983 | G20: 1 | H20: 43984 | L20: =IF(AND($F20<(L$2+7),$F20>L$2),1, IF(AND($H20<L$2+7,$H20>L$2),3, IF(AND($F20<=L$2, $H20>=L$2), 2, "" ))) | M20: =IF(AND($F20<(M$2+7),$F20>M$2),1, IF(AND($H20<M$2+7,$H20>M$2),3, IF(AND($F20<=M$2, $H20>=M$2), 2, "" ))) | N20: =IF(AND($F20<(N$2+7),$F20>N$2),1, IF(AND($H20<N$2+7,$H20>N$2),3, IF(AND($F20<=N$2, $H20>=N$2), 2, "" ))) | O20: =IF(AND($F20<(O$2+7),$F20>O$2),1, IF(AND($H20<O$2+7,$H20>O$2),3, IF(AND($F20<=O$2, $H20>=O$2), 2, "" ))) | P20: =IF(AND($F20<(P$2+7),$F20>P$2),1, IF(AND($H20<P$2+7,$H20>P$2),3, IF(AND($F20<=P$2, $H20>=P$2), 2, "" ))) | Q20: =IF(AND($F20<(Q$2+7),$F20>Q$2),1, IF(AND($H20<Q$2+7,$H20>Q$2),3, IF(AND($F20<=Q$2, $H20>=Q$2), 2, "" ))) | R20: =IF(AND($F20<(R$2+7),$F20>R$2),1, IF(AND($H20<R$2+7,$H20>R$2),3, IF(AND($F20<=R$2, $H20>=R$2), 2, "" ))) | S20: =IF(AND($F20<(S$2+7),$F20>S$2),1, IF(AND($H20<S$2+7,$H20>S$2),3, IF(AND($F20<=S$2, $H20>=S$2), 2, "" ))) | ... AQ20: =IF(AND($F20<(AQ$2+7),$F20>AQ$2),1, IF(AND($H20<AQ$2+7,$H20>AQ$2),3, IF(AND($F20<=AQ$2, $H20>=AQ$2), 2, "" )))
A21: C | B21: PAYMENT MILESTONE 3: DELIVERY OF INVERTERS AND BOS | C21: 43985 | D21: 2 | E21: 43987 | F21: 43985 | G21: 2 | H21: 43987
A22: 8 | B22: Installation | C22: 43990 | D22: 22 | E22: 44012 | F22: 43990 | G22: 22 | H22: 44012 | L22: =IF(AND($F22<(L$2+7),$F22>L$2),1, IF(AND($H22<L$2+7,$H22>L$2),3, IF(AND($F22<=L$2, $H22>=L$2), 2, "" ))) | M22: =IF(AND($F22<(M$2+7),$F22>M$2),1, IF(AND($H22<M$2+7,$H22>M$2),3, IF(AND($F22<=M$2, $H22>=M$2), 2, "" ))) | N22: =IF(AND($F22<(N$2+7),$F22>N$2),1, IF(AND($H22<N$2+7,$H22>N$2),3, IF(AND($F22<=N$2, $H22>=N$2), 2, "" ))) | O22: =IF(AND($F22<(O$2+7),$F22>O$2),1, IF(AND($H22<O$2+7,$H22>O$2),3, IF(AND($F22<=O$2, $H22>=O$2), 2, "" ))) | P22: =IF(AND($F22<(P$2+7),$F22>P$2),1, IF(AND($H22<P$2+7,$H22>P$2),3, IF(AND($F22<=P$2, $H22>=P$2), 2, "" ))) | Q22: =IF(AND($F22<(Q$2+7),$F22>Q$2),1, IF(AND($H22<Q$2+7,$H22>Q$2),3, IF(AND($F22<=Q$2, $H22>=Q$2), 2, "" ))) | R22: =IF(AND($F22<(R$2+7),$F22>R$2),1, IF(AND($H22<R$2+7,$H22>R$2),3, IF(AND($F22<=R$2, $H22>=R$2), 2, "" ))) | S22: =IF(AND($F22<(S$2+7),$F22>S$2),1, IF(AND($H22<S$2+7,$H22>S$2),3, IF(AND($F22<=S$2, $H22>=S$2), 2, "" ))) | ... AQ22: =IF(AND($F22<(AQ$2+7),$F22>AQ$2),1, IF(AND($H22<AQ$2+7,$H22>AQ$2),3, IF(AND($F22<=AQ$2, $H22>=AQ$2), 2, "" ))) -> 2
B23: Site Establishment | C23: 43990 | D23: 1 | E23: 43991 | F23: 43990 | G23: 1 | H23: 43991 | J23: Installation placed on hold due to Covid-19 case | L23: =IF(AND($F23<(L$2+7),$F23>L$2),1, IF(AND($H23<L$2+7,$H23>L$2),3, IF(AND($F23<=L$2, $H23>=L$2), 2, "" ))) | M23: =IF(AND($F23<(M$2+7),$F23>M$2),1, IF(AND($H23<M$2+7,$H23>M$2),3, IF(AND($F23<=M$2, $H23>=M$2), 2, "" ))) | N23: =IF(AND($F23<(N$2+7),$F23>N$2),1, IF(AND($H23<N$2+7,$H23>N$2),3, IF(AND($F23<=N$2, $H23>=N$2), 2, "" ))) | O23: =IF(AND($F23<(O$2+7),$F23>O$2),1, IF(AND($H23<O$2+7,$H23>O$2),3, IF(AND($F23<=O$2, $H23>=O$2), 2, "" ))) | P23: =IF(AND($F23<(P$2+7),$F23>P$2),1, IF(AND($H23<P$2+7,$H23>P$2),3, IF(AND($F23<=P$2, $H23>=P$2), 2, "" ))) | Q23: =IF(AND($F23<(Q$2+7),$F23>Q$2),1, IF(AND($H23<Q$2+7,$H23>Q$2),3, IF(AND($F23<=Q$2, $H23>=Q$2), 2, "" ))) | R23: =IF(AND($F23<(R$2+7),$F23>R$2),1, IF(AND($H23<R$2+7,$H23>R$2),3, IF(AND($F23<=R$2, $H23>=R$2), 2, "" ))) | S23: =IF(AND($F23<(S$2+7),$F23>S$2),1, IF(AND($H23<S$2+7,$H23>S$2),3, IF(AND($F23<=S$2, $H23>=S$2), 2, "" ))) | ... AQ23: =IF(AND($F23<(AQ$2+7),$F23>AQ$2),1, IF(AND($H23<AQ$2+7,$H23>AQ$2),3, IF(AND($F23<=AQ$2, $H23>=AQ$2), 2, "" )))
A24: 9 | B24: DC Works | C24: 43991 | D24: 16 | E24: 44012 | F24: 43991 | G24: 16 | H24: 44012 | L24: =IF(AND($F24<(L$2+7),$F24>L$2),1, IF(AND($H24<L$2+7,$H24>L$2),3, IF(AND($F24<=L$2, $H24>=L$2), 2, "" ))) | M24: =IF(AND($F24<(M$2+7),$F24>M$2),1, IF(AND($H24<M$2+7,$H24>M$2),3, IF(AND($F24<=M$2, $H24>=M$2), 2, "" ))) | N24: =IF(AND($F24<(N$2+7),$F24>N$2),1, IF(AND($H24<N$2+7,$H24>N$2),3, IF(AND($F24<=N$2, $H24>=N$2), 2, "" ))) | O24: =IF(AND($F24<(O$2+7),$F24>O$2),1, IF(AND($H24<O$2+7,$H24>O$2),3, IF(AND($F24<=O$2, $H24>=O$2), 2, "" ))) | P24: =IF(AND($F24<(P$2+7),$F24>P$2),1, IF(AND($H24<P$2+7,$H24>P$2),3, IF(AND($F24<=P$2, $H24>=P$2), 2, "" ))) | Q24: =IF(AND($F24<(Q$2+7),$F24>Q$2),1, IF(AND($H24<Q$2+7,$H24>Q$2),3, IF(AND($F24<=Q$2, $H24>=Q$2), 2, "" ))) | R24: =IF(AND($F24<(R$2+7),$F24>R$2),1, IF(AND($H24<R$2+7,$H24>R$2),3, IF(AND($F24<=R$2, $H24>=R$2), 2, "" ))) | S24: =IF(AND($F24<(S$2+7),$F24>S$2),1, IF(AND($H24<S$2+7,$H24>S$2),3, IF(AND($F24<=S$2, $H24>=S$2), 2, "" ))) | ... AQ24: =IF(AND($F24<(AQ$2+7),$F24>AQ$2),1, IF(AND($H24<AQ$2+7,$H24>AQ$2),3, IF(AND($F24<=AQ$2, $H24>=AQ$2), 2, "" ))) -> 2
B25: Mounting structure Installation | C25: 43991 | D25: 4 | E25: 43997 | F25: 43991 | G25: 4 | H25: 43997 | L25: =IF(AND($F25<(L$2+7),$F25>L$2),1, IF(AND($H25<L$2+7,$H25>L$2),3, IF(AND($F25<=L$2, $H25>=L$2), 2, "" ))) | M25: =IF(AND($F25<(M$2+7),$F25>M$2),1, IF(AND($H25<M$2+7,$H25>M$2),3, IF(AND($F25<=M$2, $H25>=M$2), 2, "" ))) | N25: =IF(AND($F25<(N$2+7),$F25>N$2),1, IF(AND($H25<N$2+7,$H25>N$2),3, IF(AND($F25<=N$2, $H25>=N$2), 2, "" ))) | O25: =IF(AND($F25<(O$2+7),$F25>O$2),1, IF(AND($H25<O$2+7,$H25>O$2),3, IF(AND($F25<=O$2, $H25>=O$2), 2, "" ))) | P25: =IF(AND($F25<(P$2+7),$F25>P$2),1, IF(AND($H25<P$2+7,$H25>P$2),3, IF(AND($F25<=P$2, $H25>=P$2), 2, "" ))) | Q25: =IF(AND($F25<(Q$2+7),$F25>Q$2),1, IF(AND($H25<Q$2+7,$H25>Q$2),3, IF(AND($F25<=Q$2, $H25>=Q$2), 2, "" ))) | R25: =IF(AND($F25<(R$2+7),$F25>R$2),1, IF(AND($H25<R$2+7,$H25>R$2),3, IF(AND($F25<=R$2, $H25>=R$2), 2, "" ))) | S25: =IF(AND($F25<(S$2+7),$F25>S$2),1, IF(AND($H25<S$2+7,$H25>S$2),3, IF(AND($F25<=S$2, $H25>=S$2), 2, "" ))) | ... AQ25: =IF(AND($F25<(AQ$2+7),$F25>AQ$2),1, IF(AND($H25<AQ$2+7,$H25>AQ$2),3, IF(AND($F25<=AQ$2, $H25>=AQ$2), 2, "" )))
B26: Cable tray Installation | C26: 43997 | D26: 3 | E26: 44004 | F26: 43997 | G26: 3 | H26: 44004 | L26: =IF(AND($F26<(L$2+7),$F26>L$2),1, IF(AND($H26<L$2+7,$H26>L$2),3, IF(AND($F26<=L$2, $H26>=L$2), 2, "" ))) | M26: =IF(AND($F26<(M$2+7),$F26>M$2),1, IF(AND($H26<M$2+7,$H26>M$2),3, IF(AND($F26<=M$2, $H26>=M$2), 2, "" ))) | N26: =IF(AND($F26<(N$2+7),$F26>N$2),1, IF(AND($H26<N$2+7,$H26>N$2),3, IF(AND($F26<=N$2, $H26>=N$2), 2, "" ))) | O26: =IF(AND($F26<(O$2+7),$F26>O$2),1, IF(AND($H26<O$2+7,$H26>O$2),3, IF(AND($F26<=O$2, $H26>=O$2), 2, "" ))) | P26: =IF(AND($F26<(P$2+7),$F26>P$2),1, IF(AND($H26<P$2+7,$H26>P$2),3, IF(AND($F26<=P$2, $H26>=P$2), 2, "" ))) | Q26: =IF(AND($F26<(Q$2+7),$F26>Q$2),1, IF(AND($H26<Q$2+7,$H26>Q$2),3, IF(AND($F26<=Q$2, $H26>=Q$2), 2, "" ))) | R26: =IF(AND($F26<(R$2+7),$F26>R$2),1, IF(AND($H26<R$2+7,$H26>R$2),3, IF(AND($F26<=R$2, $H26>=R$2), 2, "" ))) | S26: =IF(AND($F26<(S$2+7),$F26>S$2),1, IF(AND($H26<S$2+7,$H26>S$2),3, IF(AND($F26<=S$2, $H26>=S$2), 2, "" ))) | ... AQ26: =IF(AND($F26<(AQ$2+7),$F26>AQ$2),1, IF(AND($H26<AQ$2+7,$H26>AQ$2),3, IF(AND($F26<=AQ$2, $H26>=AQ$2), 2, "" )))
B27: DC Cable Installation | C27: 44004 | D27: 2 | E27: 44006 | F27: 44004 | G27: 2 | H27: 44006 | L27: =IF(AND($F27<(L$2+7),$F27>L$2),1, IF(AND($H27<L$2+7,$H27>L$2),3, IF(AND($F27<=L$2, $H27>=L$2), 2, "" ))) | M27: =IF(AND($F27<(M$2+7),$F27>M$2),1, IF(AND($H27<M$2+7,$H27>M$2),3, IF(AND($F27<=M$2, $H27>=M$2), 2, "" ))) | N27: =IF(AND($F27<(N$2+7),$F27>N$2),1, IF(AND($H27<N$2+7,$H27>N$2),3, IF(AND($F27<=N$2, $H27>=N$2), 2, "" ))) | O27: =IF(AND($F27<(O$2+7),$F27>O$2),1, IF(AND($H27<O$2+7,$H27>O$2),3, IF(AND($F27<=O$2, $H27>=O$2), 2, "" ))) | P27: =IF(AND($F27<(P$2+7),$F27>P$2),1, IF(AND($H27<P$2+7,$H27>P$2),3, IF(AND($F27<=P$2, $H27>=P$2), 2, "" ))) | Q27: =IF(AND($F27<(Q$2+7),$F27>Q$2),1, IF(AND($H27<Q$2+7,$H27>Q$2),3, IF(AND($F27<=Q$2, $H27>=Q$2), 2, "" ))) | R27: =IF(AND($F27<(R$2+7),$F27>R$2),1, IF(AND($H27<R$2+7,$H27>R$2),3, IF(AND($F27<=R$2, $H27>=R$2), 2, "" ))) | S27: =IF(AND($F27<(S$2+7),$F27>S$2),1, IF(AND($H27<S$2+7,$H27>S$2),3, IF(AND($F27<=S$2, $H27>=S$2), 2, "" ))) | ... AQ27: =IF(AND($F27<(AQ$2+7),$F27>AQ$2),1, IF(AND($H27<AQ$2+7,$H27>AQ$2),3, IF(AND($F27<=AQ$2, $H27>=AQ$2), 2, "" )))
B28: Module Installation | C28: 44006 | D28: 4 | E28: 44012 | F28: 44006 | G28: 4 | H28: 44012 | L28: =IF(AND($F28<(L$2+7),$F28>L$2),1, IF(AND($H28<L$2+7,$H28>L$2),3, IF(AND($F28<=L$2, $H28>=L$2), 2, "" ))) | M28: =IF(AND($F28<(M$2+7),$F28>M$2),1, IF(AND($H28<M$2+7,$H28>M$2),3, IF(AND($F28<=M$2, $H28>=M$2), 2, "" ))) | N28: =IF(AND($F28<(N$2+7),$F28>N$2),1, IF(AND($H28<N$2+7,$H28>N$2),3, IF(AND($F28<=N$2, $H28>=N$2), 2, "" ))) | O28: =IF(AND($F28<(O$2+7),$F28>O$2),1, IF(AND($H28<O$2+7,$H28>O$2),3, IF(AND($F28<=O$2, $H28>=O$2), 2, "" ))) | P28: =IF(AND($F28<(P$2+7),$F28>P$2),1, IF(AND($H28<P$2+7,$H28>P$2),3, IF(AND($F28<=P$2, $H28>=P$2), 2, "" ))) | Q28: =IF(AND($F28<(Q$2+7),$F28>Q$2),1, IF(AND($H28<Q$2+7,$H28>Q$2),3, IF(AND($F28<=Q$2, $H28>=Q$2), 2, "" ))) | R28: =IF(AND($F28<(R$2+7),$F28>R$2),1, IF(AND($H28<R$2+7,$H28>R$2),3, IF(AND($F28<=R$2, $H28>=R$2), 2, "" ))) | S28: =IF(AND($F28<(S$2+7),$F28>S$2),1, IF(AND($H28<S$2+7,$H28>S$2),3, IF(AND($F28<=S$2, $H28>=S$2), 2, "" ))) | ... AQ28: =IF(AND($F28<(AQ$2+7),$F28>AQ$2),1, IF(AND($H28<AQ$2+7,$H28>AQ$2),3, IF(AND($F28<=AQ$2, $H28>=AQ$2), 2, "" ))) -> 2
B29: Earth Cable Installation | C29: 44004 | D29: 1 | E29: 44005 | F29: 44004 | G29: 1 | H29: 44005 | L29: =IF(AND($F29<(L$2+7),$F29>L$2),1, IF(AND($H29<L$2+7,$H29>L$2),3, IF(AND($F29<=L$2, $H29>=L$2), 2, "" ))) | M29: =IF(AND($F29<(M$2+7),$F29>M$2),1, IF(AND($H29<M$2+7,$H29>M$2),3, IF(AND($F29<=M$2, $H29>=M$2), 2, "" ))) | N29: =IF(AND($F29<(N$2+7),$F29>N$2),1, IF(AND($H29<N$2+7,$H29>N$2),3, IF(AND($F29<=N$2, $H29>=N$2), 2, "" ))) | O29: =IF(AND($F29<(O$2+7),$F29>O$2),1, IF(AND($H29<O$2+7,$H29>O$2),3, IF(AND($F29<=O$2, $H29>=O$2), 2, "" ))) | P29: =IF(AND($F29<(P$2+7),$F29>P$2),1, IF(AND($H29<P$2+7,$H29>P$2),3, IF(AND($F29<=P$2, $H29>=P$2), 2, "" ))) | Q29: =IF(AND($F29<(Q$2+7),$F29>Q$2),1, IF(AND($H29<Q$2+7,$H29>Q$2),3, IF(AND($F29<=Q$2, $H29>=Q$2), 2, "" ))) | R29: =IF(AND($F29<(R$2+7),$F29>R$2),1, IF(AND($H29<R$2+7,$H29>R$2),3, IF(AND($F29<=R$2, $H29>=R$2), 2, "" ))) | S29: =IF(AND($F29<(S$2+7),$F29>S$2),1, IF(AND($H29<S$2+7,$H29>S$2),3, IF(AND($F29<=S$2, $H29>=S$2), 2, "" ))) | ... AQ29: =IF(AND($F29<(AQ$2+7),$F29>AQ$2),1, IF(AND($H29<AQ$2+7,$H29>AQ$2),3, IF(AND($F29<=AQ$2, $H29>=AQ$2), 2, "" )))
A30: 10 | B30: AC Works | C30: 43991 | D30: 8 | E30: 44000 | F30: 43991 | G30: 8 | H30: 44000
B31: Inverters Installation | C31: 43991 | D31: 2 | E31: 43993 | F31: 43991 | G31: 2 | H31: 43993 | L31: =IF(AND($F31<(L$2+7),$F31>L$2),1, IF(AND($H31<L$2+7,$H31>L$2),3, IF(AND($F31<=L$2, $H31>=L$2), 2, "" ))) | M31: =IF(AND($F31<(M$2+7),$F31>M$2),1, IF(AND($H31<M$2+7,$H31>M$2),3, IF(AND($F31<=M$2, $H31>=M$2), 2, "" ))) | N31: =IF(AND($F31<(N$2+7),$F31>N$2),1, IF(AND($H31<N$2+7,$H31>N$2),3, IF(AND($F31<=N$2, $H31>=N$2), 2, "" ))) | O31: =IF(AND($F31<(O$2+7),$F31>O$2),1, IF(AND($H31<O$2+7,$H31>O$2),3, IF(AND($F31<=O$2, $H31>=O$2), 2, "" ))) | P31: =IF(AND($F31<(P$2+7),$F31>P$2),1, IF(AND($H31<P$2+7,$H31>P$2),3, IF(AND($F31<=P$2, $H31>=P$2), 2, "" ))) | Q31: =IF(AND($F31<(Q$2+7),$F31>Q$2),1, IF(AND($H31<Q$2+7,$H31>Q$2),3, IF(AND($F31<=Q$2, $H31>=Q$2), 2, "" ))) | R31: =IF(AND($F31<(R$2+7),$F31>R$2),1, IF(AND($H31<R$2+7,$H31>R$2),3, IF(AND($F31<=R$2, $H31>=R$2), 2, "" ))) | S31: =IF(AND($F31<(S$2+7),$F31>S$2),1, IF(AND($H31<S$2+7,$H31>S$2),3, IF(AND($F31<=S$2, $H31>=S$2), 2, "" ))) | ... AQ31: =IF(AND($F31<(AQ$2+7),$F31>AQ$2),1, IF(AND($H31<AQ$2+7,$H31>AQ$2),3, IF(AND($F31<=AQ$2, $H31>=AQ$2), 2, "" )))
B32: AC BOS Installation | C32: 43993 | D32: 3 | E32: 44000 | F32: 43993 | G32: 3 | H32: 44000 | L32: =IF(AND($F32<(L$2+7),$F32>L$2),1, IF(AND($H32<L$2+7,$H32>L$2),3, IF(AND($F32<=L$2, $H32>=L$2), 2, "" ))) | M32: =IF(AND($F32<(M$2+7),$F32>M$2),1, IF(AND($H32<M$2+7,$H32>M$2),3, IF(AND($F32<=M$2, $H32>=M$2), 2, "" ))) | N32: =IF(AND($F32<(N$2+7),$F32>N$2),1, IF(AND($H32<N$2+7,$H32>N$2),3, IF(AND($F32<=N$2, $H32>=N$2), 2, "" ))) | O32: =IF(AND($F32<(O$2+7),$F32>O$2),1, IF(AND($H32<O$2+7,$H32>O$2),3, IF(AND($F32<=O$2, $H32>=O$2), 2, "" ))) | P32: =IF(AND($F32<(P$2+7),$F32>P$2),1, IF(AND($H32<P$2+7,$H32>P$2),3, IF(AND($F32<=P$2, $H32>=P$2), 2, "" ))) | Q32: =IF(AND($F32<(Q$2+7),$F32>Q$2),1, IF(AND($H32<Q$2+7,$H32>Q$2),3, IF(AND($F32<=Q$2, $H32>=Q$2), 2, "" ))) | R32: =IF(AND($F32<(R$2+7),$F32>R$2),1, IF(AND($H32<R$2+7,$H32>R$2),3, IF(AND($F32<=R$2, $H32>=R$2), 2, "" ))) | S32: =IF(AND($F32<(S$2+7),$F32>S$2),1, IF(AND($H32<S$2+7,$H32>S$2),3, IF(AND($F32<=S$2, $H32>=S$2), 2, "" ))) | ... AQ32: =IF(AND($F32<(AQ$2+7),$F32>AQ$2),1, IF(AND($H32<AQ$2+7,$H32>AQ$2),3, IF(AND($F32<=AQ$2, $H32>=AQ$2), 2, "" )))
B33: AC Cable/Tie-In | C33: 43992 | D33: 3 | E33: 43997 | F33: 43992 | G33: 3 | H33: 43997 | L33: =IF(AND($F33<(L$2+7),$F33>L$2),1, IF(AND($H33<L$2+7,$H33>L$2),3, IF(AND($F33<=L$2, $H33>=L$2), 2, "" ))) | M33: =IF(AND($F33<(M$2+7),$F33>M$2),1, IF(AND($H33<M$2+7,$H33>M$2),3, IF(AND($F33<=M$2, $H33>=M$2), 2, "" ))) | N33: =IF(AND($F33<(N$2+7),$F33>N$2),1, IF(AND($H33<N$2+7,$H33>N$2),3, IF(AND($F33<=N$2, $H33>=N$2), 2, "" ))) | O33: =IF(AND($F33<(O$2+7),$F33>O$2),1, IF(AND($H33<O$2+7,$H33>O$2),3, IF(AND($F33<=O$2, $H33>=O$2), 2, "" ))) | P33: =IF(AND($F33<(P$2+7),$F33>P$2),1, IF(AND($H33<P$2+7,$H33>P$2),3, IF(AND($F33<=P$2, $H33>=P$2), 2, "" ))) | Q33: =IF(AND($F33<(Q$2+7),$F33>Q$2),1, IF(AND($H33<Q$2+7,$H33>Q$2),3, IF(AND($F33<=Q$2, $H33>=Q$2), 2, "" ))) | R33: =IF(AND($F33<(R$2+7),$F33>R$2),1, IF(AND($H33<R$2+7,$H33>R$2),3, IF(AND($F33<=R$2, $H33>=R$2), 2, "" ))) | S33: =IF(AND($F33<(S$2+7),$F33>S$2),1, IF(AND($H33<S$2+7,$H33>S$2),3, IF(AND($F33<=S$2, $H33>=S$2), 2, "" ))) | ... AQ33: =IF(AND($F33<(AQ$2+7),$F33>AQ$2),1, IF(AND($H33<AQ$2+7,$H33>AQ$2),3, IF(AND($F33<=AQ$2, $H33>=AQ$2), 2, "" )))
B34: Monitoring Platform Installation | C34: 43997 | D34: 1 | E34: 44000 | F34: 43997 | G34: 1 | H34: 44000
A35: 11 | B35: Completion | C35: 44000 | D35: 14 | E35: 44014 | F35: 44000 | G35: 14 | H35: 44014 | L35: =IF(AND($F35<(L$2+7),$F35>L$2),1, IF(AND($H35<L$2+7,$H35>L$2),3, IF(AND($F35<=L$2, $H35>=L$2), 2, "" ))) | M35: =IF(AND($F35<(M$2+7),$F35>M$2),1, IF(AND($H35<M$2+7,$H35>M$2),3, IF(AND($F35<=M$2, $H35>=M$2), 2, "" ))) | N35: =IF(AND($F35<(N$2+7),$F35>N$2),1, IF(AND($H35<N$2+7,$H35>N$2),3, IF(AND($F35<=N$2, $H35>=N$2), 2, "" ))) | O35: =IF(AND($F35<(O$2+7),$F35>O$2),1, IF(AND($H35<O$2+7,$H35>O$2),3, IF(AND($F35<=O$2, $H35>=O$2), 2, "" ))) | P35: =IF(AND($F35<(P$2+7),$F35>P$2),1, IF(AND($H35<P$2+7,$H35>P$2),3, IF(AND($F35<=P$2, $H35>=P$2), 2, "" ))) | Q35: =IF(AND($F35<(Q$2+7),$F35>Q$2),1, IF(AND($H35<Q$2+7,$H35>Q$2),3, IF(AND($F35<=Q$2, $H35>=Q$2), 2, "" ))) | R35: =IF(AND($F35<(R$2+7),$F35>R$2),1, IF(AND($H35<R$2+7,$H35>R$2),3, IF(AND($F35<=R$2, $H35>=R$2), 2, "" ))) | S35: =IF(AND($F35<(S$2+7),$F35>S$2),1, IF(AND($H35<S$2+7,$H35>S$2),3, IF(AND($F35<=S$2, $H35>=S$2), 2, "" ))) | ... AQ35: =IF(AND($F35<(AQ$2+7),$F35>AQ$2),1, IF(AND($H35<AQ$2+7,$H35>AQ$2),3, IF(AND($F35<=AQ$2, $H35>=AQ$2), 2, "" ))) -> 3
B36: DC Works | C36: 44012 | D36: 2 | E36: 44014 | F36: 44012 | G36: 2 | H36: 44014 | L36: =IF(AND($F36<(L$2+7),$F36>L$2),1, IF(AND($H36<L$2+7,$H36>L$2),3, IF(AND($F36<=L$2, $H36>=L$2), 2, "" ))) | M36: =IF(AND($F36<(M$2+7),$F36>M$2),1, IF(AND($H36<M$2+7,$H36>M$2),3, IF(AND($F36<=M$2, $H36>=M$2), 2, "" ))) | N36: =IF(AND($F36<(N$2+7),$F36>N$2),1, IF(AND($H36<N$2+7,$H36>N$2),3, IF(AND($F36<=N$2, $H36>=N$2), 2, "" ))) | O36: =IF(AND($F36<(O$2+7),$F36>O$2),1, IF(AND($H36<O$2+7,$H36>O$2),3, IF(AND($F36<=O$2, $H36>=O$2), 2, "" ))) | P36: =IF(AND($F36<(P$2+7),$F36>P$2),1, IF(AND($H36<P$2+7,$H36>P$2),3, IF(AND($F36<=P$2, $H36>=P$2), 2, "" ))) | Q36: =IF(AND($F36<(Q$2+7),$F36>Q$2),1, IF(AND($H36<Q$2+7,$H36>Q$2),3, IF(AND($F36<=Q$2, $H36>=Q$2), 2, "" ))) | R36: =IF(AND($F36<(R$2+7),$F36>R$2),1, IF(AND($H36<R$2+7,$H36>R$2),3, IF(AND($F36<=R$2, $H36>=R$2), 2, "" ))) | S36: =IF(AND($F36<(S$2+7),$F36>S$2),1, IF(AND($H36<S$2+7,$H36>S$2),3, IF(AND($F36<=S$2, $H36>=S$2), 2, "" ))) | ... AQ36: =IF(AND($F36<(AQ$2+7),$F36>AQ$2),1, IF(AND($H36<AQ$2+7,$H36>AQ$2),3, IF(AND($F36<=AQ$2, $H36>=AQ$2), 2, "" ))) -> 3
B37: AC Works | C37: 44000 | D37: 2 | E37: 44004 | F37: 44000 | G37: 2 | H37: 44004 | L37: =IF(AND($F37<(L$2+7),$F37>L$2),1, IF(AND($H37<L$2+7,$H37>L$2),3, IF(AND($F37<=L$2, $H37>=L$2), 2, "" ))) | M37: =IF(AND($F37<(M$2+7),$F37>M$2),1, IF(AND($H37<M$2+7,$H37>M$2),3, IF(AND($F37<=M$2, $H37>=M$2), 2, "" ))) | N37: =IF(AND($F37<(N$2+7),$F37>N$2),1, IF(AND($H37<N$2+7,$H37>N$2),3, IF(AND($F37<=N$2, $H37>=N$2), 2, "" ))) | O37: =IF(AND($F37<(O$2+7),$F37>O$2),1, IF(AND($H37<O$2+7,$H37>O$2),3, IF(AND($F37<=O$2, $H37>=O$2), 2, "" ))) | P37: =IF(AND($F37<(P$2+7),$F37>P$2),1, IF(AND($H37<P$2+7,$H37>P$2),3, IF(AND($F37<=P$2, $H37>=P$2), 2, "" ))) | Q37: =IF(AND($F37<(Q$2+7),$F37>Q$2),1, IF(AND($H37<Q$2+7,$H37>Q$2),3, IF(AND($F37<=Q$2, $H37>=Q$2), 2, "" ))) | R37: =IF(AND($F37<(R$2+7),$F37>R$2),1, IF(AND($H37<R$2+7,$H37>R$2),3, IF(AND($F37<=R$2, $H37>=R$2), 2, "" ))) | S37: =IF(AND($F37<(S$2+7),$F37>S$2),1, IF(AND($H37<S$2+7,$H37>S$2),3, IF(AND($F37<=S$2, $H37>=S$2), 2, "" ))) | ... AQ37: =IF(AND($F37<(AQ$2+7),$F37>AQ$2),1, IF(AND($H37<AQ$2+7,$H37>AQ$2),3, IF(AND($F37<=AQ$2, $H37>=AQ$2), 2, "" )))
A38: D | B38: PAYMENT MILESTONE 4: PRACTICAL COMPLETION | C38: 44012 | D38: 1 | E38: 44013 | F38: 44012 | G38: 1 | H38: 44013 | L38: =IF(AND($F38<(L$2+7),$F38>L$2),1, IF(AND($H38<L$2+7,$H38>L$2),3, IF(AND($F38<=L$2, $H38>=L$2), 2, "" ))) | M38: =IF(AND($F38<(M$2+7),$F38>M$2),1, IF(AND($H38<M$2+7,$H38>M$2),3, IF(AND($F38<=M$2, $H38>=M$2), 2, "" ))) | N38: =IF(AND($F38<(N$2+7),$F38>N$2),1, IF(AND($H38<N$2+7,$H38>N$2),3, IF(AND($F38<=N$2, $H38>=N$2), 2, "" ))) | O38: =IF(AND($F38<(O$2+7),$F38>O$2),1, IF(AND($H38<O$2+7,$H38>O$2),3, IF(AND($F38<=O$2, $H38>=O$2), 2, "" ))) | P38: =IF(AND($F38<(P$2+7),$F38>P$2),1, IF(AND($H38<P$2+7,$H38>P$2),3, IF(AND($F38<=P$2, $H38>=P$2), 2, "" ))) | Q38: =IF(AND($F38<(Q$2+7),$F38>Q$2),1, IF(AND($H38<Q$2+7,$H38>Q$2),3, IF(AND($F38<=Q$2, $H38>=Q$2), 2, "" ))) | R38: =IF(AND($F38<(R$2+7),$F38>R$2),1, IF(AND($H38<R$2+7,$H38>R$2),3, IF(AND($F38<=R$2, $H38>=R$2), 2, "" ))) | S38: =IF(AND($F38<(S$2+7),$F38>S$2),1, IF(AND($H38<S$2+7,$H38>S$2),3, IF(AND($F38<=S$2, $H38>=S$2), 2, "" ))) | ... AQ38: =IF(AND($F38<(AQ$2+7),$F38>AQ$2),1, IF(AND($H38<AQ$2+7,$H38>AQ$2),3, IF(AND($F38<=AQ$2, $H38>=AQ$2), 2, "" ))) -> 3
A39: 12 | B39: Commissioning | C39: 43997 | D39: 22 | E39: 44019 | F39: 43997 | G39: 22 | H39: 44019 | L39: =IF(AND($F39<(L$2+7),$F39>L$2),1, IF(AND($H39<L$2+7,$H39>L$2),3, IF(AND($F39<=L$2, $H39>=L$2), 2, "" ))) | M39: =IF(AND($F39<(M$2+7),$F39>M$2),1, IF(AND($H39<M$2+7,$H39>M$2),3, IF(AND($F39<=M$2, $H39>=M$2), 2, "" ))) | N39: =IF(AND($F39<(N$2+7),$F39>N$2),1, IF(AND($H39<N$2+7,$H39>N$2),3, IF(AND($F39<=N$2, $H39>=N$2), 2, "" ))) | O39: =IF(AND($F39<(O$2+7),$F39>O$2),1, IF(AND($H39<O$2+7,$H39>O$2),3, IF(AND($F39<=O$2, $H39>=O$2), 2, "" ))) | P39: =IF(AND($F39<(P$2+7),$F39>P$2),1, IF(AND($H39<P$2+7,$H39>P$2),3, IF(AND($F39<=P$2, $H39>=P$2), 2, "" ))) | Q39: =IF(AND($F39<(Q$2+7),$F39>Q$2),1, IF(AND($H39<Q$2+7,$H39>Q$2),3, IF(AND($F39<=Q$2, $H39>=Q$2), 2, "" ))) | R39: =IF(AND($F39<(R$2+7),$F39>R$2),1, IF(AND($H39<R$2+7,$H39>R$2),3, IF(AND($F39<=R$2, $H39>=R$2), 2, "" ))) | S39: =IF(AND($F39<(S$2+7),$F39>S$2),1, IF(AND($H39<S$2+7,$H39>S$2),3, IF(AND($F39<=S$2, $H39>=S$2), 2, "" ))) | ... AQ39: =IF(AND($F39<(AQ$2+7),$F39>AQ$2),1, IF(AND($H39<AQ$2+7,$H39>AQ$2),3, IF(AND($F39<=AQ$2, $H39>=AQ$2), 2, "" ))) -> 2
B40: Snag List | C40: 44014 | D40: 3 | E40: 44019 | F40: 44014 | G40: 3 | H40: 44019
B41: Pre-Commissioning Checks | C41: 44010 | D41: 2 | E41: 44012 | F41: 44010 | G41: 2 | H41: 44012
B42: Issue CoC | C42: 43997 | D42: 2 | E42: 44001 | F42: 43997 | G42: 2 | H42: 44001 | L42: =IF(AND($F42<(L$2+7),$F42>L$2),1, IF(AND($H42<L$2+7,$H42>L$2),3, IF(AND($F42<=L$2, $H42>=L$2), 2, "" ))) | M42: =IF(AND($F42<(M$2+7),$F42>M$2),1, IF(AND($H42<M$2+7,$H42>M$2),3, IF(AND($F42<=M$2, $H42>=M$2), 2, "" ))) | N42: =IF(AND($F42<(N$2+7),$F42>N$2),1, IF(AND($H42<N$2+7,$H42>N$2),3, IF(AND($F42<=N$2, $H42>=N$2), 2, "" ))) | O42: =IF(AND($F42<(O$2+7),$F42>O$2),1, IF(AND($H42<O$2+7,$H42>O$2),3, IF(AND($F42<=O$2, $H42>=O$2), 2, "" ))) | P42: =IF(AND($F42<(P$2+7),$F42>P$2),1, IF(AND($H42<P$2+7,$H42>P$2),3, IF(AND($F42<=P$2, $H42>=P$2), 2, "" ))) | Q42: =IF(AND($F42<(Q$2+7),$F42>Q$2),1, IF(AND($H42<Q$2+7,$H42>Q$2),3, IF(AND($F42<=Q$2, $H42>=Q$2), 2, "" ))) | R42: =IF(AND($F42<(R$2+7),$F42>R$2),1, IF(AND($H42<R$2+7,$H42>R$2),3, IF(AND($F42<=R$2, $H42>=R$2), 2, "" ))) | S42: =IF(AND($F42<(S$2+7),$F42>S$2),1, IF(AND($H42<S$2+7,$H42>S$2),3, IF(AND($F42<=S$2, $H42>=S$2), 2, "" ))) | ... AQ42: =IF(AND($F42<(AQ$2+7),$F42>AQ$2),1, IF(AND($H42<AQ$2+7,$H42>AQ$2),3, IF(AND($F42<=AQ$2, $H42>=AQ$2), 2, "" )))
B43: Cold Commissioning | C43: 44012 | D43: 1 | E43: 44013 | F43: 44012 | G43: 1 | H43: 44013 | L43: =IF(AND($F43<(L$2+7),$F43>L$2),1, IF(AND($H43<L$2+7,$H43>L$2),3, IF(AND($F43<=L$2, $H43>=L$2), 2, "" ))) | M43: =IF(AND($F43<(M$2+7),$F43>M$2),1, IF(AND($H43<M$2+7,$H43>M$2),3, IF(AND($F43<=M$2, $H43>=M$2), 2, "" ))) | N43: =IF(AND($F43<(N$2+7),$F43>N$2),1, IF(AND($H43<N$2+7,$H43>N$2),3, IF(AND($F43<=N$2, $H43>=N$2), 2, "" ))) | O43: =IF(AND($F43<(O$2+7),$F43>O$2),1, IF(AND($H43<O$2+7,$H43>O$2),3, IF(AND($F43<=O$2, $H43>=O$2), 2, "" ))) | P43: =IF(AND($F43<(P$2+7),$F43>P$2),1, IF(AND($H43<P$2+7,$H43>P$2),3, IF(AND($F43<=P$2, $H43>=P$2), 2, "" ))) | Q43: =IF(AND($F43<(Q$2+7),$F43>Q$2),1, IF(AND($H43<Q$2+7,$H43>Q$2),3, IF(AND($F43<=Q$2, $H43>=Q$2), 2, "" ))) | R43: =IF(AND($F43<(R$2+7),$F43>R$2),1, IF(AND($H43<R$2+7,$H43>R$2),3, IF(AND($F43<=R$2, $H43>=R$2), 2, "" ))) | S43: =IF(AND($F43<(S$2+7),$F43>S$2),1, IF(AND($H43<S$2+7,$H43>S$2),3, IF(AND($F43<=S$2, $H43>=S$2), 2, "" ))) | ... AQ43: =IF(AND($F43<(AQ$2+7),$F43>AQ$2),1, IF(AND($H43<AQ$2+7,$H43>AQ$2),3, IF(AND($F43<=AQ$2, $H43>=AQ$2), 2, "" ))) -> 3
B44: Hot Commissioning | C44: 44013 | D44: 2 | E44: 44015 | F44: 44013 | G44: 2 | H44: 44015 | L44: =IF(AND($F44<(L$2+7),$F44>L$2),1, IF(AND($H44<L$2+7,$H44>L$2),3, IF(AND($F44<=L$2, $H44>=L$2), 2, "" ))) | M44: =IF(AND($F44<(M$2+7),$F44>M$2),1, IF(AND($H44<M$2+7,$H44>M$2),3, IF(AND($F44<=M$2, $H44>=M$2), 2, "" ))) | N44: =IF(AND($F44<(N$2+7),$F44>N$2),1, IF(AND($H44<N$2+7,$H44>N$2),3, IF(AND($F44<=N$2, $H44>=N$2), 2, "" ))) | O44: =IF(AND($F44<(O$2+7),$F44>O$2),1, IF(AND($H44<O$2+7,$H44>O$2),3, IF(AND($F44<=O$2, $H44>=O$2), 2, "" ))) | P44: =IF(AND($F44<(P$2+7),$F44>P$2),1, IF(AND($H44<P$2+7,$H44>P$2),3, IF(AND($F44<=P$2, $H44>=P$2), 2, "" ))) | Q44: =IF(AND($F44<(Q$2+7),$F44>Q$2),1, IF(AND($H44<Q$2+7,$H44>Q$2),3, IF(AND($F44<=Q$2, $H44>=Q$2), 2, "" ))) | R44: =IF(AND($F44<(R$2+7),$F44>R$2),1, IF(AND($H44<R$2+7,$H44>R$2),3, IF(AND($F44<=R$2, $H44>=R$2), 2, "" ))) | S44: =IF(AND($F44<(S$2+7),$F44>S$2),1, IF(AND($H44<S$2+7,$H44>S$2),3, IF(AND($F44<=S$2, $H44>=S$2), 2, "" ))) | ... AQ44: =IF(AND($F44<(AQ$2+7),$F44>AQ$2),1, IF(AND($H44<AQ$2+7,$H44>AQ$2),3, IF(AND($F44<=AQ$2, $H44>=AQ$2), 2, "" ))) -> 1
A45: 13 | B45: Handover | C45: 44020 | D45: 1 | E45: 44021 | F45: 44020 | G45: 1 | H45: 44021 | L45: =IF(AND($F45<(L$2+7),$F45>L$2),1, IF(AND($H45<L$2+7,$H45>L$2),3, IF(AND($F45<=L$2, $H45>=L$2), 2, "" ))) | M45: =IF(AND($F45<(M$2+7),$F45>M$2),1, IF(AND($H45<M$2+7,$H45>M$2),3, IF(AND($F45<=M$2, $H45>=M$2), 2, "" ))) | N45: =IF(AND($F45<(N$2+7),$F45>N$2),1, IF(AND($H45<N$2+7,$H45>N$2),3, IF(AND($F45<=N$2, $H45>=N$2), 2, "" ))) | O45: =IF(AND($F45<(O$2+7),$F45>O$2),1, IF(AND($H45<O$2+7,$H45>O$2),3, IF(AND($F45<=O$2, $H45>=O$2), 2, "" ))) | P45: =IF(AND($F45<(P$2+7),$F45>P$2),1, IF(AND($H45<P$2+7,$H45>P$2),3, IF(AND($F45<=P$2, $H45>=P$2), 2, "" ))) | Q45: =IF(AND($F45<(Q$2+7),$F45>Q$2),1, IF(AND($H45<Q$2+7,$H45>Q$2),3, IF(AND($F45<=Q$2, $H45>=Q$2), 2, "" ))) | R45: =IF(AND($F45<(R$2+7),$F45>R$2),1, IF(AND($H45<R$2+7,$H45>R$2),3, IF(AND($F45<=R$2, $H45>=R$2), 2, "" ))) | S45: =IF(AND($F45<(S$2+7),$F45>S$2),1, IF(AND($H45<S$2+7,$H45>S$2),3, IF(AND($F45<=S$2, $H45>=S$2), 2, "" ))) | ... AQ45: =IF(AND($F45<(AQ$2+7),$F45>AQ$2),1, IF(AND($H45<AQ$2+7,$H45>AQ$2),3, IF(AND($F45<=AQ$2, $H45>=AQ$2), 2, "" )))
A46: E | B46: PAYMENT MILESTONE 6: HANDOVER COMPLETE | C46: 44022 | D46: 1 | E46: 44025 | F46: 44022 | G46: 1 | H46: 44025
C47: 43831 | D47: These numbers are used to set the start and end dates on the Gantt Chart
C48: 44014

Sheet Certificate - Financial Close
B2: Emergent Energy – Financial Close Completion Certificate | H2: FINANCIAL CLOSE CERTIFICATE
B4: Project Name: | C4: ='Project Plan'!E2 -> Sibasa
B5: COO: | C5: Johannes Potgieter
B6: Programme Manager: | C6: Roedolph Venter
B7: HoPD: | C7: Natasha Watkins-Baker
B9: Date of Phase Completion:
B10: Phase Deliverables Checklist: (Y/N)
B11: Product Agreement | C11: NA
B12: EPC Agreement | C12: NA
B13: O&M Agreeement | C13: NA
B14: Cost Proposal | C14: Signed
B15: Deposit Received | C15: Yes
B16: Risks / Notes | C16: None
B18: Acknowledgement and Acceptance:
B19: Role | C19: Name | D19: Signature | E19: Date
B20: COO | C20: Johannes | D20: JTP | E20: 45953

Sheet Compliance
B2: HSE
B4: Description | C4: Status | D4: Approved By | E4: Date | F4: Results / Comments
B5: NOC
B6: 7.1 Agreement
B7: 13.2 Agreement
B8: EE File
B9: Subbie File
B16: SSEG
B18: Description | C18: Status | D18: Approved By | E18: Date | F18: Results / Comments
B19: SSEG Application
B20: PTI
B21: Commissioning Approval

Sheet Project Plan
N1: =TODAY() -> 46062 | O1: =TODAY() -> 46062
C2: PROJECT PLAN | E2: Sibasa | N2: 0 | O2: 1
C3: PROJECT SIZE (kWp) | E3: 467
C4: PROJECT DEVELOPER | E4: Natasha Watkins-Baker
C5: PROJECT MANAGERS | E5: Eon Van Rensburg
C6: CONTRACT VALUE | E6: 4662650
C7: Phase: | E7: Construction
B8: No. | C8: HIGH LEVEL PROGRAMME | E8: Planned Start | F8: Duration (days) | G8: Planned End | I8: Actual Start | J8: Duration (days) | K8: Actual End | M8: Status | N8: Expected Status | O8: Comment
F9: =G41-E19 -> 61 | J9: =K41-I19 -> 266 | M9: =AVERAGE(M11,M18,M21,M28,M35,M39,M46,M43) -> 0.74776786 | N9: =AVERAGE(N11,N18,N21,N28,N35,N39,N46,N43) -> 0.6875
B11: 1 | C11: Project Initiation | E11: =MIN(E12:E16) -> 45769 | F11: =G11-E11 -> 23 | G11: =MAX(G12:G16) -> 45792 | I11: =MIN(I12:I16) -> 45776 | J11: =K11-I11 -> 17 | K11: =MAX(K12:K16) -> 45793 | M11: =(J12*M12+J13*M13+J14*M14+J15*M15+J16*M16)/SUM(J12:J16) -> 1 | N11: =AVERAGE(N12:N16) -> 1
B12: 1.1 | C12: BD Handover | E12: 45769 | F12: 1 | G12: =WORKDAY.INTL(E12,F12,1,Data!$C$3:$C$44) -> 45770 | I12: 45790 | J12: 1 | K12: =WORKDAY.INTL(I12,J12,1,Data!$C$3:$C$44) -> 45791 | M12: 1 | N12: =_xlfn.LET( _xlpm.s,VALUE($I12), _xlpm.e,VALUE($K12), IF(OR(_xlpm.s="",_xlpm.e=""),"", IF(_xlpm.e<=_xlpm.s, IF(TODAY()>=_xlpm.e,1,0), MAX(0,MIN(1,(TODAY()-_xlpm.s)/(_xlpm.e-_xlpm.s))))) ) -> 1
B13: 1.2 | C13: Project Introduction | E13: =WORKDAY.INTL(E19,0,1,Data!$C$3:$C$44)-7 -> 45791 | F13: 1 | G13: =WORKDAY.INTL(E13,F13,1,Data!$C$3:$C$44) -> 45792 | I13: 45792 | J13: 1 | K13: =WORKDAY.INTL(I13,J13,1,Data!$C$3:$C$44) -> 45793 | M13: 1 | N13: =_xlfn.LET( _xlpm.s,VALUE($I13), _xlpm.e,VALUE($K13), IF(OR(_xlpm.s="",_xlpm.e=""),"", IF(_xlpm.e<=_xlpm.s, IF(TODAY()>=_xlpm.e,1,0), MAX(0,MIN(1,(TODAY()-_xlpm.s)/(_xlpm.e-_xlpm.s))))) ) -> 1
B14: 1.3 | C14: HSE | E14: =E12 -> 45769 | F14: 10 | G14: =WORKDAY.INTL(E14,F14,1,Data!$C$3:$C$44) -> 45784 | I14: =I12-14 -> 45776 | J14: 10 | K14: =WORKDAY.INTL(I14,J14,1,Data!$C$3:$C$44) -> 45791 | M14: 1 | N14: =_xlfn.LET( _xlpm.s,VALUE($I14), _xlpm.e,VALUE($K14), IF(OR(_xlpm.s="",_xlpm.e=""),"", IF(_xlpm.e<=_xlpm.s, IF(TODAY()>=_xlpm.e,1,0), MAX(0,MIN(1,(TODAY()-_xlpm.s)/(_xlpm.e-_xlpm.s))))) ) -> 1
B15: 1.4 | C15: Installer Kick Off | E15: =WORKDAY.INTL(E19,0,1,Data!$C$3:$C$44)-14 -> 45784 | F15: 1 | G15: =WORKDAY.INTL(E15,F15,1,Data!$C$3:$C$44) -> 45785 | I15: 45791 | J15: 1 | K15: =WORKDAY.INTL(I15,J15,1,Data!$C$3:$C$44) -> 45792 | M15: 1 | N15: =_xlfn.LET( _xlpm.s,VALUE($I15), _xlpm.e,VALUE($K15), IF(OR(_xlpm.s="",_xlpm.e=""),"", IF(_xlpm.e<=_xlpm.s, IF(TODAY()>=_xlpm.e,1,0), MAX(0,MIN(1,(TODAY()-_xlpm.s)/(_xlpm.e-_xlpm.s))))) ) -> 1
B16: 1.5 | C16: Project Review | E16: =WORKDAY.INTL(E19,0,1,Data!$C$3:$C$44)-14 -> 45784 | F16: 1 | G16: =WORKDAY.INTL(E16,F16,1,Data!$C$3:$C$44) -> 45785 | I16: 45785 | J16: 1 | K16: =WORKDAY.INTL(I16,J16,1,Data!$C$3:$C$44) -> 45786 | M16: 1 | N16: =_xlfn.LET( _xlpm.s,VALUE($I16), _xlpm.e,VALUE($K16), IF(OR(_xlpm.s="",_xlpm.e=""),"", IF(_xlpm.e<=_xlpm.s, IF(TODAY()>=_xlpm.e,1,0), MAX(0,MIN(1,(TODAY()-_xlpm.s)/(_xlpm.e-_xlpm.s))))) ) -> 1
B18: 2 | C18: Site Establishment | E18: =MIN(E19:E20) -> 45798 | F18: =G18-E18 -> 1 | G18: =MAX(G19) -> 45799 | I18: =MIN(I19:I20) -> 45798 | J18: =K18-I18 -> 1 | K18: =MAX(K19) -> 45799 | M18: =(J19*M19)/J18 -> 1 | N18: =(J19*N19)/J18 -> 1
B19: 2.1 | C19: Solar Contractor Establishment | E19: 45798 | F19: 1 | G19: =E19+F19 -> 45799 | I19: 45798 | J19: 1 | K19: =I19+J19 -> 45799 | M19: 1 | N19: =_xlfn.LET( _xlpm.s,VALUE($I19), _xlpm.e,VALUE($K19), IF(OR(_xlpm.s="",_xlpm.e=""),"", IF(_xlpm.e<=_xlpm.s, IF(TODAY()>=_xlpm.e,1,0), MAX(0,MIN(1,(TODAY()-_xlpm.s)/(_xlpm.e-_xlpm.s))))) ) -> 1 | S19: =NETWORKDAYS(I19,K41,Data!C3:C45) -> 166 | T19: Net Work Days
B21: 3 | C21: AC Installation | E21: =MIN(E22:E26) -> 45770 | F21: =G21-E21 -> 72 | G21: =MAX(G22:G26) -> 45842 | I21: =MIN(I22:I26) -> 45770 | J21: =K21-I21 -> 112 | K21: =MAX(K22:K26) -> 45882 | M21: =(J22*M22+J23*M23+J24*M24+J25*M25+J26*M26)/SUM(J22:J26) -> 1 | N21: =AVERAGE(N22:N26) -> 1 | S21: =S19/5 -> 33.2 | T21: Total Weeks
B22: 3.1 | C22: Inverters delivered | E22: =WORKDAY.INTL(G19,0,1,Data!$C$3:$C$44) -> 45799 | F22: 1 | G22: =WORKDAY.INTL(E22,F22,1,Data!$C$3:$C$44) -> 45800 | I22: 45799 | J22: 1 | K22: =WORKDAY.INTL(I22,J22,1,Data!$C$3:$C$44) -> 45800 | M22: 1 | N22: =_xlfn.LET( _xlpm.s,VALUE($I22), _xlpm.e,VALUE($K22), IF(OR(_xlpm.s="",_xlpm.e=""),"", IF(_xlpm.e<=_xlpm.s, IF(TODAY()>=_xlpm.e,1,0), MAX(0,MIN(1,(TODAY()-_xlpm.s)/(_xlpm.e-_xlpm.s))))) ) -> 1 | S22: =E3/S21 -> 14.066265 | T22: kW/Week Installation Rate
B23: 3.2 | C23: Inverters Mounted | E23: =WORKDAY.INTL(G22,0,1,Data!$C$3:$C$44) -> 45800 | F23: 5 | G23: =WORKDAY.INTL(E23,F23,1,Data!$C$3:$C$44) -> 45807 | I23: 45861 | J23: 12 | K23: =WORKDAY.INTL(I23,J23,1,Data!$C$3:$C$44) -> 45877 | M23: 1 | N23: =_xlfn.LET( _xlpm.s,VALUE($I23), _xlpm.e,VALUE($K23), IF(OR(_xlpm.s="",_xlpm.e=""),"", IF(_xlpm.e<=_xlpm.s, IF(TODAY()>=_xlpm.e,1,0), MAX(0,MIN(1,(TODAY()-_xlpm.s)/(_xlpm.e-_xlpm.s))))) ) -> 1
B24: 3.3 | C24: Solar DB Lead Time | E24: =WORKDAY.INTL(E19,0,1,Data!$C$3:$C$44)-28 -> 45770 | F24: 25 | G24: =WORKDAY.INTL(E24,F24,1,Data!$C$3:$C$44) -> 45806 | I24: =WORKDAY.INTL(I19,0,1,Data!$C$3:$C$44)-28 -> 45770 | J24: 45 | K24: =WORKDAY.INTL(I24,J24,1,Data!$C$3:$C$44) -> 45835 | M24: 1 | N24: =_xlfn.LET( _xlpm.s,VALUE($I24), _xlpm.e,VALUE($K24), IF(OR(_xlpm.s="",_xlpm.e=""),"", IF(_xlpm.e<=_xlpm.s, IF(TODAY()>=_xlpm.e,1,0), MAX(0,MIN(1,(TODAY()-_xlpm.s)/(_xlpm.e-_xlpm.s))))) ) -> 1
B25: 3.4 | C25: AC Works | E25: =WORKDAY.INTL(G24,0,1,Data!$C$3:$C$44) -> 45806 | F25: 25 | G25: =WORKDAY.INTL(E25,F25,1,Data!$C$3:$C$44) -> 45842 | I25: =I23 -> 45861 | J25: 15 | K25: =WORKDAY.INTL(I25,J25,1,Data!$C$3:$C$44) -> 45882 | M25: 1 | N25: =_xlfn.LET( _xlpm.s,VALUE($I25), _xlpm.e,VALUE($K25), IF(OR(_xlpm.s="",_xlpm.e=""),"", IF(_xlpm.e<=_xlpm.s, IF(TODAY()>=_xlpm.e,1,0), MAX(0,MIN(1,(TODAY()-_xlpm.s)/(_xlpm.e-_xlpm.s))))) ) -> 1
B26: 3.5 | C26: AC Tie-In | E26: =WORKDAY.INTL(E25,0,1,Data!$C$3:$C$44) -> 45806 | F26: 3 | G26: =WORKDAY.INTL(E26,F26,1,Data!$C$3:$C$44) -> 45811 | I26: 45875 | J26: 1 | K26: =WORKDAY.INTL(I26,J26,1,Data!$C$3:$C$44) -> 45876 | M26: 1 | N26: =_xlfn.LET( _xlpm.s,VALUE($I26), _xlpm.e,VALUE($K26), IF(OR(_xlpm.s="",_xlpm.e=""),"", IF(_xlpm.e<=_xlpm.s, IF(TODAY()>=_xlpm.e,1,0), MAX(0,MIN(1,(TODAY()-_xlpm.s)/(_xlpm.e-_xlpm.s))))) ) -> 1
B28: 4 | C28: DC Works | E28: =MIN(E30:E33) -> 45798 | F28: =G28-E28 -> 51 | G28: =MAX(G30:G33) -> 45849 | I28: =MIN(I30:I33) -> 45798 | J28: =K28-I28 -> 89 | K28: =MAX(K30:K33) -> 45887 | M28: 1 | N28: =AVERAGE(N30:N33) -> 1
B29: 4.1 | C29: Lifeline Installation (If Applicable) | M29: 0 | N29: 0
B30: 4.1 | C30: Mounting Structure delivered | E30: =E19 -> 45798 | F30: 1 | G30: =WORKDAY.INTL(E30,F30,1,Data!$C$3:$C$44) -> 45799 | I30: =I19 -> 45798 | J30: 1 | K30: =WORKDAY.INTL(I30,J30,1,Data!$C$3:$C$44) -> 45799 | M30: 1 | N30: =_xlfn.LET( _xlpm.s,VALUE($I30), _xlpm.e,VALUE($K30), IF(OR(_xlpm.s="",_xlpm.e=""),"", IF(_xlpm.e<=_xlpm.s, IF(TODAY()>=_xlpm.e,1,0), MAX(0,MIN(1,(TODAY()-_xlpm.s)/(_xlpm.e-_xlpm.s))))) ) -> 1
B31: 4.2 | C31: Mounting Structure installation | E31: =WORKDAY.INTL(G30,0,1,Data!$C$3:$C$44) -> 45799 | F31: 10 | G31: =WORKDAY.INTL(E31,F31,1,Data!$C$3:$C$44) -> 45813 | I31: =WORKDAY.INTL(K30,0,1,Data!$C$3:$C$44) -> 45799 | J31: 10 | K31: =WORKDAY.INTL(I31,J31,1,Data!$C$3:$C$44) -> 45813 | M31: 1 | N31: =_xlfn.LET( _xlpm.s,VALUE($I31), _xlpm.e,VALUE($K31), IF(OR(_xlpm.s="",_xlpm.e=""),"", IF(_xlpm.e<=_xlpm.s, IF(TODAY()>=_xlpm.e,1,0), MAX(0,MIN(1,(TODAY()-_xlpm.s)/(_xlpm.e-_xlpm.s))))) ) -> 1
B32: 4.3 | C32: DC Cable delivered | E32: =E30 -> 45798 | F32: 1 | G32: =WORKDAY.INTL(E32,F32,1,Data!$C$3:$C$44) -> 45799 | I32: 45806 | J32: 1 | K32: =WORKDAY.INTL(I32,J32,1,Data!$C$3:$C$44) -> 45807 | M32: 1 | N32: =_xlfn.LET( _xlpm.s,VALUE($I32), _xlpm.e,VALUE($K32), IF(OR(_xlpm.s="",_xlpm.e=""),"", IF(_xlpm.e<=_xlpm.s, IF(TODAY()>=_xlpm.e,1,0), MAX(0,MIN(1,(TODAY()-_xlpm.s)/(_xlpm.e-_xlpm.s))))) ) -> 1
B33: 4.3 | C33: DC Stringing | E33: =WORKDAY.INTL(G37,0,1,Data!$C$3:$C$44)-3 -> 45835 | F33: 10 | G33: =WORKDAY.INTL(E33,F33,1,Data!$C$3:$C$44) -> 45849 | I33: =WORKDAY.INTL(K37,0,1,Data!$C$3:$C$44)-7 -> 45824 | J33: 45 | K33: =WORKDAY.INTL(I33,J33,1,Data!$C$3:$C$44) -> 45887 | M33: 1 | N33: =_xlfn.LET( _xlpm.s,VALUE($I33), _xlpm.e,VALUE($K33), IF(OR(_xlpm.s="",_xlpm.e=""),"", IF(_xlpm.e<=_xlpm.s, IF(TODAY()>=_xlpm.e,1,0), MAX(0,MIN(1,(TODAY()-_xlpm.s)/(_xlpm.e-_xlpm.s))))) ) -> 1
B35: 5 | C35: Module installation | E35: =MIN(E36:E37) -> 45806 | F35: =G35-E35 -> 32 | G35: =MAX(G36:G37) -> 45838 | I35: =MIN(I36:I37) -> 45806 | J35: =K35-I35 -> 25 | K35: =MAX(K36:K37) -> 45831 | M35: =(J36*M36+J37*M37)/SUM(J36:J37) -> 1 | N35: =AVERAGE(N36:N37) -> 1
B36: 5.1 | C36: Module delivery | E36: =WORKDAY.INTL(G31,0,1,Data!$C$3:$C$44)-7 -> 45806 | F36: 1 | G36: =WORKDAY.INTL(E36,F36,1,Data!$C$3:$C$44) -> 45807 | I36: =WORKDAY.INTL(K31,0,1,Data!$C$3:$C$44)-7 -> 45806 | J36: 1 | K36: =WORKDAY.INTL(I36,J36,1,Data!$C$3:$C$44) -> 45807 | M36: 1 | N36: =_xlfn.LET( _xlpm.s,VALUE($I36), _xlpm.e,VALUE($K36), IF(OR(_xlpm.s="",_xlpm.e=""),"", IF(_xlpm.e<=_xlpm.s, IF(TODAY()>=_xlpm.e,1,0), MAX(0,MIN(1,(TODAY()-_xlpm.s)/(_xlpm.e-_xlpm.s))))) ) -> 1
B37: 5.2 | C37: Module mounting | E37: =G36 -> 45807 | F37: 20 | G37: =WORKDAY.INTL(E37,F37,1,Data!$C$3:$C$44) -> 45838 | I37: =K36 -> 45807 | J37: 15 | K37: =WORKDAY.INTL(I37,J37,1,Data!$C$3:$C$44) -> 45831 | M37: 1 | N37: =_xlfn.LET( _xlpm.s,VALUE($I37), _xlpm.e,VALUE($K37), IF(OR(_xlpm.s="",_xlpm.e=""),"", IF(_xlpm.e<=_xlpm.s, IF(TODAY()>=_xlpm.e,1,0), MAX(0,MIN(1,(TODAY()-_xlpm.s)/(_xlpm.e-_xlpm.s))))) ) -> 1
B39: 6 | C39: Commissioning | E39: =MIN(E40:E41) -> 45849 | F39: =G39-E39 -> 10 | G39: =MAX(G40:G41) -> 45859 | I39: =MIN(I40:I41) -> 45950 | J39: =K39-I39 -> 114 | K39: =MAX(K40:K41) -> 46064 | M39: =(J40*M40+J41*M41)/SUM(J40:J41) -> 0.98214286 | N39: =AVERAGE(N40:N41) -> 0.5
B40: 6.1 | C40: Roof Work Removal and Refit | E40: =WORKDAY.INTL(MAX(G21,G28,G35),0,1,Data!$C$3:$C$44) -> 45849 | F40: 1 | G40: =WORKDAY.INTL(E40,F40,1,Data!$C$3:$C$44) -> 45852 | I40: 45950 | J40: 55 | K40: =WORKDAY.INTL(I40,J40,1,Data!$C$3:$C$44) -> 46058 | M40: 1 | N40: =_xlfn.LET( _xlpm.s,VALUE($I40), _xlpm.e,VALUE($K40), IF(OR(_xlpm.s="",_xlpm.e=""),"", IF(_xlpm.e<=_xlpm.s, IF(TODAY()>=_xlpm.e,1,0), MAX(0,MIN(1,(TODAY()-_xlpm.s)/(_xlpm.e-_xlpm.s))))) ) -> 1
B41: 6.2 | C41: Practical Completion | E41: =WORKDAY.INTL(G40,0,1,Data!$C$3:$C$44) -> 45852 | F41: 5 | G41: =WORKDAY.INTL(E41,F41,1,Data!$C$3:$C$44) -> 45859 | I41: 46063 | J41: 1 | K41: =WORKDAY.INTL(I41,J41,1,Data!$C$3:$C$44) -> 46064 | M41: 0 | N41: =_xlfn.LET( _xlpm.s,VALUE($I41), _xlpm.e,VALUE($K41), IF(OR(_xlpm.s="",_xlpm.e=""),"", IF(_xlpm.e<=_xlpm.s, IF(TODAY()>=_xlpm.e,1,0), MAX(0,MIN(1,(TODAY()-_xlpm.s)/(_xlpm.e-_xlpm.s))))) ) -> 0
B43: 7 | C43: QA Inspections | E43: =MIN(E44) -> 45859 | F43: =G43-E43 -> 1 | G43: =MAX(G44) -> 45860 | I43: =MIN(I44) -> 46064 | J43: =K43-I43 -> 1 | K43: =MAX(K44) -> 46065 | M43: =(J44*M44)/SUM(J44) -> 0 | N43: =(K44*N44)/SUM(K44) -> 0
B44: 7.1 | C44: Red-Team Inspection | E44: =WORKDAY.INTL(G41,0,1,Data!$C$3:$C$44) -> 45859 | F44: 1 | G44: =WORKDAY.INTL(E44,F44,1,Data!$C$3:$C$44) -> 45860 | I44: 46064 | J44: 1 | K44: =WORKDAY.INTL(I44,J44,1,Data!$C$3:$C$44) -> 46065 | M44: 0 | N44: =_xlfn.LET( _xlpm.s,VALUE($I44), _xlpm.e,VALUE($K44), IF(OR(_xlpm.s="",_xlpm.e=""),"", IF(_xlpm.e<=_xlpm.s, IF(TODAY()>=_xlpm.e,1,0), MAX(0,MIN(1,(TODAY()-_xlpm.s)/(_xlpm.e-_xlpm.s))))) ) -> 0 | O44: Anderson Colsulting booked for 11 Feb
B46: 8 | C46: Project Closure | E46: =MIN(E47:E52) -> 45860 | F46: =G46-E46 -> 14 | G46: =MAX(G47:G52) -> 45874 | I46: =MIN(I47:I52) -> 46065 | J46: =K46-I46 -> 11 | K46: =MAX(K47:K52) -> 46076 | M46: =(J47*M47+J48*M48+J49*M49+J50*M50+J51*M51+J52*M52)/SUM(J47:J52) -> 0 | N46: =AVERAGE(N47:N52) -> 0
B47: 8.1 | C47: Equipment serial numbers | E47: =G44 -> 45860 | F47: 2 | G47: =WORKDAY.INTL(E47,F47,1,Data!$C$3:$C$44) -> 45862 | I47: =K44 -> 46065 | J47: 2 | K47: =WORKDAY.INTL(I47,J47,1,Data!$C$3:$C$44) -> 46069 | M47: 0 | N47: =_xlfn.LET( _xlpm.s,VALUE($I47), _xlpm.e,VALUE($K47), IF(OR(_xlpm.s="",_xlpm.e=""),"", IF(_xlpm.e<=_xlpm.s, IF(TODAY()>=_xlpm.e,1,0), MAX(0,MIN(1,(TODAY()-_xlpm.s)/(_xlpm.e-_xlpm.s))))) ) -> 0
B48: 8.2 | C48: Snags completion | E48: =G44 -> 45860 | F48: 5 | G48: =WORKDAY.INTL(E48,F48,1,Data!$C$3:$C$44) -> 45867 | I48: =K44 -> 46065 | J48: 1 | K48: =WORKDAY.INTL(I48,J48,1,Data!$C$3:$C$44) -> 46066 | M48: 0 | N48: =_xlfn.LET( _xlpm.s,VALUE($I48), _xlpm.e,VALUE($K48), IF(OR(_xlpm.s="",_xlpm.e=""),"", IF(_xlpm.e<=_xlpm.s, IF(TODAY()>=_xlpm.e,1,0), MAX(0,MIN(1,(TODAY()-_xlpm.s)/(_xlpm.e-_xlpm.s))))) ) -> 0
B49: 8.3 | C49: System Performance Monitoring | E49: =WORKDAY.INTL(G48,0,1,Data!$C$3:$C$44) -> 45867 | F49: 5 | G49: =WORKDAY.INTL(E49,F49,1,Data!$C$3:$C$44) -> 45874 | I49: =WORKDAY.INTL(K48,0,1,Data!$C$3:$C$44) -> 46066 | J49: 5 | K49: =WORKDAY.INTL(I49,J49,1,Data!$C$3:$C$44) -> 46073 | M49: 0 | N49: =_xlfn.LET( _xlpm.s,VALUE($I49), _xlpm.e,VALUE($K49), IF(OR(_xlpm.s="",_xlpm.e=""),"", IF(_xlpm.e<=_xlpm.s, IF(TODAY()>=_xlpm.e,1,0), MAX(0,MIN(1,(TODAY()-_xlpm.s)/(_xlpm.e-_xlpm.s))))) ) -> 0
B50: 8.4 | C50: Handover documentation | E50: =WORKDAY.INTL(E48,0,1,Data!$C$3:$C$44) -> 45860 | F50: 6 | G50: =WORKDAY.INTL(E50,F50,1,Data!$C$3:$C$44) -> 45868 | I50: =WORKDAY.INTL(I48,0,1,Data!$C$3:$C$44) -> 46065 | J50: 6 | K50: =WORKDAY.INTL(I50,J50,1,Data!$C$3:$C$44) -> 46073 | M50: 0 | N50: =_xlfn.LET( _xlpm.s,VALUE($I50), _xlpm.e,VALUE($K50), IF(OR(_xlpm.s="",_xlpm.e=""),"", IF(_xlpm.e<=_xlpm.s, IF(TODAY()>=_xlpm.e,1,0), MAX(0,MIN(1,(TODAY()-_xlpm.s)/(_xlpm.e-_xlpm.s))))) ) -> 0
B51: 8.5 | C51: Handover to Client | E51: =WORKDAY.INTL(G50,0,1,Data!$C$3:$C$44) -> 45868 | F51: 1 | G51: =WORKDAY.INTL(E51,F51,1,Data!$C$3:$C$44) -> 45869 | I51: =WORKDAY.INTL(K50,0,1,Data!$C$3:$C$44) -> 46073 | J51: 1 | K51: =WORKDAY.INTL(I51,J51,1,Data!$C$3:$C$44) -> 46076 | M51: 0 | N51: =_xlfn.LET( _xlpm.s,VALUE($I51), _xlpm.e,VALUE($K51), IF(OR(_xlpm.s="",_xlpm.e=""),"", IF(_xlpm.e<=_xlpm.s, IF(TODAY()>=_xlpm.e,1,0), MAX(0,MIN(1,(TODAY()-_xlpm.s)/(_xlpm.e-_xlpm.s))))) ) -> 0
B52: 8.6 | C52: Handover to Matriarch | E52: =WORKDAY.INTL(E48,0,1,Data!$C$3:$C$44)+2 -> 45862 | F52: 5 | G52: =WORKDAY.INTL(E52,F52,1,Data!$C$3:$C$44) -> 45869 | I52: =WORKDAY.INTL(I48,0,1,Data!$C$3:$C$44)+2 -> 46067 | J52: 5 | K52: =WORKDAY.INTL(I52,J52,1,Data!$C$3:$C$44) -> 46073 | M52: 0 | N52: =_xlfn.LET( _xlpm.s,VALUE($I52), _xlpm.e,VALUE($K52), IF(OR(_xlpm.s="",_xlpm.e=""),"", IF(_xlpm.e<=_xlpm.s, IF(TODAY()>=_xlpm.e,1,0), MAX(0,MIN(1,(TODAY()-_xlpm.s)/(_xlpm.e-_xlpm.s))))) ) -> 0

Sheet Revenue Tracking
B2: HIGH LEVEL PROJECT REVENUE TRACKING
D3: COSTED | F3: ACTUAL | L3: FINANCIAL REVIEW | N3: TIMELINE REVIEW | P3: 2025 Actual Revenue | Q3: 2025 Actual COS | R3: 2026 Budget Revenue | S3: 2026 Budget COS | T3: 2026 Actual Revenue | U3: 2026 Actual COS
B4: 1 | C4: Planned Revenue | D4: ='Project Plan'!E6 -> 4662650 | F4: =F22 -> 4662650 | N4: Start Date | P4: =SUMIFS('Expenditure Breakdown'!$U:$U, 'Expenditure Breakdown'!$T:$T, ">"&DATE(2024,8,31), 'Expenditure Breakdown'!$T:$T, "<="&DATE(2025,8,31), 'Expenditure Breakdown'!$S:$S, "<>") -> 4538499.1 | Q4: =SUMIFS('Expenditure Breakdown'!$Q:$Q, 'Expenditure Breakdown'!$T:$T, ">"&DATE(2024,8,31), 'Expenditure Breakdown'!$T:$T, "<="&DATE(2025,8,31), 'Expenditure Breakdown'!$S:$S, "<>") -> 3579234 | R4: =SUMIFS('Expenditure Breakdown'!$U:$U, 'Expenditure Breakdown'!$T:$T, ">"&DATE(2025,8,31), 'Expenditure Breakdown'!$T:$T, "<="&DATE(2026,8,31)) -> 0 | S4: =SUMIFS('Expenditure Breakdown'!$Q:$Q, 'Expenditure Breakdown'!$T:$T, ">"&DATE(2025,8,31), 'Expenditure Breakdown'!$T:$T, "<="&DATE(2026,8,31)) -> 588692.32 | T4: =SUMIFS('Expenditure Breakdown'!$U:$U, 'Expenditure Breakdown'!$T:$T, ">"&DATE(2025,8,31), 'Expenditure Breakdown'!$T:$T, "<="&DATE(2026,8,31), 'Expenditure Breakdown'!$S:$S, "<>") -> 0 | U4: =SUMIFS('Expenditure Breakdown'!$Q:$Q, 'Expenditure Breakdown'!$T:$T, ">"&DATE(2025,8,31), 'Expenditure Breakdown'!$T:$T, "<="&DATE(2026,8,31), 'Expenditure Breakdown'!$S:$S, "<>") -> 473612.32
B5: 2 | C5: Planned Expenditure | D5: =+'Expenditure Tracking'!F5 -> 4250720.1 | F5: =+'Expenditure Tracking'!H5 -> 4169426.3 | G5: VO PM LIMIT | H5: CURRENT VO Total
B6: 3 | C6: Planned Profit | D6: =+D4-D5 -> 411929.85 | F6: =+F4-F5 -> 493223.65 | G6: =D6*0.05 -> 20596.493 | H6: =SUMIF('Expenditure Breakdown'!N:N,"*VO*",'Expenditure Breakdown'!Q:Q) -> 553310 | N6: End Date - PC
B7: 4 | C7: Planned Margin | D7: =+D6/D4 -> 0.088346724 | F7: =+F6/F4 -> 0.10578183
B10: CONTRACT
B12: No. | C12: PAYMENT MILESTONE | E12: % | F12: VALUE | H12: PLANNED PAYMENT DATE | L12: INVOICE NUMBER | N12: INVOICE RAISED DATE | P12: PAYMENT RECEIVED DATE | R12: MILESTONE NOTES & COMMENTS
B13: 1 | C13: Deposit | E13: 0.2 | F13: =$D$4*E13 -> 932530 | H13: 45807 | L13: 004738 | N13: 45778 | P13: 45777
B14: 2 | C14: Delivery of Panels | E14: 0.2 | F14: 827620.87 | H14: ='Project Plan'!E36+7 -> 45813 | L14: 004738 | N14: 45778 | P14: ='Project Plan'!I36+8 -> 45814
F15: =932530-F14 -> 104909.13 | H15: ='Project Plan'!E37+7 -> 45814 | L15: 004738 | N15: 45778 | P15: 45842
B16: 3 | C16: Delivery of Inverters | E16: 0.15 | F16: =$D$4*E16 -> 699397.5 | H16: ='Project Plan'!E22+7 -> 45806 | L16: 004738 | N16: 45778 | P16: ='Project Plan'!I22+8 -> 45807
B17: 4 | C17: Commissioning Complete | E17: 0.15 | F17: =$D$4*E17 -> 699397.5 | H17: ='Project Plan'!G39+7 -> 45866 | L17: 004738 | N17: 45778 | P17: ='Project Plan'!K39+7 -> 46071
B18: 5 | C18: Final Completion Issued | E18: 0.25 | F18: =$D$4*E18 -> 1165662.5 | H18: ='Project Plan'!E50+7 -> 45867 | L18: 004738 | N18: 45778 | P18: ='Project Plan'!I50+7 -> 46072
B19: 6 | C19: Handover | E19: 0.05 | F19: =$D$4*E19 -> 233132.5 | H19: ='Project Plan'!K51+7 -> 46083 | L19: 004738 | N19: 45778 | P19: ='Project Plan'!K51+7 -> 46083
B20: 7 | C20: - | E20: 0 | F20: =$D$4*E20 -> 0
E22: =SUM(E13:E20) -> 1 | F22: =SUM(F13:F20) -> 4662650
B24: KEY: | C24: contains an error (in result or a check has failed)
C25: Red Font - IF TEXT : content not yet confirmed
C26: Red Font - IF NUMBER: Negative value
C27: Anything in yellow is a concern or risk for noting or action
C28: confirmed
C29: [ADD INITIALS: comment for noting in square brackets, use colour or red to draw attention if important]
C30: [RT: When adding rows into sheet, ensure you insert between first and last row of each category]
C31: end of sheet - do not insert information below/beyond this
B41: No. | C41: PAYMENT MILESTONE | E41: % | F41: VALUE
B42: 1 | C42: Deposit - Project commencement | E42: 0.35 | F42: =$F$48*E42 -> 1631927.5
B43: 2 | C43: Delivery of Panels | E43: 0.3 | F43: =$F$48*E43 -> 1398795
B44: 3 | C44: Delivery of Inverters | E44: 0.2 | F44: =$F$48*E44 -> 932530
B45: 4 | C45: Practical Completion | E45: 0.1 | F45: =$F$48*E45 -> 466265
B46: 5 | C46: Handover | E46: 0.05 | F46: =$F$48*E46 -> 233132.5
C47: Total | E47: =SUM(E42:E46) -> 1 | F47: =SUM(F42:F46) -> 4662650
E48: =SUM(E42:E46) -> 1 | F48: =F22 -> 4662650

Sheet Data
C2: Public holidays | F2: Drop down list
C3: 45658 | D3: New Years Day | F3: Approved
C4: 45737 | D4: Human Rights day | F4: Pending
C5: 45765 | D5: Good Friday | F5: Declined
C6: 45768 | D6: Family Day | F6: Abanded
C7: 45774 | D7: Freedom Day
C8: 45765 | D8: Freedom DayObserved
C9: 45778 | D9: Workers day
C10: 45824 | D10: Youth Day Holiday
C11: 45878 | D11: Womens Day
C12: 45924 | D12: Heritage Day
C13: 46007 | D13: Day of Reconciliation | H13: Manual dates
C14: 46008 | D14: Builders Holiday
C15: 46009 | D15: Builders Holiday
C16: 46010 | D16: Builders Holiday
C17: 46011 | D17: Builders Holiday
C18: 46012 | D18: Builders Holiday
C19: 46013 | D19: Builders Holiday
C20: 46014 | D20: Builders Holiday
C21: 46015 | D21: Builders Holiday
C22: 46016 | D22: Builders Holiday
C23: 46017 | D23: Builders Holiday
C24: 46018 | D24: Builders Holiday
C25: 46019 | D25: Builders Holiday
... C45: 46017 | D45: Day of Goodwill

Sheet Expenditure Tracking
B2: HIGH LEVEL PROJECT EXPENDITURE TRACKING
F4: COSTED | H4: ACTUAL | J4: Difference from costed
B5: EXPENDITURE | F5: =SUM(F9:F23) -> 4250720.1 | H5: =SUM(H9:H23) -> 4169426.3 | J5: =SUM(J9:J23) -> 81293.798
B7: No. | D7: Item | F7: Costed Expenditure | H7: Actual Expenditure | J7: Saving / Overrun | L7: Comments on variations from planned expenditure
B9: ='Expenditure Breakdown'!L6 -> 1 | D9: ='Expenditure Breakdown'!M6 -> 1. Panels | F9: ='Expenditure Breakdown'!I6 -> 1020809.8 | H9: ='Expenditure Breakdown'!X6 -> 929051.4 | J9: =F9-H9 -> 91758.43
B10: ='Expenditure Breakdown'!L13 -> 2 | D10: ='Expenditure Breakdown'!M13 -> 2. Inverters | F10: ='Expenditure Breakdown'!I13 -> 320000 | H10: ='Expenditure Breakdown'!X13 -> 275481.4 | J10: =F10-H10 -> 44518.6
B11: ='Expenditure Breakdown'!L21 -> 3 | D11: ='Expenditure Breakdown'!M21 -> 3. Mounting Structures | F11: ='Expenditure Breakdown'!I21 -> 379532.79 | H11: ='Expenditure Breakdown'!X21 -> 154149.2 | J11: =F11-H11 -> 225383.59
B12: ='Expenditure Breakdown'!L28 -> 4 | D12: ='Expenditure Breakdown'!M28 -> 4. DC Equipment | F12: ='Expenditure Breakdown'!I28 -> 363479.3 | H12: ='Expenditure Breakdown'!X28 -> 383972.25 | J12: =F12-H12 -> -20492.952
B13: ='Expenditure Breakdown'!L44 -> 5 | D13: ='Expenditure Breakdown'!M44 -> 5. Monitoring | F13: ='Expenditure Breakdown'!I44 -> 49000 | H13: ='Expenditure Breakdown'!X44 -> 35927.14 | J13: =F13-H13 -> 13072.86
B14: ='Expenditure Breakdown'!L53 -> 6 | D14: ='Expenditure Breakdown'!M53 -> 6. AC Equipment | F14: ='Expenditure Breakdown'!I53 -> 628218.81 | H14: ='Expenditure Breakdown'!X53 -> 280470.48 | J14: =F14-H14 -> 347748.33
B15: ='Expenditure Breakdown'!L71 -> 7 | D15: ='Expenditure Breakdown'!M71 -> 7.BESS | F15: ='Expenditure Breakdown'!I71 -> 0 | H15: ='Expenditure Breakdown'!X71 -> 0 | J15: =F15-H15 -> 0
B16: ='Expenditure Breakdown'!L80 -> 8 | D16: ='Expenditure Breakdown'!M80 -> 8. Product Add On | F16: ='Expenditure Breakdown'!I80 -> 0 | H16: ='Expenditure Breakdown'!X80 -> 629215 | J16: =F16-H16 -> -629215
B17: ='Expenditure Breakdown'!L94 -> 9 | D17: ='Expenditure Breakdown'!M94 -> 9. AC & DC installation | F17: ='Expenditure Breakdown'!I94 -> 368077.5 | H17: ='Expenditure Breakdown'!X94 -> 560350 | J17: =F17-H17 -> -192272.5
B18: ='Expenditure Breakdown'!L107 -> 10 | D18: ='Expenditure Breakdown'!M107 -> 10. Site Logistics | F18: ='Expenditure Breakdown'!I107 -> 99195.133 | H18: ='Expenditure Breakdown'!X107 -> 86215.75 | J18: =F18-H18 -> 12979.383
B19: ='Expenditure Breakdown'!L128 -> 11 | D19: ='Expenditure Breakdown'!M128 -> 11. Due Dilligence | F19: ='Expenditure Breakdown'!I128 -> 115012.25 | H19: ='Expenditure Breakdown'!X128 -> 36674.97 | J19: =F19-H19 -> 78337.28
B20: ='Expenditure Breakdown'!L134 -> 12 | D20: ='Expenditure Breakdown'!M134 -> 12. BDP Commission | F20: ='Expenditure Breakdown'!I134 -> 90423.6 | H20: ='Expenditure Breakdown'!X134 -> 0 | J20: =F20-H20 -> 90423.6
B21: ='Expenditure Breakdown'!L137 -> 13 | D21: ='Expenditure Breakdown'!M138 -> 13. Engineering | F21: ='Expenditure Breakdown'!I137 -> 158920.93 | H21: ='Expenditure Breakdown'!X137 -> 58283.125 | J21: =F21-H21 -> 100637.81
B22: ='Expenditure Breakdown'!L144 -> 14 | D22: ='Expenditure Breakdown'!M144 -> 14. General Expenses | F22: ='Expenditure Breakdown'!I144 -> 8050 | H22: ='Expenditure Breakdown'!X144 -> 40635.63 | J22: =F22-H22 -> -32585.63
B23: ='Expenditure Breakdown'!L157 -> 15 | D23: ='Expenditure Breakdown'!M157 -> 15. Service Add On | F23: ='Expenditure Breakdown'!I157 -> 650000 | H23: ='Expenditure Breakdown'!X157 -> 699000 | J23: =F23-H23 -> -49000
D25: check: | F25: ='Expenditure Breakdown'!I2-'Expenditure Tracking'!F5 -> 0 | G25: =#REF!-G5 -> #REF! | H25: ='Expenditure Breakdown'!X2-H5 -> 0

Sheet Expenditure Breakdown
B2: COSTED EXPENDITURE BREAKDOWN | I2: =SUM(I6:I169) -> 4250720.1 | J2: =SUM(J6:J169) -> 4662649.9 | L2: ACTUAL EXPENDITURE BREAKDOWN | R2: FINANCE ONLY | X2: =SUM(X6:X169) -> 4169426.3
B4: No. | C4: Product / Service | D4: Description of Work | E4: QTY | F4: Rate / Unit | G4: Budget Total | H4: FINANCE PAYMENT DATE | I4: Total COS | J4: =IF(J2-'Revenue Tracking'!D4>=0, "Total Revenue", "ERROR on REV" ) -> ERROR on REV | L4: No. | M4: Product/ Service | N4: Description of Work | O4: QTY | P4: Rate / Unit | Q4: Actual Total | R4: PO NUMBER | S4: INVOICE NUMBER | T4: INVOICE RAISED DATE | U4: REVENUE RECOGNITION AMOUNT | V4: CHECK | W4: FINANCE PAYMENT DATE | X4: Total COS
B6: 1 | C6: Panels | D6: Panels Budget | G6: =D170 -> 1020809.8 | H6: 45867 | I6: =SUM(G6:G11) -> 1020809.8 | J6: =F170 -> 1160011.2 | L6: 1 | M6: 1. Panels | N6: Jinko 620W - MENLO | O6: 753 | P6: =1.99*620 -> 1233.8 | Q6: =O6*P6 -> 929051.4 | R6: PO3901-DIP-PH2-SIBA-20250514 | S6: Menlo INV0002964 | T6: =IF(W6>1,EOMONTH(W6,-2),"") -> 45808 | U6: 1160011.2 | V6: =J6-SUM(U6:U11) -> 0 | W6: 45867 | X6: =SUM(Q6:Q11) -> 929051.4
B7: 1 | D7: Delivery Budget | L7: 1 | M7: 1. Panels | T7: =IF(W7>1,EOMONTH(W7,0),"") | U7: 0
B8: 1 | L8: 1 | M8: 1. Panels | T8: =IF(W8>1,EOMONTH(W8,0),"") | U8: 0
B9: 1 | L9: 1 | M9: 1. Panels | T9: =IF(W9>1,EOMONTH(W9,0),"") | U9: 0
B10: 1 | L10: 1 | M10: 1. Panels | T10: =IF(W10>1,EOMONTH(W10,0),"") | U10: 0
B11: 1 | L11: 1 | M11: 1. Panels | T11: =IF(W11>1,EOMONTH(W11,0),"") | U11: 0 | Y11: BUDGET | Z11: Installer Allocation
T12: =IF(W12>1,EOMONTH(W12,0),"") | Y12: AC Equipment | Z12: =G53 -> 628218.81
B13: 2 | C13: Inverters | D13: Inverter Budget | G13: =D171 -> 320000 | H13: 45855 | I13: =SUM(G13:G19) -> 320000 | J13: =F171 -> 363636.36 | L13: 2 | M13: 2. Inverters | N13: Huawei 100KTL - MENLO | O13: 4 | P13: 68870.35 | Q13: =O13*P13 -> 275481.4 | R13: PO3901-DIP-PH2-SIBA-20250514 | S13: Menlo INV0002927 | T13: =IF(W13>1,EOMONTH(W13,-2),"") -> 45808 | U13: 363636.36 | V13: =J13-SUM(U13:U19) -> 0 | W13: 45855 | X13: =SUM(Q13:Q19) -> 275481.4 | Y13: DC Equipment | Z13: =G29 -> 208317.3
B14: 2 | L14: 2 | M14: 2. Inverters | T14: =IF(W14>1,EOMONTH(W14,0),"") | U14: 0 | Y14: AC Labour | Z14: =G94 -> 116707.5
B15: 2 | L15: 2 | M15: 2. Inverters | T15: =IF(W15>1,EOMONTH(W15,0),"") | U15: 0 | Y15: DC Labour | Z15: =G95 -> 251370
B16: 2 | L16: 2 | M16: 2. Inverters | T16: =IF(W16>1,EOMONTH(W16,0),"") | U16: 0 | Y16: Offloading | Z16: =G107 -> 8500
B17: 2 | L17: 2 | M17: 2. Inverters | T17: =IF(W17>1,EOMONTH(W17,0),"") | U17: 0 | Y17: Scaffolding | Z17: =G108 -> 29821.8
B18: 2 | L18: 2 | M18: 2. Inverters | T18: =IF(W18>1,EOMONTH(W18,0),"") | U18: 0 | Y18: Storage | Z18: =G115 -> 5673.3333
B19: 2 | L19: 2 | M19: 2. Inverters | T19: =IF(W19>1,EOMONTH(W19,0),"") | U19: 0 | Y19: Telehandler | Z19: 0
T20: =IF(W20>1,EOMONTH(W20,0),"")
B21: 3 | C21: Mounting Structures | D21: Structure Budget | G21: =D172 -> 379532.79 | H21: 45835 | I21: =SUM(G21:G26) -> 379532.79 | J21: =F172 -> 431287.26 | L21: 3 | M21: 3. Mounting Structures | N21: Schletter Structure | P21: =Q21*1.15 -> 155161.68 | Q21: 134923.2 | R21: PO3898-DSS-20250514 - RV Approved | S21: Schletter - INV1781 | T21: =IF(W21>1,EOMONTH(W21,-1),"") -> 45808 | U21: 377495.68 | V21: =J21-SUM(U21:U26) -> 0 | W21: 45835 | X21: =SUM(Q21:Q26) -> 154149.2 | Y21: Other | Z21: 0
B22: 3 | H22: 45806 | L22: 3 | M22: 3. Mounting Structures | N22: KlipLok Structure | Q22: 19226 | R22: PO3954-DSS-20250526 - RV Approved | S22: Schletter - INV1800 | T22: 45808 | U22: 53791.579 | W22: 45806 | Y22: Total | Z22: =SUM(Z12:Z21) -> 1248608.7
B23: 3 | L23: 3 | M23: 3. Mounting Structures | U23: 0 | Y23: Less 15% | Z23: =+Z22*0.85 -> 1061317.4
B24: 3 | L24: 3 | M24: 3. Mounting Structures | T24: =IF(W24>1,EOMONTH(W24,0),"") | U24: 0 | Y24: R/Wp | Z24: =Z23/'Project Plan'!$E$3/1000 -> 2.2726283
B25: 3 | L25: 3 | M25: 3. Mounting Structures | T25: =IF(W25>1,EOMONTH(W25,0),"") | U25: 0
B26: 3 | L26: 3 | M26: 3. Mounting Structures | T26: =IF(W26>1,EOMONTH(W26,0),"") | U26: 0 | Y26: ACTUAL - Cosmic Sun | Z26: Installer Price
T27: =IF(W27>1,EOMONTH(W27,0),"") | Y27: =Y12 -> AC Equipment | Z27: 98446.4
B28: 4 | C28: DC Equipment | D28: DC Cable Budget | E28: =G28/14*1.15 -> 12745.45 | G28: 155162 | H28: 45782 | I28: =SUM(G28:G42) -> 363479.3 | J28: =F173 -> 413044.66 | L28: 4 | M28: 4. DC Equipment | N28: DC Cable | O28: 8000 | P28: 13.89 | Q28: =O28*P28 -> 111120 | R28: PO3933-DIP-Ph2-Siba--20250519 - RV Approved | S28: Krannich - INV 15-10012803 | T28: =T13 -> 45808 | U28: 156288.25 | V28: =J28-SUM(U28:U42) -> -0.0026009821 | W28: 45782 | X28: =SUM(Q28:Q42) -> 383972.25 | Y28: =Y13 -> DC Equipment | Z28: 147452.25
B29: 4 | D29: DC Equipment Budget | G29: =D173-G28 -> 208317.3 | H29: 45782 | L29: 4 | M29: 4. DC Equipment | N29: Freight | Q29: 35100 | S29: Krannich - INV 15-10012803 | T29: 45808 | U29: 49367.509 | W29: 45782 | Y29: =Y14 -> AC Labour | Z29: 184110
B30: 4 | H30: 45867 | L30: 4 | M30: 4. DC Equipment | N30: Additional DC Cable - VO | O30: 6000 | P30: 13.89 | Q30: 90300 | R30: PO3997-DSS-20250612 - RV Approved | S30: Krannich - INV 15-10012950 | T30: 45838 | U30: =(Q30/$X$28*$J$28)-60557.81 -> 36579.242 | W30: 45867 | Y30: =Y15 -> DC Labour | Z30: 376240
B31: 4 | L31: 4 | M31: 4. DC Equipment | N31: Freight | T31: =IF(W31>1,EOMONTH(W31,0),"") | U31: 0 | Y31: =Y16 -> Offloading | Z31: 8800
B32: 4 | H32: =H95 -> 45792 | L32: 4 | M32: 4. DC Equipment | N32: Project Kick Off | O32: =Z28 -> 147452.25 | P32: 0.1 | Q32: =$O$32*P32 -> 14745.225 | R32: =R95 -> PO3888-DSS-20250513 - RV Approved | S32: Cosmic Sun: CS_SRS_001 | T32: =IF(W32>1,EOMONTH(W32,0),"") -> 45808 | U32: 20738.89 | W32: =W95 -> 45792 | Y32: =Y17 -> Scaffolding | Z32: 19852.4
B33: 4 | H33: =H96 -> #REF! | L33: 4 | M33: 4. DC Equipment | N33: Site Establishment | P33: 0.15 | Q33: 22117.84 | S33: Cosmic Sun : CS_SRS_002 | T33: =IF(W33>1,EOMONTH(W33,0),"") -> 45808 | U33: 31108.338 | W33: =W96 -> 45806 | Y33: =Y18 -> Storage | Z33: 0
B34: 4 | H34: =H97 -> 45890 | L34: 4 | M34: 4. DC Equipment | N34: AC Installation Complete | P34: 0.2 | Q34: =$O$32*P34 -> 29490.45 | S34: Cosmic Sun: CS_SRS_004 | T34: 45838 | U34: 31723.315 | W34: =W97 -> 45890 | Y34: =Y19 -> Telehandler | Z34: =Z19*0.75 -> 0
B35: 4 | H35: 45834 | L35: 4 | M35: 4. DC Equipment | N35: DC Installation Complete | P35: 0.25 | Q35: =$O$32*P35 -> 36863.062 | S35: Cosmic Sun : CS_SRS_003 | T35: 45838 | U35: 39654.144 | W35: 45834 | Y35: HSE | Z35: 4500
B36: 4 | H36: =H99 -> #REF! | L36: 4 | M36: 4. DC Equipment | N36: Commissioning Complete | P36: 0.1 | Q36: =$O$32*P36 -> 14745.225 | S36: Cosmic Sun : CS_SRS_005 | T36: 45838 | U36: 15861.658 | W36: =W99 -> 46066 | Y36: Other | Z36: 0
B37: 4 | H37: =H100 -> #REF! | L37: 4 | M37: 4. DC Equipment | N37: Site De-establisment | P37: 0.1 | Q37: =$O$32*P37 -> 14745.225 | S37: Cosmic Sun : CS_SRS_006 | T37: 45838 | U37: 15861.658 | W37: =W100 -> 46073 | Y37: Other | Z37: 0
B38: 4 | H38: =H101 -> #REF! | L38: 4 | M38: 4. DC Equipment | N38: Handover Document Complete | P38: 0.05 | Q38: =$O$32*P38 -> 7372.6125 | S38: Cosmic Sun : CS_SRS_007 | T38: 45838 | U38: 7930.8288 | W38: =W101 -> 46081 | Y38: Total | Z38: =SUM(Z27:Z37) -> 839401.05
B39: 4 | H39: =H102 -> 45961 | L39: 4 | M39: 4. DC Equipment | N39: End of Defects Period | P39: 0.05 | Q39: =$O$32*P39 -> 7372.6125 | S39: Cosmic Sun : CS_SRS_008 | T39: 45838 | U39: 7930.8288 | W39: =W102 -> 46111 | Y39: R/Wp | Z39: =Z38/'Project Plan'!$E$3/1000 -> 1.7974327
B40: 4 | L40: 4 | M40: 4. DC Equipment | T40: =IF(W40>1,EOMONTH(W40,0),"") | U40: =(Q40/$X$28*$J$28) -> 0
B41: 4 | L41: 4 | M41: 4. DC Equipment | T41: =IF(W41>1,EOMONTH(W41,0),"") | U41: =(Q41/$X$28*$J$28) -> 0
B42: 4 | L42: 4 | M42: 4. DC Equipment | T42: =IF(W42>1,EOMONTH(W42,0),"") | U42: =(Q42/$X$28*$J$28) -> 0
T43: =IF(W43>1,EOMONTH(W43,0),"")
B44: 5 | C44: Monitoring | D44: Monitoring Budget | G44: =D175-G45 -> 34000 | H44: 45855 | I44: =SUM(G44:G51) -> 49000 | J44: =F175 -> 55681.818 | L44: 5 | M44: 5. Monitoring | N44: Smartlogger - MENLO | Q44: 8598.36 | R44: PO3901-DIP-PH2-SIBA-20250514 | S44: Menlo INV0002927 | T44: =T13 -> 45808 | U44: 12277.104 | V44: =J44-SUM(U44:U51) -> 0.00021546279 | W44: 45855 | X44: =SUM(Q44:Q51) -> 35927.14
B45: 5 | D45: Revenue Metering | G45: 15000 | H45: 45806 | L45: 5 | M45: 5. Monitoring | N45: CTs & Meters | Q45: 13695 | R45: PO3833-DIP-Ph2-Sibasa-20250429 - RV Approved | S45: ACCUENERGY - INV ASAI-005359 | T45: 45777 | U45: 19114.237 | W45: 45806
H46: 45867 | L46: 5 | M46: 5. Monitoring | Q46: 214.28 | S46: Accuenergy - Inv ASAI-005800 | T46: 45838 | U46: 332.10269 | W46: 45867
B47: 5 | H47: 45838 | L47: 5 | M47: 5. Monitoring | N47: Techsitter | Q47: 11169 | S47: Matriarch Inv: 4451 | T47: 45838 | U47: 20789.438 | W47: 45838
B48: 5 | H48: 45799 | L48: 5 | M48: 5. Monitoring | N48: UPS | Q48: 2250.5 | R48: PO3863-DIP Ph2-20250509 - RV Approved | S48: Frontline INV725690 | T48: 45808 | U48: 3168.9352 | W48: 45799
B49: 5 | L49: 5 | M49: 5. Monitoring | T49: =IF(W49>1,EOMONTH(W49,0),"") | U49: =(Q49/$X$44*$J$44) -> 0
B50: 5 | L50: 5 | M50: 5. Monitoring | T50: =IF(W50>1,EOMONTH(W50,0),"") | U50: =(Q50/$X$44*$J$44) -> 0
B51: 5 | L51: 5 | M51: 5. Monitoring | T51: =IF(W51>1,EOMONTH(W51,0),"") | U51: =(Q51/$X$44*$J$44) -> 0
T52: =IF(W52>1,EOMONTH(W52,0),"")
B53: 6 | C53: AC Equipment | D53: AC Equipment Budget | G53: =D174 -> 628218.81 | H53: =H54 -> 45867 | I53: =SUM(G53:G69) -> 628218.81 | J53: =F174 -> 713885.01 | L53: 6 | M53: 6. AC Equipment | T53: =IF(W53>1,EOMONTH(W53,0),"") | U53: =(Q53/$X$53*$J$53) -> 0 | V53: =J53-SUM(U53:U69) -> 0.0022849592 | X53: =SUM(Q53:Q69) -> 280470.48
B54: 6 | H54: 45867 | L54: 6 | M54: 6. AC Equipment | N54: PVDB | Q54: 182024.08 | R54: PO3887-DIP-Ph2-Sibasa-20250513 - RV Approved | S54: Switchboard - Inv 2-SOI002092 | T54: 45838 | U54: 462275 | W54: 45867
B55: 6 | L55: 6 | M55: 6. AC Equipment | T55: =IF(W55>1,EOMONTH(W55,0),"") | U55: =(Q55/$X$53*$J$53) -> 0
B56: 6 | L56: 6 | M56: 6. AC Equipment | T56: =IF(W56>1,EOMONTH(W56,0),"") | U56: =(Q56/$X$53*$J$53) -> 0
B57: 6 | L57: 6 | M57: 6. AC Equipment | T57: =IF(W57>1,EOMONTH(W57,0),"") | U57: =(Q57/$X$53*$J$53) -> 0
B58: 6 | L58: 6 | M58: 6. AC Equipment | T58: =IF(W58>1,EOMONTH(W58,0),"") | U58: =(Q58/$X$53*$J$53) -> 0
B59: 6 | H59: =H95 -> 45792 | L59: 6 | M59: 6. AC Equipment | N59: Project Kick Off | O59: =Z27 -> 98446.4 | P59: 0.1 | Q59: =$O$59*P59 -> 9844.64 | R59: =R95 -> PO3888-DSS-20250513 - RV Approved | S59: Cosmic Sun: CS_SRS_001 | T59: =IF(W59>1,EOMONTH(W59,0),"") -> 45808 | U59: 25470.948 | W59: =W95 -> 45792
B60: 6 | H60: =H96 -> #REF! | L60: 6 | M60: 6. AC Equipment | N60: Site Establishment | P60: 0.15 | Q60: =$O$59*P60 -> 14766.96 | S60: Cosmic Sun : CS_SRS_002 | T60: =IF(W60>1,EOMONTH(W60,0),"") -> 45808 | U60: 38206.422 | W60: =W96 -> 45806
B61: 6 | H61: =H97 -> 45890 | L61: 6 | M61: 6. AC Equipment | N61: AC Installation Complete | P61: 0.2 | Q61: =$O$59*P61 -> 19689.28 | S61: Cosmic Sun: CS_SRS_004 | T61: 45838 | U61: 50115.37 | W61: =W97 -> 45890
B62: 6 | H62: =H98 -> 45834 | L62: 6 | M62: 6. AC Equipment | N62: DC Installation Complete | P62: 0.25 | Q62: =$O$59*P62 -> 24611.6 | S62: Cosmic Sun : CS_SRS_003 | T62: 45838 | U62: 62644.212 | W62: =W98 -> 45834
B63: 6 | H63: =H99 -> #REF! | L63: 6 | M63: 6. AC Equipment | N63: Commissioning Complete | P63: 0.1 | Q63: =$O$59*P63 -> 9844.64 | S63: Cosmic Sun : CS_SRS_005 | T63: 45838 | U63: 25057.685 | W63: =W99 -> 46066
B64: 6 | H64: =H100 -> #REF! | L64: 6 | M64: 6. AC Equipment | N64: Site De-establisment | P64: 0.1 | Q64: =$O$59*P64 -> 9844.64 | S64: Cosmic Sun : CS_SRS_006 | T64: 45838 | U64: 25057.685 | W64: =W100 -> 46073
B65: 6 | H65: =H101 -> #REF! | L65: 6 | M65: 6. AC Equipment | N65: Handover Document Complete | P65: 0.05 | Q65: =$O$59*P65 -> 4922.32 | S65: Cosmic Sun : CS_SRS_007 | T65: 45838 | U65: 12528.842 | W65: =W101 -> 46081
B66: 6 | H66: =H102 -> 45961 | L66: 6 | M66: 6. AC Equipment | N66: End of Defects Period | P66: 0.05 | Q66: =$O$59*P66 -> 4922.32 | S66: Cosmic Sun : CS_SRS_008 | T66: 45838 | U66: 12528.842 | W66: =W102 -> 46111
B67: 6 | L67: 6 | M67: 6. AC Equipment | T67: =IF(W67>1,EOMONTH(W67,0),"") | U67: =(Q67/$X$53*$J$53) -> 0
B68: 6 | L68: 6 | M68: 6. AC Equipment | T68: =IF(W68>1,EOMONTH(W68,0),"") | U68: =(Q68/$X$53*$J$53) -> 0
B69: 6 | L69: 6 | M69: 6. AC Equipment | T69: =IF(W69>1,EOMONTH(W69,0),"") | U69: =(Q69/$X$53*$J$53) -> 0
T70: =IF(W70>1,EOMONTH(W70,0),"")
B71: 7 | C71: BESS | I71: =SUM(G71:G78) -> 0 | J71: 0 | L71: 7 | M71: 7.BESS | T71: =IF(W71>1,EOMONTH(W71,0),"") | V71: =J71-SUM(U71:U78) -> 0 | X71: =SUM(Q71:Q78) -> 0
B72: 7 | L72: 7 | M72: 7.BESS | T72: =IF(W72>1,EOMONTH(W72,0),"")
B73: 7 | L73: 7 | M73: 7.BESS | T73: =IF(W73>1,EOMONTH(W73,0),"")
B74: 7 | L74: 7 | M74: 7.BESS | T74: =IF(W74>1,EOMONTH(W74,0),"")
B75: 7 | L75: 7 | M75: 7.BESS | T75: =IF(W75>1,EOMONTH(W75,0),"")
B76: 7 | L76: 7 | M76: 7.BESS | T76: =IF(W76>1,EOMONTH(W76,0),"")
B77: 7 | L77: 7 | M77: 7.BESS | T77: =IF(W77>1,EOMONTH(W77,0),"")
B78: 7 | L78: 7 | M78: 7.BESS | T78: =IF(W78>1,EOMONTH(W78,0),"")
T79: =IF(W79>1,EOMONTH(W79,0),"")
B80: 8 | C80: Product Add On | I80: =D177 -> 0 | J80: =F177 -> 0 | L80: 8 | M80: 8. Product Add On | T80: =IF(W80>1,EOMONTH(W80,0),"") | V80: =J80-SUM(U80:U92) -> 0 | X80: =SUM(Q80:Q92) -> 629215
B81: 8 | L81: 8 | M81: 8. Product Add On | T81: =IF(W81>1,EOMONTH(W81,0),"")
B82: 8 | H82: 45869 | L82: 8 | M82: 8. Product Add On | N82: Inverter Cage with roof | Q82: 97734 | S82: The Engineering Hub INV/2025/06/0575 | T82: 45838 | W82: 45869
B83: 8 | L83: 8 | M83: 8. Product Add On | N83: E-stop | Q83: 12300 | S83: Cosmic Sun - CS_SRS_010 | T83: 45991 | W83: 45995
B84: 8 | H84: =E84 -> 0 | L84: 8 | M84: 8. Product Add On | N84: Waterpoints | Q84: 24295 | R84: PO4341-DSS-20250929 - RV Approved | S84: Shanduka Projects - QT2365 | T84: 45930 | W84: =T84 -> 45930
B85: 8 | H85: =E85 -> 0 | L85: 8 | M85: 8. Product Add On | N85: CS - Re-establishment Cost - VO | Q85: =9690+5000 -> 14690 | S85: Cosmic Sun - CS_SRS_012 | T85: 46053 | W85: 46065
B86: 8 | H86: =E86 -> 0 | L86: 8 | M86: 8. Product Add On | N86: CS - Waterproofing removing and reinstall panels - Deposit - VO | O86: 448320 | P86: 0.5 | Q86: =$O$86*P86 -> 224160 | R86: PO4376-DSS-20251017 - RV Approved | S86: Cosmic Sun - CS_SRS_009 | T86: 45961 | W86: 45954
L87: 8 | M87: 8. Product Add On | N87: CS - Waterproofing removing and reinstall panels - All material on roof - VO | P87: 0.25 | Q87: =$O$86*P87 -> 112080 | S87: Cosmic Sun -CS_SRS_011 | T87: 46022 | W87: 46003
L88: 8 | M88: 8. Product Add On | N88: CS - Waterproofing removing and reinstall panels - Snag Completion - VO | P88: 0.25 | Q88: =$O$86*P88 -> 112080 | T88: 46081 | W88: 46065
L89: 8 | M89: 8. Product Add On
L90: 8 | M90: 8. Product Add On | N90: Amendment to inverter cage (updated design) | Q90: 31876 | R90: PO4582-DSS-20260127 - RV Approved | S90: Engineering Hub INV/2026/01/0246 | T90: 46053 | W90: 46081
B91: 8 | L91: 8 | M91: 8. Product Add On | T91: =IF(W91>1,EOMONTH(W91,0),"")
B92: 8 | L92: 8 | M92: 8. Product Add On | T92: =IF(W92>1,EOMONTH(W92,0),"")
K93: Only services to be capture below, products above | T93: =IF(W93>1,EOMONTH(W93,0),"")
B94: 9 | C94: AC & DC Installation | D94: AC Installation Budget | G94: =D183 -> 116707.5 | H94: 45791 | I94: =SUM(G94:G105) -> 368077.5 | J94: =F183+F184 -> 433032.35 | L94: 9 | M94: 9. AC & DC installation | T94: =IF(W94>1,EOMONTH(W94,0),"") | U94: =(Q94/$X$94*$J$94) -> 0 | V94: =J94-SUM(U94:U105) -> 0 | X94: =SUM(Q94:Q105) -> 560350
B95: 9 | D95: DC Installation Budget | G95: =D184 -> 251370 | H95: 45792 | L95: 9 | M95: 9. AC & DC installation | N95: Project Kick Off | O95: =Z30+Z29 -> 560350 | P95: 0.1 | Q95: =$O$95*P95 -> 56035 | R95: PO3888-DSS-20250513 - RV Approved | S95: Cosmic Sun: CS_SRS_001 | T95: =IF(W95>1,EOMONTH(W95,0),"") -> 45808 | U95: 43303.235 | W95: 45792
B96: 9 | H96: ='Project Plan'!#REF!+8 -> #REF! | L96: 9 | M96: 9. AC & DC installation | N96: Site Establishment | P96: 0.15 | Q96: =$O$95*P96 -> 84052.5 | S96: Cosmic Sun : CS_SRS_002 | T96: =IF(W96>1,EOMONTH(W96,0),"") -> 45808 | U96: 64954.853 | W96: 45806
B97: 9 | H97: 45890 | L97: 9 | M97: 9. AC & DC installation | N97: AC Installation Complete | P97: 0.2 | Q97: =$O$95*P97 -> 112070 | S97: Cosmic Sun: CS_SRS_004 | T97: 45838 | U97: 86606.471 | W97: 45890
B98: 9 | H98: 45834 | L98: 9 | M98: 9. AC & DC installation | N98: DC Installation Complete | P98: 0.25 | Q98: =$O$95*P98 -> 140087.5 | S98: Cosmic Sun : CS_SRS_003 | T98: 45838 | U98: 108258.09 | W98: 45834
B99: 9 | H99: ='Project Plan'!#REF!+7 -> #REF! | L99: 9 | M99: 9. AC & DC installation | N99: Commissioning Complete | P99: 0.1 | Q99: =$O$95*P99 -> 56035 | S99: Cosmic Sun : CS_SRS_005 | T99: 45838 | U99: 43303.235 | W99: 46066
B100: 9 | H100: ='Project Plan'!#REF!+7 -> #REF! | L100: 9 | M100: 9. AC & DC installation | N100: Site De-establisment | P100: 0.1 | Q100: =$O$95*P100 -> 56035 | S100: Cosmic Sun : CS_SRS_006 | T100: 45838 | U100: 43303.235 | W100: 46073
B101: 9 | H101: ='Project Plan'!#REF!+7 -> #REF! | L101: 9 | M101: 9. AC & DC installation | N101: Handover Document Complete | P101: 0.05 | Q101: =$O$95*P101 -> 28017.5 | S101: Cosmic Sun : CS_SRS_007 | T101: 45838 | U101: 21651.618 | W101: 46081
B102: 9 | H102: 45961 | L102: 9 | M102: 9. AC & DC installation | N102: End of Defects Period | P102: 0.05 | Q102: =$O$95*P102 -> 28017.5 | S102: Cosmic Sun : CS_SRS_008 | T102: 45838 | U102: 21651.618 | W102: 46111
B103: 9 | L103: 9 | M103: 9. AC & DC installation | T103: =IF(W103>1,EOMONTH(W103,0),"") | U103: =(Q103/$X$94*$J$94) -> 0
...

Sheet Cashflow
D1: [RT: Double Check the first date is always a MONDAY] | F1: 45677 | G1: =F1+7 -> 45684 | H1: =G1+7 -> 45691 | I1: =H1+7 -> 45698 | J1: =I1+7 -> 45705 | K1: =J1+7 -> 45712 | L1: =K1+7 -> 45719 | M1: =L1+7 -> 45726 | N1: =M1+7 -> 45733 | ... LD1: =LC1+7 -> 47847
A2: PLANNED | C2: CHECK | D2: CHECK
B3: Planned Revenue | C3: ='Revenue Tracking'!D4 -> 4662650 | D3: =SUM(F3:LD3) -> 4662650 | F3: =SUMIFS('Revenue Tracking'!$F$13:$F$20, 'Revenue Tracking'!$H$13:$H$20, ">="&F1,'Revenue Tracking'!$H$13:$H$20, "<"&G1) -> 0 | G3: =SUMIFS('Revenue Tracking'!$F$13:$F$20, 'Revenue Tracking'!$H$13:$H$20, ">="&G1,'Revenue Tracking'!$H$13:$H$20, "<"&H1) -> 0 | H3: =SUMIFS('Revenue Tracking'!$F$13:$F$20, 'Revenue Tracking'!$H$13:$H$20, ">="&H1,'Revenue Tracking'!$H$13:$H$20, "<"&I1) -> 0 | I3: =SUMIFS('Revenue Tracking'!$F$13:$F$20, 'Revenue Tracking'!$H$13:$H$20, ">="&I1,'Revenue Tracking'!$H$13:$H$20, "<"&J1) -> 0 | J3: =SUMIFS('Revenue Tracking'!$F$13:$F$20, 'Revenue Tracking'!$H$13:$H$20, ">="&J1,'Revenue Tracking'!$H$13:$H$20, "<"&K1) -> 0 | K3: =SUMIFS('Revenue Tracking'!$F$13:$F$20, 'Revenue Tracking'!$H$13:$H$20, ">="&K1,'Revenue Tracking'!$H$13:$H$20, "<"&L1) -> 0 | L3: =SUMIFS('Revenue Tracking'!$F$13:$F$20, 'Revenue Tracking'!$H$13:$H$20, ">="&L1,'Revenue Tracking'!$H$13:$H$20, "<"&M1) -> 0 | M3: =SUMIFS('Revenue Tracking'!$F$13:$F$20, 'Revenue Tracking'!$H$13:$H$20, ">="&M1,'Revenue Tracking'!$H$13:$H$20, "<"&N1) -> 0 | ... LC3: =SUMIFS('Revenue Tracking'!$F$13:$F$20, 'Revenue Tracking'!$H$13:$H$20, ">="&LC1,'Revenue Tracking'!$H$13:$H$20, "<"&LD1) -> 0 | LD3: =SUMIFS('Revenue Tracking'!$F$13:$F$20, 'Revenue Tracking'!$H$13:$H$20, ">="&LD1,'Revenue Tracking'!$H$13:$H$20, "<"&#REF!) -> 0
B4: Planned Revenue - Cumulative | F4: =F3 -> 0 | G4: =F4+G3 -> 0 | H4: =G4+H3 -> 0 | I4: =H4+I3 -> 0 | J4: =I4+J3 -> 0 | K4: =J4+K3 -> 0 | L4: =K4+L3 -> 0 | M4: =L4+M3 -> 0 | N4: =M4+N3 -> 0 | ... LD4: =LC4+LD3 -> 4662650
B5: Planned Expenditure | C5: ='Revenue Tracking'!D5 -> 4250720.1 | D5: =SUM(F5:LD5) -> 4250720.1 | F5: =SUMIFS('Expenditure Breakdown'!$G$6:$G$204, 'Expenditure Breakdown'!$H$6:$H$204, ">="&F1,'Expenditure Breakdown'!$H$6:$H$204, "<"&G1) -> 0 | G5: =SUMIFS('Expenditure Breakdown'!$G$6:$G$204, 'Expenditure Breakdown'!$H$6:$H$204, ">="&G1,'Expenditure Breakdown'!$H$6:$H$204, "<"&H1) -> 0 | H5: =SUMIFS('Expenditure Breakdown'!$G$6:$G$204, 'Expenditure Breakdown'!$H$6:$H$204, ">="&H1,'Expenditure Breakdown'!$H$6:$H$204, "<"&I1) -> 0 | I5: =SUMIFS('Expenditure Breakdown'!$G$6:$G$204, 'Expenditure Breakdown'!$H$6:$H$204, ">="&I1,'Expenditure Breakdown'!$H$6:$H$204, "<"&J1) -> 0 | J5: =SUMIFS('Expenditure Breakdown'!$G$6:$G$204, 'Expenditure Breakdown'!$H$6:$H$204, ">="&J1,'Expenditure Breakdown'!$H$6:$H$204, "<"&K1) -> 0 | K5: =SUMIFS('Expenditure Breakdown'!$G$6:$G$204, 'Expenditure Breakdown'!$H$6:$H$204, ">="&K1,'Expenditure Breakdown'!$H$6:$H$204, "<"&L1) -> 0 | L5: =SUMIFS('Expenditure Breakdown'!$G$6:$G$204, 'Expenditure Breakdown'!$H$6:$H$204, ">="&L1,'Expenditure Breakdown'!$H$6:$H$204, "<"&M1) -> 0 | M5: =SUMIFS('Expenditure Breakdown'!$G$6:$G$204, 'Expenditure Breakdown'!$H$6:$H$204, ">="&M1,'Expenditure Breakdown'!$H$6:$H$204, "<"&N1) -> 0 | ... LC5: =SUMIFS('Expenditure Breakdown'!$G$6:$G$204, 'Expenditure Breakdown'!$H$6:$H$204, ">="&LC1,'Expenditure Breakdown'!$H$6:$H$204, "<"&LD1) -> 0 | LD5: =SUMIFS('Expenditure Breakdown'!$G$6:$G$204, 'Expenditure Breakdown'!$H$6:$H$204, ">="&LD1,'Expenditure Breakdown'!$H$6:$H$204, "<"&#REF!) -> 0
B6: Planned Expenditure - Cumulative | F6: =F5 -> 0 | G6: =F6+G5 -> 0 | H6: =G6+H5 -> 0 | I6: =H6+I5 -> 0 | J6: =I6+J5 -> 0 | K6: =J6+K5 -> 0 | L6: =K6+L5 -> 0 | M6: =L6+M5 -> 0 | N6: =M6+N5 -> 0 | ... LD6: =LC6+LD5 -> 4250720.1
B7: PLANNED CashFlow | F7: =F4-F6 -> 0 | G7: =G4-G6 -> 0 | H7: =H4-H6 -> 0 | I7: =I4-I6 -> 0 | J7: =J4-J6 -> 0 | K7: =K4-K6 -> 0 | L7: =L4-L6 -> 0 | M7: =M4-M6 -> 0 | ... LD7: =LD4-LD6 -> 411929.85
A8: ACTUAL | C8: CHECK | D8: CHECK
B9: Actual + Planned Revenue | C9: ='Revenue Tracking'!F4 -> 4662650 | D9: =SUM(F9:LD9) -> 4662650 | F9: =SUMIFS('Revenue Tracking'!$F$13:$F$20, 'Revenue Tracking'!$P$13:$P$20, ">="&F1,'Revenue Tracking'!$P$13:$P$20, "<"&G1) -> 0 | G9: =SUMIFS('Revenue Tracking'!$F$13:$F$20, 'Revenue Tracking'!$P$13:$P$20, ">="&G1,'Revenue Tracking'!$P$13:$P$20, "<"&H1) -> 0 | H9: =SUMIFS('Revenue Tracking'!$F$13:$F$20, 'Revenue Tracking'!$P$13:$P$20, ">="&H1,'Revenue Tracking'!$P$13:$P$20, "<"&I1) -> 0 | I9: =SUMIFS('Revenue Tracking'!$F$13:$F$20, 'Revenue Tracking'!$P$13:$P$20, ">="&I1,'Revenue Tracking'!$P$13:$P$20, "<"&J1) -> 0 | J9: =SUMIFS('Revenue Tracking'!$F$13:$F$20, 'Revenue Tracking'!$P$13:$P$20, ">="&J1,'Revenue Tracking'!$P$13:$P$20, "<"&K1) -> 0 | K9: =SUMIFS('Revenue Tracking'!$F$13:$F$20, 'Revenue Tracking'!$P$13:$P$20, ">="&K1,'Revenue Tracking'!$P$13:$P$20, "<"&L1) -> 0 | L9: =SUMIFS('Revenue Tracking'!$F$13:$F$20, 'Revenue Tracking'!$P$13:$P$20, ">="&L1,'Revenue Tracking'!$P$13:$P$20, "<"&M1) -> 0 | M9: =SUMIFS('Revenue Tracking'!$F$13:$F$20, 'Revenue Tracking'!$P$13:$P$20, ">="&M1,'Revenue Tracking'!$P$13:$P$20, "<"&N1) -> 0 | ... LC9: =SUMIFS('Revenue Tracking'!$F$13:$F$20, 'Revenue Tracking'!$P$13:$P$20, ">="&LC1,'Revenue Tracking'!$P$13:$P$20, "<"&LD1) -> 0 | LD9: =SUMIFS('Revenue Tracking'!$F$13:$F$20, 'Revenue Tracking'!$P$13:$P$20, ">="&LD1,'Revenue Tracking'!$P$13:$P$20, "<"&#REF!) -> 0
B10: Actual + Planned Revenue - Cumulative | F10: =F9 -> 0 | G10: =F10+G9 -> 0 | H10: =G10+H9 -> 0 | I10: =H10+I9 -> 0 | J10: =I10+J9 -> 0 | K10: =J10+K9 -> 0 | L10: =K10+L9 -> 0 | M10: =L10+M9 -> 0 | N10: =M10+N9 -> 0 | ... LD10: =LC10+LD9 -> 4662650
B11: Actual + Planned Expenditure | C11: ='Revenue Tracking'!F5 -> 4169426.3 | D11: =SUM(F11:LD11) -> 4167926.3 | F11: =SUMIFS('Expenditure Breakdown'!$Q$6:$Q$176, 'Expenditure Breakdown'!$W$6:$W$176, ">="&F1,'Expenditure Breakdown'!$W$6:$W$176, "<"&G1) -> 0 | G11: =SUMIFS('Expenditure Breakdown'!$Q$6:$Q$176, 'Expenditure Breakdown'!$W$6:$W$176, ">="&G1,'Expenditure Breakdown'!$W$6:$W$176, "<"&H1) -> 0 | H11: =SUMIFS('Expenditure Breakdown'!$Q$6:$Q$176, 'Expenditure Breakdown'!$W$6:$W$176, ">="&H1,'Expenditure Breakdown'!$W$6:$W$176, "<"&I1) -> 0 | I11: =SUMIFS('Expenditure Breakdown'!$Q$6:$Q$176, 'Expenditure Breakdown'!$W$6:$W$176, ">="&I1,'Expenditure Breakdown'!$W$6:$W$176, "<"&J1) -> 0 | J11: =SUMIFS('Expenditure Breakdown'!$Q$6:$Q$176, 'Expenditure Breakdown'!$W$6:$W$176, ">="&J1,'Expenditure Breakdown'!$W$6:$W$176, "<"&K1) -> 0 | K11: =SUMIFS('Expenditure Breakdown'!$Q$6:$Q$176, 'Expenditure Breakdown'!$W$6:$W$176, ">="&K1,'Expenditure Breakdown'!$W$6:$W$176, "<"&L1) -> 0 | L11: =SUMIFS('Expenditure Breakdown'!$Q$6:$Q$176, 'Expenditure Breakdown'!$W$6:$W$176, ">="&L1,'Expenditure Breakdown'!$W$6:$W$176, "<"&M1) -> 0 | M11: =SUMIFS('Expenditure Breakdown'!$Q$6:$Q$176, 'Expenditure Breakdown'!$W$6:$W$176, ">="&M1,'Expenditure Breakdown'!$W$6:$W$176, "<"&N1) -> 0 | ... LC11: =SUMIFS('Expenditure Breakdown'!$Q$6:$Q$176, 'Expenditure Breakdown'!$W$6:$W$176, ">="&LC1,'Expenditure Breakdown'!$W$6:$W$176, "<"&LD1) -> 0 | LD11: =SUMIFS('Expenditure Breakdown'!$Q$6:$Q$176, 'Expenditure Breakdown'!$W$6:$W$176, ">="&LD1,'Expenditure Breakdown'!$W$6:$W$176, "<"&#REF!) -> 0
B12: Actual + Planned Expenditure - Cumulative | F12: =F11 -> 0 | G12: =F12+G11 -> 0 | H12: =G12+H11 -> 0 | I12: =H12+I11 -> 0 | J12: =I12+J11 -> 0 | K12: =J12+K11 -> 0 | L12: =K12+L11 -> 0 | M12: =L12+M11 -> 0 | N12: =M12+N11 -> 0 | ... LD12: =LC12+LD11 -> 4167926.3
B14: ACTUAL CashFlow | F14: =F10-F12 -> 0 | G14: =G10-G12 -> 0 | H14: =H10-H12 -> 0 | I14: =I10-I12 -> 0 | J14: =J10-J12 -> 0 | K14: =K10-K12 -> 0 | L14: =L10-L12 -> 0 | M14: =M10-M12 -> 0 | ... LD14: =LD10-LD12 -> 494723.65
C16: CHECK | D16: CHECK
B17: Revenue Recognition | C17: =C3-D17 -> 15368.966 | D17: =SUM(F17:LD17) -> 4647281 | F17: =SUMIFS('Expenditure Breakdown'!$U$6:$U$176, 'Expenditure Breakdown'!$T$6:$T$176, ">="&F1,'Expenditure Breakdown'!$T$6:$T$176, "<"&G1) -> 0 | G17: =SUMIFS('Expenditure Breakdown'!$U$6:$U$176, 'Expenditure Breakdown'!$T$6:$T$176, ">="&G1,'Expenditure Breakdown'!$T$6:$T$176, "<"&H1) -> 0 | H17: =SUMIFS('Expenditure Breakdown'!$U$6:$U$176, 'Expenditure Breakdown'!$T$6:$T$176, ">="&H1,'Expenditure Breakdown'!$T$6:$T$176, "<"&I1) -> 0 | I17: =SUMIFS('Expenditure Breakdown'!$U$6:$U$176, 'Expenditure Breakdown'!$T$6:$T$176, ">="&I1,'Expenditure Breakdown'!$T$6:$T$176, "<"&J1) -> 0 | J17: =SUMIFS('Expenditure Breakdown'!$U$6:$U$176, 'Expenditure Breakdown'!$T$6:$T$176, ">="&J1,'Expenditure Breakdown'!$T$6:$T$176, "<"&K1) -> 0 | K17: =SUMIFS('Expenditure Breakdown'!$U$6:$U$176, 'Expenditure Breakdown'!$T$6:$T$176, ">="&K1,'Expenditure Breakdown'!$T$6:$T$176, "<"&L1) -> 0 | L17: =SUMIFS('Expenditure Breakdown'!$U$6:$U$176, 'Expenditure Breakdown'!$T$6:$T$176, ">="&L1,'Expenditure Breakdown'!$T$6:$T$176, "<"&M1) -> 0 | M17: =SUMIFS('Expenditure Breakdown'!$U$6:$U$176, 'Expenditure Breakdown'!$T$6:$T$176, ">="&M1,'Expenditure Breakdown'!$T$6:$T$176, "<"&N1) -> 0 | ... LC17: =SUMIFS('Expenditure Breakdown'!$U$6:$U$176, 'Expenditure Breakdown'!$T$6:$T$176, ">="&LC1,'Expenditure Breakdown'!$T$6:$T$176, "<"&LD1) -> 0 | LD17: =SUMIFS('Expenditure Breakdown'!$U$6:$U$176, 'Expenditure Breakdown'!$T$6:$T$176, ">="&LD1,'Expenditure Breakdown'!$T$6:$T$176, "<"&#REF!) -> 0
B18: Revenue Recognition Cumulative | C18: =D17-D18 -> 0 | D18: =MAX(F18:LD18) -> 4647281 | F18: =F17 -> 0 | G18: =F18+G17 -> 0 | H18: =G18+H17 -> 0 | I18: =H18+I17 -> 0 | J18: =I18+J17 -> 0 | K18: =J18+K17 -> 0 | L18: =K18+L17 -> 0 | M18: =L18+M17 -> 0 | N18: =M18+N17 -> 0 | ... LD18: =LC18+LD17 -> 4647281

Sheet Finance - Revenue
A3: Sum of REVENUE RECOGNITION AMOUNT | B3: Column Labels
A4: Row Labels | B4: (blank) | C4: 45777 | D4: 45808 | E4: 45838 | F4: 45869 | G4: 45900 | H4: 45930 | I4: 45961 | J4: 45991 | K4: 46022 | M4: 46053 | N4: 46081 | O4: Grand Total
A5: (blank)
A6: 1. Panels | D6: 1160011.2 | L6: 0 | O6: 1160011.2
A7: 2. Inverters | D7: 363636.36 | L7: 0 | O7: 363636.36
A8: 3. Mounting Structures | B8: 0 | D8: 431287.26 | L8: 0 | O8: 431287.26
A9: 4. DC Equipment | D9: 257502.99 | E9: 155541.67 | L9: 0 | O9: 413044.66
A10: 5. Monitoring | C10: 19114.237 | D10: 15446.04 | E10: 21121.541 | L10: 0 | O10: 55681.818
A11: 6. AC Equipment | D11: 63677.37 | E11: 650207.64 | L11: 0 | O11: 713885.01
A12: 8. Product Add On
A13: 9. AC & DC installation | D13: 108258.09 | E13: 324774.26 | L13: 0 | O13: 433032.35
A14: 10. Site Logistics | D14: 17396.603 | E14: 41905.039 | G14: 57398.52 | L14: 0 | O14: 116700.16
A15: 11. Due Dilligence | C15: 45725.471 | E15: 33638.623 | F15: 55944.435 | L15: 0 | O15: 135308.53
A16: 13. Engineering | F16: 180591.97 | L16: 0 | O16: 180591.97
A17: 14. General Expenses | C17: 5699.53 | D17: 2681.3708 | E17: 598.82222 | F17: 0 | G17: 490.86342 | H17: 0 | I17: 0 | J17: 0 | L17: 0 | M17: 0 | N17: 0 | O17: 9470.5865
A18: 15. Service Add On | E18: 583247.75 | G18: 66752.249 | L18: 0 | O18: 650000
A19: 12. BDP Commission
A20: 7.BESS
A21: Grand Total | B21: 0 | C21: 70539.238 | D21: 2419897.3 | E21: 1811035.4 | F21: 236536.4 | G21: 124641.63 | H21: 0 | I21: 0 | J21: 0 | L21: 0 | M21: 0 | N21: 0 | O21: 4662649.9
G23: 4662650
G24: =SUM(B21:G21) -> 4662649.9
P26: ='Revenue Tracking'!F4 -> 4662650
P27: =O21-P26 -> -0.1164757

Sheet Finance - COS
A3: Sum of Actual Total | B3: Column Labels
A4: Row Labels | B4: (blank) | C4: 45777 | D4: 45808 | E4: 45838 | F4: 45869 | G4: 45900 | H4: 45930 | I4: 45961 | J4: 45991 | K4: 46022 | M4: 46053 | N4: 46081 | O4: Grand Total
A5: (blank)
A6: 1. Panels | D6: 929051.4 | O6: 929051.4
A7: 2. Inverters | D7: 275481.4 | O7: 275481.4
A8: 3. Mounting Structures | D8: 154149.2 | O8: 154149.2
A9: 4. DC Equipment | D9: 183083.07 | E9: 200889.19 | O9: 383972.25
A10: 5. Monitoring | C10: 13695 | D10: 10848.86 | E10: 11383.28 | O10: 35927.14
A11: 6. AC Equipment | D11: 24611.6 | E11: 255858.88 | O11: 280470.48
A12: 8. Product Add On | E12: 97734 | H12: 24295 | I12: 224160 | J12: 12300 | K12: 112080 | M12: 14690 | N12: 112080 | O12: 597339
A13: 9. AC & DC installation | D13: 140087.5 | E13: 420262.5 | O13: 560350
A14: 10. Site Logistics | D14: 11113.1 | E14: 26769.3 | J14: 29000 | K14: 19333.35 | M14: 19333.35 | N14: 19333.35 | O14: 124882.45
A15: 11. Due Dilligence | C15: 9019.6 | E15: 8830.8 | F15: 18824.57 | O15: 36674.97
A16: 13. Engineering | F16: 58283.125 | O16: 58283.125
A17: 14. General Expenses | C17: 10950 | D17: 7624.05 | E17: 10878.61 | F17: 0 | G17: 805 | H17: 0 | I17: 1247.83 | J17: 4630.14 | M17: 1500 | N17: 3000 | O17: 40635.63
A18: 15. Service Add On | E18: 699000 | G18: 0 | O18: 699000
A19: 12. BDP Commission
A20: 7.BESS
A21: Grand Total | C21: 33664.6 | D21: 1736050.2 | E21: 1731606.6 | F21: 77107.695 | G21: 805 | H21: 24295 | I21: 225407.83 | J21: 45930.14 | K21: 131413.35 | M21: 35523.35 | N21: 134413.35 | O21: 4176217

Sheet Project Margins
A1: [capture project margins from costing sheet]
A3: Products | D3: 0.32
A4: Services | D4: 0.5
A5: Expenses | D5: 0.15
A6: Subcontractors | D6: 0.2

Sheet Equipment Quotes
B2: Equipment Quote and Budget comparision
B4: Description | D4: Budget | F4: Supplier 1 | H4: Variance | J4: Supplier 2 | L4: Variance | N4: Comments / Notes
F7: >Name< | J7: >Name<
B9: Inverters | D9: =SUM(D10:D11) -> #REF! | F9: =SUM(F10:F13) -> 0 | H9: =$D$9-F9 -> #REF! | J9: =SUM(J10:J13) -> 0 | L9: =$D$9-J9 -> #REF!
B10: Inverters | D10: =#REF! -> #REF!
B11: Optimizers | D11: =#REF! -> #REF!
B12: Warranty
B13: Delivery fee
F15: >Name< | J15: >Name<
B17: Mounting Structure | D17: =SUM(D18:D19) -> #REF! | F17: =SUM(F18:F20) -> 0 | H17: =$D$17- F17 -> #REF! | J17: =SUM(J18:J20) -> 0 | L17: =$D$17- J17 -> #REF!
B18: Mounting Structure | D18: =#REF! -> #REF!
B19: Delivery fee
F21: >Name< | J21: >Name<
B23: DC Cable | D23: =SUM(D24:D25) -> #REF! | F23: =SUM(F24:F25) -> 0 | H23: =$D$23- F23 -> #REF! | J23: =SUM(J24:J25) -> 0 | L23: =$D$23- J23 -> #REF!
B24: DC Cable | D24: =#REF! -> #REF!
B25: Delivery fee
F27: >Name< | J27: >Name<
B29: Monitoring system | D29: =SUM(D30:D32) -> #REF! | F29: =SUM(F30:F42) -> 0 | H29: =$D$29-F29 -> #REF! | J29: =SUM(J30:J32) -> 0 | L29: =$D$29-J29 -> #REF!
B30: =#REF! -> #REF! | D30: =#REF! -> #REF!
B31: =#REF! -> #REF! | D31: =#REF! -> #REF!
B32: Delivery fee
F34: >Name< | J34: >Name<
B36: Additional Scope | D36: =SUM(D37:D41) -> #REF! | F36: =SUM(F37:F41) -> 0 | H36: =$D$29-F36 -> #REF! | J36: =SUM(J37:J41) -> 0 | L36: =$D$29-J36 -> #REF!
B37: SCADA | D37: =#REF! -> #REF!
B38: Inverter cage
B39: Cat ladders
B40: Gen Integration
B41: Lifelines
B43: Totals | D43: =D36+D29+D23+D17+D9 -> #REF! | H43: =SUM(H7:H42) -> #REF! | L43: =SUM(L7:L42) -> #REF!
B47: All amounts are incl VAT

Sheet Installer Quotes
B2: Installer Quote and Budget comparision
B4: Description | D4: Budget | G4: Cosmic Sun | J4: Variance | L4: Matthews Group | O4: Variance
B6: AC Equipment | D6: =#REF! -> #REF! | E6: =D6/(1000*'Project Plan'!$E$3) -> #REF! | G6: 277892.91 | H6: =G6/('Project Plan'!$E$3*1000) -> 0.59505976 | J6: =D6-G6 -> #REF! | M6: =L6/('Project Plan'!$E$3*1000) -> 0 | O6: =D6-L6 -> #REF!
B7: DC Equipment | D7: =#REF! -> #REF! | E7: =D7/(1000*'Project Plan'!$E$3) -> #REF! | G7: 142158.25 | H7: =G7/('Project Plan'!$E$3*1000) -> 0.30440739 | J7: =D7-G7 -> #REF! | M7: =L7/('Project Plan'!$E$3*1000) -> 0 | O7: =D7-L7 -> #REF!
B8: AC Labour | D8: =#REF! -> #REF! | E8: =D8/(1000*'Project Plan'!$E$3) -> #REF! | G8: 96174 | H8: =G8/('Project Plan'!$E$3*1000) -> 0.20594004 | J8: =D8-G8 -> #REF! | M8: =L8/('Project Plan'!$E$3*1000) -> 0 | O8: =D8-L8 -> #REF!
B9: DC Labour | D9: =#REF! -> #REF! | E9: =D9/(1000*'Project Plan'!$E$3) -> #REF! | G9: 230160 | H9: =G9/('Project Plan'!$E$3*1000) -> 0.49284797 | J9: =D9-G9 -> #REF! | M9: =L9/('Project Plan'!$E$3*1000) -> 0 | O9: =D9-L9 -> #REF!
B10: Offloading | D10: =#REF! -> #REF! | G10: 0 | J10: =D10-G10 -> #REF! | O10: =D10-L10 -> #REF!
B11: Roof Access/Scaffolding | D11: =#REF! -> #REF! | G11: 29257.61 | J11: =D11-G11 -> #REF! | O11: =D11-L11 -> #REF!
B12: Storage | D12: =#REF! -> #REF! | J12: =D12-G12 -> #REF! | O12: =D12-L12 -> #REF!
B13: Telehandler | D13: =#REF! -> #REF!
B14: HSE | D14: 0
B15: Totals | D15: =SUM(D6:D13) -> #REF! | G15: =SUM(G6:G13) -> 775642.77 | J15: =SUM(J6:J14) -> #REF! | L15: =SUM(L6:L13) -> 0 | O15: =SUM(O6:O14) -> #REF!
B18: Description | D18: Budget | G18: >Installer Name 3< | J18: Variance | L18: >Installer Name 4< | O18: Variance
B20: AC installation | D20: =#REF! -> #REF! | E20: =D20/(1000*'Project Plan'!$E$3) -> #REF! | H20: =G20/(1000*'Project Plan'!$E$3) -> 0 | J20: =D20-G20 -> #REF! | M20: =L20/(1000*'Project Plan'!$E$3) -> 0 | O20: =D6-L20 -> #REF!
B21: AC equipment | D21: =#REF! -> #REF! | E21: =D21/(1000*'Project Plan'!$E$3) -> #REF! | J21: =D21-G21 -> #REF! | M21: =L21/(1000*'Project Plan'!$E$3) -> 0 | O21: =D7-L21 -> #REF!
B22: DC installation | D22: =#REF! -> #REF! | E22: =D22/(1000*'Project Plan'!$E$3) -> #REF! | H22: =G22/(1000*'Project Plan'!$E$3) -> 0 | J22: =D22-G22 -> #REF! | M22: =L22/(1000*'Project Plan'!$E$3) -> 0 | O22: =D8-L22 -> #REF!
B23: DC equipment | D23: =SUM(#REF!) -> #REF! | E23: =D23/(1000*'Project Plan'!$E$3) -> #REF! | J23: =D23-G23 -> #REF! | O23: =D9-L23 -> #REF!
B24: Storage | D24: =#REF! -> #REF! | J24: =D24-G24 -> #REF! | O24: =D10-L24 -> #REF!
B25: Panel lifting equipment | D25: =SUM(#REF!) -> #REF! | J25: =D25-G25 -> #REF! | O25: =D11-L25 -> #REF!
B26: Offloading | D26: =#REF! -> #REF! | J26: =D26-G26 -> #REF! | O26: =D12-L26 -> #REF!
B29: Totals | D29: =SUM(D20:D27) -> #REF! | G29: =SUM(G20:G27) -> 0 | J29: =SUM(J20:J28) -> #REF! | L29: =SUM(L20:L27) -> 0 | O29: =SUM(O20:O28) -> #REF!
B32: Budget Summary
B34: Budget | D34: =D15 -> #REF!
B35: =G4 -> Cosmic Sun | D35: =G15 -> 775642.77
B36: =L4 -> Matthews Group | D36: =L15 -> 0
B37: =G18 -> >Installer Name 3< | D37: =G29 -> 0
B38: =L18 -> >Installer Name 4< | D38: =L29 -> 0
B40: =IF(D40<D34,"Saving","Loss") -> #REF! | D40: =D34-MIN(D35:D38) -> #REF!
B42: All amounts are exc VAT

Sheet Decision Register
B1: =D15 -> Sibasa | E1: Decision Register
B3: ID | C3: Decision Description | D3: Decision Impact | E3: Proposed Date | F3: Proposed By | G3: Status | H3: Approved By | I3: Date | J3: Results / Comments
B4: DEC001
B5: DEC002
B6: DEC003
B7: DEC004
B8: DEC005
B9: DEC006
B10: DEC007
B11: DEC008
B12: DEC009
B13: DEC010
D15: {='Project Plan'!E2:H2} -> Sibasa | E15: 0 | F15: 0 | G15: 0
