Workbook
Name Inverter_Capacity: #REF!
Name Inverter_Supplier: #REF!
Name Project_Size: 'Certificate - Financial Close'!Projectsize
Name Project_Size: Compliance!Projectsize
Name Project_Size: 'Finance - Revenue'!Projectsize
Name Project_Size: Projectsize
Name Projectsize: #REF!
Name Projectsize: #REF!
Name Projectsize: #REF!
Name Projectsize: 'Project Margins'!$K$5
Name Security_Serv: #REF!
Name Security_Serv: #REF!
Name SSS: #REF!
Name SSS: #REF!
Name USD_ZAR: #REF!

Sheet Sheet1
A1: PROJECT PLAN
A2: # | B2: Project Milestone | C2: Planned Start Date | D2: Duration (Work Days) | E2: Planned End Date | F2: Actual Start Date | H2: Actual End Date | J2: Comments | L2: =C3 -> 43831 | M2: =L2+3 -> 43834 | N2: =M2+7 -> 43841 | O2: =N2+7 -> 43848 | P2: =O2+7 -> 43855 | Q2: =P2+6 -> 43861 | R2: =Q2+1 -> 43862 | S2: =R2+7 -> 43869 | T2: =S2+7 -> 43876 | U2: =T2+7 -> 43883 | V2: =U2+6 -> 43889 | W2: =V2+7 -> 43896 | X2: =W2+7 -> 43903 | Y2: =X2+7 -> 43910 | Z2: =Y2+7 -> 43917 | AA2: =Z2+3 -> 43920 | AB2: =AA2+4 -> 43924 | AC2: =AB2+7 -> 43931 | AD2: =AC2+7 -> 43938 | AE2: =AD2+7 -> 43945 | AF2: =AE2+6 -> 43951 | AG2: =AF2+2 -> 43953 | AH2: =AG2+7 -> 43960 | AI2: =AH2+7 -> 43967 | AJ2: =AI2+7 -> 43974 | AK2: =AJ2+7 -> 43981 | AL2: =AK2+1 -> 43982 | AM2: =AL2+6 -> 43988 | AN2: =AM2+7 -> 43995 | AO2: =AN2+7 -> 44002 | AP2: =AO2+7 -> 44009 | AQ2: =AP2+3 -> 44012 | AR2: =AQ2+4 -> 44016 | AS2: =AR2+7 -> 44023 | AT2: =AS2+7 -> 44030 | AU2: =AT2+7 -> 44037 | AV2: =AU2+6 -> 44043 | AW2: =AV2+1 -> 44044 | AX2: =AW2+7 -> 44051 | AY2: =AX2+7 -> 44058 | AZ2: =AY2+7 -> 44065 | BA2: =AZ2+7 -> 44072 | BB2: =BA2+2 -> 44074 | BC2: =BB2+5 -> 44079 | BD2: =BC2+7 -> 44086 | BE2: =BD2+7 -> 44093 | BF2: =BE2+7 -> 44100 | BG2: =BF2+4 -> 44104
A3: 1 | B3: Contract Signature | C3: 43831 | D3: 1 | E3: 43832 | F3: 43831 | G3: 1 | H3: 43832 | L3: =IF(AND($F3<(L$2+7),$F3>L$2),1, IF(AND($H3<L$2+7,$H3>L$2),3, IF(AND($F3<=L$2, $H3>=L$2), 2, "" ))) -> 3 | M3: =IF(AND($F3<(M$2+7),$F3>M$2),1, IF(AND($H3<M$2+7,$H3>M$2),3, IF(AND($F3<=M$2, $H3>=M$2), 2, "" ))) | N3: =IF(AND($F3<(N$2+7),$F3>N$2),1, IF(AND($H3<N$2+7,$H3>N$2),3, IF(AND($F3<=N$2, $H3>=N$2), 2, "" ))) | O3: =IF(AND($F3<(O$2+7),$F3>O$2),1, IF(AND($H3<O$2+7,$H3>O$2),3, IF(AND($F3<=O$2, $H3>=O$2), 2, "" ))) | P3: =IF(AND($F3<(P$2+7),$F3>P$2),1, IF(AND($H3<P$2+7,$H3>P$2),3, IF(AND($F3<=P$2, $H3>=P$2), 2, "" ))) | Q3: =IF(AND($F3<(Q$2+7),$F3>Q$2),1, IF(AND($H3<Q$2+7,$H3>Q$2),3, IF(AND($F3<=Q$2, $H3>=Q$2), 2, "" ))) | R3: =IF(AND($F3<(R$2+7),$F3>R$2),1, IF(AND($H3<R$2+7,$H3>R$2),3, IF(AND($F3<=R$2, $H3>=R$2), 2, "" ))) | S3: =IF(AND($F3<(S$2+7),$F3>S$2),1, IF(AND($H3<S$2+7,$H3>S$2),3, IF(AND($F3<=S$2, $H3>=S$2), 2, "" ))) | ... AQ3: =IF(AND($F3<(AQ$2+7),$F3>AQ$2),1, IF(AND($H3<AQ$2+7,$H3>AQ$2),3, IF(AND($F3<=AQ$2, $H3>=AQ$2), 2, "" )))
A4: A | B4: PAYMENT MILESTONE 1: DEPOSIT | C4: 43832 | D4: 1 | E4: 43833 | F4: 43832 | G4: 1 | H4: 43833 | L4: =IF(AND($F4<(L$2+7),$F4>L$2),1, IF(AND($H4<L$2+7,$H4>L$2),3, IF(AND($F4<=L$2, $H4>=L$2), 2, "" ))) -> 1 | M4: =IF(AND($F4<(M$2+7),$F4>M$2),1, IF(AND($H4<M$2+7,$H4>M$2),3, IF(AND($F4<=M$2, $H4>=M$2), 2, "" ))) | N4: =IF(AND($F4<(N$2+7),$F4>N$2),1, IF(AND($H4<N$2+7,$H4>N$2),3, IF(AND($F4<=N$2, $H4>=N$2), 2, "" ))) | O4: =IF(AND($F4<(O$2+7),$F4>O$2),1, IF(AND($H4<O$2+7,$H4>O$2),3, IF(AND($F4<=O$2, $H4>=O$2), 2, "" ))) | P4: =IF(AND($F4<(P$2+7),$F4>P$2),1, IF(AND($H4<P$2+7,$H4>P$2),3, IF(AND($F4<=P$2, $H4>=P$2), 2, "" ))) | Q4: =IF(AND($F4<(Q$2+7),$F4>Q$2),1, IF(AND($H4<Q$2+7,$H4>Q$2),3, IF(AND($F4<=Q$2, $H4>=Q$2), 2, "" ))) | R4: =IF(AND($F4<(R$2+7),$F4>R$2),1, IF(AND($H4<R$2+7,$H4>R$2),3, IF(AND($F4<=R$2, $H4>=R$2), 2, "" ))) | S4: =IF(AND($F4<(S$2+7),$F4>S$2),1, IF(AND($H4<S$2+7,$H4>S$2),3, IF(AND($F4<=S$2, $H4>=S$2), 2, "" ))) | ... AQ4: =IF(AND($F4<(AQ$2+7),$F4>AQ$2),1, IF(AND($H4<AQ$2+7,$H4>AQ$2),3, IF(AND($F4<=AQ$2, $H4>=AQ$2), 2, "" )))
A5: 2 | B5: Structural and Electrical Due Diligences | C5: 43833 | D5: 5 | E5: 43840 | F5: 43833 | G5: 5 | H5: 43840 | L5: =IF(AND($F5<(L$2+7),$F5>L$2),1, IF(AND($H5<L$2+7,$H5>L$2),3, IF(AND($F5<=L$2, $H5>=L$2), 2, "" ))) -> 1 | M5: =IF(AND($F5<(M$2+7),$F5>M$2),1, IF(AND($H5<M$2+7,$H5>M$2),3, IF(AND($F5<=M$2, $H5>=M$2), 2, "" ))) -> 3 | N5: =IF(AND($F5<(N$2+7),$F5>N$2),1, IF(AND($H5<N$2+7,$H5>N$2),3, IF(AND($F5<=N$2, $H5>=N$2), 2, "" ))) | O5: =IF(AND($F5<(O$2+7),$F5>O$2),1, IF(AND($H5<O$2+7,$H5>O$2),3, IF(AND($F5<=O$2, $H5>=O$2), 2, "" ))) | P5: =IF(AND($F5<(P$2+7),$F5>P$2),1, IF(AND($H5<P$2+7,$H5>P$2),3, IF(AND($F5<=P$2, $H5>=P$2), 2, "" ))) | Q5: =IF(AND($F5<(Q$2+7),$F5>Q$2),1, IF(AND($H5<Q$2+7,$H5>Q$2),3, IF(AND($F5<=Q$2, $H5>=Q$2), 2, "" ))) | R5: =IF(AND($F5<(R$2+7),$F5>R$2),1, IF(AND($H5<R$2+7,$H5>R$2),3, IF(AND($F5<=R$2, $H5>=R$2), 2, "" ))) | S5: =IF(AND($F5<(S$2+7),$F5>S$2),1, IF(AND($H5<S$2+7,$H5>S$2),3, IF(AND($F5<=S$2, $H5>=S$2), 2, "" ))) | ... AQ5: =IF(AND($F5<(AQ$2+7),$F5>AQ$2),1, IF(AND($H5<AQ$2+7,$H5>AQ$2),3, IF(AND($F5<=AQ$2, $H5>=AQ$2), 2, "" )))
A6: 3 | B6: Design Confirmation | C6: 43841 | D6: 2 | E6: 43844 | F6: 43841 | G6: 2 | H6: 43844 | L6: =IF(AND($F6<(L$2+7),$F6>L$2),1, IF(AND($H6<L$2+7,$H6>L$2),3, IF(AND($F6<=L$2, $H6>=L$2), 2, "" ))) | M6: =IF(AND($F6<(M$2+7),$F6>M$2),1, IF(AND($H6<M$2+7,$H6>M$2),3, IF(AND($F6<=M$2, $H6>=M$2), 2, "" ))) | N6: =IF(AND($F6<(N$2+7),$F6>N$2),1, IF(AND($H6<N$2+7,$H6>N$2),3, IF(AND($F6<=N$2, $H6>=N$2), 2, "" ))) -> 3 | O6: =IF(AND($F6<(O$2+7),$F6>O$2),1, IF(AND($H6<O$2+7,$H6>O$2),3, IF(AND($F6<=O$2, $H6>=O$2), 2, "" ))) | P6: =IF(AND($F6<(P$2+7),$F6>P$2),1, IF(AND($H6<P$2+7,$H6>P$2),3, IF(AND($F6<=P$2, $H6>=P$2), 2, "" ))) | Q6: =IF(AND($F6<(Q$2+7),$F6>Q$2),1, IF(AND($H6<Q$2+7,$H6>Q$2),3, IF(AND($F6<=Q$2, $H6>=Q$2), 2, "" ))) | R6: =IF(AND($F6<(R$2+7),$F6>R$2),1, IF(AND($H6<R$2+7,$H6>R$2),3, IF(AND($F6<=R$2, $H6>=R$2), 2, "" ))) | S6: =IF(AND($F6<(S$2+7),$F6>S$2),1, IF(AND($H6<S$2+7,$H6>S$2),3, IF(AND($F6<=S$2, $H6>=S$2), 2, "" ))) | ... AQ6: =IF(AND($F6<(AQ$2+7),$F6>AQ$2),1, IF(AND($H6<AQ$2+7,$H6>AQ$2),3, IF(AND($F6<=AQ$2, $H6>=AQ$2), 2, "" )))
A7: 4 | B7: Equipment Procurement | C7: 43833 | E7: 43949 | F7: 43833 | H7: 43949 | L7: =IF(AND($F7<(L$2+7),$F7>L$2),1, IF(AND($H7<L$2+7,$H7>L$2),3, IF(AND($F7<=L$2, $H7>=L$2), 2, "" ))) -> 1 | M7: =IF(AND($F7<(M$2+7),$F7>M$2),1, IF(AND($H7<M$2+7,$H7>M$2),3, IF(AND($F7<=M$2, $H7>=M$2), 2, "" ))) -> 2 | N7: =IF(AND($F7<(N$2+7),$F7>N$2),1, IF(AND($H7<N$2+7,$H7>N$2),3, IF(AND($F7<=N$2, $H7>=N$2), 2, "" ))) -> 2 | O7: =IF(AND($F7<(O$2+7),$F7>O$2),1, IF(AND($H7<O$2+7,$H7>O$2),3, IF(AND($F7<=O$2, $H7>=O$2), 2, "" ))) -> 2 | P7: =IF(AND($F7<(P$2+7),$F7>P$2),1, IF(AND($H7<P$2+7,$H7>P$2),3, IF(AND($F7<=P$2, $H7>=P$2), 2, "" ))) -> 2 | Q7: =IF(AND($F7<(Q$2+7),$F7>Q$2),1, IF(AND($H7<Q$2+7,$H7>Q$2),3, IF(AND($F7<=Q$2, $H7>=Q$2), 2, "" ))) -> 2 | R7: =IF(AND($F7<(R$2+7),$F7>R$2),1, IF(AND($H7<R$2+7,$H7>R$2),3, IF(AND($F7<=R$2, $H7>=R$2), 2, "" ))) -> 2 | S7: =IF(AND($F7<(S$2+7),$F7>S$2),1, IF(AND($H7<S$2+7,$H7>S$2),3, IF(AND($F7<=S$2, $H7>=S$2), 2, "" ))) -> 2 | ... AQ7: =IF(AND($F7<(AQ$2+7),$F7>AQ$2),1, IF(AND($H7<AQ$2+7,$H7>AQ$2),3, IF(AND($F7<=AQ$2, $H7>=AQ$2), 2, "" )))
B8: Panel Procurement | C8: 43833 | D8: 5 | E8: 43840 | F8: 43833 | G8: 5 | H8: 43840 | L8: =IF(AND($F8<(L$2+7),$F8>L$2),1, IF(AND($H8<L$2+7,$H8>L$2),3, IF(AND($F8<=L$2, $H8>=L$2), 2, "" ))) -> 1 | M8: =IF(AND($F8<(M$2+7),$F8>M$2),1, IF(AND($H8<M$2+7,$H8>M$2),3, IF(AND($F8<=M$2, $H8>=M$2), 2, "" ))) -> 3 | N8: =IF(AND($F8<(N$2+7),$F8>N$2),1, IF(AND($H8<N$2+7,$H8>N$2),3, IF(AND($F8<=N$2, $H8>=N$2), 2, "" ))) | O8: =IF(AND($F8<(O$2+7),$F8>O$2),1, IF(AND($H8<O$2+7,$H8>O$2),3, IF(AND($F8<=O$2, $H8>=O$2), 2, "" ))) | P8: =IF(AND($F8<(P$2+7),$F8>P$2),1, IF(AND($H8<P$2+7,$H8>P$2),3, IF(AND($F8<=P$2, $H8>=P$2), 2, "" ))) | Q8: =IF(AND($F8<(Q$2+7),$F8>Q$2),1, IF(AND($H8<Q$2+7,$H8>Q$2),3, IF(AND($F8<=Q$2, $H8>=Q$2), 2, "" ))) | R8: =IF(AND($F8<(R$2+7),$F8>R$2),1, IF(AND($H8<R$2+7,$H8>R$2),3, IF(AND($F8<=R$2, $H8>=R$2), 2, "" ))) | S8: =IF(AND($F8<(S$2+7),$F8>S$2),1, IF(AND($H8<S$2+7,$H8>S$2),3, IF(AND($F8<=S$2, $H8>=S$2), 2, "" ))) | ... AQ8: =IF(AND($F8<(AQ$2+7),$F8>AQ$2),1, IF(AND($H8<AQ$2+7,$H8>AQ$2),3, IF(AND($F8<=AQ$2, $H8>=AQ$2), 2, "" )))
B9: Inverter Procurement | C9: 43941 | D9: 5 | E9: 43949 | F9: 43941 | G9: 5 | H9: 43949 | L9: =IF(AND($F9<(L$2+7),$F9>L$2),1, IF(AND($H9<L$2+7,$H9>L$2),3, IF(AND($F9<=L$2, $H9>=L$2), 2, "" ))) | M9: =IF(AND($F9<(M$2+7),$F9>M$2),1, IF(AND($H9<M$2+7,$H9>M$2),3, IF(AND($F9<=M$2, $H9>=M$2), 2, "" ))) | N9: =IF(AND($F9<(N$2+7),$F9>N$2),1, IF(AND($H9<N$2+7,$H9>N$2),3, IF(AND($F9<=N$2, $H9>=N$2), 2, "" ))) | O9: =IF(AND($F9<(O$2+7),$F9>O$2),1, IF(AND($H9<O$2+7,$H9>O$2),3, IF(AND($F9<=O$2, $H9>=O$2), 2, "" ))) | P9: =IF(AND($F9<(P$2+7),$F9>P$2),1, IF(AND($H9<P$2+7,$H9>P$2),3, IF(AND($F9<=P$2, $H9>=P$2), 2, "" ))) | Q9: =IF(AND($F9<(Q$2+7),$F9>Q$2),1, IF(AND($H9<Q$2+7,$H9>Q$2),3, IF(AND($F9<=Q$2, $H9>=Q$2), 2, "" ))) | R9: =IF(AND($F9<(R$2+7),$F9>R$2),1, IF(AND($H9<R$2+7,$H9>R$2),3, IF(AND($F9<=R$2, $H9>=R$2), 2, "" ))) | S9: =IF(AND($F9<(S$2+7),$F9>S$2),1, IF(AND($H9<S$2+7,$H9>S$2),3, IF(AND($F9<=S$2, $H9>=S$2), 2, "" ))) | ... AQ9: =IF(AND($F9<(AQ$2+7),$F9>AQ$2),1, IF(AND($H9<AQ$2+7,$H9>AQ$2),3, IF(AND($F9<=AQ$2, $H9>=AQ$2), 2, "" )))
B10: Mounting Structure Procurement | C10: 43941 | D10: 5 | E10: 43949 | F10: 43941 | G10: 5 | H10: 43949 | L10: =IF(AND($F10<(L$2+7),$F10>L$2),1, IF(AND($H10<L$2+7,$H10>L$2),3, IF(AND($F10<=L$2, $H10>=L$2), 2, "" ))) | M10: =IF(AND($F10<(M$2+7),$F10>M$2),1, IF(AND($H10<M$2+7,$H10>M$2),3, IF(AND($F10<=M$2, $H10>=M$2), 2, "" ))) | N10: =IF(AND($F10<(N$2+7),$F10>N$2),1, IF(AND($H10<N$2+7,$H10>N$2),3, IF(AND($F10<=N$2, $H10>=N$2), 2, "" ))) | O10: =IF(AND($F10<(O$2+7),$F10>O$2),1, IF(AND($H10<O$2+7,$H10>O$2),3, IF(AND($F10<=O$2, $H10>=O$2), 2, "" ))) | P10: =IF(AND($F10<(P$2+7),$F10>P$2),1, IF(AND($H10<P$2+7,$H10>P$2),3, IF(AND($F10<=P$2, $H10>=P$2), 2, "" ))) | Q10: =IF(AND($F10<(Q$2+7),$F10>Q$2),1, IF(AND($H10<Q$2+7,$H10>Q$2),3, IF(AND($F10<=Q$2, $H10>=Q$2), 2, "" ))) | R10: =IF(AND($F10<(R$2+7),$F10>R$2),1, IF(AND($H10<R$2+7,$H10>R$2),3, IF(AND($F10<=R$2, $H10>=R$2), 2, "" ))) | S10: =IF(AND($F10<(S$2+7),$F10>S$2),1, IF(AND($H10<S$2+7,$H10>S$2),3, IF(AND($F10<=S$2, $H10>=S$2), 2, "" ))) | ... AQ10: =IF(AND($F10<(AQ$2+7),$F10>AQ$2),1, IF(AND($H10<AQ$2+7,$H10>AQ$2),3, IF(AND($F10<=AQ$2, $H10>=AQ$2), 2, "" )))
B11: BOS Procurement | C11: 43941 | D11: 5 | E11: 43949 | F11: 43941 | G11: 5 | H11: 43949 | L11: =IF(AND($F11<(L$2+7),$F11>L$2),1, IF(AND($H11<L$2+7,$H11>L$2),3, IF(AND($F11<=L$2, $H11>=L$2), 2, "" ))) | M11: =IF(AND($F11<(M$2+7),$F11>M$2),1, IF(AND($H11<M$2+7,$H11>M$2),3, IF(AND($F11<=M$2, $H11>=M$2), 2, "" ))) | N11: =IF(AND($F11<(N$2+7),$F11>N$2),1, IF(AND($H11<N$2+7,$H11>N$2),3, IF(AND($F11<=N$2, $H11>=N$2), 2, "" ))) | O11: =IF(AND($F11<(O$2+7),$F11>O$2),1, IF(AND($H11<O$2+7,$H11>O$2),3, IF(AND($F11<=O$2, $H11>=O$2), 2, "" ))) | P11: =IF(AND($F11<(P$2+7),$F11>P$2),1, IF(AND($H11<P$2+7,$H11>P$2),3, IF(AND($F11<=P$2, $H11>=P$2), 2, "" ))) | Q11: =IF(AND($F11<(Q$2+7),$F11>Q$2),1, IF(AND($H11<Q$2+7,$H11>Q$2),3, IF(AND($F11<=Q$2, $H11>=Q$2), 2, "" ))) | R11: =IF(AND($F11<(R$2+7),$F11>R$2),1, IF(AND($H11<R$2+7,$H11>R$2),3, IF(AND($F11<=R$2, $H11>=R$2), 2, "" ))) | S11: =IF(AND($F11<(S$2+7),$F11>S$2),1, IF(AND($H11<S$2+7,$H11>S$2),3, IF(AND($F11<=S$2, $H11>=S$2), 2, "" ))) | ... AQ11: =IF(AND($F11<(AQ$2+7),$F11>AQ$2),1, IF(AND($H11<AQ$2+7,$H11>AQ$2),3, IF(AND($F11<=AQ$2, $H11>=AQ$2), 2, "" )))
A12: 5 | B12: Internal Project Kick off | C12: 43936 | D12: 5 | E12: 43943 | F12: 43936 | G12: 5 | H12: 43943
A13: 6 | B13: Client Project Kick-off | C13: 43963 | D13: 5 | E13: 43970 | F13: 43963 | G13: 5 | H13: 43970 | L13: =IF(AND($F13<(L$2+7),$F13>L$2),1, IF(AND($H13<L$2+7,$H13>L$2),3, IF(AND($F13<=L$2, $H13>=L$2), 2, "" ))) | M13: =IF(AND($F13<(M$2+7),$F13>M$2),1, IF(AND($H13<M$2+7,$H13>M$2),3, IF(AND($F13<=M$2, $H13>=M$2), 2, "" ))) | N13: =IF(AND($F13<(N$2+7),$F13>N$2),1, IF(AND($H13<N$2+7,$H13>N$2),3, IF(AND($F13<=N$2, $H13>=N$2), 2, "" ))) | O13: =IF(AND($F13<(O$2+7),$F13>O$2),1, IF(AND($H13<O$2+7,$H13>O$2),3, IF(AND($F13<=O$2, $H13>=O$2), 2, "" ))) | P13: =IF(AND($F13<(P$2+7),$F13>P$2),1, IF(AND($H13<P$2+7,$H13>P$2),3, IF(AND($F13<=P$2, $H13>=P$2), 2, "" ))) | Q13: =IF(AND($F13<(Q$2+7),$F13>Q$2),1, IF(AND($H13<Q$2+7,$H13>Q$2),3, IF(AND($F13<=Q$2, $H13>=Q$2), 2, "" ))) | R13: =IF(AND($F13<(R$2+7),$F13>R$2),1, IF(AND($H13<R$2+7,$H13>R$2),3, IF(AND($F13<=R$2, $H13>=R$2), 2, "" ))) | S13: =IF(AND($F13<(S$2+7),$F13>S$2),1, IF(AND($H13<S$2+7,$H13>S$2),3, IF(AND($F13<=S$2, $H13>=S$2), 2, "" ))) | ... AQ13: =IF(AND($F13<(AQ$2+7),$F13>AQ$2),1, IF(AND($H13<AQ$2+7,$H13>AQ$2),3, IF(AND($F13<=AQ$2, $H13>=AQ$2), 2, "" )))
A14: 7 | B14: Equipment Delivery | C14: 43983 | D14: 9 | E14: 43994 | F14: 43983 | G14: 9 | H14: 43994 | L14: =IF(AND($F14<(L$2+7),$F14>L$2),1, IF(AND($H14<L$2+7,$H14>L$2),3, IF(AND($F14<=L$2, $H14>=L$2), 2, "" ))) | M14: =IF(AND($F14<(M$2+7),$F14>M$2),1, IF(AND($H14<M$2+7,$H14>M$2),3, IF(AND($F14<=M$2, $H14>=M$2), 2, "" ))) | N14: =IF(AND($F14<(N$2+7),$F14>N$2),1, IF(AND($H14<N$2+7,$H14>N$2),3, IF(AND($F14<=N$2, $H14>=N$2), 2, "" ))) | O14: =IF(AND($F14<(O$2+7),$F14>O$2),1, IF(AND($H14<O$2+7,$H14>O$2),3, IF(AND($F14<=O$2, $H14>=O$2), 2, "" ))) | P14: =IF(AND($F14<(P$2+7),$F14>P$2),1, IF(AND($H14<P$2+7,$H14>P$2),3, IF(AND($F14<=P$2, $H14>=P$2), 2, "" ))) | Q14: =IF(AND($F14<(Q$2+7),$F14>Q$2),1, IF(AND($H14<Q$2+7,$H14>Q$2),3, IF(AND($F14<=Q$2, $H14>=Q$2), 2, "" ))) | R14: =IF(AND($F14<(R$2+7),$F14>R$2),1, IF(AND($H14<R$2+7,$H14>R$2),3, IF(AND($F14<=R$2, $H14>=R$2), 2, "" ))) | S14: =IF(AND($F14<(S$2+7),$F14>S$2),1, IF(AND($H14<S$2+7,$H14>S$2),3, IF(AND($F14<=S$2, $H14>=S$2), 2, "" ))) | ... AQ14: =IF(AND($F14<(AQ$2+7),$F14>AQ$2),1, IF(AND($H14<AQ$2+7,$H14>AQ$2),3, IF(AND($F14<=AQ$2, $H14>=AQ$2), 2, "" )))
B15: Mounting Structure Delivery | C15: 43983 | D15: 2 | E15: 43985 | F15: 43983 | G15: 2 | H15: 43985
B16: Panel Delivery | C16: 43990 | D16: 2 | E16: 43992 | F16: 43990 | G16: 2 | H16: 43992 | L16: =IF(AND($F16<(L$2+7),$F16>L$2),1, IF(AND($H16<L$2+7,$H16>L$2),3, IF(AND($F16<=L$2, $H16>=L$2), 2, "" ))) | M16: =IF(AND($F16<(M$2+7),$F16>M$2),1, IF(AND($H16<M$2+7,$H16>M$2),3, IF(AND($F16<=M$2, $H16>=M$2), 2, "" ))) | N16: =IF(AND($F16<(N$2+7),$F16>N$2),1, IF(AND($H16<N$2+7,$H16>N$2),3, IF(AND($F16<=N$2, $H16>=N$2), 2, "" ))) | O16: =IF(AND($F16<(O$2+7),$F16>O$2),1, IF(AND($H16<O$2+7,$H16>O$2),3, IF(AND($F16<=O$2, $H16>=O$2), 2, "" ))) | P16: =IF(AND($F16<(P$2+7),$F16>P$2),1, IF(AND($H16<P$2+7,$H16>P$2),3, IF(AND($F16<=P$2, $H16>=P$2), 2, "" ))) | Q16: =IF(AND($F16<(Q$2+7),$F16>Q$2),1, IF(AND($H16<Q$2+7,$H16>Q$2),3, IF(AND($F16<=Q$2, $H16>=Q$2), 2, "" ))) | R16: =IF(AND($F16<(R$2+7),$F16>R$2),1, IF(AND($H16<R$2+7,$H16>R$2),3, IF(AND($F16<=R$2, $H16>=R$2), 2, "" ))) | S16: =IF(AND($F16<(S$2+7),$F16>S$2),1, IF(AND($H16<S$2+7,$H16>S$2),3, IF(AND($F16<=S$2, $H16>=S$2), 2, "" ))) | ... AQ16: =IF(AND($F16<(AQ$2+7),$F16>AQ$2),1, IF(AND($H16<AQ$2+7,$H16>AQ$2),3, IF(AND($F16<=AQ$2, $H16>=AQ$2), 2, "" )))
B17: Generator Delivery | C17: 43983 | D17: 2 | E17: 43985 | F17: 43983 | G17: 2 | H17: 43985
A18: B | B18: PAYMENT MILESTONE 2: DELIVERY OF PV PANELS | C18: 43992 | D18: 2 | E18: 43994 | F18: 43992 | G18: 2 | H18: 43994
B19: Inverter Delivery | C19: 43983 | D19: 2 | E19: 43985 | F19: 43983 | G19: 2 | H19: 43985 | L19: =IF(AND($F19<(L$2+7),$F19>L$2),1, IF(AND($H19<L$2+7,$H19>L$2),3, IF(AND($F19<=L$2, $H19>=L$2), 2, "" ))) | M19: =IF(AND($F19<(M$2+7),$F19>M$2),1, IF(AND($H19<M$2+7,$H19>M$2),3, IF(AND($F19<=M$2, $H19>=M$2), 2, "" ))) | N19: =IF(AND($F19<(N$2+7),$F19>N$2),1, IF(AND($H19<N$2+7,$H19>N$2),3, IF(AND($F19<=N$2, $H19>=N$2), 2, "" ))) | O19: =IF(AND($F19<(O$2+7),$F19>O$2),1, IF(AND($H19<O$2+7,$H19>O$2),3, IF(AND($F19<=O$2, $H19>=O$2), 2, "" ))) | P19: =IF(AND($F19<(P$2+7),$F19>P$2),1, IF(AND($H19<P$2+7,$H19>P$2),3, IF(AND($F19<=P$2, $H19>=P$2), 2, "" ))) | Q19: =IF(AND($F19<(Q$2+7),$F19>Q$2),1, IF(AND($H19<Q$2+7,$H19>Q$2),3, IF(AND($F19<=Q$2, $H19>=Q$2), 2, "" ))) | R19: =IF(AND($F19<(R$2+7),$F19>R$2),1, IF(AND($H19<R$2+7,$H19>R$2),3, IF(AND($F19<=R$2, $H19>=R$2), 2, "" ))) | S19: =IF(AND($F19<(S$2+7),$F19>S$2),1, IF(AND($H19<S$2+7,$H19>S$2),3, IF(AND($F19<=S$2, $H19>=S$2), 2, "" ))) | ... AQ19: =IF(AND($F19<(AQ$2+7),$F19>AQ$2),1, IF(AND($H19<AQ$2+7,$H19>AQ$2),3, IF(AND($F19<=AQ$2, $H19>=AQ$2), 2, "" )))
B20: BOS Delivery | C20: 43983 | D20: 1 | E20: 43984 | F20: 43983 | G20: 1 | H20: 43984 | L20: =IF(AND($F20<(L$2+7),$F20>L$2),1, IF(AND($H20<L$2+7,$H20>L$2),3, IF(AND($F20<=L$2, $H20>=L$2), 2, "" ))) | M20: =IF(AND($F20<(M$2+7),$F20>M$2),1, IF(AND($H20<M$2+7,$H20>M$2),3, IF(AND($F20<=M$2, $H20>=M$2), 2, "" ))) | N20: =IF(AND($F20<(N$2+7),$F20>N$2),1, IF(AND($H20<N$2+7,$H20>N$2),3, IF(AND($F20<=N$2, $H20>=N$2), 2, "" ))) | O20: =IF(AND($F20<(O$2+7),$F20>O$2),1, IF(AND($H20<O$2+7,$H20>O$2),3, IF(AND($F20<=O$2, $H20>=O$2), 2, "" ))) | P20: =IF(AND($F20<(P$2+7),$F20>P$2),1, IF(AND($H20<P$2+7,$H20>P$2),3, IF(AND($F20<=P$2, $H20>=P$2), 2, "" ))) | Q20: =IF(AND($F20<(Q$2+7),$F20>Q$2),1, IF(AND($H20<Q$2+7,$H20>Q$2),3, IF(AND($F20<=Q$2, $H20>=Q$2), 2, "" ))) | R20: =IF(AND($F20<(R$2+7),$F20>R$2),1, IF(AND($H20<R$2+7,$H20>R$2),3, IF(AND($F20<=R$2, $H20>=R$2), 2, "" ))) | S20: =IF(AND($F20<(S$2+7),$F20>S$2),1, IF(AND($H20<S$2+7,$H20>S$2),3, IF(AND($F20<=S$2, $H20>=S$2), 2, "" ))) | ... AQ20: =IF(AND($F20<(AQ$2+7),$F20>AQ$2),1, IF(AND($H20<AQ$2+7,$H20>AQ$2),3, IF(AND($F20<=AQ$2, $H20>=AQ$2), 2, "" )))
A21: C | B21: PAYMENT MILESTONE 3: DELIVERY OF INVERTERS AND BOS | C21: 43985 | D21: 2 | E21: 43987 | F21: 43985 | G21: 2 | H21: 43987
A22: 8 | B22: Installation | C22: 43990 | D22: 22 | E22: 44012 | F22: 43990 | G22: 22 | H22: 44012 | L22: =IF(AND($F22<(L$2+7),$F22>L$2),1, IF(AND($H22<L$2+7,$H22>L$2),3, IF(AND($F22<=L$2, $H22>=L$2), 2, "" ))) | M22: =IF(AND($F22<(M$2+7),$F22>M$2),1, IF(AND($H22<M$2+7,$H22>M$2),3, IF(AND($F22<=M$2, $H22>=M$2), 2, "" ))) | N22: =IF(AND($F22<(N$2+7),$F22>N$2),1, IF(AND($H22<N$2+7,$H22>N$2),3, IF(AND($F22<=N$2, $H22>=N$2), 2, "" ))) | O22: =IF(AND($F22<(O$2+7),$F22>O$2),1, IF(AND($H22<O$2+7,$H22>O$2),3, IF(AND($F22<=O$2, $H22>=O$2), 2, "" ))) | P22: =IF(AND($F22<(P$2+7),$F22>P$2),1, IF(AND($H22<P$2+7,$H22>P$2),3, IF(AND($F22<=P$2, $H22>=P$2), 2, "" ))) | Q22: =IF(AND($F22<(Q$2+7),$F22>Q$2),1, IF(AND($H22<Q$2+7,$H22>Q$2),3, IF(AND($F22<=Q$2, $H22>=Q$2), 2, "" ))) | R22: =IF(AND($F22<(R$2+7),$F22>R$2),1, IF(AND($H22<R$2+7,$H22>R$2),3, IF(AND($F22<=R$2, $H22>=R$2), 2, "" ))) | S22: =IF(AND($F22<(S$2+7),$F22>S$2),1, IF(AND($H22<S$2+7,$H22>S$2),3, IF(AND($F22<=S$2, $H22>=S$2), 2, "" ))) | ... AQ22: =IF(AND($F22<(AQ$2+7),$F22>AQ$2),1, IF(AND($H22<AQ$2+7,$H22>AQ$2),3, IF(AND($F22<=AQ$2, $H22>=AQ$2), 2, "" ))) -> 2
B23: Site Establishment | C23: 43990 | D23: 1 | E23: 43991 | F23: 43990 | G23: 1 | H23: 43991 | J23: Installation placed on hold due to Covid-19 case | L23: =IF(AND($F23<(L$2+7),$F23>L$2),1, IF(AND($H23<L$2+7,$H23>L$2),3, IF(AND($F23<=L$2, $H23>=L$2), 2, "" ))) | M23: =IF(AND($F23<(M$2+7),$F23>M$2),1, IF(AND($H23<M$2+7,$H23>M$2),3, IF(AND($F23<=M$2, $H23>=M$2), 2, "" ))) | N23: =IF(AND($F23<(N$2+7),$F23>N$2),1, IF(AND($H23<N$2+7,$H23>N$2),3, IF(AND($F23<=N$2, $H23>=N$2), 2, "" ))) | O23: =IF(AND($F23<(O$2+7),$F23>O$2),1, IF(AND($H23<O$2+7,$H23>O$2),3, IF(AND($F23<=O$2, $H23>=O$2), 2, "" ))) | P23: =IF(AND($F23<(P$2+7),$F23>P$2),1, IF(AND($H23<P$2+7,$H23>P$2),3, IF(AND($F23<=P$2, $H23>=P$2), 2, "" ))) | Q23: =IF(AND($F23<(Q$2+7),$F23>Q$2),1, IF(AND($H23<Q$2+7,$H23>Q$2),3, IF(AND($F23<=Q$2, $H23>=Q$2), 2, "" ))) | R23: =IF(AND($F23<(R$2+7),$F23>R$2),1, IF(AND($H23<R$2+7,$H23>R$2),3, IF(AND($F23<=R$2, $H23>=R$2), 2, "" ))) | S23: =IF(AND($F23<(S$2+7),$F23>S$2),1, IF(AND($H23<S$2+7,$H23>S$2),3, IF(AND($F23<=S$2, $H23>=S$2), 2, "" ))) | ... AQ23: =IF(AND($F23<(AQ$2+7),$F23>AQ$2),1, IF(AND($H23<AQ$2+7,$H23>AQ$2),3, IF(AND($F23<=AQ$2, $H23>=AQ$2), 2, "" )))
A24: 9 | B24: DC Works | C24: 43991 | D24: 16 | E24: 44012 | F24: 43991 | G24: 16 | H24: 44012 | L24: =IF(AND($F24<(L$2+7),$F24>L$2),1, IF(AND($H24<L$2+7,$H24>L$2),3, IF(AND($F24<=L$2, $H24>=L$2), 2, "" ))) | M24: =IF(AND($F24<(M$2+7),$F24>M$2),1, IF(AND($H24<M$2+7,$H24>M$2),3, IF(AND($F24<=M$2, $H24>=M$2), 2, "" ))) | N24: =IF(AND($F24<(N$2+7),$F24>N$2),1, IF(AND($H24<N$2+7,$H24>N$2),3, IF(AND($F24<=N$2, $H24>=N$2), 2, "" ))) | O24: =IF(AND($F24<(O$2+7),$F24>O$2),1, IF(AND($H24<O$2+7,$H24>O$2),3, IF(AND($F24<=O$2, $H24>=O$2), 2, "" ))) | P24: =IF(AND($F24<(P$2+7),$F24>P$2),1, IF(AND($H24<P$2+7,$H24>P$2),3, IF(AND($F24<=P$2, $H24>=P$2), 2, "" ))) | Q24: =IF(AND($F24<(Q$2+7),$F24>Q$2),1, IF(AND($H24<Q$2+7,$H24>Q$2),3, IF(AND($F24<=Q$2, $H24>=Q$2), 2, "" ))) | R24: =IF(AND($F24<(R$2+7),$F24>R$2),1, IF(AND($H24<R$2+7,$H24>R$2),3, IF(AND($F24<=R$2, $H24>=R$2), 2, "" ))) | S24: =IF(AND($F24<(S$2+7),$F24>S$2),1, IF(AND($H24<S$2+7,$H24>S$2),3, IF(AND($F24<=S$2, $H24>=S$2), 2, "" ))) | ... AQ24: =IF(AND($F24<(AQ$2+7),$F24>AQ$2),1, IF(AND($H24<AQ$2+7,$H24>AQ$2),3, IF(AND($F24<=AQ$2, $H24>=AQ$2), 2, "" ))) -> 2
B25: Mounting structure Installation | C25: 43991 | D25: 4 | E25: 43997 | F25: 43991 | G25: 4 | H25: 43997 | L25: =IF(AND($F25<(L$2+7),$F25>L$2),1, IF(AND($H25<L$2+7,$H25>L$2),3, IF(AND($F25<=L$2, $H25>=L$2), 2, "" ))) | M25: =IF(AND($F25<(M$2+7),$F25>M$2),1, IF(AND($H25<M$2+7,$H25>M$2),3, IF(AND($F25<=M$2, $H25>=M$2), 2, "" ))) | N25: =IF(AND($F25<(N$2+7),$F25>N$2),1, IF(AND($H25<N$2+7,$H25>N$2),3, IF(AND($F25<=N$2, $H25>=N$2), 2, "" ))) | O25: =IF(AND($F25<(O$2+7),$F25>O$2),1, IF(AND($H25<O$2+7,$H25>O$2),3, IF(AND($F25<=O$2, $H25>=O$2), 2, "" ))) | P25: =IF(AND($F25<(P$2+7),$F25>P$2),1, IF(AND($H25<P$2+7,$H25>P$2),3, IF(AND($F25<=P$2, $H25>=P$2), 2, "" ))) | Q25: =IF(AND($F25<(Q$2+7),$F25>Q$2),1, IF(AND($H25<Q$2+7,$H25>Q$2),3, IF(AND($F25<=Q$2, $H25>=Q$2), 2, "" ))) | R25: =IF(AND($F25<(R$2+7),$F25>R$2),1, IF(AND($H25<R$2+7,$H25>R$2),3, IF(AND($F25<=R$2, $H25>=R$2), 2, "" ))) | S25: =IF(AND($F25<(S$2+7),$F25>S$2),1, IF(AND($H25<S$2+7,$H25>S$2),3, IF(AND($F25<=S$2, $H25>=S$2), 2, "" ))) | ... AQ25: =IF(AND($F25<(AQ$2+7),$F25>AQ$2),1, IF(AND($H25<AQ$2+7,$H25>AQ$2),3, IF(AND($F25<=AQ$2, $H25>=AQ$2), 2, "" )))
B26: Cable tray Installation | C26: 43997 | D26: 3 | E26: 44004 | F26: 43997 | G26: 3 | H26: 44004 | L26: =IF(AND($F26<(L$2+7),$F26>L$2),1, IF(AND($H26<L$2+7,$H26>L$2),3, IF(AND($F26<=L$2, $H26>=L$2), 2, "" ))) | M26: =IF(AND($F26<(M$2+7),$F26>M$2),1, IF(AND($H26<M$2+7,$H26>M$2),3, IF(AND($F26<=M$2, $H26>=M$2), 2, "" ))) | N26: =IF(AND($F26<(N$2+7),$F26>N$2),1, IF(AND($H26<N$2+7,$H26>N$2),3, IF(AND($F26<=N$2, $H26>=N$2), 2, "" ))) | O26: =IF(AND($F26<(O$2+7),$F26>O$2),1, IF(AND($H26<O$2+7,$H26>O$2),3, IF(AND($F26<=O$2, $H26>=O$2), 2, "" ))) | P26: =IF(AND($F26<(P$2+7),$F26>P$2),1, IF(AND($H26<P$2+7,$H26>P$2),3, IF(AND($F26<=P$2, $H26>=P$2), 2, "" ))) | Q26: =IF(AND($F26<(Q$2+7),$F26>Q$2),1, IF(AND($H26<Q$2+7,$H26>Q$2),3, IF(AND($F26<=Q$2, $H26>=Q$2), 2, "" ))) | R26: =IF(AND($F26<(R$2+7),$F26>R$2),1, IF(AND($H26<R$2+7,$H26>R$2),3, IF(AND($F26<=R$2, $H26>=R$2), 2, "" ))) | S26: =IF(AND($F26<(S$2+7),$F26>S$2),1, IF(AND($H26<S$2+7,$H26>S$2),3, IF(AND($F26<=S$2, $H26>=S$2), 2, "" ))) | ... AQ26: =IF(AND($F26<(AQ$2+7),$F26>AQ$2),1, IF(AND($H26<AQ$2+7,$H26>AQ$2),3, IF(AND($F26<=AQ$2, $H26>=AQ$2), 2, "" )))
B27: DC Cable Installation | C27: 44004 | D27: 2 | E27: 44006 | F27: 44004 | G27: 2 | H27: 44006 | L27: =IF(AND($F27<(L$2+7),$F27>L$2),1, IF(AND($H27<L$2+7,$H27>L$2),3, IF(AND($F27<=L$2, $H27>=L$2), 2, "" ))) | M27: =IF(AND($F27<(M$2+7),$F27>M$2),1, IF(AND($H27<M$2+7,$H27>M$2),3, IF(AND($F27<=M$2, $H27>=M$2), 2, "" ))) | N27: =IF(AND($F27<(N$2+7),$F27>N$2),1, IF(AND($H27<N$2+7,$H27>N$2),3, IF(AND($F27<=N$2, $H27>=N$2), 2, "" ))) | O27: =IF(AND($F27<(O$2+7),$F27>O$2),1, IF(AND($H27<O$2+7,$H27>O$2),3, IF(AND($F27<=O$2, $H27>=O$2), 2, "" ))) | P27: =IF(AND($F27<(P$2+7),$F27>P$2),1, IF(AND($H27<P$2+7,$H27>P$2),3, IF(AND($F27<=P$2, $H27>=P$2), 2, "" ))) | Q27: =IF(AND($F27<(Q$2+7),$F27>Q$2),1, IF(AND($H27<Q$2+7,$H27>Q$2),3, IF(AND($F27<=Q$2, $H27>=Q$2), 2, "" ))) | R27: =IF(AND($F27<(R$2+7),$F27>R$2),1, IF(AND($H27<R$2+7,$H27>R$2),3, IF(AND($F27<=R$2, $H27>=R$2), 2, "" ))) | S27: =IF(AND($F27<(S$2+7),$F27>S$2),1, IF(AND($H27<S$2+7,$H27>S$2),3, IF(AND($F27<=S$2, $H27>=S$2), 2, "" ))) | ... AQ27: =IF(AND($F27<(AQ$2+7),$F27>AQ$2),1, IF(AND($H27<AQ$2+7,$H27>AQ$2),3, IF(AND($F27<=AQ$2, $H27>=AQ$2), 2, "" )))
B28: Module Installation | C28: 44006 | D28: 4 | E28: 44012 | F28: 44006 | G28: 4 | H28: 44012 | L28: =IF(AND($F28<(L$2+7),$F28>L$2),1, IF(AND($H28<L$2+7,$H28>L$2),3, IF(AND($F28<=L$2, $H28>=L$2), 2, "" ))) | M28: =IF(AND($F28<(M$2+7),$F28>M$2),1, IF(AND($H28<M$2+7,$H28>M$2),3, IF(AND($F28<=M$2, $H28>=M$2), 2, "" ))) | N28: =IF(AND($F28<(N$2+7),$F28>N$2),1, IF(AND($H28<N$2+7,$H28>N$2),3, IF(AND($F28<=N$2, $H28>=N$2), 2, "" ))) | O28: =IF(AND($F28<(O$2+7),$F28>O$2),1, IF(AND($H28<O$2+7,$H28>O$2),3, IF(AND($F28<=O$2, $H28>=O$2), 2, "" ))) | P28: =IF(AND($F28<(P$2+7),$F28>P$2),1, IF(AND($H28<P$2+7,$H28>P$2),3, IF(AND($F28<=P$2, $H28>=P$2), 2, "" ))) | Q28: =IF(AND($F28<(Q$2+7),$F28>Q$2),1, IF(AND($H28<Q$2+7,$H28>Q$2),3, IF(AND($F28<=Q$2, $H28>=Q$2), 2, "" ))) | R28: =IF(AND($F28<(R$2+7),$F28>R$2),1, IF(AND($H28<R$2+7,$H28>R$2),3, IF(AND($F28<=R$2, $H28>=R$2), 2, "" ))) | S28: =IF(AND($F28<(S$2+7),$F28>S$2),1, IF(AND($H28<S$2+7,$H28>S$2),3, IF(AND($F28<=S$2, $H28>=S$2), 2, "" ))) | ... AQ28: =IF(AND($F28<(AQ$2+7),$F28>AQ$2),1, IF(AND($H28<AQ$2+7,$H28>AQ$2),3, IF(AND($F28<=AQ$2, $H28>=AQ$2), 2, "" ))) -> 2
B29: Earth Cable Installation | C29: 44004 | D29: 1 | E29: 44005 | F29: 44004 | G29: 1 | H29: 44005 | L29: =IF(AND($F29<(L$2+7),$F29>L$2),1, IF(AND($H29<L$2+7,$H29>L$2),3, IF(AND($F29<=L$2, $H29>=L$2), 2, "" ))) | M29: =IF(AND($F29<(M$2+7),$F29>M$2),1, IF(AND($H29<M$2+7,$H29>M$2),3, IF(AND($F29<=M$2, $H29>=M$2), 2, "" ))) | N29: =IF(AND($F29<(N$2+7),$F29>N$2),1, IF(AND($H29<N$2+7,$H29>N$2),3, IF(AND($F29<=N$2, $H29>=N$2), 2, "" ))) | O29: =IF(AND($F29<(O$2+7),$F29>O$2),1, IF(AND($H29<O$2+7,$H29>O$2),3, IF(AND($F29<=O$2, $H29>=O$2), 2, "" ))) | P29: =IF(AND($F29<(P$2+7),$F29>P$2),1, IF(AND($H29<P$2+7,$H29>P$2),3, IF(AND($F29<=P$2, $H29>=P$2), 2, "" ))) | Q29: =IF(AND($F29<(Q$2+7),$F29>Q$2),1, IF(AND($H29<Q$2+7,$H29>Q$2),3, IF(AND($F29<=Q$2, $H29>=Q$2), 2, "" ))) | R29: =IF(AND($F29<(R$2+7),$F29>R$2),1, IF(AND($H29<R$2+7,$H29>R$2),3, IF(AND($F29<=R$2, $H29>=R$2), 2, "" ))) | S29: =IF(AND($F29<(S$2+7),$F29>S$2),1, IF(AND($H29<S$2+7,$H29>S$2),3, IF(AND($F29<=S$2, $H29>=S$2), 2, "" ))) | ... AQ29: =IF(AND($F29<(AQ$2+7),$F29>AQ$2),1, IF(AND($H29<AQ$2+7,$H29>AQ$2),3, IF(AND($F29<=AQ$2, $H29>=AQ$2), 2, "" )))
A30: 10 | B30: AC Works | C30: 43991 | D30: 8 | E30: 44000 | F30: 43991 | G30: 8 | H30: 44000
B31: Inverters Installation | C31: 43991 | D31: 2 | E31: 43993 | F31: 43991 | G31: 2 | H31: 43993 | L31: =IF(AND($F31<(L$2+7),$F31>L$2),1, IF(AND($H31<L$2+7,$H31>L$2),3, IF(AND($F31<=L$2, $H31>=L$2), 2, "" ))) | M31: =IF(AND($F31<(M$2+7),$F31>M$2),1, IF(AND($H31<M$2+7,$H31>M$2),3, IF(AND($F31<=M$2, $H31>=M$2), 2, "" ))) | N31: =IF(AND($F31<(N$2+7),$F31>N$2),1, IF(AND($H31<N$2+7,$H31>N$2),3, IF(AND($F31<=N$2, $H31>=N$2), 2, "" ))) | O31: =IF(AND($F31<(O$2+7),$F31>O$2),1, IF(AND($H31<O$2+7,$H31>O$2),3, IF(AND($F31<=O$2, $H31>=O$2), 2, "" ))) | P31: =IF(AND($F31<(P$2+7),$F31>P$2),1, IF(AND($H31<P$2+7,$H31>P$2),3, IF(AND($F31<=P$2, $H31>=P$2), 2, "" ))) | Q31: =IF(AND($F31<(Q$2+7),$F31>Q$2),1, IF(AND($H31<Q$2+7,$H31>Q$2),3, IF(AND($F31<=Q$2, $H31>=Q$2), 2, "" ))) | R31: =IF(AND($F31<(R$2+7),$F31>R$2),1, IF(AND($H31<R$2+7,$H31>R$2),3, IF(AND($F31<=R$2, $H31>=R$2), 2, "" ))) | S31: =IF(AND($F31<(S$2+7),$F31>S$2),1, IF(AND($H31<S$2+7,$H31>S$2),3, IF(AND($F31<=S$2, $H31>=S$2), 2, "" ))) | ... AQ31: =IF(AND($F31<(AQ$2+7),$F31>AQ$2),1, IF(AND($H31<AQ$2+7,$H31>AQ$2),3, IF(AND($F31<=AQ$2, $H31>=AQ$2), 2, "" )))
B32: AC BOS Installation | C32: 43993 | D32: 3 | E32: 44000 | F32: 43993 | G32: 3 | H32: 44000 | L32: =IF(AND($F32<(L$2+7),$F32>L$2),1, IF(AND($H32<L$2+7,$H32>L$2),3, IF(AND($F32<=L$2, $H32>=L$2), 2, "" ))) | M32: =IF(AND($F32<(M$2+7),$F32>M$2),1, IF(AND($H32<M$2+7,$H32>M$2),3, IF(AND($F32<=M$2, $H32>=M$2), 2, "" ))) | N32: =IF(AND($F32<(N$2+7),$F32>N$2),1, IF(AND($H32<N$2+7,$H32>N$2),3, IF(AND($F32<=N$2, $H32>=N$2), 2, "" ))) | O32: =IF(AND($F32<(O$2+7),$F32>O$2),1, IF(AND($H32<O$2+7,$H32>O$2),3, IF(AND($F32<=O$2, $H32>=O$2), 2, "" ))) | P32: =IF(AND($F32<(P$2+7),$F32>P$2),1, IF(AND($H32<P$2+7,$H32>P$2),3, IF(AND($F32<=P$2, $H32>=P$2), 2, "" ))) | Q32: =IF(AND($F32<(Q$2+7),$F32>Q$2),1, IF(AND($H32<Q$2+7,$H32>Q$2),3, IF(AND($F32<=Q$2, $H32>=Q$2), 2, "" ))) | R32: =IF(AND($F32<(R$2+7),$F32>R$2),1, IF(AND($H32<R$2+7,$H32>R$2),3, IF(AND($F32<=R$2, $H32>=R$2), 2, "" ))) | S32: =IF(AND($F32<(S$2+7),$F32>S$2),1, IF(AND($H32<S$2+7,$H32>S$2),3, IF(AND($F32<=S$2, $H32>=S$2), 2, "" ))) | ... AQ32: =IF(AND($F32<(AQ$2+7),$F32>AQ$2),1, IF(AND($H32<AQ$2+7,$H32>AQ$2),3, IF(AND($F32<=AQ$2, $H32>=AQ$2), 2, "" )))
B33: AC Cable/Tie-In | C33: 43992 | D33: 3 | E33: 43997 | F33: 43992 | G33: 3 | H33: 43997 | L33: =IF(AND($F33<(L$2+7),$F33>L$2),1, IF(AND($H33<L$2+7,$H33>L$2),3, IF(AND($F33<=L$2, $H33>=L$2), 2, "" ))) | M33: =IF(AND($F33<(M$2+7),$F33>M$2),1, IF(AND($H33<M$2+7,$H33>M$2),3, IF(AND($F33<=M$2, $H33>=M$2), 2, "" ))) | N33: =IF(AND($F33<(N$2+7),$F33>N$2),1, IF(AND($H33<N$2+7,$H33>N$2),3, IF(AND($F33<=N$2, $H33>=N$2), 2, "" ))) | O33: =IF(AND($F33<(O$2+7),$F33>O$2),1, IF(AND($H33<O$2+7,$H33>O$2),3, IF(AND($F33<=O$2, $H33>=O$2), 2, "" ))) | P33: =IF(AND($F33<(P$2+7),$F33>P$2),1, IF(AND($H33<P$2+7,$H33>P$2),3, IF(AND($F33<=P$2, $H33>=P$2), 2, "" ))) | Q33: =IF(AND($F33<(Q$2+7),$F33>Q$2),1, IF(AND($H33<Q$2+7,$H33>Q$2),3, IF(AND($F33<=Q$2, $H33>=Q$2), 2, "" ))) | R33: =IF(AND($F33<(R$2+7),$F33>R$2),1, IF(AND($H33<R$2+7,$H33>R$2),3, IF(AND($F33<=R$2, $H33>=R$2), 2, "" ))) | S33: =IF(AND($F33<(S$2+7),$F33>S$2),1, IF(AND($H33<S$2+7,$H33>S$2),3, IF(AND($F33<=S$2, $H33>=S$2), 2, "" ))) | ... AQ33: =IF(AND($F33<(AQ$2+7),$F33>AQ$2),1, IF(AND($H33<AQ$2+7,$H33>AQ$2),3, IF(AND($F33<=AQ$2, $H33>=AQ$2), 2, "" )))
B34: Monitoring Platform Installation | C34: 43997 | D34: 1 | E34: 44000 | F34: 43997 | G34: 1 | H34: 44000
A35: 11 | B35: Completion | C35: 44000 | D35: 14 | E35: 44014 | F35: 44000 | G35: 14 | H35: 44014 | L35: =IF(AND($F35<(L$2+7),$F35>L$2),1, IF(AND($H35<L$2+7,$H35>L$2),3, IF(AND($F35<=L$2, $H35>=L$2), 2, "" ))) | M35: =IF(AND($F35<(M$2+7),$F35>M$2),1, IF(AND($H35<M$2+7,$H35>M$2),3, IF(AND($F35<=M$2, $H35>=M$2), 2, "" ))) | N35: =IF(AND($F35<(N$2+7),$F35>N$2),1, IF(AND($H35<N$2+7,$H35>N$2),3, IF(AND($F35<=N$2, $H35>=N$2), 2, "" ))) | O35: =IF(AND($F35<(O$2+7),$F35>O$2),1, IF(AND($H35<O$2+7,$H35>O$2),3, IF(AND($F35<=O$2, $H35>=O$2), 2, "" ))) | P35: =IF(AND($F35<(P$2+7),$F35>P$2),1, IF(AND($H35<P$2+7,$H35>P$2),3, IF(AND($F35<=P$2, $H35>=P$2), 2, "" ))) | Q35: =IF(AND($F35<(Q$2+7),$F35>Q$2),1, IF(AND($H35<Q$2+7,$H35>Q$2),3, IF(AND($F35<=Q$2, $H35>=Q$2), 2, "" ))) | R35: =IF(AND($F35<(R$2+7),$F35>R$2),1, IF(AND($H35<R$2+7,$H35>R$2),3, IF(AND($F35<=R$2, $H35>=R$2), 2, "" ))) | S35: =IF(AND($F35<(S$2+7),$F35>S$2),1, IF(AND($H35<S$2+7,$H35>S$2),3, IF(AND($F35<=S$2, $H35>=S$2), 2, "" ))) | ... AQ35: =IF(AND($F35<(AQ$2+7),$F35>AQ$2),1, IF(AND($H35<AQ$2+7,$H35>AQ$2),3, IF(AND($F35<=AQ$2, $H35>=AQ$2), 2, "" ))) -> 3
B36: DC Works | C36: 44012 | D36: 2 | E36: 44014 | F36: 44012 | G36: 2 | H36: 44014 | L36: =IF(AND($F36<(L$2+7),$F36>L$2),1, IF(AND($H36<L$2+7,$H36>L$2),3, IF(AND($F36<=L$2, $H36>=L$2), 2, "" ))) | M36: =IF(AND($F36<(M$2+7),$F36>M$2),1, IF(AND($H36<M$2+7,$H36>M$2),3, IF(AND($F36<=M$2, $H36>=M$2), 2, "" ))) | N36: =IF(AND($F36<(N$2+7),$F36>N$2),1, IF(AND($H36<N$2+7,$H36>N$2),3, IF(AND($F36<=N$2, $H36>=N$2), 2, "" ))) | O36: =IF(AND($F36<(O$2+7),$F36>O$2),1, IF(AND($H36<O$2+7,$H36>O$2),3, IF(AND($F36<=O$2, $H36>=O$2), 2, "" ))) | P36: =IF(AND($F36<(P$2+7),$F36>P$2),1, IF(AND($H36<P$2+7,$H36>P$2),3, IF(AND($F36<=P$2, $H36>=P$2), 2, "" ))) | Q36: =IF(AND($F36<(Q$2+7),$F36>Q$2),1, IF(AND($H36<Q$2+7,$H36>Q$2),3, IF(AND($F36<=Q$2, $H36>=Q$2), 2, "" ))) | R36: =IF(AND($F36<(R$2+7),$F36>R$2),1, IF(AND($H36<R$2+7,$H36>R$2),3, IF(AND($F36<=R$2, $H36>=R$2), 2, "" ))) | S36: =IF(AND($F36<(S$2+7),$F36>S$2),1, IF(AND($H36<S$2+7,$H36>S$2),3, IF(AND($F36<=S$2, $H36>=S$2), 2, "" ))) | ... AQ36: =IF(AND($F36<(AQ$2+7),$F36>AQ$2),1, IF(AND($H36<AQ$2+7,$H36>AQ$2),3, IF(AND($F36<=AQ$2, $H36>=AQ$2), 2, "" ))) -> 3
B37: AC Works | C37: 44000 | D37: 2 | E37: 44004 | F37: 44000 | G37: 2 | H37: 44004 | L37: =IF(AND($F37<(L$2+7),$F37>L$2),1, IF(AND($H37<L$2+7,$H37>L$2),3, IF(AND($F37<=L$2, $H37>=L$2), 2, "" ))) | M37: =IF(AND($F37<(M$2+7),$F37>M$2),1, IF(AND($H37<M$2+7,$H37>M$2),3, IF(AND($F37<=M$2, $H37>=M$2), 2, "" ))) | N37: =IF(AND($F37<(N$2+7),$F37>N$2),1, IF(AND($H37<N$2+7,$H37>N$2),3, IF(AND($F37<=N$2, $H37>=N$2), 2, "" ))) | O37: =IF(AND($F37<(O$2+7),$F37>O$2),1, IF(AND($H37<O$2+7,$H37>O$2),3, IF(AND($F37<=O$2, $H37>=O$2), 2, "" ))) | P37: =IF(AND($F37<(P$2+7),$F37>P$2),1, IF(AND($H37<P$2+7,$H37>P$2),3, IF(AND($F37<=P$2, $H37>=P$2), 2, "" ))) | Q37: =IF(AND($F37<(Q$2+7),$F37>Q$2),1, IF(AND($H37<Q$2+7,$H37>Q$2),3, IF(AND($F37<=Q$2, $H37>=Q$2), 2, "" ))) | R37: =IF(AND($F37<(R$2+7),$F37>R$2),1, IF(AND($H37<R$2+7,$H37>R$2),3, IF(AND($F37<=R$2, $H37>=R$2), 2, "" ))) | S37: =IF(AND($F37<(S$2+7),$F37>S$2),1, IF(AND($H37<S$2+7,$H37>S$2),3, IF(AND($F37<=S$2, $H37>=S$2), 2, "" ))) | ... AQ37: =IF(AND($F37<(AQ$2+7),$F37>AQ$2),1, IF(AND($H37<AQ$2+7,$H37>AQ$2),3, IF(AND($F37<=AQ$2, $H37>=AQ$2), 2, "" )))
A38: D | B38: PAYMENT MILESTONE 4: PRACTICAL COMPLETION | C38: 44012 | D38: 1 | E38: 44013 | F38: 44012 | G38: 1 | H38: 44013 | L38: =IF(AND($F38<(L$2+7),$F38>L$2),1, IF(AND($H38<L$2+7,$H38>L$2),3, IF(AND($F38<=L$2, $H38>=L$2), 2, "" ))) | M38: =IF(AND($F38<(M$2+7),$F38>M$2),1, IF(AND($H38<M$2+7,$H38>M$2),3, IF(AND($F38<=M$2, $H38>=M$2), 2, "" ))) | N38: =IF(AND($F38<(N$2+7),$F38>N$2),1, IF(AND($H38<N$2+7,$H38>N$2),3, IF(AND($F38<=N$2, $H38>=N$2), 2, "" ))) | O38: =IF(AND($F38<(O$2+7),$F38>O$2),1, IF(AND($H38<O$2+7,$H38>O$2),3, IF(AND($F38<=O$2, $H38>=O$2), 2, "" ))) | P38: =IF(AND($F38<(P$2+7),$F38>P$2),1, IF(AND($H38<P$2+7,$H38>P$2),3, IF(AND($F38<=P$2, $H38>=P$2), 2, "" ))) | Q38: =IF(AND($F38<(Q$2+7),$F38>Q$2),1, IF(AND($H38<Q$2+7,$H38>Q$2),3, IF(AND($F38<=Q$2, $H38>=Q$2), 2, "" ))) | R38: =IF(AND($F38<(R$2+7),$F38>R$2),1, IF(AND($H38<R$2+7,$H38>R$2),3, IF(AND($F38<=R$2, $H38>=R$2), 2, "" ))) | S38: =IF(AND($F38<(S$2+7),$F38>S$2),1, IF(AND($H38<S$2+7,$H38>S$2),3, IF(AND($F38<=S$2, $H38>=S$2), 2, "" ))) | ... AQ38: =IF(AND($F38<(AQ$2+7),$F38>AQ$2),1, IF(AND($H38<AQ$2+7,$H38>AQ$2),3, IF(AND($F38<=AQ$2, $H38>=AQ$2), 2, "" ))) -> 3
A39: 12 | B39: Commissioning | C39: 43997 | D39: 22 | E39: 44019 | F39: 43997 | G39: 22 | H39: 44019 | L39: =IF(AND($F39<(L$2+7),$F39>L$2),1, IF(AND($H39<L$2+7,$H39>L$2),3, IF(AND($F39<=L$2, $H39>=L$2), 2, "" ))) | M39: =IF(AND($F39<(M$2+7),$F39>M$2),1, IF(AND($H39<M$2+7,$H39>M$2),3, IF(AND($F39<=M$2, $H39>=M$2), 2, "" ))) | N39: =IF(AND($F39<(N$2+7),$F39>N$2),1, IF(AND($H39<N$2+7,$H39>N$2),3, IF(AND($F39<=N$2, $H39>=N$2), 2, "" ))) | O39: =IF(AND($F39<(O$2+7),$F39>O$2),1, IF(AND($H39<O$2+7,$H39>O$2),3, IF(AND($F39<=O$2, $H39>=O$2), 2, "" ))) | P39: =IF(AND($F39<(P$2+7),$F39>P$2),1, IF(AND($H39<P$2+7,$H39>P$2),3, IF(AND($F39<=P$2, $H39>=P$2), 2, "" ))) | Q39: =IF(AND($F39<(Q$2+7),$F39>Q$2),1, IF(AND($H39<Q$2+7,$H39>Q$2),3, IF(AND($F39<=Q$2, $H39>=Q$2), 2, "" ))) | R39: =IF(AND($F39<(R$2+7),$F39>R$2),1, IF(AND($H39<R$2+7,$H39>R$2),3, IF(AND($F39<=R$2, $H39>=R$2), 2, "" ))) | S39: =IF(AND($F39<(S$2+7),$F39>S$2),1, IF(AND($H39<S$2+7,$H39>S$2),3, IF(AND($F39<=S$2, $H39>=S$2), 2, "" ))) | ... AQ39: =IF(AND($F39<(AQ$2+7),$F39>AQ$2),1, IF(AND($H39<AQ$2+7,$H39>AQ$2),3, IF(AND($F39<=AQ$2, $H39>=AQ$2), 2, "" ))) -> 2
B40: Snag List | C40: 44014 | D40: 3 | E40: 44019 | F40: 44014 | G40: 3 | H40: 44019
B41: Pre-Commissioning Checks | C41: 44010 | D41: 2 | E41: 44012 | F41: 44010 | G41: 2 | H41: 44012
B42: Issue CoC | C42: 43997 | D42: 2 | E42: 44001 | F42: 43997 | G42: 2 | H42: 44001 | L42: =IF(AND($F42<(L$2+7),$F42>L$2),1, IF(AND($H42<L$2+7,$H42>L$2),3, IF(AND($F42<=L$2, $H42>=L$2), 2, "" ))) | M42: =IF(AND($F42<(M$2+7),$F42>M$2),1, IF(AND($H42<M$2+7,$H42>M$2),3, IF(AND($F42<=M$2, $H42>=M$2), 2, "" ))) | N42: =IF(AND($F42<(N$2+7),$F42>N$2),1, IF(AND($H42<N$2+7,$H42>N$2),3, IF(AND($F42<=N$2, $H42>=N$2), 2, "" ))) | O42: =IF(AND($F42<(O$2+7),$F42>O$2),1, IF(AND($H42<O$2+7,$H42>O$2),3, IF(AND($F42<=O$2, $H42>=O$2), 2, "" ))) | P42: =IF(AND($F42<(P$2+7),$F42>P$2),1, IF(AND($H42<P$2+7,$H42>P$2),3, IF(AND($F42<=P$2, $H42>=P$2), 2, "" ))) | Q42: =IF(AND($F42<(Q$2+7),$F42>Q$2),1, IF(AND($H42<Q$2+7,$H42>Q$2),3, IF(AND($F42<=Q$2, $H42>=Q$2), 2, "" ))) | R42: =IF(AND($F42<(R$2+7),$F42>R$2),1, IF(AND($H42<R$2+7,$H42>R$2),3, IF(AND($F42<=R$2, $H42>=R$2), 2, "" ))) | S42: =IF(AND($F42<(S$2+7),$F42>S$2),1, IF(AND($H42<S$2+7,$H42>S$2),3, IF(AND($F42<=S$2, $H42>=S$2), 2, "" ))) | ... AQ42: =IF(AND($F42<(AQ$2+7),$F42>AQ$2),1, IF(AND($H42<AQ$2+7,$H42>AQ$2),3, IF(AND($F42<=AQ$2, $H42>=AQ$2), 2, "" )))
B43: Cold Commissioning | C43: 44012 | D43: 1 | E43: 44013 | F43: 44012 | G43: 1 | H43: 44013 | L43: =IF(AND($F43<(L$2+7),$F43>L$2),1, IF(AND($H43<L$2+7,$H43>L$2),3, IF(AND($F43<=L$2, $H43>=L$2), 2, "" ))) | M43: =IF(AND($F43<(M$2+7),$F43>M$2),1, IF(AND($H43<M$2+7,$H43>M$2),3, IF(AND($F43<=M$2, $H43>=M$2), 2, "" ))) | N43: =IF(AND($F43<(N$2+7),$F43>N$2),1, IF(AND($H43<N$2+7,$H43>N$2),3, IF(AND($F43<=N$2, $H43>=N$2), 2, "" ))) | O43: =IF(AND($F43<(O$2+7),$F43>O$2),1, IF(AND($H43<O$2+7,$H43>O$2),3, IF(AND($F43<=O$2, $H43>=O$2), 2, "" ))) | P43: =IF(AND($F43<(P$2+7),$F43>P$2),1, IF(AND($H43<P$2+7,$H43>P$2),3, IF(AND($F43<=P$2, $H43>=P$2), 2, "" ))) | Q43: =IF(AND($F43<(Q$2+7),$F43>Q$2),1, IF(AND($H43<Q$2+7,$H43>Q$2),3, IF(AND($F43<=Q$2, $H43>=Q$2), 2, "" ))) | R43: =IF(AND($F43<(R$2+7),$F43>R$2),1, IF(AND($H43<R$2+7,$H43>R$2),3, IF(AND($F43<=R$2, $H43>=R$2), 2, "" ))) | S43: =IF(AND($F43<(S$2+7),$F43>S$2),1, IF(AND($H43<S$2+7,$H43>S$2),3, IF(AND($F43<=S$2, $H43>=S$2), 2, "" ))) | ... AQ43: =IF(AND($F43<(AQ$2+7),$F43>AQ$2),1, IF(AND($H43<AQ$2+7,$H43>AQ$2),3, IF(AND($F43<=AQ$2, $H43>=AQ$2), 2, "" ))) -> 3
B44: Hot Commissioning | C44: 44013 | D44: 2 | E44: 44015 | F44: 44013 | G44: 2 | H44: 44015 | L44: =IF(AND($F44<(L$2+7),$F44>L$2),1, IF(AND($H44<L$2+7,$H44>L$2),3, IF(AND($F44<=L$2, $H44>=L$2), 2, "" ))) | M44: =IF(AND($F44<(M$2+7),$F44>M$2),1, IF(AND($H44<M$2+7,$H44>M$2),3, IF(AND($F44<=M$2, $H44>=M$2), 2, "" ))) | N44: =IF(AND($F44<(N$2+7),$F44>N$2),1, IF(AND($H44<N$2+7,$H44>N$2),3, IF(AND($F44<=N$2, $H44>=N$2), 2, "" ))) | O44: =IF(AND($F44<(O$2+7),$F44>O$2),1, IF(AND($H44<O$2+7,$H44>O$2),3, IF(AND($F44<=O$2, $H44>=O$2), 2, "" ))) | P44: =IF(AND($F44<(P$2+7),$F44>P$2),1, IF(AND($H44<P$2+7,$H44>P$2),3, IF(AND($F44<=P$2, $H44>=P$2), 2, "" ))) | Q44: =IF(AND($F44<(Q$2+7),$F44>Q$2),1, IF(AND($H44<Q$2+7,$H44>Q$2),3, IF(AND($F44<=Q$2, $H44>=Q$2), 2, "" ))) | R44: =IF(AND($F44<(R$2+7),$F44>R$2),1, IF(AND($H44<R$2+7,$H44>R$2),3, IF(AND($F44<=R$2, $H44>=R$2), 2, "" ))) | S44: =IF(AND($F44<(S$2+7),$F44>S$2),1, IF(AND($H44<S$2+7,$H44>S$2),3, IF(AND($F44<=S$2, $H44>=S$2), 2, "" ))) | ... AQ44: =IF(AND($F44<(AQ$2+7),$F44>AQ$2),1, IF(AND($H44<AQ$2+7,$H44>AQ$2),3, IF(AND($F44<=AQ$2, $H44>=AQ$2), 2, "" ))) -> 1
A45: 13 | B45: Handover | C45: 44020 | D45: 1 | E45: 44021 | F45: 44020 | G45: 1 | H45: 44021 | L45: =IF(AND($F45<(L$2+7),$F45>L$2),1, IF(AND($H45<L$2+7,$H45>L$2),3, IF(AND($F45<=L$2, $H45>=L$2), 2, "" ))) | M45: =IF(AND($F45<(M$2+7),$F45>M$2),1, IF(AND($H45<M$2+7,$H45>M$2),3, IF(AND($F45<=M$2, $H45>=M$2), 2, "" ))) | N45: =IF(AND($F45<(N$2+7),$F45>N$2),1, IF(AND($H45<N$2+7,$H45>N$2),3, IF(AND($F45<=N$2, $H45>=N$2), 2, "" ))) | O45: =IF(AND($F45<(O$2+7),$F45>O$2),1, IF(AND($H45<O$2+7,$H45>O$2),3, IF(AND($F45<=O$2, $H45>=O$2), 2, "" ))) | P45: =IF(AND($F45<(P$2+7),$F45>P$2),1, IF(AND($H45<P$2+7,$H45>P$2),3, IF(AND($F45<=P$2, $H45>=P$2), 2, "" ))) | Q45: =IF(AND($F45<(Q$2+7),$F45>Q$2),1, IF(AND($H45<Q$2+7,$H45>Q$2),3, IF(AND($F45<=Q$2, $H45>=Q$2), 2, "" ))) | R45: =IF(AND($F45<(R$2+7),$F45>R$2),1, IF(AND($H45<R$2+7,$H45>R$2),3, IF(AND($F45<=R$2, $H45>=R$2), 2, "" ))) | S45: =IF(AND($F45<(S$2+7),$F45>S$2),1, IF(AND($H45<S$2+7,$H45>S$2),3, IF(AND($F45<=S$2, $H45>=S$2), 2, "" ))) | ... AQ45: =IF(AND($F45<(AQ$2+7),$F45>AQ$2),1, IF(AND($H45<AQ$2+7,$H45>AQ$2),3, IF(AND($F45<=AQ$2, $H45>=AQ$2), 2, "" )))
A46: E | B46: PAYMENT MILESTONE 6: HANDOVER COMPLETE | C46: 44022 | D46: 1 | E46: 44025 | F46: 44022 | G46: 1 | H46: 44025
C47: 43831 | D47: These numbers are used to set the start and end dates on the Gantt Chart
C48: 44014

Sheet Compliance
B2: HSE
B4: Description | C4: Status | D4: Approved By | E4: Date | F4: Results / Comments
B5: NOC
B6: 7.1 Agreement
B7: 13.2 Agreement
B8: EE File
B9: Subbie File
B16: SSEG
B18: Description | C18: Status | D18: Approved By | E18: Date | F18: Results / Comments
B19: SSEG Application
B20: PTI
B21: Commissioning Approval

Sheet Revenue Tracking
B2: HIGH LEVEL PROJECT REVENUE TRACKING
D3: PLANNED | F3: ACTUAL | L3: FINANCIAL REVIEW | N3: TIMELINE REVIEW | R3: Allocated in 2024 | S3: Budgeted | T3: Acutal
B4: 1 | C4: Planned Revenue | D4: ='Project Plan'!E6 -> 1735813.3 | F4: =F21 -> 1776820.4 | L4: 1735813.3 | N4: Start Date | P4: Sales | R4: =GETPIVOTDATA("REVENUE RECOGNITION AMOUNT",'Finance - Revenue'!$A$3,"INVOICE RAISED DATE",DATE(2024,7,31))+GETPIVOTDATA("REVENUE RECOGNITION AMOUNT",'Finance - Revenue'!$A$3,"INVOICE RAISED DATE",DATE(2024,8,31)) -> 576833.44 | S4: 1158979.9 | T4: =F4-R4 -> 1199987
B5: 2 | C5: Planned Expenditure | D5: =+'Expenditure Tracking'!F5 -> 1461076.8 | F5: =+'Expenditure Tracking'!J5 -> 1332390.7 | L5: 1396689.4 | N5: 45577 | P5: COS | R5: =GETPIVOTDATA("Actual Total ",'Finance - COS'!$A$3,"INVOICE RAISED DATE",DATE(2024,7,31))+GETPIVOTDATA("Actual Total ",'Finance - COS'!$A$3,"INVOICE RAISED DATE",DATE(2024,8,31)) -> 462261.2 | S5: 926219.16 | T5: =F5-R5 -> 870129.54
B6: 3 | C6: Planned Profit | D6: =+D4-D5 -> 274736.57 | F6: =+F4-F5 -> 444429.71 | L6: 339123.95 | N6: End Date - PC | P6: GP | R6: =R4-R5 -> 114572.24 | S6: =S4-S5 -> 232760.74 | T6: =T4-T5 -> 329857.47
B7: 4 | C7: Planned Margin | D7: =+D6/D4 -> 0.15827541 | F7: =+F6/F4 -> 0.2501264 | L7: 0.19536891 | N7: 45632
B10: CONTRACT
B12: No. | C12: PAYMENT MILESTONE | E12: % | F12: VALUE | H12: PLANNED PAYMENT DATE | L12: INVOICE NUMBER | N12: INVOICE RAISED DATE | P12: PAYMENT RECEIVED DATE | R12: MILESTONE NOTES & COMMENTS
B13: 1 | C13: Acceptance and Initial Deposit | E13: 0.35 | F13: =$D$4*E13 -> 607534.67 | H13: 45491 | L13: 004471 | N13: 45488 | P13: 45490
B14: 2 | C14: Delivery of Inverters | E14: 0.25 | F14: =$D$4*E14 -> 433953.33 | H14: ='Project Plan'!E22+7 -> 45567 | L14: 004554 | N14: 45567 | P14: 45573
B15: 3 | C15: Delivery of Panels | E15: 0.25 | F15: =$D$4*E15 -> 433953.33 | H15: ='Project Plan'!E35+7 -> 45595 | L15: 004583 | N15: 45597 | P15: =N15+7 -> 45604
B16: 4 | C16: Practical Completion | E16: 0.1 | F16: =$D$4*E16 -> 173581.33 | H16: ='Project Plan'!E39+7 -> 45625 | L16: 004619 | N16: 45624 | P16: 45684
B17: 5 | C17: Handover | E17: 0.05 | F17: =$D$4*E17 -> 86790.667 | H17: ='Project Plan'!E50+7 -> 45652 | L17: 004692 | N17: 45714 | P17: 45946
B18: 6 | C18: VO - Walkways | E18: 0 | F18: ='Expenditure Breakdown'!R65+'Expenditure Breakdown'!R66+'Expenditure Breakdown'!R67 -> 49914.42 | L18: 004619 | N18: 45624 | P18: =P16 -> 45684
B19: 7 | C19: Credit Note - Walk ways | E19: 0 | F19: -8907.31 | L19: 004931 | N19: 46045 | P19: 46053
E21: =SUM(E13:E19) -> 1 | F21: =SUM(F13:F19) -> 1776820.4
B23: KEY: | C23: contains an error (in result or a check has failed)
C24: Red Font - IF TEXT : content not yet confirmed
C25: Red Font - IF NUMBER: Negative value
C26: Anything in yellow is a concern or risk for noting or action
C27: confirmed
C28: [ADD INITIALS: comment for noting in square brackets, use colour or red to draw attention if important]
C29: [RT: When adding rows into sheet, ensure you insert between first and last row of each category]
C30: end of sheet - do not insert information below/beyond this
B40: No. | C40: PAYMENT MILESTONE | E40: % | F40: VALUE
B41: 1 | C41: Deposit - Project commencement | E41: 0.35 | F41: =$F$47*E41 -> 621887.16
B42: 2 | C42: Delivery of Panels | E42: 0.3 | F42: =$F$47*E42 -> 533046.13
B43: 3 | C43: Delivery of Inverters | E43: 0.2 | F43: =$F$47*E43 -> 355364.09
B44: 4 | C44: Practical Completion | E44: 0.1 | F44: =$F$47*E44 -> 177682.04
B45: 5 | C45: Handover | E45: 0.05 | F45: =$F$47*E45 -> 88841.022
C46: Total | E46: =SUM(E41:E45) -> 1 | F46: =SUM(F41:F45) -> 1776820.4
E47: =SUM(E41:E45) -> 1 | F47: =F21 -> 1776820.4

Sheet Project Plan
N1: 45943 | O1: 45943
C2: PROJECT PLAN | E2: SA Metal - 20 Christiaan | N2: 0 | O2: 1
C3: PROJECT SIZE (kWp) | E3: 148
C4: BUSINESS DEVELOPER | E4: Peet
C5: PROJECT MANAGER | E5: Lloyd
C6: CONTRACT VALUE | E6: 1735813.3
C7: Phase: | E7: Compliance Handover
B8: No. | C8: HIGH LEVEL PROGRAMME | E8: Planned Start | F8: Duration (days) | G8: Planned End | I8: Actual Start | J8: Duration (days) | K8: Actual End | M8: Status | O8: Comment
F9: 64 | J9: 65 | M9: 1 | N9: 1
B11: 1 | C11: Project Initiation | E11: 45518 | F11: 37 | G11: 45555 | I11: 45518 | J11: 37 | K11: 45555 | M11: 1 | N11: 1
B12: 1.1 | C12: BD Handover | E12: 45518 | F12: 1 | G12: 45519 | I12: 45518 | J12: 1 | K12: 45519 | M12: 1 | N12: 1
B13: 1.2 | C13: Project Introduction | E13: 45540 | F13: 1 | G13: 45541 | I13: 45540 | J13: 1 | K13: 45541 | M13: 1 | N13: 1
B14: 1.3 | C14: HSE | E14: 45540 | F14: 15 | G14: 45555 | I14: 45540 | J14: 15 | K14: 45555 | M14: 1 | N14: 1
B15: 1.4 | C15: Installer Kick Off | E15: 45548 | F15: 1 | G15: 45551 | I15: 45548 | J15: 1 | K15: 45551 | M15: 1 | N15: 1
B16: 1.5 | C16: Project Review | E16: 45547 | F16: 1 | G16: 45548 | I16: 45547 | J16: 1 | K16: 45548 | M16: 1 | N16: 1
B18: 2 | C18: Site Establishment | E18: 45560 | F18: 1 | G18: 45561 | I18: 45560 | J18: 1 | K18: 45561 | M18: 1 | N18: 1
B19: 2.1 | C19: Installer on site & Roof Assessment | E19: 45560 | F19: 1 | G19: 45561 | I19: 45560 | J19: 1 | K19: 45561 | M19: 1 | N19: 1
B21: 3 | C21: AC Installation | E21: 45586 | F21: 32 | G21: 45618 | I21: 45586 | J21: 32 | K21: 45618 | M21: 1 | N21: 1
B22: 3.1 | C22: Inverters delivered | E22: 45560 | F22: 1 | G22: 45561 | I22: 45565 | J22: 1 | K22: 45566 | M22: 1 | N22: 1
B23: 3.2 | C23: Inverters Mounted | E23: 45561 | F23: 1 | G23: 45562 | I23: 45566 | J23: 1 | K23: 45567 | M23: 1 | N23: 1
B24: 3.3 | C24: Solar DB lead time | E24: 45560 | F24: 30 | G24: 45602 | I24: 45560 | J24: 30 | K24: 45602 | M24: 1 | N24: 1
B25: 3.4 | C25: AC Works | E25: 45561 | F25: 10 | G25: 45575 | I25: 45566 | J25: 10 | K25: 45580 | M25: 1 | N25: 1
B26: 3.5 | C26: AC Tie - in | E26: 45569 | F26: 1 | G26: 45572 | I26: 45574 | J26: 1 | K26: 45575 | M26: 1 | N26: 1
B28: 4 | C28: DC Works | E28: 45575 | F28: 42 | G28: 45617 | I28: 45575 | J28: 42 | K28: 45617 | M28: 1 | N28: 1
B29: 4.1 | C29: Mounting Structure delivered | E29: 45575 | F29: 1 | G29: 45576 | I29: 45575 | J29: 1 | K29: 45576 | M29: 1 | N29: 1
B30: 4.2 | C30: Mounting Structure installation | E30: 45575 | F30: 8 | G30: 45587 | I30: 45575 | J30: 8 | K30: 45587 | M30: 1 | N30: 1
B31: 4.3 | C31: DC Cable delivered | E31: 45575 | F31: 1 | G31: 45576 | I31: 45575 | J31: 1 | K31: 45576 | M31: 1 | N31: 1
B32: 4.3 | C32: DC Stringing | E32: 45608 | F32: 5 | G32: 45615 | I32: 45608 | J32: 5 | K32: 45615 | M32: 1 | N32: 1
B34: 5 | C34: Module installation | E34: 45588 | F34: 29 | G34: 45617 | I34: 45588 | J34: 29 | K34: 45617 | M34: 1 | N34: 1
B35: 5.1 | C35: Module delivery | E35: 45588 | F35: 1 | G35: 45589 | I35: 45588 | J35: 1 | K35: 45589 | M35: 1 | N35: 1
B36: 5.2 | C36: Module mounting | E36: 45587 | F36: 15 | G36: 45608 | I36: 45587 | J36: 15 | K36: 45608 | M36: 1 | N36: 1
B38: 6 | C38: Commissioning | E38: 45618 | F38: 7 | G38: 45625 | I38: 45622 | J38: 3 | K38: 45625 | M38: 1 | N38: 1
B39: 6.1 | C39: Commissioning | E39: 45618 | F39: 1 | G39: 45621 | I39: 45621 | J39: 1 | K39: 45622 | M39: 1 | N39: 1
B40: 6.2 | C40: Practical Completion | E40: 45618 | F40: 4 | G40: 45624 | I40: 45621 | J40: 4 | K40: 45625 | M40: 1 | N40: 1
B42: 7 | C42: QA Inspections | E42: 45625 | F42: 11 | G42: 45636 | I42: 45625 | J42: 11 | K42: 45636 | M42: 1 | N42: 1
B43: 7.1 | C43: Red-Team Inspection | E43: 45624 | F43: 3 | G43: 45629 | I43: 45625 | J43: 3 | K43: 45630 | M43: 1 | N43: 1
B45: 8 | C45: Project Closure | E45: 45633 | F45: 53 | G45: 45686 | I45: 45633 | J45: 53 | K45: 45686 | M45: 1 | N45: 1
B46: 8.1 | C46: Equipment serial numbers | E46: 45629 | F46: 1 | G46: 45630 | I46: 45630 | J46: 1 | K46: 45631 | M46: 1 | N46: 1
B47: 8.2 | C47: Snags completion | E47: 45630 | F47: 5 | G47: 45637 | I47: 45631 | J47: 33 | K47: 45681 | M47: 1 | N47: 1
B48: 8.3 | C48: System Performance Monitoring | E48: 45637 | F48: 5 | G48: 45645 | I48: 45638 | J48: 5 | K48: 45646 | M48: 1 | N48: 1
B49: 8.4 | C49: Handover documentation | E49: 45637 | F49: 5 | G49: 45645 | I49: 45638 | J49: 5 | K49: 45646 | M49: 1 | N49: 1
B50: 8.5 | C50: Handover to Client | E50: 45645 | F50: 1 | G50: 45646 | I50: 45708 | J50: 1 | K50: 45898 | M50: 1 | N50: 1
B51: 8.6 | C51: Handover to Matriarch | E51: 45626 | F51: 1 | G51: 45628 | I51: 45776 | J51: 1 | K51: 45777 | M51: 1 | N51: 1

Sheet Data
C2: Public holidays | F2: Drop down list
C3: 45292 | D3: New Years Day | F3: Approved
C4: 45372 | D4: Human Rights day | F4: Pending
C5: 45380 | D5: Good Friday | F5: Declined
C6: 45383 | D6: Family Day | F6: Abanded
C7: 45413 | D7: Workers day
C8: 45460 | D8: Youth Day Holiday
C9: 45513 | D9: Womens Day
C10: 45559 | D10: Heritage Day
C11: 45642 | D11: Day of Reconciliation
C12: 45651 | D12: Christmas Day
C13: 45652 | D13: Day of Goodwill | H13: Manual dates

Sheet Expenditure Tracking
B2: HIGH LEVEL PROJECT EXPENDITURE TRACKING
F4: COSTED | H4: PLANNED | J4: ACTUAL | L4: Difference from costed | N4: Difference from planned
B5: EXPENDITURE | F5: =SUM(F9:F23) -> 1461076.8 | H5: =SUM(H9:H23) -> 1396689.4 | J5: =SUM(J9:J23) -> 1332390.7 | L5: =SUM(L9:L23) -> 128686.03 | N5: =SUM(N9:N23) -> 64298.647
B7: No. | D7: Item | F7: Costed Expenditure | H7: Planned Expenditure | J7: Actual Expenditure | L7: Saving / Overrun | N7: Saving / Overrun | P7: Comments on variations from planned expenditure
B9: ='Expenditure Breakdown'!B6 -> 1 | D9: ='Expenditure Breakdown'!C6 -> Panels | F9: ='Expenditure Breakdown'!J6 -> 461154.35 | H9: 476456.5 | J9: ='Expenditure Breakdown'!X6 -> 384202.5 | L9: =F9-J9 -> 76951.85 | N9: =H9-J9 -> 92254
B10: ='Expenditure Breakdown'!B13 -> 2 | D10: ='Expenditure Breakdown'!C13 -> Inverters | F10: =+'Expenditure Breakdown'!J13 -> 118044 | H10: 121107 | J10: =+'Expenditure Breakdown'!X13 -> 115325.23 | L10: =F10-J10 -> 2718.77 | N10: =H10-J10 -> 5781.77
B11: ='Expenditure Breakdown'!B18 -> 3 | D11: ='Expenditure Breakdown'!C18 -> Mounting Structures | F11: =+'Expenditure Breakdown'!J18 -> 66690 | H11: 29643.2 | J11: =+'Expenditure Breakdown'!X18 -> 22391.32 | L11: =F11-J11 -> 44298.68 | N11: =H11-J11 -> 7251.88
B12: ='Expenditure Breakdown'!B24 -> 4 | D12: ='Expenditure Breakdown'!C24 -> DC Equipment | F12: =+'Expenditure Breakdown'!J24 -> 109793.5 | H12: 133412 | J12: =+'Expenditure Breakdown'!X24 -> 125312 | L12: =F12-J12 -> -15518.5 | N12: =H12-J12 -> 8100
B13: ='Expenditure Breakdown'!B35 -> 5 | D13: ='Expenditure Breakdown'!C35 -> Monitoring | F13: =+'Expenditure Breakdown'!J35 -> 49000 | H13: 80520.5 | J13: =+'Expenditure Breakdown'!X35 -> 107002.01 | L13: =F13-J13 -> -58002.01 | N13: =H13-J13 -> -26481.51
B14: ='Expenditure Breakdown'!B42 -> 6 | D14: ='Expenditure Breakdown'!C42 -> AC Equipment | F14: =+'Expenditure Breakdown'!J42 -> 257521.38 | H14: 158246 | J14: =+'Expenditure Breakdown'!X42 -> 158246 | L14: =F14-J14 -> 99275.38 | N14: =H14-J14 -> 0
B15: ='Expenditure Breakdown'!B56 -> 7 | D15: ='Expenditure Breakdown'!C56 -> Battery Systems | F15: =+'Expenditure Breakdown'!J56 -> 0 | H15: 0 | J15: ='Expenditure Breakdown'!X56 -> 0 | L15: =F15-J15 -> 0 | N15: =H15-J15 -> 0
B16: ='Expenditure Breakdown'!B65 -> 8 | D16: ='Expenditure Breakdown'!C65 -> Product Add On | F16: ='Expenditure Breakdown'!J65 -> 0 | H16: 0 | J16: ='Expenditure Breakdown'!X65 -> 83299.38 | L16: =F16-J16 -> -83299.38 | N16: =H16-J16 -> -83299.38
B17: ='Expenditure Breakdown'!M72 -> 9 | D17: ='Expenditure Breakdown'!C72 -> AC & DC Installation | F17: =+'Expenditure Breakdown'!J72 -> 123500 | H17: 103690 | J17: =+'Expenditure Breakdown'!X72 -> 103690 | L17: =F17-J17 -> 19810 | N17: =H17-J17 -> 0
B18: ='Expenditure Breakdown'!B81 -> 10 | D18: ='Expenditure Breakdown'!C81 -> Site Logistics | F18: =+'Expenditure Breakdown'!J81 -> 31594.3 | H18: 110446 | J18: =+'Expenditure Breakdown'!X81 -> 93158.2 | L18: =F18-J18 -> -61563.9 | N18: =H18-J18 -> 17287.8
B19: ='Expenditure Breakdown'!B93 -> 11 | D19: ='Expenditure Breakdown'!C93 -> Due Dilligence | F19: ='Expenditure Breakdown'!J93 -> 89000 | H19: 23020 | J19: ='Expenditure Breakdown'!X93 -> 11867.62 | L19: =F19-J19 -> 77132.38 | N19: =H19-J19 -> 11152.38
B20: ='Expenditure Breakdown'!B101 -> 12 | D20: ='Expenditure Breakdown'!C101 -> BDP Commission | F20: ='Expenditure Breakdown'!G99 -> 48482.92 | H20: 48482.92 | J20: ='Expenditure Breakdown'!X99 -> 48482.92 | L20: =F20-J20 -> 0 | N20: =H20-J20 -> 0
B21: ='Expenditure Breakdown'!B103 -> 13 | D21: ='Expenditure Breakdown'!C103 -> Engineering | F21: =+'Expenditure Breakdown'!J103 -> 103846.32 | H21: 109215.27 | J21: =+'Expenditure Breakdown'!X103 -> 72067.67 | L21: =F21-J21 -> 31778.65 | N21: =H21-J21 -> 37147.597 | P21: RV: Matriarch defects percentage 1.25%
B22: ='Expenditure Breakdown'!B111 -> 14 | D22: ='Expenditure Breakdown'!C111 -> General Expenses | F22: =+'Expenditure Breakdown'!J111 -> 2450 | H22: 2450 | J22: =+'Expenditure Breakdown'!X111 -> 7345.89 | L22: =F22-J22 -> -4895.89 | N22: =H22-J22 -> -4895.89
B23: ='Expenditure Breakdown'!B120 -> 15 | D23: ='Expenditure Breakdown'!C120 -> Service Add On | F23: =+'Expenditure Breakdown'!J120 -> 0 | H23: 0 | J23: =+'Expenditure Breakdown'!X120 -> 0 | L23: =F23-J23 -> 0 | N23: =H23-J23 -> 0
D25: check: | F25: ='Expenditure Breakdown'!J2-'Expenditure Tracking'!F5 -> 0 | G25: ='Expenditure Breakdown'!#REF!-G5 -> #REF! | H25: ='Expenditure Breakdown'!X2-J5 -> 0 | I25: ='Expenditure Breakdown'!#REF!-I5 -> #REF! | J25: ='Expenditure Breakdown'!X2-J5 -> 0
A27: Copy amounts in column H and paste as values at Project review.

Sheet Expenditure Breakdown
B2: COSTED EXPENDITURE BREAKDOWN | J2: =SUM(J6:J124) -> 1461076.8 | K2: =SUM(K6:K124) -> 1735813.3 | M2: ACTUAL EXPENDITURE BREAKDOWN | S2: FINANCE ONLY | X2: =SUM(X6:X124) -> 1332390.7
B4: No. | C4: Product / Service | D4: Description of Work | E4: QTY | F4: Rate / Unit | G4: Budget Total | H4: Project Related date | J4: Total COS | K4: =IF(K2-'Revenue Tracking'!D4>=0, "Total Revenue", "ERROR on REV" ) -> Total Revenue | M4: No. | N4: Product/ Service | O4: Description of Work | P4: QTY | Q4: Rate / Unit | R4: Actual Total | S4: INVOICE NUMBER | T4: INVOICE RAISED DATE | U4: REVENUE RECOGNITION AMOUNT | V4: CHECK | W4: FINANCE PAYMENT DATE | X4: Total COS | Y4: PO NUMBER | Z4: COMMENTS
B6: 1 | C6: Panels | D6: Longi 570W - Costing Sheet | E6: 260 | F6: 1696.7475 | G6: =E6*F6 -> 441154.35 | H6: ='Project Plan'!E35+60 -> 45648 | J6: =SUM(G6:G11) -> 461154.35 | K6: 576442.94 | M6: 1 | N6: 1. Panels | O6: Canadian Solar 555W - Deposit - Herholdts | P6: 266 | Q6: 1415.25 | R6: =P6*Q6*0.5 -> 188228.25 | S6: Herholdts Inv: INV875402 | T6: 45504 | U6: 260538.24 | V6: =K6-SUM(U6:U11) -> 0.0026437702 | W6: 45562 | X6: =SUM(R6:R11) -> 384202.5 | Y6: PO3244-SAM-20240719 - RV Approved | AA6: 19
B7: 1 | D7: Jinko Solar 575W | M7: 1 | N7: 1. Panels | R7: =P6*Q6*0.5 -> 188228.25 | S7: Herholdts Inv: INV875402 | T7: 45504 | U7: 260538.24 | W7: 45596 | AA7: BUDGET | AB7: Installer Allocation
B8: 1 | M8: 1 | N8: 1. Panels | O8: Handling Fee | R8: 800 | S8: Supply Chain: Inv SCO04502 | T8: 45596 | U8: 1200.2898 | W8: 45625 | AA8: AC Equipment | AB8: =C48 -> 257521.38
B9: 1 | D9: Delivery | G9: 20000 | H9: =H6 -> 45648 | M9: 1 | N9: 1. Panels | O9: Delivery | R9: 5650 | S9: Supply Chain: Inv SCO04533 | T9: 45596 | U9: 8477.0469 | W9: 45625 | AA9: DC Equipment | AB9: =SUM(G26:G33) -> 50273.5
B10: 1 | M10: 1 | N10: 1. Panels | O10: Storage | R10: 1296 | S10: Supply Chain: Inv SCO04502 | T10: 45596 | U10: 45689.11 | W10: 45625 | AA10: AC Labour | AB10: =C74 -> 86450
B11: 1 | M11: 1 | N11: 1. Panels | O11: Storage and delivery budget | U11: =(R11/$X$6*$K$6) -> 0 | AA11: DC Labour | AB11: =C73 -> 37050
AA12: Offloading | AB12: =G88 -> 8500
B13: 2 | C13: Inverters | D13: Huawei 100KTL | E13: 1 | F13: 78898 | G13: =E13*F13 -> 78898 | H13: ='Project Plan'!E22+30 -> 45590 | J13: =SUM(G13:G16) -> 118044 | K13: 147555 | M13: 2 | N13: 2. Inverters | O13: Huawei 100KTL | P13: 1 | Q13: 68870 | R13: =P13*Q13 -> 68870 | S13: Kathea Inv 518635 | T13: 45565 | U13: 88116.996 | V13: =K13-SUM(U13:U16) -> 0 | W13: 45596 | X13: =SUM(R13:R16) -> 115325.23 | Z13: MI: Kathea quote | AA13: Telehandler | AB13: =G81 -> 0
B14: 2 | D14: Huawei 50KTL | E14: 1 | F14: 39146 | G14: =E14*F14 -> 39146 | H14: =H13 -> 45590 | M14: 2 | N14: 2. Inverters | O14: Huawei 50KTL | P14: 1 | Q14: 45350 | R14: =P14*Q14 -> 45350 | S14: Kathea Inv518655 | T14: 45596 | U14: 58023.897 | W14: 45596 | Z14: MI: Kathea quote | AA14: Storage | AB14: =G89 -> 0
B15: 2 | M15: 2 | N15: 2. Inverters | O15: Delivery | R15: 1105.23 | S15: Kathea Inv 518635 | T15: 45565 | U15: 1414.107 | W15: =W13 -> 45596 | AA15: =D91 -> Scaffolding | AB15: =G91 -> 23094.3
B16: 2 | M16: 2 | N16: 2. Inverters | U16: =(R16/$X$13*$K$13) -> 0 | AA16: Other | AB16: 0
AA17: Total | AB17: =SUM(AB8:AB16) -> 462889.18
B18: 3 | C18: Mounting Structures | D18: KlipLok Roof | E18: ='Project Plan'!E3*1000 -> 148000 | F18: 0.45 | G18: 66690 | H18: ='Project Plan'!E19+30 -> 45590 | J18: =SUM(G18:G22) -> 66690 | K18: 83362.5 | M18: 3 | N18: 3. Mounting Structures | O18: KlipLok Roof | P18: 1 | Q18: 27793.2 | R18: =P18*Q18 -> 27793.2 | S18: Schletter INV0895 | T18: 45565 | U18: 78159.937 | V18: =K18-SUM(U18:U22) -> 0 | W18: 45558 | X18: =SUM(R18:R22) -> 22391.32 | Y18: PO3363-SAM20-20240918 - RV Approved | AA18: Less 15% | AB18: =+AB17*0.85 -> 393455.8
B19: 3 | M19: 3 | N19: 3. Mounting Structures | R19: 9567 | S19: SCHLETTER - INV1081 | T19: 45626 | U19: 0 | W19: 45645 | Z19: TC: Added cost for Extra MS and freight | AA19: R/Wp | AB19: =+AB18/'Project Plan'!$E$3/1000 -> 2.6584852
B20: 3 | M20: 3 | N20: 3. Mounting Structures | O20: Delivery | R20: 1850 | S20: Schletter Inv0893 | T20: 45565 | U20: 5202.5633 | W20: =W18 -> 45558
M21: 3 | N21: 3. Mounting Structures | O21: Schletter Credit: MS | R21: -16818.88 | S21: Schletter Credit Note: CRN0159 | T21: 45626 | U21: 0 | W21: 45645
B22: 3 | M22: 3 | N22: 3. Mounting Structures | U22: =(R22/$X$18*$K$18) -> 0 | AA22: ACTUAL - Cosmic Sun | AB22: Installer Price | AD22: ACTUAL - Thula Moya | AE22: Installer Price | AG22: ACTUAL - CornerStone | AH22: Installer Price
AA23: AC Equipment | AB23: 69800 | AD23: AC Equipment | AE23: 95446 | AG23: AC Equipment | AH23: =38489.54+3612.4 -> 42101.94 | AI23: * Excluded R25976,34 for Comms and metering
B24: 4 | C24: DC Equipment | D24: DC Cable | E24: 2345 | F24: 16 | G24: =E24*F24 -> 37520 | H24: ='Project Plan'!E31+30 -> 45605 | J24: =SUM(G24:G33) -> 109793.5 | K24: 137241.88 | M24: 4 | N24: 4. DC Equipment | O24: DC Cable | P24: 3000 | Q24: 13.5 | R24: =P24*Q24 -> 40500 | S24: Herholdts Inv: INV922149 | T24: 45596 | U24: 44355.656 | V24: =K24-SUM(U24:U33) -> 0 | W24: 45596 | X24: =SUM(R24:R33) -> 125312 | Y24: PO3315-MUL-20240823 - RV Approved | Z24: MI: Herholdts quote | AA24: DC Equipment | AB24: 61872.4 | AD24: DC Equipment | AE24: 84812 | AG24: DC Equipment | AH24: 70901.16
B25: 4 | D25: DC Surge Arrestor | E25: 4 | F25: 5500 | G25: =E25*F25 -> 22000 | H25: =H26 -> 45618 | M25: 4 | N25: 4. DC Equipment | O25: Delivery | U25: =(R25/$X$24*$K$24) -> 0 | AA25: AC Labour | AB25: 37000 | AD25: AC Labour | AE25: 37034 | AG25: AC Labour | AH25: 15154.29
B26: 4 | D26: DC Cable Tray | E26: 140 | F26: 130 | G26: =E26*F26 -> 18200 | H26: ='Project Plan'!E34+30 -> 45618 | M26: 4 | N26: 4. DC Equipment | O26: Project Kick Off | P26: =AE24 -> 84812 | Q26: 0.1 | R26: =$P$26*Q26 -> 8481.2 | S26: Thula Moya INV IN04448 | T26: 45565 | U26: 9288.6219 | W26: =W72 -> 45582 | Y26: PO3378-SAM20-20240930 - RV Approved | AA26: DC Labour | AB26: 89500 | AC26: =SUM(AB25:AB26)/148000 -> 0.85472973 | AD26: DC Labour | AE26: 66656 | AF26: =SUM(AE25:AE26)/148000 -> 0.70060811 | AG26: DC Labour | AH26: 124563.28 | AI26: =SUM(AH25:AH26)/148000 -> 0.94403764
B27: 4 | D27: Earth Cable | E27: =E24 -> 2345 | F27: 13.5 | G27: =E27*F27 -> 31657.5 | H27: =H18 -> 45590 | M27: 4 | N27: 4. DC Equipment | O27: Site Establishment | Q27: 0.15 | R27: =P26*Q27 -> 12721.8 | S27: Thula Moya IN0449 | T27: 45596 | U27: 13932.933 | W27: =W73 -> 45582 | AA27: Offloading | AB27: 8500 | AD27: Site Logistics | AE27: 35954 | AG27: Site Logistics | AH27: =54896.4+15381.6 -> 70278
B28: 4 | D28: Earth clamp | E28: 26 | F28: 16 | G28: =E28*F28 -> 416 | H28: ='Project Plan'!E35 -> 45588 | M28: 4 | N28: 4. DC Equipment | O28: AC Installation Complete | Q28: 0.2 | R28: =$P$26*Q28 -> 16962.4 | S28: Thula Moya IN04519 | T28: =T74 -> 45626 | U28: 18577.244 | W28: 45625 | AA28: Roof Access | AB28: 15000 | AD28: Sundries | AE28: 11544 | AG28: HSE | AH28: 7027.8
B29: 4 | M29: 4 | N29: 4. DC Equipment | O29: DC Installation Complete | Q29: 0.25 | R29: =$P$26*Q29 -> 21203 | S29: =S75 -> Thula Moya IN04520 | T29: =T75 -> 45626 | U29: 23221.555 | W29: 45625 | AA29: Container | AB29: 0 | AD29: Accomodation | AE29: 40322 | AG29: COC | AH29: 3978
B30: 4 | M30: 4 | N30: 4. DC Equipment | O30: Commissioning Complete | Q30: 0.1 | R30: =$P$26*Q30 -> 8481.2 | S30: =S76 -> Thula Moya IN04521 | T30: =T76 -> 45626 | U30: 9288.6219 | W30: =W76 -> 45701 | AA30: HSE | AB30: 4500 | AD30: Scaffolding | AE30: 0 | AG30: Travel | AH30: 14818.05
B31: 4 | M31: 4 | N31: 4. DC Equipment | O31: Site De-establisment | Q31: 0.1 | R31: =$P$26*Q31 -> 8481.2 | S31: Thula Moya IN04537 | T31: =T77 -> 45626 | U31: 9288.6219 | W31: =W77 -> 45631 | AA31: Other | AB31: 0 | AD31: Other | AE31: 0 | AG31: Other | AH31: 0
B32: 4 | M32: 4 | N32: 4. DC Equipment | O32: Handover Document Complete | Q32: 0.05 | R32: =$P$26*Q32 -> 4240.6 | S32: Thula Moya IN04538 | T32: =T78 -> 45626 | U32: 4644.311 | W32: =W78 -> 45701 | AA32: Other | AB32: 0 | AD32: Other | AE32: 0 | AG32: Other | AH32: 0
B33: 4 | M33: 4 | N33: 4. DC Equipment | O33: End of Defects Period | Q33: 0.05 | R33: =$P$26*Q33 -> 4240.6 | S33: Thula Moya IN04594 | T33: =T79 -> 45688 | U33: 4644.311 | W33: =W79 -> 45722 | AA33: Other | AB33: 0 | AD33: Other | AE33: 0 | AG33: Other | AH33: 0
T34: =IF(W34>1,EOMONTH(W34,-1),"") | AA34: Total | AB34: =SUM(AB23:AB33) -> 286172.4 | AD34: Total | AE34: =SUM(AE23:AE33) -> 371768 | AG34: Total | AH34: =SUM(AH23:AH33) -> 348822.52
B35: 5 | C35: Monitoring | D35: Smartlogger 3000 | E35: 1 | F35: 26000 | G35: =F35*E35 -> 26000 | H35: =H13 -> 45590 | J35: =SUM(G35:G40) -> 49000 | K35: 61250 | M35: 5 | N35: 5. Monitoring | O35: Smartlogger 3000 | P35: 1 | Q35: 8000 | R35: =Q35*P35 -> 8000 | S35: Solarworld SASIV-24-00517 | T35: 45535 | U35: 6085.4068 | V35: =K35-SUM(U35:U40) -> -0.0049190076 | W35: 45561 | X35: =SUM(R35:R40) -> 107002.01 | Z35: MI: Kathea quote | AA35: R/Wp | AB35: =AB34/'Project Plan'!$E$3/1000 -> 1.9335973 | AD35: R/Wp | AE35: =AE34/'Project Plan'!$E$3/1000 -> 2.5119459 | AG35: R/Wp | AH35: =AH34/'Project Plan'!$E$3/1000 -> 2.3569089
B36: 5 | D36: Comms DB | G36: 8000 | H36: =H35 -> 45590 | M36: 5 | N36: 5. Monitoring | O36: CTs | R36: 13770.5 | S36: AccuEnergy ASAI-003743 | T36: 45535 | U36: 10474.887 | W36: 45562
B37: 5 | D37: Revenue Grade Meter | E37: 1 | F37: 15000 | G37: =F37*E37 -> 15000 | H37: ='Project Plan'!G51 -> 45628 | M37: 5 | N37: 5. Monitoring | O37: Revenue Grade Meter | P37: 1 | Q37: 11169 | R37: =Q37*P37 -> 11169 | S37: MATRIARCH - INV-3278 | T37: 45626 | U37: 3168.69 | W37: 45626
B38: 5 | M38: 5 | N38: 5. Monitoring | O38: SCADA | R38: 35750 | S38: Rubicon INVWCRE-0060133 | T38: 45535 | U38: 27194.162 | W38: 45562
B39: 5 | M39: 5 | N39: 5. Monitoring | O39: Frontline Comms Equipment | R39: =12812.55/5 -> 2562.51 | S39: Frontline Electrical: INV697940 | T39: 45596 | U39: 14326.86 | W39: 45575 | Y39: PO3387-SAM-20241007 - RV Approved | Z39: PO split across the portfolio
B40: 5 | M40: 5 | N40: 5. Monitoring | O40: DNP3 Controller | R40: 35750 | S40: Rubicon INVWCRE-0062783 | T40: 45626 | U40: 0 | W40: 45666 | Y40: PO3476-SAM20-20241122 - RV Approved
T41: =IF(W41>1,EOMONTH(W41,-1),"")
B42: 6 | C42: AC Equipment | J42: =SUM(G42:G54) -> 257521.38 | K42: 321901.73 | M42: 6 | N42: 6. AC Equipment | T42: =IF(W42>1,EOMONTH(W42,-1),"") | U42: =(R42/$X$42*$K$42) -> 0 | V42: =K42-SUM(U42:U54) -> 0 | X42: =SUM(R42:R54) -> 158246
M43: 6 | N43: 6. AC Equipment | O43: AC & Comms Board - Deposit | P43: 0.4 | Q43: 62800 | R43: =P43*Q43 -> 25120 | S43: Cosmic Sun CS_SAMPVDB_001 | T43: 45565 | U43: 51098.741 | W43: 45568 | Y43: PO3375-SAMPort-20240930 - RV Approved
M44: 6 | N44: 6. AC Equipment | O44: AC & Comms Board - Balance | P44: 0.6 | R44: =Q43*P44 -> 37680 | S44: Cosmic Sun CS_SAMPVDB_002 | T44: 45596 | U44: =(R44/$X$42*$K$42) -> 76648.112 | W44: 45596
M45: 6 | N45: 6. AC Equipment | U45: =(R45/$X$42*$K$42) -> 0
M46: 6 | N46: 6. AC Equipment | T46: =T71 | U46: =(R46/$X$42*$K$42) -> 0
B47: 6 | D47: Project Kick Off | F47: 0.1 | G47: =$C$48*F47 -> 25752.138 | H47: =H78 -> 45645 | M47: 6 | N47: 6. AC Equipment | O47: Project Kick Off | P47: =AE23 -> 95446 | Q47: 0.1 | R47: =$P$47*Q47 -> 9544.6 | S47: Thula Moya INV IN04448 | T47: 45565 | U47: 19415.488 | W47: =W72 -> 45582 | Y47: PO3378-SAM20-20240930 - RV Approved
B48: 6 | C48: 257521.38 | D48: Site Establishment | F48: 0.15 | G48: =$C$48*F48 -> 38628.207 | H48: =H73 -> 45560 | M48: 6 | N48: 6. AC Equipment | O48: Site Establishment | Q48: 0.15 | R48: =P47*Q48 -> 14316.9 | S48: Thula Moya IN0449 | T48: =T73 -> 45596 | U48: 29123.231 | W48: =W73 -> 45582
B49: 6 | D49: AC Installation Complete | F49: 0.2 | G49: =$C$48*F49 -> 51504.276 | H49: =H74 -> 45618 | M49: 6 | N49: 6. AC Equipment | O49: AC Installation Complete | Q49: 0.2 | R49: =$P$47*Q49 -> 19089.2 | S49: Thula Moya IN04519 | T49: =T74 -> 45626 | U49: 38830.975 | W49: 45625
B50: 6 | D50: DC Installation Complete | F50: 0.25 | G50: =$C$48*F50 -> 64380.345 | H50: =H75 -> 45617 | M50: 6 | N50: 6. AC Equipment | O50: DC Installation Complete | Q50: 0.25 | R50: =$P$47*Q50 -> 23861.5 | S50: =S75 -> Thula Moya IN04520 | T50: =T75 -> 45626 | U50: 48538.719 | W50: 45625
B51: 6 | D51: Commissioning Complete | F51: 0.1 | G51: =$C$48*F51 -> 25752.138 | H51: =H76 -> 45625 | M51: 6 | N51: 6. AC Equipment | O51: Commissioning Complete | Q51: 0.1 | R51: =$P$47*Q51 -> 9544.6 | S51: Thula Moya IN04521 | T51: =T76 -> 45626 | U51: 19415.488 | W51: =W76 -> 45701
B52: 6 | D52: Site De-establisment | F52: 0.1 | G52: =$C$48*F52 -> 25752.138 | H52: =H77 -> 45637 | M52: 6 | N52: 6. AC Equipment | O52: Site De-establisment | Q52: 0.1 | R52: =$P$47*Q52 -> 9544.6 | S52: Thula Moya IN04537 | T52: =T77 -> 45626 | U52: 19415.488 | W52: =W77 -> 45631
B53: 6 | D53: Handover Document Complete | F53: 0.05 | G53: =$C$48*F53 -> 12876.069 | H53: =H78 -> 45645 | M53: 6 | N53: 6. AC Equipment | O53: Handover Document Complete | Q53: 0.05 | R53: =$P$47*Q53 -> 4772.3 | S53: Thula Moya IN04538 | T53: =T78 -> 45626 | U53: 9707.7438 | W53: =W78 -> 45701
B54: 6 | D54: End of Defects Period | F54: 0.05 | G54: =$C$48*F54 -> 12876.069 | H54: =H79 -> 45675 | M54: 6 | N54: 6. AC Equipment | O54: End of Defects Period | Q54: 0.05 | R54: =$P$47*Q54 -> 4772.3 | S54: Thula Moya IN04594 | T54: =T79 -> 45688 | U54: 9707.7438 | W54: =W79 -> 45722
T55: =IF(W55>1,EOMONTH(W55,-1),"")
B56: 7 | C56: Battery Systems | J56: =SUM(G56:G63) -> 0 | K56: 0 | M56: 7 | N56: Battery Systems | T56: =IF(W56>1,EOMONTH(W56,-1),"") | V56: =K56-SUM(U56:U63) -> 0 | X56: =SUM(R56:R63) -> 0
B57: 7 | M57: 7 | T57: =IF(W57>1,EOMONTH(W57,-1),"")
B58: 7 | M58: 7 | T58: =IF(W58>1,EOMONTH(W58,-1),"")
B59: 7 | M59: 7 | T59: =IF(W59>1,EOMONTH(W59,-1),"")
B60: 7 | M60: 7 | T60: =IF(W60>1,EOMONTH(W60,-1),"")
B61: 7 | M61: 7 | T61: =IF(W61>1,EOMONTH(W61,-1),"")
B62: 7 | M62: 7 | T62: =IF(W62>1,EOMONTH(W62,-1),"")
B63: 7 | M63: 7 | T63: =IF(W63>1,EOMONTH(W63,-1),"")
T64: =IF(W64>1,EOMONTH(W64,-1),"")
B65: 8 | C65: Product Add On | J65: =SUM(G65:G69) -> 0 | K65: 0 | M65: 8 | N65: 8. Product Add On | O65: Walkways - Transport | R65: 4025 | S65: Onvlee Engineering: Inv01048652 | T65: 45596 | U65: 0 | V65: =K65-SUM(U65:U69) -> 0 | W65: 45575 | X65: =SUM(R65:R69) -> 83299.38
B66: 8 | M66: 8 | N66: 8. Product Add On | O66: Mounting Structure for Walkways | R66: =21221.6/5 -> 4244.32 | S66: Schletter INV0951 | T66: 45596 | U66: 0 | W66: =T66+29 -> 45625 | Y66: PO3389-SAM-20241008 - RV Approved
B67: 8 | M67: 8 | N67: 8. Product Add On | O67: Walkways | R67: 41645.1 | S67: Onvlee Engineering: Inv01048652 | T67: =T66 -> 45596 | U67: 0 | W67: 45575 | Y67: PO3390-SAM-20241008 - RV Approved
B68: 8 | M68: 8 | N68: 8. Product Add On | O68: Supply and Install Tie in Breaker - Thula Moya | R68: 24300.96 | S68: Thula Moya IN04487 | T68: 45596 | U68: 0 | W68: 45597 | Y68: PO3433-SAM-20241029 - RV Approved
B69: 8 | M69: 8 | N69: 8. Product Add On | O69: Installation of walkways | R69: 9084 | S69: Thula Moya IN04597 | T69: 45688 | U69: 0 | W69: 45869
M70: 8 | N70: 8. Product Add On | T70: 45688 | U70: 49914.42
L71: Only services to be capture below, products above | T71: =IF(W71>1,EOMONTH(W71,-1),"")
B72: 9 | C72: AC & DC Installation | D72: Project Kick Off | F72: 0.1 | G72: =SUM($C$73:$C$74)*F72 -> 12350 | H72: ='Project Plan'!E19-7 -> 45553 | J72: =SUM(G72:G79) -> 123500 | K72: =43588.23529+101705.8824 -> 145294.12 | M72: 9 | N72: 9. AC & DC installation | O72: Project Kick Off | P72: =AE25+AE26 -> 103690 | Q72: 0.1 | R72: =P72*Q72 -> 10369 | S72: Thula Moya INV IN04448 | T72: 45565 | U72: 14529.412 | V72: 0 | W72: 45582 | X72: =SUM(R72:R79) -> 103690 | Y72: PO3378-SAM20-20240930 - RV Approved
B73: 9 | C73: 37050 | D73: Site Establishment | F73: 0.15 | G73: =SUM($C$73:$C$74)*F73 -> 18525 | H73: ='Project Plan'!I19 -> 45560 | M73: 9 | N73: 9. AC & DC installation | O73: Site Establishment | Q73: 0.15 | R73: =P72*Q73 -> 15553.5 | S73: Thula Moya IN0449 | T73: 45596 | U73: 21794.118 | W73: 45582
B74: 9 | C74: 86450 | D74: AC Installation Complete | F74: 0.2 | G74: =SUM($C$73:$C$74)*F74 -> 24700 | H74: ='Project Plan'!G21 -> 45618 | M74: 9 | N74: 9. AC & DC installation | O74: AC Installation Complete | Q74: 0.2 | R74: =$P$72*Q74 -> 20738 | S74: Thula Moya IN04519 | T74: 45626 | U74: 29058.824 | W74: 45625
B75: 9 | D75: DC Installation Complete | F75: 0.25 | G75: =SUM($C$73:$C$74)*F75 -> 30875 | H75: ='Project Plan'!G28 -> 45617 | M75: 9 | N75: 9. AC & DC installation | O75: DC Installation Complete | Q75: 0.25 | R75: =$P$72*Q75 -> 25922.5 | S75: Thula Moya IN04520 | T75: 45626 | U75: 36323.529 | W75: 45625
B76: 9 | D76: Commissioning Complete | F76: 0.1 | G76: =SUM($C$73:$C$74)*F76 -> 12350 | H76: ='Project Plan'!G38 -> 45625 | M76: 9 | N76: 9. AC & DC installation | O76: Commissioning Complete | Q76: 0.1 | R76: =$P$72*Q76 -> 10369 | S76: Thula Moya IN04521 | T76: 45626 | U76: 14529.412 | W76: 45701
B77: 9 | D77: Site De-establisment | F77: 0.1 | G77: =SUM($C$73:$C$74)*F77 -> 12350 | H77: ='Project Plan'!G47 -> 45637 | M77: 9 | N77: 9. AC & DC installation | O77: Site De-establisment | Q77: 0.1 | R77: =$P$72*Q77 -> 10369 | S77: Thula Moya IN04537 | T77: 45626 | U77: 14529.412 | W77: ='Project Plan'!I47 -> 45631
B78: 9 | D78: Handover Document Complete | F78: 0.05 | G78: =SUM($C$73:$C$74)*F78 -> 6175 | H78: ='Project Plan'!G49 -> 45645 | M78: 9 | N78: 9. AC & DC installation | O78: Handover Document Complete | Q78: 0.05 | R78: =$P$72*Q78 -> 5184.5 | S78: Thula Moya IN04538 | T78: 45626 | U78: 7264.7059 | W78: 45701
B79: 9 | D79: End of Defects Period | F79: 0.05 | G79: =SUM($C$73:$C$74)*F79 -> 6175 | H79: =H78+30 -> 45675 | M79: 9 | N79: 9. AC & DC installation | O79: End of Defects Period | Q79: 0.05 | R79: =$P$72*Q79 -> 5184.5 | S79: Thula Moya IN04594 | T79: 45688 | U79: 7264.7059 | W79: 45722
T80: =IF(W80>1,EOMONTH(W80,-1),"")
B81: 10 | C81: Site Logistics | J81: =SUM(G81:G91) -> 31594.3 | K81: =10000+27169.76471 -> 37169.765 | M81: 10 | N81: 10. Site Logistics | O81: Security | U81: =(R81/$X$81*$K$81) -> 0 | V81: =K81-SUM(U81:U91) -> 0.0042105345 | X81: =SUM(R81:R91) -> 93158.2
M82: 10 | N82: 10. Site Logistics | T82: =IF(W82>1,EOMONTH(W82,-1),"") | U82: =(R82/$X$81*$K$81) -> 0
M83: 10 | N83: 10. Site Logistics | O83: Project Kick Off | P83: =AE27+AE28+AE29 -> 87820 | Q83: 0.1 | R83: =P83*Q83 -> 8782 | S83: Thula Moya INV IN04448 | T83: =T72 -> 45565 | U83: 3007.4293 | W83: =W72 -> 45582 | Y83: PO3378-SAM20-20240930 - RV Approved
M84: 10 | N84: 10. Site Logistics | O84: Site Establishment | Q84: 0.15 | R84: =P83*Q84 -> 13173 | S84: Thula Moya IN0449 | T84: =T73 -> 45596 | U84: 4511.144 | W84: =W73 -> 45582
M85: 10 | N85: 10. Site Logistics | O85: AC Installation Complete | Q85: 0.2 | R85: =$P$47*Q85 -> 19089.2 | S85: =S74 -> Thula Moya IN04519 | T85: =T74 -> 45626 | U85: 8791.15 | W85: =W74 -> 45625
M86: 10 | N86: 10. Site Logistics | O86: DC Installation Complete | Q86: 0.25 | R86: =$P$47*Q86 -> 23861.5 | S86: =S75 -> Thula Moya IN04520 | T86: =T75 -> 45626 | U86: 9481.8375 | W86: =W75 -> 45625
M87: 10 | N87: 10. Site Logistics | O87: Commissioning Complete | Q87: 0.1 | R87: =$P$47*Q87 -> 9544.6 | S87: =S76 -> Thula Moya IN04521 | T87: =T76 -> 45626 | U87: 3792.735 | W87: =W76 -> 45701
B88: 10 | D88: Offloading | G88: 8500 | H88: =H76 -> 45625 | M88: 10 | N88: 10. Site Logistics | O88: Site De-establisment | Q88: 0.1 | R88: =$P$47*Q88 -> 9544.6 | S88: Thula Moya IN04537 | T88: =T77 -> 45626 | U88: 3792.735 | W88: =W77 -> 45631
B89: 10 | M89: 10 | N89: 10. Site Logistics | O89: Handover Document Complete | Q89: 0.05 | R89: =$P$47*Q89 -> 4772.3 | S89: Thula Moya IN04538 | T89: =T78 -> 45626 | U89: 1896.3675 | W89: =W78 -> 45701
B90: 10 | M90: 10 | N90: 10. Site Logistics | O90: End of Defects Period | Q90: 0.05 | R90: =P83*Q90 -> 4391 | S90: Thula Moya IN04594 | T90: =T79 -> 45688 | U90: =1751.99216860792+144.37 -> 1896.3622 | W90: =W79 -> 45722 | Z90: MI: Waiting on revised invoice 1/2
B91: 10 | D91: Scaffolding | G91: 23094.3 | H91: =H88 -> 45625 | M91: 10 | N91: 10. Site Logistics | T91: =IF(W91>1,EOMONTH(W91,-1),"") | U91: =(R91/$X$81*$K$81) -> 0
T92: =IF(W92>1,EOMONTH(W92,-1),"")
B93: 11 | C93: Due Dilligence | D93: Electrical PrEng sign off | G93: 11000 | H93: ='Project Plan'!E51 -> 45626 | J93: =SUM(G93:G97) -> 89000 | K93: 104705.88 | M93: 11 | N93: 11. Due Dilligence | O93: Electrical PrEng sign off | R93: 3347.62 | S93: Sun Spot Inv E005 | T93: 45626 | U93: 40306.801 | V93: =K93-SUM(U93:U97) -> 0.0022771507 | W93: 45673 | X93: =SUM(R93:R97) -> 11867.62
B94: 11 | D94: Structural sign off | G94: 18000 | H94: ='Project Plan'!E19 -> 45560 | M94: 11 | N94: 11. Due Dilligence | O94: Structural sign off | R94: 2520 | S94: L&B Consulting Inv1742 | T94: 45535 | U94: 11462.156 | W94: 45537
B95: 11 | D95: SCADA - COCT | G95: 60000 | H95: =H94+30 -> 45590 | M95: 11 | N95: 11. Due Dilligence | T95: =IF(W95>1,EOMONTH(W95,-1),"") | U95: =R95/$X$93*$K$93 -> 0
B96: 11 | M96: 11 | N96: 11. Due Dilligence | T96: =IF(W96>1,EOMONTH(W96,-1),"") | U96: =R96/$X$93*$K$93 -> 0
B97: 11 | M97: 11 | N97: 11. Due Dilligence | O97: Red Team Inspection | R97: 6000 | S97: MATRIARCH - INV-3413 | T97: 45626 | U97: 52936.924 | W97: =T97 -> 45626
T98: =IF(W98>1,EOMONTH(W98,-1),"")
B99: 12 | C99: BDP Commission | D99: Referral Fee | G99: 48482.92 | H99: ='Project Plan'!G50 -> 45646 | J99: =SUM(G99:G101) -> 48482.92 | K99: 0 | M99: 12 | N99: BDP Commission | O99: Referral Fee | R99: =48482.92/2 -> 24241.46 | S99: Green Co Inv: INV0000518 | T99: 45535 | W99: 45537 | X99: =SUM(R99:R101) -> 48482.92
M100: 12 | N100: BDP Commission | O100: Referral Fee | R100: 24241.46 | S100: Green Co Inv: INV0000527 | T100: =T76 -> 45626 | W100: 45638
B101: 12 | C101: BDP Commission | M101: 12 | N101: BDP Commission | T101: =IF(W101>1,EOMONTH(W101,-1),"")
T102: =IF(W102>1,EOMONTH(W102,-1),"")
B103: 13 | C103: Engineering | D103: Matriarch Defects Period | G103: 16328.72 | H103: ='Project Plan'!G51+31 -> 45659 | J103: =SUM(G103:G109) -> 103846.32 | K103: 118007.18 | M103: 13 | N103: 13. Engineering | O103: Matriarch Defects Period | R103: 21667.67 | S103: Matriarch Inv: INV-3417 | T103: 45626 | U103: 118007.18 | V103: =K103-SUM(U103:U109) -> 0 | W103: 45626 | X103: =SUM(R103:R109) -> 72067.67
...

Sheet Cashflow
D1: [RT: Double Check the first date is always a MONDAY] | F1: 45488 | G1: =F1+7 -> 45495 | H1: =G1+7 -> 45502 | I1: =H1+7 -> 45509 | J1: =I1+7 -> 45516 | K1: =J1+7 -> 45523 | L1: =K1+7 -> 45530 | M1: =L1+7 -> 45537 | N1: =M1+7 -> 45544 | ... BW1: =BV1+7 -> 45971
A2: PLANNED | C2: CHECK | D2: CHECK
B3: Planned Revenue | C3: ='Revenue Tracking'!D4 -> 1735813.3 | D3: =SUM(F3:BM3) -> 1735813.3 | F3: =SUMIFS('Revenue Tracking'!$F$13:$F$19, 'Revenue Tracking'!$H$13:$H$19, ">="&F1,'Revenue Tracking'!$H$13:$H$19, "<"&G1) -> 607534.67 | G3: =SUMIFS('Revenue Tracking'!$F$13:$F$19, 'Revenue Tracking'!$H$13:$H$19, ">="&G1,'Revenue Tracking'!$H$13:$H$19, "<"&H1) -> 0 | H3: =SUMIFS('Revenue Tracking'!$F$13:$F$19, 'Revenue Tracking'!$H$13:$H$19, ">="&H1,'Revenue Tracking'!$H$13:$H$19, "<"&I1) -> 0 | I3: =SUMIFS('Revenue Tracking'!$F$13:$F$19, 'Revenue Tracking'!$H$13:$H$19, ">="&I1,'Revenue Tracking'!$H$13:$H$19, "<"&J1) -> 0 | J3: =SUMIFS('Revenue Tracking'!$F$13:$F$19, 'Revenue Tracking'!$H$13:$H$19, ">="&J1,'Revenue Tracking'!$H$13:$H$19, "<"&K1) -> 0 | K3: =SUMIFS('Revenue Tracking'!$F$13:$F$19, 'Revenue Tracking'!$H$13:$H$19, ">="&K1,'Revenue Tracking'!$H$13:$H$19, "<"&L1) -> 0 | L3: =SUMIFS('Revenue Tracking'!$F$13:$F$19, 'Revenue Tracking'!$H$13:$H$19, ">="&L1,'Revenue Tracking'!$H$13:$H$19, "<"&M1) -> 0 | M3: =SUMIFS('Revenue Tracking'!$F$13:$F$19, 'Revenue Tracking'!$H$13:$H$19, ">="&M1,'Revenue Tracking'!$H$13:$H$19, "<"&N1) -> 0 | ... BW3: =SUMIFS('Revenue Tracking'!$F$13:$F$19, 'Revenue Tracking'!$H$13:$H$19, ">="&BW1,'Revenue Tracking'!$H$13:$H$19, "<"&BX1) -> 0
B4: Planned Revenue - Cumulative | F4: =F3 -> 607534.67 | G4: =F4+G3 -> 607534.67 | H4: =G4+H3 -> 607534.67 | I4: =H4+I3 -> 607534.67 | J4: =I4+J3 -> 607534.67 | K4: =J4+K3 -> 607534.67 | L4: =K4+L3 -> 607534.67 | M4: =L4+M3 -> 607534.67 | N4: =M4+N3 -> 607534.67 | ... BW4: =BV4+BW3 -> 1735813.3
B5: Planned Expenditure | C5: ='Revenue Tracking'!D5 -> 1461076.8 | D5: =SUM(F5:BM5) -> 1461076.8 | F5: =SUMIFS('Expenditure Breakdown'!$G$6:$G$123, 'Expenditure Breakdown'!$H$6:$H$123, ">="&F1,'Expenditure Breakdown'!$H$6:$H$123, "<"&G1) -> 0 | G5: =SUMIFS('Expenditure Breakdown'!$G$6:$G$123, 'Expenditure Breakdown'!$H$6:$H$123, ">="&G1,'Expenditure Breakdown'!$H$6:$H$123, "<"&H1) -> 0 | H5: =SUMIFS('Expenditure Breakdown'!$G$6:$G$123, 'Expenditure Breakdown'!$H$6:$H$123, ">="&H1,'Expenditure Breakdown'!$H$6:$H$123, "<"&I1) -> 0 | I5: =SUMIFS('Expenditure Breakdown'!$G$6:$G$123, 'Expenditure Breakdown'!$H$6:$H$123, ">="&I1,'Expenditure Breakdown'!$H$6:$H$123, "<"&J1) -> 0 | J5: =SUMIFS('Expenditure Breakdown'!$G$6:$G$123, 'Expenditure Breakdown'!$H$6:$H$123, ">="&J1,'Expenditure Breakdown'!$H$6:$H$123, "<"&K1) -> 0 | K5: =SUMIFS('Expenditure Breakdown'!$G$6:$G$123, 'Expenditure Breakdown'!$H$6:$H$123, ">="&K1,'Expenditure Breakdown'!$H$6:$H$123, "<"&L1) -> 0 | L5: =SUMIFS('Expenditure Breakdown'!$G$6:$G$123, 'Expenditure Breakdown'!$H$6:$H$123, ">="&L1,'Expenditure Breakdown'!$H$6:$H$123, "<"&M1) -> 0 | M5: =SUMIFS('Expenditure Breakdown'!$G$6:$G$123, 'Expenditure Breakdown'!$H$6:$H$123, ">="&M1,'Expenditure Breakdown'!$H$6:$H$123, "<"&N1) -> 0 | ... BW5: =SUMIFS('Expenditure Breakdown'!$G$6:$G$123, 'Expenditure Breakdown'!$H$6:$H$123, ">="&BW1,'Expenditure Breakdown'!$H$6:$H$123, "<"&BX1) -> 0
B6: Planned Expenditure - Cumulative | F6: =F5 -> 0 | G6: =F6+G5 -> 0 | H6: =G6+H5 -> 0 | I6: =H6+I5 -> 0 | J6: =I6+J5 -> 0 | K6: =J6+K5 -> 0 | L6: =K6+L5 -> 0 | M6: =L6+M5 -> 0 | N6: =M6+N5 -> 0 | ... BW6: =BV6+BW5 -> 1461076.8
B7: PLANNED CashFlow | F7: =F4-F6 -> 607534.67 | G7: =G4-G6 -> 607534.67 | H7: =H4-H6 -> 607534.67 | I7: =I4-I6 -> 607534.67 | J7: =J4-J6 -> 607534.67 | K7: =K4-K6 -> 607534.67 | L7: =L4-L6 -> 607534.67 | M7: =M4-M6 -> 607534.67 | ... BW7: =BW4-BW6 -> 274736.57
A8: ACTUAL | C8: CHECK | D8: CHECK
B9: Actual + Planned Revenue | C9: ='Revenue Tracking'!F4 -> 1776820.4 | D9: =SUM(F9:BW9) -> 1785727.8 | F9: =SUMIFS('Revenue Tracking'!$F$13:$F$19, 'Revenue Tracking'!$P$13:$P$19, ">="&F1,'Revenue Tracking'!$P$13:$P$19, "<"&G1) -> 607534.67 | G9: =SUMIFS('Revenue Tracking'!$F$13:$F$19, 'Revenue Tracking'!$P$13:$P$19, ">="&G1,'Revenue Tracking'!$P$13:$P$19, "<"&H1) -> 0 | H9: =SUMIFS('Revenue Tracking'!$F$13:$F$19, 'Revenue Tracking'!$P$13:$P$19, ">="&H1,'Revenue Tracking'!$P$13:$P$19, "<"&I1) -> 0 | I9: =SUMIFS('Revenue Tracking'!$F$13:$F$19, 'Revenue Tracking'!$P$13:$P$19, ">="&I1,'Revenue Tracking'!$P$13:$P$19, "<"&J1) -> 0 | J9: =SUMIFS('Revenue Tracking'!$F$13:$F$19, 'Revenue Tracking'!$P$13:$P$19, ">="&J1,'Revenue Tracking'!$P$13:$P$19, "<"&K1) -> 0 | K9: =SUMIFS('Revenue Tracking'!$F$13:$F$19, 'Revenue Tracking'!$P$13:$P$19, ">="&K1,'Revenue Tracking'!$P$13:$P$19, "<"&L1) -> 0 | L9: =SUMIFS('Revenue Tracking'!$F$13:$F$19, 'Revenue Tracking'!$P$13:$P$19, ">="&L1,'Revenue Tracking'!$P$13:$P$19, "<"&M1) -> 0 | M9: =SUMIFS('Revenue Tracking'!$F$13:$F$19, 'Revenue Tracking'!$P$13:$P$19, ">="&M1,'Revenue Tracking'!$P$13:$P$19, "<"&N1) -> 0 | ... BW9: =SUMIFS('Revenue Tracking'!$F$13:$F$19, 'Revenue Tracking'!$P$13:$P$19, ">="&BW1,'Revenue Tracking'!$P$13:$P$19, "<"&BX1) -> 0
B10: Actual + Planned Revenue - Cumulative | F10: =F9 -> 607534.67 | G10: =F10+G9 -> 607534.67 | H10: =G10+H9 -> 607534.67 | I10: =H10+I9 -> 607534.67 | J10: =I10+J9 -> 607534.67 | K10: =J10+K9 -> 607534.67 | L10: =K10+L9 -> 607534.67 | M10: =L10+M9 -> 607534.67 | N10: =M10+N9 -> 607534.67 | ... BW10: =BV10+BW9 -> 1785727.8
B11: Actual + Planned Expenditure | C11: ='Revenue Tracking'!F5 -> 1332390.7 | D11: =SUM(F11:BW11) -> 1332390.7 | F11: =SUMIFS('Expenditure Breakdown'!$R$6:$R$123, 'Expenditure Breakdown'!$W$6:$W$123, ">="&F1,'Expenditure Breakdown'!$W$6:$W$123, "<"&G1) -> 0 | G11: =SUMIFS('Expenditure Breakdown'!$R$6:$R$123, 'Expenditure Breakdown'!$W$6:$W$123, ">="&G1,'Expenditure Breakdown'!$W$6:$W$123, "<"&H1) -> 0 | H11: =SUMIFS('Expenditure Breakdown'!$R$6:$R$123, 'Expenditure Breakdown'!$W$6:$W$123, ">="&H1,'Expenditure Breakdown'!$W$6:$W$123, "<"&I1) -> 0 | I11: =SUMIFS('Expenditure Breakdown'!$R$6:$R$123, 'Expenditure Breakdown'!$W$6:$W$123, ">="&I1,'Expenditure Breakdown'!$W$6:$W$123, "<"&J1) -> 0 | J11: =SUMIFS('Expenditure Breakdown'!$R$6:$R$123, 'Expenditure Breakdown'!$W$6:$W$123, ">="&J1,'Expenditure Breakdown'!$W$6:$W$123, "<"&K1) -> 0 | K11: =SUMIFS('Expenditure Breakdown'!$R$6:$R$123, 'Expenditure Breakdown'!$W$6:$W$123, ">="&K1,'Expenditure Breakdown'!$W$6:$W$123, "<"&L1) -> 0 | L11: =SUMIFS('Expenditure Breakdown'!$R$6:$R$123, 'Expenditure Breakdown'!$W$6:$W$123, ">="&L1,'Expenditure Breakdown'!$W$6:$W$123, "<"&M1) -> 0 | M11: =SUMIFS('Expenditure Breakdown'!$R$6:$R$123, 'Expenditure Breakdown'!$W$6:$W$123, ">="&M1,'Expenditure Breakdown'!$W$6:$W$123, "<"&N1) -> 28284.2 | ... BW11: =SUMIFS('Expenditure Breakdown'!$R$6:$R$123, 'Expenditure Breakdown'!$W$6:$W$123, ">="&BW1,'Expenditure Breakdown'!$W$6:$W$123, "<"&BX1) -> 0
B12: Actual + Planned Expenditure - Cumulative | F12: =F11 -> 0 | G12: =F12+G11 -> 0 | H12: =G12+H11 -> 0 | I12: =H12+I11 -> 0 | J12: =I12+J11 -> 0 | K12: =J12+K11 -> 0 | L12: =K12+L11 -> 0 | M12: =L12+M11 -> 28284.2 | N12: =M12+N11 -> 28284.2 | ... BW12: =BV12+BW11 -> 1332390.7
B14: ACTUAL CashFlow | F14: =F10-F12 -> 607534.67 | G14: =G10-G12 -> 607534.67 | H14: =H10-H12 -> 607534.67 | I14: =I10-I12 -> 607534.67 | J14: =J10-J12 -> 607534.67 | K14: =K10-K12 -> 607534.67 | L14: =L10-L12 -> 607534.67 | M14: =M10-M12 -> 579250.47 | ... BW14: =BW10-BW12 -> 453337.02
C16: CHECK | D16: CHECK
B17: Revenue Recognition | C17: =C3-D17 -> -49914.413 | D17: =SUM(F17:BM17) -> 1785727.8 | F17: =SUMIFS('Expenditure Breakdown'!$U$6:$U$123, 'Expenditure Breakdown'!$T$6:$T$123, ">="&F1,'Expenditure Breakdown'!$T$6:$T$123, "<"&G1) -> 0 | G17: =SUMIFS('Expenditure Breakdown'!$U$6:$U$123, 'Expenditure Breakdown'!$T$6:$T$123, ">="&G1,'Expenditure Breakdown'!$T$6:$T$123, "<"&H1) -> 0 | H17: =SUMIFS('Expenditure Breakdown'!$U$6:$U$123, 'Expenditure Breakdown'!$T$6:$T$123, ">="&H1,'Expenditure Breakdown'!$T$6:$T$123, "<"&I1) -> 521076.49 | I17: =SUMIFS('Expenditure Breakdown'!$U$6:$U$123, 'Expenditure Breakdown'!$T$6:$T$123, ">="&I1,'Expenditure Breakdown'!$T$6:$T$123, "<"&J1) -> 0 | J17: =SUMIFS('Expenditure Breakdown'!$U$6:$U$123, 'Expenditure Breakdown'!$T$6:$T$123, ">="&J1,'Expenditure Breakdown'!$T$6:$T$123, "<"&K1) -> 0 | K17: =SUMIFS('Expenditure Breakdown'!$U$6:$U$123, 'Expenditure Breakdown'!$T$6:$T$123, ">="&K1,'Expenditure Breakdown'!$T$6:$T$123, "<"&L1) -> 0 | L17: =SUMIFS('Expenditure Breakdown'!$U$6:$U$123, 'Expenditure Breakdown'!$T$6:$T$123, ">="&L1,'Expenditure Breakdown'!$T$6:$T$123, "<"&M1) -> 55756.955 | M17: =SUMIFS('Expenditure Breakdown'!$U$6:$U$123, 'Expenditure Breakdown'!$T$6:$T$123, ">="&M1,'Expenditure Breakdown'!$T$6:$T$123, "<"&N1) -> 0 | ... BW17: =SUMIFS('Expenditure Breakdown'!$U$6:$U$123, 'Expenditure Breakdown'!$T$6:$T$123, ">="&BW1,'Expenditure Breakdown'!$T$6:$T$123, "<"&BX1) -> 0
B18: Revenue Recognition Cumulative | C18: =D17-D18 -> 0 | D18: =MAX(F18:BM18) -> 1785727.8 | F18: =F17 -> 0 | G18: =F18+G17 -> 0 | H18: =G18+H17 -> 521076.49 | I18: =H18+I17 -> 521076.49 | J18: =I18+J17 -> 521076.49 | K18: =J18+K17 -> 521076.49 | L18: =K18+L17 -> 576833.44 | M18: =L18+M17 -> 576833.44 | N18: =M18+N17 -> 576833.44 | ... BW18: =BV18+BW17 -> 1785727.8
B20: Installer Expenditure | D20: =SUM(F20:BM20) -> 283948 | F20: =SUMIFS('Expenditure Breakdown'!$R$26:$R$33, 'Expenditure Breakdown'!$W$26:$W$33, ">="&F1,'Expenditure Breakdown'!$W$26:$W$33, "<"&G1)+SUMIFS('Expenditure Breakdown'!$R$47:$R$54, 'Expenditure Breakdown'!$W$47:$W$54, ">="&F1,'Expenditure Breakdown'!$W$47:$W$54, "<"&G1)+SUMIFS('Expenditure Breakdown'!$R$72:$R$79, 'Expenditure Breakdown'!$W$72:$W$79, ">="&F1,'Expenditure Breakdown'!$W$72:$W$79, "<"&G1) -> 0 | G20: =SUMIFS('Expenditure Breakdown'!$R$26:$R$33, 'Expenditure Breakdown'!$W$26:$W$33, ">="&G1,'Expenditure Breakdown'!$W$26:$W$33, "<"&H1)+SUMIFS('Expenditure Breakdown'!$R$47:$R$54, 'Expenditure Breakdown'!$W$47:$W$54, ">="&G1,'Expenditure Breakdown'!$W$47:$W$54, "<"&H1)+SUMIFS('Expenditure Breakdown'!$R$72:$R$79, 'Expenditure Breakdown'!$W$72:$W$79, ">="&G1,'Expenditure Breakdown'!$W$72:$W$79, "<"&H1) -> 0 | H20: =SUMIFS('Expenditure Breakdown'!$R$26:$R$33, 'Expenditure Breakdown'!$W$26:$W$33, ">="&H1,'Expenditure Breakdown'!$W$26:$W$33, "<"&I1)+SUMIFS('Expenditure Breakdown'!$R$47:$R$54, 'Expenditure Breakdown'!$W$47:$W$54, ">="&H1,'Expenditure Breakdown'!$W$47:$W$54, "<"&I1)+SUMIFS('Expenditure Breakdown'!$R$72:$R$79, 'Expenditure Breakdown'!$W$72:$W$79, ">="&H1,'Expenditure Breakdown'!$W$72:$W$79, "<"&I1) -> 0 | I20: =SUMIFS('Expenditure Breakdown'!$R$26:$R$33, 'Expenditure Breakdown'!$W$26:$W$33, ">="&I1,'Expenditure Breakdown'!$W$26:$W$33, "<"&J1)+SUMIFS('Expenditure Breakdown'!$R$47:$R$54, 'Expenditure Breakdown'!$W$47:$W$54, ">="&I1,'Expenditure Breakdown'!$W$47:$W$54, "<"&J1)+SUMIFS('Expenditure Breakdown'!$R$72:$R$79, 'Expenditure Breakdown'!$W$72:$W$79, ">="&I1,'Expenditure Breakdown'!$W$72:$W$79, "<"&J1) -> 0 | J20: =SUMIFS('Expenditure Breakdown'!$R$26:$R$33, 'Expenditure Breakdown'!$W$26:$W$33, ">="&J1,'Expenditure Breakdown'!$W$26:$W$33, "<"&K1)+SUMIFS('Expenditure Breakdown'!$R$47:$R$54, 'Expenditure Breakdown'!$W$47:$W$54, ">="&J1,'Expenditure Breakdown'!$W$47:$W$54, "<"&K1)+SUMIFS('Expenditure Breakdown'!$R$72:$R$79, 'Expenditure Breakdown'!$W$72:$W$79, ">="&J1,'Expenditure Breakdown'!$W$72:$W$79, "<"&K1) -> 0 | K20: =SUMIFS('Expenditure Breakdown'!$R$26:$R$33, 'Expenditure Breakdown'!$W$26:$W$33, ">="&K1,'Expenditure Breakdown'!$W$26:$W$33, "<"&L1)+SUMIFS('Expenditure Breakdown'!$R$47:$R$54, 'Expenditure Breakdown'!$W$47:$W$54, ">="&K1,'Expenditure Breakdown'!$W$47:$W$54, "<"&L1)+SUMIFS('Expenditure Breakdown'!$R$72:$R$79, 'Expenditure Breakdown'!$W$72:$W$79, ">="&K1,'Expenditure Breakdown'!$W$72:$W$79, "<"&L1) -> 0 | L20: =SUMIFS('Expenditure Breakdown'!$R$26:$R$33, 'Expenditure Breakdown'!$W$26:$W$33, ">="&L1,'Expenditure Breakdown'!$W$26:$W$33, "<"&M1)+SUMIFS('Expenditure Breakdown'!$R$47:$R$54, 'Expenditure Breakdown'!$W$47:$W$54, ">="&L1,'Expenditure Breakdown'!$W$47:$W$54, "<"&M1)+SUMIFS('Expenditure Breakdown'!$R$72:$R$79, 'Expenditure Breakdown'!$W$72:$W$79, ">="&L1,'Expenditure Breakdown'!$W$72:$W$79, "<"&M1) -> 0 | M20: =SUMIFS('Expenditure Breakdown'!$R$26:$R$33, 'Expenditure Breakdown'!$W$26:$W$33, ">="&M1,'Expenditure Breakdown'!$W$26:$W$33, "<"&N1)+SUMIFS('Expenditure Breakdown'!$R$47:$R$54, 'Expenditure Breakdown'!$W$47:$W$54, ">="&M1,'Expenditure Breakdown'!$W$47:$W$54, "<"&N1)+SUMIFS('Expenditure Breakdown'!$R$72:$R$79, 'Expenditure Breakdown'!$W$72:$W$79, ">="&M1,'Expenditure Breakdown'!$W$72:$W$79, "<"&N1) -> 0 | ... BW20: =SUMIFS('Expenditure Breakdown'!$R$26:$R$33, 'Expenditure Breakdown'!$W$26:$W$33, ">="&BW1,'Expenditure Breakdown'!$W$26:$W$33, "<"&BX1)+SUMIFS('Expenditure Breakdown'!$R$47:$R$54, 'Expenditure Breakdown'!$W$47:$W$54, ">="&BW1,'Expenditure Breakdown'!$W$47:$W$54, "<"&BX1)+SUMIFS('Expenditure Breakdown'!$R$72:$R$79, 'Expenditure Breakdown'!$W$72:$W$79, ">="&BW1,'Expenditure Breakdown'!$W$72:$W$79, "<"&BX1) -> 0
B21: Installer Expenditure - Cumulative | F21: =F20 -> 0 | G21: =G20+F21 -> 0 | H21: =H20+G21 -> 0 | I21: =I20+H21 -> 0 | J21: =J20+I21 -> 0 | K21: =K20+J21 -> 0 | L21: =L20+K21 -> 0 | M21: =M20+L21 -> 0 | N21: =N20+M21 -> 0 | ... BW21: =BW20+BV21 -> 283948

Sheet Finance - Revenue
A1: REVENUE RECOGNITION AMOUNT | B1: (All)
A3: Sum of REVENUE RECOGNITION AMOUNT | B3: Column Labels
A4: Row Labels | C4: (blank) | D4: 45504 | E4: 45535 | F4: 45565 | G4: 45596 | H4: 45626 | I4: 45688 | J4: 45716 | K4: 45777 | L4: 45869 | M4: 45900 | N4: Grand Total
A5: (blank)
A6: Battery Systems
A7: BDP Commission
A8: 1. Panels | C8: 0 | D8: 521076.49 | G8: 55366.446 | N8: 576442.93
A9: 2. Inverters | B9: 0 | F9: 89531.103 | G9: 58023.897 | N9: 147555
A10: 3. Mounting Structures | B10: 0 | F10: 83362.5 | H10: 0 | N10: 83362.5
A11: 4. DC Equipment | C11: 0 | F11: 9288.6219 | G11: 58288.589 | H11: 65020.353 | I11: 4644.311 | N11: 137241.88
A12: 5. Monitoring | E12: 43754.455 | G12: 14326.86 | H12: 3168.69 | N12: 61250.005
A13: 6. AC Equipment | B13: 0 | C13: 0 | F13: 70514.229 | G13: 105771.34 | H13: 135908.41 | I13: 9707.7438 | N13: 321901.73
A14: 8. Product Add On | G14: 0 | I14: 49914.42 | N14: 49914.42
A15: 9. AC & DC installation | F15: 14529.412 | G15: 21794.118 | H15: 101705.88 | I15: 7264.7059 | N15: 145294.12
A16: 10. Site Logistics | B16: 0 | C16: 0 | F16: 3007.4293 | G16: 4511.144 | H16: 27754.825 | I16: 1896.3622 | N16: 37169.76
A17: 11. Due Dilligence | B17: 0 | E17: 11462.156 | H17: 93243.724 | N17: 104705.88
A18: 13. Engineering | C18: 0 | H18: 118007.18 | M18: 0 | N18: 118007.18
A19: 14. General Expenses | E19: 540.34404 | F19: 568.24839 | G19: 591.25409 | H19: 27.123818 | I19: 399.26696 | J19: 756.1124 | K19: 0 | N19: 2882.3497
A20: 15. Service Add On
A21: Grand Total | B21: 0 | C21: 0 | D21: 521076.49 | E21: 55756.955 | F21: 270801.54 | G21: 318673.65 | H21: 544836.19 | I21: 73826.81 | J21: 756.1124 | K21: 0 | M21: 0 | N21: 1785727.8
D23: 521076.49 | E23: 55756.96 | F23: 270801.54 | G23: 310158.52 | H23: 544836.19 | I23: 73826.81 | J23: 756.11 | K23: =SUM(D23:J23) -> 1777212.6
D24: =D21-D23 -> -0.0013367933 | E24: =E21-E23 -> -0.0049011544 | F24: =F21-F23 -> 0.0033445973 | G24: =G21-G23 -> 8515.1302 | H24: =H21-H23 -> 0.0025985589 | I24: =I21-I23 -> -0.00026840389 | J24: =J21-J23 -> 0.0023994257
J30: =J23+G24 -> 9271.2402

Sheet Finance - COS
A3: Sum of Actual Total | B3: Column Labels
A4: Row Labels | B4: (blank) | C4: 45504 | D4: 45535 | E4: 45565 | F4: 45596 | G4: 45626 | H4: 45688 | I4: 45716 | J4: 45777 | L4: 45869 | M4: 45900 | N4: Grand Total
A5: Battery Systems
A6: BDP Commission | D6: 24241.46 | G6: 24241.46 | N6: 48482.92
A7: (blank)
A8: 1. Panels | C8: 376456.5 | F8: 7746 | N8: 384202.5
A9: 2. Inverters | E9: 69975.23 | F9: 45350 | N9: 115325.23
A10: 3. Mounting Structures | E10: 29643.2 | G10: -7251.88 | N10: 22391.32
A11: 4. DC Equipment | E11: 8481.2 | F11: 53221.8 | G11: 59368.4 | H11: 4240.6 | N11: 125312
A12: 5. Monitoring | D12: 57520.5 | F12: 2562.51 | G12: 46919 | N12: 107002.01
A13: 6. AC Equipment | E13: 34664.6 | F13: 51996.9 | G13: 66812.2 | H13: 4772.3 | N13: 158246
A14: 8. Product Add On | F14: 74215.38 | H14: 9084 | N14: 83299.38
A15: 9. AC & DC installation | E15: 10369 | F15: 15553.5 | G15: 72583 | H15: 5184.5 | N15: 103690
A16: 10. Site Logistics | E16: 8782 | F16: 13173 | G16: 66812.2 | H16: 4391 | N16: 93158.2
A17: 11. Due Dilligence | D17: 2520 | G17: 9347.62 | N17: 11867.62
A18: 13. Engineering | B18: 0 | G18: 21667.67 | M18: 50400 | N18: 72067.67
A19: 14. General Expenses | D19: 1522.74 | E19: 1570.98 | F19: 1671 | G19: 53.96 | H19: 1016.01 | I19: 423.22 | J19: 1087.98 | N19: 7345.89
A20: 15. Service Add On | L20: 19463.42 | N20: 19463.42
A21: Grand Total | B21: 0 | C21: 376456.5 | D21: 85804.7 | E21: 163486.21 | F21: 265490.09 | G21: 360553.63 | H21: 28688.41 | I21: 423.22 | J21: 1087.98 | L21: 19463.42 | M21: 50400 | N21: 1351854.2

Sheet Certificate - Financial Close
B2: Emergent Energy – Financial Close Completion Certificate | H2: FINANCIAL CLOSE CERTIFICATE
B4: Project Name: | C4: ='Project Plan'!E2 -> SA Metal - 20 Christiaan
B5: COO: | C5: Johannes Potgieter
B6: Programme Manager: | C6: Roedolph Venter
B7: HoPD: | C7: Natasha Watkins-Baker
B9: Date of Phase Completion: | F9: {=_xlfn.LET(_xlpm.w,$B$10:$B$54,_xlpm.r,$M$10:$M$54,_xlpm.v,IF(ISNUMBER(_xlpm.r),_xlpm.r,IFERROR(VALUE(SUBSTITUTE(_xlpm.r,"%",""))/100,0)),_xlpm.g,IFERROR(VALUE(LEFT(_xlpm.w,1)),0),_xlpm.bdOnly,(SUMPRODUCT((_xlpm.w="1.1")*(_xlpm.v>0))>0)*(SUMPRODUCT((_xlpm.w<>"1.1")*(_xlpm.v>0))=0),_xlpm.anyConstr,SUMPRODUCT((_xlpm.g>=2)*(_xlpm.g<=6)*(_xlpm.v>0))>0,_xlpm.anyQA,SUMPRODUCT((_xlpm.g=7)*(_xlpm.v>0))>0,_xlpm.anyHO,SUMPRODUCT((_xlpm.g=8)*(_xlpm.v>0))>0,_xlpm.anyPlan,SUMPRODUCT((_xlpm.g=1)*(_xlpm.v>0))>0,IF(_xlpm.bdOnly,"1. Financial Close",IF(_xlpm.anyConstr,"3. Construction",IF(_xlpm.anyQA,"4. QA",IF(_xlpm.anyHO,"5. Handover",IF(_xlpm.anyPlan,"2. Planning","1. Financial Close"))))))} -> 1. Financial Close | G9: {=_xlfn.LET(_xlpm.w,$B$10:$B$54,_xlpm.r,$N$10:$N$54,_xlpm.v,IF(ISNUMBER(_xlpm.r),_xlpm.r,IFERROR(VALUE(SUBSTITUTE(_xlpm.r,"%",""))/100,0)),_xlpm.g,IFERROR(VALUE(LEFT(_xlpm.w,1)),0),_xlpm.bdOnly,(SUMPRODUCT((_xlpm.w="1.1")*(_xlpm.v>0))>0)*(SUMPRODUCT((_xlpm.w<>"1.1")*(_xlpm.v>0))=0),_xlpm.anyConstr,SUMPRODUCT((_xlpm.g>=2)*(_xlpm.g<=6)*(_xlpm.v>0))>0,_xlpm.anyQA,SUMPRODUCT((_xlpm.g=7)*(_xlpm.v>0))>0,_xlpm.anyHO,SUMPRODUCT((_xlpm.g=8)*(_xlpm.v>0))>0,_xlpm.anyPlan,SUMPRODUCT((_xlpm.g=1)*(_xlpm.v>0))>0,IF(_xlpm.bdOnly,"1. Financial Close",IF(_xlpm.anyConstr,"3. Construction",IF(_xlpm.anyQA,"4. QA",IF(_xlpm.anyHO,"5. Handover",IF(_xlpm.anyPlan,"2. Planning","1. Financial Close"))))))} -> 1. Financial Close
B10: Phase Deliverables Checklist: (Y/N)
B11: Product Agreement | C11: NA
B12: EPC Agreement | C12: NA
B13: O&M Agreeement | C13: NA
B14: Cost Proposal | C14: Signed
B15: Deposit Received | C15: Yes
B16: Risks / Notes | C16: None
B18: Acknowledgement and Acceptance:
B19: Role | C19: Name | D19: Signature | E19: Date
B20: COO | C20: Johannes | D20: JTP | E20: 45953

Sheet Project Margins
A1: [capture project margins from costing sheet]
A3: Products | D3: 0.32
A4: Services | D4: 0.5
A5: Expenses | D5: 0.15
A6: Subcontractors | D6: 0.2

Sheet Equipment Quotes
B2: Equipment Quote and Budget comparision
B4: Description | D4: Budget | F4: Supplier 1 | H4: Variance | J4: Supplier 2 | L4: Variance | N4: Comments / Notes
F7: >Name< | J7: >Name<
B9: Inverters | D9: =SUM(D10:D11) -> 118044 | F9: =SUM(F10:F13) -> 0 | H9: =$D$9-F9 -> 118044 | J9: =SUM(J10:J13) -> 0 | L9: =$D$9-J9 -> 118044
B10: Inverters | D10: ='Expenditure Breakdown'!G13 -> 78898
B11: Optimizers | D11: ='Expenditure Breakdown'!G14 -> 39146
B12: Warranty
B13: Delivery fee
F15: >Name< | J15: >Name<
B17: Mounting Structure | D17: =SUM(D18:D19) -> 66690 | F17: =SUM(F18:F20) -> 0 | H17: =$D$17- F17 -> 66690 | J17: =SUM(J18:J20) -> 0 | L17: =$D$17- J17 -> 66690
B18: Mounting Structure | D18: ='Expenditure Breakdown'!G18 -> 66690
B19: Delivery fee
F21: >Name< | J21: >Name<
B23: DC Cable | D23: =SUM(D24:D25) -> 37520 | F23: =SUM(F24:F25) -> 0 | H23: =$D$23- F23 -> 37520 | J23: =SUM(J24:J25) -> 0 | L23: =$D$23- J23 -> 37520
B24: DC Cable | D24: ='Expenditure Breakdown'!G24 -> 37520
B25: Delivery fee
F27: >Name< | J27: >Name<
B29: Monitoring system | D29: =SUM(D30:D32) -> #REF! | F29: =SUM(F30:F42) -> 0 | H29: =$D$29-F29 -> #REF! | J29: =SUM(J30:J32) -> 0 | L29: =$D$29-J29 -> #REF!
B30: ='Expenditure Breakdown'!D35 -> Smartlogger 3000 | D30: ='Expenditure Breakdown'!G35 -> 26000
B31: ='Expenditure Breakdown'!#REF! -> #REF! | D31: ='Expenditure Breakdown'!#REF! -> #REF!
B32: Delivery fee
F34: >Name< | J34: >Name<
B36: Additional Scope | D36: =SUM(D37:D41) -> 0 | F36: =SUM(F37:F41) -> 0 | H36: =$D$29-F36 -> #REF! | J36: =SUM(J37:J41) -> 0 | L36: =$D$29-J36 -> #REF!
B37: SCADA | D37: ='Expenditure Breakdown'!G65 -> 0
B38: Inverter cage
B39: Cat ladders
B40: Gen Integration
B41: Lifelines
B43: Totals | D43: =D36+D29+D23+D17+D9 -> #REF! | H43: =SUM(H7:H42) -> #REF! | L43: =SUM(L7:L42) -> #REF!
B47: All amounts are incl VAT

Sheet Installer Quotes
B2: Installer Quote and Budget comparision
B4: Description | D4: Budget | G4: Cosmic Sun | J4: Variance | L4: Matthews Group | O4: Variance
B6: AC Equipment | D6: ='Expenditure Breakdown'!AB8 -> 257521.38 | E6: =D6/(1000*'Project Plan'!$E$3) -> 1.7400093 | G6: 277892.91 | H6: =G6/('Project Plan'!$E$3*1000) -> 1.8776548 | J6: =D6-G6 -> -20371.53 | M6: =L6/('Project Plan'!$E$3*1000) -> 0 | O6: =D6-L6 -> 257521.38
B7: DC Equipment | D7: ='Expenditure Breakdown'!AB9 -> 50273.5 | E7: =D7/(1000*'Project Plan'!$E$3) -> 0.33968581 | G7: 142158.25 | H7: =G7/('Project Plan'!$E$3*1000) -> 0.96052872 | J7: =D7-G7 -> -91884.75 | M7: =L7/('Project Plan'!$E$3*1000) -> 0 | O7: =D7-L7 -> 50273.5
B8: AC Labour | D8: ='Expenditure Breakdown'!AB10 -> 86450 | E8: =D8/(1000*'Project Plan'!$E$3) -> 0.58412162 | G8: 96174 | H8: =G8/('Project Plan'!$E$3*1000) -> 0.64982432 | J8: =D8-G8 -> -9724 | M8: =L8/('Project Plan'!$E$3*1000) -> 0 | O8: =D8-L8 -> 86450
B9: DC Labour | D9: ='Expenditure Breakdown'!AB11 -> 37050 | E9: =D9/(1000*'Project Plan'!$E$3) -> 0.25033784 | G9: 230160 | H9: =G9/('Project Plan'!$E$3*1000) -> 1.5551351 | J9: =D9-G9 -> -193110 | M9: =L9/('Project Plan'!$E$3*1000) -> 0 | O9: =D9-L9 -> 37050
B10: Offloading | D10: ='Expenditure Breakdown'!AB12 -> 8500 | G10: 0 | J10: =D10-G10 -> 8500 | O10: =D10-L10 -> 8500
B11: Roof Access/Scaffolding | D11: ='Expenditure Breakdown'!AB13 -> 0 | G11: 29257.61 | J11: =D11-G11 -> -29257.61 | O11: =D11-L11 -> 0
B12: Storage | D12: ='Expenditure Breakdown'!AB14 -> 0 | J12: =D12-G12 -> 0 | O12: =D12-L12 -> 0
B13: Telehandler | D13: ='Expenditure Breakdown'!AB15 -> 23094.3
B14: HSE | D14: 0
B15: Totals | D15: =SUM(D6:D13) -> 462889.18 | G15: =SUM(G6:G13) -> 775642.77 | J15: =SUM(J6:J14) -> -335847.89 | L15: =SUM(L6:L13) -> 0 | O15: =SUM(O6:O14) -> 439794.88
B18: Description | D18: Budget | G18: >Installer Name 3< | J18: Variance | L18: >Installer Name 4< | O18: Variance
B20: AC installation | D20: ='Expenditure Breakdown'!#REF! -> #REF! | E20: =D20/(1000*'Project Plan'!$E$3) -> #REF! | H20: =G20/(1000*'Project Plan'!$E$3) -> 0 | J20: =D20-G20 -> #REF! | M20: =L20/(1000*'Project Plan'!$E$3) -> 0 | O20: =D6-L20 -> 257521.38
B21: AC equipment | D21: ='Expenditure Breakdown'!C54 -> 0 | E21: =D21/(1000*'Project Plan'!$E$3) -> 0 | J21: =D21-G21 -> 0 | M21: =L21/(1000*'Project Plan'!$E$3) -> 0 | O21: =D7-L21 -> 50273.5
B22: DC installation | D22: ='Expenditure Breakdown'!#REF! -> #REF! | E22: =D22/(1000*'Project Plan'!$E$3) -> #REF! | H22: =G22/(1000*'Project Plan'!$E$3) -> 0 | J22: =D22-G22 -> #REF! | M22: =L22/(1000*'Project Plan'!$E$3) -> 0 | O22: =D8-L22 -> 86450
B23: DC equipment | D23: =SUM('Expenditure Breakdown'!G31:G32) -> 0 | E23: =D23/(1000*'Project Plan'!$E$3) -> 0 | J23: =D23-G23 -> 0 | O23: =D9-L23 -> 37050
B24: Storage | D24: ='Expenditure Breakdown'!G97 -> 0 | J24: =D24-G24 -> 0 | O24: =D10-L24 -> 8500
B25: Panel lifting equipment | D25: =SUM('Expenditure Breakdown'!G81:G89) -> 8500 | J25: =D25-G25 -> 8500 | O25: =D11-L25 -> 0
B26: Offloading | D26: ='Expenditure Breakdown'!G91 -> 23094.3 | J26: =D26-G26 -> 23094.3 | O26: =D12-L26 -> 0
B29: Totals | D29: =SUM(D20:D27) -> #REF! | G29: =SUM(G20:G27) -> 0 | J29: =SUM(J20:J28) -> #REF! | L29: =SUM(L20:L27) -> 0 | O29: =SUM(O20:O28) -> 439794.88
B32: Budget Summary
B34: Budget | D34: =D15 -> 462889.18
B35: =G4 -> Cosmic Sun | D35: =G15 -> 775642.77
B36: =L4 -> Matthews Group | D36: =L15 -> 0
B37: =G18 -> >Installer Name 3< | D37: =G29 -> 0
B38: =L18 -> >Installer Name 4< | D38: =L29 -> 0
B40: =IF(D40<D34,"Saving","Loss") -> Loss | D40: =D34-MIN(D35:D38) -> 462889.18
B42: All amounts are exc VAT

Sheet Decision Register
B1: =D15 -> SA Metal - 20 Christiaan | E1: Decision Register
B3: ID | C3: Decision Description | D3: Decision Impact | E3: Proposed Date | F3: Proposed By | G3: Status | H3: Approved By | I3: Date | J3: Results / Comments
B4: DEC001
B5: DEC002
B6: DEC003
B7: DEC004
B8: DEC005
B9: DEC006
B10: DEC007
B11: DEC008
B12: DEC009
B13: DEC010
D15: {='Project Plan'!E2:H2} -> SA Metal - 20 Christiaan | E15: 0 | F15: 0 | G15: 0
