Workbook
Name AC_Equipment_Product: #REF!
Name AC_Installation_Services: #REF!
Name Civil___Electrical_Due_Dilligence_Services: #REF!
Name DC_Equipment_Product: #REF!
Name Engineering___Project_Management_Services: #REF!
Name Installation_Services: #REF!
Name Inverter_Capacity: #REF!
Name Inverter_Supplier: #REF!
Name Material_Roof_access: #REF!
Name Mounting_Structures_Product: #REF!
Name Offloading_service: #REF!
Name Project_Size: 'Finance - Revenue'!Projectsize
Name Project_Size: Projectsize
Name Projectsize: #REF!
Name Projectsize: 'Project Margins'!$K$5
Name PV_Modules_Product: #REF!
Name Security_Serv: #REF!
Name Security_Serv: #REF!
Name Site_Storage_services: #REF!
Name SSS: #REF!
Name SSS: #REF!
Name Travel: #REF!
Name USD_ZAR: #REF!

Sheet Sheet1
A1: PROJECT PLAN
A2: # | B2: Project Milestone | C2: Planned Start Date | D2: Duration (Work Days) | E2: Planned End Date | F2: Actual Start Date | H2: Actual End Date | J2: Comments | L2: =C3 -> 43831 | M2: =L2+3 -> 43834 | N2: =M2+7 -> 43841 | O2: =N2+7 -> 43848 | P2: =O2+7 -> 43855 | Q2: =P2+6 -> 43861 | R2: =Q2+1 -> 43862 | S2: =R2+7 -> 43869 | T2: =S2+7 -> 43876 | U2: =T2+7 -> 43883 | V2: =U2+6 -> 43889 | W2: =V2+7 -> 43896 | X2: =W2+7 -> 43903 | Y2: =X2+7 -> 43910 | Z2: =Y2+7 -> 43917 | AA2: =Z2+3 -> 43920 | AB2: =AA2+4 -> 43924 | AC2: =AB2+7 -> 43931 | AD2: =AC2+7 -> 43938 | AE2: =AD2+7 -> 43945 | AF2: =AE2+6 -> 43951 | AG2: =AF2+2 -> 43953 | AH2: =AG2+7 -> 43960 | AI2: =AH2+7 -> 43967 | AJ2: =AI2+7 -> 43974 | AK2: =AJ2+7 -> 43981 | AL2: =AK2+1 -> 43982 | AM2: =AL2+6 -> 43988 | AN2: =AM2+7 -> 43995 | AO2: =AN2+7 -> 44002 | AP2: =AO2+7 -> 44009 | AQ2: =AP2+3 -> 44012 | AR2: =AQ2+4 -> 44016 | AS2: =AR2+7 -> 44023 | AT2: =AS2+7 -> 44030 | AU2: =AT2+7 -> 44037 | AV2: =AU2+6 -> 44043 | AW2: =AV2+1 -> 44044 | AX2: =AW2+7 -> 44051 | AY2: =AX2+7 -> 44058 | AZ2: =AY2+7 -> 44065 | BA2: =AZ2+7 -> 44072 | BB2: =BA2+2 -> 44074 | BC2: =BB2+5 -> 44079 | BD2: =BC2+7 -> 44086 | BE2: =BD2+7 -> 44093 | BF2: =BE2+7 -> 44100 | BG2: =BF2+4 -> 44104
A3: 1 | B3: Contract Signature | C3: 43831 | D3: 1 | E3: 43832 | F3: 43831 | G3: 1 | H3: 43832 | L3: =IF(AND($F3<(L$2+7),$F3>L$2),1, IF(AND($H3<L$2+7,$H3>L$2),3, IF(AND($F3<=L$2, $H3>=L$2), 2, "" ))) -> 3 | M3: =IF(AND($F3<(M$2+7),$F3>M$2),1, IF(AND($H3<M$2+7,$H3>M$2),3, IF(AND($F3<=M$2, $H3>=M$2), 2, "" ))) | N3: =IF(AND($F3<(N$2+7),$F3>N$2),1, IF(AND($H3<N$2+7,$H3>N$2),3, IF(AND($F3<=N$2, $H3>=N$2), 2, "" ))) | O3: =IF(AND($F3<(O$2+7),$F3>O$2),1, IF(AND($H3<O$2+7,$H3>O$2),3, IF(AND($F3<=O$2, $H3>=O$2), 2, "" ))) | P3: =IF(AND($F3<(P$2+7),$F3>P$2),1, IF(AND($H3<P$2+7,$H3>P$2),3, IF(AND($F3<=P$2, $H3>=P$2), 2, "" ))) | Q3: =IF(AND($F3<(Q$2+7),$F3>Q$2),1, IF(AND($H3<Q$2+7,$H3>Q$2),3, IF(AND($F3<=Q$2, $H3>=Q$2), 2, "" ))) | R3: =IF(AND($F3<(R$2+7),$F3>R$2),1, IF(AND($H3<R$2+7,$H3>R$2),3, IF(AND($F3<=R$2, $H3>=R$2), 2, "" ))) | S3: =IF(AND($F3<(S$2+7),$F3>S$2),1, IF(AND($H3<S$2+7,$H3>S$2),3, IF(AND($F3<=S$2, $H3>=S$2), 2, "" ))) | ... AQ3: =IF(AND($F3<(AQ$2+7),$F3>AQ$2),1, IF(AND($H3<AQ$2+7,$H3>AQ$2),3, IF(AND($F3<=AQ$2, $H3>=AQ$2), 2, "" )))
A4: A | B4: PAYMENT MILESTONE 1: DEPOSIT | C4: 43832 | D4: 1 | E4: 43833 | F4: 43832 | G4: 1 | H4: 43833 | L4: =IF(AND($F4<(L$2+7),$F4>L$2),1, IF(AND($H4<L$2+7,$H4>L$2),3, IF(AND($F4<=L$2, $H4>=L$2), 2, "" ))) -> 1 | M4: =IF(AND($F4<(M$2+7),$F4>M$2),1, IF(AND($H4<M$2+7,$H4>M$2),3, IF(AND($F4<=M$2, $H4>=M$2), 2, "" ))) | N4: =IF(AND($F4<(N$2+7),$F4>N$2),1, IF(AND($H4<N$2+7,$H4>N$2),3, IF(AND($F4<=N$2, $H4>=N$2), 2, "" ))) | O4: =IF(AND($F4<(O$2+7),$F4>O$2),1, IF(AND($H4<O$2+7,$H4>O$2),3, IF(AND($F4<=O$2, $H4>=O$2), 2, "" ))) | P4: =IF(AND($F4<(P$2+7),$F4>P$2),1, IF(AND($H4<P$2+7,$H4>P$2),3, IF(AND($F4<=P$2, $H4>=P$2), 2, "" ))) | Q4: =IF(AND($F4<(Q$2+7),$F4>Q$2),1, IF(AND($H4<Q$2+7,$H4>Q$2),3, IF(AND($F4<=Q$2, $H4>=Q$2), 2, "" ))) | R4: =IF(AND($F4<(R$2+7),$F4>R$2),1, IF(AND($H4<R$2+7,$H4>R$2),3, IF(AND($F4<=R$2, $H4>=R$2), 2, "" ))) | S4: =IF(AND($F4<(S$2+7),$F4>S$2),1, IF(AND($H4<S$2+7,$H4>S$2),3, IF(AND($F4<=S$2, $H4>=S$2), 2, "" ))) | ... AQ4: =IF(AND($F4<(AQ$2+7),$F4>AQ$2),1, IF(AND($H4<AQ$2+7,$H4>AQ$2),3, IF(AND($F4<=AQ$2, $H4>=AQ$2), 2, "" )))
A5: 2 | B5: Structural and Electrical Due Diligences | C5: 43833 | D5: 5 | E5: 43840 | F5: 43833 | G5: 5 | H5: 43840 | L5: =IF(AND($F5<(L$2+7),$F5>L$2),1, IF(AND($H5<L$2+7,$H5>L$2),3, IF(AND($F5<=L$2, $H5>=L$2), 2, "" ))) -> 1 | M5: =IF(AND($F5<(M$2+7),$F5>M$2),1, IF(AND($H5<M$2+7,$H5>M$2),3, IF(AND($F5<=M$2, $H5>=M$2), 2, "" ))) -> 3 | N5: =IF(AND($F5<(N$2+7),$F5>N$2),1, IF(AND($H5<N$2+7,$H5>N$2),3, IF(AND($F5<=N$2, $H5>=N$2), 2, "" ))) | O5: =IF(AND($F5<(O$2+7),$F5>O$2),1, IF(AND($H5<O$2+7,$H5>O$2),3, IF(AND($F5<=O$2, $H5>=O$2), 2, "" ))) | P5: =IF(AND($F5<(P$2+7),$F5>P$2),1, IF(AND($H5<P$2+7,$H5>P$2),3, IF(AND($F5<=P$2, $H5>=P$2), 2, "" ))) | Q5: =IF(AND($F5<(Q$2+7),$F5>Q$2),1, IF(AND($H5<Q$2+7,$H5>Q$2),3, IF(AND($F5<=Q$2, $H5>=Q$2), 2, "" ))) | R5: =IF(AND($F5<(R$2+7),$F5>R$2),1, IF(AND($H5<R$2+7,$H5>R$2),3, IF(AND($F5<=R$2, $H5>=R$2), 2, "" ))) | S5: =IF(AND($F5<(S$2+7),$F5>S$2),1, IF(AND($H5<S$2+7,$H5>S$2),3, IF(AND($F5<=S$2, $H5>=S$2), 2, "" ))) | ... AQ5: =IF(AND($F5<(AQ$2+7),$F5>AQ$2),1, IF(AND($H5<AQ$2+7,$H5>AQ$2),3, IF(AND($F5<=AQ$2, $H5>=AQ$2), 2, "" )))
A6: 3 | B6: Design Confirmation | C6: 43841 | D6: 2 | E6: 43844 | F6: 43841 | G6: 2 | H6: 43844 | L6: =IF(AND($F6<(L$2+7),$F6>L$2),1, IF(AND($H6<L$2+7,$H6>L$2),3, IF(AND($F6<=L$2, $H6>=L$2), 2, "" ))) | M6: =IF(AND($F6<(M$2+7),$F6>M$2),1, IF(AND($H6<M$2+7,$H6>M$2),3, IF(AND($F6<=M$2, $H6>=M$2), 2, "" ))) | N6: =IF(AND($F6<(N$2+7),$F6>N$2),1, IF(AND($H6<N$2+7,$H6>N$2),3, IF(AND($F6<=N$2, $H6>=N$2), 2, "" ))) -> 3 | O6: =IF(AND($F6<(O$2+7),$F6>O$2),1, IF(AND($H6<O$2+7,$H6>O$2),3, IF(AND($F6<=O$2, $H6>=O$2), 2, "" ))) | P6: =IF(AND($F6<(P$2+7),$F6>P$2),1, IF(AND($H6<P$2+7,$H6>P$2),3, IF(AND($F6<=P$2, $H6>=P$2), 2, "" ))) | Q6: =IF(AND($F6<(Q$2+7),$F6>Q$2),1, IF(AND($H6<Q$2+7,$H6>Q$2),3, IF(AND($F6<=Q$2, $H6>=Q$2), 2, "" ))) | R6: =IF(AND($F6<(R$2+7),$F6>R$2),1, IF(AND($H6<R$2+7,$H6>R$2),3, IF(AND($F6<=R$2, $H6>=R$2), 2, "" ))) | S6: =IF(AND($F6<(S$2+7),$F6>S$2),1, IF(AND($H6<S$2+7,$H6>S$2),3, IF(AND($F6<=S$2, $H6>=S$2), 2, "" ))) | ... AQ6: =IF(AND($F6<(AQ$2+7),$F6>AQ$2),1, IF(AND($H6<AQ$2+7,$H6>AQ$2),3, IF(AND($F6<=AQ$2, $H6>=AQ$2), 2, "" )))
A7: 4 | B7: Equipment Procurement | C7: 43833 | E7: 43949 | F7: 43833 | H7: 43949 | L7: =IF(AND($F7<(L$2+7),$F7>L$2),1, IF(AND($H7<L$2+7,$H7>L$2),3, IF(AND($F7<=L$2, $H7>=L$2), 2, "" ))) -> 1 | M7: =IF(AND($F7<(M$2+7),$F7>M$2),1, IF(AND($H7<M$2+7,$H7>M$2),3, IF(AND($F7<=M$2, $H7>=M$2), 2, "" ))) -> 2 | N7: =IF(AND($F7<(N$2+7),$F7>N$2),1, IF(AND($H7<N$2+7,$H7>N$2),3, IF(AND($F7<=N$2, $H7>=N$2), 2, "" ))) -> 2 | O7: =IF(AND($F7<(O$2+7),$F7>O$2),1, IF(AND($H7<O$2+7,$H7>O$2),3, IF(AND($F7<=O$2, $H7>=O$2), 2, "" ))) -> 2 | P7: =IF(AND($F7<(P$2+7),$F7>P$2),1, IF(AND($H7<P$2+7,$H7>P$2),3, IF(AND($F7<=P$2, $H7>=P$2), 2, "" ))) -> 2 | Q7: =IF(AND($F7<(Q$2+7),$F7>Q$2),1, IF(AND($H7<Q$2+7,$H7>Q$2),3, IF(AND($F7<=Q$2, $H7>=Q$2), 2, "" ))) -> 2 | R7: =IF(AND($F7<(R$2+7),$F7>R$2),1, IF(AND($H7<R$2+7,$H7>R$2),3, IF(AND($F7<=R$2, $H7>=R$2), 2, "" ))) -> 2 | S7: =IF(AND($F7<(S$2+7),$F7>S$2),1, IF(AND($H7<S$2+7,$H7>S$2),3, IF(AND($F7<=S$2, $H7>=S$2), 2, "" ))) -> 2 | ... AQ7: =IF(AND($F7<(AQ$2+7),$F7>AQ$2),1, IF(AND($H7<AQ$2+7,$H7>AQ$2),3, IF(AND($F7<=AQ$2, $H7>=AQ$2), 2, "" )))
B8: Panel Procurement | C8: 43833 | D8: 5 | E8: 43840 | F8: 43833 | G8: 5 | H8: 43840 | L8: =IF(AND($F8<(L$2+7),$F8>L$2),1, IF(AND($H8<L$2+7,$H8>L$2),3, IF(AND($F8<=L$2, $H8>=L$2), 2, "" ))) -> 1 | M8: =IF(AND($F8<(M$2+7),$F8>M$2),1, IF(AND($H8<M$2+7,$H8>M$2),3, IF(AND($F8<=M$2, $H8>=M$2), 2, "" ))) -> 3 | N8: =IF(AND($F8<(N$2+7),$F8>N$2),1, IF(AND($H8<N$2+7,$H8>N$2),3, IF(AND($F8<=N$2, $H8>=N$2), 2, "" ))) | O8: =IF(AND($F8<(O$2+7),$F8>O$2),1, IF(AND($H8<O$2+7,$H8>O$2),3, IF(AND($F8<=O$2, $H8>=O$2), 2, "" ))) | P8: =IF(AND($F8<(P$2+7),$F8>P$2),1, IF(AND($H8<P$2+7,$H8>P$2),3, IF(AND($F8<=P$2, $H8>=P$2), 2, "" ))) | Q8: =IF(AND($F8<(Q$2+7),$F8>Q$2),1, IF(AND($H8<Q$2+7,$H8>Q$2),3, IF(AND($F8<=Q$2, $H8>=Q$2), 2, "" ))) | R8: =IF(AND($F8<(R$2+7),$F8>R$2),1, IF(AND($H8<R$2+7,$H8>R$2),3, IF(AND($F8<=R$2, $H8>=R$2), 2, "" ))) | S8: =IF(AND($F8<(S$2+7),$F8>S$2),1, IF(AND($H8<S$2+7,$H8>S$2),3, IF(AND($F8<=S$2, $H8>=S$2), 2, "" ))) | ... AQ8: =IF(AND($F8<(AQ$2+7),$F8>AQ$2),1, IF(AND($H8<AQ$2+7,$H8>AQ$2),3, IF(AND($F8<=AQ$2, $H8>=AQ$2), 2, "" )))
B9: Inverter Procurement | C9: 43941 | D9: 5 | E9: 43949 | F9: 43941 | G9: 5 | H9: 43949 | L9: =IF(AND($F9<(L$2+7),$F9>L$2),1, IF(AND($H9<L$2+7,$H9>L$2),3, IF(AND($F9<=L$2, $H9>=L$2), 2, "" ))) | M9: =IF(AND($F9<(M$2+7),$F9>M$2),1, IF(AND($H9<M$2+7,$H9>M$2),3, IF(AND($F9<=M$2, $H9>=M$2), 2, "" ))) | N9: =IF(AND($F9<(N$2+7),$F9>N$2),1, IF(AND($H9<N$2+7,$H9>N$2),3, IF(AND($F9<=N$2, $H9>=N$2), 2, "" ))) | O9: =IF(AND($F9<(O$2+7),$F9>O$2),1, IF(AND($H9<O$2+7,$H9>O$2),3, IF(AND($F9<=O$2, $H9>=O$2), 2, "" ))) | P9: =IF(AND($F9<(P$2+7),$F9>P$2),1, IF(AND($H9<P$2+7,$H9>P$2),3, IF(AND($F9<=P$2, $H9>=P$2), 2, "" ))) | Q9: =IF(AND($F9<(Q$2+7),$F9>Q$2),1, IF(AND($H9<Q$2+7,$H9>Q$2),3, IF(AND($F9<=Q$2, $H9>=Q$2), 2, "" ))) | R9: =IF(AND($F9<(R$2+7),$F9>R$2),1, IF(AND($H9<R$2+7,$H9>R$2),3, IF(AND($F9<=R$2, $H9>=R$2), 2, "" ))) | S9: =IF(AND($F9<(S$2+7),$F9>S$2),1, IF(AND($H9<S$2+7,$H9>S$2),3, IF(AND($F9<=S$2, $H9>=S$2), 2, "" ))) | ... AQ9: =IF(AND($F9<(AQ$2+7),$F9>AQ$2),1, IF(AND($H9<AQ$2+7,$H9>AQ$2),3, IF(AND($F9<=AQ$2, $H9>=AQ$2), 2, "" )))
B10: Mounting Structure Procurement | C10: 43941 | D10: 5 | E10: 43949 | F10: 43941 | G10: 5 | H10: 43949 | L10: =IF(AND($F10<(L$2+7),$F10>L$2),1, IF(AND($H10<L$2+7,$H10>L$2),3, IF(AND($F10<=L$2, $H10>=L$2), 2, "" ))) | M10: =IF(AND($F10<(M$2+7),$F10>M$2),1, IF(AND($H10<M$2+7,$H10>M$2),3, IF(AND($F10<=M$2, $H10>=M$2), 2, "" ))) | N10: =IF(AND($F10<(N$2+7),$F10>N$2),1, IF(AND($H10<N$2+7,$H10>N$2),3, IF(AND($F10<=N$2, $H10>=N$2), 2, "" ))) | O10: =IF(AND($F10<(O$2+7),$F10>O$2),1, IF(AND($H10<O$2+7,$H10>O$2),3, IF(AND($F10<=O$2, $H10>=O$2), 2, "" ))) | P10: =IF(AND($F10<(P$2+7),$F10>P$2),1, IF(AND($H10<P$2+7,$H10>P$2),3, IF(AND($F10<=P$2, $H10>=P$2), 2, "" ))) | Q10: =IF(AND($F10<(Q$2+7),$F10>Q$2),1, IF(AND($H10<Q$2+7,$H10>Q$2),3, IF(AND($F10<=Q$2, $H10>=Q$2), 2, "" ))) | R10: =IF(AND($F10<(R$2+7),$F10>R$2),1, IF(AND($H10<R$2+7,$H10>R$2),3, IF(AND($F10<=R$2, $H10>=R$2), 2, "" ))) | S10: =IF(AND($F10<(S$2+7),$F10>S$2),1, IF(AND($H10<S$2+7,$H10>S$2),3, IF(AND($F10<=S$2, $H10>=S$2), 2, "" ))) | ... AQ10: =IF(AND($F10<(AQ$2+7),$F10>AQ$2),1, IF(AND($H10<AQ$2+7,$H10>AQ$2),3, IF(AND($F10<=AQ$2, $H10>=AQ$2), 2, "" )))
B11: BOS Procurement | C11: 43941 | D11: 5 | E11: 43949 | F11: 43941 | G11: 5 | H11: 43949 | L11: =IF(AND($F11<(L$2+7),$F11>L$2),1, IF(AND($H11<L$2+7,$H11>L$2),3, IF(AND($F11<=L$2, $H11>=L$2), 2, "" ))) | M11: =IF(AND($F11<(M$2+7),$F11>M$2),1, IF(AND($H11<M$2+7,$H11>M$2),3, IF(AND($F11<=M$2, $H11>=M$2), 2, "" ))) | N11: =IF(AND($F11<(N$2+7),$F11>N$2),1, IF(AND($H11<N$2+7,$H11>N$2),3, IF(AND($F11<=N$2, $H11>=N$2), 2, "" ))) | O11: =IF(AND($F11<(O$2+7),$F11>O$2),1, IF(AND($H11<O$2+7,$H11>O$2),3, IF(AND($F11<=O$2, $H11>=O$2), 2, "" ))) | P11: =IF(AND($F11<(P$2+7),$F11>P$2),1, IF(AND($H11<P$2+7,$H11>P$2),3, IF(AND($F11<=P$2, $H11>=P$2), 2, "" ))) | Q11: =IF(AND($F11<(Q$2+7),$F11>Q$2),1, IF(AND($H11<Q$2+7,$H11>Q$2),3, IF(AND($F11<=Q$2, $H11>=Q$2), 2, "" ))) | R11: =IF(AND($F11<(R$2+7),$F11>R$2),1, IF(AND($H11<R$2+7,$H11>R$2),3, IF(AND($F11<=R$2, $H11>=R$2), 2, "" ))) | S11: =IF(AND($F11<(S$2+7),$F11>S$2),1, IF(AND($H11<S$2+7,$H11>S$2),3, IF(AND($F11<=S$2, $H11>=S$2), 2, "" ))) | ... AQ11: =IF(AND($F11<(AQ$2+7),$F11>AQ$2),1, IF(AND($H11<AQ$2+7,$H11>AQ$2),3, IF(AND($F11<=AQ$2, $H11>=AQ$2), 2, "" )))
A12: 5 | B12: Internal Project Kick off | C12: 43936 | D12: 5 | E12: 43943 | F12: 43936 | G12: 5 | H12: 43943
A13: 6 | B13: Client Project Kick-off | C13: 43963 | D13: 5 | E13: 43970 | F13: 43963 | G13: 5 | H13: 43970 | L13: =IF(AND($F13<(L$2+7),$F13>L$2),1, IF(AND($H13<L$2+7,$H13>L$2),3, IF(AND($F13<=L$2, $H13>=L$2), 2, "" ))) | M13: =IF(AND($F13<(M$2+7),$F13>M$2),1, IF(AND($H13<M$2+7,$H13>M$2),3, IF(AND($F13<=M$2, $H13>=M$2), 2, "" ))) | N13: =IF(AND($F13<(N$2+7),$F13>N$2),1, IF(AND($H13<N$2+7,$H13>N$2),3, IF(AND($F13<=N$2, $H13>=N$2), 2, "" ))) | O13: =IF(AND($F13<(O$2+7),$F13>O$2),1, IF(AND($H13<O$2+7,$H13>O$2),3, IF(AND($F13<=O$2, $H13>=O$2), 2, "" ))) | P13: =IF(AND($F13<(P$2+7),$F13>P$2),1, IF(AND($H13<P$2+7,$H13>P$2),3, IF(AND($F13<=P$2, $H13>=P$2), 2, "" ))) | Q13: =IF(AND($F13<(Q$2+7),$F13>Q$2),1, IF(AND($H13<Q$2+7,$H13>Q$2),3, IF(AND($F13<=Q$2, $H13>=Q$2), 2, "" ))) | R13: =IF(AND($F13<(R$2+7),$F13>R$2),1, IF(AND($H13<R$2+7,$H13>R$2),3, IF(AND($F13<=R$2, $H13>=R$2), 2, "" ))) | S13: =IF(AND($F13<(S$2+7),$F13>S$2),1, IF(AND($H13<S$2+7,$H13>S$2),3, IF(AND($F13<=S$2, $H13>=S$2), 2, "" ))) | ... AQ13: =IF(AND($F13<(AQ$2+7),$F13>AQ$2),1, IF(AND($H13<AQ$2+7,$H13>AQ$2),3, IF(AND($F13<=AQ$2, $H13>=AQ$2), 2, "" )))
A14: 7 | B14: Equipment Delivery | C14: 43983 | D14: 9 | E14: 43994 | F14: 43983 | G14: 9 | H14: 43994 | L14: =IF(AND($F14<(L$2+7),$F14>L$2),1, IF(AND($H14<L$2+7,$H14>L$2),3, IF(AND($F14<=L$2, $H14>=L$2), 2, "" ))) | M14: =IF(AND($F14<(M$2+7),$F14>M$2),1, IF(AND($H14<M$2+7,$H14>M$2),3, IF(AND($F14<=M$2, $H14>=M$2), 2, "" ))) | N14: =IF(AND($F14<(N$2+7),$F14>N$2),1, IF(AND($H14<N$2+7,$H14>N$2),3, IF(AND($F14<=N$2, $H14>=N$2), 2, "" ))) | O14: =IF(AND($F14<(O$2+7),$F14>O$2),1, IF(AND($H14<O$2+7,$H14>O$2),3, IF(AND($F14<=O$2, $H14>=O$2), 2, "" ))) | P14: =IF(AND($F14<(P$2+7),$F14>P$2),1, IF(AND($H14<P$2+7,$H14>P$2),3, IF(AND($F14<=P$2, $H14>=P$2), 2, "" ))) | Q14: =IF(AND($F14<(Q$2+7),$F14>Q$2),1, IF(AND($H14<Q$2+7,$H14>Q$2),3, IF(AND($F14<=Q$2, $H14>=Q$2), 2, "" ))) | R14: =IF(AND($F14<(R$2+7),$F14>R$2),1, IF(AND($H14<R$2+7,$H14>R$2),3, IF(AND($F14<=R$2, $H14>=R$2), 2, "" ))) | S14: =IF(AND($F14<(S$2+7),$F14>S$2),1, IF(AND($H14<S$2+7,$H14>S$2),3, IF(AND($F14<=S$2, $H14>=S$2), 2, "" ))) | ... AQ14: =IF(AND($F14<(AQ$2+7),$F14>AQ$2),1, IF(AND($H14<AQ$2+7,$H14>AQ$2),3, IF(AND($F14<=AQ$2, $H14>=AQ$2), 2, "" )))
B15: Mounting Structure Delivery | C15: 43983 | D15: 2 | E15: 43985 | F15: 43983 | G15: 2 | H15: 43985
B16: Panel Delivery | C16: 43990 | D16: 2 | E16: 43992 | F16: 43990 | G16: 2 | H16: 43992 | L16: =IF(AND($F16<(L$2+7),$F16>L$2),1, IF(AND($H16<L$2+7,$H16>L$2),3, IF(AND($F16<=L$2, $H16>=L$2), 2, "" ))) | M16: =IF(AND($F16<(M$2+7),$F16>M$2),1, IF(AND($H16<M$2+7,$H16>M$2),3, IF(AND($F16<=M$2, $H16>=M$2), 2, "" ))) | N16: =IF(AND($F16<(N$2+7),$F16>N$2),1, IF(AND($H16<N$2+7,$H16>N$2),3, IF(AND($F16<=N$2, $H16>=N$2), 2, "" ))) | O16: =IF(AND($F16<(O$2+7),$F16>O$2),1, IF(AND($H16<O$2+7,$H16>O$2),3, IF(AND($F16<=O$2, $H16>=O$2), 2, "" ))) | P16: =IF(AND($F16<(P$2+7),$F16>P$2),1, IF(AND($H16<P$2+7,$H16>P$2),3, IF(AND($F16<=P$2, $H16>=P$2), 2, "" ))) | Q16: =IF(AND($F16<(Q$2+7),$F16>Q$2),1, IF(AND($H16<Q$2+7,$H16>Q$2),3, IF(AND($F16<=Q$2, $H16>=Q$2), 2, "" ))) | R16: =IF(AND($F16<(R$2+7),$F16>R$2),1, IF(AND($H16<R$2+7,$H16>R$2),3, IF(AND($F16<=R$2, $H16>=R$2), 2, "" ))) | S16: =IF(AND($F16<(S$2+7),$F16>S$2),1, IF(AND($H16<S$2+7,$H16>S$2),3, IF(AND($F16<=S$2, $H16>=S$2), 2, "" ))) | ... AQ16: =IF(AND($F16<(AQ$2+7),$F16>AQ$2),1, IF(AND($H16<AQ$2+7,$H16>AQ$2),3, IF(AND($F16<=AQ$2, $H16>=AQ$2), 2, "" )))
B17: Generator Delivery | C17: 43983 | D17: 2 | E17: 43985 | F17: 43983 | G17: 2 | H17: 43985
A18: B | B18: PAYMENT MILESTONE 2: DELIVERY OF PV PANELS | C18: 43992 | D18: 2 | E18: 43994 | F18: 43992 | G18: 2 | H18: 43994
B19: Inverter Delivery | C19: 43983 | D19: 2 | E19: 43985 | F19: 43983 | G19: 2 | H19: 43985 | L19: =IF(AND($F19<(L$2+7),$F19>L$2),1, IF(AND($H19<L$2+7,$H19>L$2),3, IF(AND($F19<=L$2, $H19>=L$2), 2, "" ))) | M19: =IF(AND($F19<(M$2+7),$F19>M$2),1, IF(AND($H19<M$2+7,$H19>M$2),3, IF(AND($F19<=M$2, $H19>=M$2), 2, "" ))) | N19: =IF(AND($F19<(N$2+7),$F19>N$2),1, IF(AND($H19<N$2+7,$H19>N$2),3, IF(AND($F19<=N$2, $H19>=N$2), 2, "" ))) | O19: =IF(AND($F19<(O$2+7),$F19>O$2),1, IF(AND($H19<O$2+7,$H19>O$2),3, IF(AND($F19<=O$2, $H19>=O$2), 2, "" ))) | P19: =IF(AND($F19<(P$2+7),$F19>P$2),1, IF(AND($H19<P$2+7,$H19>P$2),3, IF(AND($F19<=P$2, $H19>=P$2), 2, "" ))) | Q19: =IF(AND($F19<(Q$2+7),$F19>Q$2),1, IF(AND($H19<Q$2+7,$H19>Q$2),3, IF(AND($F19<=Q$2, $H19>=Q$2), 2, "" ))) | R19: =IF(AND($F19<(R$2+7),$F19>R$2),1, IF(AND($H19<R$2+7,$H19>R$2),3, IF(AND($F19<=R$2, $H19>=R$2), 2, "" ))) | S19: =IF(AND($F19<(S$2+7),$F19>S$2),1, IF(AND($H19<S$2+7,$H19>S$2),3, IF(AND($F19<=S$2, $H19>=S$2), 2, "" ))) | ... AQ19: =IF(AND($F19<(AQ$2+7),$F19>AQ$2),1, IF(AND($H19<AQ$2+7,$H19>AQ$2),3, IF(AND($F19<=AQ$2, $H19>=AQ$2), 2, "" )))
B20: BOS Delivery | C20: 43983 | D20: 1 | E20: 43984 | F20: 43983 | G20: 1 | H20: 43984 | L20: =IF(AND($F20<(L$2+7),$F20>L$2),1, IF(AND($H20<L$2+7,$H20>L$2),3, IF(AND($F20<=L$2, $H20>=L$2), 2, "" ))) | M20: =IF(AND($F20<(M$2+7),$F20>M$2),1, IF(AND($H20<M$2+7,$H20>M$2),3, IF(AND($F20<=M$2, $H20>=M$2), 2, "" ))) | N20: =IF(AND($F20<(N$2+7),$F20>N$2),1, IF(AND($H20<N$2+7,$H20>N$2),3, IF(AND($F20<=N$2, $H20>=N$2), 2, "" ))) | O20: =IF(AND($F20<(O$2+7),$F20>O$2),1, IF(AND($H20<O$2+7,$H20>O$2),3, IF(AND($F20<=O$2, $H20>=O$2), 2, "" ))) | P20: =IF(AND($F20<(P$2+7),$F20>P$2),1, IF(AND($H20<P$2+7,$H20>P$2),3, IF(AND($F20<=P$2, $H20>=P$2), 2, "" ))) | Q20: =IF(AND($F20<(Q$2+7),$F20>Q$2),1, IF(AND($H20<Q$2+7,$H20>Q$2),3, IF(AND($F20<=Q$2, $H20>=Q$2), 2, "" ))) | R20: =IF(AND($F20<(R$2+7),$F20>R$2),1, IF(AND($H20<R$2+7,$H20>R$2),3, IF(AND($F20<=R$2, $H20>=R$2), 2, "" ))) | S20: =IF(AND($F20<(S$2+7),$F20>S$2),1, IF(AND($H20<S$2+7,$H20>S$2),3, IF(AND($F20<=S$2, $H20>=S$2), 2, "" ))) | ... AQ20: =IF(AND($F20<(AQ$2+7),$F20>AQ$2),1, IF(AND($H20<AQ$2+7,$H20>AQ$2),3, IF(AND($F20<=AQ$2, $H20>=AQ$2), 2, "" )))
A21: C | B21: PAYMENT MILESTONE 3: DELIVERY OF INVERTERS AND BOS | C21: 43985 | D21: 2 | E21: 43987 | F21: 43985 | G21: 2 | H21: 43987
A22: 8 | B22: Installation | C22: 43990 | D22: 22 | E22: 44012 | F22: 43990 | G22: 22 | H22: 44012 | L22: =IF(AND($F22<(L$2+7),$F22>L$2),1, IF(AND($H22<L$2+7,$H22>L$2),3, IF(AND($F22<=L$2, $H22>=L$2), 2, "" ))) | M22: =IF(AND($F22<(M$2+7),$F22>M$2),1, IF(AND($H22<M$2+7,$H22>M$2),3, IF(AND($F22<=M$2, $H22>=M$2), 2, "" ))) | N22: =IF(AND($F22<(N$2+7),$F22>N$2),1, IF(AND($H22<N$2+7,$H22>N$2),3, IF(AND($F22<=N$2, $H22>=N$2), 2, "" ))) | O22: =IF(AND($F22<(O$2+7),$F22>O$2),1, IF(AND($H22<O$2+7,$H22>O$2),3, IF(AND($F22<=O$2, $H22>=O$2), 2, "" ))) | P22: =IF(AND($F22<(P$2+7),$F22>P$2),1, IF(AND($H22<P$2+7,$H22>P$2),3, IF(AND($F22<=P$2, $H22>=P$2), 2, "" ))) | Q22: =IF(AND($F22<(Q$2+7),$F22>Q$2),1, IF(AND($H22<Q$2+7,$H22>Q$2),3, IF(AND($F22<=Q$2, $H22>=Q$2), 2, "" ))) | R22: =IF(AND($F22<(R$2+7),$F22>R$2),1, IF(AND($H22<R$2+7,$H22>R$2),3, IF(AND($F22<=R$2, $H22>=R$2), 2, "" ))) | S22: =IF(AND($F22<(S$2+7),$F22>S$2),1, IF(AND($H22<S$2+7,$H22>S$2),3, IF(AND($F22<=S$2, $H22>=S$2), 2, "" ))) | ... AQ22: =IF(AND($F22<(AQ$2+7),$F22>AQ$2),1, IF(AND($H22<AQ$2+7,$H22>AQ$2),3, IF(AND($F22<=AQ$2, $H22>=AQ$2), 2, "" ))) -> 2
B23: Site Establishment | C23: 43990 | D23: 1 | E23: 43991 | F23: 43990 | G23: 1 | H23: 43991 | J23: Installation placed on hold due to Covid-19 case | L23: =IF(AND($F23<(L$2+7),$F23>L$2),1, IF(AND($H23<L$2+7,$H23>L$2),3, IF(AND($F23<=L$2, $H23>=L$2), 2, "" ))) | M23: =IF(AND($F23<(M$2+7),$F23>M$2),1, IF(AND($H23<M$2+7,$H23>M$2),3, IF(AND($F23<=M$2, $H23>=M$2), 2, "" ))) | N23: =IF(AND($F23<(N$2+7),$F23>N$2),1, IF(AND($H23<N$2+7,$H23>N$2),3, IF(AND($F23<=N$2, $H23>=N$2), 2, "" ))) | O23: =IF(AND($F23<(O$2+7),$F23>O$2),1, IF(AND($H23<O$2+7,$H23>O$2),3, IF(AND($F23<=O$2, $H23>=O$2), 2, "" ))) | P23: =IF(AND($F23<(P$2+7),$F23>P$2),1, IF(AND($H23<P$2+7,$H23>P$2),3, IF(AND($F23<=P$2, $H23>=P$2), 2, "" ))) | Q23: =IF(AND($F23<(Q$2+7),$F23>Q$2),1, IF(AND($H23<Q$2+7,$H23>Q$2),3, IF(AND($F23<=Q$2, $H23>=Q$2), 2, "" ))) | R23: =IF(AND($F23<(R$2+7),$F23>R$2),1, IF(AND($H23<R$2+7,$H23>R$2),3, IF(AND($F23<=R$2, $H23>=R$2), 2, "" ))) | S23: =IF(AND($F23<(S$2+7),$F23>S$2),1, IF(AND($H23<S$2+7,$H23>S$2),3, IF(AND($F23<=S$2, $H23>=S$2), 2, "" ))) | ... AQ23: =IF(AND($F23<(AQ$2+7),$F23>AQ$2),1, IF(AND($H23<AQ$2+7,$H23>AQ$2),3, IF(AND($F23<=AQ$2, $H23>=AQ$2), 2, "" )))
A24: 9 | B24: DC Works | C24: 43991 | D24: 16 | E24: 44012 | F24: 43991 | G24: 16 | H24: 44012 | L24: =IF(AND($F24<(L$2+7),$F24>L$2),1, IF(AND($H24<L$2+7,$H24>L$2),3, IF(AND($F24<=L$2, $H24>=L$2), 2, "" ))) | M24: =IF(AND($F24<(M$2+7),$F24>M$2),1, IF(AND($H24<M$2+7,$H24>M$2),3, IF(AND($F24<=M$2, $H24>=M$2), 2, "" ))) | N24: =IF(AND($F24<(N$2+7),$F24>N$2),1, IF(AND($H24<N$2+7,$H24>N$2),3, IF(AND($F24<=N$2, $H24>=N$2), 2, "" ))) | O24: =IF(AND($F24<(O$2+7),$F24>O$2),1, IF(AND($H24<O$2+7,$H24>O$2),3, IF(AND($F24<=O$2, $H24>=O$2), 2, "" ))) | P24: =IF(AND($F24<(P$2+7),$F24>P$2),1, IF(AND($H24<P$2+7,$H24>P$2),3, IF(AND($F24<=P$2, $H24>=P$2), 2, "" ))) | Q24: =IF(AND($F24<(Q$2+7),$F24>Q$2),1, IF(AND($H24<Q$2+7,$H24>Q$2),3, IF(AND($F24<=Q$2, $H24>=Q$2), 2, "" ))) | R24: =IF(AND($F24<(R$2+7),$F24>R$2),1, IF(AND($H24<R$2+7,$H24>R$2),3, IF(AND($F24<=R$2, $H24>=R$2), 2, "" ))) | S24: =IF(AND($F24<(S$2+7),$F24>S$2),1, IF(AND($H24<S$2+7,$H24>S$2),3, IF(AND($F24<=S$2, $H24>=S$2), 2, "" ))) | ... AQ24: =IF(AND($F24<(AQ$2+7),$F24>AQ$2),1, IF(AND($H24<AQ$2+7,$H24>AQ$2),3, IF(AND($F24<=AQ$2, $H24>=AQ$2), 2, "" ))) -> 2
B25: Mounting structure Installation | C25: 43991 | D25: 4 | E25: 43997 | F25: 43991 | G25: 4 | H25: 43997 | L25: =IF(AND($F25<(L$2+7),$F25>L$2),1, IF(AND($H25<L$2+7,$H25>L$2),3, IF(AND($F25<=L$2, $H25>=L$2), 2, "" ))) | M25: =IF(AND($F25<(M$2+7),$F25>M$2),1, IF(AND($H25<M$2+7,$H25>M$2),3, IF(AND($F25<=M$2, $H25>=M$2), 2, "" ))) | N25: =IF(AND($F25<(N$2+7),$F25>N$2),1, IF(AND($H25<N$2+7,$H25>N$2),3, IF(AND($F25<=N$2, $H25>=N$2), 2, "" ))) | O25: =IF(AND($F25<(O$2+7),$F25>O$2),1, IF(AND($H25<O$2+7,$H25>O$2),3, IF(AND($F25<=O$2, $H25>=O$2), 2, "" ))) | P25: =IF(AND($F25<(P$2+7),$F25>P$2),1, IF(AND($H25<P$2+7,$H25>P$2),3, IF(AND($F25<=P$2, $H25>=P$2), 2, "" ))) | Q25: =IF(AND($F25<(Q$2+7),$F25>Q$2),1, IF(AND($H25<Q$2+7,$H25>Q$2),3, IF(AND($F25<=Q$2, $H25>=Q$2), 2, "" ))) | R25: =IF(AND($F25<(R$2+7),$F25>R$2),1, IF(AND($H25<R$2+7,$H25>R$2),3, IF(AND($F25<=R$2, $H25>=R$2), 2, "" ))) | S25: =IF(AND($F25<(S$2+7),$F25>S$2),1, IF(AND($H25<S$2+7,$H25>S$2),3, IF(AND($F25<=S$2, $H25>=S$2), 2, "" ))) | ... AQ25: =IF(AND($F25<(AQ$2+7),$F25>AQ$2),1, IF(AND($H25<AQ$2+7,$H25>AQ$2),3, IF(AND($F25<=AQ$2, $H25>=AQ$2), 2, "" )))
B26: Cable tray Installation | C26: 43997 | D26: 3 | E26: 44004 | F26: 43997 | G26: 3 | H26: 44004 | L26: =IF(AND($F26<(L$2+7),$F26>L$2),1, IF(AND($H26<L$2+7,$H26>L$2),3, IF(AND($F26<=L$2, $H26>=L$2), 2, "" ))) | M26: =IF(AND($F26<(M$2+7),$F26>M$2),1, IF(AND($H26<M$2+7,$H26>M$2),3, IF(AND($F26<=M$2, $H26>=M$2), 2, "" ))) | N26: =IF(AND($F26<(N$2+7),$F26>N$2),1, IF(AND($H26<N$2+7,$H26>N$2),3, IF(AND($F26<=N$2, $H26>=N$2), 2, "" ))) | O26: =IF(AND($F26<(O$2+7),$F26>O$2),1, IF(AND($H26<O$2+7,$H26>O$2),3, IF(AND($F26<=O$2, $H26>=O$2), 2, "" ))) | P26: =IF(AND($F26<(P$2+7),$F26>P$2),1, IF(AND($H26<P$2+7,$H26>P$2),3, IF(AND($F26<=P$2, $H26>=P$2), 2, "" ))) | Q26: =IF(AND($F26<(Q$2+7),$F26>Q$2),1, IF(AND($H26<Q$2+7,$H26>Q$2),3, IF(AND($F26<=Q$2, $H26>=Q$2), 2, "" ))) | R26: =IF(AND($F26<(R$2+7),$F26>R$2),1, IF(AND($H26<R$2+7,$H26>R$2),3, IF(AND($F26<=R$2, $H26>=R$2), 2, "" ))) | S26: =IF(AND($F26<(S$2+7),$F26>S$2),1, IF(AND($H26<S$2+7,$H26>S$2),3, IF(AND($F26<=S$2, $H26>=S$2), 2, "" ))) | ... AQ26: =IF(AND($F26<(AQ$2+7),$F26>AQ$2),1, IF(AND($H26<AQ$2+7,$H26>AQ$2),3, IF(AND($F26<=AQ$2, $H26>=AQ$2), 2, "" )))
B27: DC Cable Installation | C27: 44004 | D27: 2 | E27: 44006 | F27: 44004 | G27: 2 | H27: 44006 | L27: =IF(AND($F27<(L$2+7),$F27>L$2),1, IF(AND($H27<L$2+7,$H27>L$2),3, IF(AND($F27<=L$2, $H27>=L$2), 2, "" ))) | M27: =IF(AND($F27<(M$2+7),$F27>M$2),1, IF(AND($H27<M$2+7,$H27>M$2),3, IF(AND($F27<=M$2, $H27>=M$2), 2, "" ))) | N27: =IF(AND($F27<(N$2+7),$F27>N$2),1, IF(AND($H27<N$2+7,$H27>N$2),3, IF(AND($F27<=N$2, $H27>=N$2), 2, "" ))) | O27: =IF(AND($F27<(O$2+7),$F27>O$2),1, IF(AND($H27<O$2+7,$H27>O$2),3, IF(AND($F27<=O$2, $H27>=O$2), 2, "" ))) | P27: =IF(AND($F27<(P$2+7),$F27>P$2),1, IF(AND($H27<P$2+7,$H27>P$2),3, IF(AND($F27<=P$2, $H27>=P$2), 2, "" ))) | Q27: =IF(AND($F27<(Q$2+7),$F27>Q$2),1, IF(AND($H27<Q$2+7,$H27>Q$2),3, IF(AND($F27<=Q$2, $H27>=Q$2), 2, "" ))) | R27: =IF(AND($F27<(R$2+7),$F27>R$2),1, IF(AND($H27<R$2+7,$H27>R$2),3, IF(AND($F27<=R$2, $H27>=R$2), 2, "" ))) | S27: =IF(AND($F27<(S$2+7),$F27>S$2),1, IF(AND($H27<S$2+7,$H27>S$2),3, IF(AND($F27<=S$2, $H27>=S$2), 2, "" ))) | ... AQ27: =IF(AND($F27<(AQ$2+7),$F27>AQ$2),1, IF(AND($H27<AQ$2+7,$H27>AQ$2),3, IF(AND($F27<=AQ$2, $H27>=AQ$2), 2, "" )))
B28: Module Installation | C28: 44006 | D28: 4 | E28: 44012 | F28: 44006 | G28: 4 | H28: 44012 | L28: =IF(AND($F28<(L$2+7),$F28>L$2),1, IF(AND($H28<L$2+7,$H28>L$2),3, IF(AND($F28<=L$2, $H28>=L$2), 2, "" ))) | M28: =IF(AND($F28<(M$2+7),$F28>M$2),1, IF(AND($H28<M$2+7,$H28>M$2),3, IF(AND($F28<=M$2, $H28>=M$2), 2, "" ))) | N28: =IF(AND($F28<(N$2+7),$F28>N$2),1, IF(AND($H28<N$2+7,$H28>N$2),3, IF(AND($F28<=N$2, $H28>=N$2), 2, "" ))) | O28: =IF(AND($F28<(O$2+7),$F28>O$2),1, IF(AND($H28<O$2+7,$H28>O$2),3, IF(AND($F28<=O$2, $H28>=O$2), 2, "" ))) | P28: =IF(AND($F28<(P$2+7),$F28>P$2),1, IF(AND($H28<P$2+7,$H28>P$2),3, IF(AND($F28<=P$2, $H28>=P$2), 2, "" ))) | Q28: =IF(AND($F28<(Q$2+7),$F28>Q$2),1, IF(AND($H28<Q$2+7,$H28>Q$2),3, IF(AND($F28<=Q$2, $H28>=Q$2), 2, "" ))) | R28: =IF(AND($F28<(R$2+7),$F28>R$2),1, IF(AND($H28<R$2+7,$H28>R$2),3, IF(AND($F28<=R$2, $H28>=R$2), 2, "" ))) | S28: =IF(AND($F28<(S$2+7),$F28>S$2),1, IF(AND($H28<S$2+7,$H28>S$2),3, IF(AND($F28<=S$2, $H28>=S$2), 2, "" ))) | ... AQ28: =IF(AND($F28<(AQ$2+7),$F28>AQ$2),1, IF(AND($H28<AQ$2+7,$H28>AQ$2),3, IF(AND($F28<=AQ$2, $H28>=AQ$2), 2, "" ))) -> 2
B29: Earth Cable Installation | C29: 44004 | D29: 1 | E29: 44005 | F29: 44004 | G29: 1 | H29: 44005 | L29: =IF(AND($F29<(L$2+7),$F29>L$2),1, IF(AND($H29<L$2+7,$H29>L$2),3, IF(AND($F29<=L$2, $H29>=L$2), 2, "" ))) | M29: =IF(AND($F29<(M$2+7),$F29>M$2),1, IF(AND($H29<M$2+7,$H29>M$2),3, IF(AND($F29<=M$2, $H29>=M$2), 2, "" ))) | N29: =IF(AND($F29<(N$2+7),$F29>N$2),1, IF(AND($H29<N$2+7,$H29>N$2),3, IF(AND($F29<=N$2, $H29>=N$2), 2, "" ))) | O29: =IF(AND($F29<(O$2+7),$F29>O$2),1, IF(AND($H29<O$2+7,$H29>O$2),3, IF(AND($F29<=O$2, $H29>=O$2), 2, "" ))) | P29: =IF(AND($F29<(P$2+7),$F29>P$2),1, IF(AND($H29<P$2+7,$H29>P$2),3, IF(AND($F29<=P$2, $H29>=P$2), 2, "" ))) | Q29: =IF(AND($F29<(Q$2+7),$F29>Q$2),1, IF(AND($H29<Q$2+7,$H29>Q$2),3, IF(AND($F29<=Q$2, $H29>=Q$2), 2, "" ))) | R29: =IF(AND($F29<(R$2+7),$F29>R$2),1, IF(AND($H29<R$2+7,$H29>R$2),3, IF(AND($F29<=R$2, $H29>=R$2), 2, "" ))) | S29: =IF(AND($F29<(S$2+7),$F29>S$2),1, IF(AND($H29<S$2+7,$H29>S$2),3, IF(AND($F29<=S$2, $H29>=S$2), 2, "" ))) | ... AQ29: =IF(AND($F29<(AQ$2+7),$F29>AQ$2),1, IF(AND($H29<AQ$2+7,$H29>AQ$2),3, IF(AND($F29<=AQ$2, $H29>=AQ$2), 2, "" )))
A30: 10 | B30: AC Works | C30: 43991 | D30: 8 | E30: 44000 | F30: 43991 | G30: 8 | H30: 44000
B31: Inverters Installation | C31: 43991 | D31: 2 | E31: 43993 | F31: 43991 | G31: 2 | H31: 43993 | L31: =IF(AND($F31<(L$2+7),$F31>L$2),1, IF(AND($H31<L$2+7,$H31>L$2),3, IF(AND($F31<=L$2, $H31>=L$2), 2, "" ))) | M31: =IF(AND($F31<(M$2+7),$F31>M$2),1, IF(AND($H31<M$2+7,$H31>M$2),3, IF(AND($F31<=M$2, $H31>=M$2), 2, "" ))) | N31: =IF(AND($F31<(N$2+7),$F31>N$2),1, IF(AND($H31<N$2+7,$H31>N$2),3, IF(AND($F31<=N$2, $H31>=N$2), 2, "" ))) | O31: =IF(AND($F31<(O$2+7),$F31>O$2),1, IF(AND($H31<O$2+7,$H31>O$2),3, IF(AND($F31<=O$2, $H31>=O$2), 2, "" ))) | P31: =IF(AND($F31<(P$2+7),$F31>P$2),1, IF(AND($H31<P$2+7,$H31>P$2),3, IF(AND($F31<=P$2, $H31>=P$2), 2, "" ))) | Q31: =IF(AND($F31<(Q$2+7),$F31>Q$2),1, IF(AND($H31<Q$2+7,$H31>Q$2),3, IF(AND($F31<=Q$2, $H31>=Q$2), 2, "" ))) | R31: =IF(AND($F31<(R$2+7),$F31>R$2),1, IF(AND($H31<R$2+7,$H31>R$2),3, IF(AND($F31<=R$2, $H31>=R$2), 2, "" ))) | S31: =IF(AND($F31<(S$2+7),$F31>S$2),1, IF(AND($H31<S$2+7,$H31>S$2),3, IF(AND($F31<=S$2, $H31>=S$2), 2, "" ))) | ... AQ31: =IF(AND($F31<(AQ$2+7),$F31>AQ$2),1, IF(AND($H31<AQ$2+7,$H31>AQ$2),3, IF(AND($F31<=AQ$2, $H31>=AQ$2), 2, "" )))
B32: AC BOS Installation | C32: 43993 | D32: 3 | E32: 44000 | F32: 43993 | G32: 3 | H32: 44000 | L32: =IF(AND($F32<(L$2+7),$F32>L$2),1, IF(AND($H32<L$2+7,$H32>L$2),3, IF(AND($F32<=L$2, $H32>=L$2), 2, "" ))) | M32: =IF(AND($F32<(M$2+7),$F32>M$2),1, IF(AND($H32<M$2+7,$H32>M$2),3, IF(AND($F32<=M$2, $H32>=M$2), 2, "" ))) | N32: =IF(AND($F32<(N$2+7),$F32>N$2),1, IF(AND($H32<N$2+7,$H32>N$2),3, IF(AND($F32<=N$2, $H32>=N$2), 2, "" ))) | O32: =IF(AND($F32<(O$2+7),$F32>O$2),1, IF(AND($H32<O$2+7,$H32>O$2),3, IF(AND($F32<=O$2, $H32>=O$2), 2, "" ))) | P32: =IF(AND($F32<(P$2+7),$F32>P$2),1, IF(AND($H32<P$2+7,$H32>P$2),3, IF(AND($F32<=P$2, $H32>=P$2), 2, "" ))) | Q32: =IF(AND($F32<(Q$2+7),$F32>Q$2),1, IF(AND($H32<Q$2+7,$H32>Q$2),3, IF(AND($F32<=Q$2, $H32>=Q$2), 2, "" ))) | R32: =IF(AND($F32<(R$2+7),$F32>R$2),1, IF(AND($H32<R$2+7,$H32>R$2),3, IF(AND($F32<=R$2, $H32>=R$2), 2, "" ))) | S32: =IF(AND($F32<(S$2+7),$F32>S$2),1, IF(AND($H32<S$2+7,$H32>S$2),3, IF(AND($F32<=S$2, $H32>=S$2), 2, "" ))) | ... AQ32: =IF(AND($F32<(AQ$2+7),$F32>AQ$2),1, IF(AND($H32<AQ$2+7,$H32>AQ$2),3, IF(AND($F32<=AQ$2, $H32>=AQ$2), 2, "" )))
B33: AC Cable/Tie-In | C33: 43992 | D33: 3 | E33: 43997 | F33: 43992 | G33: 3 | H33: 43997 | L33: =IF(AND($F33<(L$2+7),$F33>L$2),1, IF(AND($H33<L$2+7,$H33>L$2),3, IF(AND($F33<=L$2, $H33>=L$2), 2, "" ))) | M33: =IF(AND($F33<(M$2+7),$F33>M$2),1, IF(AND($H33<M$2+7,$H33>M$2),3, IF(AND($F33<=M$2, $H33>=M$2), 2, "" ))) | N33: =IF(AND($F33<(N$2+7),$F33>N$2),1, IF(AND($H33<N$2+7,$H33>N$2),3, IF(AND($F33<=N$2, $H33>=N$2), 2, "" ))) | O33: =IF(AND($F33<(O$2+7),$F33>O$2),1, IF(AND($H33<O$2+7,$H33>O$2),3, IF(AND($F33<=O$2, $H33>=O$2), 2, "" ))) | P33: =IF(AND($F33<(P$2+7),$F33>P$2),1, IF(AND($H33<P$2+7,$H33>P$2),3, IF(AND($F33<=P$2, $H33>=P$2), 2, "" ))) | Q33: =IF(AND($F33<(Q$2+7),$F33>Q$2),1, IF(AND($H33<Q$2+7,$H33>Q$2),3, IF(AND($F33<=Q$2, $H33>=Q$2), 2, "" ))) | R33: =IF(AND($F33<(R$2+7),$F33>R$2),1, IF(AND($H33<R$2+7,$H33>R$2),3, IF(AND($F33<=R$2, $H33>=R$2), 2, "" ))) | S33: =IF(AND($F33<(S$2+7),$F33>S$2),1, IF(AND($H33<S$2+7,$H33>S$2),3, IF(AND($F33<=S$2, $H33>=S$2), 2, "" ))) | ... AQ33: =IF(AND($F33<(AQ$2+7),$F33>AQ$2),1, IF(AND($H33<AQ$2+7,$H33>AQ$2),3, IF(AND($F33<=AQ$2, $H33>=AQ$2), 2, "" )))
B34: Monitoring Platform Installation | C34: 43997 | D34: 1 | E34: 44000 | F34: 43997 | G34: 1 | H34: 44000
A35: 11 | B35: Completion | C35: 44000 | D35: 14 | E35: 44014 | F35: 44000 | G35: 14 | H35: 44014 | L35: =IF(AND($F35<(L$2+7),$F35>L$2),1, IF(AND($H35<L$2+7,$H35>L$2),3, IF(AND($F35<=L$2, $H35>=L$2), 2, "" ))) | M35: =IF(AND($F35<(M$2+7),$F35>M$2),1, IF(AND($H35<M$2+7,$H35>M$2),3, IF(AND($F35<=M$2, $H35>=M$2), 2, "" ))) | N35: =IF(AND($F35<(N$2+7),$F35>N$2),1, IF(AND($H35<N$2+7,$H35>N$2),3, IF(AND($F35<=N$2, $H35>=N$2), 2, "" ))) | O35: =IF(AND($F35<(O$2+7),$F35>O$2),1, IF(AND($H35<O$2+7,$H35>O$2),3, IF(AND($F35<=O$2, $H35>=O$2), 2, "" ))) | P35: =IF(AND($F35<(P$2+7),$F35>P$2),1, IF(AND($H35<P$2+7,$H35>P$2),3, IF(AND($F35<=P$2, $H35>=P$2), 2, "" ))) | Q35: =IF(AND($F35<(Q$2+7),$F35>Q$2),1, IF(AND($H35<Q$2+7,$H35>Q$2),3, IF(AND($F35<=Q$2, $H35>=Q$2), 2, "" ))) | R35: =IF(AND($F35<(R$2+7),$F35>R$2),1, IF(AND($H35<R$2+7,$H35>R$2),3, IF(AND($F35<=R$2, $H35>=R$2), 2, "" ))) | S35: =IF(AND($F35<(S$2+7),$F35>S$2),1, IF(AND($H35<S$2+7,$H35>S$2),3, IF(AND($F35<=S$2, $H35>=S$2), 2, "" ))) | ... AQ35: =IF(AND($F35<(AQ$2+7),$F35>AQ$2),1, IF(AND($H35<AQ$2+7,$H35>AQ$2),3, IF(AND($F35<=AQ$2, $H35>=AQ$2), 2, "" ))) -> 3
B36: DC Works | C36: 44012 | D36: 2 | E36: 44014 | F36: 44012 | G36: 2 | H36: 44014 | L36: =IF(AND($F36<(L$2+7),$F36>L$2),1, IF(AND($H36<L$2+7,$H36>L$2),3, IF(AND($F36<=L$2, $H36>=L$2), 2, "" ))) | M36: =IF(AND($F36<(M$2+7),$F36>M$2),1, IF(AND($H36<M$2+7,$H36>M$2),3, IF(AND($F36<=M$2, $H36>=M$2), 2, "" ))) | N36: =IF(AND($F36<(N$2+7),$F36>N$2),1, IF(AND($H36<N$2+7,$H36>N$2),3, IF(AND($F36<=N$2, $H36>=N$2), 2, "" ))) | O36: =IF(AND($F36<(O$2+7),$F36>O$2),1, IF(AND($H36<O$2+7,$H36>O$2),3, IF(AND($F36<=O$2, $H36>=O$2), 2, "" ))) | P36: =IF(AND($F36<(P$2+7),$F36>P$2),1, IF(AND($H36<P$2+7,$H36>P$2),3, IF(AND($F36<=P$2, $H36>=P$2), 2, "" ))) | Q36: =IF(AND($F36<(Q$2+7),$F36>Q$2),1, IF(AND($H36<Q$2+7,$H36>Q$2),3, IF(AND($F36<=Q$2, $H36>=Q$2), 2, "" ))) | R36: =IF(AND($F36<(R$2+7),$F36>R$2),1, IF(AND($H36<R$2+7,$H36>R$2),3, IF(AND($F36<=R$2, $H36>=R$2), 2, "" ))) | S36: =IF(AND($F36<(S$2+7),$F36>S$2),1, IF(AND($H36<S$2+7,$H36>S$2),3, IF(AND($F36<=S$2, $H36>=S$2), 2, "" ))) | ... AQ36: =IF(AND($F36<(AQ$2+7),$F36>AQ$2),1, IF(AND($H36<AQ$2+7,$H36>AQ$2),3, IF(AND($F36<=AQ$2, $H36>=AQ$2), 2, "" ))) -> 3
B37: AC Works | C37: 44000 | D37: 2 | E37: 44004 | F37: 44000 | G37: 2 | H37: 44004 | L37: =IF(AND($F37<(L$2+7),$F37>L$2),1, IF(AND($H37<L$2+7,$H37>L$2),3, IF(AND($F37<=L$2, $H37>=L$2), 2, "" ))) | M37: =IF(AND($F37<(M$2+7),$F37>M$2),1, IF(AND($H37<M$2+7,$H37>M$2),3, IF(AND($F37<=M$2, $H37>=M$2), 2, "" ))) | N37: =IF(AND($F37<(N$2+7),$F37>N$2),1, IF(AND($H37<N$2+7,$H37>N$2),3, IF(AND($F37<=N$2, $H37>=N$2), 2, "" ))) | O37: =IF(AND($F37<(O$2+7),$F37>O$2),1, IF(AND($H37<O$2+7,$H37>O$2),3, IF(AND($F37<=O$2, $H37>=O$2), 2, "" ))) | P37: =IF(AND($F37<(P$2+7),$F37>P$2),1, IF(AND($H37<P$2+7,$H37>P$2),3, IF(AND($F37<=P$2, $H37>=P$2), 2, "" ))) | Q37: =IF(AND($F37<(Q$2+7),$F37>Q$2),1, IF(AND($H37<Q$2+7,$H37>Q$2),3, IF(AND($F37<=Q$2, $H37>=Q$2), 2, "" ))) | R37: =IF(AND($F37<(R$2+7),$F37>R$2),1, IF(AND($H37<R$2+7,$H37>R$2),3, IF(AND($F37<=R$2, $H37>=R$2), 2, "" ))) | S37: =IF(AND($F37<(S$2+7),$F37>S$2),1, IF(AND($H37<S$2+7,$H37>S$2),3, IF(AND($F37<=S$2, $H37>=S$2), 2, "" ))) | ... AQ37: =IF(AND($F37<(AQ$2+7),$F37>AQ$2),1, IF(AND($H37<AQ$2+7,$H37>AQ$2),3, IF(AND($F37<=AQ$2, $H37>=AQ$2), 2, "" )))
A38: D | B38: PAYMENT MILESTONE 4: PRACTICAL COMPLETION | C38: 44012 | D38: 1 | E38: 44013 | F38: 44012 | G38: 1 | H38: 44013 | L38: =IF(AND($F38<(L$2+7),$F38>L$2),1, IF(AND($H38<L$2+7,$H38>L$2),3, IF(AND($F38<=L$2, $H38>=L$2), 2, "" ))) | M38: =IF(AND($F38<(M$2+7),$F38>M$2),1, IF(AND($H38<M$2+7,$H38>M$2),3, IF(AND($F38<=M$2, $H38>=M$2), 2, "" ))) | N38: =IF(AND($F38<(N$2+7),$F38>N$2),1, IF(AND($H38<N$2+7,$H38>N$2),3, IF(AND($F38<=N$2, $H38>=N$2), 2, "" ))) | O38: =IF(AND($F38<(O$2+7),$F38>O$2),1, IF(AND($H38<O$2+7,$H38>O$2),3, IF(AND($F38<=O$2, $H38>=O$2), 2, "" ))) | P38: =IF(AND($F38<(P$2+7),$F38>P$2),1, IF(AND($H38<P$2+7,$H38>P$2),3, IF(AND($F38<=P$2, $H38>=P$2), 2, "" ))) | Q38: =IF(AND($F38<(Q$2+7),$F38>Q$2),1, IF(AND($H38<Q$2+7,$H38>Q$2),3, IF(AND($F38<=Q$2, $H38>=Q$2), 2, "" ))) | R38: =IF(AND($F38<(R$2+7),$F38>R$2),1, IF(AND($H38<R$2+7,$H38>R$2),3, IF(AND($F38<=R$2, $H38>=R$2), 2, "" ))) | S38: =IF(AND($F38<(S$2+7),$F38>S$2),1, IF(AND($H38<S$2+7,$H38>S$2),3, IF(AND($F38<=S$2, $H38>=S$2), 2, "" ))) | ... AQ38: =IF(AND($F38<(AQ$2+7),$F38>AQ$2),1, IF(AND($H38<AQ$2+7,$H38>AQ$2),3, IF(AND($F38<=AQ$2, $H38>=AQ$2), 2, "" ))) -> 3
A39: 12 | B39: Commissioning | C39: 43997 | D39: 22 | E39: 44019 | F39: 43997 | G39: 22 | H39: 44019 | L39: =IF(AND($F39<(L$2+7),$F39>L$2),1, IF(AND($H39<L$2+7,$H39>L$2),3, IF(AND($F39<=L$2, $H39>=L$2), 2, "" ))) | M39: =IF(AND($F39<(M$2+7),$F39>M$2),1, IF(AND($H39<M$2+7,$H39>M$2),3, IF(AND($F39<=M$2, $H39>=M$2), 2, "" ))) | N39: =IF(AND($F39<(N$2+7),$F39>N$2),1, IF(AND($H39<N$2+7,$H39>N$2),3, IF(AND($F39<=N$2, $H39>=N$2), 2, "" ))) | O39: =IF(AND($F39<(O$2+7),$F39>O$2),1, IF(AND($H39<O$2+7,$H39>O$2),3, IF(AND($F39<=O$2, $H39>=O$2), 2, "" ))) | P39: =IF(AND($F39<(P$2+7),$F39>P$2),1, IF(AND($H39<P$2+7,$H39>P$2),3, IF(AND($F39<=P$2, $H39>=P$2), 2, "" ))) | Q39: =IF(AND($F39<(Q$2+7),$F39>Q$2),1, IF(AND($H39<Q$2+7,$H39>Q$2),3, IF(AND($F39<=Q$2, $H39>=Q$2), 2, "" ))) | R39: =IF(AND($F39<(R$2+7),$F39>R$2),1, IF(AND($H39<R$2+7,$H39>R$2),3, IF(AND($F39<=R$2, $H39>=R$2), 2, "" ))) | S39: =IF(AND($F39<(S$2+7),$F39>S$2),1, IF(AND($H39<S$2+7,$H39>S$2),3, IF(AND($F39<=S$2, $H39>=S$2), 2, "" ))) | ... AQ39: =IF(AND($F39<(AQ$2+7),$F39>AQ$2),1, IF(AND($H39<AQ$2+7,$H39>AQ$2),3, IF(AND($F39<=AQ$2, $H39>=AQ$2), 2, "" ))) -> 2
B40: Snag List | C40: 44014 | D40: 3 | E40: 44019 | F40: 44014 | G40: 3 | H40: 44019
B41: Pre-Commissioning Checks | C41: 44010 | D41: 2 | E41: 44012 | F41: 44010 | G41: 2 | H41: 44012
B42: Issue CoC | C42: 43997 | D42: 2 | E42: 44001 | F42: 43997 | G42: 2 | H42: 44001 | L42: =IF(AND($F42<(L$2+7),$F42>L$2),1, IF(AND($H42<L$2+7,$H42>L$2),3, IF(AND($F42<=L$2, $H42>=L$2), 2, "" ))) | M42: =IF(AND($F42<(M$2+7),$F42>M$2),1, IF(AND($H42<M$2+7,$H42>M$2),3, IF(AND($F42<=M$2, $H42>=M$2), 2, "" ))) | N42: =IF(AND($F42<(N$2+7),$F42>N$2),1, IF(AND($H42<N$2+7,$H42>N$2),3, IF(AND($F42<=N$2, $H42>=N$2), 2, "" ))) | O42: =IF(AND($F42<(O$2+7),$F42>O$2),1, IF(AND($H42<O$2+7,$H42>O$2),3, IF(AND($F42<=O$2, $H42>=O$2), 2, "" ))) | P42: =IF(AND($F42<(P$2+7),$F42>P$2),1, IF(AND($H42<P$2+7,$H42>P$2),3, IF(AND($F42<=P$2, $H42>=P$2), 2, "" ))) | Q42: =IF(AND($F42<(Q$2+7),$F42>Q$2),1, IF(AND($H42<Q$2+7,$H42>Q$2),3, IF(AND($F42<=Q$2, $H42>=Q$2), 2, "" ))) | R42: =IF(AND($F42<(R$2+7),$F42>R$2),1, IF(AND($H42<R$2+7,$H42>R$2),3, IF(AND($F42<=R$2, $H42>=R$2), 2, "" ))) | S42: =IF(AND($F42<(S$2+7),$F42>S$2),1, IF(AND($H42<S$2+7,$H42>S$2),3, IF(AND($F42<=S$2, $H42>=S$2), 2, "" ))) | ... AQ42: =IF(AND($F42<(AQ$2+7),$F42>AQ$2),1, IF(AND($H42<AQ$2+7,$H42>AQ$2),3, IF(AND($F42<=AQ$2, $H42>=AQ$2), 2, "" )))
B43: Cold Commissioning | C43: 44012 | D43: 1 | E43: 44013 | F43: 44012 | G43: 1 | H43: 44013 | L43: =IF(AND($F43<(L$2+7),$F43>L$2),1, IF(AND($H43<L$2+7,$H43>L$2),3, IF(AND($F43<=L$2, $H43>=L$2), 2, "" ))) | M43: =IF(AND($F43<(M$2+7),$F43>M$2),1, IF(AND($H43<M$2+7,$H43>M$2),3, IF(AND($F43<=M$2, $H43>=M$2), 2, "" ))) | N43: =IF(AND($F43<(N$2+7),$F43>N$2),1, IF(AND($H43<N$2+7,$H43>N$2),3, IF(AND($F43<=N$2, $H43>=N$2), 2, "" ))) | O43: =IF(AND($F43<(O$2+7),$F43>O$2),1, IF(AND($H43<O$2+7,$H43>O$2),3, IF(AND($F43<=O$2, $H43>=O$2), 2, "" ))) | P43: =IF(AND($F43<(P$2+7),$F43>P$2),1, IF(AND($H43<P$2+7,$H43>P$2),3, IF(AND($F43<=P$2, $H43>=P$2), 2, "" ))) | Q43: =IF(AND($F43<(Q$2+7),$F43>Q$2),1, IF(AND($H43<Q$2+7,$H43>Q$2),3, IF(AND($F43<=Q$2, $H43>=Q$2), 2, "" ))) | R43: =IF(AND($F43<(R$2+7),$F43>R$2),1, IF(AND($H43<R$2+7,$H43>R$2),3, IF(AND($F43<=R$2, $H43>=R$2), 2, "" ))) | S43: =IF(AND($F43<(S$2+7),$F43>S$2),1, IF(AND($H43<S$2+7,$H43>S$2),3, IF(AND($F43<=S$2, $H43>=S$2), 2, "" ))) | ... AQ43: =IF(AND($F43<(AQ$2+7),$F43>AQ$2),1, IF(AND($H43<AQ$2+7,$H43>AQ$2),3, IF(AND($F43<=AQ$2, $H43>=AQ$2), 2, "" ))) -> 3
B44: Hot Commissioning | C44: 44013 | D44: 2 | E44: 44015 | F44: 44013 | G44: 2 | H44: 44015 | L44: =IF(AND($F44<(L$2+7),$F44>L$2),1, IF(AND($H44<L$2+7,$H44>L$2),3, IF(AND($F44<=L$2, $H44>=L$2), 2, "" ))) | M44: =IF(AND($F44<(M$2+7),$F44>M$2),1, IF(AND($H44<M$2+7,$H44>M$2),3, IF(AND($F44<=M$2, $H44>=M$2), 2, "" ))) | N44: =IF(AND($F44<(N$2+7),$F44>N$2),1, IF(AND($H44<N$2+7,$H44>N$2),3, IF(AND($F44<=N$2, $H44>=N$2), 2, "" ))) | O44: =IF(AND($F44<(O$2+7),$F44>O$2),1, IF(AND($H44<O$2+7,$H44>O$2),3, IF(AND($F44<=O$2, $H44>=O$2), 2, "" ))) | P44: =IF(AND($F44<(P$2+7),$F44>P$2),1, IF(AND($H44<P$2+7,$H44>P$2),3, IF(AND($F44<=P$2, $H44>=P$2), 2, "" ))) | Q44: =IF(AND($F44<(Q$2+7),$F44>Q$2),1, IF(AND($H44<Q$2+7,$H44>Q$2),3, IF(AND($F44<=Q$2, $H44>=Q$2), 2, "" ))) | R44: =IF(AND($F44<(R$2+7),$F44>R$2),1, IF(AND($H44<R$2+7,$H44>R$2),3, IF(AND($F44<=R$2, $H44>=R$2), 2, "" ))) | S44: =IF(AND($F44<(S$2+7),$F44>S$2),1, IF(AND($H44<S$2+7,$H44>S$2),3, IF(AND($F44<=S$2, $H44>=S$2), 2, "" ))) | ... AQ44: =IF(AND($F44<(AQ$2+7),$F44>AQ$2),1, IF(AND($H44<AQ$2+7,$H44>AQ$2),3, IF(AND($F44<=AQ$2, $H44>=AQ$2), 2, "" ))) -> 1
A45: 13 | B45: Handover | C45: 44020 | D45: 1 | E45: 44021 | F45: 44020 | G45: 1 | H45: 44021 | L45: =IF(AND($F45<(L$2+7),$F45>L$2),1, IF(AND($H45<L$2+7,$H45>L$2),3, IF(AND($F45<=L$2, $H45>=L$2), 2, "" ))) | M45: =IF(AND($F45<(M$2+7),$F45>M$2),1, IF(AND($H45<M$2+7,$H45>M$2),3, IF(AND($F45<=M$2, $H45>=M$2), 2, "" ))) | N45: =IF(AND($F45<(N$2+7),$F45>N$2),1, IF(AND($H45<N$2+7,$H45>N$2),3, IF(AND($F45<=N$2, $H45>=N$2), 2, "" ))) | O45: =IF(AND($F45<(O$2+7),$F45>O$2),1, IF(AND($H45<O$2+7,$H45>O$2),3, IF(AND($F45<=O$2, $H45>=O$2), 2, "" ))) | P45: =IF(AND($F45<(P$2+7),$F45>P$2),1, IF(AND($H45<P$2+7,$H45>P$2),3, IF(AND($F45<=P$2, $H45>=P$2), 2, "" ))) | Q45: =IF(AND($F45<(Q$2+7),$F45>Q$2),1, IF(AND($H45<Q$2+7,$H45>Q$2),3, IF(AND($F45<=Q$2, $H45>=Q$2), 2, "" ))) | R45: =IF(AND($F45<(R$2+7),$F45>R$2),1, IF(AND($H45<R$2+7,$H45>R$2),3, IF(AND($F45<=R$2, $H45>=R$2), 2, "" ))) | S45: =IF(AND($F45<(S$2+7),$F45>S$2),1, IF(AND($H45<S$2+7,$H45>S$2),3, IF(AND($F45<=S$2, $H45>=S$2), 2, "" ))) | ... AQ45: =IF(AND($F45<(AQ$2+7),$F45>AQ$2),1, IF(AND($H45<AQ$2+7,$H45>AQ$2),3, IF(AND($F45<=AQ$2, $H45>=AQ$2), 2, "" )))
A46: E | B46: PAYMENT MILESTONE 6: HANDOVER COMPLETE | C46: 44022 | D46: 1 | E46: 44025 | F46: 44022 | G46: 1 | H46: 44025
C47: 43831 | D47: These numbers are used to set the start and end dates on the Gantt Chart
C48: 44014

Sheet Certificate - Financial Close
B2: Emergent Energy – Financial Close Completion Certificate | H2: FINANCIAL CLOSE CERTIFICATE
B4: Project Name: | C4: ='Project Plan'!E2 -> Seshego Circle
B5: COO: | C5: Johannes Potgieter
B6: Programme Manager: | C6: Roedolph Venter
B7: HoPD: | C7: Natasha Watkins-Baker
B9: Date of Phase Completion:
B10: Phase Deliverables Checklist: (Y/N)
B11: Product Agreement
B12: EPC Agreement
B13: O&M Agreeement
B14: Cost Proposal
B15: Deposit Received
B16: Risks / Notes
B18: Acknowledgement and Acceptance:
B19: Role | C19: Name | D19: Signature | E19: Date

Sheet Certificate - Planning
B2: Emergent Energy – Planning Phase Completion Certificate | H2: PLANNING CERTIFICATE
B4: Project Name: | C4: ='Project Plan'!E2 -> Seshego Circle
B5: Client Representative:
B6: Programme Manager: | C6: Roedolph Venter
B7: Project Manager: | C7: ='Project Plan'!E5 -> Eon Van Rensburg
B8: Project Engineer:
B10: Date of Phase Completion:
B11: Phase Deliverables Checklist: (Y/N)
B12: Project Introduction Presentation
B13: Project Brief
B14: Engineering Pack
B15: BOQ
B16: PO – Material & Equipment
B17: PO - Contractors
B18: HSE – NOC
B19: HSE – EE File
B20: HSE – Contractor File
... B24: Acknowledgement and Acceptance:
B25: Role | C25: Name | D25: Signature | E25: Date

Sheet Change Register
F1: Change Register
B3: ID | C3: Description | D3: Supporting Image (If Applicable) | E3: Impact | F3: Proposed Date | G3: Proposed By | H3: Status | I3: Approved By | J3: Approved Date | K3: Results / Comments
B4: DEC001 | C4: We need to manufacture Tie-In Kiosks because of space contraints in the Mini-subs | E4: AC tie-in delay | F4: 46056 | G4: Peet | H4: In Progress
B5: DEC002
B6: DEC003
B7: DEC004
B8: DEC005
B9: DEC006
B10: DEC007
B11: DEC008
B12: DEC009
B13: DEC010
B14: DEC011
B15: DEC012
B16: DEC013
... B33: DEC030

Sheet BOQ
B2: Item | C2: Supplier | D2: Description | E2: Quantity | F2: Comments
B3: PV Module
B4: DC Cable Red & Black
B5: Inverters
B6: Mounting Structure
B7: Current Transformers (Production)
B8: Current Transformers (Consumption)
B9: Solar Production Meter (Techistter)
B10: Grid Consumption Meter
B11: Wi-Fi Router & Sim
B12: Switch
B13: Back Up Battery
B14: PVDB
... B30: Techsitter

Sheet Compliance
B2: HSE
B4: Description | C4: Status | D4: Approved By | E4: Date | F4: Results / Comments
B5: NOC
B6: 7.1 Agreement
B7: 13.2 Agreement
B8: EE File
B9: Subbie File
B16: SSEG
B18: Description | C18: Status | D18: Approved By | E18: Date | F18: Results / Comments
B19: SSEG Application
B20: PTI
B21: Commissioning Approval

Sheet Project Plan
N1: =TODAY() -> 46069 | O1: =TODAY() -> 46069
C2: PROJECT PLAN | E2: Seshego Circle | N2: 0 | O2: Kios
C3: PROJECT SIZE (kWp) | E3: 1360 | O3: AC kiosk delay TBC AC Tie in delay. **RISK**
C4: PROJECT DEVELOPER | E4: Dayne Sage | J4: Target Month | K4: 45961
C5: PROJECT MANAGERS | E5: Eon Van Rensburg
C6: CONTRACT VALUE | E6: 10428344
C7: Phase: | E7: Construction
B8: No. | C8: HIGH LEVEL PROGRAMME | E8: Planned Start | F8: Duration (days) | G8: Planned End | I8: Actual Start | J8: Duration (days) | K8: Actual End | M8: Status | N8: Status | O8: Comment
F9: =G51-E19 -> 60 | J9: =K51-I19 -> 137 | M9: =AVERAGE(M11,M18,M23,M33,M42,M47,M56,M53) -> 0.59833333 | N9: =AVERAGE(N11,N18,N23,N33,N42,N47,N56,N53) -> 0.6135
B11: 1 | C11: Project Initiation | E11: =MIN(E12:E16) -> 45845 | F11: =G11-E11 -> 94 | G11: =MAX(G12:G16) -> 45939 | I11: =MIN(I12:I16) -> 45845 | J11: =K11-I11 -> 94 | K11: =MAX(K12:K16) -> 45939 | M11: =(J12*M12+J13*M13+J14*M14+J15*M15+J16*M16)/SUM(J12:J16) -> 1 | N11: =(K12*N12+K13*N13+K14*N14+K15*N15+K16*N16)/SUM(K12:K16) -> 1
B12: 1.1 | C12: BD Handover | E12: 45845 | F12: 5 | G12: =WORKDAY.INTL(E12,F12,1,Data!$C$3:$C$45) -> 45852 | I12: 45845 | J12: 5 | K12: =WORKDAY.INTL(I12,J12,1,Data!$C$3:$C$45) -> 45852 | M12: 1 | N12: =_xlfn.LET( _xlpm.s,VALUE($I12), _xlpm.e,VALUE($K12), IF(OR(_xlpm.s="",_xlpm.e=""),"", IF(_xlpm.e<=_xlpm.s, IF(TODAY()>=_xlpm.e,1,0), MAX(0,MIN(1,(TODAY()-_xlpm.s)/(_xlpm.e-_xlpm.s))))) ) -> 1
B13: 1.2 | C13: Project Introduction | E13: =WORKDAY.INTL(E19,0,1,Data!$C$3:$C$45)-14 -> 45929 | F13: 1 | G13: =WORKDAY.INTL(E13,F13,1,Data!$C$3:$C$45) -> 45930 | I13: =WORKDAY.INTL(I19,0,1,Data!$C$3:$C$45)-14 -> 45929 | J13: 1 | K13: =WORKDAY.INTL(I13,J13,1,Data!$C$3:$C$45) -> 45930 | M13: 1 | N13: =_xlfn.LET( _xlpm.s,VALUE($I13), _xlpm.e,VALUE($K13), IF(OR(_xlpm.s="",_xlpm.e=""),"", IF(_xlpm.e<=_xlpm.s, IF(TODAY()>=_xlpm.e,1,0), MAX(0,MIN(1,(TODAY()-_xlpm.s)/(_xlpm.e-_xlpm.s))))) ) -> 1
B14: 1.3 | C14: HSE | E14: =E13 -> 45929 | F14: 8 | G14: =WORKDAY.INTL(E14,F14,1,Data!$C$3:$C$45) -> 45939 | I14: =I13 -> 45929 | J14: 8 | K14: =WORKDAY.INTL(I14,J14,1,Data!$C$3:$C$45) -> 45939 | M14: 1 | N14: =_xlfn.LET( _xlpm.s,VALUE($I14), _xlpm.e,VALUE($K14), IF(OR(_xlpm.s="",_xlpm.e=""),"", IF(_xlpm.e<=_xlpm.s, IF(TODAY()>=_xlpm.e,1,0), MAX(0,MIN(1,(TODAY()-_xlpm.s)/(_xlpm.e-_xlpm.s))))) ) -> 1
B15: 1.4 | C15: Installer Kick Off | E15: =WORKDAY.INTL(E19,0,1,Data!$C$3:$C$45)-14 -> 45929 | F15: 1 | G15: =WORKDAY.INTL(E15,F15,1,Data!$C$3:$C$45) -> 45930 | I15: =WORKDAY.INTL(I19,0,1,Data!$C$3:$C$45)-14 -> 45929 | J15: 1 | K15: =WORKDAY.INTL(I15,J15,1,Data!$C$3:$C$45) -> 45930 | M15: 1 | N15: =_xlfn.LET( _xlpm.s,VALUE($I15), _xlpm.e,VALUE($K15), IF(OR(_xlpm.s="",_xlpm.e=""),"", IF(_xlpm.e<=_xlpm.s, IF(TODAY()>=_xlpm.e,1,0), MAX(0,MIN(1,(TODAY()-_xlpm.s)/(_xlpm.e-_xlpm.s))))) ) -> 1
B16: 1.5 | C16: Project Review | E16: =WORKDAY.INTL(E19,0,1,Data!$C$3:$C$45)-14 -> 45929 | F16: 1 | G16: =WORKDAY.INTL(E16,F16,1,Data!$C$3:$C$45) -> 45930 | I16: =WORKDAY.INTL(I19,0,1,Data!$C$3:$C$45)-14 -> 45929 | J16: 1 | K16: =WORKDAY.INTL(I16,J16,1,Data!$C$3:$C$45) -> 45930 | M16: 1 | N16: =_xlfn.LET( _xlpm.s,VALUE($I16), _xlpm.e,VALUE($K16), IF(OR(_xlpm.s="",_xlpm.e=""),"", IF(_xlpm.e<=_xlpm.s, IF(TODAY()>=_xlpm.e,1,0), MAX(0,MIN(1,(TODAY()-_xlpm.s)/(_xlpm.e-_xlpm.s))))) ) -> 1
B18: 2 | C18: Site Establishment | E18: =MIN(E19:E22) -> 45943 | F18: =G18-E18 -> 1 | G18: =MAX(G19) -> 45944 | I18: =MIN(I19:I22) -> 45943 | J18: =K18-I18 -> 1 | K18: =MAX(K19) -> 45944 | M18: =(J19*M19)/J18 -> 1 | N18: =(K19*N19)/K18 -> 1
B19: 2.1 | C19: Solar Contractor Establishment | E19: 45943 | F19: 1 | G19: =E19+F19 -> 45944 | I19: 45943 | J19: 1 | K19: =I19+J19 -> 45944 | M19: 1 | N19: =_xlfn.LET( _xlpm.s,VALUE($I19), _xlpm.e,VALUE($K19), IF(OR(_xlpm.s="",_xlpm.e=""),"", IF(_xlpm.e<=_xlpm.s, IF(TODAY()>=_xlpm.e,1,0), MAX(0,MIN(1,(TODAY()-_xlpm.s)/(_xlpm.e-_xlpm.s))))) ) -> 1 | S19: =NETWORKDAYS(I19,K51,Data!C3:C46) -> 76 | T19: Net Work Days
B20: 2.2 | C20: Civil Works | I20: 45957 | J20: 36 | K20: =I20+J20 -> 45993 | M20: 1 | N20: =_xlfn.LET( _xlpm.s,VALUE($I20), _xlpm.e,VALUE($K20), IF(OR(_xlpm.s="",_xlpm.e=""),"", IF(_xlpm.e<=_xlpm.s, IF(TODAY()>=_xlpm.e,1,0), MAX(0,MIN(1,(TODAY()-_xlpm.s)/(_xlpm.e-_xlpm.s))))) ) -> 1
B21: 2.2 | C21: Roof Remedial Work | I21: 45950 | J21: 10 | K21: =I21+J21 -> 45960 | M21: 1 | N21: =_xlfn.LET( _xlpm.s,VALUE($I21), _xlpm.e,VALUE($K21), IF(OR(_xlpm.s="",_xlpm.e=""),"", IF(_xlpm.e<=_xlpm.s, IF(TODAY()>=_xlpm.e,1,0), MAX(0,MIN(1,(TODAY()-_xlpm.s)/(_xlpm.e-_xlpm.s))))) ) -> 1
B23: 3 | C23: AC Installation | E23: =MIN(E24:E31) -> 45929 | F23: =G23-E23 -> 52 | G23: =MAX(G24:G31) -> 45981 | I23: =MIN(I24:I31) -> 45929 | J23: =K23-I23 -> 147 | K23: =MAX(K24:K31) -> 46076 | M23: =(J24*M24+J25*M25+J26*M26+J27*M27+J31*M31+J28*M28+J29*M29+J30*M30)/SUM(J24:J31) -> 0.78666667 | N23: =(J24*N24+J25*N25+J26*N26+J27*N27+J31*N31+J28*N28+J29*N29+J30*N30)/SUM(J24:J31) -> 0.908 | S23: =S19/5 -> 15.2 | T23: Total Weeks
B24: 3.1 | C24: Inverters delivered | E24: =E19 -> 45943 | F24: 1 | G24: =WORKDAY.INTL(E24,F24,1,Data!$C$3:$C$45) -> 45944 | I24: =I19 -> 45943 | J24: 1 | K24: =WORKDAY.INTL(I24,J24,1,Data!$C$3:$C$45) -> 45944 | M24: 1 | N24: =_xlfn.LET( _xlpm.s,VALUE($I24), _xlpm.e,VALUE($K24), IF(OR(_xlpm.s="",_xlpm.e=""),"", IF(_xlpm.e<=_xlpm.s, IF(TODAY()>=_xlpm.e,1,0), MAX(0,MIN(1,(TODAY()-_xlpm.s)/(_xlpm.e-_xlpm.s))))) ) -> 1 | S24: =E3/S23 -> 89.473684 | T24: kW/Week Installation Rate
B25: 3.2 | C25: Inverters Mounted | E25: =WORKDAY.INTL(G24,0,1,Data!$C$3:$C$45)+21 -> 45965 | F25: 1 | G25: =WORKDAY.INTL(E25,F25,1,Data!$C$3:$C$45) -> 45966 | I25: =WORKDAY.INTL(K20,0,1,Data!$C$3:$C$45) -> 45993 | J25: 1 | K25: =WORKDAY.INTL(I25,J25,1,Data!$C$3:$C$45) -> 45994 | M25: 1 | N25: =_xlfn.LET( _xlpm.s,VALUE($I25), _xlpm.e,VALUE($K25), IF(OR(_xlpm.s="",_xlpm.e=""),"", IF(_xlpm.e<=_xlpm.s, IF(TODAY()>=_xlpm.e,1,0), MAX(0,MIN(1,(TODAY()-_xlpm.s)/(_xlpm.e-_xlpm.s))))) ) -> 1
B26: 3.3 | C26: Solar DB Lead Time | E26: =WORKDAY.INTL(E19,0,1,Data!$C$3:$C$45)-14 -> 45929 | F26: 30 | G26: =WORKDAY.INTL(E26,F26,1,Data!$C$3:$C$45) -> 45971 | I26: =WORKDAY.INTL(I19,0,1,Data!$C$3:$C$45)-14 -> 45929 | J26: 34 | K26: =WORKDAY.INTL(I26,J26,1,Data!$C$3:$C$45) -> 45975 | M26: 1 | N26: =_xlfn.LET( _xlpm.s,VALUE($I26), _xlpm.e,VALUE($K26), IF(OR(_xlpm.s="",_xlpm.e=""),"", IF(_xlpm.e<=_xlpm.s, IF(TODAY()>=_xlpm.e,1,0), MAX(0,MIN(1,(TODAY()-_xlpm.s)/(_xlpm.e-_xlpm.s))))) ) -> 1
B27: 3.4 | C27: AC Works - Tie In 1 | E27: =WORKDAY.INTL(G26,0,1,Data!$C$3:$C$45) -> 45971 | F27: 8 | G27: =WORKDAY.INTL(E27,F27,1,Data!$C$3:$C$45) -> 45981 | I27: =WORKDAY.INTL(K20,0,1,Data!$C$3:$C$45) -> 45993 | J27: 15 | K27: =WORKDAY.INTL(I27,J27,1,Data!$C$3:$C$45) -> 46048 | M27: 1 | N27: =_xlfn.LET( _xlpm.s,VALUE($I27), _xlpm.e,VALUE($K27), IF(OR(_xlpm.s="",_xlpm.e=""),"", IF(_xlpm.e<=_xlpm.s, IF(TODAY()>=_xlpm.e,1,0), MAX(0,MIN(1,(TODAY()-_xlpm.s)/(_xlpm.e-_xlpm.s))))) ) -> 1
B28: 3.5 | C28: AC Works - Tie In 2 | I28: 46034 | J28: 8 | K28: =WORKDAY.INTL(I28,J28,1,Data!$C$3:$C$45) -> 46050 | M28: 1 | N28: =_xlfn.LET( _xlpm.s,VALUE($I28), _xlpm.e,VALUE($K28), IF(OR(_xlpm.s="",_xlpm.e=""),"", IF(_xlpm.e<=_xlpm.s, IF(TODAY()>=_xlpm.e,1,0), MAX(0,MIN(1,(TODAY()-_xlpm.s)/(_xlpm.e-_xlpm.s))))) ) -> 1
B29: 3.6 | C29: Tie in Kiosk | I29: 46056 | J29: 14 | K29: =WORKDAY.INTL(I29,J29,1,Data!$C$3:$C$45) -> 46076 | M29: 0 | N29: =_xlfn.LET( _xlpm.s,VALUE($I29), _xlpm.e,VALUE($K29), IF(OR(_xlpm.s="",_xlpm.e=""),"", IF(_xlpm.e<=_xlpm.s, IF(TODAY()>=_xlpm.e,1,0), MAX(0,MIN(1,(TODAY()-_xlpm.s)/(_xlpm.e-_xlpm.s))))) ) -> 0.65 | O29: delivery date pending
B30: 3.7 | C30: AC Tie In 1 | I30: 46072 | J30: 1 | K30: =WORKDAY.INTL(I30,J30,1,Data!$C$3:$C$45) -> 46073 | M30: 0 | N30: =_xlfn.LET( _xlpm.s,VALUE($I30), _xlpm.e,VALUE($K30), IF(OR(_xlpm.s="",_xlpm.e=""),"", IF(_xlpm.e<=_xlpm.s, IF(TODAY()>=_xlpm.e,1,0), MAX(0,MIN(1,(TODAY()-_xlpm.s)/(_xlpm.e-_xlpm.s))))) ) -> 0 | O30: check with installer
B31: 3.8 | C31: AC Tie-In 2 | E31: =WORKDAY.INTL(E27,0,1,Data!$C$3:$C$45) -> 45971 | F31: 2 | G31: =WORKDAY.INTL(E31,F31,1,Data!$C$3:$C$45) -> 45973 | I31: 46072 | J31: 1 | K31: =WORKDAY.INTL(I31,J31,1,Data!$C$3:$C$45) -> 46073 | M31: 0 | N31: =_xlfn.LET( _xlpm.s,VALUE($I31), _xlpm.e,VALUE($K31), IF(OR(_xlpm.s="",_xlpm.e=""),"", IF(_xlpm.e<=_xlpm.s, IF(TODAY()>=_xlpm.e,1,0), MAX(0,MIN(1,(TODAY()-_xlpm.s)/(_xlpm.e-_xlpm.s))))) ) -> 0 | O31: check with installer
B33: 4 | C33: DC Works | E33: =MIN(E35:E40) -> 45943 | F33: =G33-E33 -> 53 | G33: =MAX(G35:G40) -> 45996 | I33: =MIN(I35:I40) -> 45943 | J33: =K33-I33 -> 100 | K33: =MAX(K35:K40) -> 46043 | M33: =(J35*M35+J36*M36+J40*M40+J37*M37+J38*M38+J39*M39)/SUM(J35:J40) -> 1 | N33: =(J34*N34+J35*N35+J36*N36+J37*N37+J41*N41+J38*N38+J39*N39+J40*N40)/SUM(J34:J41) -> 1
B34: 4.1 | C34: Lifeline Installation (If Applicable) | M34: 0 | N34: 0
B35: 4.1 | C35: Mounting Structure delivered | E35: =E24 -> 45943 | F35: 1 | G35: =WORKDAY.INTL(E35,F35,1,Data!$C$3:$C$45) -> 45944 | I35: =I24 -> 45943 | J35: 1 | K35: =WORKDAY.INTL(I35,J35,1,Data!$C$3:$C$45) -> 45944 | M35: 1 | N35: =_xlfn.LET( _xlpm.s,VALUE($I35), _xlpm.e,VALUE($K35), IF(OR(_xlpm.s="",_xlpm.e=""),"", IF(_xlpm.e<=_xlpm.s, IF(TODAY()>=_xlpm.e,1,0), MAX(0,MIN(1,(TODAY()-_xlpm.s)/(_xlpm.e-_xlpm.s))))) ) -> 1
B36: 4.2 | C36: Mounting Structure installation -Tie In 1 | E36: =WORKDAY.INTL(G35,0,1,Data!$C$3:$C$45) -> 45944 | F36: 10 | G36: =WORKDAY.INTL(E36,F36,1,Data!$C$3:$C$45) -> 45958 | I36: =WORKDAY.INTL(K21,0,1,Data!$C$3:$C$45)-3 -> 45957 | J36: 8 | K36: =WORKDAY.INTL(I36,J36,1,Data!$C$3:$C$45) -> 45967 | M36: 1 | N36: =_xlfn.LET( _xlpm.s,VALUE($I36), _xlpm.e,VALUE($K36), IF(OR(_xlpm.s="",_xlpm.e=""),"", IF(_xlpm.e<=_xlpm.s, IF(TODAY()>=_xlpm.e,1,0), MAX(0,MIN(1,(TODAY()-_xlpm.s)/(_xlpm.e-_xlpm.s))))) ) -> 1
B37: 4.3 | C37: Mounting Structure installation -Tie In 2 | I37: =WORKDAY.INTL(K36,0,1,Data!$C$3:$C$45)+7 -> 45974 | J37: 8 | K37: =WORKDAY.INTL(I37,J37,1,Data!$C$3:$C$45) -> 45986 | M37: 1 | N37: =_xlfn.LET( _xlpm.s,VALUE($I37), _xlpm.e,VALUE($K37), IF(OR(_xlpm.s="",_xlpm.e=""),"", IF(_xlpm.e<=_xlpm.s, IF(TODAY()>=_xlpm.e,1,0), MAX(0,MIN(1,(TODAY()-_xlpm.s)/(_xlpm.e-_xlpm.s))))) ) -> 1
B38: 4.4 | C38: DC Cable delivered | E38: =E24 -> 45943 | F38: 1 | G38: =WORKDAY.INTL(E38,F38,1,Data!$C$3:$C$45) -> 45944 | I38: =I24 -> 45943 | J38: 1 | K38: =WORKDAY.INTL(I38,J38,1,Data!$C$3:$C$45) -> 45944 | M38: 1 | N38: =_xlfn.LET( _xlpm.s,VALUE($I38), _xlpm.e,VALUE($K38), IF(OR(_xlpm.s="",_xlpm.e=""),"", IF(_xlpm.e<=_xlpm.s, IF(TODAY()>=_xlpm.e,1,0), MAX(0,MIN(1,(TODAY()-_xlpm.s)/(_xlpm.e-_xlpm.s))))) ) -> 1
B39: 4.5 | C39: DC Stringing Tie In 1 | I39: =K44-5 -> 45976 | J39: 6 | K39: =WORKDAY.INTL(I39,J39,1,Data!$C$3:$C$45) -> 45985 | M39: 1 | N39: =_xlfn.LET( _xlpm.s,VALUE($I39), _xlpm.e,VALUE($K39), IF(OR(_xlpm.s="",_xlpm.e=""),"", IF(_xlpm.e<=_xlpm.s, IF(TODAY()>=_xlpm.e,1,0), MAX(0,MIN(1,(TODAY()-_xlpm.s)/(_xlpm.e-_xlpm.s))))) ) -> 1
B40: 4.6 | C40: DC Stringing Tie In 2 | E40: =WORKDAY.INTL(G44,0,1,Data!$C$3:$C$45)-3 -> 45976 | F40: 15 | G40: =WORKDAY.INTL(E40,F40,1,Data!$C$3:$C$45) -> 45996 | I40: =WORKDAY.INTL(K45,0,1,Data!$C$3:$C$45)-14 -> 45979 | J40: 22 | K40: =WORKDAY.INTL(I40,J40,1,Data!$C$3:$C$45) -> 46043 | M40: 1 | N40: =_xlfn.LET( _xlpm.s,VALUE($I40), _xlpm.e,VALUE($K40), IF(OR(_xlpm.s="",_xlpm.e=""),"", IF(_xlpm.e<=_xlpm.s, IF(TODAY()>=_xlpm.e,1,0), MAX(0,MIN(1,(TODAY()-_xlpm.s)/(_xlpm.e-_xlpm.s))))) ) -> 1
B42: 5 | C42: Module installation | E42: =MIN(E43:E44) -> 45943 | F42: =G42-E42 -> 36 | G42: =MAX(G43:G44) -> 45979 | I42: =MIN(I43:I44) -> 45943 | J42: =K42-I42 -> 38 | K42: =MAX(K43:K44) -> 45981 | M42: =(J43*M43+J44*M44+J45*M45)/SUM(J43:J45) -> 1 | N42: =(J43*N43+J44*N44+J45*N45)/SUM(J43:J45) -> 1
B43: 5.1 | C43: Module delivery | E43: =E24 -> 45943 | F43: 1 | G43: =WORKDAY.INTL(E43,F43,1,Data!$C$3:$C$45) -> 45944 | I43: =I24 -> 45943 | J43: 1 | K43: =WORKDAY.INTL(I43,J43,1,Data!$C$3:$C$45) -> 45944 | M43: 1 | N43: =_xlfn.LET( _xlpm.s,VALUE($I43), _xlpm.e,VALUE($K43), IF(OR(_xlpm.s="",_xlpm.e=""),"", IF(_xlpm.e<=_xlpm.s, IF(TODAY()>=_xlpm.e,1,0), MAX(0,MIN(1,(TODAY()-_xlpm.s)/(_xlpm.e-_xlpm.s))))) ) -> 1
B44: 5.2 | C44: Module mounting - Tie In 1 | E44: =G36-7 -> 45951 | F44: 20 | G44: =WORKDAY.INTL(E44,F44,1,Data!$C$3:$C$45) -> 45979 | I44: =K36-2 -> 45965 | J44: 12 | K44: =WORKDAY.INTL(I44,J44,1,Data!$C$3:$C$45) -> 45981 | M44: 1 | N44: =_xlfn.LET( _xlpm.s,VALUE($I44), _xlpm.e,VALUE($K44), IF(OR(_xlpm.s="",_xlpm.e=""),"", IF(_xlpm.e<=_xlpm.s, IF(TODAY()>=_xlpm.e,1,0), MAX(0,MIN(1,(TODAY()-_xlpm.s)/(_xlpm.e-_xlpm.s))))) ) -> 1
B45: 5.2 | C45: Module mounting - Tie In 2 | E45: =G36-7 -> 45951 | F45: 20 | G45: =WORKDAY.INTL(E45,F45,1,Data!$C$3:$C$45) -> 45979 | I45: =K44-2 -> 45979 | J45: 10 | K45: =WORKDAY.INTL(I45,J45,1,Data!$C$3:$C$45) -> 45993 | M45: 1 | N45: =_xlfn.LET( _xlpm.s,VALUE($I45), _xlpm.e,VALUE($K45), IF(OR(_xlpm.s="",_xlpm.e=""),"", IF(_xlpm.e<=_xlpm.s, IF(TODAY()>=_xlpm.e,1,0), MAX(0,MIN(1,(TODAY()-_xlpm.s)/(_xlpm.e-_xlpm.s))))) ) -> 1
B47: 6 | C47: Commissioning | E47: =MIN(E49:E51) -> 45996 | F47: =G47-E47 -> 7 | G47: =MAX(G49:G51) -> 46003 | I47: =MIN(I49:I51) -> 46076 | J47: =K47-I47 -> 4 | K47: =MAX(K49:K51) -> 46080 | M47: =(J49*M49+J51*M51+J48*M48+J50*M50)/SUM(J48:J51) -> 0 | N47: =(J49*N49+J51*N51+J48*N48+J50*N50)/SUM(J48:J51) -> 0
B48: 6.1 | C48: Fibre cable install | I48: 46070 | J48: 2 | K48: =WORKDAY.INTL(I48,J48,1,Data!$C$3:$C$45) -> 46072 | M48: 0 | N48: =_xlfn.LET( _xlpm.s,VALUE($I48), _xlpm.e,VALUE($K48), IF(OR(_xlpm.s="",_xlpm.e=""),"", IF(_xlpm.e<=_xlpm.s, IF(TODAY()>=_xlpm.e,1,0), MAX(0,MIN(1,(TODAY()-_xlpm.s)/(_xlpm.e-_xlpm.s))))) ) -> 0
B49: 6.2 | C49: Commissioning - Tie In 1 | E49: =WORKDAY.INTL(MAX(G23,G33,G42),0,1,Data!$C$3:$C$45) -> 45996 | F49: 2 | G49: =WORKDAY.INTL(E49,F49,1,Data!$C$3:$C$45) -> 46000 | I49: 46076 | J49: 2 | K49: =WORKDAY.INTL(I49,J49,1,Data!$C$3:$C$45) -> 46078 | M49: 0 | N49: =_xlfn.LET( _xlpm.s,VALUE($I49), _xlpm.e,VALUE($K49), IF(OR(_xlpm.s="",_xlpm.e=""),"", IF(_xlpm.e<=_xlpm.s, IF(TODAY()>=_xlpm.e,1,0), MAX(0,MIN(1,(TODAY()-_xlpm.s)/(_xlpm.e-_xlpm.s))))) ) -> 0 | O49: possible delay
B50: 6.3 | C50: Commissioning - Tie In 2 | I50: 46076 | J50: 2 | K50: =WORKDAY.INTL(I50,J50,1,Data!$C$3:$C$45) -> 46078 | M50: 0 | N50: =_xlfn.LET( _xlpm.s,VALUE($I50), _xlpm.e,VALUE($K50), IF(OR(_xlpm.s="",_xlpm.e=""),"", IF(_xlpm.e<=_xlpm.s, IF(TODAY()>=_xlpm.e,1,0), MAX(0,MIN(1,(TODAY()-_xlpm.s)/(_xlpm.e-_xlpm.s))))) ) -> 0 | O50: possible delay
B51: 6.4 | C51: Practical Completion | E51: =WORKDAY.INTL(G49,0,1,Data!$C$3:$C$45) -> 46000 | F51: 3 | G51: =WORKDAY.INTL(E51,F51,1,Data!$C$3:$C$45) -> 46003 | I51: 46077 | J51: 3 | K51: =WORKDAY.INTL(I51,J51,1,Data!$C$3:$C$45) -> 46080 | M51: 0 | N51: =_xlfn.LET( _xlpm.s,VALUE($I51), _xlpm.e,VALUE($K51), IF(OR(_xlpm.s="",_xlpm.e=""),"", IF(_xlpm.e<=_xlpm.s, IF(TODAY()>=_xlpm.e,1,0), MAX(0,MIN(1,(TODAY()-_xlpm.s)/(_xlpm.e-_xlpm.s))))) ) -> 0 | O51: hinges on above
B53: 7 | C53: QA Inspections | E53: =MIN(E54) -> 45996 | F53: =G53-E53 -> 3 | G53: =MAX(G54) -> 45999 | I53: =MIN(I54) -> 46078 | J53: =K53-I53 -> 1 | K53: =MAX(K54) -> 46079 | M53: =(J54*M54)/SUM(J54) -> 0 | N53: =(K54*N54)/SUM(K54) -> 0
B54: 7.1 | C54: Red-Team Inspection | E54: =WORKDAY.INTL(E49,0,1,Data!$C$3:$C$45) -> 45996 | F54: 1 | G54: =WORKDAY.INTL(E54,F54,1,Data!$C$3:$C$45) -> 45999 | I54: 46078 | J54: 1 | K54: =WORKDAY.INTL(I54,J54,1,Data!$C$3:$C$45) -> 46079 | M54: 0 | N54: =_xlfn.LET( _xlpm.s,VALUE($I54), _xlpm.e,VALUE($K54), IF(OR(_xlpm.s="",_xlpm.e=""),"", IF(_xlpm.e<=_xlpm.s, IF(TODAY()>=_xlpm.e,1,0), MAX(0,MIN(1,(TODAY()-_xlpm.s)/(_xlpm.e-_xlpm.s))))) ) -> 0
B56: 8 | C56: Project Closure | E56: =MIN(E57:E62) -> 45996 | F56: =G56-E56 -> 48 | G56: =MAX(G57:G62) -> 46044 | I56: =MIN(I57:I62) -> 46078 | J56: =K56-I56 -> 16 | K56: =MAX(K57:K62) -> 46094 | M56: =(J57*M57+J58*M58+J59*M59+J60*M60+J61*M61+J62*M62)/SUM(J57:J62) -> 0 | N56: =(J57*N57+J58*N58+J59*N59+J60*N60+J61*N61+J62*N62)/SUM(J57:J62) -> 0
B57: 8.1 | C57: Equipment serial numbers | E57: =E54 -> 45996 | F57: 1 | G57: =WORKDAY.INTL(E57,F57,1,Data!$C$3:$C$45) -> 45999 | I57: =I54 -> 46078 | J57: 1 | K57: =WORKDAY.INTL(I57,J57,1,Data!$C$3:$C$45) -> 46079 | M57: 0 | N57: =_xlfn.LET( _xlpm.s,VALUE($I57), _xlpm.e,VALUE($K57), IF(OR(_xlpm.s="",_xlpm.e=""),"", IF(_xlpm.e<=_xlpm.s, IF(TODAY()>=_xlpm.e,1,0), MAX(0,MIN(1,(TODAY()-_xlpm.s)/(_xlpm.e-_xlpm.s))))) ) -> 0
B58: 8.2 | C58: Snags completion | E58: =G54 -> 45999 | F58: 5 | G58: =WORKDAY.INTL(E58,F58,1,Data!$C$3:$C$45) -> 46006 | I58: =K54 -> 46079 | J58: 5 | K58: =WORKDAY.INTL(I58,J58,1,Data!$C$3:$C$45) -> 46086 | M58: 0 | N58: =_xlfn.LET( _xlpm.s,VALUE($I58), _xlpm.e,VALUE($K58), IF(OR(_xlpm.s="",_xlpm.e=""),"", IF(_xlpm.e<=_xlpm.s, IF(TODAY()>=_xlpm.e,1,0), MAX(0,MIN(1,(TODAY()-_xlpm.s)/(_xlpm.e-_xlpm.s))))) ) -> 0
B59: 8.3 | C59: System Performance Monitoring | E59: =WORKDAY.INTL(G47,0,1,Data!$C$3:$C$45) -> 46003 | F59: 5 | G59: =WORKDAY.INTL(E59,F59,1,Data!$C$3:$C$45) -> 46044 | I59: =WORKDAY.INTL(K47,0,1,Data!$C$3:$C$45) -> 46080 | J59: 5 | K59: =WORKDAY.INTL(I59,J59,1,Data!$C$3:$C$45) -> 46087 | M59: 0 | N59: =_xlfn.LET( _xlpm.s,VALUE($I59), _xlpm.e,VALUE($K59), IF(OR(_xlpm.s="",_xlpm.e=""),"", IF(_xlpm.e<=_xlpm.s, IF(TODAY()>=_xlpm.e,1,0), MAX(0,MIN(1,(TODAY()-_xlpm.s)/(_xlpm.e-_xlpm.s))))) ) -> 0
B60: 8.4 | C60: Handover documentation | E60: =WORKDAY.INTL(G58,0,1,Data!$C$3:$C$45) -> 46006 | F60: 1 | G60: =WORKDAY.INTL(E60,F60,1,Data!$C$3:$C$45) -> 46041 | I60: =WORKDAY.INTL(K58,0,1,Data!$C$3:$C$45) -> 46086 | J60: 1 | K60: =WORKDAY.INTL(I60,J60,1,Data!$C$3:$C$45) -> 46087 | M60: 0 | N60: =_xlfn.LET( _xlpm.s,VALUE($I60), _xlpm.e,VALUE($K60), IF(OR(_xlpm.s="",_xlpm.e=""),"", IF(_xlpm.e<=_xlpm.s, IF(TODAY()>=_xlpm.e,1,0), MAX(0,MIN(1,(TODAY()-_xlpm.s)/(_xlpm.e-_xlpm.s))))) ) -> 0
B61: 8.5 | C61: Handover to Client | E61: =WORKDAY.INTL(G60,0,1,Data!$C$3:$C$45) -> 46041 | F61: 1 | G61: =WORKDAY.INTL(E61,F61,1,Data!$C$3:$C$45) -> 46042 | I61: =WORKDAY.INTL(K60,0,1,Data!$C$3:$C$45) -> 46087 | J61: 1 | K61: =WORKDAY.INTL(I61,J61,1,Data!$C$3:$C$45) -> 46090 | M61: 0 | N61: =_xlfn.LET( _xlpm.s,VALUE($I61), _xlpm.e,VALUE($K61), IF(OR(_xlpm.s="",_xlpm.e=""),"", IF(_xlpm.e<=_xlpm.s, IF(TODAY()>=_xlpm.e,1,0), MAX(0,MIN(1,(TODAY()-_xlpm.s)/(_xlpm.e-_xlpm.s))))) ) -> 0
B62: 8.6 | C62: Handover to Matriarch | E62: =WORKDAY.INTL(E61,0,1,Data!$C$3:$C$45) -> 46041 | F62: 1 | G62: =WORKDAY.INTL(E62,F62,1,Data!$C$3:$C$45) -> 46042 | I62: =WORKDAY.INTL(I61,0,1,Data!$C$3:$C$45) -> 46087 | J62: 5 | K62: =WORKDAY.INTL(I62,J62,1,Data!$C$3:$C$45) -> 46094 | M62: 0 | N62: =_xlfn.LET( _xlpm.s,VALUE($I62), _xlpm.e,VALUE($K62), IF(OR(_xlpm.s="",_xlpm.e=""),"", IF(_xlpm.e<=_xlpm.s, IF(TODAY()>=_xlpm.e,1,0), MAX(0,MIN(1,(TODAY()-_xlpm.s)/(_xlpm.e-_xlpm.s))))) ) -> 0

Sheet Revenue Tracking
B2: HIGH LEVEL PROJECT REVENUE TRACKING
D3: COSTED | F3: ACTUAL | L3: FINANCIAL REVIEW | N3: TIMELINE REVIEW
B4: 1 | C4: Planned Revenue | D4: ='Project Plan'!E6 -> 10428344 | F4: =F22 -> 10428344 | N4: Start Date
B5: 2 | C5: Planned Expenditure | D5: =+'Expenditure Tracking'!F5 -> 9590676.1 | F5: =+'Expenditure Tracking'!H5 -> 7470904.2
B6: 3 | C6: Planned Profit | D6: =+D4-D5 -> 837668.22 | F6: =+F4-F5 -> 2957440.2 | N6: End Date - PC
B7: 4 | C7: Planned Margin | D7: =+D6/D4 -> 0.080326098 | F7: =+F6/F4 -> 0.28359633
B10: CONTRACT
B12: No. | C12: PAYMENT MILESTONE | E12: % | F12: VALUE | H12: PLANNED PAYMENT DATE | L12: INVOICE NUMBER | N12: INVOICE RAISED DATE | P12: PAYMENT RECEIVED DATE | R12: MILESTONE NOTES & COMMENTS
B13: 1 | C13: Claim 1 | E13: =F13/$D$4 -> 0.28831062 | F13: =6013204.76-F14 -> 3006602.4 | H13: 45986 | L13: 004866 | N13: 45958 | P13: 45999
B14: 1 | C14: Claim 1 | E14: 0.29 | F14: 3006602.4 | H14: 45986 | L14: 004866 | N14: 45958 | P14: 45994
B15: 2 | C15: Claim 2 | E15: =F15/$D$4 -> 0.21341537 | F15: 2225569 | H15: 46016 | L15: 004903 | N15: 46008 | P15: 46034
B16: 3 | C16: Claim 3 | E16: 0 | F16: 0
B17: 4 | C17: Claim 4 | E17: 0.21 | F17: 2189570.6 | H17: 46078 | P17: 46106
B18: 5 | E18: 0 | F18: =$D$4*E18 -> 0
B19: 6 | E19: 0 | F19: =$D$4*E19 -> 0
B20: 7 | C20: - | E20: 0 | F20: =$D$4*E20 -> 0
E22: =SUM(E13:E20) -> 1.001726 | F22: =SUM(F13:F20) -> 10428344
B24: KEY: | C24: contains an error (in result or a check has failed)
C25: Red Font - IF TEXT : content not yet confirmed
C26: Red Font - IF NUMBER: Negative value
C27: Anything in yellow is a concern or risk for noting or action
C28: confirmed
C29: [ADD INITIALS: comment for noting in square brackets, use colour or red to draw attention if important]
C30: [RT: When adding rows into sheet, ensure you insert between first and last row of each category]
C31: end of sheet - do not insert information below/beyond this
B41: No. | C41: PAYMENT MILESTONE | E41: % | F41: VALUE
B42: 1 | C42: Deposit - Project commencement | E42: 0.35 | F42: =$F$48*E42 -> 3649920.5
B43: 2 | C43: Delivery of Panels | E43: 0.3 | F43: =$F$48*E43 -> 3128503.3
B44: 3 | C44: Delivery of Inverters | E44: 0.2 | F44: =$F$48*E44 -> 2085668.9
B45: 4 | C45: Practical Completion | E45: 0.1 | F45: =$F$48*E45 -> 1042834.4
B46: 5 | C46: Handover | E46: 0.05 | F46: =$F$48*E46 -> 521417.22
C47: Total | E47: =SUM(E42:E46) -> 1 | F47: =SUM(F42:F46) -> 10428344
E48: =SUM(E42:E46) -> 1 | F48: =F22 -> 10428344

Sheet Data
C2: Public holidays | F2: Drop down list
C3: 45658 | D3: New Years Day | F3: Approved
C4: 45737 | D4: Human Rights day | F4: Pending
C5: 45765 | D5: Good Friday | F5: Declined
C6: 45768 | D6: Family Day | F6: Abanded
C7: 45774 | D7: Freedom Day
C8: 45765 | D8: Freedom DayObserved
C9: 45778 | D9: Workers day
C10: 45824 | D10: Youth Day Holiday
C11: 45878 | D11: Womens Day
C12: 45924 | D12: Heritage Day
C13: 46007 | D13: Day of Reconciliation | H13: Manual dates
C14: 46008 | D14: Builders Holiday
C15: 46009 | D15: Builders Holiday
C16: 46010 | D16: Builders Holiday
C17: 46011 | D17: Builders Holiday
C18: 46012 | D18: Builders Holiday
C19: 46013 | D19: Builders Holiday
C20: 46014 | D20: Builders Holiday
C21: 46015 | D21: Builders Holiday
C22: 46016 | D22: Builders Holiday
C23: 46017 | D23: Builders Holiday
C24: 46018 | D24: Builders Holiday
C25: 46019 | D25: Builders Holiday
... C46: 46017 | D46: Day of Goodwill

Sheet Expenditure Tracking
B2: HIGH LEVEL PROJECT EXPENDITURE TRACKING
F4: COSTED | H4: ACTUAL | J4: Difference from costed
B5: EXPENDITURE | F5: =SUM(F9:F23) -> 9590676.1 | H5: =SUM(H9:H23) -> 7470904.2 | J5: =SUM(J9:J23) -> 2119771.9
B7: No. | D7: Item | F7: Costed Expenditure | H7: Actual Expenditure | J7: Saving / Overrun | L7: Comments on variations from planned expenditure
B9: ='Expenditure Breakdown'!L6 -> 1 | D9: ='Expenditure Breakdown'!M6 -> 1. Panels | F9: ='Expenditure Breakdown'!I6 -> 2857717.2 | H9: ='Expenditure Breakdown'!X6 -> 2667866.8 | J9: =F9-H9 -> 189850.37
B10: ='Expenditure Breakdown'!L13 -> 2 | D10: ='Expenditure Breakdown'!M13 -> 2. Inverters | F10: ='Expenditure Breakdown'!I13 -> 770000 | H10: ='Expenditure Breakdown'!X13 -> 757573.94 | J10: =F10-H10 -> 12426.062
B11: ='Expenditure Breakdown'!L21 -> 3 | D11: ='Expenditure Breakdown'!M21 -> 3. Mounting Structures | F11: ='Expenditure Breakdown'!I21 -> 1105818.2 | H11: ='Expenditure Breakdown'!X21 -> 365443.08 | J11: =F11-H11 -> 740375.13
B12: ='Expenditure Breakdown'!L31 -> 4 | D12: ='Expenditure Breakdown'!M31 -> 4. DC Equipment | F12: ='Expenditure Breakdown'!I31 -> 1117490.1 | H12: ='Expenditure Breakdown'!X31 -> 713565.2 | J12: =F12-H12 -> 403924.9
B13: ='Expenditure Breakdown'!L51 -> 5 | D13: ='Expenditure Breakdown'!M51 -> 5. Monitoring | F13: ='Expenditure Breakdown'!I51 -> 49000 | H13: ='Expenditure Breakdown'!X51 -> 91265.29 | J13: =F13-H13 -> -42265.29
B14: ='Expenditure Breakdown'!L63 -> 6 | D14: ='Expenditure Breakdown'!M63 -> 6. AC Equipment | F14: ='Expenditure Breakdown'!I63 -> 1511034.3 | H14: ='Expenditure Breakdown'!X63 -> 586437.82 | J14: =F14-H14 -> 924596.48
B15: ='Expenditure Breakdown'!L85 -> 7 | D15: ='Expenditure Breakdown'!M85 -> 7.BESS | F15: ='Expenditure Breakdown'!I85 -> 0 | H15: ='Expenditure Breakdown'!X85 -> 0 | J15: =F15-H15 -> 0
B16: ='Expenditure Breakdown'!L94 -> 8 | D16: ='Expenditure Breakdown'!M94 -> 8. Product Add On | F16: ='Expenditure Breakdown'!I94 -> 300000 | H16: ='Expenditure Breakdown'!X94 -> 341826 | J16: =F16-H16 -> -41826
B17: ='Expenditure Breakdown'!L104 -> 9 | D17: ='Expenditure Breakdown'!M104 -> 9. AC & DC installation | F17: ='Expenditure Breakdown'!I104 -> 1060132.5 | H17: ='Expenditure Breakdown'!X104 -> 1105292.2 | J17: =F17-H17 -> -45159.71
B18: ='Expenditure Breakdown'!L121 -> 10 | D18: ='Expenditure Breakdown'!M121 -> 10. Site Logistics | F18: ='Expenditure Breakdown'!I121 -> 184440.47 | H18: ='Expenditure Breakdown'!X121 -> 302543.9 | J18: =F18-H18 -> -118103.43
B19: ='Expenditure Breakdown'!L145 -> 11 | D19: ='Expenditure Breakdown'!M145 -> 11. Due Dilligence | F19: ='Expenditure Breakdown'!I145 -> 182012.75 | H19: ='Expenditure Breakdown'!X145 -> 142343.85 | J19: =F19-H19 -> 39668.9
B20: ='Expenditure Breakdown'!L151 -> 12 | D20: ='Expenditure Breakdown'!M151 -> 12. BDP Commission | F20: ='Expenditure Breakdown'!I151 -> 0 | H20: ='Expenditure Breakdown'!X151 -> 0 | J20: =F20-H20 -> 0
B21: ='Expenditure Breakdown'!L154 -> 13 | D21: ='Expenditure Breakdown'!M155 -> 13. Engineering | F21: ='Expenditure Breakdown'!I154 -> 429230.63 | H21: ='Expenditure Breakdown'!X154 -> 130354.3 | J21: =F21-H21 -> 298876.33
B22: ='Expenditure Breakdown'!L161 -> 14 | D22: ='Expenditure Breakdown'!M161 -> 14. General Expenses | F22: ='Expenditure Breakdown'!I161 -> 23800 | H22: ='Expenditure Breakdown'!X161 -> 38589.8 | J22: =F22-H22 -> -14789.8
B23: ='Expenditure Breakdown'!L174 -> 15 | D23: ='Expenditure Breakdown'!M174 -> 15. Service Add On | F23: ='Expenditure Breakdown'!I174 -> 0 | H23: ='Expenditure Breakdown'!X174 -> 227802 | J23: =F23-H23 -> -227802
D25: check: | F25: ='Expenditure Breakdown'!I2-'Expenditure Tracking'!F5 -> 0 | G25: =#REF!-G5 -> #REF! | H25: ='Expenditure Breakdown'!X2-H5 -> 0

Sheet Expenditure Breakdown
B2: COSTED EXPENDITURE BREAKDOWN | I2: =SUM(I6:I186) -> 9590676.1 | J2: =SUM(J6:J186) -> 12428344 | L2: ACTUAL EXPENDITURE BREAKDOWN | R2: FINANCE ONLY | X2: =SUM(X6:X186) -> 7470904.2
B4: No. | C4: Product / Service | D4: Description of Work | E4: QTY | F4: Rate / Unit | G4: Budget Total | H4: FINANCE PAYMENT DATE | I4: Total COS | J4: =IF(J2-'Revenue Tracking'!D4>=0, "Total Revenue", "ERROR on REV" ) -> Total Revenue | L4: No. | M4: Product/ Service | N4: Description of Work | O4: QTY | P4: Rate / Unit | Q4: Actual Total | R4: PO NUMBER | S4: INVOICE NUMBER | T4: INVOICE RAISED DATE | U4: REVENUE RECOGNITION AMOUNT | V4: CHECK | W4: FINANCE PAYMENT DATE | X4: Total COS
B6: 1 | C6: Panels | D6: Panels Budget | G6: =D187 -> 2857717.2 | H6: 46022 | I6: =SUM(G6:G11) -> 2857717.2 | J6: =F187 -> 3072814.2 | L6: 1 | M6: 1. Panels | N6: Jinko 590 | O6: 1298 | P6: 1150.5 | Q6: =O6*P6 -> 1493349 | S6: Menlo - INV0003320 | T6: 45961 | U6: 1729623.9 | V6: =J6-SUM(U6:U11) -> 0 | W6: 46003 | X6: =SUM(Q6:Q11) -> 2667866.8
B7: 1 | D7: Delivery Budget | L7: 1 | M7: 1. Panels | N7: Jinko 590 balance | O7: =2306-O6 -> 1008 | P7: 1150.5 | Q7: =O7*P7 -> 1159704 | S7: Menlo - INV0003319 | T7: 45961 | U7: 1343190.2 | W7: 46009
B8: 1 | L8: 1 | M8: 1. Panels | T8: =IF(W8>1,EOMONTH(W8,0),"") | U8: 0
B9: 1 | L9: 1 | M9: 1. Panels | N9: Replacement Panels - Damaged due to weather | O9: 2 | Q9: 4136.4 | R9: PO4556-DSHC-20260119 - RV Approved | S9: MSA Energy - INV0003547 | T9: 46053 | U9: 0 | W9: =T9+60 -> 46113
B10: 1 | L10: 1 | M10: 1. Panels | N10: Panels and Delivery | O10: 7 | Q10: 10677.4 | S10: MSA Energy - INV0003541 | T10: 46053 | U10: 0 | W10: 46097
B11: 1 | L11: 1 | M11: 1. Panels | T11: =IF(W11>1,EOMONTH(W11,0),"") | U11: 0 | Y11: BUDGET | Z11: Installer Allocation
T12: =IF(W12>1,EOMONTH(W12,0),"") | Y12: AC Equipment | Z12: =G63 -> 1511034.3
B13: 2 | C13: Inverters | D13: Inverter Budget | E13: 11 | G13: =D188 -> 770000 | H13: =H6 -> 46022 | I13: =SUM(G13:G19) -> 770000 | J13: =F188 -> 827956.99 | L13: 2 | M13: 2. Inverters | N13: Huawei 100KTL | O13: 11 | P13: 68870.358 | Q13: =O13*P13 -> 757573.94 | S13: =S6 -> Menlo - INV0003320 | T13: 45961 | U13: 827956.99 | V13: =J13-SUM(U13:U19) -> 0 | W13: =W6 -> 46003 | X13: =SUM(Q13:Q19) -> 757573.94 | Y13: DC Equipment | Z13: =G32 -> 675888.1
B14: 2 | L14: 2 | M14: 2. Inverters | T14: =IF(W14>1,EOMONTH(W14,0),"") | U14: 0 | Y14: AC Labour | Z14: =G104 -> 340042.5
B15: 2 | L15: 2 | M15: 2. Inverters | T15: =IF(W15>1,EOMONTH(W15,0),"") | U15: 0 | Y15: DC Labour | Z15: =G105 -> 720090
B16: 2 | L16: 2 | M16: 2. Inverters | T16: =IF(W16>1,EOMONTH(W16,0),"") | U16: 0 | Y16: Offloading | Z16: =G121 -> 8500
B17: 2 | L17: 2 | M17: 2. Inverters | T17: =IF(W17>1,EOMONTH(W17,0),"") | U17: 0 | Y17: Scaffolding | Z17: =G122 -> 70393.8
B18: 2 | L18: 2 | M18: 2. Inverters | T18: =IF(W18>1,EOMONTH(W18,0),"") | U18: 0 | Y18: Storage | Z18: =G128 -> 33546.667
B19: 2 | L19: 2 | M19: 2. Inverters | T19: =IF(W19>1,EOMONTH(W19,0),"") | U19: 0 | Y19: Telehandler | Z19: 0
T20: =IF(W20>1,EOMONTH(W20,0),"")
B21: 3 | C21: Mounting Structures | D21: Structure Budget | G21: =D189 -> 1105818.2 | H21: =E21+30 -> 30 | I21: =SUM(G21:G29) -> 1105818.2 | J21: =F189 -> 1189051.8 | L21: 3 | M21: 3. Mounting Structures | N21: K2 Structure | Q21: 40621.45 | R21: PO4364-DSHC-20251009 - RV Approved | S21: Krannich - 15-10014095 | T21: 45961 | U21: 142264.22 | V21: =J21-SUM(U21:U29) -> 0 | W21: 46003 | X21: =SUM(Q21:Q29) -> 365443.08 | Y21: Other | Z21: 0
B22: 3 | L22: 3 | M22: 3. Mounting Structures | Q22: 45778.95 | S22: krannich - 15-10014122 | T22: 45961 | U22: 160326.79 | W22: 46009 | Y22: Total | Z22: =SUM(Z12:Z21) -> 3359495.4
B23: 3 | L23: 3 | M23: 3. Mounting Structures | Q23: 50931.2 | S23: krannich - 15-10014093 | T23: 45961 | U23: 178370.97 | W23: 46003 | Y23: Less 15% | Z23: =+Z22*0.85 -> 2855571.1
B24: 3 | L24: 3 | M24: 3. Mounting Structures | Q24: 202184.62 | S24: Krannich - 15-10014094 | T24: 45961 | U24: 708089.86 | W24: 46003 | Y24: R/Wp | Z24: =Z23/'Project Plan'!$E$3/1000 -> 2.0996846
B25: 3 | L25: 3 | M25: 3. Mounting Structures | N25: Earthing plates | Q25: 71394.92 | R25: PO4490-DSHC-20251125 - RV Approved | S25: K2 Systems - Inv139402 | T25: 45991 | U25: 0 | W25: 45989
L26: 3 | M26: 3. Mounting Structures | Q26: -67046.2 | S26: K2 Systems - Credit SACN42026 | T26: 46053 | U26: 0 | W26: 46059
L27: 3 | M27: 3. Mounting Structures | N27: XS Clamps - K2 | Q27: 2283.7 | R27: PO4616-DSHC-20260211 - RV Approved | S27: K2 Systems - SAI1382026 | T27: 46081 | W27: =T27 -> 46081
L28: 3 | M28: 3. Mounting Structures | N28: Terragriff (254 clamps short returned) to be deducted from subbie | Q28: 3737.49 | T28: 46081 | U28: 0 | W28: =T28 -> 46081
B29: 3 | L29: 3 | M29: 3. Mounting Structures | N29: Universal KL-Clamp | Q29: 15556.95 | R29: PO4553-DSHC-20260116 - RV Approved | S29: K2 Systems - InvSAI672026 | T29: 46053 | U29: 0 | W29: 46045 | Y29: ACTUAL - JA Electrical | Z29: Installer Price
T30: =IF(W30>1,EOMONTH(W30,0),"") | Y30: =Y12 -> AC Equipment | Z30: 231508.8
B31: 4 | C31: DC Equipment | D31: DC Cable Budget | E31: =G31/14*1.15 -> 36274.45 | G31: 441602 | H31: =H6 -> 46022 | I31: =SUM(G31:G49) -> 1117490.1 | J31: =F190 -> 1201602.3 | L31: 4 | M31: 4. DC Equipment | N31: DC Cable - old price | O31: 14000 | P31: 13.5 | Q31: =O31*P31 -> 189000 | S31: =S13 -> Menlo - INV0003320 | T31: 45961 | U31: 318265 | V31: =J31-SUM(U31:U49) -> 0 | W31: =W6 -> 46003 | X31: =SUM(Q31:Q49) -> 713565.2 | Y31: =Y13 -> DC Equipment | Z31: 169665.2
B32: 4 | D32: DC Equipment Budget | G32: =D190-G31 -> 675888.1 | H32: 46022 | L32: 4 | M32: 4. DC Equipment | O32: =40000-O31 -> 26000 | P32: 13.65 | Q32: =P32*O32 -> 354900 | S32: =S6 -> Menlo - INV0003320 | T32: 45961 | U32: 597630.94 | W32: =W7 -> 46009 | Y32: =Y14 -> AC Labour | Z32: 142795.4
B33: 4 | L33: 4 | M33: 4. DC Equipment | T33: =IF(W33>1,EOMONTH(W33,0),"") | U33: =(Q33/$X$31*$J$31) -> 0 | Y33: =Y15 -> DC Labour | Z33: 962496.8
B34: 4 | L34: 4 | M34: 4. DC Equipment | T34: =IF(W34>1,EOMONTH(W34,0),"") | U34: =(Q34/$X$31*$J$31) -> 0 | Y34: =Y16 -> Offloading | Z34: 55490
B35: 4 | H35: =H105 -> 45900 | L35: 4 | M35: 4. DC Equipment | N35: Project Kick Off | O35: =Z31 -> 169665.2 | P35: 0.1 | Q35: =$O$35*P35 -> 16966.52 | S35: =S105 -> JA Electrical - Inv 1104 | T35: =T105 -> 45961 | U35: 28570.632 | W35: =W105 -> 45967 | Y35: =Y17 -> Scaffolding | Z35: 75760
B36: 4 | H36: =H106 -> #REF! | L36: 4 | M36: 4. DC Equipment | N36: Site Establishment | P36: 0.15 | Q36: =$O$35*P36 -> 25449.78 | S36: =S106 -> JA Electrical - Inv 1105 | T36: =T106 -> 45961 | U36: 42855.948 | W36: =W106 -> 45967 | Y36: =Y18 -> Storage | Z36: 11407
B37: 4 | H37: =H107 -> #REF! | L37: 4 | M37: 4. DC Equipment | N37: AC Installation Complete | P37: 0.1 | Q37: =$O$35*P37 -> 16966.52 | S37: JA ElectricalInv 1142 | T37: =T107 -> 46022 | U37: 28570.632 | W37: =W107 -> 46003 | Y37: Site Ablutions | Z37: 17072
L38: 4 | M38: 4. DC Equipment | N38: AC Installation Complete | P38: =P108 -> 0.075 | Q38: =$O$35*P38 -> 12724.89 | S38: JA Electrical Inv 1156 | T38: =T108 -> 46053 | U38: 21427.974 | W38: =W72 -> 46066
L39: 4 | M39: 4. DC Equipment | N39: AC Installation Complete | P39: =P109 -> 0.025 | Q39: =$O$35*P39 -> 4241.63 | T39: =T109 -> 46081 | U39: =(Q39/$X$31*$J$31) -> 7142.658 | W39: =W73 -> 46073
B40: 4 | H40: =H110 -> #REF! | L40: 4 | M40: 4. DC Equipment | N40: DC Installation Complete | P40: 0.2 | Q40: =$O$35*P40 -> 33933.04 | S40: JA ElectricalInv 1142 | T40: =T110 -> 46022 | U40: 57141.264 | W40: =W110 -> 46003 | Y40: Return of excess material | Z40: 14195
L41: 4 | M41: 4. DC Equipment | N41: DC Installation Complete | P41: =P111 -> 0.025 | Q41: =$O$35*P41 -> 4241.63 | S41: JA Electrical Inv 1156 | T41: =T111 -> 46053 | U41: 7142.658 | W41: =W76 -> 46066
L42: 4 | M42: 4. DC Equipment | N42: DC Installation Complete | P42: =P112 -> 0.025 | Q42: =$O$35*P42 -> 4241.63 | T42: =T112 -> 46081 | U42: =(Q42/$X$31*$J$31) -> 7142.658 | W42: =W112 -> 46073
B43: 4 | H43: =H113 -> #REF! | L43: 4 | M43: 4. DC Equipment | N43: Commissioning Complete | P43: 0.1 | Q43: =$O$35*P43 -> 16966.52 | T43: =T113 -> 46112 | U43: =(Q43/$X$31*$J$31) -> 28570.632 | W43: =W113 -> 46087 | Y43: Waste Skip | Z43: 22620
B44: 4 | H44: =H114 -> #REF! | L44: 4 | M44: 4. DC Equipment | N44: Site De-establisment | P44: 0.1 | Q44: =$O$35*P44 -> 16966.52 | T44: =T114 -> 46112 | U44: =(Q44/$X$31*$J$31) -> 28570.632 | W44: =W114 -> 46093 | Y44: Other | Z44: 0
B45: 4 | H45: =H115 -> #REF! | L45: 4 | M45: 4. DC Equipment | N45: Handover Document Complete | P45: 0.05 | Q45: =$O$35*P45 -> 8483.26 | T45: =T115 -> 46112 | U45: =(Q45/$X$31*$J$31) -> 14285.316 | W45: =W115 -> 46093 | Y45: Total | Z45: =SUM(Z30:Z44) -> 1703010.2
B46: 4 | H46: =H116 -> #REF! | L46: 4 | M46: 4. DC Equipment | N46: End of Defects Period | P46: 0.05 | Q46: =$O$35*P46 -> 8483.26 | T46: =T116 -> 46112 | U46: =(Q46/$X$31*$J$31) -> 14285.316 | W46: =W116 -> 46116 | Y46: R/Wp | Z46: =Z45/'Project Plan'!$E$3/1000 -> 1.2522134
B47: 4 | L47: 4 | M47: 4. DC Equipment | T47: =IF(W47>1,EOMONTH(W47,0),"") | U47: =(Q47/$X$31*$J$31) -> 0
B48: 4 | L48: 4 | M48: 4. DC Equipment | T48: =IF(W48>1,EOMONTH(W48,0),"") | U48: =(Q48/$X$31*$J$31) -> 0
B49: 4 | L49: 4 | M49: 4. DC Equipment | T49: =IF(W49>1,EOMONTH(W49,0),"") | U49: =(Q49/$X$31*$J$31) -> 0
T50: =IF(W50>1,EOMONTH(W50,0),"")
B51: 5 | C51: Monitoring | D51: Monitoring Budget | G51: =D192-G52 -> 34000 | H51: 45900 | I51: =SUM(G51:G61) -> 49000 | J51: =F192 -> 52688.172 | L51: 5 | M51: 5. Monitoring | N51: Smartlogger | Q51: 8598.34 | S51: =S6 -> Menlo - INV0003320 | T51: 45961 | U51: 5015.4617 | V51: =J51-SUM(U51:U61) -> 0.0040393824 | W51: =W6 -> 46003 | X51: =SUM(Q51:Q61) -> 91265.29
B52: 5 | D52: Revenue Metering | G52: 15000 | H52: 45900 | L52: 5 | M52: 5. Monitoring | N52: CTs & Meters | Q52: 27301 | R52: PO4416-DSHC-20251028 - RV Approved | S52: Accuenergy Inv :ASAI-006727 | T52: 45961 | U52: 9478.94 | W52: 45989
B53: 5 | H53: 45900 | L53: 5 | M53: 5. Monitoring | N53: Techsitter | Q53: 11169 | S53: Matriarch - INV-4742 | T53: 45930 | U53: 7261.7211 | W53: 45900
L54: 5 | M54: 5. Monitoring | N54: DElivery of Techsitter | Q54: 335.86 | S54: DSV Inv:180156930 | T54: 45991 | U54: 0 | W54: 46022
B55: 5 | H55: 45900 | L55: 5 | M55: 5. Monitoring | N55: Apex Device and Licenses | Q55: 44000 | R55: PO4077-DSHC-20250630 - RV Approved | S55: Rubicon INVWCRE-0069079 | T55: 45930 | U55: 28607.371 | W55: 45900
L56: 5 | M56: 5. Monitoring | N56: Above Apex allocated to Corporate Park | Q56: =-1*Q55 -> -44000 | S56: Allocated to Corporate Park | T56: 45961 | U56: 0 | W56: =T56 -> 45961
L57: 5 | M57: 5. Monitoring | N57: New Apex device | Q57: 40000 | R57: PO4420-DSHC-20251029 - RV Approved | S57: Rubicon - INVWCRE-0072121 | T57: 45991 | U57: 0 | W57: 46021
L58: 5 | M58: 5. Monitoring | N58: Delivery of Apex | Q58: 285.59 | S58: DSV Inv:180155155 | T58: 45991 | U58: 0 | W58: 46021
B59: 5 | H59: 45876 | L59: 5 | M59: 5. Monitoring | N59: UPS | Q59: 3575.5 | R59: PO4070-DSHC-20250630 - RV Approved | S59: Frontiline QTE107313 | T59: 45930 | U59: 2324.674 | W59: 45876
B60: 5 | L60: 5 | M60: 5. Monitoring | T60: =IF(W60>1,EOMONTH(W60,0),"") | U60: =(Q60/$X$51*$J$51) -> 0
B61: 5 | L61: 5 | M61: 5. Monitoring | T61: =IF(W61>1,EOMONTH(W61,0),"") | U61: =(Q61/$X$51*$J$51) -> 0
T62: =IF(W62>1,EOMONTH(W62,0),"")
B63: 6 | C63: AC Equipment | D63: AC Equipment Budget | G63: =D191 -> 1511034.3 | H63: 45900 | I63: =SUM(G63:G83) -> 1511034.3 | J63: =F191 -> 1624768.1 | L63: 6 | M63: 6. AC Equipment | T63: =IF(W63>1,EOMONTH(W63,0),"") | U63: =(Q63/$X$63*$J$63) -> 0 | V63: =J63-SUM(U63:U83) -> 5.3090509e-05 | X63: =SUM(Q63:Q83) -> 586437.82
B64: 6 | H64: =E64+30 -> 30 | L64: 6 | M64: 6. AC Equipment | N64: PVDB | Q64: 354929.22 | R64: PO4330-DSHC-20250925 - MI Approved | S64: Switchboard - 2-SOI002604 | T64: 45991 | U64: 983356.54 | W64: =T64+30 -> 46021
B65: 6 | L65: 6 | M65: 6. AC Equipment | T65: =IF(W65>1,EOMONTH(W65,0),"") | U65: =(Q65/$X$63*$J$63) -> 0
B66: 6 | L66: 6 | M66: 6. AC Equipment | T66: =IF(W66>1,EOMONTH(W66,0),"") | U66: =(Q66/$X$63*$J$63) -> 0
B67: 6 | L67: 6 | M67: 6. AC Equipment | T67: =IF(W67>1,EOMONTH(W67,0),"") | U67: =(Q67/$X$63*$J$63) -> 0
B68: 6 | L68: 6 | M68: 6. AC Equipment | T68: =IF(W68>1,EOMONTH(W68,0),"") | U68: =(Q68/$X$63*$J$63) -> 0
B69: 6 | H69: =H105 -> 45900 | L69: 6 | M69: 6. AC Equipment | N69: Project Kick Off | O69: =Z30 -> 231508.8 | P69: 0.1 | Q69: =$O$69*P69 -> 23150.88 | S69: =S105 -> JA Electrical - Inv 1104 | T69: =T105 -> 45961 | U69: 64141.153 | W69: =W105 -> 45967
B70: 6 | H70: =H106 -> #REF! | L70: 6 | M70: 6. AC Equipment | N70: Site Establishment | P70: 0.15 | Q70: =$O$69*P70 -> 34726.32 | S70: =S106 -> JA Electrical - Inv 1105 | T70: =T106 -> 45961 | U70: 96211.729 | W70: =W106 -> 45967
B71: 6 | H71: =H107 -> #REF! | L71: 6 | M71: 6. AC Equipment | N71: AC Installation Complete | P71: 0.1 | Q71: 23150.78 | S71: JA ElectricalInv 1142 | T71: =T107 -> 46022 | U71: 64141.287 | W71: =W107 -> 46003
L72: 6. | M72: 6. AC Equipment | N72: AC Installation Complete | P72: =P108 -> 0.075 | Q72: =$O$69*P72 -> 17363.16 | S72: JA Electrical Inv 1156 | T72: =T108 -> 46053 | U72: 48105.881 | W72: =W108 -> 46066
L73: 6. | M73: 6. AC Equipment | N73: AC Installation Complete | P73: =P109 -> 0.025 | Q73: =$O$69*P73 -> 5787.72 | T73: =T109 -> 46081 | U73: =(Q73/$X$63*$J$63) -> 16035.294 | W73: =W109 -> 46073
B74: 6 | H74: =H110 -> #REF! | L74: 6 | M74: 6. AC Equipment | N74: DC Installation Complete | P74: 0.2 | Q74: 46301.66 | S74: JA ElectricalInv 1142 | T74: =T110 -> 46022 | U74: 128282.07 | W74: =W110 -> 46003
L75: 6 | M75: 6. AC Equipment | N75: DC Installation Complete | P75: =P111 -> 0.025 | Q75: =$O$69*P75 -> 5787.72 | T75: =T112 -> 46081 | U75: =(Q75/$X$63*$J$63) -> 16035.294 | W75: =W112 -> 46073
L76: 6 | M76: 6. AC Equipment | N76: DC Installation Complete | P76: =P112 -> 0.025 | Q76: =$O$69*P76 -> 5787.72 | S76: JA Electrical Inv 1156 | T76: =T111 -> 46053 | U76: 16035.294 | W76: =W111 -> 46066
B77: 6 | H77: =H113 -> #REF! | L77: 6 | M77: 6. AC Equipment | N77: Commissioning Complete | P77: 0.1 | Q77: =$O$69*P77 -> 23150.88 | T77: =T113 -> 46112 | U77: =(Q77/$X$63*$J$63) -> 64141.174 | W77: =W113 -> 46087
B78: 6 | H78: =H114 -> #REF! | L78: 6 | M78: 6. AC Equipment | N78: Site De-establisment | P78: 0.1 | Q78: =$O$69*P78 -> 23150.88 | T78: =T114 -> 46112 | U78: =(Q78/$X$63*$J$63) -> 64141.174 | W78: =W114 -> 46093
B79: 6 | H79: =H115 -> #REF! | L79: 6 | M79: 6. AC Equipment | N79: Handover Document Complete | P79: 0.05 | Q79: =$O$69*P79 -> 11575.44 | T79: =T115 -> 46112 | U79: =(Q79/$X$63*$J$63) -> 32070.587 | W79: =W115 -> 46093
B80: 6 | H80: =H116 -> #REF! | L80: 6 | M80: 6. AC Equipment | N80: End of Defects Period | P80: 0.05 | Q80: =$O$69*P80 -> 11575.44 | T80: =T116 -> 46112 | U80: =(Q80/$X$63*$J$63) -> 32070.587 | W80: =W116 -> 46116
B81: 6 | L81: 6 | M81: 6. AC Equipment | T81: =IF(W81>1,EOMONTH(W81,0),"") | U81: =(Q81/$X$63*$J$63) -> 0
B82: 6 | L82: 6 | M82: 6. AC Equipment | T82: =IF(W82>1,EOMONTH(W82,0),"") | U82: =(Q82/$X$63*$J$63) -> 0
B83: 6 | L83: 6 | M83: 6. AC Equipment | T83: =IF(W83>1,EOMONTH(W83,0),"") | U83: =(Q83/$X$63*$J$63) -> 0
T84: =IF(W84>1,EOMONTH(W84,0),"")
B85: 7 | C85: BESS | I85: =SUM(G85:G92) -> 0 | J85: =F196 -> 0 | L85: 7 | M85: 7.BESS | V85: =J85-SUM(U85:U92) -> 0 | X85: =SUM(Q85:Q92) -> 0
B86: 7 | L86: 7 | M86: 7.BESS
B87: 7 | L87: 7 | M87: 7.BESS
B88: 7 | L88: 7 | M88: 7.BESS
B89: 7 | L89: 7 | M89: 7.BESS
B90: 7 | L90: 7 | M90: 7.BESS
B91: 7 | L91: 7 | M91: 7.BESS
B92: 7 | L92: 7 | M92: 7.BESS
T93: =IF(W93>1,EOMONTH(W93,0),"")
B94: 8 | C94: Product Add On | I94: =SUM(G94:G102) -> 300000 | J94: =F194+F195 -> 322580.65 | L94: 8 | M94: 8. Product Add On | T94: =IF(W94>1,EOMONTH(W94,0),"") | U94: =(Q94/$X$94*$J$94) -> 0 | V94: =J94-SUM(U94:U102) -> 0.0035152828 | X94: =SUM(Q94:Q102) -> 341826
B95: 8 | D95: Transformer | G95: 300000 | H95: 45900 | L95: 8 | M95: 8. Product Add On | N95: Tie In Kiosk | O95: 2 | P95: 25000 | Q95: =O95*P95 -> 50000 | T95: 46081 | U95: 0 | W95: =T95-14 -> 46067
B96: 8 | L96: 8 | M96: 8. Product Add On | T96: =IF(W96>1,EOMONTH(W96,0),"") | U96: =(Q96/$X$94*$J$94) -> 0
B97: 8 | H97: =E97+30 -> 30 | L97: 8 | M97: 8. Product Add On | N97: Brick Face Inverter Rooms | O97: 232956 | P97: 0.75 | Q97: =$O$97*P97 -> 174717 | R97: PO4365-DSHC-20251013 - RV Approved | S97: Van Staden Three : Inv 3021 | T97: 45961 | U97: 200089.19 | W97: 45946
B98: 8 | L98: 8 | M98: 8. Product Add On | P98: 0.25 | Q98: =$O$97*P98 -> 58239 | S98: Van Staden Three : Inv 3037 | T98: 45961 | U98: 66696.397 | W98: 46009
B99: 8 | L99: 8 | M99: 8. Product Add On | N99: Inverter stand | Q99: 48720 | R99: PO4450-DSHC-20251107 - RV Approved | S99: JA Electrical - Inv 1144 | T99: 46022 | U99: 55795.055 | W99: 46066
B100: 8 | L100: 8 | M100: 8. Product Add On | T100: =IF(W100>1,EOMONTH(W100,0),"") | U100: =(Q100/$X$94*$J$94) -> 0
B101: 8 | L101: 8 | M101: 8. Product Add On | N101: Grounding Washers | Q101: 10150 | R101: PO4571-DSHC-20260123 - RV Approved | S101: JA Electrical Inv 1156 | T101: 46053 | U101: 0 | W101: 46066
B102: 8 | L102: 8 | M102: 8. Product Add On | T102: =IF(W102>1,EOMONTH(W102,0),"") | U102: =(Q102/$X$94*$J$94) -> 0
K103: Only services to be capture below, products above | T103: =IF(W103>1,EOMONTH(W103,0),"")
...

Sheet Cashflow
D1: [RT: Double Check the first date is always a MONDAY] | F1: 45677 | G1: =F1+7 -> 45684 | H1: =G1+7 -> 45691 | I1: =H1+7 -> 45698 | J1: =I1+7 -> 45705 | K1: =J1+7 -> 45712 | L1: =K1+7 -> 45719 | M1: =L1+7 -> 45726 | N1: =M1+7 -> 45733 | ... LD1: =LC1+7 -> 47847
A2: PLANNED | C2: CHECK | D2: CHECK
B3: Planned Revenue | C3: ='Revenue Tracking'!D4 -> 10428344 | D3: =SUM(F3:LD3) -> 10428344 | F3: =SUMIFS('Revenue Tracking'!$F$13:$F$20, 'Revenue Tracking'!$H$13:$H$20, ">="&F1,'Revenue Tracking'!$H$13:$H$20, "<"&G1) -> 0 | G3: =SUMIFS('Revenue Tracking'!$F$13:$F$20, 'Revenue Tracking'!$H$13:$H$20, ">="&G1,'Revenue Tracking'!$H$13:$H$20, "<"&H1) -> 0 | H3: =SUMIFS('Revenue Tracking'!$F$13:$F$20, 'Revenue Tracking'!$H$13:$H$20, ">="&H1,'Revenue Tracking'!$H$13:$H$20, "<"&I1) -> 0 | I3: =SUMIFS('Revenue Tracking'!$F$13:$F$20, 'Revenue Tracking'!$H$13:$H$20, ">="&I1,'Revenue Tracking'!$H$13:$H$20, "<"&J1) -> 0 | J3: =SUMIFS('Revenue Tracking'!$F$13:$F$20, 'Revenue Tracking'!$H$13:$H$20, ">="&J1,'Revenue Tracking'!$H$13:$H$20, "<"&K1) -> 0 | K3: =SUMIFS('Revenue Tracking'!$F$13:$F$20, 'Revenue Tracking'!$H$13:$H$20, ">="&K1,'Revenue Tracking'!$H$13:$H$20, "<"&L1) -> 0 | L3: =SUMIFS('Revenue Tracking'!$F$13:$F$20, 'Revenue Tracking'!$H$13:$H$20, ">="&L1,'Revenue Tracking'!$H$13:$H$20, "<"&M1) -> 0 | M3: =SUMIFS('Revenue Tracking'!$F$13:$F$20, 'Revenue Tracking'!$H$13:$H$20, ">="&M1,'Revenue Tracking'!$H$13:$H$20, "<"&N1) -> 0 | ... LC3: =SUMIFS('Revenue Tracking'!$F$13:$F$20, 'Revenue Tracking'!$H$13:$H$20, ">="&LC1,'Revenue Tracking'!$H$13:$H$20, "<"&LD1) -> 0 | LD3: =SUMIFS('Revenue Tracking'!$F$13:$F$20, 'Revenue Tracking'!$H$13:$H$20, ">="&LD1,'Revenue Tracking'!$H$13:$H$20, "<"&#REF!) -> 0
B4: Planned Revenue - Cumulative | F4: =F3 -> 0 | G4: =F4+G3 -> 0 | H4: =G4+H3 -> 0 | I4: =H4+I3 -> 0 | J4: =I4+J3 -> 0 | K4: =J4+K3 -> 0 | L4: =K4+L3 -> 0 | M4: =L4+M3 -> 0 | N4: =M4+N3 -> 0 | ... LD4: =LC4+LD3 -> 10428344
B5: Planned Expenditure | C5: ='Revenue Tracking'!D5 -> 9590676.1 | D5: =SUM(F5:LD5) -> 8484857.9 | F5: =SUMIFS('Expenditure Breakdown'!$G$6:$G$224, 'Expenditure Breakdown'!$H$6:$H$224, ">="&F1,'Expenditure Breakdown'!$H$6:$H$224, "<"&G1) -> 0 | G5: =SUMIFS('Expenditure Breakdown'!$G$6:$G$224, 'Expenditure Breakdown'!$H$6:$H$224, ">="&G1,'Expenditure Breakdown'!$H$6:$H$224, "<"&H1) -> 0 | H5: =SUMIFS('Expenditure Breakdown'!$G$6:$G$224, 'Expenditure Breakdown'!$H$6:$H$224, ">="&H1,'Expenditure Breakdown'!$H$6:$H$224, "<"&I1) -> 0 | I5: =SUMIFS('Expenditure Breakdown'!$G$6:$G$224, 'Expenditure Breakdown'!$H$6:$H$224, ">="&I1,'Expenditure Breakdown'!$H$6:$H$224, "<"&J1) -> 0 | J5: =SUMIFS('Expenditure Breakdown'!$G$6:$G$224, 'Expenditure Breakdown'!$H$6:$H$224, ">="&J1,'Expenditure Breakdown'!$H$6:$H$224, "<"&K1) -> 0 | K5: =SUMIFS('Expenditure Breakdown'!$G$6:$G$224, 'Expenditure Breakdown'!$H$6:$H$224, ">="&K1,'Expenditure Breakdown'!$H$6:$H$224, "<"&L1) -> 0 | L5: =SUMIFS('Expenditure Breakdown'!$G$6:$G$224, 'Expenditure Breakdown'!$H$6:$H$224, ">="&L1,'Expenditure Breakdown'!$H$6:$H$224, "<"&M1) -> 0 | M5: =SUMIFS('Expenditure Breakdown'!$G$6:$G$224, 'Expenditure Breakdown'!$H$6:$H$224, ">="&M1,'Expenditure Breakdown'!$H$6:$H$224, "<"&N1) -> 0 | ... LC5: =SUMIFS('Expenditure Breakdown'!$G$6:$G$224, 'Expenditure Breakdown'!$H$6:$H$224, ">="&LC1,'Expenditure Breakdown'!$H$6:$H$224, "<"&LD1) -> 0 | LD5: =SUMIFS('Expenditure Breakdown'!$G$6:$G$224, 'Expenditure Breakdown'!$H$6:$H$224, ">="&LD1,'Expenditure Breakdown'!$H$6:$H$224, "<"&#REF!) -> 0
B6: Planned Expenditure - Cumulative | F6: =F5 -> 0 | G6: =F6+G5 -> 0 | H6: =G6+H5 -> 0 | I6: =H6+I5 -> 0 | J6: =I6+J5 -> 0 | K6: =J6+K5 -> 0 | L6: =K6+L5 -> 0 | M6: =L6+M5 -> 0 | N6: =M6+N5 -> 0 | ... LD6: =LC6+LD5 -> 8484857.9
B7: PLANNED CashFlow | F7: =F4-F6 -> 0 | G7: =G4-G6 -> 0 | H7: =H4-H6 -> 0 | I7: =I4-I6 -> 0 | J7: =J4-J6 -> 0 | K7: =K4-K6 -> 0 | L7: =L4-L6 -> 0 | M7: =M4-M6 -> 0 | ... LD7: =LD4-LD6 -> 1943486.4
A8: ACTUAL | C8: CHECK | D8: CHECK
B9: Actual + Planned Revenue | C9: ='Revenue Tracking'!F4 -> 10428344 | D9: =SUM(F9:LD9) -> 10428344 | F9: =SUMIFS('Revenue Tracking'!$F$13:$F$20, 'Revenue Tracking'!$P$13:$P$20, ">="&F1,'Revenue Tracking'!$P$13:$P$20, "<"&G1) -> 0 | G9: =SUMIFS('Revenue Tracking'!$F$13:$F$20, 'Revenue Tracking'!$P$13:$P$20, ">="&G1,'Revenue Tracking'!$P$13:$P$20, "<"&H1) -> 0 | H9: =SUMIFS('Revenue Tracking'!$F$13:$F$20, 'Revenue Tracking'!$P$13:$P$20, ">="&H1,'Revenue Tracking'!$P$13:$P$20, "<"&I1) -> 0 | I9: =SUMIFS('Revenue Tracking'!$F$13:$F$20, 'Revenue Tracking'!$P$13:$P$20, ">="&I1,'Revenue Tracking'!$P$13:$P$20, "<"&J1) -> 0 | J9: =SUMIFS('Revenue Tracking'!$F$13:$F$20, 'Revenue Tracking'!$P$13:$P$20, ">="&J1,'Revenue Tracking'!$P$13:$P$20, "<"&K1) -> 0 | K9: =SUMIFS('Revenue Tracking'!$F$13:$F$20, 'Revenue Tracking'!$P$13:$P$20, ">="&K1,'Revenue Tracking'!$P$13:$P$20, "<"&L1) -> 0 | L9: =SUMIFS('Revenue Tracking'!$F$13:$F$20, 'Revenue Tracking'!$P$13:$P$20, ">="&L1,'Revenue Tracking'!$P$13:$P$20, "<"&M1) -> 0 | M9: =SUMIFS('Revenue Tracking'!$F$13:$F$20, 'Revenue Tracking'!$P$13:$P$20, ">="&M1,'Revenue Tracking'!$P$13:$P$20, "<"&N1) -> 0 | ... LC9: =SUMIFS('Revenue Tracking'!$F$13:$F$20, 'Revenue Tracking'!$P$13:$P$20, ">="&LC1,'Revenue Tracking'!$P$13:$P$20, "<"&LD1) -> 0 | LD9: =SUMIFS('Revenue Tracking'!$F$13:$F$20, 'Revenue Tracking'!$P$13:$P$20, ">="&LD1,'Revenue Tracking'!$P$13:$P$20, "<"&#REF!) -> 0
B10: Actual + Planned Revenue - Cumulative | F10: =F9 -> 0 | G10: =F10+G9 -> 0 | H10: =G10+H9 -> 0 | I10: =H10+I9 -> 0 | J10: =I10+J9 -> 0 | K10: =J10+K9 -> 0 | L10: =K10+L9 -> 0 | M10: =L10+M9 -> 0 | N10: =M10+N9 -> 0 | ... LD10: =LC10+LD9 -> 10428344
B11: Actual + Planned Expenditure | C11: ='Revenue Tracking'!F5 -> 7470904.2 | D11: =SUM(F11:LD11) -> 7470904.2 | F11: =SUMIFS('Expenditure Breakdown'!$Q$6:$Q$193, 'Expenditure Breakdown'!$W$6:$W$193, ">="&F1,'Expenditure Breakdown'!$W$6:$W$193, "<"&G1) -> 0 | G11: =SUMIFS('Expenditure Breakdown'!$Q$6:$Q$193, 'Expenditure Breakdown'!$W$6:$W$193, ">="&G1,'Expenditure Breakdown'!$W$6:$W$193, "<"&H1) -> 0 | H11: =SUMIFS('Expenditure Breakdown'!$Q$6:$Q$193, 'Expenditure Breakdown'!$W$6:$W$193, ">="&H1,'Expenditure Breakdown'!$W$6:$W$193, "<"&I1) -> 0 | I11: =SUMIFS('Expenditure Breakdown'!$Q$6:$Q$193, 'Expenditure Breakdown'!$W$6:$W$193, ">="&I1,'Expenditure Breakdown'!$W$6:$W$193, "<"&J1) -> 0 | J11: =SUMIFS('Expenditure Breakdown'!$Q$6:$Q$193, 'Expenditure Breakdown'!$W$6:$W$193, ">="&J1,'Expenditure Breakdown'!$W$6:$W$193, "<"&K1) -> 0 | K11: =SUMIFS('Expenditure Breakdown'!$Q$6:$Q$193, 'Expenditure Breakdown'!$W$6:$W$193, ">="&K1,'Expenditure Breakdown'!$W$6:$W$193, "<"&L1) -> 79700 | L11: =SUMIFS('Expenditure Breakdown'!$Q$6:$Q$193, 'Expenditure Breakdown'!$W$6:$W$193, ">="&L1,'Expenditure Breakdown'!$W$6:$W$193, "<"&M1) -> 9620 | M11: =SUMIFS('Expenditure Breakdown'!$Q$6:$Q$193, 'Expenditure Breakdown'!$W$6:$W$193, ">="&M1,'Expenditure Breakdown'!$W$6:$W$193, "<"&N1) -> 0 | ... LC11: =SUMIFS('Expenditure Breakdown'!$Q$6:$Q$193, 'Expenditure Breakdown'!$W$6:$W$193, ">="&LC1,'Expenditure Breakdown'!$W$6:$W$193, "<"&LD1) -> 0 | LD11: =SUMIFS('Expenditure Breakdown'!$Q$6:$Q$193, 'Expenditure Breakdown'!$W$6:$W$193, ">="&LD1,'Expenditure Breakdown'!$W$6:$W$193, "<"&#REF!) -> 0
B12: Actual + Planned Expenditure - Cumulative | F12: =F11 -> 0 | G12: =F12+G11 -> 0 | H12: =G12+H11 -> 0 | I12: =H12+I11 -> 0 | J12: =I12+J11 -> 0 | K12: =J12+K11 -> 79700 | L12: =K12+L11 -> 89320 | M12: =L12+M11 -> 89320 | N12: =M12+N11 -> 89320 | ... LD12: =LC12+LD11 -> 7470904.2
B14: ACTUAL CashFlow | F14: =F10-F12 -> 0 | G14: =G10-G12 -> 0 | H14: =H10-H12 -> 0 | I14: =I10-I12 -> 0 | J14: =J10-J12 -> 0 | K14: =K10-K12 -> -79700 | L14: =L10-L12 -> -89320 | M14: =M10-M12 -> -89320 | ... LD14: =LD10-LD12 -> 2957440.2
C16: CHECK | D16: CHECK
B17: Revenue Recognition | C17: =C3-D17 -> 0.0083446708 | D17: =SUM(F17:LD17) -> 10428344 | F17: =SUMIFS('Expenditure Breakdown'!$U$6:$U$193, 'Expenditure Breakdown'!$T$6:$T$193, ">="&F1,'Expenditure Breakdown'!$T$6:$T$193, "<"&G1) -> 0 | G17: =SUMIFS('Expenditure Breakdown'!$U$6:$U$193, 'Expenditure Breakdown'!$T$6:$T$193, ">="&G1,'Expenditure Breakdown'!$T$6:$T$193, "<"&H1) -> 0 | H17: =SUMIFS('Expenditure Breakdown'!$U$6:$U$193, 'Expenditure Breakdown'!$T$6:$T$193, ">="&H1,'Expenditure Breakdown'!$T$6:$T$193, "<"&I1) -> 0 | I17: =SUMIFS('Expenditure Breakdown'!$U$6:$U$193, 'Expenditure Breakdown'!$T$6:$T$193, ">="&I1,'Expenditure Breakdown'!$T$6:$T$193, "<"&J1) -> 0 | J17: =SUMIFS('Expenditure Breakdown'!$U$6:$U$193, 'Expenditure Breakdown'!$T$6:$T$193, ">="&J1,'Expenditure Breakdown'!$T$6:$T$193, "<"&K1) -> 0 | K17: =SUMIFS('Expenditure Breakdown'!$U$6:$U$193, 'Expenditure Breakdown'!$T$6:$T$193, ">="&K1,'Expenditure Breakdown'!$T$6:$T$193, "<"&L1) -> 0 | L17: =SUMIFS('Expenditure Breakdown'!$U$6:$U$193, 'Expenditure Breakdown'!$T$6:$T$193, ">="&L1,'Expenditure Breakdown'!$T$6:$T$193, "<"&M1) -> 0 | M17: =SUMIFS('Expenditure Breakdown'!$U$6:$U$193, 'Expenditure Breakdown'!$T$6:$T$193, ">="&M1,'Expenditure Breakdown'!$T$6:$T$193, "<"&N1) -> 0 | ... LC17: =SUMIFS('Expenditure Breakdown'!$U$6:$U$193, 'Expenditure Breakdown'!$T$6:$T$193, ">="&LC1,'Expenditure Breakdown'!$T$6:$T$193, "<"&LD1) -> 0 | LD17: =SUMIFS('Expenditure Breakdown'!$U$6:$U$193, 'Expenditure Breakdown'!$T$6:$T$193, ">="&LD1,'Expenditure Breakdown'!$T$6:$T$193, "<"&#REF!) -> 0
B18: Revenue Recognition Cumulative | C18: =D17-D18 -> 0 | D18: =MAX(F18:LD18) -> 10428344 | F18: =F17 -> 0 | G18: =F18+G17 -> 0 | H18: =G18+H17 -> 0 | I18: =H18+I17 -> 0 | J18: =I18+J17 -> 0 | K18: =J18+K17 -> 0 | L18: =K18+L17 -> 0 | M18: =L18+M17 -> 0 | N18: =M18+N17 -> 0 | ... LD18: =LC18+LD17 -> 10428344

Sheet Finance - Revenue
A3: Sum of REVENUE RECOGNITION AMOUNT | B3: Column Labels
A4: Row Labels | B4: (blank) | C4: 45930 | D4: 45961 | E4: 45991 | F4: 46022 | H4: 46053 | I4: 46081 | J4: 46112 | K4: Grand Total
A5: (blank)
A6: 1. Panels | D6: 3072814.2 | G6: 0 | H6: 0 | K6: 3072814.2
A7: 2. Inverters | D7: 827956.99 | G7: 0 | K7: 827956.99
A8: 3. Mounting Structures | D8: 1189051.8 | E8: 0 | H8: 0 | I8: 0 | K8: 1189051.8
A9: 4. DC Equipment | D9: 987322.52 | F9: 85711.896 | G9: 0 | H9: 28570.632 | I9: 42855.948 | J9: 57141.264 | K9: 1201602.3
A10: 5. Monitoring | C10: 38193.766 | D10: 14494.402 | E10: 0 | G10: 0 | K10: 52688.168
A11: 6. AC Equipment | D11: 160352.88 | E11: 983356.54 | F11: 192423.36 | G11: 0 | H11: 64141.174 | I11: 96211.762 | J11: 128282.35 | K11: 1624768.1
A12: 8. Product Add On | D12: 266785.59 | F12: 55795.055 | G12: 0 | H12: 0 | I12: 0 | K12: 322580.64
A13: 9. AC & DC installation | D13: 301174.01 | F13: 361408.81 | G13: 0 | H13: 120469.6 | I13: 180704.41 | J13: 240939.2 | K13: 1204696
A14: 10. Site Logistics | B14: 0 | D14: 58979.113 | E14: 38348.821 | F14: 50992.154 | G14: 0 | H14: 13615.861 | I14: 20423.783 | J14: 27231.711 | K14: 209591.44
A15: 11. Due Dilligence | C15: 152536.78 | I15: 54295.887 | K15: 206832.67
A16: 13. Engineering | B16: 0 | G16: 0 | I16: 487762.08 | K16: 487762.08
A17: 14. General Expenses | C17: 16326.888 | D17: 3732.1067 | E17: 3279.4745 | F17: 0 | G17: 0 | H17: 0 | I17: 4661.531 | K17: 28000
A18: 15. Service Add On
A19: 12. BDP Commission
A20: 7.BESS
A21: Grand Total | B21: 0 | C21: 207057.44 | D21: 6882663.6 | E21: 1024984.8 | F21: 746331.27 | G21: 0 | H21: 226797.26 | I21: 886915.4 | J21: 453594.53 | K21: 10428344

Sheet Finance - COS
A3: Sum of Actual Total | B3: Column Labels
A4: Row Labels | B4: (blank) | C4: 45930 | D4: 45961 | E4: 45991 | F4: 46022 | H4: 46053 | I4: 46081 | J4: 46112 | K4: Grand Total
A5: (blank)
A6: 1. Panels | D6: 2653053 | H6: 14813.8 | K6: 2667866.8
A7: 2. Inverters | D7: 757573.94 | K7: 757573.94
A8: 3. Mounting Structures | D8: 339516.22 | E8: 71394.92 | H8: -51489.25 | I8: 3737.49 | K8: 363159.38
A9: 4. DC Equipment | D9: 586316.3 | F9: 50899.56 | H9: 16966.52 | I9: 25449.78 | J9: 33933.04 | K9: 713565.2
A10: 5. Monitoring | C10: 58744.5 | D10: -8100.66 | E10: 40621.45 | K10: 91265.29
A11: 6. AC Equipment | D11: 57877.2 | E11: 354929.22 | F11: 69452.44 | H11: 23150.88 | I11: 34726.32 | J11: 46301.76 | K11: 586437.82
A12: 8. Product Add On | D12: 232956 | F12: 48720 | H12: 10150 | I12: 50000 | K12: 341826
A13: 9. AC & DC installation | D13: 276323.05 | F13: 331587.66 | H13: 110529.23 | I13: 165793.84 | J13: 221058.44 | K13: 1105292.2
A14: 10. Site Logistics | D14: 85136 | E14: 60000 | F14: 68963.1 | H14: 19654.4 | I14: 29481.6 | J14: 39308.8 | K14: 302543.9
A15: 11. Due Dilligence | C15: 98339.6 | I15: 44004.25 | K15: 142343.85
A16: 13. Engineering | I16: 130354.3 | K16: 130354.3
A17: 14. General Expenses | C17: 13986.75 | D17: 10587.7 | E17: 5515.35 | F17: 0 | H17: 0 | I17: 8500 | K17: 38589.8
A18: 15. Service Add On | F18: 56132.72 | H18: 150275.33 | J18: 21393.95 | K18: 227802
A19: 12. BDP Commission
A20: 7.BESS
A21: Grand Total | C21: 171070.85 | D21: 4991238.7 | E21: 532460.94 | F21: 625755.48 | H21: 294050.91 | I21: 492047.58 | J21: 361995.99 | K21: 7468620.5

Sheet Project Margins
A1: [capture project margins from costing sheet]
A3: Products | D3: 0.32
A4: Services | D4: 0.5
A5: Expenses | D5: 0.15
A6: Subcontractors | D6: 0.2

Sheet Equipment Quotes
B2: Equipment Quote and Budget comparision
B4: Description | D4: Budget | F4: Supplier 1 | H4: Variance | J4: Supplier 2 | L4: Variance | N4: Comments / Notes
F7: >Name< | J7: >Name<
B9: Inverters | D9: =SUM(D10:D11) -> #REF! | F9: =SUM(F10:F13) -> 0 | H9: =$D$9-F9 -> #REF! | J9: =SUM(J10:J13) -> 0 | L9: =$D$9-J9 -> #REF!
B10: Inverters | D10: =#REF! -> #REF!
B11: Optimizers | D11: =#REF! -> #REF!
B12: Warranty
B13: Delivery fee
F15: >Name< | J15: >Name<
B17: Mounting Structure | D17: =SUM(D18:D19) -> #REF! | F17: =SUM(F18:F20) -> 0 | H17: =$D$17- F17 -> #REF! | J17: =SUM(J18:J20) -> 0 | L17: =$D$17- J17 -> #REF!
B18: Mounting Structure | D18: =#REF! -> #REF!
B19: Delivery fee
F21: >Name< | J21: >Name<
B23: DC Cable | D23: =SUM(D24:D25) -> #REF! | F23: =SUM(F24:F25) -> 0 | H23: =$D$23- F23 -> #REF! | J23: =SUM(J24:J25) -> 0 | L23: =$D$23- J23 -> #REF!
B24: DC Cable | D24: =#REF! -> #REF!
B25: Delivery fee
F27: >Name< | J27: >Name<
B29: Monitoring system | D29: =SUM(D30:D32) -> #REF! | F29: =SUM(F30:F42) -> 0 | H29: =$D$29-F29 -> #REF! | J29: =SUM(J30:J32) -> 0 | L29: =$D$29-J29 -> #REF!
B30: =#REF! -> #REF! | D30: =#REF! -> #REF!
B31: =#REF! -> #REF! | D31: =#REF! -> #REF!
B32: Delivery fee
F34: >Name< | J34: >Name<
B36: Additional Scope | D36: =SUM(D37:D41) -> #REF! | F36: =SUM(F37:F41) -> 0 | H36: =$D$29-F36 -> #REF! | J36: =SUM(J37:J41) -> 0 | L36: =$D$29-J36 -> #REF!
B37: SCADA | D37: =#REF! -> #REF!
B38: Inverter cage
B39: Cat ladders
B40: Gen Integration
B41: Lifelines
B43: Totals | D43: =D36+D29+D23+D17+D9 -> #REF! | H43: =SUM(H7:H42) -> #REF! | L43: =SUM(L7:L42) -> #REF!
B47: All amounts are incl VAT

Sheet Installer Quotes
B2: Installer Quote and Budget comparision
B4: Description | D4: Budget | G4: Cosmic Sun | J4: Variance | L4: Matthews Group | O4: Variance
B6: AC Equipment | D6: =#REF! -> #REF! | E6: =D6/(1000*'Project Plan'!$E$3) -> #REF! | G6: 277892.91 | H6: =G6/('Project Plan'!$E$3*1000) -> 0.20433302 | J6: =D6-G6 -> #REF! | M6: =L6/('Project Plan'!$E$3*1000) -> 0 | O6: =D6-L6 -> #REF!
B7: DC Equipment | D7: =#REF! -> #REF! | E7: =D7/(1000*'Project Plan'!$E$3) -> #REF! | G7: 142158.25 | H7: =G7/('Project Plan'!$E$3*1000) -> 0.10452812 | J7: =D7-G7 -> #REF! | M7: =L7/('Project Plan'!$E$3*1000) -> 0 | O7: =D7-L7 -> #REF!
B8: AC Labour | D8: =#REF! -> #REF! | E8: =D8/(1000*'Project Plan'!$E$3) -> #REF! | G8: 96174 | H8: =G8/('Project Plan'!$E$3*1000) -> 0.070716176 | J8: =D8-G8 -> #REF! | M8: =L8/('Project Plan'!$E$3*1000) -> 0 | O8: =D8-L8 -> #REF!
B9: DC Labour | D9: =#REF! -> #REF! | E9: =D9/(1000*'Project Plan'!$E$3) -> #REF! | G9: 230160 | H9: =G9/('Project Plan'!$E$3*1000) -> 0.16923529 | J9: =D9-G9 -> #REF! | M9: =L9/('Project Plan'!$E$3*1000) -> 0 | O9: =D9-L9 -> #REF!
B10: Offloading | D10: =#REF! -> #REF! | G10: 0 | J10: =D10-G10 -> #REF! | O10: =D10-L10 -> #REF!
B11: Roof Access/Scaffolding | D11: =#REF! -> #REF! | G11: 29257.61 | J11: =D11-G11 -> #REF! | O11: =D11-L11 -> #REF!
B12: Storage | D12: =#REF! -> #REF! | J12: =D12-G12 -> #REF! | O12: =D12-L12 -> #REF!
B13: Telehandler | D13: =#REF! -> #REF!
B14: HSE | D14: 0
B15: Totals | D15: =SUM(D6:D13) -> #REF! | G15: =SUM(G6:G13) -> 775642.77 | J15: =SUM(J6:J14) -> #REF! | L15: =SUM(L6:L13) -> 0 | O15: =SUM(O6:O14) -> #REF!
B18: Description | D18: Budget | G18: >Installer Name 3< | J18: Variance | L18: >Installer Name 4< | O18: Variance
B20: AC installation | D20: =#REF! -> #REF! | E20: =D20/(1000*'Project Plan'!$E$3) -> #REF! | H20: =G20/(1000*'Project Plan'!$E$3) -> 0 | J20: =D20-G20 -> #REF! | M20: =L20/(1000*'Project Plan'!$E$3) -> 0 | O20: =D6-L20 -> #REF!
B21: AC equipment | D21: =#REF! -> #REF! | E21: =D21/(1000*'Project Plan'!$E$3) -> #REF! | J21: =D21-G21 -> #REF! | M21: =L21/(1000*'Project Plan'!$E$3) -> 0 | O21: =D7-L21 -> #REF!
B22: DC installation | D22: =#REF! -> #REF! | E22: =D22/(1000*'Project Plan'!$E$3) -> #REF! | H22: =G22/(1000*'Project Plan'!$E$3) -> 0 | J22: =D22-G22 -> #REF! | M22: =L22/(1000*'Project Plan'!$E$3) -> 0 | O22: =D8-L22 -> #REF!
B23: DC equipment | D23: =SUM(#REF!) -> #REF! | E23: =D23/(1000*'Project Plan'!$E$3) -> #REF! | J23: =D23-G23 -> #REF! | O23: =D9-L23 -> #REF!
B24: Storage | D24: =#REF! -> #REF! | J24: =D24-G24 -> #REF! | O24: =D10-L24 -> #REF!
B25: Panel lifting equipment | D25: =SUM(#REF!) -> #REF! | J25: =D25-G25 -> #REF! | O25: =D11-L25 -> #REF!
B26: Offloading | D26: =#REF! -> #REF! | J26: =D26-G26 -> #REF! | O26: =D12-L26 -> #REF!
B29: Totals | D29: =SUM(D20:D27) -> #REF! | G29: =SUM(G20:G27) -> 0 | J29: =SUM(J20:J28) -> #REF! | L29: =SUM(L20:L27) -> 0 | O29: =SUM(O20:O28) -> #REF!
B32: Budget Summary
B34: Budget | D34: =D15 -> #REF!
B35: =G4 -> Cosmic Sun | D35: =G15 -> 775642.77
B36: =L4 -> Matthews Group | D36: =L15 -> 0
B37: =G18 -> >Installer Name 3< | D37: =G29 -> 0
B38: =L18 -> >Installer Name 4< | D38: =L29 -> 0
B40: =IF(D40<D34,"Saving","Loss") -> #REF! | D40: =D34-MIN(D35:D38) -> #REF!
B42: All amounts are exc VAT

Sheet Decision Register
B1: =D15 -> Seshego Circle | E1: Decision Register
B3: ID | C3: Decision Description | D3: Decision Impact | E3: Proposed Date | F3: Proposed By | G3: Status | H3: Approved By | I3: Date | J3: Results / Comments
B4: DEC001
B5: DEC002
B6: DEC003
B7: DEC004
B8: DEC005
B9: DEC006
B10: DEC007
B11: DEC008
B12: DEC009
B13: DEC010
D15: {='Project Plan'!E2:H2} -> Seshego Circle | E15: 0 | F15: 0 | G15: 0
