Workbook
Name Inverter_Capacity: #REF!
Name Inverter_Capacity: #REF!
Name Inverter_Capacity: #REF!
Name Inverter_Supplier: #REF!
Name Inverter_Supplier: #REF!
Name Inverter_Supplier: #REF!
Name Project_Size: 'Certificate - Financial Close'!Projectsize
Name Project_Size: Compliance!Projectsize
Name Project_Size: 'Finance - Revenue'!Projectsize
Name Project_Size: Projectsize
Name Projectsize: #REF!
Name Projectsize: #REF!
Name Projectsize: #REF!
Name Projectsize: 'Project Margins'!$K$5
Name Security_Serv: #REF!
Name Security_Serv: #REF!
Name SSS: #REF!
Name SSS: #REF!
Name USD_ZAR: #REF!
Name USD_ZAR: #REF!
Name USD_ZAR: #REF!

Sheet Sheet1
A1: PROJECT PLAN
A2: # | B2: Project Milestone | C2: Planned Start Date | D2: Duration (Work Days) | E2: Planned End Date | F2: Actual Start Date | H2: Actual End Date | J2: Comments | L2: =C3 -> 43831 | M2: =L2+3 -> 43834 | N2: =M2+7 -> 43841 | O2: =N2+7 -> 43848 | P2: =O2+7 -> 43855 | Q2: =P2+6 -> 43861 | R2: =Q2+1 -> 43862 | S2: =R2+7 -> 43869 | T2: =S2+7 -> 43876 | U2: =T2+7 -> 43883 | V2: =U2+6 -> 43889 | W2: =V2+7 -> 43896 | X2: =W2+7 -> 43903 | Y2: =X2+7 -> 43910 | Z2: =Y2+7 -> 43917 | AA2: =Z2+3 -> 43920 | AB2: =AA2+4 -> 43924 | AC2: =AB2+7 -> 43931 | AD2: =AC2+7 -> 43938 | AE2: =AD2+7 -> 43945 | AF2: =AE2+6 -> 43951 | AG2: =AF2+2 -> 43953 | AH2: =AG2+7 -> 43960 | AI2: =AH2+7 -> 43967 | AJ2: =AI2+7 -> 43974 | AK2: =AJ2+7 -> 43981 | AL2: =AK2+1 -> 43982 | AM2: =AL2+6 -> 43988 | AN2: =AM2+7 -> 43995 | AO2: =AN2+7 -> 44002 | AP2: =AO2+7 -> 44009 | AQ2: =AP2+3 -> 44012 | AR2: =AQ2+4 -> 44016 | AS2: =AR2+7 -> 44023 | AT2: =AS2+7 -> 44030 | AU2: =AT2+7 -> 44037 | AV2: =AU2+6 -> 44043 | AW2: =AV2+1 -> 44044 | AX2: =AW2+7 -> 44051 | AY2: =AX2+7 -> 44058 | AZ2: =AY2+7 -> 44065 | BA2: =AZ2+7 -> 44072 | BB2: =BA2+2 -> 44074 | BC2: =BB2+5 -> 44079 | BD2: =BC2+7 -> 44086 | BE2: =BD2+7 -> 44093 | BF2: =BE2+7 -> 44100 | BG2: =BF2+4 -> 44104
A3: 1 | B3: Contract Signature | C3: 43831 | D3: 1 | E3: 43832 | F3: 43831 | G3: 1 | H3: 43832 | L3: =IF(AND($F3<(L$2+7),$F3>L$2),1, IF(AND($H3<L$2+7,$H3>L$2),3, IF(AND($F3<=L$2, $H3>=L$2), 2, "" ))) -> 3 | M3: =IF(AND($F3<(M$2+7),$F3>M$2),1, IF(AND($H3<M$2+7,$H3>M$2),3, IF(AND($F3<=M$2, $H3>=M$2), 2, "" ))) | N3: =IF(AND($F3<(N$2+7),$F3>N$2),1, IF(AND($H3<N$2+7,$H3>N$2),3, IF(AND($F3<=N$2, $H3>=N$2), 2, "" ))) | O3: =IF(AND($F3<(O$2+7),$F3>O$2),1, IF(AND($H3<O$2+7,$H3>O$2),3, IF(AND($F3<=O$2, $H3>=O$2), 2, "" ))) | P3: =IF(AND($F3<(P$2+7),$F3>P$2),1, IF(AND($H3<P$2+7,$H3>P$2),3, IF(AND($F3<=P$2, $H3>=P$2), 2, "" ))) | Q3: =IF(AND($F3<(Q$2+7),$F3>Q$2),1, IF(AND($H3<Q$2+7,$H3>Q$2),3, IF(AND($F3<=Q$2, $H3>=Q$2), 2, "" ))) | R3: =IF(AND($F3<(R$2+7),$F3>R$2),1, IF(AND($H3<R$2+7,$H3>R$2),3, IF(AND($F3<=R$2, $H3>=R$2), 2, "" ))) | S3: =IF(AND($F3<(S$2+7),$F3>S$2),1, IF(AND($H3<S$2+7,$H3>S$2),3, IF(AND($F3<=S$2, $H3>=S$2), 2, "" ))) | ... AQ3: =IF(AND($F3<(AQ$2+7),$F3>AQ$2),1, IF(AND($H3<AQ$2+7,$H3>AQ$2),3, IF(AND($F3<=AQ$2, $H3>=AQ$2), 2, "" )))
A4: A | B4: PAYMENT MILESTONE 1: DEPOSIT | C4: 43832 | D4: 1 | E4: 43833 | F4: 43832 | G4: 1 | H4: 43833 | L4: =IF(AND($F4<(L$2+7),$F4>L$2),1, IF(AND($H4<L$2+7,$H4>L$2),3, IF(AND($F4<=L$2, $H4>=L$2), 2, "" ))) -> 1 | M4: =IF(AND($F4<(M$2+7),$F4>M$2),1, IF(AND($H4<M$2+7,$H4>M$2),3, IF(AND($F4<=M$2, $H4>=M$2), 2, "" ))) | N4: =IF(AND($F4<(N$2+7),$F4>N$2),1, IF(AND($H4<N$2+7,$H4>N$2),3, IF(AND($F4<=N$2, $H4>=N$2), 2, "" ))) | O4: =IF(AND($F4<(O$2+7),$F4>O$2),1, IF(AND($H4<O$2+7,$H4>O$2),3, IF(AND($F4<=O$2, $H4>=O$2), 2, "" ))) | P4: =IF(AND($F4<(P$2+7),$F4>P$2),1, IF(AND($H4<P$2+7,$H4>P$2),3, IF(AND($F4<=P$2, $H4>=P$2), 2, "" ))) | Q4: =IF(AND($F4<(Q$2+7),$F4>Q$2),1, IF(AND($H4<Q$2+7,$H4>Q$2),3, IF(AND($F4<=Q$2, $H4>=Q$2), 2, "" ))) | R4: =IF(AND($F4<(R$2+7),$F4>R$2),1, IF(AND($H4<R$2+7,$H4>R$2),3, IF(AND($F4<=R$2, $H4>=R$2), 2, "" ))) | S4: =IF(AND($F4<(S$2+7),$F4>S$2),1, IF(AND($H4<S$2+7,$H4>S$2),3, IF(AND($F4<=S$2, $H4>=S$2), 2, "" ))) | ... AQ4: =IF(AND($F4<(AQ$2+7),$F4>AQ$2),1, IF(AND($H4<AQ$2+7,$H4>AQ$2),3, IF(AND($F4<=AQ$2, $H4>=AQ$2), 2, "" )))
A5: 2 | B5: Structural and Electrical Due Diligences | C5: 43833 | D5: 5 | E5: 43840 | F5: 43833 | G5: 5 | H5: 43840 | L5: =IF(AND($F5<(L$2+7),$F5>L$2),1, IF(AND($H5<L$2+7,$H5>L$2),3, IF(AND($F5<=L$2, $H5>=L$2), 2, "" ))) -> 1 | M5: =IF(AND($F5<(M$2+7),$F5>M$2),1, IF(AND($H5<M$2+7,$H5>M$2),3, IF(AND($F5<=M$2, $H5>=M$2), 2, "" ))) -> 3 | N5: =IF(AND($F5<(N$2+7),$F5>N$2),1, IF(AND($H5<N$2+7,$H5>N$2),3, IF(AND($F5<=N$2, $H5>=N$2), 2, "" ))) | O5: =IF(AND($F5<(O$2+7),$F5>O$2),1, IF(AND($H5<O$2+7,$H5>O$2),3, IF(AND($F5<=O$2, $H5>=O$2), 2, "" ))) | P5: =IF(AND($F5<(P$2+7),$F5>P$2),1, IF(AND($H5<P$2+7,$H5>P$2),3, IF(AND($F5<=P$2, $H5>=P$2), 2, "" ))) | Q5: =IF(AND($F5<(Q$2+7),$F5>Q$2),1, IF(AND($H5<Q$2+7,$H5>Q$2),3, IF(AND($F5<=Q$2, $H5>=Q$2), 2, "" ))) | R5: =IF(AND($F5<(R$2+7),$F5>R$2),1, IF(AND($H5<R$2+7,$H5>R$2),3, IF(AND($F5<=R$2, $H5>=R$2), 2, "" ))) | S5: =IF(AND($F5<(S$2+7),$F5>S$2),1, IF(AND($H5<S$2+7,$H5>S$2),3, IF(AND($F5<=S$2, $H5>=S$2), 2, "" ))) | ... AQ5: =IF(AND($F5<(AQ$2+7),$F5>AQ$2),1, IF(AND($H5<AQ$2+7,$H5>AQ$2),3, IF(AND($F5<=AQ$2, $H5>=AQ$2), 2, "" )))
A6: 3 | B6: Design Confirmation | C6: 43841 | D6: 2 | E6: 43844 | F6: 43841 | G6: 2 | H6: 43844 | L6: =IF(AND($F6<(L$2+7),$F6>L$2),1, IF(AND($H6<L$2+7,$H6>L$2),3, IF(AND($F6<=L$2, $H6>=L$2), 2, "" ))) | M6: =IF(AND($F6<(M$2+7),$F6>M$2),1, IF(AND($H6<M$2+7,$H6>M$2),3, IF(AND($F6<=M$2, $H6>=M$2), 2, "" ))) | N6: =IF(AND($F6<(N$2+7),$F6>N$2),1, IF(AND($H6<N$2+7,$H6>N$2),3, IF(AND($F6<=N$2, $H6>=N$2), 2, "" ))) -> 3 | O6: =IF(AND($F6<(O$2+7),$F6>O$2),1, IF(AND($H6<O$2+7,$H6>O$2),3, IF(AND($F6<=O$2, $H6>=O$2), 2, "" ))) | P6: =IF(AND($F6<(P$2+7),$F6>P$2),1, IF(AND($H6<P$2+7,$H6>P$2),3, IF(AND($F6<=P$2, $H6>=P$2), 2, "" ))) | Q6: =IF(AND($F6<(Q$2+7),$F6>Q$2),1, IF(AND($H6<Q$2+7,$H6>Q$2),3, IF(AND($F6<=Q$2, $H6>=Q$2), 2, "" ))) | R6: =IF(AND($F6<(R$2+7),$F6>R$2),1, IF(AND($H6<R$2+7,$H6>R$2),3, IF(AND($F6<=R$2, $H6>=R$2), 2, "" ))) | S6: =IF(AND($F6<(S$2+7),$F6>S$2),1, IF(AND($H6<S$2+7,$H6>S$2),3, IF(AND($F6<=S$2, $H6>=S$2), 2, "" ))) | ... AQ6: =IF(AND($F6<(AQ$2+7),$F6>AQ$2),1, IF(AND($H6<AQ$2+7,$H6>AQ$2),3, IF(AND($F6<=AQ$2, $H6>=AQ$2), 2, "" )))
A7: 4 | B7: Equipment Procurement | C7: 43833 | E7: 43949 | F7: 43833 | H7: 43949 | L7: =IF(AND($F7<(L$2+7),$F7>L$2),1, IF(AND($H7<L$2+7,$H7>L$2),3, IF(AND($F7<=L$2, $H7>=L$2), 2, "" ))) -> 1 | M7: =IF(AND($F7<(M$2+7),$F7>M$2),1, IF(AND($H7<M$2+7,$H7>M$2),3, IF(AND($F7<=M$2, $H7>=M$2), 2, "" ))) -> 2 | N7: =IF(AND($F7<(N$2+7),$F7>N$2),1, IF(AND($H7<N$2+7,$H7>N$2),3, IF(AND($F7<=N$2, $H7>=N$2), 2, "" ))) -> 2 | O7: =IF(AND($F7<(O$2+7),$F7>O$2),1, IF(AND($H7<O$2+7,$H7>O$2),3, IF(AND($F7<=O$2, $H7>=O$2), 2, "" ))) -> 2 | P7: =IF(AND($F7<(P$2+7),$F7>P$2),1, IF(AND($H7<P$2+7,$H7>P$2),3, IF(AND($F7<=P$2, $H7>=P$2), 2, "" ))) -> 2 | Q7: =IF(AND($F7<(Q$2+7),$F7>Q$2),1, IF(AND($H7<Q$2+7,$H7>Q$2),3, IF(AND($F7<=Q$2, $H7>=Q$2), 2, "" ))) -> 2 | R7: =IF(AND($F7<(R$2+7),$F7>R$2),1, IF(AND($H7<R$2+7,$H7>R$2),3, IF(AND($F7<=R$2, $H7>=R$2), 2, "" ))) -> 2 | S7: =IF(AND($F7<(S$2+7),$F7>S$2),1, IF(AND($H7<S$2+7,$H7>S$2),3, IF(AND($F7<=S$2, $H7>=S$2), 2, "" ))) -> 2 | ... AQ7: =IF(AND($F7<(AQ$2+7),$F7>AQ$2),1, IF(AND($H7<AQ$2+7,$H7>AQ$2),3, IF(AND($F7<=AQ$2, $H7>=AQ$2), 2, "" )))
B8: Panel Procurement | C8: 43833 | D8: 5 | E8: 43840 | F8: 43833 | G8: 5 | H8: 43840 | L8: =IF(AND($F8<(L$2+7),$F8>L$2),1, IF(AND($H8<L$2+7,$H8>L$2),3, IF(AND($F8<=L$2, $H8>=L$2), 2, "" ))) -> 1 | M8: =IF(AND($F8<(M$2+7),$F8>M$2),1, IF(AND($H8<M$2+7,$H8>M$2),3, IF(AND($F8<=M$2, $H8>=M$2), 2, "" ))) -> 3 | N8: =IF(AND($F8<(N$2+7),$F8>N$2),1, IF(AND($H8<N$2+7,$H8>N$2),3, IF(AND($F8<=N$2, $H8>=N$2), 2, "" ))) | O8: =IF(AND($F8<(O$2+7),$F8>O$2),1, IF(AND($H8<O$2+7,$H8>O$2),3, IF(AND($F8<=O$2, $H8>=O$2), 2, "" ))) | P8: =IF(AND($F8<(P$2+7),$F8>P$2),1, IF(AND($H8<P$2+7,$H8>P$2),3, IF(AND($F8<=P$2, $H8>=P$2), 2, "" ))) | Q8: =IF(AND($F8<(Q$2+7),$F8>Q$2),1, IF(AND($H8<Q$2+7,$H8>Q$2),3, IF(AND($F8<=Q$2, $H8>=Q$2), 2, "" ))) | R8: =IF(AND($F8<(R$2+7),$F8>R$2),1, IF(AND($H8<R$2+7,$H8>R$2),3, IF(AND($F8<=R$2, $H8>=R$2), 2, "" ))) | S8: =IF(AND($F8<(S$2+7),$F8>S$2),1, IF(AND($H8<S$2+7,$H8>S$2),3, IF(AND($F8<=S$2, $H8>=S$2), 2, "" ))) | ... AQ8: =IF(AND($F8<(AQ$2+7),$F8>AQ$2),1, IF(AND($H8<AQ$2+7,$H8>AQ$2),3, IF(AND($F8<=AQ$2, $H8>=AQ$2), 2, "" )))
B9: Inverter Procurement | C9: 43941 | D9: 5 | E9: 43949 | F9: 43941 | G9: 5 | H9: 43949 | L9: =IF(AND($F9<(L$2+7),$F9>L$2),1, IF(AND($H9<L$2+7,$H9>L$2),3, IF(AND($F9<=L$2, $H9>=L$2), 2, "" ))) | M9: =IF(AND($F9<(M$2+7),$F9>M$2),1, IF(AND($H9<M$2+7,$H9>M$2),3, IF(AND($F9<=M$2, $H9>=M$2), 2, "" ))) | N9: =IF(AND($F9<(N$2+7),$F9>N$2),1, IF(AND($H9<N$2+7,$H9>N$2),3, IF(AND($F9<=N$2, $H9>=N$2), 2, "" ))) | O9: =IF(AND($F9<(O$2+7),$F9>O$2),1, IF(AND($H9<O$2+7,$H9>O$2),3, IF(AND($F9<=O$2, $H9>=O$2), 2, "" ))) | P9: =IF(AND($F9<(P$2+7),$F9>P$2),1, IF(AND($H9<P$2+7,$H9>P$2),3, IF(AND($F9<=P$2, $H9>=P$2), 2, "" ))) | Q9: =IF(AND($F9<(Q$2+7),$F9>Q$2),1, IF(AND($H9<Q$2+7,$H9>Q$2),3, IF(AND($F9<=Q$2, $H9>=Q$2), 2, "" ))) | R9: =IF(AND($F9<(R$2+7),$F9>R$2),1, IF(AND($H9<R$2+7,$H9>R$2),3, IF(AND($F9<=R$2, $H9>=R$2), 2, "" ))) | S9: =IF(AND($F9<(S$2+7),$F9>S$2),1, IF(AND($H9<S$2+7,$H9>S$2),3, IF(AND($F9<=S$2, $H9>=S$2), 2, "" ))) | ... AQ9: =IF(AND($F9<(AQ$2+7),$F9>AQ$2),1, IF(AND($H9<AQ$2+7,$H9>AQ$2),3, IF(AND($F9<=AQ$2, $H9>=AQ$2), 2, "" )))
B10: Mounting Structure Procurement | C10: 43941 | D10: 5 | E10: 43949 | F10: 43941 | G10: 5 | H10: 43949 | L10: =IF(AND($F10<(L$2+7),$F10>L$2),1, IF(AND($H10<L$2+7,$H10>L$2),3, IF(AND($F10<=L$2, $H10>=L$2), 2, "" ))) | M10: =IF(AND($F10<(M$2+7),$F10>M$2),1, IF(AND($H10<M$2+7,$H10>M$2),3, IF(AND($F10<=M$2, $H10>=M$2), 2, "" ))) | N10: =IF(AND($F10<(N$2+7),$F10>N$2),1, IF(AND($H10<N$2+7,$H10>N$2),3, IF(AND($F10<=N$2, $H10>=N$2), 2, "" ))) | O10: =IF(AND($F10<(O$2+7),$F10>O$2),1, IF(AND($H10<O$2+7,$H10>O$2),3, IF(AND($F10<=O$2, $H10>=O$2), 2, "" ))) | P10: =IF(AND($F10<(P$2+7),$F10>P$2),1, IF(AND($H10<P$2+7,$H10>P$2),3, IF(AND($F10<=P$2, $H10>=P$2), 2, "" ))) | Q10: =IF(AND($F10<(Q$2+7),$F10>Q$2),1, IF(AND($H10<Q$2+7,$H10>Q$2),3, IF(AND($F10<=Q$2, $H10>=Q$2), 2, "" ))) | R10: =IF(AND($F10<(R$2+7),$F10>R$2),1, IF(AND($H10<R$2+7,$H10>R$2),3, IF(AND($F10<=R$2, $H10>=R$2), 2, "" ))) | S10: =IF(AND($F10<(S$2+7),$F10>S$2),1, IF(AND($H10<S$2+7,$H10>S$2),3, IF(AND($F10<=S$2, $H10>=S$2), 2, "" ))) | ... AQ10: =IF(AND($F10<(AQ$2+7),$F10>AQ$2),1, IF(AND($H10<AQ$2+7,$H10>AQ$2),3, IF(AND($F10<=AQ$2, $H10>=AQ$2), 2, "" )))
B11: BOS Procurement | C11: 43941 | D11: 5 | E11: 43949 | F11: 43941 | G11: 5 | H11: 43949 | L11: =IF(AND($F11<(L$2+7),$F11>L$2),1, IF(AND($H11<L$2+7,$H11>L$2),3, IF(AND($F11<=L$2, $H11>=L$2), 2, "" ))) | M11: =IF(AND($F11<(M$2+7),$F11>M$2),1, IF(AND($H11<M$2+7,$H11>M$2),3, IF(AND($F11<=M$2, $H11>=M$2), 2, "" ))) | N11: =IF(AND($F11<(N$2+7),$F11>N$2),1, IF(AND($H11<N$2+7,$H11>N$2),3, IF(AND($F11<=N$2, $H11>=N$2), 2, "" ))) | O11: =IF(AND($F11<(O$2+7),$F11>O$2),1, IF(AND($H11<O$2+7,$H11>O$2),3, IF(AND($F11<=O$2, $H11>=O$2), 2, "" ))) | P11: =IF(AND($F11<(P$2+7),$F11>P$2),1, IF(AND($H11<P$2+7,$H11>P$2),3, IF(AND($F11<=P$2, $H11>=P$2), 2, "" ))) | Q11: =IF(AND($F11<(Q$2+7),$F11>Q$2),1, IF(AND($H11<Q$2+7,$H11>Q$2),3, IF(AND($F11<=Q$2, $H11>=Q$2), 2, "" ))) | R11: =IF(AND($F11<(R$2+7),$F11>R$2),1, IF(AND($H11<R$2+7,$H11>R$2),3, IF(AND($F11<=R$2, $H11>=R$2), 2, "" ))) | S11: =IF(AND($F11<(S$2+7),$F11>S$2),1, IF(AND($H11<S$2+7,$H11>S$2),3, IF(AND($F11<=S$2, $H11>=S$2), 2, "" ))) | ... AQ11: =IF(AND($F11<(AQ$2+7),$F11>AQ$2),1, IF(AND($H11<AQ$2+7,$H11>AQ$2),3, IF(AND($F11<=AQ$2, $H11>=AQ$2), 2, "" )))
A12: 5 | B12: Internal Project Kick off | C12: 43936 | D12: 5 | E12: 43943 | F12: 43936 | G12: 5 | H12: 43943
A13: 6 | B13: Client Project Kick-off | C13: 43963 | D13: 5 | E13: 43970 | F13: 43963 | G13: 5 | H13: 43970 | L13: =IF(AND($F13<(L$2+7),$F13>L$2),1, IF(AND($H13<L$2+7,$H13>L$2),3, IF(AND($F13<=L$2, $H13>=L$2), 2, "" ))) | M13: =IF(AND($F13<(M$2+7),$F13>M$2),1, IF(AND($H13<M$2+7,$H13>M$2),3, IF(AND($F13<=M$2, $H13>=M$2), 2, "" ))) | N13: =IF(AND($F13<(N$2+7),$F13>N$2),1, IF(AND($H13<N$2+7,$H13>N$2),3, IF(AND($F13<=N$2, $H13>=N$2), 2, "" ))) | O13: =IF(AND($F13<(O$2+7),$F13>O$2),1, IF(AND($H13<O$2+7,$H13>O$2),3, IF(AND($F13<=O$2, $H13>=O$2), 2, "" ))) | P13: =IF(AND($F13<(P$2+7),$F13>P$2),1, IF(AND($H13<P$2+7,$H13>P$2),3, IF(AND($F13<=P$2, $H13>=P$2), 2, "" ))) | Q13: =IF(AND($F13<(Q$2+7),$F13>Q$2),1, IF(AND($H13<Q$2+7,$H13>Q$2),3, IF(AND($F13<=Q$2, $H13>=Q$2), 2, "" ))) | R13: =IF(AND($F13<(R$2+7),$F13>R$2),1, IF(AND($H13<R$2+7,$H13>R$2),3, IF(AND($F13<=R$2, $H13>=R$2), 2, "" ))) | S13: =IF(AND($F13<(S$2+7),$F13>S$2),1, IF(AND($H13<S$2+7,$H13>S$2),3, IF(AND($F13<=S$2, $H13>=S$2), 2, "" ))) | ... AQ13: =IF(AND($F13<(AQ$2+7),$F13>AQ$2),1, IF(AND($H13<AQ$2+7,$H13>AQ$2),3, IF(AND($F13<=AQ$2, $H13>=AQ$2), 2, "" )))
A14: 7 | B14: Equipment Delivery | C14: 43983 | D14: 9 | E14: 43994 | F14: 43983 | G14: 9 | H14: 43994 | L14: =IF(AND($F14<(L$2+7),$F14>L$2),1, IF(AND($H14<L$2+7,$H14>L$2),3, IF(AND($F14<=L$2, $H14>=L$2), 2, "" ))) | M14: =IF(AND($F14<(M$2+7),$F14>M$2),1, IF(AND($H14<M$2+7,$H14>M$2),3, IF(AND($F14<=M$2, $H14>=M$2), 2, "" ))) | N14: =IF(AND($F14<(N$2+7),$F14>N$2),1, IF(AND($H14<N$2+7,$H14>N$2),3, IF(AND($F14<=N$2, $H14>=N$2), 2, "" ))) | O14: =IF(AND($F14<(O$2+7),$F14>O$2),1, IF(AND($H14<O$2+7,$H14>O$2),3, IF(AND($F14<=O$2, $H14>=O$2), 2, "" ))) | P14: =IF(AND($F14<(P$2+7),$F14>P$2),1, IF(AND($H14<P$2+7,$H14>P$2),3, IF(AND($F14<=P$2, $H14>=P$2), 2, "" ))) | Q14: =IF(AND($F14<(Q$2+7),$F14>Q$2),1, IF(AND($H14<Q$2+7,$H14>Q$2),3, IF(AND($F14<=Q$2, $H14>=Q$2), 2, "" ))) | R14: =IF(AND($F14<(R$2+7),$F14>R$2),1, IF(AND($H14<R$2+7,$H14>R$2),3, IF(AND($F14<=R$2, $H14>=R$2), 2, "" ))) | S14: =IF(AND($F14<(S$2+7),$F14>S$2),1, IF(AND($H14<S$2+7,$H14>S$2),3, IF(AND($F14<=S$2, $H14>=S$2), 2, "" ))) | ... AQ14: =IF(AND($F14<(AQ$2+7),$F14>AQ$2),1, IF(AND($H14<AQ$2+7,$H14>AQ$2),3, IF(AND($F14<=AQ$2, $H14>=AQ$2), 2, "" )))
B15: Mounting Structure Delivery | C15: 43983 | D15: 2 | E15: 43985 | F15: 43983 | G15: 2 | H15: 43985
B16: Panel Delivery | C16: 43990 | D16: 2 | E16: 43992 | F16: 43990 | G16: 2 | H16: 43992 | L16: =IF(AND($F16<(L$2+7),$F16>L$2),1, IF(AND($H16<L$2+7,$H16>L$2),3, IF(AND($F16<=L$2, $H16>=L$2), 2, "" ))) | M16: =IF(AND($F16<(M$2+7),$F16>M$2),1, IF(AND($H16<M$2+7,$H16>M$2),3, IF(AND($F16<=M$2, $H16>=M$2), 2, "" ))) | N16: =IF(AND($F16<(N$2+7),$F16>N$2),1, IF(AND($H16<N$2+7,$H16>N$2),3, IF(AND($F16<=N$2, $H16>=N$2), 2, "" ))) | O16: =IF(AND($F16<(O$2+7),$F16>O$2),1, IF(AND($H16<O$2+7,$H16>O$2),3, IF(AND($F16<=O$2, $H16>=O$2), 2, "" ))) | P16: =IF(AND($F16<(P$2+7),$F16>P$2),1, IF(AND($H16<P$2+7,$H16>P$2),3, IF(AND($F16<=P$2, $H16>=P$2), 2, "" ))) | Q16: =IF(AND($F16<(Q$2+7),$F16>Q$2),1, IF(AND($H16<Q$2+7,$H16>Q$2),3, IF(AND($F16<=Q$2, $H16>=Q$2), 2, "" ))) | R16: =IF(AND($F16<(R$2+7),$F16>R$2),1, IF(AND($H16<R$2+7,$H16>R$2),3, IF(AND($F16<=R$2, $H16>=R$2), 2, "" ))) | S16: =IF(AND($F16<(S$2+7),$F16>S$2),1, IF(AND($H16<S$2+7,$H16>S$2),3, IF(AND($F16<=S$2, $H16>=S$2), 2, "" ))) | ... AQ16: =IF(AND($F16<(AQ$2+7),$F16>AQ$2),1, IF(AND($H16<AQ$2+7,$H16>AQ$2),3, IF(AND($F16<=AQ$2, $H16>=AQ$2), 2, "" )))
B17: Generator Delivery | C17: 43983 | D17: 2 | E17: 43985 | F17: 43983 | G17: 2 | H17: 43985
A18: B | B18: PAYMENT MILESTONE 2: DELIVERY OF PV PANELS | C18: 43992 | D18: 2 | E18: 43994 | F18: 43992 | G18: 2 | H18: 43994
B19: Inverter Delivery | C19: 43983 | D19: 2 | E19: 43985 | F19: 43983 | G19: 2 | H19: 43985 | L19: =IF(AND($F19<(L$2+7),$F19>L$2),1, IF(AND($H19<L$2+7,$H19>L$2),3, IF(AND($F19<=L$2, $H19>=L$2), 2, "" ))) | M19: =IF(AND($F19<(M$2+7),$F19>M$2),1, IF(AND($H19<M$2+7,$H19>M$2),3, IF(AND($F19<=M$2, $H19>=M$2), 2, "" ))) | N19: =IF(AND($F19<(N$2+7),$F19>N$2),1, IF(AND($H19<N$2+7,$H19>N$2),3, IF(AND($F19<=N$2, $H19>=N$2), 2, "" ))) | O19: =IF(AND($F19<(O$2+7),$F19>O$2),1, IF(AND($H19<O$2+7,$H19>O$2),3, IF(AND($F19<=O$2, $H19>=O$2), 2, "" ))) | P19: =IF(AND($F19<(P$2+7),$F19>P$2),1, IF(AND($H19<P$2+7,$H19>P$2),3, IF(AND($F19<=P$2, $H19>=P$2), 2, "" ))) | Q19: =IF(AND($F19<(Q$2+7),$F19>Q$2),1, IF(AND($H19<Q$2+7,$H19>Q$2),3, IF(AND($F19<=Q$2, $H19>=Q$2), 2, "" ))) | R19: =IF(AND($F19<(R$2+7),$F19>R$2),1, IF(AND($H19<R$2+7,$H19>R$2),3, IF(AND($F19<=R$2, $H19>=R$2), 2, "" ))) | S19: =IF(AND($F19<(S$2+7),$F19>S$2),1, IF(AND($H19<S$2+7,$H19>S$2),3, IF(AND($F19<=S$2, $H19>=S$2), 2, "" ))) | ... AQ19: =IF(AND($F19<(AQ$2+7),$F19>AQ$2),1, IF(AND($H19<AQ$2+7,$H19>AQ$2),3, IF(AND($F19<=AQ$2, $H19>=AQ$2), 2, "" )))
B20: BOS Delivery | C20: 43983 | D20: 1 | E20: 43984 | F20: 43983 | G20: 1 | H20: 43984 | L20: =IF(AND($F20<(L$2+7),$F20>L$2),1, IF(AND($H20<L$2+7,$H20>L$2),3, IF(AND($F20<=L$2, $H20>=L$2), 2, "" ))) | M20: =IF(AND($F20<(M$2+7),$F20>M$2),1, IF(AND($H20<M$2+7,$H20>M$2),3, IF(AND($F20<=M$2, $H20>=M$2), 2, "" ))) | N20: =IF(AND($F20<(N$2+7),$F20>N$2),1, IF(AND($H20<N$2+7,$H20>N$2),3, IF(AND($F20<=N$2, $H20>=N$2), 2, "" ))) | O20: =IF(AND($F20<(O$2+7),$F20>O$2),1, IF(AND($H20<O$2+7,$H20>O$2),3, IF(AND($F20<=O$2, $H20>=O$2), 2, "" ))) | P20: =IF(AND($F20<(P$2+7),$F20>P$2),1, IF(AND($H20<P$2+7,$H20>P$2),3, IF(AND($F20<=P$2, $H20>=P$2), 2, "" ))) | Q20: =IF(AND($F20<(Q$2+7),$F20>Q$2),1, IF(AND($H20<Q$2+7,$H20>Q$2),3, IF(AND($F20<=Q$2, $H20>=Q$2), 2, "" ))) | R20: =IF(AND($F20<(R$2+7),$F20>R$2),1, IF(AND($H20<R$2+7,$H20>R$2),3, IF(AND($F20<=R$2, $H20>=R$2), 2, "" ))) | S20: =IF(AND($F20<(S$2+7),$F20>S$2),1, IF(AND($H20<S$2+7,$H20>S$2),3, IF(AND($F20<=S$2, $H20>=S$2), 2, "" ))) | ... AQ20: =IF(AND($F20<(AQ$2+7),$F20>AQ$2),1, IF(AND($H20<AQ$2+7,$H20>AQ$2),3, IF(AND($F20<=AQ$2, $H20>=AQ$2), 2, "" )))
A21: C | B21: PAYMENT MILESTONE 3: DELIVERY OF INVERTERS AND BOS | C21: 43985 | D21: 2 | E21: 43987 | F21: 43985 | G21: 2 | H21: 43987
A22: 8 | B22: Installation | C22: 43990 | D22: 22 | E22: 44012 | F22: 43990 | G22: 22 | H22: 44012 | L22: =IF(AND($F22<(L$2+7),$F22>L$2),1, IF(AND($H22<L$2+7,$H22>L$2),3, IF(AND($F22<=L$2, $H22>=L$2), 2, "" ))) | M22: =IF(AND($F22<(M$2+7),$F22>M$2),1, IF(AND($H22<M$2+7,$H22>M$2),3, IF(AND($F22<=M$2, $H22>=M$2), 2, "" ))) | N22: =IF(AND($F22<(N$2+7),$F22>N$2),1, IF(AND($H22<N$2+7,$H22>N$2),3, IF(AND($F22<=N$2, $H22>=N$2), 2, "" ))) | O22: =IF(AND($F22<(O$2+7),$F22>O$2),1, IF(AND($H22<O$2+7,$H22>O$2),3, IF(AND($F22<=O$2, $H22>=O$2), 2, "" ))) | P22: =IF(AND($F22<(P$2+7),$F22>P$2),1, IF(AND($H22<P$2+7,$H22>P$2),3, IF(AND($F22<=P$2, $H22>=P$2), 2, "" ))) | Q22: =IF(AND($F22<(Q$2+7),$F22>Q$2),1, IF(AND($H22<Q$2+7,$H22>Q$2),3, IF(AND($F22<=Q$2, $H22>=Q$2), 2, "" ))) | R22: =IF(AND($F22<(R$2+7),$F22>R$2),1, IF(AND($H22<R$2+7,$H22>R$2),3, IF(AND($F22<=R$2, $H22>=R$2), 2, "" ))) | S22: =IF(AND($F22<(S$2+7),$F22>S$2),1, IF(AND($H22<S$2+7,$H22>S$2),3, IF(AND($F22<=S$2, $H22>=S$2), 2, "" ))) | ... AQ22: =IF(AND($F22<(AQ$2+7),$F22>AQ$2),1, IF(AND($H22<AQ$2+7,$H22>AQ$2),3, IF(AND($F22<=AQ$2, $H22>=AQ$2), 2, "" ))) -> 2
B23: Site Establishment | C23: 43990 | D23: 1 | E23: 43991 | F23: 43990 | G23: 1 | H23: 43991 | J23: Installation placed on hold due to Covid-19 case | L23: =IF(AND($F23<(L$2+7),$F23>L$2),1, IF(AND($H23<L$2+7,$H23>L$2),3, IF(AND($F23<=L$2, $H23>=L$2), 2, "" ))) | M23: =IF(AND($F23<(M$2+7),$F23>M$2),1, IF(AND($H23<M$2+7,$H23>M$2),3, IF(AND($F23<=M$2, $H23>=M$2), 2, "" ))) | N23: =IF(AND($F23<(N$2+7),$F23>N$2),1, IF(AND($H23<N$2+7,$H23>N$2),3, IF(AND($F23<=N$2, $H23>=N$2), 2, "" ))) | O23: =IF(AND($F23<(O$2+7),$F23>O$2),1, IF(AND($H23<O$2+7,$H23>O$2),3, IF(AND($F23<=O$2, $H23>=O$2), 2, "" ))) | P23: =IF(AND($F23<(P$2+7),$F23>P$2),1, IF(AND($H23<P$2+7,$H23>P$2),3, IF(AND($F23<=P$2, $H23>=P$2), 2, "" ))) | Q23: =IF(AND($F23<(Q$2+7),$F23>Q$2),1, IF(AND($H23<Q$2+7,$H23>Q$2),3, IF(AND($F23<=Q$2, $H23>=Q$2), 2, "" ))) | R23: =IF(AND($F23<(R$2+7),$F23>R$2),1, IF(AND($H23<R$2+7,$H23>R$2),3, IF(AND($F23<=R$2, $H23>=R$2), 2, "" ))) | S23: =IF(AND($F23<(S$2+7),$F23>S$2),1, IF(AND($H23<S$2+7,$H23>S$2),3, IF(AND($F23<=S$2, $H23>=S$2), 2, "" ))) | ... AQ23: =IF(AND($F23<(AQ$2+7),$F23>AQ$2),1, IF(AND($H23<AQ$2+7,$H23>AQ$2),3, IF(AND($F23<=AQ$2, $H23>=AQ$2), 2, "" )))
A24: 9 | B24: DC Works | C24: 43991 | D24: 16 | E24: 44012 | F24: 43991 | G24: 16 | H24: 44012 | L24: =IF(AND($F24<(L$2+7),$F24>L$2),1, IF(AND($H24<L$2+7,$H24>L$2),3, IF(AND($F24<=L$2, $H24>=L$2), 2, "" ))) | M24: =IF(AND($F24<(M$2+7),$F24>M$2),1, IF(AND($H24<M$2+7,$H24>M$2),3, IF(AND($F24<=M$2, $H24>=M$2), 2, "" ))) | N24: =IF(AND($F24<(N$2+7),$F24>N$2),1, IF(AND($H24<N$2+7,$H24>N$2),3, IF(AND($F24<=N$2, $H24>=N$2), 2, "" ))) | O24: =IF(AND($F24<(O$2+7),$F24>O$2),1, IF(AND($H24<O$2+7,$H24>O$2),3, IF(AND($F24<=O$2, $H24>=O$2), 2, "" ))) | P24: =IF(AND($F24<(P$2+7),$F24>P$2),1, IF(AND($H24<P$2+7,$H24>P$2),3, IF(AND($F24<=P$2, $H24>=P$2), 2, "" ))) | Q24: =IF(AND($F24<(Q$2+7),$F24>Q$2),1, IF(AND($H24<Q$2+7,$H24>Q$2),3, IF(AND($F24<=Q$2, $H24>=Q$2), 2, "" ))) | R24: =IF(AND($F24<(R$2+7),$F24>R$2),1, IF(AND($H24<R$2+7,$H24>R$2),3, IF(AND($F24<=R$2, $H24>=R$2), 2, "" ))) | S24: =IF(AND($F24<(S$2+7),$F24>S$2),1, IF(AND($H24<S$2+7,$H24>S$2),3, IF(AND($F24<=S$2, $H24>=S$2), 2, "" ))) | ... AQ24: =IF(AND($F24<(AQ$2+7),$F24>AQ$2),1, IF(AND($H24<AQ$2+7,$H24>AQ$2),3, IF(AND($F24<=AQ$2, $H24>=AQ$2), 2, "" ))) -> 2
B25: Mounting structure Installation | C25: 43991 | D25: 4 | E25: 43997 | F25: 43991 | G25: 4 | H25: 43997 | L25: =IF(AND($F25<(L$2+7),$F25>L$2),1, IF(AND($H25<L$2+7,$H25>L$2),3, IF(AND($F25<=L$2, $H25>=L$2), 2, "" ))) | M25: =IF(AND($F25<(M$2+7),$F25>M$2),1, IF(AND($H25<M$2+7,$H25>M$2),3, IF(AND($F25<=M$2, $H25>=M$2), 2, "" ))) | N25: =IF(AND($F25<(N$2+7),$F25>N$2),1, IF(AND($H25<N$2+7,$H25>N$2),3, IF(AND($F25<=N$2, $H25>=N$2), 2, "" ))) | O25: =IF(AND($F25<(O$2+7),$F25>O$2),1, IF(AND($H25<O$2+7,$H25>O$2),3, IF(AND($F25<=O$2, $H25>=O$2), 2, "" ))) | P25: =IF(AND($F25<(P$2+7),$F25>P$2),1, IF(AND($H25<P$2+7,$H25>P$2),3, IF(AND($F25<=P$2, $H25>=P$2), 2, "" ))) | Q25: =IF(AND($F25<(Q$2+7),$F25>Q$2),1, IF(AND($H25<Q$2+7,$H25>Q$2),3, IF(AND($F25<=Q$2, $H25>=Q$2), 2, "" ))) | R25: =IF(AND($F25<(R$2+7),$F25>R$2),1, IF(AND($H25<R$2+7,$H25>R$2),3, IF(AND($F25<=R$2, $H25>=R$2), 2, "" ))) | S25: =IF(AND($F25<(S$2+7),$F25>S$2),1, IF(AND($H25<S$2+7,$H25>S$2),3, IF(AND($F25<=S$2, $H25>=S$2), 2, "" ))) | ... AQ25: =IF(AND($F25<(AQ$2+7),$F25>AQ$2),1, IF(AND($H25<AQ$2+7,$H25>AQ$2),3, IF(AND($F25<=AQ$2, $H25>=AQ$2), 2, "" )))
B26: Cable tray Installation | C26: 43997 | D26: 3 | E26: 44004 | F26: 43997 | G26: 3 | H26: 44004 | L26: =IF(AND($F26<(L$2+7),$F26>L$2),1, IF(AND($H26<L$2+7,$H26>L$2),3, IF(AND($F26<=L$2, $H26>=L$2), 2, "" ))) | M26: =IF(AND($F26<(M$2+7),$F26>M$2),1, IF(AND($H26<M$2+7,$H26>M$2),3, IF(AND($F26<=M$2, $H26>=M$2), 2, "" ))) | N26: =IF(AND($F26<(N$2+7),$F26>N$2),1, IF(AND($H26<N$2+7,$H26>N$2),3, IF(AND($F26<=N$2, $H26>=N$2), 2, "" ))) | O26: =IF(AND($F26<(O$2+7),$F26>O$2),1, IF(AND($H26<O$2+7,$H26>O$2),3, IF(AND($F26<=O$2, $H26>=O$2), 2, "" ))) | P26: =IF(AND($F26<(P$2+7),$F26>P$2),1, IF(AND($H26<P$2+7,$H26>P$2),3, IF(AND($F26<=P$2, $H26>=P$2), 2, "" ))) | Q26: =IF(AND($F26<(Q$2+7),$F26>Q$2),1, IF(AND($H26<Q$2+7,$H26>Q$2),3, IF(AND($F26<=Q$2, $H26>=Q$2), 2, "" ))) | R26: =IF(AND($F26<(R$2+7),$F26>R$2),1, IF(AND($H26<R$2+7,$H26>R$2),3, IF(AND($F26<=R$2, $H26>=R$2), 2, "" ))) | S26: =IF(AND($F26<(S$2+7),$F26>S$2),1, IF(AND($H26<S$2+7,$H26>S$2),3, IF(AND($F26<=S$2, $H26>=S$2), 2, "" ))) | ... AQ26: =IF(AND($F26<(AQ$2+7),$F26>AQ$2),1, IF(AND($H26<AQ$2+7,$H26>AQ$2),3, IF(AND($F26<=AQ$2, $H26>=AQ$2), 2, "" )))
B27: DC Cable Installation | C27: 44004 | D27: 2 | E27: 44006 | F27: 44004 | G27: 2 | H27: 44006 | L27: =IF(AND($F27<(L$2+7),$F27>L$2),1, IF(AND($H27<L$2+7,$H27>L$2),3, IF(AND($F27<=L$2, $H27>=L$2), 2, "" ))) | M27: =IF(AND($F27<(M$2+7),$F27>M$2),1, IF(AND($H27<M$2+7,$H27>M$2),3, IF(AND($F27<=M$2, $H27>=M$2), 2, "" ))) | N27: =IF(AND($F27<(N$2+7),$F27>N$2),1, IF(AND($H27<N$2+7,$H27>N$2),3, IF(AND($F27<=N$2, $H27>=N$2), 2, "" ))) | O27: =IF(AND($F27<(O$2+7),$F27>O$2),1, IF(AND($H27<O$2+7,$H27>O$2),3, IF(AND($F27<=O$2, $H27>=O$2), 2, "" ))) | P27: =IF(AND($F27<(P$2+7),$F27>P$2),1, IF(AND($H27<P$2+7,$H27>P$2),3, IF(AND($F27<=P$2, $H27>=P$2), 2, "" ))) | Q27: =IF(AND($F27<(Q$2+7),$F27>Q$2),1, IF(AND($H27<Q$2+7,$H27>Q$2),3, IF(AND($F27<=Q$2, $H27>=Q$2), 2, "" ))) | R27: =IF(AND($F27<(R$2+7),$F27>R$2),1, IF(AND($H27<R$2+7,$H27>R$2),3, IF(AND($F27<=R$2, $H27>=R$2), 2, "" ))) | S27: =IF(AND($F27<(S$2+7),$F27>S$2),1, IF(AND($H27<S$2+7,$H27>S$2),3, IF(AND($F27<=S$2, $H27>=S$2), 2, "" ))) | ... AQ27: =IF(AND($F27<(AQ$2+7),$F27>AQ$2),1, IF(AND($H27<AQ$2+7,$H27>AQ$2),3, IF(AND($F27<=AQ$2, $H27>=AQ$2), 2, "" )))
B28: Module Installation | C28: 44006 | D28: 4 | E28: 44012 | F28: 44006 | G28: 4 | H28: 44012 | L28: =IF(AND($F28<(L$2+7),$F28>L$2),1, IF(AND($H28<L$2+7,$H28>L$2),3, IF(AND($F28<=L$2, $H28>=L$2), 2, "" ))) | M28: =IF(AND($F28<(M$2+7),$F28>M$2),1, IF(AND($H28<M$2+7,$H28>M$2),3, IF(AND($F28<=M$2, $H28>=M$2), 2, "" ))) | N28: =IF(AND($F28<(N$2+7),$F28>N$2),1, IF(AND($H28<N$2+7,$H28>N$2),3, IF(AND($F28<=N$2, $H28>=N$2), 2, "" ))) | O28: =IF(AND($F28<(O$2+7),$F28>O$2),1, IF(AND($H28<O$2+7,$H28>O$2),3, IF(AND($F28<=O$2, $H28>=O$2), 2, "" ))) | P28: =IF(AND($F28<(P$2+7),$F28>P$2),1, IF(AND($H28<P$2+7,$H28>P$2),3, IF(AND($F28<=P$2, $H28>=P$2), 2, "" ))) | Q28: =IF(AND($F28<(Q$2+7),$F28>Q$2),1, IF(AND($H28<Q$2+7,$H28>Q$2),3, IF(AND($F28<=Q$2, $H28>=Q$2), 2, "" ))) | R28: =IF(AND($F28<(R$2+7),$F28>R$2),1, IF(AND($H28<R$2+7,$H28>R$2),3, IF(AND($F28<=R$2, $H28>=R$2), 2, "" ))) | S28: =IF(AND($F28<(S$2+7),$F28>S$2),1, IF(AND($H28<S$2+7,$H28>S$2),3, IF(AND($F28<=S$2, $H28>=S$2), 2, "" ))) | ... AQ28: =IF(AND($F28<(AQ$2+7),$F28>AQ$2),1, IF(AND($H28<AQ$2+7,$H28>AQ$2),3, IF(AND($F28<=AQ$2, $H28>=AQ$2), 2, "" ))) -> 2
B29: Earth Cable Installation | C29: 44004 | D29: 1 | E29: 44005 | F29: 44004 | G29: 1 | H29: 44005 | L29: =IF(AND($F29<(L$2+7),$F29>L$2),1, IF(AND($H29<L$2+7,$H29>L$2),3, IF(AND($F29<=L$2, $H29>=L$2), 2, "" ))) | M29: =IF(AND($F29<(M$2+7),$F29>M$2),1, IF(AND($H29<M$2+7,$H29>M$2),3, IF(AND($F29<=M$2, $H29>=M$2), 2, "" ))) | N29: =IF(AND($F29<(N$2+7),$F29>N$2),1, IF(AND($H29<N$2+7,$H29>N$2),3, IF(AND($F29<=N$2, $H29>=N$2), 2, "" ))) | O29: =IF(AND($F29<(O$2+7),$F29>O$2),1, IF(AND($H29<O$2+7,$H29>O$2),3, IF(AND($F29<=O$2, $H29>=O$2), 2, "" ))) | P29: =IF(AND($F29<(P$2+7),$F29>P$2),1, IF(AND($H29<P$2+7,$H29>P$2),3, IF(AND($F29<=P$2, $H29>=P$2), 2, "" ))) | Q29: =IF(AND($F29<(Q$2+7),$F29>Q$2),1, IF(AND($H29<Q$2+7,$H29>Q$2),3, IF(AND($F29<=Q$2, $H29>=Q$2), 2, "" ))) | R29: =IF(AND($F29<(R$2+7),$F29>R$2),1, IF(AND($H29<R$2+7,$H29>R$2),3, IF(AND($F29<=R$2, $H29>=R$2), 2, "" ))) | S29: =IF(AND($F29<(S$2+7),$F29>S$2),1, IF(AND($H29<S$2+7,$H29>S$2),3, IF(AND($F29<=S$2, $H29>=S$2), 2, "" ))) | ... AQ29: =IF(AND($F29<(AQ$2+7),$F29>AQ$2),1, IF(AND($H29<AQ$2+7,$H29>AQ$2),3, IF(AND($F29<=AQ$2, $H29>=AQ$2), 2, "" )))
A30: 10 | B30: AC Works | C30: 43991 | D30: 8 | E30: 44000 | F30: 43991 | G30: 8 | H30: 44000
B31: Inverters Installation | C31: 43991 | D31: 2 | E31: 43993 | F31: 43991 | G31: 2 | H31: 43993 | L31: =IF(AND($F31<(L$2+7),$F31>L$2),1, IF(AND($H31<L$2+7,$H31>L$2),3, IF(AND($F31<=L$2, $H31>=L$2), 2, "" ))) | M31: =IF(AND($F31<(M$2+7),$F31>M$2),1, IF(AND($H31<M$2+7,$H31>M$2),3, IF(AND($F31<=M$2, $H31>=M$2), 2, "" ))) | N31: =IF(AND($F31<(N$2+7),$F31>N$2),1, IF(AND($H31<N$2+7,$H31>N$2),3, IF(AND($F31<=N$2, $H31>=N$2), 2, "" ))) | O31: =IF(AND($F31<(O$2+7),$F31>O$2),1, IF(AND($H31<O$2+7,$H31>O$2),3, IF(AND($F31<=O$2, $H31>=O$2), 2, "" ))) | P31: =IF(AND($F31<(P$2+7),$F31>P$2),1, IF(AND($H31<P$2+7,$H31>P$2),3, IF(AND($F31<=P$2, $H31>=P$2), 2, "" ))) | Q31: =IF(AND($F31<(Q$2+7),$F31>Q$2),1, IF(AND($H31<Q$2+7,$H31>Q$2),3, IF(AND($F31<=Q$2, $H31>=Q$2), 2, "" ))) | R31: =IF(AND($F31<(R$2+7),$F31>R$2),1, IF(AND($H31<R$2+7,$H31>R$2),3, IF(AND($F31<=R$2, $H31>=R$2), 2, "" ))) | S31: =IF(AND($F31<(S$2+7),$F31>S$2),1, IF(AND($H31<S$2+7,$H31>S$2),3, IF(AND($F31<=S$2, $H31>=S$2), 2, "" ))) | ... AQ31: =IF(AND($F31<(AQ$2+7),$F31>AQ$2),1, IF(AND($H31<AQ$2+7,$H31>AQ$2),3, IF(AND($F31<=AQ$2, $H31>=AQ$2), 2, "" )))
B32: AC BOS Installation | C32: 43993 | D32: 3 | E32: 44000 | F32: 43993 | G32: 3 | H32: 44000 | L32: =IF(AND($F32<(L$2+7),$F32>L$2),1, IF(AND($H32<L$2+7,$H32>L$2),3, IF(AND($F32<=L$2, $H32>=L$2), 2, "" ))) | M32: =IF(AND($F32<(M$2+7),$F32>M$2),1, IF(AND($H32<M$2+7,$H32>M$2),3, IF(AND($F32<=M$2, $H32>=M$2), 2, "" ))) | N32: =IF(AND($F32<(N$2+7),$F32>N$2),1, IF(AND($H32<N$2+7,$H32>N$2),3, IF(AND($F32<=N$2, $H32>=N$2), 2, "" ))) | O32: =IF(AND($F32<(O$2+7),$F32>O$2),1, IF(AND($H32<O$2+7,$H32>O$2),3, IF(AND($F32<=O$2, $H32>=O$2), 2, "" ))) | P32: =IF(AND($F32<(P$2+7),$F32>P$2),1, IF(AND($H32<P$2+7,$H32>P$2),3, IF(AND($F32<=P$2, $H32>=P$2), 2, "" ))) | Q32: =IF(AND($F32<(Q$2+7),$F32>Q$2),1, IF(AND($H32<Q$2+7,$H32>Q$2),3, IF(AND($F32<=Q$2, $H32>=Q$2), 2, "" ))) | R32: =IF(AND($F32<(R$2+7),$F32>R$2),1, IF(AND($H32<R$2+7,$H32>R$2),3, IF(AND($F32<=R$2, $H32>=R$2), 2, "" ))) | S32: =IF(AND($F32<(S$2+7),$F32>S$2),1, IF(AND($H32<S$2+7,$H32>S$2),3, IF(AND($F32<=S$2, $H32>=S$2), 2, "" ))) | ... AQ32: =IF(AND($F32<(AQ$2+7),$F32>AQ$2),1, IF(AND($H32<AQ$2+7,$H32>AQ$2),3, IF(AND($F32<=AQ$2, $H32>=AQ$2), 2, "" )))
B33: AC Cable/Tie-In | C33: 43992 | D33: 3 | E33: 43997 | F33: 43992 | G33: 3 | H33: 43997 | L33: =IF(AND($F33<(L$2+7),$F33>L$2),1, IF(AND($H33<L$2+7,$H33>L$2),3, IF(AND($F33<=L$2, $H33>=L$2), 2, "" ))) | M33: =IF(AND($F33<(M$2+7),$F33>M$2),1, IF(AND($H33<M$2+7,$H33>M$2),3, IF(AND($F33<=M$2, $H33>=M$2), 2, "" ))) | N33: =IF(AND($F33<(N$2+7),$F33>N$2),1, IF(AND($H33<N$2+7,$H33>N$2),3, IF(AND($F33<=N$2, $H33>=N$2), 2, "" ))) | O33: =IF(AND($F33<(O$2+7),$F33>O$2),1, IF(AND($H33<O$2+7,$H33>O$2),3, IF(AND($F33<=O$2, $H33>=O$2), 2, "" ))) | P33: =IF(AND($F33<(P$2+7),$F33>P$2),1, IF(AND($H33<P$2+7,$H33>P$2),3, IF(AND($F33<=P$2, $H33>=P$2), 2, "" ))) | Q33: =IF(AND($F33<(Q$2+7),$F33>Q$2),1, IF(AND($H33<Q$2+7,$H33>Q$2),3, IF(AND($F33<=Q$2, $H33>=Q$2), 2, "" ))) | R33: =IF(AND($F33<(R$2+7),$F33>R$2),1, IF(AND($H33<R$2+7,$H33>R$2),3, IF(AND($F33<=R$2, $H33>=R$2), 2, "" ))) | S33: =IF(AND($F33<(S$2+7),$F33>S$2),1, IF(AND($H33<S$2+7,$H33>S$2),3, IF(AND($F33<=S$2, $H33>=S$2), 2, "" ))) | ... AQ33: =IF(AND($F33<(AQ$2+7),$F33>AQ$2),1, IF(AND($H33<AQ$2+7,$H33>AQ$2),3, IF(AND($F33<=AQ$2, $H33>=AQ$2), 2, "" )))
B34: Monitoring Platform Installation | C34: 43997 | D34: 1 | E34: 44000 | F34: 43997 | G34: 1 | H34: 44000
A35: 11 | B35: Completion | C35: 44000 | D35: 14 | E35: 44014 | F35: 44000 | G35: 14 | H35: 44014 | L35: =IF(AND($F35<(L$2+7),$F35>L$2),1, IF(AND($H35<L$2+7,$H35>L$2),3, IF(AND($F35<=L$2, $H35>=L$2), 2, "" ))) | M35: =IF(AND($F35<(M$2+7),$F35>M$2),1, IF(AND($H35<M$2+7,$H35>M$2),3, IF(AND($F35<=M$2, $H35>=M$2), 2, "" ))) | N35: =IF(AND($F35<(N$2+7),$F35>N$2),1, IF(AND($H35<N$2+7,$H35>N$2),3, IF(AND($F35<=N$2, $H35>=N$2), 2, "" ))) | O35: =IF(AND($F35<(O$2+7),$F35>O$2),1, IF(AND($H35<O$2+7,$H35>O$2),3, IF(AND($F35<=O$2, $H35>=O$2), 2, "" ))) | P35: =IF(AND($F35<(P$2+7),$F35>P$2),1, IF(AND($H35<P$2+7,$H35>P$2),3, IF(AND($F35<=P$2, $H35>=P$2), 2, "" ))) | Q35: =IF(AND($F35<(Q$2+7),$F35>Q$2),1, IF(AND($H35<Q$2+7,$H35>Q$2),3, IF(AND($F35<=Q$2, $H35>=Q$2), 2, "" ))) | R35: =IF(AND($F35<(R$2+7),$F35>R$2),1, IF(AND($H35<R$2+7,$H35>R$2),3, IF(AND($F35<=R$2, $H35>=R$2), 2, "" ))) | S35: =IF(AND($F35<(S$2+7),$F35>S$2),1, IF(AND($H35<S$2+7,$H35>S$2),3, IF(AND($F35<=S$2, $H35>=S$2), 2, "" ))) | ... AQ35: =IF(AND($F35<(AQ$2+7),$F35>AQ$2),1, IF(AND($H35<AQ$2+7,$H35>AQ$2),3, IF(AND($F35<=AQ$2, $H35>=AQ$2), 2, "" ))) -> 3
B36: DC Works | C36: 44012 | D36: 2 | E36: 44014 | F36: 44012 | G36: 2 | H36: 44014 | L36: =IF(AND($F36<(L$2+7),$F36>L$2),1, IF(AND($H36<L$2+7,$H36>L$2),3, IF(AND($F36<=L$2, $H36>=L$2), 2, "" ))) | M36: =IF(AND($F36<(M$2+7),$F36>M$2),1, IF(AND($H36<M$2+7,$H36>M$2),3, IF(AND($F36<=M$2, $H36>=M$2), 2, "" ))) | N36: =IF(AND($F36<(N$2+7),$F36>N$2),1, IF(AND($H36<N$2+7,$H36>N$2),3, IF(AND($F36<=N$2, $H36>=N$2), 2, "" ))) | O36: =IF(AND($F36<(O$2+7),$F36>O$2),1, IF(AND($H36<O$2+7,$H36>O$2),3, IF(AND($F36<=O$2, $H36>=O$2), 2, "" ))) | P36: =IF(AND($F36<(P$2+7),$F36>P$2),1, IF(AND($H36<P$2+7,$H36>P$2),3, IF(AND($F36<=P$2, $H36>=P$2), 2, "" ))) | Q36: =IF(AND($F36<(Q$2+7),$F36>Q$2),1, IF(AND($H36<Q$2+7,$H36>Q$2),3, IF(AND($F36<=Q$2, $H36>=Q$2), 2, "" ))) | R36: =IF(AND($F36<(R$2+7),$F36>R$2),1, IF(AND($H36<R$2+7,$H36>R$2),3, IF(AND($F36<=R$2, $H36>=R$2), 2, "" ))) | S36: =IF(AND($F36<(S$2+7),$F36>S$2),1, IF(AND($H36<S$2+7,$H36>S$2),3, IF(AND($F36<=S$2, $H36>=S$2), 2, "" ))) | ... AQ36: =IF(AND($F36<(AQ$2+7),$F36>AQ$2),1, IF(AND($H36<AQ$2+7,$H36>AQ$2),3, IF(AND($F36<=AQ$2, $H36>=AQ$2), 2, "" ))) -> 3
B37: AC Works | C37: 44000 | D37: 2 | E37: 44004 | F37: 44000 | G37: 2 | H37: 44004 | L37: =IF(AND($F37<(L$2+7),$F37>L$2),1, IF(AND($H37<L$2+7,$H37>L$2),3, IF(AND($F37<=L$2, $H37>=L$2), 2, "" ))) | M37: =IF(AND($F37<(M$2+7),$F37>M$2),1, IF(AND($H37<M$2+7,$H37>M$2),3, IF(AND($F37<=M$2, $H37>=M$2), 2, "" ))) | N37: =IF(AND($F37<(N$2+7),$F37>N$2),1, IF(AND($H37<N$2+7,$H37>N$2),3, IF(AND($F37<=N$2, $H37>=N$2), 2, "" ))) | O37: =IF(AND($F37<(O$2+7),$F37>O$2),1, IF(AND($H37<O$2+7,$H37>O$2),3, IF(AND($F37<=O$2, $H37>=O$2), 2, "" ))) | P37: =IF(AND($F37<(P$2+7),$F37>P$2),1, IF(AND($H37<P$2+7,$H37>P$2),3, IF(AND($F37<=P$2, $H37>=P$2), 2, "" ))) | Q37: =IF(AND($F37<(Q$2+7),$F37>Q$2),1, IF(AND($H37<Q$2+7,$H37>Q$2),3, IF(AND($F37<=Q$2, $H37>=Q$2), 2, "" ))) | R37: =IF(AND($F37<(R$2+7),$F37>R$2),1, IF(AND($H37<R$2+7,$H37>R$2),3, IF(AND($F37<=R$2, $H37>=R$2), 2, "" ))) | S37: =IF(AND($F37<(S$2+7),$F37>S$2),1, IF(AND($H37<S$2+7,$H37>S$2),3, IF(AND($F37<=S$2, $H37>=S$2), 2, "" ))) | ... AQ37: =IF(AND($F37<(AQ$2+7),$F37>AQ$2),1, IF(AND($H37<AQ$2+7,$H37>AQ$2),3, IF(AND($F37<=AQ$2, $H37>=AQ$2), 2, "" )))
A38: D | B38: PAYMENT MILESTONE 4: PRACTICAL COMPLETION | C38: 44012 | D38: 1 | E38: 44013 | F38: 44012 | G38: 1 | H38: 44013 | L38: =IF(AND($F38<(L$2+7),$F38>L$2),1, IF(AND($H38<L$2+7,$H38>L$2),3, IF(AND($F38<=L$2, $H38>=L$2), 2, "" ))) | M38: =IF(AND($F38<(M$2+7),$F38>M$2),1, IF(AND($H38<M$2+7,$H38>M$2),3, IF(AND($F38<=M$2, $H38>=M$2), 2, "" ))) | N38: =IF(AND($F38<(N$2+7),$F38>N$2),1, IF(AND($H38<N$2+7,$H38>N$2),3, IF(AND($F38<=N$2, $H38>=N$2), 2, "" ))) | O38: =IF(AND($F38<(O$2+7),$F38>O$2),1, IF(AND($H38<O$2+7,$H38>O$2),3, IF(AND($F38<=O$2, $H38>=O$2), 2, "" ))) | P38: =IF(AND($F38<(P$2+7),$F38>P$2),1, IF(AND($H38<P$2+7,$H38>P$2),3, IF(AND($F38<=P$2, $H38>=P$2), 2, "" ))) | Q38: =IF(AND($F38<(Q$2+7),$F38>Q$2),1, IF(AND($H38<Q$2+7,$H38>Q$2),3, IF(AND($F38<=Q$2, $H38>=Q$2), 2, "" ))) | R38: =IF(AND($F38<(R$2+7),$F38>R$2),1, IF(AND($H38<R$2+7,$H38>R$2),3, IF(AND($F38<=R$2, $H38>=R$2), 2, "" ))) | S38: =IF(AND($F38<(S$2+7),$F38>S$2),1, IF(AND($H38<S$2+7,$H38>S$2),3, IF(AND($F38<=S$2, $H38>=S$2), 2, "" ))) | ... AQ38: =IF(AND($F38<(AQ$2+7),$F38>AQ$2),1, IF(AND($H38<AQ$2+7,$H38>AQ$2),3, IF(AND($F38<=AQ$2, $H38>=AQ$2), 2, "" ))) -> 3
A39: 12 | B39: Commissioning | C39: 43997 | D39: 22 | E39: 44019 | F39: 43997 | G39: 22 | H39: 44019 | L39: =IF(AND($F39<(L$2+7),$F39>L$2),1, IF(AND($H39<L$2+7,$H39>L$2),3, IF(AND($F39<=L$2, $H39>=L$2), 2, "" ))) | M39: =IF(AND($F39<(M$2+7),$F39>M$2),1, IF(AND($H39<M$2+7,$H39>M$2),3, IF(AND($F39<=M$2, $H39>=M$2), 2, "" ))) | N39: =IF(AND($F39<(N$2+7),$F39>N$2),1, IF(AND($H39<N$2+7,$H39>N$2),3, IF(AND($F39<=N$2, $H39>=N$2), 2, "" ))) | O39: =IF(AND($F39<(O$2+7),$F39>O$2),1, IF(AND($H39<O$2+7,$H39>O$2),3, IF(AND($F39<=O$2, $H39>=O$2), 2, "" ))) | P39: =IF(AND($F39<(P$2+7),$F39>P$2),1, IF(AND($H39<P$2+7,$H39>P$2),3, IF(AND($F39<=P$2, $H39>=P$2), 2, "" ))) | Q39: =IF(AND($F39<(Q$2+7),$F39>Q$2),1, IF(AND($H39<Q$2+7,$H39>Q$2),3, IF(AND($F39<=Q$2, $H39>=Q$2), 2, "" ))) | R39: =IF(AND($F39<(R$2+7),$F39>R$2),1, IF(AND($H39<R$2+7,$H39>R$2),3, IF(AND($F39<=R$2, $H39>=R$2), 2, "" ))) | S39: =IF(AND($F39<(S$2+7),$F39>S$2),1, IF(AND($H39<S$2+7,$H39>S$2),3, IF(AND($F39<=S$2, $H39>=S$2), 2, "" ))) | ... AQ39: =IF(AND($F39<(AQ$2+7),$F39>AQ$2),1, IF(AND($H39<AQ$2+7,$H39>AQ$2),3, IF(AND($F39<=AQ$2, $H39>=AQ$2), 2, "" ))) -> 2
B40: Snag List | C40: 44014 | D40: 3 | E40: 44019 | F40: 44014 | G40: 3 | H40: 44019
B41: Pre-Commissioning Checks | C41: 44010 | D41: 2 | E41: 44012 | F41: 44010 | G41: 2 | H41: 44012
B42: Issue CoC | C42: 43997 | D42: 2 | E42: 44001 | F42: 43997 | G42: 2 | H42: 44001 | L42: =IF(AND($F42<(L$2+7),$F42>L$2),1, IF(AND($H42<L$2+7,$H42>L$2),3, IF(AND($F42<=L$2, $H42>=L$2), 2, "" ))) | M42: =IF(AND($F42<(M$2+7),$F42>M$2),1, IF(AND($H42<M$2+7,$H42>M$2),3, IF(AND($F42<=M$2, $H42>=M$2), 2, "" ))) | N42: =IF(AND($F42<(N$2+7),$F42>N$2),1, IF(AND($H42<N$2+7,$H42>N$2),3, IF(AND($F42<=N$2, $H42>=N$2), 2, "" ))) | O42: =IF(AND($F42<(O$2+7),$F42>O$2),1, IF(AND($H42<O$2+7,$H42>O$2),3, IF(AND($F42<=O$2, $H42>=O$2), 2, "" ))) | P42: =IF(AND($F42<(P$2+7),$F42>P$2),1, IF(AND($H42<P$2+7,$H42>P$2),3, IF(AND($F42<=P$2, $H42>=P$2), 2, "" ))) | Q42: =IF(AND($F42<(Q$2+7),$F42>Q$2),1, IF(AND($H42<Q$2+7,$H42>Q$2),3, IF(AND($F42<=Q$2, $H42>=Q$2), 2, "" ))) | R42: =IF(AND($F42<(R$2+7),$F42>R$2),1, IF(AND($H42<R$2+7,$H42>R$2),3, IF(AND($F42<=R$2, $H42>=R$2), 2, "" ))) | S42: =IF(AND($F42<(S$2+7),$F42>S$2),1, IF(AND($H42<S$2+7,$H42>S$2),3, IF(AND($F42<=S$2, $H42>=S$2), 2, "" ))) | ... AQ42: =IF(AND($F42<(AQ$2+7),$F42>AQ$2),1, IF(AND($H42<AQ$2+7,$H42>AQ$2),3, IF(AND($F42<=AQ$2, $H42>=AQ$2), 2, "" )))
B43: Cold Commissioning | C43: 44012 | D43: 1 | E43: 44013 | F43: 44012 | G43: 1 | H43: 44013 | L43: =IF(AND($F43<(L$2+7),$F43>L$2),1, IF(AND($H43<L$2+7,$H43>L$2),3, IF(AND($F43<=L$2, $H43>=L$2), 2, "" ))) | M43: =IF(AND($F43<(M$2+7),$F43>M$2),1, IF(AND($H43<M$2+7,$H43>M$2),3, IF(AND($F43<=M$2, $H43>=M$2), 2, "" ))) | N43: =IF(AND($F43<(N$2+7),$F43>N$2),1, IF(AND($H43<N$2+7,$H43>N$2),3, IF(AND($F43<=N$2, $H43>=N$2), 2, "" ))) | O43: =IF(AND($F43<(O$2+7),$F43>O$2),1, IF(AND($H43<O$2+7,$H43>O$2),3, IF(AND($F43<=O$2, $H43>=O$2), 2, "" ))) | P43: =IF(AND($F43<(P$2+7),$F43>P$2),1, IF(AND($H43<P$2+7,$H43>P$2),3, IF(AND($F43<=P$2, $H43>=P$2), 2, "" ))) | Q43: =IF(AND($F43<(Q$2+7),$F43>Q$2),1, IF(AND($H43<Q$2+7,$H43>Q$2),3, IF(AND($F43<=Q$2, $H43>=Q$2), 2, "" ))) | R43: =IF(AND($F43<(R$2+7),$F43>R$2),1, IF(AND($H43<R$2+7,$H43>R$2),3, IF(AND($F43<=R$2, $H43>=R$2), 2, "" ))) | S43: =IF(AND($F43<(S$2+7),$F43>S$2),1, IF(AND($H43<S$2+7,$H43>S$2),3, IF(AND($F43<=S$2, $H43>=S$2), 2, "" ))) | ... AQ43: =IF(AND($F43<(AQ$2+7),$F43>AQ$2),1, IF(AND($H43<AQ$2+7,$H43>AQ$2),3, IF(AND($F43<=AQ$2, $H43>=AQ$2), 2, "" ))) -> 3
B44: Hot Commissioning | C44: 44013 | D44: 2 | E44: 44015 | F44: 44013 | G44: 2 | H44: 44015 | L44: =IF(AND($F44<(L$2+7),$F44>L$2),1, IF(AND($H44<L$2+7,$H44>L$2),3, IF(AND($F44<=L$2, $H44>=L$2), 2, "" ))) | M44: =IF(AND($F44<(M$2+7),$F44>M$2),1, IF(AND($H44<M$2+7,$H44>M$2),3, IF(AND($F44<=M$2, $H44>=M$2), 2, "" ))) | N44: =IF(AND($F44<(N$2+7),$F44>N$2),1, IF(AND($H44<N$2+7,$H44>N$2),3, IF(AND($F44<=N$2, $H44>=N$2), 2, "" ))) | O44: =IF(AND($F44<(O$2+7),$F44>O$2),1, IF(AND($H44<O$2+7,$H44>O$2),3, IF(AND($F44<=O$2, $H44>=O$2), 2, "" ))) | P44: =IF(AND($F44<(P$2+7),$F44>P$2),1, IF(AND($H44<P$2+7,$H44>P$2),3, IF(AND($F44<=P$2, $H44>=P$2), 2, "" ))) | Q44: =IF(AND($F44<(Q$2+7),$F44>Q$2),1, IF(AND($H44<Q$2+7,$H44>Q$2),3, IF(AND($F44<=Q$2, $H44>=Q$2), 2, "" ))) | R44: =IF(AND($F44<(R$2+7),$F44>R$2),1, IF(AND($H44<R$2+7,$H44>R$2),3, IF(AND($F44<=R$2, $H44>=R$2), 2, "" ))) | S44: =IF(AND($F44<(S$2+7),$F44>S$2),1, IF(AND($H44<S$2+7,$H44>S$2),3, IF(AND($F44<=S$2, $H44>=S$2), 2, "" ))) | ... AQ44: =IF(AND($F44<(AQ$2+7),$F44>AQ$2),1, IF(AND($H44<AQ$2+7,$H44>AQ$2),3, IF(AND($F44<=AQ$2, $H44>=AQ$2), 2, "" ))) -> 1
A45: 13 | B45: Handover | C45: 44020 | D45: 1 | E45: 44021 | F45: 44020 | G45: 1 | H45: 44021 | L45: =IF(AND($F45<(L$2+7),$F45>L$2),1, IF(AND($H45<L$2+7,$H45>L$2),3, IF(AND($F45<=L$2, $H45>=L$2), 2, "" ))) | M45: =IF(AND($F45<(M$2+7),$F45>M$2),1, IF(AND($H45<M$2+7,$H45>M$2),3, IF(AND($F45<=M$2, $H45>=M$2), 2, "" ))) | N45: =IF(AND($F45<(N$2+7),$F45>N$2),1, IF(AND($H45<N$2+7,$H45>N$2),3, IF(AND($F45<=N$2, $H45>=N$2), 2, "" ))) | O45: =IF(AND($F45<(O$2+7),$F45>O$2),1, IF(AND($H45<O$2+7,$H45>O$2),3, IF(AND($F45<=O$2, $H45>=O$2), 2, "" ))) | P45: =IF(AND($F45<(P$2+7),$F45>P$2),1, IF(AND($H45<P$2+7,$H45>P$2),3, IF(AND($F45<=P$2, $H45>=P$2), 2, "" ))) | Q45: =IF(AND($F45<(Q$2+7),$F45>Q$2),1, IF(AND($H45<Q$2+7,$H45>Q$2),3, IF(AND($F45<=Q$2, $H45>=Q$2), 2, "" ))) | R45: =IF(AND($F45<(R$2+7),$F45>R$2),1, IF(AND($H45<R$2+7,$H45>R$2),3, IF(AND($F45<=R$2, $H45>=R$2), 2, "" ))) | S45: =IF(AND($F45<(S$2+7),$F45>S$2),1, IF(AND($H45<S$2+7,$H45>S$2),3, IF(AND($F45<=S$2, $H45>=S$2), 2, "" ))) | ... AQ45: =IF(AND($F45<(AQ$2+7),$F45>AQ$2),1, IF(AND($H45<AQ$2+7,$H45>AQ$2),3, IF(AND($F45<=AQ$2, $H45>=AQ$2), 2, "" )))
A46: E | B46: PAYMENT MILESTONE 6: HANDOVER COMPLETE | C46: 44022 | D46: 1 | E46: 44025 | F46: 44022 | G46: 1 | H46: 44025
C47: 43831 | D47: These numbers are used to set the start and end dates on the Gantt Chart
C48: 44014

Sheet Compliance
B2: HSE
B4: Description | C4: Status | D4: Approved By | E4: Date | F4: Results / Comments
B5: NOC
B6: 7.1 Agreement
B7: 13.2 Agreement
B8: EE File
B9: Subbie File
B16: SSEG
B18: Description | C18: Status | D18: Approved By | E18: Date | F18: Results / Comments
B19: SSEG Application
B20: PTI
B21: Commissioning Approval

Sheet Certificate - Financial Close
B2: Emergent Energy – Financial Close Completion Certificate | H2: FINANCIAL CLOSE CERTIFICATE
B4: Project Name: | C4: ='Project Plan'!E2 -> Lynridge Mall
B5: COO: | C5: Johannes Potgieter
B6: Programme Manager: | C6: Roedolph Venter
B7: HoPD: | C7: Natasha Watkins-Baker
B9: Date of Phase Completion: | F9: {=_xlfn.LET(_xlpm.w,$B$10:$B$54,_xlpm.r,$M$10:$M$54,_xlpm.v,IF(ISNUMBER(_xlpm.r),_xlpm.r,IFERROR(VALUE(SUBSTITUTE(_xlpm.r,"%",""))/100,0)),_xlpm.g,IFERROR(VALUE(LEFT(_xlpm.w,1)),0),_xlpm.bdOnly,(SUMPRODUCT((_xlpm.w="1.1")*(_xlpm.v>0))>0)*(SUMPRODUCT((_xlpm.w<>"1.1")*(_xlpm.v>0))=0),_xlpm.anyConstr,SUMPRODUCT((_xlpm.g>=2)*(_xlpm.g<=6)*(_xlpm.v>0))>0,_xlpm.anyQA,SUMPRODUCT((_xlpm.g=7)*(_xlpm.v>0))>0,_xlpm.anyHO,SUMPRODUCT((_xlpm.g=8)*(_xlpm.v>0))>0,_xlpm.anyPlan,SUMPRODUCT((_xlpm.g=1)*(_xlpm.v>0))>0,IF(_xlpm.bdOnly,"1. Financial Close",IF(_xlpm.anyConstr,"3. Construction",IF(_xlpm.anyQA,"4. QA",IF(_xlpm.anyHO,"5. Handover",IF(_xlpm.anyPlan,"2. Planning","1. Financial Close"))))))} -> 1. Financial Close | G9: {=_xlfn.LET(_xlpm.w,$B$10:$B$54,_xlpm.r,$N$10:$N$54,_xlpm.v,IF(ISNUMBER(_xlpm.r),_xlpm.r,IFERROR(VALUE(SUBSTITUTE(_xlpm.r,"%",""))/100,0)),_xlpm.g,IFERROR(VALUE(LEFT(_xlpm.w,1)),0),_xlpm.bdOnly,(SUMPRODUCT((_xlpm.w="1.1")*(_xlpm.v>0))>0)*(SUMPRODUCT((_xlpm.w<>"1.1")*(_xlpm.v>0))=0),_xlpm.anyConstr,SUMPRODUCT((_xlpm.g>=2)*(_xlpm.g<=6)*(_xlpm.v>0))>0,_xlpm.anyQA,SUMPRODUCT((_xlpm.g=7)*(_xlpm.v>0))>0,_xlpm.anyHO,SUMPRODUCT((_xlpm.g=8)*(_xlpm.v>0))>0,_xlpm.anyPlan,SUMPRODUCT((_xlpm.g=1)*(_xlpm.v>0))>0,IF(_xlpm.bdOnly,"1. Financial Close",IF(_xlpm.anyConstr,"3. Construction",IF(_xlpm.anyQA,"4. QA",IF(_xlpm.anyHO,"5. Handover",IF(_xlpm.anyPlan,"2. Planning","1. Financial Close"))))))} -> 1. Financial Close
B10: Phase Deliverables Checklist: (Y/N)
B11: Product Agreement | C11: NA
B12: EPC Agreement | C12: NA
B13: O&M Agreeement | C13: NA
B14: Cost Proposal | C14: Signed
B15: Deposit Received | C15: Yes
B16: Risks / Notes | C16: None
B18: Acknowledgement and Acceptance:
B19: Role | C19: Name | D19: Signature | E19: Date
B20: COO | C20: Johannes | D20: JTP | E20: 45953

Sheet Project Plan
N1: =TODAY() -> 46070 | O1: =TODAY() -> 46070
C2: PROJECT PLAN | E2: Lynridge Mall | N2: 0 | O2: 1
C3: PROJECT SIZE (kWp) | E3: 700
C4: PROJECT DEVELOPER | E4: Peet Verenney
C5: PROJECT MANAGERS | E5: Eon Van Rensburg
C6: CONTRACT VALUE | E6: 5818787.2
C7: Phase: | E7: Compliance Handover
B8: No. | C8: HIGH LEVEL PROGRAMME | E8: Planned Start | F8: Duration (days) | G8: Planned End | I8: Actual Start | J8: Duration (days) | K8: Actual End | M8: Status | N8: Expected Status | O8: Comment
F9: =G42-E19 -> 53 | J9: =K42-I19 -> 90 | M9: =AVERAGE(M11,M18,M21,M28,M36,M40,M47,M44) -> 1 | N9: =AVERAGE(N11,N18,N21,N28,N36,N40,N47,N44) -> 1
B11: 1 | C11: Project Initiation | E11: =MIN(E12:E16) -> 45685 | F11: =G11-E11 -> 140 | G11: =MAX(G12:G16) -> 45825 | I11: =MIN(I12:I16) -> 45685 | J11: =K11-I11 -> 140 | K11: =MAX(K12:K16) -> 45825 | M11: =(J12*M12+J13*M13+J14*M14+J15*M15+J16*M16)/SUM(J12:J16) -> 1 | N11: =(K12*N12+K13*N13+K14*N14+K15*N15+K16*N16)/SUM(K12:K16) -> 1
B12: 1.1 | C12: BD Handover | E12: 45685 | F12: 1 | G12: =WORKDAY.INTL(E12,F12,1,Data!$C$3:$C$14) -> 45686 | I12: 45685 | J12: 1 | K12: =WORKDAY.INTL(I12,J12,1,Data!$C$3:$C$14) -> 45686 | M12: 1 | N12: 1
B13: 1.2 | C13: Project Introduction | E13: 45721 | F13: 1 | G13: =WORKDAY.INTL(E13,F13,1,Data!$C$3:$C$14) -> 45722 | I13: 45721 | J13: 1 | K13: =WORKDAY.INTL(I13,J13,1,Data!$C$3:$C$14) -> 45722 | M13: 1 | N13: 1
B14: 1.3 | C14: HSE | E14: 45699 | F14: 126 | G14: =E14+F14 -> 45825 | I14: 45699 | J14: 126 | K14: =I14+J14 -> 45825 | M14: 1 | N14: 1
B15: 1.4 | C15: Installer Kick Off | E15: =E16 -> 45818 | F15: 1 | G15: =WORKDAY.INTL(E15,F15,1,Data!$C$3:$C$14) -> 45819 | I15: =I16 -> 45818 | J15: 1 | K15: =WORKDAY.INTL(I15,J15,1,Data!$C$3:$C$14) -> 45819 | M15: 1 | N15: 1
B16: 1.5 | C16: Project Review | E16: =WORKDAY.INTL(G14,0,1,Data!$C$3:$C$14)-7 -> 45818 | F16: 1 | G16: =WORKDAY.INTL(E16,F16,1,Data!$C$3:$C$14) -> 45819 | I16: =WORKDAY.INTL(K14,0,1,Data!$C$3:$C$14)-7 -> 45818 | J16: 1 | K16: =WORKDAY.INTL(I16,J16,1,Data!$C$3:$C$14) -> 45819 | M16: 1 | N16: 1
B18: 2 | C18: Site Establishment | E18: =MIN(E19:E20) -> 45827 | F18: =G18-E18 -> 1 | G18: =MAX(G19) -> 45828 | I18: =MIN(I19:I20) -> 45826 | J18: =K18-I18 -> 1 | K18: =MAX(K19) -> 45827 | M18: =(J19*M19)/J18 -> 1 | N18: =(K19*N19)/K18 -> 1
B19: 2.1 | C19: Installer on site & Roof Assessment | E19: 45827 | F19: 1 | G19: =E19+F19 -> 45828 | I19: 45826 | J19: 1 | K19: =I19+J19 -> 45827 | M19: 1 | N19: 1 | S19: =NETWORKDAYS(I19,K42,Data!C3:C15) -> 65 | T19: Net Work Days
B21: 3 | C21: AC Installation | E21: =MIN(E22:E26) -> 45827 | F21: =G21-E21 -> 49 | G21: =MAX(G22:G26) -> 45876 | I21: =MIN(I22:I26) -> 45825 | J21: =K21-I21 -> 59 | K21: =MAX(K22:K26) -> 45884 | M21: =(J22*M22+J23*M23+J24*M24+J25*M25+J26*M26)/SUM(J22:J26) -> 1 | N21: =(K22*N22+K23*N23+K24*N24+K25*N25+K26*N26)/SUM(K22:K26) -> 1 | S21: =S19/5 -> 13 | T21: Total Weeks
B22: 3.1 | C22: Inverters delivered | E22: =WORKDAY.INTL(E19,0,1,Data!$C$3:$C$14) -> 45827 | F22: 1 | G22: =WORKDAY.INTL(E22,F22,1,Data!$C$3:$C$14) -> 45828 | I22: 45825 | J22: 1 | K22: =WORKDAY.INTL(I22,J22,1,Data!$C$3:$C$14) -> 45826 | M22: 1 | N22: 1 | S22: =E3/S21 -> 53.846154 | T22: kW/Week Installation Rate
B23: 3.2 | C23: Inverters Mounted | E23: =WORKDAY.INTL(G19,0,1,Data!$C$3:$C$14) -> 45828 | F23: 5 | G23: =WORKDAY.INTL(E23,F23,1,Data!$C$3:$C$14) -> 45835 | I23: =WORKDAY.INTL(K19,0,1,Data!$C$3:$C$14) -> 45827 | J23: 5 | K23: =WORKDAY.INTL(I23,J23,1,Data!$C$3:$C$14) -> 45834 | M23: 1 | N23: 1
B24: 3.3 | C24: Solar DB Lead Time | E24: =WORKDAY.INTL(E19,0,1,Data!$C$3:$C$14) -> 45827 | F24: 20 | G24: =WORKDAY.INTL(E24,F24,1,Data!$C$3:$C$14) -> 45855 | I24: =I19 -> 45826 | J24: 30 | K24: 45869 | M24: 1 | N24: 1
B25: 3.4 | C25: AC Works | E25: =WORKDAY.INTL(G24,0,1,Data!$C$3:$C$14) -> 45855 | F25: 15 | G25: =WORKDAY.INTL(E25,F25,1,Data!$C$3:$C$14) -> 45876 | I25: 45860 | J25: 17 | K25: =WORKDAY.INTL(I25,J25,1,Data!$C$3:$C$14) -> 45883 | M25: 1 | N25: 1
B26: 3.5 | C26: AC Tie-In | E26: =WORKDAY.INTL(E25,0,1,Data!$C$3:$C$14) -> 45855 | F26: 3 | G26: =WORKDAY.INTL(E26,F26,1,Data!$C$3:$C$14) -> 45860 | I26: 45882 | J26: 2 | K26: =WORKDAY.INTL(I26,J26,1,Data!$C$3:$C$14) -> 45884 | M26: 1 | N26: 1
B28: 4 | C28: DC Works | E28: =MIN(E30:E34) -> 45827 | F28: =G28-E28 -> 46 | G28: =MAX(G30:G34) -> 45873 | I28: =MIN(I30:I34) -> 45825 | J28: =K28-I28 -> 72 | K28: =MAX(K30:K34) -> 45897 | M28: =AVERAGE(M30:M34) -> 1 | N28: =AVERAGE(N30:N34) -> 1
B29: 4.1 | C29: Lifeline Installation (If Applicable) | M29: 0 | N29: 0
B30: 4.1 | C30: Mounting Structure delivered | E30: =E19 -> 45827 | F30: 1 | G30: =WORKDAY.INTL(E30,F30,1,Data!$C$3:$C$14) -> 45828 | I30: 45825 | J30: 1 | K30: =WORKDAY.INTL(I30,J30,1,Data!$C$3:$C$14) -> 45826 | M30: 1 | N30: 1
B31: 4.2 | C31: Mounting Structure installation | E31: =WORKDAY.INTL(E19,0,1,Data!$C$3:$C$14) -> 45827 | F31: 10 | G31: =WORKDAY.INTL(E31,F31,1,Data!$C$3:$C$14) -> 45841 | I31: =WORKDAY.INTL(I19,0,1,Data!$C$3:$C$14) -> 45826 | J31: 35 | K31: =WORKDAY.INTL(I31,J31,1,Data!$C$3:$C$14) -> 45875 | M31: 1 | N31: 1
B32: 4.3 | C32: DC Cable delivered | E32: =E37 -> 45834 | F32: 1 | G32: =WORKDAY.INTL(E32,F32,1,Data!$C$3:$C$14) -> 45835 | I32: =I37 -> 45861 | J32: 1 | K32: =WORKDAY.INTL(I32,J32,1,Data!$C$3:$C$14) -> 45862 | M32: 1 | N32: 1
B33: 4.4 | C33: Trunking installation | I33: 45856 | J33: 9 | K33: =WORKDAY.INTL(I33,J33,1,Data!$C$3:$C$14) -> 45869 | M33: 1 | N33: 1
B34: 4.5 | C34: DC Stringing | E34: =WORKDAY.INTL(G38,0,1,Data!$C$3:$C$14)-3 -> 45859 | F34: 10 | G34: =WORKDAY.INTL(E34,F34,1,Data!$C$3:$C$14) -> 45873 | I34: 45867 | J34: 22 | K34: =WORKDAY.INTL(I34,J34,1,Data!$C$3:$C$14) -> 45897 | M34: 1 | N34: 1
B36: 5 | C36: Module installation | E36: =MIN(E37:E38) -> 45834 | F36: =G36-E36 -> 28 | G36: =MAX(G37:G38) -> 45862 | I36: =MIN(I37:I38) -> 45861 | J36: =K36-I36 -> 22 | K36: =MAX(K37:K38) -> 45883 | M36: =(J37*M37+J38*M38)/SUM(J37:J38) -> 1 | N36: =(K37*N37+K38*N38)/SUM(K37:K38) -> 1
B37: 5.1 | C37: Module delivery | E37: =WORKDAY.INTL(E19,0,1,Data!$C$3:$C$14)+7 -> 45834 | F37: 1 | G37: =WORKDAY.INTL(E37,F37,1,Data!$C$3:$C$14) -> 45835 | I37: 45861 | J37: 1 | K37: =WORKDAY.INTL(I37,J37,1,Data!$C$3:$C$14) -> 45862 | M37: 1 | N37: 1
B38: 5.2 | C38: Module mounting | E38: =G31 -> 45841 | F38: 15 | G38: =WORKDAY.INTL(E38,F38,1,Data!$C$3:$C$14) -> 45862 | I38: 45862 | J38: 15 | K38: =WORKDAY.INTL(I38,J38,1,Data!$C$3:$C$14) -> 45883 | M38: 1 | N38: 1
B40: 6 | C40: Commissioning | E40: =MIN(E41:E42) -> 45876 | F40: =G40-E40 -> 4 | G40: =MAX(G41:G42) -> 45880 | I40: =MIN(I41:I42) -> 45897 | J40: =K40-I40 -> 19 | K40: =MAX(K41:K42) -> 45916 | M40: =(J41*M41+J42*M42)/SUM(J41:J42) -> 1 | N40: =(K41*N41+K42*N42)/SUM(K41:K42) -> 1
B41: 6.1 | C41: Commissioning | E41: =WORKDAY.INTL(MAX(G21,G28,G36),0,1,Data!$C$3:$C$14) -> 45876 | F41: 1 | G41: =WORKDAY.INTL(E41,F41,1,Data!$C$3:$C$14) -> 45877 | I41: =WORKDAY.INTL(MAX(K21,K28,K36),0,1,Data!$C$3:$C$14) -> 45897 | J41: 3 | K41: =WORKDAY.INTL(I41,J41,1,Data!$C$3:$C$14) -> 45902 | M41: 1 | N41: 1
B42: 6.2 | C42: Practical Completion | E42: =WORKDAY.INTL(G41,0,1,Data!$C$3:$C$14) -> 45877 | F42: 1 | G42: =WORKDAY.INTL(E42,F42,1,Data!$C$3:$C$14) -> 45880 | I42: =WORKDAY.INTL(K41,0,1,Data!$C$3:$C$14) -> 45902 | J42: 10 | K42: =WORKDAY.INTL(I42,J42,1,Data!$C$3:$C$14) -> 45916 | M42: 1 | N42: 1 | O42: Engineering to assist with technical issues, APEX and SMA data manager coms
B44: 7 | C44: QA Inspections | E44: =MIN(E45) -> 45880 | F44: =G44-E44 -> 1 | G44: =MAX(G45) -> 45881 | I44: =MIN(I45) -> 45911 | J44: =K44-I44 -> 1 | K44: =MAX(K45) -> 45912 | M44: =(J45*M45)/SUM(J45) -> 1 | N44: =(K45*N45)/SUM(K45) -> 1
B45: 7.1 | C45: Red-Team Inspection | E45: =WORKDAY.INTL(G42,0,1,Data!$C$3:$C$14) -> 45880 | F45: 1 | G45: =WORKDAY.INTL(E45,F45,1,Data!$C$3:$C$14) -> 45881 | I45: =WORKDAY.INTL(K42,0,1,Data!$C$3:$C$14)-5 -> 45911 | J45: 1 | K45: =WORKDAY.INTL(I45,J45,1,Data!$C$3:$C$14) -> 45912 | M45: 1 | N45: 1
B47: 8 | C47: Project Closure | E47: =MIN(E48:E53) -> 45881 | F47: =G47-E47 -> 24 | G47: =MAX(G48:G53) -> 45905 | I47: =MIN(I48:I53) -> 45912 | J47: =K47-I47 -> 41 | K47: =MAX(K48:K53) -> 45953 | M47: =(J48*M48+J49*M49+J50*M50+J51*M51+J52*M52+J53*M53)/SUM(J48:J53) -> 1 | N47: =(K48*N48+K49*N49+K50*N50+K51*N51+K52*N52+K53*N53)/SUM(K48:K53) -> 1
B48: 8.1 | C48: Equipment serial numbers | E48: =G45 -> 45881 | F48: 2 | G48: =WORKDAY.INTL(E48,F48,1,Data!$C$3:$C$14) -> 45883 | I48: =K45 -> 45912 | J48: 2 | K48: =WORKDAY.INTL(I48,J48,1,Data!$C$3:$C$14) -> 45916 | M48: 1 | N48: 1
B49: 8.2 | C49: Snags completion | E49: =G45 -> 45881 | F49: 2 | G49: =WORKDAY.INTL(E49,F49,1,Data!$C$3:$C$14) -> 45883 | I49: =K45 -> 45912 | J49: 2 | K49: =WORKDAY.INTL(I49,J49,1,Data!$C$3:$C$14) -> 45916 | M49: 1 | N49: 1
B50: 8.3 | C50: System Performance Monitoring | E50: =WORKDAY.INTL(G49,0,1,Data!$C$3:$C$14) -> 45883 | F50: 5 | G50: =WORKDAY.INTL(E50,F50,1,Data!$C$3:$C$14) -> 45890 | I50: =WORKDAY.INTL(K49,0,1,Data!$C$3:$C$14) -> 45916 | J50: 5 | K50: =WORKDAY.INTL(I50,J50,1,Data!$C$3:$C$14) -> 45923 | M50: 1 | N50: 1
B51: 8.4 | C51: Handover documentation | E51: =WORKDAY.INTL(G50,0,1,Data!$C$3:$C$14) -> 45890 | F51: 10 | G51: =WORKDAY.INTL(E51,F51,1,Data!$C$3:$C$14) -> 45904 | I51: =WORKDAY.INTL(K50,0,1,Data!$C$3:$C$14) -> 45923 | J51: 10 | K51: =WORKDAY.INTL(I51,J51,1,Data!$C$3:$C$14) -> 45938 | M51: 1 | N51: 1
B52: 8.5 | C52: Handover to Client | E52: =WORKDAY.INTL(G51,0,1,Data!$C$3:$C$14) -> 45904 | F52: 1 | G52: =WORKDAY.INTL(E52,F52,1,Data!$C$3:$C$14) -> 45905 | I52: 45947 | J52: 0 | K52: =WORKDAY.INTL(I52,J52,1,Data!$C$3:$C$14) -> 45947 | M52: 1 | N52: 1
B53: 8.6 | C53: Handover to Matriarch | E53: =WORKDAY.INTL(G49,0,1,Data!$C$3:$C$14)+2 -> 45885 | F53: 5 | G53: =WORKDAY.INTL(E53,F53,1,Data!$C$3:$C$14) -> 45891 | I53: 45946 | J53: 5 | K53: =WORKDAY.INTL(I53,J53,1,Data!$C$3:$C$14) -> 45953 | M53: 1 | N53: 1

Sheet Revenue Tracking
B2: HIGH LEVEL PROJECT REVENUE TRACKING
D3: PLANNED | F3: ACTUAL | L3: FINANCIAL REVIEW | N3: TIMELINE REVIEW
B4: 1 | C4: Planned Revenue | D4: ='Project Plan'!E6 -> 5818787.2 | F4: =F21 -> 5818787.2 | N4: Start Date
B5: 2 | C5: Planned Expenditure | D5: =+'Expenditure Tracking'!F5 -> 4908792.2 | F5: =+'Expenditure Tracking'!H5 -> 4056639.2
B6: 3 | C6: Planned Profit | D6: =+D4-D5 -> 909995.01 | F6: =+F4-F5 -> 1762148 | N6: End Date - PC
B7: 4 | C7: Planned Margin | D7: =+D6/D4 -> 0.15638912 | F7: =+F6/F4 -> 0.30283767
B10: CONTRACT
B12: No. | C12: PAYMENT MILESTONE | E12: % | F12: VALUE | H12: PLANNED PAYMENT DATE | L12: INVOICE NUMBER | N12: INVOICE RAISED DATE | P12: PAYMENT RECEIVED DATE | R12: MILESTONE NOTES & COMMENTS
B13: 1 | C13: Acceptance and initial Deposit | E13: 0.35 | F13: =$D$4*E13 -> 2036575.5 | H13: 45808 | L13: 004766 | N13: 45819 | P13: 45814
B14: 2 | C14: Delivery of Panels | E14: 0.2 | F14: =$D$4*E14 -> 1163757.4 | H14: ='Project Plan'!E37+30 -> 45864 | L14: 004766 | N14: 45819 | P14: 45855
B15: 3 | C15: Delivery of Inverters | E15: 0.3 | F15: =$D$4*E15 -> 1745636.2 | H15: ='Project Plan'!E22+30 -> 45857 | L15: 004766 | N15: 45819 | P15: ='Project Plan'!I22+30 -> 45855
B16: 4 | C16: Practical Completion | E16: 0.1 | F16: =$D$4*E16 -> 581878.72 | H16: ='Project Plan'!G40+30 -> 45910 | L16: 004766 | N16: 45819 | P16: 45926
B17: 5 | C17: Handover | E17: 0.05 | F17: =$D$4*E17 -> 290939.36 | H17: ='Project Plan'!G52+30 -> 45935 | L17: 004766 | N17: 45819 | P17: 45947
B18: 6 | E18: 0
B19: 7 | C19: - | E19: 0 | F19: =$D$4*E19 -> 0
E21: =SUM(E13:E19) -> 1 | F21: =SUM(F13:F19) -> 5818787.2
B23: KEY: | C23: contains an error (in result or a check has failed) | L23: =1.15*F14 -> 1338321.1
C24: Red Font - IF TEXT : content not yet confirmed | L24: =1.15*F15 -> 2007481.6
C25: Red Font - IF NUMBER: Negative value
C26: Anything in yellow is a concern or risk for noting or action
C27: confirmed
C28: [ADD INITIALS: comment for noting in square brackets, use colour or red to draw attention if important]
C29: [RT: When adding rows into sheet, ensure you insert between first and last row of each category]
C30: end of sheet - do not insert information below/beyond this
B40: No. | C40: PAYMENT MILESTONE | E40: % | F40: VALUE
B41: 1 | C41: Deposit - Project commencement | E41: 0.35 | F41: =$F$47*E41 -> 2036575.5
B42: 2 | C42: Delivery of Panels | E42: 0.3 | F42: =$F$47*E42 -> 1745636.2
B43: 3 | C43: Delivery of Inverters | E43: 0.2 | F43: =$F$47*E43 -> 1163757.4
B44: 4 | C44: Practical Completion | E44: 0.1 | F44: =$F$47*E44 -> 581878.72
B45: 5 | C45: Handover | E45: 0.05 | F45: =$F$47*E45 -> 290939.36
C46: Total | E46: =SUM(E41:E45) -> 1 | F46: =SUM(F41:F45) -> 5818787.2
E47: =SUM(E41:E45) -> 1 | F47: =F21 -> 5818787.2

Sheet Expenditure Tracking
B2: HIGH LEVEL PROJECT EXPENDITURE TRACKING
F4: COSTED | H4: ACTUAL | J4: Difference from costed
B5: EXPENDITURE | F5: =SUM(F9:F23) -> 4908792.2 | H5: =SUM(H9:H23) -> 4056639.2 | J5: =SUM(J9:J23) -> 852152.96
B7: No. | D7: Item | F7: Costed Expenditure | H7: Actual Expenditure | J7: Saving / Overrun | L7: Comments on variations from planned expenditure
B9: ='Expenditure Breakdown'!B6 -> 1 | D9: ='Expenditure Breakdown'!C6 -> Panels | F9: ='Expenditure Breakdown'!I6 -> 1743145.4 | H9: ='Expenditure Breakdown'!X6 -> 1387821.6 | J9: =F9-H9 -> 355323.79
B10: ='Expenditure Breakdown'!B13 -> 2 | D10: ='Expenditure Breakdown'!C13 -> Inverters | F10: =+'Expenditure Breakdown'!I13 -> 400000 | H10: =+'Expenditure Breakdown'!X13 -> 272034.43 | J10: =F10-H10 -> 127965.57
B11: ='Expenditure Breakdown'!B19 -> 3 | D11: ='Expenditure Breakdown'!C19 -> Mounting Structures | F11: =+'Expenditure Breakdown'!I19 -> 280164 | H11: =+'Expenditure Breakdown'!X19 -> 161872.3 | J11: =F11-H11 -> 118291.7
B12: ='Expenditure Breakdown'!B32 -> 4 | D12: ='Expenditure Breakdown'!C32 -> DC Equipment | F12: =+'Expenditure Breakdown'!I32 -> 540581.7 | H12: =+'Expenditure Breakdown'!X32 -> 612357.56 | J12: =F12-H12 -> -71775.86
B13: ='Expenditure Breakdown'!B51 -> 5 | D13: ='Expenditure Breakdown'!C51 -> Monitoring | F13: =+'Expenditure Breakdown'!I51 -> 174000 | H13: =+'Expenditure Breakdown'!X51 -> 159713.84 | J13: =F13-H13 -> 14286.16
B14: ='Expenditure Breakdown'!B61 -> 6 | D14: ='Expenditure Breakdown'!C61 -> AC Equipment | F14: =+'Expenditure Breakdown'!I61 -> 644291.89 | H14: =+'Expenditure Breakdown'!X61 -> 372881.45 | J14: =F14-H14 -> 271410.44
B15: ='Expenditure Breakdown'!B71 -> 7 | D15: ='Expenditure Breakdown'!C71 -> Battery Systems | F15: =+'Expenditure Breakdown'!I71 -> 0 | H15: ='Expenditure Breakdown'!X71 -> 0 | J15: =F15-H15 -> 0
B16: ='Expenditure Breakdown'!B80 -> 8 | D16: ='Expenditure Breakdown'!C80 -> Product Add On | F16: ='Expenditure Breakdown'!I80 -> 50000 | H16: ='Expenditure Breakdown'!X80 -> 109213.4 | J16: =F16-H16 -> -59213.4
B17: ='Expenditure Breakdown'!L87 -> 9 | D17: ='Expenditure Breakdown'!C87 -> AC & DC Installation | F17: =+'Expenditure Breakdown'!I87 -> 594717.5 | H17: =+'Expenditure Breakdown'!X87 -> 515836.3 | J17: =F17-H17 -> 78881.2
B18: ='Expenditure Breakdown'!B96 -> 10 | D18: ='Expenditure Breakdown'!C96 -> Site Logistics | F18: =+'Expenditure Breakdown'!I96 -> 82411.5 | H18: =+'Expenditure Breakdown'!X96 -> 150323.9 | J18: =F18-H18 -> -67912.4
B19: ='Expenditure Breakdown'!B106 -> 11 | D19: ='Expenditure Breakdown'!C106 -> Due Dilligence | F19: ='Expenditure Breakdown'!I106 -> 139530.75 | H19: ='Expenditure Breakdown'!X106 -> 108250 | J19: =F19-H19 -> 31280.75
B20: ='Expenditure Breakdown'!B114 -> 12 | D20: ='Expenditure Breakdown'!C114 -> BDP Commission | F20: ='Expenditure Breakdown'!G112 -> 0 | H20: ='Expenditure Breakdown'!X112 -> 45499.75 | J20: =F20-H20 -> -45499.75
B21: ='Expenditure Breakdown'!B116 -> 13 | D21: ='Expenditure Breakdown'!C116 -> Engineering | F21: =+'Expenditure Breakdown'!I116 -> 247699.47 | H21: =+'Expenditure Breakdown'!X116 -> 72734.84 | J21: =F21-H21 -> 174964.63 | L21: RV: Matriarch defects percentage 1.25%
B22: ='Expenditure Breakdown'!B124 -> 14 | D22: ='Expenditure Breakdown'!C124 -> General Expenses | F22: =+'Expenditure Breakdown'!I124 -> 12250 | H22: =+'Expenditure Breakdown'!X124 -> 9057.37 | J22: =F22-H22 -> 3192.63
B23: ='Expenditure Breakdown'!B131 -> 15 | D23: ='Expenditure Breakdown'!C131 -> Service Add On | F23: =+'Expenditure Breakdown'!I131 -> 0 | H23: =+'Expenditure Breakdown'!X131 -> 79042.5 | J23: =F23-H23 -> -79042.5
D25: check: | F25: ='Expenditure Breakdown'!I2-'Expenditure Tracking'!F5 -> 0 | G25: ='Expenditure Breakdown'!#REF!-G5 -> #REF! | H25: ='Expenditure Breakdown'!X2-H5 -> 0
A27: Copy amounts in column H and paste as values at Project review.

Sheet Data
C2: Public holidays | F2: Drop down list
C3: 45658 | D3: New Years Day | F3: Approved
C4: 45737 | D4: Human Rights day | F4: Pending
C5: 45765 | D5: Good Friday | F5: Declined
C6: 45768 | D6: Family Day | F6: Abanded
C7: 45774 | D7: Freedom Day
C8: 45765 | D8: Freedom DayObserved
C9: 45778 | D9: Workers day
C10: 45824 | D10: Youth Day Holiday
C11: 45878 | D11: Womens Day
C12: 45924 | D12: Heritage Day
C13: 46007 | D13: Day of Reconciliation | H13: Manual dates
C14: 46016 | D14: Christmas Day
C15: 46017 | D15: Day of Goodwill

Sheet Expenditure Breakdown
B2: COSTED EXPENDITURE BREAKDOWN | I2: =SUM(I6:I135) -> 4908792.2 | J2: =SUM(J6:J135) -> 5818787.2 | L2: ACTUAL EXPENDITURE BREAKDOWN | S2: FINANCE ONLY | X2: =SUM(X6:X135) -> 4056639.2
B4: No. | C4: Product / Service | D4: Description of Work | E4: QTY | F4: Rate / Unit | G4: Budget Total | H4: Project Related date | I4: Total COS | J4: =IF(J2-'Revenue Tracking'!D4>=0, "Total Revenue", "ERROR on REV" ) -> ERROR on REV | L4: No. | M4: Product/ Service | N4: Description of Work | O4: QTY | P4: Rate / Unit | Q4: Actual Total | R4: PO NUMBER | S4: INVOICE NUMBER | T4: INVOICE RAISED DATE | U4: REVENUE RECOGNITION AMOUNT | V4: CHECK | W4: FINANCE PAYMENT DATE | X4: Total COS | Y4: COMMENTS
B6: 1 | C6: Panels | D6: Longi 555W | E6: 1262 | F6: 1381.2562 | G6: =E6*F6 -> 1743145.4 | H6: ='Project Plan'!E36+30 -> 45864 | I6: =G6+G8 -> 1743145.4 | J6: 2075173.1 | L6: 1 | M6: 1. Panels | N6: Jinko 590 - Menlo | O6: 1187 | P6: 1168.2 | Q6: =O6*P6 -> 1386653.4 | S6: Menlo Inv0003034 | T6: 45838 | U6: 2075173.1 | V6: =J6-SUM(U6:U11) -> 0 | W6: 45867 | X6: =SUM(Q6:Q11) -> 1387821.6 | Z6: 19
B7: 1 | L7: 1 | M7: 1. Panels | N7: Jinko 590 - Menlo (additional panel) | P7: =P6/590 -> 1.98 | Q7: 1168.2 | S7: Menlo - INV0003138 | T7: 45900 | U7: 0 | W7: 45939 | Z7: BUDGET | AA7: Installer Allocation
B8: 1 | L8: 1 | M8: 1. Panels | T8: =IF(W8>1,EOMONTH(W8,0),"") | U8: 0 | Z8: AC Equipment | AA8: =C63-150000 -> 494291.89
B9: 1 | L9: 1 | M9: 1. Panels | T9: =IF(W9>1,EOMONTH(W9,0),"") | U9: 0 | Z9: DC Equipment | AA9: =C41-80000 -> 238331.7
B10: 1 | L10: 1 | M10: 1. Panels | T10: =IF(W10>1,EOMONTH(W10,0),"") | U10: 0 | Z10: AC Labour | AA10: =C88 -> 175102.5
B11: 1 | L11: 1 | M11: 1. Panels | T11: =IF(W11>1,EOMONTH(W11,0),"") | U11: 0 | Z11: DC Labour | AA11: =C89-50000 -> 369615
T12: =IF(W12>1,EOMONTH(W12,0),"") | Z12: Offloading | AA12: =G101 -> 8500
B13: 2 | C13: Inverters | D13: SMA Core 2 | E13: 5 | F13: 80000 | G13: =E13*F13 -> 400000 | H13: ='Project Plan'!E22+30 -> 45857 | I13: =SUM(G13:G17) -> 400000 | J13: 476190.48 | L13: 2 | M13: 2. Inverters | N13: SMA Core 2 - Krannich | O13: 5 | P13: 54000 | Q13: 269428.85 | R13: PO4001-LYNN-20250617 - RV Approved | S13: Krannich - Inv 15-10012990 | T13: 45838 | U13: 471629.46 | V13: =J13-SUM(U13:U17) -> 0 | W13: 45827 | X13: =SUM(Q13:Q17) -> 272034.43 | Z13: Roof Access/Scaffolding | AA13: =G97 -> 60961.5
B14: 2 | L14: 2 | M14: 2. Inverters | N14: Delivery | Q14: 2110.03 | S14: Krannich - Inv 15-10012990 | T14: 45838 | U14: 3693.5626 | W14: =W13 -> 45827 | Z14: Storage | AA14: =G98 -> 12950
B15: 2 | L15: 2 | M15: 2. Inverters | N15: EPR Fees | Q15: 495.55 | S15: Krannich - Inv 15-10012990 | T15: 45838 | U15: 867.44972 | W15: =W13 -> 45827 | Z15: Telehandler | AA15: 0
B16: 2 | L16: 2 | M16: 2. Inverters | Q16: 0 | T16: 45838 | U16: 0 | W16: 45893
B17: 2 | L17: 2 | M17: 2. Inverters | T17: =IF(W17>1,EOMONTH(W17,0),"") | U17: 0 | Z17: Other | AA17: 0
T18: =IF(W18>1,EOMONTH(W18,0),"") | Z18: Total | AA18: =SUM(AA8:AA17) -> 1359752.6
B19: 3 | C19: Mounting Structures | D19: Lumax Pitch Roof | G19: 280164 | H19: ='Project Plan'!E30+30 -> 45857 | I19: =SUM(G19:G30) -> 280164 | J19: 333528.57 | L19: 3 | M19: 3. Mounting Structures | U19: 0 | V19: =J19-SUM(U19:U30) -> 0 | X19: =SUM(Q19:Q30) -> 161872.3 | Z19: Less 15% | AA19: =+AA18*0.85 -> 1155789.7
L20: 3 | M20: 3. Mounting Structures | N20: Kliplok order | Q20: 145483.3 | R20: PO4011-LYNN-20250619 - RV Approved | S20: Schletter - INV1888 | T20: 45838 | U20: 303206.52 | W20: 45867
L21: 3 | M21: 3. Mounting Structures | U21: 0
L22: 3 | M22: 3. Mounting Structures | N22: Additional Clamps | Q22: 14549 | R22: PO4043-LYNN-20250627 - RV Approved | S22: Schletter - INV1909 | T22: 45838 | U22: 30322.049 | W22: 45867
B23: 3 | L23: 3 | M23: 3. Mounting Structures | U23: 0 | Y23: Stock in storeroom couldn't be used onsite. | Z23: R/Wp | AA23: =+AA19/'Project Plan'!$E$3/1000 -> 1.6511281
L24: 3 | M24: 3. Mounting Structures | N24: Replacement Clamps | Q24: 1840 | R24: PO4223-LYNN-20250814 - RV Approved | S24: Schletter - INV2069 | T24: 45900 | U24: 0 | W24: 45930
B25: 3 | L25: 3 | M25: 3. Mounting Structures | U25: 0
L26: 3 | M26: 3. Mounting Structures | U26: 0
L27: 3 | M27: 3. Mounting Structures | U27: 0
L28: 3 | M28: 3. Mounting Structures | U28: 0
L29: 3 | M29: 3. Mounting Structures | U29: 0
B30: 3 | L30: 3 | M30: 3. Mounting Structures | U30: 0 | Z30: ACTUAL | AA30: Installer Price
T31: =IF(W31>1,EOMONTH(W31,0),"") | Z31: =Z8 -> AC Equipment | AA31: 372881.45
B32: 4 | C32: DC Equipment | D32: DC Cabling (Total Cable Length) | E32: 15875 | F32: 14 | G32: =E32*F32 -> 222250 | H32: ='Project Plan'!E32+30 -> 45864 | I32: =SUM(G32:G49) -> 540581.7 | J32: 643549.64 | L32: 4 | M32: 4. DC Equipment | T32: =IF(W32>1,EOMONTH(W32,0),"") | U32: =(Q32/$X$32*$J$32) -> 0 | V32: =J32-SUM(U32:U49) -> 0 | X32: =SUM(Q32:Q49) -> 612357.56 | Z32: =Z9 -> DC Equipment | AA32: 131480.3
L33: 4 | M33: 4. DC Equipment | N33: DC Cable | O33: 22400 | P33: 13.5 | Q33: 333360 | S33: Krannich - Inv 15-10013067 | T33: 45838 | U33: 460007.23 | W33: 45867 | Z33: =Z10 -> AC Labour | AA33: 87718.86 | AC33: =AA33/700000 -> 0.12531266
L34: 4 | M34: 4. DC Equipment | N34: Delivery | Q34: 1530 | S34: Krannich - Inv 15-10013067 | T34: 45838 | U34: 2111.2643 | W34: 45867
L35: 4 | M35: 4. DC Equipment | N35: DC Cable - Cape Town Store (3 red, 4 black) | O35: 7000 | P35: 13.5 | Q35: =O35*P35 -> 94500 | S35: Allocated from Cpt Storage | T35: 45900 | U35: 0 | W35: 45900
L36: 4 | M36: 4. DC Equipment | N36: DC Cable - JHB store (red) | O36: 300 | P36: 13.3 | Q36: =O36*P36 -> 3990 | S36: Allocated from Jhb Storage | T36: 45900 | U36: 0 | W36: 45900 | Z36: =Z11 -> DC Labour | AA36: 428117.44 | AC36: =AA36/700000 -> 0.61159634
L37: 4 | M37: 4. DC Equipment | N37: DC Cable - Red (Check stock count) | O37: 100 | P37: 13.3 | Q37: 1330 | S37: Allocated from Jhb Storage | T37: 45900 | U37: 0 | W37: 45900
L38: 4 | M38: 4. DC Equipment | N38: DC Cable - Red | Q38: 27000 | S38: Rubicon - INVWCRE-0070295 | T38: 45900 | U38: 0 | W38: 45930
L39: 4 | M39: 4. DC Equipment | N39: Delivery of Cable | Q39: 19167.26 | S39: DSV Inv: 180144108 | T39: 45900 | U39: 0 | W39: 45930
B40: 4 | D40: Project Kick Off | F40: 0.1 | G40: =$C$41*F40 -> 31833.17 | H40: =H87 -> 45820 | L40: 4 | M40: 4. DC Equipment | T40: =IF(W40>1,EOMONTH(W40,0),"") | U40: =(Q40/$X$32*$J$32) -> 0 | Z40: =Z12 -> Offloading | AA40: 36930
B41: 4 | C41: 318331.7 | D41: Site Establishment | F41: 0.15 | G41: =$C$41*F41 -> 47749.755 | H41: =H88 -> 45834 | L41: 4 | M41: 4. DC Equipment | N41: Project Kick Off | O41: =AA32 -> 131480.3 | P41: 0.1 | Q41: =$O$41*P41 -> 13148.03 | R41: PO3998-LYNN-20260613 - RV Approved | S41: JA ELECTRICAL - Inv 1070 | T41: 45838 | U41: 18143.115 | W41: 45834 | Z41: =Z13 -> Roof Access/Scaffolding | AA41: 61062.4
B42: 4 | D42: AC Installation Complete | F42: 0.2 | G42: =$C$41*F42 -> 63666.34 | H42: =H89 -> 45883 | L42: 4 | M42: 4. DC Equipment | N42: Site Establishment | P42: 0.15 | Q42: =$O$41*P42 -> 19722.045 | S42: JA ELECTRICAL - Inv 1070 | T42: 45838 | U42: 27214.673 | W42: 45834 | Z42: =Z14 -> Storage | AA42: 10730
B43: 4 | D43: DC Installation Complete | F43: 0.25 | G43: =$C$41*F43 -> 79582.925 | H43: =H90 -> 45880 | L43: 4 | M43: 4. DC Equipment | N43: AC Installation Complete | P43: 0.2 | Q43: =$O$41*P43 -> 26296.06 | S43: JA ELECTRICAL - Inv 1070 | T43: 45838 | U43: 36286.23 | W43: 45834 | Z43: Site Ablutions | AA43: 4476
L44: 4 | M44: 4. DC Equipment | N44: DC Installation Complete | Q44: 831.95 | S44: JA ELECTRICAL - Inv 1070 | T44: 45838 | U44: 0 | W44: 45834
B45: 4 | D45: Commissioning Complete | F45: 0.1 | G45: =$C$41*F45 -> 31833.17 | H45: =H91 -> 45887 | L45: 4 | M45: 4. DC Equipment | N45: DC Installation Complete | P45: 0.25 | Q45: =($O$41*P45)-Q44 -> 32038.125 | S45: JA ELECTRICAL - Inv 1070 | T45: 45838 | U45: 45357.788 | W45: =W90 -> 45904 | Z45: Return Of Excess Material | AA45: 7220.5
B46: 4 | D46: Site De-establisment | F46: 0.1 | G46: =$C$41*F46 -> 31833.17 | H46: =H92 -> 45923 | L46: 4 | M46: 4. DC Equipment | N46: Commissioning Complete | P46: 0.1 | Q46: =$O$41*P46 -> 13148.03 | S46: JA ELECTRICAL - Inv 1070 | T46: 45838 | U46: 18143.115 | W46: =W91 -> 45918 | Z46: Waste Skip | AA46: 15855
B47: 4 | D47: Handover Document Complete | F47: 0.05 | G47: =$C$41*F47 -> 15916.585 | H47: =H93 -> 45890 | L47: 4 | M47: 4. DC Equipment | N47: Site De-establisment | P47: 0.1 | Q47: =$O$41*P47 -> 13148.03 | S47: JA ELECTRICAL - Inv 1070 | T47: 45838 | U47: 18143.115 | W47: =W92 -> 45916 | Z47: Other | AA47: 0
B48: 4 | D48: End of Defects Period | F48: 0.05 | G48: =$C$41*F48 -> 15916.585 | H48: =H94 -> 45920 | L48: 4 | M48: 4. DC Equipment | N48: Handover Document Complete | P48: 0.05 | Q48: =$O$41*P48 -> 6574.015 | S48: JA ELECTRICAL - Inv 1070 | T48: 45838 | U48: 9071.5575 | W48: =W93 -> 45916 | Z48: Total | AA48: =SUM(AA31:AA47) -> 1156471.9
B49: 4 | L49: 4 | M49: 4. DC Equipment | N49: End of Defects Period | P49: 0.05 | Q49: =$O$41*P49 -> 6574.015 | S49: JA ELECTRICAL - Inv 1070 | T49: 45838 | U49: 9071.5575 | W49: =W94 -> 45918 | Z49: R/Wp | AA49: =+AA48/'Project Plan'!$E$3/1000 -> 1.6521028
T50: =IF(W50>1,EOMONTH(W50,0),"")
B51: 5 | C51: Monitoring | D51: SMA Datamanager | G51: 26000 | H51: =H13 -> 45857 | I51: =SUM(G51:G59) -> 174000 | J51: 207142.86 | L51: 5 | M51: 5. Monitoring | N51: SMA Data Manager | Q51: 29966.34 | R51: PO4277-LYNN-20250826 - RV Approved | S51: IBC Inv ZA22502201 | T51: 45900 | U51: 0 | V51: =J51-SUM(U51:U59) -> -0.0025723704 | W51: 45896 | X51: =SUM(Q51:Q59) -> 159713.84
B52: 5 | D52: Comms DB | G52: 8000 | H52: =H51 -> 45857 | L52: 5 | M52: 5. Monitoring | N52: CTs & Meters | Q52: 25135 | R52: PO4067-LYNN-20250630 - RV Approved | S52: AccuEnergy ASAI-005849 | T52: 45838 | U52: 38986.104 | W52: 45867
L53: 5 | M53: 5. Monitoring | Q53: -3960 | S53: Accuenergy - CN-00224 | T53: 45900 | U53: 0 | W53: 45900
L54: 5 | M54: 5. Monitoring | Q54: 7690 | S54: Accuenergy - ASAI-006153 | T54: 45900 | U54: 0 | W54: 45930
B55: 5 | L55: 5 | M55: 5. Monitoring | N55: SMA Power Supply | Q55: 838 | R55: PO4001-LYNN-20250617 - RV Approved | S55: Krannich - Inv 15-10012990 | T55: 45838 | U55: 1299.7953 | W55: =W13 -> 45827
B56: 5 | D56: Generator Integration | G56: 125000 | H56: =H47 -> 45890 | L56: 5 | M56: 5. Monitoring | N56: Apex Controller | Q56: 85000 | R56: PO4121-LYNN-20250714 - RV Approved | S56: Rubicon - INVWCRE-0069678 | T56: 45869 | U56: 142127.37 | W56: 45901
B57: 5 | D57: Revenue Grade Meter | G57: 15000 | H57: =H48 -> 45920 | L57: 5 | M57: 5. Monitoring | N57: Revenue Grade Meter | O57: 1 | P57: 15000 | Q57: 11169 | S57: Matriarch - INV-4742 | T57: 45869 | U57: 18359.185 | W57: 45869
B58: 5 | L58: 5 | M58: 5. Monitoring | N58: Anntenna | Q58: 300 | R58: PO4082-LYNN-20250702 - RV Approved | S58: Accuenergy Inv: ASAI-005952 | T58: 45869 | U58: 493.12879 | W58: 45898
B59: 5 | L59: 5 | M59: 5. Monitoring | N59: UPS | Q59: 3575.5 | R59: PO4082-LYNN-20250702 - RV Approved | S59: Frontline INV733385 | T59: 45869 | U59: 5877.2733 | W59: 45869
T60: =IF(W60>1,EOMONTH(W60,0),"")
B61: 6 | C61: AC Equipment | I61: =SUM(G61:G69) -> 644291.89 | J61: 767014.16 | L61: 6 | M61: 6. AC Equipment | T61: =IF(W61>1,EOMONTH(W61,0),"") | V61: =J61-SUM(U61:U69) -> 0 | X61: =SUM(Q61:Q69) -> 372881.45
B62: 6 | D62: Project Kick Off | F62: 0.1 | G62: =C63*F62 -> 64429.189 | H62: ='Project Plan'!E19-7 -> 45820 | L62: 6 | M62: 6. AC Equipment | N62: Project Kick Off | O62: =AA31 -> 372881.45 | P62: 0.1 | Q62: =O$62*P62 -> 37288.145 | R62: PO3998-LYNN-20260613 - RV Approved | S62: JA ELECTRICAL - Inv 1070 | T62: 45838 | U62: 76701.416 | W62: 45834
B63: 6 | C63: 644291.89 | D63: Site Establishment | F63: 0.15 | G63: =$C$63*F63 -> 96643.784 | H63: ='Project Plan'!E19+7 -> 45834 | L63: 6 | M63: 6. AC Equipment | N63: Site Establishment | P63: 0.15 | Q63: =O$62*P63 -> 55932.217 | S63: JA ELECTRICAL - Inv 1070 | T63: 45838 | U63: 115052.12 | W63: 45834
B64: 6 | D64: AC Installation Complete | F64: 0.2 | G64: =$C$63*F64 -> 128858.38 | H64: ='Project Plan'!G21+7 -> 45883 | L64: 6 | M64: 6. AC Equipment | N64: AC Installation Complete | P64: 0.2 | Q64: =O$62*P64 -> 74576.29 | S64: JA ELECTRICAL - Inv 1070 | T64: 45838 | U64: 153402.83 | W64: 45834
B65: 6 | D65: DC Installation Complete | F65: 0.25 | G65: =$C$63*F65 -> 161072.97 | H65: ='Project Plan'!G28+7 -> 45880 | L65: 6 | M65: 6. AC Equipment | N65: DC Installation Complete | P65: 0.25 | Q65: =O$62*P65 -> 93220.363 | S65: JA ELECTRICAL - Inv 1070 | T65: 45838 | U65: 191753.54 | W65: =W90 -> 45904
B66: 6 | D66: Commissioning Complete | F66: 0.1 | G66: =$C$63*F66 -> 64429.189 | H66: ='Project Plan'!G40+7 -> 45887 | L66: 6 | M66: 6. AC Equipment | N66: Commissioning Complete | P66: 0.1 | Q66: =O$62*P66 -> 37288.145 | S66: JA ELECTRICAL - Inv 1070 | T66: 45838 | U66: 76701.416 | W66: =W91 -> 45918
B67: 6 | D67: Site De-establisment | F67: 0.1 | G67: =$C$63*F67 -> 64429.189 | H67: ='Project Plan'!K49+7 -> 45923 | L67: 6 | M67: 6. AC Equipment | N67: Site De-establisment | P67: 0.1 | Q67: =O$62*P67 -> 37288.145 | S67: JA ELECTRICAL - Inv 1070 | T67: 45838 | U67: 76701.416 | W67: =W92 -> 45916
B68: 6 | D68: Handover Document Complete | F68: 0.05 | G68: =$C$63*F68 -> 32214.595 | H68: ='Project Plan'!G48+7 -> 45890 | L68: 6 | M68: 6. AC Equipment | N68: Handover Document Complete | P68: 0.05 | Q68: =O$62*P68 -> 18644.073 | S68: JA ELECTRICAL - Inv 1070 | T68: 45838 | U68: 38350.708 | W68: =W93 -> 45916
B69: 6 | D69: End of Defects Period | F69: 0.05 | G69: =$C$63*F69 -> 32214.595 | H69: =H68+30 -> 45920 | L69: 6 | M69: 6. AC Equipment | N69: End of Defects Period | P69: 0.05 | Q69: =O62*P69 -> 18644.073 | S69: JA ELECTRICAL - Inv 1070 | T69: 45838 | U69: 38350.708 | W69: =W94 -> 45918
T70: =IF(W70>1,EOMONTH(W70,0),"")
B71: 7 | C71: Battery Systems | I71: =SUM(G71:G78) -> 0 | J71: 0 | L71: 7 | M71: Battery Systems | T71: =IF(W71>1,EOMONTH(W71,0),"") | V71: =J71-SUM(U71:U78) -> 0 | X71: =SUM(Q71:Q78) -> 0
B72: 7 | L72: 7 | T72: =IF(W72>1,EOMONTH(W72,0),"")
B73: 7 | L73: 7 | T73: =IF(W73>1,EOMONTH(W73,0),"")
B74: 7 | L74: 7 | T74: =IF(W74>1,EOMONTH(W74,0),"")
B75: 7 | L75: 7 | T75: =IF(W75>1,EOMONTH(W75,0),"")
B76: 7 | L76: 7 | T76: =IF(W76>1,EOMONTH(W76,0),"")
B77: 7 | L77: 7 | T77: =IF(W77>1,EOMONTH(W77,0),"")
B78: 7 | L78: 7 | T78: =IF(W78>1,EOMONTH(W78,0),"")
T79: =IF(W79>1,EOMONTH(W79,0),"")
B80: 8 | C80: Product Add On | I80: =SUM(G80:G85) -> 50000 | J80: 59523.81 | L80: 8 | M80: 8. Product Add On | N80: Catladder | Q80: 4900 | R80: PO4145-LYNN-20250722 - RV Approved | S80: JRL Engineering | T80: 45869 | U80: 2757.7278 | V80: 0 | W80: 45869 | X80: =SUM(Q80:Q85) -> 109213.4
B81: 8 | D81: Inverter Cage | G81: 50000 | H81: =H66 -> 45887 | L81: 8 | M81: 8. Product Add On | N81: Inverter Cage/Awning Deposit | O81: 0.8 | P81: 11800 | Q81: =P81*O81 -> 9440 | R81: PO4102-LYNN-20250709 -MI Approved | S81: JRL Engineering INV00343 | T81: 45869 | U81: 5312.847 | W81: 45849
B82: 8 | L82: 8 | M82: 8. Product Add On | O82: 0.2 | Q82: =O82*P81 -> 2360 | R82: PO4103LYNN-20250709 - MI Approved | S82: JRL Engineering INV00343 | T82: 45869 | U82: 1328.2117 | W82: 45869
B83: 8 | L83: 8 | M83: 8. Product Add On | N83: DB box | Q83: 1900 | S83: JRL Engineering INV00344 | T83: 45869 | U83: 1069.323 | W83: 45849
L84: 8 | M84: 8. Product Add On | N84: Additional Work | Q84: 3450 | R84: PO4237-LYNN-20250819 - RV Approved | S84: JRL Engineering INV00349 | T84: 45900 | U84: 0 | W84: 45890
B85: 8 | L85: 8 | M85: 8. Product Add On | N85: Cable Route VO | Q85: 87163.4 | R85: PO4152-LYNN-20250723 - RV Approved | S85: JA Electrical - Inv 1087 | T85: 45900 | U85: 0 | W85: 45904
K86: Only services to be capture below, products above | T86: =IF(W86>1,EOMONTH(W86,0),"")
B87: 9 | C87: AC & DC Installation | D87: Project Kick Off | F87: 0.1 | G87: =SUM($C$88:$C$89)*F87 -> 59471.75 | H87: =H62 -> 45820 | I87: =SUM(G87:G94) -> 594717.5 | J87: =206002.941176471+493664.705882353 -> 699667.65 | L87: 9 | M87: 9. AC & DC installation | N87: Project Kick Off | O87: =AA33+AA36 -> 515836.3 | P87: 0.1 | Q87: =$O$87*P87 -> 51583.63 | R87: PO3998-LYNN-20260613 - RV Approved | S87: JA ELECTRICAL - Inv 1079 | T87: 45869 | U87: 69966.765 | V87: 0 | W87: 45869 | X87: =SUM(Q87:Q94) -> 515836.3
B88: 9 | C88: 175102.5 | D88: Site Establishment | F88: 0.15 | G88: =SUM($C$88:$C$89)*F88 -> 89207.625 | H88: =H63 -> 45834 | L88: 9 | M88: 9. AC & DC installation | N88: Site Establishment | P88: 0.15 | Q88: =$O$87*P88 -> 77375.445 | S88: JA ELECTRICAL - Inv 1079 | T88: 45869 | U88: 104950.15 | W88: =W87 -> 45869
B89: 9 | C89: 419615 | D89: AC Installation Complete | F89: 0.2 | G89: =SUM($C$88:$C$89)*F89 -> 118943.5 | H89: =H64 -> 45883 | L89: 9 | M89: 9. AC & DC installation | N89: AC Installation Complete | P89: 0.2 | Q89: =$O$87*P89 -> 103167.26 | S89: JA ELECTRICAL - Inv 1079 | T89: 45869 | U89: 139933.53 | W89: 45898
B90: 9 | D90: DC Installation Complete | F90: 0.25 | G90: =SUM($C$88:$C$89)*F90 -> 148679.38 | H90: =H65 -> 45880 | L90: 9 | M90: 9. AC & DC installation | N90: DC Installation Complete | P90: 0.25 | Q90: =$O$87*P90 -> 128959.07 | S90: JA ELECTRICAL - Inv 1079 | T90: 45869 | U90: 174916.91 | W90: ='Project Plan'!K28+7 -> 45904
B91: 9 | D91: Commissioning Complete | F91: 0.1 | G91: =SUM($C$88:$C$89)*F91 -> 59471.75 | H91: =H66 -> 45887 | L91: 9 | M91: 9. AC & DC installation | N91: Commissioning Complete | P91: 0.1 | Q91: =$O$87*P91 -> 51583.63 | S91: JA ELECTRICAL - Inv 1079 | T91: 45900 | U91: 69966.765 | W91: 45918
B92: 9 | D92: Site De-establisment | F92: 0.1 | G92: =SUM($C$88:$C$89)*F92 -> 59471.75 | H92: =H67 -> 45923 | L92: 9 | M92: 9. AC & DC installation | N92: Site De-establisment | P92: 0.1 | Q92: =$O$87*P92 -> 51583.63 | S92: JA ELECTRICAL - Inv 1079 | T92: 45900 | U92: 69966.765 | W92: ='Project Plan'!K49 -> 45916
B93: 9 | D93: Handover Document Complete | F93: 0.05 | G93: =SUM($C$88:$C$89)*F93 -> 29735.875 | H93: =H68 -> 45890 | L93: 9 | M93: 9. AC & DC installation | N93: Handover Document Complete | P93: 0.05 | Q93: =$O$87*P93 -> 25791.815 | S93: JA ELECTRICAL - Inv 1079 | T93: 45900 | U93: 34983.382 | W93: ='Project Plan'!K48 -> 45916
B94: 9 | D94: End of Defects Period | F94: 0.05 | G94: =SUM($C$88:$C$89)*F94 -> 29735.875 | H94: =H69 -> 45920 | L94: 9 | M94: 9. AC & DC installation | N94: End of Defects Period | P94: 0.05 | Q94: =$O$87*P94 -> 25791.815 | S94: JA ELECTRICAL - Inv 1079 | T94: 45900 | U94: 34983.382 | W94: 45918
T95: =IF(W95>1,EOMONTH(W95,0),"")
B96: 10 | C96: Site Logistics | I96: =SUM(G96:G104) -> 82411.5 | J96: =10000+15235.2941176471+71719.4117647059 -> 96954.706 | L96: 10 | M96: 10. Site Logistics | N96: Security | Q96: 14050 | R96: PO4285-LYNN-20250827 - RV Approved | S96: Nightguard Security | T96: 45900 | U96: 0 | V96: =J96-SUM(U96:U104) -> 0 | W96: 45899 | X96: =SUM(Q96:Q104) -> 150323.9
B97: 10 | D97: Scaffolding | G97: 60961.5 | H97: =H98 -> 45887 | L97: 10 | M97: 10. Site Logistics | N97: Project Kick Off | O97: =SUM(AA40:AA46) -> 136273.9 | P97: 0.1 | Q97: =$O$97*P97 -> 13627.39 | R97: PO3998-LYNN-20260613 - RV Approved | S97: JA ELECTRICAL - Inv 1070 | T97: 45838 | U97: 9695.4706 | W97: 45834
B98: 10 | D98: Site Storage | G98: 12950 | H98: =H101 -> 45887 | L98: 10 | M98: 10. Site Logistics | N98: Site Establishment | P98: 0.15 | Q98: =$O$97*P98 -> 20441.085 | S98: JA ELECTRICAL - Inv 1070 | T98: 45838 | U98: 14543.206 | W98: 45834
B99: 10 | L99: 10 | M99: 10. Site Logistics | N99: AC Installation Complete | P99: 0.2 | Q99: =$O$97*P99 -> 27254.78 | S99: JA ELECTRICAL - Inv 1070 | T99: 45838 | U99: 19390.941 | W99: 45834
B100: 10 | L100: 10 | M100: 10. Site Logistics | N100: DC Installation Complete | P100: 0.25 | Q100: =$O$97*P100 -> 34068.475 | S100: JA ELECTRICAL - Inv 1070 | T100: 45838 | U100: 24238.676 | W100: =W90 -> 45904
B101: 10 | D101: Offloading | G101: 8500 | H101: =H91 -> 45887 | L101: 10 | M101: 10. Site Logistics | N101: Commissioning Complete | P101: 0.1 | Q101: =$O$97*P101 -> 13627.39 | S101: JA ELECTRICAL - Inv 1070 | T101: 45838 | U101: 9695.4706 | W101: =W91 -> 45918
B102: 10 | L102: 10 | M102: 10. Site Logistics | N102: Site De-establisment | P102: 0.1 | Q102: =$O$97*P102 -> 13627.39 | S102: JA ELECTRICAL - Inv 1070 | T102: 45838 | U102: 9695.4706 | W102: =W92 -> 45916
B103: 10 | L103: 10 | M103: 10. Site Logistics | N103: Handover Document Complete | P103: 0.05 | Q103: =$O$97*P103 -> 6813.695 | S103: JA ELECTRICAL - Inv 1070 | T103: 45838 | U103: 4847.7353 | W103: =W93 -> 45916
...

Sheet Finance - Revenue
A1: REVENUE RECOGNITION AMOUNT | B1: (All)
A3: Sum of REVENUE RECOGNITION AMOUNT | B3: Column Labels
A4: Row Labels | C4: (blank) | D4: 45808 | E4: 45838 | F4: 45869 | G4: 45900 | H4: 45930 | I4: Grand Total
A5: (blank)
A6: Battery Systems
A7: BDP Commission
A8: 1. Panels | B8: 0 | E8: 2075173.1 | G8: 0 | I8: 2075173.1
A9: 2. Inverters | B9: 0 | E9: 476190.48 | I9: 476190.48
A10: 3. Mounting Structures | C10: 0 | E10: 333528.57 | G10: 0 | I10: 333528.57
A11: 4. DC Equipment | B11: 0 | E11: 643549.64 | G11: 0 | I11: 643549.64
A12: 5. Monitoring | E12: 40285.899 | F12: 166856.96 | G12: 0 | I12: 207142.86
A13: 6. AC Equipment | E13: 767014.16 | I13: 767014.16
A14: 8. Product Add On | F14: 10468.11 | G14: 0 | I14: 10468.11 | J14: =SUM(I8:I14) -> 4513066.9
A15: 9. AC & DC installation | F15: 489767.35 | G15: 209900.29 | I15: 699667.65
A16: 10. Site Logistics | E16: 96954.706 | G16: 0 | I16: 96954.706
A17: 11. Due Dilligence | D17: 109289.39 | E17: 18532.695 | F17: 24200.282 | G17: 12131.46 | I17: 164153.83
A18: 13. Engineering | B18: 0 | C18: 0 | G18: 281476.68 | I18: 281476.68
A19: 14. General Expenses | D19: 739.9661 | E19: 1236.064 | F19: 5282.649 | G19: 7153.0855 | I19: 14411.765
A20: 15. Service Add On
A21: Grand Total | B21: 0 | C21: 0 | D21: 110029.35 | E21: 4452465.3 | F21: 696575.35 | G21: 510661.52 | I21: 5769731.5
D23: 117855.98 | E23: 4452465.3 | F23: 696575.35 | G23: =525682.89+26207.7 -> 551890.59 | I23: =SUM(C23:H23) -> 5818787.2
D24: =GETPIVOTDATA("REVENUE RECOGNITION AMOUNT",$A$3,"INVOICE RAISED DATE",DATE(2025,5,31))-D23 -> -7826.6251 | E24: =GETPIVOTDATA("REVENUE RECOGNITION AMOUNT",$A$3,"INVOICE RAISED DATE",DATE(2025,6,30))-E23 -> 0.0017028432 | F24: =GETPIVOTDATA("REVENUE RECOGNITION AMOUNT",$A$3,"INVOICE RAISED DATE",DATE(2025,7,31))-F23 -> 0.003660577 | G24: =GETPIVOTDATA("REVENUE RECOGNITION AMOUNT",$A$3,"INVOICE RAISED DATE",DATE(2025,8,31))-G23 -> -41229.075
I26: ='Revenue Tracking'!F4 -> 5818787.2
I27: =I23 -> 5818787.2
I28: =I26-I27 -> 0.00011622999

Sheet Finance - COS
A3: Sum of Actual Total | B3: Column Labels
A4: Row Labels | B4: (blank) | D4: 45808 | E4: 45838 | F4: 45869 | G4: 45900 | H4: 45930 | I4: Grand Total
A5: Battery Systems
A6: BDP Commission | F6: 45499.75 | I6: 45499.75 | J6: =SUM(D6:G6) -> 45499.75
A7: (blank) | J7: =SUM(D7:G7) -> 0
A8: 1. Panels | E8: 1386653.4 | G8: 1168.2 | I8: 1387821.6 | J8: =SUM(D8:G8) -> 1387821.6
A9: 2. Inverters | E9: 272034.43 | I9: 272034.43 | J9: =SUM(D9:G9) -> 272034.43
A10: 3. Mounting Structures | E10: 160032.3 | G10: 1840 | I10: 161872.3 | J10: =SUM(D10:G10) -> 161872.3
A11: 4. DC Equipment | E11: 466370.3 | G11: 145987.26 | I11: 612357.56 | J11: =SUM(D11:G11) -> 612357.56
A12: 5. Monitoring | E12: 25973 | F12: 100044.5 | G12: 33696.34 | I12: 159713.84 | J12: =SUM(D12:G12) -> 159713.84
A13: 6. AC Equipment | E13: 372881.45 | I13: 372881.45 | J13: =SUM(D13:G13) -> 372881.45
A14: 8. Product Add On | F14: 18600 | G14: 90613.4 | I14: 109213.4 | J14: =SUM(D14:G14) -> 109213.4 | K14: =SUM(J8:J14) -> 3075894.6
A15: 9. AC & DC installation | F15: 361085.41 | G15: 154750.89 | I15: 515836.3 | J15: =SUM(D15:G15) -> 515836.3
A16: 10. Site Logistics | E16: 136273.9 | G16: 14050 | I16: 150323.9 | J16: =SUM(D16:G16) -> 150323.9
A17: 11. Due Dilligence | D17: 79700 | E17: 10050 | F17: 10500 | G17: 8000 | I17: 108250 | J17: =SUM(D17:G17) -> 108250
A18: 13. Engineering | B18: 0 | G18: 72734.84 | I18: 72734.84 | J18: =SUM(D18:G18) -> 72734.84
A19: 14. General Expenses | D19: 994.52 | E19: 952 | F19: 4268.89 | G19: 2841.96 | I19: 9057.37 | J19: =SUM(D19:G19) -> 9057.37
A20: 15. Service Add On | H20: 79042.5 | I20: 79042.5 | J20: =SUM(D20:G20) -> 0
A21: Grand Total | B21: 0 | D21: 80694.52 | E21: 2831220.8 | F21: 539998.55 | G21: 525682.89 | H21: 79042.5 | I21: 4056639.2 | J21: =SUM(D21:G21) -> 3977596.7

Sheet Cashflow
D1: [RT: Double Check the first date is always a MONDAY] | F1: 45677 | G1: =F1+7 -> 45684 | H1: =G1+7 -> 45691 | I1: =H1+7 -> 45698 | J1: =I1+7 -> 45705 | K1: =J1+7 -> 45712 | L1: =K1+7 -> 45719 | M1: =L1+7 -> 45726 | N1: =M1+7 -> 45733 | ... CP1: =CO1+7 -> 46293
A2: PLANNED | C2: CHECK | D2: CHECK
B3: Planned Revenue | C3: ='Revenue Tracking'!D4 -> 5818787.2 | D3: =SUM(F3:CP3) -> 5818787.2 | F3: =SUMIFS('Revenue Tracking'!$F$13:$F$19, 'Revenue Tracking'!$H$13:$H$19, ">="&F1,'Revenue Tracking'!$H$13:$H$19, "<"&G1) -> 0 | G3: =SUMIFS('Revenue Tracking'!$F$13:$F$19, 'Revenue Tracking'!$H$13:$H$19, ">="&G1,'Revenue Tracking'!$H$13:$H$19, "<"&H1) -> 0 | H3: =SUMIFS('Revenue Tracking'!$F$13:$F$19, 'Revenue Tracking'!$H$13:$H$19, ">="&H1,'Revenue Tracking'!$H$13:$H$19, "<"&I1) -> 0 | I3: =SUMIFS('Revenue Tracking'!$F$13:$F$19, 'Revenue Tracking'!$H$13:$H$19, ">="&I1,'Revenue Tracking'!$H$13:$H$19, "<"&J1) -> 0 | J3: =SUMIFS('Revenue Tracking'!$F$13:$F$19, 'Revenue Tracking'!$H$13:$H$19, ">="&J1,'Revenue Tracking'!$H$13:$H$19, "<"&K1) -> 0 | K3: =SUMIFS('Revenue Tracking'!$F$13:$F$19, 'Revenue Tracking'!$H$13:$H$19, ">="&K1,'Revenue Tracking'!$H$13:$H$19, "<"&L1) -> 0 | L3: =SUMIFS('Revenue Tracking'!$F$13:$F$19, 'Revenue Tracking'!$H$13:$H$19, ">="&L1,'Revenue Tracking'!$H$13:$H$19, "<"&M1) -> 0 | M3: =SUMIFS('Revenue Tracking'!$F$13:$F$19, 'Revenue Tracking'!$H$13:$H$19, ">="&M1,'Revenue Tracking'!$H$13:$H$19, "<"&N1) -> 0 | ... CP3: =SUMIFS('Revenue Tracking'!$F$13:$F$19, 'Revenue Tracking'!$H$13:$H$19, ">="&CP1,'Revenue Tracking'!$H$13:$H$19, "<"&CQ1) -> 0
B4: Planned Revenue - Cumulative | F4: =F3 -> 0 | G4: =F4+G3 -> 0 | H4: =G4+H3 -> 0 | I4: =H4+I3 -> 0 | J4: =I4+J3 -> 0 | K4: =J4+K3 -> 0 | L4: =K4+L3 -> 0 | M4: =L4+M3 -> 0 | N4: =M4+N3 -> 0 | ... CP4: =CO4+CP3 -> 5818787.2
B5: Planned Expenditure | C5: ='Revenue Tracking'!D5 -> 4908792.2 | D5: =SUM(F5:CP5) -> 4908792.2 | F5: =SUMIFS('Expenditure Breakdown'!$G$6:$G$134, 'Expenditure Breakdown'!$H$6:$H$134, ">="&F1,'Expenditure Breakdown'!$H$6:$H$134, "<"&G1) -> 0 | G5: =SUMIFS('Expenditure Breakdown'!$G$6:$G$134, 'Expenditure Breakdown'!$H$6:$H$134, ">="&G1,'Expenditure Breakdown'!$H$6:$H$134, "<"&H1) -> 0 | H5: =SUMIFS('Expenditure Breakdown'!$G$6:$G$134, 'Expenditure Breakdown'!$H$6:$H$134, ">="&H1,'Expenditure Breakdown'!$H$6:$H$134, "<"&I1) -> 0 | I5: =SUMIFS('Expenditure Breakdown'!$G$6:$G$134, 'Expenditure Breakdown'!$H$6:$H$134, ">="&I1,'Expenditure Breakdown'!$H$6:$H$134, "<"&J1) -> 0 | J5: =SUMIFS('Expenditure Breakdown'!$G$6:$G$134, 'Expenditure Breakdown'!$H$6:$H$134, ">="&J1,'Expenditure Breakdown'!$H$6:$H$134, "<"&K1) -> 0 | K5: =SUMIFS('Expenditure Breakdown'!$G$6:$G$134, 'Expenditure Breakdown'!$H$6:$H$134, ">="&K1,'Expenditure Breakdown'!$H$6:$H$134, "<"&L1) -> 0 | L5: =SUMIFS('Expenditure Breakdown'!$G$6:$G$134, 'Expenditure Breakdown'!$H$6:$H$134, ">="&L1,'Expenditure Breakdown'!$H$6:$H$134, "<"&M1) -> 0 | M5: =SUMIFS('Expenditure Breakdown'!$G$6:$G$134, 'Expenditure Breakdown'!$H$6:$H$134, ">="&M1,'Expenditure Breakdown'!$H$6:$H$134, "<"&N1) -> 0 | ... CP5: =SUMIFS('Expenditure Breakdown'!$G$6:$G$134, 'Expenditure Breakdown'!$H$6:$H$134, ">="&CP1,'Expenditure Breakdown'!$H$6:$H$134, "<"&CQ1) -> 0
B6: Planned Expenditure - Cumulative | F6: =F5 -> 0 | G6: =F6+G5 -> 0 | H6: =G6+H5 -> 0 | I6: =H6+I5 -> 0 | J6: =I6+J5 -> 0 | K6: =J6+K5 -> 0 | L6: =K6+L5 -> 0 | M6: =L6+M5 -> 0 | N6: =M6+N5 -> 0 | ... CP6: =CO6+CP5 -> 4908792.2
B7: PLANNED CashFlow | F7: =F4-F6 -> 0 | G7: =G4-G6 -> 0 | H7: =H4-H6 -> 0 | I7: =I4-I6 -> 0 | J7: =J4-J6 -> 0 | K7: =K4-K6 -> 0 | L7: =L4-L6 -> 0 | M7: =M4-M6 -> 0 | ... CP7: =CP4-CP6 -> 909995.01
A8: ACTUAL | C8: CHECK | D8: CHECK
B9: Actual + Planned Revenue | C9: ='Revenue Tracking'!F4 -> 5818787.2 | D9: =SUM(F9:CP9) -> 5818787.2 | F9: =SUMIFS('Revenue Tracking'!$F$13:$F$19, 'Revenue Tracking'!$P$13:$P$19, ">="&F1,'Revenue Tracking'!$P$13:$P$19, "<"&G1) -> 0 | G9: =SUMIFS('Revenue Tracking'!$F$13:$F$19, 'Revenue Tracking'!$P$13:$P$19, ">="&G1,'Revenue Tracking'!$P$13:$P$19, "<"&H1) -> 0 | H9: =SUMIFS('Revenue Tracking'!$F$13:$F$19, 'Revenue Tracking'!$P$13:$P$19, ">="&H1,'Revenue Tracking'!$P$13:$P$19, "<"&I1) -> 0 | I9: =SUMIFS('Revenue Tracking'!$F$13:$F$19, 'Revenue Tracking'!$P$13:$P$19, ">="&I1,'Revenue Tracking'!$P$13:$P$19, "<"&J1) -> 0 | J9: =SUMIFS('Revenue Tracking'!$F$13:$F$19, 'Revenue Tracking'!$P$13:$P$19, ">="&J1,'Revenue Tracking'!$P$13:$P$19, "<"&K1) -> 0 | K9: =SUMIFS('Revenue Tracking'!$F$13:$F$19, 'Revenue Tracking'!$P$13:$P$19, ">="&K1,'Revenue Tracking'!$P$13:$P$19, "<"&L1) -> 0 | L9: =SUMIFS('Revenue Tracking'!$F$13:$F$19, 'Revenue Tracking'!$P$13:$P$19, ">="&L1,'Revenue Tracking'!$P$13:$P$19, "<"&M1) -> 0 | M9: =SUMIFS('Revenue Tracking'!$F$13:$F$19, 'Revenue Tracking'!$P$13:$P$19, ">="&M1,'Revenue Tracking'!$P$13:$P$19, "<"&N1) -> 0 | ... CP9: =SUMIFS('Revenue Tracking'!$F$13:$F$19, 'Revenue Tracking'!$P$13:$P$19, ">="&CP1,'Revenue Tracking'!$P$13:$P$19, "<"&CQ1) -> 0
B10: Actual + Planned Revenue - Cumulative | F10: =F9 -> 0 | G10: =F10+G9 -> 0 | H10: =G10+H9 -> 0 | I10: =H10+I9 -> 0 | J10: =I10+J9 -> 0 | K10: =J10+K9 -> 0 | L10: =K10+L9 -> 0 | M10: =L10+M9 -> 0 | N10: =M10+N9 -> 0 | ... CP10: =CO10+CP9 -> 5818787.2
B11: Actual + Planned Expenditure | C11: ='Revenue Tracking'!F5 -> 4056639.2 | D11: =SUM(F11:CP11) -> 4056639.2 | F11: =SUMIFS('Expenditure Breakdown'!$Q$6:$Q$134, 'Expenditure Breakdown'!$W$6:$W$134, ">="&F1,'Expenditure Breakdown'!$W$6:$W$134, "<"&G1) -> 0 | G11: =SUMIFS('Expenditure Breakdown'!$Q$6:$Q$134, 'Expenditure Breakdown'!$W$6:$W$134, ">="&G1,'Expenditure Breakdown'!$W$6:$W$134, "<"&H1) -> 0 | H11: =SUMIFS('Expenditure Breakdown'!$Q$6:$Q$134, 'Expenditure Breakdown'!$W$6:$W$134, ">="&H1,'Expenditure Breakdown'!$W$6:$W$134, "<"&I1) -> 0 | I11: =SUMIFS('Expenditure Breakdown'!$Q$6:$Q$134, 'Expenditure Breakdown'!$W$6:$W$134, ">="&I1,'Expenditure Breakdown'!$W$6:$W$134, "<"&J1) -> 0 | J11: =SUMIFS('Expenditure Breakdown'!$Q$6:$Q$134, 'Expenditure Breakdown'!$W$6:$W$134, ">="&J1,'Expenditure Breakdown'!$W$6:$W$134, "<"&K1) -> 0 | K11: =SUMIFS('Expenditure Breakdown'!$Q$6:$Q$134, 'Expenditure Breakdown'!$W$6:$W$134, ">="&K1,'Expenditure Breakdown'!$W$6:$W$134, "<"&L1) -> 0 | L11: =SUMIFS('Expenditure Breakdown'!$Q$6:$Q$134, 'Expenditure Breakdown'!$W$6:$W$134, ">="&L1,'Expenditure Breakdown'!$W$6:$W$134, "<"&M1) -> 0 | M11: =SUMIFS('Expenditure Breakdown'!$Q$6:$Q$134, 'Expenditure Breakdown'!$W$6:$W$134, ">="&M1,'Expenditure Breakdown'!$W$6:$W$134, "<"&N1) -> 0 | ... CP11: =SUMIFS('Expenditure Breakdown'!$Q$6:$Q$134, 'Expenditure Breakdown'!$W$6:$W$134, ">="&CP1,'Expenditure Breakdown'!$W$6:$W$134, "<"&CQ1) -> 0
B12: Actual + Planned Expenditure - Cumulative | F12: =F11 -> 0 | G12: =F12+G11 -> 0 | H12: =G12+H11 -> 0 | I12: =H12+I11 -> 0 | J12: =I12+J11 -> 0 | K12: =J12+K11 -> 0 | L12: =K12+L11 -> 0 | M12: =L12+M11 -> 0 | N12: =M12+N11 -> 0 | ... CP12: =CO12+CP11 -> 4056639.2
B14: ACTUAL CashFlow | F14: =F10-F12 -> 0 | G14: =G10-G12 -> 0 | H14: =H10-H12 -> 0 | I14: =I10-I12 -> 0 | J14: =J10-J12 -> 0 | K14: =K10-K12 -> 0 | L14: =L10-L12 -> 0 | M14: =M10-M12 -> 0 | ... CP14: =CP10-CP12 -> 1762148
C16: CHECK | D16: CHECK
B17: Revenue Recognition | C17: =C3-D17 -> 49055.695 | D17: =SUM(F17:CP17) -> 5769731.5 | F17: =SUMIFS('Expenditure Breakdown'!$U$6:$U$134, 'Expenditure Breakdown'!$T$6:$T$134, ">="&F1,'Expenditure Breakdown'!$T$6:$T$134, "<"&G1) -> 0 | G17: =SUMIFS('Expenditure Breakdown'!$U$6:$U$134, 'Expenditure Breakdown'!$T$6:$T$134, ">="&G1,'Expenditure Breakdown'!$T$6:$T$134, "<"&H1) -> 0 | H17: =SUMIFS('Expenditure Breakdown'!$U$6:$U$134, 'Expenditure Breakdown'!$T$6:$T$134, ">="&H1,'Expenditure Breakdown'!$T$6:$T$134, "<"&I1) -> 0 | I17: =SUMIFS('Expenditure Breakdown'!$U$6:$U$134, 'Expenditure Breakdown'!$T$6:$T$134, ">="&I1,'Expenditure Breakdown'!$T$6:$T$134, "<"&J1) -> 0 | J17: =SUMIFS('Expenditure Breakdown'!$U$6:$U$134, 'Expenditure Breakdown'!$T$6:$T$134, ">="&J1,'Expenditure Breakdown'!$T$6:$T$134, "<"&K1) -> 0 | K17: =SUMIFS('Expenditure Breakdown'!$U$6:$U$134, 'Expenditure Breakdown'!$T$6:$T$134, ">="&K1,'Expenditure Breakdown'!$T$6:$T$134, "<"&L1) -> 0 | L17: =SUMIFS('Expenditure Breakdown'!$U$6:$U$134, 'Expenditure Breakdown'!$T$6:$T$134, ">="&L1,'Expenditure Breakdown'!$T$6:$T$134, "<"&M1) -> 0 | M17: =SUMIFS('Expenditure Breakdown'!$U$6:$U$134, 'Expenditure Breakdown'!$T$6:$T$134, ">="&M1,'Expenditure Breakdown'!$T$6:$T$134, "<"&N1) -> 0 | ... CP17: =SUMIFS('Expenditure Breakdown'!$U$6:$U$134, 'Expenditure Breakdown'!$T$6:$T$134, ">="&CP1,'Expenditure Breakdown'!$T$6:$T$134, "<"&CQ1) -> 0
B18: Revenue Recognition Cumulative | C18: =D17-D18 -> 0 | D18: =MAX(F18:CP18) -> 5769731.5 | F18: =F17 -> 0 | G18: =F18+G17 -> 0 | H18: =G18+H17 -> 0 | I18: =H18+I17 -> 0 | J18: =I18+J17 -> 0 | K18: =J18+K17 -> 0 | L18: =K18+L17 -> 0 | M18: =L18+M17 -> 0 | N18: =M18+N17 -> 0 | ... CP18: =CO18+CP17 -> 5769731.5
B20: Installer Expenditure | D20: =SUM(F20:CP20) -> 1020198.1 | F20: =SUMIFS('Expenditure Breakdown'!$Q$41:$Q$49, 'Expenditure Breakdown'!$W$41:$W$49, ">="&F1,'Expenditure Breakdown'!$W$41:$W$49, "<"&G1)+SUMIFS('Expenditure Breakdown'!$Q$62:$Q$69, 'Expenditure Breakdown'!$W$62:$W$69, ">="&F1,'Expenditure Breakdown'!$W$62:$W$69, "<"&G1)+SUMIFS('Expenditure Breakdown'!$Q$87:$Q$94, 'Expenditure Breakdown'!$W$87:$W$94, ">="&F1,'Expenditure Breakdown'!$W$87:$W$94, "<"&G1) -> 0 | G20: =SUMIFS('Expenditure Breakdown'!$Q$41:$Q$49, 'Expenditure Breakdown'!$W$41:$W$49, ">="&G1,'Expenditure Breakdown'!$W$41:$W$49, "<"&H1)+SUMIFS('Expenditure Breakdown'!$Q$62:$Q$69, 'Expenditure Breakdown'!$W$62:$W$69, ">="&G1,'Expenditure Breakdown'!$W$62:$W$69, "<"&H1)+SUMIFS('Expenditure Breakdown'!$Q$87:$Q$94, 'Expenditure Breakdown'!$W$87:$W$94, ">="&G1,'Expenditure Breakdown'!$W$87:$W$94, "<"&H1) -> 0 | H20: =SUMIFS('Expenditure Breakdown'!$Q$41:$Q$49, 'Expenditure Breakdown'!$W$41:$W$49, ">="&H1,'Expenditure Breakdown'!$W$41:$W$49, "<"&I1)+SUMIFS('Expenditure Breakdown'!$Q$62:$Q$69, 'Expenditure Breakdown'!$W$62:$W$69, ">="&H1,'Expenditure Breakdown'!$W$62:$W$69, "<"&I1)+SUMIFS('Expenditure Breakdown'!$Q$87:$Q$94, 'Expenditure Breakdown'!$W$87:$W$94, ">="&H1,'Expenditure Breakdown'!$W$87:$W$94, "<"&I1) -> 0 | I20: =SUMIFS('Expenditure Breakdown'!$Q$41:$Q$49, 'Expenditure Breakdown'!$W$41:$W$49, ">="&I1,'Expenditure Breakdown'!$W$41:$W$49, "<"&J1)+SUMIFS('Expenditure Breakdown'!$Q$62:$Q$69, 'Expenditure Breakdown'!$W$62:$W$69, ">="&I1,'Expenditure Breakdown'!$W$62:$W$69, "<"&J1)+SUMIFS('Expenditure Breakdown'!$Q$87:$Q$94, 'Expenditure Breakdown'!$W$87:$W$94, ">="&I1,'Expenditure Breakdown'!$W$87:$W$94, "<"&J1) -> 0 | J20: =SUMIFS('Expenditure Breakdown'!$Q$41:$Q$49, 'Expenditure Breakdown'!$W$41:$W$49, ">="&J1,'Expenditure Breakdown'!$W$41:$W$49, "<"&K1)+SUMIFS('Expenditure Breakdown'!$Q$62:$Q$69, 'Expenditure Breakdown'!$W$62:$W$69, ">="&J1,'Expenditure Breakdown'!$W$62:$W$69, "<"&K1)+SUMIFS('Expenditure Breakdown'!$Q$87:$Q$94, 'Expenditure Breakdown'!$W$87:$W$94, ">="&J1,'Expenditure Breakdown'!$W$87:$W$94, "<"&K1) -> 0 | K20: =SUMIFS('Expenditure Breakdown'!$Q$41:$Q$49, 'Expenditure Breakdown'!$W$41:$W$49, ">="&K1,'Expenditure Breakdown'!$W$41:$W$49, "<"&L1)+SUMIFS('Expenditure Breakdown'!$Q$62:$Q$69, 'Expenditure Breakdown'!$W$62:$W$69, ">="&K1,'Expenditure Breakdown'!$W$62:$W$69, "<"&L1)+SUMIFS('Expenditure Breakdown'!$Q$87:$Q$94, 'Expenditure Breakdown'!$W$87:$W$94, ">="&K1,'Expenditure Breakdown'!$W$87:$W$94, "<"&L1) -> 0 | L20: =SUMIFS('Expenditure Breakdown'!$Q$41:$Q$49, 'Expenditure Breakdown'!$W$41:$W$49, ">="&L1,'Expenditure Breakdown'!$W$41:$W$49, "<"&M1)+SUMIFS('Expenditure Breakdown'!$Q$62:$Q$69, 'Expenditure Breakdown'!$W$62:$W$69, ">="&L1,'Expenditure Breakdown'!$W$62:$W$69, "<"&M1)+SUMIFS('Expenditure Breakdown'!$Q$87:$Q$94, 'Expenditure Breakdown'!$W$87:$W$94, ">="&L1,'Expenditure Breakdown'!$W$87:$W$94, "<"&M1) -> 0 | M20: =SUMIFS('Expenditure Breakdown'!$Q$41:$Q$49, 'Expenditure Breakdown'!$W$41:$W$49, ">="&M1,'Expenditure Breakdown'!$W$41:$W$49, "<"&N1)+SUMIFS('Expenditure Breakdown'!$Q$62:$Q$69, 'Expenditure Breakdown'!$W$62:$W$69, ">="&M1,'Expenditure Breakdown'!$W$62:$W$69, "<"&N1)+SUMIFS('Expenditure Breakdown'!$Q$87:$Q$94, 'Expenditure Breakdown'!$W$87:$W$94, ">="&M1,'Expenditure Breakdown'!$W$87:$W$94, "<"&N1) -> 0 | ... CP20: =SUMIFS('Expenditure Breakdown'!$Q$41:$Q$49, 'Expenditure Breakdown'!$W$41:$W$49, ">="&CP1,'Expenditure Breakdown'!$W$41:$W$49, "<"&CQ1)+SUMIFS('Expenditure Breakdown'!$Q$62:$Q$69, 'Expenditure Breakdown'!$W$62:$W$69, ">="&CP1,'Expenditure Breakdown'!$W$62:$W$69, "<"&CQ1)+SUMIFS('Expenditure Breakdown'!$Q$87:$Q$94, 'Expenditure Breakdown'!$W$87:$W$94, ">="&CP1,'Expenditure Breakdown'!$W$87:$W$94, "<"&CQ1) -> 0
B21: Installer Expenditure - Cumulative | F21: =F20 -> 0 | G21: =G20+F21 -> 0 | H21: =H20+G21 -> 0 | I21: =I20+H21 -> 0 | J21: =J20+I21 -> 0 | K21: =K20+J21 -> 0 | L21: =L20+K21 -> 0 | M21: =M20+L21 -> 0 | N21: =N20+M21 -> 0 | ... CP21: =CP20+CO21 -> 1020198.1

Sheet Project Margins
A1: [capture project margins from costing sheet]
A3: Products | D3: 0.32
A4: Services | D4: 0.5
A5: Expenses | D5: 0.15
A6: Subcontractors | D6: 0.2

Sheet Equipment Quotes
B2: Equipment Quote and Budget comparision
B4: Description | D4: Budget | F4: Supplier 1 | H4: Variance | J4: Supplier 2 | L4: Variance | N4: Comments / Notes
F7: >Name< | J7: >Name<
B9: Inverters | D9: =SUM(D10:D11) -> 400000 | F9: =SUM(F10:F13) -> 0 | H9: =$D$9-F9 -> 400000 | J9: =SUM(J10:J13) -> 0 | L9: =$D$9-J9 -> 400000
B10: Inverters | D10: ='Expenditure Breakdown'!G13 -> 400000
B11: Optimizers | D11: ='Expenditure Breakdown'!G14 -> 0
B12: Warranty
B13: Delivery fee
F15: >Name< | J15: >Name<
B17: Mounting Structure | D17: =SUM(D18:D19) -> 280164 | F17: =SUM(F18:F20) -> 0 | H17: =$D$17- F17 -> 280164 | J17: =SUM(J18:J20) -> 0 | L17: =$D$17- J17 -> 280164
B18: Mounting Structure | D18: ='Expenditure Breakdown'!G19 -> 280164
B19: Delivery fee
F21: >Name< | J21: >Name<
B23: DC Cable | D23: =SUM(D24:D25) -> 222250 | F23: =SUM(F24:F25) -> 0 | H23: =$D$23- F23 -> 222250 | J23: =SUM(J24:J25) -> 0 | L23: =$D$23- J23 -> 222250
B24: DC Cable | D24: ='Expenditure Breakdown'!G32 -> 222250
B25: Delivery fee
F27: >Name< | J27: >Name<
B29: Monitoring system | D29: =SUM(D30:D32) -> #REF! | F29: =SUM(F30:F42) -> 0 | H29: =$D$29-F29 -> #REF! | J29: =SUM(J30:J32) -> 0 | L29: =$D$29-J29 -> #REF!
B30: ='Expenditure Breakdown'!D51 -> SMA Datamanager | D30: ='Expenditure Breakdown'!G51 -> 26000
B31: ='Expenditure Breakdown'!#REF! -> #REF! | D31: ='Expenditure Breakdown'!#REF! -> #REF!
B32: Delivery fee
F34: >Name< | J34: >Name<
B36: Additional Scope | D36: =SUM(D37:D41) -> 0 | F36: =SUM(F37:F41) -> 0 | H36: =$D$29-F36 -> #REF! | J36: =SUM(J37:J41) -> 0 | L36: =$D$29-J36 -> #REF!
B37: SCADA | D37: ='Expenditure Breakdown'!G80 -> 0
B38: Inverter cage
B39: Cat ladders
B40: Gen Integration
B41: Lifelines
B43: Totals | D43: =D36+D29+D23+D17+D9 -> #REF! | H43: =SUM(H7:H42) -> #REF! | L43: =SUM(L7:L42) -> #REF!
B47: All amounts are incl VAT

Sheet Installer Quotes
B2: Installer Quote and Budget comparision
B4: Description | D4: Budget | G4: Cosmic Sun | J4: Variance | L4: Matthews Group | O4: Variance
B6: AC Equipment | D6: ='Expenditure Breakdown'!AA8 -> 494291.89 | E6: =D6/(1000*'Project Plan'!$E$3) -> 0.70613127 | G6: 277892.91 | H6: =G6/('Project Plan'!$E$3*1000) -> 0.39698987 | J6: =D6-G6 -> 216398.98 | M6: =L6/('Project Plan'!$E$3*1000) -> 0 | O6: =D6-L6 -> 494291.89
B7: DC Equipment | D7: ='Expenditure Breakdown'!AA9 -> 238331.7 | E7: =D7/(1000*'Project Plan'!$E$3) -> 0.34047386 | G7: 142158.25 | H7: =G7/('Project Plan'!$E$3*1000) -> 0.20308321 | J7: =D7-G7 -> 96173.45 | M7: =L7/('Project Plan'!$E$3*1000) -> 0 | O7: =D7-L7 -> 238331.7
B8: AC Labour | D8: ='Expenditure Breakdown'!AA10 -> 175102.5 | E8: =D8/(1000*'Project Plan'!$E$3) -> 0.25014643 | G8: 96174 | H8: =G8/('Project Plan'!$E$3*1000) -> 0.13739143 | J8: =D8-G8 -> 78928.5 | M8: =L8/('Project Plan'!$E$3*1000) -> 0 | O8: =D8-L8 -> 175102.5
B9: DC Labour | D9: ='Expenditure Breakdown'!AA11 -> 369615 | E9: =D9/(1000*'Project Plan'!$E$3) -> 0.52802143 | G9: 230160 | H9: =G9/('Project Plan'!$E$3*1000) -> 0.3288 | J9: =D9-G9 -> 139455 | M9: =L9/('Project Plan'!$E$3*1000) -> 0 | O9: =D9-L9 -> 369615
B10: Offloading | D10: ='Expenditure Breakdown'!AA12 -> 8500 | G10: 0 | J10: =D10-G10 -> 8500 | O10: =D10-L10 -> 8500
B11: Roof Access/Scaffolding | D11: ='Expenditure Breakdown'!AA13 -> 60961.5 | G11: 29257.61 | J11: =D11-G11 -> 31703.89 | O11: =D11-L11 -> 60961.5
B12: Storage | D12: ='Expenditure Breakdown'!AA14 -> 12950 | J12: =D12-G12 -> 12950 | O12: =D12-L12 -> 12950
B13: Telehandler | D13: ='Expenditure Breakdown'!AA15 -> 0
B14: HSE | D14: 0
B15: Totals | D15: =SUM(D6:D13) -> 1359752.6 | G15: =SUM(G6:G13) -> 775642.77 | J15: =SUM(J6:J14) -> 584109.82 | L15: =SUM(L6:L13) -> 0 | O15: =SUM(O6:O14) -> 1359752.6
B18: Description | D18: Budget | G18: >Installer Name 3< | J18: Variance | L18: >Installer Name 4< | O18: Variance
B20: AC installation | D20: ='Expenditure Breakdown'!#REF! -> #REF! | E20: =D20/(1000*'Project Plan'!$E$3) -> #REF! | H20: =G20/(1000*'Project Plan'!$E$3) -> 0 | J20: =D20-G20 -> #REF! | M20: =L20/(1000*'Project Plan'!$E$3) -> 0 | O20: =D6-L20 -> 494291.89
B21: AC equipment | D21: ='Expenditure Breakdown'!C69 -> 0 | E21: =D21/(1000*'Project Plan'!$E$3) -> 0 | J21: =D21-G21 -> 0 | M21: =L21/(1000*'Project Plan'!$E$3) -> 0 | O21: =D7-L21 -> 238331.7
B22: DC installation | D22: ='Expenditure Breakdown'!#REF! -> #REF! | E22: =D22/(1000*'Project Plan'!$E$3) -> #REF! | H22: =G22/(1000*'Project Plan'!$E$3) -> 0 | J22: =D22-G22 -> #REF! | M22: =L22/(1000*'Project Plan'!$E$3) -> 0 | O22: =D8-L22 -> 175102.5
B23: DC equipment | D23: =SUM('Expenditure Breakdown'!G47:G48) -> 31833.17 | E23: =D23/(1000*'Project Plan'!$E$3) -> 0.045475957 | J23: =D23-G23 -> 31833.17 | O23: =D9-L23 -> 369615
B24: Storage | D24: ='Expenditure Breakdown'!G110 -> 7000 | J24: =D24-G24 -> 7000 | O24: =D10-L24 -> 8500
B25: Panel lifting equipment | D25: =SUM('Expenditure Breakdown'!G96:G102) -> 82411.5 | J25: =D25-G25 -> 82411.5 | O25: =D11-L25 -> 60961.5
B26: Offloading | D26: ='Expenditure Breakdown'!G104 -> 0 | J26: =D26-G26 -> 0 | O26: =D12-L26 -> 12950
B29: Totals | D29: =SUM(D20:D27) -> #REF! | G29: =SUM(G20:G27) -> 0 | J29: =SUM(J20:J28) -> #REF! | L29: =SUM(L20:L27) -> 0 | O29: =SUM(O20:O28) -> 1359752.6
B32: Budget Summary
B34: Budget | D34: =D15 -> 1359752.6
B35: =G4 -> Cosmic Sun | D35: =G15 -> 775642.77
B36: =L4 -> Matthews Group | D36: =L15 -> 0
B37: =G18 -> >Installer Name 3< | D37: =G29 -> 0
B38: =L18 -> >Installer Name 4< | D38: =L29 -> 0
B40: =IF(D40<D34,"Saving","Loss") -> Loss | D40: =D34-MIN(D35:D38) -> 1359752.6
B42: All amounts are exc VAT

Sheet Decision Register
B1: =D15 -> Lynridge Mall | E1: Decision Register
B3: ID | C3: Decision Description | D3: Decision Impact | E3: Proposed Date | F3: Proposed By | G3: Status | H3: Approved By | I3: Date | J3: Results / Comments
B4: DEC001
B5: DEC002
B6: DEC003
B7: DEC004
B8: DEC005
B9: DEC006
B10: DEC007
B11: DEC008
B12: DEC009
B13: DEC010
D15: {='Project Plan'!E2:H2} -> Lynridge Mall | E15: 0 | F15: 0 | G15: 0
