Workbook
Name Inverter_Capacity: #REF!
Name Inverter_Supplier: #REF!
Name Project_Size: Compliance!Projectsize
Name Project_Size: 'Finance - Revenue'!Projectsize
Name Project_Size: Projectsize
Name Projectsize: #REF!
Name Projectsize: #REF!
Name Projectsize: 'Project Margins'!$K$5
Name Security_Serv: #REF!
Name Security_Serv: #REF!
Name SSS: #REF!
Name SSS: #REF!
Name USD_ZAR: #REF!

Sheet Sheet1
A1: PROJECT PLAN
A2: # | B2: Project Milestone | C2: Planned Start Date | D2: Duration (Work Days) | E2: Planned End Date | F2: Actual Start Date | H2: Actual End Date | J2: Comments | L2: =C3 -> 43831 | M2: =L2+3 -> 43834 | N2: =M2+7 -> 43841 | O2: =N2+7 -> 43848 | P2: =O2+7 -> 43855 | Q2: =P2+6 -> 43861 | R2: =Q2+1 -> 43862 | S2: =R2+7 -> 43869 | T2: =S2+7 -> 43876 | U2: =T2+7 -> 43883 | V2: =U2+6 -> 43889 | W2: =V2+7 -> 43896 | X2: =W2+7 -> 43903 | Y2: =X2+7 -> 43910 | Z2: =Y2+7 -> 43917 | AA2: =Z2+3 -> 43920 | AB2: =AA2+4 -> 43924 | AC2: =AB2+7 -> 43931 | AD2: =AC2+7 -> 43938 | AE2: =AD2+7 -> 43945 | AF2: =AE2+6 -> 43951 | AG2: =AF2+2 -> 43953 | AH2: =AG2+7 -> 43960 | AI2: =AH2+7 -> 43967 | AJ2: =AI2+7 -> 43974 | AK2: =AJ2+7 -> 43981 | AL2: =AK2+1 -> 43982 | AM2: =AL2+6 -> 43988 | AN2: =AM2+7 -> 43995 | AO2: =AN2+7 -> 44002 | AP2: =AO2+7 -> 44009 | AQ2: =AP2+3 -> 44012 | AR2: =AQ2+4 -> 44016 | AS2: =AR2+7 -> 44023 | AT2: =AS2+7 -> 44030 | AU2: =AT2+7 -> 44037 | AV2: =AU2+6 -> 44043 | AW2: =AV2+1 -> 44044 | AX2: =AW2+7 -> 44051 | AY2: =AX2+7 -> 44058 | AZ2: =AY2+7 -> 44065 | BA2: =AZ2+7 -> 44072 | BB2: =BA2+2 -> 44074 | BC2: =BB2+5 -> 44079 | BD2: =BC2+7 -> 44086 | BE2: =BD2+7 -> 44093 | BF2: =BE2+7 -> 44100 | BG2: =BF2+4 -> 44104
A3: 1 | B3: Contract Signature | C3: 43831 | D3: 1 | E3: 43832 | F3: 43831 | G3: 1 | H3: 43832 | L3: =IF(AND($F3<(L$2+7),$F3>L$2),1, IF(AND($H3<L$2+7,$H3>L$2),3, IF(AND($F3<=L$2, $H3>=L$2), 2, "" ))) -> 3 | M3: =IF(AND($F3<(M$2+7),$F3>M$2),1, IF(AND($H3<M$2+7,$H3>M$2),3, IF(AND($F3<=M$2, $H3>=M$2), 2, "" ))) | N3: =IF(AND($F3<(N$2+7),$F3>N$2),1, IF(AND($H3<N$2+7,$H3>N$2),3, IF(AND($F3<=N$2, $H3>=N$2), 2, "" ))) | O3: =IF(AND($F3<(O$2+7),$F3>O$2),1, IF(AND($H3<O$2+7,$H3>O$2),3, IF(AND($F3<=O$2, $H3>=O$2), 2, "" ))) | P3: =IF(AND($F3<(P$2+7),$F3>P$2),1, IF(AND($H3<P$2+7,$H3>P$2),3, IF(AND($F3<=P$2, $H3>=P$2), 2, "" ))) | Q3: =IF(AND($F3<(Q$2+7),$F3>Q$2),1, IF(AND($H3<Q$2+7,$H3>Q$2),3, IF(AND($F3<=Q$2, $H3>=Q$2), 2, "" ))) | R3: =IF(AND($F3<(R$2+7),$F3>R$2),1, IF(AND($H3<R$2+7,$H3>R$2),3, IF(AND($F3<=R$2, $H3>=R$2), 2, "" ))) | S3: =IF(AND($F3<(S$2+7),$F3>S$2),1, IF(AND($H3<S$2+7,$H3>S$2),3, IF(AND($F3<=S$2, $H3>=S$2), 2, "" ))) | ... AQ3: =IF(AND($F3<(AQ$2+7),$F3>AQ$2),1, IF(AND($H3<AQ$2+7,$H3>AQ$2),3, IF(AND($F3<=AQ$2, $H3>=AQ$2), 2, "" )))
A4: A | B4: PAYMENT MILESTONE 1: DEPOSIT | C4: 43832 | D4: 1 | E4: 43833 | F4: 43832 | G4: 1 | H4: 43833 | L4: =IF(AND($F4<(L$2+7),$F4>L$2),1, IF(AND($H4<L$2+7,$H4>L$2),3, IF(AND($F4<=L$2, $H4>=L$2), 2, "" ))) -> 1 | M4: =IF(AND($F4<(M$2+7),$F4>M$2),1, IF(AND($H4<M$2+7,$H4>M$2),3, IF(AND($F4<=M$2, $H4>=M$2), 2, "" ))) | N4: =IF(AND($F4<(N$2+7),$F4>N$2),1, IF(AND($H4<N$2+7,$H4>N$2),3, IF(AND($F4<=N$2, $H4>=N$2), 2, "" ))) | O4: =IF(AND($F4<(O$2+7),$F4>O$2),1, IF(AND($H4<O$2+7,$H4>O$2),3, IF(AND($F4<=O$2, $H4>=O$2), 2, "" ))) | P4: =IF(AND($F4<(P$2+7),$F4>P$2),1, IF(AND($H4<P$2+7,$H4>P$2),3, IF(AND($F4<=P$2, $H4>=P$2), 2, "" ))) | Q4: =IF(AND($F4<(Q$2+7),$F4>Q$2),1, IF(AND($H4<Q$2+7,$H4>Q$2),3, IF(AND($F4<=Q$2, $H4>=Q$2), 2, "" ))) | R4: =IF(AND($F4<(R$2+7),$F4>R$2),1, IF(AND($H4<R$2+7,$H4>R$2),3, IF(AND($F4<=R$2, $H4>=R$2), 2, "" ))) | S4: =IF(AND($F4<(S$2+7),$F4>S$2),1, IF(AND($H4<S$2+7,$H4>S$2),3, IF(AND($F4<=S$2, $H4>=S$2), 2, "" ))) | ... AQ4: =IF(AND($F4<(AQ$2+7),$F4>AQ$2),1, IF(AND($H4<AQ$2+7,$H4>AQ$2),3, IF(AND($F4<=AQ$2, $H4>=AQ$2), 2, "" )))
A5: 2 | B5: Structural and Electrical Due Diligences | C5: 43833 | D5: 5 | E5: 43840 | F5: 43833 | G5: 5 | H5: 43840 | L5: =IF(AND($F5<(L$2+7),$F5>L$2),1, IF(AND($H5<L$2+7,$H5>L$2),3, IF(AND($F5<=L$2, $H5>=L$2), 2, "" ))) -> 1 | M5: =IF(AND($F5<(M$2+7),$F5>M$2),1, IF(AND($H5<M$2+7,$H5>M$2),3, IF(AND($F5<=M$2, $H5>=M$2), 2, "" ))) -> 3 | N5: =IF(AND($F5<(N$2+7),$F5>N$2),1, IF(AND($H5<N$2+7,$H5>N$2),3, IF(AND($F5<=N$2, $H5>=N$2), 2, "" ))) | O5: =IF(AND($F5<(O$2+7),$F5>O$2),1, IF(AND($H5<O$2+7,$H5>O$2),3, IF(AND($F5<=O$2, $H5>=O$2), 2, "" ))) | P5: =IF(AND($F5<(P$2+7),$F5>P$2),1, IF(AND($H5<P$2+7,$H5>P$2),3, IF(AND($F5<=P$2, $H5>=P$2), 2, "" ))) | Q5: =IF(AND($F5<(Q$2+7),$F5>Q$2),1, IF(AND($H5<Q$2+7,$H5>Q$2),3, IF(AND($F5<=Q$2, $H5>=Q$2), 2, "" ))) | R5: =IF(AND($F5<(R$2+7),$F5>R$2),1, IF(AND($H5<R$2+7,$H5>R$2),3, IF(AND($F5<=R$2, $H5>=R$2), 2, "" ))) | S5: =IF(AND($F5<(S$2+7),$F5>S$2),1, IF(AND($H5<S$2+7,$H5>S$2),3, IF(AND($F5<=S$2, $H5>=S$2), 2, "" ))) | ... AQ5: =IF(AND($F5<(AQ$2+7),$F5>AQ$2),1, IF(AND($H5<AQ$2+7,$H5>AQ$2),3, IF(AND($F5<=AQ$2, $H5>=AQ$2), 2, "" )))
A6: 3 | B6: Design Confirmation | C6: 43841 | D6: 2 | E6: 43844 | F6: 43841 | G6: 2 | H6: 43844 | L6: =IF(AND($F6<(L$2+7),$F6>L$2),1, IF(AND($H6<L$2+7,$H6>L$2),3, IF(AND($F6<=L$2, $H6>=L$2), 2, "" ))) | M6: =IF(AND($F6<(M$2+7),$F6>M$2),1, IF(AND($H6<M$2+7,$H6>M$2),3, IF(AND($F6<=M$2, $H6>=M$2), 2, "" ))) | N6: =IF(AND($F6<(N$2+7),$F6>N$2),1, IF(AND($H6<N$2+7,$H6>N$2),3, IF(AND($F6<=N$2, $H6>=N$2), 2, "" ))) -> 3 | O6: =IF(AND($F6<(O$2+7),$F6>O$2),1, IF(AND($H6<O$2+7,$H6>O$2),3, IF(AND($F6<=O$2, $H6>=O$2), 2, "" ))) | P6: =IF(AND($F6<(P$2+7),$F6>P$2),1, IF(AND($H6<P$2+7,$H6>P$2),3, IF(AND($F6<=P$2, $H6>=P$2), 2, "" ))) | Q6: =IF(AND($F6<(Q$2+7),$F6>Q$2),1, IF(AND($H6<Q$2+7,$H6>Q$2),3, IF(AND($F6<=Q$2, $H6>=Q$2), 2, "" ))) | R6: =IF(AND($F6<(R$2+7),$F6>R$2),1, IF(AND($H6<R$2+7,$H6>R$2),3, IF(AND($F6<=R$2, $H6>=R$2), 2, "" ))) | S6: =IF(AND($F6<(S$2+7),$F6>S$2),1, IF(AND($H6<S$2+7,$H6>S$2),3, IF(AND($F6<=S$2, $H6>=S$2), 2, "" ))) | ... AQ6: =IF(AND($F6<(AQ$2+7),$F6>AQ$2),1, IF(AND($H6<AQ$2+7,$H6>AQ$2),3, IF(AND($F6<=AQ$2, $H6>=AQ$2), 2, "" )))
A7: 4 | B7: Equipment Procurement | C7: 43833 | E7: 43949 | F7: 43833 | H7: 43949 | L7: =IF(AND($F7<(L$2+7),$F7>L$2),1, IF(AND($H7<L$2+7,$H7>L$2),3, IF(AND($F7<=L$2, $H7>=L$2), 2, "" ))) -> 1 | M7: =IF(AND($F7<(M$2+7),$F7>M$2),1, IF(AND($H7<M$2+7,$H7>M$2),3, IF(AND($F7<=M$2, $H7>=M$2), 2, "" ))) -> 2 | N7: =IF(AND($F7<(N$2+7),$F7>N$2),1, IF(AND($H7<N$2+7,$H7>N$2),3, IF(AND($F7<=N$2, $H7>=N$2), 2, "" ))) -> 2 | O7: =IF(AND($F7<(O$2+7),$F7>O$2),1, IF(AND($H7<O$2+7,$H7>O$2),3, IF(AND($F7<=O$2, $H7>=O$2), 2, "" ))) -> 2 | P7: =IF(AND($F7<(P$2+7),$F7>P$2),1, IF(AND($H7<P$2+7,$H7>P$2),3, IF(AND($F7<=P$2, $H7>=P$2), 2, "" ))) -> 2 | Q7: =IF(AND($F7<(Q$2+7),$F7>Q$2),1, IF(AND($H7<Q$2+7,$H7>Q$2),3, IF(AND($F7<=Q$2, $H7>=Q$2), 2, "" ))) -> 2 | R7: =IF(AND($F7<(R$2+7),$F7>R$2),1, IF(AND($H7<R$2+7,$H7>R$2),3, IF(AND($F7<=R$2, $H7>=R$2), 2, "" ))) -> 2 | S7: =IF(AND($F7<(S$2+7),$F7>S$2),1, IF(AND($H7<S$2+7,$H7>S$2),3, IF(AND($F7<=S$2, $H7>=S$2), 2, "" ))) -> 2 | ... AQ7: =IF(AND($F7<(AQ$2+7),$F7>AQ$2),1, IF(AND($H7<AQ$2+7,$H7>AQ$2),3, IF(AND($F7<=AQ$2, $H7>=AQ$2), 2, "" )))
B8: Panel Procurement | C8: 43833 | D8: 5 | E8: 43840 | F8: 43833 | G8: 5 | H8: 43840 | L8: =IF(AND($F8<(L$2+7),$F8>L$2),1, IF(AND($H8<L$2+7,$H8>L$2),3, IF(AND($F8<=L$2, $H8>=L$2), 2, "" ))) -> 1 | M8: =IF(AND($F8<(M$2+7),$F8>M$2),1, IF(AND($H8<M$2+7,$H8>M$2),3, IF(AND($F8<=M$2, $H8>=M$2), 2, "" ))) -> 3 | N8: =IF(AND($F8<(N$2+7),$F8>N$2),1, IF(AND($H8<N$2+7,$H8>N$2),3, IF(AND($F8<=N$2, $H8>=N$2), 2, "" ))) | O8: =IF(AND($F8<(O$2+7),$F8>O$2),1, IF(AND($H8<O$2+7,$H8>O$2),3, IF(AND($F8<=O$2, $H8>=O$2), 2, "" ))) | P8: =IF(AND($F8<(P$2+7),$F8>P$2),1, IF(AND($H8<P$2+7,$H8>P$2),3, IF(AND($F8<=P$2, $H8>=P$2), 2, "" ))) | Q8: =IF(AND($F8<(Q$2+7),$F8>Q$2),1, IF(AND($H8<Q$2+7,$H8>Q$2),3, IF(AND($F8<=Q$2, $H8>=Q$2), 2, "" ))) | R8: =IF(AND($F8<(R$2+7),$F8>R$2),1, IF(AND($H8<R$2+7,$H8>R$2),3, IF(AND($F8<=R$2, $H8>=R$2), 2, "" ))) | S8: =IF(AND($F8<(S$2+7),$F8>S$2),1, IF(AND($H8<S$2+7,$H8>S$2),3, IF(AND($F8<=S$2, $H8>=S$2), 2, "" ))) | ... AQ8: =IF(AND($F8<(AQ$2+7),$F8>AQ$2),1, IF(AND($H8<AQ$2+7,$H8>AQ$2),3, IF(AND($F8<=AQ$2, $H8>=AQ$2), 2, "" )))
B9: Inverter Procurement | C9: 43941 | D9: 5 | E9: 43949 | F9: 43941 | G9: 5 | H9: 43949 | L9: =IF(AND($F9<(L$2+7),$F9>L$2),1, IF(AND($H9<L$2+7,$H9>L$2),3, IF(AND($F9<=L$2, $H9>=L$2), 2, "" ))) | M9: =IF(AND($F9<(M$2+7),$F9>M$2),1, IF(AND($H9<M$2+7,$H9>M$2),3, IF(AND($F9<=M$2, $H9>=M$2), 2, "" ))) | N9: =IF(AND($F9<(N$2+7),$F9>N$2),1, IF(AND($H9<N$2+7,$H9>N$2),3, IF(AND($F9<=N$2, $H9>=N$2), 2, "" ))) | O9: =IF(AND($F9<(O$2+7),$F9>O$2),1, IF(AND($H9<O$2+7,$H9>O$2),3, IF(AND($F9<=O$2, $H9>=O$2), 2, "" ))) | P9: =IF(AND($F9<(P$2+7),$F9>P$2),1, IF(AND($H9<P$2+7,$H9>P$2),3, IF(AND($F9<=P$2, $H9>=P$2), 2, "" ))) | Q9: =IF(AND($F9<(Q$2+7),$F9>Q$2),1, IF(AND($H9<Q$2+7,$H9>Q$2),3, IF(AND($F9<=Q$2, $H9>=Q$2), 2, "" ))) | R9: =IF(AND($F9<(R$2+7),$F9>R$2),1, IF(AND($H9<R$2+7,$H9>R$2),3, IF(AND($F9<=R$2, $H9>=R$2), 2, "" ))) | S9: =IF(AND($F9<(S$2+7),$F9>S$2),1, IF(AND($H9<S$2+7,$H9>S$2),3, IF(AND($F9<=S$2, $H9>=S$2), 2, "" ))) | ... AQ9: =IF(AND($F9<(AQ$2+7),$F9>AQ$2),1, IF(AND($H9<AQ$2+7,$H9>AQ$2),3, IF(AND($F9<=AQ$2, $H9>=AQ$2), 2, "" )))
B10: Mounting Structure Procurement | C10: 43941 | D10: 5 | E10: 43949 | F10: 43941 | G10: 5 | H10: 43949 | L10: =IF(AND($F10<(L$2+7),$F10>L$2),1, IF(AND($H10<L$2+7,$H10>L$2),3, IF(AND($F10<=L$2, $H10>=L$2), 2, "" ))) | M10: =IF(AND($F10<(M$2+7),$F10>M$2),1, IF(AND($H10<M$2+7,$H10>M$2),3, IF(AND($F10<=M$2, $H10>=M$2), 2, "" ))) | N10: =IF(AND($F10<(N$2+7),$F10>N$2),1, IF(AND($H10<N$2+7,$H10>N$2),3, IF(AND($F10<=N$2, $H10>=N$2), 2, "" ))) | O10: =IF(AND($F10<(O$2+7),$F10>O$2),1, IF(AND($H10<O$2+7,$H10>O$2),3, IF(AND($F10<=O$2, $H10>=O$2), 2, "" ))) | P10: =IF(AND($F10<(P$2+7),$F10>P$2),1, IF(AND($H10<P$2+7,$H10>P$2),3, IF(AND($F10<=P$2, $H10>=P$2), 2, "" ))) | Q10: =IF(AND($F10<(Q$2+7),$F10>Q$2),1, IF(AND($H10<Q$2+7,$H10>Q$2),3, IF(AND($F10<=Q$2, $H10>=Q$2), 2, "" ))) | R10: =IF(AND($F10<(R$2+7),$F10>R$2),1, IF(AND($H10<R$2+7,$H10>R$2),3, IF(AND($F10<=R$2, $H10>=R$2), 2, "" ))) | S10: =IF(AND($F10<(S$2+7),$F10>S$2),1, IF(AND($H10<S$2+7,$H10>S$2),3, IF(AND($F10<=S$2, $H10>=S$2), 2, "" ))) | ... AQ10: =IF(AND($F10<(AQ$2+7),$F10>AQ$2),1, IF(AND($H10<AQ$2+7,$H10>AQ$2),3, IF(AND($F10<=AQ$2, $H10>=AQ$2), 2, "" )))
B11: BOS Procurement | C11: 43941 | D11: 5 | E11: 43949 | F11: 43941 | G11: 5 | H11: 43949 | L11: =IF(AND($F11<(L$2+7),$F11>L$2),1, IF(AND($H11<L$2+7,$H11>L$2),3, IF(AND($F11<=L$2, $H11>=L$2), 2, "" ))) | M11: =IF(AND($F11<(M$2+7),$F11>M$2),1, IF(AND($H11<M$2+7,$H11>M$2),3, IF(AND($F11<=M$2, $H11>=M$2), 2, "" ))) | N11: =IF(AND($F11<(N$2+7),$F11>N$2),1, IF(AND($H11<N$2+7,$H11>N$2),3, IF(AND($F11<=N$2, $H11>=N$2), 2, "" ))) | O11: =IF(AND($F11<(O$2+7),$F11>O$2),1, IF(AND($H11<O$2+7,$H11>O$2),3, IF(AND($F11<=O$2, $H11>=O$2), 2, "" ))) | P11: =IF(AND($F11<(P$2+7),$F11>P$2),1, IF(AND($H11<P$2+7,$H11>P$2),3, IF(AND($F11<=P$2, $H11>=P$2), 2, "" ))) | Q11: =IF(AND($F11<(Q$2+7),$F11>Q$2),1, IF(AND($H11<Q$2+7,$H11>Q$2),3, IF(AND($F11<=Q$2, $H11>=Q$2), 2, "" ))) | R11: =IF(AND($F11<(R$2+7),$F11>R$2),1, IF(AND($H11<R$2+7,$H11>R$2),3, IF(AND($F11<=R$2, $H11>=R$2), 2, "" ))) | S11: =IF(AND($F11<(S$2+7),$F11>S$2),1, IF(AND($H11<S$2+7,$H11>S$2),3, IF(AND($F11<=S$2, $H11>=S$2), 2, "" ))) | ... AQ11: =IF(AND($F11<(AQ$2+7),$F11>AQ$2),1, IF(AND($H11<AQ$2+7,$H11>AQ$2),3, IF(AND($F11<=AQ$2, $H11>=AQ$2), 2, "" )))
A12: 5 | B12: Internal Project Kick off | C12: 43936 | D12: 5 | E12: 43943 | F12: 43936 | G12: 5 | H12: 43943
A13: 6 | B13: Client Project Kick-off | C13: 43963 | D13: 5 | E13: 43970 | F13: 43963 | G13: 5 | H13: 43970 | L13: =IF(AND($F13<(L$2+7),$F13>L$2),1, IF(AND($H13<L$2+7,$H13>L$2),3, IF(AND($F13<=L$2, $H13>=L$2), 2, "" ))) | M13: =IF(AND($F13<(M$2+7),$F13>M$2),1, IF(AND($H13<M$2+7,$H13>M$2),3, IF(AND($F13<=M$2, $H13>=M$2), 2, "" ))) | N13: =IF(AND($F13<(N$2+7),$F13>N$2),1, IF(AND($H13<N$2+7,$H13>N$2),3, IF(AND($F13<=N$2, $H13>=N$2), 2, "" ))) | O13: =IF(AND($F13<(O$2+7),$F13>O$2),1, IF(AND($H13<O$2+7,$H13>O$2),3, IF(AND($F13<=O$2, $H13>=O$2), 2, "" ))) | P13: =IF(AND($F13<(P$2+7),$F13>P$2),1, IF(AND($H13<P$2+7,$H13>P$2),3, IF(AND($F13<=P$2, $H13>=P$2), 2, "" ))) | Q13: =IF(AND($F13<(Q$2+7),$F13>Q$2),1, IF(AND($H13<Q$2+7,$H13>Q$2),3, IF(AND($F13<=Q$2, $H13>=Q$2), 2, "" ))) | R13: =IF(AND($F13<(R$2+7),$F13>R$2),1, IF(AND($H13<R$2+7,$H13>R$2),3, IF(AND($F13<=R$2, $H13>=R$2), 2, "" ))) | S13: =IF(AND($F13<(S$2+7),$F13>S$2),1, IF(AND($H13<S$2+7,$H13>S$2),3, IF(AND($F13<=S$2, $H13>=S$2), 2, "" ))) | ... AQ13: =IF(AND($F13<(AQ$2+7),$F13>AQ$2),1, IF(AND($H13<AQ$2+7,$H13>AQ$2),3, IF(AND($F13<=AQ$2, $H13>=AQ$2), 2, "" )))
A14: 7 | B14: Equipment Delivery | C14: 43983 | D14: 9 | E14: 43994 | F14: 43983 | G14: 9 | H14: 43994 | L14: =IF(AND($F14<(L$2+7),$F14>L$2),1, IF(AND($H14<L$2+7,$H14>L$2),3, IF(AND($F14<=L$2, $H14>=L$2), 2, "" ))) | M14: =IF(AND($F14<(M$2+7),$F14>M$2),1, IF(AND($H14<M$2+7,$H14>M$2),3, IF(AND($F14<=M$2, $H14>=M$2), 2, "" ))) | N14: =IF(AND($F14<(N$2+7),$F14>N$2),1, IF(AND($H14<N$2+7,$H14>N$2),3, IF(AND($F14<=N$2, $H14>=N$2), 2, "" ))) | O14: =IF(AND($F14<(O$2+7),$F14>O$2),1, IF(AND($H14<O$2+7,$H14>O$2),3, IF(AND($F14<=O$2, $H14>=O$2), 2, "" ))) | P14: =IF(AND($F14<(P$2+7),$F14>P$2),1, IF(AND($H14<P$2+7,$H14>P$2),3, IF(AND($F14<=P$2, $H14>=P$2), 2, "" ))) | Q14: =IF(AND($F14<(Q$2+7),$F14>Q$2),1, IF(AND($H14<Q$2+7,$H14>Q$2),3, IF(AND($F14<=Q$2, $H14>=Q$2), 2, "" ))) | R14: =IF(AND($F14<(R$2+7),$F14>R$2),1, IF(AND($H14<R$2+7,$H14>R$2),3, IF(AND($F14<=R$2, $H14>=R$2), 2, "" ))) | S14: =IF(AND($F14<(S$2+7),$F14>S$2),1, IF(AND($H14<S$2+7,$H14>S$2),3, IF(AND($F14<=S$2, $H14>=S$2), 2, "" ))) | ... AQ14: =IF(AND($F14<(AQ$2+7),$F14>AQ$2),1, IF(AND($H14<AQ$2+7,$H14>AQ$2),3, IF(AND($F14<=AQ$2, $H14>=AQ$2), 2, "" )))
B15: Mounting Structure Delivery | C15: 43983 | D15: 2 | E15: 43985 | F15: 43983 | G15: 2 | H15: 43985
B16: Panel Delivery | C16: 43990 | D16: 2 | E16: 43992 | F16: 43990 | G16: 2 | H16: 43992 | L16: =IF(AND($F16<(L$2+7),$F16>L$2),1, IF(AND($H16<L$2+7,$H16>L$2),3, IF(AND($F16<=L$2, $H16>=L$2), 2, "" ))) | M16: =IF(AND($F16<(M$2+7),$F16>M$2),1, IF(AND($H16<M$2+7,$H16>M$2),3, IF(AND($F16<=M$2, $H16>=M$2), 2, "" ))) | N16: =IF(AND($F16<(N$2+7),$F16>N$2),1, IF(AND($H16<N$2+7,$H16>N$2),3, IF(AND($F16<=N$2, $H16>=N$2), 2, "" ))) | O16: =IF(AND($F16<(O$2+7),$F16>O$2),1, IF(AND($H16<O$2+7,$H16>O$2),3, IF(AND($F16<=O$2, $H16>=O$2), 2, "" ))) | P16: =IF(AND($F16<(P$2+7),$F16>P$2),1, IF(AND($H16<P$2+7,$H16>P$2),3, IF(AND($F16<=P$2, $H16>=P$2), 2, "" ))) | Q16: =IF(AND($F16<(Q$2+7),$F16>Q$2),1, IF(AND($H16<Q$2+7,$H16>Q$2),3, IF(AND($F16<=Q$2, $H16>=Q$2), 2, "" ))) | R16: =IF(AND($F16<(R$2+7),$F16>R$2),1, IF(AND($H16<R$2+7,$H16>R$2),3, IF(AND($F16<=R$2, $H16>=R$2), 2, "" ))) | S16: =IF(AND($F16<(S$2+7),$F16>S$2),1, IF(AND($H16<S$2+7,$H16>S$2),3, IF(AND($F16<=S$2, $H16>=S$2), 2, "" ))) | ... AQ16: =IF(AND($F16<(AQ$2+7),$F16>AQ$2),1, IF(AND($H16<AQ$2+7,$H16>AQ$2),3, IF(AND($F16<=AQ$2, $H16>=AQ$2), 2, "" )))
B17: Generator Delivery | C17: 43983 | D17: 2 | E17: 43985 | F17: 43983 | G17: 2 | H17: 43985
A18: B | B18: PAYMENT MILESTONE 2: DELIVERY OF PV PANELS | C18: 43992 | D18: 2 | E18: 43994 | F18: 43992 | G18: 2 | H18: 43994
B19: Inverter Delivery | C19: 43983 | D19: 2 | E19: 43985 | F19: 43983 | G19: 2 | H19: 43985 | L19: =IF(AND($F19<(L$2+7),$F19>L$2),1, IF(AND($H19<L$2+7,$H19>L$2),3, IF(AND($F19<=L$2, $H19>=L$2), 2, "" ))) | M19: =IF(AND($F19<(M$2+7),$F19>M$2),1, IF(AND($H19<M$2+7,$H19>M$2),3, IF(AND($F19<=M$2, $H19>=M$2), 2, "" ))) | N19: =IF(AND($F19<(N$2+7),$F19>N$2),1, IF(AND($H19<N$2+7,$H19>N$2),3, IF(AND($F19<=N$2, $H19>=N$2), 2, "" ))) | O19: =IF(AND($F19<(O$2+7),$F19>O$2),1, IF(AND($H19<O$2+7,$H19>O$2),3, IF(AND($F19<=O$2, $H19>=O$2), 2, "" ))) | P19: =IF(AND($F19<(P$2+7),$F19>P$2),1, IF(AND($H19<P$2+7,$H19>P$2),3, IF(AND($F19<=P$2, $H19>=P$2), 2, "" ))) | Q19: =IF(AND($F19<(Q$2+7),$F19>Q$2),1, IF(AND($H19<Q$2+7,$H19>Q$2),3, IF(AND($F19<=Q$2, $H19>=Q$2), 2, "" ))) | R19: =IF(AND($F19<(R$2+7),$F19>R$2),1, IF(AND($H19<R$2+7,$H19>R$2),3, IF(AND($F19<=R$2, $H19>=R$2), 2, "" ))) | S19: =IF(AND($F19<(S$2+7),$F19>S$2),1, IF(AND($H19<S$2+7,$H19>S$2),3, IF(AND($F19<=S$2, $H19>=S$2), 2, "" ))) | ... AQ19: =IF(AND($F19<(AQ$2+7),$F19>AQ$2),1, IF(AND($H19<AQ$2+7,$H19>AQ$2),3, IF(AND($F19<=AQ$2, $H19>=AQ$2), 2, "" )))
B20: BOS Delivery | C20: 43983 | D20: 1 | E20: 43984 | F20: 43983 | G20: 1 | H20: 43984 | L20: =IF(AND($F20<(L$2+7),$F20>L$2),1, IF(AND($H20<L$2+7,$H20>L$2),3, IF(AND($F20<=L$2, $H20>=L$2), 2, "" ))) | M20: =IF(AND($F20<(M$2+7),$F20>M$2),1, IF(AND($H20<M$2+7,$H20>M$2),3, IF(AND($F20<=M$2, $H20>=M$2), 2, "" ))) | N20: =IF(AND($F20<(N$2+7),$F20>N$2),1, IF(AND($H20<N$2+7,$H20>N$2),3, IF(AND($F20<=N$2, $H20>=N$2), 2, "" ))) | O20: =IF(AND($F20<(O$2+7),$F20>O$2),1, IF(AND($H20<O$2+7,$H20>O$2),3, IF(AND($F20<=O$2, $H20>=O$2), 2, "" ))) | P20: =IF(AND($F20<(P$2+7),$F20>P$2),1, IF(AND($H20<P$2+7,$H20>P$2),3, IF(AND($F20<=P$2, $H20>=P$2), 2, "" ))) | Q20: =IF(AND($F20<(Q$2+7),$F20>Q$2),1, IF(AND($H20<Q$2+7,$H20>Q$2),3, IF(AND($F20<=Q$2, $H20>=Q$2), 2, "" ))) | R20: =IF(AND($F20<(R$2+7),$F20>R$2),1, IF(AND($H20<R$2+7,$H20>R$2),3, IF(AND($F20<=R$2, $H20>=R$2), 2, "" ))) | S20: =IF(AND($F20<(S$2+7),$F20>S$2),1, IF(AND($H20<S$2+7,$H20>S$2),3, IF(AND($F20<=S$2, $H20>=S$2), 2, "" ))) | ... AQ20: =IF(AND($F20<(AQ$2+7),$F20>AQ$2),1, IF(AND($H20<AQ$2+7,$H20>AQ$2),3, IF(AND($F20<=AQ$2, $H20>=AQ$2), 2, "" )))
A21: C | B21: PAYMENT MILESTONE 3: DELIVERY OF INVERTERS AND BOS | C21: 43985 | D21: 2 | E21: 43987 | F21: 43985 | G21: 2 | H21: 43987
A22: 8 | B22: Installation | C22: 43990 | D22: 22 | E22: 44012 | F22: 43990 | G22: 22 | H22: 44012 | L22: =IF(AND($F22<(L$2+7),$F22>L$2),1, IF(AND($H22<L$2+7,$H22>L$2),3, IF(AND($F22<=L$2, $H22>=L$2), 2, "" ))) | M22: =IF(AND($F22<(M$2+7),$F22>M$2),1, IF(AND($H22<M$2+7,$H22>M$2),3, IF(AND($F22<=M$2, $H22>=M$2), 2, "" ))) | N22: =IF(AND($F22<(N$2+7),$F22>N$2),1, IF(AND($H22<N$2+7,$H22>N$2),3, IF(AND($F22<=N$2, $H22>=N$2), 2, "" ))) | O22: =IF(AND($F22<(O$2+7),$F22>O$2),1, IF(AND($H22<O$2+7,$H22>O$2),3, IF(AND($F22<=O$2, $H22>=O$2), 2, "" ))) | P22: =IF(AND($F22<(P$2+7),$F22>P$2),1, IF(AND($H22<P$2+7,$H22>P$2),3, IF(AND($F22<=P$2, $H22>=P$2), 2, "" ))) | Q22: =IF(AND($F22<(Q$2+7),$F22>Q$2),1, IF(AND($H22<Q$2+7,$H22>Q$2),3, IF(AND($F22<=Q$2, $H22>=Q$2), 2, "" ))) | R22: =IF(AND($F22<(R$2+7),$F22>R$2),1, IF(AND($H22<R$2+7,$H22>R$2),3, IF(AND($F22<=R$2, $H22>=R$2), 2, "" ))) | S22: =IF(AND($F22<(S$2+7),$F22>S$2),1, IF(AND($H22<S$2+7,$H22>S$2),3, IF(AND($F22<=S$2, $H22>=S$2), 2, "" ))) | ... AQ22: =IF(AND($F22<(AQ$2+7),$F22>AQ$2),1, IF(AND($H22<AQ$2+7,$H22>AQ$2),3, IF(AND($F22<=AQ$2, $H22>=AQ$2), 2, "" ))) -> 2
B23: Site Establishment | C23: 43990 | D23: 1 | E23: 43991 | F23: 43990 | G23: 1 | H23: 43991 | J23: Installation placed on hold due to Covid-19 case | L23: =IF(AND($F23<(L$2+7),$F23>L$2),1, IF(AND($H23<L$2+7,$H23>L$2),3, IF(AND($F23<=L$2, $H23>=L$2), 2, "" ))) | M23: =IF(AND($F23<(M$2+7),$F23>M$2),1, IF(AND($H23<M$2+7,$H23>M$2),3, IF(AND($F23<=M$2, $H23>=M$2), 2, "" ))) | N23: =IF(AND($F23<(N$2+7),$F23>N$2),1, IF(AND($H23<N$2+7,$H23>N$2),3, IF(AND($F23<=N$2, $H23>=N$2), 2, "" ))) | O23: =IF(AND($F23<(O$2+7),$F23>O$2),1, IF(AND($H23<O$2+7,$H23>O$2),3, IF(AND($F23<=O$2, $H23>=O$2), 2, "" ))) | P23: =IF(AND($F23<(P$2+7),$F23>P$2),1, IF(AND($H23<P$2+7,$H23>P$2),3, IF(AND($F23<=P$2, $H23>=P$2), 2, "" ))) | Q23: =IF(AND($F23<(Q$2+7),$F23>Q$2),1, IF(AND($H23<Q$2+7,$H23>Q$2),3, IF(AND($F23<=Q$2, $H23>=Q$2), 2, "" ))) | R23: =IF(AND($F23<(R$2+7),$F23>R$2),1, IF(AND($H23<R$2+7,$H23>R$2),3, IF(AND($F23<=R$2, $H23>=R$2), 2, "" ))) | S23: =IF(AND($F23<(S$2+7),$F23>S$2),1, IF(AND($H23<S$2+7,$H23>S$2),3, IF(AND($F23<=S$2, $H23>=S$2), 2, "" ))) | ... AQ23: =IF(AND($F23<(AQ$2+7),$F23>AQ$2),1, IF(AND($H23<AQ$2+7,$H23>AQ$2),3, IF(AND($F23<=AQ$2, $H23>=AQ$2), 2, "" )))
A24: 9 | B24: DC Works | C24: 43991 | D24: 16 | E24: 44012 | F24: 43991 | G24: 16 | H24: 44012 | L24: =IF(AND($F24<(L$2+7),$F24>L$2),1, IF(AND($H24<L$2+7,$H24>L$2),3, IF(AND($F24<=L$2, $H24>=L$2), 2, "" ))) | M24: =IF(AND($F24<(M$2+7),$F24>M$2),1, IF(AND($H24<M$2+7,$H24>M$2),3, IF(AND($F24<=M$2, $H24>=M$2), 2, "" ))) | N24: =IF(AND($F24<(N$2+7),$F24>N$2),1, IF(AND($H24<N$2+7,$H24>N$2),3, IF(AND($F24<=N$2, $H24>=N$2), 2, "" ))) | O24: =IF(AND($F24<(O$2+7),$F24>O$2),1, IF(AND($H24<O$2+7,$H24>O$2),3, IF(AND($F24<=O$2, $H24>=O$2), 2, "" ))) | P24: =IF(AND($F24<(P$2+7),$F24>P$2),1, IF(AND($H24<P$2+7,$H24>P$2),3, IF(AND($F24<=P$2, $H24>=P$2), 2, "" ))) | Q24: =IF(AND($F24<(Q$2+7),$F24>Q$2),1, IF(AND($H24<Q$2+7,$H24>Q$2),3, IF(AND($F24<=Q$2, $H24>=Q$2), 2, "" ))) | R24: =IF(AND($F24<(R$2+7),$F24>R$2),1, IF(AND($H24<R$2+7,$H24>R$2),3, IF(AND($F24<=R$2, $H24>=R$2), 2, "" ))) | S24: =IF(AND($F24<(S$2+7),$F24>S$2),1, IF(AND($H24<S$2+7,$H24>S$2),3, IF(AND($F24<=S$2, $H24>=S$2), 2, "" ))) | ... AQ24: =IF(AND($F24<(AQ$2+7),$F24>AQ$2),1, IF(AND($H24<AQ$2+7,$H24>AQ$2),3, IF(AND($F24<=AQ$2, $H24>=AQ$2), 2, "" ))) -> 2
B25: Mounting structure Installation | C25: 43991 | D25: 4 | E25: 43997 | F25: 43991 | G25: 4 | H25: 43997 | L25: =IF(AND($F25<(L$2+7),$F25>L$2),1, IF(AND($H25<L$2+7,$H25>L$2),3, IF(AND($F25<=L$2, $H25>=L$2), 2, "" ))) | M25: =IF(AND($F25<(M$2+7),$F25>M$2),1, IF(AND($H25<M$2+7,$H25>M$2),3, IF(AND($F25<=M$2, $H25>=M$2), 2, "" ))) | N25: =IF(AND($F25<(N$2+7),$F25>N$2),1, IF(AND($H25<N$2+7,$H25>N$2),3, IF(AND($F25<=N$2, $H25>=N$2), 2, "" ))) | O25: =IF(AND($F25<(O$2+7),$F25>O$2),1, IF(AND($H25<O$2+7,$H25>O$2),3, IF(AND($F25<=O$2, $H25>=O$2), 2, "" ))) | P25: =IF(AND($F25<(P$2+7),$F25>P$2),1, IF(AND($H25<P$2+7,$H25>P$2),3, IF(AND($F25<=P$2, $H25>=P$2), 2, "" ))) | Q25: =IF(AND($F25<(Q$2+7),$F25>Q$2),1, IF(AND($H25<Q$2+7,$H25>Q$2),3, IF(AND($F25<=Q$2, $H25>=Q$2), 2, "" ))) | R25: =IF(AND($F25<(R$2+7),$F25>R$2),1, IF(AND($H25<R$2+7,$H25>R$2),3, IF(AND($F25<=R$2, $H25>=R$2), 2, "" ))) | S25: =IF(AND($F25<(S$2+7),$F25>S$2),1, IF(AND($H25<S$2+7,$H25>S$2),3, IF(AND($F25<=S$2, $H25>=S$2), 2, "" ))) | ... AQ25: =IF(AND($F25<(AQ$2+7),$F25>AQ$2),1, IF(AND($H25<AQ$2+7,$H25>AQ$2),3, IF(AND($F25<=AQ$2, $H25>=AQ$2), 2, "" )))
B26: Cable tray Installation | C26: 43997 | D26: 3 | E26: 44004 | F26: 43997 | G26: 3 | H26: 44004 | L26: =IF(AND($F26<(L$2+7),$F26>L$2),1, IF(AND($H26<L$2+7,$H26>L$2),3, IF(AND($F26<=L$2, $H26>=L$2), 2, "" ))) | M26: =IF(AND($F26<(M$2+7),$F26>M$2),1, IF(AND($H26<M$2+7,$H26>M$2),3, IF(AND($F26<=M$2, $H26>=M$2), 2, "" ))) | N26: =IF(AND($F26<(N$2+7),$F26>N$2),1, IF(AND($H26<N$2+7,$H26>N$2),3, IF(AND($F26<=N$2, $H26>=N$2), 2, "" ))) | O26: =IF(AND($F26<(O$2+7),$F26>O$2),1, IF(AND($H26<O$2+7,$H26>O$2),3, IF(AND($F26<=O$2, $H26>=O$2), 2, "" ))) | P26: =IF(AND($F26<(P$2+7),$F26>P$2),1, IF(AND($H26<P$2+7,$H26>P$2),3, IF(AND($F26<=P$2, $H26>=P$2), 2, "" ))) | Q26: =IF(AND($F26<(Q$2+7),$F26>Q$2),1, IF(AND($H26<Q$2+7,$H26>Q$2),3, IF(AND($F26<=Q$2, $H26>=Q$2), 2, "" ))) | R26: =IF(AND($F26<(R$2+7),$F26>R$2),1, IF(AND($H26<R$2+7,$H26>R$2),3, IF(AND($F26<=R$2, $H26>=R$2), 2, "" ))) | S26: =IF(AND($F26<(S$2+7),$F26>S$2),1, IF(AND($H26<S$2+7,$H26>S$2),3, IF(AND($F26<=S$2, $H26>=S$2), 2, "" ))) | ... AQ26: =IF(AND($F26<(AQ$2+7),$F26>AQ$2),1, IF(AND($H26<AQ$2+7,$H26>AQ$2),3, IF(AND($F26<=AQ$2, $H26>=AQ$2), 2, "" )))
B27: DC Cable Installation | C27: 44004 | D27: 2 | E27: 44006 | F27: 44004 | G27: 2 | H27: 44006 | L27: =IF(AND($F27<(L$2+7),$F27>L$2),1, IF(AND($H27<L$2+7,$H27>L$2),3, IF(AND($F27<=L$2, $H27>=L$2), 2, "" ))) | M27: =IF(AND($F27<(M$2+7),$F27>M$2),1, IF(AND($H27<M$2+7,$H27>M$2),3, IF(AND($F27<=M$2, $H27>=M$2), 2, "" ))) | N27: =IF(AND($F27<(N$2+7),$F27>N$2),1, IF(AND($H27<N$2+7,$H27>N$2),3, IF(AND($F27<=N$2, $H27>=N$2), 2, "" ))) | O27: =IF(AND($F27<(O$2+7),$F27>O$2),1, IF(AND($H27<O$2+7,$H27>O$2),3, IF(AND($F27<=O$2, $H27>=O$2), 2, "" ))) | P27: =IF(AND($F27<(P$2+7),$F27>P$2),1, IF(AND($H27<P$2+7,$H27>P$2),3, IF(AND($F27<=P$2, $H27>=P$2), 2, "" ))) | Q27: =IF(AND($F27<(Q$2+7),$F27>Q$2),1, IF(AND($H27<Q$2+7,$H27>Q$2),3, IF(AND($F27<=Q$2, $H27>=Q$2), 2, "" ))) | R27: =IF(AND($F27<(R$2+7),$F27>R$2),1, IF(AND($H27<R$2+7,$H27>R$2),3, IF(AND($F27<=R$2, $H27>=R$2), 2, "" ))) | S27: =IF(AND($F27<(S$2+7),$F27>S$2),1, IF(AND($H27<S$2+7,$H27>S$2),3, IF(AND($F27<=S$2, $H27>=S$2), 2, "" ))) | ... AQ27: =IF(AND($F27<(AQ$2+7),$F27>AQ$2),1, IF(AND($H27<AQ$2+7,$H27>AQ$2),3, IF(AND($F27<=AQ$2, $H27>=AQ$2), 2, "" )))
B28: Module Installation | C28: 44006 | D28: 4 | E28: 44012 | F28: 44006 | G28: 4 | H28: 44012 | L28: =IF(AND($F28<(L$2+7),$F28>L$2),1, IF(AND($H28<L$2+7,$H28>L$2),3, IF(AND($F28<=L$2, $H28>=L$2), 2, "" ))) | M28: =IF(AND($F28<(M$2+7),$F28>M$2),1, IF(AND($H28<M$2+7,$H28>M$2),3, IF(AND($F28<=M$2, $H28>=M$2), 2, "" ))) | N28: =IF(AND($F28<(N$2+7),$F28>N$2),1, IF(AND($H28<N$2+7,$H28>N$2),3, IF(AND($F28<=N$2, $H28>=N$2), 2, "" ))) | O28: =IF(AND($F28<(O$2+7),$F28>O$2),1, IF(AND($H28<O$2+7,$H28>O$2),3, IF(AND($F28<=O$2, $H28>=O$2), 2, "" ))) | P28: =IF(AND($F28<(P$2+7),$F28>P$2),1, IF(AND($H28<P$2+7,$H28>P$2),3, IF(AND($F28<=P$2, $H28>=P$2), 2, "" ))) | Q28: =IF(AND($F28<(Q$2+7),$F28>Q$2),1, IF(AND($H28<Q$2+7,$H28>Q$2),3, IF(AND($F28<=Q$2, $H28>=Q$2), 2, "" ))) | R28: =IF(AND($F28<(R$2+7),$F28>R$2),1, IF(AND($H28<R$2+7,$H28>R$2),3, IF(AND($F28<=R$2, $H28>=R$2), 2, "" ))) | S28: =IF(AND($F28<(S$2+7),$F28>S$2),1, IF(AND($H28<S$2+7,$H28>S$2),3, IF(AND($F28<=S$2, $H28>=S$2), 2, "" ))) | ... AQ28: =IF(AND($F28<(AQ$2+7),$F28>AQ$2),1, IF(AND($H28<AQ$2+7,$H28>AQ$2),3, IF(AND($F28<=AQ$2, $H28>=AQ$2), 2, "" ))) -> 2
B29: Earth Cable Installation | C29: 44004 | D29: 1 | E29: 44005 | F29: 44004 | G29: 1 | H29: 44005 | L29: =IF(AND($F29<(L$2+7),$F29>L$2),1, IF(AND($H29<L$2+7,$H29>L$2),3, IF(AND($F29<=L$2, $H29>=L$2), 2, "" ))) | M29: =IF(AND($F29<(M$2+7),$F29>M$2),1, IF(AND($H29<M$2+7,$H29>M$2),3, IF(AND($F29<=M$2, $H29>=M$2), 2, "" ))) | N29: =IF(AND($F29<(N$2+7),$F29>N$2),1, IF(AND($H29<N$2+7,$H29>N$2),3, IF(AND($F29<=N$2, $H29>=N$2), 2, "" ))) | O29: =IF(AND($F29<(O$2+7),$F29>O$2),1, IF(AND($H29<O$2+7,$H29>O$2),3, IF(AND($F29<=O$2, $H29>=O$2), 2, "" ))) | P29: =IF(AND($F29<(P$2+7),$F29>P$2),1, IF(AND($H29<P$2+7,$H29>P$2),3, IF(AND($F29<=P$2, $H29>=P$2), 2, "" ))) | Q29: =IF(AND($F29<(Q$2+7),$F29>Q$2),1, IF(AND($H29<Q$2+7,$H29>Q$2),3, IF(AND($F29<=Q$2, $H29>=Q$2), 2, "" ))) | R29: =IF(AND($F29<(R$2+7),$F29>R$2),1, IF(AND($H29<R$2+7,$H29>R$2),3, IF(AND($F29<=R$2, $H29>=R$2), 2, "" ))) | S29: =IF(AND($F29<(S$2+7),$F29>S$2),1, IF(AND($H29<S$2+7,$H29>S$2),3, IF(AND($F29<=S$2, $H29>=S$2), 2, "" ))) | ... AQ29: =IF(AND($F29<(AQ$2+7),$F29>AQ$2),1, IF(AND($H29<AQ$2+7,$H29>AQ$2),3, IF(AND($F29<=AQ$2, $H29>=AQ$2), 2, "" )))
A30: 10 | B30: AC Works | C30: 43991 | D30: 8 | E30: 44000 | F30: 43991 | G30: 8 | H30: 44000
B31: Inverters Installation | C31: 43991 | D31: 2 | E31: 43993 | F31: 43991 | G31: 2 | H31: 43993 | L31: =IF(AND($F31<(L$2+7),$F31>L$2),1, IF(AND($H31<L$2+7,$H31>L$2),3, IF(AND($F31<=L$2, $H31>=L$2), 2, "" ))) | M31: =IF(AND($F31<(M$2+7),$F31>M$2),1, IF(AND($H31<M$2+7,$H31>M$2),3, IF(AND($F31<=M$2, $H31>=M$2), 2, "" ))) | N31: =IF(AND($F31<(N$2+7),$F31>N$2),1, IF(AND($H31<N$2+7,$H31>N$2),3, IF(AND($F31<=N$2, $H31>=N$2), 2, "" ))) | O31: =IF(AND($F31<(O$2+7),$F31>O$2),1, IF(AND($H31<O$2+7,$H31>O$2),3, IF(AND($F31<=O$2, $H31>=O$2), 2, "" ))) | P31: =IF(AND($F31<(P$2+7),$F31>P$2),1, IF(AND($H31<P$2+7,$H31>P$2),3, IF(AND($F31<=P$2, $H31>=P$2), 2, "" ))) | Q31: =IF(AND($F31<(Q$2+7),$F31>Q$2),1, IF(AND($H31<Q$2+7,$H31>Q$2),3, IF(AND($F31<=Q$2, $H31>=Q$2), 2, "" ))) | R31: =IF(AND($F31<(R$2+7),$F31>R$2),1, IF(AND($H31<R$2+7,$H31>R$2),3, IF(AND($F31<=R$2, $H31>=R$2), 2, "" ))) | S31: =IF(AND($F31<(S$2+7),$F31>S$2),1, IF(AND($H31<S$2+7,$H31>S$2),3, IF(AND($F31<=S$2, $H31>=S$2), 2, "" ))) | ... AQ31: =IF(AND($F31<(AQ$2+7),$F31>AQ$2),1, IF(AND($H31<AQ$2+7,$H31>AQ$2),3, IF(AND($F31<=AQ$2, $H31>=AQ$2), 2, "" )))
B32: AC BOS Installation | C32: 43993 | D32: 3 | E32: 44000 | F32: 43993 | G32: 3 | H32: 44000 | L32: =IF(AND($F32<(L$2+7),$F32>L$2),1, IF(AND($H32<L$2+7,$H32>L$2),3, IF(AND($F32<=L$2, $H32>=L$2), 2, "" ))) | M32: =IF(AND($F32<(M$2+7),$F32>M$2),1, IF(AND($H32<M$2+7,$H32>M$2),3, IF(AND($F32<=M$2, $H32>=M$2), 2, "" ))) | N32: =IF(AND($F32<(N$2+7),$F32>N$2),1, IF(AND($H32<N$2+7,$H32>N$2),3, IF(AND($F32<=N$2, $H32>=N$2), 2, "" ))) | O32: =IF(AND($F32<(O$2+7),$F32>O$2),1, IF(AND($H32<O$2+7,$H32>O$2),3, IF(AND($F32<=O$2, $H32>=O$2), 2, "" ))) | P32: =IF(AND($F32<(P$2+7),$F32>P$2),1, IF(AND($H32<P$2+7,$H32>P$2),3, IF(AND($F32<=P$2, $H32>=P$2), 2, "" ))) | Q32: =IF(AND($F32<(Q$2+7),$F32>Q$2),1, IF(AND($H32<Q$2+7,$H32>Q$2),3, IF(AND($F32<=Q$2, $H32>=Q$2), 2, "" ))) | R32: =IF(AND($F32<(R$2+7),$F32>R$2),1, IF(AND($H32<R$2+7,$H32>R$2),3, IF(AND($F32<=R$2, $H32>=R$2), 2, "" ))) | S32: =IF(AND($F32<(S$2+7),$F32>S$2),1, IF(AND($H32<S$2+7,$H32>S$2),3, IF(AND($F32<=S$2, $H32>=S$2), 2, "" ))) | ... AQ32: =IF(AND($F32<(AQ$2+7),$F32>AQ$2),1, IF(AND($H32<AQ$2+7,$H32>AQ$2),3, IF(AND($F32<=AQ$2, $H32>=AQ$2), 2, "" )))
B33: AC Cable/Tie-In | C33: 43992 | D33: 3 | E33: 43997 | F33: 43992 | G33: 3 | H33: 43997 | L33: =IF(AND($F33<(L$2+7),$F33>L$2),1, IF(AND($H33<L$2+7,$H33>L$2),3, IF(AND($F33<=L$2, $H33>=L$2), 2, "" ))) | M33: =IF(AND($F33<(M$2+7),$F33>M$2),1, IF(AND($H33<M$2+7,$H33>M$2),3, IF(AND($F33<=M$2, $H33>=M$2), 2, "" ))) | N33: =IF(AND($F33<(N$2+7),$F33>N$2),1, IF(AND($H33<N$2+7,$H33>N$2),3, IF(AND($F33<=N$2, $H33>=N$2), 2, "" ))) | O33: =IF(AND($F33<(O$2+7),$F33>O$2),1, IF(AND($H33<O$2+7,$H33>O$2),3, IF(AND($F33<=O$2, $H33>=O$2), 2, "" ))) | P33: =IF(AND($F33<(P$2+7),$F33>P$2),1, IF(AND($H33<P$2+7,$H33>P$2),3, IF(AND($F33<=P$2, $H33>=P$2), 2, "" ))) | Q33: =IF(AND($F33<(Q$2+7),$F33>Q$2),1, IF(AND($H33<Q$2+7,$H33>Q$2),3, IF(AND($F33<=Q$2, $H33>=Q$2), 2, "" ))) | R33: =IF(AND($F33<(R$2+7),$F33>R$2),1, IF(AND($H33<R$2+7,$H33>R$2),3, IF(AND($F33<=R$2, $H33>=R$2), 2, "" ))) | S33: =IF(AND($F33<(S$2+7),$F33>S$2),1, IF(AND($H33<S$2+7,$H33>S$2),3, IF(AND($F33<=S$2, $H33>=S$2), 2, "" ))) | ... AQ33: =IF(AND($F33<(AQ$2+7),$F33>AQ$2),1, IF(AND($H33<AQ$2+7,$H33>AQ$2),3, IF(AND($F33<=AQ$2, $H33>=AQ$2), 2, "" )))
B34: Monitoring Platform Installation | C34: 43997 | D34: 1 | E34: 44000 | F34: 43997 | G34: 1 | H34: 44000
A35: 11 | B35: Completion | C35: 44000 | D35: 14 | E35: 44014 | F35: 44000 | G35: 14 | H35: 44014 | L35: =IF(AND($F35<(L$2+7),$F35>L$2),1, IF(AND($H35<L$2+7,$H35>L$2),3, IF(AND($F35<=L$2, $H35>=L$2), 2, "" ))) | M35: =IF(AND($F35<(M$2+7),$F35>M$2),1, IF(AND($H35<M$2+7,$H35>M$2),3, IF(AND($F35<=M$2, $H35>=M$2), 2, "" ))) | N35: =IF(AND($F35<(N$2+7),$F35>N$2),1, IF(AND($H35<N$2+7,$H35>N$2),3, IF(AND($F35<=N$2, $H35>=N$2), 2, "" ))) | O35: =IF(AND($F35<(O$2+7),$F35>O$2),1, IF(AND($H35<O$2+7,$H35>O$2),3, IF(AND($F35<=O$2, $H35>=O$2), 2, "" ))) | P35: =IF(AND($F35<(P$2+7),$F35>P$2),1, IF(AND($H35<P$2+7,$H35>P$2),3, IF(AND($F35<=P$2, $H35>=P$2), 2, "" ))) | Q35: =IF(AND($F35<(Q$2+7),$F35>Q$2),1, IF(AND($H35<Q$2+7,$H35>Q$2),3, IF(AND($F35<=Q$2, $H35>=Q$2), 2, "" ))) | R35: =IF(AND($F35<(R$2+7),$F35>R$2),1, IF(AND($H35<R$2+7,$H35>R$2),3, IF(AND($F35<=R$2, $H35>=R$2), 2, "" ))) | S35: =IF(AND($F35<(S$2+7),$F35>S$2),1, IF(AND($H35<S$2+7,$H35>S$2),3, IF(AND($F35<=S$2, $H35>=S$2), 2, "" ))) | ... AQ35: =IF(AND($F35<(AQ$2+7),$F35>AQ$2),1, IF(AND($H35<AQ$2+7,$H35>AQ$2),3, IF(AND($F35<=AQ$2, $H35>=AQ$2), 2, "" ))) -> 3
B36: DC Works | C36: 44012 | D36: 2 | E36: 44014 | F36: 44012 | G36: 2 | H36: 44014 | L36: =IF(AND($F36<(L$2+7),$F36>L$2),1, IF(AND($H36<L$2+7,$H36>L$2),3, IF(AND($F36<=L$2, $H36>=L$2), 2, "" ))) | M36: =IF(AND($F36<(M$2+7),$F36>M$2),1, IF(AND($H36<M$2+7,$H36>M$2),3, IF(AND($F36<=M$2, $H36>=M$2), 2, "" ))) | N36: =IF(AND($F36<(N$2+7),$F36>N$2),1, IF(AND($H36<N$2+7,$H36>N$2),3, IF(AND($F36<=N$2, $H36>=N$2), 2, "" ))) | O36: =IF(AND($F36<(O$2+7),$F36>O$2),1, IF(AND($H36<O$2+7,$H36>O$2),3, IF(AND($F36<=O$2, $H36>=O$2), 2, "" ))) | P36: =IF(AND($F36<(P$2+7),$F36>P$2),1, IF(AND($H36<P$2+7,$H36>P$2),3, IF(AND($F36<=P$2, $H36>=P$2), 2, "" ))) | Q36: =IF(AND($F36<(Q$2+7),$F36>Q$2),1, IF(AND($H36<Q$2+7,$H36>Q$2),3, IF(AND($F36<=Q$2, $H36>=Q$2), 2, "" ))) | R36: =IF(AND($F36<(R$2+7),$F36>R$2),1, IF(AND($H36<R$2+7,$H36>R$2),3, IF(AND($F36<=R$2, $H36>=R$2), 2, "" ))) | S36: =IF(AND($F36<(S$2+7),$F36>S$2),1, IF(AND($H36<S$2+7,$H36>S$2),3, IF(AND($F36<=S$2, $H36>=S$2), 2, "" ))) | ... AQ36: =IF(AND($F36<(AQ$2+7),$F36>AQ$2),1, IF(AND($H36<AQ$2+7,$H36>AQ$2),3, IF(AND($F36<=AQ$2, $H36>=AQ$2), 2, "" ))) -> 3
B37: AC Works | C37: 44000 | D37: 2 | E37: 44004 | F37: 44000 | G37: 2 | H37: 44004 | L37: =IF(AND($F37<(L$2+7),$F37>L$2),1, IF(AND($H37<L$2+7,$H37>L$2),3, IF(AND($F37<=L$2, $H37>=L$2), 2, "" ))) | M37: =IF(AND($F37<(M$2+7),$F37>M$2),1, IF(AND($H37<M$2+7,$H37>M$2),3, IF(AND($F37<=M$2, $H37>=M$2), 2, "" ))) | N37: =IF(AND($F37<(N$2+7),$F37>N$2),1, IF(AND($H37<N$2+7,$H37>N$2),3, IF(AND($F37<=N$2, $H37>=N$2), 2, "" ))) | O37: =IF(AND($F37<(O$2+7),$F37>O$2),1, IF(AND($H37<O$2+7,$H37>O$2),3, IF(AND($F37<=O$2, $H37>=O$2), 2, "" ))) | P37: =IF(AND($F37<(P$2+7),$F37>P$2),1, IF(AND($H37<P$2+7,$H37>P$2),3, IF(AND($F37<=P$2, $H37>=P$2), 2, "" ))) | Q37: =IF(AND($F37<(Q$2+7),$F37>Q$2),1, IF(AND($H37<Q$2+7,$H37>Q$2),3, IF(AND($F37<=Q$2, $H37>=Q$2), 2, "" ))) | R37: =IF(AND($F37<(R$2+7),$F37>R$2),1, IF(AND($H37<R$2+7,$H37>R$2),3, IF(AND($F37<=R$2, $H37>=R$2), 2, "" ))) | S37: =IF(AND($F37<(S$2+7),$F37>S$2),1, IF(AND($H37<S$2+7,$H37>S$2),3, IF(AND($F37<=S$2, $H37>=S$2), 2, "" ))) | ... AQ37: =IF(AND($F37<(AQ$2+7),$F37>AQ$2),1, IF(AND($H37<AQ$2+7,$H37>AQ$2),3, IF(AND($F37<=AQ$2, $H37>=AQ$2), 2, "" )))
A38: D | B38: PAYMENT MILESTONE 4: PRACTICAL COMPLETION | C38: 44012 | D38: 1 | E38: 44013 | F38: 44012 | G38: 1 | H38: 44013 | L38: =IF(AND($F38<(L$2+7),$F38>L$2),1, IF(AND($H38<L$2+7,$H38>L$2),3, IF(AND($F38<=L$2, $H38>=L$2), 2, "" ))) | M38: =IF(AND($F38<(M$2+7),$F38>M$2),1, IF(AND($H38<M$2+7,$H38>M$2),3, IF(AND($F38<=M$2, $H38>=M$2), 2, "" ))) | N38: =IF(AND($F38<(N$2+7),$F38>N$2),1, IF(AND($H38<N$2+7,$H38>N$2),3, IF(AND($F38<=N$2, $H38>=N$2), 2, "" ))) | O38: =IF(AND($F38<(O$2+7),$F38>O$2),1, IF(AND($H38<O$2+7,$H38>O$2),3, IF(AND($F38<=O$2, $H38>=O$2), 2, "" ))) | P38: =IF(AND($F38<(P$2+7),$F38>P$2),1, IF(AND($H38<P$2+7,$H38>P$2),3, IF(AND($F38<=P$2, $H38>=P$2), 2, "" ))) | Q38: =IF(AND($F38<(Q$2+7),$F38>Q$2),1, IF(AND($H38<Q$2+7,$H38>Q$2),3, IF(AND($F38<=Q$2, $H38>=Q$2), 2, "" ))) | R38: =IF(AND($F38<(R$2+7),$F38>R$2),1, IF(AND($H38<R$2+7,$H38>R$2),3, IF(AND($F38<=R$2, $H38>=R$2), 2, "" ))) | S38: =IF(AND($F38<(S$2+7),$F38>S$2),1, IF(AND($H38<S$2+7,$H38>S$2),3, IF(AND($F38<=S$2, $H38>=S$2), 2, "" ))) | ... AQ38: =IF(AND($F38<(AQ$2+7),$F38>AQ$2),1, IF(AND($H38<AQ$2+7,$H38>AQ$2),3, IF(AND($F38<=AQ$2, $H38>=AQ$2), 2, "" ))) -> 3
A39: 12 | B39: Commissioning | C39: 43997 | D39: 22 | E39: 44019 | F39: 43997 | G39: 22 | H39: 44019 | L39: =IF(AND($F39<(L$2+7),$F39>L$2),1, IF(AND($H39<L$2+7,$H39>L$2),3, IF(AND($F39<=L$2, $H39>=L$2), 2, "" ))) | M39: =IF(AND($F39<(M$2+7),$F39>M$2),1, IF(AND($H39<M$2+7,$H39>M$2),3, IF(AND($F39<=M$2, $H39>=M$2), 2, "" ))) | N39: =IF(AND($F39<(N$2+7),$F39>N$2),1, IF(AND($H39<N$2+7,$H39>N$2),3, IF(AND($F39<=N$2, $H39>=N$2), 2, "" ))) | O39: =IF(AND($F39<(O$2+7),$F39>O$2),1, IF(AND($H39<O$2+7,$H39>O$2),3, IF(AND($F39<=O$2, $H39>=O$2), 2, "" ))) | P39: =IF(AND($F39<(P$2+7),$F39>P$2),1, IF(AND($H39<P$2+7,$H39>P$2),3, IF(AND($F39<=P$2, $H39>=P$2), 2, "" ))) | Q39: =IF(AND($F39<(Q$2+7),$F39>Q$2),1, IF(AND($H39<Q$2+7,$H39>Q$2),3, IF(AND($F39<=Q$2, $H39>=Q$2), 2, "" ))) | R39: =IF(AND($F39<(R$2+7),$F39>R$2),1, IF(AND($H39<R$2+7,$H39>R$2),3, IF(AND($F39<=R$2, $H39>=R$2), 2, "" ))) | S39: =IF(AND($F39<(S$2+7),$F39>S$2),1, IF(AND($H39<S$2+7,$H39>S$2),3, IF(AND($F39<=S$2, $H39>=S$2), 2, "" ))) | ... AQ39: =IF(AND($F39<(AQ$2+7),$F39>AQ$2),1, IF(AND($H39<AQ$2+7,$H39>AQ$2),3, IF(AND($F39<=AQ$2, $H39>=AQ$2), 2, "" ))) -> 2
B40: Snag List | C40: 44014 | D40: 3 | E40: 44019 | F40: 44014 | G40: 3 | H40: 44019
B41: Pre-Commissioning Checks | C41: 44010 | D41: 2 | E41: 44012 | F41: 44010 | G41: 2 | H41: 44012
B42: Issue CoC | C42: 43997 | D42: 2 | E42: 44001 | F42: 43997 | G42: 2 | H42: 44001 | L42: =IF(AND($F42<(L$2+7),$F42>L$2),1, IF(AND($H42<L$2+7,$H42>L$2),3, IF(AND($F42<=L$2, $H42>=L$2), 2, "" ))) | M42: =IF(AND($F42<(M$2+7),$F42>M$2),1, IF(AND($H42<M$2+7,$H42>M$2),3, IF(AND($F42<=M$2, $H42>=M$2), 2, "" ))) | N42: =IF(AND($F42<(N$2+7),$F42>N$2),1, IF(AND($H42<N$2+7,$H42>N$2),3, IF(AND($F42<=N$2, $H42>=N$2), 2, "" ))) | O42: =IF(AND($F42<(O$2+7),$F42>O$2),1, IF(AND($H42<O$2+7,$H42>O$2),3, IF(AND($F42<=O$2, $H42>=O$2), 2, "" ))) | P42: =IF(AND($F42<(P$2+7),$F42>P$2),1, IF(AND($H42<P$2+7,$H42>P$2),3, IF(AND($F42<=P$2, $H42>=P$2), 2, "" ))) | Q42: =IF(AND($F42<(Q$2+7),$F42>Q$2),1, IF(AND($H42<Q$2+7,$H42>Q$2),3, IF(AND($F42<=Q$2, $H42>=Q$2), 2, "" ))) | R42: =IF(AND($F42<(R$2+7),$F42>R$2),1, IF(AND($H42<R$2+7,$H42>R$2),3, IF(AND($F42<=R$2, $H42>=R$2), 2, "" ))) | S42: =IF(AND($F42<(S$2+7),$F42>S$2),1, IF(AND($H42<S$2+7,$H42>S$2),3, IF(AND($F42<=S$2, $H42>=S$2), 2, "" ))) | ... AQ42: =IF(AND($F42<(AQ$2+7),$F42>AQ$2),1, IF(AND($H42<AQ$2+7,$H42>AQ$2),3, IF(AND($F42<=AQ$2, $H42>=AQ$2), 2, "" )))
B43: Cold Commissioning | C43: 44012 | D43: 1 | E43: 44013 | F43: 44012 | G43: 1 | H43: 44013 | L43: =IF(AND($F43<(L$2+7),$F43>L$2),1, IF(AND($H43<L$2+7,$H43>L$2),3, IF(AND($F43<=L$2, $H43>=L$2), 2, "" ))) | M43: =IF(AND($F43<(M$2+7),$F43>M$2),1, IF(AND($H43<M$2+7,$H43>M$2),3, IF(AND($F43<=M$2, $H43>=M$2), 2, "" ))) | N43: =IF(AND($F43<(N$2+7),$F43>N$2),1, IF(AND($H43<N$2+7,$H43>N$2),3, IF(AND($F43<=N$2, $H43>=N$2), 2, "" ))) | O43: =IF(AND($F43<(O$2+7),$F43>O$2),1, IF(AND($H43<O$2+7,$H43>O$2),3, IF(AND($F43<=O$2, $H43>=O$2), 2, "" ))) | P43: =IF(AND($F43<(P$2+7),$F43>P$2),1, IF(AND($H43<P$2+7,$H43>P$2),3, IF(AND($F43<=P$2, $H43>=P$2), 2, "" ))) | Q43: =IF(AND($F43<(Q$2+7),$F43>Q$2),1, IF(AND($H43<Q$2+7,$H43>Q$2),3, IF(AND($F43<=Q$2, $H43>=Q$2), 2, "" ))) | R43: =IF(AND($F43<(R$2+7),$F43>R$2),1, IF(AND($H43<R$2+7,$H43>R$2),3, IF(AND($F43<=R$2, $H43>=R$2), 2, "" ))) | S43: =IF(AND($F43<(S$2+7),$F43>S$2),1, IF(AND($H43<S$2+7,$H43>S$2),3, IF(AND($F43<=S$2, $H43>=S$2), 2, "" ))) | ... AQ43: =IF(AND($F43<(AQ$2+7),$F43>AQ$2),1, IF(AND($H43<AQ$2+7,$H43>AQ$2),3, IF(AND($F43<=AQ$2, $H43>=AQ$2), 2, "" ))) -> 3
B44: Hot Commissioning | C44: 44013 | D44: 2 | E44: 44015 | F44: 44013 | G44: 2 | H44: 44015 | L44: =IF(AND($F44<(L$2+7),$F44>L$2),1, IF(AND($H44<L$2+7,$H44>L$2),3, IF(AND($F44<=L$2, $H44>=L$2), 2, "" ))) | M44: =IF(AND($F44<(M$2+7),$F44>M$2),1, IF(AND($H44<M$2+7,$H44>M$2),3, IF(AND($F44<=M$2, $H44>=M$2), 2, "" ))) | N44: =IF(AND($F44<(N$2+7),$F44>N$2),1, IF(AND($H44<N$2+7,$H44>N$2),3, IF(AND($F44<=N$2, $H44>=N$2), 2, "" ))) | O44: =IF(AND($F44<(O$2+7),$F44>O$2),1, IF(AND($H44<O$2+7,$H44>O$2),3, IF(AND($F44<=O$2, $H44>=O$2), 2, "" ))) | P44: =IF(AND($F44<(P$2+7),$F44>P$2),1, IF(AND($H44<P$2+7,$H44>P$2),3, IF(AND($F44<=P$2, $H44>=P$2), 2, "" ))) | Q44: =IF(AND($F44<(Q$2+7),$F44>Q$2),1, IF(AND($H44<Q$2+7,$H44>Q$2),3, IF(AND($F44<=Q$2, $H44>=Q$2), 2, "" ))) | R44: =IF(AND($F44<(R$2+7),$F44>R$2),1, IF(AND($H44<R$2+7,$H44>R$2),3, IF(AND($F44<=R$2, $H44>=R$2), 2, "" ))) | S44: =IF(AND($F44<(S$2+7),$F44>S$2),1, IF(AND($H44<S$2+7,$H44>S$2),3, IF(AND($F44<=S$2, $H44>=S$2), 2, "" ))) | ... AQ44: =IF(AND($F44<(AQ$2+7),$F44>AQ$2),1, IF(AND($H44<AQ$2+7,$H44>AQ$2),3, IF(AND($F44<=AQ$2, $H44>=AQ$2), 2, "" ))) -> 1
A45: 13 | B45: Handover | C45: 44020 | D45: 1 | E45: 44021 | F45: 44020 | G45: 1 | H45: 44021 | L45: =IF(AND($F45<(L$2+7),$F45>L$2),1, IF(AND($H45<L$2+7,$H45>L$2),3, IF(AND($F45<=L$2, $H45>=L$2), 2, "" ))) | M45: =IF(AND($F45<(M$2+7),$F45>M$2),1, IF(AND($H45<M$2+7,$H45>M$2),3, IF(AND($F45<=M$2, $H45>=M$2), 2, "" ))) | N45: =IF(AND($F45<(N$2+7),$F45>N$2),1, IF(AND($H45<N$2+7,$H45>N$2),3, IF(AND($F45<=N$2, $H45>=N$2), 2, "" ))) | O45: =IF(AND($F45<(O$2+7),$F45>O$2),1, IF(AND($H45<O$2+7,$H45>O$2),3, IF(AND($F45<=O$2, $H45>=O$2), 2, "" ))) | P45: =IF(AND($F45<(P$2+7),$F45>P$2),1, IF(AND($H45<P$2+7,$H45>P$2),3, IF(AND($F45<=P$2, $H45>=P$2), 2, "" ))) | Q45: =IF(AND($F45<(Q$2+7),$F45>Q$2),1, IF(AND($H45<Q$2+7,$H45>Q$2),3, IF(AND($F45<=Q$2, $H45>=Q$2), 2, "" ))) | R45: =IF(AND($F45<(R$2+7),$F45>R$2),1, IF(AND($H45<R$2+7,$H45>R$2),3, IF(AND($F45<=R$2, $H45>=R$2), 2, "" ))) | S45: =IF(AND($F45<(S$2+7),$F45>S$2),1, IF(AND($H45<S$2+7,$H45>S$2),3, IF(AND($F45<=S$2, $H45>=S$2), 2, "" ))) | ... AQ45: =IF(AND($F45<(AQ$2+7),$F45>AQ$2),1, IF(AND($H45<AQ$2+7,$H45>AQ$2),3, IF(AND($F45<=AQ$2, $H45>=AQ$2), 2, "" )))
A46: E | B46: PAYMENT MILESTONE 6: HANDOVER COMPLETE | C46: 44022 | D46: 1 | E46: 44025 | F46: 44022 | G46: 1 | H46: 44025
C47: 43831 | D47: These numbers are used to set the start and end dates on the Gantt Chart
C48: 44014

Sheet Compliance
B2: HSE
B4: Description | C4: Status | D4: Approved By | E4: Date | F4: Results / Comments
B5: NOC
B6: 7.1 Agreement
B7: 13.2 Agreement
B8: EE File
B9: Subbie File
B16: SSEG
B18: Description | C18: Status | D18: Approved By | E18: Date | F18: Results / Comments
B19: SSEG Application
B20: PTI
B21: Commissioning Approval

Sheet Project Plan
N1: =TODAY() -> 46069 | O1: =TODAY() -> 46069
C2: PROJECT PLAN | E2: Corporate Park | N2: 0 | O2: 1
C3: PROJECT SIZE (kWp) | E3: 257
C4: PROJECT DEVELOPER | E4: Natasha Watkins-Baker
C5: PROJECT MANAGERS | E5: Eon Van Rensberg
C6: CONTRACT VALUE | E6: 2655906.3
C7: Phase: | E7: DLP
B8: No. | C8: HIGH LEVEL PROGRAMME | E8: Planned Start | F8: Duration (days) | G8: Planned End | I8: Actual Start | J8: Duration (days) | K8: Actual End | M8: Status | N8: Status | O8: Comment
F9: =G41-E19 -> 31 | J9: =K41-I19 -> 86 | M9: =AVERAGE(M11,M18,M21,M28,M35,M39,M46,M43) -> 0.99479167 | N9: =AVERAGE(N11,N18,N21,N28,N35,N39,N46,N43) -> 1
B11: 1 | C11: Project Initiation | E11: =MIN(E12:E16) -> 45769 | F11: =G11-E11 -> 63 | G11: =MAX(G12:G16) -> 45832 | I11: =MIN(I12:I16) -> 45769 | J11: =K11-I11 -> 62 | K11: =MAX(K12:K16) -> 45831 | M11: =(J12*M12+J13*M13+J14*M14+J15*M15+J16*M16)/SUM(J12:J16) -> 1 | N11: =(K12*N12+K13*N13+K14*N14+K15*N15+K16*N16)/SUM(K12:K16) -> 1
B12: 1.1 | C12: BD Handover | E12: 45769 | F12: 1 | G12: =WORKDAY.INTL(E12,F12,1,Data!$C$3:$C$14) -> 45770 | I12: 45769 | J12: 1 | K12: =WORKDAY.INTL(I12,J12,1,Data!$C$3:$C$14) -> 45770 | M12: 1 | N12: =_xlfn.LET( _xlpm.s,VALUE($I12), _xlpm.e,VALUE($K12), IF(OR(_xlpm.s="",_xlpm.e=""),"", IF(_xlpm.e<=_xlpm.s, IF(TODAY()>=_xlpm.e,1,0), MAX(0,MIN(1,(TODAY()-_xlpm.s)/(_xlpm.e-_xlpm.s))))) ) -> 1
B13: 1.2 | C13: Project Introduction | E13: =WORKDAY.INTL(E19,0,1,Data!$C$3:$C$14)-14 -> 45817 | F13: 1 | G13: =WORKDAY.INTL(E13,F13,1,Data!$C$3:$C$14) -> 45818 | I13: =WORKDAY.INTL(I19,0,1,Data!$C$3:$C$14)-16 -> 45815 | J13: 1 | K13: =WORKDAY.INTL(I13,J13,1,Data!$C$3:$C$14) -> 45817 | M13: 1 | N13: =_xlfn.LET( _xlpm.s,VALUE($I13), _xlpm.e,VALUE($K13), IF(OR(_xlpm.s="",_xlpm.e=""),"", IF(_xlpm.e<=_xlpm.s, IF(TODAY()>=_xlpm.e,1,0), MAX(0,MIN(1,(TODAY()-_xlpm.s)/(_xlpm.e-_xlpm.s))))) ) -> 1
B14: 1.3 | C14: HSE | E14: =E13 -> 45817 | F14: 10 | G14: =WORKDAY.INTL(E14,F14,1,Data!$C$3:$C$14) -> 45832 | I14: =I13 -> 45815 | J14: 10 | K14: =WORKDAY.INTL(I14,J14,1,Data!$C$3:$C$14) -> 45831 | M14: 1 | N14: =_xlfn.LET( _xlpm.s,VALUE($I14), _xlpm.e,VALUE($K14), IF(OR(_xlpm.s="",_xlpm.e=""),"", IF(_xlpm.e<=_xlpm.s, IF(TODAY()>=_xlpm.e,1,0), MAX(0,MIN(1,(TODAY()-_xlpm.s)/(_xlpm.e-_xlpm.s))))) ) -> 1
B15: 1.4 | C15: Installer Kick Off | E15: =WORKDAY.INTL(E19,0,1,Data!$C$3:$C$14)-14 -> 45817 | F15: 1 | G15: =WORKDAY.INTL(E15,F15,1,Data!$C$3:$C$14) -> 45818 | I15: =WORKDAY.INTL(I19,0,1,Data!$C$3:$C$14)-16 -> 45815 | J15: 1 | K15: =WORKDAY.INTL(I15,J15,1,Data!$C$3:$C$14) -> 45817 | M15: 1 | N15: =_xlfn.LET( _xlpm.s,VALUE($I15), _xlpm.e,VALUE($K15), IF(OR(_xlpm.s="",_xlpm.e=""),"", IF(_xlpm.e<=_xlpm.s, IF(TODAY()>=_xlpm.e,1,0), MAX(0,MIN(1,(TODAY()-_xlpm.s)/(_xlpm.e-_xlpm.s))))) ) -> 1
B16: 1.5 | C16: Project Review | E16: =WORKDAY.INTL(E19,0,1,Data!$C$3:$C$14)-14 -> 45817 | F16: 1 | G16: =WORKDAY.INTL(E16,F16,1,Data!$C$3:$C$14) -> 45818 | I16: =WORKDAY.INTL(I19,0,1,Data!$C$3:$C$14)-20 -> 45811 | J16: 1 | K16: =WORKDAY.INTL(I16,J16,1,Data!$C$3:$C$14) -> 45812 | M16: 1 | N16: =_xlfn.LET( _xlpm.s,VALUE($I16), _xlpm.e,VALUE($K16), IF(OR(_xlpm.s="",_xlpm.e=""),"", IF(_xlpm.e<=_xlpm.s, IF(TODAY()>=_xlpm.e,1,0), MAX(0,MIN(1,(TODAY()-_xlpm.s)/(_xlpm.e-_xlpm.s))))) ) -> 1
B18: 2 | C18: Site Establishment | E18: =MIN(E19:E20) -> 45831 | F18: =G18-E18 -> 1 | G18: =MAX(G19) -> 45832 | I18: =MIN(I19:I20)-16 -> 45815 | J18: =K18-I18 -> 17 | K18: =MAX(K19) -> 45832 | M18: 1 | N18: 1
B19: 2.1 | C19: Solar Contractor Establishment | E19: 45831 | F19: 1 | G19: =E19+F19 -> 45832 | I19: 45831 | J19: 1 | K19: =I19+J19 -> 45832 | M19: 1 | N19: =_xlfn.LET( _xlpm.s,VALUE($I19), _xlpm.e,VALUE($K19), IF(OR(_xlpm.s="",_xlpm.e=""),"", IF(_xlpm.e<=_xlpm.s, IF(TODAY()>=_xlpm.e,1,0), MAX(0,MIN(1,(TODAY()-_xlpm.s)/(_xlpm.e-_xlpm.s))))) ) -> 1 | S19: =NETWORKDAYS(I19,K41,Data!C3:C15) -> 63 | T19: Net Work Days
B21: 3 | C21: AC Installation | E21: =MIN(E22:E26) -> 45810 | F21: =G21-E21 -> 46 | G21: =MAX(G22:G26) -> 45856 | I21: =MIN(I22:I26) -> 45810 | J21: =K21-I21 -> 94 | K21: =MAX(K22:K26) -> 45904 | M21: =(J22*M22+J23*M23+J24*M24+J25*M25+J26*M26)/SUM(J22:J26) -> 1 | N21: =(K22*N22+K23*N23+K24*N24+K25*N25+K26*N26)/SUM(K22:K26) -> 1 | S21: =S19/5 -> 12.6 | T21: Total Weeks
B22: 3.1 | C22: Inverters delivered | E22: =WORKDAY.INTL(G19,0,1,Data!$C$3:$C$14) -> 45832 | F22: 1 | G22: =WORKDAY.INTL(E22,F22,1,Data!$C$3:$C$14) -> 45833 | I22: =WORKDAY.INTL(K19,0,1,Data!$C$3:$C$14) -> 45832 | J22: 1 | K22: =WORKDAY.INTL(I22,J22,1,Data!$C$3:$C$14) -> 45833 | M22: 1 | N22: =_xlfn.LET( _xlpm.s,VALUE($I22), _xlpm.e,VALUE($K22), IF(OR(_xlpm.s="",_xlpm.e=""),"", IF(_xlpm.e<=_xlpm.s, IF(TODAY()>=_xlpm.e,1,0), MAX(0,MIN(1,(TODAY()-_xlpm.s)/(_xlpm.e-_xlpm.s))))) ) -> 1 | S22: =E3/S21 -> 20.396825 | T22: kW/Week Installation Rate
B23: 3.2 | C23: Inverters Mounted | E23: =WORKDAY.INTL(G22,0,1,Data!$C$3:$C$14) -> 45833 | F23: 5 | G23: =WORKDAY.INTL(E23,F23,1,Data!$C$3:$C$14) -> 45840 | I23: 45860 | J23: 2 | K23: =WORKDAY.INTL(I23,J23,1,Data!$C$3:$C$14) -> 45862 | M23: 1 | N23: =_xlfn.LET( _xlpm.s,VALUE($I23), _xlpm.e,VALUE($K23), IF(OR(_xlpm.s="",_xlpm.e=""),"", IF(_xlpm.e<=_xlpm.s, IF(TODAY()>=_xlpm.e,1,0), MAX(0,MIN(1,(TODAY()-_xlpm.s)/(_xlpm.e-_xlpm.s))))) ) -> 1
B24: 3.3 | C24: Solar DB Lead Time | E24: =WORKDAY.INTL(E19,0,1,Data!$C$3:$C$14)-21 -> 45810 | F24: 25 | G24: =WORKDAY.INTL(E24,F24,1,Data!$C$3:$C$14) -> 45846 | I24: =WORKDAY.INTL(I19,0,1,Data!$C$3:$C$14)-21 -> 45810 | J24: 61 | K24: =WORKDAY.INTL(I24,J24,1,Data!$C$3:$C$14) -> 45896 | M24: 1 | N24: =_xlfn.LET( _xlpm.s,VALUE($I24), _xlpm.e,VALUE($K24), IF(OR(_xlpm.s="",_xlpm.e=""),"", IF(_xlpm.e<=_xlpm.s, IF(TODAY()>=_xlpm.e,1,0), MAX(0,MIN(1,(TODAY()-_xlpm.s)/(_xlpm.e-_xlpm.s))))) ) -> 1
B25: 3.4 | C25: AC Works | E25: =WORKDAY.INTL(G24,0,1,Data!$C$3:$C$14) -> 45846 | F25: 8 | G25: =WORKDAY.INTL(E25,F25,1,Data!$C$3:$C$14) -> 45856 | I25: =K24 -> 45896 | J25: 5 | K25: =WORKDAY.INTL(I25,J25,1,Data!$C$3:$C$14) -> 45903 | M25: 1 | N25: =_xlfn.LET( _xlpm.s,VALUE($I25), _xlpm.e,VALUE($K25), IF(OR(_xlpm.s="",_xlpm.e=""),"", IF(_xlpm.e<=_xlpm.s, IF(TODAY()>=_xlpm.e,1,0), MAX(0,MIN(1,(TODAY()-_xlpm.s)/(_xlpm.e-_xlpm.s))))) ) -> 1
B26: 3.5 | C26: AC Tie-In | E26: =WORKDAY.INTL(E25,0,1,Data!$C$3:$C$14) -> 45846 | F26: 3 | G26: =WORKDAY.INTL(E26,F26,1,Data!$C$3:$C$14) -> 45849 | I26: =K25 -> 45903 | J26: 1 | K26: =WORKDAY.INTL(I26,J26,1,Data!$C$3:$C$14) -> 45904 | M26: 1 | N26: =_xlfn.LET( _xlpm.s,VALUE($I26), _xlpm.e,VALUE($K26), IF(OR(_xlpm.s="",_xlpm.e=""),"", IF(_xlpm.e<=_xlpm.s, IF(TODAY()>=_xlpm.e,1,0), MAX(0,MIN(1,(TODAY()-_xlpm.s)/(_xlpm.e-_xlpm.s))))) ) -> 1
B28: 4 | C28: DC Works | E28: =MIN(E30:E33) -> 45831 | F28: =G28-E28 -> 29 | G28: =MAX(G30:G33) -> 45860 | I28: =MIN(I30:I33) -> 45831 | J28: =K28-I28 -> 51 | K28: =MAX(K30:K33) -> 45882 | M28: 1 | N28: 1
B29: 4.1 | C29: Lifeline Installation (If Applicable) | M29: 0 | N29: 0
B30: 4.1 | C30: Mounting Structure delivered | E30: =E19 -> 45831 | F30: 1 | G30: =WORKDAY.INTL(E30,F30,1,Data!$C$3:$C$14) -> 45832 | I30: =I19 -> 45831 | J30: 1 | K30: =WORKDAY.INTL(I30,J30,1,Data!$C$3:$C$14) -> 45832 | M30: 1 | N30: =_xlfn.LET( _xlpm.s,VALUE($I30), _xlpm.e,VALUE($K30), IF(OR(_xlpm.s="",_xlpm.e=""),"", IF(_xlpm.e<=_xlpm.s, IF(TODAY()>=_xlpm.e,1,0), MAX(0,MIN(1,(TODAY()-_xlpm.s)/(_xlpm.e-_xlpm.s))))) ) -> 1
B31: 4.2 | C31: Mounting Structure installation | E31: =WORKDAY.INTL(G30,0,1,Data!$C$3:$C$14) -> 45832 | F31: 14 | G31: =WORKDAY.INTL(E31,F31,1,Data!$C$3:$C$14) -> 45852 | I31: =WORKDAY.INTL(K30,0,1,Data!$C$3:$C$14) -> 45832 | J31: 7 | K31: 45858 | M31: 1 | N31: =_xlfn.LET( _xlpm.s,VALUE($I31), _xlpm.e,VALUE($K31), IF(OR(_xlpm.s="",_xlpm.e=""),"", IF(_xlpm.e<=_xlpm.s, IF(TODAY()>=_xlpm.e,1,0), MAX(0,MIN(1,(TODAY()-_xlpm.s)/(_xlpm.e-_xlpm.s))))) ) -> 1
B32: 4.3 | C32: DC Cable delivered | E32: =E30 -> 45831 | F32: 1 | G32: =WORKDAY.INTL(E32,F32,1,Data!$C$3:$C$14) -> 45832 | I32: =I22 -> 45832 | J32: 1 | K32: =WORKDAY.INTL(I32,J32,1,Data!$C$3:$C$14) -> 45833 | M32: 1 | N32: =_xlfn.LET( _xlpm.s,VALUE($I32), _xlpm.e,VALUE($K32), IF(OR(_xlpm.s="",_xlpm.e=""),"", IF(_xlpm.e<=_xlpm.s, IF(TODAY()>=_xlpm.e,1,0), MAX(0,MIN(1,(TODAY()-_xlpm.s)/(_xlpm.e-_xlpm.s))))) ) -> 1
B33: 4.3 | C33: DC Stringing | E33: =WORKDAY.INTL(G37,0,1,Data!$C$3:$C$14)-3 -> 45852 | F33: 6 | G33: =WORKDAY.INTL(E33,F33,1,Data!$C$3:$C$14) -> 45860 | I33: =WORKDAY.INTL(K31,0,1,Data!$C$3:$C$14)-3 -> 45855 | J33: 19 | K33: =WORKDAY.INTL(I33,J33,1,Data!$C$3:$C$14) -> 45882 | M33: 1 | N33: =_xlfn.LET( _xlpm.s,VALUE($I33), _xlpm.e,VALUE($K33), IF(OR(_xlpm.s="",_xlpm.e=""),"", IF(_xlpm.e<=_xlpm.s, IF(TODAY()>=_xlpm.e,1,0), MAX(0,MIN(1,(TODAY()-_xlpm.s)/(_xlpm.e-_xlpm.s))))) ) -> 1
B35: 5 | C35: Module installation | E35: =MIN(E36:E37) -> 45845 | F35: =G35-E35 -> 10 | G35: =MAX(G36:G37) -> 45855 | I35: =MIN(I36:I37) -> 45832 | J35: =K35-I35 -> 57 | K35: =MAX(K36:K37) -> 45889 | M35: =(J36*M36+J37*M37)/SUM(J36:J37) -> 1 | N35: =(K36*N36+K37*N37)/SUM(K36:K37) -> 1
B36: 5.1 | C36: Module delivery | E36: =WORKDAY.INTL(G31,0,1,Data!$C$3:$C$14)-7 -> 45845 | F36: 1 | G36: =WORKDAY.INTL(E36,F36,1,Data!$C$3:$C$14) -> 45846 | I36: =WORKDAY.INTL(I22,0,1,Data!$C$3:$C$14) -> 45832 | J36: 1 | K36: =WORKDAY.INTL(I36,J36,1,Data!$C$3:$C$14) -> 45833 | M36: 1 | N36: =_xlfn.LET( _xlpm.s,VALUE($I36), _xlpm.e,VALUE($K36), IF(OR(_xlpm.s="",_xlpm.e=""),"", IF(_xlpm.e<=_xlpm.s, IF(TODAY()>=_xlpm.e,1,0), MAX(0,MIN(1,(TODAY()-_xlpm.s)/(_xlpm.e-_xlpm.s))))) ) -> 1
B37: 5.2 | C37: Module mounting | E37: =G36 -> 45846 | F37: 7 | G37: =WORKDAY.INTL(E37,F37,1,Data!$C$3:$C$14) -> 45855 | I37: =K33-5 -> 45877 | J37: 8 | K37: =WORKDAY.INTL(I37,J37,1,Data!$C$3:$C$14) -> 45889 | M37: 1 | N37: =_xlfn.LET( _xlpm.s,VALUE($I37), _xlpm.e,VALUE($K37), IF(OR(_xlpm.s="",_xlpm.e=""),"", IF(_xlpm.e<=_xlpm.s, IF(TODAY()>=_xlpm.e,1,0), MAX(0,MIN(1,(TODAY()-_xlpm.s)/(_xlpm.e-_xlpm.s))))) ) -> 1
B39: 6 | C39: Commissioning | E39: =MIN(E40:E41) -> 45860 | F39: =G39-E39 -> 2 | G39: =MAX(G40:G41) -> 45862 | I39: =MIN(I40:I41) -> 45911 | J39: =K39-I39 -> 6 | K39: =MAX(K40:K41) -> 45917 | M39: =(J40*M40+J41*M41)/SUM(J40:J41) -> 1 | N39: =(K40*N40+K41*N41)/SUM(K40:K41) -> 1
B40: 6.1 | C40: Commissioning | E40: =WORKDAY.INTL(MAX(G21,G28,G35),0,1,Data!$C$3:$C$14) -> 45860 | F40: 1 | G40: =WORKDAY.INTL(E40,F40,1,Data!$C$3:$C$14) -> 45861 | I40: 45911 | J40: 1 | K40: =WORKDAY.INTL(I40,J40,1,Data!$C$3:$C$14) -> 45912 | M40: 1 | N40: =_xlfn.LET( _xlpm.s,VALUE($I40), _xlpm.e,VALUE($K40), IF(OR(_xlpm.s="",_xlpm.e=""),"", IF(_xlpm.e<=_xlpm.s, IF(TODAY()>=_xlpm.e,1,0), MAX(0,MIN(1,(TODAY()-_xlpm.s)/(_xlpm.e-_xlpm.s))))) ) -> 1
B41: 6.2 | C41: Practical Completion | E41: =WORKDAY.INTL(G40,0,1,Data!$C$3:$C$14) -> 45861 | F41: 1 | G41: =WORKDAY.INTL(E41,F41,1,Data!$C$3:$C$14) -> 45862 | I41: =WORKDAY.INTL(K40,0,1,Data!$C$3:$C$14) -> 45912 | J41: 3 | K41: =WORKDAY.INTL(I41,J41,1,Data!$C$3:$C$14) -> 45917 | M41: 1 | N41: =_xlfn.LET( _xlpm.s,VALUE($I41), _xlpm.e,VALUE($K41), IF(OR(_xlpm.s="",_xlpm.e=""),"", IF(_xlpm.e<=_xlpm.s, IF(TODAY()>=_xlpm.e,1,0), MAX(0,MIN(1,(TODAY()-_xlpm.s)/(_xlpm.e-_xlpm.s))))) ) -> 1
B43: 7 | C43: QA Inspections | E43: =MIN(E44) -> 45862 | F43: =G43-E43 -> 1 | G43: =MAX(G44) -> 45863 | I43: =MIN(I44) -> 45912 | J43: =K43-I43 -> 3 | K43: =MAX(K44) -> 45915 | M43: =(J44*M44)/SUM(J44) -> 1 | N43: =(K44*N44)/SUM(K44) -> 1
B44: 7.1 | C44: Red-Team Inspection | E44: =WORKDAY.INTL(G41,0,1,Data!$C$3:$C$14) -> 45862 | F44: 1 | G44: =WORKDAY.INTL(E44,F44,1,Data!$C$3:$C$14) -> 45863 | I44: =WORKDAY.INTL(I40,0,1,Data!$C$3:$C$14)+1 -> 45912 | J44: 1 | K44: =WORKDAY.INTL(I44,J44,1,Data!$C$3:$C$14) -> 45915 | M44: 1 | N44: =_xlfn.LET( _xlpm.s,VALUE($I44), _xlpm.e,VALUE($K44), IF(OR(_xlpm.s="",_xlpm.e=""),"", IF(_xlpm.e<=_xlpm.s, IF(TODAY()>=_xlpm.e,1,0), MAX(0,MIN(1,(TODAY()-_xlpm.s)/(_xlpm.e-_xlpm.s))))) ) -> 1
B46: 8 | C46: Project Closure | E46: =MIN(E47:E52) -> 45863 | F46: =G46-E46 -> 13 | G46: =MAX(G47:G52) -> 45876 | I46: =MIN(I47:I52) -> 45915 | J46: =K46-I46 -> 133 | K46: =MAX(K47:K52) -> 46048 | M46: =(J47*M47+J48*M48+J49*M49+J50*M50+J51*M51+J52*M52)/SUM(J47:J52) -> 0.95833333 | N46: =(J47*N47+J48*N48+J49*N49+J50*N50+J51*N51+J52*N52)/SUM(J47:J52) -> 1
B47: 8.1 | C47: Equipment serial numbers | E47: =G44 -> 45863 | F47: 2 | G47: =WORKDAY.INTL(E47,F47,1,Data!$C$3:$C$14) -> 45867 | I47: =K44 -> 45915 | J47: 2 | K47: =WORKDAY.INTL(I47,J47,1,Data!$C$3:$C$14) -> 45917 | M47: 1 | N47: =_xlfn.LET( _xlpm.s,VALUE($I47), _xlpm.e,VALUE($K47), IF(OR(_xlpm.s="",_xlpm.e=""),"", IF(_xlpm.e<=_xlpm.s, IF(TODAY()>=_xlpm.e,1,0), MAX(0,MIN(1,(TODAY()-_xlpm.s)/(_xlpm.e-_xlpm.s))))) ) -> 1
B48: 8.2 | C48: Snags completion | E48: =G44 -> 45863 | F48: 4 | G48: =WORKDAY.INTL(E48,F48,1,Data!$C$3:$C$14) -> 45869 | I48: =K44+1 -> 45916 | J48: 2 | K48: =WORKDAY.INTL(I48,J48,1,Data!$C$3:$C$14) -> 45918 | M48: 1 | N48: =_xlfn.LET( _xlpm.s,VALUE($I48), _xlpm.e,VALUE($K48), IF(OR(_xlpm.s="",_xlpm.e=""),"", IF(_xlpm.e<=_xlpm.s, IF(TODAY()>=_xlpm.e,1,0), MAX(0,MIN(1,(TODAY()-_xlpm.s)/(_xlpm.e-_xlpm.s))))) ) -> 1
B49: 8.3 | C49: System Performance Monitoring | E49: =WORKDAY.INTL(G48,0,1,Data!$C$3:$C$14) -> 45869 | F49: 5 | G49: =WORKDAY.INTL(E49,F49,1,Data!$C$3:$C$14) -> 45876 | I49: =WORKDAY.INTL(K48,0,1,Data!$C$3:$C$14) -> 45918 | J49: 5 | K49: =WORKDAY.INTL(I49,J49,1,Data!$C$3:$C$14) -> 45926 | M49: 1 | N49: =_xlfn.LET( _xlpm.s,VALUE($I49), _xlpm.e,VALUE($K49), IF(OR(_xlpm.s="",_xlpm.e=""),"", IF(_xlpm.e<=_xlpm.s, IF(TODAY()>=_xlpm.e,1,0), MAX(0,MIN(1,(TODAY()-_xlpm.s)/(_xlpm.e-_xlpm.s))))) ) -> 1
B50: 8.4 | C50: Handover documentation | E50: =WORKDAY.INTL(E48,0,1,Data!$C$3:$C$14) -> 45863 | F50: 4 | G50: =WORKDAY.INTL(E50,F50,1,Data!$C$3:$C$14) -> 45869 | I50: =WORKDAY.INTL(I48,0,1,Data!$C$3:$C$14) -> 45916 | J50: 4 | K50: =WORKDAY.INTL(I50,J50,1,Data!$C$3:$C$14) -> 45922 | M50: 1 | N50: =_xlfn.LET( _xlpm.s,VALUE($I50), _xlpm.e,VALUE($K50), IF(OR(_xlpm.s="",_xlpm.e=""),"", IF(_xlpm.e<=_xlpm.s, IF(TODAY()>=_xlpm.e,1,0), MAX(0,MIN(1,(TODAY()-_xlpm.s)/(_xlpm.e-_xlpm.s))))) ) -> 1
B51: 8.5 | C51: Handover to Client | E51: =WORKDAY.INTL(G50,0,1,Data!$C$3:$C$14) -> 45869 | F51: 1 | G51: =WORKDAY.INTL(E51,F51,1,Data!$C$3:$C$14) -> 45870 | I51: 46045 | J51: 1 | K51: =WORKDAY.INTL(I51,J51,1,Data!$C$3:$C$14) -> 46048 | M51: 0 | N51: =_xlfn.LET( _xlpm.s,VALUE($I51), _xlpm.e,VALUE($K51), IF(OR(_xlpm.s="",_xlpm.e=""),"", IF(_xlpm.e<=_xlpm.s, IF(TODAY()>=_xlpm.e,1,0), MAX(0,MIN(1,(TODAY()-_xlpm.s)/(_xlpm.e-_xlpm.s))))) ) -> 1 | O51: Portfolio Handover
B52: 8.6 | C52: Handover to Matriarch | E52: =WORKDAY.INTL(E48,0,1,Data!$C$3:$C$14)+2 -> 45865 | F52: 5 | G52: =WORKDAY.INTL(E52,F52,1,Data!$C$3:$C$14) -> 45870 | I52: 45945 | J52: 10 | K52: =WORKDAY.INTL(I52,J52,1,Data!$C$3:$C$14) -> 45959 | M52: 1 | N52: =_xlfn.LET( _xlpm.s,VALUE($I52), _xlpm.e,VALUE($K52), IF(OR(_xlpm.s="",_xlpm.e=""),"", IF(_xlpm.e<=_xlpm.s, IF(TODAY()>=_xlpm.e,1,0), MAX(0,MIN(1,(TODAY()-_xlpm.s)/(_xlpm.e-_xlpm.s))))) ) -> 1

Sheet Revenue Tracking
B2: HIGH LEVEL PROJECT REVENUE TRACKING
D3: COSTED | F3: ACTUAL | L3: FINANCIAL REVIEW | N3: TIMELINE REVIEW | P3: 2025 Actual Revenue | Q3: 2025 Actual COS | R3: 2026 Budget Revenue | S3: 2026 Budget COS | T3: 2026 Actual Revenue | U3: 2026 Actual COS
B4: 1 | C4: Planned Revenue | D4: ='Project Plan'!E6 -> 2655906.3 | F4: =F21 -> 2655906.3 | N4: Start Date | P4: =SUMIFS('Expenditure Breakdown'!$U:$U, 'Expenditure Breakdown'!$T:$T, ">"&DATE(2024,8,31), 'Expenditure Breakdown'!$T:$T, "<="&DATE(2025,8,31), 'Expenditure Breakdown'!$S:$S, "<>") -> 2371815.4 | Q4: =SUMIFS('Expenditure Breakdown'!$Q:$Q, 'Expenditure Breakdown'!$T:$T, ">"&DATE(2024,8,31), 'Expenditure Breakdown'!$T:$T, "<="&DATE(2025,8,31), 'Expenditure Breakdown'!$S:$S, "<>") -> 2087502.2 | R4: =SUMIFS('Expenditure Breakdown'!$U:$U, 'Expenditure Breakdown'!$T:$T, ">"&DATE(2025,8,31), 'Expenditure Breakdown'!$T:$T, "<="&DATE(2026,8,31)) -> 284090.91 | S4: =SUMIFS('Expenditure Breakdown'!$Q:$Q, 'Expenditure Breakdown'!$T:$T, ">"&DATE(2025,8,31), 'Expenditure Breakdown'!$T:$T, "<="&DATE(2026,8,31)) -> 141847.23 | T4: =SUMIFS('Expenditure Breakdown'!$U:$U, 'Expenditure Breakdown'!$T:$T, ">"&DATE(2025,8,31), 'Expenditure Breakdown'!$T:$T, "<="&DATE(2026,8,31), 'Expenditure Breakdown'!$S:$S, "<>") -> 284090.91 | U4: =SUMIFS('Expenditure Breakdown'!$Q:$Q, 'Expenditure Breakdown'!$T:$T, ">"&DATE(2025,8,31), 'Expenditure Breakdown'!$T:$T, "<="&DATE(2026,8,31), 'Expenditure Breakdown'!$S:$S, "<>") -> 141847.23
B5: 2 | C5: Planned Expenditure | D5: =+'Expenditure Tracking'!F5 -> 2415274.8 | F5: =+'Expenditure Tracking'!H5 -> 2220751.1 | G5: VO PM Limit | H5: Current VO Total
B6: 3 | C6: Planned Profit | D6: =+D4-D5 -> 240631.5 | F6: =+F4-F5 -> 435155.21 | G6: =D6*0.05 -> 12031.575 | H6: =SUMIF('Expenditure Breakdown'!N:N,"*VO*",'Expenditure Breakdown'!Q:Q) -> 39935 | N6: End Date - PC
B7: 4 | C7: Planned Margin | D7: =+D6/D4 -> 0.090602406 | F7: =+F6/F4 -> 0.16384434
B10: CONTRACT
B12: No. | C12: PAYMENT MILESTONE | E12: % | F12: VALUE | H12: PLANNED PAYMENT DATE | L12: INVOICE NUMBER | N12: INVOICE RAISED DATE | P12: PAYMENT RECEIVED DATE | R12: MILESTONE NOTES & COMMENTS
B13: 1 | C13: Deposit | E13: 0.2 | F13: =$D$4*E13 -> 531181.26 | H13: 45777 | L13: 004728 | N13: 45777 | P13: 45777
B14: 2 | C14: Delivery of Panels | E14: 0.2 | F14: =$D$4*E14 -> 531181.26 | H14: ='Project Plan'!E36+7 -> 45852 | L14: 004728 | N14: 45777 | P14: 45842
B15: 3 | C15: Delivery of Inverters | E15: 0.15 | F15: =$D$4*E15 -> 398385.95 | H15: ='Project Plan'!E22+7 -> 45839 | L15: 004728 | N15: 45777 | P15: 45842
B16: 4 | C16: Commissioning Complete | E16: 0.15 | F16: =$D$4*E16 -> 398385.95 | H16: ='Project Plan'!G39+7 -> 45869 | L16: 004728 | N16: 45777 | P16: 45918
B17: 5 | C17: Final Completion Issued | E17: 0.25 | F17: =$D$4*E17 -> 663976.58 | H17: ='Project Plan'!E50+7 -> 45870 | L17: 004728 | N17: 45777 | P17: 45891
B18: 6 | C18: Handover | E18: 0.05 | F18: =$D$4*E18 -> 132795.32 | H18: ='Project Plan'!K51+7 -> 46055 | L18: 004728 | N18: 45777 | P18: 45926
B19: 7 | C19: - | E19: 0 | F19: =$D$4*E19 -> 0
E21: =SUM(E13:E19) -> 1 | F21: =SUM(F13:F19) -> 2655906.3
B23: KEY: | C23: contains an error (in result or a check has failed)
C24: Red Font - IF TEXT : content not yet confirmed
C25: Red Font - IF NUMBER: Negative value
C26: Anything in yellow is a concern or risk for noting or action
C27: confirmed
C28: [ADD INITIALS: comment for noting in square brackets, use colour or red to draw attention if important]
C29: [RT: When adding rows into sheet, ensure you insert between first and last row of each category]
C30: end of sheet - do not insert information below/beyond this
B40: No. | C40: PAYMENT MILESTONE | E40: % | F40: VALUE
B41: 1 | C41: Deposit - Project commencement | E41: 0.35 | F41: =$F$47*E41 -> 929567.21
B42: 2 | C42: Delivery of Panels | E42: 0.3 | F42: =$F$47*E42 -> 796771.89
B43: 3 | C43: Delivery of Inverters | E43: 0.2 | F43: =$F$47*E43 -> 531181.26
B44: 4 | C44: Practical Completion | E44: 0.1 | F44: =$F$47*E44 -> 265590.63
B45: 5 | C45: Handover | E45: 0.05 | F45: =$F$47*E45 -> 132795.32
C46: Total | E46: =SUM(E41:E45) -> 1 | F46: =SUM(F41:F45) -> 2655906.3
E47: =SUM(E41:E45) -> 1 | F47: =F21 -> 2655906.3

Sheet Data
C2: Public holidays | F2: Drop down list
C3: 45658 | D3: New Years Day | F3: Approved
C4: 45737 | D4: Human Rights day | F4: Pending
C5: 45765 | D5: Good Friday | F5: Declined
C6: 45768 | D6: Family Day | F6: Abanded
C7: 45774 | D7: Freedom Day
C8: 45765 | D8: Freedom DayObserved
C9: 45778 | D9: Workers day
C10: 45824 | D10: Youth Day Holiday
C11: 45878 | D11: Womens Day
C12: 45924 | D12: Heritage Day
C13: 46007 | D13: Day of Reconciliation | H13: Manual dates
C14: 46016 | D14: Christmas Day
C15: 46017 | D15: Day of Goodwill

Sheet Expenditure Tracking
B2: HIGH LEVEL PROJECT EXPENDITURE TRACKING
F4: COSTED | H4: ACTUAL | J4: Difference from costed
B5: EXPENDITURE | F5: =SUM(F9:F23) -> 2415274.8 | H5: =SUM(H9:H23) -> 2220751.1 | J5: =SUM(J9:J23) -> 194523.71
B7: No. | D7: Item | F7: Costed Expenditure | H7: Actual Expenditure | J7: Saving / Overrun | L7: Comments on variations from planned expenditure
B9: ='Expenditure Breakdown'!L6 -> 1 | D9: ='Expenditure Breakdown'!M6 -> 1. Panels | F9: ='Expenditure Breakdown'!I6 -> 560797.4 | H9: ='Expenditure Breakdown'!X6 -> 512827 | J9: =F9-H9 -> 47970.4
B10: ='Expenditure Breakdown'!L13 -> 2 | D10: ='Expenditure Breakdown'!M13 -> 2. Inverters | F10: ='Expenditure Breakdown'!I13 -> 160000 | H10: ='Expenditure Breakdown'!X13 -> 137740.7 | J10: =F10-H10 -> 22259.3
B11: ='Expenditure Breakdown'!L21 -> 3 | D11: ='Expenditure Breakdown'!M21 -> 3. Mounting Structures | F11: ='Expenditure Breakdown'!I21 -> 115830 | H11: ='Expenditure Breakdown'!X21 -> 82657.4 | J11: =F11-H11 -> 33172.6
B12: ='Expenditure Breakdown'!L28 -> 4 | D12: ='Expenditure Breakdown'!M28 -> 4. DC Equipment | F12: ='Expenditure Breakdown'!I28 -> 203544 | H12: ='Expenditure Breakdown'!X28 -> 206242.26 | J12: =F12-H12 -> -2698.264
B13: ='Expenditure Breakdown'!L45 -> 5 | D13: ='Expenditure Breakdown'!M45 -> 5. Monitoring | F13: ='Expenditure Breakdown'!I45 -> 49000 | H13: ='Expenditure Breakdown'!X45 -> 101514.84 | J13: =F13-H13 -> -52514.84
B14: ='Expenditure Breakdown'!L59 -> 6 | D14: ='Expenditure Breakdown'!M59 -> 6. AC Equipment | F14: ='Expenditure Breakdown'!I59 -> 306751.82 | H14: ='Expenditure Breakdown'!X59 -> 208384.92 | J14: =F14-H14 -> 98366.893
B15: ='Expenditure Breakdown'!L78 -> 7 | D15: ='Expenditure Breakdown'!M78 -> 7.BESS | F15: ='Expenditure Breakdown'!I78 -> 0 | H15: ='Expenditure Breakdown'!X78 -> 0 | J15: =F15-H15 -> 0
B16: ='Expenditure Breakdown'!L87 -> 8 | D16: ='Expenditure Breakdown'!M87 -> 8. Product Add On | F16: ='Expenditure Breakdown'!I87 -> 250000 | H16: ='Expenditure Breakdown'!X87 -> 49132.22 | J16: =F16-H16 -> 200867.78
B17: ='Expenditure Breakdown'!L97 -> 9 | D17: ='Expenditure Breakdown'!M97 -> 9. AC & DC installation | F17: ='Expenditure Breakdown'!I97 -> 210650 | H17: ='Expenditure Breakdown'!X97 -> 289124 | J17: =F17-H17 -> -78474
B18: ='Expenditure Breakdown'!L111 -> 10 | D18: ='Expenditure Breakdown'!M111 -> 10. Site Logistics | F18: ='Expenditure Breakdown'!I111 -> 60396.667 | H18: ='Expenditure Breakdown'!X111 -> 65924.73 | J18: =F18-H18 -> -5528.0633
B19: ='Expenditure Breakdown'!L136 -> 11 | D19: ='Expenditure Breakdown'!M136 -> 11. Due Dilligence | F19: ='Expenditure Breakdown'!I136 -> 29000 | H19: ='Expenditure Breakdown'!X136 -> 22077.23 | J19: =F19-H19 -> 6922.77
B20: ='Expenditure Breakdown'!L142 -> 12 | D20: ='Expenditure Breakdown'!M142 -> 12. BDP Commission | F20: ='Expenditure Breakdown'!I142 -> 52821.549 | H20: ='Expenditure Breakdown'!X142 -> 0 | J20: =F20-H20 -> 52821.549
B21: ='Expenditure Breakdown'!L145 -> 13 | D21: ='Expenditure Breakdown'!M146 -> 13. Engineering | F21: ='Expenditure Breakdown'!I145 -> 112108.37 | H21: ='Expenditure Breakdown'!X145 -> 33198.829 | J21: =F21-H21 -> 78909.538
B22: ='Expenditure Breakdown'!L152 -> 14 | D22: ='Expenditure Breakdown'!M152 -> 14. General Expenses | F22: ='Expenditure Breakdown'!I152 -> 4375 | H22: ='Expenditure Breakdown'!X152 -> 33819.85 | J22: =F22-H22 -> -29444.85
B23: ='Expenditure Breakdown'!L165 -> 15 | D23: ='Expenditure Breakdown'!M165 -> 15. Service Add On | F23: ='Expenditure Breakdown'!I165 -> 300000 | H23: ='Expenditure Breakdown'!X165 -> 478107.1 | J23: =F23-H23 -> -178107.1
D25: check: | F25: ='Expenditure Breakdown'!I2-'Expenditure Tracking'!F5 -> 0 | G25: =#REF!-G5 -> #REF! | H25: ='Expenditure Breakdown'!X2-H5 -> 0

Sheet Expenditure Breakdown
B2: COSTED EXPENDITURE BREAKDOWN | I2: =SUM(I6:I177) -> 2415274.8 | J2: =SUM(J6:J177) -> 2655906.3 | L2: ACTUAL EXPENDITURE BREAKDOWN | R2: FINANCE ONLY | X2: =SUM(X6:X177) -> 2220751.1
B4: No. | C4: Product / Service | D4: Description of Work | E4: QTY | F4: Rate / Unit | G4: Budget Total | H4: FINANCE PAYMENT DATE | I4: Total COS | J4: =IF(J2-'Revenue Tracking'!D4>=0, "Total Revenue", "ERROR on REV" ) -> Total Revenue | L4: No. | M4: Product/ Service | N4: Description of Work | O4: QTY | P4: Rate / Unit | Q4: Actual Total | R4: PO NUMBER | S4: INVOICE NUMBER | T4: INVOICE RAISED DATE | U4: REVENUE RECOGNITION AMOUNT | V4: CHECK | W4: FINANCE PAYMENT DATE | X4: Total COS
B6: 1 | C6: Panels | D6: Panels Budget | G6: =D178 -> 560797.4 | H6: 45867 | I6: =SUM(G6:G11) -> 560797.4 | J6: =F178 -> 637269.77 | L6: 1 | M6: 1. Panels | N6: Jinko 620W - Menlo | O6: 415 | P6: =620*1.99 -> 1233.8 | Q6: =O6*P6 -> 512027 | R6: PO3909-DIP-PH2-CORP-20250514 | S6: Menlo INV0003028 | T6: 45838 | U6: 637269.77 | V6: =J6-SUM(U6:U11) -> 0 | W6: 45867 | X6: =SUM(Q6:Q11) -> 512827
B7: 1 | D7: Delivery Budget | L7: 1 | M7: 1. Panels | P7: 1.99 | T7: =IF(W7>1,EOMONTH(W7,0),"") | U7: 0
B8: 1 | H8: 45968 | L8: 1 | M8: 1. Panels | P8: 800 | Q8: 800 | S8: Menlo - INV0003230 | T8: 45930 | U8: 0 | W8: 45967
B9: 1 | L9: 1 | M9: 1. Panels | T9: =IF(W9>1,EOMONTH(W9,0),"") | U9: 0
B10: 1 | L10: 1 | M10: 1. Panels | T10: =IF(W10>1,EOMONTH(W10,0),"") | U10: 0
B11: 1 | L11: 1 | M11: 1. Panels | T11: =IF(W11>1,EOMONTH(W11,0),"") | U11: 0 | Y11: BUDGET | Z11: Installer Allocation
T12: =IF(W12>1,EOMONTH(W12,0),"") | Y12: AC Equipment | Z12: =G59 -> 306751.82
B13: 2 | C13: Inverters | D13: Inverter Budget | G13: =D179 -> 160000 | H13: 45867 | I13: =SUM(G13:G19) -> 160000 | J13: =F179 -> 181818.18 | L13: 2 | M13: 2. Inverters | N13: Huawei 100KTL | O13: 2 | P13: 68870 | Q13: 137740.7 | R13: PO3909-DIP-PH2-CORP-20250514 | S13: Menlo INV0003028 | T13: 45838 | U13: 181818.18 | V13: =J13-SUM(U13:U19) -> 0 | W13: 45867 | X13: =SUM(Q13:Q19) -> 137740.7 | Y13: DC Equipment | Z13: =G29 -> 117304
B14: 2 | L14: 2 | M14: 2. Inverters | T14: =IF(W14>1,EOMONTH(W14,0),"") | U14: 0 | Y14: AC Labour | Z14: =G97 -> 64350
B15: 2 | L15: 2 | M15: 2. Inverters | T15: =IF(W15>1,EOMONTH(W15,0),"") | U15: 0 | Y15: DC Labour | Z15: =G98 -> 146300
B16: 2 | L16: 2 | M16: 2. Inverters | T16: =IF(W16>1,EOMONTH(W16,0),"") | U16: 0 | Y16: Offloading | Z16: =G111 -> 8500
B17: 2 | L17: 2 | M17: 2. Inverters | T17: =IF(W17>1,EOMONTH(W17,0),"") | U17: 0 | Y17: Scaffolding | Z17: =G112 -> 20355
B18: 2 | L18: 2 | M18: 2. Inverters | T18: =IF(W18>1,EOMONTH(W18,0),"") | U18: 0 | Y18: Storage | Z18: =G114 -> 1541.6667
B19: 2 | L19: 2 | M19: 2. Inverters | T19: =IF(W19>1,EOMONTH(W19,0),"") | U19: 0 | Y19: Telehandler | Z19: 0
T20: =IF(W20>1,EOMONTH(W20,0),"")
B21: 3 | C21: Mounting Structures | D21: Structure Budget | G21: =D180 -> 115830 | H21: 45867 | I21: =SUM(G21:G26) -> 115830 | J21: =F180 -> 131625 | L21: 3 | M21: 3. Mounting Structures | N21: Schletter Structure | Q21: 82657.4 | R21: PO3902-DSS-20250603 - RV Approved | S21: Schletter - INV1883 | T21: 45838 | U21: 131625 | V21: =J21-SUM(U21:U26) -> 0 | W21: 45867 | X21: =SUM(Q21:Q26) -> 82657.4 | Y21: Other | Z21: 0
B22: 3 | L22: 3 | M22: 3. Mounting Structures | T22: =IF(W22>1,EOMONTH(W22,0),"") | U22: 0 | Y22: Total | Z22: =SUM(Z12:Z21) -> 665102.48
B23: 3 | L23: 3 | M23: 3. Mounting Structures | T23: =IF(W23>1,EOMONTH(W23,0),"") | U23: 0 | Y23: Less 15% | Z23: =+Z22*0.85 -> 565337.11
B24: 3 | L24: 3 | M24: 3. Mounting Structures | T24: =IF(W24>1,EOMONTH(W24,0),"") | U24: 0 | Y24: R/Wp | Z24: =Z23/'Project Plan'!$E$3/1000 -> 2.1997553
B25: 3 | L25: 3 | M25: 3. Mounting Structures | T25: =IF(W25>1,EOMONTH(W25,0),"") | U25: 0
B26: 3 | L26: 3 | M26: 3. Mounting Structures | T26: =IF(W26>1,EOMONTH(W26,0),"") | U26: 0 | Y26: ACTUAL | Z26: Installer Price
T27: =IF(W27>1,EOMONTH(W27,0),"") | Y27: =Y12 -> AC Equipment | Z27: 108910.56
B28: 4 | C28: DC Equipment | D28: DC Cable Budget | E28: =G28/14*1.15 -> 7084 | G28: 86240 | H28: 45867 | I28: =SUM(G28:G43) -> 203544 | J28: =F181 -> 231300 | L28: 4 | M28: 4. DC Equipment | N28: DC Cable - Menlo | O28: 6000 | P28: 13.4 | Q28: =O28*P28 -> 80400 | R28: PO3909-DIP-PH2-CORP-20250514 | S28: Menlo INV0003028 | T28: 45838 | U28: 90168.327 | V28: =J28-SUM(U28:U43) -> 0 | W28: 45867 | X28: =SUM(Q28:Q43) -> 206242.26 | Y28: =Y13 -> DC Equipment | Z28: 125842.26
B29: 4 | D29: DC Equipment Budget | G29: =D181-G28 -> 117304 | H29: 45867 | L29: 4 | M29: 4. DC Equipment | T29: =IF(W29>1,EOMONTH(W29,0),"") | U29: 0 | Y29: =Y14 -> AC Labour | Z29: 98004
B30: 4 | L30: 4 | M30: 4. DC Equipment | T30: =IF(W30>1,EOMONTH(W30,0),"") | U30: 0 | Y30: =Y15 -> DC Labour | Z30: 191120
B31: 4 | L31: 4 | M31: 4. DC Equipment | T31: =IF(W31>1,EOMONTH(W31,0),"") | U31: 0 | Y31: Logistics | Z31: 49778
B32: 4 | H32: =H98 -> 45827 | L32: 4 | M32: 4. DC Equipment | N32: Project Kick Off | O32: 125842.26 | P32: 0.1 | Q32: 11730.4 | S32: The Greenway - INV0001397 | T32: 45838 | U32: 13155.604 | W32: =W98 -> 45827 | Y32: =Y17 -> Scaffolding
H33: 45834 | L33: 4 | M33: 4. DC Equipment | N33: Project Kick Off (top up) | Q33: 853.83 | S33: The Greenway - INV0001403 | T33: 45838 | U33: 957.56745 | W33: 45834
B34: 4 | H34: =H100 -> 45834 | L34: 4 | M34: 4. DC Equipment | N34: Site Establishment | P34: 0.15 | Q34: =$O$32*P34 -> 18876.339 | S34: The Greenway - INV0001404 | T34: 45838 | U34: 21169.75 | W34: =W100 -> 45834 | Y34: =Y18 -> Storage
B35: 4 | H35: =H101 -> 45925 | L35: 4 | M35: 4. DC Equipment | N35: AC Installation Complete | P35: 0.2 | Q35: =$O$32*P35 -> 25168.452 | S35: The Greenway- INV0001426 | T35: 45869 | U35: 28226.334 | W35: =W101 -> 45925 | Y35: =Y19 -> Telehandler | Z35: =Z19*0.75 -> 0
B36: 4 | H36: =H102 -> 45925 | L36: 4 | M36: 4. DC Equipment | N36: DC Installation Complete | P36: 0.25 | Q36: =$O$32*P36 -> 31460.565 | S36: The Greenway- INV0001426 | T36: 45869 | U36: 35282.917 | W36: =W102 -> 45925 | Y36: HSE | Z36: 0
B37: 4 | H37: =H103 -> 45925 | L37: 4 | M37: 4. DC Equipment | N37: Commissioning Complete | P37: 0.1 | Q37: =$O$32*P37 -> 12584.226 | S37: The Greenway- INV0001426 | T37: 45869 | U37: 14113.167 | W37: =W103 -> 45925 | Y37: Other | Z37: 0
B38: 4 | H38: =H104 -> 45925 | L38: 4 | M38: 4. DC Equipment | N38: Site De-establisment | P38: 0.1 | Q38: =$O$32*P38 -> 12584.226 | S38: The Greenway- INV0001426 | T38: 45869 | U38: 14113.167 | W38: =W104 -> 45925 | Y38: Other | Z38: 0
B39: 4 | H39: =H105 -> 45932 | L39: 4 | M39: 4. DC Equipment | N39: Handover Document Complete | P39: 0.05 | Q39: =$O$32*P39 -> 6292.113 | S39: The Greenway- INV0001426 | T39: 45869 | U39: 7056.5834 | W39: 46037 | Y39: Total | Z39: =SUM(Z27:Z38) -> 573654.82
B40: 4 | H40: =H106 -> 45961 | L40: 4 | M40: 4. DC Equipment | N40: End of Defects Period | P40: 0.05 | Q40: =$O$32*P40 -> 6292.113 | S40: The Greenway- INV0001426 | T40: 45869 | U40: 7056.5834 | W40: 46037 | Y40: R/Wp | Z40: =Z39/'Project Plan'!$E$3/1000 -> 2.2321199
B41: 4 | L41: 4 | M41: 4. DC Equipment | T41: =IF(W41>1,EOMONTH(W41,0),"") | U41: =(Q41/$X$28*$J$28) -> 0
B42: 4 | L42: 4 | M42: 4. DC Equipment | T42: =IF(W42>1,EOMONTH(W42,0),"") | U42: =(Q42/$X$28*$J$28) -> 0
B43: 4 | L43: 4 | M43: 4. DC Equipment | T43: =IF(W43>1,EOMONTH(W43,0),"") | U43: =(Q43/$X$28*$J$28) -> 0
T44: =IF(W44>1,EOMONTH(W44,0),"")
B45: 5 | C45: Monitoring | D45: Monitoring Budget | G45: =D183-G48 -> 34000 | H45: 45855 | I45: =SUM(G45:G57) -> 49000 | J45: =F183 -> 55681.818 | L45: 5 | M45: 5. Monitoring | N45: Smartlogger - Menlo | Q45: 8598.35 | R45: PO3909-DIP-PH2-CORP-20250514 | S45: Menlo INV0002936 | T45: 45808 | U45: 9244.4169 | V45: =J45-SUM(U45:U57) -> 0.0013886615 | W45: 45855 | X45: =SUM(Q45:Q57) -> 101514.84
H46: 45969 | L46: 5 | M46: 5. Monitoring | Q46: 8598.34 | S46: Menlo INV0003243 | T46: 45930 | U46: 0 | W46: 45967
L47: 5 | M47: 5. Monitoring | N47: Smartlogger - Menlo RMA replacement | Q47: -8598.35 | U47: 0
B48: 5 | D48: Revenue Metering | G48: 15000 | H48: 45808 | L48: 5 | M48: 5. Monitoring | N48: CTs & Meters | Q48: 27555 | R48: PO3839-DIP-Ph2-Corp-20250429 - RV Approved | S48: Accuenergy Inv: ASAI-005365 | T48: 45777 | U48: 10673.107 | W48: 45808
H49: 45867 | L49: 5 | M49: 5. Monitoring | Q49: 214.29 | S49: Accenergy - INV ASAI-005800 | T49: 45838 | U49: 117.96083 | W49: 45867
B50: 5 | H50: =E50+30 -> 30 | L50: 5 | M50: 5. Monitoring | N50: Techsitter | Q50: 11169 | S50: Matriarch - INV-4999 | T50: 45900 | U50: 7650.358 | W50: =T50+30 -> 45930
B51: 5 | H51: 45799 | L51: 5 | M51: 5. Monitoring | N51: UPS | Q51: 2250.5 | S51: Frontline INV725690 | T51: 45808 | U51: 1267.6392 | W51: 45799
B52: 5 | H52: 45900 | L52: 5 | M52: 5. Monitoring | N52: Apex Device and License - Allocated to IconSA KZN | Q52: 44000 | R52: PO4176-DCP-20250728 - RV Approved | S52: Rubicon INVWCRE-0069677 | T52: 45869 | U52: =23299.4492770989-824.63 -> 22474.819 | W52: 45900
L53: 5 | M53: 5. Monitoring | N53: Apex Device and License - Allocated to IconSA KZN | Q53: =-1*Q52 -> -44000 | S53: Allocated to Icon SA - KZN | T53: 45961 | W53: =T53 -> 45961
L54: 5 | M54: 5. Monitoring | N54: Apex Device allocated from Seshego Circle | Q54: 44000 | R54: PO4077-DSHC-20250630 - RV Approved | S54: Allocated from Seshego Circle | T54: 45961 | W54: =T54 -> 45961
H55: 45930 | L55: 5 | M55: 5. Monitoring | N55: Delivery of Apex | Q55: 193.15 | S55: DSV Inv: 180144979 | T55: 45900 | U55: 105.94453 | W55: 45930
B56: 5 | H56: 45813 | L56: 5 | M56: 5. Monitoring | N56: GivEnergy - Transceiver Kit | Q56: 7534.56 | R56: PO3972-DIP-Ph2-Corp P-20250530 - RV Approved | S56: GivEnergy: INV000009 | T56: 45838 | U56: 4147.5709 | W56: 45813
B57: 5 | H57: 45814 | L57: 5 | M57: 5. Monitoring | U57: =(Q57/$X$45*$J$45) -> 0
H58: 45815 | T58: =IF(W58>1,EOMONTH(W58,0),"")
B59: 6 | C59: AC Equipment | D59: AC Equipment Budget | G59: =D182 -> 306751.82 | H59: 45816 | I59: =SUM(G59:G76) -> 306751.82 | J59: =F182 -> 348581.61 | L59: 6 | M59: 6. AC Equipment | T59: =IF(W59>1,EOMONTH(W59,0),"") | U59: =(Q59/$X$59*$J$59) -> 0 | V59: =J59-SUM(U59:U76) -> 0.0028194372 | X59: =SUM(Q59:Q76) -> 208384.92
B60: 6 | H60: =E60+30 -> 30 | L60: 6 | M60: 6. AC Equipment | N60: PVDB | Q60: 99474.36 | R60: PO3930-DIP-Ph2-Corp P-20250519 - RV Approved | S60: Switchboard 2-SOI002242 | T60: 45900 | U60: 165848.36 | W60: =T60+30 -> 45930
B61: 6 | L61: 6 | M61: 6. AC Equipment | T61: =IF(W61>1,EOMONTH(W61,0),"") | U61: =(Q61/$X$59*$J$59) -> 0
B62: 6 | L62: 6 | M62: 6. AC Equipment | T62: =IF(W62>1,EOMONTH(W62,0),"") | U62: =(Q62/$X$59*$J$59) -> 0
B63: 6 | L63: 6 | M63: 6. AC Equipment | T63: =IF(W63>1,EOMONTH(W63,0),"") | U63: =(Q63/$X$59*$J$59) -> 0
B64: 6 | L64: 6 | M64: 6. AC Equipment | T64: =IF(W64>1,EOMONTH(W64,0),"") | U64: =(Q64/$X$59*$J$59) -> 0
B65: 6 | H65: =H98 -> 45827 | L65: 6 | M65: 6. AC Equipment | N65: Project Kick Off | O65: 108910.56 | P65: 0.1 | Q65: 9472.63 | S65: The Greenway - INV0001397 | T65: 45838 | U65: 16036.987 | W65: =W98 -> 45827
H66: 45834 | M66: 6. AC Equipment | N66: Project Kick Off (top up) | Q66: 1418.43 | S66: The Greenway - INV0001403 | T66: 45838 | U66: 2401.3757 | W66: 45834
B67: 6 | H67: =H100 -> 45834 | L67: 6 | M67: 6. AC Equipment | N67: Site Establishment | P67: 0.15 | Q67: =$O$65*P67 -> 16336.584 | S67: The Greenway - INV0001404 | T67: 45838 | U67: 27657.534 | W67: =W100 -> 45834
B68: 6 | H68: =H101 -> 45925 | L68: 6 | M68: 6. AC Equipment | N68: AC Installation Complete | P68: 0.2 | Q68: =$O$65*P68 -> 21782.112 | S68: The Greenway- INV0001426 | T68: 45869 | U68: 36436.627 | W68: =W101 -> 45925
B69: 6 | H69: =H102 -> 45925 | L69: 6 | M69: 6. AC Equipment | N69: DC Installation Complete | P69: 0.25 | Q69: =$O$65*P69 -> 27227.64 | S69: The Greenway- INV0001426 | T69: 45869 | U69: 45545.783 | W69: =W102 -> 45925
B70: 6 | H70: =H103 -> 45925 | L70: 6 | M70: 6. AC Equipment | N70: Commissioning Complete | P70: 0.1 | Q70: =$O$65*P70 -> 10891.056 | S70: The Greenway- INV0001426 | T70: 45869 | U70: 18218.313 | W70: =W103 -> 45925
B71: 6 | H71: =H104 -> 45925 | L71: 6 | M71: 6. AC Equipment | N71: Site De-establisment | P71: 0.1 | Q71: =$O$65*P71 -> 10891.056 | S71: The Greenway- INV0001426 | T71: 45869 | U71: 18218.313 | W71: =W104 -> 45925
B72: 6 | H72: =H105 -> 45932 | L72: 6 | M72: 6. AC Equipment | N72: Handover Document Complete | P72: 0.05 | Q72: =$O$65*P72 -> 5445.528 | S72: The Greenway- INV0001426 | T72: 45869 | U72: 9109.1567 | W72: 46009
B73: 6 | H73: =H106 -> 45961 | L73: 6 | M73: 6. AC Equipment | N73: End of Defects Period | P73: 0.05 | Q73: =$O$65*P73 -> 5445.528 | S73: The Greenway- INV0001426 | T73: 45869 | U73: 9109.1567 | W73: 46037
B74: 6 | L74: 6 | M74: 6. AC Equipment | T74: =IF(W74>1,EOMONTH(W74,0),"") | U74: =(Q74/$X$59*$J$59) -> 0
B75: 6 | L75: 6 | M75: 6. AC Equipment | T75: =IF(W75>1,EOMONTH(W75,0),"") | U75: =(Q75/$X$59*$J$59) -> 0
B76: 6 | L76: 6 | M76: 6. AC Equipment | T76: =IF(W76>1,EOMONTH(W76,0),"") | U76: =(Q76/$X$59*$J$59) -> 0
T77: =IF(W77>1,EOMONTH(W77,0),"")
B78: 7 | C78: BESS | I78: =SUM(G78:G85) -> 0 | J78: 0 | L78: 7 | M78: 7.BESS | T78: =IF(W78>1,EOMONTH(W78,0),"") | V78: =J78-SUM(U78:U85) -> 0 | X78: =SUM(Q78:Q85) -> 0
B79: 7 | L79: 7 | M79: 7.BESS | T79: =IF(W79>1,EOMONTH(W79,0),"")
B80: 7 | L80: 7 | M80: 7.BESS | T80: =IF(W80>1,EOMONTH(W80,0),"")
B81: 7 | L81: 7 | M81: 7.BESS | T81: =IF(W81>1,EOMONTH(W81,0),"")
B82: 7 | L82: 7 | M82: 7.BESS | T82: =IF(W82>1,EOMONTH(W82,0),"")
B83: 7 | L83: 7 | M83: 7.BESS | T83: =IF(W83>1,EOMONTH(W83,0),"")
B84: 7 | L84: 7 | M84: 7.BESS | T84: =IF(W84>1,EOMONTH(W84,0),"")
B85: 7 | L85: 7 | M85: 7.BESS | T85: =IF(W85>1,EOMONTH(W85,0),"")
T86: =IF(W86>1,EOMONTH(W86,0),"")
B87: 8 | C87: Product Add On | I87: =D185 -> 250000 | J87: =F185 -> 284090.91 | L87: 8 | M87: 8. Product Add On | T87: =IF(W87>1,EOMONTH(W87,0),"") | U87: =(Q87/$X$87*$J$87) -> 0 | V87: =J87-SUM(U87:U95) -> -0.00090449827 | X87: =SUM(Q87:Q95) -> 49132.22
B88: 8 | D88: MV Metering | G88: 250000 | H88: 45930 | L88: 8 | M88: 8. Product Add On | T88: =IF(W88>1,EOMONTH(W88,0),"") | U88: =(Q88/$X$87*$J$87) -> 0
B89: 8 | L89: 8 | M89: 8. Product Add On | N89: E-Stop | Q89: 5203 | R89: PO4383-DCP-20251020 - RV Approved | S89: The Greenway - INV0001510 | T89: 45961 | U89: 16658.267 | W89: 46066
L90: 8 | M90: 8. Product Add On | U90: =(Q90/$X$87*$J$87) -> 0
B91: 8 | H91: =E91 -> 0 | L91: 8 | M91: 8. Product Add On | N91: Inverter Cage with roof - Deposit | O91: 0.75 | P91: 35400 | Q91: =O91*P91 -> 26550 | R91: PO4483-DCP-20251124 - RV Approved | S91: Van Staden Three - Inv3075 | T91: 45991 | U91: 188952.72 | W91: 45989
B92: 8 | L92: 8 | M92: 8. Product Add On | N92: Inverter Cage with roof - Balance | O92: 0.25 | Q92: =P91*O92 -> 8850 | S92: Van Staden Three - Inv3110 | T92: 46022 | U92: 51172.215 | W92: 46031
B93: 8 | L93: 8 | M93: 8. Product Add On | N93: Waterpoints | Q93: 8529.22 | S93: Toys 4Boys - 12392 | T93: 45961 | U93: 27307.711 | W93: 45989
B94: 8 | L94: 8 | M94: 8. Product Add On | T94: =IF(W94>1,EOMONTH(W94,0),"") | U94: =(Q94/$X$87*$J$87) -> 0
B95: 8 | L95: 8 | M95: 8. Product Add On | T95: =IF(W95>1,EOMONTH(W95,0),"") | U95: =(Q95/$X$87*$J$87) -> 0
K96: Only services to be capture below, products above | T96: =IF(W96>1,EOMONTH(W96,0),"")
B97: 9 | C97: AC & DC Installation | D97: AC Installation Budget | G97: =D191 -> 64350 | H97: 45930 | I97: =SUM(G97:G109) -> 210650 | J97: =F191+F192 -> 247823.53 | L97: 9 | M97: 9. AC & DC installation | T97: =IF(W97>1,EOMONTH(W97,0),"") | U97: =(Q97/$X$97*$J$97) -> 0 | V97: =J97-SUM(U97:U109) -> 0 | X97: =SUM(Q97:Q109) -> 289124
B98: 9 | D98: DC Installation Budget | G98: =D192 -> 146300 | H98: 45827 | L98: 9 | M98: 9. AC & DC installation | N98: Project Kick Off | O98: =98004+191120 -> 289124 | P98: 0.1 | Q98: 21065 | S98: The Greenway - INV0001397 | T98: 45838 | U98: 18055.93 | W98: 45827
H99: 45834 | L99: 9 | M99: 9. AC & DC installation | N99: Project Kick Off (top up) | Q99: 7847.4 | S99: The Greenway - INV0001403 | T99: 45838 | U99: 6726.4231 | W99: 45834
B100: 9 | H100: 45834 | L100: 9 | M100: 9. AC & DC installation | N100: Site Establishment | P100: 0.15 | Q100: =$O$98*P100 -> 43368.6 | S100: The Greenway - INV0001404 | T100: 45838 | U100: 37173.529 | W100: 45834
B101: 9 | H101: 45925 | L101: 9 | M101: 9. AC & DC installation | N101: AC Installation Complete | P101: 0.2 | Q101: =$O$98*P101 -> 57824.8 | S101: The Greenway- INV0001426 | T101: 45900 | U101: 49564.706 | W101: 45925
B102: 9 | H102: 45925 | L102: 9 | M102: 9. AC & DC installation | N102: DC Installation Complete | P102: 0.25 | Q102: =$O$98*P102 -> 72281 | S102: The Greenway- INV0001426 | T102: 45900 | U102: 61955.882 | W102: 45925
B103: 9 | H103: 45925 | L103: 9 | M103: 9. AC & DC installation | N103: Commissioning Complete | P103: 0.1 | Q103: =$O$98*P103 -> 28912.4 | S103: The Greenway- INV0001426 | T103: 45900 | U103: 24782.353 | W103: 45925
...

Sheet Cashflow
D1: [RT: Double Check the first date is always a MONDAY] | F1: 45677 | G1: =F1+7 -> 45684 | H1: =G1+7 -> 45691 | I1: =H1+7 -> 45698 | J1: =I1+7 -> 45705 | K1: =J1+7 -> 45712 | L1: =K1+7 -> 45719 | M1: =L1+7 -> 45726 | N1: =M1+7 -> 45733 | ... LD1: =LC1+7 -> 47847
A2: PLANNED | C2: CHECK | D2: CHECK
B3: Planned Revenue | C3: ='Revenue Tracking'!D4 -> 2655906.3 | D3: =SUM(F3:LD3) -> 2655906.3 | F3: =SUMIFS('Revenue Tracking'!$F$13:$F$19, 'Revenue Tracking'!$H$13:$H$19, ">="&F1,'Revenue Tracking'!$H$13:$H$19, "<"&G1) -> 0 | G3: =SUMIFS('Revenue Tracking'!$F$13:$F$19, 'Revenue Tracking'!$H$13:$H$19, ">="&G1,'Revenue Tracking'!$H$13:$H$19, "<"&H1) -> 0 | H3: =SUMIFS('Revenue Tracking'!$F$13:$F$19, 'Revenue Tracking'!$H$13:$H$19, ">="&H1,'Revenue Tracking'!$H$13:$H$19, "<"&I1) -> 0 | I3: =SUMIFS('Revenue Tracking'!$F$13:$F$19, 'Revenue Tracking'!$H$13:$H$19, ">="&I1,'Revenue Tracking'!$H$13:$H$19, "<"&J1) -> 0 | J3: =SUMIFS('Revenue Tracking'!$F$13:$F$19, 'Revenue Tracking'!$H$13:$H$19, ">="&J1,'Revenue Tracking'!$H$13:$H$19, "<"&K1) -> 0 | K3: =SUMIFS('Revenue Tracking'!$F$13:$F$19, 'Revenue Tracking'!$H$13:$H$19, ">="&K1,'Revenue Tracking'!$H$13:$H$19, "<"&L1) -> 0 | L3: =SUMIFS('Revenue Tracking'!$F$13:$F$19, 'Revenue Tracking'!$H$13:$H$19, ">="&L1,'Revenue Tracking'!$H$13:$H$19, "<"&M1) -> 0 | M3: =SUMIFS('Revenue Tracking'!$F$13:$F$19, 'Revenue Tracking'!$H$13:$H$19, ">="&M1,'Revenue Tracking'!$H$13:$H$19, "<"&N1) -> 0 | ... LC3: =SUMIFS('Revenue Tracking'!$F$13:$F$19, 'Revenue Tracking'!$H$13:$H$19, ">="&LC1,'Revenue Tracking'!$H$13:$H$19, "<"&LD1) -> 0 | LD3: =SUMIFS('Revenue Tracking'!$F$13:$F$19, 'Revenue Tracking'!$H$13:$H$19, ">="&LD1,'Revenue Tracking'!$H$13:$H$19, "<"&#REF!) -> 0
B4: Planned Revenue - Cumulative | F4: =F3 -> 0 | G4: =F4+G3 -> 0 | H4: =G4+H3 -> 0 | I4: =H4+I3 -> 0 | J4: =I4+J3 -> 0 | K4: =J4+K3 -> 0 | L4: =K4+L3 -> 0 | M4: =L4+M3 -> 0 | N4: =M4+N3 -> 0 | ... LD4: =LC4+LD3 -> 2655906.3
B5: Planned Expenditure | C5: ='Revenue Tracking'!D5 -> 2415274.8 | D5: =SUM(F5:LD5) -> 2415274.8 | F5: =SUMIFS('Expenditure Breakdown'!$G$6:$G$184, 'Expenditure Breakdown'!$H$6:$H$184, ">="&F1,'Expenditure Breakdown'!$H$6:$H$184, "<"&G1) -> 0 | G5: =SUMIFS('Expenditure Breakdown'!$G$6:$G$184, 'Expenditure Breakdown'!$H$6:$H$184, ">="&G1,'Expenditure Breakdown'!$H$6:$H$184, "<"&H1) -> 0 | H5: =SUMIFS('Expenditure Breakdown'!$G$6:$G$184, 'Expenditure Breakdown'!$H$6:$H$184, ">="&H1,'Expenditure Breakdown'!$H$6:$H$184, "<"&I1) -> 0 | I5: =SUMIFS('Expenditure Breakdown'!$G$6:$G$184, 'Expenditure Breakdown'!$H$6:$H$184, ">="&I1,'Expenditure Breakdown'!$H$6:$H$184, "<"&J1) -> 0 | J5: =SUMIFS('Expenditure Breakdown'!$G$6:$G$184, 'Expenditure Breakdown'!$H$6:$H$184, ">="&J1,'Expenditure Breakdown'!$H$6:$H$184, "<"&K1) -> 0 | K5: =SUMIFS('Expenditure Breakdown'!$G$6:$G$184, 'Expenditure Breakdown'!$H$6:$H$184, ">="&K1,'Expenditure Breakdown'!$H$6:$H$184, "<"&L1) -> 0 | L5: =SUMIFS('Expenditure Breakdown'!$G$6:$G$184, 'Expenditure Breakdown'!$H$6:$H$184, ">="&L1,'Expenditure Breakdown'!$H$6:$H$184, "<"&M1) -> 0 | M5: =SUMIFS('Expenditure Breakdown'!$G$6:$G$184, 'Expenditure Breakdown'!$H$6:$H$184, ">="&M1,'Expenditure Breakdown'!$H$6:$H$184, "<"&N1) -> 0 | ... LC5: =SUMIFS('Expenditure Breakdown'!$G$6:$G$184, 'Expenditure Breakdown'!$H$6:$H$184, ">="&LC1,'Expenditure Breakdown'!$H$6:$H$184, "<"&LD1) -> 0 | LD5: =SUMIFS('Expenditure Breakdown'!$G$6:$G$184, 'Expenditure Breakdown'!$H$6:$H$184, ">="&LD1,'Expenditure Breakdown'!$H$6:$H$184, "<"&#REF!) -> 0
B6: Planned Expenditure - Cumulative | F6: =F5 -> 0 | G6: =F6+G5 -> 0 | H6: =G6+H5 -> 0 | I6: =H6+I5 -> 0 | J6: =I6+J5 -> 0 | K6: =J6+K5 -> 0 | L6: =K6+L5 -> 0 | M6: =L6+M5 -> 0 | N6: =M6+N5 -> 0 | ... LD6: =LC6+LD5 -> 2415274.8
B7: PLANNED CashFlow | F7: =F4-F6 -> 0 | G7: =G4-G6 -> 0 | H7: =H4-H6 -> 0 | I7: =I4-I6 -> 0 | J7: =J4-J6 -> 0 | K7: =K4-K6 -> 0 | L7: =L4-L6 -> 0 | M7: =M4-M6 -> 0 | ... LD7: =LD4-LD6 -> 240631.5
A8: ACTUAL | C8: CHECK | D8: CHECK
B9: Actual + Planned Revenue | C9: ='Revenue Tracking'!F4 -> 2655906.3 | D9: =SUM(F9:LD9) -> 2655906.3 | F9: =SUMIFS('Revenue Tracking'!$F$13:$F$19, 'Revenue Tracking'!$P$13:$P$19, ">="&F1,'Revenue Tracking'!$P$13:$P$19, "<"&G1) -> 0 | G9: =SUMIFS('Revenue Tracking'!$F$13:$F$19, 'Revenue Tracking'!$P$13:$P$19, ">="&G1,'Revenue Tracking'!$P$13:$P$19, "<"&H1) -> 0 | H9: =SUMIFS('Revenue Tracking'!$F$13:$F$19, 'Revenue Tracking'!$P$13:$P$19, ">="&H1,'Revenue Tracking'!$P$13:$P$19, "<"&I1) -> 0 | I9: =SUMIFS('Revenue Tracking'!$F$13:$F$19, 'Revenue Tracking'!$P$13:$P$19, ">="&I1,'Revenue Tracking'!$P$13:$P$19, "<"&J1) -> 0 | J9: =SUMIFS('Revenue Tracking'!$F$13:$F$19, 'Revenue Tracking'!$P$13:$P$19, ">="&J1,'Revenue Tracking'!$P$13:$P$19, "<"&K1) -> 0 | K9: =SUMIFS('Revenue Tracking'!$F$13:$F$19, 'Revenue Tracking'!$P$13:$P$19, ">="&K1,'Revenue Tracking'!$P$13:$P$19, "<"&L1) -> 0 | L9: =SUMIFS('Revenue Tracking'!$F$13:$F$19, 'Revenue Tracking'!$P$13:$P$19, ">="&L1,'Revenue Tracking'!$P$13:$P$19, "<"&M1) -> 0 | M9: =SUMIFS('Revenue Tracking'!$F$13:$F$19, 'Revenue Tracking'!$P$13:$P$19, ">="&M1,'Revenue Tracking'!$P$13:$P$19, "<"&N1) -> 0 | ... LC9: =SUMIFS('Revenue Tracking'!$F$13:$F$19, 'Revenue Tracking'!$P$13:$P$19, ">="&LC1,'Revenue Tracking'!$P$13:$P$19, "<"&LD1) -> 0 | LD9: =SUMIFS('Revenue Tracking'!$F$13:$F$19, 'Revenue Tracking'!$P$13:$P$19, ">="&LD1,'Revenue Tracking'!$P$13:$P$19, "<"&#REF!) -> 0
B10: Actual + Planned Revenue - Cumulative | F10: =F9 -> 0 | G10: =F10+G9 -> 0 | H10: =G10+H9 -> 0 | I10: =H10+I9 -> 0 | J10: =I10+J9 -> 0 | K10: =J10+K9 -> 0 | L10: =K10+L9 -> 0 | M10: =L10+M9 -> 0 | N10: =M10+N9 -> 0 | ... LD10: =LC10+LD9 -> 2655906.3
B11: Actual + Planned Expenditure | C11: ='Revenue Tracking'!F5 -> 2220751.1 | D11: =SUM(F11:LD11) -> 2229349.4 | F11: =SUMIFS('Expenditure Breakdown'!$Q$6:$Q$184, 'Expenditure Breakdown'!$W$6:$W$184, ">="&F1,'Expenditure Breakdown'!$W$6:$W$184, "<"&G1) -> 0 | G11: =SUMIFS('Expenditure Breakdown'!$Q$6:$Q$184, 'Expenditure Breakdown'!$W$6:$W$184, ">="&G1,'Expenditure Breakdown'!$W$6:$W$184, "<"&H1) -> 0 | H11: =SUMIFS('Expenditure Breakdown'!$Q$6:$Q$184, 'Expenditure Breakdown'!$W$6:$W$184, ">="&H1,'Expenditure Breakdown'!$W$6:$W$184, "<"&I1) -> 0 | I11: =SUMIFS('Expenditure Breakdown'!$Q$6:$Q$184, 'Expenditure Breakdown'!$W$6:$W$184, ">="&I1,'Expenditure Breakdown'!$W$6:$W$184, "<"&J1) -> 0 | J11: =SUMIFS('Expenditure Breakdown'!$Q$6:$Q$184, 'Expenditure Breakdown'!$W$6:$W$184, ">="&J1,'Expenditure Breakdown'!$W$6:$W$184, "<"&K1) -> 0 | K11: =SUMIFS('Expenditure Breakdown'!$Q$6:$Q$184, 'Expenditure Breakdown'!$W$6:$W$184, ">="&K1,'Expenditure Breakdown'!$W$6:$W$184, "<"&L1) -> 0 | L11: =SUMIFS('Expenditure Breakdown'!$Q$6:$Q$184, 'Expenditure Breakdown'!$W$6:$W$184, ">="&L1,'Expenditure Breakdown'!$W$6:$W$184, "<"&M1) -> 0 | M11: =SUMIFS('Expenditure Breakdown'!$Q$6:$Q$184, 'Expenditure Breakdown'!$W$6:$W$184, ">="&M1,'Expenditure Breakdown'!$W$6:$W$184, "<"&N1) -> 0 | ... LC11: =SUMIFS('Expenditure Breakdown'!$Q$6:$Q$184, 'Expenditure Breakdown'!$W$6:$W$184, ">="&LC1,'Expenditure Breakdown'!$W$6:$W$184, "<"&LD1) -> 0 | LD11: =SUMIFS('Expenditure Breakdown'!$Q$6:$Q$184, 'Expenditure Breakdown'!$W$6:$W$184, ">="&LD1,'Expenditure Breakdown'!$W$6:$W$184, "<"&#REF!) -> 0
B12: Actual + Planned Expenditure - Cumulative | F12: =F11 -> 0 | G12: =F12+G11 -> 0 | H12: =G12+H11 -> 0 | I12: =H12+I11 -> 0 | J12: =I12+J11 -> 0 | K12: =J12+K11 -> 0 | L12: =K12+L11 -> 0 | M12: =L12+M11 -> 0 | N12: =M12+N11 -> 0 | ... LD12: =LC12+LD11 -> 2229349.4
B14: ACTUAL CashFlow | F14: =F10-F12 -> 0 | G14: =G10-G12 -> 0 | H14: =H10-H12 -> 0 | I14: =I10-I12 -> 0 | J14: =J10-J12 -> 0 | K14: =K10-K12 -> 0 | L14: =L10-L12 -> 0 | M14: =M10-M12 -> 0 | ... LD14: =LD10-LD12 -> 426556.86
C16: CHECK | D16: CHECK
B17: Revenue Recognition | C17: =C3-D17 -> 0.0030123224 | D17: =SUM(F17:LD17) -> 2655906.3 | F17: =SUMIFS('Expenditure Breakdown'!$U$6:$U$184, 'Expenditure Breakdown'!$T$6:$T$184, ">="&F1,'Expenditure Breakdown'!$T$6:$T$184, "<"&G1) -> 0 | G17: =SUMIFS('Expenditure Breakdown'!$U$6:$U$184, 'Expenditure Breakdown'!$T$6:$T$184, ">="&G1,'Expenditure Breakdown'!$T$6:$T$184, "<"&H1) -> 0 | H17: =SUMIFS('Expenditure Breakdown'!$U$6:$U$184, 'Expenditure Breakdown'!$T$6:$T$184, ">="&H1,'Expenditure Breakdown'!$T$6:$T$184, "<"&I1) -> 0 | I17: =SUMIFS('Expenditure Breakdown'!$U$6:$U$184, 'Expenditure Breakdown'!$T$6:$T$184, ">="&I1,'Expenditure Breakdown'!$T$6:$T$184, "<"&J1) -> 0 | J17: =SUMIFS('Expenditure Breakdown'!$U$6:$U$184, 'Expenditure Breakdown'!$T$6:$T$184, ">="&J1,'Expenditure Breakdown'!$T$6:$T$184, "<"&K1) -> 0 | K17: =SUMIFS('Expenditure Breakdown'!$U$6:$U$184, 'Expenditure Breakdown'!$T$6:$T$184, ">="&K1,'Expenditure Breakdown'!$T$6:$T$184, "<"&L1) -> 0 | L17: =SUMIFS('Expenditure Breakdown'!$U$6:$U$184, 'Expenditure Breakdown'!$T$6:$T$184, ">="&L1,'Expenditure Breakdown'!$T$6:$T$184, "<"&M1) -> 0 | M17: =SUMIFS('Expenditure Breakdown'!$U$6:$U$184, 'Expenditure Breakdown'!$T$6:$T$184, ">="&M1,'Expenditure Breakdown'!$T$6:$T$184, "<"&N1) -> 0 | ... LC17: =SUMIFS('Expenditure Breakdown'!$U$6:$U$184, 'Expenditure Breakdown'!$T$6:$T$184, ">="&LC1,'Expenditure Breakdown'!$T$6:$T$184, "<"&LD1) -> 0 | LD17: =SUMIFS('Expenditure Breakdown'!$U$6:$U$184, 'Expenditure Breakdown'!$T$6:$T$184, ">="&LD1,'Expenditure Breakdown'!$T$6:$T$184, "<"&#REF!) -> 0
B18: Revenue Recognition Cumulative | C18: =D17-D18 -> 0 | D18: =MAX(F18:LD18) -> 2655906.3 | F18: =F17 -> 0 | G18: =F18+G17 -> 0 | H18: =G18+H17 -> 0 | I18: =H18+I17 -> 0 | J18: =I18+J17 -> 0 | K18: =J18+K17 -> 0 | L18: =K18+L17 -> 0 | M18: =L18+M17 -> 0 | N18: =M18+N17 -> 0 | ... LD18: =LC18+LD17 -> 2655906.3

Sheet Finance - Revenue
A3: Sum of REVENUE RECOGNITION AMOUNT | B3: Column Labels
A4: Row Labels | B4: (blank) | C4: 45777 | D4: 45808 | E4: 45838 | F4: 45869 | G4: 45900 | H4: 45930 | I4: 45961 | J4: 45991 | K4: 46022 | M4: Grand Total
A5: (blank)
A6: 1. Panels | E6: 637269.77 | H6: 0 | L6: 0 | M6: 637269.77
A7: 2. Inverters | E7: 181818.18 | L7: 0 | M7: 181818.18
A8: 3. Mounting Structures | E8: 131625 | L8: 0 | M8: 131625
A9: 4. DC Equipment | E9: 124493.68 | F9: 105848.75 | L9: 0 | M9: 230342.43
A10: 5. Monitoring | B10: 0 | C10: 10673.107 | D10: 10512.056 | E10: 4265.5318 | F10: 22474.819 | G10: 7756.3026 | H10: 0 | M10: 55681.817
A11: 6. AC Equipment | E11: 46095.897 | F11: 136637.35 | G11: 165848.36 | L11: 0 | M11: 348581.61
A12: 8. Product Add On | B12: 0 | I12: 43965.978 | J12: 188952.72 | K12: 51172.215 | L12: 0 | M12: 284090.91
A13: 9. AC & DC installation | E13: 61955.882 | G13: 185867.65 | L13: 0 | M13: 247823.53
A14: 10. Site Logistics | B14: 0 | E14: 8450.871 | F14: 62604.035 | G14: 0 | L14: 0 | M14: 71054.906
A15: 11. Due Dilligence | C15: 11826.759 | F15: 14423.516 | G15: 7867.373 | L15: 0 | M15: 34117.648
A16: 13. Engineering | B16: 0 | G16: 127395.87 | L16: 0 | M16: 127395.87
A17: 14. General Expenses | B17: 0 | C17: 3545.7516 | D17: 1196.4605 | E17: 287.34276 | F17: 0 | G17: 117.5 | H17: 0 | I17: 0 | L17: 0 | M17: 5147.0549
A18: 15. Service Add On | E18: 300000 | H18: 0 | L18: 0 | M18: 300000
A19: 12. BDP Commission
A20: 7.BESS
A21: 4. DC Equipment | E21: 957.56745 | M21: 957.56745
A22: Grand Total | B22: 0 | C22: 26045.617 | D22: 11708.517 | E22: 1497219.7 | F22: 341988.47 | G22: 494853.05 | H22: 0 | I22: 43965.978 | J22: 188952.72 | K22: 51172.215 | L22: 0 | M22: 2655906.3

Sheet Finance - COS
A3: Sum of Actual Total | B3: Column Labels
A4: Row Labels | B4: (blank) | C4: 45777 | D4: 45808 | E4: 45838 | F4: 45869 | G4: 45900 | H4: 45930 | I4: 45961 | J4: 45991 | K4: 46022 | M4: Grand Total
A5: (blank)
A6: 1. Panels | E6: 512027 | H6: 800 | M6: 512827
A7: 2. Inverters | E7: 137740.7 | M7: 137740.7
A8: 3. Mounting Structures | E8: 82657.4 | M8: 82657.4
A9: 4. DC Equipment | E9: 111006.74 | F9: 94381.695 | M9: 205388.43
A10: 5. Monitoring | B10: -8598.35 | C10: 27555 | D10: 10848.85 | E10: 7748.85 | F10: 44000 | G10: 11362.15 | H10: 8598.34 | I10: 0 | M10: 101514.84
A11: 6. AC Equipment | E11: 27227.644 | F11: 81682.92 | G11: 99474.36 | M11: 208384.92
A12: 8. Product Add On | I12: 13732.22 | J12: 26550 | K12: 8850 | M12: 49132.22
A13: 9. AC & DC installation | E13: 72281 | G13: 216843 | M13: 289124
A14: 10. Site Logistics | E14: 13090.25 | F14: 52188.75 | G14: 645.73 | M14: 65924.73
A15: 11. Due Dilligence | C15: 9019.6 | F15: 7057.63 | G15: 6000 | M15: 22077.23
A16: 13. Engineering | B16: 0 | G16: 33198.829 | M16: 33198.829
A17: 14. General Expenses | B17: 0 | C17: 7750 | D17: 7624.05 | E17: 12174.8 | F17: 0 | G17: 3061.43 | H17: 1307.83 | I17: 1901.74 | M17: 33819.85
A18: 15. Service Add On | E18: 398000 | H18: 237.1 | I18: 79870 | M18: 478107.1
A19: 12. BDP Commission
A20: 7.BESS
A21: 4. DC Equipment | E21: 853.83 | M21: 853.83
A22: Grand Total | B22: -8598.35 | C22: 44324.6 | D22: 18472.9 | E22: 1374808.2 | F22: 279310.99 | G22: 370585.5 | H22: 10943.27 | I22: 95503.96 | J22: 26550 | K22: 8850 | M22: 2220751.1

Sheet Project Margins
A1: [capture project margins from costing sheet]
A3: Products | D3: 0.32
A4: Services | D4: 0.5
A5: Expenses | D5: 0.15
A6: Subcontractors | D6: 0.2

Sheet Equipment Quotes
B2: Equipment Quote and Budget comparision
B4: Description | D4: Budget | F4: Supplier 1 | H4: Variance | J4: Supplier 2 | L4: Variance | N4: Comments / Notes
F7: >Name< | J7: >Name<
B9: Inverters | D9: =SUM(D10:D11) -> #REF! | F9: =SUM(F10:F13) -> 0 | H9: =$D$9-F9 -> #REF! | J9: =SUM(J10:J13) -> 0 | L9: =$D$9-J9 -> #REF!
B10: Inverters | D10: =#REF! -> #REF!
B11: Optimizers | D11: =#REF! -> #REF!
B12: Warranty
B13: Delivery fee
F15: >Name< | J15: >Name<
B17: Mounting Structure | D17: =SUM(D18:D19) -> #REF! | F17: =SUM(F18:F20) -> 0 | H17: =$D$17- F17 -> #REF! | J17: =SUM(J18:J20) -> 0 | L17: =$D$17- J17 -> #REF!
B18: Mounting Structure | D18: =#REF! -> #REF!
B19: Delivery fee
F21: >Name< | J21: >Name<
B23: DC Cable | D23: =SUM(D24:D25) -> #REF! | F23: =SUM(F24:F25) -> 0 | H23: =$D$23- F23 -> #REF! | J23: =SUM(J24:J25) -> 0 | L23: =$D$23- J23 -> #REF!
B24: DC Cable | D24: =#REF! -> #REF!
B25: Delivery fee
F27: >Name< | J27: >Name<
B29: Monitoring system | D29: =SUM(D30:D32) -> #REF! | F29: =SUM(F30:F42) -> 0 | H29: =$D$29-F29 -> #REF! | J29: =SUM(J30:J32) -> 0 | L29: =$D$29-J29 -> #REF!
B30: =#REF! -> #REF! | D30: =#REF! -> #REF!
B31: =#REF! -> #REF! | D31: =#REF! -> #REF!
B32: Delivery fee
F34: >Name< | J34: >Name<
B36: Additional Scope | D36: =SUM(D37:D41) -> #REF! | F36: =SUM(F37:F41) -> 0 | H36: =$D$29-F36 -> #REF! | J36: =SUM(J37:J41) -> 0 | L36: =$D$29-J36 -> #REF!
B37: SCADA | D37: =#REF! -> #REF!
B38: Inverter cage
B39: Cat ladders
B40: Gen Integration
B41: Lifelines
B43: Totals | D43: =D36+D29+D23+D17+D9 -> #REF! | H43: =SUM(H7:H42) -> #REF! | L43: =SUM(L7:L42) -> #REF!
B47: All amounts are incl VAT

Sheet Installer Quotes
B2: Installer Quote and Budget comparision
B4: Description | D4: Budget | G4: Cosmic Sun | J4: Variance | L4: Matthews Group | O4: Variance
B6: AC Equipment | D6: =#REF! -> #REF! | E6: =D6/(1000*'Project Plan'!$E$3) -> #REF! | G6: 277892.91 | H6: =G6/('Project Plan'!$E$3*1000) -> 1.0812954 | J6: =D6-G6 -> #REF! | M6: =L6/('Project Plan'!$E$3*1000) -> 0 | O6: =D6-L6 -> #REF!
B7: DC Equipment | D7: =#REF! -> #REF! | E7: =D7/(1000*'Project Plan'!$E$3) -> #REF! | G7: 142158.25 | H7: =G7/('Project Plan'!$E$3*1000) -> 0.55314494 | J7: =D7-G7 -> #REF! | M7: =L7/('Project Plan'!$E$3*1000) -> 0 | O7: =D7-L7 -> #REF!
B8: AC Labour | D8: =#REF! -> #REF! | E8: =D8/(1000*'Project Plan'!$E$3) -> #REF! | G8: 96174 | H8: =G8/('Project Plan'!$E$3*1000) -> 0.3742179 | J8: =D8-G8 -> #REF! | M8: =L8/('Project Plan'!$E$3*1000) -> 0 | O8: =D8-L8 -> #REF!
B9: DC Labour | D9: =#REF! -> #REF! | E9: =D9/(1000*'Project Plan'!$E$3) -> #REF! | G9: 230160 | H9: =G9/('Project Plan'!$E$3*1000) -> 0.8955642 | J9: =D9-G9 -> #REF! | M9: =L9/('Project Plan'!$E$3*1000) -> 0 | O9: =D9-L9 -> #REF!
B10: Offloading | D10: =#REF! -> #REF! | G10: 0 | J10: =D10-G10 -> #REF! | O10: =D10-L10 -> #REF!
B11: Roof Access/Scaffolding | D11: =#REF! -> #REF! | G11: 29257.61 | J11: =D11-G11 -> #REF! | O11: =D11-L11 -> #REF!
B12: Storage | D12: =#REF! -> #REF! | J12: =D12-G12 -> #REF! | O12: =D12-L12 -> #REF!
B13: Telehandler | D13: =#REF! -> #REF!
B14: HSE | D14: 0
B15: Totals | D15: =SUM(D6:D13) -> #REF! | G15: =SUM(G6:G13) -> 775642.77 | J15: =SUM(J6:J14) -> #REF! | L15: =SUM(L6:L13) -> 0 | O15: =SUM(O6:O14) -> #REF!
B18: Description | D18: Budget | G18: >Installer Name 3< | J18: Variance | L18: >Installer Name 4< | O18: Variance
B20: AC installation | D20: =#REF! -> #REF! | E20: =D20/(1000*'Project Plan'!$E$3) -> #REF! | H20: =G20/(1000*'Project Plan'!$E$3) -> 0 | J20: =D20-G20 -> #REF! | M20: =L20/(1000*'Project Plan'!$E$3) -> 0 | O20: =D6-L20 -> #REF!
B21: AC equipment | D21: =#REF! -> #REF! | E21: =D21/(1000*'Project Plan'!$E$3) -> #REF! | J21: =D21-G21 -> #REF! | M21: =L21/(1000*'Project Plan'!$E$3) -> 0 | O21: =D7-L21 -> #REF!
B22: DC installation | D22: =#REF! -> #REF! | E22: =D22/(1000*'Project Plan'!$E$3) -> #REF! | H22: =G22/(1000*'Project Plan'!$E$3) -> 0 | J22: =D22-G22 -> #REF! | M22: =L22/(1000*'Project Plan'!$E$3) -> 0 | O22: =D8-L22 -> #REF!
B23: DC equipment | D23: =SUM(#REF!) -> #REF! | E23: =D23/(1000*'Project Plan'!$E$3) -> #REF! | J23: =D23-G23 -> #REF! | O23: =D9-L23 -> #REF!
B24: Storage | D24: =#REF! -> #REF! | J24: =D24-G24 -> #REF! | O24: =D10-L24 -> #REF!
B25: Panel lifting equipment | D25: =SUM(#REF!) -> #REF! | J25: =D25-G25 -> #REF! | O25: =D11-L25 -> #REF!
B26: Offloading | D26: =#REF! -> #REF! | J26: =D26-G26 -> #REF! | O26: =D12-L26 -> #REF!
B29: Totals | D29: =SUM(D20:D27) -> #REF! | G29: =SUM(G20:G27) -> 0 | J29: =SUM(J20:J28) -> #REF! | L29: =SUM(L20:L27) -> 0 | O29: =SUM(O20:O28) -> #REF!
B32: Budget Summary
B34: Budget | D34: =D15 -> #REF!
B35: =G4 -> Cosmic Sun | D35: =G15 -> 775642.77
B36: =L4 -> Matthews Group | D36: =L15 -> 0
B37: =G18 -> >Installer Name 3< | D37: =G29 -> 0
B38: =L18 -> >Installer Name 4< | D38: =L29 -> 0
B40: =IF(D40<D34,"Saving","Loss") -> #REF! | D40: =D34-MIN(D35:D38) -> #REF!
B42: All amounts are exc VAT

Sheet Decision Register
B1: =D15 -> Corporate Park | E1: Decision Register
B3: ID | C3: Decision Description | D3: Decision Impact | E3: Proposed Date | F3: Proposed By | G3: Status | H3: Approved By | I3: Date | J3: Results / Comments
B4: DEC001
B5: DEC002
B6: DEC003
B7: DEC004
B8: DEC005
B9: DEC006
B10: DEC007
B11: DEC008
B12: DEC009
B13: DEC010
D15: {='Project Plan'!E2:H2} -> Corporate Park | E15: 0 | F15: 0 | G15: 0
