Workbook
Name Inverter_Capacity: #REF!
Name Inverter_Capacity: #REF!
Name Inverter_Capacity: #REF!
Name Inverter_Supplier: #REF!
Name Inverter_Supplier: #REF!
Name Inverter_Supplier: #REF!
Name Project_Size: 'Certificate - Financial Close'!Projectsize
Name Project_Size: Compliance!Projectsize
Name Project_Size: 'Finance - Revenue'!Projectsize
Name Project_Size: Projectsize
Name Projectsize: #REF!
Name Projectsize: #REF!
Name Projectsize: #REF!
Name Projectsize: 'Project Margins'!$K$5
Name Security_Serv: #REF!
Name Security_Serv: #REF!
Name SSS: #REF!
Name SSS: #REF!
Name USD_ZAR: #REF!
Name USD_ZAR: #REF!
Name USD_ZAR: #REF!

Sheet Sheet1
A1: PROJECT PLAN
A2: # | B2: Project Milestone | C2: Planned Start Date | D2: Duration (Work Days) | E2: Planned End Date | F2: Actual Start Date | H2: Actual End Date | J2: Comments | L2: =C3 -> 43831 | M2: =L2+3 -> 43834 | N2: =M2+7 -> 43841 | O2: =N2+7 -> 43848 | P2: =O2+7 -> 43855 | Q2: =P2+6 -> 43861 | R2: =Q2+1 -> 43862 | S2: =R2+7 -> 43869 | T2: =S2+7 -> 43876 | U2: =T2+7 -> 43883 | V2: =U2+6 -> 43889 | W2: =V2+7 -> 43896 | X2: =W2+7 -> 43903 | Y2: =X2+7 -> 43910 | Z2: =Y2+7 -> 43917 | AA2: =Z2+3 -> 43920 | AB2: =AA2+4 -> 43924 | AC2: =AB2+7 -> 43931 | AD2: =AC2+7 -> 43938 | AE2: =AD2+7 -> 43945 | AF2: =AE2+6 -> 43951 | AG2: =AF2+2 -> 43953 | AH2: =AG2+7 -> 43960 | AI2: =AH2+7 -> 43967 | AJ2: =AI2+7 -> 43974 | AK2: =AJ2+7 -> 43981 | AL2: =AK2+1 -> 43982 | AM2: =AL2+6 -> 43988 | AN2: =AM2+7 -> 43995 | AO2: =AN2+7 -> 44002 | AP2: =AO2+7 -> 44009 | AQ2: =AP2+3 -> 44012 | AR2: =AQ2+4 -> 44016 | AS2: =AR2+7 -> 44023 | AT2: =AS2+7 -> 44030 | AU2: =AT2+7 -> 44037 | AV2: =AU2+6 -> 44043 | AW2: =AV2+1 -> 44044 | AX2: =AW2+7 -> 44051 | AY2: =AX2+7 -> 44058 | AZ2: =AY2+7 -> 44065 | BA2: =AZ2+7 -> 44072 | BB2: =BA2+2 -> 44074 | BC2: =BB2+5 -> 44079 | BD2: =BC2+7 -> 44086 | BE2: =BD2+7 -> 44093 | BF2: =BE2+7 -> 44100 | BG2: =BF2+4 -> 44104
A3: 1 | B3: Contract Signature | C3: 43831 | D3: 1 | E3: 43832 | F3: 43831 | G3: 1 | H3: 43832 | L3: =IF(AND($F3<(L$2+7),$F3>L$2),1, IF(AND($H3<L$2+7,$H3>L$2),3, IF(AND($F3<=L$2, $H3>=L$2), 2, "" ))) -> 3 | M3: =IF(AND($F3<(M$2+7),$F3>M$2),1, IF(AND($H3<M$2+7,$H3>M$2),3, IF(AND($F3<=M$2, $H3>=M$2), 2, "" ))) | N3: =IF(AND($F3<(N$2+7),$F3>N$2),1, IF(AND($H3<N$2+7,$H3>N$2),3, IF(AND($F3<=N$2, $H3>=N$2), 2, "" ))) | O3: =IF(AND($F3<(O$2+7),$F3>O$2),1, IF(AND($H3<O$2+7,$H3>O$2),3, IF(AND($F3<=O$2, $H3>=O$2), 2, "" ))) | P3: =IF(AND($F3<(P$2+7),$F3>P$2),1, IF(AND($H3<P$2+7,$H3>P$2),3, IF(AND($F3<=P$2, $H3>=P$2), 2, "" ))) | Q3: =IF(AND($F3<(Q$2+7),$F3>Q$2),1, IF(AND($H3<Q$2+7,$H3>Q$2),3, IF(AND($F3<=Q$2, $H3>=Q$2), 2, "" ))) | R3: =IF(AND($F3<(R$2+7),$F3>R$2),1, IF(AND($H3<R$2+7,$H3>R$2),3, IF(AND($F3<=R$2, $H3>=R$2), 2, "" ))) | S3: =IF(AND($F3<(S$2+7),$F3>S$2),1, IF(AND($H3<S$2+7,$H3>S$2),3, IF(AND($F3<=S$2, $H3>=S$2), 2, "" ))) | ... AQ3: =IF(AND($F3<(AQ$2+7),$F3>AQ$2),1, IF(AND($H3<AQ$2+7,$H3>AQ$2),3, IF(AND($F3<=AQ$2, $H3>=AQ$2), 2, "" )))
A4: A | B4: PAYMENT MILESTONE 1: DEPOSIT | C4: 43832 | D4: 1 | E4: 43833 | F4: 43832 | G4: 1 | H4: 43833 | L4: =IF(AND($F4<(L$2+7),$F4>L$2),1, IF(AND($H4<L$2+7,$H4>L$2),3, IF(AND($F4<=L$2, $H4>=L$2), 2, "" ))) -> 1 | M4: =IF(AND($F4<(M$2+7),$F4>M$2),1, IF(AND($H4<M$2+7,$H4>M$2),3, IF(AND($F4<=M$2, $H4>=M$2), 2, "" ))) | N4: =IF(AND($F4<(N$2+7),$F4>N$2),1, IF(AND($H4<N$2+7,$H4>N$2),3, IF(AND($F4<=N$2, $H4>=N$2), 2, "" ))) | O4: =IF(AND($F4<(O$2+7),$F4>O$2),1, IF(AND($H4<O$2+7,$H4>O$2),3, IF(AND($F4<=O$2, $H4>=O$2), 2, "" ))) | P4: =IF(AND($F4<(P$2+7),$F4>P$2),1, IF(AND($H4<P$2+7,$H4>P$2),3, IF(AND($F4<=P$2, $H4>=P$2), 2, "" ))) | Q4: =IF(AND($F4<(Q$2+7),$F4>Q$2),1, IF(AND($H4<Q$2+7,$H4>Q$2),3, IF(AND($F4<=Q$2, $H4>=Q$2), 2, "" ))) | R4: =IF(AND($F4<(R$2+7),$F4>R$2),1, IF(AND($H4<R$2+7,$H4>R$2),3, IF(AND($F4<=R$2, $H4>=R$2), 2, "" ))) | S4: =IF(AND($F4<(S$2+7),$F4>S$2),1, IF(AND($H4<S$2+7,$H4>S$2),3, IF(AND($F4<=S$2, $H4>=S$2), 2, "" ))) | ... AQ4: =IF(AND($F4<(AQ$2+7),$F4>AQ$2),1, IF(AND($H4<AQ$2+7,$H4>AQ$2),3, IF(AND($F4<=AQ$2, $H4>=AQ$2), 2, "" )))
A5: 2 | B5: Structural and Electrical Due Diligences | C5: 43833 | D5: 5 | E5: 43840 | F5: 43833 | G5: 5 | H5: 43840 | L5: =IF(AND($F5<(L$2+7),$F5>L$2),1, IF(AND($H5<L$2+7,$H5>L$2),3, IF(AND($F5<=L$2, $H5>=L$2), 2, "" ))) -> 1 | M5: =IF(AND($F5<(M$2+7),$F5>M$2),1, IF(AND($H5<M$2+7,$H5>M$2),3, IF(AND($F5<=M$2, $H5>=M$2), 2, "" ))) -> 3 | N5: =IF(AND($F5<(N$2+7),$F5>N$2),1, IF(AND($H5<N$2+7,$H5>N$2),3, IF(AND($F5<=N$2, $H5>=N$2), 2, "" ))) | O5: =IF(AND($F5<(O$2+7),$F5>O$2),1, IF(AND($H5<O$2+7,$H5>O$2),3, IF(AND($F5<=O$2, $H5>=O$2), 2, "" ))) | P5: =IF(AND($F5<(P$2+7),$F5>P$2),1, IF(AND($H5<P$2+7,$H5>P$2),3, IF(AND($F5<=P$2, $H5>=P$2), 2, "" ))) | Q5: =IF(AND($F5<(Q$2+7),$F5>Q$2),1, IF(AND($H5<Q$2+7,$H5>Q$2),3, IF(AND($F5<=Q$2, $H5>=Q$2), 2, "" ))) | R5: =IF(AND($F5<(R$2+7),$F5>R$2),1, IF(AND($H5<R$2+7,$H5>R$2),3, IF(AND($F5<=R$2, $H5>=R$2), 2, "" ))) | S5: =IF(AND($F5<(S$2+7),$F5>S$2),1, IF(AND($H5<S$2+7,$H5>S$2),3, IF(AND($F5<=S$2, $H5>=S$2), 2, "" ))) | ... AQ5: =IF(AND($F5<(AQ$2+7),$F5>AQ$2),1, IF(AND($H5<AQ$2+7,$H5>AQ$2),3, IF(AND($F5<=AQ$2, $H5>=AQ$2), 2, "" )))
A6: 3 | B6: Design Confirmation | C6: 43841 | D6: 2 | E6: 43844 | F6: 43841 | G6: 2 | H6: 43844 | L6: =IF(AND($F6<(L$2+7),$F6>L$2),1, IF(AND($H6<L$2+7,$H6>L$2),3, IF(AND($F6<=L$2, $H6>=L$2), 2, "" ))) | M6: =IF(AND($F6<(M$2+7),$F6>M$2),1, IF(AND($H6<M$2+7,$H6>M$2),3, IF(AND($F6<=M$2, $H6>=M$2), 2, "" ))) | N6: =IF(AND($F6<(N$2+7),$F6>N$2),1, IF(AND($H6<N$2+7,$H6>N$2),3, IF(AND($F6<=N$2, $H6>=N$2), 2, "" ))) -> 3 | O6: =IF(AND($F6<(O$2+7),$F6>O$2),1, IF(AND($H6<O$2+7,$H6>O$2),3, IF(AND($F6<=O$2, $H6>=O$2), 2, "" ))) | P6: =IF(AND($F6<(P$2+7),$F6>P$2),1, IF(AND($H6<P$2+7,$H6>P$2),3, IF(AND($F6<=P$2, $H6>=P$2), 2, "" ))) | Q6: =IF(AND($F6<(Q$2+7),$F6>Q$2),1, IF(AND($H6<Q$2+7,$H6>Q$2),3, IF(AND($F6<=Q$2, $H6>=Q$2), 2, "" ))) | R6: =IF(AND($F6<(R$2+7),$F6>R$2),1, IF(AND($H6<R$2+7,$H6>R$2),3, IF(AND($F6<=R$2, $H6>=R$2), 2, "" ))) | S6: =IF(AND($F6<(S$2+7),$F6>S$2),1, IF(AND($H6<S$2+7,$H6>S$2),3, IF(AND($F6<=S$2, $H6>=S$2), 2, "" ))) | ... AQ6: =IF(AND($F6<(AQ$2+7),$F6>AQ$2),1, IF(AND($H6<AQ$2+7,$H6>AQ$2),3, IF(AND($F6<=AQ$2, $H6>=AQ$2), 2, "" )))
A7: 4 | B7: Equipment Procurement | C7: 43833 | E7: 43949 | F7: 43833 | H7: 43949 | L7: =IF(AND($F7<(L$2+7),$F7>L$2),1, IF(AND($H7<L$2+7,$H7>L$2),3, IF(AND($F7<=L$2, $H7>=L$2), 2, "" ))) -> 1 | M7: =IF(AND($F7<(M$2+7),$F7>M$2),1, IF(AND($H7<M$2+7,$H7>M$2),3, IF(AND($F7<=M$2, $H7>=M$2), 2, "" ))) -> 2 | N7: =IF(AND($F7<(N$2+7),$F7>N$2),1, IF(AND($H7<N$2+7,$H7>N$2),3, IF(AND($F7<=N$2, $H7>=N$2), 2, "" ))) -> 2 | O7: =IF(AND($F7<(O$2+7),$F7>O$2),1, IF(AND($H7<O$2+7,$H7>O$2),3, IF(AND($F7<=O$2, $H7>=O$2), 2, "" ))) -> 2 | P7: =IF(AND($F7<(P$2+7),$F7>P$2),1, IF(AND($H7<P$2+7,$H7>P$2),3, IF(AND($F7<=P$2, $H7>=P$2), 2, "" ))) -> 2 | Q7: =IF(AND($F7<(Q$2+7),$F7>Q$2),1, IF(AND($H7<Q$2+7,$H7>Q$2),3, IF(AND($F7<=Q$2, $H7>=Q$2), 2, "" ))) -> 2 | R7: =IF(AND($F7<(R$2+7),$F7>R$2),1, IF(AND($H7<R$2+7,$H7>R$2),3, IF(AND($F7<=R$2, $H7>=R$2), 2, "" ))) -> 2 | S7: =IF(AND($F7<(S$2+7),$F7>S$2),1, IF(AND($H7<S$2+7,$H7>S$2),3, IF(AND($F7<=S$2, $H7>=S$2), 2, "" ))) -> 2 | ... AQ7: =IF(AND($F7<(AQ$2+7),$F7>AQ$2),1, IF(AND($H7<AQ$2+7,$H7>AQ$2),3, IF(AND($F7<=AQ$2, $H7>=AQ$2), 2, "" )))
B8: Panel Procurement | C8: 43833 | D8: 5 | E8: 43840 | F8: 43833 | G8: 5 | H8: 43840 | L8: =IF(AND($F8<(L$2+7),$F8>L$2),1, IF(AND($H8<L$2+7,$H8>L$2),3, IF(AND($F8<=L$2, $H8>=L$2), 2, "" ))) -> 1 | M8: =IF(AND($F8<(M$2+7),$F8>M$2),1, IF(AND($H8<M$2+7,$H8>M$2),3, IF(AND($F8<=M$2, $H8>=M$2), 2, "" ))) -> 3 | N8: =IF(AND($F8<(N$2+7),$F8>N$2),1, IF(AND($H8<N$2+7,$H8>N$2),3, IF(AND($F8<=N$2, $H8>=N$2), 2, "" ))) | O8: =IF(AND($F8<(O$2+7),$F8>O$2),1, IF(AND($H8<O$2+7,$H8>O$2),3, IF(AND($F8<=O$2, $H8>=O$2), 2, "" ))) | P8: =IF(AND($F8<(P$2+7),$F8>P$2),1, IF(AND($H8<P$2+7,$H8>P$2),3, IF(AND($F8<=P$2, $H8>=P$2), 2, "" ))) | Q8: =IF(AND($F8<(Q$2+7),$F8>Q$2),1, IF(AND($H8<Q$2+7,$H8>Q$2),3, IF(AND($F8<=Q$2, $H8>=Q$2), 2, "" ))) | R8: =IF(AND($F8<(R$2+7),$F8>R$2),1, IF(AND($H8<R$2+7,$H8>R$2),3, IF(AND($F8<=R$2, $H8>=R$2), 2, "" ))) | S8: =IF(AND($F8<(S$2+7),$F8>S$2),1, IF(AND($H8<S$2+7,$H8>S$2),3, IF(AND($F8<=S$2, $H8>=S$2), 2, "" ))) | ... AQ8: =IF(AND($F8<(AQ$2+7),$F8>AQ$2),1, IF(AND($H8<AQ$2+7,$H8>AQ$2),3, IF(AND($F8<=AQ$2, $H8>=AQ$2), 2, "" )))
B9: Inverter Procurement | C9: 43941 | D9: 5 | E9: 43949 | F9: 43941 | G9: 5 | H9: 43949 | L9: =IF(AND($F9<(L$2+7),$F9>L$2),1, IF(AND($H9<L$2+7,$H9>L$2),3, IF(AND($F9<=L$2, $H9>=L$2), 2, "" ))) | M9: =IF(AND($F9<(M$2+7),$F9>M$2),1, IF(AND($H9<M$2+7,$H9>M$2),3, IF(AND($F9<=M$2, $H9>=M$2), 2, "" ))) | N9: =IF(AND($F9<(N$2+7),$F9>N$2),1, IF(AND($H9<N$2+7,$H9>N$2),3, IF(AND($F9<=N$2, $H9>=N$2), 2, "" ))) | O9: =IF(AND($F9<(O$2+7),$F9>O$2),1, IF(AND($H9<O$2+7,$H9>O$2),3, IF(AND($F9<=O$2, $H9>=O$2), 2, "" ))) | P9: =IF(AND($F9<(P$2+7),$F9>P$2),1, IF(AND($H9<P$2+7,$H9>P$2),3, IF(AND($F9<=P$2, $H9>=P$2), 2, "" ))) | Q9: =IF(AND($F9<(Q$2+7),$F9>Q$2),1, IF(AND($H9<Q$2+7,$H9>Q$2),3, IF(AND($F9<=Q$2, $H9>=Q$2), 2, "" ))) | R9: =IF(AND($F9<(R$2+7),$F9>R$2),1, IF(AND($H9<R$2+7,$H9>R$2),3, IF(AND($F9<=R$2, $H9>=R$2), 2, "" ))) | S9: =IF(AND($F9<(S$2+7),$F9>S$2),1, IF(AND($H9<S$2+7,$H9>S$2),3, IF(AND($F9<=S$2, $H9>=S$2), 2, "" ))) | ... AQ9: =IF(AND($F9<(AQ$2+7),$F9>AQ$2),1, IF(AND($H9<AQ$2+7,$H9>AQ$2),3, IF(AND($F9<=AQ$2, $H9>=AQ$2), 2, "" )))
B10: Mounting Structure Procurement | C10: 43941 | D10: 5 | E10: 43949 | F10: 43941 | G10: 5 | H10: 43949 | L10: =IF(AND($F10<(L$2+7),$F10>L$2),1, IF(AND($H10<L$2+7,$H10>L$2),3, IF(AND($F10<=L$2, $H10>=L$2), 2, "" ))) | M10: =IF(AND($F10<(M$2+7),$F10>M$2),1, IF(AND($H10<M$2+7,$H10>M$2),3, IF(AND($F10<=M$2, $H10>=M$2), 2, "" ))) | N10: =IF(AND($F10<(N$2+7),$F10>N$2),1, IF(AND($H10<N$2+7,$H10>N$2),3, IF(AND($F10<=N$2, $H10>=N$2), 2, "" ))) | O10: =IF(AND($F10<(O$2+7),$F10>O$2),1, IF(AND($H10<O$2+7,$H10>O$2),3, IF(AND($F10<=O$2, $H10>=O$2), 2, "" ))) | P10: =IF(AND($F10<(P$2+7),$F10>P$2),1, IF(AND($H10<P$2+7,$H10>P$2),3, IF(AND($F10<=P$2, $H10>=P$2), 2, "" ))) | Q10: =IF(AND($F10<(Q$2+7),$F10>Q$2),1, IF(AND($H10<Q$2+7,$H10>Q$2),3, IF(AND($F10<=Q$2, $H10>=Q$2), 2, "" ))) | R10: =IF(AND($F10<(R$2+7),$F10>R$2),1, IF(AND($H10<R$2+7,$H10>R$2),3, IF(AND($F10<=R$2, $H10>=R$2), 2, "" ))) | S10: =IF(AND($F10<(S$2+7),$F10>S$2),1, IF(AND($H10<S$2+7,$H10>S$2),3, IF(AND($F10<=S$2, $H10>=S$2), 2, "" ))) | ... AQ10: =IF(AND($F10<(AQ$2+7),$F10>AQ$2),1, IF(AND($H10<AQ$2+7,$H10>AQ$2),3, IF(AND($F10<=AQ$2, $H10>=AQ$2), 2, "" )))
B11: BOS Procurement | C11: 43941 | D11: 5 | E11: 43949 | F11: 43941 | G11: 5 | H11: 43949 | L11: =IF(AND($F11<(L$2+7),$F11>L$2),1, IF(AND($H11<L$2+7,$H11>L$2),3, IF(AND($F11<=L$2, $H11>=L$2), 2, "" ))) | M11: =IF(AND($F11<(M$2+7),$F11>M$2),1, IF(AND($H11<M$2+7,$H11>M$2),3, IF(AND($F11<=M$2, $H11>=M$2), 2, "" ))) | N11: =IF(AND($F11<(N$2+7),$F11>N$2),1, IF(AND($H11<N$2+7,$H11>N$2),3, IF(AND($F11<=N$2, $H11>=N$2), 2, "" ))) | O11: =IF(AND($F11<(O$2+7),$F11>O$2),1, IF(AND($H11<O$2+7,$H11>O$2),3, IF(AND($F11<=O$2, $H11>=O$2), 2, "" ))) | P11: =IF(AND($F11<(P$2+7),$F11>P$2),1, IF(AND($H11<P$2+7,$H11>P$2),3, IF(AND($F11<=P$2, $H11>=P$2), 2, "" ))) | Q11: =IF(AND($F11<(Q$2+7),$F11>Q$2),1, IF(AND($H11<Q$2+7,$H11>Q$2),3, IF(AND($F11<=Q$2, $H11>=Q$2), 2, "" ))) | R11: =IF(AND($F11<(R$2+7),$F11>R$2),1, IF(AND($H11<R$2+7,$H11>R$2),3, IF(AND($F11<=R$2, $H11>=R$2), 2, "" ))) | S11: =IF(AND($F11<(S$2+7),$F11>S$2),1, IF(AND($H11<S$2+7,$H11>S$2),3, IF(AND($F11<=S$2, $H11>=S$2), 2, "" ))) | ... AQ11: =IF(AND($F11<(AQ$2+7),$F11>AQ$2),1, IF(AND($H11<AQ$2+7,$H11>AQ$2),3, IF(AND($F11<=AQ$2, $H11>=AQ$2), 2, "" )))
A12: 5 | B12: Internal Project Kick off | C12: 43936 | D12: 5 | E12: 43943 | F12: 43936 | G12: 5 | H12: 43943
A13: 6 | B13: Client Project Kick-off | C13: 43963 | D13: 5 | E13: 43970 | F13: 43963 | G13: 5 | H13: 43970 | L13: =IF(AND($F13<(L$2+7),$F13>L$2),1, IF(AND($H13<L$2+7,$H13>L$2),3, IF(AND($F13<=L$2, $H13>=L$2), 2, "" ))) | M13: =IF(AND($F13<(M$2+7),$F13>M$2),1, IF(AND($H13<M$2+7,$H13>M$2),3, IF(AND($F13<=M$2, $H13>=M$2), 2, "" ))) | N13: =IF(AND($F13<(N$2+7),$F13>N$2),1, IF(AND($H13<N$2+7,$H13>N$2),3, IF(AND($F13<=N$2, $H13>=N$2), 2, "" ))) | O13: =IF(AND($F13<(O$2+7),$F13>O$2),1, IF(AND($H13<O$2+7,$H13>O$2),3, IF(AND($F13<=O$2, $H13>=O$2), 2, "" ))) | P13: =IF(AND($F13<(P$2+7),$F13>P$2),1, IF(AND($H13<P$2+7,$H13>P$2),3, IF(AND($F13<=P$2, $H13>=P$2), 2, "" ))) | Q13: =IF(AND($F13<(Q$2+7),$F13>Q$2),1, IF(AND($H13<Q$2+7,$H13>Q$2),3, IF(AND($F13<=Q$2, $H13>=Q$2), 2, "" ))) | R13: =IF(AND($F13<(R$2+7),$F13>R$2),1, IF(AND($H13<R$2+7,$H13>R$2),3, IF(AND($F13<=R$2, $H13>=R$2), 2, "" ))) | S13: =IF(AND($F13<(S$2+7),$F13>S$2),1, IF(AND($H13<S$2+7,$H13>S$2),3, IF(AND($F13<=S$2, $H13>=S$2), 2, "" ))) | ... AQ13: =IF(AND($F13<(AQ$2+7),$F13>AQ$2),1, IF(AND($H13<AQ$2+7,$H13>AQ$2),3, IF(AND($F13<=AQ$2, $H13>=AQ$2), 2, "" )))
A14: 7 | B14: Equipment Delivery | C14: 43983 | D14: 9 | E14: 43994 | F14: 43983 | G14: 9 | H14: 43994 | L14: =IF(AND($F14<(L$2+7),$F14>L$2),1, IF(AND($H14<L$2+7,$H14>L$2),3, IF(AND($F14<=L$2, $H14>=L$2), 2, "" ))) | M14: =IF(AND($F14<(M$2+7),$F14>M$2),1, IF(AND($H14<M$2+7,$H14>M$2),3, IF(AND($F14<=M$2, $H14>=M$2), 2, "" ))) | N14: =IF(AND($F14<(N$2+7),$F14>N$2),1, IF(AND($H14<N$2+7,$H14>N$2),3, IF(AND($F14<=N$2, $H14>=N$2), 2, "" ))) | O14: =IF(AND($F14<(O$2+7),$F14>O$2),1, IF(AND($H14<O$2+7,$H14>O$2),3, IF(AND($F14<=O$2, $H14>=O$2), 2, "" ))) | P14: =IF(AND($F14<(P$2+7),$F14>P$2),1, IF(AND($H14<P$2+7,$H14>P$2),3, IF(AND($F14<=P$2, $H14>=P$2), 2, "" ))) | Q14: =IF(AND($F14<(Q$2+7),$F14>Q$2),1, IF(AND($H14<Q$2+7,$H14>Q$2),3, IF(AND($F14<=Q$2, $H14>=Q$2), 2, "" ))) | R14: =IF(AND($F14<(R$2+7),$F14>R$2),1, IF(AND($H14<R$2+7,$H14>R$2),3, IF(AND($F14<=R$2, $H14>=R$2), 2, "" ))) | S14: =IF(AND($F14<(S$2+7),$F14>S$2),1, IF(AND($H14<S$2+7,$H14>S$2),3, IF(AND($F14<=S$2, $H14>=S$2), 2, "" ))) | ... AQ14: =IF(AND($F14<(AQ$2+7),$F14>AQ$2),1, IF(AND($H14<AQ$2+7,$H14>AQ$2),3, IF(AND($F14<=AQ$2, $H14>=AQ$2), 2, "" )))
B15: Mounting Structure Delivery | C15: 43983 | D15: 2 | E15: 43985 | F15: 43983 | G15: 2 | H15: 43985
B16: Panel Delivery | C16: 43990 | D16: 2 | E16: 43992 | F16: 43990 | G16: 2 | H16: 43992 | L16: =IF(AND($F16<(L$2+7),$F16>L$2),1, IF(AND($H16<L$2+7,$H16>L$2),3, IF(AND($F16<=L$2, $H16>=L$2), 2, "" ))) | M16: =IF(AND($F16<(M$2+7),$F16>M$2),1, IF(AND($H16<M$2+7,$H16>M$2),3, IF(AND($F16<=M$2, $H16>=M$2), 2, "" ))) | N16: =IF(AND($F16<(N$2+7),$F16>N$2),1, IF(AND($H16<N$2+7,$H16>N$2),3, IF(AND($F16<=N$2, $H16>=N$2), 2, "" ))) | O16: =IF(AND($F16<(O$2+7),$F16>O$2),1, IF(AND($H16<O$2+7,$H16>O$2),3, IF(AND($F16<=O$2, $H16>=O$2), 2, "" ))) | P16: =IF(AND($F16<(P$2+7),$F16>P$2),1, IF(AND($H16<P$2+7,$H16>P$2),3, IF(AND($F16<=P$2, $H16>=P$2), 2, "" ))) | Q16: =IF(AND($F16<(Q$2+7),$F16>Q$2),1, IF(AND($H16<Q$2+7,$H16>Q$2),3, IF(AND($F16<=Q$2, $H16>=Q$2), 2, "" ))) | R16: =IF(AND($F16<(R$2+7),$F16>R$2),1, IF(AND($H16<R$2+7,$H16>R$2),3, IF(AND($F16<=R$2, $H16>=R$2), 2, "" ))) | S16: =IF(AND($F16<(S$2+7),$F16>S$2),1, IF(AND($H16<S$2+7,$H16>S$2),3, IF(AND($F16<=S$2, $H16>=S$2), 2, "" ))) | ... AQ16: =IF(AND($F16<(AQ$2+7),$F16>AQ$2),1, IF(AND($H16<AQ$2+7,$H16>AQ$2),3, IF(AND($F16<=AQ$2, $H16>=AQ$2), 2, "" )))
B17: Generator Delivery | C17: 43983 | D17: 2 | E17: 43985 | F17: 43983 | G17: 2 | H17: 43985
A18: B | B18: PAYMENT MILESTONE 2: DELIVERY OF PV PANELS | C18: 43992 | D18: 2 | E18: 43994 | F18: 43992 | G18: 2 | H18: 43994
B19: Inverter Delivery | C19: 43983 | D19: 2 | E19: 43985 | F19: 43983 | G19: 2 | H19: 43985 | L19: =IF(AND($F19<(L$2+7),$F19>L$2),1, IF(AND($H19<L$2+7,$H19>L$2),3, IF(AND($F19<=L$2, $H19>=L$2), 2, "" ))) | M19: =IF(AND($F19<(M$2+7),$F19>M$2),1, IF(AND($H19<M$2+7,$H19>M$2),3, IF(AND($F19<=M$2, $H19>=M$2), 2, "" ))) | N19: =IF(AND($F19<(N$2+7),$F19>N$2),1, IF(AND($H19<N$2+7,$H19>N$2),3, IF(AND($F19<=N$2, $H19>=N$2), 2, "" ))) | O19: =IF(AND($F19<(O$2+7),$F19>O$2),1, IF(AND($H19<O$2+7,$H19>O$2),3, IF(AND($F19<=O$2, $H19>=O$2), 2, "" ))) | P19: =IF(AND($F19<(P$2+7),$F19>P$2),1, IF(AND($H19<P$2+7,$H19>P$2),3, IF(AND($F19<=P$2, $H19>=P$2), 2, "" ))) | Q19: =IF(AND($F19<(Q$2+7),$F19>Q$2),1, IF(AND($H19<Q$2+7,$H19>Q$2),3, IF(AND($F19<=Q$2, $H19>=Q$2), 2, "" ))) | R19: =IF(AND($F19<(R$2+7),$F19>R$2),1, IF(AND($H19<R$2+7,$H19>R$2),3, IF(AND($F19<=R$2, $H19>=R$2), 2, "" ))) | S19: =IF(AND($F19<(S$2+7),$F19>S$2),1, IF(AND($H19<S$2+7,$H19>S$2),3, IF(AND($F19<=S$2, $H19>=S$2), 2, "" ))) | ... AQ19: =IF(AND($F19<(AQ$2+7),$F19>AQ$2),1, IF(AND($H19<AQ$2+7,$H19>AQ$2),3, IF(AND($F19<=AQ$2, $H19>=AQ$2), 2, "" )))
B20: BOS Delivery | C20: 43983 | D20: 1 | E20: 43984 | F20: 43983 | G20: 1 | H20: 43984 | L20: =IF(AND($F20<(L$2+7),$F20>L$2),1, IF(AND($H20<L$2+7,$H20>L$2),3, IF(AND($F20<=L$2, $H20>=L$2), 2, "" ))) | M20: =IF(AND($F20<(M$2+7),$F20>M$2),1, IF(AND($H20<M$2+7,$H20>M$2),3, IF(AND($F20<=M$2, $H20>=M$2), 2, "" ))) | N20: =IF(AND($F20<(N$2+7),$F20>N$2),1, IF(AND($H20<N$2+7,$H20>N$2),3, IF(AND($F20<=N$2, $H20>=N$2), 2, "" ))) | O20: =IF(AND($F20<(O$2+7),$F20>O$2),1, IF(AND($H20<O$2+7,$H20>O$2),3, IF(AND($F20<=O$2, $H20>=O$2), 2, "" ))) | P20: =IF(AND($F20<(P$2+7),$F20>P$2),1, IF(AND($H20<P$2+7,$H20>P$2),3, IF(AND($F20<=P$2, $H20>=P$2), 2, "" ))) | Q20: =IF(AND($F20<(Q$2+7),$F20>Q$2),1, IF(AND($H20<Q$2+7,$H20>Q$2),3, IF(AND($F20<=Q$2, $H20>=Q$2), 2, "" ))) | R20: =IF(AND($F20<(R$2+7),$F20>R$2),1, IF(AND($H20<R$2+7,$H20>R$2),3, IF(AND($F20<=R$2, $H20>=R$2), 2, "" ))) | S20: =IF(AND($F20<(S$2+7),$F20>S$2),1, IF(AND($H20<S$2+7,$H20>S$2),3, IF(AND($F20<=S$2, $H20>=S$2), 2, "" ))) | ... AQ20: =IF(AND($F20<(AQ$2+7),$F20>AQ$2),1, IF(AND($H20<AQ$2+7,$H20>AQ$2),3, IF(AND($F20<=AQ$2, $H20>=AQ$2), 2, "" )))
A21: C | B21: PAYMENT MILESTONE 3: DELIVERY OF INVERTERS AND BOS | C21: 43985 | D21: 2 | E21: 43987 | F21: 43985 | G21: 2 | H21: 43987
A22: 8 | B22: Installation | C22: 43990 | D22: 22 | E22: 44012 | F22: 43990 | G22: 22 | H22: 44012 | L22: =IF(AND($F22<(L$2+7),$F22>L$2),1, IF(AND($H22<L$2+7,$H22>L$2),3, IF(AND($F22<=L$2, $H22>=L$2), 2, "" ))) | M22: =IF(AND($F22<(M$2+7),$F22>M$2),1, IF(AND($H22<M$2+7,$H22>M$2),3, IF(AND($F22<=M$2, $H22>=M$2), 2, "" ))) | N22: =IF(AND($F22<(N$2+7),$F22>N$2),1, IF(AND($H22<N$2+7,$H22>N$2),3, IF(AND($F22<=N$2, $H22>=N$2), 2, "" ))) | O22: =IF(AND($F22<(O$2+7),$F22>O$2),1, IF(AND($H22<O$2+7,$H22>O$2),3, IF(AND($F22<=O$2, $H22>=O$2), 2, "" ))) | P22: =IF(AND($F22<(P$2+7),$F22>P$2),1, IF(AND($H22<P$2+7,$H22>P$2),3, IF(AND($F22<=P$2, $H22>=P$2), 2, "" ))) | Q22: =IF(AND($F22<(Q$2+7),$F22>Q$2),1, IF(AND($H22<Q$2+7,$H22>Q$2),3, IF(AND($F22<=Q$2, $H22>=Q$2), 2, "" ))) | R22: =IF(AND($F22<(R$2+7),$F22>R$2),1, IF(AND($H22<R$2+7,$H22>R$2),3, IF(AND($F22<=R$2, $H22>=R$2), 2, "" ))) | S22: =IF(AND($F22<(S$2+7),$F22>S$2),1, IF(AND($H22<S$2+7,$H22>S$2),3, IF(AND($F22<=S$2, $H22>=S$2), 2, "" ))) | ... AQ22: =IF(AND($F22<(AQ$2+7),$F22>AQ$2),1, IF(AND($H22<AQ$2+7,$H22>AQ$2),3, IF(AND($F22<=AQ$2, $H22>=AQ$2), 2, "" ))) -> 2
B23: Site Establishment | C23: 43990 | D23: 1 | E23: 43991 | F23: 43990 | G23: 1 | H23: 43991 | J23: Installation placed on hold due to Covid-19 case | L23: =IF(AND($F23<(L$2+7),$F23>L$2),1, IF(AND($H23<L$2+7,$H23>L$2),3, IF(AND($F23<=L$2, $H23>=L$2), 2, "" ))) | M23: =IF(AND($F23<(M$2+7),$F23>M$2),1, IF(AND($H23<M$2+7,$H23>M$2),3, IF(AND($F23<=M$2, $H23>=M$2), 2, "" ))) | N23: =IF(AND($F23<(N$2+7),$F23>N$2),1, IF(AND($H23<N$2+7,$H23>N$2),3, IF(AND($F23<=N$2, $H23>=N$2), 2, "" ))) | O23: =IF(AND($F23<(O$2+7),$F23>O$2),1, IF(AND($H23<O$2+7,$H23>O$2),3, IF(AND($F23<=O$2, $H23>=O$2), 2, "" ))) | P23: =IF(AND($F23<(P$2+7),$F23>P$2),1, IF(AND($H23<P$2+7,$H23>P$2),3, IF(AND($F23<=P$2, $H23>=P$2), 2, "" ))) | Q23: =IF(AND($F23<(Q$2+7),$F23>Q$2),1, IF(AND($H23<Q$2+7,$H23>Q$2),3, IF(AND($F23<=Q$2, $H23>=Q$2), 2, "" ))) | R23: =IF(AND($F23<(R$2+7),$F23>R$2),1, IF(AND($H23<R$2+7,$H23>R$2),3, IF(AND($F23<=R$2, $H23>=R$2), 2, "" ))) | S23: =IF(AND($F23<(S$2+7),$F23>S$2),1, IF(AND($H23<S$2+7,$H23>S$2),3, IF(AND($F23<=S$2, $H23>=S$2), 2, "" ))) | ... AQ23: =IF(AND($F23<(AQ$2+7),$F23>AQ$2),1, IF(AND($H23<AQ$2+7,$H23>AQ$2),3, IF(AND($F23<=AQ$2, $H23>=AQ$2), 2, "" )))
A24: 9 | B24: DC Works | C24: 43991 | D24: 16 | E24: 44012 | F24: 43991 | G24: 16 | H24: 44012 | L24: =IF(AND($F24<(L$2+7),$F24>L$2),1, IF(AND($H24<L$2+7,$H24>L$2),3, IF(AND($F24<=L$2, $H24>=L$2), 2, "" ))) | M24: =IF(AND($F24<(M$2+7),$F24>M$2),1, IF(AND($H24<M$2+7,$H24>M$2),3, IF(AND($F24<=M$2, $H24>=M$2), 2, "" ))) | N24: =IF(AND($F24<(N$2+7),$F24>N$2),1, IF(AND($H24<N$2+7,$H24>N$2),3, IF(AND($F24<=N$2, $H24>=N$2), 2, "" ))) | O24: =IF(AND($F24<(O$2+7),$F24>O$2),1, IF(AND($H24<O$2+7,$H24>O$2),3, IF(AND($F24<=O$2, $H24>=O$2), 2, "" ))) | P24: =IF(AND($F24<(P$2+7),$F24>P$2),1, IF(AND($H24<P$2+7,$H24>P$2),3, IF(AND($F24<=P$2, $H24>=P$2), 2, "" ))) | Q24: =IF(AND($F24<(Q$2+7),$F24>Q$2),1, IF(AND($H24<Q$2+7,$H24>Q$2),3, IF(AND($F24<=Q$2, $H24>=Q$2), 2, "" ))) | R24: =IF(AND($F24<(R$2+7),$F24>R$2),1, IF(AND($H24<R$2+7,$H24>R$2),3, IF(AND($F24<=R$2, $H24>=R$2), 2, "" ))) | S24: =IF(AND($F24<(S$2+7),$F24>S$2),1, IF(AND($H24<S$2+7,$H24>S$2),3, IF(AND($F24<=S$2, $H24>=S$2), 2, "" ))) | ... AQ24: =IF(AND($F24<(AQ$2+7),$F24>AQ$2),1, IF(AND($H24<AQ$2+7,$H24>AQ$2),3, IF(AND($F24<=AQ$2, $H24>=AQ$2), 2, "" ))) -> 2
B25: Mounting structure Installation | C25: 43991 | D25: 4 | E25: 43997 | F25: 43991 | G25: 4 | H25: 43997 | L25: =IF(AND($F25<(L$2+7),$F25>L$2),1, IF(AND($H25<L$2+7,$H25>L$2),3, IF(AND($F25<=L$2, $H25>=L$2), 2, "" ))) | M25: =IF(AND($F25<(M$2+7),$F25>M$2),1, IF(AND($H25<M$2+7,$H25>M$2),3, IF(AND($F25<=M$2, $H25>=M$2), 2, "" ))) | N25: =IF(AND($F25<(N$2+7),$F25>N$2),1, IF(AND($H25<N$2+7,$H25>N$2),3, IF(AND($F25<=N$2, $H25>=N$2), 2, "" ))) | O25: =IF(AND($F25<(O$2+7),$F25>O$2),1, IF(AND($H25<O$2+7,$H25>O$2),3, IF(AND($F25<=O$2, $H25>=O$2), 2, "" ))) | P25: =IF(AND($F25<(P$2+7),$F25>P$2),1, IF(AND($H25<P$2+7,$H25>P$2),3, IF(AND($F25<=P$2, $H25>=P$2), 2, "" ))) | Q25: =IF(AND($F25<(Q$2+7),$F25>Q$2),1, IF(AND($H25<Q$2+7,$H25>Q$2),3, IF(AND($F25<=Q$2, $H25>=Q$2), 2, "" ))) | R25: =IF(AND($F25<(R$2+7),$F25>R$2),1, IF(AND($H25<R$2+7,$H25>R$2),3, IF(AND($F25<=R$2, $H25>=R$2), 2, "" ))) | S25: =IF(AND($F25<(S$2+7),$F25>S$2),1, IF(AND($H25<S$2+7,$H25>S$2),3, IF(AND($F25<=S$2, $H25>=S$2), 2, "" ))) | ... AQ25: =IF(AND($F25<(AQ$2+7),$F25>AQ$2),1, IF(AND($H25<AQ$2+7,$H25>AQ$2),3, IF(AND($F25<=AQ$2, $H25>=AQ$2), 2, "" )))
B26: Cable tray Installation | C26: 43997 | D26: 3 | E26: 44004 | F26: 43997 | G26: 3 | H26: 44004 | L26: =IF(AND($F26<(L$2+7),$F26>L$2),1, IF(AND($H26<L$2+7,$H26>L$2),3, IF(AND($F26<=L$2, $H26>=L$2), 2, "" ))) | M26: =IF(AND($F26<(M$2+7),$F26>M$2),1, IF(AND($H26<M$2+7,$H26>M$2),3, IF(AND($F26<=M$2, $H26>=M$2), 2, "" ))) | N26: =IF(AND($F26<(N$2+7),$F26>N$2),1, IF(AND($H26<N$2+7,$H26>N$2),3, IF(AND($F26<=N$2, $H26>=N$2), 2, "" ))) | O26: =IF(AND($F26<(O$2+7),$F26>O$2),1, IF(AND($H26<O$2+7,$H26>O$2),3, IF(AND($F26<=O$2, $H26>=O$2), 2, "" ))) | P26: =IF(AND($F26<(P$2+7),$F26>P$2),1, IF(AND($H26<P$2+7,$H26>P$2),3, IF(AND($F26<=P$2, $H26>=P$2), 2, "" ))) | Q26: =IF(AND($F26<(Q$2+7),$F26>Q$2),1, IF(AND($H26<Q$2+7,$H26>Q$2),3, IF(AND($F26<=Q$2, $H26>=Q$2), 2, "" ))) | R26: =IF(AND($F26<(R$2+7),$F26>R$2),1, IF(AND($H26<R$2+7,$H26>R$2),3, IF(AND($F26<=R$2, $H26>=R$2), 2, "" ))) | S26: =IF(AND($F26<(S$2+7),$F26>S$2),1, IF(AND($H26<S$2+7,$H26>S$2),3, IF(AND($F26<=S$2, $H26>=S$2), 2, "" ))) | ... AQ26: =IF(AND($F26<(AQ$2+7),$F26>AQ$2),1, IF(AND($H26<AQ$2+7,$H26>AQ$2),3, IF(AND($F26<=AQ$2, $H26>=AQ$2), 2, "" )))
B27: DC Cable Installation | C27: 44004 | D27: 2 | E27: 44006 | F27: 44004 | G27: 2 | H27: 44006 | L27: =IF(AND($F27<(L$2+7),$F27>L$2),1, IF(AND($H27<L$2+7,$H27>L$2),3, IF(AND($F27<=L$2, $H27>=L$2), 2, "" ))) | M27: =IF(AND($F27<(M$2+7),$F27>M$2),1, IF(AND($H27<M$2+7,$H27>M$2),3, IF(AND($F27<=M$2, $H27>=M$2), 2, "" ))) | N27: =IF(AND($F27<(N$2+7),$F27>N$2),1, IF(AND($H27<N$2+7,$H27>N$2),3, IF(AND($F27<=N$2, $H27>=N$2), 2, "" ))) | O27: =IF(AND($F27<(O$2+7),$F27>O$2),1, IF(AND($H27<O$2+7,$H27>O$2),3, IF(AND($F27<=O$2, $H27>=O$2), 2, "" ))) | P27: =IF(AND($F27<(P$2+7),$F27>P$2),1, IF(AND($H27<P$2+7,$H27>P$2),3, IF(AND($F27<=P$2, $H27>=P$2), 2, "" ))) | Q27: =IF(AND($F27<(Q$2+7),$F27>Q$2),1, IF(AND($H27<Q$2+7,$H27>Q$2),3, IF(AND($F27<=Q$2, $H27>=Q$2), 2, "" ))) | R27: =IF(AND($F27<(R$2+7),$F27>R$2),1, IF(AND($H27<R$2+7,$H27>R$2),3, IF(AND($F27<=R$2, $H27>=R$2), 2, "" ))) | S27: =IF(AND($F27<(S$2+7),$F27>S$2),1, IF(AND($H27<S$2+7,$H27>S$2),3, IF(AND($F27<=S$2, $H27>=S$2), 2, "" ))) | ... AQ27: =IF(AND($F27<(AQ$2+7),$F27>AQ$2),1, IF(AND($H27<AQ$2+7,$H27>AQ$2),3, IF(AND($F27<=AQ$2, $H27>=AQ$2), 2, "" )))
B28: Module Installation | C28: 44006 | D28: 4 | E28: 44012 | F28: 44006 | G28: 4 | H28: 44012 | L28: =IF(AND($F28<(L$2+7),$F28>L$2),1, IF(AND($H28<L$2+7,$H28>L$2),3, IF(AND($F28<=L$2, $H28>=L$2), 2, "" ))) | M28: =IF(AND($F28<(M$2+7),$F28>M$2),1, IF(AND($H28<M$2+7,$H28>M$2),3, IF(AND($F28<=M$2, $H28>=M$2), 2, "" ))) | N28: =IF(AND($F28<(N$2+7),$F28>N$2),1, IF(AND($H28<N$2+7,$H28>N$2),3, IF(AND($F28<=N$2, $H28>=N$2), 2, "" ))) | O28: =IF(AND($F28<(O$2+7),$F28>O$2),1, IF(AND($H28<O$2+7,$H28>O$2),3, IF(AND($F28<=O$2, $H28>=O$2), 2, "" ))) | P28: =IF(AND($F28<(P$2+7),$F28>P$2),1, IF(AND($H28<P$2+7,$H28>P$2),3, IF(AND($F28<=P$2, $H28>=P$2), 2, "" ))) | Q28: =IF(AND($F28<(Q$2+7),$F28>Q$2),1, IF(AND($H28<Q$2+7,$H28>Q$2),3, IF(AND($F28<=Q$2, $H28>=Q$2), 2, "" ))) | R28: =IF(AND($F28<(R$2+7),$F28>R$2),1, IF(AND($H28<R$2+7,$H28>R$2),3, IF(AND($F28<=R$2, $H28>=R$2), 2, "" ))) | S28: =IF(AND($F28<(S$2+7),$F28>S$2),1, IF(AND($H28<S$2+7,$H28>S$2),3, IF(AND($F28<=S$2, $H28>=S$2), 2, "" ))) | ... AQ28: =IF(AND($F28<(AQ$2+7),$F28>AQ$2),1, IF(AND($H28<AQ$2+7,$H28>AQ$2),3, IF(AND($F28<=AQ$2, $H28>=AQ$2), 2, "" ))) -> 2
B29: Earth Cable Installation | C29: 44004 | D29: 1 | E29: 44005 | F29: 44004 | G29: 1 | H29: 44005 | L29: =IF(AND($F29<(L$2+7),$F29>L$2),1, IF(AND($H29<L$2+7,$H29>L$2),3, IF(AND($F29<=L$2, $H29>=L$2), 2, "" ))) | M29: =IF(AND($F29<(M$2+7),$F29>M$2),1, IF(AND($H29<M$2+7,$H29>M$2),3, IF(AND($F29<=M$2, $H29>=M$2), 2, "" ))) | N29: =IF(AND($F29<(N$2+7),$F29>N$2),1, IF(AND($H29<N$2+7,$H29>N$2),3, IF(AND($F29<=N$2, $H29>=N$2), 2, "" ))) | O29: =IF(AND($F29<(O$2+7),$F29>O$2),1, IF(AND($H29<O$2+7,$H29>O$2),3, IF(AND($F29<=O$2, $H29>=O$2), 2, "" ))) | P29: =IF(AND($F29<(P$2+7),$F29>P$2),1, IF(AND($H29<P$2+7,$H29>P$2),3, IF(AND($F29<=P$2, $H29>=P$2), 2, "" ))) | Q29: =IF(AND($F29<(Q$2+7),$F29>Q$2),1, IF(AND($H29<Q$2+7,$H29>Q$2),3, IF(AND($F29<=Q$2, $H29>=Q$2), 2, "" ))) | R29: =IF(AND($F29<(R$2+7),$F29>R$2),1, IF(AND($H29<R$2+7,$H29>R$2),3, IF(AND($F29<=R$2, $H29>=R$2), 2, "" ))) | S29: =IF(AND($F29<(S$2+7),$F29>S$2),1, IF(AND($H29<S$2+7,$H29>S$2),3, IF(AND($F29<=S$2, $H29>=S$2), 2, "" ))) | ... AQ29: =IF(AND($F29<(AQ$2+7),$F29>AQ$2),1, IF(AND($H29<AQ$2+7,$H29>AQ$2),3, IF(AND($F29<=AQ$2, $H29>=AQ$2), 2, "" )))
A30: 10 | B30: AC Works | C30: 43991 | D30: 8 | E30: 44000 | F30: 43991 | G30: 8 | H30: 44000
B31: Inverters Installation | C31: 43991 | D31: 2 | E31: 43993 | F31: 43991 | G31: 2 | H31: 43993 | L31: =IF(AND($F31<(L$2+7),$F31>L$2),1, IF(AND($H31<L$2+7,$H31>L$2),3, IF(AND($F31<=L$2, $H31>=L$2), 2, "" ))) | M31: =IF(AND($F31<(M$2+7),$F31>M$2),1, IF(AND($H31<M$2+7,$H31>M$2),3, IF(AND($F31<=M$2, $H31>=M$2), 2, "" ))) | N31: =IF(AND($F31<(N$2+7),$F31>N$2),1, IF(AND($H31<N$2+7,$H31>N$2),3, IF(AND($F31<=N$2, $H31>=N$2), 2, "" ))) | O31: =IF(AND($F31<(O$2+7),$F31>O$2),1, IF(AND($H31<O$2+7,$H31>O$2),3, IF(AND($F31<=O$2, $H31>=O$2), 2, "" ))) | P31: =IF(AND($F31<(P$2+7),$F31>P$2),1, IF(AND($H31<P$2+7,$H31>P$2),3, IF(AND($F31<=P$2, $H31>=P$2), 2, "" ))) | Q31: =IF(AND($F31<(Q$2+7),$F31>Q$2),1, IF(AND($H31<Q$2+7,$H31>Q$2),3, IF(AND($F31<=Q$2, $H31>=Q$2), 2, "" ))) | R31: =IF(AND($F31<(R$2+7),$F31>R$2),1, IF(AND($H31<R$2+7,$H31>R$2),3, IF(AND($F31<=R$2, $H31>=R$2), 2, "" ))) | S31: =IF(AND($F31<(S$2+7),$F31>S$2),1, IF(AND($H31<S$2+7,$H31>S$2),3, IF(AND($F31<=S$2, $H31>=S$2), 2, "" ))) | ... AQ31: =IF(AND($F31<(AQ$2+7),$F31>AQ$2),1, IF(AND($H31<AQ$2+7,$H31>AQ$2),3, IF(AND($F31<=AQ$2, $H31>=AQ$2), 2, "" )))
B32: AC BOS Installation | C32: 43993 | D32: 3 | E32: 44000 | F32: 43993 | G32: 3 | H32: 44000 | L32: =IF(AND($F32<(L$2+7),$F32>L$2),1, IF(AND($H32<L$2+7,$H32>L$2),3, IF(AND($F32<=L$2, $H32>=L$2), 2, "" ))) | M32: =IF(AND($F32<(M$2+7),$F32>M$2),1, IF(AND($H32<M$2+7,$H32>M$2),3, IF(AND($F32<=M$2, $H32>=M$2), 2, "" ))) | N32: =IF(AND($F32<(N$2+7),$F32>N$2),1, IF(AND($H32<N$2+7,$H32>N$2),3, IF(AND($F32<=N$2, $H32>=N$2), 2, "" ))) | O32: =IF(AND($F32<(O$2+7),$F32>O$2),1, IF(AND($H32<O$2+7,$H32>O$2),3, IF(AND($F32<=O$2, $H32>=O$2), 2, "" ))) | P32: =IF(AND($F32<(P$2+7),$F32>P$2),1, IF(AND($H32<P$2+7,$H32>P$2),3, IF(AND($F32<=P$2, $H32>=P$2), 2, "" ))) | Q32: =IF(AND($F32<(Q$2+7),$F32>Q$2),1, IF(AND($H32<Q$2+7,$H32>Q$2),3, IF(AND($F32<=Q$2, $H32>=Q$2), 2, "" ))) | R32: =IF(AND($F32<(R$2+7),$F32>R$2),1, IF(AND($H32<R$2+7,$H32>R$2),3, IF(AND($F32<=R$2, $H32>=R$2), 2, "" ))) | S32: =IF(AND($F32<(S$2+7),$F32>S$2),1, IF(AND($H32<S$2+7,$H32>S$2),3, IF(AND($F32<=S$2, $H32>=S$2), 2, "" ))) | ... AQ32: =IF(AND($F32<(AQ$2+7),$F32>AQ$2),1, IF(AND($H32<AQ$2+7,$H32>AQ$2),3, IF(AND($F32<=AQ$2, $H32>=AQ$2), 2, "" )))
B33: AC Cable/Tie-In | C33: 43992 | D33: 3 | E33: 43997 | F33: 43992 | G33: 3 | H33: 43997 | L33: =IF(AND($F33<(L$2+7),$F33>L$2),1, IF(AND($H33<L$2+7,$H33>L$2),3, IF(AND($F33<=L$2, $H33>=L$2), 2, "" ))) | M33: =IF(AND($F33<(M$2+7),$F33>M$2),1, IF(AND($H33<M$2+7,$H33>M$2),3, IF(AND($F33<=M$2, $H33>=M$2), 2, "" ))) | N33: =IF(AND($F33<(N$2+7),$F33>N$2),1, IF(AND($H33<N$2+7,$H33>N$2),3, IF(AND($F33<=N$2, $H33>=N$2), 2, "" ))) | O33: =IF(AND($F33<(O$2+7),$F33>O$2),1, IF(AND($H33<O$2+7,$H33>O$2),3, IF(AND($F33<=O$2, $H33>=O$2), 2, "" ))) | P33: =IF(AND($F33<(P$2+7),$F33>P$2),1, IF(AND($H33<P$2+7,$H33>P$2),3, IF(AND($F33<=P$2, $H33>=P$2), 2, "" ))) | Q33: =IF(AND($F33<(Q$2+7),$F33>Q$2),1, IF(AND($H33<Q$2+7,$H33>Q$2),3, IF(AND($F33<=Q$2, $H33>=Q$2), 2, "" ))) | R33: =IF(AND($F33<(R$2+7),$F33>R$2),1, IF(AND($H33<R$2+7,$H33>R$2),3, IF(AND($F33<=R$2, $H33>=R$2), 2, "" ))) | S33: =IF(AND($F33<(S$2+7),$F33>S$2),1, IF(AND($H33<S$2+7,$H33>S$2),3, IF(AND($F33<=S$2, $H33>=S$2), 2, "" ))) | ... AQ33: =IF(AND($F33<(AQ$2+7),$F33>AQ$2),1, IF(AND($H33<AQ$2+7,$H33>AQ$2),3, IF(AND($F33<=AQ$2, $H33>=AQ$2), 2, "" )))
B34: Monitoring Platform Installation | C34: 43997 | D34: 1 | E34: 44000 | F34: 43997 | G34: 1 | H34: 44000
A35: 11 | B35: Completion | C35: 44000 | D35: 14 | E35: 44014 | F35: 44000 | G35: 14 | H35: 44014 | L35: =IF(AND($F35<(L$2+7),$F35>L$2),1, IF(AND($H35<L$2+7,$H35>L$2),3, IF(AND($F35<=L$2, $H35>=L$2), 2, "" ))) | M35: =IF(AND($F35<(M$2+7),$F35>M$2),1, IF(AND($H35<M$2+7,$H35>M$2),3, IF(AND($F35<=M$2, $H35>=M$2), 2, "" ))) | N35: =IF(AND($F35<(N$2+7),$F35>N$2),1, IF(AND($H35<N$2+7,$H35>N$2),3, IF(AND($F35<=N$2, $H35>=N$2), 2, "" ))) | O35: =IF(AND($F35<(O$2+7),$F35>O$2),1, IF(AND($H35<O$2+7,$H35>O$2),3, IF(AND($F35<=O$2, $H35>=O$2), 2, "" ))) | P35: =IF(AND($F35<(P$2+7),$F35>P$2),1, IF(AND($H35<P$2+7,$H35>P$2),3, IF(AND($F35<=P$2, $H35>=P$2), 2, "" ))) | Q35: =IF(AND($F35<(Q$2+7),$F35>Q$2),1, IF(AND($H35<Q$2+7,$H35>Q$2),3, IF(AND($F35<=Q$2, $H35>=Q$2), 2, "" ))) | R35: =IF(AND($F35<(R$2+7),$F35>R$2),1, IF(AND($H35<R$2+7,$H35>R$2),3, IF(AND($F35<=R$2, $H35>=R$2), 2, "" ))) | S35: =IF(AND($F35<(S$2+7),$F35>S$2),1, IF(AND($H35<S$2+7,$H35>S$2),3, IF(AND($F35<=S$2, $H35>=S$2), 2, "" ))) | ... AQ35: =IF(AND($F35<(AQ$2+7),$F35>AQ$2),1, IF(AND($H35<AQ$2+7,$H35>AQ$2),3, IF(AND($F35<=AQ$2, $H35>=AQ$2), 2, "" ))) -> 3
B36: DC Works | C36: 44012 | D36: 2 | E36: 44014 | F36: 44012 | G36: 2 | H36: 44014 | L36: =IF(AND($F36<(L$2+7),$F36>L$2),1, IF(AND($H36<L$2+7,$H36>L$2),3, IF(AND($F36<=L$2, $H36>=L$2), 2, "" ))) | M36: =IF(AND($F36<(M$2+7),$F36>M$2),1, IF(AND($H36<M$2+7,$H36>M$2),3, IF(AND($F36<=M$2, $H36>=M$2), 2, "" ))) | N36: =IF(AND($F36<(N$2+7),$F36>N$2),1, IF(AND($H36<N$2+7,$H36>N$2),3, IF(AND($F36<=N$2, $H36>=N$2), 2, "" ))) | O36: =IF(AND($F36<(O$2+7),$F36>O$2),1, IF(AND($H36<O$2+7,$H36>O$2),3, IF(AND($F36<=O$2, $H36>=O$2), 2, "" ))) | P36: =IF(AND($F36<(P$2+7),$F36>P$2),1, IF(AND($H36<P$2+7,$H36>P$2),3, IF(AND($F36<=P$2, $H36>=P$2), 2, "" ))) | Q36: =IF(AND($F36<(Q$2+7),$F36>Q$2),1, IF(AND($H36<Q$2+7,$H36>Q$2),3, IF(AND($F36<=Q$2, $H36>=Q$2), 2, "" ))) | R36: =IF(AND($F36<(R$2+7),$F36>R$2),1, IF(AND($H36<R$2+7,$H36>R$2),3, IF(AND($F36<=R$2, $H36>=R$2), 2, "" ))) | S36: =IF(AND($F36<(S$2+7),$F36>S$2),1, IF(AND($H36<S$2+7,$H36>S$2),3, IF(AND($F36<=S$2, $H36>=S$2), 2, "" ))) | ... AQ36: =IF(AND($F36<(AQ$2+7),$F36>AQ$2),1, IF(AND($H36<AQ$2+7,$H36>AQ$2),3, IF(AND($F36<=AQ$2, $H36>=AQ$2), 2, "" ))) -> 3
B37: AC Works | C37: 44000 | D37: 2 | E37: 44004 | F37: 44000 | G37: 2 | H37: 44004 | L37: =IF(AND($F37<(L$2+7),$F37>L$2),1, IF(AND($H37<L$2+7,$H37>L$2),3, IF(AND($F37<=L$2, $H37>=L$2), 2, "" ))) | M37: =IF(AND($F37<(M$2+7),$F37>M$2),1, IF(AND($H37<M$2+7,$H37>M$2),3, IF(AND($F37<=M$2, $H37>=M$2), 2, "" ))) | N37: =IF(AND($F37<(N$2+7),$F37>N$2),1, IF(AND($H37<N$2+7,$H37>N$2),3, IF(AND($F37<=N$2, $H37>=N$2), 2, "" ))) | O37: =IF(AND($F37<(O$2+7),$F37>O$2),1, IF(AND($H37<O$2+7,$H37>O$2),3, IF(AND($F37<=O$2, $H37>=O$2), 2, "" ))) | P37: =IF(AND($F37<(P$2+7),$F37>P$2),1, IF(AND($H37<P$2+7,$H37>P$2),3, IF(AND($F37<=P$2, $H37>=P$2), 2, "" ))) | Q37: =IF(AND($F37<(Q$2+7),$F37>Q$2),1, IF(AND($H37<Q$2+7,$H37>Q$2),3, IF(AND($F37<=Q$2, $H37>=Q$2), 2, "" ))) | R37: =IF(AND($F37<(R$2+7),$F37>R$2),1, IF(AND($H37<R$2+7,$H37>R$2),3, IF(AND($F37<=R$2, $H37>=R$2), 2, "" ))) | S37: =IF(AND($F37<(S$2+7),$F37>S$2),1, IF(AND($H37<S$2+7,$H37>S$2),3, IF(AND($F37<=S$2, $H37>=S$2), 2, "" ))) | ... AQ37: =IF(AND($F37<(AQ$2+7),$F37>AQ$2),1, IF(AND($H37<AQ$2+7,$H37>AQ$2),3, IF(AND($F37<=AQ$2, $H37>=AQ$2), 2, "" )))
A38: D | B38: PAYMENT MILESTONE 4: PRACTICAL COMPLETION | C38: 44012 | D38: 1 | E38: 44013 | F38: 44012 | G38: 1 | H38: 44013 | L38: =IF(AND($F38<(L$2+7),$F38>L$2),1, IF(AND($H38<L$2+7,$H38>L$2),3, IF(AND($F38<=L$2, $H38>=L$2), 2, "" ))) | M38: =IF(AND($F38<(M$2+7),$F38>M$2),1, IF(AND($H38<M$2+7,$H38>M$2),3, IF(AND($F38<=M$2, $H38>=M$2), 2, "" ))) | N38: =IF(AND($F38<(N$2+7),$F38>N$2),1, IF(AND($H38<N$2+7,$H38>N$2),3, IF(AND($F38<=N$2, $H38>=N$2), 2, "" ))) | O38: =IF(AND($F38<(O$2+7),$F38>O$2),1, IF(AND($H38<O$2+7,$H38>O$2),3, IF(AND($F38<=O$2, $H38>=O$2), 2, "" ))) | P38: =IF(AND($F38<(P$2+7),$F38>P$2),1, IF(AND($H38<P$2+7,$H38>P$2),3, IF(AND($F38<=P$2, $H38>=P$2), 2, "" ))) | Q38: =IF(AND($F38<(Q$2+7),$F38>Q$2),1, IF(AND($H38<Q$2+7,$H38>Q$2),3, IF(AND($F38<=Q$2, $H38>=Q$2), 2, "" ))) | R38: =IF(AND($F38<(R$2+7),$F38>R$2),1, IF(AND($H38<R$2+7,$H38>R$2),3, IF(AND($F38<=R$2, $H38>=R$2), 2, "" ))) | S38: =IF(AND($F38<(S$2+7),$F38>S$2),1, IF(AND($H38<S$2+7,$H38>S$2),3, IF(AND($F38<=S$2, $H38>=S$2), 2, "" ))) | ... AQ38: =IF(AND($F38<(AQ$2+7),$F38>AQ$2),1, IF(AND($H38<AQ$2+7,$H38>AQ$2),3, IF(AND($F38<=AQ$2, $H38>=AQ$2), 2, "" ))) -> 3
A39: 12 | B39: Commissioning | C39: 43997 | D39: 22 | E39: 44019 | F39: 43997 | G39: 22 | H39: 44019 | L39: =IF(AND($F39<(L$2+7),$F39>L$2),1, IF(AND($H39<L$2+7,$H39>L$2),3, IF(AND($F39<=L$2, $H39>=L$2), 2, "" ))) | M39: =IF(AND($F39<(M$2+7),$F39>M$2),1, IF(AND($H39<M$2+7,$H39>M$2),3, IF(AND($F39<=M$2, $H39>=M$2), 2, "" ))) | N39: =IF(AND($F39<(N$2+7),$F39>N$2),1, IF(AND($H39<N$2+7,$H39>N$2),3, IF(AND($F39<=N$2, $H39>=N$2), 2, "" ))) | O39: =IF(AND($F39<(O$2+7),$F39>O$2),1, IF(AND($H39<O$2+7,$H39>O$2),3, IF(AND($F39<=O$2, $H39>=O$2), 2, "" ))) | P39: =IF(AND($F39<(P$2+7),$F39>P$2),1, IF(AND($H39<P$2+7,$H39>P$2),3, IF(AND($F39<=P$2, $H39>=P$2), 2, "" ))) | Q39: =IF(AND($F39<(Q$2+7),$F39>Q$2),1, IF(AND($H39<Q$2+7,$H39>Q$2),3, IF(AND($F39<=Q$2, $H39>=Q$2), 2, "" ))) | R39: =IF(AND($F39<(R$2+7),$F39>R$2),1, IF(AND($H39<R$2+7,$H39>R$2),3, IF(AND($F39<=R$2, $H39>=R$2), 2, "" ))) | S39: =IF(AND($F39<(S$2+7),$F39>S$2),1, IF(AND($H39<S$2+7,$H39>S$2),3, IF(AND($F39<=S$2, $H39>=S$2), 2, "" ))) | ... AQ39: =IF(AND($F39<(AQ$2+7),$F39>AQ$2),1, IF(AND($H39<AQ$2+7,$H39>AQ$2),3, IF(AND($F39<=AQ$2, $H39>=AQ$2), 2, "" ))) -> 2
B40: Snag List | C40: 44014 | D40: 3 | E40: 44019 | F40: 44014 | G40: 3 | H40: 44019
B41: Pre-Commissioning Checks | C41: 44010 | D41: 2 | E41: 44012 | F41: 44010 | G41: 2 | H41: 44012
B42: Issue CoC | C42: 43997 | D42: 2 | E42: 44001 | F42: 43997 | G42: 2 | H42: 44001 | L42: =IF(AND($F42<(L$2+7),$F42>L$2),1, IF(AND($H42<L$2+7,$H42>L$2),3, IF(AND($F42<=L$2, $H42>=L$2), 2, "" ))) | M42: =IF(AND($F42<(M$2+7),$F42>M$2),1, IF(AND($H42<M$2+7,$H42>M$2),3, IF(AND($F42<=M$2, $H42>=M$2), 2, "" ))) | N42: =IF(AND($F42<(N$2+7),$F42>N$2),1, IF(AND($H42<N$2+7,$H42>N$2),3, IF(AND($F42<=N$2, $H42>=N$2), 2, "" ))) | O42: =IF(AND($F42<(O$2+7),$F42>O$2),1, IF(AND($H42<O$2+7,$H42>O$2),3, IF(AND($F42<=O$2, $H42>=O$2), 2, "" ))) | P42: =IF(AND($F42<(P$2+7),$F42>P$2),1, IF(AND($H42<P$2+7,$H42>P$2),3, IF(AND($F42<=P$2, $H42>=P$2), 2, "" ))) | Q42: =IF(AND($F42<(Q$2+7),$F42>Q$2),1, IF(AND($H42<Q$2+7,$H42>Q$2),3, IF(AND($F42<=Q$2, $H42>=Q$2), 2, "" ))) | R42: =IF(AND($F42<(R$2+7),$F42>R$2),1, IF(AND($H42<R$2+7,$H42>R$2),3, IF(AND($F42<=R$2, $H42>=R$2), 2, "" ))) | S42: =IF(AND($F42<(S$2+7),$F42>S$2),1, IF(AND($H42<S$2+7,$H42>S$2),3, IF(AND($F42<=S$2, $H42>=S$2), 2, "" ))) | ... AQ42: =IF(AND($F42<(AQ$2+7),$F42>AQ$2),1, IF(AND($H42<AQ$2+7,$H42>AQ$2),3, IF(AND($F42<=AQ$2, $H42>=AQ$2), 2, "" )))
B43: Cold Commissioning | C43: 44012 | D43: 1 | E43: 44013 | F43: 44012 | G43: 1 | H43: 44013 | L43: =IF(AND($F43<(L$2+7),$F43>L$2),1, IF(AND($H43<L$2+7,$H43>L$2),3, IF(AND($F43<=L$2, $H43>=L$2), 2, "" ))) | M43: =IF(AND($F43<(M$2+7),$F43>M$2),1, IF(AND($H43<M$2+7,$H43>M$2),3, IF(AND($F43<=M$2, $H43>=M$2), 2, "" ))) | N43: =IF(AND($F43<(N$2+7),$F43>N$2),1, IF(AND($H43<N$2+7,$H43>N$2),3, IF(AND($F43<=N$2, $H43>=N$2), 2, "" ))) | O43: =IF(AND($F43<(O$2+7),$F43>O$2),1, IF(AND($H43<O$2+7,$H43>O$2),3, IF(AND($F43<=O$2, $H43>=O$2), 2, "" ))) | P43: =IF(AND($F43<(P$2+7),$F43>P$2),1, IF(AND($H43<P$2+7,$H43>P$2),3, IF(AND($F43<=P$2, $H43>=P$2), 2, "" ))) | Q43: =IF(AND($F43<(Q$2+7),$F43>Q$2),1, IF(AND($H43<Q$2+7,$H43>Q$2),3, IF(AND($F43<=Q$2, $H43>=Q$2), 2, "" ))) | R43: =IF(AND($F43<(R$2+7),$F43>R$2),1, IF(AND($H43<R$2+7,$H43>R$2),3, IF(AND($F43<=R$2, $H43>=R$2), 2, "" ))) | S43: =IF(AND($F43<(S$2+7),$F43>S$2),1, IF(AND($H43<S$2+7,$H43>S$2),3, IF(AND($F43<=S$2, $H43>=S$2), 2, "" ))) | ... AQ43: =IF(AND($F43<(AQ$2+7),$F43>AQ$2),1, IF(AND($H43<AQ$2+7,$H43>AQ$2),3, IF(AND($F43<=AQ$2, $H43>=AQ$2), 2, "" ))) -> 3
B44: Hot Commissioning | C44: 44013 | D44: 2 | E44: 44015 | F44: 44013 | G44: 2 | H44: 44015 | L44: =IF(AND($F44<(L$2+7),$F44>L$2),1, IF(AND($H44<L$2+7,$H44>L$2),3, IF(AND($F44<=L$2, $H44>=L$2), 2, "" ))) | M44: =IF(AND($F44<(M$2+7),$F44>M$2),1, IF(AND($H44<M$2+7,$H44>M$2),3, IF(AND($F44<=M$2, $H44>=M$2), 2, "" ))) | N44: =IF(AND($F44<(N$2+7),$F44>N$2),1, IF(AND($H44<N$2+7,$H44>N$2),3, IF(AND($F44<=N$2, $H44>=N$2), 2, "" ))) | O44: =IF(AND($F44<(O$2+7),$F44>O$2),1, IF(AND($H44<O$2+7,$H44>O$2),3, IF(AND($F44<=O$2, $H44>=O$2), 2, "" ))) | P44: =IF(AND($F44<(P$2+7),$F44>P$2),1, IF(AND($H44<P$2+7,$H44>P$2),3, IF(AND($F44<=P$2, $H44>=P$2), 2, "" ))) | Q44: =IF(AND($F44<(Q$2+7),$F44>Q$2),1, IF(AND($H44<Q$2+7,$H44>Q$2),3, IF(AND($F44<=Q$2, $H44>=Q$2), 2, "" ))) | R44: =IF(AND($F44<(R$2+7),$F44>R$2),1, IF(AND($H44<R$2+7,$H44>R$2),3, IF(AND($F44<=R$2, $H44>=R$2), 2, "" ))) | S44: =IF(AND($F44<(S$2+7),$F44>S$2),1, IF(AND($H44<S$2+7,$H44>S$2),3, IF(AND($F44<=S$2, $H44>=S$2), 2, "" ))) | ... AQ44: =IF(AND($F44<(AQ$2+7),$F44>AQ$2),1, IF(AND($H44<AQ$2+7,$H44>AQ$2),3, IF(AND($F44<=AQ$2, $H44>=AQ$2), 2, "" ))) -> 1
A45: 13 | B45: Handover | C45: 44020 | D45: 1 | E45: 44021 | F45: 44020 | G45: 1 | H45: 44021 | L45: =IF(AND($F45<(L$2+7),$F45>L$2),1, IF(AND($H45<L$2+7,$H45>L$2),3, IF(AND($F45<=L$2, $H45>=L$2), 2, "" ))) | M45: =IF(AND($F45<(M$2+7),$F45>M$2),1, IF(AND($H45<M$2+7,$H45>M$2),3, IF(AND($F45<=M$2, $H45>=M$2), 2, "" ))) | N45: =IF(AND($F45<(N$2+7),$F45>N$2),1, IF(AND($H45<N$2+7,$H45>N$2),3, IF(AND($F45<=N$2, $H45>=N$2), 2, "" ))) | O45: =IF(AND($F45<(O$2+7),$F45>O$2),1, IF(AND($H45<O$2+7,$H45>O$2),3, IF(AND($F45<=O$2, $H45>=O$2), 2, "" ))) | P45: =IF(AND($F45<(P$2+7),$F45>P$2),1, IF(AND($H45<P$2+7,$H45>P$2),3, IF(AND($F45<=P$2, $H45>=P$2), 2, "" ))) | Q45: =IF(AND($F45<(Q$2+7),$F45>Q$2),1, IF(AND($H45<Q$2+7,$H45>Q$2),3, IF(AND($F45<=Q$2, $H45>=Q$2), 2, "" ))) | R45: =IF(AND($F45<(R$2+7),$F45>R$2),1, IF(AND($H45<R$2+7,$H45>R$2),3, IF(AND($F45<=R$2, $H45>=R$2), 2, "" ))) | S45: =IF(AND($F45<(S$2+7),$F45>S$2),1, IF(AND($H45<S$2+7,$H45>S$2),3, IF(AND($F45<=S$2, $H45>=S$2), 2, "" ))) | ... AQ45: =IF(AND($F45<(AQ$2+7),$F45>AQ$2),1, IF(AND($H45<AQ$2+7,$H45>AQ$2),3, IF(AND($F45<=AQ$2, $H45>=AQ$2), 2, "" )))
A46: E | B46: PAYMENT MILESTONE 6: HANDOVER COMPLETE | C46: 44022 | D46: 1 | E46: 44025 | F46: 44022 | G46: 1 | H46: 44025
C47: 43831 | D47: These numbers are used to set the start and end dates on the Gantt Chart
C48: 44014

Sheet Compliance
B2: HSE
B4: Description | C4: Status | D4: Approved By | E4: Date | F4: Results / Comments
B5: NOC
B6: 7.1 Agreement
B7: 13.2 Agreement
B8: EE File
B9: Subbie File
B16: SSEG
B18: Description | C18: Status | D18: Approved By | E18: Date | F18: Results / Comments
B19: SSEG Application
B20: PTI
B21: Commissioning Approval

Sheet Project Plan
N1: =TODAY() -> 46076 | O1: =TODAY() -> 46076
C2: PROJECT PLAN | E2: Ridgeview Mall | N2: 0 | O2: 1
C3: PROJECT SIZE (kWp) | E3: 600
C4: PROJECT DEVELOPER | E4: Peet Verenney
C5: PROJECT MANAGERS | E5: JT Moorosi
C6: CONTRACT VALUE | E6: 5813800
C7: Phase: | E7: Compliance Handover
B8: No. | C8: HIGH LEVEL PROGRAMME | E8: Planned Start | F8: Duration (days) | G8: Planned End | I8: Actual Start | J8: Duration (days) | K8: Actual End | M8: Status | N8: Status | O8: Comment
F9: =G42-E20 -> 74 | J9: =K42-I20 -> 133 | M9: =AVERAGE(M11,M19,M22,M29,M36,M40,M47,M44) -> 1 | N9: =AVERAGE(N11,N19,N22,N29,N36,N40,N47,N44) -> 1
B11: 1 | C11: Project Initiation | E11: =MIN(E12:E17) -> 45685 | F11: =G11-E11 -> 35 | G11: =MAX(G12:G17) -> 45720 | I11: =MIN(I12:I17) -> 45685 | J11: =K11-I11 -> 57 | K11: =MAX(K12:K17) -> 45742 | M11: =(J12*M12+J13*M13+J14*M14+J16*M16+J17*M17)/SUM(J12:J17) -> 1 | N11: =(K12*N12+K13*N13+K14*N14+K16*N16+K17*N17)/SUM(K12:K17) -> 1
B12: 1.1 | C12: BD Handover | E12: 45685 | F12: 1 | G12: =WORKDAY.INTL(E12,F12,1,Data!$C$3:$C$14) -> 45686 | I12: 45685 | J12: 1 | K12: =WORKDAY.INTL(I12,J12,1,Data!$C$3:$C$14) -> 45686 | M12: 1 | N12: 1
B13: 1.2 | C13: Project Introduction | E13: =E12+14 -> 45699 | F13: 1 | G13: =WORKDAY.INTL(E13,F13,1,Data!$C$3:$C$14) -> 45700 | I13: =I12+14 -> 45699 | J13: 1 | K13: =WORKDAY.INTL(I13,J13,1,Data!$C$3:$C$14) -> 45700 | M13: 1 | N13: 1
B14: 1.3 | C14: HSE | E14: =E13 -> 45699 | F14: 20 | G14: =E14+F14 -> 45719 | I14: =I13 -> 45699 | J14: 43 | K14: =I14+J14 -> 45742 | M14: 1 | N14: 1
B15: 1.4 | C15: Engineering Sign Off
B16: 1.5 | C16: Installer Kick Off | E16: =E17 -> 45719 | F16: 1 | G16: =WORKDAY.INTL(E16,F16,1,Data!$C$3:$C$14) -> 45720 | I16: 45719 | J16: 1 | K16: 45720 | M16: 1 | N16: 1
B17: 1.6 | C17: Project Review | E17: =WORKDAY.INTL(G14,0,1,Data!$C$3:$C$14) -> 45719 | F17: 1 | G17: =WORKDAY.INTL(E17,F17,1,Data!$C$3:$C$14) -> 45720 | I17: 45719 | J17: 1 | K17: 45720 | M17: 1 | N17: 1
B19: 2 | C19: Site Establishment | E19: =MIN(E20:E21) -> 45726 | F19: =G19-E19 -> 1 | G19: =MAX(G20) -> 45727 | I19: =MIN(I20:I21) -> 45726 | J19: =K19-I19 -> 1 | K19: =MAX(K20) -> 45727 | M19: =(J20*M20)/J19 -> 1 | N19: =(K20*N20)/K19 -> 1
B20: 2.1 | C20: Installer on site & Roof Assessment | E20: 45726 | F20: 1 | G20: =E20+F20 -> 45727 | I20: 45726 | J20: 1 | K20: =I20+J20 -> 45727 | M20: 1 | N20: 1 | S20: =NETWORKDAYS(I20,K42,Data!C3:C15) -> 91 | T20: Net Work Days
B22: 3 | C22: AC Installation | E22: =MIN(E23:E27) -> 45726 | F22: =G22-E22 -> 60 | G22: =MAX(G23:G27) -> 45786 | I22: =MIN(I23:I27) -> 45726 | J22: =K22-I22 -> 127 | K22: =MAX(K23:K27) -> 45853 | M22: =(J23*M23+J24*M24+J25*M25+J26*M26+J27*M27)/SUM(J23:J27) -> 1 | N22: =(K23*N23+K24*N24+K25*N25+K26*N26+K27*N27)/SUM(K23:K27) -> 1 | S22: =S20/5 -> 18.2 | T22: Total Weeks
B23: 3.1 | C23: Inverters delivered | E23: =WORKDAY.INTL(G20,0,1,Data!$C$3:$C$14) -> 45727 | F23: 1 | G23: =WORKDAY.INTL(E23,F23,1,Data!$C$3:$C$14) -> 45728 | I23: =WORKDAY.INTL(K20,0,1,Data!$C$3:$C$14) -> 45727 | J23: 1 | K23: =WORKDAY.INTL(I23,J23,1,Data!$C$3:$C$14) -> 45728 | M23: 1 | N23: 1 | S23: =E3/S22 -> 32.967033 | T23: kW/Week Installation Rate
B24: 3.2 | C24: Inverters Mounted | E24: =WORKDAY.INTL(G20,0,1,Data!$C$3:$C$14) -> 45727 | F24: 5 | G24: =WORKDAY.INTL(E24,F24,1,Data!$C$3:$C$14) -> 45734 | I24: 45817 | J24: 5 | K24: =WORKDAY.INTL(I24,J24,1,Data!$C$3:$C$14) -> 45825 | M24: 1 | N24: 1
B25: 3.3 | C25: Solar DB Lead Time | E25: =WORKDAY.INTL(E20,0,1,Data!$C$3:$C$14) -> 45726 | F25: 25 | G25: =WORKDAY.INTL(E25,F25,1,Data!$C$3:$C$14) -> 45762 | I25: =WORKDAY.INTL(I20,0,1,Data!$C$3:$C$14) -> 45726 | J25: 25 | K25: =WORKDAY.INTL(I25,J25,1,Data!$C$3:$C$14) -> 45762 | M25: 1 | N25: 1
B26: 3.4 | C26: AC Works | E26: =WORKDAY.INTL(G25,0,1,Data!$C$3:$C$14) -> 45762 | F26: 15 | G26: =WORKDAY.INTL(E26,F26,1,Data!$C$3:$C$14) -> 45786 | I26: =WORKDAY.INTL(I24,0,1,Data!$C$3:$C$14) -> 45817 | J26: 12 | K26: =WORKDAY.INTL(I26,J26,1,Data!$C$3:$C$14) -> 45834 | M26: 1 | N26: 1
B27: 3.5 | C27: AC Tie-In | E27: =WORKDAY.INTL(E26,0,1,Data!$C$3:$C$14) -> 45762 | F27: 3 | G27: =WORKDAY.INTL(E27,F27,1,Data!$C$3:$C$14) -> 45769 | I27: 45852 | J27: 1 | K27: =WORKDAY.INTL(I27,J27,1,Data!$C$3:$C$14) -> 45853 | M27: 1 | N27: 1
B29: 4 | C29: DC Works | E29: =MIN(E31:E34) -> 45726 | F29: =G29-E29 -> 60 | G29: =MAX(G31:G34) -> 45786 | I29: =MIN(I31:I34) -> 45726 | J29: =K29-I29 -> 63 | K29: =MAX(K31:K34) -> 45789 | M29: 1 | N29: 1
B30: 4.1 | C30: Lifeline Installation (If Applicable) | M30: 0 | N30: 0
B31: 4.1 | C31: Mounting Structure delivered | E31: =G20 -> 45727 | F31: 1 | G31: =WORKDAY.INTL(E31,F31,1,Data!$C$3:$C$14) -> 45728 | I31: =K20 -> 45727 | J31: 1 | K31: =WORKDAY.INTL(I31,J31,1,Data!$C$3:$C$14) -> 45728 | M31: 1 | N31: 1
B32: 4.2 | C32: Mounting Structure installation | E32: =WORKDAY.INTL(E20,0,1,Data!$C$3:$C$14) -> 45726 | F32: 10 | G32: =WORKDAY.INTL(E32,F32,1,Data!$C$3:$C$14) -> 45741 | I32: =WORKDAY.INTL(I20,0,1,Data!$C$3:$C$14) -> 45726 | J32: 10 | K32: =WORKDAY.INTL(I32,J32,1,Data!$C$3:$C$14) -> 45741 | M32: 1 | N32: 1
B33: 4.3 | C33: DC Cable delivered | E33: =G20 -> 45727 | F33: 1 | G33: =WORKDAY.INTL(E33,F33,1,Data!$C$3:$C$14) -> 45728 | I33: =K20 -> 45727 | J33: 1 | K33: =WORKDAY.INTL(I33,J33,1,Data!$C$3:$C$14) -> 45728 | M33: 1 | N33: 1
B34: 4.3 | C34: DC Stringing | E34: =WORKDAY.INTL(G38,0,1,Data!$C$3:$C$14)-3 -> 45768 | F34: 13 | G34: =WORKDAY.INTL(E34,F34,1,Data!$C$3:$C$14) -> 45786 | I34: =WORKDAY.INTL(K38,0,1,Data!$C$3:$C$14)-3 -> 45776 | J34: 8 | K34: =WORKDAY.INTL(I34,J34,1,Data!$C$3:$C$14) -> 45789 | M34: 1 | N34: 1
B36: 5 | C36: Module installation | E36: =MIN(E37:E38) -> 45726 | F36: =G36-E36 -> 45 | G36: =MAX(G37:G38) -> 45771 | I36: =MIN(I37:I38) -> 45741 | J36: =K36-I36 -> 38 | K36: =MAX(K37:K38) -> 45779 | M36: =(J37*M37+J38*M38)/SUM(J37:J38) -> 1 | N36: =(K37*N37+K38*N38)/SUM(K37:K38) -> 1
B37: 5.1 | C37: Module delivery | E37: =WORKDAY.INTL(E20,0,1,Data!$C$3:$C$14) -> 45726 | F37: 1 | G37: =WORKDAY.INTL(E37,F37,1,Data!$C$3:$C$14) -> 45727 | I37: 45741 | J37: 1 | K37: =WORKDAY.INTL(I37,J37,1,Data!$C$3:$C$14) -> 45742 | M37: 1 | N37: 1
B38: 5.2 | C38: Module mounting | E38: =G32 -> 45741 | F38: 20 | G38: =WORKDAY.INTL(E38,F38,1,Data!$C$3:$C$14) -> 45771 | I38: =K32 -> 45741 | J38: 20 | K38: 45779 | M38: 1 | N38: 1
B40: 6 | C40: Commissioning | E40: =MIN(E41:E42) -> 45786 | F40: =G40-E40 -> 14 | G40: =MAX(G41:G42) -> 45800 | I40: =MIN(I41:I42) -> 45855 | J40: =K40-I40 -> 4 | K40: =MAX(K41:K42) -> 45859 | M40: =(J41*M41+J42*M42)/SUM(J41:J42) -> 1 | N40: =(K41*N41+K42*N42)/SUM(K41:K42) -> 1
B41: 6.1 | C41: Commissioning | E41: =WORKDAY.INTL(MAX(G22,G29,G36),0,1,Data!$C$3:$C$14) -> 45786 | F41: 5 | G41: =WORKDAY.INTL(E41,F41,1,Data!$C$3:$C$14) -> 45793 | I41: 45855 | J41: 1 | K41: =WORKDAY.INTL(I41,J41,1,Data!$C$3:$C$14) -> 45856 | M41: 1 | N41: 1
B42: 6.2 | C42: Practical Completion | E42: =WORKDAY.INTL(G41,0,1,Data!$C$3:$C$14) -> 45793 | F42: 5 | G42: =WORKDAY.INTL(E42,F42,1,Data!$C$3:$C$14) -> 45800 | I42: =WORKDAY.INTL(K41,0,1,Data!$C$3:$C$14) -> 45856 | J42: 1 | K42: =WORKDAY.INTL(I42,J42,1,Data!$C$3:$C$14) -> 45859 | M42: 1 | N42: 1
B44: 7 | C44: QA Inspections | E44: =MIN(E45) -> 45800 | F44: =G44-E44 -> 7 | G44: =MAX(G45) -> 45807 | I44: =MIN(I45) -> 45859 | J44: =K44-I44 -> 7 | K44: =MAX(K45) -> 45866 | M44: =(J45*M45)/SUM(J45) -> 1 | N44: =(K45*N45)/SUM(K45) -> 1
B45: 7.1 | C45: Red-Team Inspection | E45: =WORKDAY.INTL(G42,0,1,Data!$C$3:$C$14) -> 45800 | F45: 5 | G45: =WORKDAY.INTL(E45,F45,1,Data!$C$3:$C$14) -> 45807 | I45: =WORKDAY.INTL(K42,0,1,Data!$C$3:$C$14) -> 45859 | J45: 5 | K45: =WORKDAY.INTL(I45,J45,1,Data!$C$3:$C$14) -> 45866 | M45: 1 | N45: 1
B47: 8 | C47: Project Closure | E47: =MIN(E48:E53) -> 45807 | F47: =G47-E47 -> 39 | G47: =MAX(G48:G53) -> 45846 | I47: =MIN(I48:I53) -> 45859 | J47: =K47-I47 -> 11 | K47: =MAX(K48:K53) -> 45870 | M47: =(J48*M48+J49*M49+J50*M50+J51*M51+J52*M52+J53*M53)/SUM(J48:J53) -> 1 | N47: =(K48*N48+K49*N49+K50*N50+K51*N51+K52*N52+K53*N53)/SUM(K48:K53) -> 1
B48: 8.1 | C48: Equipment serial numbers | E48: =G45 -> 45807 | F48: 2 | G48: =WORKDAY.INTL(E48,F48,1,Data!$C$3:$C$14) -> 45811 | I48: =K45 -> 45866 | J48: 2 | K48: =WORKDAY.INTL(I48,J48,1,Data!$C$3:$C$14) -> 45868 | M48: 1 | N48: 1
B49: 8.2 | C49: Snags completion | E49: =G45 -> 45807 | F49: 10 | G49: =WORKDAY.INTL(E49,F49,1,Data!$C$3:$C$14) -> 45821 | I49: =K45 -> 45866 | J49: 1 | K49: =WORKDAY.INTL(I49,J49,1,Data!$C$3:$C$14) -> 45867 | M49: 1 | N49: 1
B50: 8.3 | C50: System Performance Monitoring | E50: =WORKDAY.INTL(G49,0,1,Data!$C$3:$C$14) -> 45821 | F50: 5 | G50: =WORKDAY.INTL(E50,F50,1,Data!$C$3:$C$14) -> 45831 | I50: =WORKDAY.INTL(K42,0,1,Data!$C$3:$C$14) -> 45859 | J50: 5 | K50: =WORKDAY.INTL(I50,J50,1,Data!$C$3:$C$14) -> 45866 | M50: 1 | N50: 1
B51: 8.4 | C51: Handover documentation | E51: =WORKDAY.INTL(G50,0,1,Data!$C$3:$C$14) -> 45831 | F51: 10 | G51: =WORKDAY.INTL(E51,F51,1,Data!$C$3:$C$14) -> 45845 | I51: =WORKDAY.INTL(K50,0,1,Data!$C$3:$C$14) -> 45866 | J51: 3 | K51: =WORKDAY.INTL(I51,J51,1,Data!$C$3:$C$14) -> 45869 | M51: 1 | N51: 1
B52: 8.5 | C52: Handover to Client | E52: =WORKDAY.INTL(G51,0,1,Data!$C$3:$C$14) -> 45845 | F52: 1 | G52: =WORKDAY.INTL(E52,F52,1,Data!$C$3:$C$14) -> 45846 | I52: =WORKDAY.INTL(K51,0,1,Data!$C$3:$C$14) -> 45869 | J52: 1 | K52: =WORKDAY.INTL(I52,J52,1,Data!$C$3:$C$14) -> 45870 | M52: 1 | N52: 1
B53: 8.6 | C53: Handover to Matriarch | E53: =WORKDAY.INTL(G49,0,1,Data!$C$3:$C$14)+2 -> 45823 | F53: 5 | G53: =WORKDAY.INTL(E53,F53,1,Data!$C$3:$C$14) -> 45831 | I53: =WORKDAY.INTL(K42,0,1,Data!$C$3:$C$14)+2 -> 45861 | J53: 5 | K53: =WORKDAY.INTL(I53,J53,1,Data!$C$3:$C$14) -> 45868 | M53: 1 | N53: 1

Sheet Revenue Tracking
B2: HIGH LEVEL PROJECT REVENUE TRACKING
D3: PLANNED | F3: ACTUAL | L3: FINANCIAL REVIEW | N3: TIMELINE REVIEW
B4: 1 | C4: Planned Revenue | D4: ='Project Plan'!E6 -> 5813800 | F4: =F21 -> 5852178.3 | L4: 5813800 | N4: Start Date
B5: 2 | C5: Planned Expenditure | D5: =+'Expenditure Tracking'!F5 -> 5151610.7 | F5: =+'Expenditure Tracking'!J5 -> 4046134 | L5: 4227923.9 | N5: 45726
B6: 3 | C6: Planned Profit | D6: =+D4-D5 -> 662189.28 | F6: =+F4-F5 -> 1806044.2 | L6: 1585876.1 | N6: End Date - PC
B7: 4 | C7: Planned Margin | D7: =+D6/D4 -> 0.11389956 | F7: =+F6/F4 -> 0.30861059 | L7: 0.27277789 | N7: 45800
B10: CONTRACT
B12: No. | C12: PAYMENT MILESTONE | E12: % | F12: VALUE | H12: PLANNED PAYMENT DATE | L12: INVOICE NUMBER | N12: INVOICE RAISED DATE | P12: PAYMENT RECEIVED DATE | R12: MILESTONE NOTES & COMMENTS
B13: 1 | C13: Acceptance and initial Deposit | E13: 0.35 | F13: =$D$4*E13 -> 2034830 | H13: 45716 | L13: 004715 | P13: 45751
B14: 2 | C14: Delivery of Panels | E14: 0.2 | F14: =$D$4*E14 -> 1162760 | H14: ='Project Plan'!E37+30 -> 45756 | L14: 004715 | P14: 45764
B15: 3 | C15: Delivery of Inverters | E15: 0.3 | F15: =$D$4*E15 -> 1744140 | H15: ='Project Plan'!E23+30 -> 45757 | L15: 004715 | P15: 45735
B16: 4 | C16: Practical Completion | E16: 0.1 | F16: =$D$4*E16 -> 581380 | H16: ='Project Plan'!G40+30 -> 45830 | L16: 004715 | P16: 45855
B17: 5 | C17: Handover | E17: 0.05 | F17: =$D$4*E17 -> 290690 | H17: ='Project Plan'!G52+30 -> 45876 | L17: 004715 | P17: ='Project Plan'!K52+7 -> 45877
B18: 6 | C18: Inverter Cage | E18: 0 | F18: 38378.26 | H18: 45920 | L18: 004835 | N18: 45900 | P18: 46081
B19: 7 | C19: - | E19: 0 | F19: =$D$4*E19 -> 0
E21: =SUM(E13:E19) -> 1 | F21: =SUM(F13:F19) -> 5852178.3
B23: KEY: | C23: contains an error (in result or a check has failed)
C24: Red Font - IF TEXT : content not yet confirmed | H24: =(F13+F14+F15)*1.15 -> 5682989.5
C25: Red Font - IF NUMBER: Negative value
C26: Anything in yellow is a concern or risk for noting or action
C27: confirmed
C28: [ADD INITIALS: comment for noting in square brackets, use colour or red to draw attention if important]
C29: [RT: When adding rows into sheet, ensure you insert between first and last row of each category]
C30: end of sheet - do not insert information below/beyond this
B40: No. | C40: PAYMENT MILESTONE | E40: % | F40: VALUE
B41: 1 | C41: Deposit - Project commencement | E41: 0.35 | F41: =$F$47*E41 -> 2048262.4
B42: 2 | C42: Delivery of Panels | E42: 0.3 | F42: =$F$47*E42 -> 1755653.5
B43: 3 | C43: Delivery of Inverters | E43: 0.2 | F43: =$F$47*E43 -> 1170435.7
B44: 4 | C44: Practical Completion | E44: 0.1 | F44: =$F$47*E44 -> 585217.83
B45: 5 | C45: Handover | E45: 0.05 | F45: =$F$47*E45 -> 292608.91
C46: Total | E46: =SUM(E41:E45) -> 1 | F46: =SUM(F41:F45) -> 5852178.3
E47: =SUM(E41:E45) -> 1 | F47: =F21 -> 5852178.3

Sheet Data
C2: Public holidays | F2: Drop down list
C3: 45658 | D3: New Years Day | F3: Approved
C4: 45737 | D4: Human Rights day | F4: Pending
C5: 45765 | D5: Good Friday | F5: Declined
C6: 45768 | D6: Family Day | F6: Abanded
C7: 45774 | D7: Freedom Day
C8: 45765 | D8: Freedom DayObserved
C9: 45778 | D9: Workers day
C10: 45824 | D10: Youth Day Holiday
C11: 45878 | D11: Womens Day
C12: 45924 | D12: Heritage Day
C13: 46007 | D13: Day of Reconciliation | H13: Manual dates
C14: 46016 | D14: Christmas Day
C15: 46017 | D15: Day of Goodwill

Sheet Expenditure Tracking
B2: HIGH LEVEL PROJECT EXPENDITURE TRACKING
F4: COSTED | H4: PLANNED | J4: ACTUAL | L4: Difference from costed | N4: Difference from planned
B5: EXPENDITURE | F5: =SUM(F9:F23) -> 5151610.7 | H5: =SUM(H9:H23) -> 4227923.9 | J5: =SUM(J9:J23) -> 4046134 | L5: =SUM(L9:L23) -> 1105476.7 | N5: =SUM(N9:N23) -> 181789.83
B7: No. | D7: Item | F7: Costed Expenditure | H7: Planned Expenditure | J7: Actual Expenditure | L7: Saving / Overrun | N7: Saving / Overrun | P7: Comments on variations from planned expenditure
B9: ='Expenditure Breakdown'!B6 -> 1 | D9: ='Expenditure Breakdown'!C6 -> Panels | F9: ='Expenditure Breakdown'!I6 -> 1496537 | H9: 1189073.9 | J9: ='Expenditure Breakdown'!X6 -> 1208550.9 | L9: =F9-J9 -> 287986.11 | N9: =H9-J9 -> -19476.984
B10: ='Expenditure Breakdown'!B13 -> 2 | D10: ='Expenditure Breakdown'!C13 -> Inverters | F10: =+'Expenditure Breakdown'!I13 -> 350000 | H10: 344350 | J10: =+'Expenditure Breakdown'!X13 -> 344350 | L10: =F10-J10 -> 5650 | N10: =H10-J10 -> 0
B11: ='Expenditure Breakdown'!B19 -> 3 | D11: ='Expenditure Breakdown'!C19 -> Mounting Structures | F11: =+'Expenditure Breakdown'!I19 -> 270229.5 | H11: 92905.88 | J11: =+'Expenditure Breakdown'!X19 -> 93481.82 | L11: =F11-J11 -> 176747.68 | N11: =H11-J11 -> -575.94
B12: ='Expenditure Breakdown'!B28 -> 4 | D12: ='Expenditure Breakdown'!C28 -> DC Equipment | F12: =+'Expenditure Breakdown'!I28 -> 548101.2 | H12: 558749.25 | J12: =+'Expenditure Breakdown'!X28 -> 671199.26 | L12: =F12-J12 -> -123098.06 | N12: =H12-J12 -> -112450.01
B13: ='Expenditure Breakdown'!B41 -> 5 | D13: ='Expenditure Breakdown'!C41 -> Monitoring | F13: =+'Expenditure Breakdown'!I41 -> 49000 | H13: 36654.33 | J13: =+'Expenditure Breakdown'!X41 -> 33421.96 | L13: =F13-J13 -> 15578.04 | N13: =H13-J13 -> 3232.37
B14: ='Expenditure Breakdown'!B48 -> 6 | D14: ='Expenditure Breakdown'!C48 -> AC Equipment | F14: =+'Expenditure Breakdown'!I48 -> 842399.37 | H14: 357261 | J14: =+'Expenditure Breakdown'!X48 -> 390951.5 | L14: =F14-J14 -> 451447.87 | N14: =H14-J14 -> -33690.5
B15: ='Expenditure Breakdown'!B58 -> 7 | D15: ='Expenditure Breakdown'!C58 -> Battery Systems | F15: =+'Expenditure Breakdown'!I58 -> 0 | H15: 0 | J15: ='Expenditure Breakdown'!X58 -> 0 | L15: =F15-J15 -> 0 | N15: =H15-J15 -> 0
B16: ='Expenditure Breakdown'!B67 -> 8 | D16: ='Expenditure Breakdown'!C67 -> Product Add On | F16: ='Expenditure Breakdown'!I67 -> 350000 | H16: 440000 | J16: ='Expenditure Breakdown'!X67 -> 138014.52 | L16: =F16-J16 -> 211985.48 | N16: =H16-J16 -> 301985.48
B17: ='Expenditure Breakdown'!L75 -> 9 | D17: ='Expenditure Breakdown'!C75 -> AC & DC Installation | F17: =+'Expenditure Breakdown'!I75 -> 509892.5 | H17: 600000 | J17: =+'Expenditure Breakdown'!X75 -> 600000 | L17: =F17-J17 -> -90107.5 | N17: =H17-J17 -> 0
B18: ='Expenditure Breakdown'!B84 -> 10 | D18: ='Expenditure Breakdown'!C84 -> Site Logistics | F18: =+'Expenditure Breakdown'!I84 -> 214099.5 | H18: 91407 | J18: =+'Expenditure Breakdown'!X84 -> 77457 | L18: =F18-J18 -> 136642.5 | N18: =H18-J18 -> 13950
B19: ='Expenditure Breakdown'!B100 -> 11 | D19: ='Expenditure Breakdown'!C100 -> Due Dilligence | F19: ='Expenditure Breakdown'!I100 -> 132038.25 | H19: 95212.75 | J19: ='Expenditure Breakdown'!X100 -> 102050 | L19: =F19-J19 -> 29988.25 | N19: =H19-J19 -> -6837.25
B20: ='Expenditure Breakdown'!B107 -> 12 | D20: ='Expenditure Breakdown'!C107 -> BDP Commission | F20: ='Expenditure Breakdown'!G106 -> 0 | H20: 0 | J20: ='Expenditure Breakdown'!X106 -> 304347.83 | L20: =F20-J20 -> -304347.83 | N20: =H20-J20 -> -304347.83
B21: ='Expenditure Breakdown'!B109 -> 13 | D21: ='Expenditure Breakdown'!C109 -> Engineering | F21: =+'Expenditure Breakdown'!I109 -> 378813.4 | H21: 400707.18 | J21: =+'Expenditure Breakdown'!X109 -> 72672.5 | L21: =F21-J21 -> 306140.9 | N21: =H21-J21 -> 328034.68 | P21: RV: Matriarch defects percentage 1.25%
B22: ='Expenditure Breakdown'!B117 -> 14 | D22: ='Expenditure Breakdown'!C117 -> General Expenses | F22: =+'Expenditure Breakdown'!I117 -> 10500 | H22: 21602.58 | J22: =+'Expenditure Breakdown'!X117 -> 6386.77 | L22: =F22-J22 -> 4113.23 | N22: =H22-J22 -> 15215.81
B23: ='Expenditure Breakdown'!B126 -> 15 | D23: ='Expenditure Breakdown'!C126 -> Service Add On | F23: =+'Expenditure Breakdown'!I126 -> 0 | H23: 0 | J23: =+'Expenditure Breakdown'!X126 -> 3250 | L23: =F23-J23 -> -3250 | N23: =H23-J23 -> -3250
D25: check: | F25: ='Expenditure Breakdown'!I2-'Expenditure Tracking'!F5 -> 0 | G25: ='Expenditure Breakdown'!#REF!-G5 -> #REF! | H25: ='Expenditure Breakdown'!X2-J5 -> 0 | I25: ='Expenditure Breakdown'!#REF!-I5 -> #REF! | J25: ='Expenditure Breakdown'!X2-J5 -> 0
A27: Copy amounts in column H and paste as values at Project review.

Sheet Expenditure Breakdown
B2: COSTED EXPENDITURE BREAKDOWN | I2: =SUM(I6:I130) -> 5151610.7 | J2: =SUM(J6:J130) -> 5813800 | L2: ACTUAL EXPENDITURE BREAKDOWN | S2: FINANCE ONLY | X2: =SUM(X6:X130) -> 4046134
B4: No. | C4: Product / Service | D4: Description of Work | E4: QTY | F4: Rate / Unit | G4: Budget Total | H4: Project Related date | I4: Total COS | J4: =IF(J2-'Revenue Tracking'!D4>=0, "Total Revenue", "ERROR on REV" ) -> Total Revenue | L4: No. | M4: Product/ Service | N4: Description of Work | O4: QTY | P4: Rate / Unit | Q4: Actual Total | R4: PO NUMBER | S4: INVOICE NUMBER | T4: INVOICE RAISED DATE | U4: REVENUE RECOGNITION AMOUNT | V4: CHECK | W4: FINANCE PAYMENT DATE | X4: Total COS | Y4: COMMENTS
B6: 1 | C6: Panels | D6: Longi 555W | E6: 1082 | F6: 1346.1525 | G6: =E6*F6 -> 1456537 | H6: ='Project Plan'!E36+30 -> 45756 | I6: =G6+G8 -> 1496537 | J6: =D131 -> 1689109.4 | L6: 1 | M6: 1. Panels | N6: Longi 575W | O6: 1044 | P6: 1138.9597 | Q6: 1189070.9 | R6: PO3611-RSV-20210131 - RV Approved | S6: Krannich - Inv 15-10012162 | T6: 45747 | U6: 1666674.4 | V6: =J6-SUM(U6:U11) -> 0 | W6: ='Project Plan'!I37+58 -> 45799 | X6: =SUM(Q6:Q11) -> 1208550.9 | Z6: 19
B7: 1 | L7: 1 | M7: 1. Panels | N7: ChemiTek | Q7: 5526 | S7: Krannich - Inv 15-10012162 | T7: 45747 | U7: 7745.5793 | W7: ='Project Plan'!I38+58 -> 45799 | Z7: BUDGET | AA7: Installer Allocation
B8: 1 | D8: Delivery | G8: 40000 | H8: =H6 -> 45756 | L8: 1 | M8: 1. Panels | N8: Freight | Q8: 10480 | S8: Krannich - Inv 15-10012162 | T8: 45747 | U8: 14689.408 | W8: 45799 | Z8: AC Equipment | AA8: =C50 -> 842399.37
B9: 1 | L9: 1 | M9: 1. Panels | N9: 580W Panel | Q9: 3473.99 | S9: Krannich - Inv 15-10013490 | T9: 45900 | U9: 0 | W9: 45932 | Z9: DC Equipment | AA9: =C32 -> 338269.2
B10: 1 | L10: 1 | M10: 1. Panels | T10: =IF(W10>1,EOMONTH(W10,0),"") | U10: =(Q10/$X$6*$J$6) -> 0 | Z10: AC Labour | AA10: =C76 -> 150127.5 | AC10: =AA10/600000 -> 0.2502125
B11: 1 | L11: 1 | M11: 1. Panels | T11: =IF(W11>1,EOMONTH(W11,0),"") | U11: =(Q11/$X$6*$J$6) -> 0 | Z11: DC Labour | AA11: =C77 -> 359765 | AC11: =AA11/600000 -> 0.59960833
T12: =IF(W12>1,EOMONTH(W12,0),"") | Z12: Offloading | AA12: =G95 -> 8500
B13: 2 | C13: Inverters | D13: Huawei 100KTL | E13: 5 | F13: 70000 | G13: =E13*F13 -> 350000 | H13: ='Project Plan'!E23+30 -> 45757 | I13: =SUM(G13:G17) -> 350000 | J13: =D132 -> 395037.54 | L13: 2 | M13: 2. Inverters | N13: Huawei 100KTL | O13: 5 | P13: 68870 | Q13: =O13*P13 -> 344350 | R13: PO3611-RSV-20210131 - RV Approved | S13: Krannich - Inv 15-10011997 | T13: =T6 -> 45747 | U13: 395037.54 | V13: =J13-SUM(U13:U17) -> 0 | W13: 45785 | X13: =SUM(Q13:Q17) -> 344350 | Z13: Roof Access/Scaffolding | AA13: =G91 -> 54199.5
B14: 2 | L14: 2 | M14: 2. Inverters | U14: 0 | Z14: Storage | AA14: =G92 -> 7400
B15: 2 | L15: 2 | M15: 2. Inverters | U15: 0 | Z15: Telehandler | AA15: 0
B16: 2 | L16: 2 | M16: 2. Inverters | T16: =IF(W16>1,EOMONTH(W16,0),"") | U16: 0
B17: 2 | L17: 2 | M17: 2. Inverters | T17: =IF(W17>1,EOMONTH(W17,0),"") | U17: 0 | Z17: Other | AA17: 0
T18: =IF(W18>1,EOMONTH(W18,0),"") | Z18: Total | AA18: =SUM(AA8:AA17) -> 1760660.6
B19: 3 | C19: Mounting Structures | D19: Lumax Pitch Roof | G19: 270229.5 | H19: ='Project Plan'!E31+30 -> 45757 | I19: =SUM(G19:G26) -> 270229.5 | J19: =D133 -> 305002.28 | L19: 3 | M19: 3. Mounting Structures | N19: KlipLock - Schletter | Q19: =74296.52-Q20 -> 71546.52 | R19: PO3719-RSC-20250305 - RV Approved | S19: Schletter - INV1531 | T19: 45747 | U19: 234881.48 | V19: =J19-SUM(U19:U26) -> 0.0014800188 | W19: =T19+30 -> 45777 | X19: =SUM(Q19:Q26) -> 93481.82 | Z19: Less 15% | AA19: =+AA18*0.85 -> 1496561.5 | AC19: [SM: Target Installation Price]
B20: 3 | L20: 3 | M20: 3. Mounting Structures | N20: Delivery | Q20: 2750 | S20: Schletter - INV1531 | T20: 45747 | U20: 9028.0291 | W20: =T20+30 -> 45777 | Z20: R/Wp | AA20: =+AA19/'Project Plan'!$E$3/1000 -> 2.4942691
L21: 3 | M21: 3. Mounting Structures | U21: 0
L22: 3 | M22: 3. Mounting Structures | N22: KlipLock Seam Clamps - JHB Storage | O22: 434 | P22: 24.88 | Q22: =P22*O22 -> 10797.92 | S22: Allocated from Stock | T22: 45747 | U22: 35448.704 | W22: =T22 -> 45747
L23: 3 | M23: 3. Mounting Structures | O23: =600-O22 -> 166 | P23: 28.35 | Q23: =P23*O23 -> 4706.1 | S23: Allocated from Stock | T23: 45869 | U23: 13558.719 | W23: =T23 -> 45869
L24: 3 | M24: 3. Mounting Structures | N24: End Clamps - JHB Storage | O24: 146 | P24: 11.48 | Q24: =P24*O24 -> 1676.08 | S24: Allocated from Stock | T24: 45747 | U24: 5502.436 | W24: =T24 -> 45747
B25: 3 | L25: 3 | M25: 3. Mounting Structures | N25: Mid Clamps - JHB Storage | O25: 180 | P25: 11.14 | Q25: =P25*O25 -> 2005.2 | S25: Allocated from Stock | T25: 45747 | U25: 6582.9105 | W25: =T25 -> 45747
B26: 3 | L26: 3 | M26: 3. Mounting Structures | T26: =IF(W26>1,EOMONTH(W26,0),"") | U26: =(Q26/$X$19*$J$19) -> 0 | Z26: ACTUAL - Cosmic Sun | AA26: Installer Price
T27: =IF(W27>1,EOMONTH(W27,0),"") | Z27: =Z8 -> AC Equipment | AA27: 357261
B28: 4 | C28: DC Equipment | D28: DC Cabling (Total Cable Length) | E28: 14988 | F28: 14 | G28: =E28*F28 -> 209832 | H28: ='Project Plan'!E33+30 -> 45757 | I28: =SUM(G28:G39) -> 548101.2 | J28: =D134 -> 618630.15 | L28: 4 | M28: 4. DC Equipment | U28: =(Q28/$X$28*$J$28) -> 0 | V28: =J28-SUM(U28:U39) -> 0.0018643818 | X28: =SUM(Q28:Q39) -> 671199.26 | Z28: =Z9 -> DC Equipment | AA28: 336509.25
L29: 4 | M29: 4. DC Equipment | N29: DC Cable | O29: 16000 | P29: 13.89 | Q29: =O29*P29 -> 222240 | R29: PO3611-RSV-20210131 - RV Approved | S29: Krannich - Inv 15-10011997 | T29: =T6 -> 45747 | U29: 205240.6 | W29: 45785 | Z29: =Z10 -> AC Labour | AA29: 180000 | AC29: =AA29/600000 -> 0.3
L30: 4 | M30: 4. DC Equipment | O30: 2000 | Q30: =55560*2 -> 111120 | S30: Krannich Inv: 15-10012069 | T30: 45747 | U30: 102620.3 | W30: 45785 | Z30: =Z11 -> DC Labour | AA30: 420000 | AC30: =AA30/600000 -> 0.7
B31: 4 | D31: Project Kick Off | F31: 0.1 | G31: =$C$32*F31 -> 33826.92 | H31: =H75 -> 45719 | L31: 4 | M31: 4. DC Equipment | N31: DC Cable - JHB Stock | O31: 100 | P31: 13.3 | Q31: =O31*P31 -> 1330 | S31: Allocated from JHB Storeroom | T31: 45900 | U31: 1225.8328 | W31: 45900 | Z31: =Z12 -> Offloading | AA31: 8800
B32: 4 | C32: 338269.2 | D32: Site Establishment | F32: 0.15 | G32: =$C$32*F32 -> 50740.38 | H32: =H76 -> 45733 | L32: 4 | M32: 4. DC Equipment | N32: =N75 -> Deposit | O32: =AA28 -> 336509.25 | P32: =P75 -> 0.3 | Q32: =$O$32*P32 -> 100952.77 | R32: PO3717-RSC-20250305 - RV Approved | S32: Cosmic Sun - CS_RSC_001 | T32: =T75 -> 45747 | U32: 93230.776 | W32: =W75 -> 45729 | Z32: =Z13 -> Roof Access/Scaffolding | AA32: 34100
B33: 4 | D33: AC Installation Complete | F33: 0.2 | G33: =$C$32*F33 -> 67653.84 | H33: =H77 -> 45793 | L33: 4 | M33: 4. DC Equipment | N33: =N76 -> All DC and AC Equipment on site | P33: =P76 -> 0.2 | Q33: =$O$32*P33 -> 67301.85 | S33: Cosmic Sun - CS_RSC_002 | T33: =T76 -> 45777 | U33: 62153.851 | W33: =W76 -> 45785 | Z33: =Z14 -> Storage | AA33: 8657
B34: 4 | D34: DC Installation Complete | F34: 0.25 | G34: =$C$32*F34 -> 84567.3 | H34: =H78 -> 45793 | L34: 4 | M34: 4. DC Equipment | N34: =N77 -> Practical completion | P34: =P77 -> 0.3 | Q34: 100952.78 | S34: Cosmic Sun - CS_RSC_003 | T34: =T77 -> 45838 | U34: 93230.77 | W34: =W77 -> 45855 | Z34: HSE | AA34: 4500
B35: 4 | D35: Commissioning Complete | F35: 0.1 | G35: =$C$32*F35 -> 33826.92 | H35: =H79 -> 45807 | L35: 4 | M35: 4. DC Equipment | N35: =N78 -> Site fully commissioned | P35: =P78 -> 0.15 | Q35: 50476.39 | S35: Cosmic Sun - CS_RSC_004 | T35: =T78 -> 45838 | U35: 46615.39 | W35: =W78 -> 45862 | Z35: Other | AA35: =AA16*0.75 -> 0
B36: 4 | D36: Site De-establisment | F36: 0.1 | G36: =$C$32*F36 -> 33826.92 | H36: =H80 -> 45874 | L36: 4 | M36: 4. DC Equipment | N36: =N79 -> Retention | P36: =P79 -> 0.05 | Q36: =$O$32*P36 -> 16825.463 | S36: Cosmic Sun - CS_RSC_007 | T36: =T79 -> 45900 | U36: 14312.633 | W36: =W79 -> 45890 | Z36: Other | AA36: 0
B37: 4 | D37: Handover Document Complete | F37: 0.05 | G37: =$C$32*F37 -> 16913.46 | H37: =H81 -> 45818 | L37: 4 | M37: 4. DC Equipment | U37: =(Q37/$X$28*$J$28) -> 0 | Z37: Other | AA37: 0
B38: 4 | D38: End of Defects Period | F38: 0.05 | G38: =$C$32*F38 -> 16913.46 | H38: =H82 -> 45848 | L38: 4 | M38: 4. DC Equipment | U38: =(Q38/$X$28*$J$28) -> 0 | Z38: Total | AA38: =SUM(AA27:AA37) -> 1349827.2
B39: 4 | L39: 4 | M39: 4. DC Equipment | U39: =(Q39/$X$28*$J$28) -> 0 | Z39: R/Wp | AA39: =+AA38/'Project Plan'!$E$3/1000 -> 2.2497121
T40: =IF(W40>1,EOMONTH(W40,0),"")
B41: 5 | C41: Monitoring | D41: Smartlogger 3000 | G41: 26000 | H41: =H13 -> 45757 | I41: =SUM(G41:G46) -> 49000 | J41: =D136 -> 55305.256 | L41: 5 | M41: 5. Monitoring | U41: =(Q41/$X$41*$J$41) -> 0 | V41: =J41-SUM(U41:U46) -> 0 | X41: =SUM(Q41:Q46) -> 33421.96
B42: 5 | D42: Comms DB | G42: 8000 | H42: =H41 -> 45757 | L42: 5 | M42: 5. Monitoring | N42: CTs, Meters, Router - AccuEnergy | Q42: 13396 | R42: PO3718-RSC-20250305 - RV Approved | S42: AccuEnergy Inv ASAI-004973 | T42: 45747 | U42: 22167.138 | W42: =T42+30 -> 45777
B43: 5 | L43: 5 | M43: 5. Monitoring | U43: 0
B44: 5 | L44: 5 | M44: 5. Monitoring | N44: Smartlogger 3000 | Q44: 8333.33 | R44: PO3611-RSV-20210131 - RV Approved | S44: Krannich - Inv 15-10011997 | T44: =T6 -> 45747 | U44: 13789.645 | W44: 45785
B45: 5 | D45: Revenue Grade Meter | G45: 15000 | H45: =H38 -> 45848 | L45: 5 | M45: 5. Monitoring | N45: Revenue Grade Meter | Q45: 11169 | S45: Matriarch - INV-4082 | T45: 45747 | U45: 18481.992 | W45: =T45+30 -> 45777
B46: 5 | L46: 5 | M46: 5. Monitoring | N46: Delivery of Techsitter | Q46: 523.63 | S46: DSV Inv: 180122089 | T46: 45747 | U46: 866.48094 | W46: 45777
T47: =IF(W47>1,EOMONTH(W47,0),"")
B48: 6 | C48: AC Equipment | I48: =SUM(G48:G56) -> 842399.37 | J48: =D135 -> 950798.22 | L48: 6 | M48: 6. AC Equipment | T48: =IF(W48>1,EOMONTH(W48,0),"") | V48: =J48-SUM(U48:U56) -> -0.0024492538 | X48: =SUM(Q48:Q56) -> 390951.5
B49: 6 | D49: Project Kick Off | F49: 0.1 | G49: =C50*F49 -> 84239.937 | H49: ='Project Plan'!E20-7 -> 45719 | L49: 6 | M49: 6. AC Equipment | N49: =N75 -> Deposit | O49: =AA27 -> 357261 | P49: =P75 -> 0.3 | Q49: =O$49*P49 -> 107178.3 | R49: PO3717-RSC-20250305 - RV Approved | S49: Cosmic Sun - CS_RSC_001 | T49: =T75 -> 45747 | U49: 285239.47 | W49: =W75 -> 45729
B50: 6 | C50: 842399.37 | D50: Site Establishment | F50: 0.15 | G50: =$C$50*F50 -> 126359.91 | H50: ='Project Plan'!E20+7 -> 45733 | L50: 6 | M50: 6. AC Equipment | N50: =N76 -> All DC and AC Equipment on site | P50: =P76 -> 0.2 | Q50: =O$49*P50 -> 71452.2 | S50: Cosmic Sun - CS_RSC_002 | T50: =T76 -> 45777 | U50: 190159.64 | W50: =W76 -> 45785
B51: 6 | D51: AC Installation Complete | F51: 0.2 | G51: =$C$50*F51 -> 168479.87 | H51: ='Project Plan'!G22+7 -> 45793 | L51: 6 | M51: 6. AC Equipment | N51: =N77 -> Practical completion | P51: =P77 -> 0.3 | Q51: =O$49*P51 -> 107178.3 | S51: Cosmic Sun - CS_RSC_003 | T51: =T77 -> 45838 | U51: 208441.99 | W51: =W77 -> 45855
B52: 6 | D52: DC Installation Complete | F52: 0.25 | G52: =$C$50*F52 -> 210599.84 | H52: ='Project Plan'!G29+7 -> 45793 | L52: 6 | M52: 6. AC Equipment | N52: =N78 -> Site fully commissioned | P52: =P78 -> 0.15 | Q52: =O$49*P52 -> 53589.15 | S52: Cosmic Sun - CS_RSC_004 | T52: =T78 -> 45838 | U52: 92421.511 | W52: =W78 -> 45862
B53: 6 | D53: Commissioning Complete | F53: 0.1 | G53: =$C$50*F53 -> 84239.937 | H53: ='Project Plan'!G40+7 -> 45807 | L53: 6 | M53: 6. AC Equipment | N53: =N79 -> Retention | P53: =P79 -> 0.05 | Q53: =O$49*P53 -> 17863.05 | S53: Cosmic Sun - CS_RSC_007 | T53: =T79 -> 45900 | U53: 40855.608 | W53: =W79 -> 45890
B54: 6 | D54: Site De-establisment | F54: 0.1 | G54: =$C$50*F54 -> 84239.937 | H54: ='Project Plan'!K49+7 -> 45874 | L54: 6 | M54: 6. AC Equipment | N54: 3P Breaker moved to Stock | Q54: -24757 | S54: Allocated to Jhb Storeroom | T54: 45900 | U54: 0 | W54: 45900
B55: 6 | D55: Handover Document Complete | F55: 0.05 | G55: =$C$50*F55 -> 42119.968 | H55: ='Project Plan'!G48+7 -> 45818 | L55: 6 | M55: 6. AC Equipment | N55: AC Cable for Tie In VO - Cosmic Sun | Q55: 29881.5 | R55: PO4026-RSC-20250524 - RV Approved | S55: Cosmic Sun - CS_RSC_005 | T55: 45869 | U55: 68344.394 | W55: 45849
B56: 6 | D56: End of Defects Period | F56: 0.05 | G56: =$C$50*F56 -> 42119.968 | H56: =H55+30 -> 45848 | L56: 6 | M56: 6. AC Equipment | N56: 4P Breaker VO- Cosmic Sun | Q56: 28566 | R56: PO4084-RSC-20250702 - RV Approved | S56: Cosmic Sun - CS_RSC_006 | T56: 45869 | U56: 65335.607 | W56: 45849
T57: =IF(W57>1,EOMONTH(W57,0),"")
B58: 7 | C58: Battery Systems | I58: =SUM(G58:G65) -> 0 | J58: 0 | L58: 7 | M58: Battery Systems | T58: =IF(W58>1,EOMONTH(W58,0),"") | V58: =J58-SUM(U58:U65) -> 0 | X58: =SUM(Q58:Q65) -> 0
B59: 7 | L59: 7 | T59: =IF(W59>1,EOMONTH(W59,0),"")
B60: 7 | L60: 7 | T60: =IF(W60>1,EOMONTH(W60,0),"")
B61: 7 | L61: 7 | T61: =IF(W61>1,EOMONTH(W61,0),"")
B62: 7 | L62: 7 | T62: =IF(W62>1,EOMONTH(W62,0),"")
B63: 7 | L63: 7 | T63: =IF(W63>1,EOMONTH(W63,0),"")
B64: 7 | L64: 7 | T64: =IF(W64>1,EOMONTH(W64,0),"")
B65: 7 | L65: 7 | T65: =IF(W65>1,EOMONTH(W65,0),"")
T66: =IF(W66>1,EOMONTH(W66,0),"")
B67: 8 | C67: Product Add On | I67: =SUM(G67:G73) -> 350000 | J67: =D139 -> 350000 | L67: 8 | M67: 8. Product Add On | N67: PV DB Cage/Enclosure Add on - JRL Eng | O67: 89800 | P67: 0.8 | Q67: =O67*P67 -> 71840 | R67: PO3924-RSC-20250516 - RV Approved | S67: JRL Engineering - INV00322 | T67: 45808 | U67: 0 | V67: =J67-SUM(U67:U73) -> 0 | W67: 45799 | X67: =SUM(Q67:Q73) -> 138014.52 | Y67: Client to be invoiced Variation of R44358,35 incl VAT
B68: 8 | D68: Extra Capex | G68: 350000 | H68: =H53 -> 45807 | L68: 8 | M68: 8. Product Add On | N68: PV DB Cage/Enclosure Add on - JRL Eng | P68: 0.2 | Q68: =O67*P68 -> 17960 | S68: JRL Engineering - INV00322 | T68: 45808 | U68: 0 | W68: 45827
B69: 8 | L69: 8 | M69: 8. Product Add On | N69: PV DB Cage/Enclosure - JRL - Deposit | O69: 61258 | P69: 0.5 | Q69: =O69*P69 -> 30629 | R69: PO3802-RSC-20250414 - RV Approved | S69: JRL Engineering - INV 2025063 | T69: 45777 | U69: 175000 | W69: 45764
B70: 8 | L70: 8 | M70: 8. Product Add On | N70: PV DB Cage/Enclosure - JRL - Balance | P70: 0.3 | Q70: =O69*P70 -> 18377.4 | S70: JRL Engineering - INV 2025063 | T70: 45777 | U70: 0 | W70: 45772
L71: 8 | M71: 8. Product Add On | N71: PV DB Cage/Enclosure - JRL - Balance | P71: 0.2 | Q71: 12251.6 | S71: JRL Engineering - INV 2025063 | T71: 45777 | U71: 0 | W71: 45827
B72: 8 | L72: 8 | M72: 8. Product Add On | N72: PV DB Cage/Enclosure - JRL - Credit | Q72: -13043.48 | S72: JRL Engineering - Credit ICA10016 | T72: 45838 | W72: 45838
B73: 8 | L73: 8 | M73: 8. Product Add On | T73: 45900 | U73: 175000 | W73: 45838
K74: Only services to be capture below, products above | T74: =IF(W74>1,EOMONTH(W74,0),"")
B75: 9 | C75: AC & DC Installation | D75: Project Kick Off | F75: 0.1 | G75: =SUM($C$76:$C$77)*F75 -> 50989.25 | H75: =H49 -> 45719 | I75: =SUM(G75:G82) -> 509892.5 | J75: =D144+D145 -> 599873.53 | L75: 9 | M75: 9. AC & DC installation | N75: Deposit | O75: =AA29+AA30 -> 600000 | P75: 0.3 | Q75: =$O$75*P75 -> 180000 | R75: PO3717-RSC-20250305 - RV Approved | S75: Cosmic Sun - CS_RSC_001 | T75: =IF(W75>1,EOMONTH(W75,0),"") -> 45747 | U75: 179962.06 | V75: 0 | W75: 45729 | X75: =SUM(Q75:Q82) -> 600000
B76: 9 | C76: 150127.5 | D76: Site Establishment | F76: 0.15 | G76: =SUM($C$76:$C$77)*F76 -> 76483.875 | H76: =H50 -> 45733 | L76: 9 | M76: 9. AC & DC installation | N76: All DC and AC Equipment on site | P76: 0.2 | Q76: =$O$75*P76 -> 120000 | S76: Cosmic Sun - CS_RSC_002 | T76: 45777 | U76: 119974.71 | W76: 45785
B77: 9 | C77: 359765 | D77: AC Installation Complete | F77: 0.2 | G77: =SUM($C$76:$C$77)*F77 -> 101978.5 | H77: =H51 -> 45793 | L77: 9 | M77: 9. AC & DC installation | N77: Practical completion | P77: 0.3 | Q77: =$O$75*P77 -> 180000 | S77: Cosmic Sun - CS_RSC_003 | T77: 45838 | U77: 179962.06 | W77: 45855
B78: 9 | D78: DC Installation Complete | F78: 0.25 | G78: =SUM($C$76:$C$77)*F78 -> 127473.12 | H78: =H52 -> 45793 | L78: 9 | M78: 9. AC & DC installation | N78: Site fully commissioned | P78: 0.15 | Q78: =$O$75*P78 -> 90000 | S78: Cosmic Sun - CS_RSC_004 | T78: 45838 | U78: 89981.029 | W78: 45862
B79: 9 | D79: Commissioning Complete | F79: 0.1 | G79: =SUM($C$76:$C$77)*F79 -> 50989.25 | H79: =H53 -> 45807 | L79: 9 | M79: 9. AC & DC installation | N79: Retention | P79: 0.05 | Q79: =$O$75*P79 -> 30000 | S79: Cosmic Sun - CS_RSC_007 | T79: 45900 | U79: 29993.676 | W79: 45890
B80: 9 | D80: Site De-establisment | F80: 0.1 | G80: =SUM($C$76:$C$77)*F80 -> 50989.25 | H80: =H54 -> 45874 | L80: 9 | M80: 9. AC & DC installation | U80: =(Q80/$X$75*$J$75) -> 0
B81: 9 | D81: Handover Document Complete | F81: 0.05 | G81: =SUM($C$76:$C$77)*F81 -> 25494.625 | H81: =H55 -> 45818 | L81: 9 | M81: 9. AC & DC installation | U81: =(Q81/$X$75*$J$75) -> 0
B82: 9 | D82: End of Defects Period | F82: 0.05 | G82: =SUM($C$76:$C$77)*F82 -> 25494.625 | H82: =H56 -> 45848 | L82: 9 | M82: 9. AC & DC installation | U82: =(Q82/$X$75*$J$75) -> 0
T83: =IF(W83>1,EOMONTH(W83,0),"")
B84: 10 | C84: Site Logistics | D84: Security | G84: 144000 | H84: =H82 -> 45848 | I84: =SUM(G84:G98) -> 214099.5 | J84: =D152+D151+D150+D149+D148 -> 251881.76 | L84: 10 | M84: 10. Site Logistics | V84: =J84-SUM(U84:U98) -> 0.002860695 | X84: =SUM(Q84:Q98) -> 77457
L85: 10 | M85: 10. Site Logistics | N85: Security - March | Q85: 4050 | R85: PO3584-RSV-20250129 - RV Approved | S85: INFANTRY - IN-2560 | T85: 45688 | U85: 4810.7689 | W85: 45744 | Y85: Credit note requested
L86: 10 | M86: 10. Site Logistics | N86: Security - April | Q86: 5350 | R86: PO3585-RSV-20250129 - RV Approved | S86: INFANTRY - IN-2561 | T86: 45688 | U86: 6354.9664 | W86: 45744 | Y86: Credit note requested
L87: 10 | M87: 10. Site Logistics | N87: Security - Credit Note - Late start | Q87: -5350 | S87: INFANTRY-CN-2643 | T87: 45747 | U87: 0 | W87: 45747
L88: 10 | M88: 10. Site Logistics | N88: Security - Credit Note - Late start | Q88: -4050 | S88: INFANTRY - CN-2642 | T88: 45747 | U88: 0 | W88: 45747
L89: 10 | M89: 10. Site Logistics | N89: Security March - Infantry | Q89: 8250 | S89: INFANTRY - IN-2688 | T89: 45747 | U89: -5807.1211 | W89: 45744
L90: 10 | M90: 10. Site Logistics | N90: Security - April | Q90: 2250 | R90: PO3811-RSC-20250416 - RV Approved | S90: Infantry - IN-2689 | T90: 45777 | U90: 5480.6151 | W90: 45764
B91: 10 | D91: Scaffolding | G91: 54199.5 | H91: =H92 -> 45807 | L91: 10 | M91: 10. Site Logistics | N91: =N75 -> Deposit | O91: =AA34+AA33+AA32+AA31 -> 56057 | P91: =P75 -> 0.3 | Q91: =$O$91*P91 -> 16817.1 | R91: PO3717-RSC-20250305 - RV Approved | S91: Cosmic Sun - CS_RSC_001 | T91: =T75 -> 45747 | U91: 40963.579 | W91: =W75 -> 45729
B92: 10 | D92: Site Storage | G92: 7400 | H92: =H95 -> 45807 | L92: 10 | M92: 10. Site Logistics | N92: =N76 -> All DC and AC Equipment on site | P92: =P76 -> 0.2 | Q92: =$O$91*P92 -> 11211.4 | S92: Cosmic Sun - CS_RSC_002 | T92: =T76 -> 45777 | U92: 27309.053 | W92: =W76 -> 45785
B93: 10 | L93: 10 | M93: 10. Site Logistics | N93: =N77 -> Practical completion | P93: =P77 -> 0.3 | Q93: =$O$91*P93 -> 16817.1 | S93: Cosmic Sun - CS_RSC_003 | T93: =T77 -> 45838 | U93: 54687.386 | W93: =W77 -> 45855
B94: 10 | L94: 10 | M94: 10. Site Logistics | N94: =N78 -> Site fully commissioned | P94: =P78 -> 0.15 | Q94: =$O$91*P94 -> 8408.55 | S94: Cosmic Sun - CS_RSC_004 | T94: =T78 -> 45838 | U94: 27343.693 | W94: =W78 -> 45862
B95: 10 | D95: Offloading | G95: 8500 | H95: =H79 -> 45807 | L95: 10 | M95: 10. Site Logistics | N95: =N79 -> Retention | P95: =P79 -> 0.05 | Q95: =$O$91*P95 -> 2802.85 | S95: Cosmic Sun - CS_RSC_007 | T95: =T79 -> 45900 | U95: 9114.5643 | W95: =W79 -> 45890
B96: 10 | L96: 10 | M96: 10. Site Logistics | N96: Crane Hire - SCO | Q96: 10900 | R96: PO3724-RSC-20250306 - RV Approved | S96: Supply Chain Inv: SCO05072 | T96: 45838 | U96: 81624.258 | W96: 45855
B97: 10 | L97: 10 | M97: 10. Site Logistics
B98: 10 | L98: 10 | M98: 10. Site Logistics
T99: =IF(W99>1,EOMONTH(W99,0),"")
B100: 11 | C100: Due Dilligence | D100: Electrical PrEng sign off | G100: 15012.75 | H100: ='Project Plan'!G42+14 -> 45814 | I100: =SUM(G100:G104) -> 132038.25 | J100: =D147 -> 155339.12 | L100: 11 | M100: 11. Due Dilligence | N100: Electrical PrEng sign off | Q100: 15750 | S100: Sunspot E026 | T100: 45838 | U100: 22754.87 | V100: =J100-SUM(U100:U104) -> -0.0013731373 | W100: 45867 | X100: =SUM(Q100:Q104) -> 102050
B101: 11 | D101: Structural sign off | G101: 30025.5 | H101: ='Project Plan'!E19-14 -> 45712 | L101: 11 | M101: 11. Due Dilligence | N101: Structural sign off - LnB Eng | Q101: 7500 | R101: PO3586-RSV-20250129 - RV Approved | S101: L&B Consulting INV-1893 | T101: 45688 | U101: 10638.427 | W101: =T101+7 -> 45695
B102: 11 | L102: 11 | M102: 11. Due Dilligence | N102: Red Team | Q102: 8000 | S102: Matriarch - IN-4753 | T102: 45869 | U102: 13703.881 | W102: =T102 -> 45869
B103: 11 | D103: Grid Study - Outside of CoCT | G103: 80000 | H103: =H111 -> 45846 | L103: 11 | M103: 11. Due Dilligence | N103: Grid Study - Outside of CoCT | Q103: 65700 | R103: PO3687-RSC-20250220 - RV Approved | S103: Okusha Electrical Inv EE10 | T103: 45777 | U103: 98881.001 | W103: 46112
...

Sheet Cashflow
D1: [RT: Double Check the first date is always a MONDAY] | F1: 45677 | G1: =F1+7 -> 45684 | H1: =G1+7 -> 45691 | I1: =H1+7 -> 45698 | J1: =I1+7 -> 45705 | K1: =J1+7 -> 45712 | L1: =K1+7 -> 45719 | M1: =L1+7 -> 45726 | N1: =M1+7 -> 45733 | ... CP1: =CO1+7 -> 46293
A2: PLANNED | C2: CHECK | D2: CHECK
B3: Planned Revenue | C3: ='Revenue Tracking'!D4 -> 5813800 | D3: =SUM(F3:CP3) -> 5852178.3 | F3: =SUMIFS('Revenue Tracking'!$F$13:$F$19, 'Revenue Tracking'!$H$13:$H$19, ">="&F1,'Revenue Tracking'!$H$13:$H$19, "<"&G1) -> 0 | G3: =SUMIFS('Revenue Tracking'!$F$13:$F$19, 'Revenue Tracking'!$H$13:$H$19, ">="&G1,'Revenue Tracking'!$H$13:$H$19, "<"&H1) -> 0 | H3: =SUMIFS('Revenue Tracking'!$F$13:$F$19, 'Revenue Tracking'!$H$13:$H$19, ">="&H1,'Revenue Tracking'!$H$13:$H$19, "<"&I1) -> 0 | I3: =SUMIFS('Revenue Tracking'!$F$13:$F$19, 'Revenue Tracking'!$H$13:$H$19, ">="&I1,'Revenue Tracking'!$H$13:$H$19, "<"&J1) -> 0 | J3: =SUMIFS('Revenue Tracking'!$F$13:$F$19, 'Revenue Tracking'!$H$13:$H$19, ">="&J1,'Revenue Tracking'!$H$13:$H$19, "<"&K1) -> 0 | K3: =SUMIFS('Revenue Tracking'!$F$13:$F$19, 'Revenue Tracking'!$H$13:$H$19, ">="&K1,'Revenue Tracking'!$H$13:$H$19, "<"&L1) -> 2034830 | L3: =SUMIFS('Revenue Tracking'!$F$13:$F$19, 'Revenue Tracking'!$H$13:$H$19, ">="&L1,'Revenue Tracking'!$H$13:$H$19, "<"&M1) -> 0 | M3: =SUMIFS('Revenue Tracking'!$F$13:$F$19, 'Revenue Tracking'!$H$13:$H$19, ">="&M1,'Revenue Tracking'!$H$13:$H$19, "<"&N1) -> 0 | ... CP3: =SUMIFS('Revenue Tracking'!$F$13:$F$19, 'Revenue Tracking'!$H$13:$H$19, ">="&CP1,'Revenue Tracking'!$H$13:$H$19, "<"&CQ1) -> 0
B4: Planned Revenue - Cumulative | F4: =F3 -> 0 | G4: =F4+G3 -> 0 | H4: =G4+H3 -> 0 | I4: =H4+I3 -> 0 | J4: =I4+J3 -> 0 | K4: =J4+K3 -> 2034830 | L4: =K4+L3 -> 2034830 | M4: =L4+M3 -> 2034830 | N4: =M4+N3 -> 2034830 | ... CP4: =CO4+CP3 -> 5852178.3
B5: Planned Expenditure | C5: ='Revenue Tracking'!D5 -> 5151610.7 | D5: =SUM(F5:CP5) -> 5151610.7 | F5: =SUMIFS('Expenditure Breakdown'!$G$6:$G$129, 'Expenditure Breakdown'!$H$6:$H$129, ">="&F1,'Expenditure Breakdown'!$H$6:$H$129, "<"&G1) -> 0 | G5: =SUMIFS('Expenditure Breakdown'!$G$6:$G$129, 'Expenditure Breakdown'!$H$6:$H$129, ">="&G1,'Expenditure Breakdown'!$H$6:$H$129, "<"&H1) -> 0 | H5: =SUMIFS('Expenditure Breakdown'!$G$6:$G$129, 'Expenditure Breakdown'!$H$6:$H$129, ">="&H1,'Expenditure Breakdown'!$H$6:$H$129, "<"&I1) -> 0 | I5: =SUMIFS('Expenditure Breakdown'!$G$6:$G$129, 'Expenditure Breakdown'!$H$6:$H$129, ">="&I1,'Expenditure Breakdown'!$H$6:$H$129, "<"&J1) -> 0 | J5: =SUMIFS('Expenditure Breakdown'!$G$6:$G$129, 'Expenditure Breakdown'!$H$6:$H$129, ">="&J1,'Expenditure Breakdown'!$H$6:$H$129, "<"&K1) -> 0 | K5: =SUMIFS('Expenditure Breakdown'!$G$6:$G$129, 'Expenditure Breakdown'!$H$6:$H$129, ">="&K1,'Expenditure Breakdown'!$H$6:$H$129, "<"&L1) -> 30025.5 | L5: =SUMIFS('Expenditure Breakdown'!$G$6:$G$129, 'Expenditure Breakdown'!$H$6:$H$129, ">="&L1,'Expenditure Breakdown'!$H$6:$H$129, "<"&M1) -> 169056.11 | M5: =SUMIFS('Expenditure Breakdown'!$G$6:$G$129, 'Expenditure Breakdown'!$H$6:$H$129, ">="&M1,'Expenditure Breakdown'!$H$6:$H$129, "<"&N1) -> 0 | ... CP5: =SUMIFS('Expenditure Breakdown'!$G$6:$G$129, 'Expenditure Breakdown'!$H$6:$H$129, ">="&CP1,'Expenditure Breakdown'!$H$6:$H$129, "<"&CQ1) -> 0
B6: Planned Expenditure - Cumulative | F6: =F5 -> 0 | G6: =F6+G5 -> 0 | H6: =G6+H5 -> 0 | I6: =H6+I5 -> 0 | J6: =I6+J5 -> 0 | K6: =J6+K5 -> 30025.5 | L6: =K6+L5 -> 199081.61 | M6: =L6+M5 -> 199081.61 | N6: =M6+N5 -> 452665.77 | ... CP6: =CO6+CP5 -> 5151610.7
B7: PLANNED CashFlow | F7: =F4-F6 -> 0 | G7: =G4-G6 -> 0 | H7: =H4-H6 -> 0 | I7: =I4-I6 -> 0 | J7: =J4-J6 -> 0 | K7: =K4-K6 -> 2004804.5 | L7: =L4-L6 -> 1835748.4 | M7: =M4-M6 -> 1835748.4 | ... CP7: =CP4-CP6 -> 700567.54
A8: ACTUAL | C8: CHECK | D8: CHECK
B9: Actual + Planned Revenue | C9: ='Revenue Tracking'!F4 -> 5852178.3 | D9: =SUM(F9:CP9) -> 5852178.3 | F9: =SUMIFS('Revenue Tracking'!$F$13:$F$19, 'Revenue Tracking'!$P$13:$P$19, ">="&F1,'Revenue Tracking'!$P$13:$P$19, "<"&G1) -> 0 | G9: =SUMIFS('Revenue Tracking'!$F$13:$F$19, 'Revenue Tracking'!$P$13:$P$19, ">="&G1,'Revenue Tracking'!$P$13:$P$19, "<"&H1) -> 0 | H9: =SUMIFS('Revenue Tracking'!$F$13:$F$19, 'Revenue Tracking'!$P$13:$P$19, ">="&H1,'Revenue Tracking'!$P$13:$P$19, "<"&I1) -> 0 | I9: =SUMIFS('Revenue Tracking'!$F$13:$F$19, 'Revenue Tracking'!$P$13:$P$19, ">="&I1,'Revenue Tracking'!$P$13:$P$19, "<"&J1) -> 0 | J9: =SUMIFS('Revenue Tracking'!$F$13:$F$19, 'Revenue Tracking'!$P$13:$P$19, ">="&J1,'Revenue Tracking'!$P$13:$P$19, "<"&K1) -> 0 | K9: =SUMIFS('Revenue Tracking'!$F$13:$F$19, 'Revenue Tracking'!$P$13:$P$19, ">="&K1,'Revenue Tracking'!$P$13:$P$19, "<"&L1) -> 0 | L9: =SUMIFS('Revenue Tracking'!$F$13:$F$19, 'Revenue Tracking'!$P$13:$P$19, ">="&L1,'Revenue Tracking'!$P$13:$P$19, "<"&M1) -> 0 | M9: =SUMIFS('Revenue Tracking'!$F$13:$F$19, 'Revenue Tracking'!$P$13:$P$19, ">="&M1,'Revenue Tracking'!$P$13:$P$19, "<"&N1) -> 0 | ... CP9: =SUMIFS('Revenue Tracking'!$F$13:$F$19, 'Revenue Tracking'!$P$13:$P$19, ">="&CP1,'Revenue Tracking'!$P$13:$P$19, "<"&CQ1) -> 0
B10: Actual + Planned Revenue - Cumulative | F10: =F9 -> 0 | G10: =F10+G9 -> 0 | H10: =G10+H9 -> 0 | I10: =H10+I9 -> 0 | J10: =I10+J9 -> 0 | K10: =J10+K9 -> 0 | L10: =K10+L9 -> 0 | M10: =L10+M9 -> 0 | N10: =M10+N9 -> 1744140 | ... CP10: =CO10+CP9 -> 5852178.3
B11: Actual + Planned Expenditure | C11: ='Revenue Tracking'!F5 -> 4046134 | D11: =SUM(F11:CP11) -> 4046134 | F11: =SUMIFS('Expenditure Breakdown'!$Q$6:$Q$129, 'Expenditure Breakdown'!$W$6:$W$129, ">="&F1,'Expenditure Breakdown'!$W$6:$W$129, "<"&G1) -> 0 | G11: =SUMIFS('Expenditure Breakdown'!$Q$6:$Q$129, 'Expenditure Breakdown'!$W$6:$W$129, ">="&G1,'Expenditure Breakdown'!$W$6:$W$129, "<"&H1) -> 0 | H11: =SUMIFS('Expenditure Breakdown'!$Q$6:$Q$129, 'Expenditure Breakdown'!$W$6:$W$129, ">="&H1,'Expenditure Breakdown'!$W$6:$W$129, "<"&I1) -> 8102.58 | I11: =SUMIFS('Expenditure Breakdown'!$Q$6:$Q$129, 'Expenditure Breakdown'!$W$6:$W$129, ">="&I1,'Expenditure Breakdown'!$W$6:$W$129, "<"&J1) -> 0 | J11: =SUMIFS('Expenditure Breakdown'!$Q$6:$Q$129, 'Expenditure Breakdown'!$W$6:$W$129, ">="&J1,'Expenditure Breakdown'!$W$6:$W$129, "<"&K1) -> 0 | K11: =SUMIFS('Expenditure Breakdown'!$Q$6:$Q$129, 'Expenditure Breakdown'!$W$6:$W$129, ">="&K1,'Expenditure Breakdown'!$W$6:$W$129, "<"&L1) -> 0 | L11: =SUMIFS('Expenditure Breakdown'!$Q$6:$Q$129, 'Expenditure Breakdown'!$W$6:$W$129, ">="&L1,'Expenditure Breakdown'!$W$6:$W$129, "<"&M1) -> 514.98 | M11: =SUMIFS('Expenditure Breakdown'!$Q$6:$Q$129, 'Expenditure Breakdown'!$W$6:$W$129, ">="&M1,'Expenditure Breakdown'!$W$6:$W$129, "<"&N1) -> 404948.17 | ... CP11: =SUMIFS('Expenditure Breakdown'!$Q$6:$Q$129, 'Expenditure Breakdown'!$W$6:$W$129, ">="&CP1,'Expenditure Breakdown'!$W$6:$W$129, "<"&CQ1) -> 0
B12: Actual + Planned Expenditure - Cumulative | F12: =F11 -> 0 | G12: =F12+G11 -> 0 | H12: =G12+H11 -> 8102.58 | I12: =H12+I11 -> 8102.58 | J12: =I12+J11 -> 8102.58 | K12: =J12+K11 -> 8102.58 | L12: =K12+L11 -> 8617.56 | M12: =L12+M11 -> 413565.73 | N12: =M12+N11 -> 413565.73 | ... CP12: =CO12+CP11 -> 4046134
B14: ACTUAL CashFlow | F14: =F10-F12 -> 0 | G14: =G10-G12 -> 0 | H14: =H10-H12 -> -8102.58 | I14: =I10-I12 -> -8102.58 | J14: =J10-J12 -> -8102.58 | K14: =K10-K12 -> -8102.58 | L14: =L10-L12 -> -8617.56 | M14: =M10-M12 -> -413565.73 | ... CP14: =CP10-CP12 -> 1806044.2
C16: CHECK | D16: CHECK
B17: Revenue Recognition | C17: =C3-D17 -> 0.0044473372 | D17: =SUM(F17:CP17) -> 5813800 | F17: =SUMIFS('Expenditure Breakdown'!$U$6:$U$129, 'Expenditure Breakdown'!$T$6:$T$129, ">="&F1,'Expenditure Breakdown'!$T$6:$T$129, "<"&G1) -> 0 | G17: =SUMIFS('Expenditure Breakdown'!$U$6:$U$129, 'Expenditure Breakdown'!$T$6:$T$129, ">="&G1,'Expenditure Breakdown'!$T$6:$T$129, "<"&H1) -> 22259.23 | H17: =SUMIFS('Expenditure Breakdown'!$U$6:$U$129, 'Expenditure Breakdown'!$T$6:$T$129, ">="&H1,'Expenditure Breakdown'!$T$6:$T$129, "<"&I1) -> 0 | I17: =SUMIFS('Expenditure Breakdown'!$U$6:$U$129, 'Expenditure Breakdown'!$T$6:$T$129, ">="&I1,'Expenditure Breakdown'!$T$6:$T$129, "<"&J1) -> 0 | J17: =SUMIFS('Expenditure Breakdown'!$U$6:$U$129, 'Expenditure Breakdown'!$T$6:$T$129, ">="&J1,'Expenditure Breakdown'!$T$6:$T$129, "<"&K1) -> 0 | K17: =SUMIFS('Expenditure Breakdown'!$U$6:$U$129, 'Expenditure Breakdown'!$T$6:$T$129, ">="&K1,'Expenditure Breakdown'!$T$6:$T$129, "<"&L1) -> 286.44449 | L17: =SUMIFS('Expenditure Breakdown'!$U$6:$U$129, 'Expenditure Breakdown'!$T$6:$T$129, ">="&L1,'Expenditure Breakdown'!$T$6:$T$129, "<"&M1) -> 0 | M17: =SUMIFS('Expenditure Breakdown'!$U$6:$U$129, 'Expenditure Breakdown'!$T$6:$T$129, ">="&M1,'Expenditure Breakdown'!$T$6:$T$129, "<"&N1) -> 0 | ... CP17: =SUMIFS('Expenditure Breakdown'!$U$6:$U$129, 'Expenditure Breakdown'!$T$6:$T$129, ">="&CP1,'Expenditure Breakdown'!$T$6:$T$129, "<"&CQ1) -> 0
B18: Revenue Recognition Cumulative | C18: =D17-D18 -> 0 | D18: =MAX(F18:CP18) -> 5813800 | F18: =F17 -> 0 | G18: =F18+G17 -> 22259.23 | H18: =G18+H17 -> 22259.23 | I18: =H18+I17 -> 22259.23 | J18: =I18+J17 -> 22259.23 | K18: =J18+K17 -> 22545.675 | L18: =K18+L17 -> 22545.675 | M18: =L18+M17 -> 22545.675 | N18: =M18+N17 -> 22545.675 | ... CP18: =CO18+CP17 -> 5813800
B20: Installer Expenditure | D20: =SUM(F20:CP20) -> 1327460.8 | F20: =SUMIFS('Expenditure Breakdown'!$Q$32:$Q$39, 'Expenditure Breakdown'!$W$32:$W$39, ">="&F1,'Expenditure Breakdown'!$W$32:$W$39, "<"&G1)+SUMIFS('Expenditure Breakdown'!$Q$49:$Q$56, 'Expenditure Breakdown'!$W$49:$W$56, ">="&F1,'Expenditure Breakdown'!$W$49:$W$56, "<"&G1)+SUMIFS('Expenditure Breakdown'!$Q$75:$Q$82, 'Expenditure Breakdown'!$W$75:$W$82, ">="&F1,'Expenditure Breakdown'!$W$75:$W$82, "<"&G1) -> 0 | G20: =SUMIFS('Expenditure Breakdown'!$Q$32:$Q$39, 'Expenditure Breakdown'!$W$32:$W$39, ">="&G1,'Expenditure Breakdown'!$W$32:$W$39, "<"&H1)+SUMIFS('Expenditure Breakdown'!$Q$49:$Q$56, 'Expenditure Breakdown'!$W$49:$W$56, ">="&G1,'Expenditure Breakdown'!$W$49:$W$56, "<"&H1)+SUMIFS('Expenditure Breakdown'!$Q$75:$Q$82, 'Expenditure Breakdown'!$W$75:$W$82, ">="&G1,'Expenditure Breakdown'!$W$75:$W$82, "<"&H1) -> 0 | H20: =SUMIFS('Expenditure Breakdown'!$Q$32:$Q$39, 'Expenditure Breakdown'!$W$32:$W$39, ">="&H1,'Expenditure Breakdown'!$W$32:$W$39, "<"&I1)+SUMIFS('Expenditure Breakdown'!$Q$49:$Q$56, 'Expenditure Breakdown'!$W$49:$W$56, ">="&H1,'Expenditure Breakdown'!$W$49:$W$56, "<"&I1)+SUMIFS('Expenditure Breakdown'!$Q$75:$Q$82, 'Expenditure Breakdown'!$W$75:$W$82, ">="&H1,'Expenditure Breakdown'!$W$75:$W$82, "<"&I1) -> 0 | I20: =SUMIFS('Expenditure Breakdown'!$Q$32:$Q$39, 'Expenditure Breakdown'!$W$32:$W$39, ">="&I1,'Expenditure Breakdown'!$W$32:$W$39, "<"&J1)+SUMIFS('Expenditure Breakdown'!$Q$49:$Q$56, 'Expenditure Breakdown'!$W$49:$W$56, ">="&I1,'Expenditure Breakdown'!$W$49:$W$56, "<"&J1)+SUMIFS('Expenditure Breakdown'!$Q$75:$Q$82, 'Expenditure Breakdown'!$W$75:$W$82, ">="&I1,'Expenditure Breakdown'!$W$75:$W$82, "<"&J1) -> 0 | J20: =SUMIFS('Expenditure Breakdown'!$Q$32:$Q$39, 'Expenditure Breakdown'!$W$32:$W$39, ">="&J1,'Expenditure Breakdown'!$W$32:$W$39, "<"&K1)+SUMIFS('Expenditure Breakdown'!$Q$49:$Q$56, 'Expenditure Breakdown'!$W$49:$W$56, ">="&J1,'Expenditure Breakdown'!$W$49:$W$56, "<"&K1)+SUMIFS('Expenditure Breakdown'!$Q$75:$Q$82, 'Expenditure Breakdown'!$W$75:$W$82, ">="&J1,'Expenditure Breakdown'!$W$75:$W$82, "<"&K1) -> 0 | K20: =SUMIFS('Expenditure Breakdown'!$Q$32:$Q$39, 'Expenditure Breakdown'!$W$32:$W$39, ">="&K1,'Expenditure Breakdown'!$W$32:$W$39, "<"&L1)+SUMIFS('Expenditure Breakdown'!$Q$49:$Q$56, 'Expenditure Breakdown'!$W$49:$W$56, ">="&K1,'Expenditure Breakdown'!$W$49:$W$56, "<"&L1)+SUMIFS('Expenditure Breakdown'!$Q$75:$Q$82, 'Expenditure Breakdown'!$W$75:$W$82, ">="&K1,'Expenditure Breakdown'!$W$75:$W$82, "<"&L1) -> 0 | L20: =SUMIFS('Expenditure Breakdown'!$Q$32:$Q$39, 'Expenditure Breakdown'!$W$32:$W$39, ">="&L1,'Expenditure Breakdown'!$W$32:$W$39, "<"&M1)+SUMIFS('Expenditure Breakdown'!$Q$49:$Q$56, 'Expenditure Breakdown'!$W$49:$W$56, ">="&L1,'Expenditure Breakdown'!$W$49:$W$56, "<"&M1)+SUMIFS('Expenditure Breakdown'!$Q$75:$Q$82, 'Expenditure Breakdown'!$W$75:$W$82, ">="&L1,'Expenditure Breakdown'!$W$75:$W$82, "<"&M1) -> 0 | M20: =SUMIFS('Expenditure Breakdown'!$Q$32:$Q$39, 'Expenditure Breakdown'!$W$32:$W$39, ">="&M1,'Expenditure Breakdown'!$W$32:$W$39, "<"&N1)+SUMIFS('Expenditure Breakdown'!$Q$49:$Q$56, 'Expenditure Breakdown'!$W$49:$W$56, ">="&M1,'Expenditure Breakdown'!$W$49:$W$56, "<"&N1)+SUMIFS('Expenditure Breakdown'!$Q$75:$Q$82, 'Expenditure Breakdown'!$W$75:$W$82, ">="&M1,'Expenditure Breakdown'!$W$75:$W$82, "<"&N1) -> 388131.08 | ... CP20: =SUMIFS('Expenditure Breakdown'!$Q$32:$Q$39, 'Expenditure Breakdown'!$W$32:$W$39, ">="&CP1,'Expenditure Breakdown'!$W$32:$W$39, "<"&CQ1)+SUMIFS('Expenditure Breakdown'!$Q$49:$Q$56, 'Expenditure Breakdown'!$W$49:$W$56, ">="&CP1,'Expenditure Breakdown'!$W$49:$W$56, "<"&CQ1)+SUMIFS('Expenditure Breakdown'!$Q$75:$Q$82, 'Expenditure Breakdown'!$W$75:$W$82, ">="&CP1,'Expenditure Breakdown'!$W$75:$W$82, "<"&CQ1) -> 0
B21: Installer Expenditure - Cumulative | F21: =F20 -> 0 | G21: =G20+F21 -> 0 | H21: =H20+G21 -> 0 | I21: =I20+H21 -> 0 | J21: =J20+I21 -> 0 | K21: =K20+J21 -> 0 | L21: =L20+K21 -> 0 | M21: =M20+L21 -> 388131.08 | N21: =N20+M21 -> 388131.08 | ... CP21: =CP20+CO21 -> 1327460.8

Sheet Finance - Revenue
A1: REVENUE RECOGNITION AMOUNT | B1: (All)
A3: Sum of REVENUE RECOGNITION AMOUNT | B3: Column Labels
A4: Row Labels | C4: (blank) | D4: 45688 | E4: 45716 | F4: 45747 | G4: 45777 | H4: 45808 | I4: 45838 | J4: 45869 | K4: 45900 | L4: Grand Total
A5: (blank)
A6: Battery Systems
A7: BDP Commission
A8: 1. Panels | B8: 0 | F8: 1689109.4 | K8: 0 | L8: 1689109.4
A9: 2. Inverters | B9: 0 | C9: 0 | F9: 395037.54 | L9: 395037.54
A10: 3. Mounting Structures | B10: 0 | C10: 0 | F10: 291443.56 | J10: 13558.719 | L10: 305002.28
A11: 4. DC Equipment | C11: 0 | F11: 401091.67 | G11: 62153.851 | I11: 139846.16 | K11: 15538.465 | L11: 618630.14
A12: 5. Monitoring | C12: 0 | F12: 55305.256 | L12: 55305.256
A13: 6. AC Equipment | F13: 285239.47 | G13: 190159.64 | I13: 300863.5 | J13: 133680 | K13: 40855.608 | L13: 950798.22
A14: 8. Product Add On | G14: 175000 | H14: 0 | K14: 175000 | L14: 350000 | M14: =SUM(L8:L14) -> 4363882.9
A15: 9. AC & DC installation | C15: 0 | F15: 179962.06 | G15: 119974.71 | I15: 269943.09 | K15: 29993.676 | L15: 599873.53
A16: 10. Site Logistics | D16: 11165.735 | F16: 35156.458 | G16: 32789.668 | I16: 163655.34 | K16: 9114.5643 | L16: 251881.76
A17: 11. Due Dilligence | D17: 10638.427 | G17: 98881.001 | I17: 22754.87 | J17: 13703.881 | K17: 9360.9404 | L17: 155339.12
A18: 13. Engineering | B18: 0 | J18: 430469.77 | L18: 430469.77
A19: 14. General Expenses | D19: 455.06798 | E19: 286.44449 | F19: 2011.2568 | G19: 521.11964 | H19: 431.43364 | I19: 2502.1022 | J19: 6145.5144 | L19: 12352.939
A20: 15. Service Add On
A21: Grand Total | B21: 0 | C21: 0 | D21: 22259.23 | E21: 286.44449 | F21: 3334356.7 | G21: 679479.99 | H21: 431.43364 | I21: 899565.06 | J21: 597557.88 | K21: 279863.25 | L21: 5813800
D23: 22148.73 | E23: 286.44 | F23: 3334356.7 | G23: 679479.99 | H23: 431.43 | I23: 899565.06 | J23: 597557.88 | K23: 318352.03 | L23: =SUM(D23:K23) -> 5852178.3
D24: =GETPIVOTDATA("REVENUE RECOGNITION AMOUNT",$A$3,"INVOICE RAISED DATE",DATE(2025,1,31))-D23 -> 110.50016 | E24: =GETPIVOTDATA("REVENUE RECOGNITION AMOUNT",$A$3,"INVOICE RAISED DATE",DATE(2025,2,28))-E23 -> 0.0044888084 | F24: =GETPIVOTDATA("REVENUE RECOGNITION AMOUNT",$A$3,"INVOICE RAISED DATE",DATE(2025,3,31))-F23 -> -0.00079136621 | G24: =GETPIVOTDATA("REVENUE RECOGNITION AMOUNT",$A$3,"INVOICE RAISED DATE",DATE(2025,4,30))-G23 -> -0.00086034602 | H24: =GETPIVOTDATA("REVENUE RECOGNITION AMOUNT",$A$3,"INVOICE RAISED DATE",DATE(2025,5,31))-H23 -> 0.00363583 | I24: =GETPIVOTDATA("REVENUE RECOGNITION AMOUNT",$A$3,"INVOICE RAISED DATE",DATE(2025,6,30))-I23 -> -0.00032972242 | J24: =GETPIVOTDATA("REVENUE RECOGNITION AMOUNT",$A$3,"INVOICE RAISED DATE",DATE(2025,7,31))-J23 -> 0.0044358713 | K24: =GETPIVOTDATA("REVENUE RECOGNITION AMOUNT",$A$3,"INVOICE RAISED DATE",DATE(2025,8,31))-K23 -> -38488.775 | L24: =GETPIVOTDATA("REVENUE RECOGNITION AMOUNT",$A$3)-L23 -> -38378.264
L28: ='Revenue Tracking'!F4 -> 5852178.3
L29: =L23 -> 5852178.3
L30: =L28-L29 -> 2.9038638e-05
K32: =K23+L30 -> 318352.03

Sheet Finance - COS
A3: Sum of Actual Total | B3: Column Labels
A4: Row Labels | B4: (blank) | D4: 45688 | E4: 45716 | F4: 45747 | G4: 45777 | H4: 45808 | I4: 45838 | J4: 45869 | K4: 45900 | L4: Grand Total
A5: Battery Systems
A6: BDP Commission | F6: 304347.83 | L6: 304347.83
A7: (blank)
A8: 1. Panels | F8: 1205076.9 | K8: 3473.99 | L8: 1208550.9
A9: 2. Inverters | F9: 344350 | L9: 344350
A10: 3. Mounting Structures | F10: 88775.72 | J10: 4706.1 | L10: 93481.82
A11: 4. DC Equipment | F11: 434312.78 | G11: 67301.85 | I11: 151429.17 | K11: 18155.463 | L11: 671199.26
A12: 5. Monitoring | F12: 33421.96 | L12: 33421.96
A13: 6. AC Equipment | F13: 107178.3 | G13: 71452.2 | I13: 160767.45 | J13: 58447.5 | K13: -6893.95 | L13: 390951.5
A14: 8. Product Add On | G14: 61258 | H14: 89800 | I14: -13043.48 | L14: 138014.52
A15: 9. AC & DC installation | F15: 180000 | G15: 120000 | I15: 270000 | K15: 30000 | L15: 600000
A16: 10. Site Logistics | D16: 9400 | F16: 15667.1 | G16: 13461.4 | I16: 36125.65 | K16: 2802.85 | L16: 77457
A17: 11. Due Dilligence | D17: 7500 | G17: 65700 | I17: 15750 | J17: 8000 | K17: 5100 | L17: 102050
A18: 13. Engineering | J18: 72672.5 | L18: 72672.5
A19: 14. General Expenses | D19: 602.58 | E19: 514.98 | F19: 2896.82 | G19: 639.27 | H19: 421.74 | I19: 704.96 | J19: 606.42 | L19: 6386.77
A20: 15. Service Add On | K20: 3250 | L20: 3250
A21: Grand Total | D21: 17502.58 | E21: 514.98 | F21: 2716027.4 | G21: 399812.72 | H21: 90221.74 | I21: 621733.75 | J21: 144432.52 | K21: 55888.353 | L21: 4046134

Sheet Certificate - Financial Close
B2: Emergent Energy – Financial Close Completion Certificate | H2: FINANCIAL CLOSE CERTIFICATE
B4: Project Name: | C4: ='Project Plan'!E2 -> Ridgeview Mall
B5: COO: | C5: Johannes Potgieter
B6: Programme Manager: | C6: Roedolph Venter
B7: HoPD: | C7: Natasha Watkins-Baker
B9: Date of Phase Completion: | F9: {=_xlfn.LET(_xlpm.w,$B$10:$B$54,_xlpm.r,$M$10:$M$54,_xlpm.v,IF(ISNUMBER(_xlpm.r),_xlpm.r,IFERROR(VALUE(SUBSTITUTE(_xlpm.r,"%",""))/100,0)),_xlpm.g,IFERROR(VALUE(LEFT(_xlpm.w,1)),0),_xlpm.bdOnly,(SUMPRODUCT((_xlpm.w="1.1")*(_xlpm.v>0))>0)*(SUMPRODUCT((_xlpm.w<>"1.1")*(_xlpm.v>0))=0),_xlpm.anyConstr,SUMPRODUCT((_xlpm.g>=2)*(_xlpm.g<=6)*(_xlpm.v>0))>0,_xlpm.anyQA,SUMPRODUCT((_xlpm.g=7)*(_xlpm.v>0))>0,_xlpm.anyHO,SUMPRODUCT((_xlpm.g=8)*(_xlpm.v>0))>0,_xlpm.anyPlan,SUMPRODUCT((_xlpm.g=1)*(_xlpm.v>0))>0,IF(_xlpm.bdOnly,"1. Financial Close",IF(_xlpm.anyConstr,"3. Construction",IF(_xlpm.anyQA,"4. QA",IF(_xlpm.anyHO,"5. Handover",IF(_xlpm.anyPlan,"2. Planning","1. Financial Close"))))))} -> 1. Financial Close | G9: {=_xlfn.LET(_xlpm.w,$B$10:$B$54,_xlpm.r,$N$10:$N$54,_xlpm.v,IF(ISNUMBER(_xlpm.r),_xlpm.r,IFERROR(VALUE(SUBSTITUTE(_xlpm.r,"%",""))/100,0)),_xlpm.g,IFERROR(VALUE(LEFT(_xlpm.w,1)),0),_xlpm.bdOnly,(SUMPRODUCT((_xlpm.w="1.1")*(_xlpm.v>0))>0)*(SUMPRODUCT((_xlpm.w<>"1.1")*(_xlpm.v>0))=0),_xlpm.anyConstr,SUMPRODUCT((_xlpm.g>=2)*(_xlpm.g<=6)*(_xlpm.v>0))>0,_xlpm.anyQA,SUMPRODUCT((_xlpm.g=7)*(_xlpm.v>0))>0,_xlpm.anyHO,SUMPRODUCT((_xlpm.g=8)*(_xlpm.v>0))>0,_xlpm.anyPlan,SUMPRODUCT((_xlpm.g=1)*(_xlpm.v>0))>0,IF(_xlpm.bdOnly,"1. Financial Close",IF(_xlpm.anyConstr,"3. Construction",IF(_xlpm.anyQA,"4. QA",IF(_xlpm.anyHO,"5. Handover",IF(_xlpm.anyPlan,"2. Planning","1. Financial Close"))))))} -> 1. Financial Close
B10: Phase Deliverables Checklist: (Y/N)
B11: Product Agreement | C11: NA
B12: EPC Agreement | C12: NA
B13: O&M Agreeement | C13: NA
B14: Cost Proposal | C14: Signed
B15: Deposit Received | C15: Yes
B16: Risks / Notes | C16: None
B18: Acknowledgement and Acceptance:
B19: Role | C19: Name | D19: Signature | E19: Date
B20: COO | C20: Johannes | D20: JTP | E20: 45953

Sheet Project Margins
A1: [capture project margins from costing sheet]
A3: Products | D3: 0.32
A4: Services | D4: 0.5
A5: Expenses | D5: 0.15
A6: Subcontractors | D6: 0.2

Sheet Equipment Quotes
B2: Equipment Quote and Budget comparision
B4: Description | D4: Budget | F4: Supplier 1 | H4: Variance | J4: Supplier 2 | L4: Variance | N4: Comments / Notes
F7: >Name< | J7: >Name<
B9: Inverters | D9: =SUM(D10:D11) -> 350000 | F9: =SUM(F10:F13) -> 0 | H9: =$D$9-F9 -> 350000 | J9: =SUM(J10:J13) -> 0 | L9: =$D$9-J9 -> 350000
B10: Inverters | D10: ='Expenditure Breakdown'!G13 -> 350000
B11: Optimizers | D11: ='Expenditure Breakdown'!G14 -> 0
B12: Warranty
B13: Delivery fee
F15: >Name< | J15: >Name<
B17: Mounting Structure | D17: =SUM(D18:D19) -> 270229.5 | F17: =SUM(F18:F20) -> 0 | H17: =$D$17- F17 -> 270229.5 | J17: =SUM(J18:J20) -> 0 | L17: =$D$17- J17 -> 270229.5
B18: Mounting Structure | D18: ='Expenditure Breakdown'!G19 -> 270229.5
B19: Delivery fee
F21: >Name< | J21: >Name<
B23: DC Cable | D23: =SUM(D24:D25) -> 209832 | F23: =SUM(F24:F25) -> 0 | H23: =$D$23- F23 -> 209832 | J23: =SUM(J24:J25) -> 0 | L23: =$D$23- J23 -> 209832
B24: DC Cable | D24: ='Expenditure Breakdown'!G28 -> 209832
B25: Delivery fee
F27: >Name< | J27: >Name<
B29: Monitoring system | D29: =SUM(D30:D32) -> #REF! | F29: =SUM(F30:F42) -> 0 | H29: =$D$29-F29 -> #REF! | J29: =SUM(J30:J32) -> 0 | L29: =$D$29-J29 -> #REF!
B30: ='Expenditure Breakdown'!D41 -> Smartlogger 3000 | D30: ='Expenditure Breakdown'!G41 -> 26000
B31: ='Expenditure Breakdown'!#REF! -> #REF! | D31: ='Expenditure Breakdown'!#REF! -> #REF!
B32: Delivery fee
F34: >Name< | J34: >Name<
B36: Additional Scope | D36: =SUM(D37:D41) -> 0 | F36: =SUM(F37:F41) -> 0 | H36: =$D$29-F36 -> #REF! | J36: =SUM(J37:J41) -> 0 | L36: =$D$29-J36 -> #REF!
B37: SCADA | D37: ='Expenditure Breakdown'!G67 -> 0
B38: Inverter cage
B39: Cat ladders
B40: Gen Integration
B41: Lifelines
B43: Totals | D43: =D36+D29+D23+D17+D9 -> #REF! | H43: =SUM(H7:H42) -> #REF! | L43: =SUM(L7:L42) -> #REF!
B47: All amounts are incl VAT

Sheet Installer Quotes
B2: Installer Quote and Budget comparision
B4: Description | D4: Budget | G4: Cosmic Sun | J4: Variance | L4: Matthews Group | O4: Variance
B6: AC Equipment | D6: ='Expenditure Breakdown'!AA8 -> 842399.37 | E6: =D6/(1000*'Project Plan'!$E$3) -> 1.4039989 | G6: 277892.91 | H6: =G6/('Project Plan'!$E$3*1000) -> 0.46315485 | J6: =D6-G6 -> 564506.46 | M6: =L6/('Project Plan'!$E$3*1000) -> 0 | O6: =D6-L6 -> 842399.37
B7: DC Equipment | D7: ='Expenditure Breakdown'!AA9 -> 338269.2 | E7: =D7/(1000*'Project Plan'!$E$3) -> 0.563782 | G7: 142158.25 | H7: =G7/('Project Plan'!$E$3*1000) -> 0.23693042 | J7: =D7-G7 -> 196110.95 | M7: =L7/('Project Plan'!$E$3*1000) -> 0 | O7: =D7-L7 -> 338269.2
B8: AC Labour | D8: ='Expenditure Breakdown'!AA10 -> 150127.5 | E8: =D8/(1000*'Project Plan'!$E$3) -> 0.2502125 | G8: 96174 | H8: =G8/('Project Plan'!$E$3*1000) -> 0.16029 | J8: =D8-G8 -> 53953.5 | M8: =L8/('Project Plan'!$E$3*1000) -> 0 | O8: =D8-L8 -> 150127.5
B9: DC Labour | D9: ='Expenditure Breakdown'!AA11 -> 359765 | E9: =D9/(1000*'Project Plan'!$E$3) -> 0.59960833 | G9: 230160 | H9: =G9/('Project Plan'!$E$3*1000) -> 0.3836 | J9: =D9-G9 -> 129605 | M9: =L9/('Project Plan'!$E$3*1000) -> 0 | O9: =D9-L9 -> 359765
B10: Offloading | D10: ='Expenditure Breakdown'!AA12 -> 8500 | G10: 0 | J10: =D10-G10 -> 8500 | O10: =D10-L10 -> 8500
B11: Roof Access/Scaffolding | D11: ='Expenditure Breakdown'!AA13 -> 54199.5 | G11: 29257.61 | J11: =D11-G11 -> 24941.89 | O11: =D11-L11 -> 54199.5
B12: Storage | D12: ='Expenditure Breakdown'!AA14 -> 7400 | J12: =D12-G12 -> 7400 | O12: =D12-L12 -> 7400
B13: Telehandler | D13: ='Expenditure Breakdown'!AA15 -> 0
B14: HSE | D14: 0
B15: Totals | D15: =SUM(D6:D13) -> 1760660.6 | G15: =SUM(G6:G13) -> 775642.77 | J15: =SUM(J6:J14) -> 985017.8 | L15: =SUM(L6:L13) -> 0 | O15: =SUM(O6:O14) -> 1760660.6
B18: Description | D18: Budget | G18: >Installer Name 3< | J18: Variance | L18: >Installer Name 4< | O18: Variance
B20: AC installation | D20: ='Expenditure Breakdown'!#REF! -> #REF! | E20: =D20/(1000*'Project Plan'!$E$3) -> #REF! | H20: =G20/(1000*'Project Plan'!$E$3) -> 0 | J20: =D20-G20 -> #REF! | M20: =L20/(1000*'Project Plan'!$E$3) -> 0 | O20: =D6-L20 -> 842399.37
B21: AC equipment | D21: ='Expenditure Breakdown'!C56 -> 0 | E21: =D21/(1000*'Project Plan'!$E$3) -> 0 | J21: =D21-G21 -> 0 | M21: =L21/(1000*'Project Plan'!$E$3) -> 0 | O21: =D7-L21 -> 338269.2
B22: DC installation | D22: ='Expenditure Breakdown'!#REF! -> #REF! | E22: =D22/(1000*'Project Plan'!$E$3) -> #REF! | H22: =G22/(1000*'Project Plan'!$E$3) -> 0 | J22: =D22-G22 -> #REF! | M22: =L22/(1000*'Project Plan'!$E$3) -> 0 | O22: =D8-L22 -> 150127.5
B23: DC equipment | D23: =SUM('Expenditure Breakdown'!G37:G38) -> 33826.92 | E23: =D23/(1000*'Project Plan'!$E$3) -> 0.0563782 | J23: =D23-G23 -> 33826.92 | O23: =D9-L23 -> 359765
B24: Storage | D24: ='Expenditure Breakdown'!G104 -> 7000 | J24: =D24-G24 -> 7000 | O24: =D10-L24 -> 8500
B25: Panel lifting equipment | D25: =SUM('Expenditure Breakdown'!G84:G96) -> 214099.5 | J25: =D25-G25 -> 214099.5 | O25: =D11-L25 -> 54199.5
B26: Offloading | D26: ='Expenditure Breakdown'!G98 -> 0 | J26: =D26-G26 -> 0 | O26: =D12-L26 -> 7400
B29: Totals | D29: =SUM(D20:D27) -> #REF! | G29: =SUM(G20:G27) -> 0 | J29: =SUM(J20:J28) -> #REF! | L29: =SUM(L20:L27) -> 0 | O29: =SUM(O20:O28) -> 1760660.6
B32: Budget Summary
B34: Budget | D34: =D15 -> 1760660.6
B35: =G4 -> Cosmic Sun | D35: =G15 -> 775642.77
B36: =L4 -> Matthews Group | D36: =L15 -> 0
B37: =G18 -> >Installer Name 3< | D37: =G29 -> 0
B38: =L18 -> >Installer Name 4< | D38: =L29 -> 0
B40: =IF(D40<D34,"Saving","Loss") -> Loss | D40: =D34-MIN(D35:D38) -> 1760660.6
B42: All amounts are exc VAT

Sheet Decision Register
B1: =D15 -> Ridgeview Mall | E1: Decision Register
B3: ID | C3: Decision Description | D3: Decision Impact | E3: Proposed Date | F3: Proposed By | G3: Status | H3: Approved By | I3: Date | J3: Results / Comments
B4: DEC001
B5: DEC002
B6: DEC003
B7: DEC004
B8: DEC005
B9: DEC006
B10: DEC007
B11: DEC008
B12: DEC009
B13: DEC010
D15: {='Project Plan'!E2:H2} -> Ridgeview Mall | E15: 0 | F15: 0 | G15: 0
