Workbook
Name Inverter_Capacity: #REF!
Name Inverter_Supplier: #REF!
Name Project_Size: 'Finance - Revenue'!Projectsize
Name Project_Size: Projectsize
Name Projectsize: #REF!
Name Projectsize: #REF!
Name Security_Serv: #REF!
Name Security_Serv: #REF!
Name SSS: #REF!
Name SSS: #REF!
Name USD_ZAR: #REF!

Sheet Certificate - Financial Close
B2: Emergent Energy – Financial Close Completion Certificate | H2: FINANCIAL CLOSE CERTIFICATE
B4: Project Name: | C4: ='Project Plan'!E2 -> Standard Bank GQ
B5: COO: | C5: Johannes Potgieter
B6: Programme Manager: | C6: Roedolph Venter
B7: HoPD: | C7: Natasha Watkins-Baker
B9: Date of Phase Completion:
B10: Phase Deliverables Checklist: (Y/N)
B11: Product Agreement
B12: EPC Agreement
B13: O&M Agreeement
B14: Cost Proposal
B15: Deposit Received
B16: Risks / Notes
B18: Acknowledgement and Acceptance:
B19: Role | C19: Name | D19: Signature | E19: Date

Sheet Certificate - Planning
B2: Emergent Energy – Planning Phase Completion Certificate | H2: PLANNING CERTIFICATE
B4: Project Name: | C4: ='Project Plan'!E2 -> Standard Bank GQ
B5: Client Representative:
B6: Programme Manager: | C6: Roedolph Venter
B7: Project Manager: | C7: ='Project Plan'!E5 -> Lloyd Brown
B8: Project Engineer:
B10: Date of Phase Completion:
B11: Phase Deliverables Checklist: (Y/N)
B12: Project Introduction Presentation
B13: Project Brief
B14: Engineering Pack
B15: BOQ
B16: PO – Material & Equipment
B17: PO - Contractors
B18: HSE – NOC
B19: HSE – EE File
B20: HSE – Contractor File
... B24: Acknowledgement and Acceptance:
B25: Role | C25: Name | D25: Signature | E25: Date

Sheet Change Register
F1: Change Register
B3: ID | C3: Description | D3: Supporting Image (If Applicable) | E3: Impact | F3: Proposed Date | G3: Proposed By | H3: Status | I3: Approved By | J3: Date | K3: Results / Comments
B4: DEC001
B5: DEC002
B6: DEC003
B7: DEC004
B8: DEC005
B9: DEC006
B10: DEC007
B11: DEC008
B12: DEC009
B13: DEC010
B14: DEC011
B15: DEC012
... B33: DEC030

Sheet BOQ
B2: Item | C2: Supplier | D2: Description | E2: Quantity | F2: Comments
B3: PV Module
B4: Mounting Structure
B5: DC Cable Red & Black
B6: Inverters
B7: Current Transformers (Production)
B8: Current Transformers (Consumption)
B9: Solar Production Meter (Techistter)
B10: Grid Consumption Meter
B11: Wi-Fi Router & Sim
B12: Switch
B13: Back Up Battery
B14: PVDB
... B30: Techsitter

Sheet Compliance
B2: HSE
B4: Description | C4: Status | D4: Approved By | E4: Date | F4: Results / Comments
B5: NOC
B6: 7.1 Agreement
B7: 13.2 Agreement
B8: EE File
B9: Subbie File
B16: SSEG
B18: Description | C18: Status | D18: Approved By | E18: Date | F18: Results / Comments
B19: SSEG Application | C19: Abanded | E19: 45946 | F19: Client opted to complete themselves
B20: PTI | C20: Abanded | E20: 45946 | F20: Client opted to complete themselves
B21: Commissioning Approval | C21: Abanded | E21: 45946 | F21: Client opted to complete themselves
B22: NERSA Regsitration | C22: Abanded | E22: 45946 | F22: Client opted to complete themselves
B23: Network/Grid Imapct Study | C23: Abanded | E23: 45946 | F23: Client opted to complete themselves

Sheet Project Plan
N1: =TODAY() -> 46076 | O1: =TODAY() -> 46076
C2: PROJECT PLAN | E2: Standard Bank GQ | I2: Net Work Days | K2: =NETWORKDAYS(I20,K55,Data!C3:C60) -> 44 | N2: 0 | O2: 1
C3: PROJECT SIZE (kWp) | E3: 460 | I3: Total Weeks | K3: =K2/5 -> 8.8
C4: PROJECT DEVELOPER | E4: Gordon Upton | I4: kW/Week Installation Rate | K4: =E3/K3 -> 52.272727
C5: PROJECT MANAGERS | E5: Lloyd Brown
C6: CONTRACT VALUE | E6: =1891415.11 -> 1891415.1
C7: Phase: | E7: Commercial Close Out
B8: No. | C8: HIGH LEVEL PROGRAMME | E8: Planned Start | F8: Duration | G8: Planned End | I8: Actual Start | J8: Duration | K8: Actual End | M8: Status | N8: Expected Status | O8: Comment
F9: =G57-E21 -> #NUM! | J9: =K57-I21 -> 54 | M9: =AVERAGE(M11,M20,M23,M30,M49,M55,M66,M61) -> 0.96428571 | N9: =AVERAGE(N11,N20,N23,N30,N49,N55,N66,N61) -> 0.97916327
B11: 1 | C11: Project Initiation | E11: =MIN(E12:E19) -> 45909 | F11: =G11-E11 -> 37 | G11: =MAX(G12:G19) -> 45946 | I11: =MIN(I12:I19) -> 45909 | J11: =K11-I11 -> 52 | K11: =MAX(K12:K19) -> 45961 | M11: 1 | N11: 1
B12: 1.1 | C12: BD Handover | E12: 45909 | F12: 1 | G12: =WORKDAY.INTL(E12,F12,1,Data!$C$3:$C$60) -> 45910 | I12: 45909 | J12: 1 | K12: =WORKDAY.INTL(I12,J12,1,Data!$C$3:$C$60) -> 45910 | M12: 1 | N12: =_xlfn.LET( _xlpm.s,VALUE($I12), _xlpm.e,VALUE($K12), IF(OR(_xlpm.s="",_xlpm.e=""),"", IF(_xlpm.e<=_xlpm.s, IF(TODAY()>=_xlpm.e,1,0), MAX(0,MIN(1,(TODAY()-_xlpm.s)/(_xlpm.e-_xlpm.s))))) ) -> 1
B13: 1.2 | C13: HSE Readiness and Signoff | E13: =WORKDAY.INTL(G12,0,1,Data!$C$3:$C$60) -> 45910 | F13: 25 | G13: =WORKDAY.INTL(E13,F13,1,Data!$C$3:$C$60) -> 45946 | I13: =WORKDAY.INTL(K12,0,1,Data!$C$3:$C$60) -> 45910 | J13: 26 | K13: =WORKDAY.INTL(I13,J13,1,Data!$C$3:$C$60) -> 45947 | M13: 1 | N13: =_xlfn.LET( _xlpm.s,VALUE($I13), _xlpm.e,VALUE($K13), IF(OR(_xlpm.s="",_xlpm.e=""),"", IF(_xlpm.e<=_xlpm.s, IF(TODAY()>=_xlpm.e,1,0), MAX(0,MIN(1,(TODAY()-_xlpm.s)/(_xlpm.e-_xlpm.s))))) ) -> 1
B14: 1.3 | C14: Safety Line Installation | I14: 45943 | J14: 14 | K14: =WORKDAY.INTL(I14,J14,1,Data!$C$3:$C$60) -> 45961 | M14: 1 | N14: =_xlfn.LET( _xlpm.s,VALUE($I14), _xlpm.e,VALUE($K14), IF(OR(_xlpm.s="",_xlpm.e=""),"", IF(_xlpm.e<=_xlpm.s, IF(TODAY()>=_xlpm.e,1,0), MAX(0,MIN(1,(TODAY()-_xlpm.s)/(_xlpm.e-_xlpm.s))))) ) -> 1
B15: 1.4 | C15: Technical Signoff | I15: =WORKDAY.INTL(K13,0,1,Data!$C$3:$C$60)-2 -> 45945 | J15: 2 | K15: =WORKDAY.INTL(I15,J15,1,Data!$C$3:$C$60) -> 45947 | M15: 1 | N15: =_xlfn.LET( _xlpm.s,VALUE($I15), _xlpm.e,VALUE($K15), IF(OR(_xlpm.s="",_xlpm.e=""),"", IF(_xlpm.e<=_xlpm.s, IF(TODAY()>=_xlpm.e,1,0), MAX(0,MIN(1,(TODAY()-_xlpm.s)/(_xlpm.e-_xlpm.s))))) ) -> 1
B16: 1.5 | C16: Project Introduction | E16: =WORKDAY.INTL(G12,0,1,Data!$C$3:$C$60)+14 -> 45924 | F16: 1 | G16: =WORKDAY.INTL(E16,F16,1,Data!$C$3:$C$60) -> 45925 | I16: =WORKDAY.INTL(K12,0,1,Data!$C$3:$C$60)+14 -> 45924 | J16: 1 | K16: =WORKDAY.INTL(I16,J16,1,Data!$C$3:$C$60) -> 45925 | M16: 1 | N16: =_xlfn.LET( _xlpm.s,VALUE($I16), _xlpm.e,VALUE($K16), IF(OR(_xlpm.s="",_xlpm.e=""),"", IF(_xlpm.e<=_xlpm.s, IF(TODAY()>=_xlpm.e,1,0), MAX(0,MIN(1,(TODAY()-_xlpm.s)/(_xlpm.e-_xlpm.s))))) ) -> 1
B17: 1.6 | C17: Installer Kick Off | E17: =WORKDAY.INTL(E16,0,1,Data!$C$3:$C$60)+7 -> 45931 | F17: 1 | G17: =WORKDAY.INTL(E17,F17,1,Data!$C$3:$C$60) -> 45932 | I17: =WORKDAY.INTL(I16,0,1,Data!$C$3:$C$60)+7 -> 45931 | J17: 1 | K17: =WORKDAY.INTL(I17,J17,1,Data!$C$3:$C$60) -> 45932 | M17: 1 | N17: =_xlfn.LET( _xlpm.s,VALUE($I17), _xlpm.e,VALUE($K17), IF(OR(_xlpm.s="",_xlpm.e=""),"", IF(_xlpm.e<=_xlpm.s, IF(TODAY()>=_xlpm.e,1,0), MAX(0,MIN(1,(TODAY()-_xlpm.s)/(_xlpm.e-_xlpm.s))))) ) -> 1
B18: 1.7 | C18: Project Review | E18: =WORKDAY.INTL(E17,0,1,Data!$C$3:$C$60)+10 -> 45941 | F18: 1 | G18: =WORKDAY.INTL(E18,F18,1,Data!$C$3:$C$60) -> 45943 | I18: =WORKDAY.INTL(I17,0,1,Data!$C$3:$C$60)+10 -> 45941 | J18: 1 | K18: =WORKDAY.INTL(I18,J18,1,Data!$C$3:$C$60) -> 45943 | M18: 1 | N18: =_xlfn.LET( _xlpm.s,VALUE($I18), _xlpm.e,VALUE($K18), IF(OR(_xlpm.s="",_xlpm.e=""),"", IF(_xlpm.e<=_xlpm.s, IF(TODAY()>=_xlpm.e,1,0), MAX(0,MIN(1,(TODAY()-_xlpm.s)/(_xlpm.e-_xlpm.s))))) ) -> 1
B20: 2 | C20: Site Establishment | E20: =MIN(E21:E22) -> 45947 | F20: =G20-E20 -> 1 | G20: =MAX(G21:G22) -> 45948 | I20: =MIN(I21:I22) -> 45950 | J20: =K20-I20 -> 1 | K20: =MAX(K21:K22) -> 45951 | M20: =(J21*M21)/J20 -> 1 | N20: =(K21*N21)/K20 -> 1
B21: 2.1 | C21: Solar Contractor Establishment | E21: 45947 | F21: 1 | G21: =E21+F21 -> 45948 | I21: 45950 | J21: 1 | K21: =I21+J21 -> 45951 | M21: 1 | N21: =_xlfn.LET( _xlpm.s,VALUE($I21), _xlpm.e,VALUE($K21), IF(OR(_xlpm.s="",_xlpm.e=""),"", IF(_xlpm.e<=_xlpm.s, IF(TODAY()>=_xlpm.e,1,0), MAX(0,MIN(1,(TODAY()-_xlpm.s)/(_xlpm.e-_xlpm.s))))) ) -> 1 | O21: Inspect all material prior to installation.
B23: 3 | C23: AC Installation | E23: =MIN(E24:E29) -> 45910 | F23: =G23-E23 -> 49 | G23: =MAX(G24:G29) -> 45959 | I23: =MIN(I24:I29) -> 45909 | J23: =K23-I23 -> 80 | K23: =MAX(K24:K29) -> 45989 | M23: =(J24*M24+J25*M25+J26*M26+J27*M27+J28*M28)/SUM(J24:J28) -> 1 | N23: =(J24*N24+J25*N25+J26*N26+J27*N27+J28*N28)/SUM(J24:J28) -> 1
B24: 3.1 | C24: Inverters delivered | E24: =WORKDAY.INTL(G21,0,1,Data!$C$3:$C$60) -> 45948 | F24: 1 | G24: =WORKDAY.INTL(E24,F24,1,Data!$C$3:$C$60) -> 45950 | I24: =WORKDAY.INTL(I26,0,1,Data!$C$3:$C$60) -> 45910 | J24: 0 | K24: =WORKDAY.INTL(I24,J24,1,Data!$C$3:$C$60) -> 45910 | M24: 1 | N24: =_xlfn.LET( _xlpm.s,VALUE($I24), _xlpm.e,VALUE($K24), IF(OR(_xlpm.s="",_xlpm.e=""),"", IF(_xlpm.e<=_xlpm.s, IF(TODAY()>=_xlpm.e,1,0), MAX(0,MIN(1,(TODAY()-_xlpm.s)/(_xlpm.e-_xlpm.s))))) ) -> 1
B25: 3.2 | C25: Inverters Mounted | E25: =WORKDAY.INTL(G24,0,1,Data!$C$3:$C$60) -> 45950 | F25: 2 | G25: =WORKDAY.INTL(E25,F25,1,Data!$C$3:$C$60) -> 45952 | I25: =WORKDAY.INTL(K24,0,1,Data!$C$3:$C$60) -> 45910 | J25: 0 | K25: =WORKDAY.INTL(I25,J25,1,Data!$C$3:$C$60) -> 45910 | M25: 1 | N25: =_xlfn.LET( _xlpm.s,VALUE($I25), _xlpm.e,VALUE($K25), IF(OR(_xlpm.s="",_xlpm.e=""),"", IF(_xlpm.e<=_xlpm.s, IF(TODAY()>=_xlpm.e,1,0), MAX(0,MIN(1,(TODAY()-_xlpm.s)/(_xlpm.e-_xlpm.s))))) ) -> 1
B26: 3.3 | C26: Solar DB Lead Time | E26: =WORKDAY.INTL(E16,0,1,Data!$C$3:$C$60)-14 -> 45910 | F26: 0 | G26: 45910 | I26: =WORKDAY.INTL(I16,0,1,Data!$C$3:$C$60)-14 -> 45910 | J26: 0 | K26: 45910 | M26: 1 | N26: =_xlfn.LET( _xlpm.s,VALUE($I26), _xlpm.e,VALUE($K26), IF(OR(_xlpm.s="",_xlpm.e=""),"", IF(_xlpm.e<=_xlpm.s, IF(TODAY()>=_xlpm.e,1,0), MAX(0,MIN(1,(TODAY()-_xlpm.s)/(_xlpm.e-_xlpm.s))))) ) -> 1
B27: 3.4 | C27: AC Works | E27: =WORKDAY.INTL(G25,0,1,Data!$C$3:$C$60) -> 45952 | F27: 5 | G27: =WORKDAY.INTL(E27,F27,1,Data!$C$3:$C$60) -> 45959 | I27: 45975 | J27: 10 | K27: =WORKDAY.INTL(I27,J27,1,Data!$C$3:$C$60) -> 45989 | M27: 1 | N27: =_xlfn.LET( _xlpm.s,VALUE($I27), _xlpm.e,VALUE($K27), IF(OR(_xlpm.s="",_xlpm.e=""),"", IF(_xlpm.e<=_xlpm.s, IF(TODAY()>=_xlpm.e,1,0), MAX(0,MIN(1,(TODAY()-_xlpm.s)/(_xlpm.e-_xlpm.s))))) ) -> 1
B28: 3.5 | C28: AC Tie-In | E28: =WORKDAY.INTL(E27,0,1,Data!$C$3:$C$60) -> 45952 | F28: 1 | G28: =WORKDAY.INTL(E28,F28,1,Data!$C$3:$C$60) -> 45953 | I28: =WORKDAY.INTL(I12,0,1,Data!$C$3:$C$60) -> 45909 | J28: 1 | K28: =WORKDAY.INTL(I28,J28,1,Data!$C$3:$C$60) -> 45910 | M28: 1 | N28: =_xlfn.LET( _xlpm.s,VALUE($I28), _xlpm.e,VALUE($K28), IF(OR(_xlpm.s="",_xlpm.e=""),"", IF(_xlpm.e<=_xlpm.s, IF(TODAY()>=_xlpm.e,1,0), MAX(0,MIN(1,(TODAY()-_xlpm.s)/(_xlpm.e-_xlpm.s))))) ) -> 1 | O28: Double check connections, link to 6.1.
B30: 4 | C30: DC Works | E30: =MIN(E32:E48) -> -3 | F30: =G30-E30 -> #NUM! | G30: =MAX(G32:G48) -> #NUM! | I30: =MIN(I32:I48) -> 45950 | J30: =K30-I30 -> 91 | K30: =MAX(K32:K48) -> 46041 | M30: 1 | N30: 1
B32: 4.1 | C32: Mounting Structure delivered | E32: =E21 -> 45947 | F32: 1 | G32: =WORKDAY.INTL(E32,F32,1,Data!$C$3:$C$60) -> 45950 | I32: =I21 -> 45950 | J32: 1 | K32: =WORKDAY.INTL(I32,J32,1,Data!$C$3:$C$60) -> 45951 | M32: 1 | N32: =_xlfn.LET( _xlpm.s,VALUE($I32), _xlpm.e,VALUE($K32), IF(OR(_xlpm.s="",_xlpm.e=""),"", IF(_xlpm.e<=_xlpm.s, IF(TODAY()>=_xlpm.e,1,0), MAX(0,MIN(1,(TODAY()-_xlpm.s)/(_xlpm.e-_xlpm.s))))) ) -> 1
B33: 4.2 | C33: Mounting Structure installation - Roof A | E33: =WORKDAY.INTL(G32,0,1,Data!$C$3:$C$60) -> 45950 | F33: 6 | G33: =WORKDAY.INTL(E33,F33,1,Data!$C$3:$C$60) -> 45958 | I33: 45950 | J33: 22 | K33: =WORKDAY.INTL(I33,J33,1,Data!$C$3:$C$60) -> 45980 | M33: 1 | N33: =_xlfn.LET( _xlpm.s,VALUE($I33), _xlpm.e,VALUE($K33), IF(OR(_xlpm.s="",_xlpm.e=""),"", IF(_xlpm.e<=_xlpm.s, IF(TODAY()>=_xlpm.e,1,0), MAX(0,MIN(1,(TODAY()-_xlpm.s)/(_xlpm.e-_xlpm.s))))) ) -> 1 | O33: 1:Noise Complaints(08:50-12:00 on/off) Stopped 3 times. Date: 04/11/2025
C34: Roof Hooks - Roof A | M34: 1 | N34: 1
B35: 4.2.2 | C35: Rails - Roof A | I35: 45971 | J35: 12 | K35: =WORKDAY.INTL(I35,J35,1,Data!$C$3:$C$60) -> 45987 | M35: 1 | N35: =_xlfn.LET( _xlpm.s,VALUE($I35), _xlpm.e,VALUE($K35), IF(OR(_xlpm.s="",_xlpm.e=""),"", IF(_xlpm.e<=_xlpm.s, IF(TODAY()>=_xlpm.e,1,0), MAX(0,MIN(1,(TODAY()-_xlpm.s)/(_xlpm.e-_xlpm.s))))) ) -> 1 | O35: Not allowed to work over far-north roof due to noise, will only happen over weekend Two rails to fit after hours
B36: 4.3 | C36: Mounting Structure installation - Roof B | I36: 45950 | J36: 19 | K36: =WORKDAY.INTL(I36,J36,1,Data!$C$3:$C$60) -> 45975 | M36: 1 | N36: =_xlfn.LET( _xlpm.s,VALUE($I36), _xlpm.e,VALUE($K36), IF(OR(_xlpm.s="",_xlpm.e=""),"", IF(_xlpm.e<=_xlpm.s, IF(TODAY()>=_xlpm.e,1,0), MAX(0,MIN(1,(TODAY()-_xlpm.s)/(_xlpm.e-_xlpm.s))))) ) -> 1
C37: Roof Hooks - Roof B | M37: 1 | N37: 1
B38: 4.3.2 | C38: Rails - Roof B | I38: 45972 | J38: 3 | K38: =WORKDAY.INTL(I38,J38,1,Data!$C$3:$C$60) -> 45975 | M38: 1 | N38: =_xlfn.LET( _xlpm.s,VALUE($I38), _xlpm.e,VALUE($K38), IF(OR(_xlpm.s="",_xlpm.e=""),"", IF(_xlpm.e<=_xlpm.s, IF(TODAY()>=_xlpm.e,1,0), MAX(0,MIN(1,(TODAY()-_xlpm.s)/(_xlpm.e-_xlpm.s))))) ) -> 1
B39: 4.4 | C39: Mounting Structure installation - Roof C | I39: 45957 | J39: 16 | K39: =WORKDAY.INTL(I39,J39,1,Data!$C$3:$C$60) -> 45979 | M39: =AVERAGE(M40:M41) -> 1 | N39: =_xlfn.LET( _xlpm.s,VALUE($I39), _xlpm.e,VALUE($K39), IF(OR(_xlpm.s="",_xlpm.e=""),"", IF(_xlpm.e<=_xlpm.s, IF(TODAY()>=_xlpm.e,1,0), MAX(0,MIN(1,(TODAY()-_xlpm.s)/(_xlpm.e-_xlpm.s))))) ) -> 1
B40: 4.4.1 | C40: Roof Hooks - Roof C | M40: 1 | N40: 1
B41: 4.4.2 | C41: Rails - Roof C | I41: 45974 | J41: 3 | K41: =WORKDAY.INTL(I41,J41,1,Data!$C$3:$C$60) -> 45979 | M41: 1 | N41: =_xlfn.LET( _xlpm.s,VALUE($I41), _xlpm.e,VALUE($K41), IF(OR(_xlpm.s="",_xlpm.e=""),"", IF(_xlpm.e<=_xlpm.s, IF(TODAY()>=_xlpm.e,1,0), MAX(0,MIN(1,(TODAY()-_xlpm.s)/(_xlpm.e-_xlpm.s))))) ) -> 1
B42: 4.5 | C42: Civil Works - Trenching | I42: 45982 | J42: 2 | K42: =I42+J42 -> 45984 | M42: 1 | N42: =_xlfn.LET( _xlpm.s,VALUE($I42), _xlpm.e,VALUE($K42), IF(OR(_xlpm.s="",_xlpm.e=""),"", IF(_xlpm.e<=_xlpm.s, IF(TODAY()>=_xlpm.e,1,0), MAX(0,MIN(1,(TODAY()-_xlpm.s)/(_xlpm.e-_xlpm.s))))) ) -> 1 | O42: Corden off parking for Saturday work
B43: 4.6 | C43: Civil Works - Scanning | I43: 45972 | J43: 4 | K43: =WORKDAY.INTL(I43,J43,1,Data!$C$3:$C$60) -> 45978 | M43: 1 | N43: =_xlfn.LET( _xlpm.s,VALUE($I43), _xlpm.e,VALUE($K43), IF(OR(_xlpm.s="",_xlpm.e=""),"", IF(_xlpm.e<=_xlpm.s, IF(TODAY()>=_xlpm.e,1,0), MAX(0,MIN(1,(TODAY()-_xlpm.s)/(_xlpm.e-_xlpm.s))))) ) -> 1 | O43: Marking out of route completed
B44: 4.7 | C44: DC Cable delivered | E44: =E32 -> 45947 | F44: 1 | G44: =WORKDAY.INTL(E44,F44,1,Data!$C$3:$C$60) -> 45950 | I44: 45950 | J44: 1 | K44: =WORKDAY.INTL(I44,J44,1,Data!$C$3:$C$60) -> 45951 | M44: 1 | N44: =_xlfn.LET( _xlpm.s,VALUE($I44), _xlpm.e,VALUE($K44), IF(OR(_xlpm.s="",_xlpm.e=""),"", IF(_xlpm.e<=_xlpm.s, IF(TODAY()>=_xlpm.e,1,0), MAX(0,MIN(1,(TODAY()-_xlpm.s)/(_xlpm.e-_xlpm.s))))) ) -> 1 | O44: Need to measure for additional material
B45: 4.7 | C45: DC Stringing - Roof A | E45: =WORKDAY.INTL(G51,0,1,Data!$C$3:$C$60)-3 -> 45968 | F45: 10 | G45: =WORKDAY.INTL(E45,F45,1,Data!$C$3:$C$60) -> 45982 | I45: 45980 | J45: 14 | K45: =WORKDAY.INTL(I45,J45,1,Data!$C$3:$C$60) -> 46000 | M45: 1 | N45: =_xlfn.LET( _xlpm.s,VALUE($I45), _xlpm.e,VALUE($K45), IF(OR(_xlpm.s="",_xlpm.e=""),"", IF(_xlpm.e<=_xlpm.s, IF(TODAY()>=_xlpm.e,1,0), MAX(0,MIN(1,(TODAY()-_xlpm.s)/(_xlpm.e-_xlpm.s))))) ) -> 1 | O45: Work to start over weekend, requires empty basement
B46: 4.8 | C46: DC Stringing - Roof B | E46: =WORKDAY.INTL(G52,0,1,Data!$C$3:$C$60)-3 -> -3 | F46: 10 | G46: =WORKDAY.INTL(E46,F46,1,Data!$C$3:$C$60) -> #NUM! | I46: 45982 | J46: 12 | K46: =WORKDAY.INTL(I46,J46,1,Data!$C$3:$C$60) -> 46000 | M46: 1 | N46: =_xlfn.LET( _xlpm.s,VALUE($I46), _xlpm.e,VALUE($K46), IF(OR(_xlpm.s="",_xlpm.e=""),"", IF(_xlpm.e<=_xlpm.s, IF(TODAY()>=_xlpm.e,1,0), MAX(0,MIN(1,(TODAY()-_xlpm.s)/(_xlpm.e-_xlpm.s))))) ) -> 1
B47: 4.9 | C47: DC Stringing - Roof C | E47: =WORKDAY.INTL(G53,0,1,Data!$C$3:$C$60)-3 -> -3 | F47: 10 | G47: =WORKDAY.INTL(E47,F47,1,Data!$C$3:$C$60) -> #NUM! | I47: =K46-4 -> 45996 | J47: 6 | K47: =WORKDAY.INTL(I47,J47,1,Data!$C$3:$C$60) -> 46041 | M47: 1 | N47: 1
B49: 5 | C49: Module installation | E49: =MIN(E50:E54) -> 45947 | F49: =G49-E49 -> 24 | G49: =MAX(G50:G54) -> 45971 | I49: =MIN(I50:I54) -> 45950 | J49: =K49-I49 -> 53 | K49: =MAX(K50:K54) -> 46003 | M49: =(J50*M50+J51*M51)/SUM(J50:J51) -> 1 | N49: =(J50*N50+J51*N51)/SUM(J50:J51) -> 1
B50: 5.1 | C50: Module delivery | E50: =WORKDAY.INTL(E21,0,1,Data!$C$3:$C$60) -> 45947 | F50: 1 | G50: =WORKDAY.INTL(E50,F50,1,Data!$C$3:$C$60) -> 45950 | I50: =WORKDAY.INTL(I21,0,1,Data!$C$3:$C$60) -> 45950 | J50: 1 | K50: =WORKDAY.INTL(I50,J50,1,Data!$C$3:$C$60) -> 45951 | M50: 1 | N50: =_xlfn.LET( _xlpm.s,VALUE($I50), _xlpm.e,VALUE($K50), IF(OR(_xlpm.s="",_xlpm.e=""),"", IF(_xlpm.e<=_xlpm.s, IF(TODAY()>=_xlpm.e,1,0), MAX(0,MIN(1,(TODAY()-_xlpm.s)/(_xlpm.e-_xlpm.s))))) ) -> 1
B51: 5.2 | C51: Module mounting - Roof A | E51: =G33 -> 45958 | F51: 9 | G51: =WORKDAY.INTL(E51,F51,1,Data!$C$3:$C$60) -> 45971 | I51: 45980 | J51: 12 | K51: =WORKDAY.INTL(I51,J51,1,Data!$C$3:$C$60) -> 45996 | M51: 1 | N51: =_xlfn.LET( _xlpm.s,VALUE($I51), _xlpm.e,VALUE($K51), IF(OR(_xlpm.s="",_xlpm.e=""),"", IF(_xlpm.e<=_xlpm.s, IF(TODAY()>=_xlpm.e,1,0), MAX(0,MIN(1,(TODAY()-_xlpm.s)/(_xlpm.e-_xlpm.s))))) ) -> 1
B52: 5.3 | C52: Module mounting - Roof B | I52: 45980 | J52: 5 | K52: =WORKDAY.INTL(I52,J52,1,Data!$C$3:$C$60) -> 45987 | M52: 1 | N52: =_xlfn.LET( _xlpm.s,VALUE($I52), _xlpm.e,VALUE($K52), IF(OR(_xlpm.s="",_xlpm.e=""),"", IF(_xlpm.e<=_xlpm.s, IF(TODAY()>=_xlpm.e,1,0), MAX(0,MIN(1,(TODAY()-_xlpm.s)/(_xlpm.e-_xlpm.s))))) ) -> 1
B53: 5.4 | C53: Module mounting - Roof C | I53: 45983 | J53: 15 | K53: =WORKDAY.INTL(I53,J53,1,Data!$C$3:$C$60) -> 46003 | M53: 1 | N53: =_xlfn.LET( _xlpm.s,VALUE($I53), _xlpm.e,VALUE($K53), IF(OR(_xlpm.s="",_xlpm.e=""),"", IF(_xlpm.e<=_xlpm.s, IF(TODAY()>=_xlpm.e,1,0), MAX(0,MIN(1,(TODAY()-_xlpm.s)/(_xlpm.e-_xlpm.s))))) ) -> 1
B55: 6 | C55: Commissioning | E55: =MIN(E56:E60) -> #NUM! | F55: =G55-E55 -> #NUM! | G55: =MAX(G56:G60) -> #NUM! | I55: =MIN(I56:I60) -> 45989 | J55: =K55-I55 -> 55 | K55: =MAX(K56:K58) -> 46044 | M55: =(J56*M56+J57*M57+J58*M58)/SUM(J56:J58) -> 1 | N55: =(K56*N56+K57*N57)/SUM(K56:K57) -> 1
B56: 6.1 | C56: Pre Commissioning | E56: =WORKDAY.INTL(MAX(G23,G30,G49),0,1,Data!$C$3:$C$60) -> #NUM! | F56: 1 | G56: =WORKDAY.INTL(E56,F56,1,Data!$C$3:$C$60) -> #NUM! | I56: =WORKDAY.INTL(MAX(K23),0,1,Data!$C$3:$C$60) -> 45989 | J56: 1 | K56: =WORKDAY.INTL(I56,J56,1,Data!$C$3:$C$60) -> 45992 | M56: 1 | N56: =_xlfn.LET( _xlpm.s,VALUE($I56), _xlpm.e,VALUE($K56), IF(OR(_xlpm.s="",_xlpm.e=""),"", IF(_xlpm.e<=_xlpm.s, IF(TODAY()>=_xlpm.e,1,0), MAX(0,MIN(1,(TODAY()-_xlpm.s)/(_xlpm.e-_xlpm.s))))) ) -> 1
B57: 6.2 | C57: Practical Completion - Energy Flowing | E57: =WORKDAY.INTL(G56,0,1,Data!$C$3:$C$60) -> #NUM! | F57: 1 | G57: =WORKDAY.INTL(E57,F57,1,Data!$C$3:$C$60) -> #NUM! | I57: 45999 | J57: 5 | K57: =I57+J57 -> 46004 | M57: 1 | N57: =_xlfn.LET( _xlpm.s,VALUE($I57), _xlpm.e,VALUE($K57), IF(OR(_xlpm.s="",_xlpm.e=""),"", IF(_xlpm.e<=_xlpm.s, IF(TODAY()>=_xlpm.e,1,0), MAX(0,MIN(1,(TODAY()-_xlpm.s)/(_xlpm.e-_xlpm.s))))) ) -> 1
B58: 6.3 | C58: System Performance Monitoring | E58: =WORKDAY.INTL(G57,0,1,Data!$C$3:$C$60) -> #NUM! | F58: 5 | G58: =WORKDAY.INTL(E58,F58,1,Data!$C$3:$C$60) -> #NUM! | I58: =K57 -> 46004 | J58: 4 | K58: =WORKDAY.INTL(I58,J58,1,Data!$C$3:$C$60) -> 46044 | M58: 1 | N58: 1
B59: 6.4 | C59: Lightning Protection Installation | E59: =WORKDAY.INTL(G58,0,1,Data!$C$3:$C$60) -> #NUM! | F59: 5 | G59: =WORKDAY.INTL(E59,F59,1,Data!$C$3:$C$60) -> #NUM! | I59: =WORKDAY.INTL(K58,0,1,Data!$C$3:$C$60) -> 46044 | J59: 2 | K59: =WORKDAY.INTL(I59,J59,1,Data!$C$3:$C$60) -> 46048 | M59: 1 | N59: 1
B61: 7 | C61: QA Inspections | E61: =MIN(E62:E65) -> #NUM! | F61: =G61-E61 -> #NUM! | G61: =MAX(G62:G65) -> #NUM! | I61: =MIN(I62:I65) -> 46037 | J61: =K61-I61 -> 7 | K61: =MAX(K62:K65) -> 46044 | M61: =(J62*M62+J63*M63)/SUM(J62:J63) -> 1 | N61: =(K62*N62)/SUM(K62) -> 1
B62: 7.1 | C62: Red-Team Inspection | E62: =WORKDAY.INTL(E58,0,1,Data!$C$3:$C$60) -> #NUM! | F62: 3 | G62: =WORKDAY.INTL(E62,F62,1,Data!$C$3:$C$60) -> #NUM! | I62: 46037 | J62: 2 | K62: =WORKDAY.INTL(I62,J62,1,Data!$C$3:$C$60) -> 46042 | M62: 1 | N62: 1 | O62: Moved to Jan - Comm delay - breakers
B63: 7.2 | C63: Snags completion | E63: =G62 -> #NUM! | F63: 7 | G63: =WORKDAY.INTL(E63,F63,1,Data!$C$3:$C$60) -> #NUM! | I63: =K62 -> 46042 | J63: 2 | K63: =WORKDAY.INTL(I63,J63,1,Data!$C$3:$C$60) -> 46044 | M63: 1 | N63: 1
B64: 7.3 | C64: Structural Engineer SignOff (CMB) | E64: =G63 -> #NUM! | F64: 7 | G64: =WORKDAY.INTL(E64,F64,1,Data!$C$3:$C$60) -> #NUM! | I64: =I63 -> 46042 | J64: 2 | K64: =WORKDAY.INTL(I64,J64,1,Data!$C$3:$C$60) -> 46044 | M64: 1 | N64: 1
B66: 8 | C66: Project Closure | E66: =MIN(E67:E69) -> #NUM! | F66: =G66-E66 -> #NUM! | G66: =MAX(G67:G69) -> #NUM! | I66: =MIN(I67:I69) -> 46042 | J66: =K66-I66 -> 15 | K66: =MAX(K67:K69) -> 46057 | M66: =(J67*M67+J68*M68+J69*M69)/SUM(J67:J69) -> 0.71428571 | N66: =(K63*N63+K58*N58+K67*N67+K68*N68+K69*N69)/SUM(K63:K69) -> 0.83330619
B67: 8.1 | C67: Handover documentation | E67: =WORKDAY.INTL(E63,0,1,Data!$C$3:$C$60) -> #NUM! | F67: 7 | G67: =WORKDAY.INTL(E67,F67,1,Data!$C$3:$C$60) -> #NUM! | I67: =WORKDAY.INTL(I63,0,1,Data!$C$3:$C$60) -> 46042 | J67: 3 | K67: =WORKDAY.INTL(I67,J67,1,Data!$C$3:$C$60) -> 46045 | M67: 1 | N67: =_xlfn.LET( _xlpm.s,VALUE($I67), _xlpm.e,VALUE($K67), IF(OR(_xlpm.s="",_xlpm.e=""),"", IF(_xlpm.e<=_xlpm.s, IF(TODAY()>=_xlpm.e,1,0), MAX(0,MIN(1,(TODAY()-_xlpm.s)/(_xlpm.e-_xlpm.s))))) ) -> 1 | O67: December holidays pushing handover to Jan
B68: 8.2 | C68: Handover to Client | E68: =WORKDAY.INTL(G67,0,1,Data!$C$3:$C$60) -> #NUM! | F68: 1 | G68: =WORKDAY.INTL(E68,F68,1,Data!$C$3:$C$60) -> #NUM! | I68: =WORKDAY.INTL(K67,0,1,Data!$C$3:$C$60) -> 46045 | J68: 3 | K68: =WORKDAY.INTL(I68,J68,1,Data!$C$3:$C$60) -> 46050 | M68: 1 | N68: =_xlfn.LET( _xlpm.s,VALUE($I68), _xlpm.e,VALUE($K68), IF(OR(_xlpm.s="",_xlpm.e=""),"", IF(_xlpm.e<=_xlpm.s, IF(TODAY()>=_xlpm.e,1,0), MAX(0,MIN(1,(TODAY()-_xlpm.s)/(_xlpm.e-_xlpm.s))))) ) -> 1
B69: 8.3 | C69: Handover to Matriarch | E69: =WORKDAY.INTL(G67,0,1,Data!$C$3:$C$60) -> #NUM! | F69: 1 | G69: =WORKDAY.INTL(E69,F69,1,Data!$C$3:$C$60) -> #NUM! | I69: =WORKDAY.INTL(K67,0,1,Data!$C$3:$C$60) -> 46045 | J69: 8 | K69: =WORKDAY.INTL(I69,J69,1,Data!$C$3:$C$60) -> 46057 | M69: 0.5 | N69: =_xlfn.LET( _xlpm.s,VALUE($I69), _xlpm.e,VALUE($K69), IF(OR(_xlpm.s="",_xlpm.e=""),"", IF(_xlpm.e<=_xlpm.s, IF(TODAY()>=_xlpm.e,1,0), MAX(0,MIN(1,(TODAY()-_xlpm.s)/(_xlpm.e-_xlpm.s))))) ) -> 1
M74: Baseline
S75: =TODAY() -> 46076 | T75: =TODAY() -> 46076
S76: 1 | T76: 0
S78: Milestone | T78: Start Date | U78: Duration | V78: End Date
S79: =C11 -> Project Initiation | T79: =I11 -> 45909 | U79: =J11 -> 52 | V79: =K11 -> 45961
S80: =C20 -> Site Establishment | T80: =I20 -> 45950 | U80: =J20 -> 1 | V80: =K20 -> 45951
S81: =C23 -> AC Installation | T81: =I23 -> 45909 | U81: =J23 -> 80 | V81: =K23 -> 45989
S82: =C30 -> DC Works | T82: =I30 -> 45950 | U82: =J30 -> 91 | V82: =K30 -> 46041
S83: =C49 -> Module installation | T83: =I49 -> 45950 | U83: =J49 -> 53 | V83: =K49 -> 46003
S84: =C49 -> Module installation | T84: =I49 -> 45950 | U84: =J49 -> 53 | V84: =K49 -> 46003
S85: =C55 -> Commissioning | T85: =I55 -> 45989 | U85: =J55 -> 55 | V85: =K55 -> 46044
S86: =C61 -> QA Inspections | T86: =I61 -> 46037 | U86: =J61 -> 7 | V86: =K61 -> 46044
S87: =C66 -> Project Closure | T87: =I66 -> 46042 | U87: =J66 -> 15 | V87: =K66 -> 46057

Sheet Revenue Tracking
B2: HIGH LEVEL PROJECT REVENUE TRACKING
D3: COSTED | F3: ACTUAL | L3: FINANCIAL REVIEW | N3: TIMELINE REVIEW | T3: 2025 Actual Revenue | U3: 2025 Actual COS | V3: 2026 Budget Revenue | W3: 2026 Budget COS | X3: 2026 Actual Revenue | Y3: 2026 Actual COS
B4: 1 | C4: Planned Revenue | D4: ='Project Plan'!E6 -> 1891415.1 | F4: =F28 -> 2041415.1 | N4: Start Date | T4: =SUMIFS('Expenditure Breakdown'!$U:$U, 'Expenditure Breakdown'!$T:$T, ">"&DATE(2024,8,31), 'Expenditure Breakdown'!$T:$T, "<="&DATE(2025,8,31), 'Expenditure Breakdown'!$S:$S, "<>") -> 0 | U4: =SUMIFS('Expenditure Breakdown'!$Q:$Q, 'Expenditure Breakdown'!$T:$T, ">"&DATE(2024,8,31), 'Expenditure Breakdown'!$T:$T, "<="&DATE(2025,8,31), 'Expenditure Breakdown'!$S:$S, "<>") -> 0 | V4: =SUMIFS('Expenditure Breakdown'!$U:$U, 'Expenditure Breakdown'!$T:$T, ">"&DATE(2025,8,31), 'Expenditure Breakdown'!$T:$T, "<="&DATE(2026,8,31)) -> 2041415.1 | W4: =SUMIFS('Expenditure Breakdown'!$Q:$Q, 'Expenditure Breakdown'!$T:$T, ">"&DATE(2025,8,31), 'Expenditure Breakdown'!$T:$T, "<="&DATE(2026,8,31)) -> 1377826.2 | X4: =SUMIFS('Expenditure Breakdown'!$U:$U, 'Expenditure Breakdown'!$T:$T, ">"&DATE(2025,8,31), 'Expenditure Breakdown'!$T:$T, "<="&DATE(2026,8,31), 'Expenditure Breakdown'!$S:$S, "<>") -> 1645718.3 | Y4: =SUMIFS('Expenditure Breakdown'!$Q:$Q, 'Expenditure Breakdown'!$T:$T, ">"&DATE(2025,8,31), 'Expenditure Breakdown'!$T:$T, "<="&DATE(2026,8,31), 'Expenditure Breakdown'!$S:$S, "<>") -> 1210806.7
B5: 2 | C5: Planned Expenditure | D5: =+'Expenditure Tracking'!F5 -> 1645950.7 | F5: =+'Expenditure Tracking'!H5 -> 1377826.2 | G5: VO PM LIMIT | H5: CURRENT VO Total
B6: 3 | C6: Planned Profit | D6: =+D4-D5 -> 245464.41 | F6: =+F4-F5 -> 663588.94 | G6: =D6*0.05 -> 12273.221 | H6: =SUMIF('Expenditure Breakdown'!N:N,"*VO*",'Expenditure Breakdown'!Q:Q) -> 0 | N6: End Date - PC
B7: 4 | C7: Planned Margin | D7: =+D6/D4 -> 0.12977818 | F7: =+F6/F4 -> 0.32506321
B10: CONTRACT
B12: No. | C12: PAYMENT MILESTONE | E12: % | F12: VALUE | H12: PLANNED PAYMENT DATE | L12: INVOICE NUMBER | N12: INVOICE RAISED DATE | P12: PAYMENT RECEIVED DATE | R12: MILESTONE NOTES & COMMENTS
B13: 1 | C13: Milestone 1: Site Establishment Preperation & HSE | E13: 0.285 | F13: 551182.07 | H13: 45968 | L13: 004852 | N13: 15/10/2025 | P13: 45989 | AO13: ='Change Register'!$Q$14+ 7 -> 7
B14: 2 | C14: Milestone 1:Retention
B15: 3 | C15: Milestone 2: DC Installation Partial Completion | E15: 0.19 | F15: 349081.98 | H15: 45993 | L15: 004884 | N15: 45989 | P15: 46081
B16: 4 | C16: Milestone 2: DC Installation Final Completion | F16: 38786.89 | H16: 46002 | L16: 004904 | N16: 46009 | P16: 46081
B17: 5 | C17: Milestone 3: AC Installation Partial Completion | E17: 0.19 | F17: 116360.66 | H17: 45994 | L17: 004884 | N17: 45989 | P17: 46081
B18: 6 | C18: Milestone 3: AC Installation Final Completion | F18: 271508.21 | H18: 45993 | L18: 004904 | N18: 46009 | P18: 46081
B19: 7 | C19: Milestone 4: Commissioning Complete | E19: 0.094999998 | F19: 183727.35 | H19: 46002 | L19: 004904 | N19: 46009 | P19: 46081
B20: 8 | C20: Milestone 4:Retention | P20: 46081
B21: 9 | C21: Milestone 5: QA Inspections Complete | E21: 0.047499999 | F21: 96967.22 | H21: 45996 | L21: 004930 | N21: 46044 | P21: 46081 | R21: Coupa portal issues preventing payment
B22: 10 | C22: Milestone 5:Retention | H22: 46180 | P22: 46081
B23: 11 | C23: Milestone 6: Project Closure | E23: 0.1425 | F23: 290901.66 | H23: 46007 | L23: 004930 | N23: 46044 | P23: 46081
B24: 12 | C24: Milestone 6:Retention | H24: 46180 | P24: 46081
B25: 13 | C25: Retentions | F25: 102070.75 | H25: 46165 | L25: 004930 | N25: 46044 | P25: 46081
B26: 14 | C26: Retention Balance | E26: 0.05 | F26: 40828.33 | H26: 46112 | L26: 004945 | N26: 46071 | P26: 46112
E28: =SUM(E13:E26) -> 1 | F28: =SUM(F13:F26) -> 2041415.1
B30: KEY: | C30: contains an error (in result or a check has failed)
C31: Red Font - IF TEXT : content not yet confirmed | L31: =F17+20414.15 -> 136774.81
C32: Red Font - IF NUMBER: Negative value
C33: Anything in yellow is a concern or risk for noting or action
C34: confirmed
C35: [ADD INITIALS: comment for noting in square brackets, use colour or red to draw attention if important]
C36: [RT: When adding rows into sheet, ensure you insert between first and last row of each category]
C37: end of sheet - do not insert information below/beyond this
B47: No. | C47: PAYMENT MILESTONE | E47: % | F47: VALUE
B48: 1 | C48: Deposit - Project commencement | E48: 0.35 | F48: =$F$54*E48 -> 714495.29
B49: 2 | C49: Delivery of Panels | E49: 0.3 | F49: =$F$54*E49 -> 612424.54
B50: 3 | C50: Delivery of Inverters | E50: 0.2 | F50: =$F$54*E50 -> 408283.02
B51: 4 | C51: Practical Completion | E51: 0.1 | F51: =$F$54*E51 -> 204141.51
B52: 5 | C52: Handover | E52: 0.05 | F52: =$F$54*E52 -> 102070.76
C53: Total | E53: =SUM(E48:E52) -> 1 | F53: =SUM(F48:F52) -> 2041415.1
E54: =SUM(E48:E52) -> 1 | F54: =F28 -> 2041415.1

Sheet Expenditure Breakdown
B2: COSTED EXPENDITURE BREAKDOWN | I2: =SUM(I6:I167) -> 1645950.7 | J2: =SUM(J6:J167) -> 1891415.1 | L2: ACTUAL EXPENDITURE BREAKDOWN | R2: FINANCE ONLY | X2: =SUM(X6:X167) -> 1377826.2
B4: No. | C4: Product / Service | D4: Description of Work | E4: QTY | F4: Rate / Unit | G4: Budget Total | H4: FORECASTED PAYMENT DATE | I4: Total COS | J4: =IF(J2-'Revenue Tracking'!D4>=0, "Total Revenue", "ERROR on REV" ) -> Total Revenue | L4: No. | M4: Product/ Service | N4: Description of Work | O4: QTY | P4: Rate / Unit | Q4: Actual Total | R4: PO NUMBER | S4: INVOICE NUMBER | T4: INVOICE RAISED DATE | U4: REVENUE RECOGNITION AMOUNT | V4: CHECK | W4: FINANCE PAYMENT DATE | X4: Total COS
B6: 1 | C6: Panels | D6: Panels Budget | G6: =D168 -> 0 | I6: =SUM(G6:G11) -> 0 | J6: =F168 -> 0 | L6: 1 | M6: 1. Panels | X6: =SUM(Q6:Q11) -> 0
B7: 1 | D7: Delivery Budget | L7: 1 | M7: 1. Panels
B8: 1 | L8: 1 | M8: 1. Panels
B9: 1 | L9: 1 | M9: 1. Panels
B10: 1 | L10: 1 | M10: 1. Panels
B11: 1 | L11: 1 | M11: 1. Panels | Y11: BUDGET | Z11: Installer Allocation
Y12: AC Equipment | Z12: =G57 -> 18000
B13: 2 | C13: Inverters | D13: Inverter Budget | G13: =D169 -> 0 | I13: =SUM(G13:G19) -> 0 | J13: =F169 -> 0 | L13: 2 | M13: 2. Inverters | X13: =SUM(Q13:Q19) -> 0 | Y13: DC Equipment | Z13: =G32 -> 44160
B14: 2 | L14: 2 | M14: 2. Inverters | Y14: AC Labour | Z14: =G95 -> 161000
B15: 2 | L15: 2 | M15: 2. Inverters | Y15: DC Labour | Z15: =G96 -> 322000
B16: 2 | L16: 2 | M16: 2. Inverters | Y16: Offloading | Z16: =G109 -> 8500
B17: 2 | L17: 2 | M17: 2. Inverters | Y17: Scaffolding | Z17: =G110 -> 17474
B18: 2 | L18: 2 | M18: 2. Inverters | Y18: Storage | Z18: =G112 -> 3782.2222
B19: 2 | L19: 2 | M19: 2. Inverters | Y19: Telehandler | Z19: 0
B21: 3 | C21: Mounting Structures | D21: Structure Budget | G21: =D170 -> 395600 | H21: ='Project Plan'!E32+30 -> 45977 | I21: =SUM(G21:G29) -> 395600 | J21: =F170 -> 565143.55 | L21: 3 | M21: 3. Mounting Structures | N21: Schletter Structure | Q21: =329925.07-Q24 -> 307922.87 | R21: PO4368-STD-20251014 - RV Approved | S21: Schletter - INV2313 | T21: 45961 | U21: 419817.36 | V21: =J21-SUM(U21:U29) -> 0 | W21: 45989 | X21: =SUM(Q21:Q29) -> 392315.21 | Y21: Other | Z21: 0
L22: 3 | M22: 3. Mounting Structures | Q22: 15800 | S22: Schletter - INV2479 | T22: 46022 | U22: 0 | W22: 46021
L23: 3 | M23: 3. Mounting Structures | N23: Internal Connectors | Q23: 1578 | R23: PO4516-STD-20251202 - RV Approved | S23: Schletter - INV2483 | T23: 46022 | U23: 0 | W23: 46021
B24: 3 | L24: 3 | M24: 3. Mounting Structures | N24: FA Screw M10 x 25 & Flange | Q24: 22002.2 | R24: PO4405-STD-20251024 - RV Approved | S24: Schletter - INV2317 | T24: 45961 | U24: 29997.465 | W24: =W21 -> 45989 | Y24: Total | Z24: =SUM(Z12:Z21) -> 574916.22
B25: 3 | L25: 3 | M25: 3. Mounting Structures | Q25: 19475 | S25: Schletter - INV2333 | T25: 45961 | U25: 26551.919 | W25: 45989 | Y25: Less 15% | Z25: =+Z24*0.85 -> 488678.79
B26: 3 | L26: 3 | M26: 3. Mounting Structures | N26: New Rails | Q26: 65115 | R26: PO4440-STD-20251104 - RV Approved | S26: Schletter - INV2392 | T26: 45991 | U26: 88776.802 | W26: =T26+30 -> 46021 | Y26: R/Wp | Z26: =Z25/'Project Plan'!$E$3/1000 -> 1.0623452
B27: 3 | L27: 3 | M27: 3. Mounting Structures | N27: Credit for old Rails | Q27: -50525 | S27: Schletter - CRN0282 | T27: 45991 | U27: 0 | W27: =T27+30 -> 46021
L28: 3 | M28: 3. Mounting Structures | Q28: 5195.4 | R28: PO4480-STD-20251120 - RV Approved | S28: Schletter - INV2449 | T28: 45991 | U28: 0 | W28: =T28+30 -> 46021
B29: 3 | L29: 3 | M29: 3. Mounting Structures | N29: Additional Rails | Q29: 5751.74 | R29: PO4470-STD-20251113 - RV Approved | S29: Schletter - INV2415 | T29: 45991 | U29: 0 | W29: =T29+30 -> 46021 | Y29: ACTUAL - Luken Solar | Z29: Installer Price
T30: =IF(W30>1,EOMONTH(W30,0),"") | Y30: =Y12 -> AC Equipment | Z30: 17282.518
B31: 4 | C31: DC Equipment | D31: DC Cable Budget | E31: 0 | G31: 0 | I31: =SUM(G31:G46) -> 44160 | J31: =F171 -> 63085.714 | L31: 4 | M31: 4. DC Equipment | U31: =(Q31/$X$31*$J$31) -> 0 | V31: =J31-SUM(U31:U46) -> -0.0012625068 | X31: =SUM(Q31:Q46) -> 103899.78 | Y31: =Y13 -> DC Equipment | Z31: 42399.778
B32: 4 | D32: DC Equipment Budget | G32: =D171-G31 -> 44160 | H32: ='Project Plan'!G30 -> #NUM! | L32: 4 | M32: 4. DC Equipment | N32: DC Cable - Rubicon + Delivery | O32: 8000 | Q32: 117500 | R32: PO4497-STB-20251126 - RV Approved | S32: Rubicon INVRED-0136070 | T32: 46022 | U32: 34768.209 | W32: =T32+30 -> 46052 | Y32: =Y14 -> AC Labour | Z32: 154582.52
B33: 4 | L33: 4 | M33: 4. DC Equipment | N33: DC Cable allocated to Superspar Despatch | O33: -4000 | P33: 14 | Q33: =O33*P33 -> -56000 | S33: Allocated to superspar Despatch - PH2 | T33: 46053 | U33: -2704.84 | W33: 46053 | Y33: =Y15 -> DC Labour | Z33: 309165.05
B34: 4 | L34: 4 | M34: 4. DC Equipment | T34: =IF(W34>1,EOMONTH(W34,0),"") | U34: =(Q34/$X$31*$J$31) -> 0 | Y34: Lifelines | Z34: 8161.1891
B35: 4 | L35: 4 | M35: 4. DC Equipment | N35: Project Kick Off | O35: =Z31 -> 42399.778 | P35: 0.1 | Q35: =$O$35*P35 -> 4239.9778 | R35: PO4351-STD-20251009 - RV Approved | S35: Luken Solar INV-0673 | T35: =T96 -> 45961 | U35: 6308.5714 | W35: =W96 -> 45954 | Y35: Forklift | Z35: 16777.484
B36: 4 | L36: 4 | M36: 4. DC Equipment | N36: Site Establishment | P36: 0.15 | Q36: =$O$35*P36 -> 6359.9667 | S36: Luken Solar INV-0674 | T36: =T97 -> 45961 | U36: 9462.8571 | W36: =W97 -> 45954 | Y36: Geda | Z36: 3631.4624
B37: 4 | L37: 4 | M37: 4. DC Equipment | N37: AC Installation Complete | P37: 0.2 | Q37: =$O$35*P37 -> 8479.9555 | S37: Luken Solar INV-0689 | T37: =T98 -> 46022 | U37: 3345.621 | W37: =W98 -> 46003 | Y37: Logistics | Z37: 0
B38: 4 | L38: 4 | M38: 4. DC Equipment | N38: DC Installation Complete | P38: 0.1 | Q38: =$O$35*P38 -> 4239.9778 | S38: Luken Solar INV-0684 | T38: =T99 -> 46022 | U38: 1672.8105 | W38: 46009 | Y38: HSE | Z38: 0
L39: 4 | M39: 4. DC Equipment | N39: DC Installation Complete | P39: 0.15 | Q39: =O35*P39 -> 6359.9667 | S39: =S100 -> Luken INV0692 | T39: =T100 -> 46022 | U39: 2509.2157 | W39: =W100 -> 46009
B40: 4 | L40: 4 | M40: 4. DC Equipment | N40: Commissioning Complete | P40: 0.1 | Q40: =$O$35*P40 -> 4239.9778 | S40: =S101 -> Luken Solar INV-0699 | T40: =T101 -> 46053 | U40: 2574.4235 | W40: =W101 -> 46051 | Y40: Other | Z40: 0
B41: 4 | L41: 4 | M41: 4. DC Equipment | N41: Site De-establisment | P41: 0.1 | Q41: =$O$35*P41 -> 4239.9778 | S41: =S102 -> Luken Solar INV-0706 | T41: =T102 -> 46053 | U41: 2574.4235 | W41: =W102 -> 46051 | Y41: Other | Z41: 0
B42: 4 | L42: 4 | M42: 4. DC Equipment | N42: Handover Document Complete | P42: 0.05 | Q42: =$O$35*P42 -> 2119.9889 | S42: =S103 -> Luken Solar INV-0702 | T42: =T103 -> 46053 | U42: 1287.2117 | W42: =W103 -> 46051 | Y42: Total | Z42: =SUM(Z30:Z41) -> 552000
B43: 4 | L43: 4 | M43: 4. DC Equipment | N43: End of Defects Period | P43: 0.05 | Q43: =$O$35*P43 -> 2119.9889 | S43: =S104 -> Luken Solar INV-0705 | T43: =T104 -> 46053 | U43: 1287.2117 | W43: 46079 | Y43: R/Wp | Z43: =Z42/'Project Plan'!$E$3/1000 -> 1.2
B44: 4 | L44: 4 | M44: 4. DC Equipment | T44: =IF(W44>1,EOMONTH(W44,0),"") | U44: =(Q44/$X$31*$J$31) -> 0
B45: 4 | L45: 4 | M45: 4. DC Equipment | T45: =IF(W45>1,EOMONTH(W45,0),"") | U45: =(Q45/$X$31*$J$31) -> 0
B46: 4 | L46: 4 | M46: 4. DC Equipment | T46: =IF(W46>1,EOMONTH(W46,0),"") | U46: =(Q46/$X$31*$J$31) -> 0
T47: =IF(W47>1,EOMONTH(W47,0),"")
B48: 5 | C48: Monitoring | D48: Monitoring Budget | G48: =D173-G49 -> 8000 | H48: =H32 -> #NUM! | I48: =SUM(G48:G55) -> 23000 | J48: =F173 -> 32857.143 | L48: 5 | M48: 5. Monitoring | T48: =IF(W48>1,EOMONTH(W48,0),"") | U48: =(Q48/$X$48*$J$48) -> 0 | V48: =J48-SUM(U48:U55) -> -0.00082806761 | X48: =SUM(Q48:Q55) -> 31776.72
B49: 5 | D49: Revenue Metering | G49: 15000 | H49: =H48 -> #NUM! | L49: 5 | M49: 5. Monitoring | N49: CTs & Meters | Q49: 18378 | R49: PO4449-STD-20251106 - RV Approved | S49: Accuenergy Inv: ASAI-006805 | T49: 45991 | U49: 16958.361 | W49: 46029
B50: 5 | L50: 5 | M50: 5. Monitoring | N50: Techsitter | Q50: 11169 | S50: Matriarch Inv: 6200 | T50: 46053 | U50: 13841.301 | W50: 46051
L51: 5 | M51: 5. Monitoring | N51: Delivery of Techsitter | Q51: 307.94 | S51: DSV Inv: 180156055 | T51: 45991 | U51: 284.15267 | W51: 46021
B52: 5 | L52: 5 | M52: 5. Monitoring | N52: Power Supply | Q52: 1664.1 | R52: PO4452-STD-20251107 - RV Approved | S52: Current Automotion - INV346556 | T52: 45991 | U52: 1535.5538 | W52: 45972
B53: 5 | L53: 5 | M53: 5. Monitoring | N53: Delivery | Q53: 257.68 | S53: DSV Inv: 180155155 | T53: 45991 | U53: 237.77508 | W53: 46021
B54: 5 | L54: 5 | M54: 5. Monitoring | T54: =IF(W54>1,EOMONTH(W54,0),"") | U54: =(Q54/$X$48*$J$48) -> 0
B55: 5 | L55: 5 | M55: 5. Monitoring | T55: =IF(W55>1,EOMONTH(W55,0),"") | U55: =(Q55/$X$48*$J$48) -> 0
T56: =IF(W56>1,EOMONTH(W56,0),"")
B57: 6 | C57: AC Equipment | D57: AC Equipment Budget | G57: =D172 -> 18000 | H57: ='Project Plan'!G26+30 -> 45940 | I57: =SUM(G57:G74) -> 18000 | J57: =F172 -> 25714.286 | L57: 6 | M57: 6. AC Equipment | T57: =IF(W57>1,EOMONTH(W57,0),"") | U57: =(Q57/$X$57*$J$57) -> 0 | V57: =J57-SUM(U57:U74) -> 0 | X57: =SUM(Q57:Q74) -> 17282.518
B58: 6 | L58: 6 | M58: 6. AC Equipment | U58: =(Q58/$X$57*$J$57) -> 0
B59: 6 | L59: 6 | M59: 6. AC Equipment | T59: =IF(W59>1,EOMONTH(W59,0),"") | U59: =(Q59/$X$57*$J$57) -> 0
B60: 6 | L60: 6 | M60: 6. AC Equipment | T60: =IF(W60>1,EOMONTH(W60,0),"") | U60: =(Q60/$X$57*$J$57) -> 0
B61: 6 | L61: 6 | M61: 6. AC Equipment | T61: =IF(W61>1,EOMONTH(W61,0),"") | U61: =(Q61/$X$57*$J$57) -> 0
B62: 6 | L62: 6 | M62: 6. AC Equipment | T62: =IF(W62>1,EOMONTH(W62,0),"") | U62: =(Q62/$X$57*$J$57) -> 0
B63: 6 | L63: 6 | M63: 6. AC Equipment | N63: Project Kick Off | O63: =Z30 -> 17282.518 | P63: 0.1 | Q63: =$O$63*P63 -> 1728.2518 | R63: PO4351-STD-20251009 - RV Approved | S63: Luken Solar INV-0673 | T63: =T96 -> 45961 | U63: 2571.4286 | W63: =W96 -> 45954
B64: 6 | L64: 6 | M64: 6. AC Equipment | N64: Site Establishment | P64: 0.15 | Q64: =$O$63*P64 -> 2592.3777 | S64: Luken Solar INV-0674 | T64: =T97 -> 45961 | U64: 3857.1429 | W64: =W97 -> 45954
B65: 6 | L65: 6 | M65: 6. AC Equipment | N65: AC Installation Complete | P65: 0.2 | Q65: =$O$63*P65 -> 3456.5036 | S65: Luken Solar INV-0689 | T65: =T98 -> 46022 | U65: 5142.8571 | W65: =W98 -> 46003
B66: 6 | L66: 6 | M66: 6. AC Equipment | N66: DC Installation Complete | P66: 0.1 | Q66: =$O$63*P66 -> 1728.2518 | S66: Luken Solar INV-0684 | T66: =T99 -> 46022 | U66: 2571.4286 | W66: 46009
L67: 6 | M67: 6. AC Equipment | N67: DC Installation Complete | P67: 0.15 | Q67: =$O$63*P67 -> 2592.3777 | S67: =S100 -> Luken INV0692 | T67: =T100 -> 46022 | U67: 3857.1429 | W67: =W117 -> 46009
B68: 6 | L68: 6 | M68: 6. AC Equipment | N68: Commissioning Complete | P68: 0.1 | Q68: =$O$63*P68 -> 1728.2518 | S68: =S101 -> Luken Solar INV-0699 | T68: =T101 -> 46053 | U68: 2571.4286 | W68: =W101 -> 46051
B69: 6 | L69: 6 | M69: 6. AC Equipment | N69: Site De-establisment | P69: 0.1 | Q69: =$O$63*P69 -> 1728.2518 | S69: =S102 -> Luken Solar INV-0706 | T69: =T102 -> 46053 | U69: 2571.4286 | W69: =W102 -> 46051
B70: 6 | L70: 6 | M70: 6. AC Equipment | N70: Handover Document Complete | P70: 0.05 | Q70: =$O$63*P70 -> 864.1259 | S70: =S103 -> Luken Solar INV-0702 | T70: =T103 -> 46053 | U70: 1285.7143 | W70: =W103 -> 46051
B71: 6 | L71: 6 | M71: 6. AC Equipment | N71: End of Defects Period | P71: 0.05 | Q71: =$O$63*P71 -> 864.1259 | S71: =S104 -> Luken Solar INV-0705 | T71: =T104 -> 46053 | U71: 1285.7143 | W71: 46079
B72: 6 | L72: 6 | M72: 6. AC Equipment | T72: =IF(W72>1,EOMONTH(W72,0),"") | U72: =(Q72/$X$57*$J$57) -> 0
B73: 6 | L73: 6 | M73: 6. AC Equipment | T73: =IF(W73>1,EOMONTH(W73,0),"") | U73: =(Q73/$X$57*$J$57) -> 0
B74: 6 | L74: 6 | M74: 6. AC Equipment | T74: =IF(W74>1,EOMONTH(W74,0),"") | U74: =(Q74/$X$57*$J$57) -> 0
T75: =IF(W75>1,EOMONTH(W75,0),"")
B76: 7 | C76: BESS | I76: =SUM(G76:G83) -> 0 | J76: =F177 -> 0 | L76: 7 | M76: 7.BESS | V76: =J76-SUM(U76:U83) -> 0 | X76: =SUM(Q76:Q83) -> 0
B77: 7 | L77: 7 | M77: 7.BESS
B78: 7 | L78: 7 | M78: 7.BESS
B79: 7 | L79: 7 | M79: 7.BESS
B80: 7 | L80: 7 | M80: 7.BESS
B81: 7 | L81: 7 | M81: 7.BESS
B82: 7 | L82: 7 | M82: 7.BESS
B83: 7 | L83: 7 | M83: 7.BESS
B85: 8 | C85: Product Add On | D85: Contigency | G85: 150000 | H85: =H88 -> #NUM! | I85: =SUM(G85:G93) -> 487000 | J85: =F176+F191 -> 453809.52 | L85: 8 | M85: 8. Product Add On | N85: Contigency | Q85: =1129.28+165640.2 -> 166769.48 | T85: 46081 | U85: =(Q85/$X$85*$J$85)+109171.68 -> 351115 | V85: =J85-SUM(U85:U93) -> -150000.01 | W85: =T85 -> 46081 | X85: =SUM(Q85:Q93) -> 312807.06
B86: 8 | L86: 8 | M86: 8. Product Add On | T86: 46081 | U86: 40828.33
B87: 8 | L87: 8 | M87: 8. Product Add On | N87: Customized Maintenance | Q87: 90120 | S87: Matriarch - iNV-6240 | T87: 46053 | U87: 125017.3 | W87: 46081
B88: 8 | D88: Performance guarantee year 1 | G88: =D191 -> 87000 | H88: =H96 -> #NUM! | L88: 8 | M88: 8. Product Add On | T88: =IF(W88>1,EOMONTH(W88,0),"") | U88: =(Q88/$X$85*$J$85) -> 0
B89: 8 | L89: 8 | M89: 8. Product Add On | N89: Lightning Protection System | Q89: 34320.9 | R89: PO4421-STD-20251029 - RV Approved | S89: LPS - IN307558 | T89: 46022 | U89: 53378.258 | W89: 46031
B90: 8 | D90: Lightning Protection System | G90: 250000 | H90: =H88 -> #NUM! | L90: 8 | M90: 8. Product Add On | T90: =IF(W90>1,EOMONTH(W90,0),"") | U90: =(Q90/$X$85*$J$85) -> 0
B91: 8 | L91: 8 | M91: 8. Product Add On | N91: Toilet Hire | Q91: 1217.4 | R91: PO4432-STD-20251031 - RV Approved | S91: Talisman - 00216340 | T91: 45991 | U91: 1893.3854 | W91: 45995
B92: 8 | L92: 8 | M92: 8. Product Add On | N92: RS 485 SPD - Luken Supply & Install | Q92: 1129.28 | R92: PO4609-STD-20260204 - RV Approved | S92: Luken Solar - INV-0708 | T92: 46081 | U92: =(Q92/$X$85*$J$85) -> 1638.3199 | W92: =T92 -> 46081
B93: 8 | L93: 8 | M93: 8. Product Add On | N93: Trench scanning | Q93: 19250 | R93: PO4503-STD-20251127 -RV Approved | S93: Luken INV-0683 | T93: 45991 | U93: 29938.943 | W93: 45989
K94: Only services to be capture below, products above | T94: =IF(W94>1,EOMONTH(W94,0),"")
B95: 9 | C95: AC & DC Installation | D95: AC Installation Budget | G95: =D181 -> 161000 | H95: ='Project Plan'!G23+7 -> 45966 | I95: =SUM(G95:G107) -> 483000 | J95: =F181+F182 -> 551207.79 | L95: 9 | M95: 9. AC & DC installation | T95: =IF(W95>1,EOMONTH(W95,0),"") | U95: =(Q95/$X$95*$J$95) -> 0 | V95: =J95-SUM(U95:U107) -> 0 | X95: =SUM(Q95:Q107) -> 463747.57
B96: 9 | D96: DC Installation Budget | G96: =D182 -> 322000 | H96: ='Project Plan'!G30+7 -> #NUM! | L96: 9 | M96: 9. AC & DC installation | N96: Project Kick Off | O96: =Z33+Z32 -> 463747.57 | P96: 0.1 | Q96: =$O$96*P96 -> 46374.757 | R96: PO4351-STD-20251009 - RV Approved | S96: Luken Solar INV-0673 | T96: 45961 | U96: 55120.779 | W96: 45954
B97: 9 | L97: 9 | M97: 9. AC & DC installation | N97: Site Establishment | P97: 0.15 | Q97: =$O$96*P97 -> 69562.135 | S97: Luken Solar INV-0674 | T97: 45961 | U97: 82681.168 | W97: 45954
B98: 9 | L98: 9 | M98: 9. AC & DC installation | N98: AC Installation Complete | P98: 0.2 | Q98: =$O$96*P98 -> 92749.514 | S98: Luken Solar INV-0689 | T98: 46022 | U98: 110241.56 | W98: ='Project Plan'!K23+14 -> 46003
B99: 9 | L99: 9 | M99: 9. AC & DC installation | N99: DC Installation Complete | P99: 0.1 | Q99: =$O$96*P99 -> 46374.757 | S99: Luken Solar INV-0684 | T99: 46022 | U99: 55120.779 | W99: 46003
L100: 9 | M100: 9. AC & DC installation | N100: DC Installation Complete | P100: 0.15 | Q100: =$O$96*P100 -> 69562.135 | S100: Luken INV0692 | T100: 46022 | U100: 82681.168 | W100: 46009
B101: 9 | L101: 9 | M101: 9. AC & DC installation | N101: Commissioning Complete | P101: 0.1 | Q101: =$O$96*P101 -> 46374.757 | S101: Luken Solar INV-0699 | T101: 46053 | U101: 55120.779 | W101: ='Project Plan'!K55+7 -> 46051
B102: 9 | L102: 9 | M102: 9. AC & DC installation | N102: Site De-establisment | P102: 0.1 | Q102: =$O$96*P102 -> 46374.757 | S102: Luken Solar INV-0706 | T102: 46053 | U102: 55120.779 | W102: ='Project Plan'!K63+7 -> 46051
B103: 9 | L103: 9 | M103: 9. AC & DC installation | N103: Handover Document Complete | P103: 0.05 | Q103: =$O$96*P103 -> 23187.378 | S103: Luken Solar INV-0702 | T103: 46053 | U103: 27560.389 | W103: ='Project Plan'!K63+7 -> 46051
B104: 9 | L104: 9 | M104: 9. AC & DC installation | N104: End of Defects Period | P104: 0.05 | Q104: =$O$96*P104 -> 23187.378 | S104: Luken Solar INV-0705 | T104: 46053 | U104: 27560.389 | W104: 46079
B105: 9 | L105: 9 | M105: 9. AC & DC installation | T105: =IF(W105>1,EOMONTH(W105,0),"") | U105: =(Q105/$X$95*$J$95) -> 0
...

Sheet Expenditure Tracking
B2: HIGH LEVEL PROJECT EXPENDITURE TRACKING
F4: COSTED | H4: ACTUAL | J4: Difference from Costed
B5: EXPENDITURE | F5: =SUM(F9:F23) -> 1645950.7 | H5: =SUM(H9:H23) -> 1377826.2 | J5: =SUM(J9:J23) -> 268124.52
B7: No. | D7: Item | F7: Costed Expenditure | H7: Actual Expenditure | J7: Saving / Overrun | L7: Comments on variations from planned expenditure
B9: ='Expenditure Breakdown'!L6 -> 1 | D9: ='Expenditure Breakdown'!M6 -> 1. Panels | F9: ='Expenditure Breakdown'!I6 -> 0 | H9: ='Expenditure Breakdown'!X6 -> 0 | J9: =F9-H9 -> 0
B10: ='Expenditure Breakdown'!L13 -> 2 | D10: ='Expenditure Breakdown'!M13 -> 2. Inverters | F10: ='Expenditure Breakdown'!I13 -> 0 | H10: ='Expenditure Breakdown'!X13 -> 0 | J10: =F10-H10 -> 0
B11: ='Expenditure Breakdown'!L21 -> 3 | D11: ='Expenditure Breakdown'!M21 -> 3. Mounting Structures | F11: ='Expenditure Breakdown'!I21 -> 395600 | H11: ='Expenditure Breakdown'!X21 -> 392315.21 | J11: =F11-H11 -> 3284.79
B12: ='Expenditure Breakdown'!L31 -> 4 | D12: ='Expenditure Breakdown'!M31 -> 4. DC Equipment | F12: ='Expenditure Breakdown'!I31 -> 44160 | H12: ='Expenditure Breakdown'!X31 -> 103899.78 | J12: =F12-H12 -> -59739.778
B13: ='Expenditure Breakdown'!L48 -> 5 | D13: ='Expenditure Breakdown'!M48 -> 5. Monitoring | F13: ='Expenditure Breakdown'!I48 -> 23000 | H13: ='Expenditure Breakdown'!X48 -> 31776.72 | J13: =F13-H13 -> -8776.72
B14: ='Expenditure Breakdown'!L57 -> 6 | D14: ='Expenditure Breakdown'!M57 -> 6. AC Equipment | F14: ='Expenditure Breakdown'!I57 -> 18000 | H14: ='Expenditure Breakdown'!X57 -> 17282.518 | J14: =F14-H14 -> 717.48193
B15: ='Expenditure Breakdown'!L76 -> 7 | D15: ='Expenditure Breakdown'!M76 -> 7.BESS | F15: ='Expenditure Breakdown'!I76 -> 0 | H15: ='Expenditure Breakdown'!X76 -> 0 | J15: =F15-H15 -> 0
B16: ='Expenditure Breakdown'!L85 -> 8 | D16: ='Expenditure Breakdown'!M85 -> 8. Product Add On | F16: ='Expenditure Breakdown'!I85 -> 487000 | H16: ='Expenditure Breakdown'!X85 -> 312807.06 | J16: =F16-H16 -> 174192.94
B17: ='Expenditure Breakdown'!L95 -> 9 | D17: ='Expenditure Breakdown'!M95 -> 9. AC & DC installation | F17: ='Expenditure Breakdown'!I95 -> 483000 | H17: ='Expenditure Breakdown'!X95 -> 463747.57 | J17: =F17-H17 -> 19252.432
B18: ='Expenditure Breakdown'!L109 -> 10 | D18: ='Expenditure Breakdown'!M109 -> 10. Site Logistics | F18: ='Expenditure Breakdown'!I109 -> 65756.222 | H18: ='Expenditure Breakdown'!X109 -> 28570.122 | J18: =F18-H18 -> 37186.1
B19: ='Expenditure Breakdown'!L126 -> 11 | D19: ='Expenditure Breakdown'!M126 -> 11. Due Dilligence | F19: ='Expenditure Breakdown'!I126 -> 91500 | H19: ='Expenditure Breakdown'!X126 -> 26725 | J19: =F19-H19 -> 64775
B20: ='Expenditure Breakdown'!L132 -> 12 | D20: ='Expenditure Breakdown'!M132 -> 12. BDP Commission | F20: ='Expenditure Breakdown'!I132 -> 15871.775 | H20: ='Expenditure Breakdown'!X132 -> 0 | J20: =F20-H20 -> 15871.775
B21: ='Expenditure Breakdown'!L135 -> 13 | D21: ='Expenditure Breakdown'!M136 -> 13. Engineering | F21: ='Expenditure Breakdown'!I135 -> 14012.703 | H21: ='Expenditure Breakdown'!X135 -> 0 | J21: =F21-H21 -> 14012.703
B22: ='Expenditure Breakdown'!L142 -> 14 | D22: ='Expenditure Breakdown'!M142 -> 14. General Expenses | F22: ='Expenditure Breakdown'!I142 -> 8050 | H22: ='Expenditure Breakdown'!X142 -> 702.2 | J22: =F22-H22 -> 7347.8
B23: ='Expenditure Breakdown'!L155 -> 15 | D23: ='Expenditure Breakdown'!M155 -> 15. Service Add On | F23: ='Expenditure Breakdown'!I155 -> 0 | H23: ='Expenditure Breakdown'!X155 -> 0 | J23: =F23-H23 -> 0
D25: check: | F25: ='Expenditure Breakdown'!I2-'Expenditure Tracking'!F5 -> 0 | G25: =#REF!-G5 -> #REF! | H25: ='Expenditure Breakdown'!X2-H5 -> 0

Sheet Cashflow
D1: [RT: Double Check the first date is always a MONDAY] | F1: 45845 | G1: =F1+7 -> 45852 | H1: =G1+7 -> 45859 | I1: =H1+7 -> 45866 | J1: =I1+7 -> 45873 | K1: =J1+7 -> 45880 | L1: =K1+7 -> 45887 | M1: =L1+7 -> 45894 | N1: =M1+7 -> 45901 | ... AZG1: =AZF1+7 -> 55316
A2: PLANNED | C2: CHECK | D2: CHECK
B3: Planned Revenue | C3: ='Revenue Tracking'!D4 -> 1891415.1 | D3: =SUM(F3:AZG3)-150000 -> 1891415.1 | F3: =SUMIFS('Revenue Tracking'!$F$13:$F$26, 'Revenue Tracking'!$H$13:$H$26, ">="&F1,'Revenue Tracking'!$H$13:$H$26, "<"&G1) -> 0 | G3: =SUMIFS('Revenue Tracking'!$F$13:$F$26, 'Revenue Tracking'!$H$13:$H$26, ">="&G1,'Revenue Tracking'!$H$13:$H$26, "<"&H1) -> 0 | H3: =SUMIFS('Revenue Tracking'!$F$13:$F$26, 'Revenue Tracking'!$H$13:$H$26, ">="&H1,'Revenue Tracking'!$H$13:$H$26, "<"&I1) -> 0 | I3: =SUMIFS('Revenue Tracking'!$F$13:$F$26, 'Revenue Tracking'!$H$13:$H$26, ">="&I1,'Revenue Tracking'!$H$13:$H$26, "<"&J1) -> 0 | J3: =SUMIFS('Revenue Tracking'!$F$13:$F$26, 'Revenue Tracking'!$H$13:$H$26, ">="&J1,'Revenue Tracking'!$H$13:$H$26, "<"&K1) -> 0 | K3: =SUMIFS('Revenue Tracking'!$F$13:$F$26, 'Revenue Tracking'!$H$13:$H$26, ">="&K1,'Revenue Tracking'!$H$13:$H$26, "<"&L1) -> 0 | L3: =SUMIFS('Revenue Tracking'!$F$13:$F$26, 'Revenue Tracking'!$H$13:$H$26, ">="&L1,'Revenue Tracking'!$H$13:$H$26, "<"&M1) -> 0 | M3: =SUMIFS('Revenue Tracking'!$F$13:$F$26, 'Revenue Tracking'!$H$13:$H$26, ">="&M1,'Revenue Tracking'!$H$13:$H$26, "<"&N1) -> 0 | ... AZG3: =SUMIFS('Revenue Tracking'!$F$13:$F$26, 'Revenue Tracking'!$H$13:$H$26, ">="&AZG1,'Revenue Tracking'!$H$13:$H$26, "<"&AZH1) -> 0
B4: Planned Revenue - Cumulative | F4: =F3 -> 0 | G4: =F4+G3 -> 0 | H4: =G4+H3 -> 0 | I4: =H4+I3 -> 0 | J4: =I4+J3 -> 0 | K4: =J4+K3 -> 0 | L4: =K4+L3 -> 0 | M4: =L4+M3 -> 0 | N4: =M4+N3 -> 0 | ... AZG4: =AZF4+AZG3 -> 2041415.1
B5: Planned Expenditure | C5: ='Revenue Tracking'!D5 -> 1645950.7 | D5: =SUM(F5:AZG5) -> 640356.22 | F5: =SUMIFS('Expenditure Breakdown'!$G$6:$G$174, 'Expenditure Breakdown'!$H$6:$H$174, ">="&F1,'Expenditure Breakdown'!$H$6:$H$174, "<"&G1) -> 0 | G5: =SUMIFS('Expenditure Breakdown'!$G$6:$G$174, 'Expenditure Breakdown'!$H$6:$H$174, ">="&G1,'Expenditure Breakdown'!$H$6:$H$174, "<"&H1) -> 0 | H5: =SUMIFS('Expenditure Breakdown'!$G$6:$G$174, 'Expenditure Breakdown'!$H$6:$H$174, ">="&H1,'Expenditure Breakdown'!$H$6:$H$174, "<"&I1) -> 0 | I5: =SUMIFS('Expenditure Breakdown'!$G$6:$G$174, 'Expenditure Breakdown'!$H$6:$H$174, ">="&I1,'Expenditure Breakdown'!$H$6:$H$174, "<"&J1) -> 0 | J5: =SUMIFS('Expenditure Breakdown'!$G$6:$G$174, 'Expenditure Breakdown'!$H$6:$H$174, ">="&J1,'Expenditure Breakdown'!$H$6:$H$174, "<"&K1) -> 0 | K5: =SUMIFS('Expenditure Breakdown'!$G$6:$G$174, 'Expenditure Breakdown'!$H$6:$H$174, ">="&K1,'Expenditure Breakdown'!$H$6:$H$174, "<"&L1) -> 0 | L5: =SUMIFS('Expenditure Breakdown'!$G$6:$G$174, 'Expenditure Breakdown'!$H$6:$H$174, ">="&L1,'Expenditure Breakdown'!$H$6:$H$174, "<"&M1) -> 0 | M5: =SUMIFS('Expenditure Breakdown'!$G$6:$G$174, 'Expenditure Breakdown'!$H$6:$H$174, ">="&M1,'Expenditure Breakdown'!$H$6:$H$174, "<"&N1) -> 0 | ... AZG5: =SUMIFS('Expenditure Breakdown'!$G$6:$G$174, 'Expenditure Breakdown'!$H$6:$H$174, ">="&AZG1,'Expenditure Breakdown'!$H$6:$H$174, "<"&AZH1) -> 0
B6: Planned Expenditure - Cumulative | F6: =F5 -> 0 | G6: =F6+G5 -> 0 | H6: =G6+H5 -> 0 | I6: =H6+I5 -> 0 | J6: =I6+J5 -> 0 | K6: =J6+K5 -> 0 | L6: =K6+L5 -> 0 | M6: =L6+M5 -> 0 | N6: =M6+N5 -> 0 | ... AZG6: =AZF6+AZG5 -> 640356.22
B7: PLANNED CashFlow | F7: =F4-F6 -> 0 | G7: =G4-G6 -> 0 | H7: =H4-H6 -> 0 | I7: =I4-I6 -> 0 | J7: =J4-J6 -> 0 | K7: =K4-K6 -> 0 | L7: =L4-L6 -> 0 | M7: =M4-M6 -> 0 | ... AZG7: =AZG4-AZG6 -> 1401058.9
A8: ACTUAL | C8: CHECK | D8: CHECK
B9: Actual + Planned Revenue | C9: ='Revenue Tracking'!F4 -> 2041415.1 | D9: =SUM(F9:AZG9)-150000 -> 1891415.1 | F9: =SUMIFS('Revenue Tracking'!$F$13:$F$26, 'Revenue Tracking'!$P$13:$P$26, ">="&F1,'Revenue Tracking'!$P$13:$P$26, "<"&G1) -> 0 | G9: =SUMIFS('Revenue Tracking'!$F$13:$F$26, 'Revenue Tracking'!$P$13:$P$26, ">="&G1,'Revenue Tracking'!$P$13:$P$26, "<"&H1) -> 0 | H9: =SUMIFS('Revenue Tracking'!$F$13:$F$26, 'Revenue Tracking'!$P$13:$P$26, ">="&H1,'Revenue Tracking'!$P$13:$P$26, "<"&I1) -> 0 | I9: =SUMIFS('Revenue Tracking'!$F$13:$F$26, 'Revenue Tracking'!$P$13:$P$26, ">="&I1,'Revenue Tracking'!$P$13:$P$26, "<"&J1) -> 0 | J9: =SUMIFS('Revenue Tracking'!$F$13:$F$26, 'Revenue Tracking'!$P$13:$P$26, ">="&J1,'Revenue Tracking'!$P$13:$P$26, "<"&K1) -> 0 | K9: =SUMIFS('Revenue Tracking'!$F$13:$F$26, 'Revenue Tracking'!$P$13:$P$26, ">="&K1,'Revenue Tracking'!$P$13:$P$26, "<"&L1) -> 0 | L9: =SUMIFS('Revenue Tracking'!$F$13:$F$26, 'Revenue Tracking'!$P$13:$P$26, ">="&L1,'Revenue Tracking'!$P$13:$P$26, "<"&M1) -> 0 | M9: =SUMIFS('Revenue Tracking'!$F$13:$F$26, 'Revenue Tracking'!$P$13:$P$26, ">="&M1,'Revenue Tracking'!$P$13:$P$26, "<"&N1) -> 0 | ... AZG9: =SUMIFS('Revenue Tracking'!$F$13:$F$26, 'Revenue Tracking'!$P$13:$P$26, ">="&AZG1,'Revenue Tracking'!$P$13:$P$26, "<"&AZH1) -> 0
B10: Actual + Planned Revenue - Cumulative | F10: =F9 -> 0 | G10: =F10+G9 -> 0 | H10: =G10+H9 -> 0 | I10: =H10+I9 -> 0 | J10: =I10+J9 -> 0 | K10: =J10+K9 -> 0 | L10: =K10+L9 -> 0 | M10: =L10+M9 -> 0 | N10: =M10+N9 -> 0 | ... AZG10: =AZF10+AZG9 -> 2041415.1
B11: Actual + Planned Expenditure | C11: ='Revenue Tracking'!F5 -> 1377826.2 | D11: =SUM(F11:AZG11) -> 1377826.2 | F11: =SUMIFS('Expenditure Breakdown'!$Q$6:$Q$174, 'Expenditure Breakdown'!$W$6:$W$174, ">="&F1,'Expenditure Breakdown'!$W$6:$W$174, "<"&G1) -> 0 | G11: =SUMIFS('Expenditure Breakdown'!$Q$6:$Q$174, 'Expenditure Breakdown'!$W$6:$W$174, ">="&G1,'Expenditure Breakdown'!$W$6:$W$174, "<"&H1) -> 0 | H11: =SUMIFS('Expenditure Breakdown'!$Q$6:$Q$174, 'Expenditure Breakdown'!$W$6:$W$174, ">="&H1,'Expenditure Breakdown'!$W$6:$W$174, "<"&I1) -> 0 | I11: =SUMIFS('Expenditure Breakdown'!$Q$6:$Q$174, 'Expenditure Breakdown'!$W$6:$W$174, ">="&I1,'Expenditure Breakdown'!$W$6:$W$174, "<"&J1) -> 0 | J11: =SUMIFS('Expenditure Breakdown'!$Q$6:$Q$174, 'Expenditure Breakdown'!$W$6:$W$174, ">="&J1,'Expenditure Breakdown'!$W$6:$W$174, "<"&K1) -> 0 | K11: =SUMIFS('Expenditure Breakdown'!$Q$6:$Q$174, 'Expenditure Breakdown'!$W$6:$W$174, ">="&K1,'Expenditure Breakdown'!$W$6:$W$174, "<"&L1) -> 0 | L11: =SUMIFS('Expenditure Breakdown'!$Q$6:$Q$174, 'Expenditure Breakdown'!$W$6:$W$174, ">="&L1,'Expenditure Breakdown'!$W$6:$W$174, "<"&M1) -> 0 | M11: =SUMIFS('Expenditure Breakdown'!$Q$6:$Q$174, 'Expenditure Breakdown'!$W$6:$W$174, ">="&M1,'Expenditure Breakdown'!$W$6:$W$174, "<"&N1) -> 0 | ... AZG11: =SUMIFS('Expenditure Breakdown'!$Q$6:$Q$174, 'Expenditure Breakdown'!$W$6:$W$174, ">="&AZG1,'Expenditure Breakdown'!$W$6:$W$174, "<"&AZH1) -> 0
B12: Actual + Planned Expenditure - Cumulative | F12: =F11 -> 0 | G12: =F12+G11 -> 0 | H12: =G12+H11 -> 0 | I12: =H12+I11 -> 0 | J12: =I12+J11 -> 0 | K12: =J12+K11 -> 0 | L12: =K12+L11 -> 0 | M12: =L12+M11 -> 0 | N12: =M12+N11 -> 0 | ... AZG12: =AZF12+AZG11 -> 1377826.2
B14: ACTUAL CashFlow | F14: =F10-F12 -> 0 | G14: =G10-G12 -> 0 | H14: =H10-H12 -> 0 | I14: =I10-I12 -> 0 | J14: =J10-J12 -> 0 | K14: =K10-K12 -> 0 | L14: =L10-L12 -> 0 | M14: =M10-M12 -> 0 | ... AZG14: =AZG10-AZG12 -> 663588.94
C16: CHECK | D16: CHECK
B17: Revenue Recognition | C17: =C3-D17 -> -150000.01 | D17: =SUM(F17:AZG17) -> 2041415.1 | F17: =SUMIFS('Expenditure Breakdown'!$U$6:$U$174, 'Expenditure Breakdown'!$T$6:$T$174, ">="&F1,'Expenditure Breakdown'!$T$6:$T$174, "<"&G1) -> 0 | G17: =SUMIFS('Expenditure Breakdown'!$U$6:$U$174, 'Expenditure Breakdown'!$T$6:$T$174, ">="&G1,'Expenditure Breakdown'!$T$6:$T$174, "<"&H1) -> 0 | H17: =SUMIFS('Expenditure Breakdown'!$U$6:$U$174, 'Expenditure Breakdown'!$T$6:$T$174, ">="&H1,'Expenditure Breakdown'!$T$6:$T$174, "<"&I1) -> 0 | I17: =SUMIFS('Expenditure Breakdown'!$U$6:$U$174, 'Expenditure Breakdown'!$T$6:$T$174, ">="&I1,'Expenditure Breakdown'!$T$6:$T$174, "<"&J1) -> 0 | J17: =SUMIFS('Expenditure Breakdown'!$U$6:$U$174, 'Expenditure Breakdown'!$T$6:$T$174, ">="&J1,'Expenditure Breakdown'!$T$6:$T$174, "<"&K1) -> 0 | K17: =SUMIFS('Expenditure Breakdown'!$U$6:$U$174, 'Expenditure Breakdown'!$T$6:$T$174, ">="&K1,'Expenditure Breakdown'!$T$6:$T$174, "<"&L1) -> 0 | L17: =SUMIFS('Expenditure Breakdown'!$U$6:$U$174, 'Expenditure Breakdown'!$T$6:$T$174, ">="&L1,'Expenditure Breakdown'!$T$6:$T$174, "<"&M1) -> 0 | M17: =SUMIFS('Expenditure Breakdown'!$U$6:$U$174, 'Expenditure Breakdown'!$T$6:$T$174, ">="&M1,'Expenditure Breakdown'!$T$6:$T$174, "<"&N1) -> 0 | ... AZG17: =SUMIFS('Expenditure Breakdown'!$U$6:$U$174, 'Expenditure Breakdown'!$T$6:$T$174, ">="&AZG1,'Expenditure Breakdown'!$T$6:$T$174, "<"&AZH1) -> 0
B18: Revenue Recognition Cumulative | C18: =D17-D18 -> 0 | D18: =MAX(F18:AZG18) -> 2041415.1 | F18: =F17 -> 0 | G18: =F18+G17 -> 0 | H18: =G18+H17 -> 0 | I18: =H18+I17 -> 0 | J18: =I18+J17 -> 0 | K18: =J18+K17 -> 0 | L18: =K18+L17 -> 0 | M18: =L18+M17 -> 0 | N18: =M18+N17 -> 0 | ... AZG18: =AZF18+AZG17 -> 2041415.1

Sheet Finance - Revenue
A3: Sum of REVENUE RECOGNITION AMOUNT | B3: Column Labels
A4: Row Labels | B4: (blank) | C4: 45961 | D4: 45991 | E4: 46022 | G4: 46053 | H4: 46081 | I4: Grand Total
A5: (blank)
A6: 1. Panels
A7: 2. Inverters
A8: 3. Mounting Structures | C8: 476366.75 | D8: 88776.802 | E8: 0 | I8: 565143.55
A9: 4. DC Equipment | B9: 0 | C9: 15771.429 | E9: 42295.857 | F9: 0 | G9: 5018.4304 | I9: 63085.716
A10: 5. Monitoring | D10: 19015.843 | F10: 0 | G10: 13841.301 | I10: 32857.144
A11: 6. AC Equipment | B11: 0 | C11: 6428.5714 | E11: 11571.429 | F11: 0 | G11: 7714.2857 | I11: 25714.286
A12: 8. Product Add On | D12: 31832.329 | E12: 53378.258 | F12: 0 | G12: 125017.3 | H12: 352753.32 | I12: 562981.2
A13: 9. AC & DC installation | B13: 0 | C13: 137801.95 | E13: 248043.5 | F13: 0 | G13: 165362.34 | I13: 551207.79
A14: 10. Site Logistics | B14: 0 | C14: 18265.617 | E14: 32878.111 | F14: 0 | G14: 21918.736 | I14: 73062.465
A15: 11. Due Dilligence | B15: 0 | E15: 78841.597 | F15: 0 | G15: 22825.07 | I15: 101666.67
A16: 13. Engineering | G16: 15923.526 | I16: 15923.526
A17: 14. General Expenses | C17: 52.577993 | D17: 1573.1532 | E17: 1018.7164 | F17: 0 | G17: 2546.53 | H17: 3753.4662 | I17: 8944.4438
A18: 15. Service Add On
A19: 12. BDP Commission
A20: 7.BESS
A21: Grand Total | B21: 0 | C21: 654686.89 | D21: 141198.13 | E21: 468027.47 | F21: 0 | G21: 380167.51 | H21: 356506.79 | I21: 2000586.8
I23: ='Revenue Tracking'!F4 -> 2041415.1
I24: =I23-I21 -> 40828.332

Sheet Finance - COS
A3: Sum of Actual Total | B3: Column Labels
A4: Row Labels | B4: (blank) | C4: 45961 | D4: 45991 | E4: 46022 | G4: 46053 | H4: 46081 | I4: Grand Total
A5: (blank)
A6: 1. Panels
A7: 2. Inverters
A8: 3. Mounting Structures | C8: 349400.07 | D8: 25537.14 | E8: 17378 | I8: 392315.21
A9: 4. DC Equipment | C9: 10599.944 | E9: 136579.9 | G9: -43280.067 | I9: 103899.78
A10: 5. Monitoring | D10: 20607.72 | G10: 11169 | I10: 31776.72
A11: 6. AC Equipment | C11: 4320.6295 | E11: 7777.1331 | G11: 5184.7554 | I11: 17282.518
A12: 8. Product Add On | D12: 20467.4 | E12: 34320.9 | G12: 90120 | H12: 167898.76 | I12: 312807.06
A13: 9. AC & DC installation | C13: 115936.89 | E13: 208686.41 | G13: 139124.27 | I13: 463747.57
A14: 10. Site Logistics | B14: 0 | C14: 7142.534 | E14: 12856.561 | G14: 8571.0272 | I14: 28570.122
A15: 11. Due Dilligence | B15: 0 | E15: 20725 | G15: 6000 | I15: 26725
A16: 13. Engineering | G16: 0 | I16: 0
A17: 14. General Expenses | C17: 23.8 | D17: 142.8 | E17: 85.68 | G17: 199.92 | H17: 250 | I17: 702.2
A18: 15. Service Add On | H18: 0 | I18: 0
A19: 12. BDP Commission | B19: 0 | I19: 0
A20: 7.BESS
A21: Grand Total | B21: 0 | C21: 487423.87 | D21: 66755.06 | E21: 438409.58 | G21: 217088.91 | H21: 168148.76 | I21: 1377826.2

Sheet Data
C2: Public holidays | F2: Drop down list
C3: 45658 | D3: New Years Day | F3: Approved
C4: 45737 | D4: Human Rights day | F4: Pending
C5: 45765 | D5: Good Friday | F5: Declined
C6: 45768 | D6: Family Day | F6: Abanded
C7: 45774 | D7: Freedom Day
C8: 45765 | D8: Freedom DayObserved
C9: 45778 | D9: Workers day
C10: 45824 | D10: Youth Day Holiday
C11: 45878 | D11: Womens Day
C12: 45924 | D12: Heritage Day
C13: 46007 | D13: Day of Reconciliation | H13: Manual dates
C14: 46016 | D14: Christmas Day
C15: 46017 | D15: Day of Goodwill
C16: 46006 | D16: Builders Break
C17: 46007 | D17: Builders Break
C18: 46008 | D18: Builders Break
C19: 46009 | D19: Builders Break
C20: 46010 | D20: Builders Break
C21: 46011 | D21: Builders Break
C22: 46012 | D22: Builders Break
C23: 46013 | D23: Builders Break
C24: 46014 | D24: Builders Break
C25: 46015 | D25: Builders Break
... C60: 46382 | D60: Day of Goodwill
