Workbook
Name Inverter_Capacity: #REF!
Name Inverter_Supplier: #REF!
Name Project_Size: BOQ!Projectsize
Name Project_Size: 'Certificate - Financial Close'!Projectsize
Name Project_Size: 'Certificate - Planning'!Projectsize
Name Project_Size: 'Change Register'!Projectsize
Name Project_Size: Compliance!Projectsize
Name Project_Size: 'Finance - Revenue'!Projectsize
Name Project_Size: 'Project Plan'!Projectsize
Name Project_Size: Projectsize
Name Projectsize: #REF!
Name Projectsize: #REF!
Name Projectsize: #REF!
Name Projectsize: #REF!
Name Projectsize: #REF!
Name Projectsize: #REF!
Name Projectsize: #REF!
Name Projectsize: 'Project Margins'!$K$5
Name Security_Serv: #REF!
Name Security_Serv: #REF!
Name SSS: #REF!
Name SSS: #REF!
Name USD_ZAR: #REF!

Sheet Sheet1
A1: PROJECT PLAN
A2: # | B2: Project Milestone | C2: Planned Start Date | D2: Duration (Work Days) | E2: Planned End Date | F2: Actual Start Date | H2: Actual End Date | J2: Comments | L2: =C3 -> 43831 | M2: =L2+3 -> 43834 | N2: =M2+7 -> 43841 | O2: =N2+7 -> 43848 | P2: =O2+7 -> 43855 | Q2: =P2+6 -> 43861 | R2: =Q2+1 -> 43862 | S2: =R2+7 -> 43869 | T2: =S2+7 -> 43876 | U2: =T2+7 -> 43883 | V2: =U2+6 -> 43889 | W2: =V2+7 -> 43896 | X2: =W2+7 -> 43903 | Y2: =X2+7 -> 43910 | Z2: =Y2+7 -> 43917 | AA2: =Z2+3 -> 43920 | AB2: =AA2+4 -> 43924 | AC2: =AB2+7 -> 43931 | AD2: =AC2+7 -> 43938 | AE2: =AD2+7 -> 43945 | AF2: =AE2+6 -> 43951 | AG2: =AF2+2 -> 43953 | AH2: =AG2+7 -> 43960 | AI2: =AH2+7 -> 43967 | AJ2: =AI2+7 -> 43974 | AK2: =AJ2+7 -> 43981 | AL2: =AK2+1 -> 43982 | AM2: =AL2+6 -> 43988 | AN2: =AM2+7 -> 43995 | AO2: =AN2+7 -> 44002 | AP2: =AO2+7 -> 44009 | AQ2: =AP2+3 -> 44012 | AR2: =AQ2+4 -> 44016 | AS2: =AR2+7 -> 44023 | AT2: =AS2+7 -> 44030 | AU2: =AT2+7 -> 44037 | AV2: =AU2+6 -> 44043 | AW2: =AV2+1 -> 44044 | AX2: =AW2+7 -> 44051 | AY2: =AX2+7 -> 44058 | AZ2: =AY2+7 -> 44065 | BA2: =AZ2+7 -> 44072 | BB2: =BA2+2 -> 44074 | BC2: =BB2+5 -> 44079 | BD2: =BC2+7 -> 44086 | BE2: =BD2+7 -> 44093 | BF2: =BE2+7 -> 44100 | BG2: =BF2+4 -> 44104
A3: 1 | B3: Contract Signature | C3: 43831 | D3: 1 | E3: 43832 | F3: 43831 | G3: 1 | H3: 43832 | L3: =IF(AND($F3<(L$2+7),$F3>L$2),1, IF(AND($H3<L$2+7,$H3>L$2),3, IF(AND($F3<=L$2, $H3>=L$2), 2, "" ))) -> 3 | M3: =IF(AND($F3<(M$2+7),$F3>M$2),1, IF(AND($H3<M$2+7,$H3>M$2),3, IF(AND($F3<=M$2, $H3>=M$2), 2, "" ))) | N3: =IF(AND($F3<(N$2+7),$F3>N$2),1, IF(AND($H3<N$2+7,$H3>N$2),3, IF(AND($F3<=N$2, $H3>=N$2), 2, "" ))) | O3: =IF(AND($F3<(O$2+7),$F3>O$2),1, IF(AND($H3<O$2+7,$H3>O$2),3, IF(AND($F3<=O$2, $H3>=O$2), 2, "" ))) | P3: =IF(AND($F3<(P$2+7),$F3>P$2),1, IF(AND($H3<P$2+7,$H3>P$2),3, IF(AND($F3<=P$2, $H3>=P$2), 2, "" ))) | Q3: =IF(AND($F3<(Q$2+7),$F3>Q$2),1, IF(AND($H3<Q$2+7,$H3>Q$2),3, IF(AND($F3<=Q$2, $H3>=Q$2), 2, "" ))) | R3: =IF(AND($F3<(R$2+7),$F3>R$2),1, IF(AND($H3<R$2+7,$H3>R$2),3, IF(AND($F3<=R$2, $H3>=R$2), 2, "" ))) | S3: =IF(AND($F3<(S$2+7),$F3>S$2),1, IF(AND($H3<S$2+7,$H3>S$2),3, IF(AND($F3<=S$2, $H3>=S$2), 2, "" ))) | ... AQ3: =IF(AND($F3<(AQ$2+7),$F3>AQ$2),1, IF(AND($H3<AQ$2+7,$H3>AQ$2),3, IF(AND($F3<=AQ$2, $H3>=AQ$2), 2, "" )))
A4: A | B4: PAYMENT MILESTONE 1: DEPOSIT | C4: 43832 | D4: 1 | E4: 43833 | F4: 43832 | G4: 1 | H4: 43833 | L4: =IF(AND($F4<(L$2+7),$F4>L$2),1, IF(AND($H4<L$2+7,$H4>L$2),3, IF(AND($F4<=L$2, $H4>=L$2), 2, "" ))) -> 1 | M4: =IF(AND($F4<(M$2+7),$F4>M$2),1, IF(AND($H4<M$2+7,$H4>M$2),3, IF(AND($F4<=M$2, $H4>=M$2), 2, "" ))) | N4: =IF(AND($F4<(N$2+7),$F4>N$2),1, IF(AND($H4<N$2+7,$H4>N$2),3, IF(AND($F4<=N$2, $H4>=N$2), 2, "" ))) | O4: =IF(AND($F4<(O$2+7),$F4>O$2),1, IF(AND($H4<O$2+7,$H4>O$2),3, IF(AND($F4<=O$2, $H4>=O$2), 2, "" ))) | P4: =IF(AND($F4<(P$2+7),$F4>P$2),1, IF(AND($H4<P$2+7,$H4>P$2),3, IF(AND($F4<=P$2, $H4>=P$2), 2, "" ))) | Q4: =IF(AND($F4<(Q$2+7),$F4>Q$2),1, IF(AND($H4<Q$2+7,$H4>Q$2),3, IF(AND($F4<=Q$2, $H4>=Q$2), 2, "" ))) | R4: =IF(AND($F4<(R$2+7),$F4>R$2),1, IF(AND($H4<R$2+7,$H4>R$2),3, IF(AND($F4<=R$2, $H4>=R$2), 2, "" ))) | S4: =IF(AND($F4<(S$2+7),$F4>S$2),1, IF(AND($H4<S$2+7,$H4>S$2),3, IF(AND($F4<=S$2, $H4>=S$2), 2, "" ))) | ... AQ4: =IF(AND($F4<(AQ$2+7),$F4>AQ$2),1, IF(AND($H4<AQ$2+7,$H4>AQ$2),3, IF(AND($F4<=AQ$2, $H4>=AQ$2), 2, "" )))
A5: 2 | B5: Structural and Electrical Due Diligences | C5: 43833 | D5: 5 | E5: 43840 | F5: 43833 | G5: 5 | H5: 43840 | L5: =IF(AND($F5<(L$2+7),$F5>L$2),1, IF(AND($H5<L$2+7,$H5>L$2),3, IF(AND($F5<=L$2, $H5>=L$2), 2, "" ))) -> 1 | M5: =IF(AND($F5<(M$2+7),$F5>M$2),1, IF(AND($H5<M$2+7,$H5>M$2),3, IF(AND($F5<=M$2, $H5>=M$2), 2, "" ))) -> 3 | N5: =IF(AND($F5<(N$2+7),$F5>N$2),1, IF(AND($H5<N$2+7,$H5>N$2),3, IF(AND($F5<=N$2, $H5>=N$2), 2, "" ))) | O5: =IF(AND($F5<(O$2+7),$F5>O$2),1, IF(AND($H5<O$2+7,$H5>O$2),3, IF(AND($F5<=O$2, $H5>=O$2), 2, "" ))) | P5: =IF(AND($F5<(P$2+7),$F5>P$2),1, IF(AND($H5<P$2+7,$H5>P$2),3, IF(AND($F5<=P$2, $H5>=P$2), 2, "" ))) | Q5: =IF(AND($F5<(Q$2+7),$F5>Q$2),1, IF(AND($H5<Q$2+7,$H5>Q$2),3, IF(AND($F5<=Q$2, $H5>=Q$2), 2, "" ))) | R5: =IF(AND($F5<(R$2+7),$F5>R$2),1, IF(AND($H5<R$2+7,$H5>R$2),3, IF(AND($F5<=R$2, $H5>=R$2), 2, "" ))) | S5: =IF(AND($F5<(S$2+7),$F5>S$2),1, IF(AND($H5<S$2+7,$H5>S$2),3, IF(AND($F5<=S$2, $H5>=S$2), 2, "" ))) | ... AQ5: =IF(AND($F5<(AQ$2+7),$F5>AQ$2),1, IF(AND($H5<AQ$2+7,$H5>AQ$2),3, IF(AND($F5<=AQ$2, $H5>=AQ$2), 2, "" )))
A6: 3 | B6: Design Confirmation | C6: 43841 | D6: 2 | E6: 43844 | F6: 43841 | G6: 2 | H6: 43844 | L6: =IF(AND($F6<(L$2+7),$F6>L$2),1, IF(AND($H6<L$2+7,$H6>L$2),3, IF(AND($F6<=L$2, $H6>=L$2), 2, "" ))) | M6: =IF(AND($F6<(M$2+7),$F6>M$2),1, IF(AND($H6<M$2+7,$H6>M$2),3, IF(AND($F6<=M$2, $H6>=M$2), 2, "" ))) | N6: =IF(AND($F6<(N$2+7),$F6>N$2),1, IF(AND($H6<N$2+7,$H6>N$2),3, IF(AND($F6<=N$2, $H6>=N$2), 2, "" ))) -> 3 | O6: =IF(AND($F6<(O$2+7),$F6>O$2),1, IF(AND($H6<O$2+7,$H6>O$2),3, IF(AND($F6<=O$2, $H6>=O$2), 2, "" ))) | P6: =IF(AND($F6<(P$2+7),$F6>P$2),1, IF(AND($H6<P$2+7,$H6>P$2),3, IF(AND($F6<=P$2, $H6>=P$2), 2, "" ))) | Q6: =IF(AND($F6<(Q$2+7),$F6>Q$2),1, IF(AND($H6<Q$2+7,$H6>Q$2),3, IF(AND($F6<=Q$2, $H6>=Q$2), 2, "" ))) | R6: =IF(AND($F6<(R$2+7),$F6>R$2),1, IF(AND($H6<R$2+7,$H6>R$2),3, IF(AND($F6<=R$2, $H6>=R$2), 2, "" ))) | S6: =IF(AND($F6<(S$2+7),$F6>S$2),1, IF(AND($H6<S$2+7,$H6>S$2),3, IF(AND($F6<=S$2, $H6>=S$2), 2, "" ))) | ... AQ6: =IF(AND($F6<(AQ$2+7),$F6>AQ$2),1, IF(AND($H6<AQ$2+7,$H6>AQ$2),3, IF(AND($F6<=AQ$2, $H6>=AQ$2), 2, "" )))
A7: 4 | B7: Equipment Procurement | C7: 43833 | E7: 43949 | F7: 43833 | H7: 43949 | L7: =IF(AND($F7<(L$2+7),$F7>L$2),1, IF(AND($H7<L$2+7,$H7>L$2),3, IF(AND($F7<=L$2, $H7>=L$2), 2, "" ))) -> 1 | M7: =IF(AND($F7<(M$2+7),$F7>M$2),1, IF(AND($H7<M$2+7,$H7>M$2),3, IF(AND($F7<=M$2, $H7>=M$2), 2, "" ))) -> 2 | N7: =IF(AND($F7<(N$2+7),$F7>N$2),1, IF(AND($H7<N$2+7,$H7>N$2),3, IF(AND($F7<=N$2, $H7>=N$2), 2, "" ))) -> 2 | O7: =IF(AND($F7<(O$2+7),$F7>O$2),1, IF(AND($H7<O$2+7,$H7>O$2),3, IF(AND($F7<=O$2, $H7>=O$2), 2, "" ))) -> 2 | P7: =IF(AND($F7<(P$2+7),$F7>P$2),1, IF(AND($H7<P$2+7,$H7>P$2),3, IF(AND($F7<=P$2, $H7>=P$2), 2, "" ))) -> 2 | Q7: =IF(AND($F7<(Q$2+7),$F7>Q$2),1, IF(AND($H7<Q$2+7,$H7>Q$2),3, IF(AND($F7<=Q$2, $H7>=Q$2), 2, "" ))) -> 2 | R7: =IF(AND($F7<(R$2+7),$F7>R$2),1, IF(AND($H7<R$2+7,$H7>R$2),3, IF(AND($F7<=R$2, $H7>=R$2), 2, "" ))) -> 2 | S7: =IF(AND($F7<(S$2+7),$F7>S$2),1, IF(AND($H7<S$2+7,$H7>S$2),3, IF(AND($F7<=S$2, $H7>=S$2), 2, "" ))) -> 2 | ... AQ7: =IF(AND($F7<(AQ$2+7),$F7>AQ$2),1, IF(AND($H7<AQ$2+7,$H7>AQ$2),3, IF(AND($F7<=AQ$2, $H7>=AQ$2), 2, "" )))
B8: Panel Procurement | C8: 43833 | D8: 5 | E8: 43840 | F8: 43833 | G8: 5 | H8: 43840 | L8: =IF(AND($F8<(L$2+7),$F8>L$2),1, IF(AND($H8<L$2+7,$H8>L$2),3, IF(AND($F8<=L$2, $H8>=L$2), 2, "" ))) -> 1 | M8: =IF(AND($F8<(M$2+7),$F8>M$2),1, IF(AND($H8<M$2+7,$H8>M$2),3, IF(AND($F8<=M$2, $H8>=M$2), 2, "" ))) -> 3 | N8: =IF(AND($F8<(N$2+7),$F8>N$2),1, IF(AND($H8<N$2+7,$H8>N$2),3, IF(AND($F8<=N$2, $H8>=N$2), 2, "" ))) | O8: =IF(AND($F8<(O$2+7),$F8>O$2),1, IF(AND($H8<O$2+7,$H8>O$2),3, IF(AND($F8<=O$2, $H8>=O$2), 2, "" ))) | P8: =IF(AND($F8<(P$2+7),$F8>P$2),1, IF(AND($H8<P$2+7,$H8>P$2),3, IF(AND($F8<=P$2, $H8>=P$2), 2, "" ))) | Q8: =IF(AND($F8<(Q$2+7),$F8>Q$2),1, IF(AND($H8<Q$2+7,$H8>Q$2),3, IF(AND($F8<=Q$2, $H8>=Q$2), 2, "" ))) | R8: =IF(AND($F8<(R$2+7),$F8>R$2),1, IF(AND($H8<R$2+7,$H8>R$2),3, IF(AND($F8<=R$2, $H8>=R$2), 2, "" ))) | S8: =IF(AND($F8<(S$2+7),$F8>S$2),1, IF(AND($H8<S$2+7,$H8>S$2),3, IF(AND($F8<=S$2, $H8>=S$2), 2, "" ))) | ... AQ8: =IF(AND($F8<(AQ$2+7),$F8>AQ$2),1, IF(AND($H8<AQ$2+7,$H8>AQ$2),3, IF(AND($F8<=AQ$2, $H8>=AQ$2), 2, "" )))
B9: Inverter Procurement | C9: 43941 | D9: 5 | E9: 43949 | F9: 43941 | G9: 5 | H9: 43949 | L9: =IF(AND($F9<(L$2+7),$F9>L$2),1, IF(AND($H9<L$2+7,$H9>L$2),3, IF(AND($F9<=L$2, $H9>=L$2), 2, "" ))) | M9: =IF(AND($F9<(M$2+7),$F9>M$2),1, IF(AND($H9<M$2+7,$H9>M$2),3, IF(AND($F9<=M$2, $H9>=M$2), 2, "" ))) | N9: =IF(AND($F9<(N$2+7),$F9>N$2),1, IF(AND($H9<N$2+7,$H9>N$2),3, IF(AND($F9<=N$2, $H9>=N$2), 2, "" ))) | O9: =IF(AND($F9<(O$2+7),$F9>O$2),1, IF(AND($H9<O$2+7,$H9>O$2),3, IF(AND($F9<=O$2, $H9>=O$2), 2, "" ))) | P9: =IF(AND($F9<(P$2+7),$F9>P$2),1, IF(AND($H9<P$2+7,$H9>P$2),3, IF(AND($F9<=P$2, $H9>=P$2), 2, "" ))) | Q9: =IF(AND($F9<(Q$2+7),$F9>Q$2),1, IF(AND($H9<Q$2+7,$H9>Q$2),3, IF(AND($F9<=Q$2, $H9>=Q$2), 2, "" ))) | R9: =IF(AND($F9<(R$2+7),$F9>R$2),1, IF(AND($H9<R$2+7,$H9>R$2),3, IF(AND($F9<=R$2, $H9>=R$2), 2, "" ))) | S9: =IF(AND($F9<(S$2+7),$F9>S$2),1, IF(AND($H9<S$2+7,$H9>S$2),3, IF(AND($F9<=S$2, $H9>=S$2), 2, "" ))) | ... AQ9: =IF(AND($F9<(AQ$2+7),$F9>AQ$2),1, IF(AND($H9<AQ$2+7,$H9>AQ$2),3, IF(AND($F9<=AQ$2, $H9>=AQ$2), 2, "" )))
B10: Mounting Structure Procurement | C10: 43941 | D10: 5 | E10: 43949 | F10: 43941 | G10: 5 | H10: 43949 | L10: =IF(AND($F10<(L$2+7),$F10>L$2),1, IF(AND($H10<L$2+7,$H10>L$2),3, IF(AND($F10<=L$2, $H10>=L$2), 2, "" ))) | M10: =IF(AND($F10<(M$2+7),$F10>M$2),1, IF(AND($H10<M$2+7,$H10>M$2),3, IF(AND($F10<=M$2, $H10>=M$2), 2, "" ))) | N10: =IF(AND($F10<(N$2+7),$F10>N$2),1, IF(AND($H10<N$2+7,$H10>N$2),3, IF(AND($F10<=N$2, $H10>=N$2), 2, "" ))) | O10: =IF(AND($F10<(O$2+7),$F10>O$2),1, IF(AND($H10<O$2+7,$H10>O$2),3, IF(AND($F10<=O$2, $H10>=O$2), 2, "" ))) | P10: =IF(AND($F10<(P$2+7),$F10>P$2),1, IF(AND($H10<P$2+7,$H10>P$2),3, IF(AND($F10<=P$2, $H10>=P$2), 2, "" ))) | Q10: =IF(AND($F10<(Q$2+7),$F10>Q$2),1, IF(AND($H10<Q$2+7,$H10>Q$2),3, IF(AND($F10<=Q$2, $H10>=Q$2), 2, "" ))) | R10: =IF(AND($F10<(R$2+7),$F10>R$2),1, IF(AND($H10<R$2+7,$H10>R$2),3, IF(AND($F10<=R$2, $H10>=R$2), 2, "" ))) | S10: =IF(AND($F10<(S$2+7),$F10>S$2),1, IF(AND($H10<S$2+7,$H10>S$2),3, IF(AND($F10<=S$2, $H10>=S$2), 2, "" ))) | ... AQ10: =IF(AND($F10<(AQ$2+7),$F10>AQ$2),1, IF(AND($H10<AQ$2+7,$H10>AQ$2),3, IF(AND($F10<=AQ$2, $H10>=AQ$2), 2, "" )))
B11: BOS Procurement | C11: 43941 | D11: 5 | E11: 43949 | F11: 43941 | G11: 5 | H11: 43949 | L11: =IF(AND($F11<(L$2+7),$F11>L$2),1, IF(AND($H11<L$2+7,$H11>L$2),3, IF(AND($F11<=L$2, $H11>=L$2), 2, "" ))) | M11: =IF(AND($F11<(M$2+7),$F11>M$2),1, IF(AND($H11<M$2+7,$H11>M$2),3, IF(AND($F11<=M$2, $H11>=M$2), 2, "" ))) | N11: =IF(AND($F11<(N$2+7),$F11>N$2),1, IF(AND($H11<N$2+7,$H11>N$2),3, IF(AND($F11<=N$2, $H11>=N$2), 2, "" ))) | O11: =IF(AND($F11<(O$2+7),$F11>O$2),1, IF(AND($H11<O$2+7,$H11>O$2),3, IF(AND($F11<=O$2, $H11>=O$2), 2, "" ))) | P11: =IF(AND($F11<(P$2+7),$F11>P$2),1, IF(AND($H11<P$2+7,$H11>P$2),3, IF(AND($F11<=P$2, $H11>=P$2), 2, "" ))) | Q11: =IF(AND($F11<(Q$2+7),$F11>Q$2),1, IF(AND($H11<Q$2+7,$H11>Q$2),3, IF(AND($F11<=Q$2, $H11>=Q$2), 2, "" ))) | R11: =IF(AND($F11<(R$2+7),$F11>R$2),1, IF(AND($H11<R$2+7,$H11>R$2),3, IF(AND($F11<=R$2, $H11>=R$2), 2, "" ))) | S11: =IF(AND($F11<(S$2+7),$F11>S$2),1, IF(AND($H11<S$2+7,$H11>S$2),3, IF(AND($F11<=S$2, $H11>=S$2), 2, "" ))) | ... AQ11: =IF(AND($F11<(AQ$2+7),$F11>AQ$2),1, IF(AND($H11<AQ$2+7,$H11>AQ$2),3, IF(AND($F11<=AQ$2, $H11>=AQ$2), 2, "" )))
A12: 5 | B12: Internal Project Kick off | C12: 43936 | D12: 5 | E12: 43943 | F12: 43936 | G12: 5 | H12: 43943
A13: 6 | B13: Client Project Kick-off | C13: 43963 | D13: 5 | E13: 43970 | F13: 43963 | G13: 5 | H13: 43970 | L13: =IF(AND($F13<(L$2+7),$F13>L$2),1, IF(AND($H13<L$2+7,$H13>L$2),3, IF(AND($F13<=L$2, $H13>=L$2), 2, "" ))) | M13: =IF(AND($F13<(M$2+7),$F13>M$2),1, IF(AND($H13<M$2+7,$H13>M$2),3, IF(AND($F13<=M$2, $H13>=M$2), 2, "" ))) | N13: =IF(AND($F13<(N$2+7),$F13>N$2),1, IF(AND($H13<N$2+7,$H13>N$2),3, IF(AND($F13<=N$2, $H13>=N$2), 2, "" ))) | O13: =IF(AND($F13<(O$2+7),$F13>O$2),1, IF(AND($H13<O$2+7,$H13>O$2),3, IF(AND($F13<=O$2, $H13>=O$2), 2, "" ))) | P13: =IF(AND($F13<(P$2+7),$F13>P$2),1, IF(AND($H13<P$2+7,$H13>P$2),3, IF(AND($F13<=P$2, $H13>=P$2), 2, "" ))) | Q13: =IF(AND($F13<(Q$2+7),$F13>Q$2),1, IF(AND($H13<Q$2+7,$H13>Q$2),3, IF(AND($F13<=Q$2, $H13>=Q$2), 2, "" ))) | R13: =IF(AND($F13<(R$2+7),$F13>R$2),1, IF(AND($H13<R$2+7,$H13>R$2),3, IF(AND($F13<=R$2, $H13>=R$2), 2, "" ))) | S13: =IF(AND($F13<(S$2+7),$F13>S$2),1, IF(AND($H13<S$2+7,$H13>S$2),3, IF(AND($F13<=S$2, $H13>=S$2), 2, "" ))) | ... AQ13: =IF(AND($F13<(AQ$2+7),$F13>AQ$2),1, IF(AND($H13<AQ$2+7,$H13>AQ$2),3, IF(AND($F13<=AQ$2, $H13>=AQ$2), 2, "" )))
A14: 7 | B14: Equipment Delivery | C14: 43983 | D14: 9 | E14: 43994 | F14: 43983 | G14: 9 | H14: 43994 | L14: =IF(AND($F14<(L$2+7),$F14>L$2),1, IF(AND($H14<L$2+7,$H14>L$2),3, IF(AND($F14<=L$2, $H14>=L$2), 2, "" ))) | M14: =IF(AND($F14<(M$2+7),$F14>M$2),1, IF(AND($H14<M$2+7,$H14>M$2),3, IF(AND($F14<=M$2, $H14>=M$2), 2, "" ))) | N14: =IF(AND($F14<(N$2+7),$F14>N$2),1, IF(AND($H14<N$2+7,$H14>N$2),3, IF(AND($F14<=N$2, $H14>=N$2), 2, "" ))) | O14: =IF(AND($F14<(O$2+7),$F14>O$2),1, IF(AND($H14<O$2+7,$H14>O$2),3, IF(AND($F14<=O$2, $H14>=O$2), 2, "" ))) | P14: =IF(AND($F14<(P$2+7),$F14>P$2),1, IF(AND($H14<P$2+7,$H14>P$2),3, IF(AND($F14<=P$2, $H14>=P$2), 2, "" ))) | Q14: =IF(AND($F14<(Q$2+7),$F14>Q$2),1, IF(AND($H14<Q$2+7,$H14>Q$2),3, IF(AND($F14<=Q$2, $H14>=Q$2), 2, "" ))) | R14: =IF(AND($F14<(R$2+7),$F14>R$2),1, IF(AND($H14<R$2+7,$H14>R$2),3, IF(AND($F14<=R$2, $H14>=R$2), 2, "" ))) | S14: =IF(AND($F14<(S$2+7),$F14>S$2),1, IF(AND($H14<S$2+7,$H14>S$2),3, IF(AND($F14<=S$2, $H14>=S$2), 2, "" ))) | ... AQ14: =IF(AND($F14<(AQ$2+7),$F14>AQ$2),1, IF(AND($H14<AQ$2+7,$H14>AQ$2),3, IF(AND($F14<=AQ$2, $H14>=AQ$2), 2, "" )))
B15: Mounting Structure Delivery | C15: 43983 | D15: 2 | E15: 43985 | F15: 43983 | G15: 2 | H15: 43985
B16: Panel Delivery | C16: 43990 | D16: 2 | E16: 43992 | F16: 43990 | G16: 2 | H16: 43992 | L16: =IF(AND($F16<(L$2+7),$F16>L$2),1, IF(AND($H16<L$2+7,$H16>L$2),3, IF(AND($F16<=L$2, $H16>=L$2), 2, "" ))) | M16: =IF(AND($F16<(M$2+7),$F16>M$2),1, IF(AND($H16<M$2+7,$H16>M$2),3, IF(AND($F16<=M$2, $H16>=M$2), 2, "" ))) | N16: =IF(AND($F16<(N$2+7),$F16>N$2),1, IF(AND($H16<N$2+7,$H16>N$2),3, IF(AND($F16<=N$2, $H16>=N$2), 2, "" ))) | O16: =IF(AND($F16<(O$2+7),$F16>O$2),1, IF(AND($H16<O$2+7,$H16>O$2),3, IF(AND($F16<=O$2, $H16>=O$2), 2, "" ))) | P16: =IF(AND($F16<(P$2+7),$F16>P$2),1, IF(AND($H16<P$2+7,$H16>P$2),3, IF(AND($F16<=P$2, $H16>=P$2), 2, "" ))) | Q16: =IF(AND($F16<(Q$2+7),$F16>Q$2),1, IF(AND($H16<Q$2+7,$H16>Q$2),3, IF(AND($F16<=Q$2, $H16>=Q$2), 2, "" ))) | R16: =IF(AND($F16<(R$2+7),$F16>R$2),1, IF(AND($H16<R$2+7,$H16>R$2),3, IF(AND($F16<=R$2, $H16>=R$2), 2, "" ))) | S16: =IF(AND($F16<(S$2+7),$F16>S$2),1, IF(AND($H16<S$2+7,$H16>S$2),3, IF(AND($F16<=S$2, $H16>=S$2), 2, "" ))) | ... AQ16: =IF(AND($F16<(AQ$2+7),$F16>AQ$2),1, IF(AND($H16<AQ$2+7,$H16>AQ$2),3, IF(AND($F16<=AQ$2, $H16>=AQ$2), 2, "" )))
B17: Generator Delivery | C17: 43983 | D17: 2 | E17: 43985 | F17: 43983 | G17: 2 | H17: 43985
A18: B | B18: PAYMENT MILESTONE 2: DELIVERY OF PV PANELS | C18: 43992 | D18: 2 | E18: 43994 | F18: 43992 | G18: 2 | H18: 43994
B19: Inverter Delivery | C19: 43983 | D19: 2 | E19: 43985 | F19: 43983 | G19: 2 | H19: 43985 | L19: =IF(AND($F19<(L$2+7),$F19>L$2),1, IF(AND($H19<L$2+7,$H19>L$2),3, IF(AND($F19<=L$2, $H19>=L$2), 2, "" ))) | M19: =IF(AND($F19<(M$2+7),$F19>M$2),1, IF(AND($H19<M$2+7,$H19>M$2),3, IF(AND($F19<=M$2, $H19>=M$2), 2, "" ))) | N19: =IF(AND($F19<(N$2+7),$F19>N$2),1, IF(AND($H19<N$2+7,$H19>N$2),3, IF(AND($F19<=N$2, $H19>=N$2), 2, "" ))) | O19: =IF(AND($F19<(O$2+7),$F19>O$2),1, IF(AND($H19<O$2+7,$H19>O$2),3, IF(AND($F19<=O$2, $H19>=O$2), 2, "" ))) | P19: =IF(AND($F19<(P$2+7),$F19>P$2),1, IF(AND($H19<P$2+7,$H19>P$2),3, IF(AND($F19<=P$2, $H19>=P$2), 2, "" ))) | Q19: =IF(AND($F19<(Q$2+7),$F19>Q$2),1, IF(AND($H19<Q$2+7,$H19>Q$2),3, IF(AND($F19<=Q$2, $H19>=Q$2), 2, "" ))) | R19: =IF(AND($F19<(R$2+7),$F19>R$2),1, IF(AND($H19<R$2+7,$H19>R$2),3, IF(AND($F19<=R$2, $H19>=R$2), 2, "" ))) | S19: =IF(AND($F19<(S$2+7),$F19>S$2),1, IF(AND($H19<S$2+7,$H19>S$2),3, IF(AND($F19<=S$2, $H19>=S$2), 2, "" ))) | ... AQ19: =IF(AND($F19<(AQ$2+7),$F19>AQ$2),1, IF(AND($H19<AQ$2+7,$H19>AQ$2),3, IF(AND($F19<=AQ$2, $H19>=AQ$2), 2, "" )))
B20: BOS Delivery | C20: 43983 | D20: 1 | E20: 43984 | F20: 43983 | G20: 1 | H20: 43984 | L20: =IF(AND($F20<(L$2+7),$F20>L$2),1, IF(AND($H20<L$2+7,$H20>L$2),3, IF(AND($F20<=L$2, $H20>=L$2), 2, "" ))) | M20: =IF(AND($F20<(M$2+7),$F20>M$2),1, IF(AND($H20<M$2+7,$H20>M$2),3, IF(AND($F20<=M$2, $H20>=M$2), 2, "" ))) | N20: =IF(AND($F20<(N$2+7),$F20>N$2),1, IF(AND($H20<N$2+7,$H20>N$2),3, IF(AND($F20<=N$2, $H20>=N$2), 2, "" ))) | O20: =IF(AND($F20<(O$2+7),$F20>O$2),1, IF(AND($H20<O$2+7,$H20>O$2),3, IF(AND($F20<=O$2, $H20>=O$2), 2, "" ))) | P20: =IF(AND($F20<(P$2+7),$F20>P$2),1, IF(AND($H20<P$2+7,$H20>P$2),3, IF(AND($F20<=P$2, $H20>=P$2), 2, "" ))) | Q20: =IF(AND($F20<(Q$2+7),$F20>Q$2),1, IF(AND($H20<Q$2+7,$H20>Q$2),3, IF(AND($F20<=Q$2, $H20>=Q$2), 2, "" ))) | R20: =IF(AND($F20<(R$2+7),$F20>R$2),1, IF(AND($H20<R$2+7,$H20>R$2),3, IF(AND($F20<=R$2, $H20>=R$2), 2, "" ))) | S20: =IF(AND($F20<(S$2+7),$F20>S$2),1, IF(AND($H20<S$2+7,$H20>S$2),3, IF(AND($F20<=S$2, $H20>=S$2), 2, "" ))) | ... AQ20: =IF(AND($F20<(AQ$2+7),$F20>AQ$2),1, IF(AND($H20<AQ$2+7,$H20>AQ$2),3, IF(AND($F20<=AQ$2, $H20>=AQ$2), 2, "" )))
A21: C | B21: PAYMENT MILESTONE 3: DELIVERY OF INVERTERS AND BOS | C21: 43985 | D21: 2 | E21: 43987 | F21: 43985 | G21: 2 | H21: 43987
A22: 8 | B22: Installation | C22: 43990 | D22: 22 | E22: 44012 | F22: 43990 | G22: 22 | H22: 44012 | L22: =IF(AND($F22<(L$2+7),$F22>L$2),1, IF(AND($H22<L$2+7,$H22>L$2),3, IF(AND($F22<=L$2, $H22>=L$2), 2, "" ))) | M22: =IF(AND($F22<(M$2+7),$F22>M$2),1, IF(AND($H22<M$2+7,$H22>M$2),3, IF(AND($F22<=M$2, $H22>=M$2), 2, "" ))) | N22: =IF(AND($F22<(N$2+7),$F22>N$2),1, IF(AND($H22<N$2+7,$H22>N$2),3, IF(AND($F22<=N$2, $H22>=N$2), 2, "" ))) | O22: =IF(AND($F22<(O$2+7),$F22>O$2),1, IF(AND($H22<O$2+7,$H22>O$2),3, IF(AND($F22<=O$2, $H22>=O$2), 2, "" ))) | P22: =IF(AND($F22<(P$2+7),$F22>P$2),1, IF(AND($H22<P$2+7,$H22>P$2),3, IF(AND($F22<=P$2, $H22>=P$2), 2, "" ))) | Q22: =IF(AND($F22<(Q$2+7),$F22>Q$2),1, IF(AND($H22<Q$2+7,$H22>Q$2),3, IF(AND($F22<=Q$2, $H22>=Q$2), 2, "" ))) | R22: =IF(AND($F22<(R$2+7),$F22>R$2),1, IF(AND($H22<R$2+7,$H22>R$2),3, IF(AND($F22<=R$2, $H22>=R$2), 2, "" ))) | S22: =IF(AND($F22<(S$2+7),$F22>S$2),1, IF(AND($H22<S$2+7,$H22>S$2),3, IF(AND($F22<=S$2, $H22>=S$2), 2, "" ))) | ... AQ22: =IF(AND($F22<(AQ$2+7),$F22>AQ$2),1, IF(AND($H22<AQ$2+7,$H22>AQ$2),3, IF(AND($F22<=AQ$2, $H22>=AQ$2), 2, "" ))) -> 2
B23: Site Establishment | C23: 43990 | D23: 1 | E23: 43991 | F23: 43990 | G23: 1 | H23: 43991 | J23: Installation placed on hold due to Covid-19 case | L23: =IF(AND($F23<(L$2+7),$F23>L$2),1, IF(AND($H23<L$2+7,$H23>L$2),3, IF(AND($F23<=L$2, $H23>=L$2), 2, "" ))) | M23: =IF(AND($F23<(M$2+7),$F23>M$2),1, IF(AND($H23<M$2+7,$H23>M$2),3, IF(AND($F23<=M$2, $H23>=M$2), 2, "" ))) | N23: =IF(AND($F23<(N$2+7),$F23>N$2),1, IF(AND($H23<N$2+7,$H23>N$2),3, IF(AND($F23<=N$2, $H23>=N$2), 2, "" ))) | O23: =IF(AND($F23<(O$2+7),$F23>O$2),1, IF(AND($H23<O$2+7,$H23>O$2),3, IF(AND($F23<=O$2, $H23>=O$2), 2, "" ))) | P23: =IF(AND($F23<(P$2+7),$F23>P$2),1, IF(AND($H23<P$2+7,$H23>P$2),3, IF(AND($F23<=P$2, $H23>=P$2), 2, "" ))) | Q23: =IF(AND($F23<(Q$2+7),$F23>Q$2),1, IF(AND($H23<Q$2+7,$H23>Q$2),3, IF(AND($F23<=Q$2, $H23>=Q$2), 2, "" ))) | R23: =IF(AND($F23<(R$2+7),$F23>R$2),1, IF(AND($H23<R$2+7,$H23>R$2),3, IF(AND($F23<=R$2, $H23>=R$2), 2, "" ))) | S23: =IF(AND($F23<(S$2+7),$F23>S$2),1, IF(AND($H23<S$2+7,$H23>S$2),3, IF(AND($F23<=S$2, $H23>=S$2), 2, "" ))) | ... AQ23: =IF(AND($F23<(AQ$2+7),$F23>AQ$2),1, IF(AND($H23<AQ$2+7,$H23>AQ$2),3, IF(AND($F23<=AQ$2, $H23>=AQ$2), 2, "" )))
A24: 9 | B24: DC Works | C24: 43991 | D24: 16 | E24: 44012 | F24: 43991 | G24: 16 | H24: 44012 | L24: =IF(AND($F24<(L$2+7),$F24>L$2),1, IF(AND($H24<L$2+7,$H24>L$2),3, IF(AND($F24<=L$2, $H24>=L$2), 2, "" ))) | M24: =IF(AND($F24<(M$2+7),$F24>M$2),1, IF(AND($H24<M$2+7,$H24>M$2),3, IF(AND($F24<=M$2, $H24>=M$2), 2, "" ))) | N24: =IF(AND($F24<(N$2+7),$F24>N$2),1, IF(AND($H24<N$2+7,$H24>N$2),3, IF(AND($F24<=N$2, $H24>=N$2), 2, "" ))) | O24: =IF(AND($F24<(O$2+7),$F24>O$2),1, IF(AND($H24<O$2+7,$H24>O$2),3, IF(AND($F24<=O$2, $H24>=O$2), 2, "" ))) | P24: =IF(AND($F24<(P$2+7),$F24>P$2),1, IF(AND($H24<P$2+7,$H24>P$2),3, IF(AND($F24<=P$2, $H24>=P$2), 2, "" ))) | Q24: =IF(AND($F24<(Q$2+7),$F24>Q$2),1, IF(AND($H24<Q$2+7,$H24>Q$2),3, IF(AND($F24<=Q$2, $H24>=Q$2), 2, "" ))) | R24: =IF(AND($F24<(R$2+7),$F24>R$2),1, IF(AND($H24<R$2+7,$H24>R$2),3, IF(AND($F24<=R$2, $H24>=R$2), 2, "" ))) | S24: =IF(AND($F24<(S$2+7),$F24>S$2),1, IF(AND($H24<S$2+7,$H24>S$2),3, IF(AND($F24<=S$2, $H24>=S$2), 2, "" ))) | ... AQ24: =IF(AND($F24<(AQ$2+7),$F24>AQ$2),1, IF(AND($H24<AQ$2+7,$H24>AQ$2),3, IF(AND($F24<=AQ$2, $H24>=AQ$2), 2, "" ))) -> 2
B25: Mounting structure Installation | C25: 43991 | D25: 4 | E25: 43997 | F25: 43991 | G25: 4 | H25: 43997 | L25: =IF(AND($F25<(L$2+7),$F25>L$2),1, IF(AND($H25<L$2+7,$H25>L$2),3, IF(AND($F25<=L$2, $H25>=L$2), 2, "" ))) | M25: =IF(AND($F25<(M$2+7),$F25>M$2),1, IF(AND($H25<M$2+7,$H25>M$2),3, IF(AND($F25<=M$2, $H25>=M$2), 2, "" ))) | N25: =IF(AND($F25<(N$2+7),$F25>N$2),1, IF(AND($H25<N$2+7,$H25>N$2),3, IF(AND($F25<=N$2, $H25>=N$2), 2, "" ))) | O25: =IF(AND($F25<(O$2+7),$F25>O$2),1, IF(AND($H25<O$2+7,$H25>O$2),3, IF(AND($F25<=O$2, $H25>=O$2), 2, "" ))) | P25: =IF(AND($F25<(P$2+7),$F25>P$2),1, IF(AND($H25<P$2+7,$H25>P$2),3, IF(AND($F25<=P$2, $H25>=P$2), 2, "" ))) | Q25: =IF(AND($F25<(Q$2+7),$F25>Q$2),1, IF(AND($H25<Q$2+7,$H25>Q$2),3, IF(AND($F25<=Q$2, $H25>=Q$2), 2, "" ))) | R25: =IF(AND($F25<(R$2+7),$F25>R$2),1, IF(AND($H25<R$2+7,$H25>R$2),3, IF(AND($F25<=R$2, $H25>=R$2), 2, "" ))) | S25: =IF(AND($F25<(S$2+7),$F25>S$2),1, IF(AND($H25<S$2+7,$H25>S$2),3, IF(AND($F25<=S$2, $H25>=S$2), 2, "" ))) | ... AQ25: =IF(AND($F25<(AQ$2+7),$F25>AQ$2),1, IF(AND($H25<AQ$2+7,$H25>AQ$2),3, IF(AND($F25<=AQ$2, $H25>=AQ$2), 2, "" )))
B26: Cable tray Installation | C26: 43997 | D26: 3 | E26: 44004 | F26: 43997 | G26: 3 | H26: 44004 | L26: =IF(AND($F26<(L$2+7),$F26>L$2),1, IF(AND($H26<L$2+7,$H26>L$2),3, IF(AND($F26<=L$2, $H26>=L$2), 2, "" ))) | M26: =IF(AND($F26<(M$2+7),$F26>M$2),1, IF(AND($H26<M$2+7,$H26>M$2),3, IF(AND($F26<=M$2, $H26>=M$2), 2, "" ))) | N26: =IF(AND($F26<(N$2+7),$F26>N$2),1, IF(AND($H26<N$2+7,$H26>N$2),3, IF(AND($F26<=N$2, $H26>=N$2), 2, "" ))) | O26: =IF(AND($F26<(O$2+7),$F26>O$2),1, IF(AND($H26<O$2+7,$H26>O$2),3, IF(AND($F26<=O$2, $H26>=O$2), 2, "" ))) | P26: =IF(AND($F26<(P$2+7),$F26>P$2),1, IF(AND($H26<P$2+7,$H26>P$2),3, IF(AND($F26<=P$2, $H26>=P$2), 2, "" ))) | Q26: =IF(AND($F26<(Q$2+7),$F26>Q$2),1, IF(AND($H26<Q$2+7,$H26>Q$2),3, IF(AND($F26<=Q$2, $H26>=Q$2), 2, "" ))) | R26: =IF(AND($F26<(R$2+7),$F26>R$2),1, IF(AND($H26<R$2+7,$H26>R$2),3, IF(AND($F26<=R$2, $H26>=R$2), 2, "" ))) | S26: =IF(AND($F26<(S$2+7),$F26>S$2),1, IF(AND($H26<S$2+7,$H26>S$2),3, IF(AND($F26<=S$2, $H26>=S$2), 2, "" ))) | ... AQ26: =IF(AND($F26<(AQ$2+7),$F26>AQ$2),1, IF(AND($H26<AQ$2+7,$H26>AQ$2),3, IF(AND($F26<=AQ$2, $H26>=AQ$2), 2, "" )))
B27: DC Cable Installation | C27: 44004 | D27: 2 | E27: 44006 | F27: 44004 | G27: 2 | H27: 44006 | L27: =IF(AND($F27<(L$2+7),$F27>L$2),1, IF(AND($H27<L$2+7,$H27>L$2),3, IF(AND($F27<=L$2, $H27>=L$2), 2, "" ))) | M27: =IF(AND($F27<(M$2+7),$F27>M$2),1, IF(AND($H27<M$2+7,$H27>M$2),3, IF(AND($F27<=M$2, $H27>=M$2), 2, "" ))) | N27: =IF(AND($F27<(N$2+7),$F27>N$2),1, IF(AND($H27<N$2+7,$H27>N$2),3, IF(AND($F27<=N$2, $H27>=N$2), 2, "" ))) | O27: =IF(AND($F27<(O$2+7),$F27>O$2),1, IF(AND($H27<O$2+7,$H27>O$2),3, IF(AND($F27<=O$2, $H27>=O$2), 2, "" ))) | P27: =IF(AND($F27<(P$2+7),$F27>P$2),1, IF(AND($H27<P$2+7,$H27>P$2),3, IF(AND($F27<=P$2, $H27>=P$2), 2, "" ))) | Q27: =IF(AND($F27<(Q$2+7),$F27>Q$2),1, IF(AND($H27<Q$2+7,$H27>Q$2),3, IF(AND($F27<=Q$2, $H27>=Q$2), 2, "" ))) | R27: =IF(AND($F27<(R$2+7),$F27>R$2),1, IF(AND($H27<R$2+7,$H27>R$2),3, IF(AND($F27<=R$2, $H27>=R$2), 2, "" ))) | S27: =IF(AND($F27<(S$2+7),$F27>S$2),1, IF(AND($H27<S$2+7,$H27>S$2),3, IF(AND($F27<=S$2, $H27>=S$2), 2, "" ))) | ... AQ27: =IF(AND($F27<(AQ$2+7),$F27>AQ$2),1, IF(AND($H27<AQ$2+7,$H27>AQ$2),3, IF(AND($F27<=AQ$2, $H27>=AQ$2), 2, "" )))
B28: Module Installation | C28: 44006 | D28: 4 | E28: 44012 | F28: 44006 | G28: 4 | H28: 44012 | L28: =IF(AND($F28<(L$2+7),$F28>L$2),1, IF(AND($H28<L$2+7,$H28>L$2),3, IF(AND($F28<=L$2, $H28>=L$2), 2, "" ))) | M28: =IF(AND($F28<(M$2+7),$F28>M$2),1, IF(AND($H28<M$2+7,$H28>M$2),3, IF(AND($F28<=M$2, $H28>=M$2), 2, "" ))) | N28: =IF(AND($F28<(N$2+7),$F28>N$2),1, IF(AND($H28<N$2+7,$H28>N$2),3, IF(AND($F28<=N$2, $H28>=N$2), 2, "" ))) | O28: =IF(AND($F28<(O$2+7),$F28>O$2),1, IF(AND($H28<O$2+7,$H28>O$2),3, IF(AND($F28<=O$2, $H28>=O$2), 2, "" ))) | P28: =IF(AND($F28<(P$2+7),$F28>P$2),1, IF(AND($H28<P$2+7,$H28>P$2),3, IF(AND($F28<=P$2, $H28>=P$2), 2, "" ))) | Q28: =IF(AND($F28<(Q$2+7),$F28>Q$2),1, IF(AND($H28<Q$2+7,$H28>Q$2),3, IF(AND($F28<=Q$2, $H28>=Q$2), 2, "" ))) | R28: =IF(AND($F28<(R$2+7),$F28>R$2),1, IF(AND($H28<R$2+7,$H28>R$2),3, IF(AND($F28<=R$2, $H28>=R$2), 2, "" ))) | S28: =IF(AND($F28<(S$2+7),$F28>S$2),1, IF(AND($H28<S$2+7,$H28>S$2),3, IF(AND($F28<=S$2, $H28>=S$2), 2, "" ))) | ... AQ28: =IF(AND($F28<(AQ$2+7),$F28>AQ$2),1, IF(AND($H28<AQ$2+7,$H28>AQ$2),3, IF(AND($F28<=AQ$2, $H28>=AQ$2), 2, "" ))) -> 2
B29: Earth Cable Installation | C29: 44004 | D29: 1 | E29: 44005 | F29: 44004 | G29: 1 | H29: 44005 | L29: =IF(AND($F29<(L$2+7),$F29>L$2),1, IF(AND($H29<L$2+7,$H29>L$2),3, IF(AND($F29<=L$2, $H29>=L$2), 2, "" ))) | M29: =IF(AND($F29<(M$2+7),$F29>M$2),1, IF(AND($H29<M$2+7,$H29>M$2),3, IF(AND($F29<=M$2, $H29>=M$2), 2, "" ))) | N29: =IF(AND($F29<(N$2+7),$F29>N$2),1, IF(AND($H29<N$2+7,$H29>N$2),3, IF(AND($F29<=N$2, $H29>=N$2), 2, "" ))) | O29: =IF(AND($F29<(O$2+7),$F29>O$2),1, IF(AND($H29<O$2+7,$H29>O$2),3, IF(AND($F29<=O$2, $H29>=O$2), 2, "" ))) | P29: =IF(AND($F29<(P$2+7),$F29>P$2),1, IF(AND($H29<P$2+7,$H29>P$2),3, IF(AND($F29<=P$2, $H29>=P$2), 2, "" ))) | Q29: =IF(AND($F29<(Q$2+7),$F29>Q$2),1, IF(AND($H29<Q$2+7,$H29>Q$2),3, IF(AND($F29<=Q$2, $H29>=Q$2), 2, "" ))) | R29: =IF(AND($F29<(R$2+7),$F29>R$2),1, IF(AND($H29<R$2+7,$H29>R$2),3, IF(AND($F29<=R$2, $H29>=R$2), 2, "" ))) | S29: =IF(AND($F29<(S$2+7),$F29>S$2),1, IF(AND($H29<S$2+7,$H29>S$2),3, IF(AND($F29<=S$2, $H29>=S$2), 2, "" ))) | ... AQ29: =IF(AND($F29<(AQ$2+7),$F29>AQ$2),1, IF(AND($H29<AQ$2+7,$H29>AQ$2),3, IF(AND($F29<=AQ$2, $H29>=AQ$2), 2, "" )))
A30: 10 | B30: AC Works | C30: 43991 | D30: 8 | E30: 44000 | F30: 43991 | G30: 8 | H30: 44000
B31: Inverters Installation | C31: 43991 | D31: 2 | E31: 43993 | F31: 43991 | G31: 2 | H31: 43993 | L31: =IF(AND($F31<(L$2+7),$F31>L$2),1, IF(AND($H31<L$2+7,$H31>L$2),3, IF(AND($F31<=L$2, $H31>=L$2), 2, "" ))) | M31: =IF(AND($F31<(M$2+7),$F31>M$2),1, IF(AND($H31<M$2+7,$H31>M$2),3, IF(AND($F31<=M$2, $H31>=M$2), 2, "" ))) | N31: =IF(AND($F31<(N$2+7),$F31>N$2),1, IF(AND($H31<N$2+7,$H31>N$2),3, IF(AND($F31<=N$2, $H31>=N$2), 2, "" ))) | O31: =IF(AND($F31<(O$2+7),$F31>O$2),1, IF(AND($H31<O$2+7,$H31>O$2),3, IF(AND($F31<=O$2, $H31>=O$2), 2, "" ))) | P31: =IF(AND($F31<(P$2+7),$F31>P$2),1, IF(AND($H31<P$2+7,$H31>P$2),3, IF(AND($F31<=P$2, $H31>=P$2), 2, "" ))) | Q31: =IF(AND($F31<(Q$2+7),$F31>Q$2),1, IF(AND($H31<Q$2+7,$H31>Q$2),3, IF(AND($F31<=Q$2, $H31>=Q$2), 2, "" ))) | R31: =IF(AND($F31<(R$2+7),$F31>R$2),1, IF(AND($H31<R$2+7,$H31>R$2),3, IF(AND($F31<=R$2, $H31>=R$2), 2, "" ))) | S31: =IF(AND($F31<(S$2+7),$F31>S$2),1, IF(AND($H31<S$2+7,$H31>S$2),3, IF(AND($F31<=S$2, $H31>=S$2), 2, "" ))) | ... AQ31: =IF(AND($F31<(AQ$2+7),$F31>AQ$2),1, IF(AND($H31<AQ$2+7,$H31>AQ$2),3, IF(AND($F31<=AQ$2, $H31>=AQ$2), 2, "" )))
B32: AC BOS Installation | C32: 43993 | D32: 3 | E32: 44000 | F32: 43993 | G32: 3 | H32: 44000 | L32: =IF(AND($F32<(L$2+7),$F32>L$2),1, IF(AND($H32<L$2+7,$H32>L$2),3, IF(AND($F32<=L$2, $H32>=L$2), 2, "" ))) | M32: =IF(AND($F32<(M$2+7),$F32>M$2),1, IF(AND($H32<M$2+7,$H32>M$2),3, IF(AND($F32<=M$2, $H32>=M$2), 2, "" ))) | N32: =IF(AND($F32<(N$2+7),$F32>N$2),1, IF(AND($H32<N$2+7,$H32>N$2),3, IF(AND($F32<=N$2, $H32>=N$2), 2, "" ))) | O32: =IF(AND($F32<(O$2+7),$F32>O$2),1, IF(AND($H32<O$2+7,$H32>O$2),3, IF(AND($F32<=O$2, $H32>=O$2), 2, "" ))) | P32: =IF(AND($F32<(P$2+7),$F32>P$2),1, IF(AND($H32<P$2+7,$H32>P$2),3, IF(AND($F32<=P$2, $H32>=P$2), 2, "" ))) | Q32: =IF(AND($F32<(Q$2+7),$F32>Q$2),1, IF(AND($H32<Q$2+7,$H32>Q$2),3, IF(AND($F32<=Q$2, $H32>=Q$2), 2, "" ))) | R32: =IF(AND($F32<(R$2+7),$F32>R$2),1, IF(AND($H32<R$2+7,$H32>R$2),3, IF(AND($F32<=R$2, $H32>=R$2), 2, "" ))) | S32: =IF(AND($F32<(S$2+7),$F32>S$2),1, IF(AND($H32<S$2+7,$H32>S$2),3, IF(AND($F32<=S$2, $H32>=S$2), 2, "" ))) | ... AQ32: =IF(AND($F32<(AQ$2+7),$F32>AQ$2),1, IF(AND($H32<AQ$2+7,$H32>AQ$2),3, IF(AND($F32<=AQ$2, $H32>=AQ$2), 2, "" )))
B33: AC Cable/Tie-In | C33: 43992 | D33: 3 | E33: 43997 | F33: 43992 | G33: 3 | H33: 43997 | L33: =IF(AND($F33<(L$2+7),$F33>L$2),1, IF(AND($H33<L$2+7,$H33>L$2),3, IF(AND($F33<=L$2, $H33>=L$2), 2, "" ))) | M33: =IF(AND($F33<(M$2+7),$F33>M$2),1, IF(AND($H33<M$2+7,$H33>M$2),3, IF(AND($F33<=M$2, $H33>=M$2), 2, "" ))) | N33: =IF(AND($F33<(N$2+7),$F33>N$2),1, IF(AND($H33<N$2+7,$H33>N$2),3, IF(AND($F33<=N$2, $H33>=N$2), 2, "" ))) | O33: =IF(AND($F33<(O$2+7),$F33>O$2),1, IF(AND($H33<O$2+7,$H33>O$2),3, IF(AND($F33<=O$2, $H33>=O$2), 2, "" ))) | P33: =IF(AND($F33<(P$2+7),$F33>P$2),1, IF(AND($H33<P$2+7,$H33>P$2),3, IF(AND($F33<=P$2, $H33>=P$2), 2, "" ))) | Q33: =IF(AND($F33<(Q$2+7),$F33>Q$2),1, IF(AND($H33<Q$2+7,$H33>Q$2),3, IF(AND($F33<=Q$2, $H33>=Q$2), 2, "" ))) | R33: =IF(AND($F33<(R$2+7),$F33>R$2),1, IF(AND($H33<R$2+7,$H33>R$2),3, IF(AND($F33<=R$2, $H33>=R$2), 2, "" ))) | S33: =IF(AND($F33<(S$2+7),$F33>S$2),1, IF(AND($H33<S$2+7,$H33>S$2),3, IF(AND($F33<=S$2, $H33>=S$2), 2, "" ))) | ... AQ33: =IF(AND($F33<(AQ$2+7),$F33>AQ$2),1, IF(AND($H33<AQ$2+7,$H33>AQ$2),3, IF(AND($F33<=AQ$2, $H33>=AQ$2), 2, "" )))
B34: Monitoring Platform Installation | C34: 43997 | D34: 1 | E34: 44000 | F34: 43997 | G34: 1 | H34: 44000
A35: 11 | B35: Completion | C35: 44000 | D35: 14 | E35: 44014 | F35: 44000 | G35: 14 | H35: 44014 | L35: =IF(AND($F35<(L$2+7),$F35>L$2),1, IF(AND($H35<L$2+7,$H35>L$2),3, IF(AND($F35<=L$2, $H35>=L$2), 2, "" ))) | M35: =IF(AND($F35<(M$2+7),$F35>M$2),1, IF(AND($H35<M$2+7,$H35>M$2),3, IF(AND($F35<=M$2, $H35>=M$2), 2, "" ))) | N35: =IF(AND($F35<(N$2+7),$F35>N$2),1, IF(AND($H35<N$2+7,$H35>N$2),3, IF(AND($F35<=N$2, $H35>=N$2), 2, "" ))) | O35: =IF(AND($F35<(O$2+7),$F35>O$2),1, IF(AND($H35<O$2+7,$H35>O$2),3, IF(AND($F35<=O$2, $H35>=O$2), 2, "" ))) | P35: =IF(AND($F35<(P$2+7),$F35>P$2),1, IF(AND($H35<P$2+7,$H35>P$2),3, IF(AND($F35<=P$2, $H35>=P$2), 2, "" ))) | Q35: =IF(AND($F35<(Q$2+7),$F35>Q$2),1, IF(AND($H35<Q$2+7,$H35>Q$2),3, IF(AND($F35<=Q$2, $H35>=Q$2), 2, "" ))) | R35: =IF(AND($F35<(R$2+7),$F35>R$2),1, IF(AND($H35<R$2+7,$H35>R$2),3, IF(AND($F35<=R$2, $H35>=R$2), 2, "" ))) | S35: =IF(AND($F35<(S$2+7),$F35>S$2),1, IF(AND($H35<S$2+7,$H35>S$2),3, IF(AND($F35<=S$2, $H35>=S$2), 2, "" ))) | ... AQ35: =IF(AND($F35<(AQ$2+7),$F35>AQ$2),1, IF(AND($H35<AQ$2+7,$H35>AQ$2),3, IF(AND($F35<=AQ$2, $H35>=AQ$2), 2, "" ))) -> 3
B36: DC Works | C36: 44012 | D36: 2 | E36: 44014 | F36: 44012 | G36: 2 | H36: 44014 | L36: =IF(AND($F36<(L$2+7),$F36>L$2),1, IF(AND($H36<L$2+7,$H36>L$2),3, IF(AND($F36<=L$2, $H36>=L$2), 2, "" ))) | M36: =IF(AND($F36<(M$2+7),$F36>M$2),1, IF(AND($H36<M$2+7,$H36>M$2),3, IF(AND($F36<=M$2, $H36>=M$2), 2, "" ))) | N36: =IF(AND($F36<(N$2+7),$F36>N$2),1, IF(AND($H36<N$2+7,$H36>N$2),3, IF(AND($F36<=N$2, $H36>=N$2), 2, "" ))) | O36: =IF(AND($F36<(O$2+7),$F36>O$2),1, IF(AND($H36<O$2+7,$H36>O$2),3, IF(AND($F36<=O$2, $H36>=O$2), 2, "" ))) | P36: =IF(AND($F36<(P$2+7),$F36>P$2),1, IF(AND($H36<P$2+7,$H36>P$2),3, IF(AND($F36<=P$2, $H36>=P$2), 2, "" ))) | Q36: =IF(AND($F36<(Q$2+7),$F36>Q$2),1, IF(AND($H36<Q$2+7,$H36>Q$2),3, IF(AND($F36<=Q$2, $H36>=Q$2), 2, "" ))) | R36: =IF(AND($F36<(R$2+7),$F36>R$2),1, IF(AND($H36<R$2+7,$H36>R$2),3, IF(AND($F36<=R$2, $H36>=R$2), 2, "" ))) | S36: =IF(AND($F36<(S$2+7),$F36>S$2),1, IF(AND($H36<S$2+7,$H36>S$2),3, IF(AND($F36<=S$2, $H36>=S$2), 2, "" ))) | ... AQ36: =IF(AND($F36<(AQ$2+7),$F36>AQ$2),1, IF(AND($H36<AQ$2+7,$H36>AQ$2),3, IF(AND($F36<=AQ$2, $H36>=AQ$2), 2, "" ))) -> 3
B37: AC Works | C37: 44000 | D37: 2 | E37: 44004 | F37: 44000 | G37: 2 | H37: 44004 | L37: =IF(AND($F37<(L$2+7),$F37>L$2),1, IF(AND($H37<L$2+7,$H37>L$2),3, IF(AND($F37<=L$2, $H37>=L$2), 2, "" ))) | M37: =IF(AND($F37<(M$2+7),$F37>M$2),1, IF(AND($H37<M$2+7,$H37>M$2),3, IF(AND($F37<=M$2, $H37>=M$2), 2, "" ))) | N37: =IF(AND($F37<(N$2+7),$F37>N$2),1, IF(AND($H37<N$2+7,$H37>N$2),3, IF(AND($F37<=N$2, $H37>=N$2), 2, "" ))) | O37: =IF(AND($F37<(O$2+7),$F37>O$2),1, IF(AND($H37<O$2+7,$H37>O$2),3, IF(AND($F37<=O$2, $H37>=O$2), 2, "" ))) | P37: =IF(AND($F37<(P$2+7),$F37>P$2),1, IF(AND($H37<P$2+7,$H37>P$2),3, IF(AND($F37<=P$2, $H37>=P$2), 2, "" ))) | Q37: =IF(AND($F37<(Q$2+7),$F37>Q$2),1, IF(AND($H37<Q$2+7,$H37>Q$2),3, IF(AND($F37<=Q$2, $H37>=Q$2), 2, "" ))) | R37: =IF(AND($F37<(R$2+7),$F37>R$2),1, IF(AND($H37<R$2+7,$H37>R$2),3, IF(AND($F37<=R$2, $H37>=R$2), 2, "" ))) | S37: =IF(AND($F37<(S$2+7),$F37>S$2),1, IF(AND($H37<S$2+7,$H37>S$2),3, IF(AND($F37<=S$2, $H37>=S$2), 2, "" ))) | ... AQ37: =IF(AND($F37<(AQ$2+7),$F37>AQ$2),1, IF(AND($H37<AQ$2+7,$H37>AQ$2),3, IF(AND($F37<=AQ$2, $H37>=AQ$2), 2, "" )))
A38: D | B38: PAYMENT MILESTONE 4: PRACTICAL COMPLETION | C38: 44012 | D38: 1 | E38: 44013 | F38: 44012 | G38: 1 | H38: 44013 | L38: =IF(AND($F38<(L$2+7),$F38>L$2),1, IF(AND($H38<L$2+7,$H38>L$2),3, IF(AND($F38<=L$2, $H38>=L$2), 2, "" ))) | M38: =IF(AND($F38<(M$2+7),$F38>M$2),1, IF(AND($H38<M$2+7,$H38>M$2),3, IF(AND($F38<=M$2, $H38>=M$2), 2, "" ))) | N38: =IF(AND($F38<(N$2+7),$F38>N$2),1, IF(AND($H38<N$2+7,$H38>N$2),3, IF(AND($F38<=N$2, $H38>=N$2), 2, "" ))) | O38: =IF(AND($F38<(O$2+7),$F38>O$2),1, IF(AND($H38<O$2+7,$H38>O$2),3, IF(AND($F38<=O$2, $H38>=O$2), 2, "" ))) | P38: =IF(AND($F38<(P$2+7),$F38>P$2),1, IF(AND($H38<P$2+7,$H38>P$2),3, IF(AND($F38<=P$2, $H38>=P$2), 2, "" ))) | Q38: =IF(AND($F38<(Q$2+7),$F38>Q$2),1, IF(AND($H38<Q$2+7,$H38>Q$2),3, IF(AND($F38<=Q$2, $H38>=Q$2), 2, "" ))) | R38: =IF(AND($F38<(R$2+7),$F38>R$2),1, IF(AND($H38<R$2+7,$H38>R$2),3, IF(AND($F38<=R$2, $H38>=R$2), 2, "" ))) | S38: =IF(AND($F38<(S$2+7),$F38>S$2),1, IF(AND($H38<S$2+7,$H38>S$2),3, IF(AND($F38<=S$2, $H38>=S$2), 2, "" ))) | ... AQ38: =IF(AND($F38<(AQ$2+7),$F38>AQ$2),1, IF(AND($H38<AQ$2+7,$H38>AQ$2),3, IF(AND($F38<=AQ$2, $H38>=AQ$2), 2, "" ))) -> 3
A39: 12 | B39: Commissioning | C39: 43997 | D39: 22 | E39: 44019 | F39: 43997 | G39: 22 | H39: 44019 | L39: =IF(AND($F39<(L$2+7),$F39>L$2),1, IF(AND($H39<L$2+7,$H39>L$2),3, IF(AND($F39<=L$2, $H39>=L$2), 2, "" ))) | M39: =IF(AND($F39<(M$2+7),$F39>M$2),1, IF(AND($H39<M$2+7,$H39>M$2),3, IF(AND($F39<=M$2, $H39>=M$2), 2, "" ))) | N39: =IF(AND($F39<(N$2+7),$F39>N$2),1, IF(AND($H39<N$2+7,$H39>N$2),3, IF(AND($F39<=N$2, $H39>=N$2), 2, "" ))) | O39: =IF(AND($F39<(O$2+7),$F39>O$2),1, IF(AND($H39<O$2+7,$H39>O$2),3, IF(AND($F39<=O$2, $H39>=O$2), 2, "" ))) | P39: =IF(AND($F39<(P$2+7),$F39>P$2),1, IF(AND($H39<P$2+7,$H39>P$2),3, IF(AND($F39<=P$2, $H39>=P$2), 2, "" ))) | Q39: =IF(AND($F39<(Q$2+7),$F39>Q$2),1, IF(AND($H39<Q$2+7,$H39>Q$2),3, IF(AND($F39<=Q$2, $H39>=Q$2), 2, "" ))) | R39: =IF(AND($F39<(R$2+7),$F39>R$2),1, IF(AND($H39<R$2+7,$H39>R$2),3, IF(AND($F39<=R$2, $H39>=R$2), 2, "" ))) | S39: =IF(AND($F39<(S$2+7),$F39>S$2),1, IF(AND($H39<S$2+7,$H39>S$2),3, IF(AND($F39<=S$2, $H39>=S$2), 2, "" ))) | ... AQ39: =IF(AND($F39<(AQ$2+7),$F39>AQ$2),1, IF(AND($H39<AQ$2+7,$H39>AQ$2),3, IF(AND($F39<=AQ$2, $H39>=AQ$2), 2, "" ))) -> 2
B40: Snag List | C40: 44014 | D40: 3 | E40: 44019 | F40: 44014 | G40: 3 | H40: 44019
B41: Pre-Commissioning Checks | C41: 44010 | D41: 2 | E41: 44012 | F41: 44010 | G41: 2 | H41: 44012
B42: Issue CoC | C42: 43997 | D42: 2 | E42: 44001 | F42: 43997 | G42: 2 | H42: 44001 | L42: =IF(AND($F42<(L$2+7),$F42>L$2),1, IF(AND($H42<L$2+7,$H42>L$2),3, IF(AND($F42<=L$2, $H42>=L$2), 2, "" ))) | M42: =IF(AND($F42<(M$2+7),$F42>M$2),1, IF(AND($H42<M$2+7,$H42>M$2),3, IF(AND($F42<=M$2, $H42>=M$2), 2, "" ))) | N42: =IF(AND($F42<(N$2+7),$F42>N$2),1, IF(AND($H42<N$2+7,$H42>N$2),3, IF(AND($F42<=N$2, $H42>=N$2), 2, "" ))) | O42: =IF(AND($F42<(O$2+7),$F42>O$2),1, IF(AND($H42<O$2+7,$H42>O$2),3, IF(AND($F42<=O$2, $H42>=O$2), 2, "" ))) | P42: =IF(AND($F42<(P$2+7),$F42>P$2),1, IF(AND($H42<P$2+7,$H42>P$2),3, IF(AND($F42<=P$2, $H42>=P$2), 2, "" ))) | Q42: =IF(AND($F42<(Q$2+7),$F42>Q$2),1, IF(AND($H42<Q$2+7,$H42>Q$2),3, IF(AND($F42<=Q$2, $H42>=Q$2), 2, "" ))) | R42: =IF(AND($F42<(R$2+7),$F42>R$2),1, IF(AND($H42<R$2+7,$H42>R$2),3, IF(AND($F42<=R$2, $H42>=R$2), 2, "" ))) | S42: =IF(AND($F42<(S$2+7),$F42>S$2),1, IF(AND($H42<S$2+7,$H42>S$2),3, IF(AND($F42<=S$2, $H42>=S$2), 2, "" ))) | ... AQ42: =IF(AND($F42<(AQ$2+7),$F42>AQ$2),1, IF(AND($H42<AQ$2+7,$H42>AQ$2),3, IF(AND($F42<=AQ$2, $H42>=AQ$2), 2, "" )))
B43: Cold Commissioning | C43: 44012 | D43: 1 | E43: 44013 | F43: 44012 | G43: 1 | H43: 44013 | L43: =IF(AND($F43<(L$2+7),$F43>L$2),1, IF(AND($H43<L$2+7,$H43>L$2),3, IF(AND($F43<=L$2, $H43>=L$2), 2, "" ))) | M43: =IF(AND($F43<(M$2+7),$F43>M$2),1, IF(AND($H43<M$2+7,$H43>M$2),3, IF(AND($F43<=M$2, $H43>=M$2), 2, "" ))) | N43: =IF(AND($F43<(N$2+7),$F43>N$2),1, IF(AND($H43<N$2+7,$H43>N$2),3, IF(AND($F43<=N$2, $H43>=N$2), 2, "" ))) | O43: =IF(AND($F43<(O$2+7),$F43>O$2),1, IF(AND($H43<O$2+7,$H43>O$2),3, IF(AND($F43<=O$2, $H43>=O$2), 2, "" ))) | P43: =IF(AND($F43<(P$2+7),$F43>P$2),1, IF(AND($H43<P$2+7,$H43>P$2),3, IF(AND($F43<=P$2, $H43>=P$2), 2, "" ))) | Q43: =IF(AND($F43<(Q$2+7),$F43>Q$2),1, IF(AND($H43<Q$2+7,$H43>Q$2),3, IF(AND($F43<=Q$2, $H43>=Q$2), 2, "" ))) | R43: =IF(AND($F43<(R$2+7),$F43>R$2),1, IF(AND($H43<R$2+7,$H43>R$2),3, IF(AND($F43<=R$2, $H43>=R$2), 2, "" ))) | S43: =IF(AND($F43<(S$2+7),$F43>S$2),1, IF(AND($H43<S$2+7,$H43>S$2),3, IF(AND($F43<=S$2, $H43>=S$2), 2, "" ))) | ... AQ43: =IF(AND($F43<(AQ$2+7),$F43>AQ$2),1, IF(AND($H43<AQ$2+7,$H43>AQ$2),3, IF(AND($F43<=AQ$2, $H43>=AQ$2), 2, "" ))) -> 3
B44: Hot Commissioning | C44: 44013 | D44: 2 | E44: 44015 | F44: 44013 | G44: 2 | H44: 44015 | L44: =IF(AND($F44<(L$2+7),$F44>L$2),1, IF(AND($H44<L$2+7,$H44>L$2),3, IF(AND($F44<=L$2, $H44>=L$2), 2, "" ))) | M44: =IF(AND($F44<(M$2+7),$F44>M$2),1, IF(AND($H44<M$2+7,$H44>M$2),3, IF(AND($F44<=M$2, $H44>=M$2), 2, "" ))) | N44: =IF(AND($F44<(N$2+7),$F44>N$2),1, IF(AND($H44<N$2+7,$H44>N$2),3, IF(AND($F44<=N$2, $H44>=N$2), 2, "" ))) | O44: =IF(AND($F44<(O$2+7),$F44>O$2),1, IF(AND($H44<O$2+7,$H44>O$2),3, IF(AND($F44<=O$2, $H44>=O$2), 2, "" ))) | P44: =IF(AND($F44<(P$2+7),$F44>P$2),1, IF(AND($H44<P$2+7,$H44>P$2),3, IF(AND($F44<=P$2, $H44>=P$2), 2, "" ))) | Q44: =IF(AND($F44<(Q$2+7),$F44>Q$2),1, IF(AND($H44<Q$2+7,$H44>Q$2),3, IF(AND($F44<=Q$2, $H44>=Q$2), 2, "" ))) | R44: =IF(AND($F44<(R$2+7),$F44>R$2),1, IF(AND($H44<R$2+7,$H44>R$2),3, IF(AND($F44<=R$2, $H44>=R$2), 2, "" ))) | S44: =IF(AND($F44<(S$2+7),$F44>S$2),1, IF(AND($H44<S$2+7,$H44>S$2),3, IF(AND($F44<=S$2, $H44>=S$2), 2, "" ))) | ... AQ44: =IF(AND($F44<(AQ$2+7),$F44>AQ$2),1, IF(AND($H44<AQ$2+7,$H44>AQ$2),3, IF(AND($F44<=AQ$2, $H44>=AQ$2), 2, "" ))) -> 1
A45: 13 | B45: Handover | C45: 44020 | D45: 1 | E45: 44021 | F45: 44020 | G45: 1 | H45: 44021 | L45: =IF(AND($F45<(L$2+7),$F45>L$2),1, IF(AND($H45<L$2+7,$H45>L$2),3, IF(AND($F45<=L$2, $H45>=L$2), 2, "" ))) | M45: =IF(AND($F45<(M$2+7),$F45>M$2),1, IF(AND($H45<M$2+7,$H45>M$2),3, IF(AND($F45<=M$2, $H45>=M$2), 2, "" ))) | N45: =IF(AND($F45<(N$2+7),$F45>N$2),1, IF(AND($H45<N$2+7,$H45>N$2),3, IF(AND($F45<=N$2, $H45>=N$2), 2, "" ))) | O45: =IF(AND($F45<(O$2+7),$F45>O$2),1, IF(AND($H45<O$2+7,$H45>O$2),3, IF(AND($F45<=O$2, $H45>=O$2), 2, "" ))) | P45: =IF(AND($F45<(P$2+7),$F45>P$2),1, IF(AND($H45<P$2+7,$H45>P$2),3, IF(AND($F45<=P$2, $H45>=P$2), 2, "" ))) | Q45: =IF(AND($F45<(Q$2+7),$F45>Q$2),1, IF(AND($H45<Q$2+7,$H45>Q$2),3, IF(AND($F45<=Q$2, $H45>=Q$2), 2, "" ))) | R45: =IF(AND($F45<(R$2+7),$F45>R$2),1, IF(AND($H45<R$2+7,$H45>R$2),3, IF(AND($F45<=R$2, $H45>=R$2), 2, "" ))) | S45: =IF(AND($F45<(S$2+7),$F45>S$2),1, IF(AND($H45<S$2+7,$H45>S$2),3, IF(AND($F45<=S$2, $H45>=S$2), 2, "" ))) | ... AQ45: =IF(AND($F45<(AQ$2+7),$F45>AQ$2),1, IF(AND($H45<AQ$2+7,$H45>AQ$2),3, IF(AND($F45<=AQ$2, $H45>=AQ$2), 2, "" )))
A46: E | B46: PAYMENT MILESTONE 6: HANDOVER COMPLETE | C46: 44022 | D46: 1 | E46: 44025 | F46: 44022 | G46: 1 | H46: 44025
C47: 43831 | D47: These numbers are used to set the start and end dates on the Gantt Chart
C48: 44014

Sheet Certificate - Financial Close
B2: Emergent Energy – Financial Close Completion Certificate | H2: FINANCIAL CLOSE CERTIFICATE
B4: Project Name: | C4: ='Project Plan'!E2 -> Hungry Lion Citrusdal
B5: COO: | C5: Johannes Potgieter
B6: Programme Manager: | C6: Roedolph Venter
B7: HoPD: | C7: Natasha Watkins-Baker
B9: Date of Phase Completion: | F9: {=_xlfn.LET(_xlpm.w,$B$10:$B$54,_xlpm.r,$M$10:$M$54,_xlpm.v,IF(ISNUMBER(_xlpm.r),_xlpm.r,IFERROR(VALUE(SUBSTITUTE(_xlpm.r,"%",""))/100,0)),_xlpm.g,IFERROR(VALUE(LEFT(_xlpm.w,1)),0),_xlpm.bdOnly,(SUMPRODUCT((_xlpm.w="1.1")*(_xlpm.v>0))>0)*(SUMPRODUCT((_xlpm.w<>"1.1")*(_xlpm.v>0))=0),_xlpm.anyConstr,SUMPRODUCT((_xlpm.g>=2)*(_xlpm.g<=6)*(_xlpm.v>0))>0,_xlpm.anyQA,SUMPRODUCT((_xlpm.g=7)*(_xlpm.v>0))>0,_xlpm.anyHO,SUMPRODUCT((_xlpm.g=8)*(_xlpm.v>0))>0,_xlpm.anyPlan,SUMPRODUCT((_xlpm.g=1)*(_xlpm.v>0))>0,IF(_xlpm.bdOnly,"1. Financial Close",IF(_xlpm.anyConstr,"3. Construction",IF(_xlpm.anyQA,"4. QA",IF(_xlpm.anyHO,"5. Handover",IF(_xlpm.anyPlan,"2. Planning","1. Financial Close"))))))} -> 1. Financial Close | G9: {=_xlfn.LET(_xlpm.w,$B$10:$B$54,_xlpm.r,$N$10:$N$54,_xlpm.v,IF(ISNUMBER(_xlpm.r),_xlpm.r,IFERROR(VALUE(SUBSTITUTE(_xlpm.r,"%",""))/100,0)),_xlpm.g,IFERROR(VALUE(LEFT(_xlpm.w,1)),0),_xlpm.bdOnly,(SUMPRODUCT((_xlpm.w="1.1")*(_xlpm.v>0))>0)*(SUMPRODUCT((_xlpm.w<>"1.1")*(_xlpm.v>0))=0),_xlpm.anyConstr,SUMPRODUCT((_xlpm.g>=2)*(_xlpm.g<=6)*(_xlpm.v>0))>0,_xlpm.anyQA,SUMPRODUCT((_xlpm.g=7)*(_xlpm.v>0))>0,_xlpm.anyHO,SUMPRODUCT((_xlpm.g=8)*(_xlpm.v>0))>0,_xlpm.anyPlan,SUMPRODUCT((_xlpm.g=1)*(_xlpm.v>0))>0,IF(_xlpm.bdOnly,"1. Financial Close",IF(_xlpm.anyConstr,"3. Construction",IF(_xlpm.anyQA,"4. QA",IF(_xlpm.anyHO,"5. Handover",IF(_xlpm.anyPlan,"2. Planning","1. Financial Close"))))))} -> 1. Financial Close
B10: Phase Deliverables Checklist: (Y/N)
B11: Product Agreement
B12: EPC Agreement
B13: O&M Agreeement
B14: Cost Proposal
B15: Deposit Received
B16: Risks / Notes
B18: Acknowledgement and Acceptance:
B19: Role | C19: Name | D19: Signature | E19: Date

Sheet Certificate - Planning
B2: Emergent Energy – Planning Phase Completion Certificate | H2: PLANNING CERTIFICATE
B4: Project Name: | C4: ='Project Plan'!E2 -> Hungry Lion Citrusdal
B5: Client Representative:
B6: Programme Manager: | C6: Roedolph Venter
B7: Project Manager: | C7: ='Project Plan'!E5 -> Peet Verreynne
B8: Project Engineer:
B10: Date of Phase Completion:
B11: Phase Deliverables Checklist: (Y/N)
B12: Project Introduction Presentation
B13: Project Brief
B14: Engineering Pack
B15: BOQ
B16: PO – Material & Equipment
B17: PO - Contractors
B18: HSE – NOC
B19: HSE – EE File
B20: HSE – Contractor File
... B24: Acknowledgement and Acceptance:
B25: Role | C25: Name | D25: Signature | E25: Date

Sheet Change Register
F1: Change Register
B3: ID | C3: Description | D3: Supporting Image (If Applicable) | E3: Impact | F3: Proposed Date | G3: Proposed By | H3: Status | I3: Approved By | J3: Date | K3: Results / Comments
B4: DEC001
B5: DEC002
B6: DEC003
B7: DEC004
B8: DEC005
B9: DEC006
B10: DEC007
B11: DEC008
B12: DEC009
B13: DEC010

Sheet Compliance
B2: HSE
B4: Description | C4: Status | D4: Approved By | E4: Date | F4: Results / Comments
B5: NOC
B6: 7.1 Agreement
B7: 13.2 Agreement
B8: EE File
B9: Subbie File
B16: SSEG
B18: Description | C18: Status | D18: Approved By | E18: Date | F18: Results / Comments
B19: SSEG Application
B20: PTI
B21: Commissioning Approval

Sheet BOQ
B2: Item | C2: Supplier | D2: Description | E2: Quantity | F2: Comments
B3: PV Module | C3: Krannich | D3: Longi 610W (LR8-66HGD -595-625M) | E3: 213
B4: Mounting Structure | C4: Schletter
B5: DC Cable Red & Black | C5: Menlo | D5: 6sqmm DC Cable | E5: 4000
B6: Inverters | C6: Menlo | D6: Huawei 100KTL | E6: 1
B7: Current Transformers (Production)
B8: Current Transformers (Consumption)
B9: Solar Production Meter | C9: Techsitter | D9: Techsitter meter | E9: 1
B10: Solar Consumption Meter
B11: Wi-Fi Router & Sim
B12: Switch | C12: Accuenergy | D12: Teltonika TSW200 | E12: 1
B13: Back Up Battery
B14: PVDB
B23: Supplier List
B24: Accuenergy
B25: Krannich
B26: Menlo
B27: Red Pole
B28: Schletter
B29: Switchboard
B30: Techsitter

Sheet Project Plan
N1: =TODAY() -> 46070 | O1: =TODAY() -> 46070
C2: PROJECT PLAN | E2: Hungry Lion Citrusdal | I2: Net Work Days | K2: =NETWORKDAYS(I18,K39,Data!C3:C60) -> 19 | N2: 0 | O2: 1
C3: PROJECT SIZE (kWp) | E3: 130 | I3: Total Weeks | K3: =K2/5 -> 3.8
C4: PROJECT DEVELOPER | E4: Peet Verreynne | I4: kW/Week Installation Rate | K4: =E3/K3 -> 34.210526
C5: PROJECT MANAGERS | E5: Peet Verreynne
C6: CONTRACT VALUE | E6: 1312612.9
C7: Phase: | E7: Compliance Handover
B8: No. | C8: HIGH LEVEL PROGRAMME | E8: Planned Start | F8: Duration | G8: Planned End | I8: Actual Start | J8: Duration | K8: Actual End | M8: Status | N8: Expected Status | O8: Comment
F9: =G41-E19 -> 35 | J9: =K41-I19 -> 19 | M9: =AVERAGE(M11,M18,M21,M28,M35,M39,M48,M44) -> 1 | N9: =AVERAGE(N11,N18,N21,N28,N35,N39,N48,N44) -> 0.99999185 | S9: =TODAY() -> 46070 | T9: =TODAY() -> 46070
S10: 1 | T10: 0
B11: 1 | C11: Project Initiation | E11: =MIN(E12:E17) -> 45931 | F11: =G11-E11 -> 29 | G11: =MAX(G12:G17) -> 45960 | I11: =MIN(I12:I17) -> 45931 | J11: =K11-I11 -> 37 | K11: =MAX(K12:K17) -> 45968 | M11: =(J12*M12+J13*M13+J14*M14+J15*M15+J16*M16)/SUM(J12:J16) -> 1 | N11: =(K12*N12+K13*N13+K14*N14+K15*N15+K16*N16)/SUM(K12:K16) -> 1
B12: 1.1 | C12: Project Charter Handover | E12: 45931 | F12: 1 | G12: =WORKDAY.INTL(E12,F12,1,Data!$C$3:$C$60) -> 45932 | I12: 45931 | J12: 1 | K12: =WORKDAY.INTL(I12,J12,1,Data!$C$3:$C$60) -> 45932 | M12: 1 | N12: =_xlfn.LET( _xlpm.s,VALUE($I12), _xlpm.e,VALUE($K12), IF(OR(_xlpm.s="",_xlpm.e=""),"", IF(_xlpm.e<=_xlpm.s, IF(TODAY()>=_xlpm.e,1,0), MAX(0,MIN(1,(TODAY()-_xlpm.s)/(_xlpm.e-_xlpm.s))))) ) -> 1 | O12: EPC signed 9 Oct | S12: Milestone | T12: Start Date | U12: Duration | V12: End Date
B13: 1.2 | C13: HSE Readiness and Signoff | E13: =WORKDAY.INTL(G12,0,1,Data!$C$3:$C$60) -> 45932 | F13: 20 | G13: =WORKDAY.INTL(E13,F13,1,Data!$C$3:$C$60) -> 45960 | I13: =WORKDAY.INTL(K12,0,1,Data!$C$3:$C$60) -> 45932 | J13: 20 | K13: =WORKDAY.INTL(I13,J13,1,Data!$C$3:$C$60) -> 45960 | M13: 1 | N13: =_xlfn.LET( _xlpm.s,VALUE($I13), _xlpm.e,VALUE($K13), IF(OR(_xlpm.s="",_xlpm.e=""),"", IF(_xlpm.e<=_xlpm.s, IF(TODAY()>=_xlpm.e,1,0), MAX(0,MIN(1,(TODAY()-_xlpm.s)/(_xlpm.e-_xlpm.s))))) ) -> 1 | S13: =C11 -> Project Initiation | T13: =I11 -> 45931 | U13: =J11 -> 37 | V13: =K11 -> 45968
B14: 1.3 | C14: Project Introduction | E14: =WORKDAY.INTL(G12,0,1,Data!$C$3:$C$60)+21 -> 45953 | F14: 1 | G14: =WORKDAY.INTL(E14,F14,1,Data!$C$3:$C$60) -> 45954 | I14: 45960 | J14: 1 | K14: =WORKDAY.INTL(I14,J14,1,Data!$C$3:$C$60) -> 45961 | M14: 1 | N14: =_xlfn.LET( _xlpm.s,VALUE($I14), _xlpm.e,VALUE($K14), IF(OR(_xlpm.s="",_xlpm.e=""),"", IF(_xlpm.e<=_xlpm.s, IF(TODAY()>=_xlpm.e,1,0), MAX(0,MIN(1,(TODAY()-_xlpm.s)/(_xlpm.e-_xlpm.s))))) ) -> 1 | S14: =C18 -> Site Establishment | T14: =I18 -> 45967 | U14: =J18 -> 1 | V14: =K18 -> 45968
B15: 1.4 | C15: Installer Kick Off | E15: =WORKDAY.INTL(G14,0,1,Data!$C$3:$C$60) -> 45954 | F15: 1 | G15: =WORKDAY.INTL(E15,F15,1,Data!$C$3:$C$60) -> 45957 | I15: 45967 | J15: 1 | K15: =WORKDAY.INTL(I15,J15,1,Data!$C$3:$C$60) -> 45968 | M15: 1 | N15: =_xlfn.LET( _xlpm.s,VALUE($I15), _xlpm.e,VALUE($K15), IF(OR(_xlpm.s="",_xlpm.e=""),"", IF(_xlpm.e<=_xlpm.s, IF(TODAY()>=_xlpm.e,1,0), MAX(0,MIN(1,(TODAY()-_xlpm.s)/(_xlpm.e-_xlpm.s))))) ) -> 1 | S15: =C21 -> AC Installation | T15: =I21 -> 45924 | U15: =J21 -> 58 | V15: =K21 -> 45982
B16: 1.5 | C16: Project Review | E16: =WORKDAY.INTL(E15,0,1,Data!$C$3:$C$60) -> 45954 | F16: 1 | G16: =WORKDAY.INTL(E16,F16,1,Data!$C$3:$C$60) -> 45957 | I16: 45952 | J16: 1 | K16: =WORKDAY.INTL(I16,J16,1,Data!$C$3:$C$60) -> 45953 | M16: 1 | N16: =_xlfn.LET( _xlpm.s,VALUE($I16), _xlpm.e,VALUE($K16), IF(OR(_xlpm.s="",_xlpm.e=""),"", IF(_xlpm.e<=_xlpm.s, IF(TODAY()>=_xlpm.e,1,0), MAX(0,MIN(1,(TODAY()-_xlpm.s)/(_xlpm.e-_xlpm.s))))) ) -> 1 | S16: =C28 -> DC Works | T16: =I28 -> 45971 | U16: =J28 -> 9 | V16: =K28 -> 45980
S17: =C35 -> Module installation | T17: =I35 -> 45967 | U17: =J35 -> 12 | V17: =K35 -> 45979
B18: 2 | C18: Site Establishment | E18: =MIN(E19:E20) -> 45967 | F18: =G18-E18 -> 1 | G18: =MAX(G19:G20) -> 45968 | I18: =MIN(I19:I20) -> 45967 | J18: =K18-I18 -> 1 | K18: =MAX(K19:K20) -> 45968 | M18: =(J19*M19)/J18 -> 1 | N18: =(K19*N19)/K18 -> 1 | S18: =C39 -> Commissioning | T18: =I39 -> 45982 | U18: =J39 -> 11 | V18: =K39 -> 45993
B19: 2.1 | C19: Solar Contractor Establishment | E19: 45967 | F19: 1 | G19: =E19+F19 -> 45968 | I19: 45967 | J19: 1 | K19: =I19+J19 -> 45968 | M19: 1 | N19: =_xlfn.LET( _xlpm.s,VALUE($I19), _xlpm.e,VALUE($K19), IF(OR(_xlpm.s="",_xlpm.e=""),"", IF(_xlpm.e<=_xlpm.s, IF(TODAY()>=_xlpm.e,1,0), MAX(0,MIN(1,(TODAY()-_xlpm.s)/(_xlpm.e-_xlpm.s))))) ) -> 1 | O19: tbc | S19: =C44 -> QA Inspections | T19: =I44 -> 45986 | U19: =J44 -> 8 | V19: =K44 -> 45994
S20: =C48 -> Project Closure | T20: =I48 -> 45989 | U20: =J48 -> 19 | V20: =K48 -> 46008
B21: 3 | C21: AC Installation | E21: =MIN(E22:E27) -> 45924 | F21: =G21-E21 -> 49 | G21: =MAX(G22:G27) -> 45973 | I21: =MIN(I22:I27) -> 45924 | J21: =K21-I21 -> 58 | K21: =MAX(K22:K27) -> 45982 | M21: =(J22*M22+J23*M23+J24*M24+J25*M25+J26*M26)/SUM(J22:J26) -> 1 | N21: =(J22*N22+J23*N23+J24*N24+J25*N25+J26*N26)/SUM(J22:J26) -> 1
B22: 3.1 | C22: Inverters delivered | E22: =WORKDAY.INTL(G19,0,1,Data!$C$3:$C$60) -> 45968 | F22: 1 | G22: =WORKDAY.INTL(E22,F22,1,Data!$C$3:$C$60) -> 45971 | I22: =WORKDAY.INTL(K19,0,1,Data!$C$3:$C$60)+3 -> 45971 | J22: 1 | K22: =WORKDAY.INTL(I22,J22,1,Data!$C$3:$C$60) -> 45972 | M22: 1 | N22: =_xlfn.LET( _xlpm.s,VALUE($I22), _xlpm.e,VALUE($K22), IF(OR(_xlpm.s="",_xlpm.e=""),"", IF(_xlpm.e<=_xlpm.s, IF(TODAY()>=_xlpm.e,1,0), MAX(0,MIN(1,(TODAY()-_xlpm.s)/(_xlpm.e-_xlpm.s))))) ) -> 1
B23: 3.2 | C23: Inverters Mounted | E23: =WORKDAY.INTL(G22,0,1,Data!$C$3:$C$60) -> 45971 | F23: 2 | G23: =WORKDAY.INTL(E23,F23,1,Data!$C$3:$C$60) -> 45973 | I23: =WORKDAY.INTL(K22,0,1,Data!$C$3:$C$60) -> 45972 | J23: 2 | K23: =WORKDAY.INTL(I23,J23,1,Data!$C$3:$C$60) -> 45974 | M23: 1 | N23: =_xlfn.LET( _xlpm.s,VALUE($I23), _xlpm.e,VALUE($K23), IF(OR(_xlpm.s="",_xlpm.e=""),"", IF(_xlpm.e<=_xlpm.s, IF(TODAY()>=_xlpm.e,1,0), MAX(0,MIN(1,(TODAY()-_xlpm.s)/(_xlpm.e-_xlpm.s))))) ) -> 1
B24: 3.3 | C24: Solar DB Lead Time | E24: =WORKDAY.INTL(E12,0,1,Data!$C$3:$C$60)-7 -> 45924 | F24: 30 | G24: =WORKDAY.INTL(E24,F24,1,Data!$C$3:$C$60) -> 45966 | I24: =WORKDAY.INTL(I12,0,1,Data!$C$3:$C$60)-7 -> 45924 | J24: 33 | K24: =WORKDAY.INTL(I24,J24,1,Data!$C$3:$C$60) -> 45971 | M24: 1 | N24: =_xlfn.LET( _xlpm.s,VALUE($I24), _xlpm.e,VALUE($K24), IF(OR(_xlpm.s="",_xlpm.e=""),"", IF(_xlpm.e<=_xlpm.s, IF(TODAY()>=_xlpm.e,1,0), MAX(0,MIN(1,(TODAY()-_xlpm.s)/(_xlpm.e-_xlpm.s))))) ) -> 1 | O24: added 3 days
B25: 3.4 | C25: AC Works | E25: =WORKDAY.INTL(G24,0,1,Data!$C$3:$C$60) -> 45966 | F25: 5 | G25: =WORKDAY.INTL(E25,F25,1,Data!$C$3:$C$60) -> 45973 | I25: =WORKDAY.INTL(K24,0,1,Data!$C$3:$C$60)+5 -> 45976 | J25: 5 | K25: =WORKDAY.INTL(I25,J25,1,Data!$C$3:$C$60) -> 45982 | M25: 1 | N25: =_xlfn.LET( _xlpm.s,VALUE($I25), _xlpm.e,VALUE($K25), IF(OR(_xlpm.s="",_xlpm.e=""),"", IF(_xlpm.e<=_xlpm.s, IF(TODAY()>=_xlpm.e,1,0), MAX(0,MIN(1,(TODAY()-_xlpm.s)/(_xlpm.e-_xlpm.s))))) ) -> 1
B26: 3.5 | C26: AC Tie-In | E26: =WORKDAY.INTL(E25,0,1,Data!$C$3:$C$60) -> 45966 | F26: 1 | G26: =WORKDAY.INTL(E26,F26,1,Data!$C$3:$C$60) -> 45967 | I26: =WORKDAY.INTL(I25,0,1,Data!$C$3:$C$60)+5 -> 45981 | J26: 1 | K26: =WORKDAY.INTL(I26,J26,1,Data!$C$3:$C$60) -> 45982 | M26: 1 | N26: =_xlfn.LET( _xlpm.s,VALUE($I26), _xlpm.e,VALUE($K26), IF(OR(_xlpm.s="",_xlpm.e=""),"", IF(_xlpm.e<=_xlpm.s, IF(TODAY()>=_xlpm.e,1,0), MAX(0,MIN(1,(TODAY()-_xlpm.s)/(_xlpm.e-_xlpm.s))))) ) -> 1
B28: 4 | C28: DC Works | E28: =MIN(E30:E34) -> 45967 | F28: =G28-E28 -> 27 | G28: =MAX(G30:G34) -> 45994 | I28: =MIN(I30:I34) -> 45971 | J28: =K28-I28 -> 9 | K28: =MAX(K30:K34) -> 45980 | M28: 1 | N28: 1
B30: 4.1 | C30: Mounting Structure delivered | E30: =E19 -> 45967 | F30: 1 | G30: =WORKDAY.INTL(E30,F30,1,Data!$C$3:$C$60) -> 45968 | I30: =I22 -> 45971 | J30: 1 | K30: =WORKDAY.INTL(I30,J30,1,Data!$C$3:$C$60) -> 45972 | M30: 1 | N30: =_xlfn.LET( _xlpm.s,VALUE($I30), _xlpm.e,VALUE($K30), IF(OR(_xlpm.s="",_xlpm.e=""),"", IF(_xlpm.e<=_xlpm.s, IF(TODAY()>=_xlpm.e,1,0), MAX(0,MIN(1,(TODAY()-_xlpm.s)/(_xlpm.e-_xlpm.s))))) ) -> 1
B31: 4.2 | C31: Mounting Structure installation | E31: =WORKDAY.INTL(G30,0,1,Data!$C$3:$C$60) -> 45968 | F31: 2 | G31: =WORKDAY.INTL(E31,F31,1,Data!$C$3:$C$60) -> 45972 | I31: =WORKDAY.INTL(K30,0,1,Data!$C$3:$C$60) -> 45972 | J31: 2 | K31: =WORKDAY.INTL(I31,J31,1,Data!$C$3:$C$60) -> 45974 | M31: 1 | N31: =_xlfn.LET( _xlpm.s,VALUE($I31), _xlpm.e,VALUE($K31), IF(OR(_xlpm.s="",_xlpm.e=""),"", IF(_xlpm.e<=_xlpm.s, IF(TODAY()>=_xlpm.e,1,0), MAX(0,MIN(1,(TODAY()-_xlpm.s)/(_xlpm.e-_xlpm.s))))) ) -> 1
B32: 4.3 | C32: DC Cable delivered | E32: =E30 -> 45967 | F32: 1 | G32: =WORKDAY.INTL(E32,F32,1,Data!$C$3:$C$60) -> 45968 | I32: =I30 -> 45971 | J32: 1 | K32: =WORKDAY.INTL(I32,J32,1,Data!$C$3:$C$60) -> 45972 | M32: 1 | N32: =_xlfn.LET( _xlpm.s,VALUE($I32), _xlpm.e,VALUE($K32), IF(OR(_xlpm.s="",_xlpm.e=""),"", IF(_xlpm.e<=_xlpm.s, IF(TODAY()>=_xlpm.e,1,0), MAX(0,MIN(1,(TODAY()-_xlpm.s)/(_xlpm.e-_xlpm.s))))) ) -> 1
B33: 4.4 | C33: DC Stringing | E33: =WORKDAY.INTL(G37,0,1,Data!$C$3:$C$60)-3 -> 45982 | F33: 8 | G33: =WORKDAY.INTL(E33,F33,1,Data!$C$3:$C$60) -> 45994 | I33: =WORKDAY.INTL(K37,0,1,Data!$C$3:$C$60)-3 -> 45976 | J33: 3 | K33: =WORKDAY.INTL(I33,J33,1,Data!$C$3:$C$60) -> 45980 | M33: 1 | N33: =_xlfn.LET( _xlpm.s,VALUE($I33), _xlpm.e,VALUE($K33), IF(OR(_xlpm.s="",_xlpm.e=""),"", IF(_xlpm.e<=_xlpm.s, IF(TODAY()>=_xlpm.e,1,0), MAX(0,MIN(1,(TODAY()-_xlpm.s)/(_xlpm.e-_xlpm.s))))) ) -> 1
B35: 5 | C35: Module installation | E35: =MIN(E36:E38) -> 45967 | F35: =G35-E35 -> 18 | G35: =MAX(G36:G38) -> 45985 | I35: =MIN(I36:I38) -> 45967 | J35: =K35-I35 -> 12 | K35: =MAX(K36:K38) -> 45979 | M35: =(J36*M36+J37*M37)/SUM(J36:J37) -> 1 | N35: =(K36*N36+K37*N37)/SUM(K36:K37) -> 1
B36: 5.1 | C36: Module delivery | E36: =WORKDAY.INTL(E19,0,1,Data!$C$3:$C$60) -> 45967 | F36: 1 | G36: =WORKDAY.INTL(E36,F36,1,Data!$C$3:$C$60) -> 45968 | I36: =WORKDAY.INTL(I19,0,1,Data!$C$3:$C$60) -> 45967 | J36: 1 | K36: =WORKDAY.INTL(I36,J36,1,Data!$C$3:$C$60) -> 45968 | M36: 1 | N36: =_xlfn.LET( _xlpm.s,VALUE($I36), _xlpm.e,VALUE($K36), IF(OR(_xlpm.s="",_xlpm.e=""),"", IF(_xlpm.e<=_xlpm.s, IF(TODAY()>=_xlpm.e,1,0), MAX(0,MIN(1,(TODAY()-_xlpm.s)/(_xlpm.e-_xlpm.s))))) ) -> 1
B37: 5.2 | C37: Module mounting | E37: =G31 -> 45972 | F37: 9 | G37: =WORKDAY.INTL(E37,F37,1,Data!$C$3:$C$60) -> 45985 | I37: =K31 -> 45974 | J37: 3 | K37: =WORKDAY.INTL(I37,J37,1,Data!$C$3:$C$60) -> 45979 | M37: 1 | N37: =_xlfn.LET( _xlpm.s,VALUE($I37), _xlpm.e,VALUE($K37), IF(OR(_xlpm.s="",_xlpm.e=""),"", IF(_xlpm.e<=_xlpm.s, IF(TODAY()>=_xlpm.e,1,0), MAX(0,MIN(1,(TODAY()-_xlpm.s)/(_xlpm.e-_xlpm.s))))) ) -> 1
B39: 6 | C39: Commissioning | E39: =MIN(E40:E43) -> 45994 | F39: =G39-E39 -> 16 | G39: =MAX(G40:G43) -> 46010 | I39: =MIN(I40:I43) -> 45982 | J39: =K39-I39 -> 11 | K39: =MAX(K40:K43) -> 45993 | M39: =(J40*M40+J41*M41+J42*M42)/SUM(J40:J42) -> 1 | N39: =(K40*N40+K41*N41)/SUM(K40:K41) -> 1
B40: 6.1 | C40: Commissioning | E40: =WORKDAY.INTL(MAX(G21,G28,G35),0,1,Data!$C$3:$C$60) -> 45994 | F40: 1 | G40: =WORKDAY.INTL(E40,F40,1,Data!$C$3:$C$60) -> 45995 | I40: =WORKDAY.INTL(MAX(K21,K28,K35),0,1,Data!$C$3:$C$60) -> 45982 | J40: 1 | K40: =WORKDAY.INTL(I40,J40,1,Data!$C$3:$C$60) -> 45985 | M40: 1 | N40: =_xlfn.LET( _xlpm.s,VALUE($I40), _xlpm.e,VALUE($K40), IF(OR(_xlpm.s="",_xlpm.e=""),"", IF(_xlpm.e<=_xlpm.s, IF(TODAY()>=_xlpm.e,1,0), MAX(0,MIN(1,(TODAY()-_xlpm.s)/(_xlpm.e-_xlpm.s))))) ) -> 1
B41: 6.2 | C41: Practical Completion | E41: =WORKDAY.INTL(G40,0,1,Data!$C$3:$C$60) -> 45995 | F41: 5 | G41: =WORKDAY.INTL(E41,F41,1,Data!$C$3:$C$60) -> 46002 | I41: =WORKDAY.INTL(K40,0,1,Data!$C$3:$C$60) -> 45985 | J41: 1 | K41: =WORKDAY.INTL(I41,J41,1,Data!$C$3:$C$60) -> 45986 | M41: 1 | N41: =_xlfn.LET( _xlpm.s,VALUE($I41), _xlpm.e,VALUE($K41), IF(OR(_xlpm.s="",_xlpm.e=""),"", IF(_xlpm.e<=_xlpm.s, IF(TODAY()>=_xlpm.e,1,0), MAX(0,MIN(1,(TODAY()-_xlpm.s)/(_xlpm.e-_xlpm.s))))) ) -> 1
B42: 6.3 | C42: System Performance Monitoring | E42: =WORKDAY.INTL(G41,0,1,Data!$C$3:$C$60) -> 46002 | F42: 5 | G42: =WORKDAY.INTL(E42,F42,1,Data!$C$3:$C$60) -> 46010 | I42: =WORKDAY.INTL(K41,0,1,Data!$C$3:$C$60) -> 45986 | J42: 5 | K42: =WORKDAY.INTL(I42,J42,1,Data!$C$3:$C$60) -> 45993 | M42: 1 | N42: =_xlfn.LET( _xlpm.s,VALUE($I42), _xlpm.e,VALUE($K42), IF(OR(_xlpm.s="",_xlpm.e=""),"", IF(_xlpm.e<=_xlpm.s, IF(TODAY()>=_xlpm.e,1,0), MAX(0,MIN(1,(TODAY()-_xlpm.s)/(_xlpm.e-_xlpm.s))))) ) -> 1
B44: 7 | C44: QA Inspections | E44: =MIN(E45:E47) -> 46002 | F44: =G44-E44 -> 11 | G44: =MAX(G45:G47) -> 46013 | I44: =MIN(I45:I47) -> 45986 | J44: =K44-I44 -> 8 | K44: =MAX(K45:K47) -> 45994 | M44: =(J45*M45+J46*M46)/SUM(J45:J46) -> 1 | N44: =(K45*N45)/SUM(K45) -> 1
B45: 7.1 | C45: Red-Team Inspection | E45: =WORKDAY.INTL(E42,0,1,Data!$C$3:$C$60) -> 46002 | F45: 3 | G45: =WORKDAY.INTL(E45,F45,1,Data!$C$3:$C$60) -> 46008 | I45: =WORKDAY.INTL(I42,0,1,Data!$C$3:$C$60) -> 45986 | J45: 3 | K45: =WORKDAY.INTL(I45,J45,1,Data!$C$3:$C$60) -> 45989 | M45: 1 | N45: =_xlfn.LET( _xlpm.s,VALUE($I45), _xlpm.e,VALUE($K45), IF(OR(_xlpm.s="",_xlpm.e=""),"", IF(_xlpm.e<=_xlpm.s, IF(TODAY()>=_xlpm.e,1,0), MAX(0,MIN(1,(TODAY()-_xlpm.s)/(_xlpm.e-_xlpm.s))))) ) -> 1
B46: 7.2 | C46: Snags completion | E46: =G45 -> 46008 | F46: 3 | G46: =WORKDAY.INTL(E46,F46,1,Data!$C$3:$C$60) -> 46013 | I46: =K45 -> 45989 | J46: 3 | K46: =WORKDAY.INTL(I46,J46,1,Data!$C$3:$C$60) -> 45994 | M46: 1 | N46: =_xlfn.LET( _xlpm.s,VALUE($I46), _xlpm.e,VALUE($K46), IF(OR(_xlpm.s="",_xlpm.e=""),"", IF(_xlpm.e<=_xlpm.s, IF(TODAY()>=_xlpm.e,1,0), MAX(0,MIN(1,(TODAY()-_xlpm.s)/(_xlpm.e-_xlpm.s))))) ) -> 1
B48: 8 | C48: Project Closure | E48: =MIN(E49:E51) -> 46041 | F48: =G48-E48 -> 11 | G48: =MAX(G49:G51) -> 46052 | I48: =MIN(I49:I51) -> 45989 | J48: =K48-I48 -> 19 | K48: =MAX(K49:K51) -> 46008 | M48: =(J49*M49+J50*M50+J51*M51)/SUM(J49:J51) -> 1 | N48: =(K46*N46+K42*N42+K49*N49+K50*N50+K51*N51)/SUM(K46:K51) -> 0.99993479
B49: 8.1 | C49: Handover documentation | E49: 46041 | F49: 3 | G49: =WORKDAY.INTL(E49,F49,1,Data!$C$3:$C$60) -> 46044 | I49: =WORKDAY.INTL(I46,0,1,Data!$C$3:$C$60) -> 45989 | J49: 7 | K49: =WORKDAY.INTL(I49,J49,1,Data!$C$3:$C$60) -> 46000 | M49: 1 | N49: =_xlfn.LET( _xlpm.s,VALUE($I49), _xlpm.e,VALUE($K49), IF(OR(_xlpm.s="",_xlpm.e=""),"", IF(_xlpm.e<=_xlpm.s, IF(TODAY()>=_xlpm.e,1,0), MAX(0,MIN(1,(TODAY()-_xlpm.s)/(_xlpm.e-_xlpm.s))))) ) -> 1
B50: 8.2 | C50: Handover to Client | E50: 46051 | F50: 1 | G50: =WORKDAY.INTL(E50,F50,1,Data!$C$3:$C$60) -> 46052 | I50: =WORKDAY.INTL(K49,0,1,Data!$C$3:$C$60) -> 46000 | J50: 1 | K50: =WORKDAY.INTL(I50,J50,1,Data!$C$3:$C$60) -> 46001 | M50: 1 | N50: 1
B51: 8.3 | C51: Handover to Matriarch | E51: =WORKDAY.INTL(G49,0,1,Data!$C$3:$C$60) -> 46044 | F51: 5 | G51: =WORKDAY.INTL(E51,F51,1,Data!$C$3:$C$60) -> 46051 | I51: =WORKDAY.INTL(K49,0,1,Data!$C$3:$C$60) -> 46000 | J51: 5 | K51: =WORKDAY.INTL(I51,J51,1,Data!$C$3:$C$60) -> 46008 | M51: 1 | N51: =_xlfn.LET( _xlpm.s,VALUE($I51), _xlpm.e,VALUE($K51), IF(OR(_xlpm.s="",_xlpm.e=""),"", IF(_xlpm.e<=_xlpm.s, IF(TODAY()>=_xlpm.e,1,0), MAX(0,MIN(1,(TODAY()-_xlpm.s)/(_xlpm.e-_xlpm.s))))) ) -> 1

Sheet Revenue Tracking
B2: HIGH LEVEL PROJECT REVENUE TRACKING
D3: COSTED | F3: ACTUAL | L3: FINANCIAL REVIEW | N3: TIMELINE REVIEW | T3: 2025 Actual Revenue | U3: 2025 Actual COS | V3: 2026 Budget Revenue | W3: 2026 Budget COS | X3: 2026 Actual Revenue | Y3: 2026 Actual COS
B4: 1 | C4: Planned Revenue | D4: ='Project Plan'!E6 -> 1312612.9 | F4: =F21 -> 1292329.4 | L4: 1312612.9 | N4: Start Date | T4: =SUMIFS('Expenditure Breakdown'!$U:$U, 'Expenditure Breakdown'!$T:$T, ">"&DATE(2024,8,31), 'Expenditure Breakdown'!$T:$T, "<="&DATE(2025,8,31), 'Expenditure Breakdown'!$S:$S, "<>") -> 0 | U4: =SUMIFS('Expenditure Breakdown'!$Q:$Q, 'Expenditure Breakdown'!$T:$T, ">"&DATE(2024,8,31), 'Expenditure Breakdown'!$T:$T, "<="&DATE(2025,8,31), 'Expenditure Breakdown'!$S:$S, "<>") -> 0 | V4: =SUMIFS('Expenditure Breakdown'!$U:$U, 'Expenditure Breakdown'!$T:$T, ">"&DATE(2025,8,31), 'Expenditure Breakdown'!$T:$T, "<="&DATE(2026,8,31)) -> 1292329.3 | W4: =SUMIFS('Expenditure Breakdown'!$Q:$Q, 'Expenditure Breakdown'!$T:$T, ">"&DATE(2025,8,31), 'Expenditure Breakdown'!$T:$T, "<="&DATE(2026,8,31)) -> 889884.76 | X4: =SUMIFS('Expenditure Breakdown'!$U:$U, 'Expenditure Breakdown'!$T:$T, ">"&DATE(2025,8,31), 'Expenditure Breakdown'!$T:$T, "<="&DATE(2026,8,31), 'Expenditure Breakdown'!$S:$S, "<>") -> 1312612.9 | Y4: =SUMIFS('Expenditure Breakdown'!$Q:$Q, 'Expenditure Breakdown'!$T:$T, ">"&DATE(2025,8,31), 'Expenditure Breakdown'!$T:$T, "<="&DATE(2026,8,31), 'Expenditure Breakdown'!$S:$S, "<>") -> 889884.76
B5: 2 | C5: Planned Expenditure | D5: =+'Expenditure Tracking'!F5 -> 997503.5 | F5: =+'Expenditure Tracking'!H5 -> 889884.76 | L5: 893355.14 | N5: 45967
B6: 3 | C6: Planned Profit | D6: =+D4-D5 -> 315109.45 | F6: =+F4-F5 -> 402444.6 | L6: 419257.8 | N6: End Date - PC
B7: 4 | C7: Planned Margin | D7: =+D6/D4 -> 0.24006273 | F7: =+F6/F4 -> 0.31141025 | L7: 0.31940703 | N7: 45986
B10: CONTRACT
B12: No. | C12: PAYMENT MILESTONE | E12: % | F12: VALUE | H12: PLANNED PAYMENT DATE | L12: INVOICE NUMBER | N12: INVOICE RAISED DATE | P12: PAYMENT RECEIVED DATE | R12: MILESTONE NOTES & COMMENTS
B13: 1 | C13: Acceptance and Initial Deposit | E13: 0.5 | F13: =$D$4*E13 -> 656306.47 | H13: 45930 | L13: 004846 + CN004886 + 004887 | N13: 45931 | P13: 45971 | AO13: ='Decision Register'!$P$14+ 7 -> 7
B14: 2 | C14: Delivery of Panels | E14: 0.25 | F14: =$D$4*E14 -> 328153.24 | H14: ='Project Plan'!E35+7 -> 45974 | L14: 004846 + CN004886 + 004887 | N14: 45931 | P14: 45975
B15: 3 | C15: Delivery of Inverters | E15: 0.1 | F15: =$D$4*E15 -> 131261.29 | H15: ='Project Plan'!E22+7 -> 45975 | L15: 004846 + CN004886 + 004887 | N15: 45931 | P15: 45975
B16: 4 | C16: Practical Completion | E16: 0.1 | F16: =$D$4*E16 -> 131261.29 | H16: ='Project Plan'!G39+7 -> 46017 | L16: 004846 + CN004886 + 004887 | N16: 45931 | P16: 46002
B17: 5 | C17: Handover | E17: 0.05 | F17: =$D$4*E17 -> 65630.647 | H17: ='Project Plan'!G48+180 -> 46232 | L17: 004846 + CN004886 + 004887 | N17: 45931 | P17: 46002
B18: 6 | C18: Reduced system size capex | E18: 0 | F18: -20283.584 | L18: CN004886 + 004887 | N18: 45993 | P18: =P16 -> 46002
B19: 7 | C19: - | E19: 0 | F19: =$D$4*E19 -> 0
E21: =SUM(E13:E19) -> 1 | F21: =SUM(F13:F19) -> 1292329.4
B23: KEY: | C23: contains an error (in result or a check has failed)
C24: Red Font - IF TEXT : content not yet confirmed
C25: Red Font - IF NUMBER: Negative value
C26: Anything in yellow is a concern or risk for noting or action
C27: confirmed
C28: [ADD INITIALS: comment for noting in square brackets, use colour or red to draw attention if important]
C29: [RT: When adding rows into sheet, ensure you insert between first and last row of each category]
C30: end of sheet - do not insert information below/beyond this
B40: No. | C40: PAYMENT MILESTONE | E40: % | F40: VALUE
B41: 1 | C41: Deposit - Project commencement | E41: 0.35 | F41: =$F$47*E41 -> 452315.28
B42: 2 | C42: Delivery of Panels | E42: 0.3 | F42: =$F$47*E42 -> 387698.81
B43: 3 | C43: Delivery of Inverters | E43: 0.2 | F43: =$F$47*E43 -> 258465.87
B44: 4 | C44: Practical Completion | E44: 0.1 | F44: =$F$47*E44 -> 129232.94
B45: 5 | C45: Handover | E45: 0.05 | F45: =$F$47*E45 -> 64616.468
C46: Total | E46: =SUM(E41:E45) -> 1 | F46: =SUM(F41:F45) -> 1292329.4
E47: =SUM(E41:E45) -> 1 | F47: =F21 -> 1292329.4

Sheet Data
C2: Public holidays | F2: Drop down list
C3: 45658 | D3: New Years Day | F3: Approved
C4: 45737 | D4: Human Rights day | F4: Pending
C5: 45765 | D5: Good Friday | F5: Declined
C6: 45768 | D6: Family Day | F6: Abanded
C7: 45774 | D7: Freedom Day
C8: 45765 | D8: Freedom DayObserved
C9: 45778 | D9: Workers day
C10: 45824 | D10: Youth Day Holiday
C11: 45878 | D11: Womens Day
C12: 45924 | D12: Heritage Day
C13: 46007 | D13: Day of Reconciliation | H13: Manual dates
C14: 46016 | D14: Christmas Day
C15: 46017 | D15: Day of Goodwill

Sheet Expenditure Tracking
B2: HIGH LEVEL PROJECT EXPENDITURE TRACKING
F4: COSTED | H4: ACTUAL | J4: Difference from costed
B5: EXPENDITURE | F5: =SUM(F9:F23) -> 997503.5 | H5: =SUM(H9:H23) -> 889884.76 | J5: =SUM(J9:J23) -> 107618.74
B7: No. | D7: Item | F7: Costed Expenditure | H7: Actual Expenditure | J7: Saving / Overrun | M7: Comments on variations from planned expenditure
B9: ='Expenditure Breakdown'!L6 -> 1 | D9: ='Expenditure Breakdown'!M6 -> 1. Panels | F9: ='Expenditure Breakdown'!I6 -> 329608.25 | H9: ='Expenditure Breakdown'!X6 -> 237358.05 | J9: =F9-H9 -> 92250.195
B10: ='Expenditure Breakdown'!L14 -> 2 | D10: ='Expenditure Breakdown'!M14 -> 2. Inverters | F10: ='Expenditure Breakdown'!I14 -> 70000 | H10: ='Expenditure Breakdown'!X14 -> 65246 | J10: =F10-H10 -> 4754
B11: ='Expenditure Breakdown'!L22 -> 3 | D11: ='Expenditure Breakdown'!M22 -> 3. Mounting Structures | F11: ='Expenditure Breakdown'!I22 -> 52216 | H11: ='Expenditure Breakdown'!X22 -> 33946 | J11: =F11-H11 -> 18270
B12: ='Expenditure Breakdown'!L30 -> 4 | D12: ='Expenditure Breakdown'!M30 -> 4. DC Equipment | F12: ='Expenditure Breakdown'!I30 -> 112097.4 | H12: ='Expenditure Breakdown'!X30 -> 83728.55 | J12: =F12-H12 -> 28368.85
B13: ='Expenditure Breakdown'!L48 -> 5 | D13: ='Expenditure Breakdown'!M48 -> 5. Monitoring | F13: ='Expenditure Breakdown'!I48 -> 49000 | H13: ='Expenditure Breakdown'!X48 -> 58278 | J13: =F13-H13 -> -9278
B14: ='Expenditure Breakdown'!L59 -> 6 | D14: ='Expenditure Breakdown'!M59 -> 6. AC Equipment | F14: ='Expenditure Breakdown'!I59 -> 153726.86 | H14: ='Expenditure Breakdown'!X59 -> 94526.15 | J14: =F14-H14 -> 59200.711
B15: ='Expenditure Breakdown'!L79 -> 7 | D15: ='Expenditure Breakdown'!M79 -> 7.BESS | F15: ='Expenditure Breakdown'!I79 -> 0 | H15: ='Expenditure Breakdown'!X79 -> 0 | J15: =F15-H15 -> 0
B16: ='Expenditure Breakdown'!L88 -> 8 | D16: ='Expenditure Breakdown'!M88 -> 8. Product Add On | F16: ='Expenditure Breakdown'!I88 -> 40000 | H16: ='Expenditure Breakdown'!X88 -> 24900 | J16: =F16-H16 -> 15100
B17: ='Expenditure Breakdown'!L98 -> 9 | D17: ='Expenditure Breakdown'!M98 -> 9. AC & DC installation | F17: ='Expenditure Breakdown'!I98 -> 103790 | H17: ='Expenditure Breakdown'!X98 -> 185936.16 | J17: =F17-H17 -> -82146.155
B18: ='Expenditure Breakdown'!L113 -> 10 | D18: ='Expenditure Breakdown'!M113 -> 10. Site Logistics | F18: ='Expenditure Breakdown'!I113 -> 36017.067 | H18: ='Expenditure Breakdown'!X113 -> 68573.54 | J18: =F18-H18 -> -32556.473
B19: ='Expenditure Breakdown'!L131 -> 11 | D19: ='Expenditure Breakdown'!M131 -> 11. Due Dilligence | F19: ='Expenditure Breakdown'!I131 -> 29000 | H19: ='Expenditure Breakdown'!X131 -> 15565 | J19: =F19-H19 -> 13435
B20: ='Expenditure Breakdown'!L137 -> 12 | D20: ='Expenditure Breakdown'!M137 -> 12. BDP Commission | F20: ='Expenditure Breakdown'!I137 -> 8079.73 | H20: ='Expenditure Breakdown'!X137 -> 0 | J20: =F20-H20 -> 8079.73
B21: ='Expenditure Breakdown'!L140 -> 13 | D21: ='Expenditure Breakdown'!M141 -> 13. Engineering | F21: ='Expenditure Breakdown'!I140 -> 11693.195 | H21: ='Expenditure Breakdown'!X140 -> 16154.12 | J21: =F21-H21 -> -4460.9253
B22: ='Expenditure Breakdown'!L147 -> 14 | D22: ='Expenditure Breakdown'!M147 -> 14. General Expenses | F22: ='Expenditure Breakdown'!I147 -> 2275 | H22: ='Expenditure Breakdown'!X147 -> 2023.19 | J22: =F22-H22 -> 251.81
B23: ='Expenditure Breakdown'!L160 -> 15 | D23: ='Expenditure Breakdown'!M160 -> 15. Service Add On | F23: ='Expenditure Breakdown'!I160 -> 0 | H23: ='Expenditure Breakdown'!X160 -> 3650 | J23: =F23-H23 -> -3650
D25: check: | F25: ='Expenditure Breakdown'!I2-'Expenditure Tracking'!F5 -> 0 | G25: =#REF!-G5 -> #REF! | H25: ='Expenditure Breakdown'!X2-H5 -> 0

Sheet Expenditure Breakdown
B2: COSTED EXPENDITURE BREAKDOWN | I2: =SUM(I6:I172) -> 997503.5 | J2: =SUM(J6:J172) -> 1312612.9 | L2: ACTUAL EXPENDITURE BREAKDOWN | R2: FINANCE ONLY | X2: =SUM(X6:X172) -> 889884.76
B4: No. | C4: Product / Service | D4: Description of Work | E4: QTY | F4: Rate / Unit | G4: Budget Total | H4: FORECASTED PAYMENT DATE | I4: Total COS | J4: =IF(J2-'Revenue Tracking'!D4>=0, "Total Revenue", "ERROR on REV" ) -> ERROR on REV | L4: No. | M4: Product/ Service | N4: Description of Work | O4: QTY | P4: Rate / Unit | Q4: Actual Total | R4: PO NUMBER | S4: INVOICE NUMBER | T4: INVOICE RAISED DATE | U4: REVENUE RECOGNITION AMOUNT | V4: CHECK | W4: FINANCE PAYMENT DATE | X4: Total COS
B6: 1 | C6: Panels | D6: Panels Budget | G6: =D173 -> 329608.25 | H6: 46022 | I6: =SUM(G6:G12) -> 329608.25 | J6: =F173 -> 457789.23 | L6: 1 | M6: 1. Panels | N6: Longi 610W - Krannich | O6: 213 | P6: =1.85*610 -> 1128.5 | Q6: =O6*P6 -> 240370.5 | S6: Krannich 15-10014209 | T6: 45961 | U6: 447965.6 | V6: =J6-SUM(U6:U12) -> 20283.584 | W6: 46009 | X6: =SUM(Q6:Q12) -> 237358.05
B7: 1 | D7: Delivery Budget | F7: =G6/'Project Plan'!E3/1000*(8*1000) -> 20283.584 | L7: 1 | M7: 1. Panels | Q7: =O7*P7 -> 0 | U7: 0
B8: 1 | L8: 1 | M8: 1. Panels | N8: EPR Fees | Q8: 5093.43 | S8: Krannich 15-10014209 | T8: 45961 | U8: 9823.6289 | W8: =W6 -> 46009
B9: 1 | L9: 1 | M9: 1. Panels | N9: Longi 610 to stock - reduction in scope | O9: -12 | P9: 1128.5 | Q9: =O9*P9 -> -13542 | S9: Allocated to Cpt Storeroom | T9: 45991 | W9: 45991
B10: 1 | L10: 1 | M10: 1. Panels | N10: Delivery Fee | Q10: 5436.12 | S10: Krannich 17-01001217 | T10: 45991 | U10: 0 | W10: 46009
L11: 1 | M11: 1. Panels | T11: 46022 | U11: -20283.584
B12: 1 | L12: 1 | M12: 1. Panels | T12: =IF(W12>1,EOMONTH(W12,0),"") | U12: 0 | Y12: BUDGET | Z12: Installer Allocation
T13: =IF(W13>1,EOMONTH(W13,0),"") | Y13: AC Equipment | Z13: =G59 -> 153726.86
B14: 2 | C14: Inverters | D14: Inverter Budget | G14: =D174 -> 70000 | H14: 46022 | I14: =SUM(G14:G20) -> 70000 | J14: =F174 -> 97222.222 | L14: 2 | M14: 2. Inverters | N14: Huawei 100KTL | O14: 1 | P14: 65246 | Q14: =O14*P14 -> 65246 | S14: Krannich 15-10014209 | T14: 45961 | U14: 97222.222 | V14: =J14-SUM(U14:U20) -> 0 | W14: 46009 | X14: =SUM(Q14:Q20) -> 65246 | Y14: DC Equipment | Z14: =G31 -> 77125.4
B15: 2 | L15: 2 | M15: 2. Inverters | T15: =IF(W15>1,EOMONTH(W15,0),"") | U15: 0 | Y15: AC Labour | Z15: =G98 -> 32635
B16: 2 | L16: 2 | M16: 2. Inverters | T16: =IF(W16>1,EOMONTH(W16,0),"") | U16: 0 | Y16: DC Labour | Z16: =G99 -> 71155
B17: 2 | L17: 2 | M17: 2. Inverters | T17: =IF(W17>1,EOMONTH(W17,0),"") | U17: 0 | Y17: Offloading | Z17: =G113 -> 8500
B18: 2 | L18: 2 | M18: 2. Inverters | T18: =IF(W18>1,EOMONTH(W18,0),"") | U18: 0 | Y18: Scaffolding | Z18: =G114 -> 11917.067
B19: 2 | L19: 2 | M19: 2. Inverters | T19: =IF(W19>1,EOMONTH(W19,0),"") | U19: 0 | Y19: Storage | Z19: =G116 -> 0
B20: 2 | L20: 2 | M20: 2. Inverters | T20: =IF(W20>1,EOMONTH(W20,0),"") | U20: 0 | Y20: Telehandler | Z20: 0
T21: =IF(W21>1,EOMONTH(W21,0),"")
B22: 3 | C22: Mounting Structures | D22: Structure Budget | G22: =D175 -> 52216 | H22: 46021 | I22: =SUM(G22:G28) -> 52216 | J22: =F175 -> 72522.222 | L22: 3 | M22: 3. Mounting Structures | N22: Schletter Structure | Q22: 27460 | S22: Schletter INV2383 | T22: 45991 | U22: 58665.534 | V22: =J22-SUM(U22:U28) -> 0 | W22: 46021 | X22: =SUM(Q22:Q28) -> 33946 | Y22: Other | Z22: 0
B23: 3 | L23: 3 | M23: 3. Mounting Structures | N23: Additional Structures | Q23: 6486 | S23: Schletter INV2383 | T23: 45991 | U23: 13856.688 | W23: 46021 | Y23: Total | Z23: =SUM(Z13:Z22) -> 355059.33
B24: 3 | L24: 3 | M24: 3. Mounting Structures | T24: =IF(W24>1,EOMONTH(W24,0),"") | U24: =(Q24/$X$22*$J$22) -> 0 | Y24: Less 15% | Z24: =+Z23*0.85 -> 301800.43
B25: 3 | L25: 3 | M25: 3. Mounting Structures | T25: =IF(W25>1,EOMONTH(W25,0),"") | U25: =(Q25/$X$22*$J$22) -> 0 | Y25: R/Wp | Z25: =Z24/'Project Plan'!$E$3/1000 -> 2.3215418
B26: 3 | L26: 3 | M26: 3. Mounting Structures | T26: =IF(W26>1,EOMONTH(W26,0),"") | U26: =(Q26/$X$22*$J$22) -> 0
B27: 3 | L27: 3 | M27: 3. Mounting Structures | T27: =IF(W27>1,EOMONTH(W27,0),"") | U27: =(Q27/$X$22*$J$22) -> 0 | Y27: Jasolar | AB27: Cosmic Sun
B28: 3 | L28: 3 | M28: 3. Mounting Structures | T28: =IF(W28>1,EOMONTH(W28,0),"") | U28: =(Q28/$X$22*$J$22) -> 0 | Y28: ACTUAL | Z28: Installer Price | AB28: ACTUAL | AC28: Installer Price
T29: =IF(W29>1,EOMONTH(W29,0),"") | Y29: =Y13 -> AC Equipment | Z29: 34122.6 | AB29: AC Equipment | AC29: 47500
B30: 4 | C30: DC Equipment | D30: DC Cable Budget | E30: =G30/14*1.15 -> 2872.7 | G30: 34972 | H30: 46021 | I30: =SUM(G30:G46) -> 112097.4 | J30: =F176 -> 155690.83 | L30: 4 | M30: 4. DC Equipment | N30: DC Cable - stock CPT | O30: 2000 | P30: 13.5 | Q30: =O30*P30 -> 27000 | S30: Allocated from Cpt Storeroom | T30: 45961 | U30: 50199.699 | V30: =J30-SUM(U30:U46) -> 0.0046814227 | W30: 45961 | X30: =SUM(Q30:Q46) -> 83728.55 | Y30: =Y14 -> DC Equipment | Z30: 29738.6 | AB30: DC Equipment | AC30: 45540.55
B31: 4 | D31: DC Equipment Budget | G31: =D176-G30 -> 77125.4 | H31: 45991 | L31: 4 | M31: 4. DC Equipment | N31: DC Cable - Stock CPT Red | O31: 2000 | P31: 13.5 | Q31: =O31*P31 -> 27000 | S31: Allocated from Cpt Storeroom | T31: 45961 | U31: 50199.699 | W31: 45961 | Y31: =Y15 -> AC Labour | Z31: 32056.56 | AA31: =Z31/'Project Plan'!$E$3/1000 -> 0.24658892 | AB31: AC Labour | AC31: 51900 | AD31: =AC31/'Project Plan'!$E$3/1000 -> 0.39923077
B32: 4 | L32: 4 | M32: 4. DC Equipment | T32: =IF(W32>1,EOMONTH(W32,0),"") | U32: =(Q32/$X$30*$J$30) -> 0 | Y32: =Y16 -> DC Labour | Z32: 153929.65 | AA32: =Z32/'Project Plan'!$E$3/1000 -> 1.1840742 | AB32: DC Labour | AC32: 103600 | AD32: =AC32/'Project Plan'!$E$3/1000 -> 0.79692308
B33: 4 | L33: 4 | M33: 4. DC Equipment | T33: =IF(W33>1,EOMONTH(W33,0),"") | U33: =(Q33/$X$30*$J$30) -> 0 | Y33: Offloading | Z33: 11410 | AB33: Offloading | AC33: 0
B34: 4 | L34: 4 | M34: 4. DC Equipment | N34: Project Kick Off | O34: =Z30 -> 29738.6 | P34: 0.1 | Q34: =$O$34*P34 -> 2973.86 | R34: PO4379-HLCD-20251017 - RV Approved | S34: =S99 -> JA Electrical Inv 1108 | T34: =T99 -> 45961 | U34: 5529.1436 | W34: =W99 -> 45967 | Y34: Geda/scaffholding | Z34: 18843 | AB34: Forklift | AC34: 0
B35: 4 | L35: 4 | M35: 4. DC Equipment | N35: Site Establishment | P35: 0.15 | Q35: =$O$34*P35 -> 4460.79 | S35: =S100 -> JA Electrical Inv 1118 | T35: =T100 -> 45991 | U35: 8307.4209 | W35: =W100 -> 45995 | Y35: Storage | Z35: 17679 | AB35: Geda | AC35: 0
B36: 4 | L36: 4 | M36: 4. DC Equipment | N36: AC Installation Complete | P36: 0.1 | Q36: =$O$34*P36 -> 2973.86 | S36: JA Electrical Inv 1125 | T36: =T101 -> 45991 | U36: 5529.8072 | W36: =W101 -> 45995 | Y36: P&G's | Z36: 7173.5 | AB36: Logistics | AC36: 0
L37: 4 | M37: 4. DC Equipment | N37: AC Installation Complete | P37: 0.1 | Q37: 2973.82 | S37: JA Electrical Inv 1141 | T37: 46022 | U37: 5529.7329 | W37: 46009
B38: 4 | L38: 4 | M38: 4. DC Equipment | N38: DC Installation Complete | P38: 0.2 | Q38: =O34*P38 -> 5947.72 | S38: JA Electrical Inv 1125 | T38: =T103 -> 45991 | U38: 11059.614 | W38: 46009 | Y38: HSE | Z38: 0 | AB38: HSE | AC38: 4500
L39: 4 | M39: 4. DC Equipment | N39: DC Installation Complete | P39: 0.05 | Q39: =O34*P39 -> 1486.93 | S39: JA Electrical Inv 1130 | T39: 45991 | U39: 2764.9036 | W39: =W104 -> 46031
B40: 4 | L40: 4 | M40: 4. DC Equipment | N40: Commissioning Complete | P40: 0.1 | Q40: =$O$34*P40 -> 2973.86 | S40: JA Electrical Inv 1137 | T40: =T105 -> 45991 | U40: 5529.8072 | W40: 46051 | Y40: Shuffle Boards | Z40: 11935 | AB40: Other | AC40: 0
B41: 4 | L41: 4 | M41: 4. DC Equipment | N41: Site De-establisment | P41: 0.1 | Q41: =$O$34*P41 -> 2973.86 | S41: JA Electrical Inv 1138 | T41: =T106 -> 45991 | U41: 5529.8072 | W41: =W106 -> 46058 | Y41: Other | Z41: 0 | AB41: Other | AC41: 0
B42: 4 | L42: 4 | M42: 4. DC Equipment | N42: Handover Document Complete | P42: 0.05 | Q42: =$O$34*P42 -> 1486.93 | S42: JA Electrical Inv 1139 | T42: =T107 -> 45991 | U42: 2764.9036 | W42: =W107 -> 46058 | Y42: Total | Z42: =SUM(Z29:Z41) -> 316887.91 | AB42: Total | AC42: =SUM(AC29:AC41) -> 253040.55
B43: 4 | L43: 4 | M43: 4. DC Equipment | N43: End of Defects Period | P43: 0.05 | Q43: 1476.92 | S43: JA Electrical Inv 1140 | T43: =T108 -> 45991 | U43: 2746.2903 | W43: =W108 -> 46088 | Y43: R/Wp | Z43: =Z42/'Project Plan'!$E$3/1000 -> 2.4375993 | AB43: R/Wp | AC43: =AC42/'Project Plan'!E3/1000 -> 1.9464658
B44: 4 | L44: 4 | M44: 4. DC Equipment | T44: =IF(W44>1,EOMONTH(W44,0),"") | U44: =(Q44/$X$30*$J$30) -> 0
B45: 4 | L45: 4 | M45: 4. DC Equipment | T45: =IF(W45>1,EOMONTH(W45,0),"") | U45: =(Q45/$X$30*$J$30) -> 0
B46: 4 | L46: 4 | M46: 4. DC Equipment | T46: =IF(W46>1,EOMONTH(W46,0),"") | U46: =(Q46/$X$30*$J$30) -> 0
T47: =IF(W47>1,EOMONTH(W47,0),"")
B48: 5 | C48: Monitoring | D48: Monitoring Budget | G48: =D178-G50 -> 34000 | H48: 46021 | I48: =SUM(G48:G57) -> 49000 | J48: =F178 -> 68055.556 | L48: 5 | M48: 5. Monitoring | N48: Smartlogger | Q48: 8598.34 | S48: Menlo INV0003384 | T48: 45991 | U48: 10016.003 | V48: =J48-SUM(U48:U57) -> -0.00028811485 | W48: 46031 | X48: =SUM(Q48:Q57) -> 58278
L49: 5 | M49: 5. Monitoring | N49: Transport | Q49: 100 | S49: Menlo INV0003384 | T49: 45991 | U49: 119.44181 | W49: =W48 -> 46031
B50: 5 | D50: Revenue Metering | G50: 15000 | H50: 46021 | L50: 5 | M50: 5. Monitoring | N50: CTs & Meters | Q50: 24561 | R50: PO4370-HLCD-20251015 - RV Approved | S50: AccuEnergy ASAI-006654 | T50: 45961 | U50: =29368.2302255249+190.94 -> 29559.17 | W50: =T50+30 -> 45991
B51: 5 | L51: 5 | M51: 5. Monitoring | N51: Techsitter | Q51: 22338 | S51: Matriarch Inv: 5366 | T51: 45961 | U51: 26710.131 | W51: 45991
L52: 5 | M52: 5. Monitoring | N52: Delivery of Techsitter | Q52: 343.33 | S52: DSV Inv:180153158 | T52: 45961 | U52: 410.52866 | W52: 45991
B53: 5 | L53: 5 | M53: 5. Monitoring | N53: Battery | Q53: 975 | S53: Red Pole - SO-35912 | T53: 45961 | U53: 1165.833 | W53: =T53+7 -> 45968
B54: 5 | L54: 5 | M54: 5. Monitoring | N54: Delivery of Comms Equip | Q54: 21.33 | S54: Uber | T54: 45991 | U54: 25.476938 | W54: 45973
B55: 5 | L55: 5 | M55: 5. Monitoring | Q55: 41 | S55: Uber | T55: 45991 | U55: 48.971143 | W55: 45990
L56: 5 | M56: 5. Monitoring | N56: Power Supply | Q56: 1300 | S56: Allocated from Cpt Storeroom | T56: 46022 | W56: 46022
B57: 5 | L57: 5 | M57: 5. Monitoring | T57: =IF(W57>1,EOMONTH(W57,0),"") | U57: =(Q57/$X$48*$J$48) -> 0
T58: =IF(W58>1,EOMONTH(W58,0),"")
B59: 6 | C59: AC Equipment | D59: AC Equipment Budget | G59: =D177 -> 153726.86 | H59: 45991 | I59: =SUM(G59:G77) -> 153726.86 | J59: =F177 -> 213509.53 | L59: 6 | M59: 6. AC Equipment | T59: =IF(W59>1,EOMONTH(W59,0),"") | U59: =(Q59/$X$59*$J$59) -> 0 | V59: =J59-SUM(U59:U77) -> 0.0016307423 | X59: =SUM(Q59:Q77) -> 94526.15
B60: 6 | L60: 6 | M60: 6. AC Equipment | N60: PVDB | Q60: 60403.57 | R60: PO4327-HLCD-20250925 - MI Approved | S60: Switchboard 2-SOI002609 | T60: 45991 | U60: 136435.66 | W60: =T60+30 -> 46021
B61: 6 | L61: 6 | M61: 6. AC Equipment | T61: =IF(W61>1,EOMONTH(W61,0),"") | U61: =(Q61/$X$59*$J$59) -> 0
B62: 6 | L62: 6 | M62: 6. AC Equipment | T62: =IF(W62>1,EOMONTH(W62,0),"") | U62: =(Q62/$X$59*$J$59) -> 0
B63: 6 | L63: 6 | M63: 6. AC Equipment | T63: =IF(W63>1,EOMONTH(W63,0),"") | U63: =(Q63/$X$59*$J$59) -> 0
B64: 6 | L64: 6 | M64: 6. AC Equipment | T64: =IF(W64>1,EOMONTH(W64,0),"") | U64: =(Q64/$X$59*$J$59) -> 0
B65: 6 | L65: 6 | M65: 6. AC Equipment | N65: Project Kick Off | O65: =Z29 -> 34122.6 | P65: 0.1 | Q65: =$O$65*P65 -> 3412.26 | R65: PO4379-HLCD-20251017 - RV Approved | S65: =S99 -> JA Electrical Inv 1108 | T65: =T99 -> 45961 | U65: 7707.3897 | W65: =W99 -> 45967
B66: 6 | L66: 6 | M66: 6. AC Equipment | N66: Site Establishment | P66: 0.15 | Q66: =$O$65*P66 -> 5118.39 | S66: =S100 -> JA Electrical Inv 1118 | T66: =T100 -> 45991 | U66: 11561.087 | W66: =W100 -> 45995
B67: 6 | L67: 6 | M67: 6. AC Equipment | N67: AC Installation Complete | P67: 0.1 | Q67: =$O$65*P67 -> 3412.26 | S67: JA Electrical Inv 1125 | T67: =T101 -> 45991 | U67: 7707.3913 | W67: =W101 -> 45995
L68: 6 | M68: 6. AC Equipment | N68: AC Installation Complete | P68: 0.1 | Q68: 3412.24 | S68: JA Electrical Inv 1141 | T68: 46022 | U68: 7707.3461 | W68: 46009
B69: 6 | L69: 6 | M69: 6. AC Equipment | N69: DC Installation Complete | P69: 0.2 | Q69: =$O$65*P69 -> 6824.52 | S69: JA Electrical Inv 1125 | T69: =T103 -> 45991 | U69: 15414.783 | W69: 46009
L70: 6 | M70: 6. AC Equipment | N70: DC Installation Complete | P70: 0.05 | Q70: =O65*P70 -> 1706.13 | S70: JA Electrical Inv 1130 | T70: 45991 | U70: 3853.6956 | W70: =W104 -> 46031
B71: 6 | L71: 6 | M71: 6. AC Equipment | N71: Commissioning Complete | P71: 0.1 | Q71: =$O$65*P71 -> 3412.26 | S71: JA Electrical Inv 1137 | T71: =T105 -> 45991 | U71: 7707.3913 | W71: 46051
B72: 6 | L72: 6 | M72: 6. AC Equipment | N72: Site De-establisment | P72: 0.1 | Q72: =$O$65*P72 -> 3412.26 | S72: JA Electrical Inv 1138 | T72: =T106 -> 45991 | U72: 7707.3913 | W72: =W106 -> 46058
B73: 6 | L73: 6 | M73: 6. AC Equipment | N73: Handover Document Complete | P73: 0.05 | Q73: =$O$65*P73 -> 1706.13 | S73: JA Electrical Inv 1139 | T73: =T107 -> 45991 | U73: 3853.6956 | W73: =W107 -> 46058
B74: 6 | L74: 6 | M74: 6. AC Equipment | N74: End of Defects Period | P74: 0.05 | Q74: =$O$65*P74 -> 1706.13 | S74: JA Electrical Inv 1140 | T74: =T108 -> 45991 | U74: 3853.6956 | W74: =W108 -> 46088
B75: 6 | L75: 6 | M75: 6. AC Equipment | T75: =IF(W75>1,EOMONTH(W75,0),"") | U75: =(Q75/$X$59*$J$59) -> 0
B76: 6 | L76: 6 | M76: 6. AC Equipment | T76: =IF(W76>1,EOMONTH(W76,0),"") | U76: =(Q76/$X$59*$J$59) -> 0
B77: 6 | L77: 6 | M77: 6. AC Equipment | T77: =IF(W77>1,EOMONTH(W77,0),"") | U77: =(Q77/$X$59*$J$59) -> 0
T78: =IF(W78>1,EOMONTH(W78,0),"")
B79: 7 | C79: BESS | I79: =SUM(G79:G86) -> 0 | J79: =F182 -> 0 | L79: 7 | M79: 7.BESS | V79: =J79-SUM(U79:U86) -> 0 | X79: =SUM(Q79:Q86) -> 0
B80: 7 | L80: 7 | M80: 7.BESS
B81: 7 | L81: 7 | M81: 7.BESS
B82: 7 | L82: 7 | M82: 7.BESS
B83: 7 | L83: 7 | M83: 7.BESS
B84: 7 | L84: 7 | M84: 7.BESS
B85: 7 | L85: 7 | M85: 7.BESS
B86: 7 | L86: 7 | M86: 7.BESS
B88: 8 | C88: Product Add On | I88: =SUM(G88:G96) -> 40000 | J88: =F179+F181 -> 44444.444 | L88: 8 | M88: 8. Product Add On | V88: =J88-SUM(U88:U96) -> 0 | X88: =SUM(Q88:Q96) -> 24900
B89: 8 | D89: Inverter Cge | G89: 40000 | H89: 45961 | L89: 8 | M89: 8. Product Add On | N89: Inverter Cage | O89: 16450 | P89: 0.7 | Q89: =O89*P89 -> 11515 | R89: PO4359-HLCD-20251007 - RV Approved | S89: Barrier Projects : 507 | T89: 45961 | U89: 31111.111 | W89: 45954
B90: 8 | L90: 8 | M90: 8. Product Add On | P90: 0.3 | Q90: =O89*P90 -> 4935 | S90: Barrier Projects : 507 | T90: 45961 | U90: 13333.333 | W90: 45995
B91: 8 | L91: 8 | M91: 8. Product Add On | Q91: -16450 | S91: Barrier Projects Credit : 507 | T91: 45991 | U91: 0 | W91: 45995
B92: 8 | L92: 8 | M92: 8. Product Add On | Q92: 24900 | S92: Barrier Projects : 507 | T92: 45991 | U92: 0 | W92: 45995
B93: 8 | L93: 8 | M93: 8. Product Add On | U93: 0
B94: 8 | L94: 8 | M94: 8. Product Add On
B95: 8 | L95: 8 | M95: 8. Product Add On
B96: 8 | L96: 8 | M96: 8. Product Add On
K97: Only services to be capture below, products above | T97: =IF(W97>1,EOMONTH(W97,0),"")
B98: 9 | C98: AC & DC Installation | D98: AC Installation Budget | G98: =D186 -> 32635 | H98: 45961 | I98: =SUM(G98:G111) -> 103790 | J98: =F186+F187 -> 115322.22 | L98: 9 | M98: 9. AC & DC installation | T98: =IF(W98>1,EOMONTH(W98,0),"") | U98: =(Q98/$X$98*$J$98) -> 0 | V98: =J98-SUM(U98:U111) -> 0.0032016007 | X98: =SUM(Q98:Q111) -> 185936.16
B99: 9 | D99: DC Installation Budget | G99: =D187 -> 71155 | H99: 45991 | L99: 9 | M99: 9. AC & DC installation | N99: Project Kick Off | O99: =Z32+Z31 -> 185986.21 | P99: 0.1 | Q99: =$O$99*P99 -> 18598.621 | R99: PO4379-HLCD-20251017 - RV Approved | S99: JA Electrical Inv 1108 | T99: 45961 | U99: 11532.222 | W99: 45967
B100: 9 | L100: 9 | M100: 9. AC & DC installation | N100: Site Establishment | P100: 0.15 | Q100: =$O$99*P100 -> 27897.931 | S100: JA Electrical Inv 1118 | T100: 45991 | U100: 17306.088 | W100: 45995
B101: 9 | L101: 9 | M101: 9. AC & DC installation | N101: AC Installation Complete | P101: 0.1 | Q101: 18598.6 | S101: JA Electrical Inv 1125 | T101: 45991 | U101: 11535.312 | W101: 45995
L102: 9 | M102: 9. AC & DC installation | N102: AC Installation Complete | P102: 0.1 | Q102: 18598.6 | S102: JA Electrical Inv 1141 | T102: 46022 | U102: 11535.325 | W102: 46009
B103: 9 | L103: 9 | M103: 9. AC & DC installation | N103: DC Installation Complete | P103: 0.2 | Q103: =$O$99*P103 -> 37197.242 | S103: JA Electrical Inv 1125 | T103: 45991 | U103: 23070.651 | W103: 46009
L104: 9 | M104: 9. AC & DC installation | N104: DC Installation Complete | P104: 0.05 | Q104: =O99*P104 -> 9299.3105 | S104: JA Electrical Inv 1130 | T104: 45991 | U104: 5767.6627 | W104: 46031
...

Sheet Cashflow
D1: [RT: Double Check the first date is always a MONDAY] | F1: 45845 | G1: =F1+7 -> 45852 | H1: =G1+7 -> 45859 | I1: =H1+7 -> 45866 | J1: =I1+7 -> 45873 | K1: =J1+7 -> 45880 | L1: =K1+7 -> 45887 | M1: =L1+7 -> 45894 | N1: =M1+7 -> 45901 | ... KF1: =KE1+7 -> 47847
A2: PLANNED | C2: CHECK | D2: CHECK
B3: Planned Revenue | C3: ='Revenue Tracking'!D4 -> 1312612.9 | D3: =SUM(F3:KF3) -> 1312612.9 | F3: =SUMIFS('Revenue Tracking'!$F$13:$F$19, 'Revenue Tracking'!$H$13:$H$19, ">="&F1,'Revenue Tracking'!$H$13:$H$19, "<"&G1) -> 0 | G3: =SUMIFS('Revenue Tracking'!$F$13:$F$19, 'Revenue Tracking'!$H$13:$H$19, ">="&G1,'Revenue Tracking'!$H$13:$H$19, "<"&H1) -> 0 | H3: =SUMIFS('Revenue Tracking'!$F$13:$F$19, 'Revenue Tracking'!$H$13:$H$19, ">="&H1,'Revenue Tracking'!$H$13:$H$19, "<"&I1) -> 0 | I3: =SUMIFS('Revenue Tracking'!$F$13:$F$19, 'Revenue Tracking'!$H$13:$H$19, ">="&I1,'Revenue Tracking'!$H$13:$H$19, "<"&J1) -> 0 | J3: =SUMIFS('Revenue Tracking'!$F$13:$F$19, 'Revenue Tracking'!$H$13:$H$19, ">="&J1,'Revenue Tracking'!$H$13:$H$19, "<"&K1) -> 0 | K3: =SUMIFS('Revenue Tracking'!$F$13:$F$19, 'Revenue Tracking'!$H$13:$H$19, ">="&K1,'Revenue Tracking'!$H$13:$H$19, "<"&L1) -> 0 | L3: =SUMIFS('Revenue Tracking'!$F$13:$F$19, 'Revenue Tracking'!$H$13:$H$19, ">="&L1,'Revenue Tracking'!$H$13:$H$19, "<"&M1) -> 0 | M3: =SUMIFS('Revenue Tracking'!$F$13:$F$19, 'Revenue Tracking'!$H$13:$H$19, ">="&M1,'Revenue Tracking'!$H$13:$H$19, "<"&N1) -> 0 | ... KE3: =SUMIFS('Revenue Tracking'!$F$13:$F$19, 'Revenue Tracking'!$H$13:$H$19, ">="&KE1,'Revenue Tracking'!$H$13:$H$19, "<"&KF1) -> 0 | KF3: =SUMIFS('Revenue Tracking'!$F$13:$F$19, 'Revenue Tracking'!$H$13:$H$19, ">="&KF1,'Revenue Tracking'!$H$13:$H$19, "<"&#REF!) -> 0
B4: Planned Revenue - Cumulative | F4: =F3 -> 0 | G4: =F4+G3 -> 0 | H4: =G4+H3 -> 0 | I4: =H4+I3 -> 0 | J4: =I4+J3 -> 0 | K4: =J4+K3 -> 0 | L4: =K4+L3 -> 0 | M4: =L4+M3 -> 0 | N4: =M4+N3 -> 0 | ... KF4: =KE4+KF3 -> 1312612.9
B5: Planned Expenditure | C5: ='Revenue Tracking'!D5 -> 997503.5 | D5: =SUM(F5:KF5) -> 997503.5 | F5: =SUMIFS('Expenditure Breakdown'!$G$6:$G$179, 'Expenditure Breakdown'!$H$6:$H$179, ">="&F1,'Expenditure Breakdown'!$H$6:$H$179, "<"&G1) -> 0 | G5: =SUMIFS('Expenditure Breakdown'!$G$6:$G$179, 'Expenditure Breakdown'!$H$6:$H$179, ">="&G1,'Expenditure Breakdown'!$H$6:$H$179, "<"&H1) -> 0 | H5: =SUMIFS('Expenditure Breakdown'!$G$6:$G$179, 'Expenditure Breakdown'!$H$6:$H$179, ">="&H1,'Expenditure Breakdown'!$H$6:$H$179, "<"&I1) -> 0 | I5: =SUMIFS('Expenditure Breakdown'!$G$6:$G$179, 'Expenditure Breakdown'!$H$6:$H$179, ">="&I1,'Expenditure Breakdown'!$H$6:$H$179, "<"&J1) -> 0 | J5: =SUMIFS('Expenditure Breakdown'!$G$6:$G$179, 'Expenditure Breakdown'!$H$6:$H$179, ">="&J1,'Expenditure Breakdown'!$H$6:$H$179, "<"&K1) -> 0 | K5: =SUMIFS('Expenditure Breakdown'!$G$6:$G$179, 'Expenditure Breakdown'!$H$6:$H$179, ">="&K1,'Expenditure Breakdown'!$H$6:$H$179, "<"&L1) -> 0 | L5: =SUMIFS('Expenditure Breakdown'!$G$6:$G$179, 'Expenditure Breakdown'!$H$6:$H$179, ">="&L1,'Expenditure Breakdown'!$H$6:$H$179, "<"&M1) -> 0 | M5: =SUMIFS('Expenditure Breakdown'!$G$6:$G$179, 'Expenditure Breakdown'!$H$6:$H$179, ">="&M1,'Expenditure Breakdown'!$H$6:$H$179, "<"&N1) -> 0 | ... KE5: =SUMIFS('Expenditure Breakdown'!$G$6:$G$179, 'Expenditure Breakdown'!$H$6:$H$179, ">="&KE1,'Expenditure Breakdown'!$H$6:$H$179, "<"&KF1) -> 0 | KF5: =SUMIFS('Expenditure Breakdown'!$G$6:$G$179, 'Expenditure Breakdown'!$H$6:$H$179, ">="&KF1,'Expenditure Breakdown'!$H$6:$H$179, "<"&#REF!) -> 0
B6: Planned Expenditure - Cumulative | F6: =F5 -> 0 | G6: =F6+G5 -> 0 | H6: =G6+H5 -> 0 | I6: =H6+I5 -> 0 | J6: =I6+J5 -> 0 | K6: =J6+K5 -> 0 | L6: =K6+L5 -> 0 | M6: =L6+M5 -> 0 | N6: =M6+N5 -> 0 | ... KF6: =KE6+KF5 -> 997503.5
B7: PLANNED CashFlow | F7: =F4-F6 -> 0 | G7: =G4-G6 -> 0 | H7: =H4-H6 -> 0 | I7: =I4-I6 -> 0 | J7: =J4-J6 -> 0 | K7: =K4-K6 -> 0 | L7: =L4-L6 -> 0 | M7: =M4-M6 -> 0 | ... KF7: =KF4-KF6 -> 315109.45
A8: ACTUAL | C8: CHECK | D8: CHECK
B9: Actual + Planned Revenue | C9: ='Revenue Tracking'!F4 -> 1292329.4 | D9: =SUM(F9:KF9) -> 1292329.4 | F9: =SUMIFS('Revenue Tracking'!$F$13:$F$19, 'Revenue Tracking'!$P$13:$P$19, ">="&F1,'Revenue Tracking'!$P$13:$P$19, "<"&G1) -> 0 | G9: =SUMIFS('Revenue Tracking'!$F$13:$F$19, 'Revenue Tracking'!$P$13:$P$19, ">="&G1,'Revenue Tracking'!$P$13:$P$19, "<"&H1) -> 0 | H9: =SUMIFS('Revenue Tracking'!$F$13:$F$19, 'Revenue Tracking'!$P$13:$P$19, ">="&H1,'Revenue Tracking'!$P$13:$P$19, "<"&I1) -> 0 | I9: =SUMIFS('Revenue Tracking'!$F$13:$F$19, 'Revenue Tracking'!$P$13:$P$19, ">="&I1,'Revenue Tracking'!$P$13:$P$19, "<"&J1) -> 0 | J9: =SUMIFS('Revenue Tracking'!$F$13:$F$19, 'Revenue Tracking'!$P$13:$P$19, ">="&J1,'Revenue Tracking'!$P$13:$P$19, "<"&K1) -> 0 | K9: =SUMIFS('Revenue Tracking'!$F$13:$F$19, 'Revenue Tracking'!$P$13:$P$19, ">="&K1,'Revenue Tracking'!$P$13:$P$19, "<"&L1) -> 0 | L9: =SUMIFS('Revenue Tracking'!$F$13:$F$19, 'Revenue Tracking'!$P$13:$P$19, ">="&L1,'Revenue Tracking'!$P$13:$P$19, "<"&M1) -> 0 | M9: =SUMIFS('Revenue Tracking'!$F$13:$F$19, 'Revenue Tracking'!$P$13:$P$19, ">="&M1,'Revenue Tracking'!$P$13:$P$19, "<"&N1) -> 0 | ... KE9: =SUMIFS('Revenue Tracking'!$F$13:$F$19, 'Revenue Tracking'!$P$13:$P$19, ">="&KE1,'Revenue Tracking'!$P$13:$P$19, "<"&KF1) -> 0 | KF9: =SUMIFS('Revenue Tracking'!$F$13:$F$19, 'Revenue Tracking'!$P$13:$P$19, ">="&KF1,'Revenue Tracking'!$P$13:$P$19, "<"&#REF!) -> 0
B10: Actual + Planned Revenue - Cumulative | F10: =F9 -> 0 | G10: =F10+G9 -> 0 | H10: =G10+H9 -> 0 | I10: =H10+I9 -> 0 | J10: =I10+J9 -> 0 | K10: =J10+K9 -> 0 | L10: =K10+L9 -> 0 | M10: =L10+M9 -> 0 | N10: =M10+N9 -> 0 | ... KF10: =KE10+KF9 -> 1292329.4
B11: Actual + Planned Expenditure | C11: ='Revenue Tracking'!F5 -> 889884.76 | D11: =SUM(F11:KF11) -> 889884.76 | F11: =SUMIFS('Expenditure Breakdown'!$Q$6:$Q$179, 'Expenditure Breakdown'!$W$6:$W$179, ">="&F1,'Expenditure Breakdown'!$W$6:$W$179, "<"&G1) -> 0 | G11: =SUMIFS('Expenditure Breakdown'!$Q$6:$Q$179, 'Expenditure Breakdown'!$W$6:$W$179, ">="&G1,'Expenditure Breakdown'!$W$6:$W$179, "<"&H1) -> 0 | H11: =SUMIFS('Expenditure Breakdown'!$Q$6:$Q$179, 'Expenditure Breakdown'!$W$6:$W$179, ">="&H1,'Expenditure Breakdown'!$W$6:$W$179, "<"&I1) -> 0 | I11: =SUMIFS('Expenditure Breakdown'!$Q$6:$Q$179, 'Expenditure Breakdown'!$W$6:$W$179, ">="&I1,'Expenditure Breakdown'!$W$6:$W$179, "<"&J1) -> 0 | J11: =SUMIFS('Expenditure Breakdown'!$Q$6:$Q$179, 'Expenditure Breakdown'!$W$6:$W$179, ">="&J1,'Expenditure Breakdown'!$W$6:$W$179, "<"&K1) -> 0 | K11: =SUMIFS('Expenditure Breakdown'!$Q$6:$Q$179, 'Expenditure Breakdown'!$W$6:$W$179, ">="&K1,'Expenditure Breakdown'!$W$6:$W$179, "<"&L1) -> 0 | L11: =SUMIFS('Expenditure Breakdown'!$Q$6:$Q$179, 'Expenditure Breakdown'!$W$6:$W$179, ">="&L1,'Expenditure Breakdown'!$W$6:$W$179, "<"&M1) -> 0 | M11: =SUMIFS('Expenditure Breakdown'!$Q$6:$Q$179, 'Expenditure Breakdown'!$W$6:$W$179, ">="&M1,'Expenditure Breakdown'!$W$6:$W$179, "<"&N1) -> 0 | ... KE11: =SUMIFS('Expenditure Breakdown'!$Q$6:$Q$179, 'Expenditure Breakdown'!$W$6:$W$179, ">="&KE1,'Expenditure Breakdown'!$W$6:$W$179, "<"&KF1) -> 0 | KF11: =SUMIFS('Expenditure Breakdown'!$Q$6:$Q$179, 'Expenditure Breakdown'!$W$6:$W$179, ">="&KF1,'Expenditure Breakdown'!$W$6:$W$179, "<"&#REF!) -> 0
B12: Actual + Planned Expenditure - Cumulative | F12: =F11 -> 0 | G12: =F12+G11 -> 0 | H12: =G12+H11 -> 0 | I12: =H12+I11 -> 0 | J12: =I12+J11 -> 0 | K12: =J12+K11 -> 0 | L12: =K12+L11 -> 0 | M12: =L12+M11 -> 0 | N12: =M12+N11 -> 0 | ... KF12: =KE12+KF11 -> 889884.76
B14: ACTUAL CashFlow | F14: =F10-F12 -> 0 | G14: =G10-G12 -> 0 | H14: =H10-H12 -> 0 | I14: =I10-I12 -> 0 | J14: =J10-J12 -> 0 | K14: =K10-K12 -> 0 | L14: =L10-L12 -> 0 | M14: =M10-M12 -> 0 | ... KF14: =KF10-KF12 -> 402444.6
C16: CHECK | D16: CHECK
B17: Revenue Recognition | C17: =C3-D17 -> 20283.595 | D17: =SUM(F17:KF17) -> 1292329.3 | F17: =SUMIFS('Expenditure Breakdown'!$U$6:$U$179, 'Expenditure Breakdown'!$T$6:$T$179, ">="&F1,'Expenditure Breakdown'!$T$6:$T$179, "<"&G1) -> 0 | G17: =SUMIFS('Expenditure Breakdown'!$U$6:$U$179, 'Expenditure Breakdown'!$T$6:$T$179, ">="&G1,'Expenditure Breakdown'!$T$6:$T$179, "<"&H1) -> 0 | H17: =SUMIFS('Expenditure Breakdown'!$U$6:$U$179, 'Expenditure Breakdown'!$T$6:$T$179, ">="&H1,'Expenditure Breakdown'!$T$6:$T$179, "<"&I1) -> 0 | I17: =SUMIFS('Expenditure Breakdown'!$U$6:$U$179, 'Expenditure Breakdown'!$T$6:$T$179, ">="&I1,'Expenditure Breakdown'!$T$6:$T$179, "<"&J1) -> 0 | J17: =SUMIFS('Expenditure Breakdown'!$U$6:$U$179, 'Expenditure Breakdown'!$T$6:$T$179, ">="&J1,'Expenditure Breakdown'!$T$6:$T$179, "<"&K1) -> 0 | K17: =SUMIFS('Expenditure Breakdown'!$U$6:$U$179, 'Expenditure Breakdown'!$T$6:$T$179, ">="&K1,'Expenditure Breakdown'!$T$6:$T$179, "<"&L1) -> 0 | L17: =SUMIFS('Expenditure Breakdown'!$U$6:$U$179, 'Expenditure Breakdown'!$T$6:$T$179, ">="&L1,'Expenditure Breakdown'!$T$6:$T$179, "<"&M1) -> 0 | M17: =SUMIFS('Expenditure Breakdown'!$U$6:$U$179, 'Expenditure Breakdown'!$T$6:$T$179, ">="&M1,'Expenditure Breakdown'!$T$6:$T$179, "<"&N1) -> 0 | ... KE17: =SUMIFS('Expenditure Breakdown'!$U$6:$U$179, 'Expenditure Breakdown'!$T$6:$T$179, ">="&KE1,'Expenditure Breakdown'!$T$6:$T$179, "<"&KF1) -> 0 | KF17: =SUMIFS('Expenditure Breakdown'!$U$6:$U$179, 'Expenditure Breakdown'!$T$6:$T$179, ">="&KF1,'Expenditure Breakdown'!$T$6:$T$179, "<"&#REF!) -> 0
B18: Revenue Recognition Cumulative | C18: =D17-D18 -> 0 | D18: =MAX(F18:KF18) -> 1292329.3 | F18: =F17 -> 0 | G18: =F18+G17 -> 0 | H18: =G18+H17 -> 0 | I18: =H18+I17 -> 0 | J18: =I18+J17 -> 0 | K18: =J18+K17 -> 0 | L18: =K18+L17 -> 0 | M18: =L18+M17 -> 0 | N18: =M18+N17 -> 0 | ... KF18: =KE18+KF17 -> 1292329.3

Sheet Finance - Revenue
A3: Sum of REVENUE RECOGNITION AMOUNT | B3: Column Labels
A4: Row Labels | B4: (blank) | C4: 45961 | D4: 45991 | E4: 46022 | G4: 46053 | H4: Grand Total
A5: (blank)
A6: 1. Panels | B6: 0 | C6: 457789.23 | D6: 0 | E6: -20283.584 | F6: 0 | H6: 437505.64
A7: 2. Inverters | C7: 97222.222 | F7: 0 | H7: 97222.222
A8: 3. Mounting Structures | D8: 72522.222 | F8: 0 | H8: 72522.222
A9: 4. DC Equipment | C9: 105928.54 | D9: 44232.555 | E9: 5529.7329 | F9: 0 | H9: 155690.83
A10: 5. Monitoring | C10: 57845.663 | D10: 10209.893 | F10: 0 | H10: 68055.556
A11: 6. AC Equipment | C11: 7707.3897 | D11: 198094.79 | E11: 7707.3461 | F11: 0 | H11: 213509.53
A12: 8. Product Add On | B12: 0 | C12: 44444.444 | D12: 0 | H12: 44444.444
A13: 9. AC & DC installation | B13: 0 | C13: 11532.222 | D13: 92254.671 | E13: 11535.325 | F13: 0 | H13: 115322.22
A14: 10. Site Logistics | C14: 3912.4293 | D14: 32194.116 | E14: 3912.4177 | F14: 0 | H14: 40018.963
A15: 11. Due Dilligence | B15: 0 | E15: 32222.222 | F15: 0 | H15: 32222.222
A16: 13. Engineering | B16: 0 | G16: 13287.721 | H16: 13287.721
A17: 14. General Expenses | B17: 0 | D17: 1960.1664 | E17: 567.60984 | F17: 0 | G17: 0 | H17: 2527.7762
A18: 15. Service Add On
A19: 12. BDP Commission
A20: 7.BESS
A21: Grand Total | B21: 0 | C21: 786382.14 | D21: 451468.42 | E21: 41191.07 | F21: 0 | G21: 13287.721 | H21: 1292329.3

Sheet Finance - COS
A3: Sum of Actual Total | B3: Column Labels
A4: Row Labels | B4: (blank) | C4: 45961 | D4: 45991 | E4: 46022 | G4: 46053 | H4: Grand Total
A5: (blank)
A6: 1. Panels | B6: 0 | C6: 245463.93 | D6: -8105.88 | H6: 237358.05
A7: 2. Inverters | C7: 65246 | H7: 65246
A8: 3. Mounting Structures | D8: 33946 | H8: 33946
A9: 4. DC Equipment | C9: 56973.86 | D9: 23780.87 | E9: 2973.82 | H9: 83728.55
A10: 5. Monitoring | C10: 48217.33 | D10: 8760.67 | E10: 1300 | H10: 58278
A11: 6. AC Equipment | C11: 3412.26 | D11: 87701.65 | E11: 3412.24 | H11: 94526.15
A12: 8. Product Add On | C12: 16450 | D12: 8450 | H12: 24900
A13: 9. AC & DC installation | C13: 18598.621 | D13: 148738.93 | E13: 18598.6 | H13: 185936.16
A14: 10. Site Logistics | C14: 6704.05 | D14: 55165.46 | E14: 6704.03 | H14: 68573.54
A15: 11. Due Dilligence | B15: 0 | E15: 15565 | H15: 15565
A16: 13. Engineering | B16: 0 | G16: 16154.12 | H16: 16154.12
A17: 14. General Expenses | D17: 863.34 | E17: 1023.4 | G17: 136.45 | H17: 2023.19
A18: 15. Service Add On | D18: 3650 | H18: 3650
A19: 12. BDP Commission | B19: 0 | H19: 0
A20: 7.BESS
A21: Grand Total | B21: 0 | C21: 461066.05 | D21: 362951.04 | E21: 49577.09 | G21: 16290.57 | H21: 889884.76

Sheet Project Margins
A1: [capture project margins from costing sheet]
A3: Products | D3: 0.32
A4: Services | D4: 0.5
A5: Expenses | D5: 0.15
A6: Subcontractors | D6: 0.2

Sheet Equipment Quotes
B2: Equipment Quote and Budget comparision
B4: Description | D4: Budget | F4: Supplier 1 | H4: Variance | J4: Supplier 2 | L4: Variance | N4: Comments / Notes
F7: >Name< | J7: >Name<
B9: Inverters | D9: =SUM(D10:D11) -> #REF! | F9: =SUM(F10:F13) -> 0 | H9: =$D$9-F9 -> #REF! | J9: =SUM(J10:J13) -> 0 | L9: =$D$9-J9 -> #REF!
B10: Inverters | D10: =#REF! -> #REF!
B11: Optimizers | D11: =#REF! -> #REF!
B12: Warranty
B13: Delivery fee
F15: >Name< | J15: >Name<
B17: Mounting Structure | D17: =SUM(D18:D19) -> #REF! | F17: =SUM(F18:F20) -> 0 | H17: =$D$17- F17 -> #REF! | J17: =SUM(J18:J20) -> 0 | L17: =$D$17- J17 -> #REF!
B18: Mounting Structure | D18: =#REF! -> #REF!
B19: Delivery fee
F21: >Name< | J21: >Name<
B23: DC Cable | D23: =SUM(D24:D25) -> #REF! | F23: =SUM(F24:F25) -> 0 | H23: =$D$23- F23 -> #REF! | J23: =SUM(J24:J25) -> 0 | L23: =$D$23- J23 -> #REF!
B24: DC Cable | D24: =#REF! -> #REF!
B25: Delivery fee
F27: >Name< | J27: >Name<
B29: Monitoring system | D29: =SUM(D30:D32) -> #REF! | F29: =SUM(F30:F42) -> 0 | H29: =$D$29-F29 -> #REF! | J29: =SUM(J30:J32) -> 0 | L29: =$D$29-J29 -> #REF!
B30: =#REF! -> #REF! | D30: =#REF! -> #REF!
B31: =#REF! -> #REF! | D31: =#REF! -> #REF!
B32: Delivery fee
F34: >Name< | J34: >Name<
B36: Additional Scope | D36: =SUM(D37:D41) -> #REF! | F36: =SUM(F37:F41) -> 0 | H36: =$D$29-F36 -> #REF! | J36: =SUM(J37:J41) -> 0 | L36: =$D$29-J36 -> #REF!
B37: SCADA | D37: =#REF! -> #REF!
B38: Inverter cage
B39: Cat ladders
B40: Gen Integration
B41: Lifelines
B43: Totals | D43: =D36+D29+D23+D17+D9 -> #REF! | H43: =SUM(H7:H42) -> #REF! | L43: =SUM(L7:L42) -> #REF!
B47: All amounts are incl VAT

Sheet Installer Quotes
B2: Installer Quote and Budget comparision
B4: Description | D4: Budget | G4: Cosmic Sun | J4: Variance | L4: Matthews Group | O4: Variance
B6: AC Equipment | D6: =#REF! -> #REF! | E6: =D6/(1000*#REF!) -> #REF! | G6: 277892.91 | H6: =G6/(#REF!*1000) -> #REF! | J6: =D6-G6 -> #REF! | M6: =L6/(#REF!*1000) -> #REF! | O6: =D6-L6 -> #REF!
B7: DC Equipment | D7: =#REF! -> #REF! | E7: =D7/(1000*#REF!) -> #REF! | G7: 142158.25 | H7: =G7/(#REF!*1000) -> #REF! | J7: =D7-G7 -> #REF! | M7: =L7/(#REF!*1000) -> #REF! | O7: =D7-L7 -> #REF!
B8: AC Labour | D8: =#REF! -> #REF! | E8: =D8/(1000*#REF!) -> #REF! | G8: 96174 | H8: =G8/(#REF!*1000) -> #REF! | J8: =D8-G8 -> #REF! | M8: =L8/(#REF!*1000) -> #REF! | O8: =D8-L8 -> #REF!
B9: DC Labour | D9: =#REF! -> #REF! | E9: =D9/(1000*#REF!) -> #REF! | G9: 230160 | H9: =G9/(#REF!*1000) -> #REF! | J9: =D9-G9 -> #REF! | M9: =L9/(#REF!*1000) -> #REF! | O9: =D9-L9 -> #REF!
B10: Offloading | D10: =#REF! -> #REF! | G10: 0 | J10: =D10-G10 -> #REF! | O10: =D10-L10 -> #REF!
B11: Roof Access/Scaffolding | D11: =#REF! -> #REF! | G11: 29257.61 | J11: =D11-G11 -> #REF! | O11: =D11-L11 -> #REF!
B12: Storage | D12: =#REF! -> #REF! | J12: =D12-G12 -> #REF! | O12: =D12-L12 -> #REF!
B13: Telehandler | D13: =#REF! -> #REF!
B14: HSE | D14: 0
B15: Totals | D15: =SUM(D6:D13) -> #REF! | G15: =SUM(G6:G13) -> 775642.77 | J15: =SUM(J6:J14) -> #REF! | L15: =SUM(L6:L13) -> 0 | O15: =SUM(O6:O14) -> #REF!
B18: Description | D18: Budget | G18: >Installer Name 3< | J18: Variance | L18: >Installer Name 4< | O18: Variance
B20: AC installation | D20: =#REF! -> #REF! | E20: =D20/(1000*#REF!) -> #REF! | H20: =G20/(1000*#REF!) -> #REF! | J20: =D20-G20 -> #REF! | M20: =L20/(1000*#REF!) -> #REF! | O20: =D6-L20 -> #REF!
B21: AC equipment | D21: =#REF! -> #REF! | E21: =D21/(1000*#REF!) -> #REF! | J21: =D21-G21 -> #REF! | M21: =L21/(1000*#REF!) -> #REF! | O21: =D7-L21 -> #REF!
B22: DC installation | D22: =#REF! -> #REF! | E22: =D22/(1000*#REF!) -> #REF! | H22: =G22/(1000*#REF!) -> #REF! | J22: =D22-G22 -> #REF! | M22: =L22/(1000*#REF!) -> #REF! | O22: =D8-L22 -> #REF!
B23: DC equipment | D23: =SUM(#REF!) -> #REF! | E23: =D23/(1000*#REF!) -> #REF! | J23: =D23-G23 -> #REF! | O23: =D9-L23 -> #REF!
B24: Storage | D24: =#REF! -> #REF! | J24: =D24-G24 -> #REF! | O24: =D10-L24 -> #REF!
B25: Panel lifting equipment | D25: =SUM(#REF!) -> #REF! | J25: =D25-G25 -> #REF! | O25: =D11-L25 -> #REF!
B26: Offloading | D26: =#REF! -> #REF! | J26: =D26-G26 -> #REF! | O26: =D12-L26 -> #REF!
B29: Totals | D29: =SUM(D20:D27) -> #REF! | G29: =SUM(G20:G27) -> 0 | J29: =SUM(J20:J28) -> #REF! | L29: =SUM(L20:L27) -> 0 | O29: =SUM(O20:O28) -> #REF!
B32: Budget Summary
B34: Budget | D34: =D15 -> #REF!
B35: =G4 -> Cosmic Sun | D35: =G15 -> 775642.77
B36: =L4 -> Matthews Group | D36: =L15 -> 0
B37: =G18 -> >Installer Name 3< | D37: =G29 -> 0
B38: =L18 -> >Installer Name 4< | D38: =L29 -> 0
B40: =IF(D40<D34,"Saving","Loss") -> #REF! | D40: =D34-MIN(D35:D38) -> #REF!
B42: All amounts are exc VAT

Sheet Decision Register
B1: =D15 -> #REF! | E1: Decision Register
B3: ID | C3: Decision Description | D3: Decision Impact | E3: Proposed Date | F3: Proposed By | G3: Status | H3: Approved By | I3: Date | J3: Results / Comments
B4: DEC001
B5: DEC002
B6: DEC003
B7: DEC004
B8: DEC005
B9: DEC006
B10: DEC007
B11: DEC008
B12: DEC009
B13: DEC010
D15: {=#REF!} -> #REF!
