Workbook
Name Inverter_Capacity: #REF!
Name Inverter_Supplier: #REF!
Name Project_Size: 'Certificate - Financial Close'!Projectsize
Name Project_Size: Compliance!Projectsize
Name Project_Size: 'Finance - Revenue'!Projectsize
Name Project_Size: Projectsize
Name Projectsize: #REF!
Name Projectsize: #REF!
Name Projectsize: #REF!
Name Projectsize: 'Project Margins'!$K$5
Name Security_Serv: #REF!
Name Security_Serv: #REF!
Name SSS: #REF!
Name SSS: #REF!
Name USD_ZAR: #REF!

Sheet Sheet1
A1: PROJECT PLAN
A2: # | B2: Project Milestone | C2: Planned Start Date | D2: Duration (Work Days) | E2: Planned End Date | F2: Actual Start Date | H2: Actual End Date | J2: Comments | L2: =C3 -> 43831 | M2: =L2+3 -> 43834 | N2: =M2+7 -> 43841 | O2: =N2+7 -> 43848 | P2: =O2+7 -> 43855 | Q2: =P2+6 -> 43861 | R2: =Q2+1 -> 43862 | S2: =R2+7 -> 43869 | T2: =S2+7 -> 43876 | U2: =T2+7 -> 43883 | V2: =U2+6 -> 43889 | W2: =V2+7 -> 43896 | X2: =W2+7 -> 43903 | Y2: =X2+7 -> 43910 | Z2: =Y2+7 -> 43917 | AA2: =Z2+3 -> 43920 | AB2: =AA2+4 -> 43924 | AC2: =AB2+7 -> 43931 | AD2: =AC2+7 -> 43938 | AE2: =AD2+7 -> 43945 | AF2: =AE2+6 -> 43951 | AG2: =AF2+2 -> 43953 | AH2: =AG2+7 -> 43960 | AI2: =AH2+7 -> 43967 | AJ2: =AI2+7 -> 43974 | AK2: =AJ2+7 -> 43981 | AL2: =AK2+1 -> 43982 | AM2: =AL2+6 -> 43988 | AN2: =AM2+7 -> 43995 | AO2: =AN2+7 -> 44002 | AP2: =AO2+7 -> 44009 | AQ2: =AP2+3 -> 44012 | AR2: =AQ2+4 -> 44016 | AS2: =AR2+7 -> 44023 | AT2: =AS2+7 -> 44030 | AU2: =AT2+7 -> 44037 | AV2: =AU2+6 -> 44043 | AW2: =AV2+1 -> 44044 | AX2: =AW2+7 -> 44051 | AY2: =AX2+7 -> 44058 | AZ2: =AY2+7 -> 44065 | BA2: =AZ2+7 -> 44072 | BB2: =BA2+2 -> 44074 | BC2: =BB2+5 -> 44079 | BD2: =BC2+7 -> 44086 | BE2: =BD2+7 -> 44093 | BF2: =BE2+7 -> 44100 | BG2: =BF2+4 -> 44104
A3: 1 | B3: Contract Signature | C3: 43831 | D3: 1 | E3: 43832 | F3: 43831 | G3: 1 | H3: 43832 | L3: =IF(AND($F3<(L$2+7),$F3>L$2),1, IF(AND($H3<L$2+7,$H3>L$2),3, IF(AND($F3<=L$2, $H3>=L$2), 2, "" ))) -> 3 | M3: =IF(AND($F3<(M$2+7),$F3>M$2),1, IF(AND($H3<M$2+7,$H3>M$2),3, IF(AND($F3<=M$2, $H3>=M$2), 2, "" ))) | N3: =IF(AND($F3<(N$2+7),$F3>N$2),1, IF(AND($H3<N$2+7,$H3>N$2),3, IF(AND($F3<=N$2, $H3>=N$2), 2, "" ))) | O3: =IF(AND($F3<(O$2+7),$F3>O$2),1, IF(AND($H3<O$2+7,$H3>O$2),3, IF(AND($F3<=O$2, $H3>=O$2), 2, "" ))) | P3: =IF(AND($F3<(P$2+7),$F3>P$2),1, IF(AND($H3<P$2+7,$H3>P$2),3, IF(AND($F3<=P$2, $H3>=P$2), 2, "" ))) | Q3: =IF(AND($F3<(Q$2+7),$F3>Q$2),1, IF(AND($H3<Q$2+7,$H3>Q$2),3, IF(AND($F3<=Q$2, $H3>=Q$2), 2, "" ))) | R3: =IF(AND($F3<(R$2+7),$F3>R$2),1, IF(AND($H3<R$2+7,$H3>R$2),3, IF(AND($F3<=R$2, $H3>=R$2), 2, "" ))) | S3: =IF(AND($F3<(S$2+7),$F3>S$2),1, IF(AND($H3<S$2+7,$H3>S$2),3, IF(AND($F3<=S$2, $H3>=S$2), 2, "" ))) | ... AQ3: =IF(AND($F3<(AQ$2+7),$F3>AQ$2),1, IF(AND($H3<AQ$2+7,$H3>AQ$2),3, IF(AND($F3<=AQ$2, $H3>=AQ$2), 2, "" )))
A4: A | B4: PAYMENT MILESTONE 1: DEPOSIT | C4: 43832 | D4: 1 | E4: 43833 | F4: 43832 | G4: 1 | H4: 43833 | L4: =IF(AND($F4<(L$2+7),$F4>L$2),1, IF(AND($H4<L$2+7,$H4>L$2),3, IF(AND($F4<=L$2, $H4>=L$2), 2, "" ))) -> 1 | M4: =IF(AND($F4<(M$2+7),$F4>M$2),1, IF(AND($H4<M$2+7,$H4>M$2),3, IF(AND($F4<=M$2, $H4>=M$2), 2, "" ))) | N4: =IF(AND($F4<(N$2+7),$F4>N$2),1, IF(AND($H4<N$2+7,$H4>N$2),3, IF(AND($F4<=N$2, $H4>=N$2), 2, "" ))) | O4: =IF(AND($F4<(O$2+7),$F4>O$2),1, IF(AND($H4<O$2+7,$H4>O$2),3, IF(AND($F4<=O$2, $H4>=O$2), 2, "" ))) | P4: =IF(AND($F4<(P$2+7),$F4>P$2),1, IF(AND($H4<P$2+7,$H4>P$2),3, IF(AND($F4<=P$2, $H4>=P$2), 2, "" ))) | Q4: =IF(AND($F4<(Q$2+7),$F4>Q$2),1, IF(AND($H4<Q$2+7,$H4>Q$2),3, IF(AND($F4<=Q$2, $H4>=Q$2), 2, "" ))) | R4: =IF(AND($F4<(R$2+7),$F4>R$2),1, IF(AND($H4<R$2+7,$H4>R$2),3, IF(AND($F4<=R$2, $H4>=R$2), 2, "" ))) | S4: =IF(AND($F4<(S$2+7),$F4>S$2),1, IF(AND($H4<S$2+7,$H4>S$2),3, IF(AND($F4<=S$2, $H4>=S$2), 2, "" ))) | ... AQ4: =IF(AND($F4<(AQ$2+7),$F4>AQ$2),1, IF(AND($H4<AQ$2+7,$H4>AQ$2),3, IF(AND($F4<=AQ$2, $H4>=AQ$2), 2, "" )))
A5: 2 | B5: Structural and Electrical Due Diligences | C5: 43833 | D5: 5 | E5: 43840 | F5: 43833 | G5: 5 | H5: 43840 | L5: =IF(AND($F5<(L$2+7),$F5>L$2),1, IF(AND($H5<L$2+7,$H5>L$2),3, IF(AND($F5<=L$2, $H5>=L$2), 2, "" ))) -> 1 | M5: =IF(AND($F5<(M$2+7),$F5>M$2),1, IF(AND($H5<M$2+7,$H5>M$2),3, IF(AND($F5<=M$2, $H5>=M$2), 2, "" ))) -> 3 | N5: =IF(AND($F5<(N$2+7),$F5>N$2),1, IF(AND($H5<N$2+7,$H5>N$2),3, IF(AND($F5<=N$2, $H5>=N$2), 2, "" ))) | O5: =IF(AND($F5<(O$2+7),$F5>O$2),1, IF(AND($H5<O$2+7,$H5>O$2),3, IF(AND($F5<=O$2, $H5>=O$2), 2, "" ))) | P5: =IF(AND($F5<(P$2+7),$F5>P$2),1, IF(AND($H5<P$2+7,$H5>P$2),3, IF(AND($F5<=P$2, $H5>=P$2), 2, "" ))) | Q5: =IF(AND($F5<(Q$2+7),$F5>Q$2),1, IF(AND($H5<Q$2+7,$H5>Q$2),3, IF(AND($F5<=Q$2, $H5>=Q$2), 2, "" ))) | R5: =IF(AND($F5<(R$2+7),$F5>R$2),1, IF(AND($H5<R$2+7,$H5>R$2),3, IF(AND($F5<=R$2, $H5>=R$2), 2, "" ))) | S5: =IF(AND($F5<(S$2+7),$F5>S$2),1, IF(AND($H5<S$2+7,$H5>S$2),3, IF(AND($F5<=S$2, $H5>=S$2), 2, "" ))) | ... AQ5: =IF(AND($F5<(AQ$2+7),$F5>AQ$2),1, IF(AND($H5<AQ$2+7,$H5>AQ$2),3, IF(AND($F5<=AQ$2, $H5>=AQ$2), 2, "" )))
A6: 3 | B6: Design Confirmation | C6: 43841 | D6: 2 | E6: 43844 | F6: 43841 | G6: 2 | H6: 43844 | L6: =IF(AND($F6<(L$2+7),$F6>L$2),1, IF(AND($H6<L$2+7,$H6>L$2),3, IF(AND($F6<=L$2, $H6>=L$2), 2, "" ))) | M6: =IF(AND($F6<(M$2+7),$F6>M$2),1, IF(AND($H6<M$2+7,$H6>M$2),3, IF(AND($F6<=M$2, $H6>=M$2), 2, "" ))) | N6: =IF(AND($F6<(N$2+7),$F6>N$2),1, IF(AND($H6<N$2+7,$H6>N$2),3, IF(AND($F6<=N$2, $H6>=N$2), 2, "" ))) -> 3 | O6: =IF(AND($F6<(O$2+7),$F6>O$2),1, IF(AND($H6<O$2+7,$H6>O$2),3, IF(AND($F6<=O$2, $H6>=O$2), 2, "" ))) | P6: =IF(AND($F6<(P$2+7),$F6>P$2),1, IF(AND($H6<P$2+7,$H6>P$2),3, IF(AND($F6<=P$2, $H6>=P$2), 2, "" ))) | Q6: =IF(AND($F6<(Q$2+7),$F6>Q$2),1, IF(AND($H6<Q$2+7,$H6>Q$2),3, IF(AND($F6<=Q$2, $H6>=Q$2), 2, "" ))) | R6: =IF(AND($F6<(R$2+7),$F6>R$2),1, IF(AND($H6<R$2+7,$H6>R$2),3, IF(AND($F6<=R$2, $H6>=R$2), 2, "" ))) | S6: =IF(AND($F6<(S$2+7),$F6>S$2),1, IF(AND($H6<S$2+7,$H6>S$2),3, IF(AND($F6<=S$2, $H6>=S$2), 2, "" ))) | ... AQ6: =IF(AND($F6<(AQ$2+7),$F6>AQ$2),1, IF(AND($H6<AQ$2+7,$H6>AQ$2),3, IF(AND($F6<=AQ$2, $H6>=AQ$2), 2, "" )))
A7: 4 | B7: Equipment Procurement | C7: 43833 | E7: 43949 | F7: 43833 | H7: 43949 | L7: =IF(AND($F7<(L$2+7),$F7>L$2),1, IF(AND($H7<L$2+7,$H7>L$2),3, IF(AND($F7<=L$2, $H7>=L$2), 2, "" ))) -> 1 | M7: =IF(AND($F7<(M$2+7),$F7>M$2),1, IF(AND($H7<M$2+7,$H7>M$2),3, IF(AND($F7<=M$2, $H7>=M$2), 2, "" ))) -> 2 | N7: =IF(AND($F7<(N$2+7),$F7>N$2),1, IF(AND($H7<N$2+7,$H7>N$2),3, IF(AND($F7<=N$2, $H7>=N$2), 2, "" ))) -> 2 | O7: =IF(AND($F7<(O$2+7),$F7>O$2),1, IF(AND($H7<O$2+7,$H7>O$2),3, IF(AND($F7<=O$2, $H7>=O$2), 2, "" ))) -> 2 | P7: =IF(AND($F7<(P$2+7),$F7>P$2),1, IF(AND($H7<P$2+7,$H7>P$2),3, IF(AND($F7<=P$2, $H7>=P$2), 2, "" ))) -> 2 | Q7: =IF(AND($F7<(Q$2+7),$F7>Q$2),1, IF(AND($H7<Q$2+7,$H7>Q$2),3, IF(AND($F7<=Q$2, $H7>=Q$2), 2, "" ))) -> 2 | R7: =IF(AND($F7<(R$2+7),$F7>R$2),1, IF(AND($H7<R$2+7,$H7>R$2),3, IF(AND($F7<=R$2, $H7>=R$2), 2, "" ))) -> 2 | S7: =IF(AND($F7<(S$2+7),$F7>S$2),1, IF(AND($H7<S$2+7,$H7>S$2),3, IF(AND($F7<=S$2, $H7>=S$2), 2, "" ))) -> 2 | ... AQ7: =IF(AND($F7<(AQ$2+7),$F7>AQ$2),1, IF(AND($H7<AQ$2+7,$H7>AQ$2),3, IF(AND($F7<=AQ$2, $H7>=AQ$2), 2, "" )))
B8: Panel Procurement | C8: 43833 | D8: 5 | E8: 43840 | F8: 43833 | G8: 5 | H8: 43840 | L8: =IF(AND($F8<(L$2+7),$F8>L$2),1, IF(AND($H8<L$2+7,$H8>L$2),3, IF(AND($F8<=L$2, $H8>=L$2), 2, "" ))) -> 1 | M8: =IF(AND($F8<(M$2+7),$F8>M$2),1, IF(AND($H8<M$2+7,$H8>M$2),3, IF(AND($F8<=M$2, $H8>=M$2), 2, "" ))) -> 3 | N8: =IF(AND($F8<(N$2+7),$F8>N$2),1, IF(AND($H8<N$2+7,$H8>N$2),3, IF(AND($F8<=N$2, $H8>=N$2), 2, "" ))) | O8: =IF(AND($F8<(O$2+7),$F8>O$2),1, IF(AND($H8<O$2+7,$H8>O$2),3, IF(AND($F8<=O$2, $H8>=O$2), 2, "" ))) | P8: =IF(AND($F8<(P$2+7),$F8>P$2),1, IF(AND($H8<P$2+7,$H8>P$2),3, IF(AND($F8<=P$2, $H8>=P$2), 2, "" ))) | Q8: =IF(AND($F8<(Q$2+7),$F8>Q$2),1, IF(AND($H8<Q$2+7,$H8>Q$2),3, IF(AND($F8<=Q$2, $H8>=Q$2), 2, "" ))) | R8: =IF(AND($F8<(R$2+7),$F8>R$2),1, IF(AND($H8<R$2+7,$H8>R$2),3, IF(AND($F8<=R$2, $H8>=R$2), 2, "" ))) | S8: =IF(AND($F8<(S$2+7),$F8>S$2),1, IF(AND($H8<S$2+7,$H8>S$2),3, IF(AND($F8<=S$2, $H8>=S$2), 2, "" ))) | ... AQ8: =IF(AND($F8<(AQ$2+7),$F8>AQ$2),1, IF(AND($H8<AQ$2+7,$H8>AQ$2),3, IF(AND($F8<=AQ$2, $H8>=AQ$2), 2, "" )))
B9: Inverter Procurement | C9: 43941 | D9: 5 | E9: 43949 | F9: 43941 | G9: 5 | H9: 43949 | L9: =IF(AND($F9<(L$2+7),$F9>L$2),1, IF(AND($H9<L$2+7,$H9>L$2),3, IF(AND($F9<=L$2, $H9>=L$2), 2, "" ))) | M9: =IF(AND($F9<(M$2+7),$F9>M$2),1, IF(AND($H9<M$2+7,$H9>M$2),3, IF(AND($F9<=M$2, $H9>=M$2), 2, "" ))) | N9: =IF(AND($F9<(N$2+7),$F9>N$2),1, IF(AND($H9<N$2+7,$H9>N$2),3, IF(AND($F9<=N$2, $H9>=N$2), 2, "" ))) | O9: =IF(AND($F9<(O$2+7),$F9>O$2),1, IF(AND($H9<O$2+7,$H9>O$2),3, IF(AND($F9<=O$2, $H9>=O$2), 2, "" ))) | P9: =IF(AND($F9<(P$2+7),$F9>P$2),1, IF(AND($H9<P$2+7,$H9>P$2),3, IF(AND($F9<=P$2, $H9>=P$2), 2, "" ))) | Q9: =IF(AND($F9<(Q$2+7),$F9>Q$2),1, IF(AND($H9<Q$2+7,$H9>Q$2),3, IF(AND($F9<=Q$2, $H9>=Q$2), 2, "" ))) | R9: =IF(AND($F9<(R$2+7),$F9>R$2),1, IF(AND($H9<R$2+7,$H9>R$2),3, IF(AND($F9<=R$2, $H9>=R$2), 2, "" ))) | S9: =IF(AND($F9<(S$2+7),$F9>S$2),1, IF(AND($H9<S$2+7,$H9>S$2),3, IF(AND($F9<=S$2, $H9>=S$2), 2, "" ))) | ... AQ9: =IF(AND($F9<(AQ$2+7),$F9>AQ$2),1, IF(AND($H9<AQ$2+7,$H9>AQ$2),3, IF(AND($F9<=AQ$2, $H9>=AQ$2), 2, "" )))
B10: Mounting Structure Procurement | C10: 43941 | D10: 5 | E10: 43949 | F10: 43941 | G10: 5 | H10: 43949 | L10: =IF(AND($F10<(L$2+7),$F10>L$2),1, IF(AND($H10<L$2+7,$H10>L$2),3, IF(AND($F10<=L$2, $H10>=L$2), 2, "" ))) | M10: =IF(AND($F10<(M$2+7),$F10>M$2),1, IF(AND($H10<M$2+7,$H10>M$2),3, IF(AND($F10<=M$2, $H10>=M$2), 2, "" ))) | N10: =IF(AND($F10<(N$2+7),$F10>N$2),1, IF(AND($H10<N$2+7,$H10>N$2),3, IF(AND($F10<=N$2, $H10>=N$2), 2, "" ))) | O10: =IF(AND($F10<(O$2+7),$F10>O$2),1, IF(AND($H10<O$2+7,$H10>O$2),3, IF(AND($F10<=O$2, $H10>=O$2), 2, "" ))) | P10: =IF(AND($F10<(P$2+7),$F10>P$2),1, IF(AND($H10<P$2+7,$H10>P$2),3, IF(AND($F10<=P$2, $H10>=P$2), 2, "" ))) | Q10: =IF(AND($F10<(Q$2+7),$F10>Q$2),1, IF(AND($H10<Q$2+7,$H10>Q$2),3, IF(AND($F10<=Q$2, $H10>=Q$2), 2, "" ))) | R10: =IF(AND($F10<(R$2+7),$F10>R$2),1, IF(AND($H10<R$2+7,$H10>R$2),3, IF(AND($F10<=R$2, $H10>=R$2), 2, "" ))) | S10: =IF(AND($F10<(S$2+7),$F10>S$2),1, IF(AND($H10<S$2+7,$H10>S$2),3, IF(AND($F10<=S$2, $H10>=S$2), 2, "" ))) | ... AQ10: =IF(AND($F10<(AQ$2+7),$F10>AQ$2),1, IF(AND($H10<AQ$2+7,$H10>AQ$2),3, IF(AND($F10<=AQ$2, $H10>=AQ$2), 2, "" )))
B11: BOS Procurement | C11: 43941 | D11: 5 | E11: 43949 | F11: 43941 | G11: 5 | H11: 43949 | L11: =IF(AND($F11<(L$2+7),$F11>L$2),1, IF(AND($H11<L$2+7,$H11>L$2),3, IF(AND($F11<=L$2, $H11>=L$2), 2, "" ))) | M11: =IF(AND($F11<(M$2+7),$F11>M$2),1, IF(AND($H11<M$2+7,$H11>M$2),3, IF(AND($F11<=M$2, $H11>=M$2), 2, "" ))) | N11: =IF(AND($F11<(N$2+7),$F11>N$2),1, IF(AND($H11<N$2+7,$H11>N$2),3, IF(AND($F11<=N$2, $H11>=N$2), 2, "" ))) | O11: =IF(AND($F11<(O$2+7),$F11>O$2),1, IF(AND($H11<O$2+7,$H11>O$2),3, IF(AND($F11<=O$2, $H11>=O$2), 2, "" ))) | P11: =IF(AND($F11<(P$2+7),$F11>P$2),1, IF(AND($H11<P$2+7,$H11>P$2),3, IF(AND($F11<=P$2, $H11>=P$2), 2, "" ))) | Q11: =IF(AND($F11<(Q$2+7),$F11>Q$2),1, IF(AND($H11<Q$2+7,$H11>Q$2),3, IF(AND($F11<=Q$2, $H11>=Q$2), 2, "" ))) | R11: =IF(AND($F11<(R$2+7),$F11>R$2),1, IF(AND($H11<R$2+7,$H11>R$2),3, IF(AND($F11<=R$2, $H11>=R$2), 2, "" ))) | S11: =IF(AND($F11<(S$2+7),$F11>S$2),1, IF(AND($H11<S$2+7,$H11>S$2),3, IF(AND($F11<=S$2, $H11>=S$2), 2, "" ))) | ... AQ11: =IF(AND($F11<(AQ$2+7),$F11>AQ$2),1, IF(AND($H11<AQ$2+7,$H11>AQ$2),3, IF(AND($F11<=AQ$2, $H11>=AQ$2), 2, "" )))
A12: 5 | B12: Internal Project Kick off | C12: 43936 | D12: 5 | E12: 43943 | F12: 43936 | G12: 5 | H12: 43943
A13: 6 | B13: Client Project Kick-off | C13: 43963 | D13: 5 | E13: 43970 | F13: 43963 | G13: 5 | H13: 43970 | L13: =IF(AND($F13<(L$2+7),$F13>L$2),1, IF(AND($H13<L$2+7,$H13>L$2),3, IF(AND($F13<=L$2, $H13>=L$2), 2, "" ))) | M13: =IF(AND($F13<(M$2+7),$F13>M$2),1, IF(AND($H13<M$2+7,$H13>M$2),3, IF(AND($F13<=M$2, $H13>=M$2), 2, "" ))) | N13: =IF(AND($F13<(N$2+7),$F13>N$2),1, IF(AND($H13<N$2+7,$H13>N$2),3, IF(AND($F13<=N$2, $H13>=N$2), 2, "" ))) | O13: =IF(AND($F13<(O$2+7),$F13>O$2),1, IF(AND($H13<O$2+7,$H13>O$2),3, IF(AND($F13<=O$2, $H13>=O$2), 2, "" ))) | P13: =IF(AND($F13<(P$2+7),$F13>P$2),1, IF(AND($H13<P$2+7,$H13>P$2),3, IF(AND($F13<=P$2, $H13>=P$2), 2, "" ))) | Q13: =IF(AND($F13<(Q$2+7),$F13>Q$2),1, IF(AND($H13<Q$2+7,$H13>Q$2),3, IF(AND($F13<=Q$2, $H13>=Q$2), 2, "" ))) | R13: =IF(AND($F13<(R$2+7),$F13>R$2),1, IF(AND($H13<R$2+7,$H13>R$2),3, IF(AND($F13<=R$2, $H13>=R$2), 2, "" ))) | S13: =IF(AND($F13<(S$2+7),$F13>S$2),1, IF(AND($H13<S$2+7,$H13>S$2),3, IF(AND($F13<=S$2, $H13>=S$2), 2, "" ))) | ... AQ13: =IF(AND($F13<(AQ$2+7),$F13>AQ$2),1, IF(AND($H13<AQ$2+7,$H13>AQ$2),3, IF(AND($F13<=AQ$2, $H13>=AQ$2), 2, "" )))
A14: 7 | B14: Equipment Delivery | C14: 43983 | D14: 9 | E14: 43994 | F14: 43983 | G14: 9 | H14: 43994 | L14: =IF(AND($F14<(L$2+7),$F14>L$2),1, IF(AND($H14<L$2+7,$H14>L$2),3, IF(AND($F14<=L$2, $H14>=L$2), 2, "" ))) | M14: =IF(AND($F14<(M$2+7),$F14>M$2),1, IF(AND($H14<M$2+7,$H14>M$2),3, IF(AND($F14<=M$2, $H14>=M$2), 2, "" ))) | N14: =IF(AND($F14<(N$2+7),$F14>N$2),1, IF(AND($H14<N$2+7,$H14>N$2),3, IF(AND($F14<=N$2, $H14>=N$2), 2, "" ))) | O14: =IF(AND($F14<(O$2+7),$F14>O$2),1, IF(AND($H14<O$2+7,$H14>O$2),3, IF(AND($F14<=O$2, $H14>=O$2), 2, "" ))) | P14: =IF(AND($F14<(P$2+7),$F14>P$2),1, IF(AND($H14<P$2+7,$H14>P$2),3, IF(AND($F14<=P$2, $H14>=P$2), 2, "" ))) | Q14: =IF(AND($F14<(Q$2+7),$F14>Q$2),1, IF(AND($H14<Q$2+7,$H14>Q$2),3, IF(AND($F14<=Q$2, $H14>=Q$2), 2, "" ))) | R14: =IF(AND($F14<(R$2+7),$F14>R$2),1, IF(AND($H14<R$2+7,$H14>R$2),3, IF(AND($F14<=R$2, $H14>=R$2), 2, "" ))) | S14: =IF(AND($F14<(S$2+7),$F14>S$2),1, IF(AND($H14<S$2+7,$H14>S$2),3, IF(AND($F14<=S$2, $H14>=S$2), 2, "" ))) | ... AQ14: =IF(AND($F14<(AQ$2+7),$F14>AQ$2),1, IF(AND($H14<AQ$2+7,$H14>AQ$2),3, IF(AND($F14<=AQ$2, $H14>=AQ$2), 2, "" )))
B15: Mounting Structure Delivery | C15: 43983 | D15: 2 | E15: 43985 | F15: 43983 | G15: 2 | H15: 43985
B16: Panel Delivery | C16: 43990 | D16: 2 | E16: 43992 | F16: 43990 | G16: 2 | H16: 43992 | L16: =IF(AND($F16<(L$2+7),$F16>L$2),1, IF(AND($H16<L$2+7,$H16>L$2),3, IF(AND($F16<=L$2, $H16>=L$2), 2, "" ))) | M16: =IF(AND($F16<(M$2+7),$F16>M$2),1, IF(AND($H16<M$2+7,$H16>M$2),3, IF(AND($F16<=M$2, $H16>=M$2), 2, "" ))) | N16: =IF(AND($F16<(N$2+7),$F16>N$2),1, IF(AND($H16<N$2+7,$H16>N$2),3, IF(AND($F16<=N$2, $H16>=N$2), 2, "" ))) | O16: =IF(AND($F16<(O$2+7),$F16>O$2),1, IF(AND($H16<O$2+7,$H16>O$2),3, IF(AND($F16<=O$2, $H16>=O$2), 2, "" ))) | P16: =IF(AND($F16<(P$2+7),$F16>P$2),1, IF(AND($H16<P$2+7,$H16>P$2),3, IF(AND($F16<=P$2, $H16>=P$2), 2, "" ))) | Q16: =IF(AND($F16<(Q$2+7),$F16>Q$2),1, IF(AND($H16<Q$2+7,$H16>Q$2),3, IF(AND($F16<=Q$2, $H16>=Q$2), 2, "" ))) | R16: =IF(AND($F16<(R$2+7),$F16>R$2),1, IF(AND($H16<R$2+7,$H16>R$2),3, IF(AND($F16<=R$2, $H16>=R$2), 2, "" ))) | S16: =IF(AND($F16<(S$2+7),$F16>S$2),1, IF(AND($H16<S$2+7,$H16>S$2),3, IF(AND($F16<=S$2, $H16>=S$2), 2, "" ))) | ... AQ16: =IF(AND($F16<(AQ$2+7),$F16>AQ$2),1, IF(AND($H16<AQ$2+7,$H16>AQ$2),3, IF(AND($F16<=AQ$2, $H16>=AQ$2), 2, "" )))
B17: Generator Delivery | C17: 43983 | D17: 2 | E17: 43985 | F17: 43983 | G17: 2 | H17: 43985
A18: B | B18: PAYMENT MILESTONE 2: DELIVERY OF PV PANELS | C18: 43992 | D18: 2 | E18: 43994 | F18: 43992 | G18: 2 | H18: 43994
B19: Inverter Delivery | C19: 43983 | D19: 2 | E19: 43985 | F19: 43983 | G19: 2 | H19: 43985 | L19: =IF(AND($F19<(L$2+7),$F19>L$2),1, IF(AND($H19<L$2+7,$H19>L$2),3, IF(AND($F19<=L$2, $H19>=L$2), 2, "" ))) | M19: =IF(AND($F19<(M$2+7),$F19>M$2),1, IF(AND($H19<M$2+7,$H19>M$2),3, IF(AND($F19<=M$2, $H19>=M$2), 2, "" ))) | N19: =IF(AND($F19<(N$2+7),$F19>N$2),1, IF(AND($H19<N$2+7,$H19>N$2),3, IF(AND($F19<=N$2, $H19>=N$2), 2, "" ))) | O19: =IF(AND($F19<(O$2+7),$F19>O$2),1, IF(AND($H19<O$2+7,$H19>O$2),3, IF(AND($F19<=O$2, $H19>=O$2), 2, "" ))) | P19: =IF(AND($F19<(P$2+7),$F19>P$2),1, IF(AND($H19<P$2+7,$H19>P$2),3, IF(AND($F19<=P$2, $H19>=P$2), 2, "" ))) | Q19: =IF(AND($F19<(Q$2+7),$F19>Q$2),1, IF(AND($H19<Q$2+7,$H19>Q$2),3, IF(AND($F19<=Q$2, $H19>=Q$2), 2, "" ))) | R19: =IF(AND($F19<(R$2+7),$F19>R$2),1, IF(AND($H19<R$2+7,$H19>R$2),3, IF(AND($F19<=R$2, $H19>=R$2), 2, "" ))) | S19: =IF(AND($F19<(S$2+7),$F19>S$2),1, IF(AND($H19<S$2+7,$H19>S$2),3, IF(AND($F19<=S$2, $H19>=S$2), 2, "" ))) | ... AQ19: =IF(AND($F19<(AQ$2+7),$F19>AQ$2),1, IF(AND($H19<AQ$2+7,$H19>AQ$2),3, IF(AND($F19<=AQ$2, $H19>=AQ$2), 2, "" )))
B20: BOS Delivery | C20: 43983 | D20: 1 | E20: 43984 | F20: 43983 | G20: 1 | H20: 43984 | L20: =IF(AND($F20<(L$2+7),$F20>L$2),1, IF(AND($H20<L$2+7,$H20>L$2),3, IF(AND($F20<=L$2, $H20>=L$2), 2, "" ))) | M20: =IF(AND($F20<(M$2+7),$F20>M$2),1, IF(AND($H20<M$2+7,$H20>M$2),3, IF(AND($F20<=M$2, $H20>=M$2), 2, "" ))) | N20: =IF(AND($F20<(N$2+7),$F20>N$2),1, IF(AND($H20<N$2+7,$H20>N$2),3, IF(AND($F20<=N$2, $H20>=N$2), 2, "" ))) | O20: =IF(AND($F20<(O$2+7),$F20>O$2),1, IF(AND($H20<O$2+7,$H20>O$2),3, IF(AND($F20<=O$2, $H20>=O$2), 2, "" ))) | P20: =IF(AND($F20<(P$2+7),$F20>P$2),1, IF(AND($H20<P$2+7,$H20>P$2),3, IF(AND($F20<=P$2, $H20>=P$2), 2, "" ))) | Q20: =IF(AND($F20<(Q$2+7),$F20>Q$2),1, IF(AND($H20<Q$2+7,$H20>Q$2),3, IF(AND($F20<=Q$2, $H20>=Q$2), 2, "" ))) | R20: =IF(AND($F20<(R$2+7),$F20>R$2),1, IF(AND($H20<R$2+7,$H20>R$2),3, IF(AND($F20<=R$2, $H20>=R$2), 2, "" ))) | S20: =IF(AND($F20<(S$2+7),$F20>S$2),1, IF(AND($H20<S$2+7,$H20>S$2),3, IF(AND($F20<=S$2, $H20>=S$2), 2, "" ))) | ... AQ20: =IF(AND($F20<(AQ$2+7),$F20>AQ$2),1, IF(AND($H20<AQ$2+7,$H20>AQ$2),3, IF(AND($F20<=AQ$2, $H20>=AQ$2), 2, "" )))
A21: C | B21: PAYMENT MILESTONE 3: DELIVERY OF INVERTERS AND BOS | C21: 43985 | D21: 2 | E21: 43987 | F21: 43985 | G21: 2 | H21: 43987
A22: 8 | B22: Installation | C22: 43990 | D22: 22 | E22: 44012 | F22: 43990 | G22: 22 | H22: 44012 | L22: =IF(AND($F22<(L$2+7),$F22>L$2),1, IF(AND($H22<L$2+7,$H22>L$2),3, IF(AND($F22<=L$2, $H22>=L$2), 2, "" ))) | M22: =IF(AND($F22<(M$2+7),$F22>M$2),1, IF(AND($H22<M$2+7,$H22>M$2),3, IF(AND($F22<=M$2, $H22>=M$2), 2, "" ))) | N22: =IF(AND($F22<(N$2+7),$F22>N$2),1, IF(AND($H22<N$2+7,$H22>N$2),3, IF(AND($F22<=N$2, $H22>=N$2), 2, "" ))) | O22: =IF(AND($F22<(O$2+7),$F22>O$2),1, IF(AND($H22<O$2+7,$H22>O$2),3, IF(AND($F22<=O$2, $H22>=O$2), 2, "" ))) | P22: =IF(AND($F22<(P$2+7),$F22>P$2),1, IF(AND($H22<P$2+7,$H22>P$2),3, IF(AND($F22<=P$2, $H22>=P$2), 2, "" ))) | Q22: =IF(AND($F22<(Q$2+7),$F22>Q$2),1, IF(AND($H22<Q$2+7,$H22>Q$2),3, IF(AND($F22<=Q$2, $H22>=Q$2), 2, "" ))) | R22: =IF(AND($F22<(R$2+7),$F22>R$2),1, IF(AND($H22<R$2+7,$H22>R$2),3, IF(AND($F22<=R$2, $H22>=R$2), 2, "" ))) | S22: =IF(AND($F22<(S$2+7),$F22>S$2),1, IF(AND($H22<S$2+7,$H22>S$2),3, IF(AND($F22<=S$2, $H22>=S$2), 2, "" ))) | ... AQ22: =IF(AND($F22<(AQ$2+7),$F22>AQ$2),1, IF(AND($H22<AQ$2+7,$H22>AQ$2),3, IF(AND($F22<=AQ$2, $H22>=AQ$2), 2, "" ))) -> 2
B23: Site Establishment | C23: 43990 | D23: 1 | E23: 43991 | F23: 43990 | G23: 1 | H23: 43991 | J23: Installation placed on hold due to Covid-19 case | L23: =IF(AND($F23<(L$2+7),$F23>L$2),1, IF(AND($H23<L$2+7,$H23>L$2),3, IF(AND($F23<=L$2, $H23>=L$2), 2, "" ))) | M23: =IF(AND($F23<(M$2+7),$F23>M$2),1, IF(AND($H23<M$2+7,$H23>M$2),3, IF(AND($F23<=M$2, $H23>=M$2), 2, "" ))) | N23: =IF(AND($F23<(N$2+7),$F23>N$2),1, IF(AND($H23<N$2+7,$H23>N$2),3, IF(AND($F23<=N$2, $H23>=N$2), 2, "" ))) | O23: =IF(AND($F23<(O$2+7),$F23>O$2),1, IF(AND($H23<O$2+7,$H23>O$2),3, IF(AND($F23<=O$2, $H23>=O$2), 2, "" ))) | P23: =IF(AND($F23<(P$2+7),$F23>P$2),1, IF(AND($H23<P$2+7,$H23>P$2),3, IF(AND($F23<=P$2, $H23>=P$2), 2, "" ))) | Q23: =IF(AND($F23<(Q$2+7),$F23>Q$2),1, IF(AND($H23<Q$2+7,$H23>Q$2),3, IF(AND($F23<=Q$2, $H23>=Q$2), 2, "" ))) | R23: =IF(AND($F23<(R$2+7),$F23>R$2),1, IF(AND($H23<R$2+7,$H23>R$2),3, IF(AND($F23<=R$2, $H23>=R$2), 2, "" ))) | S23: =IF(AND($F23<(S$2+7),$F23>S$2),1, IF(AND($H23<S$2+7,$H23>S$2),3, IF(AND($F23<=S$2, $H23>=S$2), 2, "" ))) | ... AQ23: =IF(AND($F23<(AQ$2+7),$F23>AQ$2),1, IF(AND($H23<AQ$2+7,$H23>AQ$2),3, IF(AND($F23<=AQ$2, $H23>=AQ$2), 2, "" )))
A24: 9 | B24: DC Works | C24: 43991 | D24: 16 | E24: 44012 | F24: 43991 | G24: 16 | H24: 44012 | L24: =IF(AND($F24<(L$2+7),$F24>L$2),1, IF(AND($H24<L$2+7,$H24>L$2),3, IF(AND($F24<=L$2, $H24>=L$2), 2, "" ))) | M24: =IF(AND($F24<(M$2+7),$F24>M$2),1, IF(AND($H24<M$2+7,$H24>M$2),3, IF(AND($F24<=M$2, $H24>=M$2), 2, "" ))) | N24: =IF(AND($F24<(N$2+7),$F24>N$2),1, IF(AND($H24<N$2+7,$H24>N$2),3, IF(AND($F24<=N$2, $H24>=N$2), 2, "" ))) | O24: =IF(AND($F24<(O$2+7),$F24>O$2),1, IF(AND($H24<O$2+7,$H24>O$2),3, IF(AND($F24<=O$2, $H24>=O$2), 2, "" ))) | P24: =IF(AND($F24<(P$2+7),$F24>P$2),1, IF(AND($H24<P$2+7,$H24>P$2),3, IF(AND($F24<=P$2, $H24>=P$2), 2, "" ))) | Q24: =IF(AND($F24<(Q$2+7),$F24>Q$2),1, IF(AND($H24<Q$2+7,$H24>Q$2),3, IF(AND($F24<=Q$2, $H24>=Q$2), 2, "" ))) | R24: =IF(AND($F24<(R$2+7),$F24>R$2),1, IF(AND($H24<R$2+7,$H24>R$2),3, IF(AND($F24<=R$2, $H24>=R$2), 2, "" ))) | S24: =IF(AND($F24<(S$2+7),$F24>S$2),1, IF(AND($H24<S$2+7,$H24>S$2),3, IF(AND($F24<=S$2, $H24>=S$2), 2, "" ))) | ... AQ24: =IF(AND($F24<(AQ$2+7),$F24>AQ$2),1, IF(AND($H24<AQ$2+7,$H24>AQ$2),3, IF(AND($F24<=AQ$2, $H24>=AQ$2), 2, "" ))) -> 2
B25: Mounting structure Installation | C25: 43991 | D25: 4 | E25: 43997 | F25: 43991 | G25: 4 | H25: 43997 | L25: =IF(AND($F25<(L$2+7),$F25>L$2),1, IF(AND($H25<L$2+7,$H25>L$2),3, IF(AND($F25<=L$2, $H25>=L$2), 2, "" ))) | M25: =IF(AND($F25<(M$2+7),$F25>M$2),1, IF(AND($H25<M$2+7,$H25>M$2),3, IF(AND($F25<=M$2, $H25>=M$2), 2, "" ))) | N25: =IF(AND($F25<(N$2+7),$F25>N$2),1, IF(AND($H25<N$2+7,$H25>N$2),3, IF(AND($F25<=N$2, $H25>=N$2), 2, "" ))) | O25: =IF(AND($F25<(O$2+7),$F25>O$2),1, IF(AND($H25<O$2+7,$H25>O$2),3, IF(AND($F25<=O$2, $H25>=O$2), 2, "" ))) | P25: =IF(AND($F25<(P$2+7),$F25>P$2),1, IF(AND($H25<P$2+7,$H25>P$2),3, IF(AND($F25<=P$2, $H25>=P$2), 2, "" ))) | Q25: =IF(AND($F25<(Q$2+7),$F25>Q$2),1, IF(AND($H25<Q$2+7,$H25>Q$2),3, IF(AND($F25<=Q$2, $H25>=Q$2), 2, "" ))) | R25: =IF(AND($F25<(R$2+7),$F25>R$2),1, IF(AND($H25<R$2+7,$H25>R$2),3, IF(AND($F25<=R$2, $H25>=R$2), 2, "" ))) | S25: =IF(AND($F25<(S$2+7),$F25>S$2),1, IF(AND($H25<S$2+7,$H25>S$2),3, IF(AND($F25<=S$2, $H25>=S$2), 2, "" ))) | ... AQ25: =IF(AND($F25<(AQ$2+7),$F25>AQ$2),1, IF(AND($H25<AQ$2+7,$H25>AQ$2),3, IF(AND($F25<=AQ$2, $H25>=AQ$2), 2, "" )))
B26: Cable tray Installation | C26: 43997 | D26: 3 | E26: 44004 | F26: 43997 | G26: 3 | H26: 44004 | L26: =IF(AND($F26<(L$2+7),$F26>L$2),1, IF(AND($H26<L$2+7,$H26>L$2),3, IF(AND($F26<=L$2, $H26>=L$2), 2, "" ))) | M26: =IF(AND($F26<(M$2+7),$F26>M$2),1, IF(AND($H26<M$2+7,$H26>M$2),3, IF(AND($F26<=M$2, $H26>=M$2), 2, "" ))) | N26: =IF(AND($F26<(N$2+7),$F26>N$2),1, IF(AND($H26<N$2+7,$H26>N$2),3, IF(AND($F26<=N$2, $H26>=N$2), 2, "" ))) | O26: =IF(AND($F26<(O$2+7),$F26>O$2),1, IF(AND($H26<O$2+7,$H26>O$2),3, IF(AND($F26<=O$2, $H26>=O$2), 2, "" ))) | P26: =IF(AND($F26<(P$2+7),$F26>P$2),1, IF(AND($H26<P$2+7,$H26>P$2),3, IF(AND($F26<=P$2, $H26>=P$2), 2, "" ))) | Q26: =IF(AND($F26<(Q$2+7),$F26>Q$2),1, IF(AND($H26<Q$2+7,$H26>Q$2),3, IF(AND($F26<=Q$2, $H26>=Q$2), 2, "" ))) | R26: =IF(AND($F26<(R$2+7),$F26>R$2),1, IF(AND($H26<R$2+7,$H26>R$2),3, IF(AND($F26<=R$2, $H26>=R$2), 2, "" ))) | S26: =IF(AND($F26<(S$2+7),$F26>S$2),1, IF(AND($H26<S$2+7,$H26>S$2),3, IF(AND($F26<=S$2, $H26>=S$2), 2, "" ))) | ... AQ26: =IF(AND($F26<(AQ$2+7),$F26>AQ$2),1, IF(AND($H26<AQ$2+7,$H26>AQ$2),3, IF(AND($F26<=AQ$2, $H26>=AQ$2), 2, "" )))
B27: DC Cable Installation | C27: 44004 | D27: 2 | E27: 44006 | F27: 44004 | G27: 2 | H27: 44006 | L27: =IF(AND($F27<(L$2+7),$F27>L$2),1, IF(AND($H27<L$2+7,$H27>L$2),3, IF(AND($F27<=L$2, $H27>=L$2), 2, "" ))) | M27: =IF(AND($F27<(M$2+7),$F27>M$2),1, IF(AND($H27<M$2+7,$H27>M$2),3, IF(AND($F27<=M$2, $H27>=M$2), 2, "" ))) | N27: =IF(AND($F27<(N$2+7),$F27>N$2),1, IF(AND($H27<N$2+7,$H27>N$2),3, IF(AND($F27<=N$2, $H27>=N$2), 2, "" ))) | O27: =IF(AND($F27<(O$2+7),$F27>O$2),1, IF(AND($H27<O$2+7,$H27>O$2),3, IF(AND($F27<=O$2, $H27>=O$2), 2, "" ))) | P27: =IF(AND($F27<(P$2+7),$F27>P$2),1, IF(AND($H27<P$2+7,$H27>P$2),3, IF(AND($F27<=P$2, $H27>=P$2), 2, "" ))) | Q27: =IF(AND($F27<(Q$2+7),$F27>Q$2),1, IF(AND($H27<Q$2+7,$H27>Q$2),3, IF(AND($F27<=Q$2, $H27>=Q$2), 2, "" ))) | R27: =IF(AND($F27<(R$2+7),$F27>R$2),1, IF(AND($H27<R$2+7,$H27>R$2),3, IF(AND($F27<=R$2, $H27>=R$2), 2, "" ))) | S27: =IF(AND($F27<(S$2+7),$F27>S$2),1, IF(AND($H27<S$2+7,$H27>S$2),3, IF(AND($F27<=S$2, $H27>=S$2), 2, "" ))) | ... AQ27: =IF(AND($F27<(AQ$2+7),$F27>AQ$2),1, IF(AND($H27<AQ$2+7,$H27>AQ$2),3, IF(AND($F27<=AQ$2, $H27>=AQ$2), 2, "" )))
B28: Module Installation | C28: 44006 | D28: 4 | E28: 44012 | F28: 44006 | G28: 4 | H28: 44012 | L28: =IF(AND($F28<(L$2+7),$F28>L$2),1, IF(AND($H28<L$2+7,$H28>L$2),3, IF(AND($F28<=L$2, $H28>=L$2), 2, "" ))) | M28: =IF(AND($F28<(M$2+7),$F28>M$2),1, IF(AND($H28<M$2+7,$H28>M$2),3, IF(AND($F28<=M$2, $H28>=M$2), 2, "" ))) | N28: =IF(AND($F28<(N$2+7),$F28>N$2),1, IF(AND($H28<N$2+7,$H28>N$2),3, IF(AND($F28<=N$2, $H28>=N$2), 2, "" ))) | O28: =IF(AND($F28<(O$2+7),$F28>O$2),1, IF(AND($H28<O$2+7,$H28>O$2),3, IF(AND($F28<=O$2, $H28>=O$2), 2, "" ))) | P28: =IF(AND($F28<(P$2+7),$F28>P$2),1, IF(AND($H28<P$2+7,$H28>P$2),3, IF(AND($F28<=P$2, $H28>=P$2), 2, "" ))) | Q28: =IF(AND($F28<(Q$2+7),$F28>Q$2),1, IF(AND($H28<Q$2+7,$H28>Q$2),3, IF(AND($F28<=Q$2, $H28>=Q$2), 2, "" ))) | R28: =IF(AND($F28<(R$2+7),$F28>R$2),1, IF(AND($H28<R$2+7,$H28>R$2),3, IF(AND($F28<=R$2, $H28>=R$2), 2, "" ))) | S28: =IF(AND($F28<(S$2+7),$F28>S$2),1, IF(AND($H28<S$2+7,$H28>S$2),3, IF(AND($F28<=S$2, $H28>=S$2), 2, "" ))) | ... AQ28: =IF(AND($F28<(AQ$2+7),$F28>AQ$2),1, IF(AND($H28<AQ$2+7,$H28>AQ$2),3, IF(AND($F28<=AQ$2, $H28>=AQ$2), 2, "" ))) -> 2
B29: Earth Cable Installation | C29: 44004 | D29: 1 | E29: 44005 | F29: 44004 | G29: 1 | H29: 44005 | L29: =IF(AND($F29<(L$2+7),$F29>L$2),1, IF(AND($H29<L$2+7,$H29>L$2),3, IF(AND($F29<=L$2, $H29>=L$2), 2, "" ))) | M29: =IF(AND($F29<(M$2+7),$F29>M$2),1, IF(AND($H29<M$2+7,$H29>M$2),3, IF(AND($F29<=M$2, $H29>=M$2), 2, "" ))) | N29: =IF(AND($F29<(N$2+7),$F29>N$2),1, IF(AND($H29<N$2+7,$H29>N$2),3, IF(AND($F29<=N$2, $H29>=N$2), 2, "" ))) | O29: =IF(AND($F29<(O$2+7),$F29>O$2),1, IF(AND($H29<O$2+7,$H29>O$2),3, IF(AND($F29<=O$2, $H29>=O$2), 2, "" ))) | P29: =IF(AND($F29<(P$2+7),$F29>P$2),1, IF(AND($H29<P$2+7,$H29>P$2),3, IF(AND($F29<=P$2, $H29>=P$2), 2, "" ))) | Q29: =IF(AND($F29<(Q$2+7),$F29>Q$2),1, IF(AND($H29<Q$2+7,$H29>Q$2),3, IF(AND($F29<=Q$2, $H29>=Q$2), 2, "" ))) | R29: =IF(AND($F29<(R$2+7),$F29>R$2),1, IF(AND($H29<R$2+7,$H29>R$2),3, IF(AND($F29<=R$2, $H29>=R$2), 2, "" ))) | S29: =IF(AND($F29<(S$2+7),$F29>S$2),1, IF(AND($H29<S$2+7,$H29>S$2),3, IF(AND($F29<=S$2, $H29>=S$2), 2, "" ))) | ... AQ29: =IF(AND($F29<(AQ$2+7),$F29>AQ$2),1, IF(AND($H29<AQ$2+7,$H29>AQ$2),3, IF(AND($F29<=AQ$2, $H29>=AQ$2), 2, "" )))
A30: 10 | B30: AC Works | C30: 43991 | D30: 8 | E30: 44000 | F30: 43991 | G30: 8 | H30: 44000
B31: Inverters Installation | C31: 43991 | D31: 2 | E31: 43993 | F31: 43991 | G31: 2 | H31: 43993 | L31: =IF(AND($F31<(L$2+7),$F31>L$2),1, IF(AND($H31<L$2+7,$H31>L$2),3, IF(AND($F31<=L$2, $H31>=L$2), 2, "" ))) | M31: =IF(AND($F31<(M$2+7),$F31>M$2),1, IF(AND($H31<M$2+7,$H31>M$2),3, IF(AND($F31<=M$2, $H31>=M$2), 2, "" ))) | N31: =IF(AND($F31<(N$2+7),$F31>N$2),1, IF(AND($H31<N$2+7,$H31>N$2),3, IF(AND($F31<=N$2, $H31>=N$2), 2, "" ))) | O31: =IF(AND($F31<(O$2+7),$F31>O$2),1, IF(AND($H31<O$2+7,$H31>O$2),3, IF(AND($F31<=O$2, $H31>=O$2), 2, "" ))) | P31: =IF(AND($F31<(P$2+7),$F31>P$2),1, IF(AND($H31<P$2+7,$H31>P$2),3, IF(AND($F31<=P$2, $H31>=P$2), 2, "" ))) | Q31: =IF(AND($F31<(Q$2+7),$F31>Q$2),1, IF(AND($H31<Q$2+7,$H31>Q$2),3, IF(AND($F31<=Q$2, $H31>=Q$2), 2, "" ))) | R31: =IF(AND($F31<(R$2+7),$F31>R$2),1, IF(AND($H31<R$2+7,$H31>R$2),3, IF(AND($F31<=R$2, $H31>=R$2), 2, "" ))) | S31: =IF(AND($F31<(S$2+7),$F31>S$2),1, IF(AND($H31<S$2+7,$H31>S$2),3, IF(AND($F31<=S$2, $H31>=S$2), 2, "" ))) | ... AQ31: =IF(AND($F31<(AQ$2+7),$F31>AQ$2),1, IF(AND($H31<AQ$2+7,$H31>AQ$2),3, IF(AND($F31<=AQ$2, $H31>=AQ$2), 2, "" )))
B32: AC BOS Installation | C32: 43993 | D32: 3 | E32: 44000 | F32: 43993 | G32: 3 | H32: 44000 | L32: =IF(AND($F32<(L$2+7),$F32>L$2),1, IF(AND($H32<L$2+7,$H32>L$2),3, IF(AND($F32<=L$2, $H32>=L$2), 2, "" ))) | M32: =IF(AND($F32<(M$2+7),$F32>M$2),1, IF(AND($H32<M$2+7,$H32>M$2),3, IF(AND($F32<=M$2, $H32>=M$2), 2, "" ))) | N32: =IF(AND($F32<(N$2+7),$F32>N$2),1, IF(AND($H32<N$2+7,$H32>N$2),3, IF(AND($F32<=N$2, $H32>=N$2), 2, "" ))) | O32: =IF(AND($F32<(O$2+7),$F32>O$2),1, IF(AND($H32<O$2+7,$H32>O$2),3, IF(AND($F32<=O$2, $H32>=O$2), 2, "" ))) | P32: =IF(AND($F32<(P$2+7),$F32>P$2),1, IF(AND($H32<P$2+7,$H32>P$2),3, IF(AND($F32<=P$2, $H32>=P$2), 2, "" ))) | Q32: =IF(AND($F32<(Q$2+7),$F32>Q$2),1, IF(AND($H32<Q$2+7,$H32>Q$2),3, IF(AND($F32<=Q$2, $H32>=Q$2), 2, "" ))) | R32: =IF(AND($F32<(R$2+7),$F32>R$2),1, IF(AND($H32<R$2+7,$H32>R$2),3, IF(AND($F32<=R$2, $H32>=R$2), 2, "" ))) | S32: =IF(AND($F32<(S$2+7),$F32>S$2),1, IF(AND($H32<S$2+7,$H32>S$2),3, IF(AND($F32<=S$2, $H32>=S$2), 2, "" ))) | ... AQ32: =IF(AND($F32<(AQ$2+7),$F32>AQ$2),1, IF(AND($H32<AQ$2+7,$H32>AQ$2),3, IF(AND($F32<=AQ$2, $H32>=AQ$2), 2, "" )))
B33: AC Cable/Tie-In | C33: 43992 | D33: 3 | E33: 43997 | F33: 43992 | G33: 3 | H33: 43997 | L33: =IF(AND($F33<(L$2+7),$F33>L$2),1, IF(AND($H33<L$2+7,$H33>L$2),3, IF(AND($F33<=L$2, $H33>=L$2), 2, "" ))) | M33: =IF(AND($F33<(M$2+7),$F33>M$2),1, IF(AND($H33<M$2+7,$H33>M$2),3, IF(AND($F33<=M$2, $H33>=M$2), 2, "" ))) | N33: =IF(AND($F33<(N$2+7),$F33>N$2),1, IF(AND($H33<N$2+7,$H33>N$2),3, IF(AND($F33<=N$2, $H33>=N$2), 2, "" ))) | O33: =IF(AND($F33<(O$2+7),$F33>O$2),1, IF(AND($H33<O$2+7,$H33>O$2),3, IF(AND($F33<=O$2, $H33>=O$2), 2, "" ))) | P33: =IF(AND($F33<(P$2+7),$F33>P$2),1, IF(AND($H33<P$2+7,$H33>P$2),3, IF(AND($F33<=P$2, $H33>=P$2), 2, "" ))) | Q33: =IF(AND($F33<(Q$2+7),$F33>Q$2),1, IF(AND($H33<Q$2+7,$H33>Q$2),3, IF(AND($F33<=Q$2, $H33>=Q$2), 2, "" ))) | R33: =IF(AND($F33<(R$2+7),$F33>R$2),1, IF(AND($H33<R$2+7,$H33>R$2),3, IF(AND($F33<=R$2, $H33>=R$2), 2, "" ))) | S33: =IF(AND($F33<(S$2+7),$F33>S$2),1, IF(AND($H33<S$2+7,$H33>S$2),3, IF(AND($F33<=S$2, $H33>=S$2), 2, "" ))) | ... AQ33: =IF(AND($F33<(AQ$2+7),$F33>AQ$2),1, IF(AND($H33<AQ$2+7,$H33>AQ$2),3, IF(AND($F33<=AQ$2, $H33>=AQ$2), 2, "" )))
B34: Monitoring Platform Installation | C34: 43997 | D34: 1 | E34: 44000 | F34: 43997 | G34: 1 | H34: 44000
A35: 11 | B35: Completion | C35: 44000 | D35: 14 | E35: 44014 | F35: 44000 | G35: 14 | H35: 44014 | L35: =IF(AND($F35<(L$2+7),$F35>L$2),1, IF(AND($H35<L$2+7,$H35>L$2),3, IF(AND($F35<=L$2, $H35>=L$2), 2, "" ))) | M35: =IF(AND($F35<(M$2+7),$F35>M$2),1, IF(AND($H35<M$2+7,$H35>M$2),3, IF(AND($F35<=M$2, $H35>=M$2), 2, "" ))) | N35: =IF(AND($F35<(N$2+7),$F35>N$2),1, IF(AND($H35<N$2+7,$H35>N$2),3, IF(AND($F35<=N$2, $H35>=N$2), 2, "" ))) | O35: =IF(AND($F35<(O$2+7),$F35>O$2),1, IF(AND($H35<O$2+7,$H35>O$2),3, IF(AND($F35<=O$2, $H35>=O$2), 2, "" ))) | P35: =IF(AND($F35<(P$2+7),$F35>P$2),1, IF(AND($H35<P$2+7,$H35>P$2),3, IF(AND($F35<=P$2, $H35>=P$2), 2, "" ))) | Q35: =IF(AND($F35<(Q$2+7),$F35>Q$2),1, IF(AND($H35<Q$2+7,$H35>Q$2),3, IF(AND($F35<=Q$2, $H35>=Q$2), 2, "" ))) | R35: =IF(AND($F35<(R$2+7),$F35>R$2),1, IF(AND($H35<R$2+7,$H35>R$2),3, IF(AND($F35<=R$2, $H35>=R$2), 2, "" ))) | S35: =IF(AND($F35<(S$2+7),$F35>S$2),1, IF(AND($H35<S$2+7,$H35>S$2),3, IF(AND($F35<=S$2, $H35>=S$2), 2, "" ))) | ... AQ35: =IF(AND($F35<(AQ$2+7),$F35>AQ$2),1, IF(AND($H35<AQ$2+7,$H35>AQ$2),3, IF(AND($F35<=AQ$2, $H35>=AQ$2), 2, "" ))) -> 3
B36: DC Works | C36: 44012 | D36: 2 | E36: 44014 | F36: 44012 | G36: 2 | H36: 44014 | L36: =IF(AND($F36<(L$2+7),$F36>L$2),1, IF(AND($H36<L$2+7,$H36>L$2),3, IF(AND($F36<=L$2, $H36>=L$2), 2, "" ))) | M36: =IF(AND($F36<(M$2+7),$F36>M$2),1, IF(AND($H36<M$2+7,$H36>M$2),3, IF(AND($F36<=M$2, $H36>=M$2), 2, "" ))) | N36: =IF(AND($F36<(N$2+7),$F36>N$2),1, IF(AND($H36<N$2+7,$H36>N$2),3, IF(AND($F36<=N$2, $H36>=N$2), 2, "" ))) | O36: =IF(AND($F36<(O$2+7),$F36>O$2),1, IF(AND($H36<O$2+7,$H36>O$2),3, IF(AND($F36<=O$2, $H36>=O$2), 2, "" ))) | P36: =IF(AND($F36<(P$2+7),$F36>P$2),1, IF(AND($H36<P$2+7,$H36>P$2),3, IF(AND($F36<=P$2, $H36>=P$2), 2, "" ))) | Q36: =IF(AND($F36<(Q$2+7),$F36>Q$2),1, IF(AND($H36<Q$2+7,$H36>Q$2),3, IF(AND($F36<=Q$2, $H36>=Q$2), 2, "" ))) | R36: =IF(AND($F36<(R$2+7),$F36>R$2),1, IF(AND($H36<R$2+7,$H36>R$2),3, IF(AND($F36<=R$2, $H36>=R$2), 2, "" ))) | S36: =IF(AND($F36<(S$2+7),$F36>S$2),1, IF(AND($H36<S$2+7,$H36>S$2),3, IF(AND($F36<=S$2, $H36>=S$2), 2, "" ))) | ... AQ36: =IF(AND($F36<(AQ$2+7),$F36>AQ$2),1, IF(AND($H36<AQ$2+7,$H36>AQ$2),3, IF(AND($F36<=AQ$2, $H36>=AQ$2), 2, "" ))) -> 3
B37: AC Works | C37: 44000 | D37: 2 | E37: 44004 | F37: 44000 | G37: 2 | H37: 44004 | L37: =IF(AND($F37<(L$2+7),$F37>L$2),1, IF(AND($H37<L$2+7,$H37>L$2),3, IF(AND($F37<=L$2, $H37>=L$2), 2, "" ))) | M37: =IF(AND($F37<(M$2+7),$F37>M$2),1, IF(AND($H37<M$2+7,$H37>M$2),3, IF(AND($F37<=M$2, $H37>=M$2), 2, "" ))) | N37: =IF(AND($F37<(N$2+7),$F37>N$2),1, IF(AND($H37<N$2+7,$H37>N$2),3, IF(AND($F37<=N$2, $H37>=N$2), 2, "" ))) | O37: =IF(AND($F37<(O$2+7),$F37>O$2),1, IF(AND($H37<O$2+7,$H37>O$2),3, IF(AND($F37<=O$2, $H37>=O$2), 2, "" ))) | P37: =IF(AND($F37<(P$2+7),$F37>P$2),1, IF(AND($H37<P$2+7,$H37>P$2),3, IF(AND($F37<=P$2, $H37>=P$2), 2, "" ))) | Q37: =IF(AND($F37<(Q$2+7),$F37>Q$2),1, IF(AND($H37<Q$2+7,$H37>Q$2),3, IF(AND($F37<=Q$2, $H37>=Q$2), 2, "" ))) | R37: =IF(AND($F37<(R$2+7),$F37>R$2),1, IF(AND($H37<R$2+7,$H37>R$2),3, IF(AND($F37<=R$2, $H37>=R$2), 2, "" ))) | S37: =IF(AND($F37<(S$2+7),$F37>S$2),1, IF(AND($H37<S$2+7,$H37>S$2),3, IF(AND($F37<=S$2, $H37>=S$2), 2, "" ))) | ... AQ37: =IF(AND($F37<(AQ$2+7),$F37>AQ$2),1, IF(AND($H37<AQ$2+7,$H37>AQ$2),3, IF(AND($F37<=AQ$2, $H37>=AQ$2), 2, "" )))
A38: D | B38: PAYMENT MILESTONE 4: PRACTICAL COMPLETION | C38: 44012 | D38: 1 | E38: 44013 | F38: 44012 | G38: 1 | H38: 44013 | L38: =IF(AND($F38<(L$2+7),$F38>L$2),1, IF(AND($H38<L$2+7,$H38>L$2),3, IF(AND($F38<=L$2, $H38>=L$2), 2, "" ))) | M38: =IF(AND($F38<(M$2+7),$F38>M$2),1, IF(AND($H38<M$2+7,$H38>M$2),3, IF(AND($F38<=M$2, $H38>=M$2), 2, "" ))) | N38: =IF(AND($F38<(N$2+7),$F38>N$2),1, IF(AND($H38<N$2+7,$H38>N$2),3, IF(AND($F38<=N$2, $H38>=N$2), 2, "" ))) | O38: =IF(AND($F38<(O$2+7),$F38>O$2),1, IF(AND($H38<O$2+7,$H38>O$2),3, IF(AND($F38<=O$2, $H38>=O$2), 2, "" ))) | P38: =IF(AND($F38<(P$2+7),$F38>P$2),1, IF(AND($H38<P$2+7,$H38>P$2),3, IF(AND($F38<=P$2, $H38>=P$2), 2, "" ))) | Q38: =IF(AND($F38<(Q$2+7),$F38>Q$2),1, IF(AND($H38<Q$2+7,$H38>Q$2),3, IF(AND($F38<=Q$2, $H38>=Q$2), 2, "" ))) | R38: =IF(AND($F38<(R$2+7),$F38>R$2),1, IF(AND($H38<R$2+7,$H38>R$2),3, IF(AND($F38<=R$2, $H38>=R$2), 2, "" ))) | S38: =IF(AND($F38<(S$2+7),$F38>S$2),1, IF(AND($H38<S$2+7,$H38>S$2),3, IF(AND($F38<=S$2, $H38>=S$2), 2, "" ))) | ... AQ38: =IF(AND($F38<(AQ$2+7),$F38>AQ$2),1, IF(AND($H38<AQ$2+7,$H38>AQ$2),3, IF(AND($F38<=AQ$2, $H38>=AQ$2), 2, "" ))) -> 3
A39: 12 | B39: Commissioning | C39: 43997 | D39: 22 | E39: 44019 | F39: 43997 | G39: 22 | H39: 44019 | L39: =IF(AND($F39<(L$2+7),$F39>L$2),1, IF(AND($H39<L$2+7,$H39>L$2),3, IF(AND($F39<=L$2, $H39>=L$2), 2, "" ))) | M39: =IF(AND($F39<(M$2+7),$F39>M$2),1, IF(AND($H39<M$2+7,$H39>M$2),3, IF(AND($F39<=M$2, $H39>=M$2), 2, "" ))) | N39: =IF(AND($F39<(N$2+7),$F39>N$2),1, IF(AND($H39<N$2+7,$H39>N$2),3, IF(AND($F39<=N$2, $H39>=N$2), 2, "" ))) | O39: =IF(AND($F39<(O$2+7),$F39>O$2),1, IF(AND($H39<O$2+7,$H39>O$2),3, IF(AND($F39<=O$2, $H39>=O$2), 2, "" ))) | P39: =IF(AND($F39<(P$2+7),$F39>P$2),1, IF(AND($H39<P$2+7,$H39>P$2),3, IF(AND($F39<=P$2, $H39>=P$2), 2, "" ))) | Q39: =IF(AND($F39<(Q$2+7),$F39>Q$2),1, IF(AND($H39<Q$2+7,$H39>Q$2),3, IF(AND($F39<=Q$2, $H39>=Q$2), 2, "" ))) | R39: =IF(AND($F39<(R$2+7),$F39>R$2),1, IF(AND($H39<R$2+7,$H39>R$2),3, IF(AND($F39<=R$2, $H39>=R$2), 2, "" ))) | S39: =IF(AND($F39<(S$2+7),$F39>S$2),1, IF(AND($H39<S$2+7,$H39>S$2),3, IF(AND($F39<=S$2, $H39>=S$2), 2, "" ))) | ... AQ39: =IF(AND($F39<(AQ$2+7),$F39>AQ$2),1, IF(AND($H39<AQ$2+7,$H39>AQ$2),3, IF(AND($F39<=AQ$2, $H39>=AQ$2), 2, "" ))) -> 2
B40: Snag List | C40: 44014 | D40: 3 | E40: 44019 | F40: 44014 | G40: 3 | H40: 44019
B41: Pre-Commissioning Checks | C41: 44010 | D41: 2 | E41: 44012 | F41: 44010 | G41: 2 | H41: 44012
B42: Issue CoC | C42: 43997 | D42: 2 | E42: 44001 | F42: 43997 | G42: 2 | H42: 44001 | L42: =IF(AND($F42<(L$2+7),$F42>L$2),1, IF(AND($H42<L$2+7,$H42>L$2),3, IF(AND($F42<=L$2, $H42>=L$2), 2, "" ))) | M42: =IF(AND($F42<(M$2+7),$F42>M$2),1, IF(AND($H42<M$2+7,$H42>M$2),3, IF(AND($F42<=M$2, $H42>=M$2), 2, "" ))) | N42: =IF(AND($F42<(N$2+7),$F42>N$2),1, IF(AND($H42<N$2+7,$H42>N$2),3, IF(AND($F42<=N$2, $H42>=N$2), 2, "" ))) | O42: =IF(AND($F42<(O$2+7),$F42>O$2),1, IF(AND($H42<O$2+7,$H42>O$2),3, IF(AND($F42<=O$2, $H42>=O$2), 2, "" ))) | P42: =IF(AND($F42<(P$2+7),$F42>P$2),1, IF(AND($H42<P$2+7,$H42>P$2),3, IF(AND($F42<=P$2, $H42>=P$2), 2, "" ))) | Q42: =IF(AND($F42<(Q$2+7),$F42>Q$2),1, IF(AND($H42<Q$2+7,$H42>Q$2),3, IF(AND($F42<=Q$2, $H42>=Q$2), 2, "" ))) | R42: =IF(AND($F42<(R$2+7),$F42>R$2),1, IF(AND($H42<R$2+7,$H42>R$2),3, IF(AND($F42<=R$2, $H42>=R$2), 2, "" ))) | S42: =IF(AND($F42<(S$2+7),$F42>S$2),1, IF(AND($H42<S$2+7,$H42>S$2),3, IF(AND($F42<=S$2, $H42>=S$2), 2, "" ))) | ... AQ42: =IF(AND($F42<(AQ$2+7),$F42>AQ$2),1, IF(AND($H42<AQ$2+7,$H42>AQ$2),3, IF(AND($F42<=AQ$2, $H42>=AQ$2), 2, "" )))
B43: Cold Commissioning | C43: 44012 | D43: 1 | E43: 44013 | F43: 44012 | G43: 1 | H43: 44013 | L43: =IF(AND($F43<(L$2+7),$F43>L$2),1, IF(AND($H43<L$2+7,$H43>L$2),3, IF(AND($F43<=L$2, $H43>=L$2), 2, "" ))) | M43: =IF(AND($F43<(M$2+7),$F43>M$2),1, IF(AND($H43<M$2+7,$H43>M$2),3, IF(AND($F43<=M$2, $H43>=M$2), 2, "" ))) | N43: =IF(AND($F43<(N$2+7),$F43>N$2),1, IF(AND($H43<N$2+7,$H43>N$2),3, IF(AND($F43<=N$2, $H43>=N$2), 2, "" ))) | O43: =IF(AND($F43<(O$2+7),$F43>O$2),1, IF(AND($H43<O$2+7,$H43>O$2),3, IF(AND($F43<=O$2, $H43>=O$2), 2, "" ))) | P43: =IF(AND($F43<(P$2+7),$F43>P$2),1, IF(AND($H43<P$2+7,$H43>P$2),3, IF(AND($F43<=P$2, $H43>=P$2), 2, "" ))) | Q43: =IF(AND($F43<(Q$2+7),$F43>Q$2),1, IF(AND($H43<Q$2+7,$H43>Q$2),3, IF(AND($F43<=Q$2, $H43>=Q$2), 2, "" ))) | R43: =IF(AND($F43<(R$2+7),$F43>R$2),1, IF(AND($H43<R$2+7,$H43>R$2),3, IF(AND($F43<=R$2, $H43>=R$2), 2, "" ))) | S43: =IF(AND($F43<(S$2+7),$F43>S$2),1, IF(AND($H43<S$2+7,$H43>S$2),3, IF(AND($F43<=S$2, $H43>=S$2), 2, "" ))) | ... AQ43: =IF(AND($F43<(AQ$2+7),$F43>AQ$2),1, IF(AND($H43<AQ$2+7,$H43>AQ$2),3, IF(AND($F43<=AQ$2, $H43>=AQ$2), 2, "" ))) -> 3
B44: Hot Commissioning | C44: 44013 | D44: 2 | E44: 44015 | F44: 44013 | G44: 2 | H44: 44015 | L44: =IF(AND($F44<(L$2+7),$F44>L$2),1, IF(AND($H44<L$2+7,$H44>L$2),3, IF(AND($F44<=L$2, $H44>=L$2), 2, "" ))) | M44: =IF(AND($F44<(M$2+7),$F44>M$2),1, IF(AND($H44<M$2+7,$H44>M$2),3, IF(AND($F44<=M$2, $H44>=M$2), 2, "" ))) | N44: =IF(AND($F44<(N$2+7),$F44>N$2),1, IF(AND($H44<N$2+7,$H44>N$2),3, IF(AND($F44<=N$2, $H44>=N$2), 2, "" ))) | O44: =IF(AND($F44<(O$2+7),$F44>O$2),1, IF(AND($H44<O$2+7,$H44>O$2),3, IF(AND($F44<=O$2, $H44>=O$2), 2, "" ))) | P44: =IF(AND($F44<(P$2+7),$F44>P$2),1, IF(AND($H44<P$2+7,$H44>P$2),3, IF(AND($F44<=P$2, $H44>=P$2), 2, "" ))) | Q44: =IF(AND($F44<(Q$2+7),$F44>Q$2),1, IF(AND($H44<Q$2+7,$H44>Q$2),3, IF(AND($F44<=Q$2, $H44>=Q$2), 2, "" ))) | R44: =IF(AND($F44<(R$2+7),$F44>R$2),1, IF(AND($H44<R$2+7,$H44>R$2),3, IF(AND($F44<=R$2, $H44>=R$2), 2, "" ))) | S44: =IF(AND($F44<(S$2+7),$F44>S$2),1, IF(AND($H44<S$2+7,$H44>S$2),3, IF(AND($F44<=S$2, $H44>=S$2), 2, "" ))) | ... AQ44: =IF(AND($F44<(AQ$2+7),$F44>AQ$2),1, IF(AND($H44<AQ$2+7,$H44>AQ$2),3, IF(AND($F44<=AQ$2, $H44>=AQ$2), 2, "" ))) -> 1
A45: 13 | B45: Handover | C45: 44020 | D45: 1 | E45: 44021 | F45: 44020 | G45: 1 | H45: 44021 | L45: =IF(AND($F45<(L$2+7),$F45>L$2),1, IF(AND($H45<L$2+7,$H45>L$2),3, IF(AND($F45<=L$2, $H45>=L$2), 2, "" ))) | M45: =IF(AND($F45<(M$2+7),$F45>M$2),1, IF(AND($H45<M$2+7,$H45>M$2),3, IF(AND($F45<=M$2, $H45>=M$2), 2, "" ))) | N45: =IF(AND($F45<(N$2+7),$F45>N$2),1, IF(AND($H45<N$2+7,$H45>N$2),3, IF(AND($F45<=N$2, $H45>=N$2), 2, "" ))) | O45: =IF(AND($F45<(O$2+7),$F45>O$2),1, IF(AND($H45<O$2+7,$H45>O$2),3, IF(AND($F45<=O$2, $H45>=O$2), 2, "" ))) | P45: =IF(AND($F45<(P$2+7),$F45>P$2),1, IF(AND($H45<P$2+7,$H45>P$2),3, IF(AND($F45<=P$2, $H45>=P$2), 2, "" ))) | Q45: =IF(AND($F45<(Q$2+7),$F45>Q$2),1, IF(AND($H45<Q$2+7,$H45>Q$2),3, IF(AND($F45<=Q$2, $H45>=Q$2), 2, "" ))) | R45: =IF(AND($F45<(R$2+7),$F45>R$2),1, IF(AND($H45<R$2+7,$H45>R$2),3, IF(AND($F45<=R$2, $H45>=R$2), 2, "" ))) | S45: =IF(AND($F45<(S$2+7),$F45>S$2),1, IF(AND($H45<S$2+7,$H45>S$2),3, IF(AND($F45<=S$2, $H45>=S$2), 2, "" ))) | ... AQ45: =IF(AND($F45<(AQ$2+7),$F45>AQ$2),1, IF(AND($H45<AQ$2+7,$H45>AQ$2),3, IF(AND($F45<=AQ$2, $H45>=AQ$2), 2, "" )))
A46: E | B46: PAYMENT MILESTONE 6: HANDOVER COMPLETE | C46: 44022 | D46: 1 | E46: 44025 | F46: 44022 | G46: 1 | H46: 44025
C47: 43831 | D47: These numbers are used to set the start and end dates on the Gantt Chart
C48: 44014

Sheet Compliance
B2: HSE
B4: Description | C4: Status | D4: Approved By | E4: Date | F4: Results / Comments
B5: NOC
B6: 7.1 Agreement
B7: 13.2 Agreement
B8: EE File
B9: Subbie File
B16: SSEG
B18: Description | C18: Status | D18: Approved By | E18: Date | F18: Results / Comments
B19: SSEG Application
B20: PTI
B21: Commissioning Approval

Sheet Project Plan
N1: =TODAY() -> 46083 | O1: =TODAY() -> 46083
C2: PROJECT PLAN | E2: The View | N2: 0 | O2: 1
C3: PROJECT SIZE (kWp) | E3: 166
C4: PROJECT DEVELOPER | E4: Natasha Watkins-Baker | J4: Target Month | K4: 45900
C5: PROJECT MANAGERS | E5: Justin Franke
C6: CONTRACT VALUE | E6: 1791940.7
C7: Phase: | E7: Compliance Handover
B8: No. | C8: HIGH LEVEL PROGRAMME | E8: Planned Start | F8: Duration (days) | G8: Planned End | I8: Actual Start | J8: Duration (days) | K8: Actual End | M8: Status | N8: Status | O8: Comment
F9: =G49-E19 -> 25 | J9: =K49-I19 -> 99 | M9: =AVERAGE(M11,M18,M21,M28,M39,M47,M54,M51) -> 1 | N9: =AVERAGE(N11,N18,N21,N28,N39,N47,N54,N51) -> 1
B11: 1 | C11: Project Initiation | E11: =MIN(E12:E16) -> 45869 | F11: =G11-E11 -> 12 | G11: =MAX(G12:G16) -> 45881 | I11: =MIN(I12:I16) -> 45873 | J11: =K11-I11 -> 17 | K11: =MAX(K12:K16) -> 45890 | M11: =(J12*M12+J13*M13+J14*M14+J15*M15+J16*M16)/SUM(J12:J16) -> 1 | N11: =(K12*N12+K13*N13+K14*N14+K15*N15+K16*N16)/SUM(K12:K16) -> 1
B12: 1.1 | C12: BD Handover | E12: 45873 | F12: 1 | G12: =WORKDAY.INTL(E12,F12,1,Data!$C$3:$C$14) -> 45874 | I12: 45873 | J12: 1 | K12: =WORKDAY.INTL(I12,J12,1,Data!$C$3:$C$14) -> 45874 | M12: 1 | N12: =_xlfn.LET( _xlpm.s,VALUE($I12), _xlpm.e,VALUE($K12), IF(OR(_xlpm.s="",_xlpm.e=""),"", IF(_xlpm.e<=_xlpm.s, IF(TODAY()>=_xlpm.e,1,0), MAX(0,MIN(1,(TODAY()-_xlpm.s)/(_xlpm.e-_xlpm.s))))) ) -> 1
B13: 1.2 | C13: Project Introduction | E13: =WORKDAY.INTL(E19,0,1,Data!$C$3:$C$14)-14 -> 45869 | F13: 1 | G13: =WORKDAY.INTL(E13,F13,1,Data!$C$3:$C$14) -> 45870 | I13: =WORKDAY.INTL(I19,0,1,Data!$C$3:$C$14)-14 -> 45880 | J13: 1 | K13: =WORKDAY.INTL(I13,J13,1,Data!$C$3:$C$14) -> 45881 | M13: 1 | N13: =_xlfn.LET( _xlpm.s,VALUE($I13), _xlpm.e,VALUE($K13), IF(OR(_xlpm.s="",_xlpm.e=""),"", IF(_xlpm.e<=_xlpm.s, IF(TODAY()>=_xlpm.e,1,0), MAX(0,MIN(1,(TODAY()-_xlpm.s)/(_xlpm.e-_xlpm.s))))) ) -> 1
B14: 1.3 | C14: HSE | E14: =E13 -> 45869 | F14: 8 | G14: =WORKDAY.INTL(E14,F14,1,Data!$C$3:$C$14) -> 45881 | I14: =I13 -> 45880 | J14: 8 | K14: =WORKDAY.INTL(I14,J14,1,Data!$C$3:$C$14) -> 45890 | M14: 1 | N14: =_xlfn.LET( _xlpm.s,VALUE($I14), _xlpm.e,VALUE($K14), IF(OR(_xlpm.s="",_xlpm.e=""),"", IF(_xlpm.e<=_xlpm.s, IF(TODAY()>=_xlpm.e,1,0), MAX(0,MIN(1,(TODAY()-_xlpm.s)/(_xlpm.e-_xlpm.s))))) ) -> 1
B15: 1.4 | C15: Installer Kick Off | E15: =WORKDAY.INTL(E19,0,1,Data!$C$3:$C$14)-14 -> 45869 | F15: 1 | G15: =WORKDAY.INTL(E15,F15,1,Data!$C$3:$C$14) -> 45870 | I15: =WORKDAY.INTL(I19,0,1,Data!$C$3:$C$14)-14 -> 45880 | J15: 1 | K15: =WORKDAY.INTL(I15,J15,1,Data!$C$3:$C$14) -> 45881 | M15: 1 | N15: =_xlfn.LET( _xlpm.s,VALUE($I15), _xlpm.e,VALUE($K15), IF(OR(_xlpm.s="",_xlpm.e=""),"", IF(_xlpm.e<=_xlpm.s, IF(TODAY()>=_xlpm.e,1,0), MAX(0,MIN(1,(TODAY()-_xlpm.s)/(_xlpm.e-_xlpm.s))))) ) -> 1
B16: 1.5 | C16: Project Review | E16: =WORKDAY.INTL(E19,0,1,Data!$C$3:$C$14)-7 -> 45876 | F16: 1 | G16: =WORKDAY.INTL(E16,F16,1,Data!$C$3:$C$14) -> 45877 | I16: =WORKDAY.INTL(I19,0,1,Data!$C$3:$C$14)-7 -> 45887 | J16: 1 | K16: =WORKDAY.INTL(I16,J16,1,Data!$C$3:$C$14) -> 45888 | M16: 1 | N16: =_xlfn.LET( _xlpm.s,VALUE($I16), _xlpm.e,VALUE($K16), IF(OR(_xlpm.s="",_xlpm.e=""),"", IF(_xlpm.e<=_xlpm.s, IF(TODAY()>=_xlpm.e,1,0), MAX(0,MIN(1,(TODAY()-_xlpm.s)/(_xlpm.e-_xlpm.s))))) ) -> 1
B18: 2 | C18: Site Establishment | E18: =MIN(E19:E20) -> 45883 | F18: =G18-E18 -> 1 | G18: =MAX(G19) -> 45884 | I18: =MIN(I19:I20) -> 45894 | J18: =K18-I18 -> 1 | K18: =MAX(K19) -> 45895 | M18: =(J19*M19)/J18 -> 1 | N18: =(K19*N19)/K18 -> 1
B19: 2.1 | C19: Solar Contractor Establishment | E19: 45883 | F19: 1 | G19: =E19+F19 -> 45884 | I19: 45894 | J19: 1 | K19: =I19+J19 -> 45895 | M19: 1 | N19: =_xlfn.LET( _xlpm.s,VALUE($I19), _xlpm.e,VALUE($K19), IF(OR(_xlpm.s="",_xlpm.e=""),"", IF(_xlpm.e<=_xlpm.s, IF(TODAY()>=_xlpm.e,1,0), MAX(0,MIN(1,(TODAY()-_xlpm.s)/(_xlpm.e-_xlpm.s))))) ) -> 1 | S19: =NETWORKDAYS(I19,K49,Data!C3:C15) -> 71 | T19: Net Work Days
B21: 3 | C21: AC Installation | E21: =MIN(E22:E26) -> 45869 | F21: =G21-E21 -> 35 | G21: =MAX(G22:G26) -> 45904 | I21: =MIN(I22:I26) -> 45868 | J21: =K21-I21 -> 119 | K21: =MAX(K22:K26) -> 45987 | M21: =(J22*M22+J23*M23+J24*M24+J25*M25+J26*M26)/SUM(J22:J26) -> 1 | N21: =(J22*N22+J23*N23+J24*N24+J25*N25+J26*N26)/SUM(J22:J26) -> 1 | S21: =S19/5 -> 14.2 | T21: Total Weeks
B22: 3.1 | C22: Inverters delivered | E22: =WORKDAY.INTL(G19,0,1,Data!$C$3:$C$14) -> 45884 | F22: 1 | G22: =WORKDAY.INTL(E22,F22,1,Data!$C$3:$C$14) -> 45887 | I22: 45868 | J22: 1 | K22: =WORKDAY.INTL(I22,J22,1,Data!$C$3:$C$14) -> 45869 | M22: 1 | N22: =_xlfn.LET( _xlpm.s,VALUE($I22), _xlpm.e,VALUE($K22), IF(OR(_xlpm.s="",_xlpm.e=""),"", IF(_xlpm.e<=_xlpm.s, IF(TODAY()>=_xlpm.e,1,0), MAX(0,MIN(1,(TODAY()-_xlpm.s)/(_xlpm.e-_xlpm.s))))) ) -> 1 | S22: =E3/S21 -> 11.690141 | T22: kW/Week Installation Rate
B23: 3.2 | C23: Inverters Mounted | E23: =WORKDAY.INTL(G22,0,1,Data!$C$3:$C$14) -> 45887 | F23: 2 | G23: =WORKDAY.INTL(E23,F23,1,Data!$C$3:$C$14) -> 45889 | I23: 45946 | J23: 1 | K23: =WORKDAY.INTL(I23,J23,1,Data!$C$3:$C$14) -> 45947 | M23: 1 | N23: =_xlfn.LET( _xlpm.s,VALUE($I23), _xlpm.e,VALUE($K23), IF(OR(_xlpm.s="",_xlpm.e=""),"", IF(_xlpm.e<=_xlpm.s, IF(TODAY()>=_xlpm.e,1,0), MAX(0,MIN(1,(TODAY()-_xlpm.s)/(_xlpm.e-_xlpm.s))))) ) -> 1
B24: 3.3 | C24: Solar DB Lead Time | E24: =WORKDAY.INTL(E19,0,1,Data!$C$3:$C$14)-14 -> 45869 | F24: 20 | G24: =WORKDAY.INTL(E24,F24,1,Data!$C$3:$C$14) -> 45897 | I24: =WORKDAY.INTL(I19,0,1,Data!$C$3:$C$14)-14 -> 45880 | J24: 25 | K24: =WORKDAY.INTL(I24,J24,1,Data!$C$3:$C$14) -> 45915 | M24: =_xlfn.LET( _xlpm.s,VALUE($I24), _xlpm.e,VALUE($K24), IF(OR(_xlpm.s="",_xlpm.e=""),"", IF(_xlpm.e<=_xlpm.s, IF(TODAY()>=_xlpm.e,1,0), MAX(0,MIN(1,(TODAY()-_xlpm.s)/(_xlpm.e-_xlpm.s))))) ) -> 1 | N24: =_xlfn.LET( _xlpm.s,VALUE($I24), _xlpm.e,VALUE($K24), IF(OR(_xlpm.s="",_xlpm.e=""),"", IF(_xlpm.e<=_xlpm.s, IF(TODAY()>=_xlpm.e,1,0), MAX(0,MIN(1,(TODAY()-_xlpm.s)/(_xlpm.e-_xlpm.s))))) ) -> 1 | O24: DB board delay
B25: 3.4 | C25: AC Works | E25: =WORKDAY.INTL(G24,0,1,Data!$C$3:$C$14) -> 45897 | F25: 5 | G25: =WORKDAY.INTL(E25,F25,1,Data!$C$3:$C$14) -> 45904 | I25: 45946 | J25: 19 | K25: =WORKDAY.INTL(I25,J25,1,Data!$C$3:$C$14) -> 45973 | M25: 1 | N25: =_xlfn.LET( _xlpm.s,VALUE($I25), _xlpm.e,VALUE($K25), IF(OR(_xlpm.s="",_xlpm.e=""),"", IF(_xlpm.e<=_xlpm.s, IF(TODAY()>=_xlpm.e,1,0), MAX(0,MIN(1,(TODAY()-_xlpm.s)/(_xlpm.e-_xlpm.s))))) ) -> 1
B26: 3.5 | C26: AC Tie-In | E26: =WORKDAY.INTL(E25,0,1,Data!$C$3:$C$14) -> 45897 | F26: 1 | G26: =WORKDAY.INTL(E26,F26,1,Data!$C$3:$C$14) -> 45898 | I26: 45986 | J26: 1 | K26: =WORKDAY.INTL(I26,J26,1,Data!$C$3:$C$14) -> 45987 | M26: 1 | N26: =_xlfn.LET( _xlpm.s,VALUE($I26), _xlpm.e,VALUE($K26), IF(OR(_xlpm.s="",_xlpm.e=""),"", IF(_xlpm.e<=_xlpm.s, IF(TODAY()>=_xlpm.e,1,0), MAX(0,MIN(1,(TODAY()-_xlpm.s)/(_xlpm.e-_xlpm.s))))) ) -> 1 | O26: Pending breaker replacement
B28: 4 | C28: DC Works | E28: =MIN(E30:E37) -> 45883 | F28: =G28-E28 -> 21 | G28: =MAX(G30:G37) -> 45904 | I28: =MIN(I30:I37) -> 45894 | J28: =K28-I28 -> 92 | K28: =MAX(K30:K37) -> 45986 | M28: =AVERAGE(M29:M37) -> 1 | N28: =AVERAGE(N29:N37) -> 1
B29: 4.1 | C29: Lifeline Installation | I29: =I19 -> 45894 | J29: 2 | K29: =K35 -> 45944 | M29: 1 | N29: =_xlfn.LET( _xlpm.s,VALUE($I29), _xlpm.e,VALUE($K29), IF(OR(_xlpm.s="",_xlpm.e=""),"", IF(_xlpm.e<=_xlpm.s, IF(TODAY()>=_xlpm.e,1,0), MAX(0,MIN(1,(TODAY()-_xlpm.s)/(_xlpm.e-_xlpm.s))))) ) -> 1
B30: 4.1 | C30: Mounting Structure delivered | E30: =E19 -> 45883 | F30: 1 | G30: =WORKDAY.INTL(E30,F30,1,Data!$C$3:$C$14) -> 45884 | I30: =I19 -> 45894 | J30: 1 | K30: =WORKDAY.INTL(I30,J30,1,Data!$C$3:$C$14) -> 45895 | M30: 1 | N30: =_xlfn.LET( _xlpm.s,VALUE($I30), _xlpm.e,VALUE($K30), IF(OR(_xlpm.s="",_xlpm.e=""),"", IF(_xlpm.e<=_xlpm.s, IF(TODAY()>=_xlpm.e,1,0), MAX(0,MIN(1,(TODAY()-_xlpm.s)/(_xlpm.e-_xlpm.s))))) ) -> 1
B31: 4.2 | C31: Mounting Structure installation - Roof A | E31: =WORKDAY.INTL(G30,0,1,Data!$C$3:$C$14) -> 45884 | F31: 3 | G31: =WORKDAY.INTL(E31,F31,1,Data!$C$3:$C$14) -> 45889 | I31: =K24+20 -> 45935 | J31: 2 | K31: =WORKDAY.INTL(I31,J31,1,Data!$C$3:$C$14) -> 45937 | M31: 1 | N31: =_xlfn.LET( _xlpm.s,VALUE($I31), _xlpm.e,VALUE($K31), IF(OR(_xlpm.s="",_xlpm.e=""),"", IF(_xlpm.e<=_xlpm.s, IF(TODAY()>=_xlpm.e,1,0), MAX(0,MIN(1,(TODAY()-_xlpm.s)/(_xlpm.e-_xlpm.s))))) ) -> 1
B32: 4.3 | C32: Mounting Structure installation - Roof B | E32: =WORKDAY.INTL(G31,0,1,Data!$C$3:$C$14) -> 45889 | F32: 1 | G32: 45898 | I32: =WORKDAY.INTL(K31,0,1,Data!$C$3:$C$14) -> 45937 | J32: 5 | K32: =WORKDAY.INTL(I32,J32,1,Data!$C$3:$C$14) -> 45944 | M32: 1 | N32: =_xlfn.LET( _xlpm.s,VALUE($I32), _xlpm.e,VALUE($K32), IF(OR(_xlpm.s="",_xlpm.e=""),"", IF(_xlpm.e<=_xlpm.s, IF(TODAY()>=_xlpm.e,1,0), MAX(0,MIN(1,(TODAY()-_xlpm.s)/(_xlpm.e-_xlpm.s))))) ) -> 1
B33: 4.4 | C33: Mounting Structure installation - Roof C | E33: =WORKDAY.INTL(G32,0,1,Data!$C$3:$C$14) -> 45898 | F33: 2 | G33: 45902 | I33: 45938 | J33: 2 | K33: =WORKDAY.INTL(I33,J33,1,Data!$C$3:$C$14) -> 45940 | M33: 1 | N33: =_xlfn.LET( _xlpm.s,VALUE($I33), _xlpm.e,VALUE($K33), IF(OR(_xlpm.s="",_xlpm.e=""),"", IF(_xlpm.e<=_xlpm.s, IF(TODAY()>=_xlpm.e,1,0), MAX(0,MIN(1,(TODAY()-_xlpm.s)/(_xlpm.e-_xlpm.s))))) ) -> 1
B34: 4.5 | C34: Mounting Structure installation - Roof D | E34: =WORKDAY.INTL(G33,0,1,Data!$C$3:$C$14) -> 45902 | F34: 1 | G34: 45903 | I34: =WORKDAY.INTL(K33,0,1,Data!$C$3:$C$14) -> 45940 | J34: 1 | K34: =WORKDAY.INTL(I34,J34,1,Data!$C$3:$C$14) -> 45943 | M34: 1 | N34: =_xlfn.LET( _xlpm.s,VALUE($I34), _xlpm.e,VALUE($K34), IF(OR(_xlpm.s="",_xlpm.e=""),"", IF(_xlpm.e<=_xlpm.s, IF(TODAY()>=_xlpm.e,1,0), MAX(0,MIN(1,(TODAY()-_xlpm.s)/(_xlpm.e-_xlpm.s))))) ) -> 1
B35: 4.6 | C35: Mounting Structure installation - Roof E | E35: =WORKDAY.INTL(G34,0,1,Data!$C$3:$C$14) -> 45903 | F35: 1 | G35: 45904 | I35: =WORKDAY.INTL(K34,0,1,Data!$C$3:$C$14) -> 45943 | J35: 1 | K35: =WORKDAY.INTL(I35,J35,1,Data!$C$3:$C$14) -> 45944 | M35: 1 | N35: =_xlfn.LET( _xlpm.s,VALUE($I35), _xlpm.e,VALUE($K35), IF(OR(_xlpm.s="",_xlpm.e=""),"", IF(_xlpm.e<=_xlpm.s, IF(TODAY()>=_xlpm.e,1,0), MAX(0,MIN(1,(TODAY()-_xlpm.s)/(_xlpm.e-_xlpm.s))))) ) -> 1
B36: 4.7 | C36: DC Cable delivered | E36: =E30 -> 45883 | F36: 1 | G36: =WORKDAY.INTL(E36,F36,1,Data!$C$3:$C$14) -> 45884 | I36: =I30 -> 45894 | J36: 1 | K36: =WORKDAY.INTL(I36,J36,1,Data!$C$3:$C$14) -> 45895 | M36: 1 | N36: =_xlfn.LET( _xlpm.s,VALUE($I36), _xlpm.e,VALUE($K36), IF(OR(_xlpm.s="",_xlpm.e=""),"", IF(_xlpm.e<=_xlpm.s, IF(TODAY()>=_xlpm.e,1,0), MAX(0,MIN(1,(TODAY()-_xlpm.s)/(_xlpm.e-_xlpm.s))))) ) -> 1
B37: 4.8 | C37: DC Stringing | E37: =WORKDAY.INTL(G41,0,1,Data!$C$3:$C$14)-3 -> 45892 | F37: 4 | G37: =WORKDAY.INTL(E37,F37,1,Data!$C$3:$C$14) -> 45897 | I37: =WORKDAY.INTL(K45,0,1,Data!$C$3:$C$14)-3 -> 45958 | J37: 20 | K37: =WORKDAY.INTL(I37,J37,1,Data!$C$3:$C$14) -> 45986 | M37: 1 | N37: =_xlfn.LET( _xlpm.s,VALUE($I37), _xlpm.e,VALUE($K37), IF(OR(_xlpm.s="",_xlpm.e=""),"", IF(_xlpm.e<=_xlpm.s, IF(TODAY()>=_xlpm.e,1,0), MAX(0,MIN(1,(TODAY()-_xlpm.s)/(_xlpm.e-_xlpm.s))))) ) -> 1
B39: 5 | C39: Module installation | E39: =MIN(E40:E41) -> 45883 | F39: =G39-E39 -> 12 | G39: =MAX(G40:G41) -> 45895 | I39: =MIN(I40:I45) -> 45868 | J39: =K39-I39 -> 114 | K39: =MAX(K40:K45) -> 45982 | M39: =AVERAGE(M40:M45) -> 1 | N39: =AVERAGE(N40:N45) -> 1
B40: 5.1 | C40: Module delivery | E40: =WORKDAY.INTL(E19,0,1,Data!$C$3:$C$14) -> 45883 | F40: 1 | G40: =WORKDAY.INTL(E40,F40,1,Data!$C$3:$C$14) -> 45884 | I40: 45868 | J40: 1 | K40: =WORKDAY.INTL(I40,J40,1,Data!$C$3:$C$14) -> 45869 | M40: 1 | N40: =_xlfn.LET( _xlpm.s,VALUE($I40), _xlpm.e,VALUE($K40), IF(OR(_xlpm.s="",_xlpm.e=""),"", IF(_xlpm.e<=_xlpm.s, IF(TODAY()>=_xlpm.e,1,0), MAX(0,MIN(1,(TODAY()-_xlpm.s)/(_xlpm.e-_xlpm.s))))) ) -> 1
B41: 5.2 | C41: Module mounting - Roof A | E41: =G31 -> 45889 | F41: 4 | G41: =WORKDAY.INTL(E41,F41,1,Data!$C$3:$C$14) -> 45895 | I41: =K35 -> 45944 | J41: 3 | K41: =WORKDAY.INTL(I41,J41,1,Data!$C$3:$C$14) -> 45947 | M41: 1 | N41: =_xlfn.LET( _xlpm.s,VALUE($I41), _xlpm.e,VALUE($K41), IF(OR(_xlpm.s="",_xlpm.e=""),"", IF(_xlpm.e<=_xlpm.s, IF(TODAY()>=_xlpm.e,1,0), MAX(0,MIN(1,(TODAY()-_xlpm.s)/(_xlpm.e-_xlpm.s))))) ) -> 1
B42: 5.3 | C42: Module mounting - Roof B | E42: =G32 -> 45898 | F42: 5 | G42: =WORKDAY.INTL(E42,F42,1,Data!$C$3:$C$14) -> 45905 | I42: =I44 -> 45979 | J42: 3 | K42: =WORKDAY.INTL(I42,J42,1,Data!$C$3:$C$14) -> 45982 | M42: 1 | N42: =_xlfn.LET( _xlpm.s,VALUE($I42), _xlpm.e,VALUE($K42), IF(OR(_xlpm.s="",_xlpm.e=""),"", IF(_xlpm.e<=_xlpm.s, IF(TODAY()>=_xlpm.e,1,0), MAX(0,MIN(1,(TODAY()-_xlpm.s)/(_xlpm.e-_xlpm.s))))) ) -> 1
B43: 5.4 | C43: Module mounting - Roof C | E43: =G33 -> 45902 | F43: 6 | G43: =WORKDAY.INTL(E43,F43,1,Data!$C$3:$C$14) -> 45910 | I43: 45952 | J43: 19 | K43: =WORKDAY.INTL(I43,J43,1,Data!$C$3:$C$14) -> 45979 | M43: 1 | N43: =_xlfn.LET( _xlpm.s,VALUE($I43), _xlpm.e,VALUE($K43), IF(OR(_xlpm.s="",_xlpm.e=""),"", IF(_xlpm.e<=_xlpm.s, IF(TODAY()>=_xlpm.e,1,0), MAX(0,MIN(1,(TODAY()-_xlpm.s)/(_xlpm.e-_xlpm.s))))) ) -> 1
B44: 5.5 | C44: Module mounting - Roof D | E44: =G34 -> 45903 | F44: 7 | G44: =WORKDAY.INTL(E44,F44,1,Data!$C$3:$C$14) -> 45912 | I44: =K43 -> 45979 | J44: 2 | K44: =WORKDAY.INTL(I44,J44,1,Data!$C$3:$C$14) -> 45981 | M44: 1 | N44: =_xlfn.LET( _xlpm.s,VALUE($I44), _xlpm.e,VALUE($K44), IF(OR(_xlpm.s="",_xlpm.e=""),"", IF(_xlpm.e<=_xlpm.s, IF(TODAY()>=_xlpm.e,1,0), MAX(0,MIN(1,(TODAY()-_xlpm.s)/(_xlpm.e-_xlpm.s))))) ) -> 1
B45: 5.6 | C45: Module mounting - Roof E | E45: =G35 -> 45904 | F45: 8 | G45: =WORKDAY.INTL(E45,F45,1,Data!$C$3:$C$14) -> 45916 | I45: 45959 | J45: 2 | K45: 45961 | M45: 1 | N45: =_xlfn.LET( _xlpm.s,VALUE($I45), _xlpm.e,VALUE($K45), IF(OR(_xlpm.s="",_xlpm.e=""),"", IF(_xlpm.e<=_xlpm.s, IF(TODAY()>=_xlpm.e,1,0), MAX(0,MIN(1,(TODAY()-_xlpm.s)/(_xlpm.e-_xlpm.s))))) ) -> 1
B47: 6 | C47: Commissioning | E47: =MIN(E48:E49) -> 45904 | F47: =G47-E47 -> 4 | G47: =MAX(G48:G49) -> 45908 | I47: =MIN(I48:I49) -> 45987 | J47: =K47-I47 -> 6 | K47: =MAX(K48:K49) -> 45993 | M47: =(J48*M48+J49*M49)/SUM(J48:J49) -> 1 | N47: =(K48*N48+K49*N49)/SUM(K48:K49) -> 1
B48: 6.1 | C48: Commissioning | E48: =WORKDAY.INTL(MAX(G21,G28,G39),0,1,Data!$C$3:$C$14) -> 45904 | F48: 1 | G48: =WORKDAY.INTL(E48,F48,1,Data!$C$3:$C$14) -> 45905 | I48: =WORKDAY.INTL(MAX(K21,K28,K39),0,1,Data!$C$3:$C$14) -> 45987 | J48: 2 | K48: =WORKDAY.INTL(I48,J48,1,Data!$C$3:$C$14) -> 45989 | M48: 1 | N48: =_xlfn.LET( _xlpm.s,VALUE($I48), _xlpm.e,VALUE($K48), IF(OR(_xlpm.s="",_xlpm.e=""),"", IF(_xlpm.e<=_xlpm.s, IF(TODAY()>=_xlpm.e,1,0), MAX(0,MIN(1,(TODAY()-_xlpm.s)/(_xlpm.e-_xlpm.s))))) ) -> 1
B49: 6.2 | C49: Practical Completion | E49: =WORKDAY.INTL(G48,0,1,Data!$C$3:$C$14) -> 45905 | F49: 1 | G49: =WORKDAY.INTL(E49,F49,1,Data!$C$3:$C$14) -> 45908 | I49: =WORKDAY.INTL(K48,0,1,Data!$C$3:$C$14) -> 45989 | J49: 2 | K49: =WORKDAY.INTL(I49,J49,1,Data!$C$3:$C$14) -> 45993 | M49: 1 | N49: =_xlfn.LET( _xlpm.s,VALUE($I49), _xlpm.e,VALUE($K49), IF(OR(_xlpm.s="",_xlpm.e=""),"", IF(_xlpm.e<=_xlpm.s, IF(TODAY()>=_xlpm.e,1,0), MAX(0,MIN(1,(TODAY()-_xlpm.s)/(_xlpm.e-_xlpm.s))))) ) -> 1
B51: 7 | C51: QA Inspections | E51: =MIN(E52) -> 45904 | F51: =G51-E51 -> 1 | G51: =MAX(G52) -> 45905 | I51: =MIN(I52) -> 46000 | J51: =K51-I51 -> 1 | K51: =MAX(K52) -> 46001 | M51: =(J52*M52)/SUM(J52) -> 1 | N51: =(K52*N52)/SUM(K52) -> 1
B52: 7.1 | C52: Red-Team Inspection | E52: =WORKDAY.INTL(E48,0,1,Data!$C$3:$C$14) -> 45904 | F52: 1 | G52: =WORKDAY.INTL(E52,F52,1,Data!$C$3:$C$14) -> 45905 | I52: =WORKDAY.INTL(K49,0,1,Data!$C$3:$C$14)+7 -> 46000 | J52: 1 | K52: =WORKDAY.INTL(I52,J52,1,Data!$C$3:$C$14) -> 46001 | M52: 1 | N52: =_xlfn.LET( _xlpm.s,VALUE($I52), _xlpm.e,VALUE($K52), IF(OR(_xlpm.s="",_xlpm.e=""),"", IF(_xlpm.e<=_xlpm.s, IF(TODAY()>=_xlpm.e,1,0), MAX(0,MIN(1,(TODAY()-_xlpm.s)/(_xlpm.e-_xlpm.s))))) ) -> 1
B54: 8 | C54: Project Closure | E54: =MIN(E55:E60) -> 45905 | F54: =G54-E54 -> 20 | G54: =MAX(G55:G60) -> 45925 | I54: =MIN(I55:I60) -> 45993 | J54: =K54-I54 -> 83 | K54: =MAX(K55:K60) -> 46076 | M54: =(J55*M55+J56*M56+J57*M57+J58*M58+J59*M59+J60*M60)/SUM(J55:J60) -> 1 | N54: =(K55*N55+K56*N56+K57*N57+K58*N58+K59*N59+K60*N60)/SUM(K55:K60) -> 1
B55: 8.1 | C55: Equipment serial numbers | E55: =G52 -> 45905 | F55: 1 | G55: =WORKDAY.INTL(E55,F55,1,Data!$C$3:$C$14) -> 45908 | I55: =K52 -> 46001 | J55: 1 | K55: =WORKDAY.INTL(I55,J55,1,Data!$C$3:$C$14) -> 46002 | M55: 1 | N55: =_xlfn.LET( _xlpm.s,VALUE($I55), _xlpm.e,VALUE($K55), IF(OR(_xlpm.s="",_xlpm.e=""),"", IF(_xlpm.e<=_xlpm.s, IF(TODAY()>=_xlpm.e,1,0), MAX(0,MIN(1,(TODAY()-_xlpm.s)/(_xlpm.e-_xlpm.s))))) ) -> 1
B56: 8.2 | C56: Snags completion | E56: =G52 -> 45905 | F56: 5 | G56: =WORKDAY.INTL(E56,F56,1,Data!$C$3:$C$14) -> 45912 | I56: 46034 | J56: 7 | K56: =WORKDAY.INTL(I56,J56,1,Data!$C$3:$C$14) -> 46043 | M56: 1 | N56: =_xlfn.LET( _xlpm.s,VALUE($I56), _xlpm.e,VALUE($K56), IF(OR(_xlpm.s="",_xlpm.e=""),"", IF(_xlpm.e<=_xlpm.s, IF(TODAY()>=_xlpm.e,1,0), MAX(0,MIN(1,(TODAY()-_xlpm.s)/(_xlpm.e-_xlpm.s))))) ) -> 1
B57: 8.3 | C57: System Performance Monitoring | E57: =WORKDAY.INTL(G47,0,1,Data!$C$3:$C$14) -> 45908 | F57: 5 | G57: =WORKDAY.INTL(E57,F57,1,Data!$C$3:$C$14) -> 45915 | I57: =WORKDAY.INTL(K47,0,1,Data!$C$3:$C$14) -> 45993 | J57: 25 | K57: =WORKDAY.INTL(I57,J57,1,Data!$C$3:$C$14) -> 46030 | M57: 1 | N57: =_xlfn.LET( _xlpm.s,VALUE($I57), _xlpm.e,VALUE($K57), IF(OR(_xlpm.s="",_xlpm.e=""),"", IF(_xlpm.e<=_xlpm.s, IF(TODAY()>=_xlpm.e,1,0), MAX(0,MIN(1,(TODAY()-_xlpm.s)/(_xlpm.e-_xlpm.s))))) ) -> 1
B58: 8.4 | C58: Handover documentation | E58: =WORKDAY.INTL(G56,0,1,Data!$C$3:$C$14) -> 45912 | F58: 1 | G58: =WORKDAY.INTL(E58,F58,1,Data!$C$3:$C$14) -> 45915 | I58: =WORKDAY.INTL(K56,0,1,Data!$C$3:$C$14) -> 46043 | J58: 16 | K58: =WORKDAY.INTL(I58,J58,1,Data!$C$3:$C$14) -> 46065 | M58: 1 | N58: =_xlfn.LET( _xlpm.s,VALUE($I58), _xlpm.e,VALUE($K58), IF(OR(_xlpm.s="",_xlpm.e=""),"", IF(_xlpm.e<=_xlpm.s, IF(TODAY()>=_xlpm.e,1,0), MAX(0,MIN(1,(TODAY()-_xlpm.s)/(_xlpm.e-_xlpm.s))))) ) -> 1
B59: 8.5 | C59: Handover to Client | E59: =WORKDAY.INTL(G58,0,1,Data!$C$3:$C$14) -> 45915 | F59: 1 | G59: =WORKDAY.INTL(E59,F59,1,Data!$C$3:$C$14) -> 45916 | I59: 46069 | J59: 1 | K59: =WORKDAY.INTL(I59,J59,1,Data!$C$3:$C$14) -> 46070 | M59: 1 | N59: =_xlfn.LET( _xlpm.s,VALUE($I59), _xlpm.e,VALUE($K59), IF(OR(_xlpm.s="",_xlpm.e=""),"", IF(_xlpm.e<=_xlpm.s, IF(TODAY()>=_xlpm.e,1,0), MAX(0,MIN(1,(TODAY()-_xlpm.s)/(_xlpm.e-_xlpm.s))))) ) -> 1
B60: 8.6 | C60: Handover to Matriarch | E60: =WORKDAY.INTL(E59,0,1,Data!$C$3:$C$14)+2 -> 45917 | F60: 5 | G60: =WORKDAY.INTL(E60,F60,1,Data!$C$3:$C$14) -> 45925 | I60: =I59 -> 46069 | J60: 5 | K60: =WORKDAY.INTL(I60,J60,1,Data!$C$3:$C$14) -> 46076 | M60: 1 | N60: =_xlfn.LET( _xlpm.s,VALUE($I60), _xlpm.e,VALUE($K60), IF(OR(_xlpm.s="",_xlpm.e=""),"", IF(_xlpm.e<=_xlpm.s, IF(TODAY()>=_xlpm.e,1,0), MAX(0,MIN(1,(TODAY()-_xlpm.s)/(_xlpm.e-_xlpm.s))))) ) -> 1

Sheet Revenue Tracking
B2: HIGH LEVEL PROJECT REVENUE TRACKING
D3: COSTED | F3: ACTUAL | L3: FINANCIAL REVIEW | N3: TIMELINE REVIEW
B4: 1 | C4: Planned Revenue | D4: ='Project Plan'!E6 -> 1791940.7 | F4: =F21 -> 1791940.7 | N4: Start Date
B5: 2 | C5: Planned Expenditure | D5: =+'Expenditure Tracking'!F5 -> 1566125.3 | F5: =+'Expenditure Tracking'!H5 -> 1865330.2 | G5: VO PM Limit | H5: Current VO Total
B6: 3 | C6: Planned Profit | D6: =+D4-D5 -> 225815.47 | F6: =+F4-F5 -> -73389.49 | G6: =D6*0.05 -> 11290.774 | H6: =SUMIF('Expenditure Breakdown'!N:N,"*VO*",'Expenditure Breakdown'!Q:Q) -> 57250 | N6: End Date - PC
B7: 4 | C7: Planned Margin | D7: =+D6/D4 -> 0.12601727 | F7: =+F6/F4 -> -0.040955311
B10: CONTRACT
B12: No. | C12: PAYMENT MILESTONE | E12: % | F12: VALUE | H12: PLANNED PAYMENT DATE | L12: INVOICE NUMBER | N12: INVOICE RAISED DATE | P12: PAYMENT RECEIVED DATE | R12: MILESTONE NOTES & COMMENTS
B13: 1 | C13: Acceptance and Initial Deposit | E13: 0.5 | F13: =$D$4*E13 -> 895970.37 | H13: 45869 | L13: 004784 | N13: 45854 | P13: 45863 | AO13: ='Decision Register'!$P$14+ 7 -> 7
B14: 2 | C14: Delivery of Panels | E14: 0.1 | F14: =$D$4*E14 -> 179194.07 | H14: ='Project Plan'!E40+7 -> 45890 | L14: 004809 | N14: 45880 | P14: 45884
B15: 3 | C15: Delivery of Inverters | E15: 0.25 | F15: =$D$4*E15 -> 447985.18 | H15: ='Project Plan'!E22+7 -> 45891 | L15: 004817 | N15: 45887 | P15: =N15+7 -> 45894
B16: 4 | C16: Practical Completion | E16: 0.1 | F16: =$D$4*E16 -> 179194.07 | H16: ='Project Plan'!G47+7 -> 45915 | L16: 004899 | N16: 46001 | P16: 46006
B17: 5 | C17: Handover | E17: 0.05 | F17: =$D$4*E17 -> 89597.037 | H17: ='Project Plan'!E59+7 -> 45922 | L17: 004929 | N17: 46044 | P17: 46052 | R17: Has this been received?
B18: 6 | C18: - | E18: 0 | F18: =$D$4*E18 -> 0
B19: 7 | C19: - | E19: 0 | F19: =$D$4*E19 -> 0
E21: =SUM(E13:E19) -> 1 | F21: =SUM(F13:F19) -> 1791940.7
B23: KEY: | C23: contains an error (in result or a check has failed)
C24: Red Font - IF TEXT : content not yet confirmed
C25: Red Font - IF NUMBER: Negative value
C26: Anything in yellow is a concern or risk for noting or action
C27: confirmed
C28: [ADD INITIALS: comment for noting in square brackets, use colour or red to draw attention if important]
C29: [RT: When adding rows into sheet, ensure you insert between first and last row of each category]
C30: end of sheet - do not insert information below/beyond this
B40: No. | C40: PAYMENT MILESTONE | E40: % | F40: VALUE
B41: 1 | C41: Deposit - Project commencement | E41: 0.35 | F41: =$F$47*E41 -> 627179.26
B42: 2 | C42: Delivery of Panels | E42: 0.3 | F42: =$F$47*E42 -> 537582.22
B43: 3 | C43: Delivery of Inverters | E43: 0.2 | F43: =$F$47*E43 -> 358388.15
B44: 4 | C44: Practical Completion | E44: 0.1 | F44: =$F$47*E44 -> 179194.07
B45: 5 | C45: Handover | E45: 0.05 | F45: =$F$47*E45 -> 89597.037
C46: Total | E46: =SUM(E41:E45) -> 1 | F46: =SUM(F41:F45) -> 1791940.7
E47: =SUM(E41:E45) -> 1 | F47: =F21 -> 1791940.7

Sheet Data
C2: Public holidays | F2: Drop down list
C3: 45658 | D3: New Years Day | F3: Approved
C4: 45737 | D4: Human Rights day | F4: Pending
C5: 45765 | D5: Good Friday | F5: Declined
C6: 45768 | D6: Family Day | F6: Abanded
C7: 45774 | D7: Freedom Day
C8: 45765 | D8: Freedom DayObserved
C9: 45778 | D9: Workers day
C10: 45824 | D10: Youth Day Holiday
C11: 45878 | D11: Womens Day
C12: 45924 | D12: Heritage Day
C13: 46007 | D13: Day of Reconciliation | H13: Manual dates
C14: 46016 | D14: Christmas Day
C15: 46017 | D15: Day of Goodwill

Sheet Expenditure Tracking
B2: HIGH LEVEL PROJECT EXPENDITURE TRACKING
F4: COSTED | H4: ACTUAL | J4: Difference from costed
B5: EXPENDITURE | F5: =SUM(F9:F23) -> 1566125.3 | H5: =SUM(H9:H23) -> 1865330.2 | J5: =SUM(J9:J23) -> -299204.96
B7: No. | D7: Item | F7: Costed Expenditure | H7: Actual Expenditure | J7: Saving / Overrun | L7: Comments on variations from planned expenditure
B9: ='Expenditure Breakdown'!L6 -> 1 | D9: ='Expenditure Breakdown'!M6 -> 1. Panels | F9: ='Expenditure Breakdown'!I6 -> 469263.17 | H9: ='Expenditure Breakdown'!X6 -> 324441 | J9: =F9-H9 -> 144822.17
B10: ='Expenditure Breakdown'!L13 -> 2 | D10: ='Expenditure Breakdown'!M13 -> 2. Inverters | F10: ='Expenditure Breakdown'!I13 -> 140000 | H10: ='Expenditure Breakdown'!X13 -> 137740.7 | J10: =F10-H10 -> 2259.3
B11: ='Expenditure Breakdown'!L23 -> 3 | D11: ='Expenditure Breakdown'!M23 -> 3. Mounting Structures | F11: ='Expenditure Breakdown'!I23 -> 66576 | H11: ='Expenditure Breakdown'!X23 -> 157679.66 | J11: =F11-H11 -> -91103.66
B12: ='Expenditure Breakdown'!L30 -> 4 | D12: ='Expenditure Breakdown'!M30 -> 4. DC Equipment | F12: ='Expenditure Breakdown'!I30 -> 151592.2 | H12: ='Expenditure Breakdown'!X30 -> 453642.25 | J12: =F12-H12 -> -302050.05
B13: ='Expenditure Breakdown'!L46 -> 5 | D13: ='Expenditure Breakdown'!M46 -> 5. Monitoring | F13: ='Expenditure Breakdown'!I46 -> 49000 | H13: ='Expenditure Breakdown'!X46 -> 36933.71 | J13: =F13-H13 -> 12066.29
B14: ='Expenditure Breakdown'!L55 -> 6 | D14: ='Expenditure Breakdown'!M55 -> 6. AC Equipment | F14: ='Expenditure Breakdown'!I55 -> 262993.38 | H14: ='Expenditure Breakdown'!X55 -> 184885.08 | J14: =F14-H14 -> 78108.303
B15: ='Expenditure Breakdown'!L74 -> 7 | D15: ='Expenditure Breakdown'!M74 -> 7.BESS | F15: ='Expenditure Breakdown'!I74 -> 0 | H15: ='Expenditure Breakdown'!X74 -> 0 | J15: =F15-H15 -> 0
B16: ='Expenditure Breakdown'!L83 -> 8 | D16: ='Expenditure Breakdown'!M83 -> 8. Product Add On | F16: ='Expenditure Breakdown'!I83 -> 4000 | H16: ='Expenditure Breakdown'!X83 -> 3600 | J16: =F16-H16 -> 400
B17: ='Expenditure Breakdown'!L93 -> 9 | D17: ='Expenditure Breakdown'!M93 -> 9. AC & DC installation | F17: ='Expenditure Breakdown'!I93 -> 138700 | H17: ='Expenditure Breakdown'!X93 -> 315566.4 | J17: =F17-H17 -> -176866.4
B18: ='Expenditure Breakdown'!L106 -> 10 | D18: ='Expenditure Breakdown'!M106 -> 10. Site Logistics | F18: ='Expenditure Breakdown'!I106 -> 76280.033 | H18: ='Expenditure Breakdown'!X106 -> 161120 | J18: =F18-H18 -> -84839.967
B19: ='Expenditure Breakdown'!L122 -> 11 | D19: ='Expenditure Breakdown'!M122 -> 11. Due Dilligence | F19: ='Expenditure Breakdown'!I122 -> 89000 | H19: ='Expenditure Breakdown'!X122 -> 20194.13 | J19: =F19-H19 -> 68805.87
B20: ='Expenditure Breakdown'!L128 -> 12 | D20: ='Expenditure Breakdown'!M128 -> 12. BDP Commission | F20: ='Expenditure Breakdown'!I128 -> 0 | H20: ='Expenditure Breakdown'!X128 -> 0 | J20: =F20-H20 -> 0
B21: ='Expenditure Breakdown'!L131 -> 13 | D21: ='Expenditure Breakdown'!M132 -> 13. Engineering | F21: ='Expenditure Breakdown'!I131 -> 115920.48 | H21: ='Expenditure Breakdown'!X131 -> 69527.3 | J21: =F21-H21 -> 46393.18
B22: ='Expenditure Breakdown'!L138 -> 14 | D22: ='Expenditure Breakdown'!M138 -> 14. General Expenses | F22: ='Expenditure Breakdown'!I138 -> 2800 | H22: ='Expenditure Breakdown'!X138 -> 0 | J22: =F22-H22 -> 2800
B23: ='Expenditure Breakdown'!L151 -> 15 | D23: ='Expenditure Breakdown'!M151 -> 15. Service Add On | F23: ='Expenditure Breakdown'!I151 -> 0 | H23: ='Expenditure Breakdown'!X151 -> 0 | J23: =F23-H23 -> 0
D25: check: | F25: ='Expenditure Breakdown'!I2-'Expenditure Tracking'!F5 -> 0 | G25: =#REF!-G5 -> #REF! | H25: ='Expenditure Breakdown'!X2-H5 -> 0

Sheet Expenditure Breakdown
B2: COSTED EXPENDITURE BREAKDOWN | I2: =SUM(I6:I163) -> 1566125.3 | J2: =SUM(J6:J163) -> 1791940.7 | L2: ACTUAL EXPENDITURE BREAKDOWN | R2: FINANCE ONLY | X2: =SUM(X6:X163) -> 1865330.2
B4: No. | C4: Product / Service | D4: Description of Work | E4: QTY | F4: Rate / Unit | G4: Budget Total | H4: FINANCE PAYMENT DATE | I4: Total COS | J4: =IF(J2-'Revenue Tracking'!D4>=0, "Total Revenue", "ERROR on REV" ) -> Total Revenue | L4: No. | M4: Product/ Service | N4: Description of Work | O4: QTY | P4: Rate / Unit | Q4: Actual Total | R4: PO NUMBER | S4: INVOICE NUMBER | T4: INVOICE RAISED DATE | U4: REVENUE RECOGNITION AMOUNT | V4: CHECK | W4: FINANCE PAYMENT DATE | X4: Total COS
B6: 1 | C6: Panels | D6: Panels Budget | G6: =D164 -> 469263.17 | H6: 45925 | I6: =SUM(G6:G11) -> 469263.17 | J6: =F164 -> 533253.6 | L6: 1 | M6: 1. Panels | N6: Jinko 590 modules | O6: 282 | P6: 1150.5 | Q6: =O6*P6 -> 324441 | S6: Menlo INV0003100 | T6: 45869 | U6: 533253.6 | V6: =J6-SUM(U6:U11) -> 0 | W6: 45925 | X6: =SUM(Q6:Q11) -> 324441
B7: 1 | D7: Delivery Budget | L7: 1 | M7: 1. Panels | T7: =IF(W7>1,EOMONTH(W7,0),"") | U7: 0
B8: 1 | L8: 1 | M8: 1. Panels | T8: =IF(W8>1,EOMONTH(W8,0),"") | U8: 0
B9: 1 | L9: 1 | M9: 1. Panels | T9: =IF(W9>1,EOMONTH(W9,0),"") | U9: 0
B10: 1 | L10: 1 | M10: 1. Panels | T10: =IF(W10>1,EOMONTH(W10,0),"") | U10: 0
B11: 1 | L11: 1 | M11: 1. Panels | T11: =IF(W11>1,EOMONTH(W11,0),"") | U11: 0 | Y11: BUDGET | Z11: Installer Allocation
S12: 45952 | T12: =IF(W12>1,EOMONTH(W12,0),"") | Y12: AC Equipment | Z12: =G55 -> 262993.38
B13: 2 | C13: Inverters | D13: Inverter Budget | G13: =D165 -> 140000 | H13: =H6 -> 45925 | I13: =SUM(G13:G21) -> 140000 | J13: =F165 -> 159090.91 | L13: 2 | M13: 2. Inverters | N13: Huawei 50KTL | O13: 1 | P13: 43606.08 | Q13: =O13*P13 -> 43606.08 | S13: Menlo INV0003100 | T13: 45869 | U13: 78238.498 | V13: =J13-SUM(U13:U21) -> 0 | W13: =W6 -> 45925 | X13: =SUM(Q13:Q21) -> 137740.7 | Y13: DC Equipment | Z13: =G31 -> 99092.2
B14: 2 | L14: 2 | M14: 2. Inverters | N14: From stock | O14: 1 | P14: 45062.94 | Q14: =O14*P14 -> 45062.94 | S14: Allocated from Cpt Stock | T14: 45869 | U14: 80852.411 | W14: 45869 | Y14: AC Labour | Z14: =G93 -> 41610
L15: 2 | M15: 2. Inverters | N15: Huawei 50KTL to be credited | Q15: -43606.08 | S15: Menlo - CRN0000252 | T15: 45930 | W15: 45926
L16: 2 | M16: 2. Inverters | N16: To be moved to Waterside | Q16: -45062.94 | S16: Allocated to Waterside | T16: 45900 | W16: 45900
B17: 2 | L17: 2 | M17: 2. Inverters | N17: Needs to be replaced with 2 x 100KTLs | U17: 0 | Y17: DC Labour | Z17: =G94 -> 97090
B18: 2 | L18: 2 | M18: 2. Inverters | N18: Huawei 100KTL (Menlo | O18: 2 | P18: =Q18/O18 -> 68870.35 | Q18: 137740.7 | S18: Menlo - INV0003227 | T18: 45900 | U18: 0 | W18: 45961 | Y18: Offloading | Z18: =G106 -> 8500
B19: 2 | L19: 2 | M19: 2. Inverters | T19: =IF(W19>1,EOMONTH(W19,0),"") | U19: 0 | Y19: Scaffolding | Z19: =G107 -> 24446.7
B20: 2 | L20: 2 | M20: 2. Inverters | T20: =IF(W20>1,EOMONTH(W20,0),"") | U20: 0 | Y20: Storage | Z20: =G109 -> 4933.3333
B21: 2 | L21: 2 | M21: 2. Inverters | T21: =IF(W21>1,EOMONTH(W21,0),"") | U21: 0 | Y21: Telehandler | Z21: 0
T22: =IF(W22>1,EOMONTH(W22,0),"")
B23: 3 | C23: Mounting Structures | D23: Structure Budget | G23: =D166 -> 66576 | H23: =H13 -> 45925 | I23: =SUM(G23:G28) -> 66576 | J23: =F166 -> 75654.545 | L23: 3 | M23: 3. Mounting Structures | N23: Schletter Structure | Q23: 154429.66 | R23: PO4233-SBT-20250818 - RV Approved | S23: Schletter INV2118 | T23: 45900 | U23: 75654.545 | V23: =J23-SUM(U23:U28) -> 0 | W23: =T23+30 -> 45930 | X23: =SUM(Q23:Q28) -> 157679.66 | Y23: Other | Z23: 0
B24: 3 | L24: 3 | M24: 3. Mounting Structures | N24: Additional Mid and End Clamps - VO | Q24: 3250 | R24: PO4471-SBT-20251114 - RV Approved | S24: Solarworld SASIV-25-00684 | T24: 45991 | U24: 0 | W24: 46031 | Y24: Total | Z24: =SUM(Z12:Z23) -> 538665.62
B25: 3 | L25: 3 | M25: 3. Mounting Structures | T25: =IF(W25>1,EOMONTH(W25,0),"") | U25: =(Q25/$X$23*$J$23) -> 0 | Y25: Less 15% | Z25: =+Z24*0.85 -> 457865.77
B26: 3 | L26: 3 | M26: 3. Mounting Structures | T26: =IF(W26>1,EOMONTH(W26,0),"") | U26: =(Q26/$X$23*$J$23) -> 0 | Y26: R/Wp | Z26: =Z25/'Project Plan'!$E$3/1000 -> 2.7582276
B27: 3 | L27: 3 | M27: 3. Mounting Structures | T27: =IF(W27>1,EOMONTH(W27,0),"") | U27: =(Q27/$X$23*$J$23) -> 0
B28: 3 | L28: 3 | M28: 3. Mounting Structures | T28: =IF(W28>1,EOMONTH(W28,0),"") | U28: =(Q28/$X$23*$J$23) -> 0 | Y28: ACTUAL - Boundary Terraces | Z28: Installer Price
T29: =IF(W29>1,EOMONTH(W29,0),"") | Y29: =Y12 -> AC Equipment | Z29: =9720+6750+68000+216+540+33750+4050 -> 123026
B30: 4 | C30: DC Equipment | D30: DC Cable Budget | E30: =G30/14*1.15 -> 4312.5 | G30: 52500 | H30: 45901 | I30: =SUM(G30:G44) -> 151592.2 | J30: =F167 -> 172263.86 | L30: 4 | M30: 4. DC Equipment | N30: DC Cable | O30: 4000 | P30: 14 | Q30: 54000 | S30: Rubicon Inv:INVWCRE-0069643 | T30: 45869 | U30: 60762.394 | V30: =J30-SUM(U30:U44) -> 0.0012712908 | W30: 45901 | X30: =SUM(Q30:Q44) -> 453642.25 | Y30: =Y13 -> DC Equipment | Z30: 345642.25
B31: 4 | D31: DC Equipment Budget | G31: =D167-G30 -> 99092.2 | H31: =H30 -> 45901 | L31: 4 | M31: 4. DC Equipment | N31: Additional DC Cable - VO | O31: 4000 | Q31: 54000 | R31: PO4257-SBT-20250831 - RV Approved | S31: Rubicon Inv:INVWCRE-0070233 | T31: 45900 | U31: 0 | W31: =T31+30 -> 45930 | Y31: =Y14 -> AC Labour | Z31: =89640+3750+6600+2250+3000+5250 -> 110490
B32: 4 | L32: 4 | M32: 4. DC Equipment | T32: =IF(W32>1,EOMONTH(W32,0),"") | U32: =(Q32/$X$30*$J$30) -> 0 | Y32: =Y17 -> DC Labour | Z32: 205076.4
B33: 4 | L33: 4 | M33: 4. DC Equipment | T33: =IF(W33>1,EOMONTH(W33,0),"") | U33: =(Q33/$X$30*$J$30) -> 0 | Y33: Lifelines
B34: 4 | L34: 4 | M34: 4. DC Equipment | N34: Project Kick Off | O34: =Z30 -> 345642.25 | P34: 0.1 | Q34: =$O$34*P34 -> 34564.225 | R34: PO4244-SBT-20250820 - RV Approved | S34: Happy Solar INV-0331 | T34: 45900 | U34: 13125.248 | W34: 45867 | Y34: Forklift
B35: 4 | L35: 4 | M35: 4. DC Equipment | N35: Site Establishment | P35: 0.15 | Q35: =$O$34*P35 -> 51846.338 | S35: Happy Solar INV-0331 | T35: 45900 | U35: 19687.872 | W35: 45905 | Y35: Geda
B36: 4 | L36: 4 | M36: 4. DC Equipment | N36: AC Installation Complete | P36: 0.2 | Q36: =$O$34*P36 -> 69128.45 | S36: Happy Solar INV-0331 | T36: 45900 | U36: 6499.4856 | W36: =W96 -> 45967 | Y36: Logistics | Z36: 161120
B37: 4 | L37: 4 | M37: 4. DC Equipment | N37: DC Installation Complete | P37: 0.25 | Q37: =$O$34*P37 -> 86410.562 | S37: Happy Solar INV-0331 | T37: 45900 | U37: 32813.119 | W37: =W97 -> 45995 | Y37: HSE | Z37: 0
B38: 4 | L38: 4 | M38: 4. DC Equipment | N38: Commissioning Complete | O38: =Q38+Q66+Q98+Q114 -> 94535.465 | P38: 0.1 | Q38: =$O$34*P38 -> 34564.225 | S38: Happy Solar INV-0331 | T38: 45900 | U38: 13125.248 | W38: 46015 | Y38: Other | Z38: 0
B39: 4 | L39: 4 | M39: 4. DC Equipment | N39: Site De-establisment | P39: 0.1 | Q39: =$O$34*P39 -> 34564.225 | S39: Happy Solar INV-0331 | T39: 45900 | U39: 13125.248 | W39: 46015 | Y39: Other | Z39: 0
B40: 4 | L40: 4 | M40: 4. DC Equipment | N40: Handover Document Complete | P40: 0.05 | Q40: =$O$34*P40 -> 17282.112 | S40: Happy Solar INV-0331 | T40: 45900 | U40: 6562.6239 | W40: =W100 -> 46051 | Y40: Total | Z40: =SUM(Z29:Z39) -> 945354.65
B41: 4 | L41: 4 | M41: 4. DC Equipment | N41: End of Defects Period | P41: 0.05 | Q41: =$O$34*P41 -> 17282.112 | S41: Happy Solar INV-0331 | T41: 45900 | U41: 6562.6239 | W41: =W101 -> 46079 | Y41: R/Wp | Z41: =Z40/'Project Plan'!$E$3/1000 -> 5.6949075
B42: 4 | L42: 4 | M42: 4. DC Equipment | T42: =IF(W42>1,EOMONTH(W42,0),"") | U42: =(Q42/$X$30*$J$30) -> 0
B43: 4 | L43: 4 | M43: 4. DC Equipment | T43: =IF(W43>1,EOMONTH(W43,0),"") | U43: =(Q43/$X$30*$J$30) -> 0
B44: 4 | L44: 4 | M44: 4. DC Equipment | T44: =IF(W44>1,EOMONTH(W44,0),"") | U44: =(Q44/$X$30*$J$30) -> 0
T45: =IF(W45>1,EOMONTH(W45,0),"")
B46: 5 | C46: Monitoring | D46: Monitoring Budget | G46: =D169-G47 -> 34000 | H46: 45925 | I46: =SUM(G46:G53) -> 49000 | J46: =F169 -> 55681.818 | L46: 5 | M46: 5. Monitoring | N46: Smartlogger | Q46: 8598.34 | S46: Menlo INV0003100 | T46: 45869 | U46: 12837.981 | V46: =J46-SUM(U46:U53) -> 0.00036923271 | W46: 45925 | X46: =SUM(Q46:Q53) -> 36933.71
B47: 5 | D47: Revenue Metering | G47: 15000 | H47: =H46 -> 45925 | L47: 5 | M47: 5. Monitoring | N47: CTs & Meters | Q47: 14768 | R47: PO4269-SBT-20250825 - RV Approved | S47: AccuEnergy - ASAI-00620 | T47: 45900 | U47: 22468.38 | W47: =T47+30 -> 45930
B48: 5 | L48: 5 | M48: 5. Monitoring | N48: Techsitter | Q48: 11169 | S48: Matriarch - INV-4999 | T48: 45900 | U48: 17104.082 | W48: 45900
L49: 5 | M49: 5. Monitoring | N49: Delivery of Techsitter Meter | Q49: 209.27 | S49: DSV Inv: 180145917 | T49: 45930 | U49: 0 | W49: 45961
B50: 5 | L50: 5 | M50: 5. Monitoring | N50: Battery | Q50: 975 | S50: Red Pole Energy: SO-35689 | T50: 45900 | U50: 1969.6941 | W50: 45899
B51: 5 | L51: 5 | M51: 5. Monitoring | N51: Powersupply | Q51: 850 | S51: Mantech-SOR1007853 | T51: 45900 | U51: 1301.6805 | W51: 45899
B52: 5 | L52: 5 | M52: 5. Monitoring | Q52: -850 | S52: Mantech - CRN949171 | T52: 45930 | U52: 0 | W52: 45930
B53: 5 | L53: 5 | M53: 5. Monitoring | Q53: 1214.1 | S53: Current Automotion - SOQ324142 | T53: 45930 | U53: 0 | W53: 45909
T54: =IF(W54>1,EOMONTH(W54,0),"")
B55: 6 | C55: AC Equipment | D55: AC Equipment Budget | G55: =D168 -> 262993.38 | H55: =H47 -> 45925 | I55: =SUM(G55:G72) -> 262993.38 | J55: =F168 -> 298856.12 | L55: 6 | M55: 6. AC Equipment | T55: =IF(W55>1,EOMONTH(W55,0),"") | U55: =(Q55/$X$55*$J$55) -> 0 | V55: =J55-SUM(U55:U72) -> 0 | X55: =SUM(Q55:Q72) -> 184885.08
B56: 6 | L56: 6 | M56: 6. AC Equipment | N56: PVDB | Q56: 61859.08 | S56: Switchboard 2-SOI002235 | T56: ='Project Plan'!K4 -> 45900 | U56: 99991.651 | W56: 45930
B57: 6 | L57: 6 | M57: 6. AC Equipment | N57: ABB XT5N 400A TP MCCB | Q57: 10499.85 | R57: PO4445-SBT-20251105 - RV Approved | S57: Switchboard 2-SOI002578 | T57: 45991 | U57: 0 | W57: 46021
B58: 6 | L58: 6 | M58: 6. AC Equipment | N58: RMA - SWB - ABB XT5N 400A TP MCCB | Q58: =-1*Q57 -> -10499.85 | T58: 46081 | U58: 0 | W58: =T58+30 -> 46111
B59: 6 | L59: 6 | M59: 6. AC Equipment | T59: =IF(W59>1,EOMONTH(W59,0),"") | U59: 0
B60: 6 | L60: 6 | M60: 6. AC Equipment | T60: =IF(W60>1,EOMONTH(W60,0),"") | U60: 0
B61: 6 | L61: 6 | M61: 6. AC Equipment | N61: Project Kick Off | O61: =Z29 -> 123026 | P61: 0.1 | Q61: =$O$61*P61-5009.68 -> 7292.92 | R61: PO4244-SBT-20250820 - RV Approved | S61: Happy Solar INV-0331 | T61: 45900 | U61: 19886.447 | W61: 45867
L62: 6 | M62: 6. AC Equipment | Q62: 5009.68 | S62: Happy Solar INV-0331 | T62: 45900 | U62: 0 | W62: 45890
B63: 6 | L63: 6 | M63: 6. AC Equipment | N63: Site Establishment | P63: 0.15 | Q63: =$O$61*P63 -> 18453.9 | S63: Happy Solar INV-0331 | T63: 45900 | U63: 29829.67 | W63: 45905
B64: 6 | L64: 6 | M64: 6. AC Equipment | N64: AC Installation Complete | P64: 0.2 | Q64: =$O$61*P64 -> 24605.2 | S64: Happy Solar INV-0331 | T64: 45900 | U64: 39772.893 | W64: =W96 -> 45967
B65: 6 | L65: 6 | M65: 6. AC Equipment | N65: DC Installation Complete | P65: 0.25 | Q65: =$O$61*P65 -> 30756.5 | S65: Happy Solar INV-0331 | T65: 45900 | U65: 49716.116 | W65: =W97 -> 45995
B66: 6 | L66: 6 | M66: 6. AC Equipment | N66: Commissioning Complete | P66: 0.1 | Q66: =$O$61*P66 -> 12302.6 | S66: Happy Solar INV-0331 | T66: 45900 | U66: 19886.447 | W66: 46015
B67: 6 | L67: 6 | M67: 6. AC Equipment | N67: Site De-establisment | P67: 0.1 | Q67: =$O$61*P67 -> 12302.6 | S67: Happy Solar INV-0331 | T67: 45900 | U67: 19886.447 | W67: 46015
B68: 6 | L68: 6 | M68: 6. AC Equipment | N68: Handover Document Complete | P68: 0.05 | Q68: =$O$61*P68 -> 6151.3 | S68: Happy Solar INV-0331 | T68: 45900 | U68: 9943.2233 | W68: =W100 -> 46051
B69: 6 | L69: 6 | M69: 6. AC Equipment | N69: End of Defects Period | P69: 0.05 | Q69: =$O$61*P69 -> 6151.3 | S69: Happy Solar INV-0331 | T69: 45900 | U69: 9943.2233 | W69: =W101 -> 46079
B70: 6 | L70: 6 | M70: 6. AC Equipment | T70: =IF(W70>1,EOMONTH(W70,0),"") | U70: =(Q70/$X$55*$J$55) -> 0
B71: 6 | L71: 6 | M71: 6. AC Equipment | T71: =IF(W71>1,EOMONTH(W71,0),"") | U71: =(Q71/$X$55*$J$55) -> 0
B72: 6 | L72: 6 | M72: 6. AC Equipment | T72: =IF(W72>1,EOMONTH(W72,0),"") | U72: =(Q72/$X$55*$J$55) -> 0
T73: =IF(W73>1,EOMONTH(W73,0),"")
B74: 7 | C74: BESS | I74: =SUM(G74:G81) -> 0 | J74: =F173 -> 0 | L74: 7 | M74: 7.BESS | V74: =J74-SUM(U74:U81) -> 0 | X74: =SUM(Q74:Q81) -> 0
B75: 7 | L75: 7 | M75: 7.BESS
B76: 7 | L76: 7 | M76: 7.BESS
B77: 7 | L77: 7 | M77: 7.BESS
B78: 7 | L78: 7 | M78: 7.BESS
B79: 7 | L79: 7 | M79: 7.BESS
B80: 7 | L80: 7 | M80: 7.BESS
B81: 7 | L81: 7 | M81: 7.BESS
B83: 8 | C83: Product Add On | I83: =SUM(G83:G91) -> 4000 | J83: =F170+F172 -> 4494.382 | L83: 8 | M83: 8. Product Add On | V83: =J83-SUM(U83:U91) -> 0 | X83: =SUM(Q83:Q91) -> 3600
B84: 8 | L84: 8 | M84: 8. Product Add On
B85: 8 | D85: Check Meter | G85: 4000 | H85: 45911 | L85: 8 | M85: 8. Product Add On | N85: Check Meter | Q85: 3600 | R85: PO4240-ARIM-20250819 - RV Approved | S85: CBB - CBB-5722 | T85: 45900 | U85: 4494.382 | W85: 45911
B86: 8 | L86: 8 | M86: 8. Product Add On
B87: 8 | L87: 8 | M87: 8. Product Add On
B88: 8 | L88: 8 | M88: 8. Product Add On
B89: 8 | L89: 8 | M89: 8. Product Add On
B90: 8 | L90: 8 | M90: 8. Product Add On
B91: 8 | L91: 8 | M91: 8. Product Add On
K92: Only services to be capture below, products above | T92: =IF(W92>1,EOMONTH(W92,0),"")
B93: 9 | C93: AC & DC Installation | D93: AC Installation Budget | G93: =D177 -> 41610 | H93: =H94 -> 45890 | I93: =SUM(G93:G104) -> 138700 | J93: =F177+F178 -> 163176.47 | L93: 9 | M93: 9. AC & DC installation | T93: =IF(W93>1,EOMONTH(W93,0),"") | U93: =(Q93/$X$93*$J$93) -> 0 | V93: =J93-SUM(U93:U104) -> 0 | X93: =SUM(Q93:Q104) -> 315566.4
B94: 9 | D94: DC Installation Budget | G94: =D178 -> 97090 | H94: 45890 | L94: 9 | M94: 9. AC & DC installation | N94: Project Kick Off | O94: =Z32+Z31 -> 315566.4 | P94: 0.1 | Q94: =$O$94*P94 -> 31556.64 | R94: PO4244-SBT-20250820 - RV Approved | S94: Happy Solar INV-0331 | T94: 45900 | U94: 16317.647 | W94: 45890
B95: 9 | L95: 9 | M95: 9. AC & DC installation | N95: Site Establishment | P95: 0.15 | Q95: =$O$94*P95 -> 47334.96 | S95: Happy Solar INV-0331 | T95: 45900 | U95: 24476.471 | W95: 45905
B96: 9 | L96: 9 | M96: 9. AC & DC installation | N96: AC Installation Complete | P96: 0.2 | Q96: =$O$94*P96 -> 63113.28 | S96: Happy Solar INV-0331 | T96: 45900 | U96: 32635.294 | W96: 45967
B97: 9 | L97: 9 | M97: 9. AC & DC installation | N97: DC Installation Complete | P97: 0.25 | Q97: =$O$94*P97 -> 78891.6 | S97: Happy Solar INV-0331 | T97: 45900 | U97: 40794.118 | W97: 45995
B98: 9 | L98: 9 | M98: 9. AC & DC installation | N98: Commissioning Complete | P98: 0.1 | Q98: =$O$94*P98 -> 31556.64 | S98: Happy Solar INV-0331 | T98: 45900 | U98: 16317.647 | W98: 46015
B99: 9 | L99: 9 | M99: 9. AC & DC installation | N99: Site De-establisment | P99: 0.1 | Q99: =$O$94*P99 -> 31556.64 | S99: Happy Solar INV-0331 | T99: 45900 | U99: 16317.647 | W99: 46015
B100: 9 | L100: 9 | M100: 9. AC & DC installation | N100: Handover Document Complete | P100: 0.05 | Q100: =$O$94*P100 -> 15778.32 | S100: Happy Solar INV-0331 | T100: 45900 | U100: 8158.8235 | W100: 46051
B101: 9 | L101: 9 | M101: 9. AC & DC installation | N101: End of Defects Period | P101: 0.05 | Q101: =$O$94*P101 -> 15778.32 | S101: Happy Solar INV-0331 | T101: 45900 | U101: 8158.8235 | W101: =W100+28 -> 46079
B102: 9 | L102: 9 | M102: 9. AC & DC installation | T102: =IF(W102>1,EOMONTH(W102,0),"") | U102: =(Q102/$X$93*$J$93) -> 0
B103: 9 | L103: 9 | M103: 9. AC & DC installation | U103: =(Q103/$X$93*$J$93) -> 0
B104: 9 | L104: 9 | M104: 9. AC & DC installation | T104: =IF(W104>1,EOMONTH(W104,0),"") | U104: =(Q104/$X$93*$J$93) -> 0
...

Sheet Cashflow
D1: [RT: Double Check the first date is always a MONDAY] | F1: 45677 | G1: =F1+7 -> 45684 | H1: =G1+7 -> 45691 | I1: =H1+7 -> 45698 | J1: =I1+7 -> 45705 | K1: =J1+7 -> 45712 | L1: =K1+7 -> 45719 | M1: =L1+7 -> 45726 | N1: =M1+7 -> 45733 | ... LD1: =LC1+7 -> 47847
A2: PLANNED | C2: CHECK | D2: CHECK
B3: Planned Revenue | C3: ='Revenue Tracking'!D4 -> 1791940.7 | D3: =SUM(F3:LD3) -> 1791940.7 | F3: =SUMIFS('Revenue Tracking'!$F$13:$F$19, 'Revenue Tracking'!$H$13:$H$19, ">="&F1,'Revenue Tracking'!$H$13:$H$19, "<"&G1) -> 0 | G3: =SUMIFS('Revenue Tracking'!$F$13:$F$19, 'Revenue Tracking'!$H$13:$H$19, ">="&G1,'Revenue Tracking'!$H$13:$H$19, "<"&H1) -> 0 | H3: =SUMIFS('Revenue Tracking'!$F$13:$F$19, 'Revenue Tracking'!$H$13:$H$19, ">="&H1,'Revenue Tracking'!$H$13:$H$19, "<"&I1) -> 0 | I3: =SUMIFS('Revenue Tracking'!$F$13:$F$19, 'Revenue Tracking'!$H$13:$H$19, ">="&I1,'Revenue Tracking'!$H$13:$H$19, "<"&J1) -> 0 | J3: =SUMIFS('Revenue Tracking'!$F$13:$F$19, 'Revenue Tracking'!$H$13:$H$19, ">="&J1,'Revenue Tracking'!$H$13:$H$19, "<"&K1) -> 0 | K3: =SUMIFS('Revenue Tracking'!$F$13:$F$19, 'Revenue Tracking'!$H$13:$H$19, ">="&K1,'Revenue Tracking'!$H$13:$H$19, "<"&L1) -> 0 | L3: =SUMIFS('Revenue Tracking'!$F$13:$F$19, 'Revenue Tracking'!$H$13:$H$19, ">="&L1,'Revenue Tracking'!$H$13:$H$19, "<"&M1) -> 0 | M3: =SUMIFS('Revenue Tracking'!$F$13:$F$19, 'Revenue Tracking'!$H$13:$H$19, ">="&M1,'Revenue Tracking'!$H$13:$H$19, "<"&N1) -> 0 | ... LC3: =SUMIFS('Revenue Tracking'!$F$13:$F$19, 'Revenue Tracking'!$H$13:$H$19, ">="&LC1,'Revenue Tracking'!$H$13:$H$19, "<"&LD1) -> 0 | LD3: =SUMIFS('Revenue Tracking'!$F$13:$F$19, 'Revenue Tracking'!$H$13:$H$19, ">="&LD1,'Revenue Tracking'!$H$13:$H$19, "<"&#REF!) -> 0
B4: Planned Revenue - Cumulative | F4: =F3 -> 0 | G4: =F4+G3 -> 0 | H4: =G4+H3 -> 0 | I4: =H4+I3 -> 0 | J4: =I4+J3 -> 0 | K4: =J4+K3 -> 0 | L4: =K4+L3 -> 0 | M4: =L4+M3 -> 0 | N4: =M4+N3 -> 0 | ... LD4: =LC4+LD3 -> 1791940.7
B5: Planned Expenditure | C5: ='Revenue Tracking'!D5 -> 1566125.3 | D5: =SUM(F5:LD5) -> 1566125.3 | F5: =SUMIFS('Expenditure Breakdown'!$G$6:$G$170, 'Expenditure Breakdown'!$H$6:$H$170, ">="&F1,'Expenditure Breakdown'!$H$6:$H$170, "<"&G1) -> 0 | G5: =SUMIFS('Expenditure Breakdown'!$G$6:$G$170, 'Expenditure Breakdown'!$H$6:$H$170, ">="&G1,'Expenditure Breakdown'!$H$6:$H$170, "<"&H1) -> 0 | H5: =SUMIFS('Expenditure Breakdown'!$G$6:$G$170, 'Expenditure Breakdown'!$H$6:$H$170, ">="&H1,'Expenditure Breakdown'!$H$6:$H$170, "<"&I1) -> 0 | I5: =SUMIFS('Expenditure Breakdown'!$G$6:$G$170, 'Expenditure Breakdown'!$H$6:$H$170, ">="&I1,'Expenditure Breakdown'!$H$6:$H$170, "<"&J1) -> 0 | J5: =SUMIFS('Expenditure Breakdown'!$G$6:$G$170, 'Expenditure Breakdown'!$H$6:$H$170, ">="&J1,'Expenditure Breakdown'!$H$6:$H$170, "<"&K1) -> 0 | K5: =SUMIFS('Expenditure Breakdown'!$G$6:$G$170, 'Expenditure Breakdown'!$H$6:$H$170, ">="&K1,'Expenditure Breakdown'!$H$6:$H$170, "<"&L1) -> 0 | L5: =SUMIFS('Expenditure Breakdown'!$G$6:$G$170, 'Expenditure Breakdown'!$H$6:$H$170, ">="&L1,'Expenditure Breakdown'!$H$6:$H$170, "<"&M1) -> 0 | M5: =SUMIFS('Expenditure Breakdown'!$G$6:$G$170, 'Expenditure Breakdown'!$H$6:$H$170, ">="&M1,'Expenditure Breakdown'!$H$6:$H$170, "<"&N1) -> 0 | ... LC5: =SUMIFS('Expenditure Breakdown'!$G$6:$G$170, 'Expenditure Breakdown'!$H$6:$H$170, ">="&LC1,'Expenditure Breakdown'!$H$6:$H$170, "<"&LD1) -> 0 | LD5: =SUMIFS('Expenditure Breakdown'!$G$6:$G$170, 'Expenditure Breakdown'!$H$6:$H$170, ">="&LD1,'Expenditure Breakdown'!$H$6:$H$170, "<"&#REF!) -> 0
B6: Planned Expenditure - Cumulative | F6: =F5 -> 0 | G6: =F6+G5 -> 0 | H6: =G6+H5 -> 0 | I6: =H6+I5 -> 0 | J6: =I6+J5 -> 0 | K6: =J6+K5 -> 0 | L6: =K6+L5 -> 0 | M6: =L6+M5 -> 0 | N6: =M6+N5 -> 0 | ... LD6: =LC6+LD5 -> 1566125.3
B7: PLANNED CashFlow | F7: =F4-F6 -> 0 | G7: =G4-G6 -> 0 | H7: =H4-H6 -> 0 | I7: =I4-I6 -> 0 | J7: =J4-J6 -> 0 | K7: =K4-K6 -> 0 | L7: =L4-L6 -> 0 | M7: =M4-M6 -> 0 | ... LD7: =LD4-LD6 -> 225815.47
A8: ACTUAL | C8: CHECK | D8: CHECK
B9: Actual + Planned Revenue | C9: ='Revenue Tracking'!F4 -> 1791940.7 | D9: =SUM(F9:LD9) -> 1791940.7 | F9: =SUMIFS('Revenue Tracking'!$F$13:$F$19, 'Revenue Tracking'!$P$13:$P$19, ">="&F1,'Revenue Tracking'!$P$13:$P$19, "<"&G1) -> 0 | G9: =SUMIFS('Revenue Tracking'!$F$13:$F$19, 'Revenue Tracking'!$P$13:$P$19, ">="&G1,'Revenue Tracking'!$P$13:$P$19, "<"&H1) -> 0 | H9: =SUMIFS('Revenue Tracking'!$F$13:$F$19, 'Revenue Tracking'!$P$13:$P$19, ">="&H1,'Revenue Tracking'!$P$13:$P$19, "<"&I1) -> 0 | I9: =SUMIFS('Revenue Tracking'!$F$13:$F$19, 'Revenue Tracking'!$P$13:$P$19, ">="&I1,'Revenue Tracking'!$P$13:$P$19, "<"&J1) -> 0 | J9: =SUMIFS('Revenue Tracking'!$F$13:$F$19, 'Revenue Tracking'!$P$13:$P$19, ">="&J1,'Revenue Tracking'!$P$13:$P$19, "<"&K1) -> 0 | K9: =SUMIFS('Revenue Tracking'!$F$13:$F$19, 'Revenue Tracking'!$P$13:$P$19, ">="&K1,'Revenue Tracking'!$P$13:$P$19, "<"&L1) -> 0 | L9: =SUMIFS('Revenue Tracking'!$F$13:$F$19, 'Revenue Tracking'!$P$13:$P$19, ">="&L1,'Revenue Tracking'!$P$13:$P$19, "<"&M1) -> 0 | M9: =SUMIFS('Revenue Tracking'!$F$13:$F$19, 'Revenue Tracking'!$P$13:$P$19, ">="&M1,'Revenue Tracking'!$P$13:$P$19, "<"&N1) -> 0 | ... LC9: =SUMIFS('Revenue Tracking'!$F$13:$F$19, 'Revenue Tracking'!$P$13:$P$19, ">="&LC1,'Revenue Tracking'!$P$13:$P$19, "<"&LD1) -> 0 | LD9: =SUMIFS('Revenue Tracking'!$F$13:$F$19, 'Revenue Tracking'!$P$13:$P$19, ">="&LD1,'Revenue Tracking'!$P$13:$P$19, "<"&#REF!) -> 0
B10: Actual + Planned Revenue - Cumulative | F10: =F9 -> 0 | G10: =F10+G9 -> 0 | H10: =G10+H9 -> 0 | I10: =H10+I9 -> 0 | J10: =I10+J9 -> 0 | K10: =J10+K9 -> 0 | L10: =K10+L9 -> 0 | M10: =L10+M9 -> 0 | N10: =M10+N9 -> 0 | ... LD10: =LC10+LD9 -> 1791940.7
B11: Actual + Planned Expenditure | C11: ='Revenue Tracking'!F5 -> 1865330.2 | D11: =SUM(F11:LD11) -> 1859510.8 | F11: =SUMIFS('Expenditure Breakdown'!$Q$6:$Q$170, 'Expenditure Breakdown'!$W$6:$W$170, ">="&F1,'Expenditure Breakdown'!$W$6:$W$170, "<"&G1) -> 0 | G11: =SUMIFS('Expenditure Breakdown'!$Q$6:$Q$170, 'Expenditure Breakdown'!$W$6:$W$170, ">="&G1,'Expenditure Breakdown'!$W$6:$W$170, "<"&H1) -> 0 | H11: =SUMIFS('Expenditure Breakdown'!$Q$6:$Q$170, 'Expenditure Breakdown'!$W$6:$W$170, ">="&H1,'Expenditure Breakdown'!$W$6:$W$170, "<"&I1) -> 0 | I11: =SUMIFS('Expenditure Breakdown'!$Q$6:$Q$170, 'Expenditure Breakdown'!$W$6:$W$170, ">="&I1,'Expenditure Breakdown'!$W$6:$W$170, "<"&J1) -> 0 | J11: =SUMIFS('Expenditure Breakdown'!$Q$6:$Q$170, 'Expenditure Breakdown'!$W$6:$W$170, ">="&J1,'Expenditure Breakdown'!$W$6:$W$170, "<"&K1) -> 0 | K11: =SUMIFS('Expenditure Breakdown'!$Q$6:$Q$170, 'Expenditure Breakdown'!$W$6:$W$170, ">="&K1,'Expenditure Breakdown'!$W$6:$W$170, "<"&L1) -> 0 | L11: =SUMIFS('Expenditure Breakdown'!$Q$6:$Q$170, 'Expenditure Breakdown'!$W$6:$W$170, ">="&L1,'Expenditure Breakdown'!$W$6:$W$170, "<"&M1) -> 0 | M11: =SUMIFS('Expenditure Breakdown'!$Q$6:$Q$170, 'Expenditure Breakdown'!$W$6:$W$170, ">="&M1,'Expenditure Breakdown'!$W$6:$W$170, "<"&N1) -> 0 | ... LC11: =SUMIFS('Expenditure Breakdown'!$Q$6:$Q$170, 'Expenditure Breakdown'!$W$6:$W$170, ">="&LC1,'Expenditure Breakdown'!$W$6:$W$170, "<"&LD1) -> 0 | LD11: =SUMIFS('Expenditure Breakdown'!$Q$6:$Q$170, 'Expenditure Breakdown'!$W$6:$W$170, ">="&LD1,'Expenditure Breakdown'!$W$6:$W$170, "<"&#REF!) -> 0
B12: Actual + Planned Expenditure - Cumulative | F12: =F11 -> 0 | G12: =F12+G11 -> 0 | H12: =G12+H11 -> 0 | I12: =H12+I11 -> 0 | J12: =I12+J11 -> 0 | K12: =J12+K11 -> 0 | L12: =K12+L11 -> 0 | M12: =L12+M11 -> 0 | N12: =M12+N11 -> 0 | ... LD12: =LC12+LD11 -> 1859510.8
B14: ACTUAL CashFlow | F14: =F10-F12 -> 0 | G14: =G10-G12 -> 0 | H14: =H10-H12 -> 0 | I14: =I10-I12 -> 0 | J14: =J10-J12 -> 0 | K14: =K10-K12 -> 0 | L14: =L10-L12 -> 0 | M14: =M10-M12 -> 0 | ... LD14: =LD10-LD12 -> -67570.06
C16: CHECK | D16: CHECK
B17: Revenue Recognition | C17: =C3-D17 -> -0.0045367337 | D17: =SUM(F17:LD17) -> 1791940.7 | F17: =SUMIFS('Expenditure Breakdown'!$U$6:$U$170, 'Expenditure Breakdown'!$T$6:$T$170, ">="&F1,'Expenditure Breakdown'!$T$6:$T$170, "<"&G1) -> 0 | G17: =SUMIFS('Expenditure Breakdown'!$U$6:$U$170, 'Expenditure Breakdown'!$T$6:$T$170, ">="&G1,'Expenditure Breakdown'!$T$6:$T$170, "<"&H1) -> 0 | H17: =SUMIFS('Expenditure Breakdown'!$U$6:$U$170, 'Expenditure Breakdown'!$T$6:$T$170, ">="&H1,'Expenditure Breakdown'!$T$6:$T$170, "<"&I1) -> 0 | I17: =SUMIFS('Expenditure Breakdown'!$U$6:$U$170, 'Expenditure Breakdown'!$T$6:$T$170, ">="&I1,'Expenditure Breakdown'!$T$6:$T$170, "<"&J1) -> 0 | J17: =SUMIFS('Expenditure Breakdown'!$U$6:$U$170, 'Expenditure Breakdown'!$T$6:$T$170, ">="&J1,'Expenditure Breakdown'!$T$6:$T$170, "<"&K1) -> 0 | K17: =SUMIFS('Expenditure Breakdown'!$U$6:$U$170, 'Expenditure Breakdown'!$T$6:$T$170, ">="&K1,'Expenditure Breakdown'!$T$6:$T$170, "<"&L1) -> 0 | L17: =SUMIFS('Expenditure Breakdown'!$U$6:$U$170, 'Expenditure Breakdown'!$T$6:$T$170, ">="&L1,'Expenditure Breakdown'!$T$6:$T$170, "<"&M1) -> 0 | M17: =SUMIFS('Expenditure Breakdown'!$U$6:$U$170, 'Expenditure Breakdown'!$T$6:$T$170, ">="&M1,'Expenditure Breakdown'!$T$6:$T$170, "<"&N1) -> 0 | ... LC17: =SUMIFS('Expenditure Breakdown'!$U$6:$U$170, 'Expenditure Breakdown'!$T$6:$T$170, ">="&LC1,'Expenditure Breakdown'!$T$6:$T$170, "<"&LD1) -> 0 | LD17: =SUMIFS('Expenditure Breakdown'!$U$6:$U$170, 'Expenditure Breakdown'!$T$6:$T$170, ">="&LD1,'Expenditure Breakdown'!$T$6:$T$170, "<"&#REF!) -> 0
B18: Revenue Recognition Cumulative | C18: =D17-D18 -> 0 | D18: =MAX(F18:LD18) -> 1791940.7 | F18: =F17 -> 0 | G18: =F18+G17 -> 0 | H18: =G18+H17 -> 0 | I18: =H18+I17 -> 0 | J18: =I18+J17 -> 0 | K18: =J18+K17 -> 0 | L18: =K18+L17 -> 0 | M18: =L18+M17 -> 0 | N18: =M18+N17 -> 0 | ... LD18: =LC18+LD17 -> 1791940.7

Sheet Finance - Revenue
A3: Sum of REVENUE RECOGNITION AMOUNT | B3: Column Labels
A4: Row Labels | B4: (blank) | C4: 45869 | D4: 45900 | E4: 45930 | F4: 45961 | G4: 45991 | I4: 46081 | J4: Grand Total
A5: (blank)
A6: 1. Panels | C6: 533253.6 | H6: 0 | J6: 533253.6
A7: 2. Inverters | B7: 0 | C7: 159090.91 | D7: 0 | H7: 0 | J7: 159090.91
A8: 3. Mounting Structures | D8: 75654.545 | G8: 0 | H8: 0 | J8: 75654.545
A9: 4. DC Equipment | C9: 60762.394 | D9: 111501.47 | H9: 0 | J9: 172263.86
A10: 5. Monitoring | C10: 12837.981 | D10: 42843.836 | E10: 0 | J10: 55681.818
A11: 6. AC Equipment | D11: 298856.12 | G11: 0 | H11: 0 | I11: 0 | J11: 298856.12
A12: 8. Product Add On | D12: 4494.382 | J12: 4494.382
A13: 9. AC & DC installation | B13: 0 | D13: 163176.47 | H13: 0 | J13: 163176.47
A14: 10. Site Logistics | B14: 0 | D14: 89741.216 | H14: 0 | J14: 89741.216
A15: 11. Due Dilligence | C15: 18532.64 | D15: 86173.247 | H15: 0 | J15: 104705.89
A16: 13. Engineering | B16: 0 | D16: 131727.82 | H16: 0 | J16: 131727.82
A17: 14. General Expenses | D17: 3294.1176 | E17: 0 | F17: 0 | G17: 0 | H17: 0 | J17: 3294.1176
A18: 15. Service Add On
A19: 12. BDP Commission
A20: 7.BESS
A21: Grand Total | B21: 0 | C21: 784477.53 | D21: 1007463.2 | E21: 0 | F21: 0 | G21: 0 | H21: 0 | I21: 0 | J21: 1791940.7
D23: 1791940.7

Sheet Finance - COS
A3: Sum of Actual Total | B3: Column Labels
A4: Row Labels | B4: (blank) | C4: 45869 | D4: 45900 | E4: 45930 | F4: 45961 | G4: 45991 | I4: 46081 | J4: Grand Total
A5: (blank)
A6: 1. Panels | C6: 324441 | J6: 324441
A7: 2. Inverters | C7: 88669.02 | D7: 92677.76 | E7: -43606.08 | J7: 137740.7
A8: 3. Mounting Structures | D8: 154429.66 | G8: 3250 | J8: 157679.66
A9: 4. DC Equipment | C9: 54000 | D9: 399642.25 | J9: 453642.25
A10: 5. Monitoring | C10: 8598.34 | D10: 27762 | E10: 573.37 | J10: 36933.71
A11: 6. AC Equipment | D11: 184885.08 | G11: 10499.85 | I11: -10499.85 | J11: 184885.08
A12: 8. Product Add On | D12: 3600 | J12: 3600
A13: 9. AC & DC installation | D13: 315566.4 | J13: 315566.4
A14: 10. Site Logistics | D14: 161120 | J14: 161120
A15: 11. Due Dilligence | C15: 14194.13 | D15: 6000 | J15: 20194.13
A16: 13. Engineering | B16: 0 | D16: 22399.259 | J16: 22399.259
A17: 14. General Expenses | D17: 0 | J17: 0
A18: 15. Service Add On
A19: 12. BDP Commission
A20: 7.BESS
A21: Grand Total | B21: 0 | C21: 489902.49 | D21: 1368082.4 | E21: -43032.71 | G21: 13749.85 | I21: -10499.85 | J21: 1818202.2

Sheet Certificate - Financial Close
B2: Emergent Energy – Financial Close Completion Certificate | H2: FINANCIAL CLOSE CERTIFICATE
B4: Project Name: | C4: ='Project Plan'!E2 -> The View
B5: COO: | C5: Johannes Potgieter
B6: Programme Manager: | C6: Roedolph Venter
B7: HoPD: | C7: Natasha Watkins-Baker
B9: Date of Phase Completion: | F9: {=_xlfn.LET(_xlpm.w,$B$10:$B$54,_xlpm.r,$M$10:$M$54,_xlpm.v,IF(ISNUMBER(_xlpm.r),_xlpm.r,IFERROR(VALUE(SUBSTITUTE(_xlpm.r,"%",""))/100,0)),_xlpm.g,IFERROR(VALUE(LEFT(_xlpm.w,1)),0),_xlpm.bdOnly,(SUMPRODUCT((_xlpm.w="1.1")*(_xlpm.v>0))>0)*(SUMPRODUCT((_xlpm.w<>"1.1")*(_xlpm.v>0))=0),_xlpm.anyConstr,SUMPRODUCT((_xlpm.g>=2)*(_xlpm.g<=6)*(_xlpm.v>0))>0,_xlpm.anyQA,SUMPRODUCT((_xlpm.g=7)*(_xlpm.v>0))>0,_xlpm.anyHO,SUMPRODUCT((_xlpm.g=8)*(_xlpm.v>0))>0,_xlpm.anyPlan,SUMPRODUCT((_xlpm.g=1)*(_xlpm.v>0))>0,IF(_xlpm.bdOnly,"1. Financial Close",IF(_xlpm.anyConstr,"3. Construction",IF(_xlpm.anyQA,"4. QA",IF(_xlpm.anyHO,"5. Handover",IF(_xlpm.anyPlan,"2. Planning","1. Financial Close"))))))} -> 1. Financial Close | G9: {=_xlfn.LET(_xlpm.w,$B$10:$B$54,_xlpm.r,$N$10:$N$54,_xlpm.v,IF(ISNUMBER(_xlpm.r),_xlpm.r,IFERROR(VALUE(SUBSTITUTE(_xlpm.r,"%",""))/100,0)),_xlpm.g,IFERROR(VALUE(LEFT(_xlpm.w,1)),0),_xlpm.bdOnly,(SUMPRODUCT((_xlpm.w="1.1")*(_xlpm.v>0))>0)*(SUMPRODUCT((_xlpm.w<>"1.1")*(_xlpm.v>0))=0),_xlpm.anyConstr,SUMPRODUCT((_xlpm.g>=2)*(_xlpm.g<=6)*(_xlpm.v>0))>0,_xlpm.anyQA,SUMPRODUCT((_xlpm.g=7)*(_xlpm.v>0))>0,_xlpm.anyHO,SUMPRODUCT((_xlpm.g=8)*(_xlpm.v>0))>0,_xlpm.anyPlan,SUMPRODUCT((_xlpm.g=1)*(_xlpm.v>0))>0,IF(_xlpm.bdOnly,"1. Financial Close",IF(_xlpm.anyConstr,"3. Construction",IF(_xlpm.anyQA,"4. QA",IF(_xlpm.anyHO,"5. Handover",IF(_xlpm.anyPlan,"2. Planning","1. Financial Close"))))))} -> 1. Financial Close
B10: Phase Deliverables Checklist: (Y/N)
B11: Product Agreement | C11: NA
B12: EPC Agreement | C12: NA
B13: O&M Agreeement | C13: NA
B14: Cost Proposal | C14: Signed
B15: Deposit Received | C15: Yes
B16: Risks / Notes | C16: None
B18: Acknowledgement and Acceptance:
B19: Role | C19: Name | D19: Signature | E19: Date
B20: COO | C20: Johannes | D20: JTP | E20: 45953

Sheet Project Margins
A1: [capture project margins from costing sheet]
A3: Products | D3: 0.32
A4: Services | D4: 0.5
A5: Expenses | D5: 0.15
A6: Subcontractors | D6: 0.2

Sheet Equipment Quotes
B2: Equipment Quote and Budget comparision
B4: Description | D4: Budget | F4: Supplier 1 | H4: Variance | J4: Supplier 2 | L4: Variance | N4: Comments / Notes
F7: >Name< | J7: >Name<
B9: Inverters | D9: =SUM(D10:D11) -> #REF! | F9: =SUM(F10:F13) -> 0 | H9: =$D$9-F9 -> #REF! | J9: =SUM(J10:J13) -> 0 | L9: =$D$9-J9 -> #REF!
B10: Inverters | D10: =#REF! -> #REF!
B11: Optimizers | D11: =#REF! -> #REF!
B12: Warranty
B13: Delivery fee
F15: >Name< | J15: >Name<
B17: Mounting Structure | D17: =SUM(D18:D19) -> #REF! | F17: =SUM(F18:F20) -> 0 | H17: =$D$17- F17 -> #REF! | J17: =SUM(J18:J20) -> 0 | L17: =$D$17- J17 -> #REF!
B18: Mounting Structure | D18: =#REF! -> #REF!
B19: Delivery fee
F21: >Name< | J21: >Name<
B23: DC Cable | D23: =SUM(D24:D25) -> #REF! | F23: =SUM(F24:F25) -> 0 | H23: =$D$23- F23 -> #REF! | J23: =SUM(J24:J25) -> 0 | L23: =$D$23- J23 -> #REF!
B24: DC Cable | D24: =#REF! -> #REF!
B25: Delivery fee
F27: >Name< | J27: >Name<
B29: Monitoring system | D29: =SUM(D30:D32) -> #REF! | F29: =SUM(F30:F42) -> 0 | H29: =$D$29-F29 -> #REF! | J29: =SUM(J30:J32) -> 0 | L29: =$D$29-J29 -> #REF!
B30: =#REF! -> #REF! | D30: =#REF! -> #REF!
B31: =#REF! -> #REF! | D31: =#REF! -> #REF!
B32: Delivery fee
F34: >Name< | J34: >Name<
B36: Additional Scope | D36: =SUM(D37:D41) -> #REF! | F36: =SUM(F37:F41) -> 0 | H36: =$D$29-F36 -> #REF! | J36: =SUM(J37:J41) -> 0 | L36: =$D$29-J36 -> #REF!
B37: SCADA | D37: =#REF! -> #REF!
B38: Inverter cage
B39: Cat ladders
B40: Gen Integration
B41: Lifelines
B43: Totals | D43: =D36+D29+D23+D17+D9 -> #REF! | H43: =SUM(H7:H42) -> #REF! | L43: =SUM(L7:L42) -> #REF!
B47: All amounts are incl VAT

Sheet Installer Quotes
B2: Installer Quote and Budget comparision
B4: Description | D4: Budget | G4: Cosmic Sun | J4: Variance | L4: Matthews Group | O4: Variance
B6: AC Equipment | D6: =#REF! -> #REF! | E6: =D6/(1000*'Project Plan'!$E$3) -> #REF! | G6: 277892.91 | H6: =G6/('Project Plan'!$E$3*1000) -> 1.6740537 | J6: =D6-G6 -> #REF! | M6: =L6/('Project Plan'!$E$3*1000) -> 0 | O6: =D6-L6 -> #REF!
B7: DC Equipment | D7: =#REF! -> #REF! | E7: =D7/(1000*'Project Plan'!$E$3) -> #REF! | G7: 142158.25 | H7: =G7/('Project Plan'!$E$3*1000) -> 0.856375 | J7: =D7-G7 -> #REF! | M7: =L7/('Project Plan'!$E$3*1000) -> 0 | O7: =D7-L7 -> #REF!
B8: AC Labour | D8: =#REF! -> #REF! | E8: =D8/(1000*'Project Plan'!$E$3) -> #REF! | G8: 96174 | H8: =G8/('Project Plan'!$E$3*1000) -> 0.57936145 | J8: =D8-G8 -> #REF! | M8: =L8/('Project Plan'!$E$3*1000) -> 0 | O8: =D8-L8 -> #REF!
B9: DC Labour | D9: =#REF! -> #REF! | E9: =D9/(1000*'Project Plan'!$E$3) -> #REF! | G9: 230160 | H9: =G9/('Project Plan'!$E$3*1000) -> 1.386506 | J9: =D9-G9 -> #REF! | M9: =L9/('Project Plan'!$E$3*1000) -> 0 | O9: =D9-L9 -> #REF!
B10: Offloading | D10: =#REF! -> #REF! | G10: 0 | J10: =D10-G10 -> #REF! | O10: =D10-L10 -> #REF!
B11: Roof Access/Scaffolding | D11: =#REF! -> #REF! | G11: 29257.61 | J11: =D11-G11 -> #REF! | O11: =D11-L11 -> #REF!
B12: Storage | D12: =#REF! -> #REF! | J12: =D12-G12 -> #REF! | O12: =D12-L12 -> #REF!
B13: Telehandler | D13: =#REF! -> #REF!
B14: HSE | D14: 0
B15: Totals | D15: =SUM(D6:D13) -> #REF! | G15: =SUM(G6:G13) -> 775642.77 | J15: =SUM(J6:J14) -> #REF! | L15: =SUM(L6:L13) -> 0 | O15: =SUM(O6:O14) -> #REF!
B18: Description | D18: Budget | G18: >Installer Name 3< | J18: Variance | L18: >Installer Name 4< | O18: Variance
B20: AC installation | D20: =#REF! -> #REF! | E20: =D20/(1000*'Project Plan'!$E$3) -> #REF! | H20: =G20/(1000*'Project Plan'!$E$3) -> 0 | J20: =D20-G20 -> #REF! | M20: =L20/(1000*'Project Plan'!$E$3) -> 0 | O20: =D6-L20 -> #REF!
B21: AC equipment | D21: =#REF! -> #REF! | E21: =D21/(1000*'Project Plan'!$E$3) -> #REF! | J21: =D21-G21 -> #REF! | M21: =L21/(1000*'Project Plan'!$E$3) -> 0 | O21: =D7-L21 -> #REF!
B22: DC installation | D22: =#REF! -> #REF! | E22: =D22/(1000*'Project Plan'!$E$3) -> #REF! | H22: =G22/(1000*'Project Plan'!$E$3) -> 0 | J22: =D22-G22 -> #REF! | M22: =L22/(1000*'Project Plan'!$E$3) -> 0 | O22: =D8-L22 -> #REF!
B23: DC equipment | D23: =SUM(#REF!) -> #REF! | E23: =D23/(1000*'Project Plan'!$E$3) -> #REF! | J23: =D23-G23 -> #REF! | O23: =D9-L23 -> #REF!
B24: Storage | D24: =#REF! -> #REF! | J24: =D24-G24 -> #REF! | O24: =D10-L24 -> #REF!
B25: Panel lifting equipment | D25: =SUM(#REF!) -> #REF! | J25: =D25-G25 -> #REF! | O25: =D11-L25 -> #REF!
B26: Offloading | D26: =#REF! -> #REF! | J26: =D26-G26 -> #REF! | O26: =D12-L26 -> #REF!
B29: Totals | D29: =SUM(D20:D27) -> #REF! | G29: =SUM(G20:G27) -> 0 | J29: =SUM(J20:J28) -> #REF! | L29: =SUM(L20:L27) -> 0 | O29: =SUM(O20:O28) -> #REF!
B32: Budget Summary
B34: Budget | D34: =D15 -> #REF!
B35: =G4 -> Cosmic Sun | D35: =G15 -> 775642.77
B36: =L4 -> Matthews Group | D36: =L15 -> 0
B37: =G18 -> >Installer Name 3< | D37: =G29 -> 0
B38: =L18 -> >Installer Name 4< | D38: =L29 -> 0
B40: =IF(D40<D34,"Saving","Loss") -> #REF! | D40: =D34-MIN(D35:D38) -> #REF!
B42: All amounts are exc VAT

Sheet Decision Register
B1: =D15 -> The View | E1: Decision Register
B3: ID | C3: Decision Description | D3: Decision Impact | E3: Proposed Date | F3: Proposed By | G3: Status | H3: Approved By | I3: Date | J3: Results / Comments
B4: DEC001
B5: DEC002
B6: DEC003
B7: DEC004
B8: DEC005
B9: DEC006
B10: DEC007
B11: DEC008
B12: DEC009
B13: DEC010
D15: {='Project Plan'!E2:H2} -> The View | E15: 0 | F15: 0 | G15: 0
