Workbook
Name Inverter_Capacity: #REF!
Name Inverter_Supplier: #REF!
Name Project_Size: 'Certificate - Financial Close'!Projectsize
Name Project_Size: Compliance!Projectsize
Name Project_Size: 'Finance - Revenue'!Projectsize
Name Project_Size: Projectsize
Name Projectsize: #REF!
Name Projectsize: #REF!
Name Projectsize: #REF!
Name Projectsize: 'Project Margins'!$K$5
Name Security_Serv: #REF!
Name Security_Serv: #REF!
Name SSS: #REF!
Name SSS: #REF!
Name USD_ZAR: #REF!

Sheet Sheet1
A1: PROJECT PLAN
A2: # | B2: Project Milestone | C2: Planned Start Date | D2: Duration (Work Days) | E2: Planned End Date | F2: Actual Start Date | H2: Actual End Date | J2: Comments | L2: =C3 -> 43831 | M2: =L2+3 -> 43834 | N2: =M2+7 -> 43841 | O2: =N2+7 -> 43848 | P2: =O2+7 -> 43855 | Q2: =P2+6 -> 43861 | R2: =Q2+1 -> 43862 | S2: =R2+7 -> 43869 | T2: =S2+7 -> 43876 | U2: =T2+7 -> 43883 | V2: =U2+6 -> 43889 | W2: =V2+7 -> 43896 | X2: =W2+7 -> 43903 | Y2: =X2+7 -> 43910 | Z2: =Y2+7 -> 43917 | AA2: =Z2+3 -> 43920 | AB2: =AA2+4 -> 43924 | AC2: =AB2+7 -> 43931 | AD2: =AC2+7 -> 43938 | AE2: =AD2+7 -> 43945 | AF2: =AE2+6 -> 43951 | AG2: =AF2+2 -> 43953 | AH2: =AG2+7 -> 43960 | AI2: =AH2+7 -> 43967 | AJ2: =AI2+7 -> 43974 | AK2: =AJ2+7 -> 43981 | AL2: =AK2+1 -> 43982 | AM2: =AL2+6 -> 43988 | AN2: =AM2+7 -> 43995 | AO2: =AN2+7 -> 44002 | AP2: =AO2+7 -> 44009 | AQ2: =AP2+3 -> 44012 | AR2: =AQ2+4 -> 44016 | AS2: =AR2+7 -> 44023 | AT2: =AS2+7 -> 44030 | AU2: =AT2+7 -> 44037 | AV2: =AU2+6 -> 44043 | AW2: =AV2+1 -> 44044 | AX2: =AW2+7 -> 44051 | AY2: =AX2+7 -> 44058 | AZ2: =AY2+7 -> 44065 | BA2: =AZ2+7 -> 44072 | BB2: =BA2+2 -> 44074 | BC2: =BB2+5 -> 44079 | BD2: =BC2+7 -> 44086 | BE2: =BD2+7 -> 44093 | BF2: =BE2+7 -> 44100 | BG2: =BF2+4 -> 44104
A3: 1 | B3: Contract Signature | C3: 43831 | D3: 1 | E3: 43832 | F3: 43831 | G3: 1 | H3: 43832 | L3: =IF(AND($F3<(L$2+7),$F3>L$2),1, IF(AND($H3<L$2+7,$H3>L$2),3, IF(AND($F3<=L$2, $H3>=L$2), 2, "" ))) -> 3 | M3: =IF(AND($F3<(M$2+7),$F3>M$2),1, IF(AND($H3<M$2+7,$H3>M$2),3, IF(AND($F3<=M$2, $H3>=M$2), 2, "" ))) | N3: =IF(AND($F3<(N$2+7),$F3>N$2),1, IF(AND($H3<N$2+7,$H3>N$2),3, IF(AND($F3<=N$2, $H3>=N$2), 2, "" ))) | O3: =IF(AND($F3<(O$2+7),$F3>O$2),1, IF(AND($H3<O$2+7,$H3>O$2),3, IF(AND($F3<=O$2, $H3>=O$2), 2, "" ))) | P3: =IF(AND($F3<(P$2+7),$F3>P$2),1, IF(AND($H3<P$2+7,$H3>P$2),3, IF(AND($F3<=P$2, $H3>=P$2), 2, "" ))) | Q3: =IF(AND($F3<(Q$2+7),$F3>Q$2),1, IF(AND($H3<Q$2+7,$H3>Q$2),3, IF(AND($F3<=Q$2, $H3>=Q$2), 2, "" ))) | R3: =IF(AND($F3<(R$2+7),$F3>R$2),1, IF(AND($H3<R$2+7,$H3>R$2),3, IF(AND($F3<=R$2, $H3>=R$2), 2, "" ))) | S3: =IF(AND($F3<(S$2+7),$F3>S$2),1, IF(AND($H3<S$2+7,$H3>S$2),3, IF(AND($F3<=S$2, $H3>=S$2), 2, "" ))) | ... AQ3: =IF(AND($F3<(AQ$2+7),$F3>AQ$2),1, IF(AND($H3<AQ$2+7,$H3>AQ$2),3, IF(AND($F3<=AQ$2, $H3>=AQ$2), 2, "" )))
A4: A | B4: PAYMENT MILESTONE 1: DEPOSIT | C4: 43832 | D4: 1 | E4: 43833 | F4: 43832 | G4: 1 | H4: 43833 | L4: =IF(AND($F4<(L$2+7),$F4>L$2),1, IF(AND($H4<L$2+7,$H4>L$2),3, IF(AND($F4<=L$2, $H4>=L$2), 2, "" ))) -> 1 | M4: =IF(AND($F4<(M$2+7),$F4>M$2),1, IF(AND($H4<M$2+7,$H4>M$2),3, IF(AND($F4<=M$2, $H4>=M$2), 2, "" ))) | N4: =IF(AND($F4<(N$2+7),$F4>N$2),1, IF(AND($H4<N$2+7,$H4>N$2),3, IF(AND($F4<=N$2, $H4>=N$2), 2, "" ))) | O4: =IF(AND($F4<(O$2+7),$F4>O$2),1, IF(AND($H4<O$2+7,$H4>O$2),3, IF(AND($F4<=O$2, $H4>=O$2), 2, "" ))) | P4: =IF(AND($F4<(P$2+7),$F4>P$2),1, IF(AND($H4<P$2+7,$H4>P$2),3, IF(AND($F4<=P$2, $H4>=P$2), 2, "" ))) | Q4: =IF(AND($F4<(Q$2+7),$F4>Q$2),1, IF(AND($H4<Q$2+7,$H4>Q$2),3, IF(AND($F4<=Q$2, $H4>=Q$2), 2, "" ))) | R4: =IF(AND($F4<(R$2+7),$F4>R$2),1, IF(AND($H4<R$2+7,$H4>R$2),3, IF(AND($F4<=R$2, $H4>=R$2), 2, "" ))) | S4: =IF(AND($F4<(S$2+7),$F4>S$2),1, IF(AND($H4<S$2+7,$H4>S$2),3, IF(AND($F4<=S$2, $H4>=S$2), 2, "" ))) | ... AQ4: =IF(AND($F4<(AQ$2+7),$F4>AQ$2),1, IF(AND($H4<AQ$2+7,$H4>AQ$2),3, IF(AND($F4<=AQ$2, $H4>=AQ$2), 2, "" )))
A5: 2 | B5: Structural and Electrical Due Diligences | C5: 43833 | D5: 5 | E5: 43840 | F5: 43833 | G5: 5 | H5: 43840 | L5: =IF(AND($F5<(L$2+7),$F5>L$2),1, IF(AND($H5<L$2+7,$H5>L$2),3, IF(AND($F5<=L$2, $H5>=L$2), 2, "" ))) -> 1 | M5: =IF(AND($F5<(M$2+7),$F5>M$2),1, IF(AND($H5<M$2+7,$H5>M$2),3, IF(AND($F5<=M$2, $H5>=M$2), 2, "" ))) -> 3 | N5: =IF(AND($F5<(N$2+7),$F5>N$2),1, IF(AND($H5<N$2+7,$H5>N$2),3, IF(AND($F5<=N$2, $H5>=N$2), 2, "" ))) | O5: =IF(AND($F5<(O$2+7),$F5>O$2),1, IF(AND($H5<O$2+7,$H5>O$2),3, IF(AND($F5<=O$2, $H5>=O$2), 2, "" ))) | P5: =IF(AND($F5<(P$2+7),$F5>P$2),1, IF(AND($H5<P$2+7,$H5>P$2),3, IF(AND($F5<=P$2, $H5>=P$2), 2, "" ))) | Q5: =IF(AND($F5<(Q$2+7),$F5>Q$2),1, IF(AND($H5<Q$2+7,$H5>Q$2),3, IF(AND($F5<=Q$2, $H5>=Q$2), 2, "" ))) | R5: =IF(AND($F5<(R$2+7),$F5>R$2),1, IF(AND($H5<R$2+7,$H5>R$2),3, IF(AND($F5<=R$2, $H5>=R$2), 2, "" ))) | S5: =IF(AND($F5<(S$2+7),$F5>S$2),1, IF(AND($H5<S$2+7,$H5>S$2),3, IF(AND($F5<=S$2, $H5>=S$2), 2, "" ))) | ... AQ5: =IF(AND($F5<(AQ$2+7),$F5>AQ$2),1, IF(AND($H5<AQ$2+7,$H5>AQ$2),3, IF(AND($F5<=AQ$2, $H5>=AQ$2), 2, "" )))
A6: 3 | B6: Design Confirmation | C6: 43841 | D6: 2 | E6: 43844 | F6: 43841 | G6: 2 | H6: 43844 | L6: =IF(AND($F6<(L$2+7),$F6>L$2),1, IF(AND($H6<L$2+7,$H6>L$2),3, IF(AND($F6<=L$2, $H6>=L$2), 2, "" ))) | M6: =IF(AND($F6<(M$2+7),$F6>M$2),1, IF(AND($H6<M$2+7,$H6>M$2),3, IF(AND($F6<=M$2, $H6>=M$2), 2, "" ))) | N6: =IF(AND($F6<(N$2+7),$F6>N$2),1, IF(AND($H6<N$2+7,$H6>N$2),3, IF(AND($F6<=N$2, $H6>=N$2), 2, "" ))) -> 3 | O6: =IF(AND($F6<(O$2+7),$F6>O$2),1, IF(AND($H6<O$2+7,$H6>O$2),3, IF(AND($F6<=O$2, $H6>=O$2), 2, "" ))) | P6: =IF(AND($F6<(P$2+7),$F6>P$2),1, IF(AND($H6<P$2+7,$H6>P$2),3, IF(AND($F6<=P$2, $H6>=P$2), 2, "" ))) | Q6: =IF(AND($F6<(Q$2+7),$F6>Q$2),1, IF(AND($H6<Q$2+7,$H6>Q$2),3, IF(AND($F6<=Q$2, $H6>=Q$2), 2, "" ))) | R6: =IF(AND($F6<(R$2+7),$F6>R$2),1, IF(AND($H6<R$2+7,$H6>R$2),3, IF(AND($F6<=R$2, $H6>=R$2), 2, "" ))) | S6: =IF(AND($F6<(S$2+7),$F6>S$2),1, IF(AND($H6<S$2+7,$H6>S$2),3, IF(AND($F6<=S$2, $H6>=S$2), 2, "" ))) | ... AQ6: =IF(AND($F6<(AQ$2+7),$F6>AQ$2),1, IF(AND($H6<AQ$2+7,$H6>AQ$2),3, IF(AND($F6<=AQ$2, $H6>=AQ$2), 2, "" )))
A7: 4 | B7: Equipment Procurement | C7: 43833 | E7: 43949 | F7: 43833 | H7: 43949 | L7: =IF(AND($F7<(L$2+7),$F7>L$2),1, IF(AND($H7<L$2+7,$H7>L$2),3, IF(AND($F7<=L$2, $H7>=L$2), 2, "" ))) -> 1 | M7: =IF(AND($F7<(M$2+7),$F7>M$2),1, IF(AND($H7<M$2+7,$H7>M$2),3, IF(AND($F7<=M$2, $H7>=M$2), 2, "" ))) -> 2 | N7: =IF(AND($F7<(N$2+7),$F7>N$2),1, IF(AND($H7<N$2+7,$H7>N$2),3, IF(AND($F7<=N$2, $H7>=N$2), 2, "" ))) -> 2 | O7: =IF(AND($F7<(O$2+7),$F7>O$2),1, IF(AND($H7<O$2+7,$H7>O$2),3, IF(AND($F7<=O$2, $H7>=O$2), 2, "" ))) -> 2 | P7: =IF(AND($F7<(P$2+7),$F7>P$2),1, IF(AND($H7<P$2+7,$H7>P$2),3, IF(AND($F7<=P$2, $H7>=P$2), 2, "" ))) -> 2 | Q7: =IF(AND($F7<(Q$2+7),$F7>Q$2),1, IF(AND($H7<Q$2+7,$H7>Q$2),3, IF(AND($F7<=Q$2, $H7>=Q$2), 2, "" ))) -> 2 | R7: =IF(AND($F7<(R$2+7),$F7>R$2),1, IF(AND($H7<R$2+7,$H7>R$2),3, IF(AND($F7<=R$2, $H7>=R$2), 2, "" ))) -> 2 | S7: =IF(AND($F7<(S$2+7),$F7>S$2),1, IF(AND($H7<S$2+7,$H7>S$2),3, IF(AND($F7<=S$2, $H7>=S$2), 2, "" ))) -> 2 | ... AQ7: =IF(AND($F7<(AQ$2+7),$F7>AQ$2),1, IF(AND($H7<AQ$2+7,$H7>AQ$2),3, IF(AND($F7<=AQ$2, $H7>=AQ$2), 2, "" )))
B8: Panel Procurement | C8: 43833 | D8: 5 | E8: 43840 | F8: 43833 | G8: 5 | H8: 43840 | L8: =IF(AND($F8<(L$2+7),$F8>L$2),1, IF(AND($H8<L$2+7,$H8>L$2),3, IF(AND($F8<=L$2, $H8>=L$2), 2, "" ))) -> 1 | M8: =IF(AND($F8<(M$2+7),$F8>M$2),1, IF(AND($H8<M$2+7,$H8>M$2),3, IF(AND($F8<=M$2, $H8>=M$2), 2, "" ))) -> 3 | N8: =IF(AND($F8<(N$2+7),$F8>N$2),1, IF(AND($H8<N$2+7,$H8>N$2),3, IF(AND($F8<=N$2, $H8>=N$2), 2, "" ))) | O8: =IF(AND($F8<(O$2+7),$F8>O$2),1, IF(AND($H8<O$2+7,$H8>O$2),3, IF(AND($F8<=O$2, $H8>=O$2), 2, "" ))) | P8: =IF(AND($F8<(P$2+7),$F8>P$2),1, IF(AND($H8<P$2+7,$H8>P$2),3, IF(AND($F8<=P$2, $H8>=P$2), 2, "" ))) | Q8: =IF(AND($F8<(Q$2+7),$F8>Q$2),1, IF(AND($H8<Q$2+7,$H8>Q$2),3, IF(AND($F8<=Q$2, $H8>=Q$2), 2, "" ))) | R8: =IF(AND($F8<(R$2+7),$F8>R$2),1, IF(AND($H8<R$2+7,$H8>R$2),3, IF(AND($F8<=R$2, $H8>=R$2), 2, "" ))) | S8: =IF(AND($F8<(S$2+7),$F8>S$2),1, IF(AND($H8<S$2+7,$H8>S$2),3, IF(AND($F8<=S$2, $H8>=S$2), 2, "" ))) | ... AQ8: =IF(AND($F8<(AQ$2+7),$F8>AQ$2),1, IF(AND($H8<AQ$2+7,$H8>AQ$2),3, IF(AND($F8<=AQ$2, $H8>=AQ$2), 2, "" )))
B9: Inverter Procurement | C9: 43941 | D9: 5 | E9: 43949 | F9: 43941 | G9: 5 | H9: 43949 | L9: =IF(AND($F9<(L$2+7),$F9>L$2),1, IF(AND($H9<L$2+7,$H9>L$2),3, IF(AND($F9<=L$2, $H9>=L$2), 2, "" ))) | M9: =IF(AND($F9<(M$2+7),$F9>M$2),1, IF(AND($H9<M$2+7,$H9>M$2),3, IF(AND($F9<=M$2, $H9>=M$2), 2, "" ))) | N9: =IF(AND($F9<(N$2+7),$F9>N$2),1, IF(AND($H9<N$2+7,$H9>N$2),3, IF(AND($F9<=N$2, $H9>=N$2), 2, "" ))) | O9: =IF(AND($F9<(O$2+7),$F9>O$2),1, IF(AND($H9<O$2+7,$H9>O$2),3, IF(AND($F9<=O$2, $H9>=O$2), 2, "" ))) | P9: =IF(AND($F9<(P$2+7),$F9>P$2),1, IF(AND($H9<P$2+7,$H9>P$2),3, IF(AND($F9<=P$2, $H9>=P$2), 2, "" ))) | Q9: =IF(AND($F9<(Q$2+7),$F9>Q$2),1, IF(AND($H9<Q$2+7,$H9>Q$2),3, IF(AND($F9<=Q$2, $H9>=Q$2), 2, "" ))) | R9: =IF(AND($F9<(R$2+7),$F9>R$2),1, IF(AND($H9<R$2+7,$H9>R$2),3, IF(AND($F9<=R$2, $H9>=R$2), 2, "" ))) | S9: =IF(AND($F9<(S$2+7),$F9>S$2),1, IF(AND($H9<S$2+7,$H9>S$2),3, IF(AND($F9<=S$2, $H9>=S$2), 2, "" ))) | ... AQ9: =IF(AND($F9<(AQ$2+7),$F9>AQ$2),1, IF(AND($H9<AQ$2+7,$H9>AQ$2),3, IF(AND($F9<=AQ$2, $H9>=AQ$2), 2, "" )))
B10: Mounting Structure Procurement | C10: 43941 | D10: 5 | E10: 43949 | F10: 43941 | G10: 5 | H10: 43949 | L10: =IF(AND($F10<(L$2+7),$F10>L$2),1, IF(AND($H10<L$2+7,$H10>L$2),3, IF(AND($F10<=L$2, $H10>=L$2), 2, "" ))) | M10: =IF(AND($F10<(M$2+7),$F10>M$2),1, IF(AND($H10<M$2+7,$H10>M$2),3, IF(AND($F10<=M$2, $H10>=M$2), 2, "" ))) | N10: =IF(AND($F10<(N$2+7),$F10>N$2),1, IF(AND($H10<N$2+7,$H10>N$2),3, IF(AND($F10<=N$2, $H10>=N$2), 2, "" ))) | O10: =IF(AND($F10<(O$2+7),$F10>O$2),1, IF(AND($H10<O$2+7,$H10>O$2),3, IF(AND($F10<=O$2, $H10>=O$2), 2, "" ))) | P10: =IF(AND($F10<(P$2+7),$F10>P$2),1, IF(AND($H10<P$2+7,$H10>P$2),3, IF(AND($F10<=P$2, $H10>=P$2), 2, "" ))) | Q10: =IF(AND($F10<(Q$2+7),$F10>Q$2),1, IF(AND($H10<Q$2+7,$H10>Q$2),3, IF(AND($F10<=Q$2, $H10>=Q$2), 2, "" ))) | R10: =IF(AND($F10<(R$2+7),$F10>R$2),1, IF(AND($H10<R$2+7,$H10>R$2),3, IF(AND($F10<=R$2, $H10>=R$2), 2, "" ))) | S10: =IF(AND($F10<(S$2+7),$F10>S$2),1, IF(AND($H10<S$2+7,$H10>S$2),3, IF(AND($F10<=S$2, $H10>=S$2), 2, "" ))) | ... AQ10: =IF(AND($F10<(AQ$2+7),$F10>AQ$2),1, IF(AND($H10<AQ$2+7,$H10>AQ$2),3, IF(AND($F10<=AQ$2, $H10>=AQ$2), 2, "" )))
B11: BOS Procurement | C11: 43941 | D11: 5 | E11: 43949 | F11: 43941 | G11: 5 | H11: 43949 | L11: =IF(AND($F11<(L$2+7),$F11>L$2),1, IF(AND($H11<L$2+7,$H11>L$2),3, IF(AND($F11<=L$2, $H11>=L$2), 2, "" ))) | M11: =IF(AND($F11<(M$2+7),$F11>M$2),1, IF(AND($H11<M$2+7,$H11>M$2),3, IF(AND($F11<=M$2, $H11>=M$2), 2, "" ))) | N11: =IF(AND($F11<(N$2+7),$F11>N$2),1, IF(AND($H11<N$2+7,$H11>N$2),3, IF(AND($F11<=N$2, $H11>=N$2), 2, "" ))) | O11: =IF(AND($F11<(O$2+7),$F11>O$2),1, IF(AND($H11<O$2+7,$H11>O$2),3, IF(AND($F11<=O$2, $H11>=O$2), 2, "" ))) | P11: =IF(AND($F11<(P$2+7),$F11>P$2),1, IF(AND($H11<P$2+7,$H11>P$2),3, IF(AND($F11<=P$2, $H11>=P$2), 2, "" ))) | Q11: =IF(AND($F11<(Q$2+7),$F11>Q$2),1, IF(AND($H11<Q$2+7,$H11>Q$2),3, IF(AND($F11<=Q$2, $H11>=Q$2), 2, "" ))) | R11: =IF(AND($F11<(R$2+7),$F11>R$2),1, IF(AND($H11<R$2+7,$H11>R$2),3, IF(AND($F11<=R$2, $H11>=R$2), 2, "" ))) | S11: =IF(AND($F11<(S$2+7),$F11>S$2),1, IF(AND($H11<S$2+7,$H11>S$2),3, IF(AND($F11<=S$2, $H11>=S$2), 2, "" ))) | ... AQ11: =IF(AND($F11<(AQ$2+7),$F11>AQ$2),1, IF(AND($H11<AQ$2+7,$H11>AQ$2),3, IF(AND($F11<=AQ$2, $H11>=AQ$2), 2, "" )))
A12: 5 | B12: Internal Project Kick off | C12: 43936 | D12: 5 | E12: 43943 | F12: 43936 | G12: 5 | H12: 43943
A13: 6 | B13: Client Project Kick-off | C13: 43963 | D13: 5 | E13: 43970 | F13: 43963 | G13: 5 | H13: 43970 | L13: =IF(AND($F13<(L$2+7),$F13>L$2),1, IF(AND($H13<L$2+7,$H13>L$2),3, IF(AND($F13<=L$2, $H13>=L$2), 2, "" ))) | M13: =IF(AND($F13<(M$2+7),$F13>M$2),1, IF(AND($H13<M$2+7,$H13>M$2),3, IF(AND($F13<=M$2, $H13>=M$2), 2, "" ))) | N13: =IF(AND($F13<(N$2+7),$F13>N$2),1, IF(AND($H13<N$2+7,$H13>N$2),3, IF(AND($F13<=N$2, $H13>=N$2), 2, "" ))) | O13: =IF(AND($F13<(O$2+7),$F13>O$2),1, IF(AND($H13<O$2+7,$H13>O$2),3, IF(AND($F13<=O$2, $H13>=O$2), 2, "" ))) | P13: =IF(AND($F13<(P$2+7),$F13>P$2),1, IF(AND($H13<P$2+7,$H13>P$2),3, IF(AND($F13<=P$2, $H13>=P$2), 2, "" ))) | Q13: =IF(AND($F13<(Q$2+7),$F13>Q$2),1, IF(AND($H13<Q$2+7,$H13>Q$2),3, IF(AND($F13<=Q$2, $H13>=Q$2), 2, "" ))) | R13: =IF(AND($F13<(R$2+7),$F13>R$2),1, IF(AND($H13<R$2+7,$H13>R$2),3, IF(AND($F13<=R$2, $H13>=R$2), 2, "" ))) | S13: =IF(AND($F13<(S$2+7),$F13>S$2),1, IF(AND($H13<S$2+7,$H13>S$2),3, IF(AND($F13<=S$2, $H13>=S$2), 2, "" ))) | ... AQ13: =IF(AND($F13<(AQ$2+7),$F13>AQ$2),1, IF(AND($H13<AQ$2+7,$H13>AQ$2),3, IF(AND($F13<=AQ$2, $H13>=AQ$2), 2, "" )))
A14: 7 | B14: Equipment Delivery | C14: 43983 | D14: 9 | E14: 43994 | F14: 43983 | G14: 9 | H14: 43994 | L14: =IF(AND($F14<(L$2+7),$F14>L$2),1, IF(AND($H14<L$2+7,$H14>L$2),3, IF(AND($F14<=L$2, $H14>=L$2), 2, "" ))) | M14: =IF(AND($F14<(M$2+7),$F14>M$2),1, IF(AND($H14<M$2+7,$H14>M$2),3, IF(AND($F14<=M$2, $H14>=M$2), 2, "" ))) | N14: =IF(AND($F14<(N$2+7),$F14>N$2),1, IF(AND($H14<N$2+7,$H14>N$2),3, IF(AND($F14<=N$2, $H14>=N$2), 2, "" ))) | O14: =IF(AND($F14<(O$2+7),$F14>O$2),1, IF(AND($H14<O$2+7,$H14>O$2),3, IF(AND($F14<=O$2, $H14>=O$2), 2, "" ))) | P14: =IF(AND($F14<(P$2+7),$F14>P$2),1, IF(AND($H14<P$2+7,$H14>P$2),3, IF(AND($F14<=P$2, $H14>=P$2), 2, "" ))) | Q14: =IF(AND($F14<(Q$2+7),$F14>Q$2),1, IF(AND($H14<Q$2+7,$H14>Q$2),3, IF(AND($F14<=Q$2, $H14>=Q$2), 2, "" ))) | R14: =IF(AND($F14<(R$2+7),$F14>R$2),1, IF(AND($H14<R$2+7,$H14>R$2),3, IF(AND($F14<=R$2, $H14>=R$2), 2, "" ))) | S14: =IF(AND($F14<(S$2+7),$F14>S$2),1, IF(AND($H14<S$2+7,$H14>S$2),3, IF(AND($F14<=S$2, $H14>=S$2), 2, "" ))) | ... AQ14: =IF(AND($F14<(AQ$2+7),$F14>AQ$2),1, IF(AND($H14<AQ$2+7,$H14>AQ$2),3, IF(AND($F14<=AQ$2, $H14>=AQ$2), 2, "" )))
B15: Mounting Structure Delivery | C15: 43983 | D15: 2 | E15: 43985 | F15: 43983 | G15: 2 | H15: 43985
B16: Panel Delivery | C16: 43990 | D16: 2 | E16: 43992 | F16: 43990 | G16: 2 | H16: 43992 | L16: =IF(AND($F16<(L$2+7),$F16>L$2),1, IF(AND($H16<L$2+7,$H16>L$2),3, IF(AND($F16<=L$2, $H16>=L$2), 2, "" ))) | M16: =IF(AND($F16<(M$2+7),$F16>M$2),1, IF(AND($H16<M$2+7,$H16>M$2),3, IF(AND($F16<=M$2, $H16>=M$2), 2, "" ))) | N16: =IF(AND($F16<(N$2+7),$F16>N$2),1, IF(AND($H16<N$2+7,$H16>N$2),3, IF(AND($F16<=N$2, $H16>=N$2), 2, "" ))) | O16: =IF(AND($F16<(O$2+7),$F16>O$2),1, IF(AND($H16<O$2+7,$H16>O$2),3, IF(AND($F16<=O$2, $H16>=O$2), 2, "" ))) | P16: =IF(AND($F16<(P$2+7),$F16>P$2),1, IF(AND($H16<P$2+7,$H16>P$2),3, IF(AND($F16<=P$2, $H16>=P$2), 2, "" ))) | Q16: =IF(AND($F16<(Q$2+7),$F16>Q$2),1, IF(AND($H16<Q$2+7,$H16>Q$2),3, IF(AND($F16<=Q$2, $H16>=Q$2), 2, "" ))) | R16: =IF(AND($F16<(R$2+7),$F16>R$2),1, IF(AND($H16<R$2+7,$H16>R$2),3, IF(AND($F16<=R$2, $H16>=R$2), 2, "" ))) | S16: =IF(AND($F16<(S$2+7),$F16>S$2),1, IF(AND($H16<S$2+7,$H16>S$2),3, IF(AND($F16<=S$2, $H16>=S$2), 2, "" ))) | ... AQ16: =IF(AND($F16<(AQ$2+7),$F16>AQ$2),1, IF(AND($H16<AQ$2+7,$H16>AQ$2),3, IF(AND($F16<=AQ$2, $H16>=AQ$2), 2, "" )))
B17: Generator Delivery | C17: 43983 | D17: 2 | E17: 43985 | F17: 43983 | G17: 2 | H17: 43985
A18: B | B18: PAYMENT MILESTONE 2: DELIVERY OF PV PANELS | C18: 43992 | D18: 2 | E18: 43994 | F18: 43992 | G18: 2 | H18: 43994
B19: Inverter Delivery | C19: 43983 | D19: 2 | E19: 43985 | F19: 43983 | G19: 2 | H19: 43985 | L19: =IF(AND($F19<(L$2+7),$F19>L$2),1, IF(AND($H19<L$2+7,$H19>L$2),3, IF(AND($F19<=L$2, $H19>=L$2), 2, "" ))) | M19: =IF(AND($F19<(M$2+7),$F19>M$2),1, IF(AND($H19<M$2+7,$H19>M$2),3, IF(AND($F19<=M$2, $H19>=M$2), 2, "" ))) | N19: =IF(AND($F19<(N$2+7),$F19>N$2),1, IF(AND($H19<N$2+7,$H19>N$2),3, IF(AND($F19<=N$2, $H19>=N$2), 2, "" ))) | O19: =IF(AND($F19<(O$2+7),$F19>O$2),1, IF(AND($H19<O$2+7,$H19>O$2),3, IF(AND($F19<=O$2, $H19>=O$2), 2, "" ))) | P19: =IF(AND($F19<(P$2+7),$F19>P$2),1, IF(AND($H19<P$2+7,$H19>P$2),3, IF(AND($F19<=P$2, $H19>=P$2), 2, "" ))) | Q19: =IF(AND($F19<(Q$2+7),$F19>Q$2),1, IF(AND($H19<Q$2+7,$H19>Q$2),3, IF(AND($F19<=Q$2, $H19>=Q$2), 2, "" ))) | R19: =IF(AND($F19<(R$2+7),$F19>R$2),1, IF(AND($H19<R$2+7,$H19>R$2),3, IF(AND($F19<=R$2, $H19>=R$2), 2, "" ))) | S19: =IF(AND($F19<(S$2+7),$F19>S$2),1, IF(AND($H19<S$2+7,$H19>S$2),3, IF(AND($F19<=S$2, $H19>=S$2), 2, "" ))) | ... AQ19: =IF(AND($F19<(AQ$2+7),$F19>AQ$2),1, IF(AND($H19<AQ$2+7,$H19>AQ$2),3, IF(AND($F19<=AQ$2, $H19>=AQ$2), 2, "" )))
B20: BOS Delivery | C20: 43983 | D20: 1 | E20: 43984 | F20: 43983 | G20: 1 | H20: 43984 | L20: =IF(AND($F20<(L$2+7),$F20>L$2),1, IF(AND($H20<L$2+7,$H20>L$2),3, IF(AND($F20<=L$2, $H20>=L$2), 2, "" ))) | M20: =IF(AND($F20<(M$2+7),$F20>M$2),1, IF(AND($H20<M$2+7,$H20>M$2),3, IF(AND($F20<=M$2, $H20>=M$2), 2, "" ))) | N20: =IF(AND($F20<(N$2+7),$F20>N$2),1, IF(AND($H20<N$2+7,$H20>N$2),3, IF(AND($F20<=N$2, $H20>=N$2), 2, "" ))) | O20: =IF(AND($F20<(O$2+7),$F20>O$2),1, IF(AND($H20<O$2+7,$H20>O$2),3, IF(AND($F20<=O$2, $H20>=O$2), 2, "" ))) | P20: =IF(AND($F20<(P$2+7),$F20>P$2),1, IF(AND($H20<P$2+7,$H20>P$2),3, IF(AND($F20<=P$2, $H20>=P$2), 2, "" ))) | Q20: =IF(AND($F20<(Q$2+7),$F20>Q$2),1, IF(AND($H20<Q$2+7,$H20>Q$2),3, IF(AND($F20<=Q$2, $H20>=Q$2), 2, "" ))) | R20: =IF(AND($F20<(R$2+7),$F20>R$2),1, IF(AND($H20<R$2+7,$H20>R$2),3, IF(AND($F20<=R$2, $H20>=R$2), 2, "" ))) | S20: =IF(AND($F20<(S$2+7),$F20>S$2),1, IF(AND($H20<S$2+7,$H20>S$2),3, IF(AND($F20<=S$2, $H20>=S$2), 2, "" ))) | ... AQ20: =IF(AND($F20<(AQ$2+7),$F20>AQ$2),1, IF(AND($H20<AQ$2+7,$H20>AQ$2),3, IF(AND($F20<=AQ$2, $H20>=AQ$2), 2, "" )))
A21: C | B21: PAYMENT MILESTONE 3: DELIVERY OF INVERTERS AND BOS | C21: 43985 | D21: 2 | E21: 43987 | F21: 43985 | G21: 2 | H21: 43987
A22: 8 | B22: Installation | C22: 43990 | D22: 22 | E22: 44012 | F22: 43990 | G22: 22 | H22: 44012 | L22: =IF(AND($F22<(L$2+7),$F22>L$2),1, IF(AND($H22<L$2+7,$H22>L$2),3, IF(AND($F22<=L$2, $H22>=L$2), 2, "" ))) | M22: =IF(AND($F22<(M$2+7),$F22>M$2),1, IF(AND($H22<M$2+7,$H22>M$2),3, IF(AND($F22<=M$2, $H22>=M$2), 2, "" ))) | N22: =IF(AND($F22<(N$2+7),$F22>N$2),1, IF(AND($H22<N$2+7,$H22>N$2),3, IF(AND($F22<=N$2, $H22>=N$2), 2, "" ))) | O22: =IF(AND($F22<(O$2+7),$F22>O$2),1, IF(AND($H22<O$2+7,$H22>O$2),3, IF(AND($F22<=O$2, $H22>=O$2), 2, "" ))) | P22: =IF(AND($F22<(P$2+7),$F22>P$2),1, IF(AND($H22<P$2+7,$H22>P$2),3, IF(AND($F22<=P$2, $H22>=P$2), 2, "" ))) | Q22: =IF(AND($F22<(Q$2+7),$F22>Q$2),1, IF(AND($H22<Q$2+7,$H22>Q$2),3, IF(AND($F22<=Q$2, $H22>=Q$2), 2, "" ))) | R22: =IF(AND($F22<(R$2+7),$F22>R$2),1, IF(AND($H22<R$2+7,$H22>R$2),3, IF(AND($F22<=R$2, $H22>=R$2), 2, "" ))) | S22: =IF(AND($F22<(S$2+7),$F22>S$2),1, IF(AND($H22<S$2+7,$H22>S$2),3, IF(AND($F22<=S$2, $H22>=S$2), 2, "" ))) | ... AQ22: =IF(AND($F22<(AQ$2+7),$F22>AQ$2),1, IF(AND($H22<AQ$2+7,$H22>AQ$2),3, IF(AND($F22<=AQ$2, $H22>=AQ$2), 2, "" ))) -> 2
B23: Site Establishment | C23: 43990 | D23: 1 | E23: 43991 | F23: 43990 | G23: 1 | H23: 43991 | J23: Installation placed on hold due to Covid-19 case | L23: =IF(AND($F23<(L$2+7),$F23>L$2),1, IF(AND($H23<L$2+7,$H23>L$2),3, IF(AND($F23<=L$2, $H23>=L$2), 2, "" ))) | M23: =IF(AND($F23<(M$2+7),$F23>M$2),1, IF(AND($H23<M$2+7,$H23>M$2),3, IF(AND($F23<=M$2, $H23>=M$2), 2, "" ))) | N23: =IF(AND($F23<(N$2+7),$F23>N$2),1, IF(AND($H23<N$2+7,$H23>N$2),3, IF(AND($F23<=N$2, $H23>=N$2), 2, "" ))) | O23: =IF(AND($F23<(O$2+7),$F23>O$2),1, IF(AND($H23<O$2+7,$H23>O$2),3, IF(AND($F23<=O$2, $H23>=O$2), 2, "" ))) | P23: =IF(AND($F23<(P$2+7),$F23>P$2),1, IF(AND($H23<P$2+7,$H23>P$2),3, IF(AND($F23<=P$2, $H23>=P$2), 2, "" ))) | Q23: =IF(AND($F23<(Q$2+7),$F23>Q$2),1, IF(AND($H23<Q$2+7,$H23>Q$2),3, IF(AND($F23<=Q$2, $H23>=Q$2), 2, "" ))) | R23: =IF(AND($F23<(R$2+7),$F23>R$2),1, IF(AND($H23<R$2+7,$H23>R$2),3, IF(AND($F23<=R$2, $H23>=R$2), 2, "" ))) | S23: =IF(AND($F23<(S$2+7),$F23>S$2),1, IF(AND($H23<S$2+7,$H23>S$2),3, IF(AND($F23<=S$2, $H23>=S$2), 2, "" ))) | ... AQ23: =IF(AND($F23<(AQ$2+7),$F23>AQ$2),1, IF(AND($H23<AQ$2+7,$H23>AQ$2),3, IF(AND($F23<=AQ$2, $H23>=AQ$2), 2, "" )))
A24: 9 | B24: DC Works | C24: 43991 | D24: 16 | E24: 44012 | F24: 43991 | G24: 16 | H24: 44012 | L24: =IF(AND($F24<(L$2+7),$F24>L$2),1, IF(AND($H24<L$2+7,$H24>L$2),3, IF(AND($F24<=L$2, $H24>=L$2), 2, "" ))) | M24: =IF(AND($F24<(M$2+7),$F24>M$2),1, IF(AND($H24<M$2+7,$H24>M$2),3, IF(AND($F24<=M$2, $H24>=M$2), 2, "" ))) | N24: =IF(AND($F24<(N$2+7),$F24>N$2),1, IF(AND($H24<N$2+7,$H24>N$2),3, IF(AND($F24<=N$2, $H24>=N$2), 2, "" ))) | O24: =IF(AND($F24<(O$2+7),$F24>O$2),1, IF(AND($H24<O$2+7,$H24>O$2),3, IF(AND($F24<=O$2, $H24>=O$2), 2, "" ))) | P24: =IF(AND($F24<(P$2+7),$F24>P$2),1, IF(AND($H24<P$2+7,$H24>P$2),3, IF(AND($F24<=P$2, $H24>=P$2), 2, "" ))) | Q24: =IF(AND($F24<(Q$2+7),$F24>Q$2),1, IF(AND($H24<Q$2+7,$H24>Q$2),3, IF(AND($F24<=Q$2, $H24>=Q$2), 2, "" ))) | R24: =IF(AND($F24<(R$2+7),$F24>R$2),1, IF(AND($H24<R$2+7,$H24>R$2),3, IF(AND($F24<=R$2, $H24>=R$2), 2, "" ))) | S24: =IF(AND($F24<(S$2+7),$F24>S$2),1, IF(AND($H24<S$2+7,$H24>S$2),3, IF(AND($F24<=S$2, $H24>=S$2), 2, "" ))) | ... AQ24: =IF(AND($F24<(AQ$2+7),$F24>AQ$2),1, IF(AND($H24<AQ$2+7,$H24>AQ$2),3, IF(AND($F24<=AQ$2, $H24>=AQ$2), 2, "" ))) -> 2
B25: Mounting structure Installation | C25: 43991 | D25: 4 | E25: 43997 | F25: 43991 | G25: 4 | H25: 43997 | L25: =IF(AND($F25<(L$2+7),$F25>L$2),1, IF(AND($H25<L$2+7,$H25>L$2),3, IF(AND($F25<=L$2, $H25>=L$2), 2, "" ))) | M25: =IF(AND($F25<(M$2+7),$F25>M$2),1, IF(AND($H25<M$2+7,$H25>M$2),3, IF(AND($F25<=M$2, $H25>=M$2), 2, "" ))) | N25: =IF(AND($F25<(N$2+7),$F25>N$2),1, IF(AND($H25<N$2+7,$H25>N$2),3, IF(AND($F25<=N$2, $H25>=N$2), 2, "" ))) | O25: =IF(AND($F25<(O$2+7),$F25>O$2),1, IF(AND($H25<O$2+7,$H25>O$2),3, IF(AND($F25<=O$2, $H25>=O$2), 2, "" ))) | P25: =IF(AND($F25<(P$2+7),$F25>P$2),1, IF(AND($H25<P$2+7,$H25>P$2),3, IF(AND($F25<=P$2, $H25>=P$2), 2, "" ))) | Q25: =IF(AND($F25<(Q$2+7),$F25>Q$2),1, IF(AND($H25<Q$2+7,$H25>Q$2),3, IF(AND($F25<=Q$2, $H25>=Q$2), 2, "" ))) | R25: =IF(AND($F25<(R$2+7),$F25>R$2),1, IF(AND($H25<R$2+7,$H25>R$2),3, IF(AND($F25<=R$2, $H25>=R$2), 2, "" ))) | S25: =IF(AND($F25<(S$2+7),$F25>S$2),1, IF(AND($H25<S$2+7,$H25>S$2),3, IF(AND($F25<=S$2, $H25>=S$2), 2, "" ))) | ... AQ25: =IF(AND($F25<(AQ$2+7),$F25>AQ$2),1, IF(AND($H25<AQ$2+7,$H25>AQ$2),3, IF(AND($F25<=AQ$2, $H25>=AQ$2), 2, "" )))
B26: Cable tray Installation | C26: 43997 | D26: 3 | E26: 44004 | F26: 43997 | G26: 3 | H26: 44004 | L26: =IF(AND($F26<(L$2+7),$F26>L$2),1, IF(AND($H26<L$2+7,$H26>L$2),3, IF(AND($F26<=L$2, $H26>=L$2), 2, "" ))) | M26: =IF(AND($F26<(M$2+7),$F26>M$2),1, IF(AND($H26<M$2+7,$H26>M$2),3, IF(AND($F26<=M$2, $H26>=M$2), 2, "" ))) | N26: =IF(AND($F26<(N$2+7),$F26>N$2),1, IF(AND($H26<N$2+7,$H26>N$2),3, IF(AND($F26<=N$2, $H26>=N$2), 2, "" ))) | O26: =IF(AND($F26<(O$2+7),$F26>O$2),1, IF(AND($H26<O$2+7,$H26>O$2),3, IF(AND($F26<=O$2, $H26>=O$2), 2, "" ))) | P26: =IF(AND($F26<(P$2+7),$F26>P$2),1, IF(AND($H26<P$2+7,$H26>P$2),3, IF(AND($F26<=P$2, $H26>=P$2), 2, "" ))) | Q26: =IF(AND($F26<(Q$2+7),$F26>Q$2),1, IF(AND($H26<Q$2+7,$H26>Q$2),3, IF(AND($F26<=Q$2, $H26>=Q$2), 2, "" ))) | R26: =IF(AND($F26<(R$2+7),$F26>R$2),1, IF(AND($H26<R$2+7,$H26>R$2),3, IF(AND($F26<=R$2, $H26>=R$2), 2, "" ))) | S26: =IF(AND($F26<(S$2+7),$F26>S$2),1, IF(AND($H26<S$2+7,$H26>S$2),3, IF(AND($F26<=S$2, $H26>=S$2), 2, "" ))) | ... AQ26: =IF(AND($F26<(AQ$2+7),$F26>AQ$2),1, IF(AND($H26<AQ$2+7,$H26>AQ$2),3, IF(AND($F26<=AQ$2, $H26>=AQ$2), 2, "" )))
B27: DC Cable Installation | C27: 44004 | D27: 2 | E27: 44006 | F27: 44004 | G27: 2 | H27: 44006 | L27: =IF(AND($F27<(L$2+7),$F27>L$2),1, IF(AND($H27<L$2+7,$H27>L$2),3, IF(AND($F27<=L$2, $H27>=L$2), 2, "" ))) | M27: =IF(AND($F27<(M$2+7),$F27>M$2),1, IF(AND($H27<M$2+7,$H27>M$2),3, IF(AND($F27<=M$2, $H27>=M$2), 2, "" ))) | N27: =IF(AND($F27<(N$2+7),$F27>N$2),1, IF(AND($H27<N$2+7,$H27>N$2),3, IF(AND($F27<=N$2, $H27>=N$2), 2, "" ))) | O27: =IF(AND($F27<(O$2+7),$F27>O$2),1, IF(AND($H27<O$2+7,$H27>O$2),3, IF(AND($F27<=O$2, $H27>=O$2), 2, "" ))) | P27: =IF(AND($F27<(P$2+7),$F27>P$2),1, IF(AND($H27<P$2+7,$H27>P$2),3, IF(AND($F27<=P$2, $H27>=P$2), 2, "" ))) | Q27: =IF(AND($F27<(Q$2+7),$F27>Q$2),1, IF(AND($H27<Q$2+7,$H27>Q$2),3, IF(AND($F27<=Q$2, $H27>=Q$2), 2, "" ))) | R27: =IF(AND($F27<(R$2+7),$F27>R$2),1, IF(AND($H27<R$2+7,$H27>R$2),3, IF(AND($F27<=R$2, $H27>=R$2), 2, "" ))) | S27: =IF(AND($F27<(S$2+7),$F27>S$2),1, IF(AND($H27<S$2+7,$H27>S$2),3, IF(AND($F27<=S$2, $H27>=S$2), 2, "" ))) | ... AQ27: =IF(AND($F27<(AQ$2+7),$F27>AQ$2),1, IF(AND($H27<AQ$2+7,$H27>AQ$2),3, IF(AND($F27<=AQ$2, $H27>=AQ$2), 2, "" )))
B28: Module Installation | C28: 44006 | D28: 4 | E28: 44012 | F28: 44006 | G28: 4 | H28: 44012 | L28: =IF(AND($F28<(L$2+7),$F28>L$2),1, IF(AND($H28<L$2+7,$H28>L$2),3, IF(AND($F28<=L$2, $H28>=L$2), 2, "" ))) | M28: =IF(AND($F28<(M$2+7),$F28>M$2),1, IF(AND($H28<M$2+7,$H28>M$2),3, IF(AND($F28<=M$2, $H28>=M$2), 2, "" ))) | N28: =IF(AND($F28<(N$2+7),$F28>N$2),1, IF(AND($H28<N$2+7,$H28>N$2),3, IF(AND($F28<=N$2, $H28>=N$2), 2, "" ))) | O28: =IF(AND($F28<(O$2+7),$F28>O$2),1, IF(AND($H28<O$2+7,$H28>O$2),3, IF(AND($F28<=O$2, $H28>=O$2), 2, "" ))) | P28: =IF(AND($F28<(P$2+7),$F28>P$2),1, IF(AND($H28<P$2+7,$H28>P$2),3, IF(AND($F28<=P$2, $H28>=P$2), 2, "" ))) | Q28: =IF(AND($F28<(Q$2+7),$F28>Q$2),1, IF(AND($H28<Q$2+7,$H28>Q$2),3, IF(AND($F28<=Q$2, $H28>=Q$2), 2, "" ))) | R28: =IF(AND($F28<(R$2+7),$F28>R$2),1, IF(AND($H28<R$2+7,$H28>R$2),3, IF(AND($F28<=R$2, $H28>=R$2), 2, "" ))) | S28: =IF(AND($F28<(S$2+7),$F28>S$2),1, IF(AND($H28<S$2+7,$H28>S$2),3, IF(AND($F28<=S$2, $H28>=S$2), 2, "" ))) | ... AQ28: =IF(AND($F28<(AQ$2+7),$F28>AQ$2),1, IF(AND($H28<AQ$2+7,$H28>AQ$2),3, IF(AND($F28<=AQ$2, $H28>=AQ$2), 2, "" ))) -> 2
B29: Earth Cable Installation | C29: 44004 | D29: 1 | E29: 44005 | F29: 44004 | G29: 1 | H29: 44005 | L29: =IF(AND($F29<(L$2+7),$F29>L$2),1, IF(AND($H29<L$2+7,$H29>L$2),3, IF(AND($F29<=L$2, $H29>=L$2), 2, "" ))) | M29: =IF(AND($F29<(M$2+7),$F29>M$2),1, IF(AND($H29<M$2+7,$H29>M$2),3, IF(AND($F29<=M$2, $H29>=M$2), 2, "" ))) | N29: =IF(AND($F29<(N$2+7),$F29>N$2),1, IF(AND($H29<N$2+7,$H29>N$2),3, IF(AND($F29<=N$2, $H29>=N$2), 2, "" ))) | O29: =IF(AND($F29<(O$2+7),$F29>O$2),1, IF(AND($H29<O$2+7,$H29>O$2),3, IF(AND($F29<=O$2, $H29>=O$2), 2, "" ))) | P29: =IF(AND($F29<(P$2+7),$F29>P$2),1, IF(AND($H29<P$2+7,$H29>P$2),3, IF(AND($F29<=P$2, $H29>=P$2), 2, "" ))) | Q29: =IF(AND($F29<(Q$2+7),$F29>Q$2),1, IF(AND($H29<Q$2+7,$H29>Q$2),3, IF(AND($F29<=Q$2, $H29>=Q$2), 2, "" ))) | R29: =IF(AND($F29<(R$2+7),$F29>R$2),1, IF(AND($H29<R$2+7,$H29>R$2),3, IF(AND($F29<=R$2, $H29>=R$2), 2, "" ))) | S29: =IF(AND($F29<(S$2+7),$F29>S$2),1, IF(AND($H29<S$2+7,$H29>S$2),3, IF(AND($F29<=S$2, $H29>=S$2), 2, "" ))) | ... AQ29: =IF(AND($F29<(AQ$2+7),$F29>AQ$2),1, IF(AND($H29<AQ$2+7,$H29>AQ$2),3, IF(AND($F29<=AQ$2, $H29>=AQ$2), 2, "" )))
A30: 10 | B30: AC Works | C30: 43991 | D30: 8 | E30: 44000 | F30: 43991 | G30: 8 | H30: 44000
B31: Inverters Installation | C31: 43991 | D31: 2 | E31: 43993 | F31: 43991 | G31: 2 | H31: 43993 | L31: =IF(AND($F31<(L$2+7),$F31>L$2),1, IF(AND($H31<L$2+7,$H31>L$2),3, IF(AND($F31<=L$2, $H31>=L$2), 2, "" ))) | M31: =IF(AND($F31<(M$2+7),$F31>M$2),1, IF(AND($H31<M$2+7,$H31>M$2),3, IF(AND($F31<=M$2, $H31>=M$2), 2, "" ))) | N31: =IF(AND($F31<(N$2+7),$F31>N$2),1, IF(AND($H31<N$2+7,$H31>N$2),3, IF(AND($F31<=N$2, $H31>=N$2), 2, "" ))) | O31: =IF(AND($F31<(O$2+7),$F31>O$2),1, IF(AND($H31<O$2+7,$H31>O$2),3, IF(AND($F31<=O$2, $H31>=O$2), 2, "" ))) | P31: =IF(AND($F31<(P$2+7),$F31>P$2),1, IF(AND($H31<P$2+7,$H31>P$2),3, IF(AND($F31<=P$2, $H31>=P$2), 2, "" ))) | Q31: =IF(AND($F31<(Q$2+7),$F31>Q$2),1, IF(AND($H31<Q$2+7,$H31>Q$2),3, IF(AND($F31<=Q$2, $H31>=Q$2), 2, "" ))) | R31: =IF(AND($F31<(R$2+7),$F31>R$2),1, IF(AND($H31<R$2+7,$H31>R$2),3, IF(AND($F31<=R$2, $H31>=R$2), 2, "" ))) | S31: =IF(AND($F31<(S$2+7),$F31>S$2),1, IF(AND($H31<S$2+7,$H31>S$2),3, IF(AND($F31<=S$2, $H31>=S$2), 2, "" ))) | ... AQ31: =IF(AND($F31<(AQ$2+7),$F31>AQ$2),1, IF(AND($H31<AQ$2+7,$H31>AQ$2),3, IF(AND($F31<=AQ$2, $H31>=AQ$2), 2, "" )))
B32: AC BOS Installation | C32: 43993 | D32: 3 | E32: 44000 | F32: 43993 | G32: 3 | H32: 44000 | L32: =IF(AND($F32<(L$2+7),$F32>L$2),1, IF(AND($H32<L$2+7,$H32>L$2),3, IF(AND($F32<=L$2, $H32>=L$2), 2, "" ))) | M32: =IF(AND($F32<(M$2+7),$F32>M$2),1, IF(AND($H32<M$2+7,$H32>M$2),3, IF(AND($F32<=M$2, $H32>=M$2), 2, "" ))) | N32: =IF(AND($F32<(N$2+7),$F32>N$2),1, IF(AND($H32<N$2+7,$H32>N$2),3, IF(AND($F32<=N$2, $H32>=N$2), 2, "" ))) | O32: =IF(AND($F32<(O$2+7),$F32>O$2),1, IF(AND($H32<O$2+7,$H32>O$2),3, IF(AND($F32<=O$2, $H32>=O$2), 2, "" ))) | P32: =IF(AND($F32<(P$2+7),$F32>P$2),1, IF(AND($H32<P$2+7,$H32>P$2),3, IF(AND($F32<=P$2, $H32>=P$2), 2, "" ))) | Q32: =IF(AND($F32<(Q$2+7),$F32>Q$2),1, IF(AND($H32<Q$2+7,$H32>Q$2),3, IF(AND($F32<=Q$2, $H32>=Q$2), 2, "" ))) | R32: =IF(AND($F32<(R$2+7),$F32>R$2),1, IF(AND($H32<R$2+7,$H32>R$2),3, IF(AND($F32<=R$2, $H32>=R$2), 2, "" ))) | S32: =IF(AND($F32<(S$2+7),$F32>S$2),1, IF(AND($H32<S$2+7,$H32>S$2),3, IF(AND($F32<=S$2, $H32>=S$2), 2, "" ))) | ... AQ32: =IF(AND($F32<(AQ$2+7),$F32>AQ$2),1, IF(AND($H32<AQ$2+7,$H32>AQ$2),3, IF(AND($F32<=AQ$2, $H32>=AQ$2), 2, "" )))
B33: AC Cable/Tie-In | C33: 43992 | D33: 3 | E33: 43997 | F33: 43992 | G33: 3 | H33: 43997 | L33: =IF(AND($F33<(L$2+7),$F33>L$2),1, IF(AND($H33<L$2+7,$H33>L$2),3, IF(AND($F33<=L$2, $H33>=L$2), 2, "" ))) | M33: =IF(AND($F33<(M$2+7),$F33>M$2),1, IF(AND($H33<M$2+7,$H33>M$2),3, IF(AND($F33<=M$2, $H33>=M$2), 2, "" ))) | N33: =IF(AND($F33<(N$2+7),$F33>N$2),1, IF(AND($H33<N$2+7,$H33>N$2),3, IF(AND($F33<=N$2, $H33>=N$2), 2, "" ))) | O33: =IF(AND($F33<(O$2+7),$F33>O$2),1, IF(AND($H33<O$2+7,$H33>O$2),3, IF(AND($F33<=O$2, $H33>=O$2), 2, "" ))) | P33: =IF(AND($F33<(P$2+7),$F33>P$2),1, IF(AND($H33<P$2+7,$H33>P$2),3, IF(AND($F33<=P$2, $H33>=P$2), 2, "" ))) | Q33: =IF(AND($F33<(Q$2+7),$F33>Q$2),1, IF(AND($H33<Q$2+7,$H33>Q$2),3, IF(AND($F33<=Q$2, $H33>=Q$2), 2, "" ))) | R33: =IF(AND($F33<(R$2+7),$F33>R$2),1, IF(AND($H33<R$2+7,$H33>R$2),3, IF(AND($F33<=R$2, $H33>=R$2), 2, "" ))) | S33: =IF(AND($F33<(S$2+7),$F33>S$2),1, IF(AND($H33<S$2+7,$H33>S$2),3, IF(AND($F33<=S$2, $H33>=S$2), 2, "" ))) | ... AQ33: =IF(AND($F33<(AQ$2+7),$F33>AQ$2),1, IF(AND($H33<AQ$2+7,$H33>AQ$2),3, IF(AND($F33<=AQ$2, $H33>=AQ$2), 2, "" )))
B34: Monitoring Platform Installation | C34: 43997 | D34: 1 | E34: 44000 | F34: 43997 | G34: 1 | H34: 44000
A35: 11 | B35: Completion | C35: 44000 | D35: 14 | E35: 44014 | F35: 44000 | G35: 14 | H35: 44014 | L35: =IF(AND($F35<(L$2+7),$F35>L$2),1, IF(AND($H35<L$2+7,$H35>L$2),3, IF(AND($F35<=L$2, $H35>=L$2), 2, "" ))) | M35: =IF(AND($F35<(M$2+7),$F35>M$2),1, IF(AND($H35<M$2+7,$H35>M$2),3, IF(AND($F35<=M$2, $H35>=M$2), 2, "" ))) | N35: =IF(AND($F35<(N$2+7),$F35>N$2),1, IF(AND($H35<N$2+7,$H35>N$2),3, IF(AND($F35<=N$2, $H35>=N$2), 2, "" ))) | O35: =IF(AND($F35<(O$2+7),$F35>O$2),1, IF(AND($H35<O$2+7,$H35>O$2),3, IF(AND($F35<=O$2, $H35>=O$2), 2, "" ))) | P35: =IF(AND($F35<(P$2+7),$F35>P$2),1, IF(AND($H35<P$2+7,$H35>P$2),3, IF(AND($F35<=P$2, $H35>=P$2), 2, "" ))) | Q35: =IF(AND($F35<(Q$2+7),$F35>Q$2),1, IF(AND($H35<Q$2+7,$H35>Q$2),3, IF(AND($F35<=Q$2, $H35>=Q$2), 2, "" ))) | R35: =IF(AND($F35<(R$2+7),$F35>R$2),1, IF(AND($H35<R$2+7,$H35>R$2),3, IF(AND($F35<=R$2, $H35>=R$2), 2, "" ))) | S35: =IF(AND($F35<(S$2+7),$F35>S$2),1, IF(AND($H35<S$2+7,$H35>S$2),3, IF(AND($F35<=S$2, $H35>=S$2), 2, "" ))) | ... AQ35: =IF(AND($F35<(AQ$2+7),$F35>AQ$2),1, IF(AND($H35<AQ$2+7,$H35>AQ$2),3, IF(AND($F35<=AQ$2, $H35>=AQ$2), 2, "" ))) -> 3
B36: DC Works | C36: 44012 | D36: 2 | E36: 44014 | F36: 44012 | G36: 2 | H36: 44014 | L36: =IF(AND($F36<(L$2+7),$F36>L$2),1, IF(AND($H36<L$2+7,$H36>L$2),3, IF(AND($F36<=L$2, $H36>=L$2), 2, "" ))) | M36: =IF(AND($F36<(M$2+7),$F36>M$2),1, IF(AND($H36<M$2+7,$H36>M$2),3, IF(AND($F36<=M$2, $H36>=M$2), 2, "" ))) | N36: =IF(AND($F36<(N$2+7),$F36>N$2),1, IF(AND($H36<N$2+7,$H36>N$2),3, IF(AND($F36<=N$2, $H36>=N$2), 2, "" ))) | O36: =IF(AND($F36<(O$2+7),$F36>O$2),1, IF(AND($H36<O$2+7,$H36>O$2),3, IF(AND($F36<=O$2, $H36>=O$2), 2, "" ))) | P36: =IF(AND($F36<(P$2+7),$F36>P$2),1, IF(AND($H36<P$2+7,$H36>P$2),3, IF(AND($F36<=P$2, $H36>=P$2), 2, "" ))) | Q36: =IF(AND($F36<(Q$2+7),$F36>Q$2),1, IF(AND($H36<Q$2+7,$H36>Q$2),3, IF(AND($F36<=Q$2, $H36>=Q$2), 2, "" ))) | R36: =IF(AND($F36<(R$2+7),$F36>R$2),1, IF(AND($H36<R$2+7,$H36>R$2),3, IF(AND($F36<=R$2, $H36>=R$2), 2, "" ))) | S36: =IF(AND($F36<(S$2+7),$F36>S$2),1, IF(AND($H36<S$2+7,$H36>S$2),3, IF(AND($F36<=S$2, $H36>=S$2), 2, "" ))) | ... AQ36: =IF(AND($F36<(AQ$2+7),$F36>AQ$2),1, IF(AND($H36<AQ$2+7,$H36>AQ$2),3, IF(AND($F36<=AQ$2, $H36>=AQ$2), 2, "" ))) -> 3
B37: AC Works | C37: 44000 | D37: 2 | E37: 44004 | F37: 44000 | G37: 2 | H37: 44004 | L37: =IF(AND($F37<(L$2+7),$F37>L$2),1, IF(AND($H37<L$2+7,$H37>L$2),3, IF(AND($F37<=L$2, $H37>=L$2), 2, "" ))) | M37: =IF(AND($F37<(M$2+7),$F37>M$2),1, IF(AND($H37<M$2+7,$H37>M$2),3, IF(AND($F37<=M$2, $H37>=M$2), 2, "" ))) | N37: =IF(AND($F37<(N$2+7),$F37>N$2),1, IF(AND($H37<N$2+7,$H37>N$2),3, IF(AND($F37<=N$2, $H37>=N$2), 2, "" ))) | O37: =IF(AND($F37<(O$2+7),$F37>O$2),1, IF(AND($H37<O$2+7,$H37>O$2),3, IF(AND($F37<=O$2, $H37>=O$2), 2, "" ))) | P37: =IF(AND($F37<(P$2+7),$F37>P$2),1, IF(AND($H37<P$2+7,$H37>P$2),3, IF(AND($F37<=P$2, $H37>=P$2), 2, "" ))) | Q37: =IF(AND($F37<(Q$2+7),$F37>Q$2),1, IF(AND($H37<Q$2+7,$H37>Q$2),3, IF(AND($F37<=Q$2, $H37>=Q$2), 2, "" ))) | R37: =IF(AND($F37<(R$2+7),$F37>R$2),1, IF(AND($H37<R$2+7,$H37>R$2),3, IF(AND($F37<=R$2, $H37>=R$2), 2, "" ))) | S37: =IF(AND($F37<(S$2+7),$F37>S$2),1, IF(AND($H37<S$2+7,$H37>S$2),3, IF(AND($F37<=S$2, $H37>=S$2), 2, "" ))) | ... AQ37: =IF(AND($F37<(AQ$2+7),$F37>AQ$2),1, IF(AND($H37<AQ$2+7,$H37>AQ$2),3, IF(AND($F37<=AQ$2, $H37>=AQ$2), 2, "" )))
A38: D | B38: PAYMENT MILESTONE 4: PRACTICAL COMPLETION | C38: 44012 | D38: 1 | E38: 44013 | F38: 44012 | G38: 1 | H38: 44013 | L38: =IF(AND($F38<(L$2+7),$F38>L$2),1, IF(AND($H38<L$2+7,$H38>L$2),3, IF(AND($F38<=L$2, $H38>=L$2), 2, "" ))) | M38: =IF(AND($F38<(M$2+7),$F38>M$2),1, IF(AND($H38<M$2+7,$H38>M$2),3, IF(AND($F38<=M$2, $H38>=M$2), 2, "" ))) | N38: =IF(AND($F38<(N$2+7),$F38>N$2),1, IF(AND($H38<N$2+7,$H38>N$2),3, IF(AND($F38<=N$2, $H38>=N$2), 2, "" ))) | O38: =IF(AND($F38<(O$2+7),$F38>O$2),1, IF(AND($H38<O$2+7,$H38>O$2),3, IF(AND($F38<=O$2, $H38>=O$2), 2, "" ))) | P38: =IF(AND($F38<(P$2+7),$F38>P$2),1, IF(AND($H38<P$2+7,$H38>P$2),3, IF(AND($F38<=P$2, $H38>=P$2), 2, "" ))) | Q38: =IF(AND($F38<(Q$2+7),$F38>Q$2),1, IF(AND($H38<Q$2+7,$H38>Q$2),3, IF(AND($F38<=Q$2, $H38>=Q$2), 2, "" ))) | R38: =IF(AND($F38<(R$2+7),$F38>R$2),1, IF(AND($H38<R$2+7,$H38>R$2),3, IF(AND($F38<=R$2, $H38>=R$2), 2, "" ))) | S38: =IF(AND($F38<(S$2+7),$F38>S$2),1, IF(AND($H38<S$2+7,$H38>S$2),3, IF(AND($F38<=S$2, $H38>=S$2), 2, "" ))) | ... AQ38: =IF(AND($F38<(AQ$2+7),$F38>AQ$2),1, IF(AND($H38<AQ$2+7,$H38>AQ$2),3, IF(AND($F38<=AQ$2, $H38>=AQ$2), 2, "" ))) -> 3
A39: 12 | B39: Commissioning | C39: 43997 | D39: 22 | E39: 44019 | F39: 43997 | G39: 22 | H39: 44019 | L39: =IF(AND($F39<(L$2+7),$F39>L$2),1, IF(AND($H39<L$2+7,$H39>L$2),3, IF(AND($F39<=L$2, $H39>=L$2), 2, "" ))) | M39: =IF(AND($F39<(M$2+7),$F39>M$2),1, IF(AND($H39<M$2+7,$H39>M$2),3, IF(AND($F39<=M$2, $H39>=M$2), 2, "" ))) | N39: =IF(AND($F39<(N$2+7),$F39>N$2),1, IF(AND($H39<N$2+7,$H39>N$2),3, IF(AND($F39<=N$2, $H39>=N$2), 2, "" ))) | O39: =IF(AND($F39<(O$2+7),$F39>O$2),1, IF(AND($H39<O$2+7,$H39>O$2),3, IF(AND($F39<=O$2, $H39>=O$2), 2, "" ))) | P39: =IF(AND($F39<(P$2+7),$F39>P$2),1, IF(AND($H39<P$2+7,$H39>P$2),3, IF(AND($F39<=P$2, $H39>=P$2), 2, "" ))) | Q39: =IF(AND($F39<(Q$2+7),$F39>Q$2),1, IF(AND($H39<Q$2+7,$H39>Q$2),3, IF(AND($F39<=Q$2, $H39>=Q$2), 2, "" ))) | R39: =IF(AND($F39<(R$2+7),$F39>R$2),1, IF(AND($H39<R$2+7,$H39>R$2),3, IF(AND($F39<=R$2, $H39>=R$2), 2, "" ))) | S39: =IF(AND($F39<(S$2+7),$F39>S$2),1, IF(AND($H39<S$2+7,$H39>S$2),3, IF(AND($F39<=S$2, $H39>=S$2), 2, "" ))) | ... AQ39: =IF(AND($F39<(AQ$2+7),$F39>AQ$2),1, IF(AND($H39<AQ$2+7,$H39>AQ$2),3, IF(AND($F39<=AQ$2, $H39>=AQ$2), 2, "" ))) -> 2
B40: Snag List | C40: 44014 | D40: 3 | E40: 44019 | F40: 44014 | G40: 3 | H40: 44019
B41: Pre-Commissioning Checks | C41: 44010 | D41: 2 | E41: 44012 | F41: 44010 | G41: 2 | H41: 44012
B42: Issue CoC | C42: 43997 | D42: 2 | E42: 44001 | F42: 43997 | G42: 2 | H42: 44001 | L42: =IF(AND($F42<(L$2+7),$F42>L$2),1, IF(AND($H42<L$2+7,$H42>L$2),3, IF(AND($F42<=L$2, $H42>=L$2), 2, "" ))) | M42: =IF(AND($F42<(M$2+7),$F42>M$2),1, IF(AND($H42<M$2+7,$H42>M$2),3, IF(AND($F42<=M$2, $H42>=M$2), 2, "" ))) | N42: =IF(AND($F42<(N$2+7),$F42>N$2),1, IF(AND($H42<N$2+7,$H42>N$2),3, IF(AND($F42<=N$2, $H42>=N$2), 2, "" ))) | O42: =IF(AND($F42<(O$2+7),$F42>O$2),1, IF(AND($H42<O$2+7,$H42>O$2),3, IF(AND($F42<=O$2, $H42>=O$2), 2, "" ))) | P42: =IF(AND($F42<(P$2+7),$F42>P$2),1, IF(AND($H42<P$2+7,$H42>P$2),3, IF(AND($F42<=P$2, $H42>=P$2), 2, "" ))) | Q42: =IF(AND($F42<(Q$2+7),$F42>Q$2),1, IF(AND($H42<Q$2+7,$H42>Q$2),3, IF(AND($F42<=Q$2, $H42>=Q$2), 2, "" ))) | R42: =IF(AND($F42<(R$2+7),$F42>R$2),1, IF(AND($H42<R$2+7,$H42>R$2),3, IF(AND($F42<=R$2, $H42>=R$2), 2, "" ))) | S42: =IF(AND($F42<(S$2+7),$F42>S$2),1, IF(AND($H42<S$2+7,$H42>S$2),3, IF(AND($F42<=S$2, $H42>=S$2), 2, "" ))) | ... AQ42: =IF(AND($F42<(AQ$2+7),$F42>AQ$2),1, IF(AND($H42<AQ$2+7,$H42>AQ$2),3, IF(AND($F42<=AQ$2, $H42>=AQ$2), 2, "" )))
B43: Cold Commissioning | C43: 44012 | D43: 1 | E43: 44013 | F43: 44012 | G43: 1 | H43: 44013 | L43: =IF(AND($F43<(L$2+7),$F43>L$2),1, IF(AND($H43<L$2+7,$H43>L$2),3, IF(AND($F43<=L$2, $H43>=L$2), 2, "" ))) | M43: =IF(AND($F43<(M$2+7),$F43>M$2),1, IF(AND($H43<M$2+7,$H43>M$2),3, IF(AND($F43<=M$2, $H43>=M$2), 2, "" ))) | N43: =IF(AND($F43<(N$2+7),$F43>N$2),1, IF(AND($H43<N$2+7,$H43>N$2),3, IF(AND($F43<=N$2, $H43>=N$2), 2, "" ))) | O43: =IF(AND($F43<(O$2+7),$F43>O$2),1, IF(AND($H43<O$2+7,$H43>O$2),3, IF(AND($F43<=O$2, $H43>=O$2), 2, "" ))) | P43: =IF(AND($F43<(P$2+7),$F43>P$2),1, IF(AND($H43<P$2+7,$H43>P$2),3, IF(AND($F43<=P$2, $H43>=P$2), 2, "" ))) | Q43: =IF(AND($F43<(Q$2+7),$F43>Q$2),1, IF(AND($H43<Q$2+7,$H43>Q$2),3, IF(AND($F43<=Q$2, $H43>=Q$2), 2, "" ))) | R43: =IF(AND($F43<(R$2+7),$F43>R$2),1, IF(AND($H43<R$2+7,$H43>R$2),3, IF(AND($F43<=R$2, $H43>=R$2), 2, "" ))) | S43: =IF(AND($F43<(S$2+7),$F43>S$2),1, IF(AND($H43<S$2+7,$H43>S$2),3, IF(AND($F43<=S$2, $H43>=S$2), 2, "" ))) | ... AQ43: =IF(AND($F43<(AQ$2+7),$F43>AQ$2),1, IF(AND($H43<AQ$2+7,$H43>AQ$2),3, IF(AND($F43<=AQ$2, $H43>=AQ$2), 2, "" ))) -> 3
B44: Hot Commissioning | C44: 44013 | D44: 2 | E44: 44015 | F44: 44013 | G44: 2 | H44: 44015 | L44: =IF(AND($F44<(L$2+7),$F44>L$2),1, IF(AND($H44<L$2+7,$H44>L$2),3, IF(AND($F44<=L$2, $H44>=L$2), 2, "" ))) | M44: =IF(AND($F44<(M$2+7),$F44>M$2),1, IF(AND($H44<M$2+7,$H44>M$2),3, IF(AND($F44<=M$2, $H44>=M$2), 2, "" ))) | N44: =IF(AND($F44<(N$2+7),$F44>N$2),1, IF(AND($H44<N$2+7,$H44>N$2),3, IF(AND($F44<=N$2, $H44>=N$2), 2, "" ))) | O44: =IF(AND($F44<(O$2+7),$F44>O$2),1, IF(AND($H44<O$2+7,$H44>O$2),3, IF(AND($F44<=O$2, $H44>=O$2), 2, "" ))) | P44: =IF(AND($F44<(P$2+7),$F44>P$2),1, IF(AND($H44<P$2+7,$H44>P$2),3, IF(AND($F44<=P$2, $H44>=P$2), 2, "" ))) | Q44: =IF(AND($F44<(Q$2+7),$F44>Q$2),1, IF(AND($H44<Q$2+7,$H44>Q$2),3, IF(AND($F44<=Q$2, $H44>=Q$2), 2, "" ))) | R44: =IF(AND($F44<(R$2+7),$F44>R$2),1, IF(AND($H44<R$2+7,$H44>R$2),3, IF(AND($F44<=R$2, $H44>=R$2), 2, "" ))) | S44: =IF(AND($F44<(S$2+7),$F44>S$2),1, IF(AND($H44<S$2+7,$H44>S$2),3, IF(AND($F44<=S$2, $H44>=S$2), 2, "" ))) | ... AQ44: =IF(AND($F44<(AQ$2+7),$F44>AQ$2),1, IF(AND($H44<AQ$2+7,$H44>AQ$2),3, IF(AND($F44<=AQ$2, $H44>=AQ$2), 2, "" ))) -> 1
A45: 13 | B45: Handover | C45: 44020 | D45: 1 | E45: 44021 | F45: 44020 | G45: 1 | H45: 44021 | L45: =IF(AND($F45<(L$2+7),$F45>L$2),1, IF(AND($H45<L$2+7,$H45>L$2),3, IF(AND($F45<=L$2, $H45>=L$2), 2, "" ))) | M45: =IF(AND($F45<(M$2+7),$F45>M$2),1, IF(AND($H45<M$2+7,$H45>M$2),3, IF(AND($F45<=M$2, $H45>=M$2), 2, "" ))) | N45: =IF(AND($F45<(N$2+7),$F45>N$2),1, IF(AND($H45<N$2+7,$H45>N$2),3, IF(AND($F45<=N$2, $H45>=N$2), 2, "" ))) | O45: =IF(AND($F45<(O$2+7),$F45>O$2),1, IF(AND($H45<O$2+7,$H45>O$2),3, IF(AND($F45<=O$2, $H45>=O$2), 2, "" ))) | P45: =IF(AND($F45<(P$2+7),$F45>P$2),1, IF(AND($H45<P$2+7,$H45>P$2),3, IF(AND($F45<=P$2, $H45>=P$2), 2, "" ))) | Q45: =IF(AND($F45<(Q$2+7),$F45>Q$2),1, IF(AND($H45<Q$2+7,$H45>Q$2),3, IF(AND($F45<=Q$2, $H45>=Q$2), 2, "" ))) | R45: =IF(AND($F45<(R$2+7),$F45>R$2),1, IF(AND($H45<R$2+7,$H45>R$2),3, IF(AND($F45<=R$2, $H45>=R$2), 2, "" ))) | S45: =IF(AND($F45<(S$2+7),$F45>S$2),1, IF(AND($H45<S$2+7,$H45>S$2),3, IF(AND($F45<=S$2, $H45>=S$2), 2, "" ))) | ... AQ45: =IF(AND($F45<(AQ$2+7),$F45>AQ$2),1, IF(AND($H45<AQ$2+7,$H45>AQ$2),3, IF(AND($F45<=AQ$2, $H45>=AQ$2), 2, "" )))
A46: E | B46: PAYMENT MILESTONE 6: HANDOVER COMPLETE | C46: 44022 | D46: 1 | E46: 44025 | F46: 44022 | G46: 1 | H46: 44025
C47: 43831 | D47: These numbers are used to set the start and end dates on the Gantt Chart
C48: 44014

Sheet Compliance
B2: HSE
B4: Description | C4: Status | D4: Approved By | E4: Date | F4: Results / Comments
B5: NOC
B6: 7.1 Agreement
B7: 13.2 Agreement
B8: EE File
B9: Subbie File
B16: SSEG
B18: Description | C18: Status | D18: Approved By | E18: Date | F18: Results / Comments
B19: SSEG Application
B20: PTI
B21: Commissioning Approval

Sheet Revenue Tracking
B2: HIGH LEVEL PROJECT REVENUE TRACKING
D3: COSTED | F3: ACTUAL | L3: FINANCIAL REVIEW | N3: TIMELINE REVIEW
B4: 1 | C4: Planned Revenue | D4: ='Project Plan'!E6 -> 3786732 | F4: =F21 -> 3786732 | N4: Start Date
B5: 2 | C5: Planned Expenditure | D5: =+'Expenditure Tracking'!F5 -> 3478221.3 | F5: =+'Expenditure Tracking'!H5 -> 2789768.9 | G5: VO PM Limit | H5: Current VO Total
B6: 3 | C6: Planned Profit | D6: =+D4-D5 -> 308510.74 | F6: =+F4-F5 -> 996963.11 | G6: =D6*0.05 -> 15425.537 | H6: =SUMIF('Expenditure Breakdown'!N:N,"*VO*",'Expenditure Breakdown'!Q:Q) -> 81762.5 | N6: End Date - PC
B7: 4 | C7: Planned Margin | D7: =+D6/D4 -> 0.081471502 | F7: =+F6/F4 -> 0.26327797
B10: CONTRACT
B12: No. | C12: PAYMENT MILESTONE | E12: % | F12: VALUE | H12: PLANNED PAYMENT DATE | L12: INVOICE NUMBER | N12: INVOICE RAISED DATE | P12: PAYMENT RECEIVED DATE | R12: MILESTONE NOTES & COMMENTS
B13: 1 | C13: Deposit | E13: 0.2 | F13: =$D$4*E13 -> 757346.4 | H13: 45777 | L13: 004733 | N13: 45778 | P13: 45776
B14: 2 | C14: Delivery of Panels | E14: 0.2 | F14: =$D$4*E14 -> 757346.4 | H14: ='Project Plan'!E36+7 -> 45826 | L14: 004733 | N14: 45778 | P14: 45828
B15: 3 | C15: Delivery of Inverters | E15: 0.15 | F15: =$D$4*E15 -> 568009.8 | H15: ='Project Plan'!E22+7 -> 45818 | L15: 004733 | N15: 45778 | P15: 45814
B16: 4 | C16: Commissioning Complete | E16: 0.15 | F16: =$D$4*E16 -> 568009.8 | H16: ='Project Plan'!G39+7 -> 45869 | L16: 004733 | N16: 45778 | P16: 45896
B17: 5 | C17: Final Completion Issued | E17: 0.25 | F17: =$D$4*E17 -> 946683 | H17: ='Project Plan'!E50+7 -> 45869 | L17: 004733 | N17: 45778 | P17: 45896
B18: 6 | C18: Handover | E18: 0.05 | F18: =$D$4*E18 -> 189336.6 | H18: ='Project Plan'!K51+7 -> 45929 | L18: 004733 | N18: 45778 | P18: 45918
B19: 7 | C19: - | E19: 0 | F19: =$D$4*E19 -> 0
E21: =SUM(E13:E19) -> 1 | F21: =SUM(F13:F19) -> 3786732
B23: KEY: | C23: contains an error (in result or a check has failed)
C24: Red Font - IF TEXT : content not yet confirmed
C25: Red Font - IF NUMBER: Negative value
C26: Anything in yellow is a concern or risk for noting or action
C27: confirmed
C28: [ADD INITIALS: comment for noting in square brackets, use colour or red to draw attention if important]
C29: [RT: When adding rows into sheet, ensure you insert between first and last row of each category]
C30: end of sheet - do not insert information below/beyond this
B40: No. | C40: PAYMENT MILESTONE | E40: % | F40: VALUE
B41: 1 | C41: Deposit - Project commencement | E41: 0.35 | F41: =$F$47*E41 -> 1325356.2
B42: 2 | C42: Delivery of Panels | E42: 0.3 | F42: =$F$47*E42 -> 1136019.6
B43: 3 | C43: Delivery of Inverters | E43: 0.2 | F43: =$F$47*E43 -> 757346.4
B44: 4 | C44: Practical Completion | E44: 0.1 | F44: =$F$47*E44 -> 378673.2
B45: 5 | C45: Handover | E45: 0.05 | F45: =$F$47*E45 -> 189336.6
C46: Total | E46: =SUM(E41:E45) -> 1 | F46: =SUM(F41:F45) -> 3786732
E47: =SUM(E41:E45) -> 1 | F47: =F21 -> 3786732

Sheet Project Plan
N1: =TODAY() -> 46077 | O1: =TODAY() -> 46077
C2: PROJECT PLAN | E2: Kroonstad | N2: 0 | O2: 1
C3: PROJECT SIZE (kWp) | E3: 391
C4: PROJECT DEVELOPER | E4: Natasha Watkins-Baker
C5: PROJECT MANAGERS | E5: JT Moorosi
C6: CONTRACT VALUE | E6: 3786732
C7: Phase: | E7: Compliance Handover
B8: No. | C8: HIGH LEVEL PROGRAMME | E8: Planned Start | F8: Duration (days) | G8: Planned End | I8: Actual Start | J8: Duration (days) | K8: Actual End | M8: Status | N8: Expected Status | O8: Comment
F9: =G41-E19 -> 52 | J9: =K41-I19 -> 91 | M9: =AVERAGE(M11,M18,M21,M28,M35,M39,M46,M43) -> 1 | N9: =AVERAGE(N11,N18,N21,N28,N35,N39,N46,N43) -> 1
B11: 1 | C11: Project Initiation | E11: =MIN(E12:E16) -> 45769 | F11: =G11-E11 -> 35 | G11: =MAX(G12:G16) -> 45804 | I11: =MIN(I12:I16) -> 45776 | J11: =K11-I11 -> 17 | K11: =MAX(K12:K16) -> 45793 | M11: =(J12*M12+J13*M13+J14*M14+J15*M15+J16*M16)/SUM(J12:J16) -> 1 | N11: =(K12*N12+K13*N13+K14*N14+K15*N15+K16*N16)/SUM(K12:K16) -> 1
B12: 1.1 | C12: BD Handover | E12: 45769 | F12: 1 | G12: =WORKDAY.INTL(E12,F12,1,Data!$C$3:$C$14) -> 45770 | I12: 45790 | J12: 1 | K12: 45791 | M12: 1 | N12: 1
B13: 1.2 | C13: Project Introduction | E13: =WORKDAY.INTL(E19,0,1,Data!$C$3:$C$14)-7 -> 45803 | F13: 1 | G13: =WORKDAY.INTL(E13,F13,1,Data!$C$3:$C$14) -> 45804 | I13: 45792 | J13: 1 | K13: 45793 | M13: 1 | N13: 1
B14: 1.3 | C14: HSE | E14: =E12 -> 45769 | F14: 10 | G14: =WORKDAY.INTL(E14,F14,1,Data!$C$3:$C$14) -> 45784 | I14: 45776 | J14: 10 | K14: 45791 | M14: 1 | N14: 1
B15: 1.4 | C15: Installer Kick Off | E15: =WORKDAY.INTL(E19,0,1,Data!$C$3:$C$14)-14 -> 45796 | F15: 1 | G15: =WORKDAY.INTL(E15,F15,1,Data!$C$3:$C$14) -> 45797 | I15: 45791 | J15: 1 | K15: 45792 | M15: 1 | N15: 1
B16: 1.5 | C16: Project Review | E16: =WORKDAY.INTL(E19,0,1,Data!$C$3:$C$14)-14 -> 45796 | F16: 1 | G16: =WORKDAY.INTL(E16,F16,1,Data!$C$3:$C$14) -> 45797 | I16: 45785 | J16: 1 | K16: 45786 | M16: 1 | N16: 1
B18: 2 | C18: Site Establishment | E18: =MIN(E19:E20) -> 45810 | F18: =G18-E18 -> 1 | G18: =MAX(G19) -> 45811 | I18: =MIN(I19:I20) -> 45810 | J18: =K18-I18 -> 1 | K18: =MAX(K19) -> 45811 | M18: =(J19*M19)/J18 -> 1 | N18: =(K19*N19)/K18 -> 1
B19: 2.1 | C19: Solar Contractor Establishment | E19: 45810 | F19: 1 | G19: =E19+F19 -> 45811 | I19: 45810 | J19: 1 | K19: =I19+J19 -> 45811 | M19: 1 | N19: 1 | S19: =NETWORKDAYS(I19,K41,Data!C3:C15) -> 65 | T19: Net Work Days
B21: 3 | C21: AC Installation | E21: =MIN(E22:E26) -> 45782 | F21: =G21-E21 -> 50 | G21: =MAX(G22:G26) -> 45832 | I21: =MIN(I22:I26) -> 45782 | J21: =K21-I21 -> 91 | K21: =MAX(K22:K26) -> 45873 | M21: =(J22*M22+J23*M23+J24*M24+J25*M25+J26*M26)/SUM(J22:J26) -> 1 | N21: =(K22*N22+K23*N23+K24*N24+K25*N25+K26*N26)/SUM(K22:K26) -> 1 | S21: =S19/5 -> 13 | T21: Total Weeks
B22: 3.1 | C22: Inverters delivered | E22: =WORKDAY.INTL(G19,0,1,Data!$C$3:$C$14) -> 45811 | F22: 1 | G22: =WORKDAY.INTL(E22,F22,1,Data!$C$3:$C$14) -> 45812 | I22: 45806 | J22: 1 | K22: =WORKDAY.INTL(I22,J22,1,Data!$C$3:$C$14) -> 45807 | M22: 1 | N22: 1 | S22: =E3/S21 -> 30.076923 | T22: kW/Week Installation Rate
B23: 3.2 | C23: Inverters Mounted | E23: =WORKDAY.INTL(G22,0,1,Data!$C$3:$C$14) -> 45812 | F23: 5 | G23: =WORKDAY.INTL(E23,F23,1,Data!$C$3:$C$14) -> 45819 | I23: 45860 | J23: 5 | K23: =WORKDAY.INTL(I23,J23,1,Data!$C$3:$C$14) -> 45867 | M23: 1 | N23: 1
B24: 3.3 | C24: Solar DB Lead Time | E24: =WORKDAY.INTL(E19,0,1,Data!$C$3:$C$14)-28 -> 45782 | F24: 25 | G24: =WORKDAY.INTL(E24,F24,1,Data!$C$3:$C$14) -> 45817 | I24: =WORKDAY.INTL(I19,0,1,Data!$C$3:$C$14)-28 -> 45782 | J24: 37 | K24: =WORKDAY.INTL(I24,J24,1,Data!$C$3:$C$14) -> 45834 | M24: 1 | N24: 1
B25: 3.4 | C25: AC Works | E25: =WORKDAY.INTL(G24,0,1,Data!$C$3:$C$14) -> 45817 | F25: 10 | G25: =WORKDAY.INTL(E25,F25,1,Data!$C$3:$C$14) -> 45832 | I25: =I23 -> 45860 | J25: 6 | K25: =WORKDAY.INTL(I25,J25,1,Data!$C$3:$C$14) -> 45868 | M25: 1 | N25: 1
B26: 3.5 | C26: AC Tie-In | E26: =WORKDAY.INTL(E25,0,1,Data!$C$3:$C$14) -> 45817 | F26: 3 | G26: =WORKDAY.INTL(E26,F26,1,Data!$C$3:$C$14) -> 45820 | I26: =WORKDAY.INTL(K25,0,1,Data!$C$3:$C$14) -> 45868 | J26: 3 | K26: =WORKDAY.INTL(I26,J26,1,Data!$C$3:$C$14) -> 45873 | M26: 1 | N26: 1
B28: 4 | C28: DC Works | E28: =MIN(E30:E33) -> 45810 | F28: =G28-E28 -> 39 | G28: =MAX(G30:G33) -> 45849 | I28: =MIN(I30:I33) -> 45799 | J28: =K28-I28 -> 62 | K28: =MAX(K30:K33) -> 45861 | M28: 1 | N28: 1
B29: 4.1 | C29: Lifeline Installation (If Applicable) | M29: 0 | N29: 0
B30: 4.1 | C30: Mounting Structure delivered | E30: =E19 -> 45810 | F30: 1 | G30: =WORKDAY.INTL(E30,F30,1,Data!$C$3:$C$14) -> 45811 | I30: 45799 | J30: 1 | K30: =WORKDAY.INTL(I30,J30,1,Data!$C$3:$C$14) -> 45800 | M30: 1 | N30: 1
B31: 4.2 | C31: Mounting Structure installation | E31: =WORKDAY.INTL(G30,0,1,Data!$C$3:$C$14) -> 45811 | F31: 10 | G31: =WORKDAY.INTL(E31,F31,1,Data!$C$3:$C$14) -> 45826 | I31: =WORKDAY.INTL(K30,0,1,Data!$C$3:$C$14)+3 -> 45803 | J31: 10 | K31: =WORKDAY.INTL(I31,J31,1,Data!$C$3:$C$14) -> 45817 | M31: 1 | N31: 1
B32: 4.3 | C32: DC Cable delivered | E32: =E30 -> 45810 | F32: 1 | G32: =WORKDAY.INTL(E32,F32,1,Data!$C$3:$C$14) -> 45811 | I32: 45860 | J32: 1 | K32: =WORKDAY.INTL(I32,J32,1,Data!$C$3:$C$14) -> 45861 | M32: 1 | N32: 1
B33: 4.3 | C33: DC Stringing | E33: =WORKDAY.INTL(G37,0,1,Data!$C$3:$C$14)-3 -> 45836 | F33: 10 | G33: =WORKDAY.INTL(E33,F33,1,Data!$C$3:$C$14) -> 45849 | I33: =WORKDAY.INTL(K37,0,1,Data!$C$3:$C$14) -> 45831 | J33: 15 | K33: =WORKDAY.INTL(I33,J33,1,Data!$C$3:$C$14) -> 45852 | M33: 1 | N33: 1
B35: 5 | C35: Module installation | E35: =MIN(E36:E37) -> 45819 | F35: =G35-E35 -> 20 | G35: =MAX(G36:G37) -> 45839 | I35: =MIN(I36:I37) -> 45811 | J35: =K35-I35 -> 20 | K35: =MAX(K36:K37) -> 45831 | M35: =(J36*M36+J37*M37)/SUM(J36:J37) -> 1 | N35: =(K36*N36+K37*N37)/SUM(K36:K37) -> 1
B36: 5.1 | C36: Module delivery | E36: =WORKDAY.INTL(G31,0,1,Data!$C$3:$C$14)-7 -> 45819 | F36: 1 | G36: =WORKDAY.INTL(E36,F36,1,Data!$C$3:$C$14) -> 45820 | I36: 45811 | J36: 1 | K36: =WORKDAY.INTL(I36,J36,1,Data!$C$3:$C$14) -> 45812 | M36: 1 | N36: 1
B37: 5.2 | C37: Module mounting | E37: =G36 -> 45820 | F37: 12 | G37: =WORKDAY.INTL(E37,F37,1,Data!$C$3:$C$14) -> 45839 | I37: =K36 -> 45812 | J37: 12 | K37: =WORKDAY.INTL(I37,J37,1,Data!$C$3:$C$14) -> 45831 | M37: 1 | N37: 1
B39: 6 | C39: Commissioning | E39: =MIN(E40:E41) -> 45849 | F39: =G39-E39 -> 13 | G39: =MAX(G40:G41) -> 45862 | I39: =MIN(I40:I41) -> 45873 | J39: =K39-I39 -> 28 | K39: =MAX(K40:K41) -> 45901 | M39: =(J40*M40+J41*M41)/SUM(J40:J41) -> 1 | N39: =(K40*N40+K41*N41)/SUM(K40:K41) -> 1 | O39: 12-Aug: IV curves captured; Techsitter rewired; comms restored; AC/DC snags fixed. Site not yet stable for PC – further investigation underway. Risk to 15-Aug PC if root cause not resolved by 13-Aug.
B40: 6.1 | C40: Commissioning | E40: =WORKDAY.INTL(MAX(G21,G28,G35),0,1,Data!$C$3:$C$14) -> 45849 | F40: 4 | G40: =WORKDAY.INTL(E40,F40,1,Data!$C$3:$C$14) -> 45855 | I40: =WORKDAY.INTL(MAX(K21,K28,K35),0,1,Data!$C$3:$C$14) -> 45873 | J40: 7 | K40: =WORKDAY.INTL(I40,J40,1,Data!$C$3:$C$14) -> 45882 | M40: 1 | N40: 1 | O40: Functional tests ongoing; logs being pulled and OEM consult planned.
B41: 6.2 | C41: Practical Completion | E41: =WORKDAY.INTL(G40,0,1,Data!$C$3:$C$14) -> 45855 | F41: 5 | G41: =WORKDAY.INTL(E41,F41,1,Data!$C$3:$C$14) -> 45862 | I41: =WORKDAY.INTL(K40,0,1,Data!$C$3:$C$14) -> 45882 | J41: 13 | K41: =WORKDAY.INTL(I41,J41,1,Data!$C$3:$C$14) -> 45901 | M41: 1 | N41: 1
B43: 7 | C43: QA Inspections | E43: =MIN(E44) -> 45862 | F43: =G43-E43 -> 1 | G43: =MAX(G44) -> 45863 | I43: =MIN(I44) -> 45901 | J43: =K43-I43 -> 1 | K43: =MAX(K44) -> 45902 | M43: =(J44*M44)/SUM(J44) -> 1 | N43: =(K44*N44)/SUM(K44) -> 1
B44: 7.1 | C44: Red-Team Inspection | E44: =WORKDAY.INTL(G41,0,1,Data!$C$3:$C$14) -> 45862 | F44: 1 | G44: =WORKDAY.INTL(E44,F44,1,Data!$C$3:$C$14) -> 45863 | I44: =WORKDAY.INTL(K41,0,1,Data!$C$3:$C$14) -> 45901 | J44: 1 | K44: =WORKDAY.INTL(I44,J44,1,Data!$C$3:$C$14) -> 45902 | M44: 1 | N44: 1
B46: 8 | C46: Project Closure | E46: =MIN(E47:E52) -> 45862 | F46: =G46-E46 -> 14 | G46: =MAX(G47:G52) -> 45876 | I46: =MIN(I47:I52) -> 45902 | J46: =K46-I46 -> 24 | K46: =MAX(K47:K52) -> 45926 | M46: =(J47*M47+J48*M48+J49*M49+J50*M50+J51*M51+J52*M52)/SUM(J47:J52) -> 1 | N46: =(K47*N47+K48*N48+K49*N49+K50*N50+K51*N51+K52*N52)/SUM(K47:K52) -> 1
B47: 8.1 | C47: Equipment serial numbers | E47: =G44 -> 45863 | F47: 2 | G47: =WORKDAY.INTL(E47,F47,1,Data!$C$3:$C$14) -> 45867 | I47: =K44 -> 45902 | J47: 2 | K47: =WORKDAY.INTL(I47,J47,1,Data!$C$3:$C$14) -> 45904 | M47: 1 | N47: 1
B48: 8.2 | C48: Snags completion | E48: =G44 -> 45863 | F48: 4 | G48: =WORKDAY.INTL(E48,F48,1,Data!$C$3:$C$14) -> 45869 | I48: =K44 -> 45902 | J48: 4 | K48: =WORKDAY.INTL(I48,J48,1,Data!$C$3:$C$14) -> 45908 | M48: 1 | N48: 1
B49: 8.3 | C49: System Performance Monitoring | E49: =WORKDAY.INTL(G48,0,1,Data!$C$3:$C$14) -> 45869 | F49: 5 | G49: =WORKDAY.INTL(E49,F49,1,Data!$C$3:$C$14) -> 45876 | I49: =WORKDAY.INTL(K48,0,1,Data!$C$3:$C$14) -> 45908 | J49: 5 | K49: =WORKDAY.INTL(I49,J49,1,Data!$C$3:$C$14) -> 45915 | M49: 1 | N49: 1
B50: 8.4 | C50: Handover documentation | E50: =WORKDAY.INTL(E44,0,1,Data!$C$3:$C$14) -> 45862 | F50: 6 | G50: =WORKDAY.INTL(E50,F50,1,Data!$C$3:$C$14) -> 45870 | I50: 45915 | J50: 4 | K50: =WORKDAY.INTL(I50,J50,1,Data!$C$3:$C$14) -> 45919 | M50: 1 | N50: 1
B51: 8.5 | C51: Handover to Client | E51: =WORKDAY.INTL(G50,0,1,Data!$C$3:$C$14) -> 45870 | F51: 1 | G51: =WORKDAY.INTL(E51,F51,1,Data!$C$3:$C$14) -> 45873 | I51: =WORKDAY.INTL(K50,0,1,Data!$C$3:$C$14) -> 45919 | J51: 1 | K51: =WORKDAY.INTL(I51,J51,1,Data!$C$3:$C$14) -> 45922 | M51: 1 | N51: 1 | O51: Align with Roedolph on client over
B52: 8.6 | C52: Handover to Matriarch | E52: =WORKDAY.INTL(E48,0,1,Data!$C$3:$C$14)+2 -> 45865 | F52: 5 | G52: =WORKDAY.INTL(E52,F52,1,Data!$C$3:$C$14) -> 45870 | I52: =K51 -> 45922 | J52: 3 | K52: =WORKDAY.INTL(I52,J52,1,Data!$C$3:$C$14) -> 45926 | M52: 1 | N52: 1

Sheet Data
C2: Public holidays | F2: Drop down list
C3: 45658 | D3: New Years Day | F3: Approved
C4: 45737 | D4: Human Rights day | F4: Pending
C5: 45765 | D5: Good Friday | F5: Declined
C6: 45768 | D6: Family Day | F6: Abanded
C7: 45774 | D7: Freedom Day
C8: 45765 | D8: Freedom DayObserved
C9: 45778 | D9: Workers day
C10: 45824 | D10: Youth Day Holiday
C11: 45878 | D11: Womens Day
C12: 45924 | D12: Heritage Day
C13: 46007 | D13: Day of Reconciliation | H13: Manual dates
C14: 46016 | D14: Christmas Day
C15: 46017 | D15: Day of Goodwill

Sheet Expenditure Tracking
B2: HIGH LEVEL PROJECT EXPENDITURE TRACKING
F4: COSTED | H4: ACTUAL | J4: Difference from costed
B5: EXPENDITURE | F5: =SUM(F9:F23) -> 3478221.3 | H5: =SUM(H9:H23) -> 2789768.9 | J5: =SUM(J9:J23) -> 688452.37
B7: No. | D7: Item | F7: Costed Expenditure | H7: Actual Expenditure | J7: Saving / Overrun | L7: Comments on variations from planned expenditure
B9: ='Expenditure Breakdown'!L6 -> 1 | D9: ='Expenditure Breakdown'!M6 -> 1. Panels | F9: ='Expenditure Breakdown'!I6 -> 822562.51 | H9: ='Expenditure Breakdown'!X6 -> 778527.8 | J9: =F9-H9 -> 44034.71
B10: ='Expenditure Breakdown'!L13 -> 2 | D10: ='Expenditure Breakdown'!M13 -> 2. Inverters | F10: ='Expenditure Breakdown'!I13 -> 210000 | H10: ='Expenditure Breakdown'!X13 -> 206611.05 | J10: =F10-H10 -> 3388.95
B11: ='Expenditure Breakdown'!L21 -> 3 | D11: ='Expenditure Breakdown'!M21 -> 3. Mounting Structures | F11: ='Expenditure Breakdown'!I21 -> 176179.5 | H11: ='Expenditure Breakdown'!X21 -> 67072.02 | J11: =F11-H11 -> 109107.48
B12: ='Expenditure Breakdown'!L31 -> 4 | D12: ='Expenditure Breakdown'!M31 -> 4. DC Equipment | F12: ='Expenditure Breakdown'!I31 -> 317797.8 | H12: ='Expenditure Breakdown'!X31 -> 228221.77 | J12: =F12-H12 -> 89576.033
B13: ='Expenditure Breakdown'!L47 -> 5 | D13: ='Expenditure Breakdown'!M47 -> 5. Monitoring | F13: ='Expenditure Breakdown'!I47 -> 49000 | H13: ='Expenditure Breakdown'!X47 -> 35927.14 | J13: =F13-H13 -> 13072.86
B14: ='Expenditure Breakdown'!L58 -> 6 | D14: ='Expenditure Breakdown'!M58 -> 6. AC Equipment | F14: ='Expenditure Breakdown'!I58 -> 398615.73 | H14: ='Expenditure Breakdown'!X58 -> 200393.09 | J14: =F14-H14 -> 198222.64
B15: ='Expenditure Breakdown'!L76 -> 7 | D15: ='Expenditure Breakdown'!M76 -> 7.BESS | F15: ='Expenditure Breakdown'!I76 -> 0 | H15: ='Expenditure Breakdown'!X76 -> 0 | J15: =F15-H15 -> 0
B16: ='Expenditure Breakdown'!L85 -> 8 | D16: ='Expenditure Breakdown'!M85 -> 8. Product Add On | F16: ='Expenditure Breakdown'!I85 -> 0 | H16: ='Expenditure Breakdown'!X85 -> 68584.8 | J16: =F16-H16 -> -68584.8
B17: ='Expenditure Breakdown'!L95 -> 9 | D17: ='Expenditure Breakdown'!M95 -> 9. AC & DC installation | F17: ='Expenditure Breakdown'!I95 -> 316662.5 | H17: ='Expenditure Breakdown'!X95 -> 470550 | J17: =F17-H17 -> -153887.5
B18: ='Expenditure Breakdown'!L108 -> 10 | D18: ='Expenditure Breakdown'!M108 -> 10. Site Logistics | F18: ='Expenditure Breakdown'!I108 -> 63976.2 | H18: ='Expenditure Breakdown'!X108 -> 46421.6 | J18: =F18-H18 -> 17554.6
B19: ='Expenditure Breakdown'!L129 -> 11 | D19: ='Expenditure Breakdown'!M129 -> 11. Due Dilligence | F19: ='Expenditure Breakdown'!I129 -> 117575.5 | H19: ='Expenditure Breakdown'!X129 -> 33449.73 | J19: =F19-H19 -> 84125.77
B20: ='Expenditure Breakdown'!L135 -> 12 | D20: ='Expenditure Breakdown'!M135 -> 12. BDP Commission | F20: ='Expenditure Breakdown'!I135 -> 67721.898 | H20: ='Expenditure Breakdown'!X135 -> 0 | J20: =F20-H20 -> 67721.898
B21: ='Expenditure Breakdown'!L138 -> 13 | D21: ='Expenditure Breakdown'!M139 -> 13. Engineering | F21: ='Expenditure Breakdown'!I138 -> 131304.62 | H21: ='Expenditure Breakdown'!X138 -> 47334.15 | J21: =F21-H21 -> 83970.472
B22: ='Expenditure Breakdown'!L145 -> 14 | D22: ='Expenditure Breakdown'!M145 -> 14. General Expenses | F22: ='Expenditure Breakdown'!I145 -> 6825 | H22: ='Expenditure Breakdown'!X145 -> 10913.24 | J22: =F22-H22 -> -4088.24
B23: ='Expenditure Breakdown'!L158 -> 15 | D23: ='Expenditure Breakdown'!M158 -> 15. Service Add On | F23: ='Expenditure Breakdown'!I158 -> 800000 | H23: ='Expenditure Breakdown'!X158 -> 595762.5 | J23: =F23-H23 -> 204237.5
D25: check: | F25: ='Expenditure Breakdown'!I2-'Expenditure Tracking'!F5 -> 0 | G25: =#REF!-G5 -> #REF! | H25: ='Expenditure Breakdown'!X2-H5 -> 0

Sheet Expenditure Breakdown
B2: COSTED EXPENDITURE BREAKDOWN | I2: =SUM(I6:I170) -> 3478221.3 | J2: =SUM(J6:J170) -> 3786732.1 | L2: ACTUAL EXPENDITURE BREAKDOWN | R2: FINANCE ONLY | X2: =SUM(X6:X170) -> 2789768.9
B4: No. | C4: Product / Service | D4: Description of Work | E4: QTY | F4: Rate / Unit | G4: Budget Total | H4: FINANCE PAYMENT DATE | I4: Total COS | J4: =IF(J2-'Revenue Tracking'!D4>=0, "Total Revenue", "ERROR on REV" ) -> Total Revenue | L4: No. | M4: Product/ Service | N4: Description of Work | O4: QTY | P4: Rate / Unit | Q4: Actual Total | R4: PO NUMBER | S4: INVOICE NUMBER | T4: INVOICE RAISED DATE | U4: REVENUE RECOGNITION AMOUNT | V4: CHECK | W4: FINANCE PAYMENT DATE | X4: Total COS
B6: 1 | C6: Panels | D6: Panels Budget | G6: =D171 -> 822562.51 | H6: 45867 | I6: =SUM(G6:G11) -> 822562.51 | J6: =F171 -> 934730.12 | L6: 1 | M6: 1. Panels | N6: Jinko 620W - MENLO | O6: 631 | P6: =1.99*620 -> 1233.8 | Q6: =O6*P6 -> 778527.8 | R6: PO3904-DIP-PH2-PNP-20250514 | S6: Menlo INV0002963 | T6: 45808 | U6: 934730.12 | V6: =J6-SUM(U6:U11) -> 0 | W6: 45867 | X6: =SUM(Q6:Q11) -> 778527.8
B7: 1 | D7: Delivery Budget | L7: 1 | M7: 1. Panels | T7: =IF(W7>1,EOMONTH(W7,0),"") | U7: 0
B8: 1 | L8: 1 | M8: 1. Panels | T8: =IF(W8>1,EOMONTH(W8,0),"") | U8: 0
B9: 1 | L9: 1 | M9: 1. Panels | T9: =IF(W9>1,EOMONTH(W9,0),"") | U9: 0
B10: 1 | L10: 1 | M10: 1. Panels | T10: =IF(W10>1,EOMONTH(W10,0),"") | U10: 0
B11: 1 | L11: 1 | M11: 1. Panels | T11: =IF(W11>1,EOMONTH(W11,0),"") | U11: 0 | Y11: BUDGET | Z11: Installer Allocation
T12: =IF(W12>1,EOMONTH(W12,0),"") | Y12: AC Equipment | Z12: =G58 -> 398615.73
B13: 2 | C13: Inverters | D13: Inverter Budget | G13: =D172 -> 210000 | H13: 45867 | I13: =SUM(G13:G19) -> 210000 | J13: =F172 -> 238636.36 | L13: 2 | M13: 2. Inverters | N13: Huawei 100KTL - MENLO | O13: 3 | P13: 68870.35 | Q13: =O13*P13 -> 206611.05 | R13: PO3904-DIP-PH2-PNP-20250514 | S13: Menlo INV0002963 | T13: =IF(W13>1,EOMONTH(W13,-2),"") -> 45808 | U13: 238636.36 | V13: =J13-SUM(U13:U19) -> 0 | W13: 45867 | X13: =SUM(Q13:Q19) -> 206611.05 | Y13: DC Equipment | Z13: =G32 -> 189585.8
B14: 2 | L14: 2 | M14: 2. Inverters | T14: =IF(W14>1,EOMONTH(W14,0),"") | U14: 0 | Y14: AC Labour | Z14: =G95 -> 97877.5
B15: 2 | L15: 2 | M15: 2. Inverters | T15: =IF(W15>1,EOMONTH(W15,0),"") | U15: 0 | Y15: DC Labour | Z15: =G96 -> 218785
B16: 2 | L16: 2 | M16: 2. Inverters | T16: =IF(W16>1,EOMONTH(W16,0),"") | U16: 0 | Y16: Offloading | Z16: =G108 -> 8500
B17: 2 | L17: 2 | M17: 2. Inverters | T17: =IF(W17>1,EOMONTH(W17,0),"") | U17: 0 | Y17: Scaffolding | Z17: =G109 -> 26666.2
B18: 2 | L18: 2 | M18: 2. Inverters | T18: =IF(W18>1,EOMONTH(W18,0),"") | U18: 0 | Y18: Storage | Z18: =G116 -> 4810
B19: 2 | L19: 2 | M19: 2. Inverters | T19: =IF(W19>1,EOMONTH(W19,0),"") | U19: 0 | Y19: Telehandler | Z19: 0
T20: =IF(W20>1,EOMONTH(W20,0),"")
B21: 3 | C21: Mounting Structures | D21: Structure Budget | G21: =D173 -> 176179.5 | H21: 45835 | I21: =SUM(G21:G29) -> 176179.5 | J21: =F173 -> 200203.98 | L21: 3 | M21: 3. Mounting Structures | N21: Schletter Structure | Q21: =70265.6-Q22 -> 62801.6 | R21: PO3946-DPK-20250521 - RV Approved | S21: Schletter - INV1786 | T21: =IF(W21>1,EOMONTH(W21,-1),"") -> 45808 | U21: 146262.48 | V21: =J21-SUM(U21:U29) -> 0.0043917412 | W21: 45835 | X21: =SUM(Q21:Q29) -> 67072.02 | Y21: Other | Z21: 0
B22: 3 | H22: 45838 | L22: 3 | M22: 3. Mounting Structures | N22: Schletter PRO 551 clamps ( stock from PE store) | O22: 300 | P22: 24.88 | Q22: =O22*P22 -> 7464 | S22: Allocated from PE Stockroom | T22: 45838 | U22: 15404.446 | W22: 45838 | Y22: Total | Z22: =SUM(Z12:Z21) -> 944840.23
H23: 45869 | L23: 3 | M23: 3. Mounting Structures | N23: Schletter PRO 551 clamps ( stock from PE store) | O23: =-O22 -> -300 | P23: 24.88 | Q23: =O23*P23 -> -7464 | S23: Allocated to PE Stockroom | T23: 45869 | U23: 0 | W23: 45869
L24: 3 | M24: 3. Mounting Structures | N24: End Clamps | O24: 300 | P24: 11.48 | Q24: =O24*P24 -> 3444 | S24: Allocated to PE Stockroom | T24: 45869 | U24: 36831.45
H25: 45867 | L25: 3 | M25: 3. Mounting Structures | N25: Delivery Fee | Q25: 826.42 | S25: DSV Invoice: 180135241 | T25: 45838 | U25: 1705.5925 | W25: 45867
B26: 3 | L26: 3 | M26: 3. Mounting Structures | U26: =(Q26/$X$21*$J$21) -> 0 | Y26: Less 15% | Z26: =+Z22*0.85 -> 803114.19
B27: 3 | L27: 3 | M27: 3. Mounting Structures | T27: =IF(W27>1,EOMONTH(W27,0),"") | U27: =(Q27/$X$21*$J$21) -> 0 | Y27: R/Wp | Z27: =Z26/'Project Plan'!$E$3/1000 -> 2.0540005
B28: 3 | L28: 3 | M28: 3. Mounting Structures | T28: =IF(W28>1,EOMONTH(W28,0),"") | U28: =(Q28/$X$21*$J$21) -> 0
B29: 3 | L29: 3 | M29: 3. Mounting Structures | T29: =IF(W29>1,EOMONTH(W29,0),"") | U29: =(Q29/$X$21*$J$21) -> 0 | Y29: ACTUAL - Cosmic Sun | Z29: Installer Price
T30: =IF(W30>1,EOMONTH(W30,0),"") | Y30: =Y12 -> AC Equipment | Z30: 106054
B31: 4 | C31: DC Equipment | D31: DC Cable Budget | E31: =G31/14*1.15 -> 10531.7 | G31: 128212 | H31: =H13 -> 45867 | I31: =SUM(G31:G45) -> 317797.8 | J31: =F174 -> 361133.86 | L31: 4 | M31: 4. DC Equipment | N31: DC Cable = Menlo | O31: 600 | P31: 13.4 | Q31: =O31*P31 -> 8040 | R31: PO3904-DIP-PH2-PNP-20250514 | S31: Menlo INV0002963 | T31: =T13 -> 45808 | U31: 16665.636 | V31: =J31-SUM(U31:U45) -> -0.010530209 | W31: =W13 -> 45867 | X31: =SUM(Q31:Q45) -> 228221.77 | Y31: =Y13 -> DC Equipment | Z31: 93821.75
B32: 4 | D32: DC Equipment Budget | G32: =D174-G31 -> 189585.8 | H32: =H31 -> 45867 | L32: 4 | M32: 4. DC Equipment | N32: DC Cable = Menlo | O32: 5400 | P32: 13.4 | Q32: =O32*P32 -> 72360 | S32: Menlo INV0002963 | T32: 45808 | U32: 149990.72 | W32: =W31 -> 45867 | Y32: =Y14 -> AC Labour | Z32: 149030
B33: 4 | H33: 45890 | L33: 4 | M33: 4. DC Equipment | N33: DC Cable = Menlo _Top Up - VO | O33: 4000 | P33: 13.5 | Q33: =O33*P33 -> 54000 | R33: PO4017-DPK-20250520 - RV Approved | S33: Menlo INV0003033 | T33: 45838 | U33: 34511.772 | W33: 45890 | Y33: =Y15 -> DC Labour | Z33: 321520
B34: 4 | L34: 4 | M34: 4. DC Equipment | T34: =IF(W34>1,EOMONTH(W34,0),"") | U34: =(Q34/$X$31*$J$31) -> 0 | Y34: =Y16 -> Offloading | Z34: 4950
B35: 4 | H35: =H96 -> 45792 | L35: 4 | M35: 4. DC Equipment | N35: Project Kick Off | O35: 93821.75 | P35: 0.1 | Q35: =$O$35*P35 -> 9382.175 | R35: PO3879-DPK-20250513 - RV Approved | S35: Cosmic Sun: CS_KRN_001 | T35: =IF(W35>1,EOMONTH(W35,0),"") -> 45808 | U35: 19447.75 | W35: =W96 -> 45792 | Y35: =Y17 -> Scaffolding | Z35: 16621.6
B36: 4 | H36: =H97 -> 45813 | L36: 4 | M36: 4. DC Equipment | N36: Site Establishment | P36: 0.15 | Q36: =$O$35*P36 -> 14073.262 | S36: Cosmic Sun: CS_KRN_002 | T36: 45808 | U36: 29171.626 | W36: =W97 -> 45813 | Y36: =Y18 -> Storage | Z36: 6600
B37: 4 | H37: =H98 -> 45876 | L37: 4 | M37: 4. DC Equipment | N37: AC Installation Complete | P37: 0.2 | Q37: 18764.35 | S37: Cosmic Sun: CS_KRN_004 | T37: 45838 | U37: 29692.357 | W37: =W98 -> 45876 | Y37: =Y19 -> Telehandler | Z37: =Z19*0.75 -> 0
B38: 4 | H38: =H99 -> 45849 | L38: 4 | M38: 4. DC Equipment | N38: DC Installation Complete | P38: 0.25 | Q38: 23455.44 | S38: Cosmic Sun: CS_KRN_003 | T38: 45838 | U38: 37115.45 | W38: =W99 -> 45849 | Y38: HSE | Z38: 4500
B39: 4 | H39: =H100 -> 45904 | L39: 4 | M39: 4. DC Equipment | N39: Commissioning Complete | P39: 0.1 | Q39: 9382.18 | S39: Cosmic Sun: CS_KRN_005 | T39: 45838 | U39: 14846.186 | W39: =W100 -> 45904 | Y39: Other | Z39: 0
B40: 4 | H40: =H101 -> 45904 | L40: 4 | M40: 4. DC Equipment | N40: Site De-establisment | P40: 0.1 | Q40: 9382.18 | S40: Cosmic Sun: CS_KRN_006 | T40: 45838 | U40: 14846.186 | W40: =W101 -> 45904 | Y40: Other | Z40: 0
B41: 4 | H41: =H102 -> 45925 | L41: 4 | M41: 4. DC Equipment | N41: Handover Document Complete | P41: 0.05 | Q41: 4691.09 | S41: Cosmic Sun: CS_KRN_007 | T41: 45838 | U41: 7423.0932 | W41: =W102 -> 45925 | Y41: Total | Z41: =SUM(Z30:Z40) -> 703097.35
B42: 4 | H42: =H103 -> 45926 | L42: 4 | M42: 4. DC Equipment | N42: End of Defects Period | P42: 0.05 | Q42: 4691.09 | S42: Cosmic Sun: CS_KRN_008 | T42: 45838 | U42: 7423.0932 | W42: =W103 -> 45954 | Y42: R/Wp | Z42: =Z41/'Project Plan'!$E$3/1000 -> 1.7982029
B43: 4 | L43: 4 | M43: 4. DC Equipment | T43: =IF(W43>1,EOMONTH(W43,0),"") | U43: =(Q43/$X$31*$J$31) -> 0
B44: 4 | L44: 4 | M44: 4. DC Equipment | T44: =IF(W44>1,EOMONTH(W44,0),"") | U44: =(Q44/$X$31*$J$31) -> 0
B45: 4 | L45: 4 | M45: 4. DC Equipment | T45: =IF(W45>1,EOMONTH(W45,0),"") | U45: =(Q45/$X$31*$J$31) -> 0
T46: =IF(W46>1,EOMONTH(W46,0),"")
B47: 5 | C47: Monitoring | D47: Monitoring Budget | G47: =D176-G50 -> 34000 | H47: 45855 | I47: =SUM(G47:G56) -> 49000 | J47: =F176 -> 55681.818 | L47: 5 | M47: 5. Monitoring | N47: Smartlogger - Menlo - faulty awaiting RMA | Q47: 8598.35 | R47: PO3904-DIP-PH2-PNP-20250514 | S47: Menlo INV0002933 | T47: =T13 -> 45808 | U47: 12277.093 | V47: =J47-SUM(U47:U56) -> 0.0049348232 | W47: 45855 | X47: =SUM(Q47:Q56) -> 35927.14
H48: 45946 | L48: 5 | M48: 5. Monitoring | Q48: 8598.35 | S48: Menlo INV0003159 | T48: 45900 | U48: 0 | W48: 45946
L49: 5 | M49: 5. Monitoring | N49: Smartlogger - Moveto BMG Fluid Tech | Q49: -8598.35 | S49: Allocated to BMG Fluid Tech | T49: 45991 | U49: 0 | W49: 45991
B50: 5 | D50: Revenue Metering | G50: 15000 | H50: 45806 | L50: 5 | M50: 5. Monitoring | N50: CTs & Meters | Q50: 13695 | R50: PO3835-DIP-Ph2-PnP-20250429 - RV Approved | S50: Accuenergy - INV ASAI-005361 | T50: 45777 | U50: 19114.237 | W50: 45806
H51: 45867 | L51: 5 | M51: 5. Monitoring | Q51: 214.29 | S51: Accuenergy - Inv ASAI-005800 | T51: 45838 | U51: 4143.3482 | W51: 45867
B52: 5 | H52: 45838 | L52: 5 | M52: 5. Monitoring | N52: Techsitter | Q52: 11169 | S52: Matriarch Inv: 4451 | T52: 45838 | U52: 16978.198 | W52: 45838
B53: 5 | H53: 45799 | L53: 5 | M53: 5. Monitoring | N53: UPS | Q53: 2250.5 | R53: PO3863-DIP Ph2-20250509 - RV Approved | S53: Frontline INV725690 | T53: 45808 | U53: 3168.936 | W53: 45799
B54: 5 | L54: 5 | M54: 5. Monitoring | T54: =IF(W54>1,EOMONTH(W54,0),"") | U54: =(Q54/$X$47*$J$47) -> 0
B55: 5 | L55: 5 | M55: 5. Monitoring | T55: =IF(W55>1,EOMONTH(W55,0),"") | U55: =(Q55/$X$47*$J$47) -> 0
B56: 5 | L56: 5 | M56: 5. Monitoring | T56: =IF(W56>1,EOMONTH(W56,0),"") | U56: =(Q56/$X$47*$J$47) -> 0
T57: =IF(W57>1,EOMONTH(W57,0),"")
B58: 6 | C58: AC Equipment | D58: AC Equipment Budget | G58: =D175 -> 398615.73 | H58: 45866 | I58: =SUM(G58:G74) -> 398615.73 | J58: =F175 -> 452972.42 | L58: 6 | M58: 6. AC Equipment | T58: =IF(W58>1,EOMONTH(W58,0),"") | U58: =(Q58/$X$58*$J$58) -> 0 | V58: =J58-SUM(U58:U74) -> -0.0017342904 | X58: =SUM(Q58:Q74) -> 200393.09
B59: 6 | H59: 45867 | L59: 6 | M59: 6. AC Equipment | N59: PVDB | Q59: 94339.09 | R59: PO3884-DIP-Ph2-Kroon-20250513 - RV Approved | S59: Switchboard - Inv 2-SOI002093 | T59: 45838 | U59: 213245.9 | W59: 45867
B60: 6 | L60: 6 | M60: 6. AC Equipment | T60: =IF(W60>1,EOMONTH(W60,0),"") | U60: =(Q60/$X$58*$J$58) -> 0
B61: 6 | L61: 6 | M61: 6. AC Equipment | T61: =IF(W61>1,EOMONTH(W61,0),"") | U61: =(Q61/$X$58*$J$58) -> 0
B62: 6 | L62: 6 | M62: 6. AC Equipment | T62: =IF(W62>1,EOMONTH(W62,0),"") | U62: =(Q62/$X$58*$J$58) -> 0
B63: 6 | L63: 6 | M63: 6. AC Equipment | T63: =IF(W63>1,EOMONTH(W63,0),"") | U63: =(Q63/$X$58*$J$58) -> 0
B64: 6 | H64: =H96 -> 45792 | L64: 6 | M64: 6. AC Equipment | N64: Project Kick Off | O64: 106054 | P64: 0.1 | Q64: =$O$64*P64 -> 10605.4 | R64: PO3879-DPK-20250513 - RV Approved | S64: Cosmic Sun: CS_KRN_001 | T64: =IF(W64>1,EOMONTH(W64,0),"") -> 45808 | U64: 24258.152 | W64: =W96 -> 45792
B65: 6 | H65: =H97 -> 45813 | L65: 6 | M65: 6. AC Equipment | N65: Site Establishment | P65: 0.15 | Q65: =$O$64*P65 -> 15908.1 | S65: Cosmic Sun: CS_KRN_002 | T65: 45808 | U65: 36387.228 | W65: =W97 -> 45813
B66: 6 | H66: =H98 -> 45876 | L66: 6 | M66: 6. AC Equipment | N66: AC Installation Complete | P66: 0.2 | Q66: =$O$64*P66 -> 21210.8 | S66: Cosmic Sun: CS_KRN_004 | T66: 45838 | U66: 47231.553 | W66: =W98 -> 45876
B67: 6 | H67: =H99 -> 45849 | L67: 6 | M67: 6. AC Equipment | N67: DC Installation Complete | P67: 0.25 | Q67: =$O$64*P67 -> 26513.5 | S67: Cosmic Sun: CS_KRN_003 | T67: 45838 | U67: 59931.628 | W67: =W99 -> 45849
B68: 6 | H68: =H100 -> 45904 | L68: 6 | M68: 6. AC Equipment | N68: Commissioning Complete | P68: 0.1 | Q68: =$O$64*P68 -> 10605.4 | S68: Cosmic Sun: CS_KRN_005 | T68: 45838 | U68: 23972.651 | W68: =W100 -> 45904
B69: 6 | H69: =H101 -> 45904 | L69: 6 | M69: 6. AC Equipment | N69: Site De-establisment | P69: 0.1 | Q69: =$O$64*P69 -> 10605.4 | S69: Cosmic Sun: CS_KRN_006 | T69: 45838 | U69: 23972.651 | W69: =W101 -> 45904
B70: 6 | H70: =H102 -> 45925 | L70: 6 | M70: 6. AC Equipment | N70: Handover Document Complete | P70: 0.05 | Q70: =$O$64*P70 -> 5302.7 | S70: Cosmic Sun: CS_KRN_007 | T70: 45838 | U70: 11986.326 | W70: =W102 -> 45925
B71: 6 | H71: =H103 -> 45926 | L71: 6 | M71: 6. AC Equipment | N71: End of Defects Period | P71: 0.05 | Q71: =$O$64*P71 -> 5302.7 | S71: Cosmic Sun: CS_KRN_008 | T71: 45838 | U71: 11986.326 | W71: =W103 -> 45954
B72: 6 | L72: 6 | M72: 6. AC Equipment | T72: =IF(W72>1,EOMONTH(W72,0),"") | U72: =(Q72/$X$58*$J$58) -> 0
B73: 6 | L73: 6 | M73: 6. AC Equipment | T73: =IF(W73>1,EOMONTH(W73,0),"") | U73: =(Q73/$X$58*$J$58) -> 0
B74: 6 | L74: 6 | M74: 6. AC Equipment | T74: =IF(W74>1,EOMONTH(W74,0),"") | U74: =(Q74/$X$58*$J$58) -> 0
T75: =IF(W75>1,EOMONTH(W75,0),"")
B76: 7 | C76: BESS | I76: =SUM(G76:G83) -> 0 | J76: 0 | L76: 7 | M76: 7.BESS | T76: =IF(W76>1,EOMONTH(W76,0),"") | V76: =J76-SUM(U76:U83) -> 0 | X76: =SUM(Q76:Q83) -> 0
B77: 7 | L77: 7 | M77: 7.BESS | T77: =IF(W77>1,EOMONTH(W77,0),"")
B78: 7 | L78: 7 | M78: 7.BESS | T78: =IF(W78>1,EOMONTH(W78,0),"")
B79: 7 | L79: 7 | M79: 7.BESS | T79: =IF(W79>1,EOMONTH(W79,0),"")
B80: 7 | L80: 7 | M80: 7.BESS | T80: =IF(W80>1,EOMONTH(W80,0),"")
B81: 7 | L81: 7 | M81: 7.BESS | T81: =IF(W81>1,EOMONTH(W81,0),"")
B82: 7 | L82: 7 | M82: 7.BESS | T82: =IF(W82>1,EOMONTH(W82,0),"")
B83: 7 | L83: 7 | M83: 7.BESS | T83: =IF(W83>1,EOMONTH(W83,0),"")
T84: =IF(W84>1,EOMONTH(W84,0),"")
B85: 8 | C85: Product Add On | I85: =D178 -> 0 | J85: =F178 -> 0 | L85: 8 | M85: 8. Product Add On | T85: =IF(W85>1,EOMONTH(W85,0),"") | V85: =J85-SUM(U85:U93) -> 0 | X85: =SUM(Q85:Q93) -> 68584.8
B86: 8 | L86: 8 | M86: 8. Product Add On | T86: =IF(W86>1,EOMONTH(W86,0),"")
B87: 8 | H87: 45961 | L87: 8 | M87: 8. Product Add On | N87: Aircons Supply and Install - Rubycon | Q87: 36794.4 | R87: PO4534-DPK-20251210 - RV Approved | S87: Rubycon - RD0710251 | T87: 46022 | W87: 46009
B88: 8 | H88: 45961 | L88: 8 | M88: 8. Product Add On | N88: Burglar Door Added Security | Q88: 5770 | R88: PO4355-DPK-20251006 - RV Approved | S88: Rubycon - RD1112253 | T88: 45961 | W88: 45939
B89: 8 | H89: 45961 | L89: 8 | M89: 8. Product Add On | N89: Waterpoints | Q89: 24908.5 | R89: PO4387-DPK-202510210 - RVApproved | S89: Rubycon - RD2310251 | T89: 45961 | W89: 45974
B90: 8 | H90: 45932 | L90: 8 | M90: 8. Product Add On | N90: Delivery of Clamps for Waterpoints | Q90: 261.4 | S90: DSV Inv: 180158820 | T90: 46022 | W90: 46051
B91: 8 | H91: =E91 -> 0 | L91: 8 | M91: 8. Product Add On | N91: Clamps | O91: 30 | P91: 28.35 | Q91: =O91*P91 -> 850.5 | S91: Allocated from Joburg Storeroom | T91: 31/01/2025 | W91: 46053
B92: 8 | L92: 8 | M92: 8. Product Add On | T92: =IF(W92>1,EOMONTH(W92,0),"")
B93: 8 | L93: 8 | M93: 8. Product Add On | T93: =IF(W93>1,EOMONTH(W93,0),"")
K94: Only services to be capture below, products above | T94: =IF(W94>1,EOMONTH(W94,0),"")
B95: 9 | C95: AC & DC Installation | D95: AC Installation Budget | G95: =D184 -> 97877.5 | H95: 45791 | I95: =SUM(G95:G106) -> 316662.5 | J95: =F184+F185 -> 372544.12 | L95: 9 | M95: 9. AC & DC installation | T95: =IF(W95>1,EOMONTH(W95,0),"") | U95: =(Q95/$X$95*$J$95) -> 0 | V95: =J95-SUM(U95:U106) -> 0 | X95: =SUM(Q95:Q106) -> 470550
B96: 9 | D96: DC Installation Budget | G96: =D185 -> 218785 | H96: 45792 | L96: 9 | M96: 9. AC & DC installation | N96: Project Kick Off | O96: 470550 | P96: 0.1 | Q96: =$O$96*P96 -> 47055 | R96: PO3879-DPK-20250513 - RV Approved | S96: Cosmic Sun: CS_KRN_001 | T96: =IF(W96>1,EOMONTH(W96,0),"") -> 45808 | U96: 37254.412 | W96: 45792
B97: 9 | H97: 45813 | L97: 9 | M97: 9. AC & DC installation | N97: Site Establishment | P97: 0.15 | Q97: =$O$96*P97 -> 70582.5 | S97: Cosmic Sun: CS_KRN_002 | T97: 45808 | U97: 55881.618 | W97: 45813
B98: 9 | H98: 45876 | L98: 9 | M98: 9. AC & DC installation | N98: AC Installation Complete | P98: 0.2 | Q98: =$O$96*P98 -> 94110 | S98: Cosmic Sun: CS_KRN_004 | T98: 45838 | U98: 74508.824 | W98: 45876
B99: 9 | H99: 45849 | L99: 9 | M99: 9. AC & DC installation | N99: DC Installation Complete | P99: 0.25 | Q99: =$O$96*P99 -> 117637.5 | S99: Cosmic Sun: CS_KRN_003 | T99: 45838 | U99: 93136.029 | W99: 45849
B100: 9 | H100: 45904 | L100: 9 | M100: 9. AC & DC installation | N100: Commissioning Complete | P100: 0.1 | Q100: =$O$96*P100 -> 47055 | S100: Cosmic Sun: CS_KRN_005 | T100: 45838 | U100: 37254.412 | W100: 45904
B101: 9 | H101: 45904 | L101: 9 | M101: 9. AC & DC installation | N101: Site De-establisment | P101: 0.1 | Q101: =$O$96*P101 -> 47055 | S101: Cosmic Sun: CS_KRN_006 | T101: 45838 | U101: 37254.412 | W101: 45904
B102: 9 | H102: 45925 | L102: 9 | M102: 9. AC & DC installation | N102: Handover Document Complete | P102: 0.05 | Q102: =$O$96*P102 -> 23527.5 | S102: Cosmic Sun: CS_KRN_007 | T102: 45838 | U102: 18627.206 | W102: 45925
B103: 9 | H103: 45926 | L103: 9 | M103: 9. AC & DC installation | N103: End of Defects Period | P103: 0.05 | Q103: =$O$96*P103 -> 23527.5 | S103: Cosmic Sun: CS_KRN_008 | T103: 45838 | U103: 18627.206 | W103: 45954
...

Sheet Cashflow
D1: [RT: Double Check the first date is always a MONDAY] | F1: 45677 | G1: =F1+7 -> 45684 | H1: =G1+7 -> 45691 | I1: =H1+7 -> 45698 | J1: =I1+7 -> 45705 | K1: =J1+7 -> 45712 | L1: =K1+7 -> 45719 | M1: =L1+7 -> 45726 | N1: =M1+7 -> 45733 | ... LD1: =LC1+7 -> 47847
A2: PLANNED | C2: CHECK | D2: CHECK
B3: Planned Revenue | C3: ='Revenue Tracking'!D4 -> 3786732 | D3: =SUM(F3:LD3) -> 3786732 | F3: =SUMIFS('Revenue Tracking'!$F$13:$F$19, 'Revenue Tracking'!$H$13:$H$19, ">="&F1,'Revenue Tracking'!$H$13:$H$19, "<"&G1) -> 0 | G3: =SUMIFS('Revenue Tracking'!$F$13:$F$19, 'Revenue Tracking'!$H$13:$H$19, ">="&G1,'Revenue Tracking'!$H$13:$H$19, "<"&H1) -> 0 | H3: =SUMIFS('Revenue Tracking'!$F$13:$F$19, 'Revenue Tracking'!$H$13:$H$19, ">="&H1,'Revenue Tracking'!$H$13:$H$19, "<"&I1) -> 0 | I3: =SUMIFS('Revenue Tracking'!$F$13:$F$19, 'Revenue Tracking'!$H$13:$H$19, ">="&I1,'Revenue Tracking'!$H$13:$H$19, "<"&J1) -> 0 | J3: =SUMIFS('Revenue Tracking'!$F$13:$F$19, 'Revenue Tracking'!$H$13:$H$19, ">="&J1,'Revenue Tracking'!$H$13:$H$19, "<"&K1) -> 0 | K3: =SUMIFS('Revenue Tracking'!$F$13:$F$19, 'Revenue Tracking'!$H$13:$H$19, ">="&K1,'Revenue Tracking'!$H$13:$H$19, "<"&L1) -> 0 | L3: =SUMIFS('Revenue Tracking'!$F$13:$F$19, 'Revenue Tracking'!$H$13:$H$19, ">="&L1,'Revenue Tracking'!$H$13:$H$19, "<"&M1) -> 0 | M3: =SUMIFS('Revenue Tracking'!$F$13:$F$19, 'Revenue Tracking'!$H$13:$H$19, ">="&M1,'Revenue Tracking'!$H$13:$H$19, "<"&N1) -> 0 | ... LC3: =SUMIFS('Revenue Tracking'!$F$13:$F$19, 'Revenue Tracking'!$H$13:$H$19, ">="&LC1,'Revenue Tracking'!$H$13:$H$19, "<"&LD1) -> 0 | LD3: =SUMIFS('Revenue Tracking'!$F$13:$F$19, 'Revenue Tracking'!$H$13:$H$19, ">="&LD1,'Revenue Tracking'!$H$13:$H$19, "<"&#REF!) -> 0
B4: Planned Revenue - Cumulative | F4: =F3 -> 0 | G4: =F4+G3 -> 0 | H4: =G4+H3 -> 0 | I4: =H4+I3 -> 0 | J4: =I4+J3 -> 0 | K4: =J4+K3 -> 0 | L4: =K4+L3 -> 0 | M4: =L4+M3 -> 0 | N4: =M4+N3 -> 0 | ... LD4: =LC4+LD3 -> 3786732
B5: Planned Expenditure | C5: ='Revenue Tracking'!D5 -> 3478221.3 | D5: =SUM(F5:LD5) -> 3478221.3 | F5: =SUMIFS('Expenditure Breakdown'!$G$6:$G$201, 'Expenditure Breakdown'!$H$6:$H$201, ">="&F1,'Expenditure Breakdown'!$H$6:$H$201, "<"&G1) -> 0 | G5: =SUMIFS('Expenditure Breakdown'!$G$6:$G$201, 'Expenditure Breakdown'!$H$6:$H$201, ">="&G1,'Expenditure Breakdown'!$H$6:$H$201, "<"&H1) -> 0 | H5: =SUMIFS('Expenditure Breakdown'!$G$6:$G$201, 'Expenditure Breakdown'!$H$6:$H$201, ">="&H1,'Expenditure Breakdown'!$H$6:$H$201, "<"&I1) -> 0 | I5: =SUMIFS('Expenditure Breakdown'!$G$6:$G$201, 'Expenditure Breakdown'!$H$6:$H$201, ">="&I1,'Expenditure Breakdown'!$H$6:$H$201, "<"&J1) -> 0 | J5: =SUMIFS('Expenditure Breakdown'!$G$6:$G$201, 'Expenditure Breakdown'!$H$6:$H$201, ">="&J1,'Expenditure Breakdown'!$H$6:$H$201, "<"&K1) -> 0 | K5: =SUMIFS('Expenditure Breakdown'!$G$6:$G$201, 'Expenditure Breakdown'!$H$6:$H$201, ">="&K1,'Expenditure Breakdown'!$H$6:$H$201, "<"&L1) -> 0 | L5: =SUMIFS('Expenditure Breakdown'!$G$6:$G$201, 'Expenditure Breakdown'!$H$6:$H$201, ">="&L1,'Expenditure Breakdown'!$H$6:$H$201, "<"&M1) -> 0 | M5: =SUMIFS('Expenditure Breakdown'!$G$6:$G$201, 'Expenditure Breakdown'!$H$6:$H$201, ">="&M1,'Expenditure Breakdown'!$H$6:$H$201, "<"&N1) -> 0 | ... LC5: =SUMIFS('Expenditure Breakdown'!$G$6:$G$201, 'Expenditure Breakdown'!$H$6:$H$201, ">="&LC1,'Expenditure Breakdown'!$H$6:$H$201, "<"&LD1) -> 0 | LD5: =SUMIFS('Expenditure Breakdown'!$G$6:$G$201, 'Expenditure Breakdown'!$H$6:$H$201, ">="&LD1,'Expenditure Breakdown'!$H$6:$H$201, "<"&#REF!) -> 0
B6: Planned Expenditure - Cumulative | F6: =F11 -> 0 | G6: =F12+G11 -> 0 | H6: =G12+H11 -> 0 | I6: =H12+I11 -> 0 | J6: =I12+J11 -> 0 | K6: =J12+K11 -> 0 | L6: =K12+L11 -> 0 | M6: =L12+M11 -> 0 | N6: =M12+N11 -> 0 | ... LD6: =LC12+LD11 -> 2786324.9
B7: PLANNED CashFlow | F7: =F4-F6 -> 0 | G7: =G4-G6 -> 0 | H7: =H4-H6 -> 0 | I7: =I4-I6 -> 0 | J7: =J4-J6 -> 0 | K7: =K4-K6 -> 0 | L7: =L4-L6 -> 0 | M7: =M4-M6 -> 0 | ... LD7: =LD4-LD6 -> 1000407.1
A8: ACTUAL | C8: CHECK | D8: CHECK
B9: Actual + Planned Revenue | C9: ='Revenue Tracking'!F4 -> 3786732 | D9: =SUM(F9:LD9) -> 3786732 | F9: =SUMIFS('Revenue Tracking'!$F$13:$F$19, 'Revenue Tracking'!$P$13:$P$19, ">="&F1,'Revenue Tracking'!$P$13:$P$19, "<"&G1) -> 0 | G9: =SUMIFS('Revenue Tracking'!$F$13:$F$19, 'Revenue Tracking'!$P$13:$P$19, ">="&G1,'Revenue Tracking'!$P$13:$P$19, "<"&H1) -> 0 | H9: =SUMIFS('Revenue Tracking'!$F$13:$F$19, 'Revenue Tracking'!$P$13:$P$19, ">="&H1,'Revenue Tracking'!$P$13:$P$19, "<"&I1) -> 0 | I9: =SUMIFS('Revenue Tracking'!$F$13:$F$19, 'Revenue Tracking'!$P$13:$P$19, ">="&I1,'Revenue Tracking'!$P$13:$P$19, "<"&J1) -> 0 | J9: =SUMIFS('Revenue Tracking'!$F$13:$F$19, 'Revenue Tracking'!$P$13:$P$19, ">="&J1,'Revenue Tracking'!$P$13:$P$19, "<"&K1) -> 0 | K9: =SUMIFS('Revenue Tracking'!$F$13:$F$19, 'Revenue Tracking'!$P$13:$P$19, ">="&K1,'Revenue Tracking'!$P$13:$P$19, "<"&L1) -> 0 | L9: =SUMIFS('Revenue Tracking'!$F$13:$F$19, 'Revenue Tracking'!$P$13:$P$19, ">="&L1,'Revenue Tracking'!$P$13:$P$19, "<"&M1) -> 0 | M9: =SUMIFS('Revenue Tracking'!$F$13:$F$19, 'Revenue Tracking'!$P$13:$P$19, ">="&M1,'Revenue Tracking'!$P$13:$P$19, "<"&N1) -> 0 | ... LC9: =SUMIFS('Revenue Tracking'!$F$13:$F$19, 'Revenue Tracking'!$P$13:$P$19, ">="&LC1,'Revenue Tracking'!$P$13:$P$19, "<"&LD1) -> 0 | LD9: =SUMIFS('Revenue Tracking'!$F$13:$F$19, 'Revenue Tracking'!$P$13:$P$19, ">="&LD1,'Revenue Tracking'!$P$13:$P$19, "<"&#REF!) -> 0
B10: Actual + Planned Revenue - Cumulative | F10: =F9 -> 0 | G10: =F10+G9 -> 0 | H10: =G10+H9 -> 0 | I10: =H10+I9 -> 0 | J10: =I10+J9 -> 0 | K10: =J10+K9 -> 0 | L10: =K10+L9 -> 0 | M10: =L10+M9 -> 0 | N10: =M10+N9 -> 0 | ... LD10: =LC10+LD9 -> 3786732
B11: Actual + Planned Expenditure | C11: ='Revenue Tracking'!F5 -> 2789768.9 | D11: =SUM(F11:LD11) -> 2786324.9 | F11: =SUMIFS('Expenditure Breakdown'!$Q$6:$Q$177, 'Expenditure Breakdown'!$W$6:$W$177, ">="&F1,'Expenditure Breakdown'!$W$6:$W$177, "<"&G1) -> 0 | G11: =SUMIFS('Expenditure Breakdown'!$Q$6:$Q$177, 'Expenditure Breakdown'!$W$6:$W$177, ">="&G1,'Expenditure Breakdown'!$W$6:$W$177, "<"&H1) -> 0 | H11: =SUMIFS('Expenditure Breakdown'!$Q$6:$Q$177, 'Expenditure Breakdown'!$W$6:$W$177, ">="&H1,'Expenditure Breakdown'!$W$6:$W$177, "<"&I1) -> 0 | I11: =SUMIFS('Expenditure Breakdown'!$Q$6:$Q$177, 'Expenditure Breakdown'!$W$6:$W$177, ">="&I1,'Expenditure Breakdown'!$W$6:$W$177, "<"&J1) -> 0 | J11: =SUMIFS('Expenditure Breakdown'!$Q$6:$Q$177, 'Expenditure Breakdown'!$W$6:$W$177, ">="&J1,'Expenditure Breakdown'!$W$6:$W$177, "<"&K1) -> 0 | K11: =SUMIFS('Expenditure Breakdown'!$Q$6:$Q$177, 'Expenditure Breakdown'!$W$6:$W$177, ">="&K1,'Expenditure Breakdown'!$W$6:$W$177, "<"&L1) -> 0 | L11: =SUMIFS('Expenditure Breakdown'!$Q$6:$Q$177, 'Expenditure Breakdown'!$W$6:$W$177, ">="&L1,'Expenditure Breakdown'!$W$6:$W$177, "<"&M1) -> 0 | M11: =SUMIFS('Expenditure Breakdown'!$Q$6:$Q$177, 'Expenditure Breakdown'!$W$6:$W$177, ">="&M1,'Expenditure Breakdown'!$W$6:$W$177, "<"&N1) -> 0 | ... LC11: =SUMIFS('Expenditure Breakdown'!$Q$6:$Q$177, 'Expenditure Breakdown'!$W$6:$W$177, ">="&LC1,'Expenditure Breakdown'!$W$6:$W$177, "<"&LD1) -> 0 | LD11: =SUMIFS('Expenditure Breakdown'!$Q$6:$Q$177, 'Expenditure Breakdown'!$W$6:$W$177, ">="&LD1,'Expenditure Breakdown'!$W$6:$W$177, "<"&#REF!) -> 0
B12: Actual + Planned Expenditure - Cumulative | F12: =F11 -> 0 | G12: =F12+G11 -> 0 | H12: =G12+H11 -> 0 | I12: =H12+I11 -> 0 | J12: =I12+J11 -> 0 | K12: =J12+K11 -> 0 | L12: =K12+L11 -> 0 | M12: =L12+M11 -> 0 | N12: =M12+N11 -> 0 | ... LD12: =LC12+LD11 -> 2786324.9
B14: ACTUAL CashFlow | F14: =F10-F12 -> 0 | G14: =G10-G12 -> 0 | H14: =H10-H12 -> 0 | I14: =I10-I12 -> 0 | J14: =J10-J12 -> 0 | K14: =K10-K12 -> 0 | L14: =L10-L12 -> 0 | M14: =M10-M12 -> 0 | ... LD14: =LD10-LD12 -> 1000407.1
C16: CHECK | D16: CHECK
B17: Revenue Recognition | C17: =C3-D17 -> -0.12802576 | D17: =SUM(F17:LD17) -> 3786732.1 | F17: =SUMIFS('Expenditure Breakdown'!$U$6:$U$177, 'Expenditure Breakdown'!$T$6:$T$177, ">="&F1,'Expenditure Breakdown'!$T$6:$T$177, "<"&G1) -> 0 | G17: =SUMIFS('Expenditure Breakdown'!$U$6:$U$177, 'Expenditure Breakdown'!$T$6:$T$177, ">="&G1,'Expenditure Breakdown'!$T$6:$T$177, "<"&H1) -> 0 | H17: =SUMIFS('Expenditure Breakdown'!$U$6:$U$177, 'Expenditure Breakdown'!$T$6:$T$177, ">="&H1,'Expenditure Breakdown'!$T$6:$T$177, "<"&I1) -> 0 | I17: =SUMIFS('Expenditure Breakdown'!$U$6:$U$177, 'Expenditure Breakdown'!$T$6:$T$177, ">="&I1,'Expenditure Breakdown'!$T$6:$T$177, "<"&J1) -> 0 | J17: =SUMIFS('Expenditure Breakdown'!$U$6:$U$177, 'Expenditure Breakdown'!$T$6:$T$177, ">="&J1,'Expenditure Breakdown'!$T$6:$T$177, "<"&K1) -> 0 | K17: =SUMIFS('Expenditure Breakdown'!$U$6:$U$177, 'Expenditure Breakdown'!$T$6:$T$177, ">="&K1,'Expenditure Breakdown'!$T$6:$T$177, "<"&L1) -> 0 | L17: =SUMIFS('Expenditure Breakdown'!$U$6:$U$177, 'Expenditure Breakdown'!$T$6:$T$177, ">="&L1,'Expenditure Breakdown'!$T$6:$T$177, "<"&M1) -> 0 | M17: =SUMIFS('Expenditure Breakdown'!$U$6:$U$177, 'Expenditure Breakdown'!$T$6:$T$177, ">="&M1,'Expenditure Breakdown'!$T$6:$T$177, "<"&N1) -> 0 | ... LC17: =SUMIFS('Expenditure Breakdown'!$U$6:$U$177, 'Expenditure Breakdown'!$T$6:$T$177, ">="&LC1,'Expenditure Breakdown'!$T$6:$T$177, "<"&LD1) -> 0 | LD17: =SUMIFS('Expenditure Breakdown'!$U$6:$U$177, 'Expenditure Breakdown'!$T$6:$T$177, ">="&LD1,'Expenditure Breakdown'!$T$6:$T$177, "<"&#REF!) -> 0
B18: Revenue Recognition Cumulative | C18: =D17-D18 -> 0 | D18: =MAX(F18:LD18) -> 3786732.1 | F18: =F17 -> 0 | G18: =F18+G17 -> 0 | H18: =G18+H17 -> 0 | I18: =H18+I17 -> 0 | J18: =I18+J17 -> 0 | K18: =J18+K17 -> 0 | L18: =K18+L17 -> 0 | M18: =L18+M17 -> 0 | N18: =M18+N17 -> 0 | ... LD18: =LC18+LD17 -> 3786732.1

Sheet Finance - Revenue
A3: Sum of REVENUE RECOGNITION AMOUNT | B3: Column Labels
A4: Row Labels | B4: (blank) | C4: 45777 | D4: 45808 | E4: 45838 | F4: 45869 | G4: 45900 | H4: 45930 | I4: 45961 | J4: 45991 | K4: 46022 | M4: 31/01/2025 | N4: Grand Total
A5: (blank)
A6: 1. Panels | D6: 934730.12 | L6: 0 | N6: 934730.12
A7: 2. Inverters | D7: 238636.36 | L7: 0 | N7: 238636.36
A8: 3. Mounting Structures | B8: 0 | D8: 146262.48 | E8: 17110.039 | F8: 36831.45 | L8: 0 | N8: 200203.97
A9: 4. DC Equipment | D9: 215275.74 | E9: 145858.14 | L9: 0 | N9: 361133.87
A10: 5. Monitoring | C10: 19114.237 | D10: 15446.029 | E10: 21121.546 | G10: 0 | J10: 0 | L10: 0 | N10: 55681.813
A11: 6. AC Equipment | D11: 60645.38 | E11: 392327.04 | L11: 0 | N11: 452972.42
A12: 8. Product Add On
A13: 9. AC & DC installation | D13: 93136.029 | E13: 279408.09 | L13: 0 | N13: 372544.12
A14: 10. Site Logistics | D14: 9848.6121 | E14: 46125.179 | G14: 19292.33 | L14: 0 | N14: 75266.121
A15: 11. Due Dilligence | C15: 68571.707 | F15: 69752.407 | L15: 0 | N15: 138324.11
A16: 13. Engineering | F16: 149209.8 | L16: 0 | N16: 149209.8
A17: 14. General Expenses | C17: 3395.1001 | D17: 2813.3629 | E17: 83.836262 | F17: 1034.4225 | G17: 702.68928 | H17: 0 | I17: 0 | J17: 0 | K17: 0 | L17: 0 | N17: 8029.4111
A18: 15. Service Add On | E18: 800000 | H18: 0 | I18: 0 | J18: 0 | L18: 0 | N18: 800000
A19: 12. BDP Commission
A20: 7.BESS
A21: Grand Total | B21: 0 | C21: 91081.045 | D21: 1716794.1 | E21: 1702033.9 | F21: 256828.08 | G21: 19995.019 | H21: 0 | I21: 0 | J21: 0 | K21: 0 | L21: 0 | N21: 3786732.1

Sheet Finance - COS
A3: Sum of Actual Total | B3: Column Labels
A4: Row Labels | B4: (blank) | C4: 45777 | D4: 45808 | E4: 45838 | F4: 45869 | G4: 45900 | H4: 45930 | I4: 45961 | J4: 45991 | K4: 46022 | M4: 31/01/2025 | N4: Grand Total
A5: (blank)
A6: 1. Panels | D6: 778527.8 | N6: 778527.8
A7: 2. Inverters | D7: 206611.05 | N7: 206611.05
A8: 3. Mounting Structures | D8: 62801.6 | E8: 8290.42 | F8: -4020 | N8: 67072.02
A9: 4. DC Equipment | D9: 103855.44 | E9: 124366.33 | N9: 228221.77
A10: 5. Monitoring | C10: 13695 | D10: 10848.85 | E10: 11383.29 | G10: 8598.35 | J10: -8598.35 | N10: 35927.14
A11: 6. AC Equipment | D11: 26513.5 | E11: 173879.59 | N11: 200393.09
A12: 8. Product Add On | I12: 30678.5 | K12: 37055.8 | M12: 850.5 | N12: 68584.8
A13: 9. AC & DC installation | D13: 117637.5 | E13: 352912.5 | N13: 470550
A14: 10. Site Logistics | D14: 8167.9 | E14: 38253.7 | N14: 46421.6
A15: 11. Due Dilligence | C15: 16712.24 | F15: 16737.49 | N15: 33449.73
A16: 13. Engineering | F16: 47334.15 | N16: 47334.15
A17: 14. General Expenses | C17: 4000 | D17: 2980.88 | E17: 88.06 | F17: 3573.38 | G17: 270.92 | H17: 0 | I17: 0 | J17: 0 | K17: 0 | N17: 10913.24
A18: 15. Service Add On | E18: 568000 | H18: 16006.25 | I18: 5756.25 | J18: 6000 | L18: 0 | N18: 595762.5
A19: 12. BDP Commission
A20: 7.BESS
A21: Grand Total | C21: 34407.24 | D21: 1317944.5 | E21: 1277173.9 | F21: 63625.02 | G21: 8869.27 | H21: 16006.25 | I21: 36434.75 | J21: -2598.35 | K21: 37055.8 | L21: 0 | M21: 850.5 | N21: 2789768.9

Sheet Certificate - Financial Close
B2: Emergent Energy – Financial Close Completion Certificate | H2: FINANCIAL CLOSE CERTIFICATE
B4: Project Name: | C4: ='Project Plan'!E2 -> Kroonstad
B5: COO: | C5: Johannes Potgieter
B6: Programme Manager: | C6: Roedolph Venter
B7: HoPD: | C7: Natasha Watkins-Baker
B9: Date of Phase Completion: | F9: {=_xlfn.LET(_xlpm.w,$B$10:$B$54,_xlpm.r,$M$10:$M$54,_xlpm.v,IF(ISNUMBER(_xlpm.r),_xlpm.r,IFERROR(VALUE(SUBSTITUTE(_xlpm.r,"%",""))/100,0)),_xlpm.g,IFERROR(VALUE(LEFT(_xlpm.w,1)),0),_xlpm.bdOnly,(SUMPRODUCT((_xlpm.w="1.1")*(_xlpm.v>0))>0)*(SUMPRODUCT((_xlpm.w<>"1.1")*(_xlpm.v>0))=0),_xlpm.anyConstr,SUMPRODUCT((_xlpm.g>=2)*(_xlpm.g<=6)*(_xlpm.v>0))>0,_xlpm.anyQA,SUMPRODUCT((_xlpm.g=7)*(_xlpm.v>0))>0,_xlpm.anyHO,SUMPRODUCT((_xlpm.g=8)*(_xlpm.v>0))>0,_xlpm.anyPlan,SUMPRODUCT((_xlpm.g=1)*(_xlpm.v>0))>0,IF(_xlpm.bdOnly,"1. Financial Close",IF(_xlpm.anyConstr,"3. Construction",IF(_xlpm.anyQA,"4. QA",IF(_xlpm.anyHO,"5. Handover",IF(_xlpm.anyPlan,"2. Planning","1. Financial Close"))))))} -> 1. Financial Close | G9: {=_xlfn.LET(_xlpm.w,$B$10:$B$54,_xlpm.r,$N$10:$N$54,_xlpm.v,IF(ISNUMBER(_xlpm.r),_xlpm.r,IFERROR(VALUE(SUBSTITUTE(_xlpm.r,"%",""))/100,0)),_xlpm.g,IFERROR(VALUE(LEFT(_xlpm.w,1)),0),_xlpm.bdOnly,(SUMPRODUCT((_xlpm.w="1.1")*(_xlpm.v>0))>0)*(SUMPRODUCT((_xlpm.w<>"1.1")*(_xlpm.v>0))=0),_xlpm.anyConstr,SUMPRODUCT((_xlpm.g>=2)*(_xlpm.g<=6)*(_xlpm.v>0))>0,_xlpm.anyQA,SUMPRODUCT((_xlpm.g=7)*(_xlpm.v>0))>0,_xlpm.anyHO,SUMPRODUCT((_xlpm.g=8)*(_xlpm.v>0))>0,_xlpm.anyPlan,SUMPRODUCT((_xlpm.g=1)*(_xlpm.v>0))>0,IF(_xlpm.bdOnly,"1. Financial Close",IF(_xlpm.anyConstr,"3. Construction",IF(_xlpm.anyQA,"4. QA",IF(_xlpm.anyHO,"5. Handover",IF(_xlpm.anyPlan,"2. Planning","1. Financial Close"))))))} -> 1. Financial Close
B10: Phase Deliverables Checklist: (Y/N)
B11: Product Agreement | C11: NA
B12: EPC Agreement | C12: NA
B13: O&M Agreeement | C13: NA
B14: Cost Proposal | C14: Signed
B15: Deposit Received | C15: Yes
B16: Risks / Notes | C16: None
B18: Acknowledgement and Acceptance:
B19: Role | C19: Name | D19: Signature | E19: Date
B20: COO | C20: Johannes | D20: JTP | E20: 45953

Sheet Project Margins
A1: [capture project margins from costing sheet]
A3: Products | D3: 0.32
A4: Services | D4: 0.5
A5: Expenses | D5: 0.15
A6: Subcontractors | D6: 0.2

Sheet Equipment Quotes
B2: Equipment Quote and Budget comparision
B4: Description | D4: Budget | F4: Supplier 1 | H4: Variance | J4: Supplier 2 | L4: Variance | N4: Comments / Notes
F7: >Name< | J7: >Name<
B9: Inverters | D9: =SUM(D10:D11) -> #REF! | F9: =SUM(F10:F13) -> 0 | H9: =$D$9-F9 -> #REF! | J9: =SUM(J10:J13) -> 0 | L9: =$D$9-J9 -> #REF!
B10: Inverters | D10: =#REF! -> #REF!
B11: Optimizers | D11: =#REF! -> #REF!
B12: Warranty
B13: Delivery fee
F15: >Name< | J15: >Name<
B17: Mounting Structure | D17: =SUM(D18:D19) -> #REF! | F17: =SUM(F18:F20) -> 0 | H17: =$D$17- F17 -> #REF! | J17: =SUM(J18:J20) -> 0 | L17: =$D$17- J17 -> #REF!
B18: Mounting Structure | D18: =#REF! -> #REF!
B19: Delivery fee
F21: >Name< | J21: >Name<
B23: DC Cable | D23: =SUM(D24:D25) -> #REF! | F23: =SUM(F24:F25) -> 0 | H23: =$D$23- F23 -> #REF! | J23: =SUM(J24:J25) -> 0 | L23: =$D$23- J23 -> #REF!
B24: DC Cable | D24: =#REF! -> #REF!
B25: Delivery fee
F27: >Name< | J27: >Name<
B29: Monitoring system | D29: =SUM(D30:D32) -> #REF! | F29: =SUM(F30:F42) -> 0 | H29: =$D$29-F29 -> #REF! | J29: =SUM(J30:J32) -> 0 | L29: =$D$29-J29 -> #REF!
B30: =#REF! -> #REF! | D30: =#REF! -> #REF!
B31: =#REF! -> #REF! | D31: =#REF! -> #REF!
B32: Delivery fee
F34: >Name< | J34: >Name<
B36: Additional Scope | D36: =SUM(D37:D41) -> #REF! | F36: =SUM(F37:F41) -> 0 | H36: =$D$29-F36 -> #REF! | J36: =SUM(J37:J41) -> 0 | L36: =$D$29-J36 -> #REF!
B37: SCADA | D37: =#REF! -> #REF!
B38: Inverter cage
B39: Cat ladders
B40: Gen Integration
B41: Lifelines
B43: Totals | D43: =D36+D29+D23+D17+D9 -> #REF! | H43: =SUM(H7:H42) -> #REF! | L43: =SUM(L7:L42) -> #REF!
B47: All amounts are incl VAT

Sheet Installer Quotes
B2: Installer Quote and Budget comparision
B4: Description | D4: Budget | G4: Cosmic Sun | J4: Variance | L4: Matthews Group | O4: Variance
B6: AC Equipment | D6: =#REF! -> #REF! | E6: =D6/(1000*'Project Plan'!$E$3) -> #REF! | G6: 277892.91 | H6: =G6/('Project Plan'!$E$3*1000) -> 0.71072355 | J6: =D6-G6 -> #REF! | M6: =L6/('Project Plan'!$E$3*1000) -> 0 | O6: =D6-L6 -> #REF!
B7: DC Equipment | D7: =#REF! -> #REF! | E7: =D7/(1000*'Project Plan'!$E$3) -> #REF! | G7: 142158.25 | H7: =G7/('Project Plan'!$E$3*1000) -> 0.36357609 | J7: =D7-G7 -> #REF! | M7: =L7/('Project Plan'!$E$3*1000) -> 0 | O7: =D7-L7 -> #REF!
B8: AC Labour | D8: =#REF! -> #REF! | E8: =D8/(1000*'Project Plan'!$E$3) -> #REF! | G8: 96174 | H8: =G8/('Project Plan'!$E$3*1000) -> 0.24596931 | J8: =D8-G8 -> #REF! | M8: =L8/('Project Plan'!$E$3*1000) -> 0 | O8: =D8-L8 -> #REF!
B9: DC Labour | D9: =#REF! -> #REF! | E9: =D9/(1000*'Project Plan'!$E$3) -> #REF! | G9: 230160 | H9: =G9/('Project Plan'!$E$3*1000) -> 0.5886445 | J9: =D9-G9 -> #REF! | M9: =L9/('Project Plan'!$E$3*1000) -> 0 | O9: =D9-L9 -> #REF!
B10: Offloading | D10: =#REF! -> #REF! | G10: 0 | J10: =D10-G10 -> #REF! | O10: =D10-L10 -> #REF!
B11: Roof Access/Scaffolding | D11: =#REF! -> #REF! | G11: 29257.61 | J11: =D11-G11 -> #REF! | O11: =D11-L11 -> #REF!
B12: Storage | D12: =#REF! -> #REF! | J12: =D12-G12 -> #REF! | O12: =D12-L12 -> #REF!
B13: Telehandler | D13: =#REF! -> #REF!
B14: HSE | D14: 0
B15: Totals | D15: =SUM(D6:D13) -> #REF! | G15: =SUM(G6:G13) -> 775642.77 | J15: =SUM(J6:J14) -> #REF! | L15: =SUM(L6:L13) -> 0 | O15: =SUM(O6:O14) -> #REF!
B18: Description | D18: Budget | G18: >Installer Name 3< | J18: Variance | L18: >Installer Name 4< | O18: Variance
B20: AC installation | D20: =#REF! -> #REF! | E20: =D20/(1000*'Project Plan'!$E$3) -> #REF! | H20: =G20/(1000*'Project Plan'!$E$3) -> 0 | J20: =D20-G20 -> #REF! | M20: =L20/(1000*'Project Plan'!$E$3) -> 0 | O20: =D6-L20 -> #REF!
B21: AC equipment | D21: =#REF! -> #REF! | E21: =D21/(1000*'Project Plan'!$E$3) -> #REF! | J21: =D21-G21 -> #REF! | M21: =L21/(1000*'Project Plan'!$E$3) -> 0 | O21: =D7-L21 -> #REF!
B22: DC installation | D22: =#REF! -> #REF! | E22: =D22/(1000*'Project Plan'!$E$3) -> #REF! | H22: =G22/(1000*'Project Plan'!$E$3) -> 0 | J22: =D22-G22 -> #REF! | M22: =L22/(1000*'Project Plan'!$E$3) -> 0 | O22: =D8-L22 -> #REF!
B23: DC equipment | D23: =SUM(#REF!) -> #REF! | E23: =D23/(1000*'Project Plan'!$E$3) -> #REF! | J23: =D23-G23 -> #REF! | O23: =D9-L23 -> #REF!
B24: Storage | D24: =#REF! -> #REF! | J24: =D24-G24 -> #REF! | O24: =D10-L24 -> #REF!
B25: Panel lifting equipment | D25: =SUM(#REF!) -> #REF! | J25: =D25-G25 -> #REF! | O25: =D11-L25 -> #REF!
B26: Offloading | D26: =#REF! -> #REF! | J26: =D26-G26 -> #REF! | O26: =D12-L26 -> #REF!
B29: Totals | D29: =SUM(D20:D27) -> #REF! | G29: =SUM(G20:G27) -> 0 | J29: =SUM(J20:J28) -> #REF! | L29: =SUM(L20:L27) -> 0 | O29: =SUM(O20:O28) -> #REF!
B32: Budget Summary
B34: Budget | D34: =D15 -> #REF!
B35: =G4 -> Cosmic Sun | D35: =G15 -> 775642.77
B36: =L4 -> Matthews Group | D36: =L15 -> 0
B37: =G18 -> >Installer Name 3< | D37: =G29 -> 0
B38: =L18 -> >Installer Name 4< | D38: =L29 -> 0
B40: =IF(D40<D34,"Saving","Loss") -> #REF! | D40: =D34-MIN(D35:D38) -> #REF!
B42: All amounts are exc VAT

Sheet Decision Register
B1: =D15 -> Kroonstad | E1: Decision Register
B3: ID | C3: Decision Description | D3: Decision Impact | E3: Proposed Date | F3: Proposed By | G3: Status | H3: Approved By | I3: Date | J3: Results / Comments
B4: DEC001
B5: DEC002
B6: DEC003
B7: DEC004
B8: DEC005
B9: DEC006
B10: DEC007
B11: DEC008
B12: DEC009
B13: DEC010
D15: {='Project Plan'!E2:H2} -> Kroonstad | E15: 0 | F15: 0 | G15: 0
