Workbook
Name AC_Product: #REF!
Name Combiner_Product: #REF!
Name DC_Product: #REF!
Name DD_SERV: #REF!
Name ENGE_SERV: #REF!
Name Installation_AC: #REF!
Name Installation_Structural_DC: #REF!
Name Inverter_Capacity: #REF!
Name Inverter_Product: #REF!
Name Inverter_Supplier: #REF!
Name Module_Product: #REF!
Name Monitoring_Product: #REF!
Name Mounting_Product: #REF!
Name OFFLOAD: #REF!
Name Project_Size: 'Finance - Revenue'!Projectsize
Name Project_Size: Projectsize
Name Projectsize: #REF!
Name Projectsize: 'Project Margins'!$K$5
Name RMACC: #REF!
Name Security_Serv: #REF!
Name Security_Serv: #REF!
Name SSS: #REF!
Name SSS: #REF!
Name TRAVEL_EXP: #REF!
Name USD_ZAR: #REF!

Sheet Sheet1
A1: PROJECT PLAN
A2: # | B2: Project Milestone | C2: Planned Start Date | D2: Duration (Work Days) | E2: Planned End Date | F2: Actual Start Date | H2: Actual End Date | J2: Comments | L2: =C3 -> 43831 | M2: =L2+3 -> 43834 | N2: =M2+7 -> 43841 | O2: =N2+7 -> 43848 | P2: =O2+7 -> 43855 | Q2: =P2+6 -> 43861 | R2: =Q2+1 -> 43862 | S2: =R2+7 -> 43869 | T2: =S2+7 -> 43876 | U2: =T2+7 -> 43883 | V2: =U2+6 -> 43889 | W2: =V2+7 -> 43896 | X2: =W2+7 -> 43903 | Y2: =X2+7 -> 43910 | Z2: =Y2+7 -> 43917 | AA2: =Z2+3 -> 43920 | AB2: =AA2+4 -> 43924 | AC2: =AB2+7 -> 43931 | AD2: =AC2+7 -> 43938 | AE2: =AD2+7 -> 43945 | AF2: =AE2+6 -> 43951 | AG2: =AF2+2 -> 43953 | AH2: =AG2+7 -> 43960 | AI2: =AH2+7 -> 43967 | AJ2: =AI2+7 -> 43974 | AK2: =AJ2+7 -> 43981 | AL2: =AK2+1 -> 43982 | AM2: =AL2+6 -> 43988 | AN2: =AM2+7 -> 43995 | AO2: =AN2+7 -> 44002 | AP2: =AO2+7 -> 44009 | AQ2: =AP2+3 -> 44012 | AR2: =AQ2+4 -> 44016 | AS2: =AR2+7 -> 44023 | AT2: =AS2+7 -> 44030 | AU2: =AT2+7 -> 44037 | AV2: =AU2+6 -> 44043 | AW2: =AV2+1 -> 44044 | AX2: =AW2+7 -> 44051 | AY2: =AX2+7 -> 44058 | AZ2: =AY2+7 -> 44065 | BA2: =AZ2+7 -> 44072 | BB2: =BA2+2 -> 44074 | BC2: =BB2+5 -> 44079 | BD2: =BC2+7 -> 44086 | BE2: =BD2+7 -> 44093 | BF2: =BE2+7 -> 44100 | BG2: =BF2+4 -> 44104
A3: 1 | B3: Contract Signature | C3: 43831 | D3: 1 | E3: 43832 | F3: 43831 | G3: 1 | H3: 43832 | L3: =IF(AND($F3<(L$2+7),$F3>L$2),1, IF(AND($H3<L$2+7,$H3>L$2),3, IF(AND($F3<=L$2, $H3>=L$2), 2, "" ))) -> 3 | M3: =IF(AND($F3<(M$2+7),$F3>M$2),1, IF(AND($H3<M$2+7,$H3>M$2),3, IF(AND($F3<=M$2, $H3>=M$2), 2, "" ))) | N3: =IF(AND($F3<(N$2+7),$F3>N$2),1, IF(AND($H3<N$2+7,$H3>N$2),3, IF(AND($F3<=N$2, $H3>=N$2), 2, "" ))) | O3: =IF(AND($F3<(O$2+7),$F3>O$2),1, IF(AND($H3<O$2+7,$H3>O$2),3, IF(AND($F3<=O$2, $H3>=O$2), 2, "" ))) | P3: =IF(AND($F3<(P$2+7),$F3>P$2),1, IF(AND($H3<P$2+7,$H3>P$2),3, IF(AND($F3<=P$2, $H3>=P$2), 2, "" ))) | Q3: =IF(AND($F3<(Q$2+7),$F3>Q$2),1, IF(AND($H3<Q$2+7,$H3>Q$2),3, IF(AND($F3<=Q$2, $H3>=Q$2), 2, "" ))) | R3: =IF(AND($F3<(R$2+7),$F3>R$2),1, IF(AND($H3<R$2+7,$H3>R$2),3, IF(AND($F3<=R$2, $H3>=R$2), 2, "" ))) | S3: =IF(AND($F3<(S$2+7),$F3>S$2),1, IF(AND($H3<S$2+7,$H3>S$2),3, IF(AND($F3<=S$2, $H3>=S$2), 2, "" ))) | ... AQ3: =IF(AND($F3<(AQ$2+7),$F3>AQ$2),1, IF(AND($H3<AQ$2+7,$H3>AQ$2),3, IF(AND($F3<=AQ$2, $H3>=AQ$2), 2, "" )))
A4: A | B4: PAYMENT MILESTONE 1: DEPOSIT | C4: 43832 | D4: 1 | E4: 43833 | F4: 43832 | G4: 1 | H4: 43833 | L4: =IF(AND($F4<(L$2+7),$F4>L$2),1, IF(AND($H4<L$2+7,$H4>L$2),3, IF(AND($F4<=L$2, $H4>=L$2), 2, "" ))) -> 1 | M4: =IF(AND($F4<(M$2+7),$F4>M$2),1, IF(AND($H4<M$2+7,$H4>M$2),3, IF(AND($F4<=M$2, $H4>=M$2), 2, "" ))) | N4: =IF(AND($F4<(N$2+7),$F4>N$2),1, IF(AND($H4<N$2+7,$H4>N$2),3, IF(AND($F4<=N$2, $H4>=N$2), 2, "" ))) | O4: =IF(AND($F4<(O$2+7),$F4>O$2),1, IF(AND($H4<O$2+7,$H4>O$2),3, IF(AND($F4<=O$2, $H4>=O$2), 2, "" ))) | P4: =IF(AND($F4<(P$2+7),$F4>P$2),1, IF(AND($H4<P$2+7,$H4>P$2),3, IF(AND($F4<=P$2, $H4>=P$2), 2, "" ))) | Q4: =IF(AND($F4<(Q$2+7),$F4>Q$2),1, IF(AND($H4<Q$2+7,$H4>Q$2),3, IF(AND($F4<=Q$2, $H4>=Q$2), 2, "" ))) | R4: =IF(AND($F4<(R$2+7),$F4>R$2),1, IF(AND($H4<R$2+7,$H4>R$2),3, IF(AND($F4<=R$2, $H4>=R$2), 2, "" ))) | S4: =IF(AND($F4<(S$2+7),$F4>S$2),1, IF(AND($H4<S$2+7,$H4>S$2),3, IF(AND($F4<=S$2, $H4>=S$2), 2, "" ))) | ... AQ4: =IF(AND($F4<(AQ$2+7),$F4>AQ$2),1, IF(AND($H4<AQ$2+7,$H4>AQ$2),3, IF(AND($F4<=AQ$2, $H4>=AQ$2), 2, "" )))
A5: 2 | B5: Structural and Electrical Due Diligences | C5: 43833 | D5: 5 | E5: 43840 | F5: 43833 | G5: 5 | H5: 43840 | L5: =IF(AND($F5<(L$2+7),$F5>L$2),1, IF(AND($H5<L$2+7,$H5>L$2),3, IF(AND($F5<=L$2, $H5>=L$2), 2, "" ))) -> 1 | M5: =IF(AND($F5<(M$2+7),$F5>M$2),1, IF(AND($H5<M$2+7,$H5>M$2),3, IF(AND($F5<=M$2, $H5>=M$2), 2, "" ))) -> 3 | N5: =IF(AND($F5<(N$2+7),$F5>N$2),1, IF(AND($H5<N$2+7,$H5>N$2),3, IF(AND($F5<=N$2, $H5>=N$2), 2, "" ))) | O5: =IF(AND($F5<(O$2+7),$F5>O$2),1, IF(AND($H5<O$2+7,$H5>O$2),3, IF(AND($F5<=O$2, $H5>=O$2), 2, "" ))) | P5: =IF(AND($F5<(P$2+7),$F5>P$2),1, IF(AND($H5<P$2+7,$H5>P$2),3, IF(AND($F5<=P$2, $H5>=P$2), 2, "" ))) | Q5: =IF(AND($F5<(Q$2+7),$F5>Q$2),1, IF(AND($H5<Q$2+7,$H5>Q$2),3, IF(AND($F5<=Q$2, $H5>=Q$2), 2, "" ))) | R5: =IF(AND($F5<(R$2+7),$F5>R$2),1, IF(AND($H5<R$2+7,$H5>R$2),3, IF(AND($F5<=R$2, $H5>=R$2), 2, "" ))) | S5: =IF(AND($F5<(S$2+7),$F5>S$2),1, IF(AND($H5<S$2+7,$H5>S$2),3, IF(AND($F5<=S$2, $H5>=S$2), 2, "" ))) | ... AQ5: =IF(AND($F5<(AQ$2+7),$F5>AQ$2),1, IF(AND($H5<AQ$2+7,$H5>AQ$2),3, IF(AND($F5<=AQ$2, $H5>=AQ$2), 2, "" )))
A6: 3 | B6: Design Confirmation | C6: 43841 | D6: 2 | E6: 43844 | F6: 43841 | G6: 2 | H6: 43844 | L6: =IF(AND($F6<(L$2+7),$F6>L$2),1, IF(AND($H6<L$2+7,$H6>L$2),3, IF(AND($F6<=L$2, $H6>=L$2), 2, "" ))) | M6: =IF(AND($F6<(M$2+7),$F6>M$2),1, IF(AND($H6<M$2+7,$H6>M$2),3, IF(AND($F6<=M$2, $H6>=M$2), 2, "" ))) | N6: =IF(AND($F6<(N$2+7),$F6>N$2),1, IF(AND($H6<N$2+7,$H6>N$2),3, IF(AND($F6<=N$2, $H6>=N$2), 2, "" ))) -> 3 | O6: =IF(AND($F6<(O$2+7),$F6>O$2),1, IF(AND($H6<O$2+7,$H6>O$2),3, IF(AND($F6<=O$2, $H6>=O$2), 2, "" ))) | P6: =IF(AND($F6<(P$2+7),$F6>P$2),1, IF(AND($H6<P$2+7,$H6>P$2),3, IF(AND($F6<=P$2, $H6>=P$2), 2, "" ))) | Q6: =IF(AND($F6<(Q$2+7),$F6>Q$2),1, IF(AND($H6<Q$2+7,$H6>Q$2),3, IF(AND($F6<=Q$2, $H6>=Q$2), 2, "" ))) | R6: =IF(AND($F6<(R$2+7),$F6>R$2),1, IF(AND($H6<R$2+7,$H6>R$2),3, IF(AND($F6<=R$2, $H6>=R$2), 2, "" ))) | S6: =IF(AND($F6<(S$2+7),$F6>S$2),1, IF(AND($H6<S$2+7,$H6>S$2),3, IF(AND($F6<=S$2, $H6>=S$2), 2, "" ))) | ... AQ6: =IF(AND($F6<(AQ$2+7),$F6>AQ$2),1, IF(AND($H6<AQ$2+7,$H6>AQ$2),3, IF(AND($F6<=AQ$2, $H6>=AQ$2), 2, "" )))
A7: 4 | B7: Equipment Procurement | C7: 43833 | E7: 43949 | F7: 43833 | H7: 43949 | L7: =IF(AND($F7<(L$2+7),$F7>L$2),1, IF(AND($H7<L$2+7,$H7>L$2),3, IF(AND($F7<=L$2, $H7>=L$2), 2, "" ))) -> 1 | M7: =IF(AND($F7<(M$2+7),$F7>M$2),1, IF(AND($H7<M$2+7,$H7>M$2),3, IF(AND($F7<=M$2, $H7>=M$2), 2, "" ))) -> 2 | N7: =IF(AND($F7<(N$2+7),$F7>N$2),1, IF(AND($H7<N$2+7,$H7>N$2),3, IF(AND($F7<=N$2, $H7>=N$2), 2, "" ))) -> 2 | O7: =IF(AND($F7<(O$2+7),$F7>O$2),1, IF(AND($H7<O$2+7,$H7>O$2),3, IF(AND($F7<=O$2, $H7>=O$2), 2, "" ))) -> 2 | P7: =IF(AND($F7<(P$2+7),$F7>P$2),1, IF(AND($H7<P$2+7,$H7>P$2),3, IF(AND($F7<=P$2, $H7>=P$2), 2, "" ))) -> 2 | Q7: =IF(AND($F7<(Q$2+7),$F7>Q$2),1, IF(AND($H7<Q$2+7,$H7>Q$2),3, IF(AND($F7<=Q$2, $H7>=Q$2), 2, "" ))) -> 2 | R7: =IF(AND($F7<(R$2+7),$F7>R$2),1, IF(AND($H7<R$2+7,$H7>R$2),3, IF(AND($F7<=R$2, $H7>=R$2), 2, "" ))) -> 2 | S7: =IF(AND($F7<(S$2+7),$F7>S$2),1, IF(AND($H7<S$2+7,$H7>S$2),3, IF(AND($F7<=S$2, $H7>=S$2), 2, "" ))) -> 2 | ... AQ7: =IF(AND($F7<(AQ$2+7),$F7>AQ$2),1, IF(AND($H7<AQ$2+7,$H7>AQ$2),3, IF(AND($F7<=AQ$2, $H7>=AQ$2), 2, "" )))
B8: Panel Procurement | C8: 43833 | D8: 5 | E8: 43840 | F8: 43833 | G8: 5 | H8: 43840 | L8: =IF(AND($F8<(L$2+7),$F8>L$2),1, IF(AND($H8<L$2+7,$H8>L$2),3, IF(AND($F8<=L$2, $H8>=L$2), 2, "" ))) -> 1 | M8: =IF(AND($F8<(M$2+7),$F8>M$2),1, IF(AND($H8<M$2+7,$H8>M$2),3, IF(AND($F8<=M$2, $H8>=M$2), 2, "" ))) -> 3 | N8: =IF(AND($F8<(N$2+7),$F8>N$2),1, IF(AND($H8<N$2+7,$H8>N$2),3, IF(AND($F8<=N$2, $H8>=N$2), 2, "" ))) | O8: =IF(AND($F8<(O$2+7),$F8>O$2),1, IF(AND($H8<O$2+7,$H8>O$2),3, IF(AND($F8<=O$2, $H8>=O$2), 2, "" ))) | P8: =IF(AND($F8<(P$2+7),$F8>P$2),1, IF(AND($H8<P$2+7,$H8>P$2),3, IF(AND($F8<=P$2, $H8>=P$2), 2, "" ))) | Q8: =IF(AND($F8<(Q$2+7),$F8>Q$2),1, IF(AND($H8<Q$2+7,$H8>Q$2),3, IF(AND($F8<=Q$2, $H8>=Q$2), 2, "" ))) | R8: =IF(AND($F8<(R$2+7),$F8>R$2),1, IF(AND($H8<R$2+7,$H8>R$2),3, IF(AND($F8<=R$2, $H8>=R$2), 2, "" ))) | S8: =IF(AND($F8<(S$2+7),$F8>S$2),1, IF(AND($H8<S$2+7,$H8>S$2),3, IF(AND($F8<=S$2, $H8>=S$2), 2, "" ))) | ... AQ8: =IF(AND($F8<(AQ$2+7),$F8>AQ$2),1, IF(AND($H8<AQ$2+7,$H8>AQ$2),3, IF(AND($F8<=AQ$2, $H8>=AQ$2), 2, "" )))
B9: Inverter Procurement | C9: 43941 | D9: 5 | E9: 43949 | F9: 43941 | G9: 5 | H9: 43949 | L9: =IF(AND($F9<(L$2+7),$F9>L$2),1, IF(AND($H9<L$2+7,$H9>L$2),3, IF(AND($F9<=L$2, $H9>=L$2), 2, "" ))) | M9: =IF(AND($F9<(M$2+7),$F9>M$2),1, IF(AND($H9<M$2+7,$H9>M$2),3, IF(AND($F9<=M$2, $H9>=M$2), 2, "" ))) | N9: =IF(AND($F9<(N$2+7),$F9>N$2),1, IF(AND($H9<N$2+7,$H9>N$2),3, IF(AND($F9<=N$2, $H9>=N$2), 2, "" ))) | O9: =IF(AND($F9<(O$2+7),$F9>O$2),1, IF(AND($H9<O$2+7,$H9>O$2),3, IF(AND($F9<=O$2, $H9>=O$2), 2, "" ))) | P9: =IF(AND($F9<(P$2+7),$F9>P$2),1, IF(AND($H9<P$2+7,$H9>P$2),3, IF(AND($F9<=P$2, $H9>=P$2), 2, "" ))) | Q9: =IF(AND($F9<(Q$2+7),$F9>Q$2),1, IF(AND($H9<Q$2+7,$H9>Q$2),3, IF(AND($F9<=Q$2, $H9>=Q$2), 2, "" ))) | R9: =IF(AND($F9<(R$2+7),$F9>R$2),1, IF(AND($H9<R$2+7,$H9>R$2),3, IF(AND($F9<=R$2, $H9>=R$2), 2, "" ))) | S9: =IF(AND($F9<(S$2+7),$F9>S$2),1, IF(AND($H9<S$2+7,$H9>S$2),3, IF(AND($F9<=S$2, $H9>=S$2), 2, "" ))) | ... AQ9: =IF(AND($F9<(AQ$2+7),$F9>AQ$2),1, IF(AND($H9<AQ$2+7,$H9>AQ$2),3, IF(AND($F9<=AQ$2, $H9>=AQ$2), 2, "" )))
B10: Mounting Structure Procurement | C10: 43941 | D10: 5 | E10: 43949 | F10: 43941 | G10: 5 | H10: 43949 | L10: =IF(AND($F10<(L$2+7),$F10>L$2),1, IF(AND($H10<L$2+7,$H10>L$2),3, IF(AND($F10<=L$2, $H10>=L$2), 2, "" ))) | M10: =IF(AND($F10<(M$2+7),$F10>M$2),1, IF(AND($H10<M$2+7,$H10>M$2),3, IF(AND($F10<=M$2, $H10>=M$2), 2, "" ))) | N10: =IF(AND($F10<(N$2+7),$F10>N$2),1, IF(AND($H10<N$2+7,$H10>N$2),3, IF(AND($F10<=N$2, $H10>=N$2), 2, "" ))) | O10: =IF(AND($F10<(O$2+7),$F10>O$2),1, IF(AND($H10<O$2+7,$H10>O$2),3, IF(AND($F10<=O$2, $H10>=O$2), 2, "" ))) | P10: =IF(AND($F10<(P$2+7),$F10>P$2),1, IF(AND($H10<P$2+7,$H10>P$2),3, IF(AND($F10<=P$2, $H10>=P$2), 2, "" ))) | Q10: =IF(AND($F10<(Q$2+7),$F10>Q$2),1, IF(AND($H10<Q$2+7,$H10>Q$2),3, IF(AND($F10<=Q$2, $H10>=Q$2), 2, "" ))) | R10: =IF(AND($F10<(R$2+7),$F10>R$2),1, IF(AND($H10<R$2+7,$H10>R$2),3, IF(AND($F10<=R$2, $H10>=R$2), 2, "" ))) | S10: =IF(AND($F10<(S$2+7),$F10>S$2),1, IF(AND($H10<S$2+7,$H10>S$2),3, IF(AND($F10<=S$2, $H10>=S$2), 2, "" ))) | ... AQ10: =IF(AND($F10<(AQ$2+7),$F10>AQ$2),1, IF(AND($H10<AQ$2+7,$H10>AQ$2),3, IF(AND($F10<=AQ$2, $H10>=AQ$2), 2, "" )))
B11: BOS Procurement | C11: 43941 | D11: 5 | E11: 43949 | F11: 43941 | G11: 5 | H11: 43949 | L11: =IF(AND($F11<(L$2+7),$F11>L$2),1, IF(AND($H11<L$2+7,$H11>L$2),3, IF(AND($F11<=L$2, $H11>=L$2), 2, "" ))) | M11: =IF(AND($F11<(M$2+7),$F11>M$2),1, IF(AND($H11<M$2+7,$H11>M$2),3, IF(AND($F11<=M$2, $H11>=M$2), 2, "" ))) | N11: =IF(AND($F11<(N$2+7),$F11>N$2),1, IF(AND($H11<N$2+7,$H11>N$2),3, IF(AND($F11<=N$2, $H11>=N$2), 2, "" ))) | O11: =IF(AND($F11<(O$2+7),$F11>O$2),1, IF(AND($H11<O$2+7,$H11>O$2),3, IF(AND($F11<=O$2, $H11>=O$2), 2, "" ))) | P11: =IF(AND($F11<(P$2+7),$F11>P$2),1, IF(AND($H11<P$2+7,$H11>P$2),3, IF(AND($F11<=P$2, $H11>=P$2), 2, "" ))) | Q11: =IF(AND($F11<(Q$2+7),$F11>Q$2),1, IF(AND($H11<Q$2+7,$H11>Q$2),3, IF(AND($F11<=Q$2, $H11>=Q$2), 2, "" ))) | R11: =IF(AND($F11<(R$2+7),$F11>R$2),1, IF(AND($H11<R$2+7,$H11>R$2),3, IF(AND($F11<=R$2, $H11>=R$2), 2, "" ))) | S11: =IF(AND($F11<(S$2+7),$F11>S$2),1, IF(AND($H11<S$2+7,$H11>S$2),3, IF(AND($F11<=S$2, $H11>=S$2), 2, "" ))) | ... AQ11: =IF(AND($F11<(AQ$2+7),$F11>AQ$2),1, IF(AND($H11<AQ$2+7,$H11>AQ$2),3, IF(AND($F11<=AQ$2, $H11>=AQ$2), 2, "" )))
A12: 5 | B12: Internal Project Kick off | C12: 43936 | D12: 5 | E12: 43943 | F12: 43936 | G12: 5 | H12: 43943
A13: 6 | B13: Client Project Kick-off | C13: 43963 | D13: 5 | E13: 43970 | F13: 43963 | G13: 5 | H13: 43970 | L13: =IF(AND($F13<(L$2+7),$F13>L$2),1, IF(AND($H13<L$2+7,$H13>L$2),3, IF(AND($F13<=L$2, $H13>=L$2), 2, "" ))) | M13: =IF(AND($F13<(M$2+7),$F13>M$2),1, IF(AND($H13<M$2+7,$H13>M$2),3, IF(AND($F13<=M$2, $H13>=M$2), 2, "" ))) | N13: =IF(AND($F13<(N$2+7),$F13>N$2),1, IF(AND($H13<N$2+7,$H13>N$2),3, IF(AND($F13<=N$2, $H13>=N$2), 2, "" ))) | O13: =IF(AND($F13<(O$2+7),$F13>O$2),1, IF(AND($H13<O$2+7,$H13>O$2),3, IF(AND($F13<=O$2, $H13>=O$2), 2, "" ))) | P13: =IF(AND($F13<(P$2+7),$F13>P$2),1, IF(AND($H13<P$2+7,$H13>P$2),3, IF(AND($F13<=P$2, $H13>=P$2), 2, "" ))) | Q13: =IF(AND($F13<(Q$2+7),$F13>Q$2),1, IF(AND($H13<Q$2+7,$H13>Q$2),3, IF(AND($F13<=Q$2, $H13>=Q$2), 2, "" ))) | R13: =IF(AND($F13<(R$2+7),$F13>R$2),1, IF(AND($H13<R$2+7,$H13>R$2),3, IF(AND($F13<=R$2, $H13>=R$2), 2, "" ))) | S13: =IF(AND($F13<(S$2+7),$F13>S$2),1, IF(AND($H13<S$2+7,$H13>S$2),3, IF(AND($F13<=S$2, $H13>=S$2), 2, "" ))) | ... AQ13: =IF(AND($F13<(AQ$2+7),$F13>AQ$2),1, IF(AND($H13<AQ$2+7,$H13>AQ$2),3, IF(AND($F13<=AQ$2, $H13>=AQ$2), 2, "" )))
A14: 7 | B14: Equipment Delivery | C14: 43983 | D14: 9 | E14: 43994 | F14: 43983 | G14: 9 | H14: 43994 | L14: =IF(AND($F14<(L$2+7),$F14>L$2),1, IF(AND($H14<L$2+7,$H14>L$2),3, IF(AND($F14<=L$2, $H14>=L$2), 2, "" ))) | M14: =IF(AND($F14<(M$2+7),$F14>M$2),1, IF(AND($H14<M$2+7,$H14>M$2),3, IF(AND($F14<=M$2, $H14>=M$2), 2, "" ))) | N14: =IF(AND($F14<(N$2+7),$F14>N$2),1, IF(AND($H14<N$2+7,$H14>N$2),3, IF(AND($F14<=N$2, $H14>=N$2), 2, "" ))) | O14: =IF(AND($F14<(O$2+7),$F14>O$2),1, IF(AND($H14<O$2+7,$H14>O$2),3, IF(AND($F14<=O$2, $H14>=O$2), 2, "" ))) | P14: =IF(AND($F14<(P$2+7),$F14>P$2),1, IF(AND($H14<P$2+7,$H14>P$2),3, IF(AND($F14<=P$2, $H14>=P$2), 2, "" ))) | Q14: =IF(AND($F14<(Q$2+7),$F14>Q$2),1, IF(AND($H14<Q$2+7,$H14>Q$2),3, IF(AND($F14<=Q$2, $H14>=Q$2), 2, "" ))) | R14: =IF(AND($F14<(R$2+7),$F14>R$2),1, IF(AND($H14<R$2+7,$H14>R$2),3, IF(AND($F14<=R$2, $H14>=R$2), 2, "" ))) | S14: =IF(AND($F14<(S$2+7),$F14>S$2),1, IF(AND($H14<S$2+7,$H14>S$2),3, IF(AND($F14<=S$2, $H14>=S$2), 2, "" ))) | ... AQ14: =IF(AND($F14<(AQ$2+7),$F14>AQ$2),1, IF(AND($H14<AQ$2+7,$H14>AQ$2),3, IF(AND($F14<=AQ$2, $H14>=AQ$2), 2, "" )))
B15: Mounting Structure Delivery | C15: 43983 | D15: 2 | E15: 43985 | F15: 43983 | G15: 2 | H15: 43985
B16: Panel Delivery | C16: 43990 | D16: 2 | E16: 43992 | F16: 43990 | G16: 2 | H16: 43992 | L16: =IF(AND($F16<(L$2+7),$F16>L$2),1, IF(AND($H16<L$2+7,$H16>L$2),3, IF(AND($F16<=L$2, $H16>=L$2), 2, "" ))) | M16: =IF(AND($F16<(M$2+7),$F16>M$2),1, IF(AND($H16<M$2+7,$H16>M$2),3, IF(AND($F16<=M$2, $H16>=M$2), 2, "" ))) | N16: =IF(AND($F16<(N$2+7),$F16>N$2),1, IF(AND($H16<N$2+7,$H16>N$2),3, IF(AND($F16<=N$2, $H16>=N$2), 2, "" ))) | O16: =IF(AND($F16<(O$2+7),$F16>O$2),1, IF(AND($H16<O$2+7,$H16>O$2),3, IF(AND($F16<=O$2, $H16>=O$2), 2, "" ))) | P16: =IF(AND($F16<(P$2+7),$F16>P$2),1, IF(AND($H16<P$2+7,$H16>P$2),3, IF(AND($F16<=P$2, $H16>=P$2), 2, "" ))) | Q16: =IF(AND($F16<(Q$2+7),$F16>Q$2),1, IF(AND($H16<Q$2+7,$H16>Q$2),3, IF(AND($F16<=Q$2, $H16>=Q$2), 2, "" ))) | R16: =IF(AND($F16<(R$2+7),$F16>R$2),1, IF(AND($H16<R$2+7,$H16>R$2),3, IF(AND($F16<=R$2, $H16>=R$2), 2, "" ))) | S16: =IF(AND($F16<(S$2+7),$F16>S$2),1, IF(AND($H16<S$2+7,$H16>S$2),3, IF(AND($F16<=S$2, $H16>=S$2), 2, "" ))) | ... AQ16: =IF(AND($F16<(AQ$2+7),$F16>AQ$2),1, IF(AND($H16<AQ$2+7,$H16>AQ$2),3, IF(AND($F16<=AQ$2, $H16>=AQ$2), 2, "" )))
B17: Generator Delivery | C17: 43983 | D17: 2 | E17: 43985 | F17: 43983 | G17: 2 | H17: 43985
A18: B | B18: PAYMENT MILESTONE 2: DELIVERY OF PV PANELS | C18: 43992 | D18: 2 | E18: 43994 | F18: 43992 | G18: 2 | H18: 43994
B19: Inverter Delivery | C19: 43983 | D19: 2 | E19: 43985 | F19: 43983 | G19: 2 | H19: 43985 | L19: =IF(AND($F19<(L$2+7),$F19>L$2),1, IF(AND($H19<L$2+7,$H19>L$2),3, IF(AND($F19<=L$2, $H19>=L$2), 2, "" ))) | M19: =IF(AND($F19<(M$2+7),$F19>M$2),1, IF(AND($H19<M$2+7,$H19>M$2),3, IF(AND($F19<=M$2, $H19>=M$2), 2, "" ))) | N19: =IF(AND($F19<(N$2+7),$F19>N$2),1, IF(AND($H19<N$2+7,$H19>N$2),3, IF(AND($F19<=N$2, $H19>=N$2), 2, "" ))) | O19: =IF(AND($F19<(O$2+7),$F19>O$2),1, IF(AND($H19<O$2+7,$H19>O$2),3, IF(AND($F19<=O$2, $H19>=O$2), 2, "" ))) | P19: =IF(AND($F19<(P$2+7),$F19>P$2),1, IF(AND($H19<P$2+7,$H19>P$2),3, IF(AND($F19<=P$2, $H19>=P$2), 2, "" ))) | Q19: =IF(AND($F19<(Q$2+7),$F19>Q$2),1, IF(AND($H19<Q$2+7,$H19>Q$2),3, IF(AND($F19<=Q$2, $H19>=Q$2), 2, "" ))) | R19: =IF(AND($F19<(R$2+7),$F19>R$2),1, IF(AND($H19<R$2+7,$H19>R$2),3, IF(AND($F19<=R$2, $H19>=R$2), 2, "" ))) | S19: =IF(AND($F19<(S$2+7),$F19>S$2),1, IF(AND($H19<S$2+7,$H19>S$2),3, IF(AND($F19<=S$2, $H19>=S$2), 2, "" ))) | ... AQ19: =IF(AND($F19<(AQ$2+7),$F19>AQ$2),1, IF(AND($H19<AQ$2+7,$H19>AQ$2),3, IF(AND($F19<=AQ$2, $H19>=AQ$2), 2, "" )))
B20: BOS Delivery | C20: 43983 | D20: 1 | E20: 43984 | F20: 43983 | G20: 1 | H20: 43984 | L20: =IF(AND($F20<(L$2+7),$F20>L$2),1, IF(AND($H20<L$2+7,$H20>L$2),3, IF(AND($F20<=L$2, $H20>=L$2), 2, "" ))) | M20: =IF(AND($F20<(M$2+7),$F20>M$2),1, IF(AND($H20<M$2+7,$H20>M$2),3, IF(AND($F20<=M$2, $H20>=M$2), 2, "" ))) | N20: =IF(AND($F20<(N$2+7),$F20>N$2),1, IF(AND($H20<N$2+7,$H20>N$2),3, IF(AND($F20<=N$2, $H20>=N$2), 2, "" ))) | O20: =IF(AND($F20<(O$2+7),$F20>O$2),1, IF(AND($H20<O$2+7,$H20>O$2),3, IF(AND($F20<=O$2, $H20>=O$2), 2, "" ))) | P20: =IF(AND($F20<(P$2+7),$F20>P$2),1, IF(AND($H20<P$2+7,$H20>P$2),3, IF(AND($F20<=P$2, $H20>=P$2), 2, "" ))) | Q20: =IF(AND($F20<(Q$2+7),$F20>Q$2),1, IF(AND($H20<Q$2+7,$H20>Q$2),3, IF(AND($F20<=Q$2, $H20>=Q$2), 2, "" ))) | R20: =IF(AND($F20<(R$2+7),$F20>R$2),1, IF(AND($H20<R$2+7,$H20>R$2),3, IF(AND($F20<=R$2, $H20>=R$2), 2, "" ))) | S20: =IF(AND($F20<(S$2+7),$F20>S$2),1, IF(AND($H20<S$2+7,$H20>S$2),3, IF(AND($F20<=S$2, $H20>=S$2), 2, "" ))) | ... AQ20: =IF(AND($F20<(AQ$2+7),$F20>AQ$2),1, IF(AND($H20<AQ$2+7,$H20>AQ$2),3, IF(AND($F20<=AQ$2, $H20>=AQ$2), 2, "" )))
A21: C | B21: PAYMENT MILESTONE 3: DELIVERY OF INVERTERS AND BOS | C21: 43985 | D21: 2 | E21: 43987 | F21: 43985 | G21: 2 | H21: 43987
A22: 8 | B22: Installation | C22: 43990 | D22: 22 | E22: 44012 | F22: 43990 | G22: 22 | H22: 44012 | L22: =IF(AND($F22<(L$2+7),$F22>L$2),1, IF(AND($H22<L$2+7,$H22>L$2),3, IF(AND($F22<=L$2, $H22>=L$2), 2, "" ))) | M22: =IF(AND($F22<(M$2+7),$F22>M$2),1, IF(AND($H22<M$2+7,$H22>M$2),3, IF(AND($F22<=M$2, $H22>=M$2), 2, "" ))) | N22: =IF(AND($F22<(N$2+7),$F22>N$2),1, IF(AND($H22<N$2+7,$H22>N$2),3, IF(AND($F22<=N$2, $H22>=N$2), 2, "" ))) | O22: =IF(AND($F22<(O$2+7),$F22>O$2),1, IF(AND($H22<O$2+7,$H22>O$2),3, IF(AND($F22<=O$2, $H22>=O$2), 2, "" ))) | P22: =IF(AND($F22<(P$2+7),$F22>P$2),1, IF(AND($H22<P$2+7,$H22>P$2),3, IF(AND($F22<=P$2, $H22>=P$2), 2, "" ))) | Q22: =IF(AND($F22<(Q$2+7),$F22>Q$2),1, IF(AND($H22<Q$2+7,$H22>Q$2),3, IF(AND($F22<=Q$2, $H22>=Q$2), 2, "" ))) | R22: =IF(AND($F22<(R$2+7),$F22>R$2),1, IF(AND($H22<R$2+7,$H22>R$2),3, IF(AND($F22<=R$2, $H22>=R$2), 2, "" ))) | S22: =IF(AND($F22<(S$2+7),$F22>S$2),1, IF(AND($H22<S$2+7,$H22>S$2),3, IF(AND($F22<=S$2, $H22>=S$2), 2, "" ))) | ... AQ22: =IF(AND($F22<(AQ$2+7),$F22>AQ$2),1, IF(AND($H22<AQ$2+7,$H22>AQ$2),3, IF(AND($F22<=AQ$2, $H22>=AQ$2), 2, "" ))) -> 2
B23: Site Establishment | C23: 43990 | D23: 1 | E23: 43991 | F23: 43990 | G23: 1 | H23: 43991 | J23: Installation placed on hold due to Covid-19 case | L23: =IF(AND($F23<(L$2+7),$F23>L$2),1, IF(AND($H23<L$2+7,$H23>L$2),3, IF(AND($F23<=L$2, $H23>=L$2), 2, "" ))) | M23: =IF(AND($F23<(M$2+7),$F23>M$2),1, IF(AND($H23<M$2+7,$H23>M$2),3, IF(AND($F23<=M$2, $H23>=M$2), 2, "" ))) | N23: =IF(AND($F23<(N$2+7),$F23>N$2),1, IF(AND($H23<N$2+7,$H23>N$2),3, IF(AND($F23<=N$2, $H23>=N$2), 2, "" ))) | O23: =IF(AND($F23<(O$2+7),$F23>O$2),1, IF(AND($H23<O$2+7,$H23>O$2),3, IF(AND($F23<=O$2, $H23>=O$2), 2, "" ))) | P23: =IF(AND($F23<(P$2+7),$F23>P$2),1, IF(AND($H23<P$2+7,$H23>P$2),3, IF(AND($F23<=P$2, $H23>=P$2), 2, "" ))) | Q23: =IF(AND($F23<(Q$2+7),$F23>Q$2),1, IF(AND($H23<Q$2+7,$H23>Q$2),3, IF(AND($F23<=Q$2, $H23>=Q$2), 2, "" ))) | R23: =IF(AND($F23<(R$2+7),$F23>R$2),1, IF(AND($H23<R$2+7,$H23>R$2),3, IF(AND($F23<=R$2, $H23>=R$2), 2, "" ))) | S23: =IF(AND($F23<(S$2+7),$F23>S$2),1, IF(AND($H23<S$2+7,$H23>S$2),3, IF(AND($F23<=S$2, $H23>=S$2), 2, "" ))) | ... AQ23: =IF(AND($F23<(AQ$2+7),$F23>AQ$2),1, IF(AND($H23<AQ$2+7,$H23>AQ$2),3, IF(AND($F23<=AQ$2, $H23>=AQ$2), 2, "" )))
A24: 9 | B24: DC Works | C24: 43991 | D24: 16 | E24: 44012 | F24: 43991 | G24: 16 | H24: 44012 | L24: =IF(AND($F24<(L$2+7),$F24>L$2),1, IF(AND($H24<L$2+7,$H24>L$2),3, IF(AND($F24<=L$2, $H24>=L$2), 2, "" ))) | M24: =IF(AND($F24<(M$2+7),$F24>M$2),1, IF(AND($H24<M$2+7,$H24>M$2),3, IF(AND($F24<=M$2, $H24>=M$2), 2, "" ))) | N24: =IF(AND($F24<(N$2+7),$F24>N$2),1, IF(AND($H24<N$2+7,$H24>N$2),3, IF(AND($F24<=N$2, $H24>=N$2), 2, "" ))) | O24: =IF(AND($F24<(O$2+7),$F24>O$2),1, IF(AND($H24<O$2+7,$H24>O$2),3, IF(AND($F24<=O$2, $H24>=O$2), 2, "" ))) | P24: =IF(AND($F24<(P$2+7),$F24>P$2),1, IF(AND($H24<P$2+7,$H24>P$2),3, IF(AND($F24<=P$2, $H24>=P$2), 2, "" ))) | Q24: =IF(AND($F24<(Q$2+7),$F24>Q$2),1, IF(AND($H24<Q$2+7,$H24>Q$2),3, IF(AND($F24<=Q$2, $H24>=Q$2), 2, "" ))) | R24: =IF(AND($F24<(R$2+7),$F24>R$2),1, IF(AND($H24<R$2+7,$H24>R$2),3, IF(AND($F24<=R$2, $H24>=R$2), 2, "" ))) | S24: =IF(AND($F24<(S$2+7),$F24>S$2),1, IF(AND($H24<S$2+7,$H24>S$2),3, IF(AND($F24<=S$2, $H24>=S$2), 2, "" ))) | ... AQ24: =IF(AND($F24<(AQ$2+7),$F24>AQ$2),1, IF(AND($H24<AQ$2+7,$H24>AQ$2),3, IF(AND($F24<=AQ$2, $H24>=AQ$2), 2, "" ))) -> 2
B25: Mounting structure Installation | C25: 43991 | D25: 4 | E25: 43997 | F25: 43991 | G25: 4 | H25: 43997 | L25: =IF(AND($F25<(L$2+7),$F25>L$2),1, IF(AND($H25<L$2+7,$H25>L$2),3, IF(AND($F25<=L$2, $H25>=L$2), 2, "" ))) | M25: =IF(AND($F25<(M$2+7),$F25>M$2),1, IF(AND($H25<M$2+7,$H25>M$2),3, IF(AND($F25<=M$2, $H25>=M$2), 2, "" ))) | N25: =IF(AND($F25<(N$2+7),$F25>N$2),1, IF(AND($H25<N$2+7,$H25>N$2),3, IF(AND($F25<=N$2, $H25>=N$2), 2, "" ))) | O25: =IF(AND($F25<(O$2+7),$F25>O$2),1, IF(AND($H25<O$2+7,$H25>O$2),3, IF(AND($F25<=O$2, $H25>=O$2), 2, "" ))) | P25: =IF(AND($F25<(P$2+7),$F25>P$2),1, IF(AND($H25<P$2+7,$H25>P$2),3, IF(AND($F25<=P$2, $H25>=P$2), 2, "" ))) | Q25: =IF(AND($F25<(Q$2+7),$F25>Q$2),1, IF(AND($H25<Q$2+7,$H25>Q$2),3, IF(AND($F25<=Q$2, $H25>=Q$2), 2, "" ))) | R25: =IF(AND($F25<(R$2+7),$F25>R$2),1, IF(AND($H25<R$2+7,$H25>R$2),3, IF(AND($F25<=R$2, $H25>=R$2), 2, "" ))) | S25: =IF(AND($F25<(S$2+7),$F25>S$2),1, IF(AND($H25<S$2+7,$H25>S$2),3, IF(AND($F25<=S$2, $H25>=S$2), 2, "" ))) | ... AQ25: =IF(AND($F25<(AQ$2+7),$F25>AQ$2),1, IF(AND($H25<AQ$2+7,$H25>AQ$2),3, IF(AND($F25<=AQ$2, $H25>=AQ$2), 2, "" )))
B26: Cable tray Installation | C26: 43997 | D26: 3 | E26: 44004 | F26: 43997 | G26: 3 | H26: 44004 | L26: =IF(AND($F26<(L$2+7),$F26>L$2),1, IF(AND($H26<L$2+7,$H26>L$2),3, IF(AND($F26<=L$2, $H26>=L$2), 2, "" ))) | M26: =IF(AND($F26<(M$2+7),$F26>M$2),1, IF(AND($H26<M$2+7,$H26>M$2),3, IF(AND($F26<=M$2, $H26>=M$2), 2, "" ))) | N26: =IF(AND($F26<(N$2+7),$F26>N$2),1, IF(AND($H26<N$2+7,$H26>N$2),3, IF(AND($F26<=N$2, $H26>=N$2), 2, "" ))) | O26: =IF(AND($F26<(O$2+7),$F26>O$2),1, IF(AND($H26<O$2+7,$H26>O$2),3, IF(AND($F26<=O$2, $H26>=O$2), 2, "" ))) | P26: =IF(AND($F26<(P$2+7),$F26>P$2),1, IF(AND($H26<P$2+7,$H26>P$2),3, IF(AND($F26<=P$2, $H26>=P$2), 2, "" ))) | Q26: =IF(AND($F26<(Q$2+7),$F26>Q$2),1, IF(AND($H26<Q$2+7,$H26>Q$2),3, IF(AND($F26<=Q$2, $H26>=Q$2), 2, "" ))) | R26: =IF(AND($F26<(R$2+7),$F26>R$2),1, IF(AND($H26<R$2+7,$H26>R$2),3, IF(AND($F26<=R$2, $H26>=R$2), 2, "" ))) | S26: =IF(AND($F26<(S$2+7),$F26>S$2),1, IF(AND($H26<S$2+7,$H26>S$2),3, IF(AND($F26<=S$2, $H26>=S$2), 2, "" ))) | ... AQ26: =IF(AND($F26<(AQ$2+7),$F26>AQ$2),1, IF(AND($H26<AQ$2+7,$H26>AQ$2),3, IF(AND($F26<=AQ$2, $H26>=AQ$2), 2, "" )))
B27: DC Cable Installation | C27: 44004 | D27: 2 | E27: 44006 | F27: 44004 | G27: 2 | H27: 44006 | L27: =IF(AND($F27<(L$2+7),$F27>L$2),1, IF(AND($H27<L$2+7,$H27>L$2),3, IF(AND($F27<=L$2, $H27>=L$2), 2, "" ))) | M27: =IF(AND($F27<(M$2+7),$F27>M$2),1, IF(AND($H27<M$2+7,$H27>M$2),3, IF(AND($F27<=M$2, $H27>=M$2), 2, "" ))) | N27: =IF(AND($F27<(N$2+7),$F27>N$2),1, IF(AND($H27<N$2+7,$H27>N$2),3, IF(AND($F27<=N$2, $H27>=N$2), 2, "" ))) | O27: =IF(AND($F27<(O$2+7),$F27>O$2),1, IF(AND($H27<O$2+7,$H27>O$2),3, IF(AND($F27<=O$2, $H27>=O$2), 2, "" ))) | P27: =IF(AND($F27<(P$2+7),$F27>P$2),1, IF(AND($H27<P$2+7,$H27>P$2),3, IF(AND($F27<=P$2, $H27>=P$2), 2, "" ))) | Q27: =IF(AND($F27<(Q$2+7),$F27>Q$2),1, IF(AND($H27<Q$2+7,$H27>Q$2),3, IF(AND($F27<=Q$2, $H27>=Q$2), 2, "" ))) | R27: =IF(AND($F27<(R$2+7),$F27>R$2),1, IF(AND($H27<R$2+7,$H27>R$2),3, IF(AND($F27<=R$2, $H27>=R$2), 2, "" ))) | S27: =IF(AND($F27<(S$2+7),$F27>S$2),1, IF(AND($H27<S$2+7,$H27>S$2),3, IF(AND($F27<=S$2, $H27>=S$2), 2, "" ))) | ... AQ27: =IF(AND($F27<(AQ$2+7),$F27>AQ$2),1, IF(AND($H27<AQ$2+7,$H27>AQ$2),3, IF(AND($F27<=AQ$2, $H27>=AQ$2), 2, "" )))
B28: Module Installation | C28: 44006 | D28: 4 | E28: 44012 | F28: 44006 | G28: 4 | H28: 44012 | L28: =IF(AND($F28<(L$2+7),$F28>L$2),1, IF(AND($H28<L$2+7,$H28>L$2),3, IF(AND($F28<=L$2, $H28>=L$2), 2, "" ))) | M28: =IF(AND($F28<(M$2+7),$F28>M$2),1, IF(AND($H28<M$2+7,$H28>M$2),3, IF(AND($F28<=M$2, $H28>=M$2), 2, "" ))) | N28: =IF(AND($F28<(N$2+7),$F28>N$2),1, IF(AND($H28<N$2+7,$H28>N$2),3, IF(AND($F28<=N$2, $H28>=N$2), 2, "" ))) | O28: =IF(AND($F28<(O$2+7),$F28>O$2),1, IF(AND($H28<O$2+7,$H28>O$2),3, IF(AND($F28<=O$2, $H28>=O$2), 2, "" ))) | P28: =IF(AND($F28<(P$2+7),$F28>P$2),1, IF(AND($H28<P$2+7,$H28>P$2),3, IF(AND($F28<=P$2, $H28>=P$2), 2, "" ))) | Q28: =IF(AND($F28<(Q$2+7),$F28>Q$2),1, IF(AND($H28<Q$2+7,$H28>Q$2),3, IF(AND($F28<=Q$2, $H28>=Q$2), 2, "" ))) | R28: =IF(AND($F28<(R$2+7),$F28>R$2),1, IF(AND($H28<R$2+7,$H28>R$2),3, IF(AND($F28<=R$2, $H28>=R$2), 2, "" ))) | S28: =IF(AND($F28<(S$2+7),$F28>S$2),1, IF(AND($H28<S$2+7,$H28>S$2),3, IF(AND($F28<=S$2, $H28>=S$2), 2, "" ))) | ... AQ28: =IF(AND($F28<(AQ$2+7),$F28>AQ$2),1, IF(AND($H28<AQ$2+7,$H28>AQ$2),3, IF(AND($F28<=AQ$2, $H28>=AQ$2), 2, "" ))) -> 2
B29: Earth Cable Installation | C29: 44004 | D29: 1 | E29: 44005 | F29: 44004 | G29: 1 | H29: 44005 | L29: =IF(AND($F29<(L$2+7),$F29>L$2),1, IF(AND($H29<L$2+7,$H29>L$2),3, IF(AND($F29<=L$2, $H29>=L$2), 2, "" ))) | M29: =IF(AND($F29<(M$2+7),$F29>M$2),1, IF(AND($H29<M$2+7,$H29>M$2),3, IF(AND($F29<=M$2, $H29>=M$2), 2, "" ))) | N29: =IF(AND($F29<(N$2+7),$F29>N$2),1, IF(AND($H29<N$2+7,$H29>N$2),3, IF(AND($F29<=N$2, $H29>=N$2), 2, "" ))) | O29: =IF(AND($F29<(O$2+7),$F29>O$2),1, IF(AND($H29<O$2+7,$H29>O$2),3, IF(AND($F29<=O$2, $H29>=O$2), 2, "" ))) | P29: =IF(AND($F29<(P$2+7),$F29>P$2),1, IF(AND($H29<P$2+7,$H29>P$2),3, IF(AND($F29<=P$2, $H29>=P$2), 2, "" ))) | Q29: =IF(AND($F29<(Q$2+7),$F29>Q$2),1, IF(AND($H29<Q$2+7,$H29>Q$2),3, IF(AND($F29<=Q$2, $H29>=Q$2), 2, "" ))) | R29: =IF(AND($F29<(R$2+7),$F29>R$2),1, IF(AND($H29<R$2+7,$H29>R$2),3, IF(AND($F29<=R$2, $H29>=R$2), 2, "" ))) | S29: =IF(AND($F29<(S$2+7),$F29>S$2),1, IF(AND($H29<S$2+7,$H29>S$2),3, IF(AND($F29<=S$2, $H29>=S$2), 2, "" ))) | ... AQ29: =IF(AND($F29<(AQ$2+7),$F29>AQ$2),1, IF(AND($H29<AQ$2+7,$H29>AQ$2),3, IF(AND($F29<=AQ$2, $H29>=AQ$2), 2, "" )))
A30: 10 | B30: AC Works | C30: 43991 | D30: 8 | E30: 44000 | F30: 43991 | G30: 8 | H30: 44000
B31: Inverters Installation | C31: 43991 | D31: 2 | E31: 43993 | F31: 43991 | G31: 2 | H31: 43993 | L31: =IF(AND($F31<(L$2+7),$F31>L$2),1, IF(AND($H31<L$2+7,$H31>L$2),3, IF(AND($F31<=L$2, $H31>=L$2), 2, "" ))) | M31: =IF(AND($F31<(M$2+7),$F31>M$2),1, IF(AND($H31<M$2+7,$H31>M$2),3, IF(AND($F31<=M$2, $H31>=M$2), 2, "" ))) | N31: =IF(AND($F31<(N$2+7),$F31>N$2),1, IF(AND($H31<N$2+7,$H31>N$2),3, IF(AND($F31<=N$2, $H31>=N$2), 2, "" ))) | O31: =IF(AND($F31<(O$2+7),$F31>O$2),1, IF(AND($H31<O$2+7,$H31>O$2),3, IF(AND($F31<=O$2, $H31>=O$2), 2, "" ))) | P31: =IF(AND($F31<(P$2+7),$F31>P$2),1, IF(AND($H31<P$2+7,$H31>P$2),3, IF(AND($F31<=P$2, $H31>=P$2), 2, "" ))) | Q31: =IF(AND($F31<(Q$2+7),$F31>Q$2),1, IF(AND($H31<Q$2+7,$H31>Q$2),3, IF(AND($F31<=Q$2, $H31>=Q$2), 2, "" ))) | R31: =IF(AND($F31<(R$2+7),$F31>R$2),1, IF(AND($H31<R$2+7,$H31>R$2),3, IF(AND($F31<=R$2, $H31>=R$2), 2, "" ))) | S31: =IF(AND($F31<(S$2+7),$F31>S$2),1, IF(AND($H31<S$2+7,$H31>S$2),3, IF(AND($F31<=S$2, $H31>=S$2), 2, "" ))) | ... AQ31: =IF(AND($F31<(AQ$2+7),$F31>AQ$2),1, IF(AND($H31<AQ$2+7,$H31>AQ$2),3, IF(AND($F31<=AQ$2, $H31>=AQ$2), 2, "" )))
B32: AC BOS Installation | C32: 43993 | D32: 3 | E32: 44000 | F32: 43993 | G32: 3 | H32: 44000 | L32: =IF(AND($F32<(L$2+7),$F32>L$2),1, IF(AND($H32<L$2+7,$H32>L$2),3, IF(AND($F32<=L$2, $H32>=L$2), 2, "" ))) | M32: =IF(AND($F32<(M$2+7),$F32>M$2),1, IF(AND($H32<M$2+7,$H32>M$2),3, IF(AND($F32<=M$2, $H32>=M$2), 2, "" ))) | N32: =IF(AND($F32<(N$2+7),$F32>N$2),1, IF(AND($H32<N$2+7,$H32>N$2),3, IF(AND($F32<=N$2, $H32>=N$2), 2, "" ))) | O32: =IF(AND($F32<(O$2+7),$F32>O$2),1, IF(AND($H32<O$2+7,$H32>O$2),3, IF(AND($F32<=O$2, $H32>=O$2), 2, "" ))) | P32: =IF(AND($F32<(P$2+7),$F32>P$2),1, IF(AND($H32<P$2+7,$H32>P$2),3, IF(AND($F32<=P$2, $H32>=P$2), 2, "" ))) | Q32: =IF(AND($F32<(Q$2+7),$F32>Q$2),1, IF(AND($H32<Q$2+7,$H32>Q$2),3, IF(AND($F32<=Q$2, $H32>=Q$2), 2, "" ))) | R32: =IF(AND($F32<(R$2+7),$F32>R$2),1, IF(AND($H32<R$2+7,$H32>R$2),3, IF(AND($F32<=R$2, $H32>=R$2), 2, "" ))) | S32: =IF(AND($F32<(S$2+7),$F32>S$2),1, IF(AND($H32<S$2+7,$H32>S$2),3, IF(AND($F32<=S$2, $H32>=S$2), 2, "" ))) | ... AQ32: =IF(AND($F32<(AQ$2+7),$F32>AQ$2),1, IF(AND($H32<AQ$2+7,$H32>AQ$2),3, IF(AND($F32<=AQ$2, $H32>=AQ$2), 2, "" )))
B33: AC Cable/Tie-In | C33: 43992 | D33: 3 | E33: 43997 | F33: 43992 | G33: 3 | H33: 43997 | L33: =IF(AND($F33<(L$2+7),$F33>L$2),1, IF(AND($H33<L$2+7,$H33>L$2),3, IF(AND($F33<=L$2, $H33>=L$2), 2, "" ))) | M33: =IF(AND($F33<(M$2+7),$F33>M$2),1, IF(AND($H33<M$2+7,$H33>M$2),3, IF(AND($F33<=M$2, $H33>=M$2), 2, "" ))) | N33: =IF(AND($F33<(N$2+7),$F33>N$2),1, IF(AND($H33<N$2+7,$H33>N$2),3, IF(AND($F33<=N$2, $H33>=N$2), 2, "" ))) | O33: =IF(AND($F33<(O$2+7),$F33>O$2),1, IF(AND($H33<O$2+7,$H33>O$2),3, IF(AND($F33<=O$2, $H33>=O$2), 2, "" ))) | P33: =IF(AND($F33<(P$2+7),$F33>P$2),1, IF(AND($H33<P$2+7,$H33>P$2),3, IF(AND($F33<=P$2, $H33>=P$2), 2, "" ))) | Q33: =IF(AND($F33<(Q$2+7),$F33>Q$2),1, IF(AND($H33<Q$2+7,$H33>Q$2),3, IF(AND($F33<=Q$2, $H33>=Q$2), 2, "" ))) | R33: =IF(AND($F33<(R$2+7),$F33>R$2),1, IF(AND($H33<R$2+7,$H33>R$2),3, IF(AND($F33<=R$2, $H33>=R$2), 2, "" ))) | S33: =IF(AND($F33<(S$2+7),$F33>S$2),1, IF(AND($H33<S$2+7,$H33>S$2),3, IF(AND($F33<=S$2, $H33>=S$2), 2, "" ))) | ... AQ33: =IF(AND($F33<(AQ$2+7),$F33>AQ$2),1, IF(AND($H33<AQ$2+7,$H33>AQ$2),3, IF(AND($F33<=AQ$2, $H33>=AQ$2), 2, "" )))
B34: Monitoring Platform Installation | C34: 43997 | D34: 1 | E34: 44000 | F34: 43997 | G34: 1 | H34: 44000
A35: 11 | B35: Completion | C35: 44000 | D35: 14 | E35: 44014 | F35: 44000 | G35: 14 | H35: 44014 | L35: =IF(AND($F35<(L$2+7),$F35>L$2),1, IF(AND($H35<L$2+7,$H35>L$2),3, IF(AND($F35<=L$2, $H35>=L$2), 2, "" ))) | M35: =IF(AND($F35<(M$2+7),$F35>M$2),1, IF(AND($H35<M$2+7,$H35>M$2),3, IF(AND($F35<=M$2, $H35>=M$2), 2, "" ))) | N35: =IF(AND($F35<(N$2+7),$F35>N$2),1, IF(AND($H35<N$2+7,$H35>N$2),3, IF(AND($F35<=N$2, $H35>=N$2), 2, "" ))) | O35: =IF(AND($F35<(O$2+7),$F35>O$2),1, IF(AND($H35<O$2+7,$H35>O$2),3, IF(AND($F35<=O$2, $H35>=O$2), 2, "" ))) | P35: =IF(AND($F35<(P$2+7),$F35>P$2),1, IF(AND($H35<P$2+7,$H35>P$2),3, IF(AND($F35<=P$2, $H35>=P$2), 2, "" ))) | Q35: =IF(AND($F35<(Q$2+7),$F35>Q$2),1, IF(AND($H35<Q$2+7,$H35>Q$2),3, IF(AND($F35<=Q$2, $H35>=Q$2), 2, "" ))) | R35: =IF(AND($F35<(R$2+7),$F35>R$2),1, IF(AND($H35<R$2+7,$H35>R$2),3, IF(AND($F35<=R$2, $H35>=R$2), 2, "" ))) | S35: =IF(AND($F35<(S$2+7),$F35>S$2),1, IF(AND($H35<S$2+7,$H35>S$2),3, IF(AND($F35<=S$2, $H35>=S$2), 2, "" ))) | ... AQ35: =IF(AND($F35<(AQ$2+7),$F35>AQ$2),1, IF(AND($H35<AQ$2+7,$H35>AQ$2),3, IF(AND($F35<=AQ$2, $H35>=AQ$2), 2, "" ))) -> 3
B36: DC Works | C36: 44012 | D36: 2 | E36: 44014 | F36: 44012 | G36: 2 | H36: 44014 | L36: =IF(AND($F36<(L$2+7),$F36>L$2),1, IF(AND($H36<L$2+7,$H36>L$2),3, IF(AND($F36<=L$2, $H36>=L$2), 2, "" ))) | M36: =IF(AND($F36<(M$2+7),$F36>M$2),1, IF(AND($H36<M$2+7,$H36>M$2),3, IF(AND($F36<=M$2, $H36>=M$2), 2, "" ))) | N36: =IF(AND($F36<(N$2+7),$F36>N$2),1, IF(AND($H36<N$2+7,$H36>N$2),3, IF(AND($F36<=N$2, $H36>=N$2), 2, "" ))) | O36: =IF(AND($F36<(O$2+7),$F36>O$2),1, IF(AND($H36<O$2+7,$H36>O$2),3, IF(AND($F36<=O$2, $H36>=O$2), 2, "" ))) | P36: =IF(AND($F36<(P$2+7),$F36>P$2),1, IF(AND($H36<P$2+7,$H36>P$2),3, IF(AND($F36<=P$2, $H36>=P$2), 2, "" ))) | Q36: =IF(AND($F36<(Q$2+7),$F36>Q$2),1, IF(AND($H36<Q$2+7,$H36>Q$2),3, IF(AND($F36<=Q$2, $H36>=Q$2), 2, "" ))) | R36: =IF(AND($F36<(R$2+7),$F36>R$2),1, IF(AND($H36<R$2+7,$H36>R$2),3, IF(AND($F36<=R$2, $H36>=R$2), 2, "" ))) | S36: =IF(AND($F36<(S$2+7),$F36>S$2),1, IF(AND($H36<S$2+7,$H36>S$2),3, IF(AND($F36<=S$2, $H36>=S$2), 2, "" ))) | ... AQ36: =IF(AND($F36<(AQ$2+7),$F36>AQ$2),1, IF(AND($H36<AQ$2+7,$H36>AQ$2),3, IF(AND($F36<=AQ$2, $H36>=AQ$2), 2, "" ))) -> 3
B37: AC Works | C37: 44000 | D37: 2 | E37: 44004 | F37: 44000 | G37: 2 | H37: 44004 | L37: =IF(AND($F37<(L$2+7),$F37>L$2),1, IF(AND($H37<L$2+7,$H37>L$2),3, IF(AND($F37<=L$2, $H37>=L$2), 2, "" ))) | M37: =IF(AND($F37<(M$2+7),$F37>M$2),1, IF(AND($H37<M$2+7,$H37>M$2),3, IF(AND($F37<=M$2, $H37>=M$2), 2, "" ))) | N37: =IF(AND($F37<(N$2+7),$F37>N$2),1, IF(AND($H37<N$2+7,$H37>N$2),3, IF(AND($F37<=N$2, $H37>=N$2), 2, "" ))) | O37: =IF(AND($F37<(O$2+7),$F37>O$2),1, IF(AND($H37<O$2+7,$H37>O$2),3, IF(AND($F37<=O$2, $H37>=O$2), 2, "" ))) | P37: =IF(AND($F37<(P$2+7),$F37>P$2),1, IF(AND($H37<P$2+7,$H37>P$2),3, IF(AND($F37<=P$2, $H37>=P$2), 2, "" ))) | Q37: =IF(AND($F37<(Q$2+7),$F37>Q$2),1, IF(AND($H37<Q$2+7,$H37>Q$2),3, IF(AND($F37<=Q$2, $H37>=Q$2), 2, "" ))) | R37: =IF(AND($F37<(R$2+7),$F37>R$2),1, IF(AND($H37<R$2+7,$H37>R$2),3, IF(AND($F37<=R$2, $H37>=R$2), 2, "" ))) | S37: =IF(AND($F37<(S$2+7),$F37>S$2),1, IF(AND($H37<S$2+7,$H37>S$2),3, IF(AND($F37<=S$2, $H37>=S$2), 2, "" ))) | ... AQ37: =IF(AND($F37<(AQ$2+7),$F37>AQ$2),1, IF(AND($H37<AQ$2+7,$H37>AQ$2),3, IF(AND($F37<=AQ$2, $H37>=AQ$2), 2, "" )))
A38: D | B38: PAYMENT MILESTONE 4: PRACTICAL COMPLETION | C38: 44012 | D38: 1 | E38: 44013 | F38: 44012 | G38: 1 | H38: 44013 | L38: =IF(AND($F38<(L$2+7),$F38>L$2),1, IF(AND($H38<L$2+7,$H38>L$2),3, IF(AND($F38<=L$2, $H38>=L$2), 2, "" ))) | M38: =IF(AND($F38<(M$2+7),$F38>M$2),1, IF(AND($H38<M$2+7,$H38>M$2),3, IF(AND($F38<=M$2, $H38>=M$2), 2, "" ))) | N38: =IF(AND($F38<(N$2+7),$F38>N$2),1, IF(AND($H38<N$2+7,$H38>N$2),3, IF(AND($F38<=N$2, $H38>=N$2), 2, "" ))) | O38: =IF(AND($F38<(O$2+7),$F38>O$2),1, IF(AND($H38<O$2+7,$H38>O$2),3, IF(AND($F38<=O$2, $H38>=O$2), 2, "" ))) | P38: =IF(AND($F38<(P$2+7),$F38>P$2),1, IF(AND($H38<P$2+7,$H38>P$2),3, IF(AND($F38<=P$2, $H38>=P$2), 2, "" ))) | Q38: =IF(AND($F38<(Q$2+7),$F38>Q$2),1, IF(AND($H38<Q$2+7,$H38>Q$2),3, IF(AND($F38<=Q$2, $H38>=Q$2), 2, "" ))) | R38: =IF(AND($F38<(R$2+7),$F38>R$2),1, IF(AND($H38<R$2+7,$H38>R$2),3, IF(AND($F38<=R$2, $H38>=R$2), 2, "" ))) | S38: =IF(AND($F38<(S$2+7),$F38>S$2),1, IF(AND($H38<S$2+7,$H38>S$2),3, IF(AND($F38<=S$2, $H38>=S$2), 2, "" ))) | ... AQ38: =IF(AND($F38<(AQ$2+7),$F38>AQ$2),1, IF(AND($H38<AQ$2+7,$H38>AQ$2),3, IF(AND($F38<=AQ$2, $H38>=AQ$2), 2, "" ))) -> 3
A39: 12 | B39: Commissioning | C39: 43997 | D39: 22 | E39: 44019 | F39: 43997 | G39: 22 | H39: 44019 | L39: =IF(AND($F39<(L$2+7),$F39>L$2),1, IF(AND($H39<L$2+7,$H39>L$2),3, IF(AND($F39<=L$2, $H39>=L$2), 2, "" ))) | M39: =IF(AND($F39<(M$2+7),$F39>M$2),1, IF(AND($H39<M$2+7,$H39>M$2),3, IF(AND($F39<=M$2, $H39>=M$2), 2, "" ))) | N39: =IF(AND($F39<(N$2+7),$F39>N$2),1, IF(AND($H39<N$2+7,$H39>N$2),3, IF(AND($F39<=N$2, $H39>=N$2), 2, "" ))) | O39: =IF(AND($F39<(O$2+7),$F39>O$2),1, IF(AND($H39<O$2+7,$H39>O$2),3, IF(AND($F39<=O$2, $H39>=O$2), 2, "" ))) | P39: =IF(AND($F39<(P$2+7),$F39>P$2),1, IF(AND($H39<P$2+7,$H39>P$2),3, IF(AND($F39<=P$2, $H39>=P$2), 2, "" ))) | Q39: =IF(AND($F39<(Q$2+7),$F39>Q$2),1, IF(AND($H39<Q$2+7,$H39>Q$2),3, IF(AND($F39<=Q$2, $H39>=Q$2), 2, "" ))) | R39: =IF(AND($F39<(R$2+7),$F39>R$2),1, IF(AND($H39<R$2+7,$H39>R$2),3, IF(AND($F39<=R$2, $H39>=R$2), 2, "" ))) | S39: =IF(AND($F39<(S$2+7),$F39>S$2),1, IF(AND($H39<S$2+7,$H39>S$2),3, IF(AND($F39<=S$2, $H39>=S$2), 2, "" ))) | ... AQ39: =IF(AND($F39<(AQ$2+7),$F39>AQ$2),1, IF(AND($H39<AQ$2+7,$H39>AQ$2),3, IF(AND($F39<=AQ$2, $H39>=AQ$2), 2, "" ))) -> 2
B40: Snag List | C40: 44014 | D40: 3 | E40: 44019 | F40: 44014 | G40: 3 | H40: 44019
B41: Pre-Commissioning Checks | C41: 44010 | D41: 2 | E41: 44012 | F41: 44010 | G41: 2 | H41: 44012
B42: Issue CoC | C42: 43997 | D42: 2 | E42: 44001 | F42: 43997 | G42: 2 | H42: 44001 | L42: =IF(AND($F42<(L$2+7),$F42>L$2),1, IF(AND($H42<L$2+7,$H42>L$2),3, IF(AND($F42<=L$2, $H42>=L$2), 2, "" ))) | M42: =IF(AND($F42<(M$2+7),$F42>M$2),1, IF(AND($H42<M$2+7,$H42>M$2),3, IF(AND($F42<=M$2, $H42>=M$2), 2, "" ))) | N42: =IF(AND($F42<(N$2+7),$F42>N$2),1, IF(AND($H42<N$2+7,$H42>N$2),3, IF(AND($F42<=N$2, $H42>=N$2), 2, "" ))) | O42: =IF(AND($F42<(O$2+7),$F42>O$2),1, IF(AND($H42<O$2+7,$H42>O$2),3, IF(AND($F42<=O$2, $H42>=O$2), 2, "" ))) | P42: =IF(AND($F42<(P$2+7),$F42>P$2),1, IF(AND($H42<P$2+7,$H42>P$2),3, IF(AND($F42<=P$2, $H42>=P$2), 2, "" ))) | Q42: =IF(AND($F42<(Q$2+7),$F42>Q$2),1, IF(AND($H42<Q$2+7,$H42>Q$2),3, IF(AND($F42<=Q$2, $H42>=Q$2), 2, "" ))) | R42: =IF(AND($F42<(R$2+7),$F42>R$2),1, IF(AND($H42<R$2+7,$H42>R$2),3, IF(AND($F42<=R$2, $H42>=R$2), 2, "" ))) | S42: =IF(AND($F42<(S$2+7),$F42>S$2),1, IF(AND($H42<S$2+7,$H42>S$2),3, IF(AND($F42<=S$2, $H42>=S$2), 2, "" ))) | ... AQ42: =IF(AND($F42<(AQ$2+7),$F42>AQ$2),1, IF(AND($H42<AQ$2+7,$H42>AQ$2),3, IF(AND($F42<=AQ$2, $H42>=AQ$2), 2, "" )))
B43: Cold Commissioning | C43: 44012 | D43: 1 | E43: 44013 | F43: 44012 | G43: 1 | H43: 44013 | L43: =IF(AND($F43<(L$2+7),$F43>L$2),1, IF(AND($H43<L$2+7,$H43>L$2),3, IF(AND($F43<=L$2, $H43>=L$2), 2, "" ))) | M43: =IF(AND($F43<(M$2+7),$F43>M$2),1, IF(AND($H43<M$2+7,$H43>M$2),3, IF(AND($F43<=M$2, $H43>=M$2), 2, "" ))) | N43: =IF(AND($F43<(N$2+7),$F43>N$2),1, IF(AND($H43<N$2+7,$H43>N$2),3, IF(AND($F43<=N$2, $H43>=N$2), 2, "" ))) | O43: =IF(AND($F43<(O$2+7),$F43>O$2),1, IF(AND($H43<O$2+7,$H43>O$2),3, IF(AND($F43<=O$2, $H43>=O$2), 2, "" ))) | P43: =IF(AND($F43<(P$2+7),$F43>P$2),1, IF(AND($H43<P$2+7,$H43>P$2),3, IF(AND($F43<=P$2, $H43>=P$2), 2, "" ))) | Q43: =IF(AND($F43<(Q$2+7),$F43>Q$2),1, IF(AND($H43<Q$2+7,$H43>Q$2),3, IF(AND($F43<=Q$2, $H43>=Q$2), 2, "" ))) | R43: =IF(AND($F43<(R$2+7),$F43>R$2),1, IF(AND($H43<R$2+7,$H43>R$2),3, IF(AND($F43<=R$2, $H43>=R$2), 2, "" ))) | S43: =IF(AND($F43<(S$2+7),$F43>S$2),1, IF(AND($H43<S$2+7,$H43>S$2),3, IF(AND($F43<=S$2, $H43>=S$2), 2, "" ))) | ... AQ43: =IF(AND($F43<(AQ$2+7),$F43>AQ$2),1, IF(AND($H43<AQ$2+7,$H43>AQ$2),3, IF(AND($F43<=AQ$2, $H43>=AQ$2), 2, "" ))) -> 3
B44: Hot Commissioning | C44: 44013 | D44: 2 | E44: 44015 | F44: 44013 | G44: 2 | H44: 44015 | L44: =IF(AND($F44<(L$2+7),$F44>L$2),1, IF(AND($H44<L$2+7,$H44>L$2),3, IF(AND($F44<=L$2, $H44>=L$2), 2, "" ))) | M44: =IF(AND($F44<(M$2+7),$F44>M$2),1, IF(AND($H44<M$2+7,$H44>M$2),3, IF(AND($F44<=M$2, $H44>=M$2), 2, "" ))) | N44: =IF(AND($F44<(N$2+7),$F44>N$2),1, IF(AND($H44<N$2+7,$H44>N$2),3, IF(AND($F44<=N$2, $H44>=N$2), 2, "" ))) | O44: =IF(AND($F44<(O$2+7),$F44>O$2),1, IF(AND($H44<O$2+7,$H44>O$2),3, IF(AND($F44<=O$2, $H44>=O$2), 2, "" ))) | P44: =IF(AND($F44<(P$2+7),$F44>P$2),1, IF(AND($H44<P$2+7,$H44>P$2),3, IF(AND($F44<=P$2, $H44>=P$2), 2, "" ))) | Q44: =IF(AND($F44<(Q$2+7),$F44>Q$2),1, IF(AND($H44<Q$2+7,$H44>Q$2),3, IF(AND($F44<=Q$2, $H44>=Q$2), 2, "" ))) | R44: =IF(AND($F44<(R$2+7),$F44>R$2),1, IF(AND($H44<R$2+7,$H44>R$2),3, IF(AND($F44<=R$2, $H44>=R$2), 2, "" ))) | S44: =IF(AND($F44<(S$2+7),$F44>S$2),1, IF(AND($H44<S$2+7,$H44>S$2),3, IF(AND($F44<=S$2, $H44>=S$2), 2, "" ))) | ... AQ44: =IF(AND($F44<(AQ$2+7),$F44>AQ$2),1, IF(AND($H44<AQ$2+7,$H44>AQ$2),3, IF(AND($F44<=AQ$2, $H44>=AQ$2), 2, "" ))) -> 1
A45: 13 | B45: Handover | C45: 44020 | D45: 1 | E45: 44021 | F45: 44020 | G45: 1 | H45: 44021 | L45: =IF(AND($F45<(L$2+7),$F45>L$2),1, IF(AND($H45<L$2+7,$H45>L$2),3, IF(AND($F45<=L$2, $H45>=L$2), 2, "" ))) | M45: =IF(AND($F45<(M$2+7),$F45>M$2),1, IF(AND($H45<M$2+7,$H45>M$2),3, IF(AND($F45<=M$2, $H45>=M$2), 2, "" ))) | N45: =IF(AND($F45<(N$2+7),$F45>N$2),1, IF(AND($H45<N$2+7,$H45>N$2),3, IF(AND($F45<=N$2, $H45>=N$2), 2, "" ))) | O45: =IF(AND($F45<(O$2+7),$F45>O$2),1, IF(AND($H45<O$2+7,$H45>O$2),3, IF(AND($F45<=O$2, $H45>=O$2), 2, "" ))) | P45: =IF(AND($F45<(P$2+7),$F45>P$2),1, IF(AND($H45<P$2+7,$H45>P$2),3, IF(AND($F45<=P$2, $H45>=P$2), 2, "" ))) | Q45: =IF(AND($F45<(Q$2+7),$F45>Q$2),1, IF(AND($H45<Q$2+7,$H45>Q$2),3, IF(AND($F45<=Q$2, $H45>=Q$2), 2, "" ))) | R45: =IF(AND($F45<(R$2+7),$F45>R$2),1, IF(AND($H45<R$2+7,$H45>R$2),3, IF(AND($F45<=R$2, $H45>=R$2), 2, "" ))) | S45: =IF(AND($F45<(S$2+7),$F45>S$2),1, IF(AND($H45<S$2+7,$H45>S$2),3, IF(AND($F45<=S$2, $H45>=S$2), 2, "" ))) | ... AQ45: =IF(AND($F45<(AQ$2+7),$F45>AQ$2),1, IF(AND($H45<AQ$2+7,$H45>AQ$2),3, IF(AND($F45<=AQ$2, $H45>=AQ$2), 2, "" )))
A46: E | B46: PAYMENT MILESTONE 6: HANDOVER COMPLETE | C46: 44022 | D46: 1 | E46: 44025 | F46: 44022 | G46: 1 | H46: 44025
C47: 43831 | D47: These numbers are used to set the start and end dates on the Gantt Chart
C48: 44014

Sheet Certificate - Financial Close
B2: Emergent Energy – Financial Close Completion Certificate | H2: FINANCIAL CLOSE CERTIFICATE
B4: Project Name: | C4: ='Project Plan'!E2 -> Malvern Engineering Phase 2 | D4: {=_xlfn.LET(_xlpm.w,$B$10:$B$54,_xlpm.r,$M$10:$M$54,_xlpm.v,IF(ISNUMBER(_xlpm.r),_xlpm.r,IFERROR(VALUE(SUBSTITUTE(_xlpm.r,"%",""))/100,0)),_xlpm.g,IFERROR(VALUE(LEFT(_xlpm.w,1)),0),_xlpm.bdOnly,(SUMPRODUCT((_xlpm.w="1.1")*(_xlpm.v>0))>0)*(SUMPRODUCT((_xlpm.w<>"1.1")*(_xlpm.v>0))=0),_xlpm.anyConstr,SUMPRODUCT((_xlpm.g>=2)*(_xlpm.g<=6)*(_xlpm.v>0))>0,_xlpm.anyQA,SUMPRODUCT((_xlpm.g=7)*(_xlpm.v>0))>0,_xlpm.anyHO,SUMPRODUCT((_xlpm.g=8)*(_xlpm.v>0))>0,_xlpm.anyPlan,SUMPRODUCT((_xlpm.g=1)*(_xlpm.v>0))>0,IF(_xlpm.bdOnly,"1. Financial Close",IF(_xlpm.anyConstr,"3. Construction",IF(_xlpm.anyQA,"4. QA",IF(_xlpm.anyHO,"5. Handover",IF(_xlpm.anyPlan,"2. Planning","1. Financial Close"))))))} -> 1. Financial Close | E4: {=_xlfn.LET(_xlpm.w,$B$10:$B$54,_xlpm.r,$N$10:$N$54,_xlpm.v,IF(ISNUMBER(_xlpm.r),_xlpm.r,IFERROR(VALUE(SUBSTITUTE(_xlpm.r,"%",""))/100,0)),_xlpm.g,IFERROR(VALUE(LEFT(_xlpm.w,1)),0),_xlpm.bdOnly,(SUMPRODUCT((_xlpm.w="1.1")*(_xlpm.v>0))>0)*(SUMPRODUCT((_xlpm.w<>"1.1")*(_xlpm.v>0))=0),_xlpm.anyConstr,SUMPRODUCT((_xlpm.g>=2)*(_xlpm.g<=6)*(_xlpm.v>0))>0,_xlpm.anyQA,SUMPRODUCT((_xlpm.g=7)*(_xlpm.v>0))>0,_xlpm.anyHO,SUMPRODUCT((_xlpm.g=8)*(_xlpm.v>0))>0,_xlpm.anyPlan,SUMPRODUCT((_xlpm.g=1)*(_xlpm.v>0))>0,IF(_xlpm.bdOnly,"1. Financial Close",IF(_xlpm.anyConstr,"3. Construction",IF(_xlpm.anyQA,"4. QA",IF(_xlpm.anyHO,"5. Handover",IF(_xlpm.anyPlan,"2. Planning","1. Financial Close"))))))} -> 1. Financial Close
B5: COO: | C5: Johannes Potgieter
B6: Programme Manager: | C6: Roedolph Venter
B7: HoPD: | C7: Natasha Watkins-Baker
B9: Date of Phase Completion:
B10: Phase Deliverables Checklist: (Y/N)
B11: Product Agreement
B12: EPC Agreement
B13: O&M Agreeement
B14: Cost Proposal
B15: Deposit Received
B16: Risks / Notes
B18: Acknowledgement and Acceptance:
B19: Role | C19: Name | D19: Signature | E19: Date

Sheet Certificate - Planning
B2: Emergent Energy – Planning Phase Completion Certificate | H2: PLANNING CERTIFICATE
B4: Project Name: | C4: ='Project Plan'!E2 -> Malvern Engineering Phase 2
B5: Client Representative: | C5: Cole Bisset
B6: Programme Manager: | C6: Roedolph Venter
B7: Project Manager: | C7: ='Project Plan'!E5 -> JT Moorosi
B8: Project Engineer: | C8: Johan Snyman
B10: Date of Phase Completion:
B11: Phase Deliverables Checklist: (Y/N)
B12: Project Introduction Presentation
B13: Project Brief
B14: Engineering Pack
B15: BOQ
B16: PO – Material & Equipment
B17: PO - Contractors
B18: HSE – NOC
B19: HSE – EE File
B20: HSE – Contractor File
B21: SSEG Application
... B24: Acknowledgement and Acceptance:
B25: Role | C25: Name | D25: Signature | E25: Date

Sheet Change Register
F1: Change Register
B3: ID | C3: Description | D3: Supporting Image (If Applicable) | E3: Impact | F3: Proposed Date | G3: Proposed By | H3: Status | I3: Approved By | J3: Approved Date | K3: Results / Comments
B4: DEC001
B5: DEC002
B6: DEC003
B7: DEC004
B8: DEC005
B9: DEC006
B10: DEC007
B11: DEC008
B12: DEC009
B13: DEC010
B14: DEC011
B15: DEC012
... B33: DEC030

Sheet BOQ
B2: Item | C2: Supplier | D2: Description | E2: Quantity | F2: Comments
B3: PV Module
B4: DC Cable Red & Black
B5: Inverters
B6: Mounting Structure
B7: Current Transformers (Production)
B8: Current Transformers (Consumption)
B9: Solar Production Meter (Techistter)
B10: Grid Consumption Meter
B11: Wi-Fi Router & Sim
B12: Switch
B13: Back Up Battery
B14: PVDB
... B30: Techsitter

Sheet Project Plan
N1: =TODAY() -> 46084 | O1: =TODAY() -> 46084
C2: PROJECT PLAN | E2: Malvern Engineering Phase 2 | N2: 0
C3: PROJECT SIZE (kWp) | E3: 147
C4: PROJECT DEVELOPER | E4: Cole Bisset | J4: Target Month | K4: 45961
C5: PROJECT MANAGERS | E5: JT Moorosi
C6: CONTRACT VALUE | E6: 1366576.1
C7: Phase: | E7: Handover
B8: No. | C8: HIGH LEVEL PROGRAMME | E8: Planned Start | F8: Duration | G8: Planned End | I8: Actual Start | J8: Duration | K8: Actual End | M8: Status | N8: Expected Status | O8: Comment
F9: =G39-E19 -> 51 | J9: =K39-I19 -> 37 | M9: =AVERAGE(M11,M18,M21,M28,M35,M39,M48,M44) -> 0.97556818 | N9: =AVERAGE(N11,N18,N21,N28,N35,N39,N48,N44) -> 0.97493726
B11: 1 | C11: Project Initiation | E11: =MIN(E12:E17) -> 45910 | F11: =G11-E11 -> 47 | G11: =MAX(G12:G17) -> 45957 | I11: =MIN(I12:I17) -> 45910 | J11: =K11-I11 -> 47 | K11: =MAX(K12:K17) -> 45957 | M11: =(J12*M12+J13*M13+J14*M14+J15*M15+J16*M16)/SUM(J12:J16) -> 1 | N11: =(K12*N12+K13*N13+K14*N14+K15*N15+K16*N16)/SUM(K12:K16) -> 1
B12: 1.1 | C12: Project Charter Handover | E12: 45910 | F12: 1 | G12: =WORKDAY.INTL(E12,F12,1,Data!$C$3:$C$60) -> 45911 | I12: 45910 | J12: 1 | K12: =WORKDAY.INTL(I12,J12,1,Data!$C$3:$C$60) -> 45911 | M12: 1 | N12: =_xlfn.LET( _xlpm.s,VALUE($I12), _xlpm.e,VALUE($K12), IF(OR(_xlpm.s="",_xlpm.e=""),"", IF(_xlpm.e<=_xlpm.s, IF(TODAY()>=_xlpm.e,1,0), MAX(0,MIN(1,(TODAY()-_xlpm.s)/(_xlpm.e-_xlpm.s))))) ) -> 1 | O12: Deposit Recevied 08 Oct
B13: 1.2 | C13: HSE Readiness and Signoff | E13: 45938 | F13: 12 | G13: =WORKDAY.INTL(E13,F13,1,Data!$C$3:$C$60) -> 45954 | I13: 45938 | J13: 12 | K13: =WORKDAY.INTL(I13,J13,1,Data!$C$3:$C$60) -> 45954 | M13: 1 | N13: =_xlfn.LET( _xlpm.s,VALUE($I13), _xlpm.e,VALUE($K13), IF(OR(_xlpm.s="",_xlpm.e=""),"", IF(_xlpm.e<=_xlpm.s, IF(TODAY()>=_xlpm.e,1,0), MAX(0,MIN(1,(TODAY()-_xlpm.s)/(_xlpm.e-_xlpm.s))))) ) -> 1
B14: 1.3 | C14: Project Introduction | E14: 45947 | F14: 1 | G14: =WORKDAY.INTL(E14,F14,1,Data!$C$3:$C$60) -> 45950 | I14: 45947 | J14: 1 | K14: =WORKDAY.INTL(I14,J14,1,Data!$C$3:$C$60) -> 45950 | M14: 1 | N14: =_xlfn.LET( _xlpm.s,VALUE($I14), _xlpm.e,VALUE($K14), IF(OR(_xlpm.s="",_xlpm.e=""),"", IF(_xlpm.e<=_xlpm.s, IF(TODAY()>=_xlpm.e,1,0), MAX(0,MIN(1,(TODAY()-_xlpm.s)/(_xlpm.e-_xlpm.s))))) ) -> 1
B15: 1.4 | C15: Installer Kick Off | E15: =WORKDAY.INTL(G13,0,1,Data!$C$3:$C$60) -> 45954 | F15: 1 | G15: =WORKDAY.INTL(E15,F15,1,Data!$C$3:$C$60) -> 45957 | I15: =WORKDAY.INTL(K13,0,1,Data!$C$3:$C$60) -> 45954 | J15: 1 | K15: =WORKDAY.INTL(I15,J15,1,Data!$C$3:$C$60) -> 45957 | M15: 1 | N15: =_xlfn.LET( _xlpm.s,VALUE($I15), _xlpm.e,VALUE($K15), IF(OR(_xlpm.s="",_xlpm.e=""),"", IF(_xlpm.e<=_xlpm.s, IF(TODAY()>=_xlpm.e,1,0), MAX(0,MIN(1,(TODAY()-_xlpm.s)/(_xlpm.e-_xlpm.s))))) ) -> 1
B16: 1.5 | C16: Project Review | E16: =WORKDAY.INTL(E15,0,1,Data!$C$3:$C$60) -> 45954 | F16: 1 | G16: =WORKDAY.INTL(E16,F16,1,Data!$C$3:$C$60) -> 45957 | I16: 45953 | J16: 1 | K16: =WORKDAY.INTL(I16,J16,1,Data!$C$3:$C$60) -> 45954 | M16: 1 | N16: =_xlfn.LET( _xlpm.s,VALUE($I16), _xlpm.e,VALUE($K16), IF(OR(_xlpm.s="",_xlpm.e=""),"", IF(_xlpm.e<=_xlpm.s, IF(TODAY()>=_xlpm.e,1,0), MAX(0,MIN(1,(TODAY()-_xlpm.s)/(_xlpm.e-_xlpm.s))))) ) -> 1
B18: 2 | C18: Site Establishment | E18: =MIN(E19:E20) -> 45957 | F18: =G18-E18 -> 1 | G18: =MAX(G19:G20) -> 45958 | I18: =MIN(I19:I20) -> 45957 | J18: =K18-I18 -> 1 | K18: =MAX(K19:K20) -> 45958 | M18: =(J19*M19)/J18 -> 1 | N18: =(K19*N19)/K18 -> 1
B19: 2.1 | C19: Solar Contractor Establishment | E19: 45957 | F19: 1 | G19: =E19+F19 -> 45958 | I19: 45957 | J19: 1 | K19: =I19+J19 -> 45958 | M19: 1 | N19: 1 | S19: =NETWORKDAYS(I19,K41,Data!C3:C15) -> 23 | T19: Net Work Days
B21: 3 | C21: AC Installation | E21: =MIN(E22:E27) -> 45947 | F21: =G21-E21 -> 49 | G21: =MAX(G22:G27) -> 45996 | I21: =MIN(I22:I27) -> 45957 | J21: =K21-I21 -> 28 | K21: =MAX(K22:K27) -> 45985 | M21: =(J22*M22+J23*M23+J24*M24+J25*M25+J26*M26)/SUM(J22:J26) -> 1 | N21: =(J22*N22+J23*N23+J24*N24+J25*N25+J26*N26)/SUM(J22:J26) -> 1 | S21: =S19/5 -> 4.6 | T21: Total Weeks
B22: 3.1 | C22: Inverters delivered | E22: =WORKDAY.INTL(G19,0,1,Data!$C$3:$C$60) -> 45958 | F22: 1 | G22: =WORKDAY.INTL(E22,F22,1,Data!$C$3:$C$60) -> 45959 | I22: =WORKDAY.INTL(K19,0,1,Data!$C$3:$C$60) -> 45958 | J22: 1 | K22: =WORKDAY.INTL(I22,J22,1,Data!$C$3:$C$60) -> 45959 | M22: 1 | N22: =_xlfn.LET( _xlpm.s,VALUE($I22), _xlpm.e,VALUE($K22), IF(OR(_xlpm.s="",_xlpm.e=""),"", IF(_xlpm.e<=_xlpm.s, IF(TODAY()>=_xlpm.e,1,0), MAX(0,MIN(1,(TODAY()-_xlpm.s)/(_xlpm.e-_xlpm.s))))) ) -> 1 | S22: =E3/S21 -> 31.956522 | T22: kW/Week Installation Rate
B23: 3.2 | C23: Inverters Mounted | E23: =WORKDAY.INTL(G22,0,1,Data!$C$3:$C$60) -> 45959 | F23: 2 | G23: =WORKDAY.INTL(E23,F23,1,Data!$C$3:$C$60) -> 45961 | I23: =WORKDAY.INTL(K22,0,1,Data!$C$3:$C$60) -> 45959 | J23: 2 | K23: =WORKDAY.INTL(I23,J23,1,Data!$C$3:$C$60) -> 45961 | M23: 1 | N23: =_xlfn.LET( _xlpm.s,VALUE($I23), _xlpm.e,VALUE($K23), IF(OR(_xlpm.s="",_xlpm.e=""),"", IF(_xlpm.e<=_xlpm.s, IF(TODAY()>=_xlpm.e,1,0), MAX(0,MIN(1,(TODAY()-_xlpm.s)/(_xlpm.e-_xlpm.s))))) ) -> 1
B24: 3.3 | C24: Solar DB Lead Time | E24: =WORKDAY.INTL(E14,0,1,Data!$C$3:$C$60) -> 45947 | F24: 30 | G24: =WORKDAY.INTL(E24,F24,1,Data!$C$3:$C$60) -> 45989 | I24: =WORKDAY.INTL(I19,0,1,Data!$C$3:$C$60) -> 45957 | J24: 15 | K24: =WORKDAY.INTL(I24,J24,1,Data!$C$3:$C$60) -> 45978 | M24: 1 | N24: =_xlfn.LET( _xlpm.s,VALUE($I24), _xlpm.e,VALUE($K24), IF(OR(_xlpm.s="",_xlpm.e=""),"", IF(_xlpm.e<=_xlpm.s, IF(TODAY()>=_xlpm.e,1,0), MAX(0,MIN(1,(TODAY()-_xlpm.s)/(_xlpm.e-_xlpm.s))))) ) -> 1 | O24: Not a full DB, stadard enclosure to house Inverter breaker.
B25: 3.4 | C25: AC Works | E25: =WORKDAY.INTL(G24,0,1,Data!$C$3:$C$60) -> 45989 | F25: 5 | G25: =WORKDAY.INTL(E25,F25,1,Data!$C$3:$C$60) -> 45996 | I25: =WORKDAY.INTL(K24,0,1,Data!$C$3:$C$60) -> 45978 | J25: 5 | K25: =WORKDAY.INTL(I25,J25,1,Data!$C$3:$C$60) -> 45985 | M25: 1 | N25: =_xlfn.LET( _xlpm.s,VALUE($I25), _xlpm.e,VALUE($K25), IF(OR(_xlpm.s="",_xlpm.e=""),"", IF(_xlpm.e<=_xlpm.s, IF(TODAY()>=_xlpm.e,1,0), MAX(0,MIN(1,(TODAY()-_xlpm.s)/(_xlpm.e-_xlpm.s))))) ) -> 1
B26: 3.5 | C26: AC Tie-In | E26: =WORKDAY.INTL(E25,0,1,Data!$C$3:$C$60) -> 45989 | F26: 1 | G26: =WORKDAY.INTL(E26,F26,1,Data!$C$3:$C$60) -> 45992 | I26: =WORKDAY.INTL(I25,0,1,Data!$C$3:$C$60) -> 45978 | J26: 1 | K26: =WORKDAY.INTL(I26,J26,1,Data!$C$3:$C$60) -> 45979 | M26: 1 | N26: =_xlfn.LET( _xlpm.s,VALUE($I26), _xlpm.e,VALUE($K26), IF(OR(_xlpm.s="",_xlpm.e=""),"", IF(_xlpm.e<=_xlpm.s, IF(TODAY()>=_xlpm.e,1,0), MAX(0,MIN(1,(TODAY()-_xlpm.s)/(_xlpm.e-_xlpm.s))))) ) -> 1
B28: 4 | C28: DC Works | E28: =MIN(E30:E34) -> 45957 | F28: =G28-E28 -> 9 | G28: =MAX(G30:G34) -> 45966 | I28: =MIN(I30:I34) -> 45957 | J28: =K28-I28 -> 23 | K28: =MAX(K30:K34) -> 45980 | M28: =(J30*M30+J31*M31+J32*M32+J33*M33)/SUM(J30:J33) -> 1 | N28: =(K30*N30+K31*N31+K32*N32+K33*N33)/SUM(K30:K33) -> 1
B30: 4.1 | C30: Mounting Structure delivered | E30: =E19 -> 45957 | F30: 1 | G30: =WORKDAY.INTL(E30,F30,1,Data!$C$3:$C$60) -> 45958 | I30: =I19 -> 45957 | J30: 1 | K30: =WORKDAY.INTL(I30,J30,1,Data!$C$3:$C$60) -> 45958 | M30: 1 | N30: =_xlfn.LET( _xlpm.s,VALUE($I30), _xlpm.e,VALUE($K30), IF(OR(_xlpm.s="",_xlpm.e=""),"", IF(_xlpm.e<=_xlpm.s, IF(TODAY()>=_xlpm.e,1,0), MAX(0,MIN(1,(TODAY()-_xlpm.s)/(_xlpm.e-_xlpm.s))))) ) -> 1
B31: 4.2 | C31: Mounting Structure installation | E31: =WORKDAY.INTL(G30,0,1,Data!$C$3:$C$60) -> 45958 | F31: 4 | G31: =WORKDAY.INTL(E31,F31,1,Data!$C$3:$C$60) -> 45964 | I31: =WORKDAY.INTL(K30,0,1,Data!$C$3:$C$60) -> 45958 | J31: 14 | K31: =WORKDAY.INTL(I31,J31,1,Data!$C$3:$C$60) -> 45978 | M31: 1 | N31: =_xlfn.LET( _xlpm.s,VALUE($I31), _xlpm.e,VALUE($K31), IF(OR(_xlpm.s="",_xlpm.e=""),"", IF(_xlpm.e<=_xlpm.s, IF(TODAY()>=_xlpm.e,1,0), MAX(0,MIN(1,(TODAY()-_xlpm.s)/(_xlpm.e-_xlpm.s))))) ) -> 1
B32: 4.3 | C32: DC Cable delivered | E32: =E30 -> 45957 | F32: 1 | G32: =WORKDAY.INTL(E32,F32,1,Data!$C$3:$C$60) -> 45958 | I32: =I30 -> 45957 | J32: 1 | K32: =WORKDAY.INTL(I32,J32,1,Data!$C$3:$C$60) -> 45958 | M32: 1 | N32: =_xlfn.LET( _xlpm.s,VALUE($I32), _xlpm.e,VALUE($K32), IF(OR(_xlpm.s="",_xlpm.e=""),"", IF(_xlpm.e<=_xlpm.s, IF(TODAY()>=_xlpm.e,1,0), MAX(0,MIN(1,(TODAY()-_xlpm.s)/(_xlpm.e-_xlpm.s))))) ) -> 1
B33: 4.4 | C33: DC Stringing | E33: =WORKDAY.INTL(E37,0,1,Data!$C$3:$C$60)-3 -> 45961 | F33: 3 | G33: =WORKDAY.INTL(E33,F33,1,Data!$C$3:$C$60) -> 45966 | I33: =WORKDAY.INTL(I37,0,1,Data!$C$3:$C$60)-3 -> 45975 | J33: 3 | K33: =WORKDAY.INTL(I33,J33,1,Data!$C$3:$C$60) -> 45980 | M33: 1 | N33: =_xlfn.LET( _xlpm.s,VALUE($I33), _xlpm.e,VALUE($K33), IF(OR(_xlpm.s="",_xlpm.e=""),"", IF(_xlpm.e<=_xlpm.s, IF(TODAY()>=_xlpm.e,1,0), MAX(0,MIN(1,(TODAY()-_xlpm.s)/(_xlpm.e-_xlpm.s))))) ) -> 1
B35: 5 | C35: Module installation | E35: =MIN(E36:E38) -> 45957 | F35: =G35-E35 -> 11 | G35: =MAX(G36:G38) -> 45968 | I35: =MIN(I36:I38) -> 45958 | J35: =K35-I35 -> 24 | K35: =MAX(K36:K38) -> 45982 | M35: =(J36*M36+J37*M37)/SUM(J36:J37) -> 1 | N35: =(K36*N36+K37*N37)/SUM(K36:K37) -> 1
B36: 5.1 | C36: Module delivery | E36: =WORKDAY.INTL(E19,0,1,Data!$C$3:$C$60) -> 45957 | F36: 1 | G36: =WORKDAY.INTL(E36,F36,1,Data!$C$3:$C$60) -> 45958 | I36: =WORKDAY.INTL(K19,0,1,Data!$C$3:$C$60) -> 45958 | J36: 1 | K36: =WORKDAY.INTL(I36,J36,1,Data!$C$3:$C$60) -> 45959 | M36: 1 | N36: =_xlfn.LET( _xlpm.s,VALUE($I36), _xlpm.e,VALUE($K36), IF(OR(_xlpm.s="",_xlpm.e=""),"", IF(_xlpm.e<=_xlpm.s, IF(TODAY()>=_xlpm.e,1,0), MAX(0,MIN(1,(TODAY()-_xlpm.s)/(_xlpm.e-_xlpm.s))))) ) -> 1
B37: 5.2 | C37: Module mounting | E37: =G31 -> 45964 | F37: 4 | G37: =WORKDAY.INTL(E37,F37,1,Data!$C$3:$C$60) -> 45968 | I37: =K31 -> 45978 | J37: 4 | K37: =WORKDAY.INTL(I37,J37,1,Data!$C$3:$C$60) -> 45982 | M37: 1 | N37: =_xlfn.LET( _xlpm.s,VALUE($I37), _xlpm.e,VALUE($K37), IF(OR(_xlpm.s="",_xlpm.e=""),"", IF(_xlpm.e<=_xlpm.s, IF(TODAY()>=_xlpm.e,1,0), MAX(0,MIN(1,(TODAY()-_xlpm.s)/(_xlpm.e-_xlpm.s))))) ) -> 1
B39: 6 | C39: Commissioning | E39: =MIN(E40:E43) -> 45996 | F39: =G39-E39 -> 12 | G39: =MAX(G40:G43) -> 46008 | I39: =MIN(I40:I43) -> 45985 | J39: =K39-I39 -> 9 | K39: =MAX(K40:K43) -> 45994 | M39: =(J40*M40+J41*M41+J42*M42)/SUM(J40:J42) -> 1 | N39: =(K40*N40+K41*N41)/SUM(K40:K41) -> 1
B40: 6.1 | C40: Commissioning | E40: =WORKDAY.INTL(MAX(G21,G28,G35),0,1,Data!$C$3:$C$60) -> 45996 | F40: 1 | G40: =WORKDAY.INTL(E40,F40,1,Data!$C$3:$C$60) -> 45999 | I40: =WORKDAY.INTL(MAX(K21,K28,K35),0,1,Data!$C$3:$C$60) -> 45985 | J40: 1 | K40: =WORKDAY.INTL(I40,J40,1,Data!$C$3:$C$60) -> 45986 | M40: 1 | N40: =_xlfn.LET( _xlpm.s,VALUE($I40), _xlpm.e,VALUE($K40), IF(OR(_xlpm.s="",_xlpm.e=""),"", IF(_xlpm.e<=_xlpm.s, IF(TODAY()>=_xlpm.e,1,0), MAX(0,MIN(1,(TODAY()-_xlpm.s)/(_xlpm.e-_xlpm.s))))) ) -> 1
B41: 6.2 | C41: Practical Completion | E41: =WORKDAY.INTL(G40,0,1,Data!$C$3:$C$60) -> 45999 | F41: 1 | G41: =WORKDAY.INTL(E41,F41,1,Data!$C$3:$C$60) -> 46000 | I41: =WORKDAY.INTL(K40,0,1,Data!$C$3:$C$60) -> 45986 | J41: 1 | K41: =WORKDAY.INTL(I41,J41,1,Data!$C$3:$C$60) -> 45987 | M41: 1 | N41: =_xlfn.LET( _xlpm.s,VALUE($I41), _xlpm.e,VALUE($K41), IF(OR(_xlpm.s="",_xlpm.e=""),"", IF(_xlpm.e<=_xlpm.s, IF(TODAY()>=_xlpm.e,1,0), MAX(0,MIN(1,(TODAY()-_xlpm.s)/(_xlpm.e-_xlpm.s))))) ) -> 1
B42: 6.3 | C42: System Performance Monitoring | E42: =WORKDAY.INTL(G41,0,1,Data!$C$3:$C$60) -> 46000 | F42: 5 | G42: =WORKDAY.INTL(E42,F42,1,Data!$C$3:$C$60) -> 46008 | I42: =WORKDAY.INTL(K41,0,1,Data!$C$3:$C$60) -> 45987 | J42: 5 | K42: =WORKDAY.INTL(I42,J42,1,Data!$C$3:$C$60) -> 45994 | M42: 1 | N42: =_xlfn.LET( _xlpm.s,VALUE($I42), _xlpm.e,VALUE($K42), IF(OR(_xlpm.s="",_xlpm.e=""),"", IF(_xlpm.e<=_xlpm.s, IF(TODAY()>=_xlpm.e,1,0), MAX(0,MIN(1,(TODAY()-_xlpm.s)/(_xlpm.e-_xlpm.s))))) ) -> 1
B44: 7 | C44: QA Inspections | E44: =MIN(E45:E47) -> 45996 | F44: =G44-E44 -> 5 | G44: =MAX(G45:G47) -> 46001 | I44: =MIN(I45:I47) -> 45985 | J44: =K44-I44 -> 3 | K44: =MAX(K45:K47) -> 45988 | M44: =(J45*M45+J46*M46)/SUM(J45:J46) -> 1 | N44: =(K45*N45)/SUM(K45) -> 1
B45: 7.1 | C45: Red-Team Inspection | E45: =WORKDAY.INTL(E40,0,1,Data!$C$3:$C$60) -> 45996 | F45: 1 | G45: =WORKDAY.INTL(E45,F45,1,Data!$C$3:$C$60) -> 45999 | I45: =WORKDAY.INTL(I40,0,1,Data!$C$3:$C$60) -> 45985 | J45: 1 | K45: =WORKDAY.INTL(I45,J45,1,Data!$C$3:$C$60) -> 45986 | M45: 1 | N45: =_xlfn.LET( _xlpm.s,VALUE($I45), _xlpm.e,VALUE($K45), IF(OR(_xlpm.s="",_xlpm.e=""),"", IF(_xlpm.e<=_xlpm.s, IF(TODAY()>=_xlpm.e,1,0), MAX(0,MIN(1,(TODAY()-_xlpm.s)/(_xlpm.e-_xlpm.s))))) ) -> 1
B46: 7.2 | C46: Snags completion | E46: =G45 -> 45999 | F46: 2 | G46: =WORKDAY.INTL(E46,F46,1,Data!$C$3:$C$60) -> 46001 | I46: =K45 -> 45986 | J46: 2 | K46: =WORKDAY.INTL(I46,J46,1,Data!$C$3:$C$60) -> 45988 | M46: 1 | N46: =_xlfn.LET( _xlpm.s,VALUE($I46), _xlpm.e,VALUE($K46), IF(OR(_xlpm.s="",_xlpm.e=""),"", IF(_xlpm.e<=_xlpm.s, IF(TODAY()>=_xlpm.e,1,0), MAX(0,MIN(1,(TODAY()-_xlpm.s)/(_xlpm.e-_xlpm.s))))) ) -> 1
B48: 8 | C48: Project Closure | E48: =MIN(E49:E51) -> 45999 | F48: =G48-E48 -> 10 | G48: =MAX(G49:G51) -> 46009 | I48: =MIN(I49:I51) -> 46055 | J48: =K48-I48 -> 32 | K48: =MAX(K49:K51) -> 46087 | M48: =(J49*M49+J50*M50+J51*M51)/SUM(J49:J51) -> 0.80454545 | N48: =(K46*N46+K42*N42+K49*N49+K50*N50+K51*N51)/SUM(K46:K51) -> 0.79949809
B49: 8.1 | C49: Handover documentation | E49: =WORKDAY.INTL(E46,0,1,Data!$C$3:$C$60) -> 45999 | F49: 2 | G49: =WORKDAY.INTL(E49,F49,1,Data!$C$3:$C$60) -> 46001 | I49: 46055 | J49: 15 | K49: =WORKDAY.INTL(I49,J49,1,Data!$C$3:$C$60) -> 46076 | M49: 1 | N49: =_xlfn.LET( _xlpm.s,VALUE($I49), _xlpm.e,VALUE($K49), IF(OR(_xlpm.s="",_xlpm.e=""),"", IF(_xlpm.e<=_xlpm.s, IF(TODAY()>=_xlpm.e,1,0), MAX(0,MIN(1,(TODAY()-_xlpm.s)/(_xlpm.e-_xlpm.s))))) ) -> 1
B50: 8.2 | C50: Handover to Client | E50: =WORKDAY.INTL(G49,0,1,Data!$C$3:$C$60) -> 46001 | F50: 1 | G50: =WORKDAY.INTL(E50,F50,1,Data!$C$3:$C$60) -> 46002 | I50: 46086 | J50: 1 | K50: =WORKDAY.INTL(I50,J50,1,Data!$C$3:$C$60) -> 46087 | M50: 0 | N50: =_xlfn.LET( _xlpm.s,VALUE($I50), _xlpm.e,VALUE($K50), IF(OR(_xlpm.s="",_xlpm.e=""),"", IF(_xlpm.e<=_xlpm.s, IF(TODAY()>=_xlpm.e,1,0), MAX(0,MIN(1,(TODAY()-_xlpm.s)/(_xlpm.e-_xlpm.s))))) ) -> 0 | O50: ready for handover - Date to be confirmed
B51: 8.3 | C51: Handover to Matriarch | E51: =WORKDAY.INTL(G49,0,1,Data!$C$3:$C$60) -> 46001 | F51: 5 | G51: =WORKDAY.INTL(E51,F51,1,Data!$C$3:$C$60) -> 46009 | I51: =WORKDAY.INTL(K49,0,1,Data!$C$3:$C$60) -> 46076 | J51: 6 | K51: =WORKDAY.INTL(I51,J51,1,Data!$C$3:$C$60) -> 46084 | M51: 0.45 | N51: =_xlfn.LET( _xlpm.s,VALUE($I51), _xlpm.e,VALUE($K51), IF(OR(_xlpm.s="",_xlpm.e=""),"", IF(_xlpm.e<=_xlpm.s, IF(TODAY()>=_xlpm.e,1,0), MAX(0,MIN(1,(TODAY()-_xlpm.s)/(_xlpm.e-_xlpm.s))))) ) -> 1

Sheet Revenue Tracking
B2: HIGH LEVEL PROJECT REVENUE TRACKING
D3: COSTED | F3: ACTUAL | L3: FINANCIAL REVIEW | N3: TIMELINE REVIEW | T3: 2025 Actual Revenue | U3: 2025 Actual COS | V3: 2026 Budget Revenue | W3: 2026 Budget COS | X3: 2026 Actual Revenue | Y3: 2026 Actual COS
B4: 1 | C4: Planned Revenue | D4: ='Project Plan'!E6 -> 1366576.1 | F4: =F21 -> 1366576.2 | N4: Start Date | T4: =SUMIFS('Expenditure Breakdown'!$U:$U, 'Expenditure Breakdown'!$T:$T, ">"&DATE(2024,8,31), 'Expenditure Breakdown'!$T:$T, "<="&DATE(2025,8,31), 'Expenditure Breakdown'!$S:$S, "<>") -> 0 | U4: =SUMIFS('Expenditure Breakdown'!$Q:$Q, 'Expenditure Breakdown'!$T:$T, ">"&DATE(2024,8,31), 'Expenditure Breakdown'!$T:$T, "<="&DATE(2025,8,31), 'Expenditure Breakdown'!$S:$S, "<>") -> 0 | V4: =SUMIFS('Expenditure Breakdown'!$U:$U, 'Expenditure Breakdown'!$T:$T, ">"&DATE(2025,8,31), 'Expenditure Breakdown'!$T:$T, "<="&DATE(2026,8,31)) -> 1366576.1 | W4: =SUMIFS('Expenditure Breakdown'!$Q:$Q, 'Expenditure Breakdown'!$T:$T, ">"&DATE(2025,8,31), 'Expenditure Breakdown'!$T:$T, "<="&DATE(2026,8,31)) -> 926046.77 | X4: =SUMIFS('Expenditure Breakdown'!$U:$U, 'Expenditure Breakdown'!$T:$T, ">"&DATE(2025,8,31), 'Expenditure Breakdown'!$T:$T, "<="&DATE(2026,8,31), 'Expenditure Breakdown'!$S:$S, "<>") -> 1348244.8 | Y4: =SUMIFS('Expenditure Breakdown'!$Q:$Q, 'Expenditure Breakdown'!$T:$T, ">"&DATE(2025,8,31), 'Expenditure Breakdown'!$T:$T, "<="&DATE(2026,8,31), 'Expenditure Breakdown'!$S:$S, "<>") -> 908464.57
B5: 2 | C5: Planned Expenditure | D5: =+'Expenditure Tracking'!F5 -> 1022445.5 | F5: =+'Expenditure Tracking'!H5 -> 926046.77
B6: 3 | C6: Planned Profit | D6: =+D4-D5 -> 344130.69 | F6: =+F4-F5 -> 440529.38 | N6: End Date - PC
B7: 4 | C7: Planned Margin | D7: =+D6/D4 -> 0.25181963 | F7: =+F6/F4 -> 0.32235992
B10: CONTRACT
B12: No. | C12: PAYMENT MILESTONE | E12: % | F12: VALUE | H12: PLANNED PAYMENT DATE | L12: INVOICE NUMBER | N12: INVOICE RAISED DATE | P12: PAYMENT RECEIVED DATE | R12: MILESTONE NOTES & COMMENTS
B13: 1 | C13: Acceptance and Initial Deposit | E13: 0.5 | F13: =$D$4*E13 -> 683288.07 | H13: 45920 | L13: 004839 | N13: 45912 | P13: 45938
B14: 2 | C14: Delivery of Panels | E14: 0.25 | F14: =$D$4*E14 -> 341644.04 | H14: ='Project Plan'!E36+7 -> 45964 | L14: 004872 | N14: 45961 | P14: 45975
B15: 3 | C15: Delivery of Inverters | E15: 0.1 | F15: =$D$4*E15 -> 136657.61 | H15: ='Project Plan'!E22+7 -> 45965 | L15: 004872 | N15: 45961 | P15: 45975
B16: 4 | C16: Practical Completion | E16: 0.05 | F16: =$D$4*E16 -> 68328.807 | H16: ='Project Plan'!G39+7 -> 46015 | L16: 004885 | N16: 45989 | P16: 46002
B17: 5 | C17: Handover | E17: 0.1 | F17: =$D$4*E17 -> 136657.61 | H17: ='Project Plan'!G51+7 -> 46016 | P17: 46265 | R17: SSEG export received
B18: 6 | C18: - | E18: 0 | F18: =$D$4*E18 -> 0
B19: 7 | C19: - | E19: 0 | F19: =$D$4*E19 -> 0
E21: =SUM(E13:E19) -> 1 | F21: =SUM(F13:F19) -> 1366576.2
B23: KEY: | C23: contains an error (in result or a check has failed)
C24: Red Font - IF TEXT : content not yet confirmed
C25: Red Font - IF NUMBER: Negative value
C26: Anything in yellow is a concern or risk for noting or action
C27: confirmed
C28: [ADD INITIALS: comment for noting in square brackets, use colour or red to draw attention if important]
C29: [RT: When adding rows into sheet, ensure you insert between first and last row of each category]
C30: end of sheet - do not insert information below/beyond this
B40: No. | C40: PAYMENT MILESTONE | E40: % | F40: VALUE
B41: 1 | C41: Deposit - Project commencement | E41: 0.35 | F41: =$F$47*E41 -> 478301.65
B42: 2 | C42: Delivery of Panels | E42: 0.3 | F42: =$F$47*E42 -> 409972.85
B43: 3 | C43: Delivery of Inverters | E43: 0.2 | F43: =$F$47*E43 -> 273315.23
B44: 4 | C44: Practical Completion | E44: 0.1 | F44: =$F$47*E44 -> 136657.62
B45: 5 | C45: Handover | E45: 0.05 | F45: =$F$47*E45 -> 68328.808
C46: Total | E46: =SUM(E41:E45) -> 1 | F46: =SUM(F41:F45) -> 1366576.2
E47: =SUM(E41:E45) -> 1 | F47: =F21 -> 1366576.2

Sheet Compliance
B2: HSE
B4: Description | C4: Status | D4: Approved By | E4: Date | F4: Results / Comments
B5: NOC
B6: 7.1 Agreement
B7: 13.2 Agreement
B8: EE File
B9: Subbie File
B16: SSEG
B18: Description | C18: Status | D18: Approved By | E18: Date | F18: Results / Comments
B19: SSEG Application
B20: PTI
B21: Commissioning Approval
B22: NERSA Registration

Sheet Data
C2: Public holidays | F2: Drop down list
C3: 45658 | D3: New Years Day | F3: Approved
C4: 45737 | D4: Human Rights day | F4: Pending
C5: 45765 | D5: Good Friday | F5: Declined
C6: 45768 | D6: Family Day | F6: Abanded
C7: 45774 | D7: Freedom Day
C8: 45765 | D8: Freedom DayObserved
C9: 45778 | D9: Workers day
C10: 45824 | D10: Youth Day Holiday
C11: 45878 | D11: Womens Day
C12: 45924 | D12: Heritage Day
C13: 46007 | D13: Day of Reconciliation | H13: Manual dates
C14: 46016 | D14: Christmas Day
C15: 46017 | D15: Day of Goodwill

Sheet Expenditure Tracking
B2: HIGH LEVEL PROJECT EXPENDITURE TRACKING
F4: COSTED | H4: ACTUAL | J4: Difference from costed
B5: EXPENDITURE | F5: =SUM(F9:F23) -> 1022445.5 | H5: =SUM(H9:H23) -> 926046.77 | J5: =SUM(J9:J23) -> 96398.684
B7: No. | D7: Item | F7: Costed Expenditure | H7: Actual Expenditure | J7: Saving / Overrun | L7: Comments on variations from planned expenditure
B9: ='Expenditure Breakdown'!L6 -> 1 | D9: ='Expenditure Breakdown'!M6 -> 1. Panels | F9: ='Expenditure Breakdown'!I6 -> 356365.6 | H9: ='Expenditure Breakdown'!X6 -> 295114.07 | J9: =F9-H9 -> 61251.53
B10: ='Expenditure Breakdown'!L13 -> 2 | D10: ='Expenditure Breakdown'!M13 -> 2. Inverters | F10: ='Expenditure Breakdown'!I13 -> 80000 | H10: ='Expenditure Breakdown'!X13 -> 53700.89 | J10: =F10-H10 -> 26299.11
B11: ='Expenditure Breakdown'!L21 -> 3 | D11: ='Expenditure Breakdown'!M21 -> 3. Mounting Structures | F11: ='Expenditure Breakdown'!I21 -> 65884.5 | H11: ='Expenditure Breakdown'!X21 -> 27717.31 | J11: =F11-H11 -> 38167.19
B12: ='Expenditure Breakdown'!L35 -> 4 | D12: ='Expenditure Breakdown'!M35 -> 4. DC Equipment | F12: ='Expenditure Breakdown'!I35 -> 123532.2 | H12: ='Expenditure Breakdown'!X35 -> 120587.7 | J12: =F12-H12 -> 2944.5
B13: ='Expenditure Breakdown'!L51 -> 5 | D13: ='Expenditure Breakdown'!M51 -> 5. Monitoring | F13: ='Expenditure Breakdown'!I51 -> 38000 | H13: ='Expenditure Breakdown'!X51 -> 11357.5 | J13: =F13-H13 -> 26642.5
B14: ='Expenditure Breakdown'!L59 -> 6 | D14: ='Expenditure Breakdown'!M59 -> 6. AC Equipment | F14: ='Expenditure Breakdown'!I59 -> 164965.25 | H14: ='Expenditure Breakdown'!X59 -> 64740.3 | J14: =F14-H14 -> 100224.95
B15: ='Expenditure Breakdown'!L77 -> 7 | D15: ='Expenditure Breakdown'!M77 -> 7.BESS | F15: ='Expenditure Breakdown'!I77 -> 0 | H15: ='Expenditure Breakdown'!X77 -> 0 | J15: =F15-H15 -> 0
B16: ='Expenditure Breakdown'!L86 -> 8 | D16: ='Expenditure Breakdown'!M86 -> 8. Product Add On | F16: ='Expenditure Breakdown'!I86 -> 0 | H16: ='Expenditure Breakdown'!X86 -> 5900 | J16: =F16-H16 -> -5900
B17: ='Expenditure Breakdown'!L96 -> 9 | D17: ='Expenditure Breakdown'!M96 -> 9. AC & DC installation | F17: ='Expenditure Breakdown'!I96 -> 117067.5 | H17: ='Expenditure Breakdown'!X96 -> 175544.1 | J17: =F17-H17 -> -58476.6
B18: ='Expenditure Breakdown'!L109 -> 10 | D18: ='Expenditure Breakdown'!M109 -> 10. Site Logistics | F18: ='Expenditure Breakdown'!I109 -> 27587.867 | H18: ='Expenditure Breakdown'!X109 -> 113120.5 | J18: =F18-H18 -> -85532.633
B19: ='Expenditure Breakdown'!L125 -> 11 | D19: ='Expenditure Breakdown'!M125 -> 11. Due Dilligence | F19: ='Expenditure Breakdown'!I125 -> 34000 | H19: ='Expenditure Breakdown'!X125 -> 25050 | J19: =F19-H19 -> 8950
B20: ='Expenditure Breakdown'!L131 -> 12 | D20: ='Expenditure Breakdown'!M131 -> 12. BDP Commission | F20: ='Expenditure Breakdown'!I131 -> 0 | H20: ='Expenditure Breakdown'!X131 -> 0 | J20: =F20-H20 -> 0
B21: ='Expenditure Breakdown'!L134 -> 13 | D21: ='Expenditure Breakdown'!M135 -> 13. Engineering | F21: ='Expenditure Breakdown'!I134 -> 12592.536 | H21: ='Expenditure Breakdown'!X134 -> 17082.202 | J21: =F21-H21 -> -4489.6654
B22: ='Expenditure Breakdown'!L141 -> 14 | D22: ='Expenditure Breakdown'!M141 -> 14. General Expenses | F22: ='Expenditure Breakdown'!I141 -> 2450 | H22: ='Expenditure Breakdown'!X141 -> 2132.2 | J22: =F22-H22 -> 317.8
B23: ='Expenditure Breakdown'!L154 -> 15 | D23: ='Expenditure Breakdown'!M154 -> 15. Service Add On | F23: ='Expenditure Breakdown'!I154 -> 0 | H23: ='Expenditure Breakdown'!X154 -> 14000 | J23: =F23-H23 -> -14000
D25: check: | F25: ='Expenditure Breakdown'!I2-'Expenditure Tracking'!F5 -> 0 | G25: =#REF!-G5 -> #REF! | H25: ='Expenditure Breakdown'!X2-H5 -> 0

Sheet Expenditure Breakdown
B2: COSTED EXPENDITURE BREAKDOWN | I2: =SUM(I6:I166) -> 1022445.5 | J2: =SUM(J6:J166) -> 1366576.2 | L2: ACTUAL EXPENDITURE BREAKDOWN | R2: FINANCE ONLY | X2: =SUM(X6:X166) -> 926046.77
B4: No. | C4: Product / Service | D4: Description of Work | E4: QTY | F4: Rate / Unit | G4: Budget Total | H4: FORECASTED PAYMENT DATE | I4: Total COS | J4: =IF(J2-'Revenue Tracking'!D4>=0, "Total Revenue", "ERROR on REV" ) -> Total Revenue | L4: No. | M4: Product/ Service | N4: Description of Work | O4: QTY | P4: Rate / Unit | Q4: Actual Total | R4: PO NUMBER | S4: INVOICE NUMBER | T4: INVOICE RAISED DATE | U4: REVENUE RECOGNITION AMOUNT | V4: CHECK | W4: FINANCE PAYMENT DATE | X4: Total COS
B6: 1 | C6: Panels | D6: Panels Budget | G6: =D167 -> 356365.6 | H6: ='Project Plan'!E36+60 -> 46017 | I6: =SUM(G6:G11) -> 356365.6 | J6: =F167 -> 494952.22 | L6: 1 | M6: 1. Panels | N6: Panels Budget - Longi 610W | O6: 241 | P6: =1.85*610 -> 1128.5 | Q6: =O6*P6 -> 271968.5 | S6: Krannich - 15-10014204 | T6: 45961 | U6: 458160.11 | V6: =J6-SUM(U6:U11) -> 0 | W6: 45989 | X6: =SUM(Q6:Q11) -> 295114.07
B7: 1 | D7: Delivery Budget | L7: 1 | M7: 1. Panels | N7: EPR Fees | Q7: 5849.67 | S7: Krannich - 15-10014204 | T7: 45961 | U7: 9854.3966 | W7: 45989
B8: 1 | L8: 1 | M8: 1. Panels | N8: Delivery | Q8: 15990.5 | S8: Krannich - 15-10014204 | T8: 45961 | U8: 26937.713 | W8: 45989
B9: 1 | L9: 1 | M9: 1. Panels | N9: Longi 610w | Q9: 1305.4 | S9: IBC Solar - ZA42502733 | T9: 45991 | U9: 0 | W9: 45980
B10: 1 | L10: 1 | M10: 1. Panels | T10: =IF(W10>1,EOMONTH(W10,0),"") | U10: 0
B11: 1 | L11: 1 | M11: 1. Panels | T11: =IF(W11>1,EOMONTH(W11,0),"") | U11: 0 | Y11: BUDGET | Z11: Installer Allocation
T12: =IF(W12>1,EOMONTH(W12,0),"") | Y12: AC Equipment | Z12: =G59 -> 164965.25
B13: 2 | C13: Inverters | D13: Inverter Budget | G13: =D168 -> 80000 | H13: ='Project Plan'!E22+60 -> 46018 | I13: =SUM(G13:G19) -> 80000 | J13: =F168 -> 111111.11 | L13: 2 | M13: 2. Inverters | N13: SMA Core 2 | O13: 1 | P13: 53700.89 | Q13: =O13*P13 -> 53700.89 | S13: Krannich - 15-10014204 | T13: 45961 | U13: 111111.11 | V13: =J13-SUM(U13:U19) -> 0 | W13: 45989 | X13: =SUM(Q13:Q19) -> 53700.89 | Y13: DC Equipment | Z13: =G36 -> 75400.2
B14: 2 | L14: 2 | M14: 2. Inverters | T14: =IF(W14>1,EOMONTH(W14,0),"") | U14: 0 | Y14: AC Labour | Z14: =G96 -> 36602.5
B15: 2 | L15: 2 | M15: 2. Inverters | T15: =IF(W15>1,EOMONTH(W15,0),"") | U15: 0 | Y15: DC Labour | Z15: =G97 -> 80465
B16: 2 | L16: 2 | M16: 2. Inverters | T16: =IF(W16>1,EOMONTH(W16,0),"") | U16: 0 | Y16: Offloading | Z16: =G109 -> 8500
B17: 2 | L17: 2 | M17: 2. Inverters | T17: =IF(W17>1,EOMONTH(W17,0),"") | U17: 0 | Y17: Scaffolding | Z17: =G110 -> 12367.867
B18: 2 | L18: 2 | M18: 2. Inverters | T18: =IF(W18>1,EOMONTH(W18,0),"") | U18: 0 | Y18: Storage | Z18: =G112 -> 0
B19: 2 | L19: 2 | M19: 2. Inverters | T19: =IF(W19>1,EOMONTH(W19,0),"") | U19: 0 | Y19: Telehandler | Z19: 0
T20: =IF(W20>1,EOMONTH(W20,0),"")
B21: 3 | C21: Mounting Structures | D21: Structure Budget | G21: =D169 -> 65884.5 | H21: ='Project Plan'!E30+30 -> 45987 | I21: =SUM(G21:G33) -> 65884.5 | J21: =F169 -> 91506.25 | L21: 3 | M21: 3. Mounting Structures | Q21: 9972 | R21: PO4402-MVE2-20251023 - RV Approved | S21: Schletter Inv: 2352 | T21: 45961 | U21: 24789.933 | V21: =J21-SUM(U21:U33) -> 0.0021012115 | W21: 45989 | X21: =SUM(Q21:Q33) -> 27717.31 | Y21: Other | Z21: 0
B22: 3 | L22: 3 | M22: 3. Mounting Structures | N22: Seam clamp Pro551/4 | Q22: 15552 | R22: PO4428-MVE2-20251030 - RV Approved | S22: Schletter - INV2378 | T22: 45991 | U22: 38661.554 | W22: 46021 | Y22: Total | Z22: =SUM(Z12:Z21) -> 378300.82
L23: 3 | M23: 3. Mounting Structures | N23: 40x End Clamps - Busamed Medical | Q23: 451.6 | S23: Allocated from Cpt Storeoom | T23: 45961 | U23: 1122.6568 | W23: =T23 -> 45961
L24: 3 | M24: 3. Mounting Structures | N24: End Clamps | O24: 73 | P24: 10.96 | Q24: =O24*P24 -> 800.08 | S24: Allocated from Cpt Storeoom | T24: 45961 | U24: 1988.962 | W24: =T24 -> 45961
L25: 3 | M25: 3. Mounting Structures | N25: End Clamps | O25: 23 | P25: 11.52 | Q25: =O25*P25 -> 264.96 | S25: Allocated from Cpt Storeoom | T25: 45961 | U25: 658.67836 | W25: =T25 -> 45961
L26: 3 | M26: 3. Mounting Structures | N26: 548x Mid Clamps - Northpoint | Q26: 6000.6 | S26: Allocared from Cpt Storeoom | T26: 45961 | U26: 14917.215 | W26: =T26 -> 45961
L27: 3 | M27: 3. Mounting Structures | N27: 119x Clampfit Pro - The Studios | O27: 119 | P27: 22.73 | Q27: =O27*P27 -> 2704.87 | S27: Allocated from The Sudios | T27: 45961 | U27: 6724.1823 | W27: =T27 -> 45961
L28: 3 | M28: 3. Mounting Structures | N28: 1200x Schletter 6 x 25 screws (No Cost on Stock Sheet) | T28: 45961 | U28: 0 | W28: =T28 -> 45961
L29: 3 | M29: 3. Mounting Structures | N29: 136x Clampfit Pro - (No Cost on Stock Sheet) | T29: 45961 | U29: 0 | W29: =T29 -> 45961
B30: 3 | L30: 3 | M30: 3. Mounting Structures | N30: 100x Schletter 6 x 25 screws (No Cost on Stock Sheet) | T30: 45961 | U30: 0 | W30: =T30 -> 45961 | Y30: Less 15% | Z30: =+Z22*0.85 -> 321555.7
B31: 3 | L31: 3 | M31: 3. Mounting Structures | N31: Delivery of MS | Q31: 1063.2 | S31: DSV Inv: 180153158 | T31: 45961 | U31: 2643.0663 | W31: 45991 | Y31: R/Wp | Z31: =Z30/'Project Plan'!$E$3/1000 -> 2.1874537
B32: 3 | L32: 3 | M32: 3. Mounting Structures | N32: Clampfit Pro - Returned | Q32: -9092 | S32: Schletter - CRN0281 | T32: 45991 | U32: 0 | W32: 46022
B33: 3 | L33: 3 | M33: 3. Mounting Structures | T33: =IF(W33>1,EOMONTH(W33,0),"") | U33: =(Q33/$X$21*$J$21) -> 0 | Y33: ACTUAL | Z33: Installer - JA Electrical | AB33: ACTUAL | AC33: Installer - Cosmic Sun
T34: =IF(W34>1,EOMONTH(W34,0),"") | Y34: =Y12 -> AC Equipment | Z34: 64740.3 | AB34: AC Equipment | AC34: 60700
B35: 4 | C35: DC Equipment | D35: DC Cable Budget | E35: =G35/14*1.15 -> 3953.7 | G35: 48132 | H35: ='Project Plan'!E32+60 -> 46017 | I35: =SUM(G35:G49) -> 123532.2 | J35: =F170 -> 171572.5 | L35: 4 | M35: 4. DC Equipment | N35: DC Cable | O35: 6000 | P35: 13.65 | Q35: =O35*P35+1000 -> 82900 | S35: Menlo - INV0003367 | T35: 45961 | U35: 117950.34 | V35: =J35-SUM(U35:U49) -> 0 | W35: 46021 | X35: =SUM(Q35:Q49) -> 120587.7 | Y35: =Y13 -> DC Equipment | Z35: 37687.7 | AB35: DC Equipment | AC35: 54780.55
B36: 4 | D36: DC Equipment Budget | G36: =D170-G35 -> 75400.2 | H36: ='Project Plan'!G28 -> 45966 | L36: 4 | M36: 4. DC Equipment | T36: =IF(W36>1,EOMONTH(W36,0),"") | U36: =(Q36/$X$35*$J$35) -> 0 | Y36: =Y14 -> AC Labour | Z36: 42332.45 | AA36: =Z36/147000 -> 0.28797585 | AB36: AC Labour | AC36: 48510 | AD36: =AC36/147000 -> 0.33
B37: 4 | L37: 4 | M37: 4. DC Equipment | T37: =IF(W37>1,EOMONTH(W37,0),"") | U37: =(Q37/$X$35*$J$35) -> 0 | Y37: =Y15 -> DC Labour | Z37: 133211.65 | AB37: DC Labour | AC37: 105840
B38: 4 | L38: 4 | M38: 4. DC Equipment | T38: =IF(W38>1,EOMONTH(W38,0),"") | U38: =(Q38/$X$35*$J$35) -> 0 | Y38: =Y16 -> Offloading | Z38: 11410 | AB38: Offloading | AC38: 6600
B39: 4 | L39: 4 | M39: 4. DC Equipment | N39: Project Kick Off | O39: =Z35 -> 37687.7 | P39: 0.1 | Q39: =$O$39*P39 -> 3768.77 | R39: PO4403-MVE2-20251023 - RV Approved | S39: JA Electrical INV 111 | T39: =T97 -> 45961 | U39: 5362.216 | W39: =W97 -> 45967 | Y39: =Y17 -> Scaffolding | Z39: 67201 | AB39: Scaffolding | AC39: 8250
B40: 4 | L40: 4 | M40: 4. DC Equipment | N40: Site Establishment | P40: 0.15 | Q40: =$O$39*P40 -> 5653.155 | S40: JA Electrical INV 1117 | T40: =T98 -> 45991 | U40: 8043.324 | W40: =W98 -> 46015 | Y40: =Y18 -> Storage | Z40: 9988 | AB40: Storage | AC40: 6600
B41: 4 | L41: 4 | M41: 4. DC Equipment | N41: AC Installation Complete | P41: 0.2 | Q41: =$O$39*P41 -> 7537.54 | S41: JA Electrical INV 1129 | T41: =T99 -> 45991 | U41: 10724.432 | W41: 46009 | Y41: Logistics | Z41: 0 | AB41: Logistics | AC41: 0
B42: 4 | L42: 4 | M42: 4. DC Equipment | N42: DC Installation Complete | P42: 0.25 | Q42: =$O$39*P42 -> 9421.925 | S42: JA Electrical INV 1132 | T42: =T100 -> 45991 | U42: 13405.54 | W42: 46009 | Y42: HSE | Z42: 17381.5 | AB42: HSE | AC42: 4500
B43: 4 | L43: 4 | M43: 4. DC Equipment | N43: Commissioning Complete | P43: 0.1 | Q43: =$O$39*P43 -> 3768.77 | S43: JA Electrical INV 1133 | T43: =T101 -> 45991 | U43: 5362.216 | W43: 46009 | Y43: Other | Z43: 0 | AB43: Other | AC43: 0
B44: 4 | L44: 4 | M44: 4. DC Equipment | N44: Site De-establisment | P44: 0.1 | Q44: =$O$39*P44 -> 3768.77 | S44: JA Electrical INV 1134 | T44: =T102 -> 45991 | U44: 5362.216 | W44: =W102 -> 46058 | Y44: Other | Z44: 0 | AB44: Other | AC44: 0
B45: 4 | L45: 4 | M45: 4. DC Equipment | N45: Handover Document Complete | P45: 0.05 | Q45: =$O$39*P45 -> 1884.385 | S45: JA Electrical INV 1135 | T45: =T103 -> 45991 | U45: 2681.108 | W45: =W103 -> 46058 | Y45: Total | Z45: =SUM(Z34:Z44) -> 383952.6 | AB45: Total | AC45: =SUM(AC34:AC44) -> 295780.55
B46: 4 | L46: 4 | M46: 4. DC Equipment | N46: End of Defects Period | P46: 0.05 | Q46: =$O$39*P46 -> 1884.385 | S46: JA Electrical INV 1136 | T46: =T104 -> 45991 | U46: 2681.108 | W46: =W104 -> 46088 | Y46: R/Wp | Z46: =Z45/'Project Plan'!$E$3/1000 -> 2.6119224 | AB46: R/Wp | AC46: =AC45/'Project Plan'!$E$3/1000 -> 2.0121126
B47: 4 | L47: 4 | M47: 4. DC Equipment | T47: =IF(W47>1,EOMONTH(W47,0),"") | U47: =(Q47/$X$35*$J$35) -> 0
B48: 4 | L48: 4 | M48: 4. DC Equipment | T48: =IF(W48>1,EOMONTH(W48,0),"") | U48: =(Q48/$X$35*$J$35) -> 0
B49: 4 | L49: 4 | M49: 4. DC Equipment | T49: =IF(W49>1,EOMONTH(W49,0),"") | U49: =(Q49/$X$35*$J$35) -> 0
T50: =IF(W50>1,EOMONTH(W50,0),"")
B51: 5 | C51: Monitoring | D51: Monitoring Budget | G51: =D172 -> 38000 | H51: =H13 -> 46018 | I51: =SUM(G51:G57) -> 38000 | J51: =F172 -> 52777.778 | L51: 5 | M51: 5. Monitoring | U51: =(Q51/$X$51*$J$51) -> 0 | V51: =J51-SUM(U51:U57) -> 0.001540037 | X51: =SUM(Q51:Q57) -> 11357.5
B52: 5 | H52: =H51 -> 46018 | L52: 5 | M52: 5. Monitoring | U52: =(Q52/$X$51*$J$51) -> 0
B53: 5 | L53: 5 | M53: 5. Monitoring | N53: Techsitter | Q53: 11169 | R53: Roedolph to confirm cost, what happened to PH1 meter? | S53: Matriarch Inv: 6200 | T53: 46053 | U53: 52433.337 | W53: 46051
B54: 5 | L54: 5 | M54: 5. Monitoring | N54: Delivery of Techsitter & CT's | Q54: 188.5 | S54: DSV Inv: 180156055 | T54: 45991 | U54: 344.43925 | W54: 46021
B55: 5 | L55: 5 | M55: 5. Monitoring | U55: =(Q55/$X$51*$J$51) -> 0
B56: 5 | L56: 5 | M56: 5. Monitoring | U56: =(Q56/$X$51*$J$51) -> 0
B57: 5 | L57: 5 | M57: 5. Monitoring | U57: =(Q57/$X$51*$J$51) -> 0
T58: =IF(W58>1,EOMONTH(W58,0),"")
B59: 6 | C59: AC Equipment | D59: AC Equipment Budget | G59: =D171 -> 164965.25 | H59: ='Project Plan'!G24+30 -> 46019 | I59: =SUM(G59:G75) -> 164965.25 | J59: =F171 -> 229118.41 | L59: 6 | M59: 6. AC Equipment | T59: =IF(W59>1,EOMONTH(W59,0),"") | U59: =(Q59/$X$59*$J$59) -> 0 | V59: =J59-SUM(U59:U75) -> 0 | X59: =SUM(Q59:Q75) -> 64740.3
B60: 6 | L60: 6 | M60: 6. AC Equipment | U60: =(Q60/$X$59*$J$59) -> 0
B61: 6 | L61: 6 | M61: 6. AC Equipment | T61: =IF(W61>1,EOMONTH(W61,0),"") | U61: =(Q61/$X$59*$J$59) -> 0
B62: 6 | L62: 6 | M62: 6. AC Equipment | T62: =IF(W62>1,EOMONTH(W62,0),"") | U62: =(Q62/$X$59*$J$59) -> 0
B63: 6 | L63: 6 | M63: 6. AC Equipment | T63: =IF(W63>1,EOMONTH(W63,0),"") | U63: =(Q63/$X$59*$J$59) -> 0
B64: 6 | L64: 6 | M64: 6. AC Equipment | T64: =IF(W64>1,EOMONTH(W64,0),"") | U64: =(Q64/$X$59*$J$59) -> 0
B65: 6 | L65: 6 | M65: 6. AC Equipment | N65: Project Kick Off | O65: =Z34 -> 64740.3 | P65: 0.1 | Q65: =$O$65*P65 -> 6474.03 | R65: PO4403-MVE2-20251023 - RV Approved | S65: JA Electrical INV 111 | T65: =T97 -> 45961 | U65: 22911.841 | W65: =W97 -> 45967
B66: 6 | L66: 6 | M66: 6. AC Equipment | N66: Site Establishment | P66: 0.15 | Q66: =$O$65*P66 -> 9711.045 | S66: JA Electrical INV 1117 | T66: =T98 -> 45991 | U66: 34367.761 | W66: =W98 -> 46015
B67: 6 | L67: 6 | M67: 6. AC Equipment | N67: AC Installation Complete | P67: 0.2 | Q67: =$O$65*P67 -> 12948.06 | S67: JA Electrical INV 1129 | T67: =T99 -> 45991 | U67: 45823.681 | W67: 46009
B68: 6 | L68: 6 | M68: 6. AC Equipment | N68: DC Installation Complete | P68: 0.25 | Q68: =$O$65*P68 -> 16185.075 | S68: JA Electrical INV 1132 | T68: =T100 -> 45991 | U68: 57279.601 | W68: 46009
B69: 6 | L69: 6 | M69: 6. AC Equipment | N69: Commissioning Complete | P69: 0.1 | Q69: =$O$65*P69 -> 6474.03 | S69: JA Electrical INV 1133 | T69: =T101 -> 45991 | U69: 22911.841 | W69: 46009
B70: 6 | L70: 6 | M70: 6. AC Equipment | N70: Site De-establisment | P70: 0.1 | Q70: =$O$65*P70 -> 6474.03 | S70: JA Electrical INV 1134 | T70: =T102 -> 45991 | U70: 22911.841 | W70: =W102 -> 46058
B71: 6 | L71: 6 | M71: 6. AC Equipment | N71: Handover Document Complete | P71: 0.05 | Q71: =$O$65*P71 -> 3237.015 | S71: JA Electrical INV 1135 | T71: =T103 -> 45991 | U71: 11455.92 | W71: =W103 -> 46058
B72: 6 | L72: 6 | M72: 6. AC Equipment | N72: End of Defects Period | P72: 0.05 | Q72: =$O$65*P72 -> 3237.015 | S72: JA Electrical INV 1136 | T72: =T104 -> 45991 | U72: 11455.92 | W72: =W104 -> 46088
B73: 6 | L73: 6 | M73: 6. AC Equipment | T73: =IF(W73>1,EOMONTH(W73,0),"") | U73: =(Q73/$X$59*$J$59) -> 0
B74: 6 | L74: 6 | M74: 6. AC Equipment | T74: =IF(W74>1,EOMONTH(W74,0),"") | U74: =(Q74/$X$59*$J$59) -> 0
B75: 6 | L75: 6 | M75: 6. AC Equipment | T75: =IF(W75>1,EOMONTH(W75,0),"") | U75: =(Q75/$X$59*$J$59) -> 0
T76: =IF(W76>1,EOMONTH(W76,0),"")
B77: 7 | C77: BESS | I77: =SUM(G77:G84) -> 0 | J77: =F176 -> 0 | L77: 7 | M77: 7.BESS | V77: =J77-SUM(U77:U84) -> 0 | X77: =SUM(Q77:Q84) -> 0
B78: 7 | L78: 7 | M78: 7.BESS
B79: 7 | L79: 7 | M79: 7.BESS
B80: 7 | L80: 7 | M80: 7.BESS
B81: 7 | L81: 7 | M81: 7.BESS
B82: 7 | L82: 7 | M82: 7.BESS
B83: 7 | L83: 7 | M83: 7.BESS
B84: 7 | L84: 7 | M84: 7.BESS
B86: 8 | C86: Product Add On | I86: =SUM(G86:G94) -> 0 | J86: =F175 -> 0 | L86: 8 | M86: 8. Product Add On | T86: =IF(W86>1,EOMONTH(W86,0),"") | V86: =J86-SUM(U86:U94) -> 0 | X86: =SUM(Q86:Q94) -> 5900
B87: 8 | L87: 8 | M87: 8. Product Add On | N87: Inverter Awning - JRL Eng | Q87: 5900 | R87: PO4504-MVE2-20251128 - RV Approved | S87: JRL Engineering INV00427 | T87: 45991 | W87: 46021
B88: 8 | L88: 8 | M88: 8. Product Add On
B89: 8 | L89: 8 | M89: 8. Product Add On
B90: 8 | L90: 8 | M90: 8. Product Add On
B91: 8 | L91: 8 | M91: 8. Product Add On
B92: 8 | L92: 8 | M92: 8. Product Add On
B93: 8 | L93: 8 | M93: 8. Product Add On
B94: 8 | L94: 8 | M94: 8. Product Add On
K95: Only services to be capture below, products above | T95: =IF(W95>1,EOMONTH(W95,0),"")
B96: 9 | C96: AC & DC Installation | D96: AC Installation Budget | G96: =D180 -> 36602.5 | H96: ='Project Plan'!G21+7 -> 46003 | I96: =SUM(G96:G107) -> 117067.5 | J96: =F180+F181 -> 130075 | L96: 9 | M96: 9. AC & DC installation | T96: =IF(W96>1,EOMONTH(W96,0),"") | U96: =(Q96/$X$96*$J$96) -> 0 | V96: =J96-SUM(U96:U107) -> 0 | X96: =SUM(Q96:Q107) -> 175544.1
B97: 9 | D97: DC Installation Budget | G97: =D181 -> 80465 | H97: ='Project Plan'!G28+7 -> 45973 | L97: 9 | M97: 9. AC & DC installation | N97: Project Kick Off | O97: =Z37+Z36 -> 175544.1 | P97: 0.1 | Q97: =$O$97*P97 -> 17554.41 | R97: PO4403-MVE2-20251023 - RV Approved | S97: JA Electrical INV 111 | T97: 45961 | U97: 13007.5 | W97: 45967
B98: 9 | L98: 9 | M98: 9. AC & DC installation | N98: Site Establishment | P98: 0.15 | Q98: =$O$97*P98 -> 26331.615 | S98: JA Electrical INV 1117 | T98: 45991 | U98: 19511.25 | W98: 46015
B99: 9 | L99: 9 | M99: 9. AC & DC installation | N99: AC Installation Complete | P99: 0.2 | Q99: =$O$97*P99 -> 35108.82 | S99: JA Electrical INV 1129 | T99: 45991 | U99: 26015 | W99: 46009
B100: 9 | L100: 9 | M100: 9. AC & DC installation | N100: DC Installation Complete | P100: 0.25 | Q100: =$O$97*P100 -> 43886.025 | S100: JA Electrical INV 1132 | T100: 45991 | U100: 32518.75 | W100: 46003
B101: 9 | L101: 9 | M101: 9. AC & DC installation | N101: Commissioning Complete | P101: 0.1 | Q101: =$O$97*P101 -> 17554.41 | S101: JA Electrical INV 1133 | T101: 45991 | U101: 13007.5 | W101: 46374
B102: 9 | L102: 9 | M102: 9. AC & DC installation | N102: Site De-establisment | P102: 0.1 | Q102: =$O$97*P102 -> 17554.41 | S102: JA Electrical INV 1134 | T102: 45991 | U102: 13007.5 | W102: 46058
B103: 9 | L103: 9 | M103: 9. AC & DC installation | N103: Handover Document Complete | P103: 0.05 | Q103: =$O$97*P103 -> 8777.205 | S103: JA Electrical INV 1135 | T103: 45991 | U103: 6503.75 | W103: =W102 -> 46058
B104: 9 | L104: 9 | M104: 9. AC & DC installation | N104: End of Defects Period | P104: 0.05 | Q104: =$O$97*P104 -> 8777.205 | S104: JA Electrical INV 1136 | T104: 45991 | U104: 6503.75 | W104: =W103+30 -> 46088
...

Sheet Cashflow
D1: [RT: Double Check the first date is always a MONDAY] | F1: 45677 | G1: =F1+7 -> 45684 | H1: =G1+7 -> 45691 | I1: =H1+7 -> 45698 | J1: =I1+7 -> 45705 | K1: =J1+7 -> 45712 | L1: =K1+7 -> 45719 | M1: =L1+7 -> 45726 | N1: =M1+7 -> 45733 | ... LD1: =LC1+7 -> 47847
A2: PLANNED | C2: CHECK | D2: CHECK
B3: Planned Revenue | C3: ='Revenue Tracking'!D4 -> 1366576.1 | D3: =SUM(F3:LD3) -> 1366576.1 | F3: =SUMIFS('Revenue Tracking'!$F$13:$F$19, 'Revenue Tracking'!$H$13:$H$19, ">="&F1,'Revenue Tracking'!$H$13:$H$19, "<"&G1) -> 0 | G3: =SUMIFS('Revenue Tracking'!$F$13:$F$19, 'Revenue Tracking'!$H$13:$H$19, ">="&G1,'Revenue Tracking'!$H$13:$H$19, "<"&H1) -> 0 | H3: =SUMIFS('Revenue Tracking'!$F$13:$F$19, 'Revenue Tracking'!$H$13:$H$19, ">="&H1,'Revenue Tracking'!$H$13:$H$19, "<"&I1) -> 0 | I3: =SUMIFS('Revenue Tracking'!$F$13:$F$19, 'Revenue Tracking'!$H$13:$H$19, ">="&I1,'Revenue Tracking'!$H$13:$H$19, "<"&J1) -> 0 | J3: =SUMIFS('Revenue Tracking'!$F$13:$F$19, 'Revenue Tracking'!$H$13:$H$19, ">="&J1,'Revenue Tracking'!$H$13:$H$19, "<"&K1) -> 0 | K3: =SUMIFS('Revenue Tracking'!$F$13:$F$19, 'Revenue Tracking'!$H$13:$H$19, ">="&K1,'Revenue Tracking'!$H$13:$H$19, "<"&L1) -> 0 | L3: =SUMIFS('Revenue Tracking'!$F$13:$F$19, 'Revenue Tracking'!$H$13:$H$19, ">="&L1,'Revenue Tracking'!$H$13:$H$19, "<"&M1) -> 0 | M3: =SUMIFS('Revenue Tracking'!$F$13:$F$19, 'Revenue Tracking'!$H$13:$H$19, ">="&M1,'Revenue Tracking'!$H$13:$H$19, "<"&N1) -> 0 | ... LC3: =SUMIFS('Revenue Tracking'!$F$13:$F$19, 'Revenue Tracking'!$H$13:$H$19, ">="&LC1,'Revenue Tracking'!$H$13:$H$19, "<"&LD1) -> 0 | LD3: =SUMIFS('Revenue Tracking'!$F$13:$F$19, 'Revenue Tracking'!$H$13:$H$19, ">="&LD1,'Revenue Tracking'!$H$13:$H$19, "<"&#REF!) -> 0
B4: Planned Revenue - Cumulative | F4: =F3 -> 0 | G4: =F4+G3 -> 0 | H4: =G4+H3 -> 0 | I4: =H4+I3 -> 0 | J4: =I4+J3 -> 0 | K4: =J4+K3 -> 0 | L4: =K4+L3 -> 0 | M4: =L4+M3 -> 0 | N4: =M4+N3 -> 0 | ... LD4: =LC4+LD3 -> 1366576.1
B5: Planned Expenditure | C5: ='Revenue Tracking'!D5 -> 1022445.5 | D5: =SUM(F5:LD5) -> 1022445.5 | F5: =SUMIFS('Expenditure Breakdown'!$G$6:$G$207, 'Expenditure Breakdown'!$H$6:$H$207, ">="&F1,'Expenditure Breakdown'!$H$6:$H$207, "<"&G1) -> 0 | G5: =SUMIFS('Expenditure Breakdown'!$G$6:$G$207, 'Expenditure Breakdown'!$H$6:$H$207, ">="&G1,'Expenditure Breakdown'!$H$6:$H$207, "<"&H1) -> 0 | H5: =SUMIFS('Expenditure Breakdown'!$G$6:$G$207, 'Expenditure Breakdown'!$H$6:$H$207, ">="&H1,'Expenditure Breakdown'!$H$6:$H$207, "<"&I1) -> 0 | I5: =SUMIFS('Expenditure Breakdown'!$G$6:$G$207, 'Expenditure Breakdown'!$H$6:$H$207, ">="&I1,'Expenditure Breakdown'!$H$6:$H$207, "<"&J1) -> 0 | J5: =SUMIFS('Expenditure Breakdown'!$G$6:$G$207, 'Expenditure Breakdown'!$H$6:$H$207, ">="&J1,'Expenditure Breakdown'!$H$6:$H$207, "<"&K1) -> 0 | K5: =SUMIFS('Expenditure Breakdown'!$G$6:$G$207, 'Expenditure Breakdown'!$H$6:$H$207, ">="&K1,'Expenditure Breakdown'!$H$6:$H$207, "<"&L1) -> 0 | L5: =SUMIFS('Expenditure Breakdown'!$G$6:$G$207, 'Expenditure Breakdown'!$H$6:$H$207, ">="&L1,'Expenditure Breakdown'!$H$6:$H$207, "<"&M1) -> 0 | M5: =SUMIFS('Expenditure Breakdown'!$G$6:$G$207, 'Expenditure Breakdown'!$H$6:$H$207, ">="&M1,'Expenditure Breakdown'!$H$6:$H$207, "<"&N1) -> 0 | ... LC5: =SUMIFS('Expenditure Breakdown'!$G$6:$G$207, 'Expenditure Breakdown'!$H$6:$H$207, ">="&LC1,'Expenditure Breakdown'!$H$6:$H$207, "<"&LD1) -> 0 | LD5: =SUMIFS('Expenditure Breakdown'!$G$6:$G$207, 'Expenditure Breakdown'!$H$6:$H$207, ">="&LD1,'Expenditure Breakdown'!$H$6:$H$207, "<"&#REF!) -> 0
B6: Planned Expenditure - Cumulative | F6: =F5 -> 0 | G6: =F6+G5 -> 0 | H6: =G6+H5 -> 0 | I6: =H6+I5 -> 0 | J6: =I6+J5 -> 0 | K6: =J6+K5 -> 0 | L6: =K6+L5 -> 0 | M6: =L6+M5 -> 0 | N6: =M6+N5 -> 0 | ... LD6: =LC6+LD5 -> 1022445.5
B7: PLANNED CashFlow | F7: =F4-F6 -> 0 | G7: =G4-G6 -> 0 | H7: =H4-H6 -> 0 | I7: =I4-I6 -> 0 | J7: =J4-J6 -> 0 | K7: =K4-K6 -> 0 | L7: =L4-L6 -> 0 | M7: =M4-M6 -> 0 | ... LD7: =LD4-LD6 -> 344130.69
A8: ACTUAL | C8: CHECK | D8: CHECK
B9: Actual + Planned Revenue | C9: ='Revenue Tracking'!F4 -> 1366576.2 | D9: =SUM(F9:LD9) -> 1366576.2 | F9: =SUMIFS('Revenue Tracking'!$F$13:$F$19, 'Revenue Tracking'!$P$13:$P$19, ">="&F1,'Revenue Tracking'!$P$13:$P$19, "<"&G1) -> 0 | G9: =SUMIFS('Revenue Tracking'!$F$13:$F$19, 'Revenue Tracking'!$P$13:$P$19, ">="&G1,'Revenue Tracking'!$P$13:$P$19, "<"&H1) -> 0 | H9: =SUMIFS('Revenue Tracking'!$F$13:$F$19, 'Revenue Tracking'!$P$13:$P$19, ">="&H1,'Revenue Tracking'!$P$13:$P$19, "<"&I1) -> 0 | I9: =SUMIFS('Revenue Tracking'!$F$13:$F$19, 'Revenue Tracking'!$P$13:$P$19, ">="&I1,'Revenue Tracking'!$P$13:$P$19, "<"&J1) -> 0 | J9: =SUMIFS('Revenue Tracking'!$F$13:$F$19, 'Revenue Tracking'!$P$13:$P$19, ">="&J1,'Revenue Tracking'!$P$13:$P$19, "<"&K1) -> 0 | K9: =SUMIFS('Revenue Tracking'!$F$13:$F$19, 'Revenue Tracking'!$P$13:$P$19, ">="&K1,'Revenue Tracking'!$P$13:$P$19, "<"&L1) -> 0 | L9: =SUMIFS('Revenue Tracking'!$F$13:$F$19, 'Revenue Tracking'!$P$13:$P$19, ">="&L1,'Revenue Tracking'!$P$13:$P$19, "<"&M1) -> 0 | M9: =SUMIFS('Revenue Tracking'!$F$13:$F$19, 'Revenue Tracking'!$P$13:$P$19, ">="&M1,'Revenue Tracking'!$P$13:$P$19, "<"&N1) -> 0 | ... LC9: =SUMIFS('Revenue Tracking'!$F$13:$F$19, 'Revenue Tracking'!$P$13:$P$19, ">="&LC1,'Revenue Tracking'!$P$13:$P$19, "<"&LD1) -> 0 | LD9: =SUMIFS('Revenue Tracking'!$F$13:$F$19, 'Revenue Tracking'!$P$13:$P$19, ">="&LD1,'Revenue Tracking'!$P$13:$P$19, "<"&#REF!) -> 0
B10: Actual + Planned Revenue - Cumulative | F10: =F9 -> 0 | G10: =F10+G9 -> 0 | H10: =G10+H9 -> 0 | I10: =H10+I9 -> 0 | J10: =I10+J9 -> 0 | K10: =J10+K9 -> 0 | L10: =K10+L9 -> 0 | M10: =L10+M9 -> 0 | N10: =M10+N9 -> 0 | ... LD10: =LC10+LD9 -> 1366576.2
B11: Actual + Planned Expenditure | C11: ='Revenue Tracking'!F5 -> 926046.77 | D11: =SUM(F11:LD11) -> 926046.77 | F11: =SUMIFS('Expenditure Breakdown'!$Q$6:$Q$173, 'Expenditure Breakdown'!$W$6:$W$173, ">="&F1,'Expenditure Breakdown'!$W$6:$W$173, "<"&G1) -> 0 | G11: =SUMIFS('Expenditure Breakdown'!$Q$6:$Q$173, 'Expenditure Breakdown'!$W$6:$W$173, ">="&G1,'Expenditure Breakdown'!$W$6:$W$173, "<"&H1) -> 0 | H11: =SUMIFS('Expenditure Breakdown'!$Q$6:$Q$173, 'Expenditure Breakdown'!$W$6:$W$173, ">="&H1,'Expenditure Breakdown'!$W$6:$W$173, "<"&I1) -> 0 | I11: =SUMIFS('Expenditure Breakdown'!$Q$6:$Q$173, 'Expenditure Breakdown'!$W$6:$W$173, ">="&I1,'Expenditure Breakdown'!$W$6:$W$173, "<"&J1) -> 0 | J11: =SUMIFS('Expenditure Breakdown'!$Q$6:$Q$173, 'Expenditure Breakdown'!$W$6:$W$173, ">="&J1,'Expenditure Breakdown'!$W$6:$W$173, "<"&K1) -> 0 | K11: =SUMIFS('Expenditure Breakdown'!$Q$6:$Q$173, 'Expenditure Breakdown'!$W$6:$W$173, ">="&K1,'Expenditure Breakdown'!$W$6:$W$173, "<"&L1) -> 0 | L11: =SUMIFS('Expenditure Breakdown'!$Q$6:$Q$173, 'Expenditure Breakdown'!$W$6:$W$173, ">="&L1,'Expenditure Breakdown'!$W$6:$W$173, "<"&M1) -> 0 | M11: =SUMIFS('Expenditure Breakdown'!$Q$6:$Q$173, 'Expenditure Breakdown'!$W$6:$W$173, ">="&M1,'Expenditure Breakdown'!$W$6:$W$173, "<"&N1) -> 0 | ... LC11: =SUMIFS('Expenditure Breakdown'!$Q$6:$Q$173, 'Expenditure Breakdown'!$W$6:$W$173, ">="&LC1,'Expenditure Breakdown'!$W$6:$W$173, "<"&LD1) -> 0 | LD11: =SUMIFS('Expenditure Breakdown'!$Q$6:$Q$173, 'Expenditure Breakdown'!$W$6:$W$173, ">="&LD1,'Expenditure Breakdown'!$W$6:$W$173, "<"&#REF!) -> 0
B12: Actual + Planned Expenditure - Cumulative | F12: =F11 -> 0 | G12: =F12+G11 -> 0 | H12: =G12+H11 -> 0 | I12: =H12+I11 -> 0 | J12: =I12+J11 -> 0 | K12: =J12+K11 -> 0 | L12: =K12+L11 -> 0 | M12: =L12+M11 -> 0 | N12: =M12+N11 -> 0 | ... LD12: =LC12+LD11 -> 926046.77
B14: ACTUAL CashFlow | F14: =F10-F12 -> 0 | G14: =G10-G12 -> 0 | H14: =H10-H12 -> 0 | I14: =I10-I12 -> 0 | J14: =J10-J12 -> 0 | K14: =K10-K12 -> 0 | L14: =L10-L12 -> 0 | M14: =M10-M12 -> 0 | ... LD14: =LD10-LD12 -> 440529.38
C16: CHECK | D16: CHECK
B17: Revenue Recognition | C17: =C3-D17 -> 0.0029907734 | D17: =SUM(F17:LD17) -> 1366576.1 | F17: =SUMIFS('Expenditure Breakdown'!$U$6:$U$173, 'Expenditure Breakdown'!$T$6:$T$173, ">="&F1,'Expenditure Breakdown'!$T$6:$T$173, "<"&G1) -> 0 | G17: =SUMIFS('Expenditure Breakdown'!$U$6:$U$173, 'Expenditure Breakdown'!$T$6:$T$173, ">="&G1,'Expenditure Breakdown'!$T$6:$T$173, "<"&H1) -> 0 | H17: =SUMIFS('Expenditure Breakdown'!$U$6:$U$173, 'Expenditure Breakdown'!$T$6:$T$173, ">="&H1,'Expenditure Breakdown'!$T$6:$T$173, "<"&I1) -> 0 | I17: =SUMIFS('Expenditure Breakdown'!$U$6:$U$173, 'Expenditure Breakdown'!$T$6:$T$173, ">="&I1,'Expenditure Breakdown'!$T$6:$T$173, "<"&J1) -> 0 | J17: =SUMIFS('Expenditure Breakdown'!$U$6:$U$173, 'Expenditure Breakdown'!$T$6:$T$173, ">="&J1,'Expenditure Breakdown'!$T$6:$T$173, "<"&K1) -> 0 | K17: =SUMIFS('Expenditure Breakdown'!$U$6:$U$173, 'Expenditure Breakdown'!$T$6:$T$173, ">="&K1,'Expenditure Breakdown'!$T$6:$T$173, "<"&L1) -> 0 | L17: =SUMIFS('Expenditure Breakdown'!$U$6:$U$173, 'Expenditure Breakdown'!$T$6:$T$173, ">="&L1,'Expenditure Breakdown'!$T$6:$T$173, "<"&M1) -> 0 | M17: =SUMIFS('Expenditure Breakdown'!$U$6:$U$173, 'Expenditure Breakdown'!$T$6:$T$173, ">="&M1,'Expenditure Breakdown'!$T$6:$T$173, "<"&N1) -> 0 | ... LC17: =SUMIFS('Expenditure Breakdown'!$U$6:$U$173, 'Expenditure Breakdown'!$T$6:$T$173, ">="&LC1,'Expenditure Breakdown'!$T$6:$T$173, "<"&LD1) -> 0 | LD17: =SUMIFS('Expenditure Breakdown'!$U$6:$U$173, 'Expenditure Breakdown'!$T$6:$T$173, ">="&LD1,'Expenditure Breakdown'!$T$6:$T$173, "<"&#REF!) -> 0
B18: Revenue Recognition Cumulative | C18: =D17-D18 -> 0 | D18: =MAX(F18:LD18) -> 1366576.1 | F18: =F17 -> 0 | G18: =F18+G17 -> 0 | H18: =G18+H17 -> 0 | I18: =H18+I17 -> 0 | J18: =I18+J17 -> 0 | K18: =J18+K17 -> 0 | L18: =K18+L17 -> 0 | M18: =L18+M17 -> 0 | N18: =M18+N17 -> 0 | ... LD18: =LC18+LD17 -> 1366576.1

Sheet Finance - Revenue
A3: Sum of REVENUE RECOGNITION AMOUNT | B3: Column Labels
A4: Row Labels | B4: (blank) | C4: 45961 | D4: 45991 | E4: 46022 | G4: 46053 | H4: 46081 | I4: Grand Total
A5: (blank)
A6: 1. Panels | C6: 494952.22 | D6: 0 | F6: 0 | I6: 494952.22
A7: 2. Inverters | C7: 111111.11 | F7: 0 | I7: 111111.11
A8: 3. Mounting Structures | C8: 52844.694 | D8: 38661.554 | F8: 0 | I8: 91506.248
A9: 4. DC Equipment | C9: 123312.56 | D9: 48259.944 | F9: 0 | I9: 171572.5
A10: 5. Monitoring | B10: 0 | D10: 344.43925 | G10: 52433.337 | I10: 52777.776
A11: 6. AC Equipment | B11: 0 | C11: 22911.841 | D11: 206206.57 | F11: 0 | I11: 229118.41
A12: 8. Product Add On
A13: 9. AC & DC installation | B13: 0 | C13: 13007.5 | D13: 117067.5 | F13: 0 | I13: 130075
A14: 10. Site Logistics | C14: 2578.6847 | D14: 24945.445 | F14: 0 | G14: 3129.06 | I14: 30653.19
A15: 11. Due Dilligence | B15: 0 | D15: 8137.1203 | E15: 20592.084 | F15: 0 | G15: 9048.5695 | I15: 37777.774
A16: 13. Engineering | F16: 0 | H16: 14309.701 | I16: 14309.701
A17: 14. General Expenses | C17: 410.25337 | D17: 988.51825 | E17: 0 | F17: 0 | G17: 430.86744 | H17: 892.57996 | I17: 2722.219
A18: 15. Service Add On
A19: 12. BDP Commission
A20: 7.BESS
A21: Grand Total | B21: 0 | C21: 821128.86 | D21: 444611.09 | E21: 20592.084 | F21: 0 | G21: 65041.834 | H21: 15202.281 | I21: 1366576.1

Sheet Finance - COS
A3: Sum of Actual Total | B3: Column Labels
A4: Row Labels | B4: (blank) | C4: 45961 | D4: 45991 | E4: 46022 | G4: 46053 | H4: 46081 | I4: Grand Total
A5: (blank)
A6: 1. Panels | C6: 293808.67 | D6: 1305.4 | I6: 295114.07
A7: 2. Inverters | C7: 53700.89 | I7: 53700.89
A8: 3. Mounting Structures | C8: 21257.31 | D8: 6460 | I8: 27717.31
A9: 4. DC Equipment | C9: 86668.77 | D9: 33918.93 | I9: 120587.7
A10: 5. Monitoring | D10: 188.5 | G10: 11169 | I10: 11357.5
A11: 6. AC Equipment | C11: 6474.03 | D11: 58266.27 | I11: 64740.3
A12: 8. Product Add On | D12: 5900 | I12: 5900
A13: 9. AC & DC installation | C13: 17554.41 | D13: 157989.69 | I13: 175544.1
A14: 10. Site Logistics | C14: 10598.05 | D14: 102522.45 | I14: 113120.5
A15: 11. Due Dilligence | D15: 5100 | E15: 13950 | G15: 6000 | I15: 25050
A16: 13. Engineering | F16: 0 | H16: 17082.202 | I16: 17082.202
A17: 14. General Expenses | C17: 326.06 | D17: 968.66 | E17: 0 | G17: 337.48 | H17: 500 | I17: 2132.2
A18: 15. Service Add On | E18: 14000 | I18: 14000
A19: 12. BDP Commission | B19: 0 | I19: 0
A20: 7.BESS
A21: Grand Total | B21: 0 | C21: 490388.19 | D21: 372619.9 | E21: 27950 | F21: 0 | G21: 17506.48 | H21: 17582.202 | I21: 926046.77

Sheet Project Margins
A1: [capture project margins from costing sheet]
A3: Products | D3: 0.32
A4: Services | D4: 0.5
A5: Expenses | D5: 0.15
A6: Subcontractors | D6: 0.2

Sheet Equipment Quotes
B2: Equipment Quote and Budget comparision
B4: Description | D4: Budget | F4: Supplier 1 | H4: Variance | J4: Supplier 2 | L4: Variance | N4: Comments / Notes
F7: >Name< | J7: >Name<
B9: Inverters | D9: =SUM(D10:D11) -> #REF! | F9: =SUM(F10:F13) -> 0 | H9: =$D$9-F9 -> #REF! | J9: =SUM(J10:J13) -> 0 | L9: =$D$9-J9 -> #REF!
B10: Inverters | D10: =#REF! -> #REF!
B11: Optimizers | D11: =#REF! -> #REF!
B12: Warranty
B13: Delivery fee
F15: >Name< | J15: >Name<
B17: Mounting Structure | D17: =SUM(D18:D19) -> #REF! | F17: =SUM(F18:F20) -> 0 | H17: =$D$17- F17 -> #REF! | J17: =SUM(J18:J20) -> 0 | L17: =$D$17- J17 -> #REF!
B18: Mounting Structure | D18: =#REF! -> #REF!
B19: Delivery fee
F21: >Name< | J21: >Name<
B23: DC Cable | D23: =SUM(D24:D25) -> #REF! | F23: =SUM(F24:F25) -> 0 | H23: =$D$23- F23 -> #REF! | J23: =SUM(J24:J25) -> 0 | L23: =$D$23- J23 -> #REF!
B24: DC Cable | D24: =#REF! -> #REF!
B25: Delivery fee
F27: >Name< | J27: >Name<
B29: Monitoring system | D29: =SUM(D30:D32) -> #REF! | F29: =SUM(F30:F42) -> 0 | H29: =$D$29-F29 -> #REF! | J29: =SUM(J30:J32) -> 0 | L29: =$D$29-J29 -> #REF!
B30: =#REF! -> #REF! | D30: =#REF! -> #REF!
B31: =#REF! -> #REF! | D31: =#REF! -> #REF!
B32: Delivery fee
F34: >Name< | J34: >Name<
B36: Additional Scope | D36: =SUM(D37:D41) -> #REF! | F36: =SUM(F37:F41) -> 0 | H36: =$D$29-F36 -> #REF! | J36: =SUM(J37:J41) -> 0 | L36: =$D$29-J36 -> #REF!
B37: SCADA | D37: =#REF! -> #REF!
B38: Inverter cage
B39: Cat ladders
B40: Gen Integration
B41: Lifelines
B43: Totals | D43: =D36+D29+D23+D17+D9 -> #REF! | H43: =SUM(H7:H42) -> #REF! | L43: =SUM(L7:L42) -> #REF!
B47: All amounts are incl VAT

Sheet Installer Quotes
B2: Installer Quote and Budget comparision
B4: Description | D4: Budget | G4: Cosmic Sun | J4: Variance | L4: Matthews Group | O4: Variance
B6: AC Equipment | D6: =#REF! -> #REF! | E6: =D6/(1000*'Project Plan'!$E$3) -> #REF! | G6: 277892.91 | H6: =G6/('Project Plan'!$E$3*1000) -> 1.890428 | J6: =D6-G6 -> #REF! | M6: =L6/('Project Plan'!$E$3*1000) -> 0 | O6: =D6-L6 -> #REF!
B7: DC Equipment | D7: =#REF! -> #REF! | E7: =D7/(1000*'Project Plan'!$E$3) -> #REF! | G7: 142158.25 | H7: =G7/('Project Plan'!$E$3*1000) -> 0.96706293 | J7: =D7-G7 -> #REF! | M7: =L7/('Project Plan'!$E$3*1000) -> 0 | O7: =D7-L7 -> #REF!
B8: AC Labour | D8: =#REF! -> #REF! | E8: =D8/(1000*'Project Plan'!$E$3) -> #REF! | G8: 96174 | H8: =G8/('Project Plan'!$E$3*1000) -> 0.6542449 | J8: =D8-G8 -> #REF! | M8: =L8/('Project Plan'!$E$3*1000) -> 0 | O8: =D8-L8 -> #REF!
B9: DC Labour | D9: =#REF! -> #REF! | E9: =D9/(1000*'Project Plan'!$E$3) -> #REF! | G9: 230160 | H9: =G9/('Project Plan'!$E$3*1000) -> 1.5657143 | J9: =D9-G9 -> #REF! | M9: =L9/('Project Plan'!$E$3*1000) -> 0 | O9: =D9-L9 -> #REF!
B10: Offloading | D10: =#REF! -> #REF! | G10: 0 | J10: =D10-G10 -> #REF! | O10: =D10-L10 -> #REF!
B11: Roof Access/Scaffolding | D11: =#REF! -> #REF! | G11: 29257.61 | J11: =D11-G11 -> #REF! | O11: =D11-L11 -> #REF!
B12: Storage | D12: =#REF! -> #REF! | J12: =D12-G12 -> #REF! | O12: =D12-L12 -> #REF!
B13: Telehandler | D13: =#REF! -> #REF!
B14: HSE | D14: 0
B15: Totals | D15: =SUM(D6:D13) -> #REF! | G15: =SUM(G6:G13) -> 775642.77 | J15: =SUM(J6:J14) -> #REF! | L15: =SUM(L6:L13) -> 0 | O15: =SUM(O6:O14) -> #REF!
B18: Description | D18: Budget | G18: >Installer Name 3< | J18: Variance | L18: >Installer Name 4< | O18: Variance
B20: AC installation | D20: =#REF! -> #REF! | E20: =D20/(1000*'Project Plan'!$E$3) -> #REF! | H20: =G20/(1000*'Project Plan'!$E$3) -> 0 | J20: =D20-G20 -> #REF! | M20: =L20/(1000*'Project Plan'!$E$3) -> 0 | O20: =D6-L20 -> #REF!
B21: AC equipment | D21: =#REF! -> #REF! | E21: =D21/(1000*'Project Plan'!$E$3) -> #REF! | J21: =D21-G21 -> #REF! | M21: =L21/(1000*'Project Plan'!$E$3) -> 0 | O21: =D7-L21 -> #REF!
B22: DC installation | D22: =#REF! -> #REF! | E22: =D22/(1000*'Project Plan'!$E$3) -> #REF! | H22: =G22/(1000*'Project Plan'!$E$3) -> 0 | J22: =D22-G22 -> #REF! | M22: =L22/(1000*'Project Plan'!$E$3) -> 0 | O22: =D8-L22 -> #REF!
B23: DC equipment | D23: =SUM(#REF!) -> #REF! | E23: =D23/(1000*'Project Plan'!$E$3) -> #REF! | J23: =D23-G23 -> #REF! | O23: =D9-L23 -> #REF!
B24: Storage | D24: =#REF! -> #REF! | J24: =D24-G24 -> #REF! | O24: =D10-L24 -> #REF!
B25: Panel lifting equipment | D25: =SUM(#REF!) -> #REF! | J25: =D25-G25 -> #REF! | O25: =D11-L25 -> #REF!
B26: Offloading | D26: =#REF! -> #REF! | J26: =D26-G26 -> #REF! | O26: =D12-L26 -> #REF!
B29: Totals | D29: =SUM(D20:D27) -> #REF! | G29: =SUM(G20:G27) -> 0 | J29: =SUM(J20:J28) -> #REF! | L29: =SUM(L20:L27) -> 0 | O29: =SUM(O20:O28) -> #REF!
B32: Budget Summary
B34: Budget | D34: =D15 -> #REF!
B35: =G4 -> Cosmic Sun | D35: =G15 -> 775642.77
B36: =L4 -> Matthews Group | D36: =L15 -> 0
B37: =G18 -> >Installer Name 3< | D37: =G29 -> 0
B38: =L18 -> >Installer Name 4< | D38: =L29 -> 0
B40: =IF(D40<D34,"Saving","Loss") -> #REF! | D40: =D34-MIN(D35:D38) -> #REF!
B42: All amounts are exc VAT

Sheet Decision Register
B1: =D15 -> Malvern Engineering Phase 2 | E1: Decision Register
B3: ID | C3: Decision Description | D3: Decision Impact | E3: Proposed Date | F3: Proposed By | G3: Status | H3: Approved By | I3: Date | J3: Results / Comments
B4: DEC001
B5: DEC002
B6: DEC003
B7: DEC004
B8: DEC005
B9: DEC006
B10: DEC007
B11: DEC008
B12: DEC009
B13: DEC010
D15: {='Project Plan'!E2:H2} -> Malvern Engineering Phase 2 | E15: 0 | F15: 0 | G15: 0
