Workbook
Name Inverter_Supplier: #REF!
Name Project_Size: 'Finance - Revenue'!Projectsize
Name Project_Size: Projectsize
Name Projectsize: #REF!
Name Projectsize: 'Project Margins'!$K$5
Name Security_Serv: #REF!
Name Security_Serv: #REF!
Name SSS: #REF!
Name SSS: #REF!
Name USD_ZAR: #REF!

Sheet Sheet1
A1: PROJECT PLAN
A2: # | B2: Project Milestone | C2: Planned Start Date | D2: Duration (Work Days) | E2: Planned End Date | F2: Actual Start Date | H2: Actual End Date | J2: Comments | L2: =C3 -> 43831 | M2: =L2+3 -> 43834 | N2: =M2+7 -> 43841 | O2: =N2+7 -> 43848 | P2: =O2+7 -> 43855 | Q2: =P2+6 -> 43861 | R2: =Q2+1 -> 43862 | S2: =R2+7 -> 43869 | T2: =S2+7 -> 43876 | U2: =T2+7 -> 43883 | V2: =U2+6 -> 43889 | W2: =V2+7 -> 43896 | X2: =W2+7 -> 43903 | Y2: =X2+7 -> 43910 | Z2: =Y2+7 -> 43917 | AA2: =Z2+3 -> 43920 | AB2: =AA2+4 -> 43924 | AC2: =AB2+7 -> 43931 | AD2: =AC2+7 -> 43938 | AE2: =AD2+7 -> 43945 | AF2: =AE2+6 -> 43951 | AG2: =AF2+2 -> 43953 | AH2: =AG2+7 -> 43960 | AI2: =AH2+7 -> 43967 | AJ2: =AI2+7 -> 43974 | AK2: =AJ2+7 -> 43981 | AL2: =AK2+1 -> 43982 | AM2: =AL2+6 -> 43988 | AN2: =AM2+7 -> 43995 | AO2: =AN2+7 -> 44002 | AP2: =AO2+7 -> 44009 | AQ2: =AP2+3 -> 44012 | AR2: =AQ2+4 -> 44016 | AS2: =AR2+7 -> 44023 | AT2: =AS2+7 -> 44030 | AU2: =AT2+7 -> 44037 | AV2: =AU2+6 -> 44043 | AW2: =AV2+1 -> 44044 | AX2: =AW2+7 -> 44051 | AY2: =AX2+7 -> 44058 | AZ2: =AY2+7 -> 44065 | BA2: =AZ2+7 -> 44072 | BB2: =BA2+2 -> 44074 | BC2: =BB2+5 -> 44079 | BD2: =BC2+7 -> 44086 | BE2: =BD2+7 -> 44093 | BF2: =BE2+7 -> 44100 | BG2: =BF2+4 -> 44104
A3: 1 | B3: Contract Signature | C3: 43831 | D3: 1 | E3: 43832 | F3: 43831 | G3: 1 | H3: 43832 | L3: =IF(AND($F3<(L$2+7),$F3>L$2),1, IF(AND($H3<L$2+7,$H3>L$2),3, IF(AND($F3<=L$2, $H3>=L$2), 2, "" ))) -> 3 | M3: =IF(AND($F3<(M$2+7),$F3>M$2),1, IF(AND($H3<M$2+7,$H3>M$2),3, IF(AND($F3<=M$2, $H3>=M$2), 2, "" ))) | N3: =IF(AND($F3<(N$2+7),$F3>N$2),1, IF(AND($H3<N$2+7,$H3>N$2),3, IF(AND($F3<=N$2, $H3>=N$2), 2, "" ))) | O3: =IF(AND($F3<(O$2+7),$F3>O$2),1, IF(AND($H3<O$2+7,$H3>O$2),3, IF(AND($F3<=O$2, $H3>=O$2), 2, "" ))) | P3: =IF(AND($F3<(P$2+7),$F3>P$2),1, IF(AND($H3<P$2+7,$H3>P$2),3, IF(AND($F3<=P$2, $H3>=P$2), 2, "" ))) | Q3: =IF(AND($F3<(Q$2+7),$F3>Q$2),1, IF(AND($H3<Q$2+7,$H3>Q$2),3, IF(AND($F3<=Q$2, $H3>=Q$2), 2, "" ))) | R3: =IF(AND($F3<(R$2+7),$F3>R$2),1, IF(AND($H3<R$2+7,$H3>R$2),3, IF(AND($F3<=R$2, $H3>=R$2), 2, "" ))) | S3: =IF(AND($F3<(S$2+7),$F3>S$2),1, IF(AND($H3<S$2+7,$H3>S$2),3, IF(AND($F3<=S$2, $H3>=S$2), 2, "" ))) | ... AQ3: =IF(AND($F3<(AQ$2+7),$F3>AQ$2),1, IF(AND($H3<AQ$2+7,$H3>AQ$2),3, IF(AND($F3<=AQ$2, $H3>=AQ$2), 2, "" )))
A4: A | B4: PAYMENT MILESTONE 1: DEPOSIT | C4: 43832 | D4: 1 | E4: 43833 | F4: 43832 | G4: 1 | H4: 43833 | L4: =IF(AND($F4<(L$2+7),$F4>L$2),1, IF(AND($H4<L$2+7,$H4>L$2),3, IF(AND($F4<=L$2, $H4>=L$2), 2, "" ))) -> 1 | M4: =IF(AND($F4<(M$2+7),$F4>M$2),1, IF(AND($H4<M$2+7,$H4>M$2),3, IF(AND($F4<=M$2, $H4>=M$2), 2, "" ))) | N4: =IF(AND($F4<(N$2+7),$F4>N$2),1, IF(AND($H4<N$2+7,$H4>N$2),3, IF(AND($F4<=N$2, $H4>=N$2), 2, "" ))) | O4: =IF(AND($F4<(O$2+7),$F4>O$2),1, IF(AND($H4<O$2+7,$H4>O$2),3, IF(AND($F4<=O$2, $H4>=O$2), 2, "" ))) | P4: =IF(AND($F4<(P$2+7),$F4>P$2),1, IF(AND($H4<P$2+7,$H4>P$2),3, IF(AND($F4<=P$2, $H4>=P$2), 2, "" ))) | Q4: =IF(AND($F4<(Q$2+7),$F4>Q$2),1, IF(AND($H4<Q$2+7,$H4>Q$2),3, IF(AND($F4<=Q$2, $H4>=Q$2), 2, "" ))) | R4: =IF(AND($F4<(R$2+7),$F4>R$2),1, IF(AND($H4<R$2+7,$H4>R$2),3, IF(AND($F4<=R$2, $H4>=R$2), 2, "" ))) | S4: =IF(AND($F4<(S$2+7),$F4>S$2),1, IF(AND($H4<S$2+7,$H4>S$2),3, IF(AND($F4<=S$2, $H4>=S$2), 2, "" ))) | ... AQ4: =IF(AND($F4<(AQ$2+7),$F4>AQ$2),1, IF(AND($H4<AQ$2+7,$H4>AQ$2),3, IF(AND($F4<=AQ$2, $H4>=AQ$2), 2, "" )))
A5: 2 | B5: Structural and Electrical Due Diligences | C5: 43833 | D5: 5 | E5: 43840 | F5: 43833 | G5: 5 | H5: 43840 | L5: =IF(AND($F5<(L$2+7),$F5>L$2),1, IF(AND($H5<L$2+7,$H5>L$2),3, IF(AND($F5<=L$2, $H5>=L$2), 2, "" ))) -> 1 | M5: =IF(AND($F5<(M$2+7),$F5>M$2),1, IF(AND($H5<M$2+7,$H5>M$2),3, IF(AND($F5<=M$2, $H5>=M$2), 2, "" ))) -> 3 | N5: =IF(AND($F5<(N$2+7),$F5>N$2),1, IF(AND($H5<N$2+7,$H5>N$2),3, IF(AND($F5<=N$2, $H5>=N$2), 2, "" ))) | O5: =IF(AND($F5<(O$2+7),$F5>O$2),1, IF(AND($H5<O$2+7,$H5>O$2),3, IF(AND($F5<=O$2, $H5>=O$2), 2, "" ))) | P5: =IF(AND($F5<(P$2+7),$F5>P$2),1, IF(AND($H5<P$2+7,$H5>P$2),3, IF(AND($F5<=P$2, $H5>=P$2), 2, "" ))) | Q5: =IF(AND($F5<(Q$2+7),$F5>Q$2),1, IF(AND($H5<Q$2+7,$H5>Q$2),3, IF(AND($F5<=Q$2, $H5>=Q$2), 2, "" ))) | R5: =IF(AND($F5<(R$2+7),$F5>R$2),1, IF(AND($H5<R$2+7,$H5>R$2),3, IF(AND($F5<=R$2, $H5>=R$2), 2, "" ))) | S5: =IF(AND($F5<(S$2+7),$F5>S$2),1, IF(AND($H5<S$2+7,$H5>S$2),3, IF(AND($F5<=S$2, $H5>=S$2), 2, "" ))) | ... AQ5: =IF(AND($F5<(AQ$2+7),$F5>AQ$2),1, IF(AND($H5<AQ$2+7,$H5>AQ$2),3, IF(AND($F5<=AQ$2, $H5>=AQ$2), 2, "" )))
A6: 3 | B6: Design Confirmation | C6: 43841 | D6: 2 | E6: 43844 | F6: 43841 | G6: 2 | H6: 43844 | L6: =IF(AND($F6<(L$2+7),$F6>L$2),1, IF(AND($H6<L$2+7,$H6>L$2),3, IF(AND($F6<=L$2, $H6>=L$2), 2, "" ))) | M6: =IF(AND($F6<(M$2+7),$F6>M$2),1, IF(AND($H6<M$2+7,$H6>M$2),3, IF(AND($F6<=M$2, $H6>=M$2), 2, "" ))) | N6: =IF(AND($F6<(N$2+7),$F6>N$2),1, IF(AND($H6<N$2+7,$H6>N$2),3, IF(AND($F6<=N$2, $H6>=N$2), 2, "" ))) -> 3 | O6: =IF(AND($F6<(O$2+7),$F6>O$2),1, IF(AND($H6<O$2+7,$H6>O$2),3, IF(AND($F6<=O$2, $H6>=O$2), 2, "" ))) | P6: =IF(AND($F6<(P$2+7),$F6>P$2),1, IF(AND($H6<P$2+7,$H6>P$2),3, IF(AND($F6<=P$2, $H6>=P$2), 2, "" ))) | Q6: =IF(AND($F6<(Q$2+7),$F6>Q$2),1, IF(AND($H6<Q$2+7,$H6>Q$2),3, IF(AND($F6<=Q$2, $H6>=Q$2), 2, "" ))) | R6: =IF(AND($F6<(R$2+7),$F6>R$2),1, IF(AND($H6<R$2+7,$H6>R$2),3, IF(AND($F6<=R$2, $H6>=R$2), 2, "" ))) | S6: =IF(AND($F6<(S$2+7),$F6>S$2),1, IF(AND($H6<S$2+7,$H6>S$2),3, IF(AND($F6<=S$2, $H6>=S$2), 2, "" ))) | ... AQ6: =IF(AND($F6<(AQ$2+7),$F6>AQ$2),1, IF(AND($H6<AQ$2+7,$H6>AQ$2),3, IF(AND($F6<=AQ$2, $H6>=AQ$2), 2, "" )))
A7: 4 | B7: Equipment Procurement | C7: 43833 | E7: 43949 | F7: 43833 | H7: 43949 | L7: =IF(AND($F7<(L$2+7),$F7>L$2),1, IF(AND($H7<L$2+7,$H7>L$2),3, IF(AND($F7<=L$2, $H7>=L$2), 2, "" ))) -> 1 | M7: =IF(AND($F7<(M$2+7),$F7>M$2),1, IF(AND($H7<M$2+7,$H7>M$2),3, IF(AND($F7<=M$2, $H7>=M$2), 2, "" ))) -> 2 | N7: =IF(AND($F7<(N$2+7),$F7>N$2),1, IF(AND($H7<N$2+7,$H7>N$2),3, IF(AND($F7<=N$2, $H7>=N$2), 2, "" ))) -> 2 | O7: =IF(AND($F7<(O$2+7),$F7>O$2),1, IF(AND($H7<O$2+7,$H7>O$2),3, IF(AND($F7<=O$2, $H7>=O$2), 2, "" ))) -> 2 | P7: =IF(AND($F7<(P$2+7),$F7>P$2),1, IF(AND($H7<P$2+7,$H7>P$2),3, IF(AND($F7<=P$2, $H7>=P$2), 2, "" ))) -> 2 | Q7: =IF(AND($F7<(Q$2+7),$F7>Q$2),1, IF(AND($H7<Q$2+7,$H7>Q$2),3, IF(AND($F7<=Q$2, $H7>=Q$2), 2, "" ))) -> 2 | R7: =IF(AND($F7<(R$2+7),$F7>R$2),1, IF(AND($H7<R$2+7,$H7>R$2),3, IF(AND($F7<=R$2, $H7>=R$2), 2, "" ))) -> 2 | S7: =IF(AND($F7<(S$2+7),$F7>S$2),1, IF(AND($H7<S$2+7,$H7>S$2),3, IF(AND($F7<=S$2, $H7>=S$2), 2, "" ))) -> 2 | ... AQ7: =IF(AND($F7<(AQ$2+7),$F7>AQ$2),1, IF(AND($H7<AQ$2+7,$H7>AQ$2),3, IF(AND($F7<=AQ$2, $H7>=AQ$2), 2, "" )))
B8: Panel Procurement | C8: 43833 | D8: 5 | E8: 43840 | F8: 43833 | G8: 5 | H8: 43840 | L8: =IF(AND($F8<(L$2+7),$F8>L$2),1, IF(AND($H8<L$2+7,$H8>L$2),3, IF(AND($F8<=L$2, $H8>=L$2), 2, "" ))) -> 1 | M8: =IF(AND($F8<(M$2+7),$F8>M$2),1, IF(AND($H8<M$2+7,$H8>M$2),3, IF(AND($F8<=M$2, $H8>=M$2), 2, "" ))) -> 3 | N8: =IF(AND($F8<(N$2+7),$F8>N$2),1, IF(AND($H8<N$2+7,$H8>N$2),3, IF(AND($F8<=N$2, $H8>=N$2), 2, "" ))) | O8: =IF(AND($F8<(O$2+7),$F8>O$2),1, IF(AND($H8<O$2+7,$H8>O$2),3, IF(AND($F8<=O$2, $H8>=O$2), 2, "" ))) | P8: =IF(AND($F8<(P$2+7),$F8>P$2),1, IF(AND($H8<P$2+7,$H8>P$2),3, IF(AND($F8<=P$2, $H8>=P$2), 2, "" ))) | Q8: =IF(AND($F8<(Q$2+7),$F8>Q$2),1, IF(AND($H8<Q$2+7,$H8>Q$2),3, IF(AND($F8<=Q$2, $H8>=Q$2), 2, "" ))) | R8: =IF(AND($F8<(R$2+7),$F8>R$2),1, IF(AND($H8<R$2+7,$H8>R$2),3, IF(AND($F8<=R$2, $H8>=R$2), 2, "" ))) | S8: =IF(AND($F8<(S$2+7),$F8>S$2),1, IF(AND($H8<S$2+7,$H8>S$2),3, IF(AND($F8<=S$2, $H8>=S$2), 2, "" ))) | ... AQ8: =IF(AND($F8<(AQ$2+7),$F8>AQ$2),1, IF(AND($H8<AQ$2+7,$H8>AQ$2),3, IF(AND($F8<=AQ$2, $H8>=AQ$2), 2, "" )))
B9: Inverter Procurement | C9: 43941 | D9: 5 | E9: 43949 | F9: 43941 | G9: 5 | H9: 43949 | L9: =IF(AND($F9<(L$2+7),$F9>L$2),1, IF(AND($H9<L$2+7,$H9>L$2),3, IF(AND($F9<=L$2, $H9>=L$2), 2, "" ))) | M9: =IF(AND($F9<(M$2+7),$F9>M$2),1, IF(AND($H9<M$2+7,$H9>M$2),3, IF(AND($F9<=M$2, $H9>=M$2), 2, "" ))) | N9: =IF(AND($F9<(N$2+7),$F9>N$2),1, IF(AND($H9<N$2+7,$H9>N$2),3, IF(AND($F9<=N$2, $H9>=N$2), 2, "" ))) | O9: =IF(AND($F9<(O$2+7),$F9>O$2),1, IF(AND($H9<O$2+7,$H9>O$2),3, IF(AND($F9<=O$2, $H9>=O$2), 2, "" ))) | P9: =IF(AND($F9<(P$2+7),$F9>P$2),1, IF(AND($H9<P$2+7,$H9>P$2),3, IF(AND($F9<=P$2, $H9>=P$2), 2, "" ))) | Q9: =IF(AND($F9<(Q$2+7),$F9>Q$2),1, IF(AND($H9<Q$2+7,$H9>Q$2),3, IF(AND($F9<=Q$2, $H9>=Q$2), 2, "" ))) | R9: =IF(AND($F9<(R$2+7),$F9>R$2),1, IF(AND($H9<R$2+7,$H9>R$2),3, IF(AND($F9<=R$2, $H9>=R$2), 2, "" ))) | S9: =IF(AND($F9<(S$2+7),$F9>S$2),1, IF(AND($H9<S$2+7,$H9>S$2),3, IF(AND($F9<=S$2, $H9>=S$2), 2, "" ))) | ... AQ9: =IF(AND($F9<(AQ$2+7),$F9>AQ$2),1, IF(AND($H9<AQ$2+7,$H9>AQ$2),3, IF(AND($F9<=AQ$2, $H9>=AQ$2), 2, "" )))
B10: Mounting Structure Procurement | C10: 43941 | D10: 5 | E10: 43949 | F10: 43941 | G10: 5 | H10: 43949 | L10: =IF(AND($F10<(L$2+7),$F10>L$2),1, IF(AND($H10<L$2+7,$H10>L$2),3, IF(AND($F10<=L$2, $H10>=L$2), 2, "" ))) | M10: =IF(AND($F10<(M$2+7),$F10>M$2),1, IF(AND($H10<M$2+7,$H10>M$2),3, IF(AND($F10<=M$2, $H10>=M$2), 2, "" ))) | N10: =IF(AND($F10<(N$2+7),$F10>N$2),1, IF(AND($H10<N$2+7,$H10>N$2),3, IF(AND($F10<=N$2, $H10>=N$2), 2, "" ))) | O10: =IF(AND($F10<(O$2+7),$F10>O$2),1, IF(AND($H10<O$2+7,$H10>O$2),3, IF(AND($F10<=O$2, $H10>=O$2), 2, "" ))) | P10: =IF(AND($F10<(P$2+7),$F10>P$2),1, IF(AND($H10<P$2+7,$H10>P$2),3, IF(AND($F10<=P$2, $H10>=P$2), 2, "" ))) | Q10: =IF(AND($F10<(Q$2+7),$F10>Q$2),1, IF(AND($H10<Q$2+7,$H10>Q$2),3, IF(AND($F10<=Q$2, $H10>=Q$2), 2, "" ))) | R10: =IF(AND($F10<(R$2+7),$F10>R$2),1, IF(AND($H10<R$2+7,$H10>R$2),3, IF(AND($F10<=R$2, $H10>=R$2), 2, "" ))) | S10: =IF(AND($F10<(S$2+7),$F10>S$2),1, IF(AND($H10<S$2+7,$H10>S$2),3, IF(AND($F10<=S$2, $H10>=S$2), 2, "" ))) | ... AQ10: =IF(AND($F10<(AQ$2+7),$F10>AQ$2),1, IF(AND($H10<AQ$2+7,$H10>AQ$2),3, IF(AND($F10<=AQ$2, $H10>=AQ$2), 2, "" )))
B11: BOS Procurement | C11: 43941 | D11: 5 | E11: 43949 | F11: 43941 | G11: 5 | H11: 43949 | L11: =IF(AND($F11<(L$2+7),$F11>L$2),1, IF(AND($H11<L$2+7,$H11>L$2),3, IF(AND($F11<=L$2, $H11>=L$2), 2, "" ))) | M11: =IF(AND($F11<(M$2+7),$F11>M$2),1, IF(AND($H11<M$2+7,$H11>M$2),3, IF(AND($F11<=M$2, $H11>=M$2), 2, "" ))) | N11: =IF(AND($F11<(N$2+7),$F11>N$2),1, IF(AND($H11<N$2+7,$H11>N$2),3, IF(AND($F11<=N$2, $H11>=N$2), 2, "" ))) | O11: =IF(AND($F11<(O$2+7),$F11>O$2),1, IF(AND($H11<O$2+7,$H11>O$2),3, IF(AND($F11<=O$2, $H11>=O$2), 2, "" ))) | P11: =IF(AND($F11<(P$2+7),$F11>P$2),1, IF(AND($H11<P$2+7,$H11>P$2),3, IF(AND($F11<=P$2, $H11>=P$2), 2, "" ))) | Q11: =IF(AND($F11<(Q$2+7),$F11>Q$2),1, IF(AND($H11<Q$2+7,$H11>Q$2),3, IF(AND($F11<=Q$2, $H11>=Q$2), 2, "" ))) | R11: =IF(AND($F11<(R$2+7),$F11>R$2),1, IF(AND($H11<R$2+7,$H11>R$2),3, IF(AND($F11<=R$2, $H11>=R$2), 2, "" ))) | S11: =IF(AND($F11<(S$2+7),$F11>S$2),1, IF(AND($H11<S$2+7,$H11>S$2),3, IF(AND($F11<=S$2, $H11>=S$2), 2, "" ))) | ... AQ11: =IF(AND($F11<(AQ$2+7),$F11>AQ$2),1, IF(AND($H11<AQ$2+7,$H11>AQ$2),3, IF(AND($F11<=AQ$2, $H11>=AQ$2), 2, "" )))
A12: 5 | B12: Internal Project Kick off | C12: 43936 | D12: 5 | E12: 43943 | F12: 43936 | G12: 5 | H12: 43943
A13: 6 | B13: Client Project Kick-off | C13: 43963 | D13: 5 | E13: 43970 | F13: 43963 | G13: 5 | H13: 43970 | L13: =IF(AND($F13<(L$2+7),$F13>L$2),1, IF(AND($H13<L$2+7,$H13>L$2),3, IF(AND($F13<=L$2, $H13>=L$2), 2, "" ))) | M13: =IF(AND($F13<(M$2+7),$F13>M$2),1, IF(AND($H13<M$2+7,$H13>M$2),3, IF(AND($F13<=M$2, $H13>=M$2), 2, "" ))) | N13: =IF(AND($F13<(N$2+7),$F13>N$2),1, IF(AND($H13<N$2+7,$H13>N$2),3, IF(AND($F13<=N$2, $H13>=N$2), 2, "" ))) | O13: =IF(AND($F13<(O$2+7),$F13>O$2),1, IF(AND($H13<O$2+7,$H13>O$2),3, IF(AND($F13<=O$2, $H13>=O$2), 2, "" ))) | P13: =IF(AND($F13<(P$2+7),$F13>P$2),1, IF(AND($H13<P$2+7,$H13>P$2),3, IF(AND($F13<=P$2, $H13>=P$2), 2, "" ))) | Q13: =IF(AND($F13<(Q$2+7),$F13>Q$2),1, IF(AND($H13<Q$2+7,$H13>Q$2),3, IF(AND($F13<=Q$2, $H13>=Q$2), 2, "" ))) | R13: =IF(AND($F13<(R$2+7),$F13>R$2),1, IF(AND($H13<R$2+7,$H13>R$2),3, IF(AND($F13<=R$2, $H13>=R$2), 2, "" ))) | S13: =IF(AND($F13<(S$2+7),$F13>S$2),1, IF(AND($H13<S$2+7,$H13>S$2),3, IF(AND($F13<=S$2, $H13>=S$2), 2, "" ))) | ... AQ13: =IF(AND($F13<(AQ$2+7),$F13>AQ$2),1, IF(AND($H13<AQ$2+7,$H13>AQ$2),3, IF(AND($F13<=AQ$2, $H13>=AQ$2), 2, "" )))
A14: 7 | B14: Equipment Delivery | C14: 43983 | D14: 9 | E14: 43994 | F14: 43983 | G14: 9 | H14: 43994 | L14: =IF(AND($F14<(L$2+7),$F14>L$2),1, IF(AND($H14<L$2+7,$H14>L$2),3, IF(AND($F14<=L$2, $H14>=L$2), 2, "" ))) | M14: =IF(AND($F14<(M$2+7),$F14>M$2),1, IF(AND($H14<M$2+7,$H14>M$2),3, IF(AND($F14<=M$2, $H14>=M$2), 2, "" ))) | N14: =IF(AND($F14<(N$2+7),$F14>N$2),1, IF(AND($H14<N$2+7,$H14>N$2),3, IF(AND($F14<=N$2, $H14>=N$2), 2, "" ))) | O14: =IF(AND($F14<(O$2+7),$F14>O$2),1, IF(AND($H14<O$2+7,$H14>O$2),3, IF(AND($F14<=O$2, $H14>=O$2), 2, "" ))) | P14: =IF(AND($F14<(P$2+7),$F14>P$2),1, IF(AND($H14<P$2+7,$H14>P$2),3, IF(AND($F14<=P$2, $H14>=P$2), 2, "" ))) | Q14: =IF(AND($F14<(Q$2+7),$F14>Q$2),1, IF(AND($H14<Q$2+7,$H14>Q$2),3, IF(AND($F14<=Q$2, $H14>=Q$2), 2, "" ))) | R14: =IF(AND($F14<(R$2+7),$F14>R$2),1, IF(AND($H14<R$2+7,$H14>R$2),3, IF(AND($F14<=R$2, $H14>=R$2), 2, "" ))) | S14: =IF(AND($F14<(S$2+7),$F14>S$2),1, IF(AND($H14<S$2+7,$H14>S$2),3, IF(AND($F14<=S$2, $H14>=S$2), 2, "" ))) | ... AQ14: =IF(AND($F14<(AQ$2+7),$F14>AQ$2),1, IF(AND($H14<AQ$2+7,$H14>AQ$2),3, IF(AND($F14<=AQ$2, $H14>=AQ$2), 2, "" )))
B15: Mounting Structure Delivery | C15: 43983 | D15: 2 | E15: 43985 | F15: 43983 | G15: 2 | H15: 43985
B16: Panel Delivery | C16: 43990 | D16: 2 | E16: 43992 | F16: 43990 | G16: 2 | H16: 43992 | L16: =IF(AND($F16<(L$2+7),$F16>L$2),1, IF(AND($H16<L$2+7,$H16>L$2),3, IF(AND($F16<=L$2, $H16>=L$2), 2, "" ))) | M16: =IF(AND($F16<(M$2+7),$F16>M$2),1, IF(AND($H16<M$2+7,$H16>M$2),3, IF(AND($F16<=M$2, $H16>=M$2), 2, "" ))) | N16: =IF(AND($F16<(N$2+7),$F16>N$2),1, IF(AND($H16<N$2+7,$H16>N$2),3, IF(AND($F16<=N$2, $H16>=N$2), 2, "" ))) | O16: =IF(AND($F16<(O$2+7),$F16>O$2),1, IF(AND($H16<O$2+7,$H16>O$2),3, IF(AND($F16<=O$2, $H16>=O$2), 2, "" ))) | P16: =IF(AND($F16<(P$2+7),$F16>P$2),1, IF(AND($H16<P$2+7,$H16>P$2),3, IF(AND($F16<=P$2, $H16>=P$2), 2, "" ))) | Q16: =IF(AND($F16<(Q$2+7),$F16>Q$2),1, IF(AND($H16<Q$2+7,$H16>Q$2),3, IF(AND($F16<=Q$2, $H16>=Q$2), 2, "" ))) | R16: =IF(AND($F16<(R$2+7),$F16>R$2),1, IF(AND($H16<R$2+7,$H16>R$2),3, IF(AND($F16<=R$2, $H16>=R$2), 2, "" ))) | S16: =IF(AND($F16<(S$2+7),$F16>S$2),1, IF(AND($H16<S$2+7,$H16>S$2),3, IF(AND($F16<=S$2, $H16>=S$2), 2, "" ))) | ... AQ16: =IF(AND($F16<(AQ$2+7),$F16>AQ$2),1, IF(AND($H16<AQ$2+7,$H16>AQ$2),3, IF(AND($F16<=AQ$2, $H16>=AQ$2), 2, "" )))
B17: Generator Delivery | C17: 43983 | D17: 2 | E17: 43985 | F17: 43983 | G17: 2 | H17: 43985
A18: B | B18: PAYMENT MILESTONE 2: DELIVERY OF PV PANELS | C18: 43992 | D18: 2 | E18: 43994 | F18: 43992 | G18: 2 | H18: 43994
B19: Inverter Delivery | C19: 43983 | D19: 2 | E19: 43985 | F19: 43983 | G19: 2 | H19: 43985 | L19: =IF(AND($F19<(L$2+7),$F19>L$2),1, IF(AND($H19<L$2+7,$H19>L$2),3, IF(AND($F19<=L$2, $H19>=L$2), 2, "" ))) | M19: =IF(AND($F19<(M$2+7),$F19>M$2),1, IF(AND($H19<M$2+7,$H19>M$2),3, IF(AND($F19<=M$2, $H19>=M$2), 2, "" ))) | N19: =IF(AND($F19<(N$2+7),$F19>N$2),1, IF(AND($H19<N$2+7,$H19>N$2),3, IF(AND($F19<=N$2, $H19>=N$2), 2, "" ))) | O19: =IF(AND($F19<(O$2+7),$F19>O$2),1, IF(AND($H19<O$2+7,$H19>O$2),3, IF(AND($F19<=O$2, $H19>=O$2), 2, "" ))) | P19: =IF(AND($F19<(P$2+7),$F19>P$2),1, IF(AND($H19<P$2+7,$H19>P$2),3, IF(AND($F19<=P$2, $H19>=P$2), 2, "" ))) | Q19: =IF(AND($F19<(Q$2+7),$F19>Q$2),1, IF(AND($H19<Q$2+7,$H19>Q$2),3, IF(AND($F19<=Q$2, $H19>=Q$2), 2, "" ))) | R19: =IF(AND($F19<(R$2+7),$F19>R$2),1, IF(AND($H19<R$2+7,$H19>R$2),3, IF(AND($F19<=R$2, $H19>=R$2), 2, "" ))) | S19: =IF(AND($F19<(S$2+7),$F19>S$2),1, IF(AND($H19<S$2+7,$H19>S$2),3, IF(AND($F19<=S$2, $H19>=S$2), 2, "" ))) | ... AQ19: =IF(AND($F19<(AQ$2+7),$F19>AQ$2),1, IF(AND($H19<AQ$2+7,$H19>AQ$2),3, IF(AND($F19<=AQ$2, $H19>=AQ$2), 2, "" )))
B20: BOS Delivery | C20: 43983 | D20: 1 | E20: 43984 | F20: 43983 | G20: 1 | H20: 43984 | L20: =IF(AND($F20<(L$2+7),$F20>L$2),1, IF(AND($H20<L$2+7,$H20>L$2),3, IF(AND($F20<=L$2, $H20>=L$2), 2, "" ))) | M20: =IF(AND($F20<(M$2+7),$F20>M$2),1, IF(AND($H20<M$2+7,$H20>M$2),3, IF(AND($F20<=M$2, $H20>=M$2), 2, "" ))) | N20: =IF(AND($F20<(N$2+7),$F20>N$2),1, IF(AND($H20<N$2+7,$H20>N$2),3, IF(AND($F20<=N$2, $H20>=N$2), 2, "" ))) | O20: =IF(AND($F20<(O$2+7),$F20>O$2),1, IF(AND($H20<O$2+7,$H20>O$2),3, IF(AND($F20<=O$2, $H20>=O$2), 2, "" ))) | P20: =IF(AND($F20<(P$2+7),$F20>P$2),1, IF(AND($H20<P$2+7,$H20>P$2),3, IF(AND($F20<=P$2, $H20>=P$2), 2, "" ))) | Q20: =IF(AND($F20<(Q$2+7),$F20>Q$2),1, IF(AND($H20<Q$2+7,$H20>Q$2),3, IF(AND($F20<=Q$2, $H20>=Q$2), 2, "" ))) | R20: =IF(AND($F20<(R$2+7),$F20>R$2),1, IF(AND($H20<R$2+7,$H20>R$2),3, IF(AND($F20<=R$2, $H20>=R$2), 2, "" ))) | S20: =IF(AND($F20<(S$2+7),$F20>S$2),1, IF(AND($H20<S$2+7,$H20>S$2),3, IF(AND($F20<=S$2, $H20>=S$2), 2, "" ))) | ... AQ20: =IF(AND($F20<(AQ$2+7),$F20>AQ$2),1, IF(AND($H20<AQ$2+7,$H20>AQ$2),3, IF(AND($F20<=AQ$2, $H20>=AQ$2), 2, "" )))
A21: C | B21: PAYMENT MILESTONE 3: DELIVERY OF INVERTERS AND BOS | C21: 43985 | D21: 2 | E21: 43987 | F21: 43985 | G21: 2 | H21: 43987
A22: 8 | B22: Installation | C22: 43990 | D22: 22 | E22: 44012 | F22: 43990 | G22: 22 | H22: 44012 | L22: =IF(AND($F22<(L$2+7),$F22>L$2),1, IF(AND($H22<L$2+7,$H22>L$2),3, IF(AND($F22<=L$2, $H22>=L$2), 2, "" ))) | M22: =IF(AND($F22<(M$2+7),$F22>M$2),1, IF(AND($H22<M$2+7,$H22>M$2),3, IF(AND($F22<=M$2, $H22>=M$2), 2, "" ))) | N22: =IF(AND($F22<(N$2+7),$F22>N$2),1, IF(AND($H22<N$2+7,$H22>N$2),3, IF(AND($F22<=N$2, $H22>=N$2), 2, "" ))) | O22: =IF(AND($F22<(O$2+7),$F22>O$2),1, IF(AND($H22<O$2+7,$H22>O$2),3, IF(AND($F22<=O$2, $H22>=O$2), 2, "" ))) | P22: =IF(AND($F22<(P$2+7),$F22>P$2),1, IF(AND($H22<P$2+7,$H22>P$2),3, IF(AND($F22<=P$2, $H22>=P$2), 2, "" ))) | Q22: =IF(AND($F22<(Q$2+7),$F22>Q$2),1, IF(AND($H22<Q$2+7,$H22>Q$2),3, IF(AND($F22<=Q$2, $H22>=Q$2), 2, "" ))) | R22: =IF(AND($F22<(R$2+7),$F22>R$2),1, IF(AND($H22<R$2+7,$H22>R$2),3, IF(AND($F22<=R$2, $H22>=R$2), 2, "" ))) | S22: =IF(AND($F22<(S$2+7),$F22>S$2),1, IF(AND($H22<S$2+7,$H22>S$2),3, IF(AND($F22<=S$2, $H22>=S$2), 2, "" ))) | ... AQ22: =IF(AND($F22<(AQ$2+7),$F22>AQ$2),1, IF(AND($H22<AQ$2+7,$H22>AQ$2),3, IF(AND($F22<=AQ$2, $H22>=AQ$2), 2, "" ))) -> 2
B23: Site Establishment | C23: 43990 | D23: 1 | E23: 43991 | F23: 43990 | G23: 1 | H23: 43991 | J23: Installation placed on hold due to Covid-19 case | L23: =IF(AND($F23<(L$2+7),$F23>L$2),1, IF(AND($H23<L$2+7,$H23>L$2),3, IF(AND($F23<=L$2, $H23>=L$2), 2, "" ))) | M23: =IF(AND($F23<(M$2+7),$F23>M$2),1, IF(AND($H23<M$2+7,$H23>M$2),3, IF(AND($F23<=M$2, $H23>=M$2), 2, "" ))) | N23: =IF(AND($F23<(N$2+7),$F23>N$2),1, IF(AND($H23<N$2+7,$H23>N$2),3, IF(AND($F23<=N$2, $H23>=N$2), 2, "" ))) | O23: =IF(AND($F23<(O$2+7),$F23>O$2),1, IF(AND($H23<O$2+7,$H23>O$2),3, IF(AND($F23<=O$2, $H23>=O$2), 2, "" ))) | P23: =IF(AND($F23<(P$2+7),$F23>P$2),1, IF(AND($H23<P$2+7,$H23>P$2),3, IF(AND($F23<=P$2, $H23>=P$2), 2, "" ))) | Q23: =IF(AND($F23<(Q$2+7),$F23>Q$2),1, IF(AND($H23<Q$2+7,$H23>Q$2),3, IF(AND($F23<=Q$2, $H23>=Q$2), 2, "" ))) | R23: =IF(AND($F23<(R$2+7),$F23>R$2),1, IF(AND($H23<R$2+7,$H23>R$2),3, IF(AND($F23<=R$2, $H23>=R$2), 2, "" ))) | S23: =IF(AND($F23<(S$2+7),$F23>S$2),1, IF(AND($H23<S$2+7,$H23>S$2),3, IF(AND($F23<=S$2, $H23>=S$2), 2, "" ))) | ... AQ23: =IF(AND($F23<(AQ$2+7),$F23>AQ$2),1, IF(AND($H23<AQ$2+7,$H23>AQ$2),3, IF(AND($F23<=AQ$2, $H23>=AQ$2), 2, "" )))
A24: 9 | B24: DC Works | C24: 43991 | D24: 16 | E24: 44012 | F24: 43991 | G24: 16 | H24: 44012 | L24: =IF(AND($F24<(L$2+7),$F24>L$2),1, IF(AND($H24<L$2+7,$H24>L$2),3, IF(AND($F24<=L$2, $H24>=L$2), 2, "" ))) | M24: =IF(AND($F24<(M$2+7),$F24>M$2),1, IF(AND($H24<M$2+7,$H24>M$2),3, IF(AND($F24<=M$2, $H24>=M$2), 2, "" ))) | N24: =IF(AND($F24<(N$2+7),$F24>N$2),1, IF(AND($H24<N$2+7,$H24>N$2),3, IF(AND($F24<=N$2, $H24>=N$2), 2, "" ))) | O24: =IF(AND($F24<(O$2+7),$F24>O$2),1, IF(AND($H24<O$2+7,$H24>O$2),3, IF(AND($F24<=O$2, $H24>=O$2), 2, "" ))) | P24: =IF(AND($F24<(P$2+7),$F24>P$2),1, IF(AND($H24<P$2+7,$H24>P$2),3, IF(AND($F24<=P$2, $H24>=P$2), 2, "" ))) | Q24: =IF(AND($F24<(Q$2+7),$F24>Q$2),1, IF(AND($H24<Q$2+7,$H24>Q$2),3, IF(AND($F24<=Q$2, $H24>=Q$2), 2, "" ))) | R24: =IF(AND($F24<(R$2+7),$F24>R$2),1, IF(AND($H24<R$2+7,$H24>R$2),3, IF(AND($F24<=R$2, $H24>=R$2), 2, "" ))) | S24: =IF(AND($F24<(S$2+7),$F24>S$2),1, IF(AND($H24<S$2+7,$H24>S$2),3, IF(AND($F24<=S$2, $H24>=S$2), 2, "" ))) | ... AQ24: =IF(AND($F24<(AQ$2+7),$F24>AQ$2),1, IF(AND($H24<AQ$2+7,$H24>AQ$2),3, IF(AND($F24<=AQ$2, $H24>=AQ$2), 2, "" ))) -> 2
B25: Mounting structure Installation | C25: 43991 | D25: 4 | E25: 43997 | F25: 43991 | G25: 4 | H25: 43997 | L25: =IF(AND($F25<(L$2+7),$F25>L$2),1, IF(AND($H25<L$2+7,$H25>L$2),3, IF(AND($F25<=L$2, $H25>=L$2), 2, "" ))) | M25: =IF(AND($F25<(M$2+7),$F25>M$2),1, IF(AND($H25<M$2+7,$H25>M$2),3, IF(AND($F25<=M$2, $H25>=M$2), 2, "" ))) | N25: =IF(AND($F25<(N$2+7),$F25>N$2),1, IF(AND($H25<N$2+7,$H25>N$2),3, IF(AND($F25<=N$2, $H25>=N$2), 2, "" ))) | O25: =IF(AND($F25<(O$2+7),$F25>O$2),1, IF(AND($H25<O$2+7,$H25>O$2),3, IF(AND($F25<=O$2, $H25>=O$2), 2, "" ))) | P25: =IF(AND($F25<(P$2+7),$F25>P$2),1, IF(AND($H25<P$2+7,$H25>P$2),3, IF(AND($F25<=P$2, $H25>=P$2), 2, "" ))) | Q25: =IF(AND($F25<(Q$2+7),$F25>Q$2),1, IF(AND($H25<Q$2+7,$H25>Q$2),3, IF(AND($F25<=Q$2, $H25>=Q$2), 2, "" ))) | R25: =IF(AND($F25<(R$2+7),$F25>R$2),1, IF(AND($H25<R$2+7,$H25>R$2),3, IF(AND($F25<=R$2, $H25>=R$2), 2, "" ))) | S25: =IF(AND($F25<(S$2+7),$F25>S$2),1, IF(AND($H25<S$2+7,$H25>S$2),3, IF(AND($F25<=S$2, $H25>=S$2), 2, "" ))) | ... AQ25: =IF(AND($F25<(AQ$2+7),$F25>AQ$2),1, IF(AND($H25<AQ$2+7,$H25>AQ$2),3, IF(AND($F25<=AQ$2, $H25>=AQ$2), 2, "" )))
B26: Cable tray Installation | C26: 43997 | D26: 3 | E26: 44004 | F26: 43997 | G26: 3 | H26: 44004 | L26: =IF(AND($F26<(L$2+7),$F26>L$2),1, IF(AND($H26<L$2+7,$H26>L$2),3, IF(AND($F26<=L$2, $H26>=L$2), 2, "" ))) | M26: =IF(AND($F26<(M$2+7),$F26>M$2),1, IF(AND($H26<M$2+7,$H26>M$2),3, IF(AND($F26<=M$2, $H26>=M$2), 2, "" ))) | N26: =IF(AND($F26<(N$2+7),$F26>N$2),1, IF(AND($H26<N$2+7,$H26>N$2),3, IF(AND($F26<=N$2, $H26>=N$2), 2, "" ))) | O26: =IF(AND($F26<(O$2+7),$F26>O$2),1, IF(AND($H26<O$2+7,$H26>O$2),3, IF(AND($F26<=O$2, $H26>=O$2), 2, "" ))) | P26: =IF(AND($F26<(P$2+7),$F26>P$2),1, IF(AND($H26<P$2+7,$H26>P$2),3, IF(AND($F26<=P$2, $H26>=P$2), 2, "" ))) | Q26: =IF(AND($F26<(Q$2+7),$F26>Q$2),1, IF(AND($H26<Q$2+7,$H26>Q$2),3, IF(AND($F26<=Q$2, $H26>=Q$2), 2, "" ))) | R26: =IF(AND($F26<(R$2+7),$F26>R$2),1, IF(AND($H26<R$2+7,$H26>R$2),3, IF(AND($F26<=R$2, $H26>=R$2), 2, "" ))) | S26: =IF(AND($F26<(S$2+7),$F26>S$2),1, IF(AND($H26<S$2+7,$H26>S$2),3, IF(AND($F26<=S$2, $H26>=S$2), 2, "" ))) | ... AQ26: =IF(AND($F26<(AQ$2+7),$F26>AQ$2),1, IF(AND($H26<AQ$2+7,$H26>AQ$2),3, IF(AND($F26<=AQ$2, $H26>=AQ$2), 2, "" )))
B27: DC Cable Installation | C27: 44004 | D27: 2 | E27: 44006 | F27: 44004 | G27: 2 | H27: 44006 | L27: =IF(AND($F27<(L$2+7),$F27>L$2),1, IF(AND($H27<L$2+7,$H27>L$2),3, IF(AND($F27<=L$2, $H27>=L$2), 2, "" ))) | M27: =IF(AND($F27<(M$2+7),$F27>M$2),1, IF(AND($H27<M$2+7,$H27>M$2),3, IF(AND($F27<=M$2, $H27>=M$2), 2, "" ))) | N27: =IF(AND($F27<(N$2+7),$F27>N$2),1, IF(AND($H27<N$2+7,$H27>N$2),3, IF(AND($F27<=N$2, $H27>=N$2), 2, "" ))) | O27: =IF(AND($F27<(O$2+7),$F27>O$2),1, IF(AND($H27<O$2+7,$H27>O$2),3, IF(AND($F27<=O$2, $H27>=O$2), 2, "" ))) | P27: =IF(AND($F27<(P$2+7),$F27>P$2),1, IF(AND($H27<P$2+7,$H27>P$2),3, IF(AND($F27<=P$2, $H27>=P$2), 2, "" ))) | Q27: =IF(AND($F27<(Q$2+7),$F27>Q$2),1, IF(AND($H27<Q$2+7,$H27>Q$2),3, IF(AND($F27<=Q$2, $H27>=Q$2), 2, "" ))) | R27: =IF(AND($F27<(R$2+7),$F27>R$2),1, IF(AND($H27<R$2+7,$H27>R$2),3, IF(AND($F27<=R$2, $H27>=R$2), 2, "" ))) | S27: =IF(AND($F27<(S$2+7),$F27>S$2),1, IF(AND($H27<S$2+7,$H27>S$2),3, IF(AND($F27<=S$2, $H27>=S$2), 2, "" ))) | ... AQ27: =IF(AND($F27<(AQ$2+7),$F27>AQ$2),1, IF(AND($H27<AQ$2+7,$H27>AQ$2),3, IF(AND($F27<=AQ$2, $H27>=AQ$2), 2, "" )))
B28: Module Installation | C28: 44006 | D28: 4 | E28: 44012 | F28: 44006 | G28: 4 | H28: 44012 | L28: =IF(AND($F28<(L$2+7),$F28>L$2),1, IF(AND($H28<L$2+7,$H28>L$2),3, IF(AND($F28<=L$2, $H28>=L$2), 2, "" ))) | M28: =IF(AND($F28<(M$2+7),$F28>M$2),1, IF(AND($H28<M$2+7,$H28>M$2),3, IF(AND($F28<=M$2, $H28>=M$2), 2, "" ))) | N28: =IF(AND($F28<(N$2+7),$F28>N$2),1, IF(AND($H28<N$2+7,$H28>N$2),3, IF(AND($F28<=N$2, $H28>=N$2), 2, "" ))) | O28: =IF(AND($F28<(O$2+7),$F28>O$2),1, IF(AND($H28<O$2+7,$H28>O$2),3, IF(AND($F28<=O$2, $H28>=O$2), 2, "" ))) | P28: =IF(AND($F28<(P$2+7),$F28>P$2),1, IF(AND($H28<P$2+7,$H28>P$2),3, IF(AND($F28<=P$2, $H28>=P$2), 2, "" ))) | Q28: =IF(AND($F28<(Q$2+7),$F28>Q$2),1, IF(AND($H28<Q$2+7,$H28>Q$2),3, IF(AND($F28<=Q$2, $H28>=Q$2), 2, "" ))) | R28: =IF(AND($F28<(R$2+7),$F28>R$2),1, IF(AND($H28<R$2+7,$H28>R$2),3, IF(AND($F28<=R$2, $H28>=R$2), 2, "" ))) | S28: =IF(AND($F28<(S$2+7),$F28>S$2),1, IF(AND($H28<S$2+7,$H28>S$2),3, IF(AND($F28<=S$2, $H28>=S$2), 2, "" ))) | ... AQ28: =IF(AND($F28<(AQ$2+7),$F28>AQ$2),1, IF(AND($H28<AQ$2+7,$H28>AQ$2),3, IF(AND($F28<=AQ$2, $H28>=AQ$2), 2, "" ))) -> 2
B29: Earth Cable Installation | C29: 44004 | D29: 1 | E29: 44005 | F29: 44004 | G29: 1 | H29: 44005 | L29: =IF(AND($F29<(L$2+7),$F29>L$2),1, IF(AND($H29<L$2+7,$H29>L$2),3, IF(AND($F29<=L$2, $H29>=L$2), 2, "" ))) | M29: =IF(AND($F29<(M$2+7),$F29>M$2),1, IF(AND($H29<M$2+7,$H29>M$2),3, IF(AND($F29<=M$2, $H29>=M$2), 2, "" ))) | N29: =IF(AND($F29<(N$2+7),$F29>N$2),1, IF(AND($H29<N$2+7,$H29>N$2),3, IF(AND($F29<=N$2, $H29>=N$2), 2, "" ))) | O29: =IF(AND($F29<(O$2+7),$F29>O$2),1, IF(AND($H29<O$2+7,$H29>O$2),3, IF(AND($F29<=O$2, $H29>=O$2), 2, "" ))) | P29: =IF(AND($F29<(P$2+7),$F29>P$2),1, IF(AND($H29<P$2+7,$H29>P$2),3, IF(AND($F29<=P$2, $H29>=P$2), 2, "" ))) | Q29: =IF(AND($F29<(Q$2+7),$F29>Q$2),1, IF(AND($H29<Q$2+7,$H29>Q$2),3, IF(AND($F29<=Q$2, $H29>=Q$2), 2, "" ))) | R29: =IF(AND($F29<(R$2+7),$F29>R$2),1, IF(AND($H29<R$2+7,$H29>R$2),3, IF(AND($F29<=R$2, $H29>=R$2), 2, "" ))) | S29: =IF(AND($F29<(S$2+7),$F29>S$2),1, IF(AND($H29<S$2+7,$H29>S$2),3, IF(AND($F29<=S$2, $H29>=S$2), 2, "" ))) | ... AQ29: =IF(AND($F29<(AQ$2+7),$F29>AQ$2),1, IF(AND($H29<AQ$2+7,$H29>AQ$2),3, IF(AND($F29<=AQ$2, $H29>=AQ$2), 2, "" )))
A30: 10 | B30: AC Works | C30: 43991 | D30: 8 | E30: 44000 | F30: 43991 | G30: 8 | H30: 44000
B31: Inverters Installation | C31: 43991 | D31: 2 | E31: 43993 | F31: 43991 | G31: 2 | H31: 43993 | L31: =IF(AND($F31<(L$2+7),$F31>L$2),1, IF(AND($H31<L$2+7,$H31>L$2),3, IF(AND($F31<=L$2, $H31>=L$2), 2, "" ))) | M31: =IF(AND($F31<(M$2+7),$F31>M$2),1, IF(AND($H31<M$2+7,$H31>M$2),3, IF(AND($F31<=M$2, $H31>=M$2), 2, "" ))) | N31: =IF(AND($F31<(N$2+7),$F31>N$2),1, IF(AND($H31<N$2+7,$H31>N$2),3, IF(AND($F31<=N$2, $H31>=N$2), 2, "" ))) | O31: =IF(AND($F31<(O$2+7),$F31>O$2),1, IF(AND($H31<O$2+7,$H31>O$2),3, IF(AND($F31<=O$2, $H31>=O$2), 2, "" ))) | P31: =IF(AND($F31<(P$2+7),$F31>P$2),1, IF(AND($H31<P$2+7,$H31>P$2),3, IF(AND($F31<=P$2, $H31>=P$2), 2, "" ))) | Q31: =IF(AND($F31<(Q$2+7),$F31>Q$2),1, IF(AND($H31<Q$2+7,$H31>Q$2),3, IF(AND($F31<=Q$2, $H31>=Q$2), 2, "" ))) | R31: =IF(AND($F31<(R$2+7),$F31>R$2),1, IF(AND($H31<R$2+7,$H31>R$2),3, IF(AND($F31<=R$2, $H31>=R$2), 2, "" ))) | S31: =IF(AND($F31<(S$2+7),$F31>S$2),1, IF(AND($H31<S$2+7,$H31>S$2),3, IF(AND($F31<=S$2, $H31>=S$2), 2, "" ))) | ... AQ31: =IF(AND($F31<(AQ$2+7),$F31>AQ$2),1, IF(AND($H31<AQ$2+7,$H31>AQ$2),3, IF(AND($F31<=AQ$2, $H31>=AQ$2), 2, "" )))
B32: AC BOS Installation | C32: 43993 | D32: 3 | E32: 44000 | F32: 43993 | G32: 3 | H32: 44000 | L32: =IF(AND($F32<(L$2+7),$F32>L$2),1, IF(AND($H32<L$2+7,$H32>L$2),3, IF(AND($F32<=L$2, $H32>=L$2), 2, "" ))) | M32: =IF(AND($F32<(M$2+7),$F32>M$2),1, IF(AND($H32<M$2+7,$H32>M$2),3, IF(AND($F32<=M$2, $H32>=M$2), 2, "" ))) | N32: =IF(AND($F32<(N$2+7),$F32>N$2),1, IF(AND($H32<N$2+7,$H32>N$2),3, IF(AND($F32<=N$2, $H32>=N$2), 2, "" ))) | O32: =IF(AND($F32<(O$2+7),$F32>O$2),1, IF(AND($H32<O$2+7,$H32>O$2),3, IF(AND($F32<=O$2, $H32>=O$2), 2, "" ))) | P32: =IF(AND($F32<(P$2+7),$F32>P$2),1, IF(AND($H32<P$2+7,$H32>P$2),3, IF(AND($F32<=P$2, $H32>=P$2), 2, "" ))) | Q32: =IF(AND($F32<(Q$2+7),$F32>Q$2),1, IF(AND($H32<Q$2+7,$H32>Q$2),3, IF(AND($F32<=Q$2, $H32>=Q$2), 2, "" ))) | R32: =IF(AND($F32<(R$2+7),$F32>R$2),1, IF(AND($H32<R$2+7,$H32>R$2),3, IF(AND($F32<=R$2, $H32>=R$2), 2, "" ))) | S32: =IF(AND($F32<(S$2+7),$F32>S$2),1, IF(AND($H32<S$2+7,$H32>S$2),3, IF(AND($F32<=S$2, $H32>=S$2), 2, "" ))) | ... AQ32: =IF(AND($F32<(AQ$2+7),$F32>AQ$2),1, IF(AND($H32<AQ$2+7,$H32>AQ$2),3, IF(AND($F32<=AQ$2, $H32>=AQ$2), 2, "" )))
B33: AC Cable/Tie-In | C33: 43992 | D33: 3 | E33: 43997 | F33: 43992 | G33: 3 | H33: 43997 | L33: =IF(AND($F33<(L$2+7),$F33>L$2),1, IF(AND($H33<L$2+7,$H33>L$2),3, IF(AND($F33<=L$2, $H33>=L$2), 2, "" ))) | M33: =IF(AND($F33<(M$2+7),$F33>M$2),1, IF(AND($H33<M$2+7,$H33>M$2),3, IF(AND($F33<=M$2, $H33>=M$2), 2, "" ))) | N33: =IF(AND($F33<(N$2+7),$F33>N$2),1, IF(AND($H33<N$2+7,$H33>N$2),3, IF(AND($F33<=N$2, $H33>=N$2), 2, "" ))) | O33: =IF(AND($F33<(O$2+7),$F33>O$2),1, IF(AND($H33<O$2+7,$H33>O$2),3, IF(AND($F33<=O$2, $H33>=O$2), 2, "" ))) | P33: =IF(AND($F33<(P$2+7),$F33>P$2),1, IF(AND($H33<P$2+7,$H33>P$2),3, IF(AND($F33<=P$2, $H33>=P$2), 2, "" ))) | Q33: =IF(AND($F33<(Q$2+7),$F33>Q$2),1, IF(AND($H33<Q$2+7,$H33>Q$2),3, IF(AND($F33<=Q$2, $H33>=Q$2), 2, "" ))) | R33: =IF(AND($F33<(R$2+7),$F33>R$2),1, IF(AND($H33<R$2+7,$H33>R$2),3, IF(AND($F33<=R$2, $H33>=R$2), 2, "" ))) | S33: =IF(AND($F33<(S$2+7),$F33>S$2),1, IF(AND($H33<S$2+7,$H33>S$2),3, IF(AND($F33<=S$2, $H33>=S$2), 2, "" ))) | ... AQ33: =IF(AND($F33<(AQ$2+7),$F33>AQ$2),1, IF(AND($H33<AQ$2+7,$H33>AQ$2),3, IF(AND($F33<=AQ$2, $H33>=AQ$2), 2, "" )))
B34: Monitoring Platform Installation | C34: 43997 | D34: 1 | E34: 44000 | F34: 43997 | G34: 1 | H34: 44000
A35: 11 | B35: Completion | C35: 44000 | D35: 14 | E35: 44014 | F35: 44000 | G35: 14 | H35: 44014 | L35: =IF(AND($F35<(L$2+7),$F35>L$2),1, IF(AND($H35<L$2+7,$H35>L$2),3, IF(AND($F35<=L$2, $H35>=L$2), 2, "" ))) | M35: =IF(AND($F35<(M$2+7),$F35>M$2),1, IF(AND($H35<M$2+7,$H35>M$2),3, IF(AND($F35<=M$2, $H35>=M$2), 2, "" ))) | N35: =IF(AND($F35<(N$2+7),$F35>N$2),1, IF(AND($H35<N$2+7,$H35>N$2),3, IF(AND($F35<=N$2, $H35>=N$2), 2, "" ))) | O35: =IF(AND($F35<(O$2+7),$F35>O$2),1, IF(AND($H35<O$2+7,$H35>O$2),3, IF(AND($F35<=O$2, $H35>=O$2), 2, "" ))) | P35: =IF(AND($F35<(P$2+7),$F35>P$2),1, IF(AND($H35<P$2+7,$H35>P$2),3, IF(AND($F35<=P$2, $H35>=P$2), 2, "" ))) | Q35: =IF(AND($F35<(Q$2+7),$F35>Q$2),1, IF(AND($H35<Q$2+7,$H35>Q$2),3, IF(AND($F35<=Q$2, $H35>=Q$2), 2, "" ))) | R35: =IF(AND($F35<(R$2+7),$F35>R$2),1, IF(AND($H35<R$2+7,$H35>R$2),3, IF(AND($F35<=R$2, $H35>=R$2), 2, "" ))) | S35: =IF(AND($F35<(S$2+7),$F35>S$2),1, IF(AND($H35<S$2+7,$H35>S$2),3, IF(AND($F35<=S$2, $H35>=S$2), 2, "" ))) | ... AQ35: =IF(AND($F35<(AQ$2+7),$F35>AQ$2),1, IF(AND($H35<AQ$2+7,$H35>AQ$2),3, IF(AND($F35<=AQ$2, $H35>=AQ$2), 2, "" ))) -> 3
B36: DC Works | C36: 44012 | D36: 2 | E36: 44014 | F36: 44012 | G36: 2 | H36: 44014 | L36: =IF(AND($F36<(L$2+7),$F36>L$2),1, IF(AND($H36<L$2+7,$H36>L$2),3, IF(AND($F36<=L$2, $H36>=L$2), 2, "" ))) | M36: =IF(AND($F36<(M$2+7),$F36>M$2),1, IF(AND($H36<M$2+7,$H36>M$2),3, IF(AND($F36<=M$2, $H36>=M$2), 2, "" ))) | N36: =IF(AND($F36<(N$2+7),$F36>N$2),1, IF(AND($H36<N$2+7,$H36>N$2),3, IF(AND($F36<=N$2, $H36>=N$2), 2, "" ))) | O36: =IF(AND($F36<(O$2+7),$F36>O$2),1, IF(AND($H36<O$2+7,$H36>O$2),3, IF(AND($F36<=O$2, $H36>=O$2), 2, "" ))) | P36: =IF(AND($F36<(P$2+7),$F36>P$2),1, IF(AND($H36<P$2+7,$H36>P$2),3, IF(AND($F36<=P$2, $H36>=P$2), 2, "" ))) | Q36: =IF(AND($F36<(Q$2+7),$F36>Q$2),1, IF(AND($H36<Q$2+7,$H36>Q$2),3, IF(AND($F36<=Q$2, $H36>=Q$2), 2, "" ))) | R36: =IF(AND($F36<(R$2+7),$F36>R$2),1, IF(AND($H36<R$2+7,$H36>R$2),3, IF(AND($F36<=R$2, $H36>=R$2), 2, "" ))) | S36: =IF(AND($F36<(S$2+7),$F36>S$2),1, IF(AND($H36<S$2+7,$H36>S$2),3, IF(AND($F36<=S$2, $H36>=S$2), 2, "" ))) | ... AQ36: =IF(AND($F36<(AQ$2+7),$F36>AQ$2),1, IF(AND($H36<AQ$2+7,$H36>AQ$2),3, IF(AND($F36<=AQ$2, $H36>=AQ$2), 2, "" ))) -> 3
B37: AC Works | C37: 44000 | D37: 2 | E37: 44004 | F37: 44000 | G37: 2 | H37: 44004 | L37: =IF(AND($F37<(L$2+7),$F37>L$2),1, IF(AND($H37<L$2+7,$H37>L$2),3, IF(AND($F37<=L$2, $H37>=L$2), 2, "" ))) | M37: =IF(AND($F37<(M$2+7),$F37>M$2),1, IF(AND($H37<M$2+7,$H37>M$2),3, IF(AND($F37<=M$2, $H37>=M$2), 2, "" ))) | N37: =IF(AND($F37<(N$2+7),$F37>N$2),1, IF(AND($H37<N$2+7,$H37>N$2),3, IF(AND($F37<=N$2, $H37>=N$2), 2, "" ))) | O37: =IF(AND($F37<(O$2+7),$F37>O$2),1, IF(AND($H37<O$2+7,$H37>O$2),3, IF(AND($F37<=O$2, $H37>=O$2), 2, "" ))) | P37: =IF(AND($F37<(P$2+7),$F37>P$2),1, IF(AND($H37<P$2+7,$H37>P$2),3, IF(AND($F37<=P$2, $H37>=P$2), 2, "" ))) | Q37: =IF(AND($F37<(Q$2+7),$F37>Q$2),1, IF(AND($H37<Q$2+7,$H37>Q$2),3, IF(AND($F37<=Q$2, $H37>=Q$2), 2, "" ))) | R37: =IF(AND($F37<(R$2+7),$F37>R$2),1, IF(AND($H37<R$2+7,$H37>R$2),3, IF(AND($F37<=R$2, $H37>=R$2), 2, "" ))) | S37: =IF(AND($F37<(S$2+7),$F37>S$2),1, IF(AND($H37<S$2+7,$H37>S$2),3, IF(AND($F37<=S$2, $H37>=S$2), 2, "" ))) | ... AQ37: =IF(AND($F37<(AQ$2+7),$F37>AQ$2),1, IF(AND($H37<AQ$2+7,$H37>AQ$2),3, IF(AND($F37<=AQ$2, $H37>=AQ$2), 2, "" )))
A38: D | B38: PAYMENT MILESTONE 4: PRACTICAL COMPLETION | C38: 44012 | D38: 1 | E38: 44013 | F38: 44012 | G38: 1 | H38: 44013 | L38: =IF(AND($F38<(L$2+7),$F38>L$2),1, IF(AND($H38<L$2+7,$H38>L$2),3, IF(AND($F38<=L$2, $H38>=L$2), 2, "" ))) | M38: =IF(AND($F38<(M$2+7),$F38>M$2),1, IF(AND($H38<M$2+7,$H38>M$2),3, IF(AND($F38<=M$2, $H38>=M$2), 2, "" ))) | N38: =IF(AND($F38<(N$2+7),$F38>N$2),1, IF(AND($H38<N$2+7,$H38>N$2),3, IF(AND($F38<=N$2, $H38>=N$2), 2, "" ))) | O38: =IF(AND($F38<(O$2+7),$F38>O$2),1, IF(AND($H38<O$2+7,$H38>O$2),3, IF(AND($F38<=O$2, $H38>=O$2), 2, "" ))) | P38: =IF(AND($F38<(P$2+7),$F38>P$2),1, IF(AND($H38<P$2+7,$H38>P$2),3, IF(AND($F38<=P$2, $H38>=P$2), 2, "" ))) | Q38: =IF(AND($F38<(Q$2+7),$F38>Q$2),1, IF(AND($H38<Q$2+7,$H38>Q$2),3, IF(AND($F38<=Q$2, $H38>=Q$2), 2, "" ))) | R38: =IF(AND($F38<(R$2+7),$F38>R$2),1, IF(AND($H38<R$2+7,$H38>R$2),3, IF(AND($F38<=R$2, $H38>=R$2), 2, "" ))) | S38: =IF(AND($F38<(S$2+7),$F38>S$2),1, IF(AND($H38<S$2+7,$H38>S$2),3, IF(AND($F38<=S$2, $H38>=S$2), 2, "" ))) | ... AQ38: =IF(AND($F38<(AQ$2+7),$F38>AQ$2),1, IF(AND($H38<AQ$2+7,$H38>AQ$2),3, IF(AND($F38<=AQ$2, $H38>=AQ$2), 2, "" ))) -> 3
A39: 12 | B39: Commissioning | C39: 43997 | D39: 22 | E39: 44019 | F39: 43997 | G39: 22 | H39: 44019 | L39: =IF(AND($F39<(L$2+7),$F39>L$2),1, IF(AND($H39<L$2+7,$H39>L$2),3, IF(AND($F39<=L$2, $H39>=L$2), 2, "" ))) | M39: =IF(AND($F39<(M$2+7),$F39>M$2),1, IF(AND($H39<M$2+7,$H39>M$2),3, IF(AND($F39<=M$2, $H39>=M$2), 2, "" ))) | N39: =IF(AND($F39<(N$2+7),$F39>N$2),1, IF(AND($H39<N$2+7,$H39>N$2),3, IF(AND($F39<=N$2, $H39>=N$2), 2, "" ))) | O39: =IF(AND($F39<(O$2+7),$F39>O$2),1, IF(AND($H39<O$2+7,$H39>O$2),3, IF(AND($F39<=O$2, $H39>=O$2), 2, "" ))) | P39: =IF(AND($F39<(P$2+7),$F39>P$2),1, IF(AND($H39<P$2+7,$H39>P$2),3, IF(AND($F39<=P$2, $H39>=P$2), 2, "" ))) | Q39: =IF(AND($F39<(Q$2+7),$F39>Q$2),1, IF(AND($H39<Q$2+7,$H39>Q$2),3, IF(AND($F39<=Q$2, $H39>=Q$2), 2, "" ))) | R39: =IF(AND($F39<(R$2+7),$F39>R$2),1, IF(AND($H39<R$2+7,$H39>R$2),3, IF(AND($F39<=R$2, $H39>=R$2), 2, "" ))) | S39: =IF(AND($F39<(S$2+7),$F39>S$2),1, IF(AND($H39<S$2+7,$H39>S$2),3, IF(AND($F39<=S$2, $H39>=S$2), 2, "" ))) | ... AQ39: =IF(AND($F39<(AQ$2+7),$F39>AQ$2),1, IF(AND($H39<AQ$2+7,$H39>AQ$2),3, IF(AND($F39<=AQ$2, $H39>=AQ$2), 2, "" ))) -> 2
B40: Snag List | C40: 44014 | D40: 3 | E40: 44019 | F40: 44014 | G40: 3 | H40: 44019
B41: Pre-Commissioning Checks | C41: 44010 | D41: 2 | E41: 44012 | F41: 44010 | G41: 2 | H41: 44012
B42: Issue CoC | C42: 43997 | D42: 2 | E42: 44001 | F42: 43997 | G42: 2 | H42: 44001 | L42: =IF(AND($F42<(L$2+7),$F42>L$2),1, IF(AND($H42<L$2+7,$H42>L$2),3, IF(AND($F42<=L$2, $H42>=L$2), 2, "" ))) | M42: =IF(AND($F42<(M$2+7),$F42>M$2),1, IF(AND($H42<M$2+7,$H42>M$2),3, IF(AND($F42<=M$2, $H42>=M$2), 2, "" ))) | N42: =IF(AND($F42<(N$2+7),$F42>N$2),1, IF(AND($H42<N$2+7,$H42>N$2),3, IF(AND($F42<=N$2, $H42>=N$2), 2, "" ))) | O42: =IF(AND($F42<(O$2+7),$F42>O$2),1, IF(AND($H42<O$2+7,$H42>O$2),3, IF(AND($F42<=O$2, $H42>=O$2), 2, "" ))) | P42: =IF(AND($F42<(P$2+7),$F42>P$2),1, IF(AND($H42<P$2+7,$H42>P$2),3, IF(AND($F42<=P$2, $H42>=P$2), 2, "" ))) | Q42: =IF(AND($F42<(Q$2+7),$F42>Q$2),1, IF(AND($H42<Q$2+7,$H42>Q$2),3, IF(AND($F42<=Q$2, $H42>=Q$2), 2, "" ))) | R42: =IF(AND($F42<(R$2+7),$F42>R$2),1, IF(AND($H42<R$2+7,$H42>R$2),3, IF(AND($F42<=R$2, $H42>=R$2), 2, "" ))) | S42: =IF(AND($F42<(S$2+7),$F42>S$2),1, IF(AND($H42<S$2+7,$H42>S$2),3, IF(AND($F42<=S$2, $H42>=S$2), 2, "" ))) | ... AQ42: =IF(AND($F42<(AQ$2+7),$F42>AQ$2),1, IF(AND($H42<AQ$2+7,$H42>AQ$2),3, IF(AND($F42<=AQ$2, $H42>=AQ$2), 2, "" )))
B43: Cold Commissioning | C43: 44012 | D43: 1 | E43: 44013 | F43: 44012 | G43: 1 | H43: 44013 | L43: =IF(AND($F43<(L$2+7),$F43>L$2),1, IF(AND($H43<L$2+7,$H43>L$2),3, IF(AND($F43<=L$2, $H43>=L$2), 2, "" ))) | M43: =IF(AND($F43<(M$2+7),$F43>M$2),1, IF(AND($H43<M$2+7,$H43>M$2),3, IF(AND($F43<=M$2, $H43>=M$2), 2, "" ))) | N43: =IF(AND($F43<(N$2+7),$F43>N$2),1, IF(AND($H43<N$2+7,$H43>N$2),3, IF(AND($F43<=N$2, $H43>=N$2), 2, "" ))) | O43: =IF(AND($F43<(O$2+7),$F43>O$2),1, IF(AND($H43<O$2+7,$H43>O$2),3, IF(AND($F43<=O$2, $H43>=O$2), 2, "" ))) | P43: =IF(AND($F43<(P$2+7),$F43>P$2),1, IF(AND($H43<P$2+7,$H43>P$2),3, IF(AND($F43<=P$2, $H43>=P$2), 2, "" ))) | Q43: =IF(AND($F43<(Q$2+7),$F43>Q$2),1, IF(AND($H43<Q$2+7,$H43>Q$2),3, IF(AND($F43<=Q$2, $H43>=Q$2), 2, "" ))) | R43: =IF(AND($F43<(R$2+7),$F43>R$2),1, IF(AND($H43<R$2+7,$H43>R$2),3, IF(AND($F43<=R$2, $H43>=R$2), 2, "" ))) | S43: =IF(AND($F43<(S$2+7),$F43>S$2),1, IF(AND($H43<S$2+7,$H43>S$2),3, IF(AND($F43<=S$2, $H43>=S$2), 2, "" ))) | ... AQ43: =IF(AND($F43<(AQ$2+7),$F43>AQ$2),1, IF(AND($H43<AQ$2+7,$H43>AQ$2),3, IF(AND($F43<=AQ$2, $H43>=AQ$2), 2, "" ))) -> 3
B44: Hot Commissioning | C44: 44013 | D44: 2 | E44: 44015 | F44: 44013 | G44: 2 | H44: 44015 | L44: =IF(AND($F44<(L$2+7),$F44>L$2),1, IF(AND($H44<L$2+7,$H44>L$2),3, IF(AND($F44<=L$2, $H44>=L$2), 2, "" ))) | M44: =IF(AND($F44<(M$2+7),$F44>M$2),1, IF(AND($H44<M$2+7,$H44>M$2),3, IF(AND($F44<=M$2, $H44>=M$2), 2, "" ))) | N44: =IF(AND($F44<(N$2+7),$F44>N$2),1, IF(AND($H44<N$2+7,$H44>N$2),3, IF(AND($F44<=N$2, $H44>=N$2), 2, "" ))) | O44: =IF(AND($F44<(O$2+7),$F44>O$2),1, IF(AND($H44<O$2+7,$H44>O$2),3, IF(AND($F44<=O$2, $H44>=O$2), 2, "" ))) | P44: =IF(AND($F44<(P$2+7),$F44>P$2),1, IF(AND($H44<P$2+7,$H44>P$2),3, IF(AND($F44<=P$2, $H44>=P$2), 2, "" ))) | Q44: =IF(AND($F44<(Q$2+7),$F44>Q$2),1, IF(AND($H44<Q$2+7,$H44>Q$2),3, IF(AND($F44<=Q$2, $H44>=Q$2), 2, "" ))) | R44: =IF(AND($F44<(R$2+7),$F44>R$2),1, IF(AND($H44<R$2+7,$H44>R$2),3, IF(AND($F44<=R$2, $H44>=R$2), 2, "" ))) | S44: =IF(AND($F44<(S$2+7),$F44>S$2),1, IF(AND($H44<S$2+7,$H44>S$2),3, IF(AND($F44<=S$2, $H44>=S$2), 2, "" ))) | ... AQ44: =IF(AND($F44<(AQ$2+7),$F44>AQ$2),1, IF(AND($H44<AQ$2+7,$H44>AQ$2),3, IF(AND($F44<=AQ$2, $H44>=AQ$2), 2, "" ))) -> 1
A45: 13 | B45: Handover | C45: 44020 | D45: 1 | E45: 44021 | F45: 44020 | G45: 1 | H45: 44021 | L45: =IF(AND($F45<(L$2+7),$F45>L$2),1, IF(AND($H45<L$2+7,$H45>L$2),3, IF(AND($F45<=L$2, $H45>=L$2), 2, "" ))) | M45: =IF(AND($F45<(M$2+7),$F45>M$2),1, IF(AND($H45<M$2+7,$H45>M$2),3, IF(AND($F45<=M$2, $H45>=M$2), 2, "" ))) | N45: =IF(AND($F45<(N$2+7),$F45>N$2),1, IF(AND($H45<N$2+7,$H45>N$2),3, IF(AND($F45<=N$2, $H45>=N$2), 2, "" ))) | O45: =IF(AND($F45<(O$2+7),$F45>O$2),1, IF(AND($H45<O$2+7,$H45>O$2),3, IF(AND($F45<=O$2, $H45>=O$2), 2, "" ))) | P45: =IF(AND($F45<(P$2+7),$F45>P$2),1, IF(AND($H45<P$2+7,$H45>P$2),3, IF(AND($F45<=P$2, $H45>=P$2), 2, "" ))) | Q45: =IF(AND($F45<(Q$2+7),$F45>Q$2),1, IF(AND($H45<Q$2+7,$H45>Q$2),3, IF(AND($F45<=Q$2, $H45>=Q$2), 2, "" ))) | R45: =IF(AND($F45<(R$2+7),$F45>R$2),1, IF(AND($H45<R$2+7,$H45>R$2),3, IF(AND($F45<=R$2, $H45>=R$2), 2, "" ))) | S45: =IF(AND($F45<(S$2+7),$F45>S$2),1, IF(AND($H45<S$2+7,$H45>S$2),3, IF(AND($F45<=S$2, $H45>=S$2), 2, "" ))) | ... AQ45: =IF(AND($F45<(AQ$2+7),$F45>AQ$2),1, IF(AND($H45<AQ$2+7,$H45>AQ$2),3, IF(AND($F45<=AQ$2, $H45>=AQ$2), 2, "" )))
A46: E | B46: PAYMENT MILESTONE 6: HANDOVER COMPLETE | C46: 44022 | D46: 1 | E46: 44025 | F46: 44022 | G46: 1 | H46: 44025
C47: 43831 | D47: These numbers are used to set the start and end dates on the Gantt Chart
C48: 44014

Sheet Revenue Tracking
B2: HIGH LEVEL PROJECT REVENUE TRACKING
D3: PLANNED | F3: ACTUAL | L3: FINANCIAL REVIEW | N3: TIMELINE REVIEW
B4: 1 | C4: Planned Revenue | D4: ='Project Plan'!E8 -> 11535559 | F4: =F22 -> 11729548 | L4: 11729548 | N4: Start Date
B5: 2 | C5: Planned Expenditure | D5: =+'Expenditure Tracking'!F5 -> 10556110 | F5: =+'Expenditure Tracking'!J5 -> 11989843 | G5: VO PM Limit | H5: Current VO Total | L5: 10805125 | N5: 45691
B6: 3 | C6: Planned Profit | D6: =+D4-D5 -> 979449.23 | F6: =+F4-F5 -> -260295 | G6: =D6*0.05 -> 48972.461 | H6: =SUMIF('Expenditure Breakdown'!O:O,"*VO*",'Expenditure Breakdown'!R:R) -> 893309.64 | L6: 924422.46 | N6: End Date - PC
B7: 4 | C7: Planned Margin | D7: =+D6/D4 -> 0.084906955 | F7: =+F6/F4 -> -0.022191393 | L7: 0.078811434 | N7: 45772
B10: CONTRACT
B12: No. | C12: PAYMENT MILESTONE | E12: % | F12: VALUE | H12: PLANNED PAYMENT DATE | L12: INVOICE NUMBER | N12: INVOICE RAISED DATE | P12: PAYMENT RECEIVED DATE | R12: MILESTONE NOTES & COMMENTS
B13: 1 | C13: Deposit | E13: 0.35 | F13: =$D$4*E13 -> 4037445.8 | H13: ='Project Plan'!G14+21 -> 45635 | L13: 004646 | N13: 45673 | P13: 45679
B14: 2 | C14: Delivery of Main Equipment (Solar Panels Inverters and Balance of System) | E14: 0.3 | F14: =$D$4*E14 -> 3460667.8 | H14: ='Project Plan'!E40+21 -> 45712 | L14: 004646 | N14: 45673 | P14: 45695
B15: 3 | C15: Delivery of Main Equipment (Inverters, Batteries and Balance of System) | E15: 0.2 | F15: =$D$4*E15 -> 2307111.9 | H15: ='Project Plan'!E26+21 -> 45733 | L15: 004646 | N15: 45673 | P15: 45679
B16: 4 | C16: Installation Completion Date (Physical Completion) | E16: 0.1 | F16: =$D$4*E16 -> 1153555.9 | H16: ='Project Plan'!G45+21 -> 45793 | L16: 004646 | N16: 45673 | P16: 45789
B17: 5 | C17: Handover | E17: 0.05 | F17: =$D$4*E17 -> 576777.97 | H17: ='Project Plan'!G56+21 -> 45810 | L17: 004646 | N17: 45673 | P17: 45835
B18: 6 | C18: VO - Roof Repairs | E18: 0.7 | F18: 73118.58 | H18: =H16 -> 45793 | L18: 004636 | N18: 45639 | P18: 45639
B19: 6 | C19: VO - Roof Repairs | F19: =149221.6-F18 -> 76103.02 | H19: =H17 -> 45810 | L19: 004636 | N19: 45639 | P19: 45701
B20: 6 | C20: VO - Roof Repairs | E20: 0.3 | F20: =149221.6*E20 -> 44766.48 | H20: =H16 -> 45793 | L20: 004654 | N20: 45684 | P20: 45701
E22: =SUM(E13:E20) -> 2 | F22: =SUM(F13:F20) -> 11729548
B24: KEY: | C24: contains an error (in result or a check has failed)
C25: Red Font - IF TEXT : content not yet confirmed | H25: =F17*1.15 -> 663294.67
C26: Red Font - IF NUMBER: Negative value
C27: Anything in yellow is a concern or risk for noting or action
C28: confirmed
C29: [ADD INITIALS: comment for noting in square brackets, use colour or red to draw attention if important]
C30: [RT: When adding rows into sheet, ensure you insert between first and last row of each category]
C31: end of sheet - do not insert information below/beyond this
L36: =6344558/1.15 -> 5517007 | N36: =L36-F13 -> 1479561.1
B41: No. | C41: PAYMENT MILESTONE | E41: % | F41: VALUE
B42: 1 | C42: Deposit - Project commencement | E42: 0.35 | F42: =$F$48*E42 -> 4105341.6
B43: 2 | C43: Delivery of Panels | E43: 0.3 | F43: =$F$48*E43 -> 3518864.3
B44: 3 | C44: Delivery of Inverters | E44: 0.2 | F44: =$F$48*E44 -> 2345909.5
B45: 4 | C45: Practical Completion | E45: 0.1 | F45: =$F$48*E45 -> 1172954.8
B46: 5 | C46: Handover | E46: 0.05 | F46: =$F$48*E46 -> 586477.38
C47: Total | E47: =SUM(E42:E46) -> 1 | F47: =SUM(F42:F46) -> 11729548
E48: =SUM(E42:E46) -> 1 | F48: =F22 -> 11729548

Sheet Project Plan
N1: =TODAY() -> 46087 | O1: =TODAY() -> 46087
C2: PROJECT PLAN | E2: Mayo Macs | N2: 0 | O2: 1
C3: PROJECT SIZE (kWp) | E3: 400
C4: SITE ADDRESS
C5: BUSINESS DEVELOPER | E5: Megan
C6: PROJECT MANAGERS | E6: JT
C7: INSTALLER | E7: TBC
C8: CONTRACT VALUE | E8: 11535559
C9: Phase: | E9: DLP
B10: No. | C10: HIGH LEVEL PROGRAMME | E10: Planned Start | F10: Duration (days) | G10: Planned End | I10: Actual Start | J10: Duration (days) | K10: Actual End | M10: Status | O10: Comment
F11: =G45-E21 -> 81 | J11: =K45-I21 -> 93 | M11: =AVERAGE(M13,M20,M24,M33,M39,M43,M51,M48) -> 1 | N11: =AVERAGE(N13,N20,N24,N33,N39,N43,N51,N48) -> 1
B13: 1 | C13: Project Initiation | E13: 45594 | F13: 25 | G13: 45619 | I13: =MIN(I14:I18) -> 45611 | J13: 25 | K13: =MAX(K14:K18) -> 45685 | M13: =(J14*M14+J15*M15+J16*M16+J17*M17+J18*M18)/SUM(J14:J18) -> 1 | N13: =(K14*N14+K15*N15+K16*N16+K17*N17+K18*N18)/SUM(K14:K18) -> 1
B14: 1.1 | C14: BD Handover | E14: 45611 | F14: 1 | G14: =WORKDAY.INTL(E14,F14,1,Data!$C$3:$C$26) -> 45614 | I14: 45611 | J14: 1 | K14: =WORKDAY.INTL(I14,J14,1,Data!$C$3:$C$26) -> 45614 | M14: 1 | N14: 1
B15: 1.2 | C15: Project Introduction | E15: 45673 | F15: 1 | G15: =WORKDAY.INTL(E15,F15,1,Data!$C$3:$C$26) -> 45674 | I15: 45673 | J15: 1 | K15: =WORKDAY.INTL(I15,J15,1,Data!$C$3:$C$26) -> 45674 | M15: 1 | N15: 1
B16: 1.3 | C16: HSE | E16: 45667 | F16: 10 | G16: =WORKDAY.INTL(E16,F16,1,Data!$C$3:$C$26) -> 45681 | I16: 45667 | J16: 10 | K16: =WORKDAY.INTL(I16,J16,1,Data!$C$3:$C$26) -> 45681 | M16: 1 | N16: 1
B17: 1.4 | C17: Installer Kick Off | E17: =E21-7 -> 45684 | F17: 1 | G17: =WORKDAY.INTL(E17,F17,1,Data!$C$3:$C$26) -> 45685 | I17: =I21-7 -> 45684 | J17: 1 | K17: =WORKDAY.INTL(I17,J17,1,Data!$C$3:$C$26) -> 45685 | M17: 1 | N17: 1
B18: 1.5 | C18: Project Review | E18: 45679 | F18: 1 | G18: =WORKDAY.INTL(E18,F18,1,Data!$C$3:$C$26) -> 45680 | I18: 45679 | J18: 1 | K18: =WORKDAY.INTL(I18,J18,1,Data!$C$3:$C$26) -> 45680 | M18: 1 | N18: 1
B20: 2 | C20: Site Establishment | E20: =MIN(E21:E23) -> 45684 | F20: =G20-E20 -> 8 | G20: =MAX(G21) -> 45692 | I20: =MIN(I21:I23) -> 45684 | J20: =K20-I20 -> 9 | K20: =MAX(K21) -> 45693 | M20: 1 | N20: 1
B21: 2.1 | C21: Installer on site & Roof Assessment | E21: 45691 | F21: 1 | G21: =WORKDAY.INTL(E21,F21,1,Data!$C$3:$C$26) -> 45692 | I21: 45691 | J21: 2 | K21: =WORKDAY.INTL(I21,J21,1,Data!$C$3:$C$26) -> 45693 | M21: 1 | N21: 1 | S21: =NETWORKDAYS(I21,K53) -> 155
B22: 2.2 | C22: Battery/Inverter Room Construction | E22: 45684 | F22: 30 | G22: =WORKDAY.INTL(E22,F22,1,Data!$C$3:$C$26) -> 45726 | I22: 45684 | J22: 40 | K22: =WORKDAY.INTL(I22,J22,1,Data!$C$3:$C$26) -> 45741 | M22: 1 | N22: 1 | S22: =NETWORKDAYS(I22,K54) -> 160
B24: 3 | C24: AC Installation | E24: =MIN(E25:E31) -> 45672 | F24: =G24-E24 -> 84 | G24: =MAX(G25:G31) -> 45756 | I24: =MIN(I25:I31) -> 45672 | J24: =K24-I24 -> 90 | K24: =MAX(K25:K31) -> 45762 | M24: =(J25*M25+J26*M26+J27*M26+J28*M28+J29*M29+J30*M30+J31*M31)/SUM(J25:J31) -> 1 | N24: =(K25*N25+K26*N26+K27*N26+K28*N28+K29*N29+K30*N30+K31*N31)/SUM(K25:K31) -> 1 | S24: =S21/5 -> 31
B25: 3.1.1 | C25: Inverters delivered | E25: =WORKDAY.INTL(G22,0,1,Data!$C$3:$C$26)-14 -> 45712 | F25: 1 | G25: =WORKDAY.INTL(E25,F25,1,Data!$C$3:$C$26) -> 45713 | I25: 45708 | J25: 1 | K25: =WORKDAY.INTL(I25,J25,1,Data!$C$3:$C$26) -> 45709 | M25: 1 | N25: 1
B26: 3.1.2 | C26: Hybrid Inverters Delivered | E26: =E25 -> 45712 | F26: 1 | G26: =WORKDAY.INTL(E26,F26,1,Data!$C$3:$C$26) -> 45713 | I26: 45729 | J26: 1 | K26: =WORKDAY.INTL(I26,J26,1,Data!$C$3:$C$26) -> 45730 | M26: 1 | N26: 1
B27: 3.1.3 | C27: Batteries Delivered | E27: 45672 | F27: 30 | G27: =WORKDAY.INTL(E27,F27,1,Data!$C$3:$C$26) -> 45714 | I27: 45672 | J27: 41 | K27: =WORKDAY.INTL(I27,J27,1,Data!$C$3:$C$26) -> 45729 | M27: 1 | N27: 1
B28: 3.2 | C28: Inverters Mounted | E28: =WORKDAY.INTL(G25,0,1,Data!$C$3:$C$26) -> 45713 | F28: 10 | G28: =WORKDAY.INTL(E28,F28,1,Data!$C$3:$C$26) -> 45727 | I28: =WORKDAY.INTL(K26,0,1,Data!$C$3:$C$26) -> 45730 | J28: 1 | K28: =WORKDAY.INTL(I28,J28,1,Data!$C$3:$C$26) -> 45733 | M28: 1 | N28: 1 | S28: =E3/S24 -> 12.903226
B29: 3.3 | C29: Solar DB Lead Time | E29: =WORKDAY.INTL(E17,0,1,Data!$C$3:$C$26) -> 45684 | F29: 30 | G29: =WORKDAY.INTL(E29,F29,1,Data!$C$3:$C$26) -> 45726 | I29: =WORKDAY.INTL(I17,0,1,Data!$C$3:$C$26) -> 45684 | J29: 40 | K29: =WORKDAY.INTL(I29,J29,1,Data!$C$3:$C$26) -> 45741 | M29: 1 | N29: 1
B30: 3.4 | C30: AC Works | E30: =WORKDAY.INTL(G28,0,1,Data!$C$3:$C$26) -> 45727 | F30: 20 | G30: =WORKDAY.INTL(E30,F30,1,Data!$C$3:$C$26) -> 45756 | I30: =WORKDAY.INTL(K28,0,1,Data!$C$3:$C$26) -> 45733 | J30: 20 | K30: =WORKDAY.INTL(I30,J30,1,Data!$C$3:$C$26) -> 45762 | M30: 1 | N30: 1
B31: 3.5 | C31: AC Tie-In | E31: =WORKDAY.INTL(G30,0,1,Data!$C$3:$C$26)-7 -> 45749 | F31: 3 | G31: =WORKDAY.INTL(E31,F31,1,Data!$C$3:$C$26) -> 45754 | I31: =WORKDAY.INTL(K30,0,1,Data!$C$3:$C$26)-7 -> 45755 | J31: 1 | K31: =WORKDAY.INTL(I31,J31,1,Data!$C$3:$C$26) -> 45756 | M31: 1 | N31: 1
B33: 4 | C33: DC Works | E33: =MIN(E34:E37) -> 45691 | F33: =G33-E33 -> 28 | G33: =MAX(G34:G37) -> 45719 | I33: =MIN(I34:I37) -> 45700 | J33: =K33-I33 -> 64 | K33: =MAX(K34:K37) -> 45764 | M33: 1 | N33: 1
B34: 4.1 | C34: Mounting Structure delivered | E34: =WORKDAY.INTL(E21,0,1,Data!$C$3:$C$26) -> 45691 | F34: 1 | G34: =WORKDAY.INTL(E34,F34,1,Data!$C$3:$C$26) -> 45692 | I34: 45700 | J34: 1 | K34: =WORKDAY.INTL(I34,J34,1,Data!$C$3:$C$26) -> 45701 | M34: 1 | N34: 1
B35: 4.2 | C35: Mounting Structure installation | E35: =WORKDAY.INTL(G34,0,1,Data!$C$3:$C$26) -> 45692 | F35: 12 | G35: =WORKDAY.INTL(E35,F35,1,Data!$C$3:$C$26) -> 45708 | I35: =WORKDAY.INTL(K34,0,1,Data!$C$3:$C$26) -> 45701 | J35: 12 | K35: =WORKDAY.INTL(I35,J35,1,Data!$C$3:$C$26) -> 45719 | M35: 1 | N35: 1
B36: 4.3 | C36: DC Cable delivered | E36: =WORKDAY.INTL(E21,0,1,Data!$C$3:$C$26) -> 45691 | F36: 1 | G36: =WORKDAY.INTL(E36,F36,1,Data!$C$3:$C$26) -> 45692 | I36: 45708 | J36: 1 | K36: =WORKDAY.INTL(I36,J36,1,Data!$C$3:$C$26) -> 45709 | M36: 1 | N36: 1
B37: 4.4 | C37: DC Stringing | E37: =WORKDAY.INTL(G36,0,1,Data!$C$3:$C$26) -> 45692 | F37: 19 | G37: =WORKDAY.INTL(E37,F37,1,Data!$C$3:$C$26) -> 45719 | I37: =WORKDAY.INTL(K41,0,1,Data!$C$3:$C$26)-10 -> 45738 | J37: 19 | K37: =WORKDAY.INTL(I37,J37,1,Data!$C$3:$C$26) -> 45764 | M37: 1 | N37: 1
B39: 5 | C39: Module installation | E39: =MIN(E40:E41) -> 45691 | F39: =G39-E39 -> 53 | G39: =MAX(G40:G41) -> 45744 | I39: =MIN(I40:I41) -> 45708 | J39: =K39-I39 -> 40 | K39: =MAX(K40:K41) -> 45748 | M39: =(J40*M40+J41*M41)/SUM(J40:J41) -> 1 | N39: =(K40*N40+K41*N41)/SUM(K40:K41) -> 1
B40: 5.1 | C40: Module delivery | E40: =E21 -> 45691 | F40: 1 | G40: =WORKDAY.INTL(E40,F40,1,Data!$C$3:$C$26) -> 45692 | I40: 45708 | J40: 1 | K40: =WORKDAY.INTL(I40,J40,1,Data!$C$3:$C$26) -> 45709 | M40: 1 | N40: 1
B41: 5.2 | C41: Module mounting | E41: =WORKDAY.INTL(G35,0,1,Data!$C$3:$C$26)-7 -> 45701 | F41: 30 | G41: =WORKDAY.INTL(E41,F41,1,Data!$C$3:$C$26) -> 45744 | I41: =WORKDAY.INTL(K35,0,1,Data!$C$3:$C$26)-7 -> 45712 | J41: 25 | K41: =WORKDAY.INTL(I41,J41,1,Data!$C$3:$C$26) -> 45748 | M41: 1 | N41: 1
B43: 6 | C43: Commissioning | E43: =MIN(E44:E45) -> 45756 | F43: =G43-E43 -> 16 | G43: =MAX(G44:G45) -> 45772 | I43: =MIN(I44:I45) -> 45764 | J43: =K43-I43 -> 20 | K43: =MAX(K44:K45) -> 45784 | M43: =(J44*M44+J45*M45)/SUM(J44:J45) -> 1 | N43: =(K44*N44+K45*N45)/SUM(K44:K45) -> 1
B44: 6.1 | C44: Commissioning | E44: =WORKDAY.INTL(MAX(G24,G33,G39),0,1,Data!$C$3:$C$26) -> 45756 | F44: 5 | G44: =WORKDAY.INTL(E44,F44,1,Data!$C$3:$C$26) -> 45763 | I44: =WORKDAY.INTL(MAX(K24,K33,K39),0,1,Data!$C$3:$C$26) -> 45764 | J44: 5 | K44: =WORKDAY.INTL(I44,J44,1,Data!$C$3:$C$26) -> 45776 | M44: 1 | N44: 1
B45: 6.2 | C45: Practical Completion | E45: =WORKDAY.INTL(G44,0,1,Data!$C$3:$C$26) -> 45763 | F45: 5 | G45: =WORKDAY.INTL(E45,F45,1,Data!$C$3:$C$26) -> 45772 | I45: =WORKDAY.INTL(K44,0,1,Data!$C$3:$C$26) -> 45776 | J45: 5 | K45: =WORKDAY.INTL(I45,J45,1,Data!$C$3:$C$26) -> 45784 | M45: 1 | N45: 1
B46: 6.3 | C46: Post-Installation Commissioning | E46: =WORKDAY.INTL(G45,0,1,Data!$C$3:$C$26) -> 45772 | F46: 10 | G46: =WORKDAY.INTL(E46,F46,1,Data!$C$3:$C$26) -> 45790 | I46: =WORKDAY.INTL(K45,0,1,Data!$C$3:$C$26) -> 45784 | J46: 15 | K46: =WORKDAY.INTL(I46,J46,1,Data!$C$3:$C$26) -> 45805 | M46: 1 | N46: 1
B48: 7 | C48: QA Inspections | E48: =MIN(E49) -> 45756 | F48: =G48-E48 -> 14 | G48: =MAX(G49) -> 45770 | I48: =MIN(I49) -> 45784 | J48: =K48-I48 -> 19 | K48: =MAX(K49) -> 45803 | M48: =(J49*M49)/SUM(J49) -> 1 | N48: =(K49*N49)/SUM(K49) -> 1
B49: 7.1 | C49: Red-Team Inspection | E49: =WORKDAY.INTL(E44,0,1,Data!$C$3:$C$26) -> 45756 | F49: 8 | G49: =WORKDAY.INTL(E49,F49,1,Data!$C$3:$C$26) -> 45770 | I49: =WORKDAY.INTL(K45,0,1,Data!$C$3:$C$26) -> 45784 | J49: 13 | K49: =WORKDAY.INTL(I49,J49,1,Data!$C$3:$C$26) -> 45803 | M49: 1 | N49: 1
B51: 8 | C51: Project Closure | E51: =MIN(E52:E57) -> 45752 | F51: =G51-E51 -> 37 | G51: =MAX(G52:G57) -> 45789 | I51: =MIN(I52:I57) -> 45780 | J51: =K51-I51 -> 131 | K51: =MAX(K52:K57) -> 45911 | M51: =(J52*M52+J53*M53+J54*M54+J55*M55+J56*M56+J57*M57)/SUM(J52:J57) -> 1 | N51: =(K52*N52+K53*N53+K54*N54+K55*N55+K56*N56+K57*N57)/SUM(K52:K57) -> 1
B52: 8.1 | C52: Equipment serial numbers | E52: =WORKDAY.INTL(E48,0,1,Data!$C$3:$C$26)-4 -> 45752 | F52: 2 | G52: =WORKDAY.INTL(E52,F52,1,Data!$C$3:$C$26) -> 45755 | I52: =WORKDAY.INTL(I48,0,1,Data!$C$3:$C$26)-4 -> 45780 | J52: 2 | K52: =WORKDAY.INTL(I52,J52,1,Data!$C$3:$C$26) -> 45783 | M52: 1 | N52: 1
B53: 8.2 | C53: Snags completion | E53: =WORKDAY.INTL(E49,0,1,Data!$C$3:$C$26) -> 45756 | F53: 2 | G53: =WORKDAY.INTL(E53,F53,1,Data!$C$3:$C$26) -> 45758 | I53: =WORKDAY.INTL(K49,0,1,Data!$C$3:$C$26) -> 45803 | J53: 73 | K53: =WORKDAY.INTL(I53,J53,1,Data!$C$3:$C$26) -> 45905 | M53: 1 | N53: 1
B54: 8.3 | C54: System Performance Monitoring | E54: =WORKDAY.INTL(G45,0,1,Data!$C$3:$C$26) -> 45772 | F54: 2 | G54: =WORKDAY.INTL(E54,F54,1,Data!$C$3:$C$26) -> 45777 | I54: =WORKDAY.INTL(K53,0,1,Data!$C$3:$C$26)-14 -> 45891 | J54: 10 | K54: =WORKDAY.INTL(I54,J54,1,Data!$C$3:$C$26) -> 45905 | M54: 1 | N54: 1
B55: 8.4 | C55: Handover documentation | E55: =WORKDAY.INTL(G49,0,1,Data!$C$3:$C$26) -> 45770 | F55: 10 | G55: =WORKDAY.INTL(E55,F55,1,Data!$C$3:$C$26) -> 45786 | I55: =WORKDAY.INTL(I52,0,1,Data!$C$3:$C$26) -> 45780 | J55: 5 | K55: =WORKDAY.INTL(I55,J55,1,Data!$C$3:$C$26) -> 45786 | M55: 1 | N55: 1
B56: 8.5 | C56: Handover to Client | E56: =WORKDAY.INTL(G55,0,1,Data!$C$3:$C$26) -> 45786 | F56: 1 | G56: =WORKDAY.INTL(E56,F56,1,Data!$C$3:$C$26) -> 45789 | I56: =WORKDAY.INTL(K53,0,1,Data!$C$3:$C$26)+5 -> 45910 | J56: 1 | K56: =WORKDAY.INTL(I56,J56,1,Data!$C$3:$C$26) -> 45911 | M56: 1 | N56: 1
B57: 8.6 | C57: Handover to Matriarch | E57: =WORKDAY.INTL(G53,0,1,Data!$C$3:$C$26)+5 -> 45763 | F57: 5 | G57: =WORKDAY.INTL(E57,F57,1,Data!$C$3:$C$26) -> 45772 | I57: 45855 | J57: 25 | K57: =WORKDAY.INTL(I57,J57,1,Data!$C$3:$C$26) -> 45890 | M57: 1 | N57: 1

Sheet Expenditure Tracking
B2: HIGH LEVEL PROJECT EXPENDITURE TRACKING
F4: COSTED | H4: PLANNED | J4: ACTUAL | L4: Difference from costed | N4: Difference from planned
B5: EXPENDITURE | F5: =SUM(F9:F23) -> 10556110 | H5: =SUM(H9:H23) -> 10804925 | J5: =SUM(J9:J23) -> 11989843 | L5: =SUM(L9:L23) -> -1433732.3 | N5: =SUM(N9:N23) -> -1184917.5
B7: No. | D7: Item | F7: Costed Expenditure | H7: Planned Expenditure | J7: Actual Expenditure | L7: Saving / Overrun | N7: Saving / Overrun | P7: Comments on variations from planned expenditure
B9: ='Expenditure Breakdown'!B6 -> 1 | D9: ='Expenditure Breakdown'!C6 -> Panels | F9: ='Expenditure Breakdown'!J6 -> 1077596.6 | H9: 948317.8 | J9: ='Expenditure Breakdown'!X6 -> 908317.8 | L9: =F9-J9 -> 169278.76 | N9: =H9-J9 -> 40000
B10: ='Expenditure Breakdown'!B13 -> 2 | D10: ='Expenditure Breakdown'!C13 -> Inverters | F10: =+'Expenditure Breakdown'!J13 -> 210000 | H10: 252941.6 | J10: =+'Expenditure Breakdown'!X13 -> 180931.83 | L10: =F10-J10 -> 29068.17 | N10: =H10-J10 -> 72009.772
B11: ='Expenditure Breakdown'!B18 -> 3 | D11: ='Expenditure Breakdown'!C18 -> Mounting Structures | F11: =+'Expenditure Breakdown'!J18 -> 180180 | H11: 86297.652 | J11: =+'Expenditure Breakdown'!X18 -> 86550.7 | L11: =F11-J11 -> 93629.3 | N11: =H11-J11 -> -253.048
B12: ='Expenditure Breakdown'!B23 -> 4 | D12: ='Expenditure Breakdown'!C23 -> DC Equipment | F12: =+'Expenditure Breakdown'!J23 -> 344364.8 | H12: 313434 | J12: =+'Expenditure Breakdown'!X23 -> 362150 | L12: =F12-J12 -> -17785.2 | N12: =H12-J12 -> -48716
B13: ='Expenditure Breakdown'!B35 -> 5 | D13: ='Expenditure Breakdown'!C35 -> Monitoring | F13: =+'Expenditure Breakdown'!J35 -> 174000 | H13: 50640.35 | J13: =+'Expenditure Breakdown'!X35 -> 68208.04 | L13: =F13-J13 -> 105791.96 | N13: =H13-J13 -> -17567.69
B14: ='Expenditure Breakdown'!B43 -> 6 | D14: ='Expenditure Breakdown'!C43 -> AC Equipment | F14: =+'Expenditure Breakdown'!J43 -> 381282.73 | H14: 1167527.7 | J14: =+'Expenditure Breakdown'!X43 -> 1167527.7 | L14: =F14-J14 -> -786244.93 | N14: =H14-J14 -> -0.0074999998
B15: ='Expenditure Breakdown'!B53 -> 7 | D15: ='Expenditure Breakdown'!C53 -> Battery Systems | F15: =+'Expenditure Breakdown'!J53 -> 7393827 | H15: 6474594 | J15: ='Expenditure Breakdown'!X53 -> 6386529 | L15: =F15-J15 -> 1007298 | N15: =H15-J15 -> 88065
B16: ='Expenditure Breakdown'!B66 -> 8 | D16: ='Expenditure Breakdown'!C66 -> Product Add On | F16: ='Expenditure Breakdown'!J66 -> 0 | H16: 135656 | J16: ='Expenditure Breakdown'!X66 -> 313051.32 | L16: =F16-J16 -> -313051.32 | N16: =H16-J16 -> -177395.32
B17: ='Expenditure Breakdown'!M78 -> 9 | D17: ='Expenditure Breakdown'!C78 -> AC & DC Installation | F17: =+'Expenditure Breakdown'!J78 -> 342160 | H17: 676952 | J17: =+'Expenditure Breakdown'!X78 -> 676952 | L17: =F17-J17 -> -334792 | N17: =H17-J17 -> 0
B18: ='Expenditure Breakdown'!B87 -> 10 | D18: ='Expenditure Breakdown'!C87 -> Site Logistics | F18: =+'Expenditure Breakdown'!J87 -> 54108.833 | H18: 314687 | J18: =+'Expenditure Breakdown'!X87 -> 114637 | L18: =F18-J18 -> -60528.167 | N18: =H18-J18 -> 200050
B19: ='Expenditure Breakdown'!B100 -> 11 | D19: ='Expenditure Breakdown'!C100 -> Due Dilligence | F19: ='Expenditure Breakdown'!J100 -> 111020 | H19: 82026.4 | J19: ='Expenditure Breakdown'!X100 -> 38759.07 | L19: =F19-J19 -> 72260.93 | N19: =H19-J19 -> 43267.33
B20: ='Expenditure Breakdown'!B108 -> 12 | D20: ='Expenditure Breakdown'!C108 -> BDP Commission | F20: ='Expenditure Breakdown'!G107 -> 0 | H20: 0 | J20: ='Expenditure Breakdown'!X107 -> 0 | L20: =F20-J20 -> 0 | N20: =H20-J20 -> 0
B21: ='Expenditure Breakdown'!B110 -> 13 | D21: ='Expenditure Breakdown'!C110 -> Engineering | F21: =+'Expenditure Breakdown'!J110 -> 239970.35 | H21: 255808.09 | J21: =+'Expenditure Breakdown'!X110 -> 447579.71 | L21: =F21-J21 -> -207609.36 | N21: =H21-J21 -> -191771.62 | P21: RV: Matriarch defects percentage 1.25%
B22: ='Expenditure Breakdown'!B118 -> 14 | D22: ='Expenditure Breakdown'!C118 -> General Expenses | F22: =+'Expenditure Breakdown'!J118 -> 47600 | H22: 46042.527 | J22: =+'Expenditure Breakdown'!X118 -> 67232.7 | L22: =F22-J22 -> -19632.7 | N22: =H22-J22 -> -21190.173
B23: ='Expenditure Breakdown'!B129 -> 15 | D23: ='Expenditure Breakdown'!C129 -> Service Add On | F23: =+'Expenditure Breakdown'!J129 -> 0 | H23: 0 | J23: =+'Expenditure Breakdown'!X129 -> 1171415.7 | L23: =F23-J23 -> -1171415.7 | N23: =H23-J23 -> -1171415.7
D25: check: | F25: ='Expenditure Breakdown'!J2-'Expenditure Tracking'!F5 -> 0 | G25: ='Expenditure Breakdown'!#REF!-G5 -> #REF! | H25: ='Expenditure Breakdown'!X2-J5 -> 0 | I25: ='Expenditure Breakdown'!#REF!-I5 -> #REF! | J25: ='Expenditure Breakdown'!X2-J5 -> 0
A27: Copy amounts in column H and paste as values at Project review.

Sheet Data
C2: Public holidays | F2: Drop down list
C3: 45292 | D3: New Years Day | F3: Approved
C4: 45372 | D4: Human Rights day | F4: Pending
C5: 45380 | D5: Good Friday | F5: Declined
C6: 45383 | D6: Family Day | F6: Abanded
C7: 45413 | D7: Workers day
C8: 45460 | D8: Youth Day Holiday
C9: 45513 | D9: Womens Day
C10: 45559 | D10: Heritage Day
C11: 45642 | D11: Day of Reconciliation
C12: 45651 | D12: Christmas Day
C13: 45652 | D13: Day of Goodwill | H13: Manual dates
C14: 45658 | D14: New Years Day
C15: 45737 | D15: Human Rights day
C16: 45765 | D16: Good Friday
C17: 45768 | D17: Family Day
C18: 45774 | D18: Freedom Day
C19: 45775 | D19: Freedom DayObserved
C20: 45778 | D20: Workers day
C21: 45824 | D21: Youth Day Holiday
C22: 45878 | D22: Womens Day
C23: 45924 | D23: Heritage Day
C24: 46007 | D24: Day of Reconciliation
C25: 46016 | D25: Christmas Day
C26: 46017 | D26: Day of Goodwill

Sheet Cashflow
D1: [RT: Double Check the first date is always a MONDAY] | F1: 45600 | G1: =F1+7 -> 45607 | H1: =G1+7 -> 45614 | I1: =H1+7 -> 45621 | J1: =I1+7 -> 45628 | K1: =J1+7 -> 45635 | L1: =K1+7 -> 45642 | M1: =L1+7 -> 45649 | N1: =M1+7 -> 45656 | ... CP1: =CO1+7 -> 46216
A2: PLANNED | C2: CHECK | D2: CHECK
B3: Planned Revenue | C3: ='Revenue Tracking'!D4 -> 11535559 | D3: =SUM(F3:CP3) -> 11729548 | F3: =SUMIFS('Revenue Tracking'!$F$13:$F$20, 'Revenue Tracking'!$H$13:$H$20, ">="&F1,'Revenue Tracking'!$H$13:$H$20, "<"&G1) -> 0 | G3: =SUMIFS('Revenue Tracking'!$F$13:$F$20, 'Revenue Tracking'!$H$13:$H$20, ">="&G1,'Revenue Tracking'!$H$13:$H$20, "<"&H1) -> 0 | H3: =SUMIFS('Revenue Tracking'!$F$13:$F$20, 'Revenue Tracking'!$H$13:$H$20, ">="&H1,'Revenue Tracking'!$H$13:$H$20, "<"&I1) -> 0 | I3: =SUMIFS('Revenue Tracking'!$F$13:$F$20, 'Revenue Tracking'!$H$13:$H$20, ">="&I1,'Revenue Tracking'!$H$13:$H$20, "<"&J1) -> 0 | J3: =SUMIFS('Revenue Tracking'!$F$13:$F$20, 'Revenue Tracking'!$H$13:$H$20, ">="&J1,'Revenue Tracking'!$H$13:$H$20, "<"&K1) -> 0 | K3: =SUMIFS('Revenue Tracking'!$F$13:$F$20, 'Revenue Tracking'!$H$13:$H$20, ">="&K1,'Revenue Tracking'!$H$13:$H$20, "<"&L1) -> 4037445.8 | L3: =SUMIFS('Revenue Tracking'!$F$13:$F$20, 'Revenue Tracking'!$H$13:$H$20, ">="&L1,'Revenue Tracking'!$H$13:$H$20, "<"&M1) -> 0 | M3: =SUMIFS('Revenue Tracking'!$F$13:$F$20, 'Revenue Tracking'!$H$13:$H$20, ">="&M1,'Revenue Tracking'!$H$13:$H$20, "<"&N1) -> 0 | ... CP3: =SUMIFS('Revenue Tracking'!$F$13:$F$20, 'Revenue Tracking'!$H$13:$H$20, ">="&CP1,'Revenue Tracking'!$H$13:$H$20, "<"&CQ1) -> 0
B4: Planned Revenue - Cumulative | F4: =F3 -> 0 | G4: =F4+G3 -> 0 | H4: =G4+H3 -> 0 | I4: =H4+I3 -> 0 | J4: =I4+J3 -> 0 | K4: =J4+K3 -> 4037445.8 | L4: =K4+L3 -> 4037445.8 | M4: =L4+M3 -> 4037445.8 | N4: =M4+N3 -> 4037445.8 | ... CP4: =CO4+CP3 -> 11729548
B5: Planned Expenditure | C5: ='Revenue Tracking'!D5 -> 10556110 | D5: =SUM(F5:CP5) -> 10556110 | F5: =SUMIFS('Expenditure Breakdown'!$G$6:$G$150, 'Expenditure Breakdown'!$H$6:$H$150, ">="&F1,'Expenditure Breakdown'!$H$6:$H$150, "<"&G1) -> 0 | G5: =SUMIFS('Expenditure Breakdown'!$G$6:$G$150, 'Expenditure Breakdown'!$H$6:$H$150, ">="&G1,'Expenditure Breakdown'!$H$6:$H$150, "<"&H1) -> 0 | H5: =SUMIFS('Expenditure Breakdown'!$G$6:$G$150, 'Expenditure Breakdown'!$H$6:$H$150, ">="&H1,'Expenditure Breakdown'!$H$6:$H$150, "<"&I1) -> 0 | I5: =SUMIFS('Expenditure Breakdown'!$G$6:$G$150, 'Expenditure Breakdown'!$H$6:$H$150, ">="&I1,'Expenditure Breakdown'!$H$6:$H$150, "<"&J1) -> 0 | J5: =SUMIFS('Expenditure Breakdown'!$G$6:$G$150, 'Expenditure Breakdown'!$H$6:$H$150, ">="&J1,'Expenditure Breakdown'!$H$6:$H$150, "<"&K1) -> 0 | K5: =SUMIFS('Expenditure Breakdown'!$G$6:$G$150, 'Expenditure Breakdown'!$H$6:$H$150, ">="&K1,'Expenditure Breakdown'!$H$6:$H$150, "<"&L1) -> 0 | L5: =SUMIFS('Expenditure Breakdown'!$G$6:$G$150, 'Expenditure Breakdown'!$H$6:$H$150, ">="&L1,'Expenditure Breakdown'!$H$6:$H$150, "<"&M1) -> 0 | M5: =SUMIFS('Expenditure Breakdown'!$G$6:$G$150, 'Expenditure Breakdown'!$H$6:$H$150, ">="&M1,'Expenditure Breakdown'!$H$6:$H$150, "<"&N1) -> 0 | ... CP5: =SUMIFS('Expenditure Breakdown'!$G$6:$G$150, 'Expenditure Breakdown'!$H$6:$H$150, ">="&CP1,'Expenditure Breakdown'!$H$6:$H$150, "<"&CQ1) -> 0
B6: Planned Expenditure - Cumulative | F6: =F5 -> 0 | G6: =F6+G5 -> 0 | H6: =G6+H5 -> 0 | I6: =H6+I5 -> 0 | J6: =I6+J5 -> 0 | K6: =J6+K5 -> 0 | L6: =K6+L5 -> 0 | M6: =L6+M5 -> 0 | N6: =M6+N5 -> 0 | ... CP6: =CO6+CP5 -> 10556110
B7: PLANNED CashFlow | F7: =F4-F6 -> 0 | G7: =G4-G6 -> 0 | H7: =H4-H6 -> 0 | I7: =I4-I6 -> 0 | J7: =J4-J6 -> 0 | K7: =K4-K6 -> 4037445.8 | L7: =L4-L6 -> 4037445.8 | M7: =M4-M6 -> 4037445.8 | ... CP7: =CP4-CP6 -> 1173437.3
A8: ACTUAL | C8: CHECK | D8: CHECK
B9: Actual + Planned Revenue | C9: ='Revenue Tracking'!F4 -> 11729548 | D9: =SUM(F9:CP9) -> 11729548 | F9: =SUMIFS('Revenue Tracking'!$F$13:$F$20, 'Revenue Tracking'!$P$13:$P$20, ">="&F1,'Revenue Tracking'!$P$13:$P$20, "<"&G1) -> 0 | G9: =SUMIFS('Revenue Tracking'!$F$13:$F$20, 'Revenue Tracking'!$P$13:$P$20, ">="&G1,'Revenue Tracking'!$P$13:$P$20, "<"&H1) -> 0 | H9: =SUMIFS('Revenue Tracking'!$F$13:$F$20, 'Revenue Tracking'!$P$13:$P$20, ">="&H1,'Revenue Tracking'!$P$13:$P$20, "<"&I1) -> 0 | I9: =SUMIFS('Revenue Tracking'!$F$13:$F$20, 'Revenue Tracking'!$P$13:$P$20, ">="&I1,'Revenue Tracking'!$P$13:$P$20, "<"&J1) -> 0 | J9: =SUMIFS('Revenue Tracking'!$F$13:$F$20, 'Revenue Tracking'!$P$13:$P$20, ">="&J1,'Revenue Tracking'!$P$13:$P$20, "<"&K1) -> 0 | K9: =SUMIFS('Revenue Tracking'!$F$13:$F$20, 'Revenue Tracking'!$P$13:$P$20, ">="&K1,'Revenue Tracking'!$P$13:$P$20, "<"&L1) -> 73118.58 | L9: =SUMIFS('Revenue Tracking'!$F$13:$F$20, 'Revenue Tracking'!$P$13:$P$20, ">="&L1,'Revenue Tracking'!$P$13:$P$20, "<"&M1) -> 0 | M9: =SUMIFS('Revenue Tracking'!$F$13:$F$20, 'Revenue Tracking'!$P$13:$P$20, ">="&M1,'Revenue Tracking'!$P$13:$P$20, "<"&N1) -> 0 | ... CP9: =SUMIFS('Revenue Tracking'!$F$13:$F$20, 'Revenue Tracking'!$P$13:$P$20, ">="&CP1,'Revenue Tracking'!$P$13:$P$20, "<"&CQ1) -> 0
B10: Actual + Planned Revenue - Cumulative | F10: =F9 -> 0 | G10: =F10+G9 -> 0 | H10: =G10+H9 -> 0 | I10: =H10+I9 -> 0 | J10: =I10+J9 -> 0 | K10: =J10+K9 -> 73118.58 | L10: =K10+L9 -> 73118.58 | M10: =L10+M9 -> 73118.58 | N10: =M10+N9 -> 73118.58 | ... CP10: =CO10+CP9 -> 11729548
B11: Actual + Planned Expenditure | C11: ='Revenue Tracking'!F5 -> 11989843 | D11: =SUM(F11:CP11) -> 11989843 | F11: =SUMIFS('Expenditure Breakdown'!$R$6:$R$150, 'Expenditure Breakdown'!$W$6:$W$150, ">="&F1,'Expenditure Breakdown'!$W$6:$W$150, "<"&G1) -> 0 | G11: =SUMIFS('Expenditure Breakdown'!$R$6:$R$150, 'Expenditure Breakdown'!$W$6:$W$150, ">="&G1,'Expenditure Breakdown'!$W$6:$W$150, "<"&H1) -> 0 | H11: =SUMIFS('Expenditure Breakdown'!$R$6:$R$150, 'Expenditure Breakdown'!$W$6:$W$150, ">="&H1,'Expenditure Breakdown'!$W$6:$W$150, "<"&I1) -> 0 | I11: =SUMIFS('Expenditure Breakdown'!$R$6:$R$150, 'Expenditure Breakdown'!$W$6:$W$150, ">="&I1,'Expenditure Breakdown'!$W$6:$W$150, "<"&J1) -> 11026.4 | J11: =SUMIFS('Expenditure Breakdown'!$R$6:$R$150, 'Expenditure Breakdown'!$W$6:$W$150, ">="&J1,'Expenditure Breakdown'!$W$6:$W$150, "<"&K1) -> 0 | K11: =SUMIFS('Expenditure Breakdown'!$R$6:$R$150, 'Expenditure Breakdown'!$W$6:$W$150, ">="&K1,'Expenditure Breakdown'!$W$6:$W$150, "<"&L1) -> 94959.2 | L11: =SUMIFS('Expenditure Breakdown'!$R$6:$R$150, 'Expenditure Breakdown'!$W$6:$W$150, ">="&L1,'Expenditure Breakdown'!$W$6:$W$150, "<"&M1) -> 0 | M11: =SUMIFS('Expenditure Breakdown'!$R$6:$R$150, 'Expenditure Breakdown'!$W$6:$W$150, ">="&M1,'Expenditure Breakdown'!$W$6:$W$150, "<"&N1) -> 0 | ... CP11: =SUMIFS('Expenditure Breakdown'!$R$6:$R$150, 'Expenditure Breakdown'!$W$6:$W$150, ">="&CP1,'Expenditure Breakdown'!$W$6:$W$150, "<"&CQ1) -> 0
B12: Actual + Planned Expenditure - Cumulative | F12: =F11 -> 0 | G12: =F12+G11 -> 0 | H12: =G12+H11 -> 0 | I12: =H12+I11 -> 11026.4 | J12: =I12+J11 -> 11026.4 | K12: =J12+K11 -> 105985.6 | L12: =K12+L11 -> 105985.6 | M12: =L12+M11 -> 105985.6 | N12: =M12+N11 -> 105985.6 | ... CP12: =CO12+CP11 -> 11989843
B14: ACTUAL CashFlow | F14: =F10-F12 -> 0 | G14: =G10-G12 -> 0 | H14: =H10-H12 -> 0 | I14: =I10-I12 -> -11026.4 | J14: =J10-J12 -> -11026.4 | K14: =K10-K12 -> -32867.02 | L14: =L10-L12 -> -32867.02 | M14: =M10-M12 -> -32867.02 | ... CP14: =CP10-CP12 -> -260295
C16: CHECK | D16: CHECK
B17: Revenue Recognition | C17: =C3-D17 -> -215227.08 | D17: =SUM(F17:CP17) -> 11750787 | F17: =SUMIFS('Expenditure Breakdown'!$U$6:$U$150, 'Expenditure Breakdown'!$T$6:$T$150, ">="&F1,'Expenditure Breakdown'!$T$6:$T$150, "<"&G1) -> 0 | G17: =SUMIFS('Expenditure Breakdown'!$U$6:$U$150, 'Expenditure Breakdown'!$T$6:$T$150, ">="&G1,'Expenditure Breakdown'!$T$6:$T$150, "<"&H1) -> 0 | H17: =SUMIFS('Expenditure Breakdown'!$U$6:$U$150, 'Expenditure Breakdown'!$T$6:$T$150, ">="&H1,'Expenditure Breakdown'!$T$6:$T$150, "<"&I1) -> 0 | I17: =SUMIFS('Expenditure Breakdown'!$U$6:$U$150, 'Expenditure Breakdown'!$T$6:$T$150, ">="&I1,'Expenditure Breakdown'!$T$6:$T$150, "<"&J1) -> 14115.734 | J17: =SUMIFS('Expenditure Breakdown'!$U$6:$U$150, 'Expenditure Breakdown'!$T$6:$T$150, ">="&J1,'Expenditure Breakdown'!$T$6:$T$150, "<"&K1) -> 0 | K17: =SUMIFS('Expenditure Breakdown'!$U$6:$U$150, 'Expenditure Breakdown'!$T$6:$T$150, ">="&K1,'Expenditure Breakdown'!$T$6:$T$150, "<"&L1) -> 0 | L17: =SUMIFS('Expenditure Breakdown'!$U$6:$U$150, 'Expenditure Breakdown'!$T$6:$T$150, ">="&L1,'Expenditure Breakdown'!$T$6:$T$150, "<"&M1) -> 0 | M17: =SUMIFS('Expenditure Breakdown'!$U$6:$U$150, 'Expenditure Breakdown'!$T$6:$T$150, ">="&M1,'Expenditure Breakdown'!$T$6:$T$150, "<"&N1) -> 0 | ... CP17: =SUMIFS('Expenditure Breakdown'!$U$6:$U$150, 'Expenditure Breakdown'!$T$6:$T$150, ">="&CP1,'Expenditure Breakdown'!$T$6:$T$150, "<"&CQ1) -> 0
B18: Revenue Recognition Cumulative | C18: =D17-D18 -> 0 | D18: =MAX(F18:CP18) -> 11750787 | F18: =F17 -> 0 | G18: =F18+G17 -> 0 | H18: =G18+H17 -> 0 | I18: =H18+I17 -> 14115.734 | J18: =I18+J17 -> 14115.734 | K18: =J18+K17 -> 14115.734 | L18: =K18+L17 -> 14115.734 | M18: =L18+M17 -> 14115.734 | N18: =M18+N17 -> 1618995.2 | ... CP18: =CO18+CP17 -> 11750787
B20: Installer Expenditure | D20: =SUM(F20:CP20) -> 1938729.7 | F20: =SUMIFS('Expenditure Breakdown'!$R$26:$R$33, 'Expenditure Breakdown'!$W$26:$W$33, ">="&F1,'Expenditure Breakdown'!$W$26:$W$33, "<"&G1)+SUMIFS('Expenditure Breakdown'!$R$44:$R$51, 'Expenditure Breakdown'!$W$44:$W$51, ">="&F1,'Expenditure Breakdown'!$W$44:$W$51, "<"&G1)+SUMIFS('Expenditure Breakdown'!$R$78:$R$85, 'Expenditure Breakdown'!$W$78:$W$85, ">="&F1,'Expenditure Breakdown'!$W$78:$W$85, "<"&G1) -> 0 | G20: =SUMIFS('Expenditure Breakdown'!$R$26:$R$33, 'Expenditure Breakdown'!$W$26:$W$33, ">="&G1,'Expenditure Breakdown'!$W$26:$W$33, "<"&H1)+SUMIFS('Expenditure Breakdown'!$R$44:$R$51, 'Expenditure Breakdown'!$W$44:$W$51, ">="&G1,'Expenditure Breakdown'!$W$44:$W$51, "<"&H1)+SUMIFS('Expenditure Breakdown'!$R$78:$R$85, 'Expenditure Breakdown'!$W$78:$W$85, ">="&G1,'Expenditure Breakdown'!$W$78:$W$85, "<"&H1) -> 0 | H20: =SUMIFS('Expenditure Breakdown'!$R$26:$R$33, 'Expenditure Breakdown'!$W$26:$W$33, ">="&H1,'Expenditure Breakdown'!$W$26:$W$33, "<"&I1)+SUMIFS('Expenditure Breakdown'!$R$44:$R$51, 'Expenditure Breakdown'!$W$44:$W$51, ">="&H1,'Expenditure Breakdown'!$W$44:$W$51, "<"&I1)+SUMIFS('Expenditure Breakdown'!$R$78:$R$85, 'Expenditure Breakdown'!$W$78:$W$85, ">="&H1,'Expenditure Breakdown'!$W$78:$W$85, "<"&I1) -> 0 | I20: =SUMIFS('Expenditure Breakdown'!$R$26:$R$33, 'Expenditure Breakdown'!$W$26:$W$33, ">="&I1,'Expenditure Breakdown'!$W$26:$W$33, "<"&J1)+SUMIFS('Expenditure Breakdown'!$R$44:$R$51, 'Expenditure Breakdown'!$W$44:$W$51, ">="&I1,'Expenditure Breakdown'!$W$44:$W$51, "<"&J1)+SUMIFS('Expenditure Breakdown'!$R$78:$R$85, 'Expenditure Breakdown'!$W$78:$W$85, ">="&I1,'Expenditure Breakdown'!$W$78:$W$85, "<"&J1) -> 0 | J20: =SUMIFS('Expenditure Breakdown'!$R$26:$R$33, 'Expenditure Breakdown'!$W$26:$W$33, ">="&J1,'Expenditure Breakdown'!$W$26:$W$33, "<"&K1)+SUMIFS('Expenditure Breakdown'!$R$44:$R$51, 'Expenditure Breakdown'!$W$44:$W$51, ">="&J1,'Expenditure Breakdown'!$W$44:$W$51, "<"&K1)+SUMIFS('Expenditure Breakdown'!$R$78:$R$85, 'Expenditure Breakdown'!$W$78:$W$85, ">="&J1,'Expenditure Breakdown'!$W$78:$W$85, "<"&K1) -> 0 | K20: =SUMIFS('Expenditure Breakdown'!$R$26:$R$33, 'Expenditure Breakdown'!$W$26:$W$33, ">="&K1,'Expenditure Breakdown'!$W$26:$W$33, "<"&L1)+SUMIFS('Expenditure Breakdown'!$R$44:$R$51, 'Expenditure Breakdown'!$W$44:$W$51, ">="&K1,'Expenditure Breakdown'!$W$44:$W$51, "<"&L1)+SUMIFS('Expenditure Breakdown'!$R$78:$R$85, 'Expenditure Breakdown'!$W$78:$W$85, ">="&K1,'Expenditure Breakdown'!$W$78:$W$85, "<"&L1) -> 0 | L20: =SUMIFS('Expenditure Breakdown'!$R$26:$R$33, 'Expenditure Breakdown'!$W$26:$W$33, ">="&L1,'Expenditure Breakdown'!$W$26:$W$33, "<"&M1)+SUMIFS('Expenditure Breakdown'!$R$44:$R$51, 'Expenditure Breakdown'!$W$44:$W$51, ">="&L1,'Expenditure Breakdown'!$W$44:$W$51, "<"&M1)+SUMIFS('Expenditure Breakdown'!$R$78:$R$85, 'Expenditure Breakdown'!$W$78:$W$85, ">="&L1,'Expenditure Breakdown'!$W$78:$W$85, "<"&M1) -> 0 | M20: =SUMIFS('Expenditure Breakdown'!$R$26:$R$33, 'Expenditure Breakdown'!$W$26:$W$33, ">="&M1,'Expenditure Breakdown'!$W$26:$W$33, "<"&N1)+SUMIFS('Expenditure Breakdown'!$R$44:$R$51, 'Expenditure Breakdown'!$W$44:$W$51, ">="&M1,'Expenditure Breakdown'!$W$44:$W$51, "<"&N1)+SUMIFS('Expenditure Breakdown'!$R$78:$R$85, 'Expenditure Breakdown'!$W$78:$W$85, ">="&M1,'Expenditure Breakdown'!$W$78:$W$85, "<"&N1) -> 0 | ... CP20: =SUMIFS('Expenditure Breakdown'!$R$26:$R$33, 'Expenditure Breakdown'!$W$26:$W$33, ">="&CP1,'Expenditure Breakdown'!$W$26:$W$33, "<"&CQ1)+SUMIFS('Expenditure Breakdown'!$R$44:$R$51, 'Expenditure Breakdown'!$W$44:$W$51, ">="&CP1,'Expenditure Breakdown'!$W$44:$W$51, "<"&CQ1)+SUMIFS('Expenditure Breakdown'!$R$78:$R$85, 'Expenditure Breakdown'!$W$78:$W$85, ">="&CP1,'Expenditure Breakdown'!$W$78:$W$85, "<"&CQ1) -> 0
B21: Installer Expenditure - Cumulative | F21: =F20 -> 0 | G21: =G20+F21 -> 0 | H21: =H20+G21 -> 0 | I21: =I20+H21 -> 0 | J21: =J20+I21 -> 0 | K21: =K20+J21 -> 0 | L21: =L20+K21 -> 0 | M21: =M20+L21 -> 0 | N21: =N20+M21 -> 0 | ... CP21: =CP20+CO21 -> 1938729.7

Sheet Expenditure Breakdown
B2: COSTED EXPENDITURE BREAKDOWN | J2: =SUM(J6:J151) -> 10556110 | K2: =SUM(K6:K151) -> 11729548 | M2: ACTUAL EXPENDITURE BREAKDOWN | S2: FINANCE ONLY | X2: =SUM(X6:X151) -> 11989843
B4: No. | C4: Product / Service | D4: Description of Work | E4: QTY | F4: Rate / Unit | G4: Budget Total | H4: Project Related date | J4: Total COS | K4: =IF(K2-'Revenue Tracking'!D4>=0, "Total Revenue", "ERROR on REV" ) -> Total Revenue | M4: No. | N4: Product/ Service | O4: Description of Work | P4: QTY | Q4: Rate / Unit | R4: Actual Total | S4: INVOICE NUMBER | T4: INVOICE RAISED DATE | U4: REVENUE RECOGNITION AMOUNT | V4: CHECK | W4: FINANCE PAYMENT DATE | X4: Total COS | Y4: PO NUMBER | Z4: COMMENTS
B6: 1 | C6: Panels | D6: Jinko 580W | E6: 728 | F6: 1425.27 | G6: =E6*F6 -> 1037596.6 | H6: ='Project Plan'!I40+60 -> 45768 | J6: =SUM(G6:G11) -> 1077596.6 | K6: 1171300.6 | M6: 1 | N6: 1. Panels | O6: Jinko 585W | P6: =400000/585 -> 683.76068 | Q6: 1327.95 | R6: 908317.8 | S6: Menlo Inv0002362 | T6: 45657 | U6: 1146065.7 | V6: =K6-SUM(U6:U11) -> -0.0042663028 | W6: 45708 | X6: =SUM(R6:R11) -> 908317.8 | AA6: 19
B7: 1 | M7: 1 | N7: 1. Panels | T7: 45688 | U7: 25234.91 | AA7: BUDGET - Solar | AB7: Installer Allocation
B8: 1 | D8: Module delivery to site | G8: 40000 | H8: =H6 -> 45768 | M8: 1 | N8: 1. Panels | O8: Module delivery to site | U8: =(R8/$X$6*$K$6) -> 0 | AA8: AC Equipment | AB8: =C45+G60+G61 -> 1142809.7
B9: 1 | M9: 1 | N9: 1. Panels | T9: =IF(W9>1,EOMONTH(W9,0),"") | U9: =(R9/$X$6*$K$6) -> 0 | AA9: DC Equipment | AB9: =SUM(G24:G33) -> 202684.8
B10: 1 | M10: 1 | N10: 1. Panels | T10: =IF(W10>1,EOMONTH(W10,0),"") | U10: =(R10/$X$6*$K$6) -> 0 | AA10: AC Labour | AB10: =C79+G59 -> 446100 | AD10: =AB10/140000 -> 3.1864286
B11: 1 | M11: 1 | N11: 1. Panels | T11: =IF(W11>1,EOMONTH(W11,0),"") | U11: =(R11/$X$6*$K$6) -> 0 | AA11: DC Labour | AB11: =C80 -> 242060 | AD11: =AB11/140000 -> 1.729
T12: =IF(W12>1,EOMONTH(W12,0),"") | AA12: Offloading | AB12: =G88 -> 8500
B13: 2 | C13: Inverters | D13: Huawei 100KTL | E13: 3 | F13: 70000 | G13: =E13*F13 -> 210000 | H13: ='Project Plan'!E25+30 -> 45742 | J13: =SUM(G13:G16) -> 210000 | K13: 228260.87 | M13: 2 | N13: 2. Inverters | O13: Huawei 100KTL | P13: 3 | Q13: 68870 | R13: 206611.05 | S13: Menlo Inv0002362 | T13: 45657 | U13: 179134.85 | V13: =K13-SUM(U13:U16) -> -0.0043873753 | W13: =W23 -> 45708 | X13: =SUM(R13:R16) -> 180931.83 | AA13: Roof Access/Scaffolding | AB13: =G90 -> 40675.5
B14: 2 | M14: 2 | N14: 2. Inverters | O14: Huawei 50KTL | P14: 1 | Q14: 43190.78 | R14: =Q14*P14 -> 43190.78 | S14: Menlo INV0002702 | T14: 45747 | U14: 49126.024 | W14: 45785 | Y14: PO3735-MMS-20250311 - RV Approved | AA14: Storage | AB14: =G89 -> 4933.3333
B15: 2 | M15: 2 | N15: 2. Inverters | O15: Huawei 100KTL - Moved to stock (JHB) | P15: 1 | Q15: -68870 | R15: =P15*Q15 -> -68870 | S15: Allocated to Joburg Storeroom | T15: 46053 | U15: 0 | W15: 46053 | AA15: Telehandler | AB15: =G87 -> 0
B16: 2 | M16: 2 | N16: 2. Inverters | U16: =(R16/$X$13*$K$13) -> 0 | AA16: Other | AB16: 0
T17: =IF(W17>1,EOMONTH(W17,0),"") | AA17: Total | AB17: =SUM(AB8:AB16) -> 2087763.3
B18: 3 | C18: Mounting Structures | D18: IBR Roof | G18: 180180 | H18: ='Project Plan'!E21+30 -> 45721 | J18: =SUM(G18:G21) -> 180180 | K18: 195847.83 | M18: 3 | N18: 3. Mounting Structures | O18: IBR Roof - Schletter | R18: =80274.7 -> 80274.7 | S18: Schletter - INV1406 | T18: 45716 | U18: 186596.42 | V18: =K18-SUM(U18:U21) -> 0 | W18: 45744 | X18: =SUM(R18:R21) -> 86550.7 | Y18: PO3638-MMS-20250211 - RV Approved | AA18: Less 15% | AB18: =+AB17*0.85 -> 1774598.8 | AD18: [SM: Target Installation Price]
B19: 3 | M19: 3 | N19: 3. Mounting Structures | O19: Delivery | R19: 3980 | S19: Schletter - INV1406 | T19: =T18 -> 45716 | U19: 9251.4049 | W19: =W18 -> 45744 | Y19: PO3638-MMS-20250211 - RV Approved | AA19: R/Wp | AB19: =+AB18/'Project Plan'!$E$3/1000 -> 4.436497
B20: 3 | M20: 3 | N20: 3. Mounting Structures | O20: End Clamps Top Up - JHB Warehouse | P20: 100 | Q20: 11.48 | R20: =Q20*P20 -> 1148 | S20: Allocated from Stock | T20: 45747 | U20: 0 | W20: 45747
B21: 3 | M21: 3 | N21: 3. Mounting Structures | O21: End Clamps Top Up - Scheltter | P21: 100 | Q21: 11.48 | R21: =Q21*P21 -> 1148 | S21: Schletter - INV1611 | T21: 45747 | W21: =T21+30 -> 45777 | Y21: PO3756-MMS-20250319 - RV Approved | AA21: ACTUAL | AB21: Installer Price
T22: =IF(W22>1,EOMONTH(W22,0),"") | AA22: AC Equipment | AB22: 1142809.7
B23: 4 | C23: DC Equipment | D23: DC Cable | E23: 10120 | F23: 14 | G23: =E23*F23 -> 141680 | H23: ='Project Plan'!E36+30 -> 45721 | J23: =SUM(G23:G33) -> 344364.8 | K23: 374309.57 | M23: 4 | N23: 4. DC Equipment | O23: DC Cable | P23: 12000 | Q23: 13.3 | R23: =P23*Q23 -> 159600 | S23: Menlo Inv0002362 | T23: 45657 | U23: 187862.44 | V23: =K23-SUM(U23:U33) -> -0.0019967229 | W23: =W6 -> 45708 | X23: =SUM(R23:R33) -> 362150 | AA23: DC Equipment | AB23: 202684.8
B24: 4 | D24: Project Kick Off | F24: 0.1 | G24: =C26*F24 -> 20268.48 | H24: =H43 -> 45684 | M24: 4 | N24: 4. DC Equipment | O24: DC Cable | R24: 55100 | S24: Menlo INV0002767 | T24: 45747 | U24: 13110.75 | W24: 45799 | Y24: PO3765-MMS-20250325 - RV Approved | AA24: AC Labour | AB24: 100100 | AD24: =AB24/140000 -> 0.715
M25: 4 | N25: 4. DC Equipment | O25: DC Cable - Additional order due to inverter room placement - VO | P25: 4000 | Q25: 13.3 | R25: =P25*Q25 -> 53200 | S25: MENLO - INV0002594 | T25: 45716 | U25: 72136.626 | W25: 45771 | AA25: DC Labour | AB25: 242060
B26: 4 | C26: 202684.8 | D26: Site Establishment | F26: 0.15 | G26: =$C$26*F26 -> 30402.72 | H26: =H45 -> 45691 | M26: 4 | N26: 4. DC Equipment | O26: Project Kick Off | P26: =AF40 -> 94250 | Q26: =Q78 -> 0.1 | R26: =$P$26*Q26 -> 9425 | S26: =S78 -> Matthews Group INV 1423 | T26: =T78 -> 45688 | U26: 11255.536 | W26: =W78 -> 45695 | Y26: PO3567-MMS-20250127 - RV Approved | AA26: =AA12 -> Offloading | AB26: 8500 | AD26: =AB25/140000 -> 1.729
B27: 4 | D27: AC Installation Complete | F27: 0.2 | G27: =$C$26*F27 -> 40536.96 | H27: =H46 -> 45756 | M27: 4 | N27: 4. DC Equipment | O27: Site Establishment | Q27: =Q79 -> 0.15 | R27: =$P$26*Q27 -> 14137.5 | S27: Matthews Group INV-1424 | T27: =T79 -> 45688 | U27: 16883.304 | W27: =W79 -> 45701 | AA27: =AA13 -> Roof Access/Scaffolding | AB27: 40675.5
B28: 4 | D28: DC Installation Complete | F28: 0.25 | G28: =$C$26*F28 -> 50671.2 | H28: =H47 -> 45719 | M28: 4 | N28: 4. DC Equipment | O28: AC Installation Complete | Q28: =Q80 -> 0.2 | R28: =$P$26*Q28 -> 18850 | S28: Matthews Group INV-1451 | T28: =T80 -> 45777 | U28: 19482.908 | W28: =W80 -> 45771 | AA28: =AA14 -> Storage | AB28: 4933.3333
B29: 4 | D29: Commissioning Complete | F29: 0.1 | G29: =$C$26*F29 -> 20268.48 | H29: =H48 -> 45772 | M29: 4 | N29: 4. DC Equipment | O29: DC Installation Complete | Q29: =Q81 -> 0.25 | R29: =$P$26*Q29 -> 23562.5 | S29: Matthews Group INV 1445 | T29: =T81 -> 45777 | U29: 24353.636 | W29: =W81 -> 45771 | AA29: =AA15 -> Telehandler | AB29: =AB15*0.75 -> 0
B30: 4 | D30: Site De-establisment | F30: 0.1 | G30: =$C$26*F30 -> 20268.48 | H30: =H49 -> 45758 | M30: 4 | N30: 4. DC Equipment | O30: Commissioning Complete | Q30: =Q82 -> 0.1 | R30: =$P$26*Q30 -> 9425 | S30: Matthews Group INV 1452 | T30: =T82 -> 45777 | U30: 9741.4542 | W30: =W82 -> 45785 | AA30: =AA16 -> Other | AB30: =AB16*0.75 -> 0
B31: 4 | D31: Handover Document Complete | F31: 0.05 | G31: =$C$26*F31 -> 10134.24 | H31: =H50 -> 45786 | M31: 4 | N31: 4. DC Equipment | O31: Site De-establisment | Q31: =Q83 -> 0.1 | R31: =$P$26*Q31 -> 9425 | S31: Matthews Group INV-1461 | T31: =T83 -> 45808 | U31: 9741.4542 | W31: =W83 -> 45820 | AA31: Other | AB31: 0
B32: 4 | D32: End of Defects Period | F32: 0.05 | G32: =$C$26*F32 -> 10134.24 | H32: =H51 -> 45876 | M32: 4 | N32: 4. DC Equipment | O32: Handover Document Complete | Q32: =Q84 -> 0.05 | R32: =$P$26*Q32 -> 4712.5 | S32: Matthews Group INV-1462 | T32: 45838 | U32: 4870.7271 | W32: =W84 -> 45793 | AA32: Other | AB32: 0
B33: 4 | M33: 4 | N33: 4. DC Equipment | O33: End of Defects Period | Q33: =Q85 -> 0.05 | R33: =$P$26*Q33 -> 4712.5 | S33: Matthews Group INV-1463 | T33: 45838 | U33: 4870.7271 | W33: =W85 -> 45869 | AA33: Total | AB33: =SUM(AB22:AB31) -> 1741763.3
T34: =IF(W34>1,EOMONTH(W34,0),"") | AA34: R/Wp | AB34: =+AB33/'Project Plan'!$E$3/1000 -> 4.3544083
B35: 5 | C35: Monitoring | D35: Smartlogger 3000 | G35: 26000 | H35: =H13 -> 45742 | J35: =SUM(G35:G41) -> 174000 | K35: 189130.43 | M35: 5 | N35: 5. Monitoring | O35: Smartlogger 3000 | R35: 7639.54 | S35: MENLO - INV0002488 | T35: 45688 | U35: 31106.653 | V35: =K35-SUM(U35:U41) -> -0.0048587007 | W35: 45708 | X35: =SUM(R35:R41) -> 68208.04
B36: 5 | D36: Comms DB | G36: 8000 | H36: =H35 -> 45742 | M36: 5 | N36: 5. Monitoring | O36: CTs, Router - AccuEnergy | R36: 6486.5 | S36: Accuenergy - INV ASAI-004649 | T36: 45688 | U36: 26411.709 | W36: 45715 | Y36: PO3566-MMS-20250127 - RV Approved
M37: 5 | N37: 5. Monitoring
B38: 5 | M38: 5 | N38: 5. Monitoring | O38: Data Guru - Herholdts | R38: 27100 | S38: Herholdts' - INV1005888 | T38: 45716 | U38: 86134.18 | W38: 45744 | Y38: PO3663-MMS-20250217 - RV Approved | AA38: ACTUAL - GreenWay Solar | AB38: Installer Price | AE38: ACTUAL - Matthews Group | AF38: Installer Price
B39: 5 | D39: Apex Controller | G39: 125000 | H39: =H35+30 -> 45772 | M39: 5 | N39: 5. Monitoring | O39: Revenue Grade Meter | R39: 11169 | S39: Matriach INV-3710 | T39: 45688 | U39: 45477.897 | W39: 45688 | AA39: AC Equipment | AB39: 2107709.6 | AE39: AC Equipment | AF39: =448746+718781.65 -> 1167527.6 | AI39: =AB39-AF39 -> 940182
B40: 5 | D40: Revenue Grade Meter | G40: 15000 | H40: =H36 -> 45742 | M40: 5 | N40: 5. Monitoring | O40: Meter + Fibre Optic Port + rogowski Coil | R40: 15813 | S40: Accuenergy Inv: ASAI-007060 | T40: 46022 | U40: 0 | W40: 46029 | AA40: DC Equipment | AB40: 90086.98 | AE40: DC Equipment | AF40: 94250 | AI40: =AB40-AF40 -> -4163.02
B41: 5 | M41: 5 | N41: 5. Monitoring | T41: =IF(W41>1,EOMONTH(W41,0),"") | U41: =(R41/$X$35*$K$35) -> 0 | AA41: AC Labour | AB41: 707500 | AD41: =AB41/400/1000 -> 1.76875 | AE41: AC Labour | AF41: 328952 | AG41: =AF41/400/1000 -> 0.82238 | AI41: =AB41-AF41 -> 378548
T42: =IF(W42>1,EOMONTH(W42,0),"") | AA42: DC Labour | AB42: 487883 | AD42: =AB42/400/1000 -> 1.2197075 | AE42: DC Labour | AF42: 348000 | AG42: =AF42/400/1000 -> 0.87 | AI42: =AB42-AF42 -> 139883
B43: 6 | C43: AC Equipment | D43: Project Kick Off | F43: 0.1 | G43: =$C$45*F43 -> 38128.273 | H43: =H78 -> 45684 | J43: =SUM(G43:G51) -> 381282.73 | K43: 414437.75 | M43: 6 | N43: 6. AC Equipment | T43: =IF(W43>1,EOMONTH(W43,0),"") | U43: =(R43/$X$43*$K$43) -> 0 | V43: =K43-SUM(U43:U51) -> 0 | X43: =SUM(R43:R51) -> 1167527.7 | AA43: Roof Access | AB43: 45135.2 | AE43: Equipment Hire - Offloading & Rigging | AF43: 76862 | AI43: =AB43-AF43 -> -31726.8
B44: 6 | M44: 6 | N44: 6. AC Equipment | O44: Project Kick Off | P44: =AF39 -> 1167527.6 | Q44: =Q78 -> 0.1 | R44: 116752.77 | S44: =S78 -> Matthews Group INV 1423 | T44: =T78 -> 45688 | U44: 41443.776 | W44: =W78 -> 45695 | Y44: PO3567-MMS-20250127 - RV Approved | AA44: Offloading & Rigging | AB44: 46000 | AE44: Accommodation 6 Weeks | AI44: =AB44-AF44 -> 46000
B45: 6 | C45: 381282.73 | D45: Site Establishment | F45: 0.15 | G45: =$C$45*F45 -> 57192.409 | H45: =H79 -> 45691 | M45: 6 | N45: 6. AC Equipment | O45: Site Establishment | Q45: =Q79 -> 0.15 | R45: 175129.15 | S45: Matthews Group INV-1424 | T45: =T79 -> 45688 | U45: 62165.662 | W45: =W79 -> 45701 | AA45: Site Costs and General | AB45: =87630-42000 -> 45630 | AE45: HSE | AF45: 14375 | AI45: =AB45-AF45 -> 31255
B46: 6 | D46: AC Installation Complete | F46: 0.2 | G46: =$C$45*F46 -> 76256.545 | H46: =H80 -> 45756 | M46: 6 | N46: 6. AC Equipment | O46: AC Installation Complete | Q46: =Q80 -> 0.2 | R46: =$P$44*Q46 -> 233505.53 | S46: Matthews Group INV-1451 | T46: =T80 -> 45777 | U46: 82887.549 | W46: =W80 -> 45771 | AA46: HSE | AB46: 15525 | AE46: Other | AF46: 0 | AI46: =AB46-AF46 -> 15525
B47: 6 | D47: DC Installation Complete | F47: 0.25 | G47: =$C$45*F47 -> 95320.682 | H47: =H81 -> 45719 | M47: 6 | N47: 6. AC Equipment | O47: DC Installation Complete | Q47: =Q81 -> 0.25 | R47: =$P$44*Q47 -> 291881.91 | S47: Matthews Group INV 1445 | T47: =T81 -> 45777 | U47: 103609.44 | W47: =W81 -> 45771 | AA47: =AA32 -> Other | AB47: =AB32*0.75 -> 0 | AE47: Other | AF47: =AF32*0.75 -> 0 | AI47: =AB47-AF47 -> 0
B48: 6 | D48: Commissioning Complete | F48: 0.1 | G48: =$C$45*F48 -> 38128.273 | H48: =H82 -> 45772 | M48: 6 | N48: 6. AC Equipment | O48: Commissioning Complete | Q48: =Q82 -> 0.1 | R48: =$P$44*Q48 -> 116752.76 | S48: Matthews Group INV 1452 | T48: =T82 -> 45777 | U48: 41443.774 | W48: =W82 -> 45785 | AA48: Other | AB48: 0 | AE48: VO | AF48: 190762.14 | AI48: =AB48-AF48 -> -190762.14
B49: 6 | D49: Site De-establisment | F49: 0.1 | G49: =$C$45*F49 -> 38128.273 | H49: =H83 -> 45758 | M49: 6 | N49: 6. AC Equipment | O49: Site De-establisment | Q49: =Q83 -> 0.1 | R49: =$P$44*Q49 -> 116752.76 | S49: Matthews Group INV-1461 | T49: =T83 -> 45808 | U49: 41443.774 | W49: =W83 -> 45820 | AA49: Other | AB49: 0 | AE49: Other | AF49: 0 | AI49: =AB49-AF49 -> 0
B50: 6 | D50: Handover Document Complete | F50: 0.05 | G50: =$C$45*F50 -> 19064.136 | H50: =H84 -> 45786 | M50: 6 | N50: 6. AC Equipment | O50: Handover Document Complete | Q50: =Q84 -> 0.05 | R50: =$P$44*Q50 -> 58376.382 | S50: Matthews Group INV-1462 | T50: =T84 -> 45838 | U50: 20721.887 | W50: =W84 -> 45793 | AA50: Total | AB50: =SUM(AB39:AB49) -> 3545469.8 | AE50: Total | AF50: =SUM(AF39:AF49) -> 2220728.8 | AI50: =AB50-AF50 -> 1324741
B51: 6 | D51: End of Defects Period | F51: 0.05 | G51: =$C$45*F51 -> 19064.136 | H51: =H85 -> 45876 | M51: 6 | N51: 6. AC Equipment | O51: End of Defects Period | Q51: =Q85 -> 0.05 | R51: =$P$44*Q51 -> 58376.382 | S51: Matthews Group INV-1463 | T51: 45838 | U51: 20721.887 | W51: =W85 -> 45869 | AA51: R/Wp | AB51: =+AB50/'Project Plan'!$E$3/1000 -> 8.8636746 | AE51: R/Wp | AF51: =+AF50/'Project Plan'!$E$3/1000 -> 5.551822
T52: =IF(W52>1,EOMONTH(W52,0),"") | AE52: R/kWh | AF52: =AF50/1400000 -> 1.5862349 | AG52: r
B53: 7 | C53: Battery Systems | D53: Battery Inverter + Battery Bank | G53: 6161300 | H53: ='Project Plan'!E33+30 -> 45721 | J53: =SUM(G53:G64) -> 7393827 | K53: 8036768.4 | M53: 7 | N53: 7. Battery Systems | O53: Battery Inverter + Battery Bank | U53: =(R53/$X$53*$K$53) -> 0 | V53: =K53-SUM(U53:U64) -> -0.001275003 | X53: =SUM(R53:R64) -> 6386529
B54: 7 | M54: 7 | N54: 7. Battery Systems | O54: ATESS -PCS630 | R54: 521100 | S54: Herholdts INV994108 | T54: 45688 | U54: 650850.7 | W54: 45701 | Y54: PO3539-MMS-20250114 - RV Approved
M55: 7 | N55: 7. Battery Systems | O55: ATESS -RTF600 | R55: 584600 | S55: Herholdts INV994108 | T55: 45688 | U55: 730161.81 | W55: =W54 -> 45701
M56: 7 | N56: 7. Battery Systems | O56: ATESS -TRF630 | R56: 296000 | S56: Herholdts INV994108 | T56: 45688 | U56: 369702.18 | W56: =W54 -> 45701
M57: 7 | N57: 7. Battery Systems | O57: FW-800/560-HV+ | P57: 2 | Q57: 2461447 | R57: =P57*Q57 -> 4922894 | S57: Herholdts INV994324 | T57: 45688 | U57: 6148664.4 | W57: =W54 -> 45701
M58: 7 | N58: 7. Battery Systems | O58: Storage/Delivery | R58: 0 | U58: =(R58/$X$53*$K$53) -> 0
B59: 7 | D59: Installation | G59: 346000 | H59: ='Project Plan'!E20 -> 45684 | M59: 7 | N59: 7. Battery Systems | U59: =(R59/$X$53*$K$53) -> 0
B60: 7 | D60: AC+DC Equipment | G60: 498000 | H60: =H59 -> 45684 | M60: 7 | N60: 7. Battery Systems | O60: 3rd Aircon/Additional - RCF Tech - VO | R60: 20645 | S60: RCF Tech INV002 | T60: 45869 | U60: 0 | W60: 45842 | Y60: PO4087-MMS-20250702 - RV Approved
B61: 7 | D61: AC Cable | G61: 263526.96 | H61: =H60+30 -> 45714 | M61: 7 | N61: 7. Battery Systems | U61: =(R61/$X$53*$K$53) -> 0
B62: 7 | D62: Airconditioned Container - 1 per 1000kWh | G62: 125000 | H62: =H61 -> 45714 | M62: 7 | N62: 7. Battery Systems | O62: Airconditioned Container - 1 per 1000kWh (Provision for Commissioning Assistance) | U62: =(R62/$X$53*$K$53) -> 0
B63: 7 | M63: 7 | N63: 7. Battery Systems | O63: Aircons - RCF Tech - Deposit | R63: =41290 * 0.8 -> 33032 | S63: RCF Tech QU001 | T63: 45777 | U63: 126963.81 | W63: 45757 | Y63: PO3789-MMS-20250404 - MI Approved
B64: 7 | M64: 7 | N64: 7. Battery Systems | O64: Aircons - RCF Tech - last 20% | R64: =41290* 0.2 -> 8258 | S64: RCF Tech QU001 | T64: 45777 | U64: 10425.517 | W64: 45785
T65: =IF(W65>1,EOMONTH(W65,0),"")
B66: 8 | C66: Product Add On | J66: =SUM(G66:G76) -> 0 | K66: 193988.08 | M66: 8 | N66: 8. Product Add On | O66: Roof Remedial - Oryx Revamp | P66: 0.7 | Q66: 135656 | R66: =P66*Q66 -> 94959.2 | S66: Oryx Revamp: Inv 1892 | T66: 45657 | U66: =(R66/$X$66*$K$66) -> 58843.237 | V66: =K66-SUM(U66:U76) -> -21238.98 | W66: 45638 | X66: =SUM(R66:R76) -> 313051.32 | Y66: PO3519-MMS-20241209
B67: 8 | M67: 8 | N67: 8. Product Add On | O67: Roof Remedial - Oryx Revamp | P67: 0.3 | R67: =Q66*P67 -> 40696.8 | S67: Oryx Revamp: Inv 1892 | T67: 45657 | U67: =(R67/$X$66*$K$66) -> 25218.53 | W67: 45680
M68: 8 | N68: 8. Product Add On | O68: Additional Aircons 2x 60000BTU - RCF Tech - VO | P68: 0.8 | Q68: 103835 | R68: =P68*Q68 -> 83068 | S68: RCF Tech Inv004 | T68: 45900 | U68: 61634.14 | W68: 45883 | Y68: PO4215-MMS-20250812
B69: 8 | M69: 8 | N69: 8. Product Add On | P69: 0.2 | R69: =Q68*P69 -> 20767 | S69: RCF Tech Inv004 | T69: 45900 | U69: 13633.19 | W69: 45901
B70: 8 | M70: 8 | N70: 8. Product Add On | O70: Trunking Clamp and Screws - Lumax | R70: 6715 | S70: Lumax Inv 1001/70000751 | T70: 45747 | U70: 9149.55 | W70: =T70+30 -> 45777 | Y70: PO3726-MMS-20250306
B71: 8 | M71: 8 | N71: 8. Product Add On | O71: Lithium Extinguishers - Firebreak SA | R71: 22794.36 | S71: Firebreak PFI_10024 | T71: 45838 | U71: 25509.433 | W71: 45834 | Y71: PO4014-MMS-20250619 - RV Approved
M72: 8 | N72: 8. Product Add On | U72: 0
M73: 8 | N73: 8. Product Add On | U73: 0
B74: 8 | M74: 8 | N74: 8. Product Add On | O74: Energitrack controller & Commission Support - Herholdts | R74: 7200 | S74: Herholdts Inv: INV1126662 | T74: 45900 | U74: 0 | W74: =T74+30 -> 45930 | Y74: PO4262-MMS-20250821 - RV Approved
B75: 8 | M75: 8 | N75: 8. Product Add On | O75: Motorized Breaker Upgrade and Grid Relay - All Electrical - VO | R75: 36485.85 | S75: All Electrical - IN144166 | T75: 45900 | U75: 21238.98 | W75: 45888 | Y75: PO4263-MMS-20250821 - RV Approved
B76: 8 | M76: 8 | N76: 8. Product Add On | O76: Delivery of Fire Extinguishers | R76: 365.11 | S76: DSV Inv: 180138260 | T76: 45869 | W76: 45900 | Y76: PO4014-MMS-20250619 - RV Approved
L77: Only services to be capture below, products above | T77: =IF(W77>1,EOMONTH(W77,0),"")
B78: 9 | C78: AC & DC Installation | D78: Project Kick Off | F78: 0.1 | G78: =SUM($C$79:$C$80)*F78 -> 34216 | H78: ='Project Plan'!E21-7 -> 45684 | J78: =SUM(G78:G85) -> 342160 | K78: =117764.705882353+284776.470588235 -> 402541.18 | M78: 9 | N78: 9. AC & DC installation | O78: Project Kick Off | P78: =AF41+AF42 -> 676952 | Q78: 0.1 | R78: =$P$78*Q78 -> 67695.2 | S78: Matthews Group INV 1423 | T78: 45688 | U78: 40254.118 | V78: 0 | W78: 45695 | X78: =SUM(R78:R85) -> 676952 | Y78: PO3567-MMS-20250127 - RV Approved
B79: 9 | C79: 100100 | D79: Site Establishment | F79: 0.15 | G79: =SUM($C$79:$C$80)*F79 -> 51324 | H79: ='Project Plan'!I21 -> 45691 | M79: 9 | N79: 9. AC & DC installation | O79: Site Establishment | Q79: 0.15 | R79: =$P$78*Q79 -> 101542.8 | S79: Matthews Group INV-1424 | T79: 45688 | U79: 60381.176 | W79: 45701
B80: 9 | C80: 242060 | D80: AC Installation Complete | F80: 0.2 | G80: =SUM($C$79:$C$80)*F80 -> 68432 | H80: ='Project Plan'!G24 -> 45756 | M80: 9 | N80: 9. AC & DC installation | O80: AC Installation Complete | Q80: 0.2 | R80: =$P$78*Q80 -> 135390.4 | S80: Matthews Group INV-1451 | T80: =IF(W80>1,EOMONTH(W80,0),"") -> 45777 | U80: 80508.235 | W80: 45771
B81: 9 | D81: DC Installation Complete | F81: 0.25 | G81: =SUM($C$79:$C$80)*F81 -> 85540 | H81: ='Project Plan'!G33 -> 45719 | M81: 9 | N81: 9. AC & DC installation | O81: DC Installation Complete | Q81: 0.25 | R81: =$P$78*Q81 -> 169238 | S81: Matthews Group INV 1445 | T81: 45777 | U81: 100635.29 | W81: 45771
B82: 9 | D82: Commissioning Complete | F82: 0.1 | G82: =SUM($C$79:$C$80)*F82 -> 34216 | H82: ='Project Plan'!G43 -> 45772 | M82: 9 | N82: 9. AC & DC installation | O82: Commissioning Complete | Q82: 0.1 | R82: =$P$78*Q82 -> 67695.2 | S82: Matthews Group INV 1452 | T82: 45777 | U82: 40254.118 | W82: 45785
B83: 9 | D83: Site De-establisment | F83: 0.1 | G83: =SUM($C$79:$C$80)*F83 -> 34216 | H83: ='Project Plan'!G53 -> 45758 | M83: 9 | N83: 9. AC & DC installation | O83: Site De-establisment | Q83: 0.1 | R83: =$P$78*Q83 -> 67695.2 | S83: Matthews Group INV-1461 | T83: 45808 | U83: 40254.118 | W83: 45820
B84: 9 | D84: Handover Document Complete | F84: 0.05 | G84: =SUM($C$79:$C$80)*F84 -> 17108 | H84: ='Project Plan'!G55 -> 45786 | M84: 9 | N84: 9. AC & DC installation | O84: Handover Document Complete | Q84: 0.05 | R84: =$P$78*Q84 -> 33847.6 | S84: Matthews Group INV-1462 | T84: 45838 | U84: 20127.059 | W84: ='Project Plan'!K55+7 -> 45793
B85: 9 | D85: End of Defects Period | F85: 0.05 | G85: =SUM($C$79:$C$80)*F85 -> 17108 | H85: =H84+90 -> 45876 | M85: 9 | N85: 9. AC & DC installation | O85: End of Defects Period | Q85: 0.05 | R85: =$P$78*Q85 -> 33847.6 | S85: Matthews Group INV-1463 | T85: 45838 | U85: 20127.059 | W85: 45869
T86: =IF(W86>1,EOMONTH(W86,0),"")
B87: 10 | C87: Site Logistics | J87: =SUM(G87:G98) -> 54108.833 | K87: =10000+5803.92156862745+47853.5294117647 -> 63657.451 | M87: 10 | N87: 10. Site Logistics | O87: Additional Security - VO | R87: 16380 | S87: DIVERGENT - Inv 1117175 | T87: 45747 | U87: 3052.5431 | V87: =K87-SUM(U87:U98) -> -0.00035580335 | W87: 45736 | X87: =SUM(R87:R98) -> 114637 | Y87: PO3734-MMS-20250311 - RV Approved
B88: 10 | D88: Offloading | G88: 8500 | H88: =H82 -> 45772 | M88: 10 | N88: 10. Site Logistics | O88: Night Guard | R88: 7020 | S88: Divergent - Inv 1117291 | T88: 45747 | U88: 109.27 | W88: 45750 | Y88: PO3766-MMS-20250325 - RV Approved
B89: 10 | D89: Storage | G89: 4933.3333 | H89: =H88 -> 45772 | M89: 10 | N89: 10. Site Logistics | O89: Project Kick Off | P89: =SUM(AF43:AF45) -> 91237 | Q89: =Q78 -> 0.1 | R89: =$P$89*Q89 -> 9123.7 | S89: =S78 -> Matthews Group INV 1423 | T89: =T78 -> 45688 | U89: 6079.1608 | W89: =W78 -> 45695 | Y89: PO3567-MMS-20250127 - RV Approved
B90: 10 | D90: Scaffolding | G90: 40675.5 | H90: =H88 -> 45772 | M90: 10 | N90: 10. Site Logistics | O90: Site Establishment | Q90: =Q79 -> 0.15 | R90: =$P$89*Q90 -> 13685.55 | S90: Matthews Group INV-1424 | T90: =T79 -> 45688 | U90: 9118.7411 | W90: =W79 -> 45701
B91: 10 | M91: 10 | N91: 10. Site Logistics | O91: AC Installation Complete | Q91: =Q80 -> 0.2 | R91: =$P$89*Q91 -> 18247.4 | S91: Matthews Group INV-1451 | T91: =T80 -> 45777 | U91: 12684.565 | W91: =W80 -> 45771
B92: 10 | M92: 10 | N92: 10. Site Logistics | O92: DC Installation Complete | Q92: =Q81 -> 0.25 | R92: =$P$89*Q92 -> 22809.25 | S92: Matthews Group INV 1445 | T92: =T81 -> 45777 | U92: 14824.169 | W92: =W81 -> 45771
B93: 10 | M93: 10 | N93: 10. Site Logistics | O93: Commissioning Complete | Q93: =Q82 -> 0.1 | R93: =$P$89*Q93 -> 9123.7 | S93: Matthews Group INV 1452 | T93: =T82 -> 45777 | U93: 5929.6675 | W93: =W82 -> 45785
B94: 10 | M94: 10 | N94: 10. Site Logistics | O94: Site De-establisment | Q94: =Q83 -> 0.1 | R94: =$P$89*Q94 -> 9123.7 | S94: Matthews Group INV-1461 | T94: =T83 -> 45808 | U94: 5929.6675 | W94: =W83 -> 45820
B95: 10 | M95: 10 | N95: 10. Site Logistics | O95: Handover Document Complete | Q95: =Q84 -> 0.05 | R95: =$P$89*Q95 -> 4561.85 | S95: Matthews Group INV-1462 | T95: =T84 -> 45838 | U95: 2964.8338 | W95: =W84 -> 45793
B96: 10 | M96: 10 | N96: 10. Site Logistics | O96: End of Defects Period | Q96: =Q85 -> 0.05 | R96: =$P$89*Q96 -> 4561.85 | S96: Matthews Group INV-1463 | T96: =T85 -> 45838 | U96: 2964.8338 | W96: =W85 -> 45869
B97: 10 | M97: 10 | N97: 10. Site Logistics | T97: =IF(W97>1,EOMONTH(W97,0),"") | U97: =(R97/$X$87*$K$87) -> 0
B98: 10 | M98: 10 | N98: 10. Site Logistics | T98: =IF(W98>1,EOMONTH(W98,0),"") | U98: =(R98/$X$87*$K$87) -> 0
T99: =IF(W99>1,EOMONTH(W99,0),"")
B100: 11 | C100: Due Dilligence | D100: Electrical PrEng sign off | G100: 11000 | H100: ='Project Plan'!E57 -> 45763 | J100: =SUM(G100:G105) -> 111020 | K100: 130611.76 | M100: 11 | N100: 11. Due Dilligence | O100: Electrical PrEng sign off | R100: 15750 | S100: Sunspot: E024 | T100: 45808 | U100: 76116.379 | V100: =K100-SUM(U100:U105) -> 0.0010185569 | W100: 45862 | X100: =SUM(R100:R105) -> 38759.07
M101: 11 | N101: 11. Due Dilligence | O101: Travel | R101: =2564.19+1418.48 -> 3982.67 | S101: Sunspot: E024 | T101: 45808 | U101: 13420.95 | W101: =W100 -> 45862
B102: 11 | D102: Structural sign off | G102: 20020 | H102: ='Project Plan'!E21 -> 45691 | M102: 11 | N102: 11. Due Dilligence | O102: Structural sign off | R102: 11026.4 | S102: LB Consulting Inv-1838 | T102: 45626 | U102: 14115.734 | W102: 45624 | Y102: PO3471-MMS-20241121 - RV Approved
B103: 11 | M103: 11 | N103: 11. Due Dilligence | O103: Red Team | R103: 8000 | S103: Matriarch - INV-4423 | T103: 45808 | U103: 26958.699 | W103: 45808
...

Sheet Finance - Revenue
A1: REVENUE RECOGNITION AMOUNT | B1: (All)
A3: Sum of REVENUE RECOGNITION AMOUNT | B3: Column Labels
A4: Row Labels | C4: (blank) | D4: 45626 | E4: 45657 | F4: 45688 | G4: 45716 | H4: 45747 | I4: 45777 | J4: 45808 | K4: 45838 | L4: 45869 | M4: 46022 | N4: 45900 | O4: 45930 | P4: 46053 | Q4: 46081 | R4: Grand Total
A5: (blank)
A6: BDP Commission
A7: 1. Panels | B7: 0 | C7: 0 | E7: 1146065.7 | F7: 25234.91 | R7: 1171300.6
A8: 2. Inverters | C8: 0 | E8: 179134.85 | H8: 49126.024 | P8: 0 | R8: 228260.87
A9: 3. Mounting Structures | G9: 195847.83 | H9: 0 | R9: 195847.83
A10: 4. DC Equipment | E10: 187862.44 | F10: 28138.84 | G10: 72136.626 | H10: 13110.75 | I10: 53577.998 | J10: 9741.4542 | K10: 9741.4542 | R10: 374309.57
A11: 5. Monitoring | B11: 0 | F11: 102996.26 | G11: 86134.18 | M11: 0 | R11: 189130.44
A12: 6. AC Equipment | B12: 0 | F12: 103609.44 | I12: 227940.76 | J12: 41443.774 | K12: 41443.774 | R12: 414437.75
A13: 8. Product Add On | C13: 0 | E13: 84061.767 | H13: 9149.55 | K13: 25509.433 | N13: 96506.31 | R13: 215227.06
A14: 9. AC & DC installation | F14: 100635.29 | I14: 221397.65 | J14: 40254.118 | K14: 40254.118 | R14: 402541.18
A15: 10. Site Logistics | B15: 0 | F15: 15197.902 | H15: 3161.8131 | I15: 33438.401 | J15: 5929.6675 | K15: 5929.6675 | R15: 63657.451
A16: 11. Due Dilligence | B16: 0 | C16: 0 | D16: 14115.734 | J16: 116496.03 | R16: 130611.76
A17: 13. Engineering | J17: 272693.58 | R17: 272693.58
A18: 14. General Expenses | E18: 7754.7473 | F18: 7583.8909 | G18: 4142.1544 | H18: 8392.208 | I18: 7747.5088 | J18: 20379.495 | K18: 0 | L18: 0 | N18: 0 | P18: 0 | R18: 56000.004
A19: 15. Service Add On
A20: 7. Battery Systems | C20: 0 | F20: 7899379.1 | I20: 137389.33 | L20: 0 | R20: 8036768.4
A21: Grand Total | B21: 0 | C21: 0 | D21: 14115.734 | E21: 1604879.5 | F21: 8282775.6 | G21: 358260.79 | H21: 82940.345 | I21: 681491.64 | J21: 506938.12 | K21: 122878.45 | L21: 0 | M21: 0 | N21: 96506.31 | P21: 0 | R21: 11750787
D23: 14115.73 | E23: 1520817.7 | F23: 8282775.6 | G23: 358260.79 | H23: 82940.35 | I23: 681491.64 | J23: 506938.12 | K23: 122878.45 | M23: =SUM(D23:L23) -> 11570218 | O23: =GETPIVOTDATA("REVENUE RECOGNITION AMOUNT",$A$3)-M23 -> 180568.07
D24: =GETPIVOTDATA("REVENUE RECOGNITION AMOUNT",$A$3,"INVOICE RAISED DATE",DATE(2024,11,30))-D23 -> 0.0043820123 | E24: =GETPIVOTDATA("REVENUE RECOGNITION AMOUNT",$A$3,"INVOICE RAISED DATE",DATE(2024,12,31))-E23 -> 84061.771 | F24: =GETPIVOTDATA("REVENUE RECOGNITION AMOUNT",$A$3,"INVOICE RAISED DATE",DATE(2025,1,31))-F23 -> 0.00018181931 | G24: =GETPIVOTDATA("REVENUE RECOGNITION AMOUNT",$A$3,"INVOICE RAISED DATE",DATE(2025,2,28))-G23 -> -0.0035108242 | H24: =GETPIVOTDATA("REVENUE RECOGNITION AMOUNT",$A$3,"INVOICE RAISED DATE",DATE(2025,3,31))-H23 -> -0.004543129 | I24: =GETPIVOTDATA("REVENUE RECOGNITION AMOUNT",$A$3,"INVOICE RAISED DATE",DATE(2025,4,30))-I23 -> 0.00058274413 | J24: =GETPIVOTDATA("REVENUE RECOGNITION AMOUNT",$A$3,"INVOICE RAISED DATE",DATE(2025,5,31))-J23 -> -0.004539145 | K24: =GETPIVOTDATA("REVENUE RECOGNITION AMOUNT",$A$3,"INVOICE RAISED DATE",DATE(2025,6,30))-K23 -> -0.003271373

Sheet Finance - COS
A3: Sum of Actual Total | B3: Column Labels
A4: Row Labels | B4: (blank) | D4: 45626 | E4: 45657 | F4: 45688 | G4: 45716 | H4: 45747 | I4: 45777 | J4: 45808 | K4: 45838 | L4: 45869 | M4: 45900 | N4: 45930 | O4: 46022 | P4: 46053 | Q4: 46081 | R4: Grand Total
A5: BDP Commission
A6: (blank)
A7: 1. Panels | E7: 908317.8 | R7: 908317.8
A8: 2. Inverters | E8: 206611.05 | H8: 43190.78 | P8: -68870 | R8: 180931.83
A9: 3. Mounting Structures | G9: 84254.7 | H9: 2296 | R9: 86550.7
A10: 4. DC Equipment | E10: 159600 | F10: 23562.5 | G10: 53200 | H10: 55100 | I10: 51837.5 | J10: 9425 | K10: 9425 | R10: 362150
A11: 5. Monitoring | F11: 25295.04 | G11: 27100 | O11: 15813 | R11: 68208.04
A12: 6. AC Equipment | F12: 291881.92 | I12: 642140.21 | J12: 116752.76 | K12: 116752.76 | R12: 1167527.7
A13: 8. Product Add On | E13: 135656 | H13: 6715 | K13: 22794.36 | L13: 365.11 | M13: 147520.85 | R13: 313051.32
A14: 9. AC & DC installation | F14: 169238 | I14: 372323.6 | J14: 67695.2 | K14: 67695.2 | R14: 676952
A15: 10. Site Logistics | F15: 22809.25 | H15: 23400 | I15: 50180.35 | J15: 9123.7 | K15: 9123.7 | R15: 114637
A16: 11. Due Dilligence | D16: 11026.4 | J16: 27732.67 | R16: 38759.07
A17: 13. Engineering | J17: 144194.49 | R17: 144194.49
A18: 14. General Expenses | E18: 6375.86 | F18: 5594.87 | G18: 725.13 | H18: 4534.32 | I18: 4040.3 | J18: 10015.22 | K18: 5888.69 | L18: 6060.22 | M18: 20384.45 | P18: 3613.64 | R18: 67232.7
A19: 15. Service Add On | I19: 190762.14 | K19: 267.01 | L19: 286244.26 | M19: 282391 | N19: 14110 | P19: 267135.65 | Q19: 128005.64 | R19: 1168915.7
A20: 7. Battery Systems | B20: 0 | F20: 6324594 | I20: 41290 | L20: 20645 | R20: 6386529
A21: Grand Total | B21: 0 | D21: 11026.4 | E21: 1416560.7 | F21: 6862975.6 | G21: 165279.83 | H21: 135236.1 | I21: 1352574.1 | J21: 384939.05 | K21: 231946.73 | L21: 313314.59 | M21: 450296.3 | N21: 14110 | O21: 15813 | P21: 201879.29 | Q21: 128005.64 | R21: 11683957

Sheet Project Margins
A1: [capture project margins from costing sheet]
A3: Products | D3: 0.32
A4: Services | D4: 0.5
A5: Expenses | D5: 0.15
A6: Subcontractors | D6: 0.2

Sheet Equipment Quotes
B2: Equipment Quote and Budget comparision
B4: Description | D4: Budget | F4: Supplier 1 | H4: Variance | J4: Supplier 2 | L4: Variance | N4: Comments / Notes
F7: >Name< | J7: >Name<
B9: Inverters | D9: =SUM(D10:D11) -> 210000 | F9: =SUM(F10:F13) -> 0 | H9: =$D$9-F9 -> 210000 | J9: =SUM(J10:J13) -> 0 | L9: =$D$9-J9 -> 210000
B10: Inverters | D10: ='Expenditure Breakdown'!G13 -> 210000
B11: Optimizers | D11: ='Expenditure Breakdown'!G14 -> 0
B12: Warranty
B13: Delivery fee
F15: >Name< | J15: >Name<
B17: Mounting Structure | D17: =SUM(D18:D19) -> 180180 | F17: =SUM(F18:F20) -> 0 | H17: =$D$17- F17 -> 180180 | J17: =SUM(J18:J20) -> 0 | L17: =$D$17- J17 -> 180180
B18: Mounting Structure | D18: ='Expenditure Breakdown'!G18 -> 180180
B19: Delivery fee
F21: >Name< | J21: >Name<
B23: DC Cable | D23: =SUM(D24:D25) -> 141680 | F23: =SUM(F24:F25) -> 0 | H23: =$D$23- F23 -> 141680 | J23: =SUM(J24:J25) -> 0 | L23: =$D$23- J23 -> 141680
B24: DC Cable | D24: ='Expenditure Breakdown'!G23 -> 141680
B25: Delivery fee
F27: >Name< | J27: >Name<
B29: Monitoring system | D29: =SUM(D30:D32) -> #REF! | F29: =SUM(F30:F42) -> 0 | H29: =$D$29-F29 -> #REF! | J29: =SUM(J30:J32) -> 0 | L29: =$D$29-J29 -> #REF!
B30: ='Expenditure Breakdown'!D35 -> Smartlogger 3000 | D30: ='Expenditure Breakdown'!G35 -> 26000
B31: ='Expenditure Breakdown'!#REF! -> #REF! | D31: ='Expenditure Breakdown'!#REF! -> #REF!
B32: Delivery fee
F34: >Name< | J34: >Name<
B36: Additional Scope | D36: =SUM(D37:D41) -> 0 | F36: =SUM(F37:F41) -> 0 | H36: =$D$29-F36 -> #REF! | J36: =SUM(J37:J41) -> 0 | L36: =$D$29-J36 -> #REF!
B37: SCADA | D37: ='Expenditure Breakdown'!G66 -> 0
B38: Inverter cage
B39: Cat ladders
B40: Gen Integration
B41: Lifelines
B43: Totals | D43: =D36+D29+D23+D17+D9 -> #REF! | H43: =SUM(H7:H42) -> #REF! | L43: =SUM(L7:L42) -> #REF!
B47: All amounts are incl VAT

Sheet Installer Quotes
B2: Installer Quote and Budget comparision
B4: Description | D4: Budget | G4: Cosmic Sun | J4: Variance | L4: Matthews Group | O4: Variance
B6: AC Equipment | D6: ='Expenditure Breakdown'!AB8 -> 1142809.7 | E6: =D6/(1000*'Project Plan'!$E$3) -> 2.8570242 | G6: 277892.91 | H6: =G6/('Project Plan'!$E$3*1000) -> 0.69473227 | J6: =D6-G6 -> 864916.77 | M6: =L6/('Project Plan'!$E$3*1000) -> 0 | O6: =D6-L6 -> 1142809.7
B7: DC Equipment | D7: ='Expenditure Breakdown'!AB9 -> 202684.8 | E7: =D7/(1000*'Project Plan'!$E$3) -> 0.506712 | G7: 142158.25 | H7: =G7/('Project Plan'!$E$3*1000) -> 0.35539562 | J7: =D7-G7 -> 60526.55 | M7: =L7/('Project Plan'!$E$3*1000) -> 0 | O7: =D7-L7 -> 202684.8
B8: AC Labour | D8: ='Expenditure Breakdown'!AB10 -> 446100 | E8: =D8/(1000*'Project Plan'!$E$3) -> 1.11525 | G8: 96174 | H8: =G8/('Project Plan'!$E$3*1000) -> 0.240435 | J8: =D8-G8 -> 349926 | M8: =L8/('Project Plan'!$E$3*1000) -> 0 | O8: =D8-L8 -> 446100
B9: DC Labour | D9: ='Expenditure Breakdown'!AB11 -> 242060 | E9: =D9/(1000*'Project Plan'!$E$3) -> 0.60515 | G9: 230160 | H9: =G9/('Project Plan'!$E$3*1000) -> 0.5754 | J9: =D9-G9 -> 11900 | M9: =L9/('Project Plan'!$E$3*1000) -> 0 | O9: =D9-L9 -> 242060
B10: Offloading | D10: ='Expenditure Breakdown'!AB12 -> 8500 | G10: 0 | J10: =D10-G10 -> 8500 | O10: =D10-L10 -> 8500
B11: Roof Access/Scaffolding | D11: ='Expenditure Breakdown'!AB13 -> 40675.5 | G11: 29257.61 | J11: =D11-G11 -> 11417.89 | O11: =D11-L11 -> 40675.5
B12: Storage | D12: ='Expenditure Breakdown'!AB14 -> 4933.3333 | J12: =D12-G12 -> 4933.3333 | O12: =D12-L12 -> 4933.3333
B13: Telehandler | D13: ='Expenditure Breakdown'!AB15 -> 0
B14: HSE | D14: 0
B15: Totals | D15: =SUM(D6:D13) -> 2087763.3 | G15: =SUM(G6:G13) -> 775642.77 | J15: =SUM(J6:J14) -> 1312120.5 | L15: =SUM(L6:L13) -> 0 | O15: =SUM(O6:O14) -> 2087763.3
B18: Description | D18: Budget | G18: >Installer Name 3< | J18: Variance | L18: >Installer Name 4< | O18: Variance
B20: AC installation | D20: ='Expenditure Breakdown'!#REF! -> #REF! | E20: =D20/(1000*'Project Plan'!$E$3) -> #REF! | H20: =G20/(1000*'Project Plan'!$E$3) -> 0 | J20: =D20-G20 -> #REF! | M20: =L20/(1000*'Project Plan'!$E$3) -> 0 | O20: =D6-L20 -> 1142809.7
B21: AC equipment | D21: ='Expenditure Breakdown'!C51 -> 0 | E21: =D21/(1000*'Project Plan'!$E$3) -> 0 | J21: =D21-G21 -> 0 | M21: =L21/(1000*'Project Plan'!$E$3) -> 0 | O21: =D7-L21 -> 202684.8
B22: DC installation | D22: ='Expenditure Breakdown'!#REF! -> #REF! | E22: =D22/(1000*'Project Plan'!$E$3) -> #REF! | H22: =G22/(1000*'Project Plan'!$E$3) -> 0 | J22: =D22-G22 -> #REF! | M22: =L22/(1000*'Project Plan'!$E$3) -> 0 | O22: =D8-L22 -> 446100
B23: DC equipment | D23: =SUM('Expenditure Breakdown'!G31:G32) -> 20268.48 | E23: =D23/(1000*'Project Plan'!$E$3) -> 0.0506712 | J23: =D23-G23 -> 20268.48 | O23: =D9-L23 -> 242060
B24: Storage | D24: ='Expenditure Breakdown'!G105 -> 0 | J24: =D24-G24 -> 0 | O24: =D10-L24 -> 8500
B25: Panel lifting equipment | D25: =SUM('Expenditure Breakdown'!G87:G89) -> 13433.333 | J25: =D25-G25 -> 13433.333 | O25: =D11-L25 -> 40675.5
B26: Offloading | D26: ='Expenditure Breakdown'!G98 -> 0 | J26: =D26-G26 -> 0 | O26: =D12-L26 -> 4933.3333
B29: Totals | D29: =SUM(D20:D27) -> #REF! | G29: =SUM(G20:G27) -> 0 | J29: =SUM(J20:J28) -> #REF! | L29: =SUM(L20:L27) -> 0 | O29: =SUM(O20:O28) -> 2087763.3
B32: Budget Summary
B34: Budget | D34: =D15 -> 2087763.3
B35: =G4 -> Cosmic Sun | D35: =G15 -> 775642.77
B36: =L4 -> Matthews Group | D36: =L15 -> 0
B37: =G18 -> >Installer Name 3< | D37: =G29 -> 0
B38: =L18 -> >Installer Name 4< | D38: =L29 -> 0
B40: =IF(D40<D34,"Saving","Loss") -> Loss | D40: =D34-MIN(D35:D38) -> 2087763.3
B42: All amounts are exc VAT

Sheet Decision Register
B1: =D15 -> Mayo Macs | E1: Decision Register
B3: ID | C3: Decision Description | D3: Decision Impact | E3: Proposed Date | F3: Proposed By | G3: Status | H3: Approved By | I3: Date | J3: Results / Comments
B4: DEC001
B5: DEC002
B6: DEC003
B7: DEC004
B8: DEC005
B9: DEC006
B10: DEC007
B11: DEC008
B12: DEC009
B13: DEC010
D15: {='Project Plan'!E2:H2} -> Mayo Macs | E15: 0 | F15: 0 | G15: 0
