Workbook
Name Inverter_Capacity: #REF!
Name Inverter_Supplier: #REF!
Name Project_Size: 'Certificate - Financial Close'!Projectsize
Name Project_Size: 'Finance (2)'!Projectsize
Name Project_Size: Projectsize
Name Projectsize: #REF!
Name Projectsize: #REF!
Name Projectsize: 'Project Margins'!$K$5
Name Security_Serv: #REF!
Name Security_Serv: #REF!
Name Security_Serv: #REF!
Name SSS: #REF!
Name SSS: #REF!
Name SSS: #REF!
Name USD_ZAR: #REF!

Sheet Sheet1
A1: PROJECT PLAN
A2: # | B2: Project Milestone | C2: Planned Start Date | D2: Duration (Work Days) | E2: Planned End Date | F2: Actual Start Date | H2: Actual End Date | J2: Comments | L2: =C3 -> 43831 | M2: =L2+3 -> 43834 | N2: =M2+7 -> 43841 | O2: =N2+7 -> 43848 | P2: =O2+7 -> 43855 | Q2: =P2+6 -> 43861 | R2: =Q2+1 -> 43862 | S2: =R2+7 -> 43869 | T2: =S2+7 -> 43876 | U2: =T2+7 -> 43883 | V2: =U2+6 -> 43889 | W2: =V2+7 -> 43896 | X2: =W2+7 -> 43903 | Y2: =X2+7 -> 43910 | Z2: =Y2+7 -> 43917 | AA2: =Z2+3 -> 43920 | AB2: =AA2+4 -> 43924 | AC2: =AB2+7 -> 43931 | AD2: =AC2+7 -> 43938 | AE2: =AD2+7 -> 43945 | AF2: =AE2+6 -> 43951 | AG2: =AF2+2 -> 43953 | AH2: =AG2+7 -> 43960 | AI2: =AH2+7 -> 43967 | AJ2: =AI2+7 -> 43974 | AK2: =AJ2+7 -> 43981 | AL2: =AK2+1 -> 43982 | AM2: =AL2+6 -> 43988 | AN2: =AM2+7 -> 43995 | AO2: =AN2+7 -> 44002 | AP2: =AO2+7 -> 44009 | AQ2: =AP2+3 -> 44012 | AR2: =AQ2+4 -> 44016 | AS2: =AR2+7 -> 44023 | AT2: =AS2+7 -> 44030 | AU2: =AT2+7 -> 44037 | AV2: =AU2+6 -> 44043 | AW2: =AV2+1 -> 44044 | AX2: =AW2+7 -> 44051 | AY2: =AX2+7 -> 44058 | AZ2: =AY2+7 -> 44065 | BA2: =AZ2+7 -> 44072 | BB2: =BA2+2 -> 44074 | BC2: =BB2+5 -> 44079 | BD2: =BC2+7 -> 44086 | BE2: =BD2+7 -> 44093 | BF2: =BE2+7 -> 44100 | BG2: =BF2+4 -> 44104
A3: 1 | B3: Contract Signature | C3: 43831 | D3: 1 | E3: 43832 | F3: 43831 | G3: 1 | H3: 43832 | L3: =IF(AND($F3<(L$2+7),$F3>L$2),1, IF(AND($H3<L$2+7,$H3>L$2),3, IF(AND($F3<=L$2, $H3>=L$2), 2, "" ))) -> 3 | M3: =IF(AND($F3<(M$2+7),$F3>M$2),1, IF(AND($H3<M$2+7,$H3>M$2),3, IF(AND($F3<=M$2, $H3>=M$2), 2, "" ))) | N3: =IF(AND($F3<(N$2+7),$F3>N$2),1, IF(AND($H3<N$2+7,$H3>N$2),3, IF(AND($F3<=N$2, $H3>=N$2), 2, "" ))) | O3: =IF(AND($F3<(O$2+7),$F3>O$2),1, IF(AND($H3<O$2+7,$H3>O$2),3, IF(AND($F3<=O$2, $H3>=O$2), 2, "" ))) | P3: =IF(AND($F3<(P$2+7),$F3>P$2),1, IF(AND($H3<P$2+7,$H3>P$2),3, IF(AND($F3<=P$2, $H3>=P$2), 2, "" ))) | Q3: =IF(AND($F3<(Q$2+7),$F3>Q$2),1, IF(AND($H3<Q$2+7,$H3>Q$2),3, IF(AND($F3<=Q$2, $H3>=Q$2), 2, "" ))) | R3: =IF(AND($F3<(R$2+7),$F3>R$2),1, IF(AND($H3<R$2+7,$H3>R$2),3, IF(AND($F3<=R$2, $H3>=R$2), 2, "" ))) | S3: =IF(AND($F3<(S$2+7),$F3>S$2),1, IF(AND($H3<S$2+7,$H3>S$2),3, IF(AND($F3<=S$2, $H3>=S$2), 2, "" ))) | ... AQ3: =IF(AND($F3<(AQ$2+7),$F3>AQ$2),1, IF(AND($H3<AQ$2+7,$H3>AQ$2),3, IF(AND($F3<=AQ$2, $H3>=AQ$2), 2, "" )))
A4: A | B4: PAYMENT MILESTONE 1: DEPOSIT | C4: 43832 | D4: 1 | E4: 43833 | F4: 43832 | G4: 1 | H4: 43833 | L4: =IF(AND($F4<(L$2+7),$F4>L$2),1, IF(AND($H4<L$2+7,$H4>L$2),3, IF(AND($F4<=L$2, $H4>=L$2), 2, "" ))) -> 1 | M4: =IF(AND($F4<(M$2+7),$F4>M$2),1, IF(AND($H4<M$2+7,$H4>M$2),3, IF(AND($F4<=M$2, $H4>=M$2), 2, "" ))) | N4: =IF(AND($F4<(N$2+7),$F4>N$2),1, IF(AND($H4<N$2+7,$H4>N$2),3, IF(AND($F4<=N$2, $H4>=N$2), 2, "" ))) | O4: =IF(AND($F4<(O$2+7),$F4>O$2),1, IF(AND($H4<O$2+7,$H4>O$2),3, IF(AND($F4<=O$2, $H4>=O$2), 2, "" ))) | P4: =IF(AND($F4<(P$2+7),$F4>P$2),1, IF(AND($H4<P$2+7,$H4>P$2),3, IF(AND($F4<=P$2, $H4>=P$2), 2, "" ))) | Q4: =IF(AND($F4<(Q$2+7),$F4>Q$2),1, IF(AND($H4<Q$2+7,$H4>Q$2),3, IF(AND($F4<=Q$2, $H4>=Q$2), 2, "" ))) | R4: =IF(AND($F4<(R$2+7),$F4>R$2),1, IF(AND($H4<R$2+7,$H4>R$2),3, IF(AND($F4<=R$2, $H4>=R$2), 2, "" ))) | S4: =IF(AND($F4<(S$2+7),$F4>S$2),1, IF(AND($H4<S$2+7,$H4>S$2),3, IF(AND($F4<=S$2, $H4>=S$2), 2, "" ))) | ... AQ4: =IF(AND($F4<(AQ$2+7),$F4>AQ$2),1, IF(AND($H4<AQ$2+7,$H4>AQ$2),3, IF(AND($F4<=AQ$2, $H4>=AQ$2), 2, "" )))
A5: 2 | B5: Structural and Electrical Due Diligences | C5: 43833 | D5: 5 | E5: 43840 | F5: 43833 | G5: 5 | H5: 43840 | L5: =IF(AND($F5<(L$2+7),$F5>L$2),1, IF(AND($H5<L$2+7,$H5>L$2),3, IF(AND($F5<=L$2, $H5>=L$2), 2, "" ))) -> 1 | M5: =IF(AND($F5<(M$2+7),$F5>M$2),1, IF(AND($H5<M$2+7,$H5>M$2),3, IF(AND($F5<=M$2, $H5>=M$2), 2, "" ))) -> 3 | N5: =IF(AND($F5<(N$2+7),$F5>N$2),1, IF(AND($H5<N$2+7,$H5>N$2),3, IF(AND($F5<=N$2, $H5>=N$2), 2, "" ))) | O5: =IF(AND($F5<(O$2+7),$F5>O$2),1, IF(AND($H5<O$2+7,$H5>O$2),3, IF(AND($F5<=O$2, $H5>=O$2), 2, "" ))) | P5: =IF(AND($F5<(P$2+7),$F5>P$2),1, IF(AND($H5<P$2+7,$H5>P$2),3, IF(AND($F5<=P$2, $H5>=P$2), 2, "" ))) | Q5: =IF(AND($F5<(Q$2+7),$F5>Q$2),1, IF(AND($H5<Q$2+7,$H5>Q$2),3, IF(AND($F5<=Q$2, $H5>=Q$2), 2, "" ))) | R5: =IF(AND($F5<(R$2+7),$F5>R$2),1, IF(AND($H5<R$2+7,$H5>R$2),3, IF(AND($F5<=R$2, $H5>=R$2), 2, "" ))) | S5: =IF(AND($F5<(S$2+7),$F5>S$2),1, IF(AND($H5<S$2+7,$H5>S$2),3, IF(AND($F5<=S$2, $H5>=S$2), 2, "" ))) | ... AQ5: =IF(AND($F5<(AQ$2+7),$F5>AQ$2),1, IF(AND($H5<AQ$2+7,$H5>AQ$2),3, IF(AND($F5<=AQ$2, $H5>=AQ$2), 2, "" )))
A6: 3 | B6: Design Confirmation | C6: 43841 | D6: 2 | E6: 43844 | F6: 43841 | G6: 2 | H6: 43844 | L6: =IF(AND($F6<(L$2+7),$F6>L$2),1, IF(AND($H6<L$2+7,$H6>L$2),3, IF(AND($F6<=L$2, $H6>=L$2), 2, "" ))) | M6: =IF(AND($F6<(M$2+7),$F6>M$2),1, IF(AND($H6<M$2+7,$H6>M$2),3, IF(AND($F6<=M$2, $H6>=M$2), 2, "" ))) | N6: =IF(AND($F6<(N$2+7),$F6>N$2),1, IF(AND($H6<N$2+7,$H6>N$2),3, IF(AND($F6<=N$2, $H6>=N$2), 2, "" ))) -> 3 | O6: =IF(AND($F6<(O$2+7),$F6>O$2),1, IF(AND($H6<O$2+7,$H6>O$2),3, IF(AND($F6<=O$2, $H6>=O$2), 2, "" ))) | P6: =IF(AND($F6<(P$2+7),$F6>P$2),1, IF(AND($H6<P$2+7,$H6>P$2),3, IF(AND($F6<=P$2, $H6>=P$2), 2, "" ))) | Q6: =IF(AND($F6<(Q$2+7),$F6>Q$2),1, IF(AND($H6<Q$2+7,$H6>Q$2),3, IF(AND($F6<=Q$2, $H6>=Q$2), 2, "" ))) | R6: =IF(AND($F6<(R$2+7),$F6>R$2),1, IF(AND($H6<R$2+7,$H6>R$2),3, IF(AND($F6<=R$2, $H6>=R$2), 2, "" ))) | S6: =IF(AND($F6<(S$2+7),$F6>S$2),1, IF(AND($H6<S$2+7,$H6>S$2),3, IF(AND($F6<=S$2, $H6>=S$2), 2, "" ))) | ... AQ6: =IF(AND($F6<(AQ$2+7),$F6>AQ$2),1, IF(AND($H6<AQ$2+7,$H6>AQ$2),3, IF(AND($F6<=AQ$2, $H6>=AQ$2), 2, "" )))
A7: 4 | B7: Equipment Procurement | C7: 43833 | E7: 43949 | F7: 43833 | H7: 43949 | L7: =IF(AND($F7<(L$2+7),$F7>L$2),1, IF(AND($H7<L$2+7,$H7>L$2),3, IF(AND($F7<=L$2, $H7>=L$2), 2, "" ))) -> 1 | M7: =IF(AND($F7<(M$2+7),$F7>M$2),1, IF(AND($H7<M$2+7,$H7>M$2),3, IF(AND($F7<=M$2, $H7>=M$2), 2, "" ))) -> 2 | N7: =IF(AND($F7<(N$2+7),$F7>N$2),1, IF(AND($H7<N$2+7,$H7>N$2),3, IF(AND($F7<=N$2, $H7>=N$2), 2, "" ))) -> 2 | O7: =IF(AND($F7<(O$2+7),$F7>O$2),1, IF(AND($H7<O$2+7,$H7>O$2),3, IF(AND($F7<=O$2, $H7>=O$2), 2, "" ))) -> 2 | P7: =IF(AND($F7<(P$2+7),$F7>P$2),1, IF(AND($H7<P$2+7,$H7>P$2),3, IF(AND($F7<=P$2, $H7>=P$2), 2, "" ))) -> 2 | Q7: =IF(AND($F7<(Q$2+7),$F7>Q$2),1, IF(AND($H7<Q$2+7,$H7>Q$2),3, IF(AND($F7<=Q$2, $H7>=Q$2), 2, "" ))) -> 2 | R7: =IF(AND($F7<(R$2+7),$F7>R$2),1, IF(AND($H7<R$2+7,$H7>R$2),3, IF(AND($F7<=R$2, $H7>=R$2), 2, "" ))) -> 2 | S7: =IF(AND($F7<(S$2+7),$F7>S$2),1, IF(AND($H7<S$2+7,$H7>S$2),3, IF(AND($F7<=S$2, $H7>=S$2), 2, "" ))) -> 2 | ... AQ7: =IF(AND($F7<(AQ$2+7),$F7>AQ$2),1, IF(AND($H7<AQ$2+7,$H7>AQ$2),3, IF(AND($F7<=AQ$2, $H7>=AQ$2), 2, "" )))
B8: Panel Procurement | C8: 43833 | D8: 5 | E8: 43840 | F8: 43833 | G8: 5 | H8: 43840 | L8: =IF(AND($F8<(L$2+7),$F8>L$2),1, IF(AND($H8<L$2+7,$H8>L$2),3, IF(AND($F8<=L$2, $H8>=L$2), 2, "" ))) -> 1 | M8: =IF(AND($F8<(M$2+7),$F8>M$2),1, IF(AND($H8<M$2+7,$H8>M$2),3, IF(AND($F8<=M$2, $H8>=M$2), 2, "" ))) -> 3 | N8: =IF(AND($F8<(N$2+7),$F8>N$2),1, IF(AND($H8<N$2+7,$H8>N$2),3, IF(AND($F8<=N$2, $H8>=N$2), 2, "" ))) | O8: =IF(AND($F8<(O$2+7),$F8>O$2),1, IF(AND($H8<O$2+7,$H8>O$2),3, IF(AND($F8<=O$2, $H8>=O$2), 2, "" ))) | P8: =IF(AND($F8<(P$2+7),$F8>P$2),1, IF(AND($H8<P$2+7,$H8>P$2),3, IF(AND($F8<=P$2, $H8>=P$2), 2, "" ))) | Q8: =IF(AND($F8<(Q$2+7),$F8>Q$2),1, IF(AND($H8<Q$2+7,$H8>Q$2),3, IF(AND($F8<=Q$2, $H8>=Q$2), 2, "" ))) | R8: =IF(AND($F8<(R$2+7),$F8>R$2),1, IF(AND($H8<R$2+7,$H8>R$2),3, IF(AND($F8<=R$2, $H8>=R$2), 2, "" ))) | S8: =IF(AND($F8<(S$2+7),$F8>S$2),1, IF(AND($H8<S$2+7,$H8>S$2),3, IF(AND($F8<=S$2, $H8>=S$2), 2, "" ))) | ... AQ8: =IF(AND($F8<(AQ$2+7),$F8>AQ$2),1, IF(AND($H8<AQ$2+7,$H8>AQ$2),3, IF(AND($F8<=AQ$2, $H8>=AQ$2), 2, "" )))
B9: Inverter Procurement | C9: 43941 | D9: 5 | E9: 43949 | F9: 43941 | G9: 5 | H9: 43949 | L9: =IF(AND($F9<(L$2+7),$F9>L$2),1, IF(AND($H9<L$2+7,$H9>L$2),3, IF(AND($F9<=L$2, $H9>=L$2), 2, "" ))) | M9: =IF(AND($F9<(M$2+7),$F9>M$2),1, IF(AND($H9<M$2+7,$H9>M$2),3, IF(AND($F9<=M$2, $H9>=M$2), 2, "" ))) | N9: =IF(AND($F9<(N$2+7),$F9>N$2),1, IF(AND($H9<N$2+7,$H9>N$2),3, IF(AND($F9<=N$2, $H9>=N$2), 2, "" ))) | O9: =IF(AND($F9<(O$2+7),$F9>O$2),1, IF(AND($H9<O$2+7,$H9>O$2),3, IF(AND($F9<=O$2, $H9>=O$2), 2, "" ))) | P9: =IF(AND($F9<(P$2+7),$F9>P$2),1, IF(AND($H9<P$2+7,$H9>P$2),3, IF(AND($F9<=P$2, $H9>=P$2), 2, "" ))) | Q9: =IF(AND($F9<(Q$2+7),$F9>Q$2),1, IF(AND($H9<Q$2+7,$H9>Q$2),3, IF(AND($F9<=Q$2, $H9>=Q$2), 2, "" ))) | R9: =IF(AND($F9<(R$2+7),$F9>R$2),1, IF(AND($H9<R$2+7,$H9>R$2),3, IF(AND($F9<=R$2, $H9>=R$2), 2, "" ))) | S9: =IF(AND($F9<(S$2+7),$F9>S$2),1, IF(AND($H9<S$2+7,$H9>S$2),3, IF(AND($F9<=S$2, $H9>=S$2), 2, "" ))) | ... AQ9: =IF(AND($F9<(AQ$2+7),$F9>AQ$2),1, IF(AND($H9<AQ$2+7,$H9>AQ$2),3, IF(AND($F9<=AQ$2, $H9>=AQ$2), 2, "" )))
B10: Mounting Structure Procurement | C10: 43941 | D10: 5 | E10: 43949 | F10: 43941 | G10: 5 | H10: 43949 | L10: =IF(AND($F10<(L$2+7),$F10>L$2),1, IF(AND($H10<L$2+7,$H10>L$2),3, IF(AND($F10<=L$2, $H10>=L$2), 2, "" ))) | M10: =IF(AND($F10<(M$2+7),$F10>M$2),1, IF(AND($H10<M$2+7,$H10>M$2),3, IF(AND($F10<=M$2, $H10>=M$2), 2, "" ))) | N10: =IF(AND($F10<(N$2+7),$F10>N$2),1, IF(AND($H10<N$2+7,$H10>N$2),3, IF(AND($F10<=N$2, $H10>=N$2), 2, "" ))) | O10: =IF(AND($F10<(O$2+7),$F10>O$2),1, IF(AND($H10<O$2+7,$H10>O$2),3, IF(AND($F10<=O$2, $H10>=O$2), 2, "" ))) | P10: =IF(AND($F10<(P$2+7),$F10>P$2),1, IF(AND($H10<P$2+7,$H10>P$2),3, IF(AND($F10<=P$2, $H10>=P$2), 2, "" ))) | Q10: =IF(AND($F10<(Q$2+7),$F10>Q$2),1, IF(AND($H10<Q$2+7,$H10>Q$2),3, IF(AND($F10<=Q$2, $H10>=Q$2), 2, "" ))) | R10: =IF(AND($F10<(R$2+7),$F10>R$2),1, IF(AND($H10<R$2+7,$H10>R$2),3, IF(AND($F10<=R$2, $H10>=R$2), 2, "" ))) | S10: =IF(AND($F10<(S$2+7),$F10>S$2),1, IF(AND($H10<S$2+7,$H10>S$2),3, IF(AND($F10<=S$2, $H10>=S$2), 2, "" ))) | ... AQ10: =IF(AND($F10<(AQ$2+7),$F10>AQ$2),1, IF(AND($H10<AQ$2+7,$H10>AQ$2),3, IF(AND($F10<=AQ$2, $H10>=AQ$2), 2, "" )))
B11: BOS Procurement | C11: 43941 | D11: 5 | E11: 43949 | F11: 43941 | G11: 5 | H11: 43949 | L11: =IF(AND($F11<(L$2+7),$F11>L$2),1, IF(AND($H11<L$2+7,$H11>L$2),3, IF(AND($F11<=L$2, $H11>=L$2), 2, "" ))) | M11: =IF(AND($F11<(M$2+7),$F11>M$2),1, IF(AND($H11<M$2+7,$H11>M$2),3, IF(AND($F11<=M$2, $H11>=M$2), 2, "" ))) | N11: =IF(AND($F11<(N$2+7),$F11>N$2),1, IF(AND($H11<N$2+7,$H11>N$2),3, IF(AND($F11<=N$2, $H11>=N$2), 2, "" ))) | O11: =IF(AND($F11<(O$2+7),$F11>O$2),1, IF(AND($H11<O$2+7,$H11>O$2),3, IF(AND($F11<=O$2, $H11>=O$2), 2, "" ))) | P11: =IF(AND($F11<(P$2+7),$F11>P$2),1, IF(AND($H11<P$2+7,$H11>P$2),3, IF(AND($F11<=P$2, $H11>=P$2), 2, "" ))) | Q11: =IF(AND($F11<(Q$2+7),$F11>Q$2),1, IF(AND($H11<Q$2+7,$H11>Q$2),3, IF(AND($F11<=Q$2, $H11>=Q$2), 2, "" ))) | R11: =IF(AND($F11<(R$2+7),$F11>R$2),1, IF(AND($H11<R$2+7,$H11>R$2),3, IF(AND($F11<=R$2, $H11>=R$2), 2, "" ))) | S11: =IF(AND($F11<(S$2+7),$F11>S$2),1, IF(AND($H11<S$2+7,$H11>S$2),3, IF(AND($F11<=S$2, $H11>=S$2), 2, "" ))) | ... AQ11: =IF(AND($F11<(AQ$2+7),$F11>AQ$2),1, IF(AND($H11<AQ$2+7,$H11>AQ$2),3, IF(AND($F11<=AQ$2, $H11>=AQ$2), 2, "" )))
A12: 5 | B12: Internal Project Kick off | C12: 43936 | D12: 5 | E12: 43943 | F12: 43936 | G12: 5 | H12: 43943
A13: 6 | B13: Client Project Kick-off | C13: 43963 | D13: 5 | E13: 43970 | F13: 43963 | G13: 5 | H13: 43970 | L13: =IF(AND($F13<(L$2+7),$F13>L$2),1, IF(AND($H13<L$2+7,$H13>L$2),3, IF(AND($F13<=L$2, $H13>=L$2), 2, "" ))) | M13: =IF(AND($F13<(M$2+7),$F13>M$2),1, IF(AND($H13<M$2+7,$H13>M$2),3, IF(AND($F13<=M$2, $H13>=M$2), 2, "" ))) | N13: =IF(AND($F13<(N$2+7),$F13>N$2),1, IF(AND($H13<N$2+7,$H13>N$2),3, IF(AND($F13<=N$2, $H13>=N$2), 2, "" ))) | O13: =IF(AND($F13<(O$2+7),$F13>O$2),1, IF(AND($H13<O$2+7,$H13>O$2),3, IF(AND($F13<=O$2, $H13>=O$2), 2, "" ))) | P13: =IF(AND($F13<(P$2+7),$F13>P$2),1, IF(AND($H13<P$2+7,$H13>P$2),3, IF(AND($F13<=P$2, $H13>=P$2), 2, "" ))) | Q13: =IF(AND($F13<(Q$2+7),$F13>Q$2),1, IF(AND($H13<Q$2+7,$H13>Q$2),3, IF(AND($F13<=Q$2, $H13>=Q$2), 2, "" ))) | R13: =IF(AND($F13<(R$2+7),$F13>R$2),1, IF(AND($H13<R$2+7,$H13>R$2),3, IF(AND($F13<=R$2, $H13>=R$2), 2, "" ))) | S13: =IF(AND($F13<(S$2+7),$F13>S$2),1, IF(AND($H13<S$2+7,$H13>S$2),3, IF(AND($F13<=S$2, $H13>=S$2), 2, "" ))) | ... AQ13: =IF(AND($F13<(AQ$2+7),$F13>AQ$2),1, IF(AND($H13<AQ$2+7,$H13>AQ$2),3, IF(AND($F13<=AQ$2, $H13>=AQ$2), 2, "" )))
A14: 7 | B14: Equipment Delivery | C14: 43983 | D14: 9 | E14: 43994 | F14: 43983 | G14: 9 | H14: 43994 | L14: =IF(AND($F14<(L$2+7),$F14>L$2),1, IF(AND($H14<L$2+7,$H14>L$2),3, IF(AND($F14<=L$2, $H14>=L$2), 2, "" ))) | M14: =IF(AND($F14<(M$2+7),$F14>M$2),1, IF(AND($H14<M$2+7,$H14>M$2),3, IF(AND($F14<=M$2, $H14>=M$2), 2, "" ))) | N14: =IF(AND($F14<(N$2+7),$F14>N$2),1, IF(AND($H14<N$2+7,$H14>N$2),3, IF(AND($F14<=N$2, $H14>=N$2), 2, "" ))) | O14: =IF(AND($F14<(O$2+7),$F14>O$2),1, IF(AND($H14<O$2+7,$H14>O$2),3, IF(AND($F14<=O$2, $H14>=O$2), 2, "" ))) | P14: =IF(AND($F14<(P$2+7),$F14>P$2),1, IF(AND($H14<P$2+7,$H14>P$2),3, IF(AND($F14<=P$2, $H14>=P$2), 2, "" ))) | Q14: =IF(AND($F14<(Q$2+7),$F14>Q$2),1, IF(AND($H14<Q$2+7,$H14>Q$2),3, IF(AND($F14<=Q$2, $H14>=Q$2), 2, "" ))) | R14: =IF(AND($F14<(R$2+7),$F14>R$2),1, IF(AND($H14<R$2+7,$H14>R$2),3, IF(AND($F14<=R$2, $H14>=R$2), 2, "" ))) | S14: =IF(AND($F14<(S$2+7),$F14>S$2),1, IF(AND($H14<S$2+7,$H14>S$2),3, IF(AND($F14<=S$2, $H14>=S$2), 2, "" ))) | ... AQ14: =IF(AND($F14<(AQ$2+7),$F14>AQ$2),1, IF(AND($H14<AQ$2+7,$H14>AQ$2),3, IF(AND($F14<=AQ$2, $H14>=AQ$2), 2, "" )))
B15: Mounting Structure Delivery | C15: 43983 | D15: 2 | E15: 43985 | F15: 43983 | G15: 2 | H15: 43985
B16: Panel Delivery | C16: 43990 | D16: 2 | E16: 43992 | F16: 43990 | G16: 2 | H16: 43992 | L16: =IF(AND($F16<(L$2+7),$F16>L$2),1, IF(AND($H16<L$2+7,$H16>L$2),3, IF(AND($F16<=L$2, $H16>=L$2), 2, "" ))) | M16: =IF(AND($F16<(M$2+7),$F16>M$2),1, IF(AND($H16<M$2+7,$H16>M$2),3, IF(AND($F16<=M$2, $H16>=M$2), 2, "" ))) | N16: =IF(AND($F16<(N$2+7),$F16>N$2),1, IF(AND($H16<N$2+7,$H16>N$2),3, IF(AND($F16<=N$2, $H16>=N$2), 2, "" ))) | O16: =IF(AND($F16<(O$2+7),$F16>O$2),1, IF(AND($H16<O$2+7,$H16>O$2),3, IF(AND($F16<=O$2, $H16>=O$2), 2, "" ))) | P16: =IF(AND($F16<(P$2+7),$F16>P$2),1, IF(AND($H16<P$2+7,$H16>P$2),3, IF(AND($F16<=P$2, $H16>=P$2), 2, "" ))) | Q16: =IF(AND($F16<(Q$2+7),$F16>Q$2),1, IF(AND($H16<Q$2+7,$H16>Q$2),3, IF(AND($F16<=Q$2, $H16>=Q$2), 2, "" ))) | R16: =IF(AND($F16<(R$2+7),$F16>R$2),1, IF(AND($H16<R$2+7,$H16>R$2),3, IF(AND($F16<=R$2, $H16>=R$2), 2, "" ))) | S16: =IF(AND($F16<(S$2+7),$F16>S$2),1, IF(AND($H16<S$2+7,$H16>S$2),3, IF(AND($F16<=S$2, $H16>=S$2), 2, "" ))) | ... AQ16: =IF(AND($F16<(AQ$2+7),$F16>AQ$2),1, IF(AND($H16<AQ$2+7,$H16>AQ$2),3, IF(AND($F16<=AQ$2, $H16>=AQ$2), 2, "" )))
B17: Generator Delivery | C17: 43983 | D17: 2 | E17: 43985 | F17: 43983 | G17: 2 | H17: 43985
A18: B | B18: PAYMENT MILESTONE 2: DELIVERY OF PV PANELS | C18: 43992 | D18: 2 | E18: 43994 | F18: 43992 | G18: 2 | H18: 43994
B19: Inverter Delivery | C19: 43983 | D19: 2 | E19: 43985 | F19: 43983 | G19: 2 | H19: 43985 | L19: =IF(AND($F19<(L$2+7),$F19>L$2),1, IF(AND($H19<L$2+7,$H19>L$2),3, IF(AND($F19<=L$2, $H19>=L$2), 2, "" ))) | M19: =IF(AND($F19<(M$2+7),$F19>M$2),1, IF(AND($H19<M$2+7,$H19>M$2),3, IF(AND($F19<=M$2, $H19>=M$2), 2, "" ))) | N19: =IF(AND($F19<(N$2+7),$F19>N$2),1, IF(AND($H19<N$2+7,$H19>N$2),3, IF(AND($F19<=N$2, $H19>=N$2), 2, "" ))) | O19: =IF(AND($F19<(O$2+7),$F19>O$2),1, IF(AND($H19<O$2+7,$H19>O$2),3, IF(AND($F19<=O$2, $H19>=O$2), 2, "" ))) | P19: =IF(AND($F19<(P$2+7),$F19>P$2),1, IF(AND($H19<P$2+7,$H19>P$2),3, IF(AND($F19<=P$2, $H19>=P$2), 2, "" ))) | Q19: =IF(AND($F19<(Q$2+7),$F19>Q$2),1, IF(AND($H19<Q$2+7,$H19>Q$2),3, IF(AND($F19<=Q$2, $H19>=Q$2), 2, "" ))) | R19: =IF(AND($F19<(R$2+7),$F19>R$2),1, IF(AND($H19<R$2+7,$H19>R$2),3, IF(AND($F19<=R$2, $H19>=R$2), 2, "" ))) | S19: =IF(AND($F19<(S$2+7),$F19>S$2),1, IF(AND($H19<S$2+7,$H19>S$2),3, IF(AND($F19<=S$2, $H19>=S$2), 2, "" ))) | ... AQ19: =IF(AND($F19<(AQ$2+7),$F19>AQ$2),1, IF(AND($H19<AQ$2+7,$H19>AQ$2),3, IF(AND($F19<=AQ$2, $H19>=AQ$2), 2, "" )))
B20: BOS Delivery | C20: 43983 | D20: 1 | E20: 43984 | F20: 43983 | G20: 1 | H20: 43984 | L20: =IF(AND($F20<(L$2+7),$F20>L$2),1, IF(AND($H20<L$2+7,$H20>L$2),3, IF(AND($F20<=L$2, $H20>=L$2), 2, "" ))) | M20: =IF(AND($F20<(M$2+7),$F20>M$2),1, IF(AND($H20<M$2+7,$H20>M$2),3, IF(AND($F20<=M$2, $H20>=M$2), 2, "" ))) | N20: =IF(AND($F20<(N$2+7),$F20>N$2),1, IF(AND($H20<N$2+7,$H20>N$2),3, IF(AND($F20<=N$2, $H20>=N$2), 2, "" ))) | O20: =IF(AND($F20<(O$2+7),$F20>O$2),1, IF(AND($H20<O$2+7,$H20>O$2),3, IF(AND($F20<=O$2, $H20>=O$2), 2, "" ))) | P20: =IF(AND($F20<(P$2+7),$F20>P$2),1, IF(AND($H20<P$2+7,$H20>P$2),3, IF(AND($F20<=P$2, $H20>=P$2), 2, "" ))) | Q20: =IF(AND($F20<(Q$2+7),$F20>Q$2),1, IF(AND($H20<Q$2+7,$H20>Q$2),3, IF(AND($F20<=Q$2, $H20>=Q$2), 2, "" ))) | R20: =IF(AND($F20<(R$2+7),$F20>R$2),1, IF(AND($H20<R$2+7,$H20>R$2),3, IF(AND($F20<=R$2, $H20>=R$2), 2, "" ))) | S20: =IF(AND($F20<(S$2+7),$F20>S$2),1, IF(AND($H20<S$2+7,$H20>S$2),3, IF(AND($F20<=S$2, $H20>=S$2), 2, "" ))) | ... AQ20: =IF(AND($F20<(AQ$2+7),$F20>AQ$2),1, IF(AND($H20<AQ$2+7,$H20>AQ$2),3, IF(AND($F20<=AQ$2, $H20>=AQ$2), 2, "" )))
A21: C | B21: PAYMENT MILESTONE 3: DELIVERY OF INVERTERS AND BOS | C21: 43985 | D21: 2 | E21: 43987 | F21: 43985 | G21: 2 | H21: 43987
A22: 8 | B22: Installation | C22: 43990 | D22: 22 | E22: 44012 | F22: 43990 | G22: 22 | H22: 44012 | L22: =IF(AND($F22<(L$2+7),$F22>L$2),1, IF(AND($H22<L$2+7,$H22>L$2),3, IF(AND($F22<=L$2, $H22>=L$2), 2, "" ))) | M22: =IF(AND($F22<(M$2+7),$F22>M$2),1, IF(AND($H22<M$2+7,$H22>M$2),3, IF(AND($F22<=M$2, $H22>=M$2), 2, "" ))) | N22: =IF(AND($F22<(N$2+7),$F22>N$2),1, IF(AND($H22<N$2+7,$H22>N$2),3, IF(AND($F22<=N$2, $H22>=N$2), 2, "" ))) | O22: =IF(AND($F22<(O$2+7),$F22>O$2),1, IF(AND($H22<O$2+7,$H22>O$2),3, IF(AND($F22<=O$2, $H22>=O$2), 2, "" ))) | P22: =IF(AND($F22<(P$2+7),$F22>P$2),1, IF(AND($H22<P$2+7,$H22>P$2),3, IF(AND($F22<=P$2, $H22>=P$2), 2, "" ))) | Q22: =IF(AND($F22<(Q$2+7),$F22>Q$2),1, IF(AND($H22<Q$2+7,$H22>Q$2),3, IF(AND($F22<=Q$2, $H22>=Q$2), 2, "" ))) | R22: =IF(AND($F22<(R$2+7),$F22>R$2),1, IF(AND($H22<R$2+7,$H22>R$2),3, IF(AND($F22<=R$2, $H22>=R$2), 2, "" ))) | S22: =IF(AND($F22<(S$2+7),$F22>S$2),1, IF(AND($H22<S$2+7,$H22>S$2),3, IF(AND($F22<=S$2, $H22>=S$2), 2, "" ))) | ... AQ22: =IF(AND($F22<(AQ$2+7),$F22>AQ$2),1, IF(AND($H22<AQ$2+7,$H22>AQ$2),3, IF(AND($F22<=AQ$2, $H22>=AQ$2), 2, "" ))) -> 2
B23: Site Establishment | C23: 43990 | D23: 1 | E23: 43991 | F23: 43990 | G23: 1 | H23: 43991 | J23: Installation placed on hold due to Covid-19 case | L23: =IF(AND($F23<(L$2+7),$F23>L$2),1, IF(AND($H23<L$2+7,$H23>L$2),3, IF(AND($F23<=L$2, $H23>=L$2), 2, "" ))) | M23: =IF(AND($F23<(M$2+7),$F23>M$2),1, IF(AND($H23<M$2+7,$H23>M$2),3, IF(AND($F23<=M$2, $H23>=M$2), 2, "" ))) | N23: =IF(AND($F23<(N$2+7),$F23>N$2),1, IF(AND($H23<N$2+7,$H23>N$2),3, IF(AND($F23<=N$2, $H23>=N$2), 2, "" ))) | O23: =IF(AND($F23<(O$2+7),$F23>O$2),1, IF(AND($H23<O$2+7,$H23>O$2),3, IF(AND($F23<=O$2, $H23>=O$2), 2, "" ))) | P23: =IF(AND($F23<(P$2+7),$F23>P$2),1, IF(AND($H23<P$2+7,$H23>P$2),3, IF(AND($F23<=P$2, $H23>=P$2), 2, "" ))) | Q23: =IF(AND($F23<(Q$2+7),$F23>Q$2),1, IF(AND($H23<Q$2+7,$H23>Q$2),3, IF(AND($F23<=Q$2, $H23>=Q$2), 2, "" ))) | R23: =IF(AND($F23<(R$2+7),$F23>R$2),1, IF(AND($H23<R$2+7,$H23>R$2),3, IF(AND($F23<=R$2, $H23>=R$2), 2, "" ))) | S23: =IF(AND($F23<(S$2+7),$F23>S$2),1, IF(AND($H23<S$2+7,$H23>S$2),3, IF(AND($F23<=S$2, $H23>=S$2), 2, "" ))) | ... AQ23: =IF(AND($F23<(AQ$2+7),$F23>AQ$2),1, IF(AND($H23<AQ$2+7,$H23>AQ$2),3, IF(AND($F23<=AQ$2, $H23>=AQ$2), 2, "" )))
A24: 9 | B24: DC Works | C24: 43991 | D24: 16 | E24: 44012 | F24: 43991 | G24: 16 | H24: 44012 | L24: =IF(AND($F24<(L$2+7),$F24>L$2),1, IF(AND($H24<L$2+7,$H24>L$2),3, IF(AND($F24<=L$2, $H24>=L$2), 2, "" ))) | M24: =IF(AND($F24<(M$2+7),$F24>M$2),1, IF(AND($H24<M$2+7,$H24>M$2),3, IF(AND($F24<=M$2, $H24>=M$2), 2, "" ))) | N24: =IF(AND($F24<(N$2+7),$F24>N$2),1, IF(AND($H24<N$2+7,$H24>N$2),3, IF(AND($F24<=N$2, $H24>=N$2), 2, "" ))) | O24: =IF(AND($F24<(O$2+7),$F24>O$2),1, IF(AND($H24<O$2+7,$H24>O$2),3, IF(AND($F24<=O$2, $H24>=O$2), 2, "" ))) | P24: =IF(AND($F24<(P$2+7),$F24>P$2),1, IF(AND($H24<P$2+7,$H24>P$2),3, IF(AND($F24<=P$2, $H24>=P$2), 2, "" ))) | Q24: =IF(AND($F24<(Q$2+7),$F24>Q$2),1, IF(AND($H24<Q$2+7,$H24>Q$2),3, IF(AND($F24<=Q$2, $H24>=Q$2), 2, "" ))) | R24: =IF(AND($F24<(R$2+7),$F24>R$2),1, IF(AND($H24<R$2+7,$H24>R$2),3, IF(AND($F24<=R$2, $H24>=R$2), 2, "" ))) | S24: =IF(AND($F24<(S$2+7),$F24>S$2),1, IF(AND($H24<S$2+7,$H24>S$2),3, IF(AND($F24<=S$2, $H24>=S$2), 2, "" ))) | ... AQ24: =IF(AND($F24<(AQ$2+7),$F24>AQ$2),1, IF(AND($H24<AQ$2+7,$H24>AQ$2),3, IF(AND($F24<=AQ$2, $H24>=AQ$2), 2, "" ))) -> 2
B25: Mounting structure Installation | C25: 43991 | D25: 4 | E25: 43997 | F25: 43991 | G25: 4 | H25: 43997 | L25: =IF(AND($F25<(L$2+7),$F25>L$2),1, IF(AND($H25<L$2+7,$H25>L$2),3, IF(AND($F25<=L$2, $H25>=L$2), 2, "" ))) | M25: =IF(AND($F25<(M$2+7),$F25>M$2),1, IF(AND($H25<M$2+7,$H25>M$2),3, IF(AND($F25<=M$2, $H25>=M$2), 2, "" ))) | N25: =IF(AND($F25<(N$2+7),$F25>N$2),1, IF(AND($H25<N$2+7,$H25>N$2),3, IF(AND($F25<=N$2, $H25>=N$2), 2, "" ))) | O25: =IF(AND($F25<(O$2+7),$F25>O$2),1, IF(AND($H25<O$2+7,$H25>O$2),3, IF(AND($F25<=O$2, $H25>=O$2), 2, "" ))) | P25: =IF(AND($F25<(P$2+7),$F25>P$2),1, IF(AND($H25<P$2+7,$H25>P$2),3, IF(AND($F25<=P$2, $H25>=P$2), 2, "" ))) | Q25: =IF(AND($F25<(Q$2+7),$F25>Q$2),1, IF(AND($H25<Q$2+7,$H25>Q$2),3, IF(AND($F25<=Q$2, $H25>=Q$2), 2, "" ))) | R25: =IF(AND($F25<(R$2+7),$F25>R$2),1, IF(AND($H25<R$2+7,$H25>R$2),3, IF(AND($F25<=R$2, $H25>=R$2), 2, "" ))) | S25: =IF(AND($F25<(S$2+7),$F25>S$2),1, IF(AND($H25<S$2+7,$H25>S$2),3, IF(AND($F25<=S$2, $H25>=S$2), 2, "" ))) | ... AQ25: =IF(AND($F25<(AQ$2+7),$F25>AQ$2),1, IF(AND($H25<AQ$2+7,$H25>AQ$2),3, IF(AND($F25<=AQ$2, $H25>=AQ$2), 2, "" )))
B26: Cable tray Installation | C26: 43997 | D26: 3 | E26: 44004 | F26: 43997 | G26: 3 | H26: 44004 | L26: =IF(AND($F26<(L$2+7),$F26>L$2),1, IF(AND($H26<L$2+7,$H26>L$2),3, IF(AND($F26<=L$2, $H26>=L$2), 2, "" ))) | M26: =IF(AND($F26<(M$2+7),$F26>M$2),1, IF(AND($H26<M$2+7,$H26>M$2),3, IF(AND($F26<=M$2, $H26>=M$2), 2, "" ))) | N26: =IF(AND($F26<(N$2+7),$F26>N$2),1, IF(AND($H26<N$2+7,$H26>N$2),3, IF(AND($F26<=N$2, $H26>=N$2), 2, "" ))) | O26: =IF(AND($F26<(O$2+7),$F26>O$2),1, IF(AND($H26<O$2+7,$H26>O$2),3, IF(AND($F26<=O$2, $H26>=O$2), 2, "" ))) | P26: =IF(AND($F26<(P$2+7),$F26>P$2),1, IF(AND($H26<P$2+7,$H26>P$2),3, IF(AND($F26<=P$2, $H26>=P$2), 2, "" ))) | Q26: =IF(AND($F26<(Q$2+7),$F26>Q$2),1, IF(AND($H26<Q$2+7,$H26>Q$2),3, IF(AND($F26<=Q$2, $H26>=Q$2), 2, "" ))) | R26: =IF(AND($F26<(R$2+7),$F26>R$2),1, IF(AND($H26<R$2+7,$H26>R$2),3, IF(AND($F26<=R$2, $H26>=R$2), 2, "" ))) | S26: =IF(AND($F26<(S$2+7),$F26>S$2),1, IF(AND($H26<S$2+7,$H26>S$2),3, IF(AND($F26<=S$2, $H26>=S$2), 2, "" ))) | ... AQ26: =IF(AND($F26<(AQ$2+7),$F26>AQ$2),1, IF(AND($H26<AQ$2+7,$H26>AQ$2),3, IF(AND($F26<=AQ$2, $H26>=AQ$2), 2, "" )))
B27: DC Cable Installation | C27: 44004 | D27: 2 | E27: 44006 | F27: 44004 | G27: 2 | H27: 44006 | L27: =IF(AND($F27<(L$2+7),$F27>L$2),1, IF(AND($H27<L$2+7,$H27>L$2),3, IF(AND($F27<=L$2, $H27>=L$2), 2, "" ))) | M27: =IF(AND($F27<(M$2+7),$F27>M$2),1, IF(AND($H27<M$2+7,$H27>M$2),3, IF(AND($F27<=M$2, $H27>=M$2), 2, "" ))) | N27: =IF(AND($F27<(N$2+7),$F27>N$2),1, IF(AND($H27<N$2+7,$H27>N$2),3, IF(AND($F27<=N$2, $H27>=N$2), 2, "" ))) | O27: =IF(AND($F27<(O$2+7),$F27>O$2),1, IF(AND($H27<O$2+7,$H27>O$2),3, IF(AND($F27<=O$2, $H27>=O$2), 2, "" ))) | P27: =IF(AND($F27<(P$2+7),$F27>P$2),1, IF(AND($H27<P$2+7,$H27>P$2),3, IF(AND($F27<=P$2, $H27>=P$2), 2, "" ))) | Q27: =IF(AND($F27<(Q$2+7),$F27>Q$2),1, IF(AND($H27<Q$2+7,$H27>Q$2),3, IF(AND($F27<=Q$2, $H27>=Q$2), 2, "" ))) | R27: =IF(AND($F27<(R$2+7),$F27>R$2),1, IF(AND($H27<R$2+7,$H27>R$2),3, IF(AND($F27<=R$2, $H27>=R$2), 2, "" ))) | S27: =IF(AND($F27<(S$2+7),$F27>S$2),1, IF(AND($H27<S$2+7,$H27>S$2),3, IF(AND($F27<=S$2, $H27>=S$2), 2, "" ))) | ... AQ27: =IF(AND($F27<(AQ$2+7),$F27>AQ$2),1, IF(AND($H27<AQ$2+7,$H27>AQ$2),3, IF(AND($F27<=AQ$2, $H27>=AQ$2), 2, "" )))
B28: Module Installation | C28: 44006 | D28: 4 | E28: 44012 | F28: 44006 | G28: 4 | H28: 44012 | L28: =IF(AND($F28<(L$2+7),$F28>L$2),1, IF(AND($H28<L$2+7,$H28>L$2),3, IF(AND($F28<=L$2, $H28>=L$2), 2, "" ))) | M28: =IF(AND($F28<(M$2+7),$F28>M$2),1, IF(AND($H28<M$2+7,$H28>M$2),3, IF(AND($F28<=M$2, $H28>=M$2), 2, "" ))) | N28: =IF(AND($F28<(N$2+7),$F28>N$2),1, IF(AND($H28<N$2+7,$H28>N$2),3, IF(AND($F28<=N$2, $H28>=N$2), 2, "" ))) | O28: =IF(AND($F28<(O$2+7),$F28>O$2),1, IF(AND($H28<O$2+7,$H28>O$2),3, IF(AND($F28<=O$2, $H28>=O$2), 2, "" ))) | P28: =IF(AND($F28<(P$2+7),$F28>P$2),1, IF(AND($H28<P$2+7,$H28>P$2),3, IF(AND($F28<=P$2, $H28>=P$2), 2, "" ))) | Q28: =IF(AND($F28<(Q$2+7),$F28>Q$2),1, IF(AND($H28<Q$2+7,$H28>Q$2),3, IF(AND($F28<=Q$2, $H28>=Q$2), 2, "" ))) | R28: =IF(AND($F28<(R$2+7),$F28>R$2),1, IF(AND($H28<R$2+7,$H28>R$2),3, IF(AND($F28<=R$2, $H28>=R$2), 2, "" ))) | S28: =IF(AND($F28<(S$2+7),$F28>S$2),1, IF(AND($H28<S$2+7,$H28>S$2),3, IF(AND($F28<=S$2, $H28>=S$2), 2, "" ))) | ... AQ28: =IF(AND($F28<(AQ$2+7),$F28>AQ$2),1, IF(AND($H28<AQ$2+7,$H28>AQ$2),3, IF(AND($F28<=AQ$2, $H28>=AQ$2), 2, "" ))) -> 2
B29: Earth Cable Installation | C29: 44004 | D29: 1 | E29: 44005 | F29: 44004 | G29: 1 | H29: 44005 | L29: =IF(AND($F29<(L$2+7),$F29>L$2),1, IF(AND($H29<L$2+7,$H29>L$2),3, IF(AND($F29<=L$2, $H29>=L$2), 2, "" ))) | M29: =IF(AND($F29<(M$2+7),$F29>M$2),1, IF(AND($H29<M$2+7,$H29>M$2),3, IF(AND($F29<=M$2, $H29>=M$2), 2, "" ))) | N29: =IF(AND($F29<(N$2+7),$F29>N$2),1, IF(AND($H29<N$2+7,$H29>N$2),3, IF(AND($F29<=N$2, $H29>=N$2), 2, "" ))) | O29: =IF(AND($F29<(O$2+7),$F29>O$2),1, IF(AND($H29<O$2+7,$H29>O$2),3, IF(AND($F29<=O$2, $H29>=O$2), 2, "" ))) | P29: =IF(AND($F29<(P$2+7),$F29>P$2),1, IF(AND($H29<P$2+7,$H29>P$2),3, IF(AND($F29<=P$2, $H29>=P$2), 2, "" ))) | Q29: =IF(AND($F29<(Q$2+7),$F29>Q$2),1, IF(AND($H29<Q$2+7,$H29>Q$2),3, IF(AND($F29<=Q$2, $H29>=Q$2), 2, "" ))) | R29: =IF(AND($F29<(R$2+7),$F29>R$2),1, IF(AND($H29<R$2+7,$H29>R$2),3, IF(AND($F29<=R$2, $H29>=R$2), 2, "" ))) | S29: =IF(AND($F29<(S$2+7),$F29>S$2),1, IF(AND($H29<S$2+7,$H29>S$2),3, IF(AND($F29<=S$2, $H29>=S$2), 2, "" ))) | ... AQ29: =IF(AND($F29<(AQ$2+7),$F29>AQ$2),1, IF(AND($H29<AQ$2+7,$H29>AQ$2),3, IF(AND($F29<=AQ$2, $H29>=AQ$2), 2, "" )))
A30: 10 | B30: AC Works | C30: 43991 | D30: 8 | E30: 44000 | F30: 43991 | G30: 8 | H30: 44000
B31: Inverters Installation | C31: 43991 | D31: 2 | E31: 43993 | F31: 43991 | G31: 2 | H31: 43993 | L31: =IF(AND($F31<(L$2+7),$F31>L$2),1, IF(AND($H31<L$2+7,$H31>L$2),3, IF(AND($F31<=L$2, $H31>=L$2), 2, "" ))) | M31: =IF(AND($F31<(M$2+7),$F31>M$2),1, IF(AND($H31<M$2+7,$H31>M$2),3, IF(AND($F31<=M$2, $H31>=M$2), 2, "" ))) | N31: =IF(AND($F31<(N$2+7),$F31>N$2),1, IF(AND($H31<N$2+7,$H31>N$2),3, IF(AND($F31<=N$2, $H31>=N$2), 2, "" ))) | O31: =IF(AND($F31<(O$2+7),$F31>O$2),1, IF(AND($H31<O$2+7,$H31>O$2),3, IF(AND($F31<=O$2, $H31>=O$2), 2, "" ))) | P31: =IF(AND($F31<(P$2+7),$F31>P$2),1, IF(AND($H31<P$2+7,$H31>P$2),3, IF(AND($F31<=P$2, $H31>=P$2), 2, "" ))) | Q31: =IF(AND($F31<(Q$2+7),$F31>Q$2),1, IF(AND($H31<Q$2+7,$H31>Q$2),3, IF(AND($F31<=Q$2, $H31>=Q$2), 2, "" ))) | R31: =IF(AND($F31<(R$2+7),$F31>R$2),1, IF(AND($H31<R$2+7,$H31>R$2),3, IF(AND($F31<=R$2, $H31>=R$2), 2, "" ))) | S31: =IF(AND($F31<(S$2+7),$F31>S$2),1, IF(AND($H31<S$2+7,$H31>S$2),3, IF(AND($F31<=S$2, $H31>=S$2), 2, "" ))) | ... AQ31: =IF(AND($F31<(AQ$2+7),$F31>AQ$2),1, IF(AND($H31<AQ$2+7,$H31>AQ$2),3, IF(AND($F31<=AQ$2, $H31>=AQ$2), 2, "" )))
B32: AC BOS Installation | C32: 43993 | D32: 3 | E32: 44000 | F32: 43993 | G32: 3 | H32: 44000 | L32: =IF(AND($F32<(L$2+7),$F32>L$2),1, IF(AND($H32<L$2+7,$H32>L$2),3, IF(AND($F32<=L$2, $H32>=L$2), 2, "" ))) | M32: =IF(AND($F32<(M$2+7),$F32>M$2),1, IF(AND($H32<M$2+7,$H32>M$2),3, IF(AND($F32<=M$2, $H32>=M$2), 2, "" ))) | N32: =IF(AND($F32<(N$2+7),$F32>N$2),1, IF(AND($H32<N$2+7,$H32>N$2),3, IF(AND($F32<=N$2, $H32>=N$2), 2, "" ))) | O32: =IF(AND($F32<(O$2+7),$F32>O$2),1, IF(AND($H32<O$2+7,$H32>O$2),3, IF(AND($F32<=O$2, $H32>=O$2), 2, "" ))) | P32: =IF(AND($F32<(P$2+7),$F32>P$2),1, IF(AND($H32<P$2+7,$H32>P$2),3, IF(AND($F32<=P$2, $H32>=P$2), 2, "" ))) | Q32: =IF(AND($F32<(Q$2+7),$F32>Q$2),1, IF(AND($H32<Q$2+7,$H32>Q$2),3, IF(AND($F32<=Q$2, $H32>=Q$2), 2, "" ))) | R32: =IF(AND($F32<(R$2+7),$F32>R$2),1, IF(AND($H32<R$2+7,$H32>R$2),3, IF(AND($F32<=R$2, $H32>=R$2), 2, "" ))) | S32: =IF(AND($F32<(S$2+7),$F32>S$2),1, IF(AND($H32<S$2+7,$H32>S$2),3, IF(AND($F32<=S$2, $H32>=S$2), 2, "" ))) | ... AQ32: =IF(AND($F32<(AQ$2+7),$F32>AQ$2),1, IF(AND($H32<AQ$2+7,$H32>AQ$2),3, IF(AND($F32<=AQ$2, $H32>=AQ$2), 2, "" )))
B33: AC Cable/Tie-In | C33: 43992 | D33: 3 | E33: 43997 | F33: 43992 | G33: 3 | H33: 43997 | L33: =IF(AND($F33<(L$2+7),$F33>L$2),1, IF(AND($H33<L$2+7,$H33>L$2),3, IF(AND($F33<=L$2, $H33>=L$2), 2, "" ))) | M33: =IF(AND($F33<(M$2+7),$F33>M$2),1, IF(AND($H33<M$2+7,$H33>M$2),3, IF(AND($F33<=M$2, $H33>=M$2), 2, "" ))) | N33: =IF(AND($F33<(N$2+7),$F33>N$2),1, IF(AND($H33<N$2+7,$H33>N$2),3, IF(AND($F33<=N$2, $H33>=N$2), 2, "" ))) | O33: =IF(AND($F33<(O$2+7),$F33>O$2),1, IF(AND($H33<O$2+7,$H33>O$2),3, IF(AND($F33<=O$2, $H33>=O$2), 2, "" ))) | P33: =IF(AND($F33<(P$2+7),$F33>P$2),1, IF(AND($H33<P$2+7,$H33>P$2),3, IF(AND($F33<=P$2, $H33>=P$2), 2, "" ))) | Q33: =IF(AND($F33<(Q$2+7),$F33>Q$2),1, IF(AND($H33<Q$2+7,$H33>Q$2),3, IF(AND($F33<=Q$2, $H33>=Q$2), 2, "" ))) | R33: =IF(AND($F33<(R$2+7),$F33>R$2),1, IF(AND($H33<R$2+7,$H33>R$2),3, IF(AND($F33<=R$2, $H33>=R$2), 2, "" ))) | S33: =IF(AND($F33<(S$2+7),$F33>S$2),1, IF(AND($H33<S$2+7,$H33>S$2),3, IF(AND($F33<=S$2, $H33>=S$2), 2, "" ))) | ... AQ33: =IF(AND($F33<(AQ$2+7),$F33>AQ$2),1, IF(AND($H33<AQ$2+7,$H33>AQ$2),3, IF(AND($F33<=AQ$2, $H33>=AQ$2), 2, "" )))
B34: Monitoring Platform Installation | C34: 43997 | D34: 1 | E34: 44000 | F34: 43997 | G34: 1 | H34: 44000
A35: 11 | B35: Completion | C35: 44000 | D35: 14 | E35: 44014 | F35: 44000 | G35: 14 | H35: 44014 | L35: =IF(AND($F35<(L$2+7),$F35>L$2),1, IF(AND($H35<L$2+7,$H35>L$2),3, IF(AND($F35<=L$2, $H35>=L$2), 2, "" ))) | M35: =IF(AND($F35<(M$2+7),$F35>M$2),1, IF(AND($H35<M$2+7,$H35>M$2),3, IF(AND($F35<=M$2, $H35>=M$2), 2, "" ))) | N35: =IF(AND($F35<(N$2+7),$F35>N$2),1, IF(AND($H35<N$2+7,$H35>N$2),3, IF(AND($F35<=N$2, $H35>=N$2), 2, "" ))) | O35: =IF(AND($F35<(O$2+7),$F35>O$2),1, IF(AND($H35<O$2+7,$H35>O$2),3, IF(AND($F35<=O$2, $H35>=O$2), 2, "" ))) | P35: =IF(AND($F35<(P$2+7),$F35>P$2),1, IF(AND($H35<P$2+7,$H35>P$2),3, IF(AND($F35<=P$2, $H35>=P$2), 2, "" ))) | Q35: =IF(AND($F35<(Q$2+7),$F35>Q$2),1, IF(AND($H35<Q$2+7,$H35>Q$2),3, IF(AND($F35<=Q$2, $H35>=Q$2), 2, "" ))) | R35: =IF(AND($F35<(R$2+7),$F35>R$2),1, IF(AND($H35<R$2+7,$H35>R$2),3, IF(AND($F35<=R$2, $H35>=R$2), 2, "" ))) | S35: =IF(AND($F35<(S$2+7),$F35>S$2),1, IF(AND($H35<S$2+7,$H35>S$2),3, IF(AND($F35<=S$2, $H35>=S$2), 2, "" ))) | ... AQ35: =IF(AND($F35<(AQ$2+7),$F35>AQ$2),1, IF(AND($H35<AQ$2+7,$H35>AQ$2),3, IF(AND($F35<=AQ$2, $H35>=AQ$2), 2, "" ))) -> 3
B36: DC Works | C36: 44012 | D36: 2 | E36: 44014 | F36: 44012 | G36: 2 | H36: 44014 | L36: =IF(AND($F36<(L$2+7),$F36>L$2),1, IF(AND($H36<L$2+7,$H36>L$2),3, IF(AND($F36<=L$2, $H36>=L$2), 2, "" ))) | M36: =IF(AND($F36<(M$2+7),$F36>M$2),1, IF(AND($H36<M$2+7,$H36>M$2),3, IF(AND($F36<=M$2, $H36>=M$2), 2, "" ))) | N36: =IF(AND($F36<(N$2+7),$F36>N$2),1, IF(AND($H36<N$2+7,$H36>N$2),3, IF(AND($F36<=N$2, $H36>=N$2), 2, "" ))) | O36: =IF(AND($F36<(O$2+7),$F36>O$2),1, IF(AND($H36<O$2+7,$H36>O$2),3, IF(AND($F36<=O$2, $H36>=O$2), 2, "" ))) | P36: =IF(AND($F36<(P$2+7),$F36>P$2),1, IF(AND($H36<P$2+7,$H36>P$2),3, IF(AND($F36<=P$2, $H36>=P$2), 2, "" ))) | Q36: =IF(AND($F36<(Q$2+7),$F36>Q$2),1, IF(AND($H36<Q$2+7,$H36>Q$2),3, IF(AND($F36<=Q$2, $H36>=Q$2), 2, "" ))) | R36: =IF(AND($F36<(R$2+7),$F36>R$2),1, IF(AND($H36<R$2+7,$H36>R$2),3, IF(AND($F36<=R$2, $H36>=R$2), 2, "" ))) | S36: =IF(AND($F36<(S$2+7),$F36>S$2),1, IF(AND($H36<S$2+7,$H36>S$2),3, IF(AND($F36<=S$2, $H36>=S$2), 2, "" ))) | ... AQ36: =IF(AND($F36<(AQ$2+7),$F36>AQ$2),1, IF(AND($H36<AQ$2+7,$H36>AQ$2),3, IF(AND($F36<=AQ$2, $H36>=AQ$2), 2, "" ))) -> 3
B37: AC Works | C37: 44000 | D37: 2 | E37: 44004 | F37: 44000 | G37: 2 | H37: 44004 | L37: =IF(AND($F37<(L$2+7),$F37>L$2),1, IF(AND($H37<L$2+7,$H37>L$2),3, IF(AND($F37<=L$2, $H37>=L$2), 2, "" ))) | M37: =IF(AND($F37<(M$2+7),$F37>M$2),1, IF(AND($H37<M$2+7,$H37>M$2),3, IF(AND($F37<=M$2, $H37>=M$2), 2, "" ))) | N37: =IF(AND($F37<(N$2+7),$F37>N$2),1, IF(AND($H37<N$2+7,$H37>N$2),3, IF(AND($F37<=N$2, $H37>=N$2), 2, "" ))) | O37: =IF(AND($F37<(O$2+7),$F37>O$2),1, IF(AND($H37<O$2+7,$H37>O$2),3, IF(AND($F37<=O$2, $H37>=O$2), 2, "" ))) | P37: =IF(AND($F37<(P$2+7),$F37>P$2),1, IF(AND($H37<P$2+7,$H37>P$2),3, IF(AND($F37<=P$2, $H37>=P$2), 2, "" ))) | Q37: =IF(AND($F37<(Q$2+7),$F37>Q$2),1, IF(AND($H37<Q$2+7,$H37>Q$2),3, IF(AND($F37<=Q$2, $H37>=Q$2), 2, "" ))) | R37: =IF(AND($F37<(R$2+7),$F37>R$2),1, IF(AND($H37<R$2+7,$H37>R$2),3, IF(AND($F37<=R$2, $H37>=R$2), 2, "" ))) | S37: =IF(AND($F37<(S$2+7),$F37>S$2),1, IF(AND($H37<S$2+7,$H37>S$2),3, IF(AND($F37<=S$2, $H37>=S$2), 2, "" ))) | ... AQ37: =IF(AND($F37<(AQ$2+7),$F37>AQ$2),1, IF(AND($H37<AQ$2+7,$H37>AQ$2),3, IF(AND($F37<=AQ$2, $H37>=AQ$2), 2, "" )))
A38: D | B38: PAYMENT MILESTONE 4: PRACTICAL COMPLETION | C38: 44012 | D38: 1 | E38: 44013 | F38: 44012 | G38: 1 | H38: 44013 | L38: =IF(AND($F38<(L$2+7),$F38>L$2),1, IF(AND($H38<L$2+7,$H38>L$2),3, IF(AND($F38<=L$2, $H38>=L$2), 2, "" ))) | M38: =IF(AND($F38<(M$2+7),$F38>M$2),1, IF(AND($H38<M$2+7,$H38>M$2),3, IF(AND($F38<=M$2, $H38>=M$2), 2, "" ))) | N38: =IF(AND($F38<(N$2+7),$F38>N$2),1, IF(AND($H38<N$2+7,$H38>N$2),3, IF(AND($F38<=N$2, $H38>=N$2), 2, "" ))) | O38: =IF(AND($F38<(O$2+7),$F38>O$2),1, IF(AND($H38<O$2+7,$H38>O$2),3, IF(AND($F38<=O$2, $H38>=O$2), 2, "" ))) | P38: =IF(AND($F38<(P$2+7),$F38>P$2),1, IF(AND($H38<P$2+7,$H38>P$2),3, IF(AND($F38<=P$2, $H38>=P$2), 2, "" ))) | Q38: =IF(AND($F38<(Q$2+7),$F38>Q$2),1, IF(AND($H38<Q$2+7,$H38>Q$2),3, IF(AND($F38<=Q$2, $H38>=Q$2), 2, "" ))) | R38: =IF(AND($F38<(R$2+7),$F38>R$2),1, IF(AND($H38<R$2+7,$H38>R$2),3, IF(AND($F38<=R$2, $H38>=R$2), 2, "" ))) | S38: =IF(AND($F38<(S$2+7),$F38>S$2),1, IF(AND($H38<S$2+7,$H38>S$2),3, IF(AND($F38<=S$2, $H38>=S$2), 2, "" ))) | ... AQ38: =IF(AND($F38<(AQ$2+7),$F38>AQ$2),1, IF(AND($H38<AQ$2+7,$H38>AQ$2),3, IF(AND($F38<=AQ$2, $H38>=AQ$2), 2, "" ))) -> 3
A39: 12 | B39: Commissioning | C39: 43997 | D39: 22 | E39: 44019 | F39: 43997 | G39: 22 | H39: 44019 | L39: =IF(AND($F39<(L$2+7),$F39>L$2),1, IF(AND($H39<L$2+7,$H39>L$2),3, IF(AND($F39<=L$2, $H39>=L$2), 2, "" ))) | M39: =IF(AND($F39<(M$2+7),$F39>M$2),1, IF(AND($H39<M$2+7,$H39>M$2),3, IF(AND($F39<=M$2, $H39>=M$2), 2, "" ))) | N39: =IF(AND($F39<(N$2+7),$F39>N$2),1, IF(AND($H39<N$2+7,$H39>N$2),3, IF(AND($F39<=N$2, $H39>=N$2), 2, "" ))) | O39: =IF(AND($F39<(O$2+7),$F39>O$2),1, IF(AND($H39<O$2+7,$H39>O$2),3, IF(AND($F39<=O$2, $H39>=O$2), 2, "" ))) | P39: =IF(AND($F39<(P$2+7),$F39>P$2),1, IF(AND($H39<P$2+7,$H39>P$2),3, IF(AND($F39<=P$2, $H39>=P$2), 2, "" ))) | Q39: =IF(AND($F39<(Q$2+7),$F39>Q$2),1, IF(AND($H39<Q$2+7,$H39>Q$2),3, IF(AND($F39<=Q$2, $H39>=Q$2), 2, "" ))) | R39: =IF(AND($F39<(R$2+7),$F39>R$2),1, IF(AND($H39<R$2+7,$H39>R$2),3, IF(AND($F39<=R$2, $H39>=R$2), 2, "" ))) | S39: =IF(AND($F39<(S$2+7),$F39>S$2),1, IF(AND($H39<S$2+7,$H39>S$2),3, IF(AND($F39<=S$2, $H39>=S$2), 2, "" ))) | ... AQ39: =IF(AND($F39<(AQ$2+7),$F39>AQ$2),1, IF(AND($H39<AQ$2+7,$H39>AQ$2),3, IF(AND($F39<=AQ$2, $H39>=AQ$2), 2, "" ))) -> 2
B40: Snag List | C40: 44014 | D40: 3 | E40: 44019 | F40: 44014 | G40: 3 | H40: 44019
B41: Pre-Commissioning Checks | C41: 44010 | D41: 2 | E41: 44012 | F41: 44010 | G41: 2 | H41: 44012
B42: Issue CoC | C42: 43997 | D42: 2 | E42: 44001 | F42: 43997 | G42: 2 | H42: 44001 | L42: =IF(AND($F42<(L$2+7),$F42>L$2),1, IF(AND($H42<L$2+7,$H42>L$2),3, IF(AND($F42<=L$2, $H42>=L$2), 2, "" ))) | M42: =IF(AND($F42<(M$2+7),$F42>M$2),1, IF(AND($H42<M$2+7,$H42>M$2),3, IF(AND($F42<=M$2, $H42>=M$2), 2, "" ))) | N42: =IF(AND($F42<(N$2+7),$F42>N$2),1, IF(AND($H42<N$2+7,$H42>N$2),3, IF(AND($F42<=N$2, $H42>=N$2), 2, "" ))) | O42: =IF(AND($F42<(O$2+7),$F42>O$2),1, IF(AND($H42<O$2+7,$H42>O$2),3, IF(AND($F42<=O$2, $H42>=O$2), 2, "" ))) | P42: =IF(AND($F42<(P$2+7),$F42>P$2),1, IF(AND($H42<P$2+7,$H42>P$2),3, IF(AND($F42<=P$2, $H42>=P$2), 2, "" ))) | Q42: =IF(AND($F42<(Q$2+7),$F42>Q$2),1, IF(AND($H42<Q$2+7,$H42>Q$2),3, IF(AND($F42<=Q$2, $H42>=Q$2), 2, "" ))) | R42: =IF(AND($F42<(R$2+7),$F42>R$2),1, IF(AND($H42<R$2+7,$H42>R$2),3, IF(AND($F42<=R$2, $H42>=R$2), 2, "" ))) | S42: =IF(AND($F42<(S$2+7),$F42>S$2),1, IF(AND($H42<S$2+7,$H42>S$2),3, IF(AND($F42<=S$2, $H42>=S$2), 2, "" ))) | ... AQ42: =IF(AND($F42<(AQ$2+7),$F42>AQ$2),1, IF(AND($H42<AQ$2+7,$H42>AQ$2),3, IF(AND($F42<=AQ$2, $H42>=AQ$2), 2, "" )))
B43: Cold Commissioning | C43: 44012 | D43: 1 | E43: 44013 | F43: 44012 | G43: 1 | H43: 44013 | L43: =IF(AND($F43<(L$2+7),$F43>L$2),1, IF(AND($H43<L$2+7,$H43>L$2),3, IF(AND($F43<=L$2, $H43>=L$2), 2, "" ))) | M43: =IF(AND($F43<(M$2+7),$F43>M$2),1, IF(AND($H43<M$2+7,$H43>M$2),3, IF(AND($F43<=M$2, $H43>=M$2), 2, "" ))) | N43: =IF(AND($F43<(N$2+7),$F43>N$2),1, IF(AND($H43<N$2+7,$H43>N$2),3, IF(AND($F43<=N$2, $H43>=N$2), 2, "" ))) | O43: =IF(AND($F43<(O$2+7),$F43>O$2),1, IF(AND($H43<O$2+7,$H43>O$2),3, IF(AND($F43<=O$2, $H43>=O$2), 2, "" ))) | P43: =IF(AND($F43<(P$2+7),$F43>P$2),1, IF(AND($H43<P$2+7,$H43>P$2),3, IF(AND($F43<=P$2, $H43>=P$2), 2, "" ))) | Q43: =IF(AND($F43<(Q$2+7),$F43>Q$2),1, IF(AND($H43<Q$2+7,$H43>Q$2),3, IF(AND($F43<=Q$2, $H43>=Q$2), 2, "" ))) | R43: =IF(AND($F43<(R$2+7),$F43>R$2),1, IF(AND($H43<R$2+7,$H43>R$2),3, IF(AND($F43<=R$2, $H43>=R$2), 2, "" ))) | S43: =IF(AND($F43<(S$2+7),$F43>S$2),1, IF(AND($H43<S$2+7,$H43>S$2),3, IF(AND($F43<=S$2, $H43>=S$2), 2, "" ))) | ... AQ43: =IF(AND($F43<(AQ$2+7),$F43>AQ$2),1, IF(AND($H43<AQ$2+7,$H43>AQ$2),3, IF(AND($F43<=AQ$2, $H43>=AQ$2), 2, "" ))) -> 3
B44: Hot Commissioning | C44: 44013 | D44: 2 | E44: 44015 | F44: 44013 | G44: 2 | H44: 44015 | L44: =IF(AND($F44<(L$2+7),$F44>L$2),1, IF(AND($H44<L$2+7,$H44>L$2),3, IF(AND($F44<=L$2, $H44>=L$2), 2, "" ))) | M44: =IF(AND($F44<(M$2+7),$F44>M$2),1, IF(AND($H44<M$2+7,$H44>M$2),3, IF(AND($F44<=M$2, $H44>=M$2), 2, "" ))) | N44: =IF(AND($F44<(N$2+7),$F44>N$2),1, IF(AND($H44<N$2+7,$H44>N$2),3, IF(AND($F44<=N$2, $H44>=N$2), 2, "" ))) | O44: =IF(AND($F44<(O$2+7),$F44>O$2),1, IF(AND($H44<O$2+7,$H44>O$2),3, IF(AND($F44<=O$2, $H44>=O$2), 2, "" ))) | P44: =IF(AND($F44<(P$2+7),$F44>P$2),1, IF(AND($H44<P$2+7,$H44>P$2),3, IF(AND($F44<=P$2, $H44>=P$2), 2, "" ))) | Q44: =IF(AND($F44<(Q$2+7),$F44>Q$2),1, IF(AND($H44<Q$2+7,$H44>Q$2),3, IF(AND($F44<=Q$2, $H44>=Q$2), 2, "" ))) | R44: =IF(AND($F44<(R$2+7),$F44>R$2),1, IF(AND($H44<R$2+7,$H44>R$2),3, IF(AND($F44<=R$2, $H44>=R$2), 2, "" ))) | S44: =IF(AND($F44<(S$2+7),$F44>S$2),1, IF(AND($H44<S$2+7,$H44>S$2),3, IF(AND($F44<=S$2, $H44>=S$2), 2, "" ))) | ... AQ44: =IF(AND($F44<(AQ$2+7),$F44>AQ$2),1, IF(AND($H44<AQ$2+7,$H44>AQ$2),3, IF(AND($F44<=AQ$2, $H44>=AQ$2), 2, "" ))) -> 1
A45: 13 | B45: Handover | C45: 44020 | D45: 1 | E45: 44021 | F45: 44020 | G45: 1 | H45: 44021 | L45: =IF(AND($F45<(L$2+7),$F45>L$2),1, IF(AND($H45<L$2+7,$H45>L$2),3, IF(AND($F45<=L$2, $H45>=L$2), 2, "" ))) | M45: =IF(AND($F45<(M$2+7),$F45>M$2),1, IF(AND($H45<M$2+7,$H45>M$2),3, IF(AND($F45<=M$2, $H45>=M$2), 2, "" ))) | N45: =IF(AND($F45<(N$2+7),$F45>N$2),1, IF(AND($H45<N$2+7,$H45>N$2),3, IF(AND($F45<=N$2, $H45>=N$2), 2, "" ))) | O45: =IF(AND($F45<(O$2+7),$F45>O$2),1, IF(AND($H45<O$2+7,$H45>O$2),3, IF(AND($F45<=O$2, $H45>=O$2), 2, "" ))) | P45: =IF(AND($F45<(P$2+7),$F45>P$2),1, IF(AND($H45<P$2+7,$H45>P$2),3, IF(AND($F45<=P$2, $H45>=P$2), 2, "" ))) | Q45: =IF(AND($F45<(Q$2+7),$F45>Q$2),1, IF(AND($H45<Q$2+7,$H45>Q$2),3, IF(AND($F45<=Q$2, $H45>=Q$2), 2, "" ))) | R45: =IF(AND($F45<(R$2+7),$F45>R$2),1, IF(AND($H45<R$2+7,$H45>R$2),3, IF(AND($F45<=R$2, $H45>=R$2), 2, "" ))) | S45: =IF(AND($F45<(S$2+7),$F45>S$2),1, IF(AND($H45<S$2+7,$H45>S$2),3, IF(AND($F45<=S$2, $H45>=S$2), 2, "" ))) | ... AQ45: =IF(AND($F45<(AQ$2+7),$F45>AQ$2),1, IF(AND($H45<AQ$2+7,$H45>AQ$2),3, IF(AND($F45<=AQ$2, $H45>=AQ$2), 2, "" )))
A46: E | B46: PAYMENT MILESTONE 6: HANDOVER COMPLETE | C46: 44022 | D46: 1 | E46: 44025 | F46: 44022 | G46: 1 | H46: 44025
C47: 43831 | D47: These numbers are used to set the start and end dates on the Gantt Chart
C48: 44014

Sheet Revenue Tracking
B2: HIGH LEVEL PROJECT REVENUE TRACKING
D3: PLANNED | F3: ACTUAL | H3: FR - Date | J3: 2023 Rev & COS RECOGNISED | K3: PLANNED | L3: ACTUAL
B4: 1 | C4: Planned Revenue | D4: ='Project Plan'!E9 -> 20939009 | F4: =F32 -> 20939009 | H4: 20939009 | J4: 12809926 | K4: 8129083.1 | L4: =F4-J4 -> 8129083.1
B5: 2 | C5: Planned Expenditure | D5: =+'Expenditure Tracking'!F5 -> 18682950 | F5: =+'Expenditure Tracking'!H5 -> 19234297 | H5: 18820454 | J5: 11843153 | K5: 6186351.1 | L5: =F5-J5 -> 7391144.5
B6: 3 | C6: Planned Profit | D6: =+D4-D5 -> 2256058.8 | F6: =+F4-F5 -> 1704711.5 | H6: 2118554.7 | J6: =J4-J5 -> 966772.97 | K6: =K4-K5 -> 1942732 | L6: =L4-L5 -> 737938.53
B7: 4 | C7: Planned Margin | D7: =+D6/D4 -> 0.1077443 | F7: =+F6/F4 -> 0.08141319 | H7: 0.10117741
B10: CONTRACT | D10: =+D4/'Project Plan'!E3/1000 -> 11.965626
L11: [Finance only]
B12: No. | C12: PAYMENT MILESTONE | E12: % | F12: VALUE | H12: PLANNED PAYMENT DATE | J12: ACTUAL PAYMENT DATE | L12: INVOICE RAISED DATE | N12: MILESTONE NOTES
B13: 1 | C13: Initial deposit | E13: 0.3 | F13: =535734.1725/1.15 -> 465855.8 | H13: =+'Project Plan'!G16+7 -> 44971 | J13: 45386 | L13: 004359 | N13: Add notes relating to the payment / assessment of milestone, draw from EPC contract or CP
F14: =2000000/1.15 -> 1739130.4 | H14: 44971 | J14: 45387 | L14: 004359
F15: =2000000/1.15 -> 1739130.4 | H15: 44971 | J15: 45392 | L15: 004359
F16: =2000000/1.15 -> 1739130.4 | H16: 44971 | J16: 45397 | L16: 004359
F17: =6281702.63091813-F13-F14-F15-F16 -> 598455.52 | H17: 44971 | J17: 45398 | L17: 004359
B18: 2 | C18: Delivery of Main Equipment(Inverters & BOS) | E18: 0.2 | F18: 1140674.9 | H18: 44970 | J18: 45398 | L18: 004359
F19: 1739130.4 | H19: 44970 | J19: 45399 | L19: 004359
F20: =4187801.75394542-F18-F19 -> 1307996.4 | H20: 44970 | J20: 45401 | L20: 004359
B21: 3 | C21: Delivery of Main Equipment(Solar Panels) | E21: 0.25 | F21: 431134.03 | H21: =+'Project Plan'!G23+7+30 -> 45148 | J21: 45401 | L21: 004359
F22: 1739130.4 | H22: 45148 | J22: 45407 | L22: 004359
F23: 1739130.4 | H23: 45148 | J23: 45408 | L23: 004359
F24: =1000000/1.15 -> 869565.22 | H24: 45148 | J24: 45411 | L24: 004359
F25: =5234752.19243177-F21-F22-F23-F24 -> 455792.08 | H25: 45148 | J25: 45412 | L25: 004359
B26: 4 | C26: Installation Complete(Physical Completion) | E26: 0.1 | F26: =$D$4*E26 -> 2093900.9 | H26: =+'Project Plan'!G37+7+30 -> 45205 | J26: 45473 | L26: 004409
B27: 5 | C27: Commissioing Complete(Testing and Checks Complete) | E27: 0.1 | F27: =$D$4*E27 -> 2093900.9 | H27: =+'Project Plan'!G45+7+30 -> 45318 | J27: 45473 | L27: 004409
B28: 6 | C28: Handover complete | E28: 0.05 | F28: =$D$4*E28 -> 1046950.4 | H28: =+H27+7+30 -> 45355 | J28: 45473 | L28: 004409
B29: 6 | E29: 0 | F29: =$D$4*E29 -> 0
B30: 7 | C30: - | E30: 0 | F30: =$D$4*E30 -> 0
E32: =SUM(E13:E30) -> 1 | F32: =SUM(F13:F30) -> 20939009
B34: KEY: | C34: contains an error (in result or a check has failed)
C35: Red Font - IF TEXT : content not yet confirmed
C36: Red Font - IF NUMBER: Negative value
C37: Anything in yellow is a concern or risk for noting or action
C38: confirmed
C39: [ADD INITIALS: comment for noting in square brackets, use colour or red to draw attention if important]
C40: [RT: When adding rows into sheet, ensure you insert between first and last row of each category]
C41: end of sheet - do not insert information below/beyond this
B51: No. | C51: PAYMENT MILESTONE | E51: % | F51: VALUE
B52: 1 | C52: Deposit - Project commencement | E52: 0.35 | F52: =$F$58*E52 -> 7328653.1
B53: 2 | C53: Delivery of Panels | E53: 0.3 | F53: =$F$58*E53 -> 6281702.6
B54: 3 | C54: Delivery of Inverters | E54: 0.2 | F54: =$F$58*E54 -> 4187801.8
B55: 4 | C55: Practical Completion | E55: 0.1 | F55: =$F$58*E55 -> 2093900.9
B56: 5 | C56: Handover | E56: 0.05 | F56: =$F$58*E56 -> 1046950.4
C57: Total | E57: =SUM(E52:E56) -> 1 | F57: =SUM(F52:F56) -> 20939009
E58: =SUM(E52:E56) -> 1 | F58: =F32 -> 20939009

Sheet Project Plan
C2: PROJECT PLAN | E2: Mega Park Extension
C3: PROJECT SIZE (kWp) | E3: 1749.93
C4: SITE ADDRESS | E4: 17 Mill Rd, Unclear, Cape Town, 7530
C5: BUSINESS DEVELOPER | E5: Natasha Watkins Baker
C6: PROJECT MANAGERS | E6: Roedolph/Simon
C7: PROJECT COORDINATOR | E7: Refiloe Mohohlo
C8: INSTALLER | E8: Smart Solar
C9: CONTRACT VALUE | E9: 20939009
C10: Phase: | E10: DLP
B11: No. | C11: HIGH LEVEL PROGRAMME | E11: Planned Start | F11: Duration (days) | G11: Planned End | I11: Actual Start | J11: Duration (days) | K11: Actual End | M11: Status | O11: Comment
F12: =G45-E20 -> 185 | J12: =K45-I20 -> 234 | M12: =AVERAGE(M14,M19,M22,M29,M36,M42,M47,M57) -> 1
B14: 1 | C14: Project Initiation | E14: =MIN(E15:E17) -> 44798 | F14: =SUM(F15:F17) -> 3 | G14: =MAX(G15:G17) -> 45062 | I14: =MIN(I15:I17) -> 44798 | J14: =SUM(J15:J17) -> 3 | K14: =MAX(K15:K17) -> 45062 | M14: =(J15*M15+J16*M16+J17*M17)/J14 -> 1
B15: 1.1 | C15: Internal Handover | E15: 44798 | F15: 1 | G15: =WORKDAY.INTL(E15,F15,1,Data!$C$3:$C$14) -> 44799 | I15: 44798 | J15: 1 | K15: =WORKDAY.INTL(I15,J15,1,Data!$C$3:$C$14) -> 44799 | M15: 1
B16: 1.2 | C16: Internal kick off | E16: 44963 | F16: 1 | G16: =WORKDAY.INTL(E16,F16,1,Data!$C$3:$C$14) -> 44964 | I16: 44963 | J16: 1 | K16: =WORKDAY.INTL(I16,J16,1,Data!$C$3:$C$14) -> 44964 | M16: 1
B17: 1.3 | C17: Client kick off | E17: 45061 | F17: 1 | G17: =WORKDAY.INTL(E17,F17,1,Data!$C$3:$C$14) -> 45062 | I17: 45061 | J17: 1 | K17: =WORKDAY.INTL(I17,J17,1,Data!$C$3:$C$14) -> 45062 | M17: 1
B19: 2 | C19: Site Establishment | E19: =MIN(E20:E21) -> 45096 | F19: =SUM(F20:F21) -> 2 | G19: =MAX(G20) -> 45098 | I19: =MIN(I20:I21) -> 45096 | J19: =SUM(J20:J21) -> 3 | K19: =MAX(K20) -> 45099 | M19: =(J20*M20)/J19 -> 1
B20: 2.1 | C20: Installer on site and roof assessment | E20: 45096 | F20: 2 | G20: =WORKDAY.INTL(E20,F20,1,Data!$C$3:$C$14) -> 45098 | I20: 45096 | J20: 3 | K20: =WORKDAY.INTL(I20,J20,1,Data!$C$3:$C$14) -> 45099 | M20: 1
B22: 3 | C22: AC Installation | E22: =MIN(E23:E27) -> 45091 | F22: =SUM(F23:F27) -> 90 | G22: =MAX(G23:G27) -> 45204 | I22: =MIN(I23:I27) -> 45092 | J22: =SUM(J23:J27) -> 179 | K22: =MAX(K23:K27) -> 45335 | M22: =(J23*M23+J24*M24+J25*M25+J26*M26+J27*M27)/J22 -> 1
B23: 3.1 | C23: Inverters delivered | E23: 45110 | F23: 1 | G23: =+F23+E23 -> 45111 | I23: 45153 | J23: 1 | K23: =+J23+I23 -> 45154 | M23: 1
B24: 3.2 | C24: Inverters Mounted | E24: =WORKDAY.INTL(G23,0,1,Data!$C$3:$C$14) -> 45111 | F24: 8 | G24: =WORKDAY.INTL(E24,F24,1,Data!$C$3:$C$14) -> 45121 | I24: 45261 | J24: 4 | K24: =WORKDAY.INTL(I24,J24,1,Data!$C$3:$C$14) -> 45267 | M24: 1
B25: 3.3 | C25: Solar DB lead time | E25: =+G20-7 -> 45091 | F25: 40 | G25: =WORKDAY.INTL(E25,F25,1,Data!$C$3:$C$14) -> 45147 | I25: =+K20-7 -> 45092 | J25: 73 | K25: =WORKDAY.INTL(I25,J25,1,Data!$C$3:$C$14) -> 45195 | M25: 1
B26: 3.4 | C26: AC Works | E26: =WORKDAY.INTL(G25,0,1,Data!$C$3:$C$14) -> 45147 | F26: 40 | G26: =WORKDAY.INTL(E26,F26,1,Data!$C$3:$C$14) -> 45203 | I26: =K25 -> 45195 | J26: 100 | K26: =WORKDAY.INTL(I26,J26,1,Data!$C$3:$C$14) -> 45335 | M26: 1 | O26: RT: too long need to push
B27: 3.5 | C27: AC Tie - in | E27: =G26 -> 45203 | F27: 1 | G27: =WORKDAY.INTL(E27,F27,1,Data!$C$3:$C$14) -> 45204 | I27: 45223 | J27: 1 | K27: =WORKDAY.INTL(I27,J27,1,Data!$C$3:$C$14) -> 45224 | M27: 1 | O27: RV: Schedule PrEng
B29: 4 | C29: DC Works | E29: =MIN(E30:E34) -> 45096 | F29: =SUM(F30:F34) -> 103 | G29: =MAX(G30:G34) -> 45239 | I29: =MIN(I30:I34) -> 45099 | J29: =SUM(J30:J34) -> 155 | K29: =MAX(K30:K34) -> 45273 | M29: =(J30*M30+J31*M31+J32*M32+J33*M33+J34*M34)/J29 -> 1
B30: 4.1 | C30: Mounting Structure delivered | E30: 45096 | F30: 1 | G30: =WORKDAY.INTL(E30,F30,1,Data!$C$3:$C$14) -> 45097 | I30: 45099 | J30: 1 | K30: =WORKDAY.INTL(I30,J30,1,Data!$C$3:$C$14) -> 45100 | M30: 1
B31: 4.2 | C31: Mounting Structure installation | E31: =WORKDAY.INTL(G30,0,1,Data!$C$3:$C$14) -> 45097 | F31: 50 | G31: =WORKDAY.INTL(E31,F31,1,Data!$C$3:$C$14) -> 45167 | I31: =WORKDAY.INTL(K30,0,1,Data!$C$3:$C$14) -> 45100 | J31: 50 | K31: =WORKDAY.INTL(I31,J31,1,Data!$C$3:$C$14) -> 45170 | M31: 1
B32: 4.3 | C32: DC Cable delivered | E32: =+G31 -> 45167 | F32: 1 | G32: =WORKDAY.INTL(E32,F32,1,Data!$C$3:$C$14) -> 45168 | I32: =+K31 -> 45170 | J32: 1 | K32: =WORKDAY.INTL(I32,J32,1,Data!$C$3:$C$14) -> 45173 | M32: 1
B33: 4.4 | C33: DC Cable Trays installation | E33: =+G32 -> 45168 | F33: 30 | G33: =WORKDAY.INTL(E33,F33,1,Data!$C$3:$C$14) -> 45210 | I33: =+K32 -> 45173 | J33: 72 | K33: =WORKDAY.INTL(I33,J33,1,Data!$C$3:$C$14) -> 45273 | M33: 1
B34: 4.5 | C34: DC Cabling | E34: =+G33 -> 45210 | F34: 21 | G34: =WORKDAY.INTL(E34,F34,1,Data!$C$3:$C$14) -> 45239 | I34: =+I31+45 -> 45145 | J34: 31 | K34: =WORKDAY.INTL(I34,J34,1,Data!$C$3:$C$14) -> 45188 | M34: 1
B36: 5 | C36: Module installation | E36: =MIN(E37:E40) -> 45167 | F36: =SUM(F37:F41) -> 73 | G36: =MAX(G37:G40) -> 45267 | I36: =MIN(I37:I40) -> 45170 | J36: =SUM(J37:J41) -> 51 | K36: =MAX(K37:K40) -> 45240 | M36: =(J37*M37+J38*M38+J39*M39+J40*M40)/J36 -> 1
B37: 5.1 | C37: Module delivery - Batch 1 | E37: =+G31 -> 45167 | F37: 1 | G37: =WORKDAY.INTL(E37,F37,1,Data!$C$3:$C$14) -> 45168 | I37: =+K31 -> 45170 | J37: 1 | K37: =WORKDAY.INTL(I37,J37,1,Data!$C$3:$C$14) -> 45173 | M37: 1 | O37: RT: we need to start mounting in phases before all MS is complete | P37: {=_xlfn.LET(_xlpm.w,$B$10:$B$53,_xlpm.r,$M$10:$M$53,_xlpm.v,IF(ISNUMBER(_xlpm.r),_xlpm.r,IFERROR(VALUE(SUBSTITUTE(_xlpm.r,"%",""))/100,0)),_xlpm.g,IFERROR(VALUE(LEFT(_xlpm.w,1)),0),_xlpm.bdOnly,(SUMPRODUCT((_xlpm.w="1.1")*(_xlpm.v>0))>0)*(SUMPRODUCT((_xlpm.w<>"1.1")*(_xlpm.v>0))=0),_xlpm.anyConstr,SUMPRODUCT((_xlpm.g>=2)*(_xlpm.g<=6)*(_xlpm.v>0))>0,_xlpm.anyQA,SUMPRODUCT((_xlpm.g=7)*(_xlpm.v>0))>0,_xlpm.anyHO,SUMPRODUCT((_xlpm.g=8)*(_xlpm.v>0))>0,_xlpm.anyPlan,SUMPRODUCT((_xlpm.g=1)*(_xlpm.v>0))>0,IF(_xlpm.bdOnly,"1. Financial Close",IF(_xlpm.anyConstr,"3. Construction",IF(_xlpm.anyQA,"4. QA",IF(_xlpm.anyHO,"5. Handover",IF(_xlpm.anyPlan,"2. Planning","1. Financial Close"))))))} -> 3. Construction | Q37: {=_xlfn.LET(_xlpm.w,$B$10:$B$53,_xlpm.r,$N$10:$N$53,_xlpm.v,IF(ISNUMBER(_xlpm.r),_xlpm.r,IFERROR(VALUE(SUBSTITUTE(_xlpm.r,"%",""))/100,0)),_xlpm.g,IFERROR(VALUE(LEFT(_xlpm.w,1)),0),_xlpm.bdOnly,(SUMPRODUCT((_xlpm.w="1.1")*(_xlpm.v>0))>0)*(SUMPRODUCT((_xlpm.w<>"1.1")*(_xlpm.v>0))=0),_xlpm.anyConstr,SUMPRODUCT((_xlpm.g>=2)*(_xlpm.g<=6)*(_xlpm.v>0))>0,_xlpm.anyQA,SUMPRODUCT((_xlpm.g=7)*(_xlpm.v>0))>0,_xlpm.anyHO,SUMPRODUCT((_xlpm.g=8)*(_xlpm.v>0))>0,_xlpm.anyPlan,SUMPRODUCT((_xlpm.g=1)*(_xlpm.v>0))>0,IF(_xlpm.bdOnly,"1. Financial Close",IF(_xlpm.anyConstr,"3. Construction",IF(_xlpm.anyQA,"4. QA",IF(_xlpm.anyHO,"5. Handover",IF(_xlpm.anyPlan,"2. Planning","1. Financial Close"))))))} -> 1. Financial Close
B38: 5.2 | C38: Module delivery - Batch 2 | E38: =+G37+7 -> 45175 | F38: 1 | G38: =WORKDAY.INTL(E38,F38,1,Data!$C$3:$C$14) -> 45176 | I38: =+K37+7 -> 45180 | J38: 1 | K38: =WORKDAY.INTL(I38,J38,1,Data!$C$3:$C$14) -> 45181 | M38: 1
B39: 5.3 | C39: Module delivery - Batch 3 | E39: =+G38+7 -> 45183 | F39: 1 | G39: =WORKDAY.INTL(E39,F39,1,Data!$C$3:$C$14) -> 45184 | I39: =+K38+7 -> 45188 | J39: 1 | K39: =WORKDAY.INTL(I39,J39,1,Data!$C$3:$C$14) -> 45189 | M39: 1
B40: 5.4 | C40: Module mounting | E40: =WORKDAY.INTL(G37,0,1,Data!$C$3:$C$14)+1 -> 45169 | F40: 70 | G40: =WORKDAY.INTL(E40,F40,1,Data!$C$3:$C$14) -> 45267 | I40: =WORKDAY.INTL(K37,0,1,Data!$C$3:$C$14)+1 -> 45174 | J40: 48 | K40: =WORKDAY.INTL(I40,J40,1,Data!$C$3:$C$14) -> 45240 | M40: 1 | O40: RT: too long need to push
B42: 6 | C42: Commissioning | E42: =MIN(E43:E45) -> 0 | F42: =SUM(F43:F46) -> 13 | G42: =MAX(G43:G45) -> 45281 | I42: =MIN(I43:I45) -> 45317 | J42: =SUM(J43:J46) -> 6 | K42: =MAX(K43:K45) -> 45330 | M42: 1
B43: 6.1 | C43: Cold commissioning | E43: =WORKDAY.INTL(G40,0,1,Data!$C$3:$C$14) -> 45267 | F43: 3 | G43: =WORKDAY.INTL(E43,F43,1,Data!$C$3:$C$14) -> 45272 | I43: 45317 | J43: 1 | K43: =WORKDAY.INTL(I43,J43,1,Data!$C$3:$C$14) -> 45320 | M43: 1 | O43: 6x inverters are switched on, not all of them have strings plugged in.
B44: 6.2 | C44: Cold commissioning - Phased | E44: =WORKDAY.INTL(G41,0,1,Data!$C$3:$C$14) -> 0 | F44: 3 | G44: =WORKDAY.INTL(E44,F44,1,Data!$C$3:$C$14) -> 4 | I44: 45321 | J44: 1 | K44: =WORKDAY.INTL(I44,J44,1,Data!$C$3:$C$14) -> 45322 | M44: 1
B45: 6.3 | C45: Practical Completion | E45: =WORKDAY.INTL(G43,0,1,Data!$C$3:$C$14) -> 45272 | F45: 7 | G45: =WORKDAY.INTL(E45,F45,1,Data!$C$3:$C$14) -> 45281 | I45: =WORKDAY.INTL(K43,0,1,Data!$C$3:$C$14)+4 -> 45324 | J45: 4 | K45: =WORKDAY.INTL(I45,J45,1,Data!$C$3:$C$14) -> 45330 | M45: 1 | O45: Next 6x inverters to be switched.
B47: 7 | C47: Project Closure | E47: =MIN(E48:E55) -> 45302 | F47: =SUM(F48:F53) -> 12 | G47: =MAX(G48:G55) -> 45322 | I47: =MIN(I48:I55) -> 45330 | J47: =SUM(J48:J53) -> 58 | K47: =MAX(K48:K55) -> 45425 | M47: 1
B48: 7.1 | C48: Equipment serial numbers | E48: =WORKDAY.INTL(E50,0,1,Data!$C$3:$C$14) -> 45302 | F48: 0 | G48: =WORKDAY.INTL(E48,F48,1,Data!$C$3:$C$14) -> 45302 | I48: =WORKDAY.INTL(K45,0,1,Data!$C$3:$C$14) -> 45330 | J48: 1 | K48: =WORKDAY.INTL(I48,J48,1,Data!$C$3:$C$14) -> 45331 | M48: 1
B49: 7.2 | C49: Fiber Installation | I49: 45356 | J49: 15 | K49: 45377 | M49: 1
B50: 7.4 | C50: Snags completion - 1 | E50: =WORKDAY.INTL(G58,0,1,Data!$C$3:$C$14) -> 45302 | F50: 3 | G50: =WORKDAY.INTL(E50,F50,1,Data!$C$3:$C$14) -> 45307 | I50: =WORKDAY.INTL(K58,0,1,Data!$C$3:$C$14) -> 45352 | J50: 20 | K50: =WORKDAY.INTL(I50,J50,1,Data!$C$3:$C$14) -> 45380 | M50: 1
B51: 7.4 | C51: Snags completion - 2 | I51: =WORKDAY.INTL(K58,0,1,Data!$C$3:$C$14)+45 -> 45397 | J51: 20 | K51: =WORKDAY.INTL(I51,J51,1,Data!$C$3:$C$14) -> 45425 | M51: 1
B52: 7.5 | C52: System Performance Monitoring | E52: =WORKDAY.INTL(G50,0,1,Data!$C$3:$C$14) -> 45307 | F52: 7 | G52: =WORKDAY.INTL(E52,F52,1,Data!$C$3:$C$14) -> 45316 | I52: =WORKDAY.INTL(K50,0,1,Data!$C$3:$C$14) -> 45380 | J52: 1 | K52: =WORKDAY.INTL(I52,J52,1,Data!$C$3:$C$14) -> 45383 | M52: 1
B53: 7.6 | C53: Handover documentation | E53: =WORKDAY.INTL(G52,0,1,Data!$C$3:$C$14) -> 45316 | F53: 2 | G53: =WORKDAY.INTL(E53,F53,1,Data!$C$3:$C$14) -> 45320 | I53: =WORKDAY.INTL(K52,0,1,Data!$C$3:$C$14)+8 -> 45391 | J53: 1 | K53: =WORKDAY.INTL(I53,J53,1,Data!$C$3:$C$14) -> 45392 | M53: 1
B54: 7.7 | C54: Handover to Client | E54: =WORKDAY.INTL(G53,0,1,Data!$C$3:$C$14) -> 45320 | F54: 1 | G54: =WORKDAY.INTL(E54,F54,1,Data!$C$3:$C$14) -> 45321 | I54: =WORKDAY.INTL(K53,0,1,Data!$C$3:$C$14) -> 45392 | J54: 1 | K54: =WORKDAY.INTL(I54,J54,1,Data!$C$3:$C$14) -> 45393 | M54: 1
B55: 7.8 | C55: Handover to O&M | E55: =WORKDAY.INTL(G54,0,1,Data!$C$3:$C$14) -> 45321 | F55: 1 | G55: =WORKDAY.INTL(E55,F55,1,Data!$C$3:$C$14) -> 45322 | I55: =WORKDAY.INTL(K54,0,1,Data!$C$3:$C$14) -> 45393 | J55: 1 | K55: =WORKDAY.INTL(I55,J55,1,Data!$C$3:$C$14) -> 45394 | M55: 1
B57: 8 | C57: QA Inspections | E57: =MIN(E58) -> 45302 | F57: =SUM(F58) -> 1 | G57: =MAX(G58) -> 45302 | I57: =MIN(I58) -> 45333 | J57: =SUM(J58) -> 15 | K57: =MAX(K58) -> 45352 | M57: =(J58*M58)/J57 -> 1
B58: 8.1 | C58: Inspection | E58: =+G45+21 -> 45302 | F58: 1 | G58: =WORKDAY.INTL(E58,0,1,Data!$C$3:$C$14) -> 45302 | I58: =+K45+3 -> 45333 | J58: 15 | K58: =WORKDAY.INTL(I58,J58,1,Data!$C$3:$C$14) -> 45352 | M58: 1
B60: 9 | C60: SSEG | I60: =MIN(I61:I69) -> 46064 | J60: =SUM(J61:J67) -> 41 | K60: =MAX(K61:K69) -> 46121 | M60: 1
B61: 9.1 | C61: Control Phil Submission | I61: 46064 | J61: 2 | K61: =WORKDAY.INTL(I61,J61,1,Data!$C$3:$C$14) -> 46066 | M61: 0
B62: 9.2 | C62: Control Phil Pre-Approval | I62: =WORKDAY.INTL(K61,0,1,Data!$C$3:$C$14) -> 46066 | J62: 15 | K62: =WORKDAY.INTL(I62,J62,1,Data!$C$3:$C$14) -> 46087 | M62: 0
B63: 9.3 | C63: Onsite Meeting - SCADA & Control Stakeholders | I63: =WORKDAY.INTL(K62,0,1,Data!$C$3:$C$14) -> 46087 | J63: 2 | K63: =WORKDAY.INTL(I63,J63,1,Data!$C$3:$C$14) -> 46091 | M63: 0
B64: 9.4 | C64: Control Phil Approval | I64: =WORKDAY.INTL(K63,0,1,Data!$C$3:$C$14) -> 46091 | J64: 10 | K64: =WORKDAY.INTL(I64,J64,1,Data!$C$3:$C$14) -> 46105 | M64: 0
B65: 9.5 | C65: Implementation | I65: =WORKDAY.INTL(K64,0,1,Data!$C$3:$C$14) -> 46105 | J65: 5 | K65: =WORKDAY.INTL(I65,J65,1,Data!$C$3:$C$14) -> 46112 | M65: 0
B66: 9.6 | C66: Testing & Monitoring | I66: =WORKDAY.INTL(K65,0,1,Data!$C$3:$C$14) -> 46112 | J66: 5 | K66: =WORKDAY.INTL(I66,J66,1,Data!$C$3:$C$14) -> 46119 | M66: 0
B67: 9.7 | C67: Close Out | I67: =WORKDAY.INTL(K66,0,1,Data!$C$3:$C$14) -> 46119 | J67: 2 | K67: =WORKDAY.INTL(I67,J67,1,Data!$C$3:$C$14) -> 46121 | M67: 0
B68: 9.8
B69: 9.9

Sheet Data
C2: Public holidays | F2: Drop down list
C3: 44197 | F3: Approved
C4: 44277 | F4: Pending
C5: 44288 | F5: Declined
C6: 44291 | F6: Abanded
C7: 44313
C8: 44317
C9: 44363
C10: 44417
C11: 44463
C12: 44546
C13: 44555 | H13: Manual dates
C14: 44556

Sheet Expenditure Tracking
B2: HIGH LEVEL PROJECT EXPENDITURE TRACKING
F4: PLANNED | H4: ACTUAL | J4: Difference
B5: EXPENDITURE | F5: =SUM(F9:F22) -> 18682950 | H5: =SUM(H9:H22) -> 19234297 | J5: =SUM(J9:J22) -> -551347.32
B7: No. | D7: Item | F7: Planned Expenditure | H7: Actual Expenditure | J7: Saving / Overrun | L7: Comments on variations from planned expenditure
B9: ='Expenditure Breakdown'!B6 -> 1 | D9: ='Expenditure Breakdown'!C6 -> Panels | F9: ='Expenditure Breakdown'!J6 -> 8604405.8 | H9: ='Expenditure Breakdown'!V6 -> 7861415.3 | J9: =F9-H9 -> 742990.53
B10: ='Expenditure Breakdown'!B28 -> 2 | D10: ='Expenditure Breakdown'!C28 -> Inverters | F10: =+'Expenditure Breakdown'!J28 -> 1020000 | H10: =+'Expenditure Breakdown'!V28 -> 1056455 | J10: =F10-H10 -> -36455
B11: ='Expenditure Breakdown'!B34 -> 3 | D11: ='Expenditure Breakdown'!C34 -> Mounting Structures | F11: =+'Expenditure Breakdown'!J34 -> 524979 | H11: =+'Expenditure Breakdown'!V34 -> 351446.8 | J11: =F11-H11 -> 173532.2
B12: ='Expenditure Breakdown'!B40 -> 4 | D12: ='Expenditure Breakdown'!C40 -> DC Equipment | F12: =+'Expenditure Breakdown'!J40 -> 637505.76 | H12: =+'Expenditure Breakdown'!V40 -> 1160597.8 | J12: =F12-H12 -> -523092
B13: ='Expenditure Breakdown'!B54 -> 5 | D13: ='Expenditure Breakdown'!C54 -> Monitoring | F13: =+'Expenditure Breakdown'!J54 -> 24567 | H13: =+'Expenditure Breakdown'!V54 -> 102506.6 | J13: =F13-H13 -> -77939.6
B14: ='Expenditure Breakdown'!B76 -> 6 | D14: ='Expenditure Breakdown'!C76 -> AC Equipment | F14: =+'Expenditure Breakdown'!J76 -> 637698.26 | H14: =+'Expenditure Breakdown'!V76 -> 954731.35 | J14: =F14-H14 -> -317033.09
B15: ='Expenditure Breakdown'!B88 -> 7 | D15: ='Expenditure Breakdown'!C88 -> Product Add On | F15: ='Expenditure Breakdown'!J88 -> 4530000 | H15: ='Expenditure Breakdown'!V88 -> 625278.52 | J15: =F15-H15 -> 3904721.5
B16: ='Expenditure Breakdown'!B106 -> 8 | D16: ='Expenditure Breakdown'!C106 -> AC & DC installation | F16: =+'Expenditure Breakdown'!J106 -> 1661472 | H16: =+'Expenditure Breakdown'!V106 -> 1378000 | J16: =F16-H16 -> 283472
B17: ='Expenditure Breakdown'!B116 -> 9 | D17: ='Expenditure Breakdown'!C116 -> Site Logistics | F17: =+'Expenditure Breakdown'!J116 -> 289840.03 | H17: =+'Expenditure Breakdown'!V116 -> 143094.86 | J17: =F17-H17 -> 146745.17
B18: ='Expenditure Breakdown'!B134 -> 10 | D18: ='Expenditure Breakdown'!C134 -> Due Dilligence | F18: ='Expenditure Breakdown'!J134 -> 78746.85 | H18: ='Expenditure Breakdown'!V134 -> 54897.75 | J18: =F18-H18 -> 23849.1
B19: ='Expenditure Breakdown'!B142 -> 11 | D19: ='Expenditure Breakdown'!C142 -> BDP Commission | F19: =+'Expenditure Breakdown'!J142 -> 0 | H19: =+'Expenditure Breakdown'!V142 -> 0 | J19: =F19-H19 -> 0
B20: ='Expenditure Breakdown'!B144 -> 12 | D20: ='Expenditure Breakdown'!C144 -> Engineering | F20: =+'Expenditure Breakdown'!J144 -> 661555.24 | H20: =+'Expenditure Breakdown'!V144 -> 133516.32 | J20: =F20-H20 -> 528038.92
B21: ='Expenditure Breakdown'!B155 -> 13 | D21: ='Expenditure Breakdown'!C155 -> General Expenses | F21: =+'Expenditure Breakdown'!J155 -> 12180 | H21: =+'Expenditure Breakdown'!V155 -> 5372.6 | J21: =F21-H21 -> 6807.4
B22: ='Expenditure Breakdown'!B170 -> 14 | D22: ='Expenditure Breakdown'!C170 -> Service Add On | F22: =+'Expenditure Breakdown'!J170 -> 0 | H22: =+'Expenditure Breakdown'!V170 -> 5406984.4 | J22: =F22-H22 -> -5406984.4
D24: check: | F24: ='Expenditure Breakdown'!J2-F5 -> 0 | G24: ='Expenditure Breakdown'!#REF!-G5 -> #REF! | H24: ='Expenditure Breakdown'!V2-H5 -> 0

Sheet Installer Payment Schedule

Sheet Expenditure Breakdown
B2: PLANNED EXPENDITURE BREAKDOWN | J2: =SUM(J6:J214) -> 18682950 | L2: ACTUAL EXPENDITURE BREAKDOWN | V2: =SUM(V6:V214) -> 19234297 | W2: Comment
B4: No. | C4: Product / Service | D4: Description of Work | E4: QTY | F4: Rate / Unit | G4: Budget Total | H4: Payment date | J4: Total | L4: No. | M4: Prodcut / Service | N4: Description of Work | O4: QTY | P4: Rate / Unit | Q4: Actual Total | R4: Payment date | T4: PO NUMBER | U4: [Finance Only] INVOICE RECEIPT DATE | V4: Total
B6: 1 | C6: Panels | D6: Longi 455 | E6: 3846 | F6: 0.1 | G6: =$C$11*F6 -> 860440.58 | H6: ='Project Plan'!G20 -> 45098 | J6: =SUM(G6:G26) -> 8604405.8 | L6: =B6 -> 1 | M6: Panels | N6: Jinko 550Wp | O6: 3182 | P6: 0.1 | Q6: =+N11*P6 -> 799123.45 | R6: 45090 | T6: =Q6+Q11 -> 2093284.6 | U6: 45107 | V6: =SUM(Q6:Q26) -> 7861415.3 | X6: RT: this is from the PO Dayne signed: | Y6: Jinko ORDER 22 May
L7: 1 | M7: Panels | Q7: 379626.82 | R7: 45344 | U7: 45107
L8: 1 | M8: Panels | Q8: 881171.97 | R8: 45373 | U8: 45107
L9: 1 | M9: Panels | Q9: 1554041.6 | R9: 45376 | U9: 45107
L10: 1 | M10: Panels | Q10: 3083109.5 | R10: 45384 | U10: 45107
B11: 1 | C11: 8604405.8 | D11: 7265214 | F11: 0.9 | G11: =$C$11*F11 -> 7743965.2 | H11: =H6+30 -> 45128 | L11: 1 | M11: Panels | N11: 7991234.5 | P11: 0.9 | Q11: =7192111.01640814-Q7-Q8-Q9-Q10 -> 1294161.2 | R11: 45384 | U11: 45107 | Y11: =117849/(930*550) -> 0.23039883 | Z11: USD/Wp FCA Walvis Bay
L12: 1 | M12: Panels | N12: Allocated to 26 Marine Drive | O12: -75 | P12: =Q12/O12 -> 2511.39 | Q12: -188354.25 | R12: 45443 | U12: 45443
B13: 1 | D13: Module delivery to site | G13: 0 | H13: =H11 -> 45128 | L13: 1 | M13: Panels | N13: Shipping and Clearing | Q13: 39939.25 | R13: 45199 | U13: 45169 | X13: USD RoE: | Y13: 19.5 | Z13: as of 22 May
L14: 1 | M14: Panels | Q14: 3997.43 | R14: 45139 | U14: 45169
B15: 1 | L15: 1 | M15: Panels | N15: Shipping and Clearing | Y15: =(Y11)*Y13 -> 4.4927771 | Z15: per Wp
D16: Cash handling / Admin fees on | L16: 1 | M16: Panels
L17: 1 | M17: Panels | N17: Balance of order that went to Sable Square (6 Pallets)
L18: 1 | M18: Panels | N18: Jinko 550W | O18: 186
L19: 1 | M19: Panels
L20: 1 | M20: Panels | N20: Cash handling / Admin fees on | Q20: 5328.39 | R20: 45105 | U20: 45107
L21: 1 | M21: Panels
L22: 1 | M22: Panels | N22: Silver solutions - Forklift hire | Q22: 4300 | R22: 45225 | U22: 45230
L23: 1 | M23: Panels
L24: 1 | M24: Panels | N24: Delivery to storage | Q24: 4550 | R24: 45246 | U24: 45230
B25: 1 | L25: =B25 -> 1 | M25: Panels | N25: Handling in/Handling out | Q25: 420 | R25: 45246 | U25: 45230
B26: 1 | L26: =B26 -> 1 | M26: Panels | Y26: =+'Project Plan'!E3*Y15*1000 -> 7862045.5 | Z26: final price tbc once FEC booked
B28: 2 | C28: Inverters | D28: SMA 110 | E28: 12 | F28: 85000 | G28: =E28*F28 -> 1020000 | H28: ='Project Plan'!G23+30 -> 45141 | J28: =SUM(G28:G32) -> 1020000 | L28: =B28 -> 2 | M28: Inverters | N28: Huawei 100ktl - Deposit | O28: 12 | P28: 89060 | Q28: =O28*P28*0.1 -> 106872 | R28: 45155 | U28: 45169 | V28: =SUM(Q28:Q32) -> 1056455 | W28: changed from 89000
B29: 2 | H29: =H28 -> 45141 | L29: =B29 -> 2 | M29: Inverters | N29: Huawei 100KTl - Balance | Q29: =O28*P28*0.9 -> 961848 | R29: 45202 | U29: 45169
L30: 2 | M30: Inverters | N30: Huawei 100KTl - Replace faulty Inverter | Q30: 76795 | R30: 45474 | U30: 45443
B31: 2 | L31: =B31 -> 2 | M31: Inverters | N31: Huawei 100KTl - RMA from Supplaier allocated to Stock | Q31: -89060 | R31: 45535 | U31: 45535
B32: 2 | L32: =B32 -> 2 | M32: Inverters
B34: 3 | C34: Mounting Structures | D34: Lumax | G34: =+'Project Plan'!E3*0.3*1000 -> 524979 | H34: ='Project Plan'!G30+30 -> 45127 | J34: =SUM(G34:G38) -> 524979 | L34: =B34 -> 3 | M34: Mounting Structures | N34: Schletter | P34: =Q34/'Project Plan'!E3/1000 -> 0.18316276 | Q34: 320522 | R34: 45148 | U34: 45107 | V34: =SUM(Q34:Q38) -> 351446.8
B35: 3 | L35: =B35 -> 3 | M35: Mounting Structures | Q35: 24371 | R35: 45148 | U35: 45107
M36: Mounting Structures | N36: Schletter - Additional Clamps | Q36: 6553.8 | R36: 45351 | U36: 45351
B37: 3 | L37: =B37 -> 3 | M37: Mounting Structures | N37: Stock allocated to Dekro Paint | Q37: =18280.34*-1 -> -18280.34 | R37: 45138 | U37: =U35 -> 45107
B38: 3 | L38: =B38 -> 3 | M38: Mounting Structures | N38: Received the stock back from Dekro Paint | Q38: =Q37*-1 -> 18280.34 | R38: 45138 | U38: =U37 -> 45107
B40: 4 | C40: DC Equipment | D40: DC Cable | E40: 29292 | F40: 11.28 | G40: =E40*F40 -> 330413.76 | H40: =+'Project Plan'!K32+30 -> 45203 | J40: =SUM(G40:G51) -> 637505.76 | L40: =B40 -> 4 | M40: DC Equipment | N40: DC Cable - Red - Delivered | O40: 20000 | P40: 13.92 | Q40: =O40*P40 -> 278400 | R40: 45169 | T40: Rubicon Bulk Order | U40: 45169 | V40: =SUM(Q40:Q51) -> 1160597.8
B41: 4 | D41: Earth Cable | E41: =+E40 -> 29292 | F41: 10.3 | G41: =E41*F41 -> 301707.6 | H41: =+H40 -> 45203 | L41: =B41 -> 4 | M41: DC Equipment | N41: DC Cable - Black - Delivered | O41: 20000 | P41: 13.92 | Q41: =O41*P41 -> 278400 | R41: =R40 -> 45169 | T41: Rubicon Bulk Order | U41: 45169
M43: DC Equipment | N43: DC Cable - Zonn - Red | O43: 3500 | P43: 15.47 | Q43: =O43*P43 -> 54145 | R43: 45205 | U43: 45169
M44: DC Equipment | N44: DC Cable - Zonn - Black | O44: 3500 | P44: 14.6 | Q44: =O44*P44 -> 51100 | R44: 45205 | U44: 45169
M46: DC Equipment | N46: DC Cable - KBE - Red - Krannich | O46: 3000 | P46: 14.28 | Q46: 42841.93 | R46: 45243 | T46: =SUM(Q46:Q47) -> 85683.86 | U46: 45230
M47: DC Equipment | N47: DC Cable - KBE - Black - Krannich | O47: 3000 | P47: 14.28 | Q47: 42841.93 | R47: 45243 | U47: 45230
Q48: 725 | R48: 45243 | U48: 45230
B49: 4 | D49: Earth clamp | E49: =+E6/10 -> 384.6 | F49: 14 | G49: =E49*F49 -> 5384.4 | H49: =H41 -> 45203 | L49: =B49 -> 4 | M49: DC Equipment | N49: DC Equipment - Deposit | O49: 0.5 | P49: =Z113 -> 420555 | Q49: =+$P$49*O49 -> 210277.5 | R49: 45092 | U49: 45107
L50: 4 | M50: DC Equipment | N50: DC Equipment - Onsite | O50: 0.4 | Q50: =+$P$49*O50 -> 168222 | R50: 45169 | U50: 45169
B51: 4 | L51: =B51 -> 4 | M51: DC Equipment | N51: DC Equipment - Retention | O51: 0.1 | P51: 42055.5 | Q51: =P51*0.8 -> 33644.4 | R51: 45484 | U51: 45473
L52: =B52 -> 0 | M52: DC Equipment | N52: DC Equipment - Retention | Q52: =P51*0.2 -> 8411.1 | R52: 45519 | U52: 45473
B54: 5 | C54: Monitoring | D54: Solarlog | G54: 21000 | H54: =H28 -> 45141 | J54: =SUM(G54:G74) -> 24567 | L54: =B54 -> 5 | M54: Monitoring | N54: Smartlogger - Deposit | Q54: =7499*0.1 -> 749.9 | R54: =R28 -> 45155 | U54: 45169 | V54: =SUM(Q54:Q74) -> 102506.6
B55: 5 | D55: Revenue Grade Meter | G55: 3567 | H55: 45014 | L55: =B55 -> 5 | M55: Monitoring | N55: Smartlogger - Balance | Q55: =7499*0.9 -> 6749.1 | R55: 45202 | U55: 45169
L56: 5 | M56: Monitoring | N56: Smartlogger Replacement | Q56: 9011 | R56: 45351 | U56: 45322
B57: 5 | L57: =B57 -> 5 | M57: Monitoring | N57: Techsitter X2 | Q57: 26788 | R57: 45350 | T57: Techsitter Inv: MN8940233 | U57: 45322
L58: 5 | M58: Monitoring | N58: Shipping of Techsitters | Q58: 242.39 | R58: 45351 | T58: DSV Inv: 180047661 | U58: 45322
L59: 5 | M59: Monitoring | N59: SPD | Q59: 1655 | R59: 45176 | T59: Plustead electrical Inv: 1001/97633203 | U59: 45176
L60: 5 | M60: Monitoring | N60: Techsitter | O60: 0 | P60: 15000 | Q60: =O60*P60 -> 0
L61: 5 | M61: Monitoring | N61: Techsitter CTs | Q61: 9006.66 | R61: 45351 | U61: 45322
L62: 5 | M62: Monitoring | N62: CT's | Q62: 4910 | R62: 45338 | T62: Accuenergy Inv: ASAI-002363 | U62: 45322
L63: 5 | M63: Monitoring | N63: UPS | Q63: 2082.61 | R63: 45096 | U63: 45107
L64: 5 | M64: Monitoring | Q64: 1999.13 | R64: 45330 | T64: Roedolph Exp Claim | U64: 45322
L65: 5 | M65: Monitoring | N65: Switch | Q65: 239.13 | R65: 45031 | U65: 45077
L66: 5 | M66: Monitoring | Q66: 6225 | R66: 45338 | T66: Accuenergy Inv: ASAI-002350 | U66: 45322
L67: 5 | M67: Monitoring | N67: Router | O67: 1 | P67: 2694 | Q67: 2969.31 | R67: 45127 | U67: 45138
L68: 5 | M68: Monitoring | N68: Lithium Batteries | Q68: 2606.09 | R68: 45313 | T68: Takelot - Order 145230153 | U68: 45322
L69: 5 | M69: Monitoring | N69: Battery Charger UPS | Q69: 1039 | R69: 45148 | U69: 45169
L70: 5 | M70: Monitoring | Q70: 2463 | R70: 45316 | T70: Current Automation Inv: SOQ294289 | U70: 45322
B71: 5 | L71: 5 | M71: Monitoring | N71: Pyronometer | Q71: 11667.2 | R71: 45428 | T71: Geosun Inv: 2366 | U71: 45412
B72: 5 | L72: 5 | M72: Monitoring | N72: Delivery | Q72: 433.29 | R72: 45443 | U72: 45412
B73: 5 | L73: 5 | M73: Monitoring | N73: Power Supply | Q73: 1201.79 | R73: 45330 | T73: Roedolph Exp Claim | U73: 45322
B74: 5 | L74: 5 | M74: Monitoring | N74: Rogowski Coil Kit + Delivery | Q74: 10469 | R74: 45351 | T74: Accuenergy Inv: 002453 | U74: 45322
Y75: BUDGET | Z75: Installer Allocation
B76: 6 | C76: AC Equipment | D76: 50% Deposit | F76: 0.5 | G76: =$C$86*F76 -> 318849.13 | H76: ='Project Plan'!G20-5 -> 45093 | J76: =SUM(G76:G86) -> 637698.26 | L76: =B76 -> 6 | M76: AC Equipment | N76: AC Equipment - Deposit | O76: =Z112 -> 388553.54 | P76: 0.5 | Q76: =+O76*0.5 -> 194276.77 | R76: 45092 | U76: 45107 | V76: =SUM(Q76:Q86) -> 954731.35 | Y76: AC Equipment | Z76: =+J76 -> 637698.26
B77: 6 | L77: =B77 -> 6 | M77: AC Equipment | N77: AC Equipment - Onsite | P77: 0.4 | Q77: =100000/1.15 -> 86956.522 | R77: 45317 | U77: 45291 | Y77: DC Equipment | Z77: =+G41+G49 -> 307092
L78: =B78 -> 0 | M78: AC Equipment | N78: AC Equipment - Onsite | Q78: =155421.416-Q77 -> 68464.894 | R78: 45323 | U78: 45291
B79: 6 | L79: =B79 -> 6 | M79: AC Equipment | N79: AC Equipment - Retention | O79: 38855.354 | P79: 0.1 | Q79: =O79*0.8 -> 31084.283 | R79: 45484 | U79: 45473 | Y79: AC Labour | Z79: =+C107 -> 437482.5
Q80: =O79*0.2 -> 7771.0708 | R80: 45519 | U80: 45473
N81: Switch Board - PV DB | Q81: 434902.77 | R81: 45198 | U81: 45138
N82: Switch Board - Comms DB | Q82: 6757.02 | R82: 45198 | U82: 45138
N83: Switch Board - Site Work | Q83: 87414.48 | R83: 45198 | U83: 45138
N84: Switch Board - Cubicle | Q84: 37103.54 | R84: 45231 | U84: 45230 | W84: TC: Added cost 24/10/2023
W85: RV: Switchboard absorbed the cost
B86: 6 | C86: 637698.26 | D86: 50% on site | F86: 0.5 | G86: =$C$86*F86 -> 318849.13 | H86: ='Project Plan'!G26 -> 45203 | L86: =B86 -> 6 | M86: AC Equipment | Y86: DC Labour | Z86: =+C109 -> 1223989.5
Y87: Offloading | Z87: =+G122 -> 8500
B88: 7 | C88: Product Add On | D88: SCADA & SSEG extras | G88: 280000 | H88: 45054 | J88: =SUM(G88:G104) -> 4530000 | L88: =B88 -> 7 | M88: Product Add On | N88: Metering & SCADA & SSEG extras | O88: =323886.66/1.15 -> 281640.57 | Q88: =O88 -> 281640.57 | R88: 45435 | T88: PO3053-MGP-20240412 | U88: 45443 | V88: =SUM(Q88:Q104) -> 625278.52 | Y88: Roof Access | Z88: =+G116+G118 -> 92066.7
N89: Fibre Installation 40% Deposit | Q89: =47816.52/1.15 -> 41579.583 | R89: 45351 | T89: Comtel Inv: CEIN023698 | U89: 45351
N90: Fibre Installation 60% Balance | Q90: =103948.95-Q89 -> 62369.367 | R90: 45394 | U90: 45351
B91: 7 | D91: CAPEX Expenditure | G91: 4000000 | H91: 45054 | L91: =B91 -> 7 | M91: Product Add On | N91: Waterpoints | Q91: 21664 | R91: 45484 | T91: PO3204-MGP-20240627 | U91: 45473 | Y91: Other | Z91: 0
B92: 7 | D92: Walkways, Inverter Cages, Warranty Extensions | G92: 250000 | H92: 45054 | L92: =B92 -> 7 | M92: Product Add On | N92: Cat Ladder, Inverter Cages | Y92: Other | Z92: 0
N93: Site Demob
N94: FDT Electric Aircon Installation 50% Deposit | Q94: =14310*2 -> 28620 | R94: 45320 | U94: 45322
N95: FDT Electric Aircon Installation 2nd Unit 50% Deposit | Q95: =29350/2 -> 14675 | R95: 45376 | T95: PO3008-MGP-20240319 | U95: 45382
Q96: =29350/2 -> 14675 | R96: 45394 | U96: 45382
N97: Lester & Co | Q97: 2850 | R97: 45428 | U97: 45443 | W97: PO3092-MGP-20240507
N98: Brice & Co. Inverter room modification & Roof Gate | Q98: 29745 | R98: 45099 | U98: 45107
N99: Brice & Co Inverter Steel Structure - Deposit | Q99: =39885*0.5 -> 19942.5 | R99: 45316 | T99: Brice & Co Inv: BC/0154 | U99: 45260
N100: Brice & Co Inverter Steel Structure - Balance | Q100: =39885*0.5 -> 19942.5 | R100: =R99 -> 45316 | T100: Brice & Co Inv: BC/0154 | U100: 45260
N101: All in Glass Aluminium - Single Y Louvred door | Q101: 10780 | R101: 45282 | U101: 45260
N102: 100KTL inverter to be replaced by RMA | Q102: 76795 | R102: 45474 | U102: 45443
N103: All in Glass Aluminium - Healt & Safety File | Q103: 0
B104: 7 | L104: =B104 -> 7 | M104: Product Add On | N104: Lifelines, Temporary Walkboards | Q104: 0 | W104: RV: 75k removed | Y104: Other | Z104: 0
B105: Only services to be capture below, products above | Y105: Total | Z105: =SUM(Z76:Z104) -> 2706829
B106: 8 | C106: AC & DC installation | D106: Upfront | F106: 0.3 | G106: =($C$107+$C$109)*F106 -> 498441.6 | H106: =H76 -> 45093 | J106: =SUM(G106:G114) -> 1661472 | L106: =B106 -> 8 | M106: AC & DC installation | N106: Upfront | O106: =Z114 -> 360000 | P106: 0.2 | Q106: =+($O$106+$O$107)*P106 -> 275600 | R106: 45092 | U106: 45107 | V106: =SUM(Q106:Q114) -> 1378000 | Y106: Less 15% | Z106: =+Z105*0.85 -> 2300804.6
B107: 8 | C107: 437482.5 | D107: AC Complete | F107: 0.15 | G107: =($C$107+$C$109)*F107 -> 249220.8 | H107: ='Project Plan'!G26 -> 45203 | L107: =B107 -> 8 | M107: AC & DC installation | N107: MS Complete - Partial | O107: =Z115 -> 1018000 | P107: 0.15 | Q107: 168222 | R107: 45169 | U107: 45169 | Y107: R/Wp | Z107: =+Z106/'Project Plan'!E3/1000 -> 1.3147981
L108: =B108 -> 0 | M108: AC & DC installation | N108: MS Complete - Partial | P108: 0.15 | Q108: =206700-Q107 -> 38478 | R108: 45148 | U108: 45169
B109: 8 | C109: 1223989.5 | D109: DC Complete | F109: 0.15 | G109: =($C$107+$C$109)*F109 -> 249220.8 | H109: ='Project Plan'!G40 -> 45267 | L109: =B109 -> 8 | M109: AC & DC installation | N109: Panels Complete | P109: 0.15 | Q109: =+($O$106+$O$107)*P109 -> 206700 | R109: 45247 | U109: 45260
...

Sheet Expenditure Breakdown-IDC
A2: ACTUAL EXPENDITURE BREAKDOWN | H2: =SUM(H6:H93) -> 18009414
A4: No. | B4: Prodcut / Service | C4: Description of Work | D4: QTY | E4: Rate / Unit | F4: Actual Total | G4: Payment date | H4: Total | I4: DIRECTORY & COMMENTS (The below indicates the directory of the invoices for the associated material/service that incurred an expense during the project)
A6: 1 | B6: Panels | C6: Jinko 550W Solar Panel - Deposit | D6: 3182 | E6: 0.1 | F6: 799123.45 | G6: 45090 | H6: 8049769.5 | I6: IDC Funding\Busamed+Spear Round2\Busamed+Spear Shared Folder\7. Drawdown Requests\Mega Park Phase 2\Invoices\1. Panels
A7: 1 | B7: Panels | C7: Jinko 550W Solar Panel - Balance | E7: 0.9 | F7: 7192111 | G7: 45327
A8: 1 | B8: Panels | C8: Shipping and Clearing | F8: 39939.25 | G8: 45199
A9: 1 | B9: Panels | C9: Shipping and Clearing | F9: 3997.43 | G9: 45139
A10: 1 | B10: Panels | C10: Cash handling / Admin fees on | F10: 5328.39 | G10: 45105
A11: 1 | B11: Panels | C11: Silver solutions - Forklift hire | F11: 4300 | G11: 45225
A12: 1 | B12: Panels | C12: Delivery to storage | F12: 4550 | G12: 45246
A13: 1 | B13: Panels | C13: Handling in/Handling out | F13: 420 | G13: 45246
A15: 2 | B15: Inverters | C15: Huawei 100ktl - Deposit | D15: 12 | E15: 89060 | F15: 106872 | G15: 45155 | H15: 1068720 | I15: IDC Funding\Busamed+Spear Round2\Busamed+Spear Shared Folder\7. Drawdown Requests\Mega Park Phase 2\Invoices\2. Inverters
A16: 2 | B16: Inverters | C16: Huawei 100KTl - Balance | F16: 961848 | G16: 45202
A18: 3 | B18: Mounting Structures | C18: Schletter | F18: 320522 | G18: 45148 | H18: 351446.8 | I18: IDC Funding\Busamed+Spear Round2\Busamed+Spear Shared Folder\7. Drawdown Requests\Mega Park Phase 2\Invoices\3. Balance of System
A19: 3 | B19: Mounting Structures | C19: Schletter - Additional Clamps | F19: 24371 | G19: 45148
A20: 3 | B20: Mounting Structures | C20: Schletter - Additional Clamps | F20: 6553.8 | G20: 45350
A21: 3 | B21: Mounting Structures | C21: Stock allocated to Dekro Paint | F21: -18280.34 | G21: 45138
A22: 3 | B22: Mounting Structures | C22: Received the stock back from Dekro Paint | F22: 18280.34 | G22: 45138
A24: 4 | B24: DC Equipment | C24: DC Cable - Red - Delivered | D24: 20000 | E24: 13.92 | F24: 278400 | G24: 45169 | H24: 1169008.9 | I24: IDC Funding\Busamed+Spear Round2\Busamed+Spear Shared Folder\7. Drawdown Requests\Mega Park Phase 2\Invoices\3. Balance of System
A25: 4 | B25: DC Equipment | C25: DC Cable - Black - Delivered | D25: 20000 | E25: 13.92 | F25: 278400 | G25: 45169
A26: 4 | B26: DC Equipment | C26: DC Cable - Zonn - Red | D26: 3500 | E26: 15.47 | F26: 54145 | G26: 45205
A27: 4 | B27: DC Equipment | C27: DC Cable - Zonn - Black | D27: 3500 | E27: 14.6 | F27: 51100 | G27: 45205
A28: 4 | B28: DC Equipment | C28: DC Cable - KBE - Red - Krannich | D28: 3000 | E28: 14.28 | F28: 42841.93 | G28: 45243
A29: 4 | B29: DC Equipment | C29: DC Cable - KBE - Black - Krannich | D29: 3000 | E29: 14.28 | F29: 42841.93 | G29: 45243
A30: 4 | B30: DC Equipment - Subcontractor | C30: DC Equipment - Deposit | D30: 0.5 | E30: 420555 | F30: 210277.5 | G30: 45092 | I30: IDC Funding\Busamed+Spear Round2\Busamed+Spear Shared Folder\7. Drawdown Requests\Mega Park Phase 2\Invoices\4. Subcontractors
A31: 4 | B31: DC Equipment - Subcontractor | C31: DC Equipment - Onsite | D31: 0.4 | F31: 168222 | G31: 45169
A32: 4 | B32: DC Equipment - Subcontractor | C32: DC Equipment - Retention | D32: 0.1 | F32: 42055.5 | G32: 45348
A34: 5 | B34: Monitoring | C34: Smartlogger - Deposit | F34: 749.9 | G34: 45155 | H34: 142410.71 | I34: IDC Funding\Busamed+Spear Round2\Busamed+Spear Shared Folder\7. Drawdown Requests\Mega Park Phase 2\Invoices\3. Balance of System
A35: 5 | B35: Monitoring | C35: Smartlogger - Balance | F35: 6749.1 | G35: 45202
A36: 5 | B36: Monitoring | C36: Smartlogger Replacement | F36: 9011 | G36: 45351
A37: 5 | B37: Monitoring | C37: Techsitter X2 | F37: 26788 | G37: 45322
A38: 5 | B38: Monitoring | C38: SPD | F38: 1655 | G38: 45176
A39: 5 | B39: Monitoring | C39: Techsitter | D39: 4 | E39: 15000 | F39: 60000 | G39: 45350
A40: 5 | B40: Monitoring | C40: Techsitter CTs | F40: 9006.66 | G40: 45350
A41: 5 | B41: Monitoring | C41: UPS | F41: 2082.61 | G41: 45096
A42: 5 | B42: Monitoring | C42: Switch | F42: 239.13 | G42: 45031
A43: 5 | B43: Monitoring | C43: Router | D43: 1 | E43: 2694 | F43: 2969.31 | G43: 45127
A44: 5 | B44: Monitoring | C44: Battery Charger UPS | F44: 1039 | G44: 45148
A45: 5 | B45: Monitoring | C45: Comms | F45: 15000 | G45: 45350
A46: 5 | B46: Monitoring | C46: Ethernet Switches | F46: 6300 | G46: 45322
A47: 5 | B47: Monitoring | C47: Power Supply | F47: 821 | G47: 45322
A49: 6 | B49: AC Equipment-Subcontractor | C49: AC Equipment - Deposit | D49: 388553.54 | E49: 0.5 | F49: 194276.77 | G49: 45092 | H49: 954731.35 | I49: IDC Funding\Busamed+Spear Round2\Busamed+Spear Shared Folder\7. Drawdown Requests\Mega Park Phase 2\Invoices\4. Subcontractors
A50: 6 | B50: AC Equipment-Subcontractor | C50: AC Equipment - Onsite | E50: 0.4 | F50: 86956.522 | G50: 45317
A51: 6 | B51: AC Equipment-Subcontractor | C51: AC Equipment - Onsite | F51: 68464.894 | G51: 45322
A52: 6 | B52: AC Equipment-Subcontractor | C52: AC Equipment - Retention | E52: 0.1 | F52: 38855.354 | G52: 45348
A53: 6 | B53: AC Equipment | C53: Switch Board - PV DB | F53: 434902.77 | G53: 45198 | I53: IDC Funding\Busamed+Spear Round2\Busamed+Spear Shared Folder\7. Drawdown Requests\Mega Park Phase 2\Invoices\3. Balance of System
A54: 6 | B54: AC Equipment | C54: Switch Board - Comms DB | F54: 6757.02 | G54: 45198
A55: 6 | B55: AC Equipment | C55: Switch Board - Site Work | F55: 87414.48 | G55: 45198
A56: 6 | B56: AC Equipment | C56: Switch Board - Cubicle | F56: 37103.54 | G56: 45231
A58: 7 | B58: Product Add On | C58: Metering & SCADA & SSEG extras | F58: 400000 | G58: 45348 | H58: 534030 | I58: IDC Funding\Busamed+Spear Round2\Busamed+Spear Shared Folder\7. Drawdown Requests\Mega Park Phase 2\Invoices\3. Balance of System
A59: 7 | B59: Product Add On | C59: Waterpoints | F59: 25000 | G59: 45348
A60: 7 | B60: Product Add On | C60: FDT Electric Aircon Installation 50% Deposit | F60: 28620 | G60: 45320
A61: 7 | B61: Product Add On | C61: Brice & Co. Inverter room modification & Roof Gate | F61: 29745 | G61: 45099
A62: 7 | B62: Product Add On | C62: Brice & Co Inverter Steel Structure - Deposit | F62: 19942.5 | G62: 45316
A63: 7 | B63: Product Add On | C63: Brice & Co Inverter Steel Structure - Balance | F63: 19942.5 | G63: 45316
A64: 7 | B64: Product Add On | C64: All in Glass Aluminium - Single Y Louvred door | F64: 10780 | G64: 45282
A66: 8 | B66: AC & DC installation | C66: Upfront | D66: 360000 | E66: 0.2 | F66: 275600 | G66: 45092 | H66: 1378000 | I66: IDC Funding\Busamed+Spear Round2\Busamed+Spear Shared Folder\7. Drawdown Requests\Mega Park Phase 2\Invoices\4. Subcontractors
A67: 8 | B67: AC & DC installation | C67: MS Complete - Partial | D67: 1018000 | E67: 0.15 | F67: 175695 | G67: 45141
A68: 0 | B68: AC & DC installation | C68: MS Complete - Partial | E68: 0.15 | F68: 31005 | G68: 45148
A69: 8 | B69: AC & DC installation | C69: Panels Complete | E69: 0.15 | F69: 206700 | G69: 45247
A70: 8 | B70: AC & DC installation | C70: AC Tie-In complete | E70: 0.15 | F70: 206700 | G70: 45335
A71: 8 | B71: AC & DC installation | C71: Practical Completion | E71: 0.2 | F71: 275600 | G71: 45335
A72: 8 | B72: AC & DC installation | C72: Retention | E72: 0.15 | F72: 206700 | G72: 45348
A74: 9 | B74: Site logistics - Subcontractor | C74: Site logistics - Deposit | D74: 0.5 | F74: 50550 | G74: 45092 | H74: 156400 | I74: IDC Funding\Busamed+Spear Round2\Busamed+Spear Shared Folder\7. Drawdown Requests\Mega Park Phase 2\Invoices\4. Subcontractors
A75: 9 | B75: Site logistics - Subcontractor | C75: Site Logistics - Onsite | D75: 0.4 | F75: 40440 | G75: 45281
A76: 9 | B76: Site logistics - Subcontractor | C76: Site logistics - Retention | D76: 0.1 | F76: 10110 | G76: 45348
A77: 9 | B77: Site logistics - Subcontractor | C77: Forklift | F77: 4300 | G77: 45225
A78: 9 | B78: Site logistics - Subcontractor | C78: Telehandler Extra - VO Smart Solar | F78: 36000 | G78: 45335
A79: 9 | B79: Site logistics - Emergent | C79: Site Office - August | F79: 739.83 | G79: 45261 | I79: IDC Funding\Busamed+Spear Round2\Busamed+Spear Shared Folder\7. Drawdown Requests\Mega Park Phase 2\Invoices\4. Subcontractors
A80: 9 | B80: Site logistics - Emergent | C80: Site Office - September | F80: 573.91 | G80: 45261
A81: 9 | B81: Site logistics - Emergent | C81: Site Office - October | F81: 584.11 | G81: 45261
A82: 9 | B82: Site logistics - Emergent | C82: Site Office - November | F82: 585.3 | G82: 45261
A83: 9 | B83: Site logistics - Emergent | C83: Site Office - December | F83: 470.12 | G83: 45316
A85: 10 | B85: Due Dilligence | C85: Structural sign off | F85: 11750 | G85: 44994 | H85: 54896.7 | I85: IDC Funding\Busamed+Spear Round2\Busamed+Spear Shared Folder\7. Drawdown Requests\Mega Park Phase 2\Invoices\4. Subcontractors
A86: 10 | B86: Due Dilligence | C86: Electrical Sign off | F86: 26248.95 | G86: 45348
A87: 10 | B87: Due Dilligence | C87: SSEg Costs | F87: 16276 | G87: 45229
A88: 10 | B88: Due Dilligence | C88: Red Team | F88: 621.75 | G88: 45260
A90: 14 | B90: Service Add On | C90: Welcome Bonus - 1 | F90: 2000000 | G90: 45350 | H90: 4150000 | I90: IDC Funding\Busamed+Spear Round2\Busamed+Spear Shared Folder\7. Drawdown Requests\Mega Park Phase 2\Invoices\4. Subcontractors
A91: 14 | B91: Service Add On | C91: Welcome Bonus - 2 | F91: 2000000 | G91: 45350
A92: 14 | B92: Service Add On | C92: Penalties - December 2023 | F92: 75000 | G92: 45322
A93: 14 | B93: Service Add On | C93: Penalties - January 2024 | F93: 75000 | G93: 45322

Sheet Cashflow
D1: [RT: Double Check the first date is always a MONDAY] | F1: 44963 | G1: =F1+7 -> 44970 | H1: =G1+7 -> 44977 | I1: =H1+7 -> 44984 | J1: =I1+7 -> 44991 | K1: =J1+7 -> 44998 | L1: =K1+7 -> 45005 | M1: =L1+7 -> 45012 | N1: =M1+7 -> 45019 | ... EI1: =EH1+7 -> 45894
A2: PLANNED | C2: CHECK | D2: CHECK
B3: Planned Revenue | C3: ='Revenue Tracking'!D4 -> 20939009 | D3: =SUM(F3:BR3) -> 20939009 | F3: =SUMIFS('Revenue Tracking'!$F$13:$F$30, 'Revenue Tracking'!$H$13:$H$30, ">="&F1,'Revenue Tracking'!$H$13:$H$30, "<"&G1) -> 0 | G3: =SUMIFS('Revenue Tracking'!$F$13:$F$30, 'Revenue Tracking'!$H$13:$H$30, ">="&G1,'Revenue Tracking'!$H$13:$H$30, "<"&H1) -> 10469504 | H3: =SUMIFS('Revenue Tracking'!$F$13:$F$30, 'Revenue Tracking'!$H$13:$H$30, ">="&H1,'Revenue Tracking'!$H$13:$H$30, "<"&I1) -> 0 | I3: =SUMIFS('Revenue Tracking'!$F$13:$F$30, 'Revenue Tracking'!$H$13:$H$30, ">="&I1,'Revenue Tracking'!$H$13:$H$30, "<"&J1) -> 0 | J3: =SUMIFS('Revenue Tracking'!$F$13:$F$30, 'Revenue Tracking'!$H$13:$H$30, ">="&J1,'Revenue Tracking'!$H$13:$H$30, "<"&K1) -> 0 | K3: =SUMIFS('Revenue Tracking'!$F$13:$F$30, 'Revenue Tracking'!$H$13:$H$30, ">="&K1,'Revenue Tracking'!$H$13:$H$30, "<"&L1) -> 0 | L3: =SUMIFS('Revenue Tracking'!$F$13:$F$30, 'Revenue Tracking'!$H$13:$H$30, ">="&L1,'Revenue Tracking'!$H$13:$H$30, "<"&M1) -> 0 | M3: =SUMIFS('Revenue Tracking'!$F$13:$F$30, 'Revenue Tracking'!$H$13:$H$30, ">="&M1,'Revenue Tracking'!$H$13:$H$30, "<"&N1) -> 0 | ... BU3: =SUMIFS('Revenue Tracking'!$F$13:$F$30, 'Revenue Tracking'!$H$13:$H$30, ">="&BU1,'Revenue Tracking'!$H$13:$H$30, "<"&BV1) -> 0 | BV3: =SUMIFS('Revenue Tracking'!$F$13:$F$30, 'Revenue Tracking'!$H$13:$H$30, ">="&BV1,'Revenue Tracking'!$H$13:$H$30, "<"&EJ1) -> 0 | BW3: =SUMIFS('Revenue Tracking'!$F$13:$F$30, 'Revenue Tracking'!$H$13:$H$30, ">="&BW1,'Revenue Tracking'!$H$13:$H$30, "<"&EK1) -> 0 | BX3: =SUMIFS('Revenue Tracking'!$F$13:$F$30, 'Revenue Tracking'!$H$13:$H$30, ">="&BX1,'Revenue Tracking'!$H$13:$H$30, "<"&EL1) -> 0 | BY3: =SUMIFS('Revenue Tracking'!$F$13:$F$30, 'Revenue Tracking'!$H$13:$H$30, ">="&BY1,'Revenue Tracking'!$H$13:$H$30, "<"&EM1) -> 0 | BZ3: =SUMIFS('Revenue Tracking'!$F$13:$F$30, 'Revenue Tracking'!$H$13:$H$30, ">="&BZ1,'Revenue Tracking'!$H$13:$H$30, "<"&EN1) -> 0 | CA3: =SUMIFS('Revenue Tracking'!$F$13:$F$30, 'Revenue Tracking'!$H$13:$H$30, ">="&CA1,'Revenue Tracking'!$H$13:$H$30, "<"&EO1) -> 0 | CB3: =SUMIFS('Revenue Tracking'!$F$13:$F$30, 'Revenue Tracking'!$H$13:$H$30, ">="&CB1,'Revenue Tracking'!$H$13:$H$30, "<"&EP1) -> 0 | CC3: =SUMIFS('Revenue Tracking'!$F$13:$F$30, 'Revenue Tracking'!$H$13:$H$30, ">="&CC1,'Revenue Tracking'!$H$13:$H$30, "<"&EQ1) -> 0 | ... EI3: =SUMIFS('Revenue Tracking'!$F$13:$F$30, 'Revenue Tracking'!$H$13:$H$30, ">="&EI1,'Revenue Tracking'!$H$13:$H$30, "<"&GW1) -> 0
B4: Planned Revenue - Cumulative | F4: =F3 -> 0 | G4: =F4+G3 -> 10469504 | H4: =G4+H3 -> 10469504 | I4: =H4+I3 -> 10469504 | J4: =I4+J3 -> 10469504 | K4: =J4+K3 -> 10469504 | L4: =K4+L3 -> 10469504 | M4: =L4+M3 -> 10469504 | N4: =M4+N3 -> 10469504 | ... EI4: =EH4+EI3 -> 20939009
B5: Planned Expenditure | C5: ='Revenue Tracking'!D5 -> 18682950 | D5: =SUM(F5:BR5) -> 18682950 | G5: =SUMIFS('Expenditure Breakdown'!$G$6:$G$212, 'Expenditure Breakdown'!$H$6:$H$212, ">="&G1,'Expenditure Breakdown'!$H$6:$H$212, "<"&H1) -> 0 | H5: =SUMIFS('Expenditure Breakdown'!$G$6:$G$212, 'Expenditure Breakdown'!$H$6:$H$212, ">="&H1,'Expenditure Breakdown'!$H$6:$H$212, "<"&I1) -> 0 | I5: =SUMIFS('Expenditure Breakdown'!$G$6:$G$212, 'Expenditure Breakdown'!$H$6:$H$212, ">="&I1,'Expenditure Breakdown'!$H$6:$H$212, "<"&J1) -> 0 | J5: =SUMIFS('Expenditure Breakdown'!$G$6:$G$212, 'Expenditure Breakdown'!$H$6:$H$212, ">="&J1,'Expenditure Breakdown'!$H$6:$H$212, "<"&K1) -> 897757.52 | K5: =SUMIFS('Expenditure Breakdown'!$G$6:$G$212, 'Expenditure Breakdown'!$H$6:$H$212, ">="&K1,'Expenditure Breakdown'!$H$6:$H$212, "<"&L1) -> 0 | L5: =SUMIFS('Expenditure Breakdown'!$G$6:$G$212, 'Expenditure Breakdown'!$H$6:$H$212, ">="&L1,'Expenditure Breakdown'!$H$6:$H$212, "<"&M1) -> 0 | M5: =SUMIFS('Expenditure Breakdown'!$G$6:$G$212, 'Expenditure Breakdown'!$H$6:$H$212, ">="&M1,'Expenditure Breakdown'!$H$6:$H$212, "<"&N1) -> 3567 | N5: =SUMIFS('Expenditure Breakdown'!$G$6:$G$212, 'Expenditure Breakdown'!$H$6:$H$212, ">="&N1,'Expenditure Breakdown'!$H$6:$H$212, "<"&O1) -> 0 | ... BU5: =SUMIFS('Expenditure Breakdown'!$G$6:$G$212, 'Expenditure Breakdown'!$H$6:$H$212, ">="&BU1,'Expenditure Breakdown'!$H$6:$H$212, "<"&BV1) -> 0 | BV5: =SUMIFS('Expenditure Breakdown'!$G$6:$G$212, 'Expenditure Breakdown'!$H$6:$H$212, ">="&BV1,'Expenditure Breakdown'!$H$6:$H$212, "<"&EJ1) -> 0 | BW5: =SUMIFS('Expenditure Breakdown'!$G$6:$G$212, 'Expenditure Breakdown'!$H$6:$H$212, ">="&BW1,'Expenditure Breakdown'!$H$6:$H$212, "<"&EK1) -> 0 | BX5: =SUMIFS('Expenditure Breakdown'!$G$6:$G$212, 'Expenditure Breakdown'!$H$6:$H$212, ">="&BX1,'Expenditure Breakdown'!$H$6:$H$212, "<"&EL1) -> 0 | BY5: =SUMIFS('Expenditure Breakdown'!$G$6:$G$212, 'Expenditure Breakdown'!$H$6:$H$212, ">="&BY1,'Expenditure Breakdown'!$H$6:$H$212, "<"&EM1) -> 0 | BZ5: =SUMIFS('Expenditure Breakdown'!$G$6:$G$212, 'Expenditure Breakdown'!$H$6:$H$212, ">="&BZ1,'Expenditure Breakdown'!$H$6:$H$212, "<"&EN1) -> 0 | CA5: =SUMIFS('Expenditure Breakdown'!$G$6:$G$212, 'Expenditure Breakdown'!$H$6:$H$212, ">="&CA1,'Expenditure Breakdown'!$H$6:$H$212, "<"&EO1) -> 0 | CB5: =SUMIFS('Expenditure Breakdown'!$G$6:$G$212, 'Expenditure Breakdown'!$H$6:$H$212, ">="&CB1,'Expenditure Breakdown'!$H$6:$H$212, "<"&EP1) -> 0 | CC5: =SUMIFS('Expenditure Breakdown'!$G$6:$G$212, 'Expenditure Breakdown'!$H$6:$H$212, ">="&CC1,'Expenditure Breakdown'!$H$6:$H$212, "<"&EQ1) -> 0 | ... EI5: =SUMIFS('Expenditure Breakdown'!$G$6:$G$212, 'Expenditure Breakdown'!$H$6:$H$212, ">="&EI1,'Expenditure Breakdown'!$H$6:$H$212, "<"&GW1) -> 0
B6: Planned Expenditure - Cumulative | F6: =F5 -> 0 | G6: =F6+G5 -> 0 | H6: =G6+H5 -> 0 | I6: =H6+I5 -> 0 | J6: =I6+J5 -> 897757.52 | K6: =J6+K5 -> 897757.52 | L6: =K6+L5 -> 897757.52 | M6: =L6+M5 -> 901324.52 | N6: =M6+N5 -> 901324.52 | ... EI6: =EH6+EI5 -> 18682950
B7: PLANNED CashFlow | F7: =F4-F6 -> 0 | G7: =G4-G6 -> 10469504 | H7: =H4-H6 -> 10469504 | I7: =I4-I6 -> 10469504 | J7: =J4-J6 -> 9571746.9 | K7: =K4-K6 -> 9571746.9 | L7: =L4-L6 -> 9571746.9 | M7: =M4-M6 -> 9568179.9 | ... EI7: =EI4-EI6 -> 2256058.8
A8: ACTUAL | C8: CHECK | D8: CHECK
B9: Actual + Forecast Revenue | C9: ='Revenue Tracking'!F4 -> 20939009 | D9: =SUM(F9:CO9) -> 20939009 | F9: =SUMIFS('Revenue Tracking'!$F$13:$F$30, 'Revenue Tracking'!$J$13:$J$30, ">="&F1,'Revenue Tracking'!$J$13:$J$30, "<"&G1) -> 0 | G9: =SUMIFS('Revenue Tracking'!$F$13:$F$30, 'Revenue Tracking'!$J$13:$J$30, ">="&G1,'Revenue Tracking'!$J$13:$J$30, "<"&H1) -> 0 | H9: =SUMIFS('Revenue Tracking'!$F$13:$F$30, 'Revenue Tracking'!$J$13:$J$30, ">="&H1,'Revenue Tracking'!$J$13:$J$30, "<"&I1) -> 0 | I9: =SUMIFS('Revenue Tracking'!$F$13:$F$30, 'Revenue Tracking'!$J$13:$J$30, ">="&I1,'Revenue Tracking'!$J$13:$J$30, "<"&J1) -> 0 | J9: =SUMIFS('Revenue Tracking'!$F$13:$F$30, 'Revenue Tracking'!$J$13:$J$30, ">="&J1,'Revenue Tracking'!$J$13:$J$30, "<"&K1) -> 0 | K9: =SUMIFS('Revenue Tracking'!$F$13:$F$30, 'Revenue Tracking'!$J$13:$J$30, ">="&K1,'Revenue Tracking'!$J$13:$J$30, "<"&L1) -> 0 | L9: =SUMIFS('Revenue Tracking'!$F$13:$F$30, 'Revenue Tracking'!$J$13:$J$30, ">="&L1,'Revenue Tracking'!$J$13:$J$30, "<"&M1) -> 0 | M9: =SUMIFS('Revenue Tracking'!$F$13:$F$30, 'Revenue Tracking'!$J$13:$J$30, ">="&M1,'Revenue Tracking'!$J$13:$J$30, "<"&N1) -> 0 | ... CN9: =SUMIFS('Revenue Tracking'!$F$13:$F$30, 'Revenue Tracking'!$J$13:$J$30, ">="&CN1,'Revenue Tracking'!$J$13:$J$30, "<"&CO1) -> 0 | CO9: =SUMIFS('Revenue Tracking'!$F$13:$F$30, 'Revenue Tracking'!$J$13:$J$30, ">="&CO1,'Revenue Tracking'!$J$13:$J$30, "<"&EJ1) -> 0 | CP9: =SUMIFS('Revenue Tracking'!$F$13:$F$30, 'Revenue Tracking'!$J$13:$J$30, ">="&CP1,'Revenue Tracking'!$J$13:$J$30, "<"&EK1) -> 0 | CQ9: =SUMIFS('Revenue Tracking'!$F$13:$F$30, 'Revenue Tracking'!$J$13:$J$30, ">="&CQ1,'Revenue Tracking'!$J$13:$J$30, "<"&EL1) -> 0 | CR9: =SUMIFS('Revenue Tracking'!$F$13:$F$30, 'Revenue Tracking'!$J$13:$J$30, ">="&CR1,'Revenue Tracking'!$J$13:$J$30, "<"&EM1) -> 0 | CS9: =SUMIFS('Revenue Tracking'!$F$13:$F$30, 'Revenue Tracking'!$J$13:$J$30, ">="&CS1,'Revenue Tracking'!$J$13:$J$30, "<"&EN1) -> 0 | CT9: =SUMIFS('Revenue Tracking'!$F$13:$F$30, 'Revenue Tracking'!$J$13:$J$30, ">="&CT1,'Revenue Tracking'!$J$13:$J$30, "<"&EO1) -> 0 | CU9: =SUMIFS('Revenue Tracking'!$F$13:$F$30, 'Revenue Tracking'!$J$13:$J$30, ">="&CU1,'Revenue Tracking'!$J$13:$J$30, "<"&EP1) -> 0 | CV9: =SUMIFS('Revenue Tracking'!$F$13:$F$30, 'Revenue Tracking'!$J$13:$J$30, ">="&CV1,'Revenue Tracking'!$J$13:$J$30, "<"&EQ1) -> 0 | ... EI9: =SUMIFS('Revenue Tracking'!$F$13:$F$30, 'Revenue Tracking'!$J$13:$J$30, ">="&EI1,'Revenue Tracking'!$J$13:$J$30, "<"&GD1) -> 0
B10: Actual + Forecast Revenue - Cumulative | F10: =F9 -> 0 | G10: =F10+G9 -> 0 | H10: =G10+H9 -> 0 | I10: =H10+I9 -> 0 | J10: =I10+J9 -> 0 | K10: =J10+K9 -> 0 | L10: =K10+L9 -> 0 | M10: =L10+M9 -> 0 | N10: =M10+N9 -> 0 | ... EI10: =EH10+EI9 -> 20939009
B11: Actual + Forecast Expenditure | C11: ='Revenue Tracking'!F5 -> 19234297 | D11: =SUM(F11:EI11) -> 18959665 | F11: =SUMIFS('Expenditure Breakdown'!$Q$6:$Q$212, 'Expenditure Breakdown'!$R$6:$R$212, ">="&F1,'Expenditure Breakdown'!$R$6:$R$212, "<"&G1) -> 0 | G11: =SUMIFS('Expenditure Breakdown'!$Q$6:$Q$212, 'Expenditure Breakdown'!$R$6:$R$212, ">="&G1,'Expenditure Breakdown'!$R$6:$R$212, "<"&H1) -> 0 | H11: =SUMIFS('Expenditure Breakdown'!$Q$6:$Q$212, 'Expenditure Breakdown'!$R$6:$R$212, ">="&H1,'Expenditure Breakdown'!$R$6:$R$212, "<"&I1) -> 0 | I11: =SUMIFS('Expenditure Breakdown'!$Q$6:$Q$212, 'Expenditure Breakdown'!$R$6:$R$212, ">="&I1,'Expenditure Breakdown'!$R$6:$R$212, "<"&J1) -> 0 | J11: =SUMIFS('Expenditure Breakdown'!$Q$6:$Q$212, 'Expenditure Breakdown'!$R$6:$R$212, ">="&J1,'Expenditure Breakdown'!$R$6:$R$212, "<"&K1) -> 11750 | K11: =SUMIFS('Expenditure Breakdown'!$Q$6:$Q$212, 'Expenditure Breakdown'!$R$6:$R$212, ">="&K1,'Expenditure Breakdown'!$R$6:$R$212, "<"&L1) -> 0 | L11: =SUMIFS('Expenditure Breakdown'!$Q$6:$Q$212, 'Expenditure Breakdown'!$R$6:$R$212, ">="&L1,'Expenditure Breakdown'!$R$6:$R$212, "<"&M1) -> 0 | M11: =SUMIFS('Expenditure Breakdown'!$Q$6:$Q$212, 'Expenditure Breakdown'!$R$6:$R$212, ">="&M1,'Expenditure Breakdown'!$R$6:$R$212, "<"&N1) -> 0 | ... EI11: =SUMIFS('Expenditure Breakdown'!$Q$6:$Q$212, 'Expenditure Breakdown'!$R$6:$R$212, ">="&EI1,'Expenditure Breakdown'!$R$6:$R$212, "<"&EJ1) -> 0
B12: Actual + Forecast Expenditure - Cumulative | F12: =F11 -> 0 | G12: =F12+G11 -> 0 | H12: =G12+H11 -> 0 | I12: =H12+I11 -> 0 | J12: =I12+J11 -> 11750 | K12: =J12+K11 -> 11750 | L12: =K12+L11 -> 11750 | M12: =L12+M11 -> 11750 | N12: =M12+N11 -> 11750 | ... EI12: =EH12+EI11 -> 18959665
B14: ACTUAL CashFlow | F14: =F10-F12 -> 0 | G14: =G10-G12 -> 0 | H14: =H10-H12 -> 0 | I14: =I10-I12 -> 0 | J14: =J10-J12 -> -11750 | K14: =K10-K12 -> -11750 | L14: =L10-L12 -> -11750 | M14: =M10-M12 -> -11750 | ... EI14: =EI10-EI12 -> 1979343.4
B16: Installer Expenditure | D16: =SUM(F16:BR16) -> 2028487.7 | F16: =SUMIFS('Expenditure Breakdown'!$Q$49:$Q$51,'Expenditure Breakdown'!$R$49:$R$51,">="&F1,'Expenditure Breakdown'!$R$49:$R$51,"<"&G1)+SUMIFS('Expenditure Breakdown'!$Q$76:$Q$79,'Expenditure Breakdown'!$R$76:$R$79,">="&F1,'Expenditure Breakdown'!$R$76:$R$79,"<"&G1)+SUMIFS('Expenditure Breakdown'!$Q$106:$Q$123,'Expenditure Breakdown'!$R$106:$R$123,">="&F1,'Expenditure Breakdown'!$R$106:$R$123,"<"&G1) -> 0 | G16: =SUMIFS('Expenditure Breakdown'!$Q$49:$Q$51,'Expenditure Breakdown'!$R$49:$R$51,">="&G1,'Expenditure Breakdown'!$R$49:$R$51,"<"&H1)+SUMIFS('Expenditure Breakdown'!$Q$76:$Q$79,'Expenditure Breakdown'!$R$76:$R$79,">="&G1,'Expenditure Breakdown'!$R$76:$R$79,"<"&H1)+SUMIFS('Expenditure Breakdown'!$Q$106:$Q$123,'Expenditure Breakdown'!$R$106:$R$123,">="&G1,'Expenditure Breakdown'!$R$106:$R$123,"<"&H1) -> 0 | H16: =SUMIFS('Expenditure Breakdown'!$Q$49:$Q$51,'Expenditure Breakdown'!$R$49:$R$51,">="&H1,'Expenditure Breakdown'!$R$49:$R$51,"<"&I1)+SUMIFS('Expenditure Breakdown'!$Q$76:$Q$79,'Expenditure Breakdown'!$R$76:$R$79,">="&H1,'Expenditure Breakdown'!$R$76:$R$79,"<"&I1)+SUMIFS('Expenditure Breakdown'!$Q$106:$Q$123,'Expenditure Breakdown'!$R$106:$R$123,">="&H1,'Expenditure Breakdown'!$R$106:$R$123,"<"&I1) -> 0 | I16: =SUMIFS('Expenditure Breakdown'!$Q$49:$Q$51,'Expenditure Breakdown'!$R$49:$R$51,">="&I1,'Expenditure Breakdown'!$R$49:$R$51,"<"&J1)+SUMIFS('Expenditure Breakdown'!$Q$76:$Q$79,'Expenditure Breakdown'!$R$76:$R$79,">="&I1,'Expenditure Breakdown'!$R$76:$R$79,"<"&J1)+SUMIFS('Expenditure Breakdown'!$Q$106:$Q$123,'Expenditure Breakdown'!$R$106:$R$123,">="&I1,'Expenditure Breakdown'!$R$106:$R$123,"<"&J1) -> 0 | J16: =SUMIFS('Expenditure Breakdown'!$Q$49:$Q$51,'Expenditure Breakdown'!$R$49:$R$51,">="&J1,'Expenditure Breakdown'!$R$49:$R$51,"<"&K1)+SUMIFS('Expenditure Breakdown'!$Q$76:$Q$79,'Expenditure Breakdown'!$R$76:$R$79,">="&J1,'Expenditure Breakdown'!$R$76:$R$79,"<"&K1)+SUMIFS('Expenditure Breakdown'!$Q$106:$Q$123,'Expenditure Breakdown'!$R$106:$R$123,">="&J1,'Expenditure Breakdown'!$R$106:$R$123,"<"&K1) -> 0 | K16: =SUMIFS('Expenditure Breakdown'!$Q$49:$Q$51,'Expenditure Breakdown'!$R$49:$R$51,">="&K1,'Expenditure Breakdown'!$R$49:$R$51,"<"&L1)+SUMIFS('Expenditure Breakdown'!$Q$76:$Q$79,'Expenditure Breakdown'!$R$76:$R$79,">="&K1,'Expenditure Breakdown'!$R$76:$R$79,"<"&L1)+SUMIFS('Expenditure Breakdown'!$Q$106:$Q$123,'Expenditure Breakdown'!$R$106:$R$123,">="&K1,'Expenditure Breakdown'!$R$106:$R$123,"<"&L1) -> 0 | L16: =SUMIFS('Expenditure Breakdown'!$Q$49:$Q$51,'Expenditure Breakdown'!$R$49:$R$51,">="&L1,'Expenditure Breakdown'!$R$49:$R$51,"<"&M1)+SUMIFS('Expenditure Breakdown'!$Q$76:$Q$79,'Expenditure Breakdown'!$R$76:$R$79,">="&L1,'Expenditure Breakdown'!$R$76:$R$79,"<"&M1)+SUMIFS('Expenditure Breakdown'!$Q$106:$Q$123,'Expenditure Breakdown'!$R$106:$R$123,">="&L1,'Expenditure Breakdown'!$R$106:$R$123,"<"&M1) -> 0 | M16: =SUMIFS('Expenditure Breakdown'!$Q$49:$Q$51,'Expenditure Breakdown'!$R$49:$R$51,">="&M1,'Expenditure Breakdown'!$R$49:$R$51,"<"&N1)+SUMIFS('Expenditure Breakdown'!$Q$76:$Q$79,'Expenditure Breakdown'!$R$76:$R$79,">="&M1,'Expenditure Breakdown'!$R$76:$R$79,"<"&N1)+SUMIFS('Expenditure Breakdown'!$Q$106:$Q$123,'Expenditure Breakdown'!$R$106:$R$123,">="&M1,'Expenditure Breakdown'!$R$106:$R$123,"<"&N1) -> 0 | ... BU16: =SUMIFS('Expenditure Breakdown'!$Q$49:$Q$51,'Expenditure Breakdown'!$R$49:$R$51,">="&BU1,'Expenditure Breakdown'!$R$49:$R$51,"<"&BV1)+SUMIFS('Expenditure Breakdown'!$Q$76:$Q$79,'Expenditure Breakdown'!$R$76:$R$79,">="&BU1,'Expenditure Breakdown'!$R$76:$R$79,"<"&BV1)+SUMIFS('Expenditure Breakdown'!$Q$106:$Q$123,'Expenditure Breakdown'!$R$106:$R$123,">="&BU1,'Expenditure Breakdown'!$R$106:$R$123,"<"&BV1) -> 0 | BV16: =SUMIFS('Expenditure Breakdown'!$Q$49:$Q$51,'Expenditure Breakdown'!$R$49:$R$51,">="&BV1,'Expenditure Breakdown'!$R$49:$R$51,"<"&EJ1)+SUMIFS('Expenditure Breakdown'!$Q$76:$Q$79,'Expenditure Breakdown'!$R$76:$R$79,">="&BV1,'Expenditure Breakdown'!$R$76:$R$79,"<"&EJ1)+SUMIFS('Expenditure Breakdown'!$Q$106:$Q$123,'Expenditure Breakdown'!$R$106:$R$123,">="&BV1,'Expenditure Breakdown'!$R$106:$R$123,"<"&EJ1) -> 0 | BW16: =SUMIFS('Expenditure Breakdown'!$Q$49:$Q$51,'Expenditure Breakdown'!$R$49:$R$51,">="&BW1,'Expenditure Breakdown'!$R$49:$R$51,"<"&EK1)+SUMIFS('Expenditure Breakdown'!$Q$76:$Q$79,'Expenditure Breakdown'!$R$76:$R$79,">="&BW1,'Expenditure Breakdown'!$R$76:$R$79,"<"&EK1)+SUMIFS('Expenditure Breakdown'!$Q$106:$Q$123,'Expenditure Breakdown'!$R$106:$R$123,">="&BW1,'Expenditure Breakdown'!$R$106:$R$123,"<"&EK1) -> 0 | BX16: =SUMIFS('Expenditure Breakdown'!$Q$49:$Q$51,'Expenditure Breakdown'!$R$49:$R$51,">="&BX1,'Expenditure Breakdown'!$R$49:$R$51,"<"&EL1)+SUMIFS('Expenditure Breakdown'!$Q$76:$Q$79,'Expenditure Breakdown'!$R$76:$R$79,">="&BX1,'Expenditure Breakdown'!$R$76:$R$79,"<"&EL1)+SUMIFS('Expenditure Breakdown'!$Q$106:$Q$123,'Expenditure Breakdown'!$R$106:$R$123,">="&BX1,'Expenditure Breakdown'!$R$106:$R$123,"<"&EL1) -> 0 | BY16: =SUMIFS('Expenditure Breakdown'!$Q$49:$Q$51,'Expenditure Breakdown'!$R$49:$R$51,">="&BY1,'Expenditure Breakdown'!$R$49:$R$51,"<"&EM1)+SUMIFS('Expenditure Breakdown'!$Q$76:$Q$79,'Expenditure Breakdown'!$R$76:$R$79,">="&BY1,'Expenditure Breakdown'!$R$76:$R$79,"<"&EM1)+SUMIFS('Expenditure Breakdown'!$Q$106:$Q$123,'Expenditure Breakdown'!$R$106:$R$123,">="&BY1,'Expenditure Breakdown'!$R$106:$R$123,"<"&EM1) -> 0 | BZ16: =SUMIFS('Expenditure Breakdown'!$Q$49:$Q$51,'Expenditure Breakdown'!$R$49:$R$51,">="&BZ1,'Expenditure Breakdown'!$R$49:$R$51,"<"&EN1)+SUMIFS('Expenditure Breakdown'!$Q$76:$Q$79,'Expenditure Breakdown'!$R$76:$R$79,">="&BZ1,'Expenditure Breakdown'!$R$76:$R$79,"<"&EN1)+SUMIFS('Expenditure Breakdown'!$Q$106:$Q$123,'Expenditure Breakdown'!$R$106:$R$123,">="&BZ1,'Expenditure Breakdown'!$R$106:$R$123,"<"&EN1) -> 0 | CA16: =SUMIFS('Expenditure Breakdown'!$Q$49:$Q$51,'Expenditure Breakdown'!$R$49:$R$51,">="&CA1,'Expenditure Breakdown'!$R$49:$R$51,"<"&EO1)+SUMIFS('Expenditure Breakdown'!$Q$76:$Q$79,'Expenditure Breakdown'!$R$76:$R$79,">="&CA1,'Expenditure Breakdown'!$R$76:$R$79,"<"&EO1)+SUMIFS('Expenditure Breakdown'!$Q$106:$Q$123,'Expenditure Breakdown'!$R$106:$R$123,">="&CA1,'Expenditure Breakdown'!$R$106:$R$123,"<"&EO1) -> 0 | CB16: =SUMIFS('Expenditure Breakdown'!$Q$49:$Q$51,'Expenditure Breakdown'!$R$49:$R$51,">="&CB1,'Expenditure Breakdown'!$R$49:$R$51,"<"&EP1)+SUMIFS('Expenditure Breakdown'!$Q$76:$Q$79,'Expenditure Breakdown'!$R$76:$R$79,">="&CB1,'Expenditure Breakdown'!$R$76:$R$79,"<"&EP1)+SUMIFS('Expenditure Breakdown'!$Q$106:$Q$123,'Expenditure Breakdown'!$R$106:$R$123,">="&CB1,'Expenditure Breakdown'!$R$106:$R$123,"<"&EP1) -> 0 | CC16: =SUMIFS('Expenditure Breakdown'!$Q$49:$Q$51,'Expenditure Breakdown'!$R$49:$R$51,">="&CC1,'Expenditure Breakdown'!$R$49:$R$51,"<"&EQ1)+SUMIFS('Expenditure Breakdown'!$Q$76:$Q$79,'Expenditure Breakdown'!$R$76:$R$79,">="&CC1,'Expenditure Breakdown'!$R$76:$R$79,"<"&EQ1)+SUMIFS('Expenditure Breakdown'!$Q$106:$Q$123,'Expenditure Breakdown'!$R$106:$R$123,">="&CC1,'Expenditure Breakdown'!$R$106:$R$123,"<"&EQ1) -> 0 | ... EI16: =SUMIFS('Expenditure Breakdown'!$Q$49:$Q$51,'Expenditure Breakdown'!$R$49:$R$51,">="&EI1,'Expenditure Breakdown'!$R$49:$R$51,"<"&GW1)+SUMIFS('Expenditure Breakdown'!$Q$76:$Q$79,'Expenditure Breakdown'!$R$76:$R$79,">="&EI1,'Expenditure Breakdown'!$R$76:$R$79,"<"&GW1)+SUMIFS('Expenditure Breakdown'!$Q$106:$Q$123,'Expenditure Breakdown'!$R$106:$R$123,">="&EI1,'Expenditure Breakdown'!$R$106:$R$123,"<"&GW1) -> 0
B17: Installer Expenditure - Cumulative | F17: =F16 -> 0 | G17: =G16+F17 -> 0 | H17: =H16+G17 -> 0 | I17: =I16+H17 -> 0 | J17: =J16+I17 -> 0 | K17: =K16+J17 -> 0 | L17: =L16+K17 -> 0 | M17: =M16+L17 -> 0 | N17: =N16+M17 -> 0 | ... EI17: =EI16+EH17 -> 2028487.7

Sheet Finance (2)
D1: 45077 | E1: 45107 | F1: 45138 | G1: 45169 | H1: 45199 | I1: 45230 | J1: 45260 | K1: 45291 | L1: 45322 | M1: 45351 | N1: 45382 | O1: 45412 | P1: 45443 | Q1: 45473 | R1: 45504 | S1: 45535 | T1: 45565 | U1: 45596 | V1: 45626 | W1: 45657 | X1: 45688 | Y1: 45716 | Z1: 45747 | AA1: 45777 | AB1: 45808 | AC1: 45838 | AD1: 45721
A2: Equipment | B2: =SUM('Expenditure Breakdown'!Q6:Q104) -> 12120842 | D2: =SUMIFS('Expenditure Breakdown'!$Q$6:$Q$104, 'Expenditure Breakdown'!$U$6:$U$104, ">="&D1,'Expenditure Breakdown'!$U$6:$U$104, "<"&E1) -> 239.13 | E2: =SUMIFS('Expenditure Breakdown'!$Q$6:$Q$104, 'Expenditure Breakdown'!$U$6:$U$104, ">="&E1,'Expenditure Breakdown'!$U$6:$U$104, "<"&F1) -> 8777837.7 | F2: =SUMIFS('Expenditure Breakdown'!$Q$6:$Q$104, 'Expenditure Breakdown'!$U$6:$U$104, ">="&F1,'Expenditure Breakdown'!$U$6:$U$104, "<"&G1) -> 532043.58 | G2: =SUMIFS('Expenditure Breakdown'!$Q$6:$Q$104, 'Expenditure Breakdown'!$U$6:$U$104, ">="&G1,'Expenditure Breakdown'!$U$6:$U$104, "<"&H1) -> 1953116.7 | H2: =SUMIFS('Expenditure Breakdown'!$Q$6:$Q$104, 'Expenditure Breakdown'!$U$6:$U$104, ">="&H1,'Expenditure Breakdown'!$U$6:$U$104, "<"&I1) -> 0 | I2: =SUMIFS('Expenditure Breakdown'!$Q$6:$Q$104, 'Expenditure Breakdown'!$U$6:$U$104, ">="&I1,'Expenditure Breakdown'!$U$6:$U$104, "<"&J1) -> 132782.4 | J2: =SUMIFS('Expenditure Breakdown'!$Q$6:$Q$104, 'Expenditure Breakdown'!$U$6:$U$104, ">="&J1,'Expenditure Breakdown'!$U$6:$U$104, "<"&K1) -> 50665 | K2: =SUMIFS('Expenditure Breakdown'!$Q$6:$Q$104, 'Expenditure Breakdown'!$U$6:$U$104, ">="&K1,'Expenditure Breakdown'!$U$6:$U$104, "<"&L1) -> 155421.42 | ... AB2: =SUMIFS('Expenditure Breakdown'!$Q$6:$Q$104, 'Expenditure Breakdown'!$U$6:$U$104, ">="&AB1,'Expenditure Breakdown'!$U$6:$U$104, "<"&AC1) -> 0 | AC2: =SUMIFS('Expenditure Breakdown'!$Q$6:$Q$104, 'Expenditure Breakdown'!$U$6:$U$104, ">="&AC1,'Expenditure Breakdown'!$U$6:$U$104, "<"&AE1) -> 0 | AF2: =B2-SUM(D2:Y2) -> 0
A3: Installation | B3: =SUM('Expenditure Breakdown'!Q106:Q122) -> 1517100 | D3: =SUMIFS('Expenditure Breakdown'!$Q$106:$Q$123, 'Expenditure Breakdown'!$U$106:$U$123, ">="&D1,'Expenditure Breakdown'!$U$106:$U$123, "<"&E1) -> 0 | E3: =SUMIFS('Expenditure Breakdown'!$Q$106:$Q$123, 'Expenditure Breakdown'!$U$106:$U$123, ">="&E1,'Expenditure Breakdown'!$U$106:$U$123, "<"&F1) -> 326150 | F3: =SUMIFS('Expenditure Breakdown'!$Q$106:$Q$123, 'Expenditure Breakdown'!$U$106:$U$123, ">="&F1,'Expenditure Breakdown'!$U$106:$U$123, "<"&G1) -> 0 | G3: =SUMIFS('Expenditure Breakdown'!$Q$106:$Q$123, 'Expenditure Breakdown'!$U$106:$U$123, ">="&G1,'Expenditure Breakdown'!$U$106:$U$123, "<"&H1) -> 206700 | H3: =SUMIFS('Expenditure Breakdown'!$Q$106:$Q$123, 'Expenditure Breakdown'!$U$106:$U$123, ">="&H1,'Expenditure Breakdown'!$U$106:$U$123, "<"&I1) -> 0 | I3: =SUMIFS('Expenditure Breakdown'!$Q$106:$Q$123, 'Expenditure Breakdown'!$U$106:$U$123, ">="&I1,'Expenditure Breakdown'!$U$106:$U$123, "<"&J1) -> 4300 | J3: =SUMIFS('Expenditure Breakdown'!$Q$106:$Q$123, 'Expenditure Breakdown'!$U$106:$U$123, ">="&J1,'Expenditure Breakdown'!$U$106:$U$123, "<"&K1) -> 206700 | K3: =SUMIFS('Expenditure Breakdown'!$Q$106:$Q$123, 'Expenditure Breakdown'!$U$106:$U$123, ">="&K1,'Expenditure Breakdown'!$U$106:$U$123, "<"&L1) -> 247140 | ... AB3: =SUMIFS('Expenditure Breakdown'!$Q$106:$Q$123, 'Expenditure Breakdown'!$U$106:$U$123, ">="&AB1,'Expenditure Breakdown'!$U$106:$U$123, "<"&AC1) -> 0 | AC3: =SUMIFS('Expenditure Breakdown'!$Q$106:$Q$123, 'Expenditure Breakdown'!$U$106:$U$123, ">="&AC1,'Expenditure Breakdown'!$U$106:$U$123, "<"&AE1) -> 0 | AF3: =B3-SUM(D3:Y3) -> 0
A4: Other Expenses | B4: =SUM('Expenditure Breakdown'!Q123:Q212) -> 5604766 | D4: =SUMIFS('Expenditure Breakdown'!$Q$124:$Q$212, 'Expenditure Breakdown'!$U$124:$U$212, ">="&D1,'Expenditure Breakdown'!$U$124:$U$212, "<"&E1) -> 32528.2 | E4: =SUMIFS('Expenditure Breakdown'!$Q$124:$Q$212, 'Expenditure Breakdown'!$U$124:$U$212, ">="&E1,'Expenditure Breakdown'!$U$124:$U$212, "<"&F1) -> 3876.62 | F4: =SUMIFS('Expenditure Breakdown'!$Q$124:$Q$212, 'Expenditure Breakdown'!$U$124:$U$212, ">="&F1,'Expenditure Breakdown'!$U$124:$U$212, "<"&G1) -> 5574.38 | G4: =SUMIFS('Expenditure Breakdown'!$Q$124:$Q$212, 'Expenditure Breakdown'!$U$124:$U$212, ">="&G1,'Expenditure Breakdown'!$U$124:$U$212, "<"&H1) -> 5086.42 | H4: =SUMIFS('Expenditure Breakdown'!$Q$124:$Q$212, 'Expenditure Breakdown'!$U$124:$U$212, ">="&H1,'Expenditure Breakdown'!$U$124:$U$212, "<"&I1) -> 1005.16 | I4: =SUMIFS('Expenditure Breakdown'!$Q$124:$Q$212, 'Expenditure Breakdown'!$U$124:$U$212, ">="&I1,'Expenditure Breakdown'!$U$124:$U$212, "<"&J1) -> 3654.83 | J4: =SUMIFS('Expenditure Breakdown'!$Q$124:$Q$212, 'Expenditure Breakdown'!$U$124:$U$212, ">="&J1,'Expenditure Breakdown'!$U$124:$U$212, "<"&K1) -> 8758.05 | K4: =SUMIFS('Expenditure Breakdown'!$Q$124:$Q$212, 'Expenditure Breakdown'!$U$124:$U$212, ">="&K1,'Expenditure Breakdown'!$U$124:$U$212, "<"&L1) -> 739.83 | ... AB4: =SUMIFS('Expenditure Breakdown'!$Q$124:$Q$212, 'Expenditure Breakdown'!$U$124:$U$212, ">="&AB1,'Expenditure Breakdown'!$U$124:$U$212, "<"&AC1) -> 0 | AC4: =SUMIFS('Expenditure Breakdown'!$Q$124:$Q$212, 'Expenditure Breakdown'!$U$124:$U$212, ">="&AC1,'Expenditure Breakdown'!$U$124:$U$212, "<"&AE1) -> 0 | AF4: =B4-SUM(D4:AC4) -> 319314.05
B5: =SUM(B3:B4) -> 7121866 | D5: =SUM(D2:D4) -> 32767.33 | E5: =SUM(E2:E4) -> 9107864.4 | F5: =SUM(F2:F4) -> 537617.96 | G5: =SUM(G2:G4) -> 2164903.1 | H5: =SUM(H2:H4) -> 1005.16 | I5: =SUM(I2:I4) -> 140737.23 | J5: =SUM(J2:J4) -> 266123.05 | K5: =SUM(K2:K4) -> 403301.25 | ... AC5: =SUM(AC2:AC4) -> 0
A7: Forecasted Expenses | D7: 6251445.4 | E7: 6251445.4 | F7: 6251445.4 | G7: 6251445.4 | H7: 6251445.4 | I7: 6251445.4 | J7: 6251445.4 | K7: 6251445.4 | L7: 6251445.4 | M7: 6251445.4 | N7: 6251446.4 | O7: 6251447.4 | P7: 6251448.4 | Q7: 6251449.4 | R7: 6251450.4 | S7: 6251451.4 | T7: 6251452.4 | U7: 6251453.4 | V7: 6251454.4 | W7: 6251455.4 | X7: 6251456.4 | Y7: 6251457.4 | Z7: 6251458.4 | AA7: 6251459.4 | AB7: 6251460.4 | AC7: 6251461.4
A8: Proportion of Exp recognised compared to forecasted expense | D8: =(D5-D2)/D7 -> 0.0052033087 | E8: =(E5-E2)/E7 -> 0.05279205 | F8: =(F5-F2)/F7 -> 0.00089169459 | G8: =(G5-G2)/G7 -> 0.033877993 | H8: =(H5-H2)/H7 -> 0.00016078842 | I8: =(I5-I2)/I7 -> 0.0012724785 | J8: =(J5-J2)/J7 -> 0.034465318 | K8: =(K5-K2)/K7 -> 0.039651603 | ... AC8: =(AC5-AC2)/AC7 -> 0
A9: Forecasted Revenue for Services | D9: 7849455.8 | E9: 7849455.8 | F9: 7849455.8 | G9: 7849455.8 | H9: 7849455.8 | I9: 7849455.8 | J9: 7849455.8 | K9: 7849455.8 | L9: 7849455.8 | M9: 7849455.8 | N9: 7849456.8 | O9: 7849457.8 | P9: 7849458.8 | Q9: 7849459.8 | R9: 7849460.8 | S9: 7849461.8 | T9: 7849462.8 | U9: 7849463.8 | V9: 7849464.8 | W9: 7849465.8 | X9: 7849466.8 | Y9: 7849467.8 | Z9: 7849468.8 | AA9: 7849469.8 | AB9: 7849470.8 | AC9: 7849471.8
A10: Revenue to be recognised | B10: =8395847.55317566-B18 -> 7849455.8 | D10: =D9*D8 -> 40843.141 | E10: =E9*E8 -> 414388.87 | F10: =F9*F8 -> 6999.3172 | G10: =G9*G8 -> 265923.81 | H10: =H9*H8 -> 1262.1016 | I10: =I9*I8 -> 9988.2639 | J10: =J9*J8 -> 270533.99 | K10: =K9*K8 -> 311243.5 | ... AC10: =AC9*AC8 -> 0 | AF10: =B10-SUM(D10:M10) -> 6335667
A12: Rev Recognised for Panels | B12: 9426585.8 | E12: 8880628.2 | G12: =B12-E12-K12 -> 238533.63 | K12: 307423.88 | AF12: =B12-SUM(D12:T12) -> 0
A13: Rev Recognised for Inverters | B13: 1117464.4 | G13: =B13 -> 1117464.4 | AF13: =B13-SUM(D13:T13) -> 0
A14: Rev Recognised for AC Equipment | B14: 575142.51 | E14: 215863.08 | F14: =B14-E14 -> 359279.43 | AF14: =B14-SUM(D14:T14) -> 0
A15: Rev Recognised for DC Equipment | B15: 698421.58 | E15: 233641.67 | G15: =B15-E15-I15-Q15 -> 301112.69 | I15: 116938.89 | Q15: 46728.333 | AF15: =B15-SUM(D15:T15) -> 0
A16: Rev Recognised for Mounting Structure | B16: 698632.47 | F16: =B16 -> 698632.47 | AF16: =B16-SUM(D16:T16) -> 0
A17: Rev Recognised for Monitoring | B17: 26914.46 | D17: 265.7 | F17: 3299.2333 | L17: =B17-D17-F17 -> 23349.526 | AF17: =B17-SUM(D17:T17) -> 0
A18: Rev Recognised for Other Equipment (Inverter Cage + Walkways + Warranty Extension) | B18: 546391.75 | F18: 33050 | J18: 56294.444 | M18: 115498.83 | N18: 32611.111 | P18: =308937.36-131994.44 -> 176942.92 | Q18: 131994.44 | AF18: =B18-SUM(D18:T18) -> -0.00075601367
D19: =SUM(D12:D18) -> 265.7 | E19: =SUM(E12:E18) -> 9330133 | F19: =SUM(F12:F18) -> 1094261.1 | G19: =SUM(G12:G18) -> 1657110.8 | H19: =SUM(H12:H18) -> 0 | I19: =SUM(I12:I18) -> 116938.89 | J19: =SUM(J12:J18) -> 56294.444 | K19: =SUM(K12:K18) -> 307423.88 | ... AC19: =SUM(AC12:AC18) -> 0
A21: Allocated to I/S | D21: =D10+D19 -> 41108.841 | E21: =E10+E19 -> 9744521.9 | F21: =F10+F19 -> 1101260.5 | G21: =G10+G19 -> 1923034.6 | H21: =H10+H19 -> 1262.1016 | I21: =I10+I19 -> 126927.15 | J21: =J10+J19 -> 326828.43 | K21: =K10+K19 -> 618667.39 | ... P21: =P10+P19 -> 5199432.6 | Q21: =Q10+Q19+391207.14 -> 842234.33 | R21: =R10+R19 -> 0 | S21: 0 | T21: 0 | U21: 0 | V21: 0 | W21: 0 | X21: 0 | Y21: 0 | Z21: 0 | AA21: 0 | AB21: 0 | AC21: 0
H23: =SUM(H21:R21) -> 8129083.1
H25: =SUM(H19:S19) -> 1007782.4
A27: Total Revenue | D27: ='Revenue Tracking'!F4 -> 20939009
A28: Recognised | D28: =SUM(D21:T21) -> 20939009
D29: =D27-D28 -> 0.0034785196
A32: SP | C32: 100 | D32: =(D34/C34)*C32 -> 109398.89
A33: P | C33: 10
A34: CP | C34: =C32-C33 -> 90 | D34: ='Expenditure Breakdown'!Q91+'Expenditure Breakdown'!Q93+'Expenditure Breakdown'!Q102 -> 98459

Sheet Certificate - Financial Close
B2: Emergent Energy – Financial Close Completion Certificate | H2: FINANCIAL CLOSE CERTIFICATE
B4: Project Name: | C4: ='Project Plan'!E2 -> Mega Park Extension
B5: COO: | C5: Johannes Potgieter
B6: Programme Manager: | C6: Roedolph Venter
B7: HoPD: | C7: Natasha Watkins-Baker
B9: Date of Phase Completion:
B10: Phase Deliverables Checklist: (Y/N)
B11: Product Agreement | C11: NA
B12: EPC Agreement | C12: NA
B13: O&M Agreeement | C13: NA
B14: Cost Proposal | C14: Signed
B15: Deposit Received | C15: Yes
B16: Risks / Notes | C16: None
B18: Acknowledgement and Acceptance:
B19: Role | C19: Name | D19: Signature | E19: Date
B20: COO | C20: Johannes | D20: JTP | E20: 45953

Sheet Project Margins
A1: [capture project margins from costing sheet]
A3: Products | D3: 0.32
A4: Services | D4: 0.5
A5: Expenses | D5: 0.15
A6: Subcontractors | D6: 0.2

Sheet Equipment Quotes
B2: Equipment Quote and Budget comparision
B4: Description | D4: Budget | F4: Supplier 1 | H4: Variance | J4: Supplier 2 | L4: Variance | N4: Comments / Notes
F7: >Name< | J7: >Name<
B9: Inverters | D9: =SUM(D10:D11) -> 1020000 | F9: =SUM(F10:F13) -> 0 | H9: =$D$9-F9 -> 1020000 | J9: =SUM(J10:J13) -> 0 | L9: =$D$9-J9 -> 1020000
B10: Inverters | D10: ='Expenditure Breakdown'!G28 -> 1020000
B11: Optimizers | D11: ='Expenditure Breakdown'!G29 -> 0
B12: Warranty
B13: Delivery fee
F15: >Name< | J15: >Name<
B17: Mounting Structure | D17: =SUM(D18:D19) -> 524979 | F17: =SUM(F18:F20) -> 0 | H17: =$D$17- F17 -> 524979 | J17: =SUM(J18:J20) -> 0 | L17: =$D$17- J17 -> 524979
B18: Mounting Structure | D18: ='Expenditure Breakdown'!G34 -> 524979
B19: Delivery fee
F21: >Name< | J21: >Name<
B23: DC Cable | D23: =SUM(D24:D25) -> 330413.76 | F23: =SUM(F24:F25) -> 0 | H23: =$D$23- F23 -> 330413.76 | J23: =SUM(J24:J25) -> 0 | L23: =$D$23- J23 -> 330413.76
B24: DC Cable | D24: ='Expenditure Breakdown'!G40 -> 330413.76
B25: Delivery fee
F27: >Name< | J27: >Name<
B29: Monitoring system | D29: =SUM(D30:D32) -> #REF! | F29: =SUM(F30:F42) -> 0 | H29: =$D$29-F29 -> #REF! | J29: =SUM(J30:J32) -> 0 | L29: =$D$29-J29 -> #REF!
B30: ='Expenditure Breakdown'!D54 -> Solarlog | D30: ='Expenditure Breakdown'!G54 -> 21000
B31: ='Expenditure Breakdown'!#REF! -> #REF! | D31: ='Expenditure Breakdown'!#REF! -> #REF!
B32: Delivery fee
F34: >Name< | J34: >Name<
B36: Additional Scope | D36: =SUM(D37:D41) -> 280000 | F36: =SUM(F37:F41) -> 0 | H36: =$D$29-F36 -> #REF! | J36: =SUM(J37:J41) -> 0 | L36: =$D$29-J36 -> #REF!
B37: SCADA | D37: ='Expenditure Breakdown'!G88 -> 280000
B38: Inverter cage
B39: Cat ladders
B40: Gen Integration
B41: Lifelines
B43: Totals | D43: =D36+D29+D23+D17+D9 -> #REF! | H43: =SUM(H7:H42) -> #REF! | L43: =SUM(L7:L42) -> #REF!
B47: All amounts are incl VAT

Sheet Installer Quotes
B2: Installer Quote and Budget comparision
B4: Description | D4: Budget | G4: >Installer Name 1< | J4: Variance | L4: >Installer Name 2< | O4: Variance
B6: AC installation | D6: ='Expenditure Breakdown'!C107 -> 437482.5 | E6: =D6/(1000*'Project Plan'!$E$3) -> 0.25 | H6: =G6/('Project Plan'!$E$3*1000) -> 0 | J6: =D6-G6 -> 437482.5 | M6: =L6/('Project Plan'!$E$3*1000) -> 0 | O6: =D6-L6 -> 437482.5
B7: AC equipment | D7: ='Expenditure Breakdown'!C109 -> 1223989.5 | E7: =D7/(1000*'Project Plan'!$E$3) -> 0.69945055 | H7: =G7/('Project Plan'!$E$3*1000) -> 0 | J7: =D7-G7 -> 1223989.5 | M7: =L7/('Project Plan'!$E$3*1000) -> 0 | O7: =D7-L7 -> 1223989.5
B8: DC installation | D8: ='Expenditure Breakdown'!C86 -> 637698.26 | E8: =D8/(1000*'Project Plan'!$E$3) -> 0.36441358 | H8: =G8/('Project Plan'!$E$3*1000) -> 0 | J8: =D8-G8 -> 637698.26 | M8: =L8/('Project Plan'!$E$3*1000) -> 0 | O8: =D8-L8 -> 637698.26
B9: DC equipment | D9: =SUM('Expenditure Breakdown'!G41:G49) -> 307092 | E9: =D9/(1000*'Project Plan'!$E$3) -> 0.17548816 | H9: =G9/('Project Plan'!$E$3*1000) -> 0 | J9: =D9-G9 -> 307092 | M9: =L9/('Project Plan'!$E$3*1000) -> 0 | O9: =D9-L9 -> 307092
B10: Storage | D10: ='Expenditure Breakdown'!G140 -> 0 | J10: =D10-G10 -> 0 | O10: =D10-L10 -> 0
B11: Panel lifting equipment | D11: =SUM('Expenditure Breakdown'!G116:G125) -> 239766.7 | J11: =D11-G11 -> 239766.7 | O11: =D11-L11 -> 239766.7
B12: Offloading | D12: ='Expenditure Breakdown'!G132 -> 0 | J12: =D12-G12 -> 0 | O12: =D12-L12 -> 0
B15: Totals | D15: =SUM(D6:D13) -> 2846029 | G15: =SUM(G6:G13) -> 0 | J15: =SUM(J6:J14) -> 2846029 | L15: =SUM(L6:L13) -> 0 | O15: =SUM(O6:O14) -> 2846029
B18: Description | D18: Budget | G18: >Installer Name 3< | J18: Variance | L18: >Installer Name 4< | O18: Variance
B20: AC installation | D20: ='Expenditure Breakdown'!C107 -> 437482.5 | E20: =D20/(1000*'Project Plan'!$E$3) -> 0.25 | H20: =G20/(1000*'Project Plan'!$E$3) -> 0 | J20: =D20-G20 -> 437482.5 | M20: =L20/(1000*'Project Plan'!$E$3) -> 0 | O20: =D6-L20 -> 437482.5
B21: AC equipment | D21: ='Expenditure Breakdown'!C86 -> 637698.26 | E21: =D21/(1000*'Project Plan'!$E$3) -> 0.36441358 | J21: =D21-G21 -> 637698.26 | M21: =L21/(1000*'Project Plan'!$E$3) -> 0 | O21: =D7-L21 -> 1223989.5
B22: DC installation | D22: ='Expenditure Breakdown'!C109 -> 1223989.5 | E22: =D22/(1000*'Project Plan'!$E$3) -> 0.69945055 | H22: =G22/(1000*'Project Plan'!$E$3) -> 0 | J22: =D22-G22 -> 1223989.5 | M22: =L22/(1000*'Project Plan'!$E$3) -> 0 | O22: =D8-L22 -> 637698.26
B23: DC equipment | D23: =SUM('Expenditure Breakdown'!G41:G49) -> 307092 | E23: =D23/(1000*'Project Plan'!$E$3) -> 0.17548816 | J23: =D23-G23 -> 307092 | O23: =D9-L23 -> 307092
B24: Storage | D24: ='Expenditure Breakdown'!G140 -> 0 | J24: =D24-G24 -> 0 | O24: =D10-L24 -> 0
B25: Panel lifting equipment | D25: =SUM('Expenditure Breakdown'!G116:G125) -> 239766.7 | J25: =D25-G25 -> 239766.7 | O25: =D11-L25 -> 239766.7
B26: Offloading | D26: ='Expenditure Breakdown'!G132 -> 0 | J26: =D26-G26 -> 0 | O26: =D12-L26 -> 0
B29: Totals | D29: =SUM(D20:D27) -> 2846029 | G29: =SUM(G20:G27) -> 0 | J29: =SUM(J20:J28) -> 2846029 | L29: =SUM(L20:L27) -> 0 | O29: =SUM(O20:O28) -> 2846029
B32: Budget Summary
B34: Budget | D34: =D15 -> 2846029
B35: =G4 -> >Installer Name 1< | D35: =G15 -> 0
B36: =L4 -> >Installer Name 2< | D36: =L15 -> 0
B37: =G18 -> >Installer Name 3< | D37: =G29 -> 0
B38: =L18 -> >Installer Name 4< | D38: =L29 -> 0
B40: =IF(D40<D34,"Saving","Loss") -> Loss | D40: =D34-MIN(D35:D38) -> 2846029
B42: All amounts are exc VAT

Sheet Decision Register
B1: =D15 -> Mega Park Extension | E1: Decision Register
B3: ID | C3: Decision Description | D3: Decision Impact | E3: Proposed Date | F3: Proposed By | G3: Status | H3: Approved By | I3: Date | J3: Results / Comments
B4: DEC001
B5: DEC002
B6: DEC003
B7: DEC004
B8: DEC005
B9: DEC006
B10: DEC007
B11: DEC008
B12: DEC009
B13: DEC010
D15: {='Project Plan'!E2:H2} -> Mega Park Extension | E15: 0 | F15: 0 | G15: 0
