Workbook
Name Inverter_Capacity: #REF!
Name Inverter_Supplier: #REF!
Name Project_Size: Compliance!Projectsize
Name Project_Size: 'Finance - Revenue'!Projectsize
Name Project_Size: Projectsize
Name Projectsize: #REF!
Name Projectsize: #REF!
Name Projectsize: 'Project Margins'!$K$5
Name Security_Serv: #REF!
Name Security_Serv: #REF!
Name SSS: #REF!
Name SSS: #REF!
Name USD_ZAR: #REF!

Sheet Sheet1
A1: PROJECT PLAN
A2: # | B2: Project Milestone | C2: Planned Start Date | D2: Duration (Work Days) | E2: Planned End Date | F2: Actual Start Date | H2: Actual End Date | J2: Comments | L2: =C3 -> 43831 | M2: =L2+3 -> 43834 | N2: =M2+7 -> 43841 | O2: =N2+7 -> 43848 | P2: =O2+7 -> 43855 | Q2: =P2+6 -> 43861 | R2: =Q2+1 -> 43862 | S2: =R2+7 -> 43869 | T2: =S2+7 -> 43876 | U2: =T2+7 -> 43883 | V2: =U2+6 -> 43889 | W2: =V2+7 -> 43896 | X2: =W2+7 -> 43903 | Y2: =X2+7 -> 43910 | Z2: =Y2+7 -> 43917 | AA2: =Z2+3 -> 43920 | AB2: =AA2+4 -> 43924 | AC2: =AB2+7 -> 43931 | AD2: =AC2+7 -> 43938 | AE2: =AD2+7 -> 43945 | AF2: =AE2+6 -> 43951 | AG2: =AF2+2 -> 43953 | AH2: =AG2+7 -> 43960 | AI2: =AH2+7 -> 43967 | AJ2: =AI2+7 -> 43974 | AK2: =AJ2+7 -> 43981 | AL2: =AK2+1 -> 43982 | AM2: =AL2+6 -> 43988 | AN2: =AM2+7 -> 43995 | AO2: =AN2+7 -> 44002 | AP2: =AO2+7 -> 44009 | AQ2: =AP2+3 -> 44012 | AR2: =AQ2+4 -> 44016 | AS2: =AR2+7 -> 44023 | AT2: =AS2+7 -> 44030 | AU2: =AT2+7 -> 44037 | AV2: =AU2+6 -> 44043 | AW2: =AV2+1 -> 44044 | AX2: =AW2+7 -> 44051 | AY2: =AX2+7 -> 44058 | AZ2: =AY2+7 -> 44065 | BA2: =AZ2+7 -> 44072 | BB2: =BA2+2 -> 44074 | BC2: =BB2+5 -> 44079 | BD2: =BC2+7 -> 44086 | BE2: =BD2+7 -> 44093 | BF2: =BE2+7 -> 44100 | BG2: =BF2+4 -> 44104
A3: 1 | B3: Contract Signature | C3: 43831 | D3: 1 | E3: 43832 | F3: 43831 | G3: 1 | H3: 43832 | L3: =IF(AND($F3<(L$2+7),$F3>L$2),1, IF(AND($H3<L$2+7,$H3>L$2),3, IF(AND($F3<=L$2, $H3>=L$2), 2, "" ))) -> 3 | M3: =IF(AND($F3<(M$2+7),$F3>M$2),1, IF(AND($H3<M$2+7,$H3>M$2),3, IF(AND($F3<=M$2, $H3>=M$2), 2, "" ))) | N3: =IF(AND($F3<(N$2+7),$F3>N$2),1, IF(AND($H3<N$2+7,$H3>N$2),3, IF(AND($F3<=N$2, $H3>=N$2), 2, "" ))) | O3: =IF(AND($F3<(O$2+7),$F3>O$2),1, IF(AND($H3<O$2+7,$H3>O$2),3, IF(AND($F3<=O$2, $H3>=O$2), 2, "" ))) | P3: =IF(AND($F3<(P$2+7),$F3>P$2),1, IF(AND($H3<P$2+7,$H3>P$2),3, IF(AND($F3<=P$2, $H3>=P$2), 2, "" ))) | Q3: =IF(AND($F3<(Q$2+7),$F3>Q$2),1, IF(AND($H3<Q$2+7,$H3>Q$2),3, IF(AND($F3<=Q$2, $H3>=Q$2), 2, "" ))) | R3: =IF(AND($F3<(R$2+7),$F3>R$2),1, IF(AND($H3<R$2+7,$H3>R$2),3, IF(AND($F3<=R$2, $H3>=R$2), 2, "" ))) | S3: =IF(AND($F3<(S$2+7),$F3>S$2),1, IF(AND($H3<S$2+7,$H3>S$2),3, IF(AND($F3<=S$2, $H3>=S$2), 2, "" ))) | ... AQ3: =IF(AND($F3<(AQ$2+7),$F3>AQ$2),1, IF(AND($H3<AQ$2+7,$H3>AQ$2),3, IF(AND($F3<=AQ$2, $H3>=AQ$2), 2, "" )))
A4: A | B4: PAYMENT MILESTONE 1: DEPOSIT | C4: 43832 | D4: 1 | E4: 43833 | F4: 43832 | G4: 1 | H4: 43833 | L4: =IF(AND($F4<(L$2+7),$F4>L$2),1, IF(AND($H4<L$2+7,$H4>L$2),3, IF(AND($F4<=L$2, $H4>=L$2), 2, "" ))) -> 1 | M4: =IF(AND($F4<(M$2+7),$F4>M$2),1, IF(AND($H4<M$2+7,$H4>M$2),3, IF(AND($F4<=M$2, $H4>=M$2), 2, "" ))) | N4: =IF(AND($F4<(N$2+7),$F4>N$2),1, IF(AND($H4<N$2+7,$H4>N$2),3, IF(AND($F4<=N$2, $H4>=N$2), 2, "" ))) | O4: =IF(AND($F4<(O$2+7),$F4>O$2),1, IF(AND($H4<O$2+7,$H4>O$2),3, IF(AND($F4<=O$2, $H4>=O$2), 2, "" ))) | P4: =IF(AND($F4<(P$2+7),$F4>P$2),1, IF(AND($H4<P$2+7,$H4>P$2),3, IF(AND($F4<=P$2, $H4>=P$2), 2, "" ))) | Q4: =IF(AND($F4<(Q$2+7),$F4>Q$2),1, IF(AND($H4<Q$2+7,$H4>Q$2),3, IF(AND($F4<=Q$2, $H4>=Q$2), 2, "" ))) | R4: =IF(AND($F4<(R$2+7),$F4>R$2),1, IF(AND($H4<R$2+7,$H4>R$2),3, IF(AND($F4<=R$2, $H4>=R$2), 2, "" ))) | S4: =IF(AND($F4<(S$2+7),$F4>S$2),1, IF(AND($H4<S$2+7,$H4>S$2),3, IF(AND($F4<=S$2, $H4>=S$2), 2, "" ))) | ... AQ4: =IF(AND($F4<(AQ$2+7),$F4>AQ$2),1, IF(AND($H4<AQ$2+7,$H4>AQ$2),3, IF(AND($F4<=AQ$2, $H4>=AQ$2), 2, "" )))
A5: 2 | B5: Structural and Electrical Due Diligences | C5: 43833 | D5: 5 | E5: 43840 | F5: 43833 | G5: 5 | H5: 43840 | L5: =IF(AND($F5<(L$2+7),$F5>L$2),1, IF(AND($H5<L$2+7,$H5>L$2),3, IF(AND($F5<=L$2, $H5>=L$2), 2, "" ))) -> 1 | M5: =IF(AND($F5<(M$2+7),$F5>M$2),1, IF(AND($H5<M$2+7,$H5>M$2),3, IF(AND($F5<=M$2, $H5>=M$2), 2, "" ))) -> 3 | N5: =IF(AND($F5<(N$2+7),$F5>N$2),1, IF(AND($H5<N$2+7,$H5>N$2),3, IF(AND($F5<=N$2, $H5>=N$2), 2, "" ))) | O5: =IF(AND($F5<(O$2+7),$F5>O$2),1, IF(AND($H5<O$2+7,$H5>O$2),3, IF(AND($F5<=O$2, $H5>=O$2), 2, "" ))) | P5: =IF(AND($F5<(P$2+7),$F5>P$2),1, IF(AND($H5<P$2+7,$H5>P$2),3, IF(AND($F5<=P$2, $H5>=P$2), 2, "" ))) | Q5: =IF(AND($F5<(Q$2+7),$F5>Q$2),1, IF(AND($H5<Q$2+7,$H5>Q$2),3, IF(AND($F5<=Q$2, $H5>=Q$2), 2, "" ))) | R5: =IF(AND($F5<(R$2+7),$F5>R$2),1, IF(AND($H5<R$2+7,$H5>R$2),3, IF(AND($F5<=R$2, $H5>=R$2), 2, "" ))) | S5: =IF(AND($F5<(S$2+7),$F5>S$2),1, IF(AND($H5<S$2+7,$H5>S$2),3, IF(AND($F5<=S$2, $H5>=S$2), 2, "" ))) | ... AQ5: =IF(AND($F5<(AQ$2+7),$F5>AQ$2),1, IF(AND($H5<AQ$2+7,$H5>AQ$2),3, IF(AND($F5<=AQ$2, $H5>=AQ$2), 2, "" )))
A6: 3 | B6: Design Confirmation | C6: 43841 | D6: 2 | E6: 43844 | F6: 43841 | G6: 2 | H6: 43844 | L6: =IF(AND($F6<(L$2+7),$F6>L$2),1, IF(AND($H6<L$2+7,$H6>L$2),3, IF(AND($F6<=L$2, $H6>=L$2), 2, "" ))) | M6: =IF(AND($F6<(M$2+7),$F6>M$2),1, IF(AND($H6<M$2+7,$H6>M$2),3, IF(AND($F6<=M$2, $H6>=M$2), 2, "" ))) | N6: =IF(AND($F6<(N$2+7),$F6>N$2),1, IF(AND($H6<N$2+7,$H6>N$2),3, IF(AND($F6<=N$2, $H6>=N$2), 2, "" ))) -> 3 | O6: =IF(AND($F6<(O$2+7),$F6>O$2),1, IF(AND($H6<O$2+7,$H6>O$2),3, IF(AND($F6<=O$2, $H6>=O$2), 2, "" ))) | P6: =IF(AND($F6<(P$2+7),$F6>P$2),1, IF(AND($H6<P$2+7,$H6>P$2),3, IF(AND($F6<=P$2, $H6>=P$2), 2, "" ))) | Q6: =IF(AND($F6<(Q$2+7),$F6>Q$2),1, IF(AND($H6<Q$2+7,$H6>Q$2),3, IF(AND($F6<=Q$2, $H6>=Q$2), 2, "" ))) | R6: =IF(AND($F6<(R$2+7),$F6>R$2),1, IF(AND($H6<R$2+7,$H6>R$2),3, IF(AND($F6<=R$2, $H6>=R$2), 2, "" ))) | S6: =IF(AND($F6<(S$2+7),$F6>S$2),1, IF(AND($H6<S$2+7,$H6>S$2),3, IF(AND($F6<=S$2, $H6>=S$2), 2, "" ))) | ... AQ6: =IF(AND($F6<(AQ$2+7),$F6>AQ$2),1, IF(AND($H6<AQ$2+7,$H6>AQ$2),3, IF(AND($F6<=AQ$2, $H6>=AQ$2), 2, "" )))
A7: 4 | B7: Equipment Procurement | C7: 43833 | E7: 43949 | F7: 43833 | H7: 43949 | L7: =IF(AND($F7<(L$2+7),$F7>L$2),1, IF(AND($H7<L$2+7,$H7>L$2),3, IF(AND($F7<=L$2, $H7>=L$2), 2, "" ))) -> 1 | M7: =IF(AND($F7<(M$2+7),$F7>M$2),1, IF(AND($H7<M$2+7,$H7>M$2),3, IF(AND($F7<=M$2, $H7>=M$2), 2, "" ))) -> 2 | N7: =IF(AND($F7<(N$2+7),$F7>N$2),1, IF(AND($H7<N$2+7,$H7>N$2),3, IF(AND($F7<=N$2, $H7>=N$2), 2, "" ))) -> 2 | O7: =IF(AND($F7<(O$2+7),$F7>O$2),1, IF(AND($H7<O$2+7,$H7>O$2),3, IF(AND($F7<=O$2, $H7>=O$2), 2, "" ))) -> 2 | P7: =IF(AND($F7<(P$2+7),$F7>P$2),1, IF(AND($H7<P$2+7,$H7>P$2),3, IF(AND($F7<=P$2, $H7>=P$2), 2, "" ))) -> 2 | Q7: =IF(AND($F7<(Q$2+7),$F7>Q$2),1, IF(AND($H7<Q$2+7,$H7>Q$2),3, IF(AND($F7<=Q$2, $H7>=Q$2), 2, "" ))) -> 2 | R7: =IF(AND($F7<(R$2+7),$F7>R$2),1, IF(AND($H7<R$2+7,$H7>R$2),3, IF(AND($F7<=R$2, $H7>=R$2), 2, "" ))) -> 2 | S7: =IF(AND($F7<(S$2+7),$F7>S$2),1, IF(AND($H7<S$2+7,$H7>S$2),3, IF(AND($F7<=S$2, $H7>=S$2), 2, "" ))) -> 2 | ... AQ7: =IF(AND($F7<(AQ$2+7),$F7>AQ$2),1, IF(AND($H7<AQ$2+7,$H7>AQ$2),3, IF(AND($F7<=AQ$2, $H7>=AQ$2), 2, "" )))
B8: Panel Procurement | C8: 43833 | D8: 5 | E8: 43840 | F8: 43833 | G8: 5 | H8: 43840 | L8: =IF(AND($F8<(L$2+7),$F8>L$2),1, IF(AND($H8<L$2+7,$H8>L$2),3, IF(AND($F8<=L$2, $H8>=L$2), 2, "" ))) -> 1 | M8: =IF(AND($F8<(M$2+7),$F8>M$2),1, IF(AND($H8<M$2+7,$H8>M$2),3, IF(AND($F8<=M$2, $H8>=M$2), 2, "" ))) -> 3 | N8: =IF(AND($F8<(N$2+7),$F8>N$2),1, IF(AND($H8<N$2+7,$H8>N$2),3, IF(AND($F8<=N$2, $H8>=N$2), 2, "" ))) | O8: =IF(AND($F8<(O$2+7),$F8>O$2),1, IF(AND($H8<O$2+7,$H8>O$2),3, IF(AND($F8<=O$2, $H8>=O$2), 2, "" ))) | P8: =IF(AND($F8<(P$2+7),$F8>P$2),1, IF(AND($H8<P$2+7,$H8>P$2),3, IF(AND($F8<=P$2, $H8>=P$2), 2, "" ))) | Q8: =IF(AND($F8<(Q$2+7),$F8>Q$2),1, IF(AND($H8<Q$2+7,$H8>Q$2),3, IF(AND($F8<=Q$2, $H8>=Q$2), 2, "" ))) | R8: =IF(AND($F8<(R$2+7),$F8>R$2),1, IF(AND($H8<R$2+7,$H8>R$2),3, IF(AND($F8<=R$2, $H8>=R$2), 2, "" ))) | S8: =IF(AND($F8<(S$2+7),$F8>S$2),1, IF(AND($H8<S$2+7,$H8>S$2),3, IF(AND($F8<=S$2, $H8>=S$2), 2, "" ))) | ... AQ8: =IF(AND($F8<(AQ$2+7),$F8>AQ$2),1, IF(AND($H8<AQ$2+7,$H8>AQ$2),3, IF(AND($F8<=AQ$2, $H8>=AQ$2), 2, "" )))
B9: Inverter Procurement | C9: 43941 | D9: 5 | E9: 43949 | F9: 43941 | G9: 5 | H9: 43949 | L9: =IF(AND($F9<(L$2+7),$F9>L$2),1, IF(AND($H9<L$2+7,$H9>L$2),3, IF(AND($F9<=L$2, $H9>=L$2), 2, "" ))) | M9: =IF(AND($F9<(M$2+7),$F9>M$2),1, IF(AND($H9<M$2+7,$H9>M$2),3, IF(AND($F9<=M$2, $H9>=M$2), 2, "" ))) | N9: =IF(AND($F9<(N$2+7),$F9>N$2),1, IF(AND($H9<N$2+7,$H9>N$2),3, IF(AND($F9<=N$2, $H9>=N$2), 2, "" ))) | O9: =IF(AND($F9<(O$2+7),$F9>O$2),1, IF(AND($H9<O$2+7,$H9>O$2),3, IF(AND($F9<=O$2, $H9>=O$2), 2, "" ))) | P9: =IF(AND($F9<(P$2+7),$F9>P$2),1, IF(AND($H9<P$2+7,$H9>P$2),3, IF(AND($F9<=P$2, $H9>=P$2), 2, "" ))) | Q9: =IF(AND($F9<(Q$2+7),$F9>Q$2),1, IF(AND($H9<Q$2+7,$H9>Q$2),3, IF(AND($F9<=Q$2, $H9>=Q$2), 2, "" ))) | R9: =IF(AND($F9<(R$2+7),$F9>R$2),1, IF(AND($H9<R$2+7,$H9>R$2),3, IF(AND($F9<=R$2, $H9>=R$2), 2, "" ))) | S9: =IF(AND($F9<(S$2+7),$F9>S$2),1, IF(AND($H9<S$2+7,$H9>S$2),3, IF(AND($F9<=S$2, $H9>=S$2), 2, "" ))) | ... AQ9: =IF(AND($F9<(AQ$2+7),$F9>AQ$2),1, IF(AND($H9<AQ$2+7,$H9>AQ$2),3, IF(AND($F9<=AQ$2, $H9>=AQ$2), 2, "" )))
B10: Mounting Structure Procurement | C10: 43941 | D10: 5 | E10: 43949 | F10: 43941 | G10: 5 | H10: 43949 | L10: =IF(AND($F10<(L$2+7),$F10>L$2),1, IF(AND($H10<L$2+7,$H10>L$2),3, IF(AND($F10<=L$2, $H10>=L$2), 2, "" ))) | M10: =IF(AND($F10<(M$2+7),$F10>M$2),1, IF(AND($H10<M$2+7,$H10>M$2),3, IF(AND($F10<=M$2, $H10>=M$2), 2, "" ))) | N10: =IF(AND($F10<(N$2+7),$F10>N$2),1, IF(AND($H10<N$2+7,$H10>N$2),3, IF(AND($F10<=N$2, $H10>=N$2), 2, "" ))) | O10: =IF(AND($F10<(O$2+7),$F10>O$2),1, IF(AND($H10<O$2+7,$H10>O$2),3, IF(AND($F10<=O$2, $H10>=O$2), 2, "" ))) | P10: =IF(AND($F10<(P$2+7),$F10>P$2),1, IF(AND($H10<P$2+7,$H10>P$2),3, IF(AND($F10<=P$2, $H10>=P$2), 2, "" ))) | Q10: =IF(AND($F10<(Q$2+7),$F10>Q$2),1, IF(AND($H10<Q$2+7,$H10>Q$2),3, IF(AND($F10<=Q$2, $H10>=Q$2), 2, "" ))) | R10: =IF(AND($F10<(R$2+7),$F10>R$2),1, IF(AND($H10<R$2+7,$H10>R$2),3, IF(AND($F10<=R$2, $H10>=R$2), 2, "" ))) | S10: =IF(AND($F10<(S$2+7),$F10>S$2),1, IF(AND($H10<S$2+7,$H10>S$2),3, IF(AND($F10<=S$2, $H10>=S$2), 2, "" ))) | ... AQ10: =IF(AND($F10<(AQ$2+7),$F10>AQ$2),1, IF(AND($H10<AQ$2+7,$H10>AQ$2),3, IF(AND($F10<=AQ$2, $H10>=AQ$2), 2, "" )))
B11: BOS Procurement | C11: 43941 | D11: 5 | E11: 43949 | F11: 43941 | G11: 5 | H11: 43949 | L11: =IF(AND($F11<(L$2+7),$F11>L$2),1, IF(AND($H11<L$2+7,$H11>L$2),3, IF(AND($F11<=L$2, $H11>=L$2), 2, "" ))) | M11: =IF(AND($F11<(M$2+7),$F11>M$2),1, IF(AND($H11<M$2+7,$H11>M$2),3, IF(AND($F11<=M$2, $H11>=M$2), 2, "" ))) | N11: =IF(AND($F11<(N$2+7),$F11>N$2),1, IF(AND($H11<N$2+7,$H11>N$2),3, IF(AND($F11<=N$2, $H11>=N$2), 2, "" ))) | O11: =IF(AND($F11<(O$2+7),$F11>O$2),1, IF(AND($H11<O$2+7,$H11>O$2),3, IF(AND($F11<=O$2, $H11>=O$2), 2, "" ))) | P11: =IF(AND($F11<(P$2+7),$F11>P$2),1, IF(AND($H11<P$2+7,$H11>P$2),3, IF(AND($F11<=P$2, $H11>=P$2), 2, "" ))) | Q11: =IF(AND($F11<(Q$2+7),$F11>Q$2),1, IF(AND($H11<Q$2+7,$H11>Q$2),3, IF(AND($F11<=Q$2, $H11>=Q$2), 2, "" ))) | R11: =IF(AND($F11<(R$2+7),$F11>R$2),1, IF(AND($H11<R$2+7,$H11>R$2),3, IF(AND($F11<=R$2, $H11>=R$2), 2, "" ))) | S11: =IF(AND($F11<(S$2+7),$F11>S$2),1, IF(AND($H11<S$2+7,$H11>S$2),3, IF(AND($F11<=S$2, $H11>=S$2), 2, "" ))) | ... AQ11: =IF(AND($F11<(AQ$2+7),$F11>AQ$2),1, IF(AND($H11<AQ$2+7,$H11>AQ$2),3, IF(AND($F11<=AQ$2, $H11>=AQ$2), 2, "" )))
A12: 5 | B12: Internal Project Kick off | C12: 43936 | D12: 5 | E12: 43943 | F12: 43936 | G12: 5 | H12: 43943
A13: 6 | B13: Client Project Kick-off | C13: 43963 | D13: 5 | E13: 43970 | F13: 43963 | G13: 5 | H13: 43970 | L13: =IF(AND($F13<(L$2+7),$F13>L$2),1, IF(AND($H13<L$2+7,$H13>L$2),3, IF(AND($F13<=L$2, $H13>=L$2), 2, "" ))) | M13: =IF(AND($F13<(M$2+7),$F13>M$2),1, IF(AND($H13<M$2+7,$H13>M$2),3, IF(AND($F13<=M$2, $H13>=M$2), 2, "" ))) | N13: =IF(AND($F13<(N$2+7),$F13>N$2),1, IF(AND($H13<N$2+7,$H13>N$2),3, IF(AND($F13<=N$2, $H13>=N$2), 2, "" ))) | O13: =IF(AND($F13<(O$2+7),$F13>O$2),1, IF(AND($H13<O$2+7,$H13>O$2),3, IF(AND($F13<=O$2, $H13>=O$2), 2, "" ))) | P13: =IF(AND($F13<(P$2+7),$F13>P$2),1, IF(AND($H13<P$2+7,$H13>P$2),3, IF(AND($F13<=P$2, $H13>=P$2), 2, "" ))) | Q13: =IF(AND($F13<(Q$2+7),$F13>Q$2),1, IF(AND($H13<Q$2+7,$H13>Q$2),3, IF(AND($F13<=Q$2, $H13>=Q$2), 2, "" ))) | R13: =IF(AND($F13<(R$2+7),$F13>R$2),1, IF(AND($H13<R$2+7,$H13>R$2),3, IF(AND($F13<=R$2, $H13>=R$2), 2, "" ))) | S13: =IF(AND($F13<(S$2+7),$F13>S$2),1, IF(AND($H13<S$2+7,$H13>S$2),3, IF(AND($F13<=S$2, $H13>=S$2), 2, "" ))) | ... AQ13: =IF(AND($F13<(AQ$2+7),$F13>AQ$2),1, IF(AND($H13<AQ$2+7,$H13>AQ$2),3, IF(AND($F13<=AQ$2, $H13>=AQ$2), 2, "" )))
A14: 7 | B14: Equipment Delivery | C14: 43983 | D14: 9 | E14: 43994 | F14: 43983 | G14: 9 | H14: 43994 | L14: =IF(AND($F14<(L$2+7),$F14>L$2),1, IF(AND($H14<L$2+7,$H14>L$2),3, IF(AND($F14<=L$2, $H14>=L$2), 2, "" ))) | M14: =IF(AND($F14<(M$2+7),$F14>M$2),1, IF(AND($H14<M$2+7,$H14>M$2),3, IF(AND($F14<=M$2, $H14>=M$2), 2, "" ))) | N14: =IF(AND($F14<(N$2+7),$F14>N$2),1, IF(AND($H14<N$2+7,$H14>N$2),3, IF(AND($F14<=N$2, $H14>=N$2), 2, "" ))) | O14: =IF(AND($F14<(O$2+7),$F14>O$2),1, IF(AND($H14<O$2+7,$H14>O$2),3, IF(AND($F14<=O$2, $H14>=O$2), 2, "" ))) | P14: =IF(AND($F14<(P$2+7),$F14>P$2),1, IF(AND($H14<P$2+7,$H14>P$2),3, IF(AND($F14<=P$2, $H14>=P$2), 2, "" ))) | Q14: =IF(AND($F14<(Q$2+7),$F14>Q$2),1, IF(AND($H14<Q$2+7,$H14>Q$2),3, IF(AND($F14<=Q$2, $H14>=Q$2), 2, "" ))) | R14: =IF(AND($F14<(R$2+7),$F14>R$2),1, IF(AND($H14<R$2+7,$H14>R$2),3, IF(AND($F14<=R$2, $H14>=R$2), 2, "" ))) | S14: =IF(AND($F14<(S$2+7),$F14>S$2),1, IF(AND($H14<S$2+7,$H14>S$2),3, IF(AND($F14<=S$2, $H14>=S$2), 2, "" ))) | ... AQ14: =IF(AND($F14<(AQ$2+7),$F14>AQ$2),1, IF(AND($H14<AQ$2+7,$H14>AQ$2),3, IF(AND($F14<=AQ$2, $H14>=AQ$2), 2, "" )))
B15: Mounting Structure Delivery | C15: 43983 | D15: 2 | E15: 43985 | F15: 43983 | G15: 2 | H15: 43985
B16: Panel Delivery | C16: 43990 | D16: 2 | E16: 43992 | F16: 43990 | G16: 2 | H16: 43992 | L16: =IF(AND($F16<(L$2+7),$F16>L$2),1, IF(AND($H16<L$2+7,$H16>L$2),3, IF(AND($F16<=L$2, $H16>=L$2), 2, "" ))) | M16: =IF(AND($F16<(M$2+7),$F16>M$2),1, IF(AND($H16<M$2+7,$H16>M$2),3, IF(AND($F16<=M$2, $H16>=M$2), 2, "" ))) | N16: =IF(AND($F16<(N$2+7),$F16>N$2),1, IF(AND($H16<N$2+7,$H16>N$2),3, IF(AND($F16<=N$2, $H16>=N$2), 2, "" ))) | O16: =IF(AND($F16<(O$2+7),$F16>O$2),1, IF(AND($H16<O$2+7,$H16>O$2),3, IF(AND($F16<=O$2, $H16>=O$2), 2, "" ))) | P16: =IF(AND($F16<(P$2+7),$F16>P$2),1, IF(AND($H16<P$2+7,$H16>P$2),3, IF(AND($F16<=P$2, $H16>=P$2), 2, "" ))) | Q16: =IF(AND($F16<(Q$2+7),$F16>Q$2),1, IF(AND($H16<Q$2+7,$H16>Q$2),3, IF(AND($F16<=Q$2, $H16>=Q$2), 2, "" ))) | R16: =IF(AND($F16<(R$2+7),$F16>R$2),1, IF(AND($H16<R$2+7,$H16>R$2),3, IF(AND($F16<=R$2, $H16>=R$2), 2, "" ))) | S16: =IF(AND($F16<(S$2+7),$F16>S$2),1, IF(AND($H16<S$2+7,$H16>S$2),3, IF(AND($F16<=S$2, $H16>=S$2), 2, "" ))) | ... AQ16: =IF(AND($F16<(AQ$2+7),$F16>AQ$2),1, IF(AND($H16<AQ$2+7,$H16>AQ$2),3, IF(AND($F16<=AQ$2, $H16>=AQ$2), 2, "" )))
B17: Generator Delivery | C17: 43983 | D17: 2 | E17: 43985 | F17: 43983 | G17: 2 | H17: 43985
A18: B | B18: PAYMENT MILESTONE 2: DELIVERY OF PV PANELS | C18: 43992 | D18: 2 | E18: 43994 | F18: 43992 | G18: 2 | H18: 43994
B19: Inverter Delivery | C19: 43983 | D19: 2 | E19: 43985 | F19: 43983 | G19: 2 | H19: 43985 | L19: =IF(AND($F19<(L$2+7),$F19>L$2),1, IF(AND($H19<L$2+7,$H19>L$2),3, IF(AND($F19<=L$2, $H19>=L$2), 2, "" ))) | M19: =IF(AND($F19<(M$2+7),$F19>M$2),1, IF(AND($H19<M$2+7,$H19>M$2),3, IF(AND($F19<=M$2, $H19>=M$2), 2, "" ))) | N19: =IF(AND($F19<(N$2+7),$F19>N$2),1, IF(AND($H19<N$2+7,$H19>N$2),3, IF(AND($F19<=N$2, $H19>=N$2), 2, "" ))) | O19: =IF(AND($F19<(O$2+7),$F19>O$2),1, IF(AND($H19<O$2+7,$H19>O$2),3, IF(AND($F19<=O$2, $H19>=O$2), 2, "" ))) | P19: =IF(AND($F19<(P$2+7),$F19>P$2),1, IF(AND($H19<P$2+7,$H19>P$2),3, IF(AND($F19<=P$2, $H19>=P$2), 2, "" ))) | Q19: =IF(AND($F19<(Q$2+7),$F19>Q$2),1, IF(AND($H19<Q$2+7,$H19>Q$2),3, IF(AND($F19<=Q$2, $H19>=Q$2), 2, "" ))) | R19: =IF(AND($F19<(R$2+7),$F19>R$2),1, IF(AND($H19<R$2+7,$H19>R$2),3, IF(AND($F19<=R$2, $H19>=R$2), 2, "" ))) | S19: =IF(AND($F19<(S$2+7),$F19>S$2),1, IF(AND($H19<S$2+7,$H19>S$2),3, IF(AND($F19<=S$2, $H19>=S$2), 2, "" ))) | ... AQ19: =IF(AND($F19<(AQ$2+7),$F19>AQ$2),1, IF(AND($H19<AQ$2+7,$H19>AQ$2),3, IF(AND($F19<=AQ$2, $H19>=AQ$2), 2, "" )))
B20: BOS Delivery | C20: 43983 | D20: 1 | E20: 43984 | F20: 43983 | G20: 1 | H20: 43984 | L20: =IF(AND($F20<(L$2+7),$F20>L$2),1, IF(AND($H20<L$2+7,$H20>L$2),3, IF(AND($F20<=L$2, $H20>=L$2), 2, "" ))) | M20: =IF(AND($F20<(M$2+7),$F20>M$2),1, IF(AND($H20<M$2+7,$H20>M$2),3, IF(AND($F20<=M$2, $H20>=M$2), 2, "" ))) | N20: =IF(AND($F20<(N$2+7),$F20>N$2),1, IF(AND($H20<N$2+7,$H20>N$2),3, IF(AND($F20<=N$2, $H20>=N$2), 2, "" ))) | O20: =IF(AND($F20<(O$2+7),$F20>O$2),1, IF(AND($H20<O$2+7,$H20>O$2),3, IF(AND($F20<=O$2, $H20>=O$2), 2, "" ))) | P20: =IF(AND($F20<(P$2+7),$F20>P$2),1, IF(AND($H20<P$2+7,$H20>P$2),3, IF(AND($F20<=P$2, $H20>=P$2), 2, "" ))) | Q20: =IF(AND($F20<(Q$2+7),$F20>Q$2),1, IF(AND($H20<Q$2+7,$H20>Q$2),3, IF(AND($F20<=Q$2, $H20>=Q$2), 2, "" ))) | R20: =IF(AND($F20<(R$2+7),$F20>R$2),1, IF(AND($H20<R$2+7,$H20>R$2),3, IF(AND($F20<=R$2, $H20>=R$2), 2, "" ))) | S20: =IF(AND($F20<(S$2+7),$F20>S$2),1, IF(AND($H20<S$2+7,$H20>S$2),3, IF(AND($F20<=S$2, $H20>=S$2), 2, "" ))) | ... AQ20: =IF(AND($F20<(AQ$2+7),$F20>AQ$2),1, IF(AND($H20<AQ$2+7,$H20>AQ$2),3, IF(AND($F20<=AQ$2, $H20>=AQ$2), 2, "" )))
A21: C | B21: PAYMENT MILESTONE 3: DELIVERY OF INVERTERS AND BOS | C21: 43985 | D21: 2 | E21: 43987 | F21: 43985 | G21: 2 | H21: 43987
A22: 8 | B22: Installation | C22: 43990 | D22: 22 | E22: 44012 | F22: 43990 | G22: 22 | H22: 44012 | L22: =IF(AND($F22<(L$2+7),$F22>L$2),1, IF(AND($H22<L$2+7,$H22>L$2),3, IF(AND($F22<=L$2, $H22>=L$2), 2, "" ))) | M22: =IF(AND($F22<(M$2+7),$F22>M$2),1, IF(AND($H22<M$2+7,$H22>M$2),3, IF(AND($F22<=M$2, $H22>=M$2), 2, "" ))) | N22: =IF(AND($F22<(N$2+7),$F22>N$2),1, IF(AND($H22<N$2+7,$H22>N$2),3, IF(AND($F22<=N$2, $H22>=N$2), 2, "" ))) | O22: =IF(AND($F22<(O$2+7),$F22>O$2),1, IF(AND($H22<O$2+7,$H22>O$2),3, IF(AND($F22<=O$2, $H22>=O$2), 2, "" ))) | P22: =IF(AND($F22<(P$2+7),$F22>P$2),1, IF(AND($H22<P$2+7,$H22>P$2),3, IF(AND($F22<=P$2, $H22>=P$2), 2, "" ))) | Q22: =IF(AND($F22<(Q$2+7),$F22>Q$2),1, IF(AND($H22<Q$2+7,$H22>Q$2),3, IF(AND($F22<=Q$2, $H22>=Q$2), 2, "" ))) | R22: =IF(AND($F22<(R$2+7),$F22>R$2),1, IF(AND($H22<R$2+7,$H22>R$2),3, IF(AND($F22<=R$2, $H22>=R$2), 2, "" ))) | S22: =IF(AND($F22<(S$2+7),$F22>S$2),1, IF(AND($H22<S$2+7,$H22>S$2),3, IF(AND($F22<=S$2, $H22>=S$2), 2, "" ))) | ... AQ22: =IF(AND($F22<(AQ$2+7),$F22>AQ$2),1, IF(AND($H22<AQ$2+7,$H22>AQ$2),3, IF(AND($F22<=AQ$2, $H22>=AQ$2), 2, "" ))) -> 2
B23: Site Establishment | C23: 43990 | D23: 1 | E23: 43991 | F23: 43990 | G23: 1 | H23: 43991 | J23: Installation placed on hold due to Covid-19 case | L23: =IF(AND($F23<(L$2+7),$F23>L$2),1, IF(AND($H23<L$2+7,$H23>L$2),3, IF(AND($F23<=L$2, $H23>=L$2), 2, "" ))) | M23: =IF(AND($F23<(M$2+7),$F23>M$2),1, IF(AND($H23<M$2+7,$H23>M$2),3, IF(AND($F23<=M$2, $H23>=M$2), 2, "" ))) | N23: =IF(AND($F23<(N$2+7),$F23>N$2),1, IF(AND($H23<N$2+7,$H23>N$2),3, IF(AND($F23<=N$2, $H23>=N$2), 2, "" ))) | O23: =IF(AND($F23<(O$2+7),$F23>O$2),1, IF(AND($H23<O$2+7,$H23>O$2),3, IF(AND($F23<=O$2, $H23>=O$2), 2, "" ))) | P23: =IF(AND($F23<(P$2+7),$F23>P$2),1, IF(AND($H23<P$2+7,$H23>P$2),3, IF(AND($F23<=P$2, $H23>=P$2), 2, "" ))) | Q23: =IF(AND($F23<(Q$2+7),$F23>Q$2),1, IF(AND($H23<Q$2+7,$H23>Q$2),3, IF(AND($F23<=Q$2, $H23>=Q$2), 2, "" ))) | R23: =IF(AND($F23<(R$2+7),$F23>R$2),1, IF(AND($H23<R$2+7,$H23>R$2),3, IF(AND($F23<=R$2, $H23>=R$2), 2, "" ))) | S23: =IF(AND($F23<(S$2+7),$F23>S$2),1, IF(AND($H23<S$2+7,$H23>S$2),3, IF(AND($F23<=S$2, $H23>=S$2), 2, "" ))) | ... AQ23: =IF(AND($F23<(AQ$2+7),$F23>AQ$2),1, IF(AND($H23<AQ$2+7,$H23>AQ$2),3, IF(AND($F23<=AQ$2, $H23>=AQ$2), 2, "" )))
A24: 9 | B24: DC Works | C24: 43991 | D24: 16 | E24: 44012 | F24: 43991 | G24: 16 | H24: 44012 | L24: =IF(AND($F24<(L$2+7),$F24>L$2),1, IF(AND($H24<L$2+7,$H24>L$2),3, IF(AND($F24<=L$2, $H24>=L$2), 2, "" ))) | M24: =IF(AND($F24<(M$2+7),$F24>M$2),1, IF(AND($H24<M$2+7,$H24>M$2),3, IF(AND($F24<=M$2, $H24>=M$2), 2, "" ))) | N24: =IF(AND($F24<(N$2+7),$F24>N$2),1, IF(AND($H24<N$2+7,$H24>N$2),3, IF(AND($F24<=N$2, $H24>=N$2), 2, "" ))) | O24: =IF(AND($F24<(O$2+7),$F24>O$2),1, IF(AND($H24<O$2+7,$H24>O$2),3, IF(AND($F24<=O$2, $H24>=O$2), 2, "" ))) | P24: =IF(AND($F24<(P$2+7),$F24>P$2),1, IF(AND($H24<P$2+7,$H24>P$2),3, IF(AND($F24<=P$2, $H24>=P$2), 2, "" ))) | Q24: =IF(AND($F24<(Q$2+7),$F24>Q$2),1, IF(AND($H24<Q$2+7,$H24>Q$2),3, IF(AND($F24<=Q$2, $H24>=Q$2), 2, "" ))) | R24: =IF(AND($F24<(R$2+7),$F24>R$2),1, IF(AND($H24<R$2+7,$H24>R$2),3, IF(AND($F24<=R$2, $H24>=R$2), 2, "" ))) | S24: =IF(AND($F24<(S$2+7),$F24>S$2),1, IF(AND($H24<S$2+7,$H24>S$2),3, IF(AND($F24<=S$2, $H24>=S$2), 2, "" ))) | ... AQ24: =IF(AND($F24<(AQ$2+7),$F24>AQ$2),1, IF(AND($H24<AQ$2+7,$H24>AQ$2),3, IF(AND($F24<=AQ$2, $H24>=AQ$2), 2, "" ))) -> 2
B25: Mounting structure Installation | C25: 43991 | D25: 4 | E25: 43997 | F25: 43991 | G25: 4 | H25: 43997 | L25: =IF(AND($F25<(L$2+7),$F25>L$2),1, IF(AND($H25<L$2+7,$H25>L$2),3, IF(AND($F25<=L$2, $H25>=L$2), 2, "" ))) | M25: =IF(AND($F25<(M$2+7),$F25>M$2),1, IF(AND($H25<M$2+7,$H25>M$2),3, IF(AND($F25<=M$2, $H25>=M$2), 2, "" ))) | N25: =IF(AND($F25<(N$2+7),$F25>N$2),1, IF(AND($H25<N$2+7,$H25>N$2),3, IF(AND($F25<=N$2, $H25>=N$2), 2, "" ))) | O25: =IF(AND($F25<(O$2+7),$F25>O$2),1, IF(AND($H25<O$2+7,$H25>O$2),3, IF(AND($F25<=O$2, $H25>=O$2), 2, "" ))) | P25: =IF(AND($F25<(P$2+7),$F25>P$2),1, IF(AND($H25<P$2+7,$H25>P$2),3, IF(AND($F25<=P$2, $H25>=P$2), 2, "" ))) | Q25: =IF(AND($F25<(Q$2+7),$F25>Q$2),1, IF(AND($H25<Q$2+7,$H25>Q$2),3, IF(AND($F25<=Q$2, $H25>=Q$2), 2, "" ))) | R25: =IF(AND($F25<(R$2+7),$F25>R$2),1, IF(AND($H25<R$2+7,$H25>R$2),3, IF(AND($F25<=R$2, $H25>=R$2), 2, "" ))) | S25: =IF(AND($F25<(S$2+7),$F25>S$2),1, IF(AND($H25<S$2+7,$H25>S$2),3, IF(AND($F25<=S$2, $H25>=S$2), 2, "" ))) | ... AQ25: =IF(AND($F25<(AQ$2+7),$F25>AQ$2),1, IF(AND($H25<AQ$2+7,$H25>AQ$2),3, IF(AND($F25<=AQ$2, $H25>=AQ$2), 2, "" )))
B26: Cable tray Installation | C26: 43997 | D26: 3 | E26: 44004 | F26: 43997 | G26: 3 | H26: 44004 | L26: =IF(AND($F26<(L$2+7),$F26>L$2),1, IF(AND($H26<L$2+7,$H26>L$2),3, IF(AND($F26<=L$2, $H26>=L$2), 2, "" ))) | M26: =IF(AND($F26<(M$2+7),$F26>M$2),1, IF(AND($H26<M$2+7,$H26>M$2),3, IF(AND($F26<=M$2, $H26>=M$2), 2, "" ))) | N26: =IF(AND($F26<(N$2+7),$F26>N$2),1, IF(AND($H26<N$2+7,$H26>N$2),3, IF(AND($F26<=N$2, $H26>=N$2), 2, "" ))) | O26: =IF(AND($F26<(O$2+7),$F26>O$2),1, IF(AND($H26<O$2+7,$H26>O$2),3, IF(AND($F26<=O$2, $H26>=O$2), 2, "" ))) | P26: =IF(AND($F26<(P$2+7),$F26>P$2),1, IF(AND($H26<P$2+7,$H26>P$2),3, IF(AND($F26<=P$2, $H26>=P$2), 2, "" ))) | Q26: =IF(AND($F26<(Q$2+7),$F26>Q$2),1, IF(AND($H26<Q$2+7,$H26>Q$2),3, IF(AND($F26<=Q$2, $H26>=Q$2), 2, "" ))) | R26: =IF(AND($F26<(R$2+7),$F26>R$2),1, IF(AND($H26<R$2+7,$H26>R$2),3, IF(AND($F26<=R$2, $H26>=R$2), 2, "" ))) | S26: =IF(AND($F26<(S$2+7),$F26>S$2),1, IF(AND($H26<S$2+7,$H26>S$2),3, IF(AND($F26<=S$2, $H26>=S$2), 2, "" ))) | ... AQ26: =IF(AND($F26<(AQ$2+7),$F26>AQ$2),1, IF(AND($H26<AQ$2+7,$H26>AQ$2),3, IF(AND($F26<=AQ$2, $H26>=AQ$2), 2, "" )))
B27: DC Cable Installation | C27: 44004 | D27: 2 | E27: 44006 | F27: 44004 | G27: 2 | H27: 44006 | L27: =IF(AND($F27<(L$2+7),$F27>L$2),1, IF(AND($H27<L$2+7,$H27>L$2),3, IF(AND($F27<=L$2, $H27>=L$2), 2, "" ))) | M27: =IF(AND($F27<(M$2+7),$F27>M$2),1, IF(AND($H27<M$2+7,$H27>M$2),3, IF(AND($F27<=M$2, $H27>=M$2), 2, "" ))) | N27: =IF(AND($F27<(N$2+7),$F27>N$2),1, IF(AND($H27<N$2+7,$H27>N$2),3, IF(AND($F27<=N$2, $H27>=N$2), 2, "" ))) | O27: =IF(AND($F27<(O$2+7),$F27>O$2),1, IF(AND($H27<O$2+7,$H27>O$2),3, IF(AND($F27<=O$2, $H27>=O$2), 2, "" ))) | P27: =IF(AND($F27<(P$2+7),$F27>P$2),1, IF(AND($H27<P$2+7,$H27>P$2),3, IF(AND($F27<=P$2, $H27>=P$2), 2, "" ))) | Q27: =IF(AND($F27<(Q$2+7),$F27>Q$2),1, IF(AND($H27<Q$2+7,$H27>Q$2),3, IF(AND($F27<=Q$2, $H27>=Q$2), 2, "" ))) | R27: =IF(AND($F27<(R$2+7),$F27>R$2),1, IF(AND($H27<R$2+7,$H27>R$2),3, IF(AND($F27<=R$2, $H27>=R$2), 2, "" ))) | S27: =IF(AND($F27<(S$2+7),$F27>S$2),1, IF(AND($H27<S$2+7,$H27>S$2),3, IF(AND($F27<=S$2, $H27>=S$2), 2, "" ))) | ... AQ27: =IF(AND($F27<(AQ$2+7),$F27>AQ$2),1, IF(AND($H27<AQ$2+7,$H27>AQ$2),3, IF(AND($F27<=AQ$2, $H27>=AQ$2), 2, "" )))
B28: Module Installation | C28: 44006 | D28: 4 | E28: 44012 | F28: 44006 | G28: 4 | H28: 44012 | L28: =IF(AND($F28<(L$2+7),$F28>L$2),1, IF(AND($H28<L$2+7,$H28>L$2),3, IF(AND($F28<=L$2, $H28>=L$2), 2, "" ))) | M28: =IF(AND($F28<(M$2+7),$F28>M$2),1, IF(AND($H28<M$2+7,$H28>M$2),3, IF(AND($F28<=M$2, $H28>=M$2), 2, "" ))) | N28: =IF(AND($F28<(N$2+7),$F28>N$2),1, IF(AND($H28<N$2+7,$H28>N$2),3, IF(AND($F28<=N$2, $H28>=N$2), 2, "" ))) | O28: =IF(AND($F28<(O$2+7),$F28>O$2),1, IF(AND($H28<O$2+7,$H28>O$2),3, IF(AND($F28<=O$2, $H28>=O$2), 2, "" ))) | P28: =IF(AND($F28<(P$2+7),$F28>P$2),1, IF(AND($H28<P$2+7,$H28>P$2),3, IF(AND($F28<=P$2, $H28>=P$2), 2, "" ))) | Q28: =IF(AND($F28<(Q$2+7),$F28>Q$2),1, IF(AND($H28<Q$2+7,$H28>Q$2),3, IF(AND($F28<=Q$2, $H28>=Q$2), 2, "" ))) | R28: =IF(AND($F28<(R$2+7),$F28>R$2),1, IF(AND($H28<R$2+7,$H28>R$2),3, IF(AND($F28<=R$2, $H28>=R$2), 2, "" ))) | S28: =IF(AND($F28<(S$2+7),$F28>S$2),1, IF(AND($H28<S$2+7,$H28>S$2),3, IF(AND($F28<=S$2, $H28>=S$2), 2, "" ))) | ... AQ28: =IF(AND($F28<(AQ$2+7),$F28>AQ$2),1, IF(AND($H28<AQ$2+7,$H28>AQ$2),3, IF(AND($F28<=AQ$2, $H28>=AQ$2), 2, "" ))) -> 2
B29: Earth Cable Installation | C29: 44004 | D29: 1 | E29: 44005 | F29: 44004 | G29: 1 | H29: 44005 | L29: =IF(AND($F29<(L$2+7),$F29>L$2),1, IF(AND($H29<L$2+7,$H29>L$2),3, IF(AND($F29<=L$2, $H29>=L$2), 2, "" ))) | M29: =IF(AND($F29<(M$2+7),$F29>M$2),1, IF(AND($H29<M$2+7,$H29>M$2),3, IF(AND($F29<=M$2, $H29>=M$2), 2, "" ))) | N29: =IF(AND($F29<(N$2+7),$F29>N$2),1, IF(AND($H29<N$2+7,$H29>N$2),3, IF(AND($F29<=N$2, $H29>=N$2), 2, "" ))) | O29: =IF(AND($F29<(O$2+7),$F29>O$2),1, IF(AND($H29<O$2+7,$H29>O$2),3, IF(AND($F29<=O$2, $H29>=O$2), 2, "" ))) | P29: =IF(AND($F29<(P$2+7),$F29>P$2),1, IF(AND($H29<P$2+7,$H29>P$2),3, IF(AND($F29<=P$2, $H29>=P$2), 2, "" ))) | Q29: =IF(AND($F29<(Q$2+7),$F29>Q$2),1, IF(AND($H29<Q$2+7,$H29>Q$2),3, IF(AND($F29<=Q$2, $H29>=Q$2), 2, "" ))) | R29: =IF(AND($F29<(R$2+7),$F29>R$2),1, IF(AND($H29<R$2+7,$H29>R$2),3, IF(AND($F29<=R$2, $H29>=R$2), 2, "" ))) | S29: =IF(AND($F29<(S$2+7),$F29>S$2),1, IF(AND($H29<S$2+7,$H29>S$2),3, IF(AND($F29<=S$2, $H29>=S$2), 2, "" ))) | ... AQ29: =IF(AND($F29<(AQ$2+7),$F29>AQ$2),1, IF(AND($H29<AQ$2+7,$H29>AQ$2),3, IF(AND($F29<=AQ$2, $H29>=AQ$2), 2, "" )))
A30: 10 | B30: AC Works | C30: 43991 | D30: 8 | E30: 44000 | F30: 43991 | G30: 8 | H30: 44000
B31: Inverters Installation | C31: 43991 | D31: 2 | E31: 43993 | F31: 43991 | G31: 2 | H31: 43993 | L31: =IF(AND($F31<(L$2+7),$F31>L$2),1, IF(AND($H31<L$2+7,$H31>L$2),3, IF(AND($F31<=L$2, $H31>=L$2), 2, "" ))) | M31: =IF(AND($F31<(M$2+7),$F31>M$2),1, IF(AND($H31<M$2+7,$H31>M$2),3, IF(AND($F31<=M$2, $H31>=M$2), 2, "" ))) | N31: =IF(AND($F31<(N$2+7),$F31>N$2),1, IF(AND($H31<N$2+7,$H31>N$2),3, IF(AND($F31<=N$2, $H31>=N$2), 2, "" ))) | O31: =IF(AND($F31<(O$2+7),$F31>O$2),1, IF(AND($H31<O$2+7,$H31>O$2),3, IF(AND($F31<=O$2, $H31>=O$2), 2, "" ))) | P31: =IF(AND($F31<(P$2+7),$F31>P$2),1, IF(AND($H31<P$2+7,$H31>P$2),3, IF(AND($F31<=P$2, $H31>=P$2), 2, "" ))) | Q31: =IF(AND($F31<(Q$2+7),$F31>Q$2),1, IF(AND($H31<Q$2+7,$H31>Q$2),3, IF(AND($F31<=Q$2, $H31>=Q$2), 2, "" ))) | R31: =IF(AND($F31<(R$2+7),$F31>R$2),1, IF(AND($H31<R$2+7,$H31>R$2),3, IF(AND($F31<=R$2, $H31>=R$2), 2, "" ))) | S31: =IF(AND($F31<(S$2+7),$F31>S$2),1, IF(AND($H31<S$2+7,$H31>S$2),3, IF(AND($F31<=S$2, $H31>=S$2), 2, "" ))) | ... AQ31: =IF(AND($F31<(AQ$2+7),$F31>AQ$2),1, IF(AND($H31<AQ$2+7,$H31>AQ$2),3, IF(AND($F31<=AQ$2, $H31>=AQ$2), 2, "" )))
B32: AC BOS Installation | C32: 43993 | D32: 3 | E32: 44000 | F32: 43993 | G32: 3 | H32: 44000 | L32: =IF(AND($F32<(L$2+7),$F32>L$2),1, IF(AND($H32<L$2+7,$H32>L$2),3, IF(AND($F32<=L$2, $H32>=L$2), 2, "" ))) | M32: =IF(AND($F32<(M$2+7),$F32>M$2),1, IF(AND($H32<M$2+7,$H32>M$2),3, IF(AND($F32<=M$2, $H32>=M$2), 2, "" ))) | N32: =IF(AND($F32<(N$2+7),$F32>N$2),1, IF(AND($H32<N$2+7,$H32>N$2),3, IF(AND($F32<=N$2, $H32>=N$2), 2, "" ))) | O32: =IF(AND($F32<(O$2+7),$F32>O$2),1, IF(AND($H32<O$2+7,$H32>O$2),3, IF(AND($F32<=O$2, $H32>=O$2), 2, "" ))) | P32: =IF(AND($F32<(P$2+7),$F32>P$2),1, IF(AND($H32<P$2+7,$H32>P$2),3, IF(AND($F32<=P$2, $H32>=P$2), 2, "" ))) | Q32: =IF(AND($F32<(Q$2+7),$F32>Q$2),1, IF(AND($H32<Q$2+7,$H32>Q$2),3, IF(AND($F32<=Q$2, $H32>=Q$2), 2, "" ))) | R32: =IF(AND($F32<(R$2+7),$F32>R$2),1, IF(AND($H32<R$2+7,$H32>R$2),3, IF(AND($F32<=R$2, $H32>=R$2), 2, "" ))) | S32: =IF(AND($F32<(S$2+7),$F32>S$2),1, IF(AND($H32<S$2+7,$H32>S$2),3, IF(AND($F32<=S$2, $H32>=S$2), 2, "" ))) | ... AQ32: =IF(AND($F32<(AQ$2+7),$F32>AQ$2),1, IF(AND($H32<AQ$2+7,$H32>AQ$2),3, IF(AND($F32<=AQ$2, $H32>=AQ$2), 2, "" )))
B33: AC Cable/Tie-In | C33: 43992 | D33: 3 | E33: 43997 | F33: 43992 | G33: 3 | H33: 43997 | L33: =IF(AND($F33<(L$2+7),$F33>L$2),1, IF(AND($H33<L$2+7,$H33>L$2),3, IF(AND($F33<=L$2, $H33>=L$2), 2, "" ))) | M33: =IF(AND($F33<(M$2+7),$F33>M$2),1, IF(AND($H33<M$2+7,$H33>M$2),3, IF(AND($F33<=M$2, $H33>=M$2), 2, "" ))) | N33: =IF(AND($F33<(N$2+7),$F33>N$2),1, IF(AND($H33<N$2+7,$H33>N$2),3, IF(AND($F33<=N$2, $H33>=N$2), 2, "" ))) | O33: =IF(AND($F33<(O$2+7),$F33>O$2),1, IF(AND($H33<O$2+7,$H33>O$2),3, IF(AND($F33<=O$2, $H33>=O$2), 2, "" ))) | P33: =IF(AND($F33<(P$2+7),$F33>P$2),1, IF(AND($H33<P$2+7,$H33>P$2),3, IF(AND($F33<=P$2, $H33>=P$2), 2, "" ))) | Q33: =IF(AND($F33<(Q$2+7),$F33>Q$2),1, IF(AND($H33<Q$2+7,$H33>Q$2),3, IF(AND($F33<=Q$2, $H33>=Q$2), 2, "" ))) | R33: =IF(AND($F33<(R$2+7),$F33>R$2),1, IF(AND($H33<R$2+7,$H33>R$2),3, IF(AND($F33<=R$2, $H33>=R$2), 2, "" ))) | S33: =IF(AND($F33<(S$2+7),$F33>S$2),1, IF(AND($H33<S$2+7,$H33>S$2),3, IF(AND($F33<=S$2, $H33>=S$2), 2, "" ))) | ... AQ33: =IF(AND($F33<(AQ$2+7),$F33>AQ$2),1, IF(AND($H33<AQ$2+7,$H33>AQ$2),3, IF(AND($F33<=AQ$2, $H33>=AQ$2), 2, "" )))
B34: Monitoring Platform Installation | C34: 43997 | D34: 1 | E34: 44000 | F34: 43997 | G34: 1 | H34: 44000
A35: 11 | B35: Completion | C35: 44000 | D35: 14 | E35: 44014 | F35: 44000 | G35: 14 | H35: 44014 | L35: =IF(AND($F35<(L$2+7),$F35>L$2),1, IF(AND($H35<L$2+7,$H35>L$2),3, IF(AND($F35<=L$2, $H35>=L$2), 2, "" ))) | M35: =IF(AND($F35<(M$2+7),$F35>M$2),1, IF(AND($H35<M$2+7,$H35>M$2),3, IF(AND($F35<=M$2, $H35>=M$2), 2, "" ))) | N35: =IF(AND($F35<(N$2+7),$F35>N$2),1, IF(AND($H35<N$2+7,$H35>N$2),3, IF(AND($F35<=N$2, $H35>=N$2), 2, "" ))) | O35: =IF(AND($F35<(O$2+7),$F35>O$2),1, IF(AND($H35<O$2+7,$H35>O$2),3, IF(AND($F35<=O$2, $H35>=O$2), 2, "" ))) | P35: =IF(AND($F35<(P$2+7),$F35>P$2),1, IF(AND($H35<P$2+7,$H35>P$2),3, IF(AND($F35<=P$2, $H35>=P$2), 2, "" ))) | Q35: =IF(AND($F35<(Q$2+7),$F35>Q$2),1, IF(AND($H35<Q$2+7,$H35>Q$2),3, IF(AND($F35<=Q$2, $H35>=Q$2), 2, "" ))) | R35: =IF(AND($F35<(R$2+7),$F35>R$2),1, IF(AND($H35<R$2+7,$H35>R$2),3, IF(AND($F35<=R$2, $H35>=R$2), 2, "" ))) | S35: =IF(AND($F35<(S$2+7),$F35>S$2),1, IF(AND($H35<S$2+7,$H35>S$2),3, IF(AND($F35<=S$2, $H35>=S$2), 2, "" ))) | ... AQ35: =IF(AND($F35<(AQ$2+7),$F35>AQ$2),1, IF(AND($H35<AQ$2+7,$H35>AQ$2),3, IF(AND($F35<=AQ$2, $H35>=AQ$2), 2, "" ))) -> 3
B36: DC Works | C36: 44012 | D36: 2 | E36: 44014 | F36: 44012 | G36: 2 | H36: 44014 | L36: =IF(AND($F36<(L$2+7),$F36>L$2),1, IF(AND($H36<L$2+7,$H36>L$2),3, IF(AND($F36<=L$2, $H36>=L$2), 2, "" ))) | M36: =IF(AND($F36<(M$2+7),$F36>M$2),1, IF(AND($H36<M$2+7,$H36>M$2),3, IF(AND($F36<=M$2, $H36>=M$2), 2, "" ))) | N36: =IF(AND($F36<(N$2+7),$F36>N$2),1, IF(AND($H36<N$2+7,$H36>N$2),3, IF(AND($F36<=N$2, $H36>=N$2), 2, "" ))) | O36: =IF(AND($F36<(O$2+7),$F36>O$2),1, IF(AND($H36<O$2+7,$H36>O$2),3, IF(AND($F36<=O$2, $H36>=O$2), 2, "" ))) | P36: =IF(AND($F36<(P$2+7),$F36>P$2),1, IF(AND($H36<P$2+7,$H36>P$2),3, IF(AND($F36<=P$2, $H36>=P$2), 2, "" ))) | Q36: =IF(AND($F36<(Q$2+7),$F36>Q$2),1, IF(AND($H36<Q$2+7,$H36>Q$2),3, IF(AND($F36<=Q$2, $H36>=Q$2), 2, "" ))) | R36: =IF(AND($F36<(R$2+7),$F36>R$2),1, IF(AND($H36<R$2+7,$H36>R$2),3, IF(AND($F36<=R$2, $H36>=R$2), 2, "" ))) | S36: =IF(AND($F36<(S$2+7),$F36>S$2),1, IF(AND($H36<S$2+7,$H36>S$2),3, IF(AND($F36<=S$2, $H36>=S$2), 2, "" ))) | ... AQ36: =IF(AND($F36<(AQ$2+7),$F36>AQ$2),1, IF(AND($H36<AQ$2+7,$H36>AQ$2),3, IF(AND($F36<=AQ$2, $H36>=AQ$2), 2, "" ))) -> 3
B37: AC Works | C37: 44000 | D37: 2 | E37: 44004 | F37: 44000 | G37: 2 | H37: 44004 | L37: =IF(AND($F37<(L$2+7),$F37>L$2),1, IF(AND($H37<L$2+7,$H37>L$2),3, IF(AND($F37<=L$2, $H37>=L$2), 2, "" ))) | M37: =IF(AND($F37<(M$2+7),$F37>M$2),1, IF(AND($H37<M$2+7,$H37>M$2),3, IF(AND($F37<=M$2, $H37>=M$2), 2, "" ))) | N37: =IF(AND($F37<(N$2+7),$F37>N$2),1, IF(AND($H37<N$2+7,$H37>N$2),3, IF(AND($F37<=N$2, $H37>=N$2), 2, "" ))) | O37: =IF(AND($F37<(O$2+7),$F37>O$2),1, IF(AND($H37<O$2+7,$H37>O$2),3, IF(AND($F37<=O$2, $H37>=O$2), 2, "" ))) | P37: =IF(AND($F37<(P$2+7),$F37>P$2),1, IF(AND($H37<P$2+7,$H37>P$2),3, IF(AND($F37<=P$2, $H37>=P$2), 2, "" ))) | Q37: =IF(AND($F37<(Q$2+7),$F37>Q$2),1, IF(AND($H37<Q$2+7,$H37>Q$2),3, IF(AND($F37<=Q$2, $H37>=Q$2), 2, "" ))) | R37: =IF(AND($F37<(R$2+7),$F37>R$2),1, IF(AND($H37<R$2+7,$H37>R$2),3, IF(AND($F37<=R$2, $H37>=R$2), 2, "" ))) | S37: =IF(AND($F37<(S$2+7),$F37>S$2),1, IF(AND($H37<S$2+7,$H37>S$2),3, IF(AND($F37<=S$2, $H37>=S$2), 2, "" ))) | ... AQ37: =IF(AND($F37<(AQ$2+7),$F37>AQ$2),1, IF(AND($H37<AQ$2+7,$H37>AQ$2),3, IF(AND($F37<=AQ$2, $H37>=AQ$2), 2, "" )))
A38: D | B38: PAYMENT MILESTONE 4: PRACTICAL COMPLETION | C38: 44012 | D38: 1 | E38: 44013 | F38: 44012 | G38: 1 | H38: 44013 | L38: =IF(AND($F38<(L$2+7),$F38>L$2),1, IF(AND($H38<L$2+7,$H38>L$2),3, IF(AND($F38<=L$2, $H38>=L$2), 2, "" ))) | M38: =IF(AND($F38<(M$2+7),$F38>M$2),1, IF(AND($H38<M$2+7,$H38>M$2),3, IF(AND($F38<=M$2, $H38>=M$2), 2, "" ))) | N38: =IF(AND($F38<(N$2+7),$F38>N$2),1, IF(AND($H38<N$2+7,$H38>N$2),3, IF(AND($F38<=N$2, $H38>=N$2), 2, "" ))) | O38: =IF(AND($F38<(O$2+7),$F38>O$2),1, IF(AND($H38<O$2+7,$H38>O$2),3, IF(AND($F38<=O$2, $H38>=O$2), 2, "" ))) | P38: =IF(AND($F38<(P$2+7),$F38>P$2),1, IF(AND($H38<P$2+7,$H38>P$2),3, IF(AND($F38<=P$2, $H38>=P$2), 2, "" ))) | Q38: =IF(AND($F38<(Q$2+7),$F38>Q$2),1, IF(AND($H38<Q$2+7,$H38>Q$2),3, IF(AND($F38<=Q$2, $H38>=Q$2), 2, "" ))) | R38: =IF(AND($F38<(R$2+7),$F38>R$2),1, IF(AND($H38<R$2+7,$H38>R$2),3, IF(AND($F38<=R$2, $H38>=R$2), 2, "" ))) | S38: =IF(AND($F38<(S$2+7),$F38>S$2),1, IF(AND($H38<S$2+7,$H38>S$2),3, IF(AND($F38<=S$2, $H38>=S$2), 2, "" ))) | ... AQ38: =IF(AND($F38<(AQ$2+7),$F38>AQ$2),1, IF(AND($H38<AQ$2+7,$H38>AQ$2),3, IF(AND($F38<=AQ$2, $H38>=AQ$2), 2, "" ))) -> 3
A39: 12 | B39: Commissioning | C39: 43997 | D39: 22 | E39: 44019 | F39: 43997 | G39: 22 | H39: 44019 | L39: =IF(AND($F39<(L$2+7),$F39>L$2),1, IF(AND($H39<L$2+7,$H39>L$2),3, IF(AND($F39<=L$2, $H39>=L$2), 2, "" ))) | M39: =IF(AND($F39<(M$2+7),$F39>M$2),1, IF(AND($H39<M$2+7,$H39>M$2),3, IF(AND($F39<=M$2, $H39>=M$2), 2, "" ))) | N39: =IF(AND($F39<(N$2+7),$F39>N$2),1, IF(AND($H39<N$2+7,$H39>N$2),3, IF(AND($F39<=N$2, $H39>=N$2), 2, "" ))) | O39: =IF(AND($F39<(O$2+7),$F39>O$2),1, IF(AND($H39<O$2+7,$H39>O$2),3, IF(AND($F39<=O$2, $H39>=O$2), 2, "" ))) | P39: =IF(AND($F39<(P$2+7),$F39>P$2),1, IF(AND($H39<P$2+7,$H39>P$2),3, IF(AND($F39<=P$2, $H39>=P$2), 2, "" ))) | Q39: =IF(AND($F39<(Q$2+7),$F39>Q$2),1, IF(AND($H39<Q$2+7,$H39>Q$2),3, IF(AND($F39<=Q$2, $H39>=Q$2), 2, "" ))) | R39: =IF(AND($F39<(R$2+7),$F39>R$2),1, IF(AND($H39<R$2+7,$H39>R$2),3, IF(AND($F39<=R$2, $H39>=R$2), 2, "" ))) | S39: =IF(AND($F39<(S$2+7),$F39>S$2),1, IF(AND($H39<S$2+7,$H39>S$2),3, IF(AND($F39<=S$2, $H39>=S$2), 2, "" ))) | ... AQ39: =IF(AND($F39<(AQ$2+7),$F39>AQ$2),1, IF(AND($H39<AQ$2+7,$H39>AQ$2),3, IF(AND($F39<=AQ$2, $H39>=AQ$2), 2, "" ))) -> 2
B40: Snag List | C40: 44014 | D40: 3 | E40: 44019 | F40: 44014 | G40: 3 | H40: 44019
B41: Pre-Commissioning Checks | C41: 44010 | D41: 2 | E41: 44012 | F41: 44010 | G41: 2 | H41: 44012
B42: Issue CoC | C42: 43997 | D42: 2 | E42: 44001 | F42: 43997 | G42: 2 | H42: 44001 | L42: =IF(AND($F42<(L$2+7),$F42>L$2),1, IF(AND($H42<L$2+7,$H42>L$2),3, IF(AND($F42<=L$2, $H42>=L$2), 2, "" ))) | M42: =IF(AND($F42<(M$2+7),$F42>M$2),1, IF(AND($H42<M$2+7,$H42>M$2),3, IF(AND($F42<=M$2, $H42>=M$2), 2, "" ))) | N42: =IF(AND($F42<(N$2+7),$F42>N$2),1, IF(AND($H42<N$2+7,$H42>N$2),3, IF(AND($F42<=N$2, $H42>=N$2), 2, "" ))) | O42: =IF(AND($F42<(O$2+7),$F42>O$2),1, IF(AND($H42<O$2+7,$H42>O$2),3, IF(AND($F42<=O$2, $H42>=O$2), 2, "" ))) | P42: =IF(AND($F42<(P$2+7),$F42>P$2),1, IF(AND($H42<P$2+7,$H42>P$2),3, IF(AND($F42<=P$2, $H42>=P$2), 2, "" ))) | Q42: =IF(AND($F42<(Q$2+7),$F42>Q$2),1, IF(AND($H42<Q$2+7,$H42>Q$2),3, IF(AND($F42<=Q$2, $H42>=Q$2), 2, "" ))) | R42: =IF(AND($F42<(R$2+7),$F42>R$2),1, IF(AND($H42<R$2+7,$H42>R$2),3, IF(AND($F42<=R$2, $H42>=R$2), 2, "" ))) | S42: =IF(AND($F42<(S$2+7),$F42>S$2),1, IF(AND($H42<S$2+7,$H42>S$2),3, IF(AND($F42<=S$2, $H42>=S$2), 2, "" ))) | ... AQ42: =IF(AND($F42<(AQ$2+7),$F42>AQ$2),1, IF(AND($H42<AQ$2+7,$H42>AQ$2),3, IF(AND($F42<=AQ$2, $H42>=AQ$2), 2, "" )))
B43: Cold Commissioning | C43: 44012 | D43: 1 | E43: 44013 | F43: 44012 | G43: 1 | H43: 44013 | L43: =IF(AND($F43<(L$2+7),$F43>L$2),1, IF(AND($H43<L$2+7,$H43>L$2),3, IF(AND($F43<=L$2, $H43>=L$2), 2, "" ))) | M43: =IF(AND($F43<(M$2+7),$F43>M$2),1, IF(AND($H43<M$2+7,$H43>M$2),3, IF(AND($F43<=M$2, $H43>=M$2), 2, "" ))) | N43: =IF(AND($F43<(N$2+7),$F43>N$2),1, IF(AND($H43<N$2+7,$H43>N$2),3, IF(AND($F43<=N$2, $H43>=N$2), 2, "" ))) | O43: =IF(AND($F43<(O$2+7),$F43>O$2),1, IF(AND($H43<O$2+7,$H43>O$2),3, IF(AND($F43<=O$2, $H43>=O$2), 2, "" ))) | P43: =IF(AND($F43<(P$2+7),$F43>P$2),1, IF(AND($H43<P$2+7,$H43>P$2),3, IF(AND($F43<=P$2, $H43>=P$2), 2, "" ))) | Q43: =IF(AND($F43<(Q$2+7),$F43>Q$2),1, IF(AND($H43<Q$2+7,$H43>Q$2),3, IF(AND($F43<=Q$2, $H43>=Q$2), 2, "" ))) | R43: =IF(AND($F43<(R$2+7),$F43>R$2),1, IF(AND($H43<R$2+7,$H43>R$2),3, IF(AND($F43<=R$2, $H43>=R$2), 2, "" ))) | S43: =IF(AND($F43<(S$2+7),$F43>S$2),1, IF(AND($H43<S$2+7,$H43>S$2),3, IF(AND($F43<=S$2, $H43>=S$2), 2, "" ))) | ... AQ43: =IF(AND($F43<(AQ$2+7),$F43>AQ$2),1, IF(AND($H43<AQ$2+7,$H43>AQ$2),3, IF(AND($F43<=AQ$2, $H43>=AQ$2), 2, "" ))) -> 3
B44: Hot Commissioning | C44: 44013 | D44: 2 | E44: 44015 | F44: 44013 | G44: 2 | H44: 44015 | L44: =IF(AND($F44<(L$2+7),$F44>L$2),1, IF(AND($H44<L$2+7,$H44>L$2),3, IF(AND($F44<=L$2, $H44>=L$2), 2, "" ))) | M44: =IF(AND($F44<(M$2+7),$F44>M$2),1, IF(AND($H44<M$2+7,$H44>M$2),3, IF(AND($F44<=M$2, $H44>=M$2), 2, "" ))) | N44: =IF(AND($F44<(N$2+7),$F44>N$2),1, IF(AND($H44<N$2+7,$H44>N$2),3, IF(AND($F44<=N$2, $H44>=N$2), 2, "" ))) | O44: =IF(AND($F44<(O$2+7),$F44>O$2),1, IF(AND($H44<O$2+7,$H44>O$2),3, IF(AND($F44<=O$2, $H44>=O$2), 2, "" ))) | P44: =IF(AND($F44<(P$2+7),$F44>P$2),1, IF(AND($H44<P$2+7,$H44>P$2),3, IF(AND($F44<=P$2, $H44>=P$2), 2, "" ))) | Q44: =IF(AND($F44<(Q$2+7),$F44>Q$2),1, IF(AND($H44<Q$2+7,$H44>Q$2),3, IF(AND($F44<=Q$2, $H44>=Q$2), 2, "" ))) | R44: =IF(AND($F44<(R$2+7),$F44>R$2),1, IF(AND($H44<R$2+7,$H44>R$2),3, IF(AND($F44<=R$2, $H44>=R$2), 2, "" ))) | S44: =IF(AND($F44<(S$2+7),$F44>S$2),1, IF(AND($H44<S$2+7,$H44>S$2),3, IF(AND($F44<=S$2, $H44>=S$2), 2, "" ))) | ... AQ44: =IF(AND($F44<(AQ$2+7),$F44>AQ$2),1, IF(AND($H44<AQ$2+7,$H44>AQ$2),3, IF(AND($F44<=AQ$2, $H44>=AQ$2), 2, "" ))) -> 1
A45: 13 | B45: Handover | C45: 44020 | D45: 1 | E45: 44021 | F45: 44020 | G45: 1 | H45: 44021 | L45: =IF(AND($F45<(L$2+7),$F45>L$2),1, IF(AND($H45<L$2+7,$H45>L$2),3, IF(AND($F45<=L$2, $H45>=L$2), 2, "" ))) | M45: =IF(AND($F45<(M$2+7),$F45>M$2),1, IF(AND($H45<M$2+7,$H45>M$2),3, IF(AND($F45<=M$2, $H45>=M$2), 2, "" ))) | N45: =IF(AND($F45<(N$2+7),$F45>N$2),1, IF(AND($H45<N$2+7,$H45>N$2),3, IF(AND($F45<=N$2, $H45>=N$2), 2, "" ))) | O45: =IF(AND($F45<(O$2+7),$F45>O$2),1, IF(AND($H45<O$2+7,$H45>O$2),3, IF(AND($F45<=O$2, $H45>=O$2), 2, "" ))) | P45: =IF(AND($F45<(P$2+7),$F45>P$2),1, IF(AND($H45<P$2+7,$H45>P$2),3, IF(AND($F45<=P$2, $H45>=P$2), 2, "" ))) | Q45: =IF(AND($F45<(Q$2+7),$F45>Q$2),1, IF(AND($H45<Q$2+7,$H45>Q$2),3, IF(AND($F45<=Q$2, $H45>=Q$2), 2, "" ))) | R45: =IF(AND($F45<(R$2+7),$F45>R$2),1, IF(AND($H45<R$2+7,$H45>R$2),3, IF(AND($F45<=R$2, $H45>=R$2), 2, "" ))) | S45: =IF(AND($F45<(S$2+7),$F45>S$2),1, IF(AND($H45<S$2+7,$H45>S$2),3, IF(AND($F45<=S$2, $H45>=S$2), 2, "" ))) | ... AQ45: =IF(AND($F45<(AQ$2+7),$F45>AQ$2),1, IF(AND($H45<AQ$2+7,$H45>AQ$2),3, IF(AND($F45<=AQ$2, $H45>=AQ$2), 2, "" )))
A46: E | B46: PAYMENT MILESTONE 6: HANDOVER COMPLETE | C46: 44022 | D46: 1 | E46: 44025 | F46: 44022 | G46: 1 | H46: 44025
C47: 43831 | D47: These numbers are used to set the start and end dates on the Gantt Chart
C48: 44014

Sheet Compliance
B2: HSE
B4: Description | C4: Status | D4: Approved By | E4: Date | F4: Results / Comments
B5: NOC
B6: 7.1 Agreement
B7: 13.2 Agreement
B8: EE File
B9: Subbie File
B16: SSEG
B18: Description | C18: Status | D18: Approved By | E18: Date | F18: Results / Comments
B19: SSEG Application
B20: PTI
B21: Commissioning Approval

Sheet Revenue Tracking
B2: HIGH LEVEL PROJECT REVENUE TRACKING
D3: PLANNED | F3: ACTUAL | L3: FINANCIAL REVIEW | N3: TIMELINE REVIEW | R3: Allocated in 2024 | S3: Budgeted | T3: Acutal
B4: 1 | C4: Planned Revenue | D4: ='Project Plan'!E6 -> 5531086.5 | F4: =F23 -> 5630723.8 | L4: 5531086.5 | N4: Start Date | P4: Sales | R4: 2657720.9 | S4: 2873365.5 | T4: =F4-R4 -> 2973002.9
B5: 2 | C5: Planned Expenditure | D5: =+'Expenditure Tracking'!F5 -> 4800198.7 | F5: =+'Expenditure Tracking'!J5 -> 4032944.1 | L5: 4211805.5 | N5: 45579 | P5: COS | R5: 1892484.5 | S5: 2276451.5 | T5: =F5-R5 -> 2140459.7
B6: 3 | C6: Planned Profit | D6: =+D4-D5 -> 730887.79 | F6: =+F4-F5 -> 1597779.6 | L6: 1319280.9 | N6: End Date - PC | P6: GP | R6: =R4-R5 -> 765236.43 | S6: =S4-S5 -> 596914.06 | T6: =T4-T5 -> 832543.2
B7: 4 | C7: Planned Margin | D7: =+D6/D4 -> 0.13214181 | F7: =+F6/F4 -> 0.28376097 | L7: 0.23852112 | N7: 45631
B10: CONTRACT
B12: No. | C12: PAYMENT MILESTONE | E12: % | F12: VALUE | H12: PLANNED PAYMENT DATE | L12: INVOICE NUMBER | N12: INVOICE RAISED DATE | P12: PAYMENT RECEIVED DATE | R12: MILESTONE NOTES & COMMENTS
B13: 1 | C13: Acceptance and Initial Deposit | E13: 0.35 | F13: =$D$4*E13 -> 1935880.3 | H13: 45491 | L13: 004467 | N13: 45488 | P13: 45490
B14: 2 | C14: Delivery of Inverters | E14: 0.2 | F14: =$D$4*E14 -> 1106217.3 | H14: ='Project Plan'!E22+7 -> 45586 | L14: 004552 | N14: 45567 | P14: =N14+6 -> 45573
B15: 3 | C15: Delivery of Panels | E15: 0.3 | F15: =$D$4*E15 -> 1659325.9 | H15: ='Project Plan'!E35+7 -> 45645 | L15: 004632 | N15: 45638 | P15: 45684
B16: 4 | C16: Practical Completion | E16: 0.1 | F16: =$D$4*E16 -> 553108.65 | H16: ='Project Plan'!E39+7 -> 45680 | L16: 004678 | N16: 45701 | P16: 46080
B17: 5 | C17: Handover | E17: 0.05 | F17: =$D$4*E17 -> 276554.32 | H17: ='Project Plan'!E50+7 -> 45702 | L17: 004690 | N17: 45714 | P17: 45946
B18: 6 | C18: VO - Walkways | E18: 0 | F18: 120546.32 | H18: =H16 -> 45680 | L18: 004678 | N18: 45701 | P18: 45709
B19: 7 | C19: Credit Note Walkways | E19: 0 | F19: -20909.01 | H19: 46001 | L19: 004898 | N19: 46001 | P19: 46080
B20: 8 | C20: Credit Note Walkways | F20: -17220.75 | L20: 004931 | N20: 46045 | P20: 46080
B21: 9 | C21: Credit Note Walkways | F21: -3136.34 | L21: 004944 | N21: 46069 | P21: 46080
E23: =SUM(E13:E19) -> 1 | F23: =SUM(F13:F19) -> 5630723.8
B25: KEY: | C25: contains an error (in result or a check has failed)
C26: Red Font - IF TEXT : content not yet confirmed
C27: Red Font - IF NUMBER: Negative value
C28: Anything in yellow is a concern or risk for noting or action
C29: confirmed
C30: [ADD INITIALS: comment for noting in square brackets, use colour or red to draw attention if important]
C31: [RT: When adding rows into sheet, ensure you insert between first and last row of each category]
C32: end of sheet - do not insert information below/beyond this
B42: No. | C42: PAYMENT MILESTONE | E42: % | F42: VALUE
B43: 1 | C43: Deposit - Project commencement | E43: 0.35 | F43: =$F$49*E43 -> 1970753.3
B44: 2 | C44: Delivery of Panels | E44: 0.3 | F44: =$F$49*E44 -> 1689217.1
B45: 3 | C45: Delivery of Inverters | E45: 0.2 | F45: =$F$49*E45 -> 1126144.8
B46: 4 | C46: Practical Completion | E46: 0.1 | F46: =$F$49*E46 -> 563072.38
B47: 5 | C47: Handover | E47: 0.05 | F47: =$F$49*E47 -> 281536.19
C48: Total | E48: =SUM(E43:E47) -> 1 | F48: =SUM(F43:F47) -> 5630723.8
E49: =SUM(E43:E47) -> 1 | F49: =F23 -> 5630723.8

Sheet Project Plan
N1: 45943 | O1: 45943
C2: PROJECT PLAN | E2: SA Metal - 14 Christiaan_A | N2: 0 | O2: 1
C3: PROJECT SIZE (kWp) | E3: 595
C4: BUSINESS DEVELOPER | E4: Peet
C5: PROJECT MANAGER | E5: Lloyd
C6: CONTRACT VALUE | E6: 5531086.5
C7: Phase: | E7: Commercial Close Out
B8: No. | C8: HIGH LEVEL PROGRAMME | E8: Planned Start | F8: Duration (days) | G8: Planned End | I8: Actual Start | J8: Duration (days) | K8: Actual End | M8: Status | O8: Comment
F9: 100 | J9: 121 | M9: 1 | N9: 1
B11: 1 | C11: Project Initiation | E11: 45518 | F11: 37 | G11: 45555 | I11: 45518 | J11: 37 | K11: 45555 | M11: 1 | N11: 1
B12: 1.1 | C12: BD Handover | E12: 45518 | F12: 1 | G12: 45519 | I12: 45518 | J12: 1 | K12: 45519 | M12: 1 | N12: 1
B13: 1.2 | C13: Project Introduction | E13: 45540 | F13: 1 | G13: 45541 | I13: 45540 | J13: 1 | K13: 45541 | M13: 1 | N13: 1
B14: 1.3 | C14: HSE | E14: 45540 | F14: 15 | G14: 45555 | I14: 45540 | J14: 15 | K14: 45555 | M14: 1 | N14: 1
B15: 1.4 | C15: Installer Kick Off | E15: 45548 | F15: 1 | G15: 45551 | I15: 45548 | J15: 1 | K15: 45551 | M15: 1 | N15: 1
B16: 1.5 | C16: Project Review | E16: 45547 | F16: 1 | G16: 45548 | I16: 45547 | J16: 1 | K16: 45548 | M16: 1 | N16: 1
B18: 2 | C18: Site Establishment | E18: 45579 | F18: 1 | G18: 45580 | I18: 45579 | J18: 1 | K18: 45580 | M18: 1 | N18: 1
B19: 2.1 | C19: Installer on site & Roof Assessment | E19: 45579 | F19: 1 | G19: 45580 | I19: 45579 | J19: 1 | K19: 45580 | M19: 1 | N19: 1 | S19: 91 | T19: Net working Days
B21: 3 | C21: AC Installation | E21: 45614 | F21: 29 | G21: 45643 | I21: 45614 | J21: 29 | K21: 45643 | M21: 1 | N21: 1 | S21: 18.2 | T21: Net Working Weeks
B22: 3.1 | C22: Inverters delivered | E22: 45579 | F22: 1 | G22: 45580 | I22: 45565 | J22: 1 | K22: 45566 | M22: 1 | N22: 1 | S22: 32.692308 | T22: kW/Week Installationn Speed
B23: 3.2 | C23: Inverters Mounted | E23: 45580 | F23: 1 | G23: 45581 | I23: 45566 | J23: 1 | K23: 45567 | M23: 1 | N23: 1
B24: 3.3 | C24: Solar DB lead time | E24: 45547 | F24: 30 | G24: 45590 | I24: 45547 | J24: 30 | K24: 45590 | M24: 1 | N24: 1
B25: 3.4 | C25: AC Works | E25: 45580 | F25: 10 | G25: 45594 | I25: 45616 | J25: 45 | K25: 45684 | M25: 1 | N25: 1
B26: 3.5 | C26: AC Tie - in | E26: 45588 | F26: 1 | G26: 45589 | I26: 45574 | J26: 1 | K26: 45575 | M26: 1 | N26: 1
B28: 4 | C28: DC Works | E28: 45614 | F28: 59 | G28: 45673 | I28: 45614 | J28: 59 | K28: 45673 | M28: 1 | N28: 1
B29: 4.1 | C29: Mounting Structure delivered | E29: 45579 | F29: 1 | G29: 45580 | I29: 45579 | J29: 1 | K29: 45580 | M29: 1 | N29: 1
B30: 4.2 | C30: Mounting Structure installation | E30: 45579 | F30: 8 | G30: 45589 | I30: 45579 | J30: 8 | K30: 45589 | M30: 1 | N30: 1
B31: 4.3 | C31: DC Cable delivered | E31: 45579 | F31: 1 | G31: 45580 | I31: 45579 | J31: 1 | K31: 45580 | M31: 1 | N31: 1
B32: 4.3 | C32: DC Stringing | E32: 45664 | F32: 5 | G32: 45671 | I32: 45684 | J32: 5 | K32: 45691 | M32: 1 | N32: 1
B34: 5 | C34: Module installation | E34: 45638 | F34: 35 | G34: 45673 | I34: 45638 | J34: 60 | K34: 45698 | M34: 1 | N34: 1
B35: 5.1 | C35: Module delivery | E35: 45638 | F35: 1 | G35: 45639 | I35: 45638 | J35: 1 | K35: 45639 | M35: 1 | N35: 1
B36: 5.2 | C36: Module mounting | E36: 45638 | F36: 15 | G36: 45664 | I36: 45670 | J36: 20 | K36: 45698 | M36: 1 | N36: 1
B38: 6 | C38: Commissioning | E38: 45663 | F38: 18 | G38: 45681 | I38: 45663 | J38: 37 | K38: 45700 | M38: 1 | N38: 1
B39: 6.1 | C39: Commissioning | E39: 45673 | F39: 1 | G39: 45674 | I39: 45698 | J39: 1 | K39: 45699 | M39: 1 | N39: 1
B40: 6.2 | C40: Practical Completion | E40: 45673 | F40: 4 | G40: 45679 | I40: 45699 | J40: 1 | K40: 45700 | M40: 1 | N40: 1
B42: 7 | C42: QA Inspections | E42: 45677 | F42: 4 | G42: 45681 | I42: 45677 | J42: 4 | K42: 45681 | M42: 1 | N42: 1
B43: 7.1 | C43: Red-Team Inspection | E43: 45677 | F43: 3 | G43: 45680 | I43: 45700 | J43: 1 | K43: 45701 | M43: 1 | N43: 1
B45: 8 | C45: Project Closure | E45: 45674 | F45: 12 | G45: 45686 | I45: 45674 | J45: 224 | K45: 45898 | M45: 1 | N45: 1
B46: 8.1 | C46: Equipment serial numbers | E46: 45680 | F46: 1 | G46: 45681 | I46: 45701 | J46: 1 | K46: 45702 | M46: 1 | N46: 1
B47: 8.2 | C47: Snags completion | E47: 45681 | F47: 5 | G47: 45688 | I47: 45701 | J47: 2 | K47: 45705 | M47: 1 | N47: 1
B48: 8.3 | C48: System Performance Monitoring | E48: 45688 | F48: 5 | G48: 45695 | I48: 45705 | J48: 1 | K48: 45706 | M48: 1 | N48: 1
B49: 8.4 | C49: Handover documentation | E49: 45688 | F49: 5 | G49: 45695 | I49: 45705 | J49: 1 | K49: 45706 | M49: 1 | N49: 1
B50: 8.5 | C50: Handover to Client | E50: 45695 | F50: 1 | G50: 45698 | I50: 45708 | J50: 1 | K50: 45898 | M50: 1 | N50: 1
B51: 8.6 | C51: Handover to Matriarch | E51: 45681 | F51: 1 | G51: 45684 | I51: 45776 | J51: 1 | K51: 45777 | M51: 1 | N51: 1

Sheet Data
C2: Public holidays | F2: Drop down list
C3: 45292 | D3: New Years Day | F3: Approved
C4: 45372 | D4: Human Rights day | F4: Pending
C5: 45380 | D5: Good Friday | F5: Declined
C6: 45383 | D6: Family Day | F6: Abanded
C7: 45413 | D7: Workers day
C8: 45460 | D8: Youth Day Holiday
C9: 45513 | D9: Womens Day
C10: 45559 | D10: Heritage Day
C11: 45642 | D11: Day of Reconciliation
C12: 45651 | D12: Christmas Day
C13: 45652 | D13: Day of Goodwill | H13: Manual dates

Sheet Expenditure Tracking
B2: HIGH LEVEL PROJECT EXPENDITURE TRACKING
F4: COSTED | H4: PLANNED | J4: ACTUAL | L4: Difference from costed | N4: Difference from planned
B5: EXPENDITURE | F5: =SUM(F9:F23) -> 4800198.7 | H5: =SUM(H9:H23) -> 4211805.5 | J5: =SUM(J9:J23) -> 4032944.1 | L5: =SUM(L9:L23) -> 767254.53 | N5: =SUM(N9:N23) -> 178861.38
B7: No. | D7: Item | F7: Costed Expenditure | H7: Planned Expenditure | J7: Actual Expenditure | L7: Saving / Overrun | N7: Saving / Overrun | P7: Comments on variations from planned expenditure
B9: ='Expenditure Breakdown'!B6 -> 1 | D9: ='Expenditure Breakdown'!C6 -> Panels | F9: ='Expenditure Breakdown'!J6 -> 1642699.2 | H9: 1618563.2 | J9: ='Expenditure Breakdown'!X6 -> 1520595.1 | L9: =F9-J9 -> 122104.07 | N9: =H9-J9 -> 97968.11
B10: ='Expenditure Breakdown'!B16 -> 2 | D10: ='Expenditure Breakdown'!C16 -> Inverters | F10: =+'Expenditure Breakdown'!J16 -> 394490 | H10: 361567.5 | J10: =+'Expenditure Breakdown'!X16 -> 345455.23 | L10: =F10-J10 -> 49034.77 | N10: =H10-J10 -> 16112.27
B11: ='Expenditure Breakdown'!B21 -> 3 | D11: ='Expenditure Breakdown'!C21 -> Mounting Structures | F11: =+'Expenditure Breakdown'!J21 -> 238032 | H11: 114681.4 | J11: =+'Expenditure Breakdown'!X21 -> 73364.1 | L11: =F11-J11 -> 164667.9 | N11: =H11-J11 -> 41317.3
B12: ='Expenditure Breakdown'!B27 -> 4 | D12: ='Expenditure Breakdown'!C27 -> DC Equipment | F12: =+'Expenditure Breakdown'!J27 -> 419782.9 | H12: 527842.4 | J12: =+'Expenditure Breakdown'!X27 -> 550887.4 | L12: =F12-J12 -> -131104.5 | N12: =H12-J12 -> -23045
B13: ='Expenditure Breakdown'!B39 -> 5 | D13: ='Expenditure Breakdown'!C39 -> Monitoring | F13: =+'Expenditure Breakdown'!J39 -> 49000 | H13: 80490.5 | J13: =+'Expenditure Breakdown'!X39 -> 109045.78 | L13: =F13-J13 -> -60045.78 | N13: =H13-J13 -> -28555.28
B14: ='Expenditure Breakdown'!B56 -> 6 | D14: ='Expenditure Breakdown'!C56 -> AC Equipment | F14: =+'Expenditure Breakdown'!J56 -> 840770.37 | H14: 362257.91 | J14: =+'Expenditure Breakdown'!X56 -> 395469.19 | L14: =F14-J14 -> 445301.18 | N14: =H14-J14 -> -33211.28
B15: ='Expenditure Breakdown'!B71 -> 7 | D15: ='Expenditure Breakdown'!C71 -> Battery Systems | F15: =+'Expenditure Breakdown'!J71 -> 0 | H15: 0 | J15: ='Expenditure Breakdown'!X71 -> 0 | L15: =F15-J15 -> 0 | N15: =H15-J15 -> 0
B16: ='Expenditure Breakdown'!B80 -> 8 | D16: ='Expenditure Breakdown'!C80 -> Product Add On | F16: ='Expenditure Breakdown'!J80 -> 30000 | H16: 0 | J16: ='Expenditure Breakdown'!X80 -> 121265.17 | L16: =F16-J16 -> -91265.17 | N16: =H16-J16 -> -121265.17
B17: ='Expenditure Breakdown'!M88 -> 9 | D17: ='Expenditure Breakdown'!C88 -> AC & DC Installation | F17: =+'Expenditure Breakdown'!J88 -> 495900 | H17: 513333.33 | J17: =+'Expenditure Breakdown'!X88 -> 513333.33 | L17: =F17-J17 -> -17433.33 | N17: =H17-J17 -> 0
B18: ='Expenditure Breakdown'!B97 -> 10 | D18: ='Expenditure Breakdown'!C97 -> Site Logistics | F18: =+'Expenditure Breakdown'!J97 -> 69299.97 | H18: 78500 | J18: =+'Expenditure Breakdown'!X97 -> 63500 | L18: =F18-J18 -> 5799.97 | N18: =H18-J18 -> 15000
B19: ='Expenditure Breakdown'!B109 -> 11 | D19: ='Expenditure Breakdown'!C109 -> Due Dilligence | F19: ='Expenditure Breakdown'!J109 -> 104631 | H19: 23020 | J19: ='Expenditure Breakdown'!X109 -> 21978.33 | L19: =F19-J19 -> 82652.67 | N19: =H19-J19 -> 1041.67
B20: ='Expenditure Breakdown'!B117 -> 12 | D20: ='Expenditure Breakdown'!C117 -> BDP Commission | F20: ='Expenditure Breakdown'!G115 -> 128980.2 | H20: 128980.2 | J20: ='Expenditure Breakdown'!X115 -> 128980.2 | L20: =F20-J20 -> 0 | N20: =H20-J20 -> 0
B21: ='Expenditure Breakdown'!B119 -> 13 | D21: ='Expenditure Breakdown'!C119 -> Engineering | F21: =+'Expenditure Breakdown'!J119 -> 376288.01 | H21: 392244.02 | J21: =+'Expenditure Breakdown'!X119 -> 155538.58 | L21: =F21-J21 -> 220749.43 | N21: =H21-J21 -> 236705.44 | P21: RV: Matriarch defects percentage 1.25%
B22: ='Expenditure Breakdown'!B127 -> 14 | D22: ='Expenditure Breakdown'!C127 -> General Expenses | F22: =+'Expenditure Breakdown'!J127 -> 10325 | H22: 10325 | J22: =+'Expenditure Breakdown'!X127 -> 8729.38 | L22: =F22-J22 -> 1595.62 | N22: =H22-J22 -> 1595.62
B23: ='Expenditure Breakdown'!B137 -> 15 | D23: ='Expenditure Breakdown'!C137 -> Service Add On | F23: =+'Expenditure Breakdown'!J137 -> 0 | H23: 0 | J23: =+'Expenditure Breakdown'!X137 -> 24802.3 | L23: =F23-J23 -> -24802.3 | N23: =H23-J23 -> -24802.3
D25: check: | F25: ='Expenditure Breakdown'!J2-'Expenditure Tracking'!F5 -> 0 | G25: ='Expenditure Breakdown'!#REF!-G5 -> #REF! | H25: ='Expenditure Breakdown'!X2-J5 -> 0 | I25: ='Expenditure Breakdown'!#REF!-I5 -> #REF! | J25: ='Expenditure Breakdown'!X2-J5 -> 0
A27: Copy amounts in column H and paste as values at Project review.

Sheet Expenditure Breakdown
B2: COSTED EXPENDITURE BREAKDOWN | J2: =SUM(J6:J141) -> 4800198.7 | K2: =SUM(K6:K141) -> 5630032.8 | M2: ACTUAL EXPENDITURE BREAKDOWN | S2: FINANCE ONLY | X2: =SUM(X6:X141) -> 4032944.1
B4: No. | C4: Product / Service | D4: Description of Work | E4: QTY | F4: Rate / Unit | G4: Budget Total | H4: Project Related date | J4: Total COS | K4: =IF(K2-'Revenue Tracking'!D4>=0, "Total Revenue", "ERROR on REV" ) -> Total Revenue | M4: No. | N4: Product/ Service | O4: Description of Work | P4: QTY | Q4: Rate / Unit | R4: Actual Total | S4: INVOICE NUMBER | T4: INVOICE RAISED DATE | U4: REVENUE RECOGNITION AMOUNT | V4: CHECK | W4: FINANCE PAYMENT DATE | X4: Total COS | Y4: PO NUMBER | Z4: COMMENTS
B6: 1 | C6: Panels | D6: Longi 570W - Costing Sheet | E6: 1044 | F6: 1535.1525 | G6: =E6*F6 -> 1602699.2 | H6: ='Project Plan'!E35+60 -> 45698 | J6: =SUM(G6:G14) -> 1642699.2 | K6: 1955594.3 | M6: 1 | N6: 1. Panels | O6: Canadian Solar 555W - Deposit - Herholdts | P6: 1073 | Q6: 1415.25 | R6: =P6*Q6*0.5 -> 759281.62 | S6: Herholdts Inv: INV875402 | T6: 45504 | U6: 940631.82 | V6: =K6-SUM(U6:U14) -> 0.0013203188 | W6: 45562 | X6: =SUM(R6:R14) -> 1520595.1 | Y6: PO3244-SAM-20240719 - RV Approved | AA6: 19
B7: 1 | D7: Jinko Solar 575W | M7: 1 | N7: 1. Panels | R7: 618186.63 | S7: Herholdts Inv: INV875402 | T7: 45504 | U7: 940631.82 | W7: 45582 | AA7: BUDGET | AB7: Installer Allocation
M8: 1 | N8: 1. Panels | R8: =759281.625-R7 -> 141094.99 | S8: Herholdts Inv: INV875402 | T8: 45504 | U8: 0 | W8: 45596
M9: 1 | N9: 1. Panels | O9: Canadian Solar 555W - moved to stock | P9: 15 | Q9: -1415.25 | R9: =P9*Q9 -> -21228.75 | S9: Allocated to Stock | T9: 45716 | W9: 45716
M10: 1 | N10: 1. Panels | O10: 2 x Canadian Solar 555W - Stock | P10: 2 | Q10: 1415.25 | R10: =P10*Q10 -> 2830.5 | S10: Stock | T10: 45900 | W10: 45900 | Y10: PO3713-SAM14A-20250304 - RV Approved
B11: 1 | M11: 1 | N11: 1. Panels | O11: Delivery | R11: 2600 | S11: Supply Chain Inv:SCO04658 | T11: 45688 | W11: 45673 | AA11: AC Equipment | AB11: =C63 -> 840770.37
B12: 1 | D12: Delivery | G12: 40000 | H12: =H6 -> 45698 | M12: 1 | N12: 1. Panels | O12: Delivery | R12: 9050 | S12: Supply Chain Inv:SCO04658 | T12: 45657 | U12: 63458.249 | W12: 45673 | AA12: DC Equipment | AB12: =SUM(G30:G37) -> 208422.9
B13: 1 | M13: 1 | N13: 1. Panels | O13: Storage | R13: 4860 | S13: Supply Chain: Inv SCO04502 | T13: 45596 | U13: 5882.6761 | W13: 45625 | AA13: AC Labour | AB13: =C90 -> 347130
B14: 1 | M14: 1 | N14: 1. Panels | O14: Storage | R14: 3920.14 | S14: Supply Chain: Inv SCO04610 | T14: 45626 | U14: 4989.7399 | W14: 45645 | AA14: DC Labour | AB14: =C89 -> 148770
AA15: Offloading | AB15: =G104 -> 8500
B16: 2 | C16: Inverters | D16: Huawei 100KTL | E16: 5 | F16: 78898 | G16: =E16*F16 -> 394490 | H16: ='Project Plan'!E22+30 -> 45609 | J16: =SUM(G16:G19) -> 394490 | K16: 469630.95 | M16: 2 | N16: 2. Inverters | O16: Huawei 100KTL | P16: 5 | Q16: 68870 | R16: =P16*Q16 -> 344350 | S16: Kathea Inv 518635 | T16: 45565 | U16: 468128.44 | V16: =K16-SUM(U16:U19) -> 0 | W16: =T16+30 -> 45595 | X16: =SUM(R16:R19) -> 345455.23 | Z16: MI: Kathea Quote | AA16: Telehandler | AB16: =G97 -> 0
B17: 2 | M17: 2 | N17: 2. Inverters | U17: 0 | AA17: Storage | AB17: =G105 -> 7276.67
B18: 2 | M18: 2 | N18: 2. Inverters | O18: Delivery | R18: 1105.23 | S18: Kathea Inv 518635 | T18: 45565 | U18: 1502.5108 | W18: =W16 -> 45595 | AA18: =D107 -> Scaffolding | AB18: =G107 -> 53523.3
B19: 2 | M19: 2 | N19: 2. Inverters | U19: 0 | AA19: Other | AB19: 0
AA20: Total | AB20: =SUM(AB11:AB19) -> 1614393.2
B21: 3 | C21: Mounting Structures | D21: KlipLok Roof | E21: ='Project Plan'!E3*1000 -> 595000 | F21: 0.45 | G21: 238032 | H21: ='Project Plan'!E19+30 -> 45609 | J21: =SUM(G21:G25) -> 238032 | K21: 283371.43 | M21: 3 | N21: 3. Mounting Structures | O21: KlipLok Roof | R21: 112831.4 | S21: Schletter Inv0892 | T21: 45565 | U21: 278800.18 | V21: =K21-SUM(U21:U25) -> 0 | W21: 45558 | X21: =SUM(R21:R25) -> 73364.1 | Y21: PO3363-SAM20-20240918 - RV Approved | AA21: Less 15% | AB21: =+AB20*0.85 -> 1372234.3
B22: 3 | M22: 3 | N22: 3. Mounting Structures | O22: IBR Clampfit brackets used from Colcab PH2 | P22: 500 | Q22: 24.13 | R22: 12065 | S22: Allocated from colcab - Phase 2 | T22: 45688 | U22: 0 | W22: 45688 | Y22: PO3419-SAM-20241024 - RV Approved | AA22: R/Wp | AB22: =+AB21/'Project Plan'!$E$3/1000 -> 2.3062761
B23: 3 | M23: 3 | N23: 3. Mounting Structures | O23: Delivery | R23: 1850 | S23: Schletter Inv0893 | T23: 45565 | U23: 4571.2482 | W23: 45558
N24: 3. Mounting Structures | R24: -58094.8 | S24: Schletter Credit: CRN0157 | T24: 45626 | U24: 0 | W24: 45626
B25: 3 | M25: 3 | N25: 3. Mounting Structures | R25: 4712.5 | S25: Schletter - INV1717 | T25: 45777 | U25: 0 | W25: 45806 | AA25: ACTUAL - Cosmic Sun | AB25: Installer Price
AA26: AC Equipment | AB26: 114860
B27: 4 | C27: DC Equipment | D27: DC Cable | E27: 11835 | F27: 16 | G27: =E27*F27 -> 189360 | H27: ='Project Plan'!E31+30 -> 45609 | J27: =SUM(G27:G37) -> 419782.9 | K27: 499741.55 | M27: 4 | N27: 4. DC Equipment | O27: DC Cable | P27: 9000 | Q27: 13.5 | R27: =P27*Q27 -> 121500 | S27: Herholdts Inv: INV8954316 | T27: 45626 | U27: 116715.45 | V27: =K27-SUM(U27:U37) -> -0.0027933418 | W27: 45645 | X27: =SUM(R27:R37) -> 550887.4 | Y27: PO3315-MUL-20240823 - RV Approved | AA27: DC Equipment | AB27: 309687.4
B28: 4 | D28: DC Surge Arrestor | E28: 4 | F28: 5500 | G28: =E28*F28 -> 22000 | H28: =H30 -> 45668 | M28: 4 | N28: 4. DC Equipment | O28: DC Cable | P28: 6000 | R28: 79800 | S28: Menlo Inv0002268 | T28: 45626 | U28: 78043.755 | W28: 45680 | Y28: PO3470-SAM-20241121 - RV Approved | Z28: TC | AA28: AC Labour | AB28: 124583.33
M29: 4 | N29: 4. DC Equipment | O29: DC Cable | P29: 3000 | Q29: 13.3 | R29: =P29*Q29 -> 39900 | S29: Menlo: INV0002444 | T29: 45688 | U29: 10968.288 | W29: 45744
B30: 4 | D30: DC Cable Tray | E30: 180 | F30: 261 | G30: =E30*F30 -> 46980 | H30: ='Project Plan'!E34+30 -> 45668 | M30: 4 | N30: 4. DC Equipment | O30: Deposit | P30: =AB27 -> 309687.4 | Q30: 0.3 | R30: =$P$30*Q30 -> 92906.22 | S30: Cosmic Sun CS_SAM14A_001 | T30: 45596 | U30: 92972.106 | W30: =W88 -> 45603 | Y30: PO3374-SAM14A-20240930 - RV Approved | AA30: DC Labour | AB30: 388750
B31: 4 | D31: Earth Cable | E31: =E27 -> 11835 | F31: 13.5 | G31: =E31*F31 -> 159772.5 | H31: =H21 -> 45609 | M31: 4 | N31: 4. DC Equipment | O31: All DC and AC Equipment on site | Q31: 0.2 | R31: =$P$30*Q31 -> 61937.48 | S31: Cosmic Sun CS_SAM14A_002 | T31: =T89 -> 45626 | U31: 60574.355 | W31: =W89 -> 45638 | AA31: Offloading | AB31: 8500
B32: 4 | D32: Earth clamp | E32: 104.4 | F32: 16 | G32: =E32*F32 -> 1670.4 | H32: ='Project Plan'!E35 -> 45638 | M32: 4 | N32: 4. DC Equipment | O32: Practical completion | Q32: 0.3 | R32: =$P$30*Q32 -> 92906.22 | S32: Cosmic Sun CS_SAM14A_005 | T32: =T90 -> 45716 | U32: 84280.559 | W32: =W90 -> 45708 | AA32: Telehandler | AB32: 0
B33: 4 | M33: 4 | N33: 4. DC Equipment | O33: Site fully Commissioned | Q33: 0.15 | R33: =$P$30*Q33 -> 46453.11 | S33: Cosmic Sun CS_SAM14A_005 | T33: =T91 -> 45716 | U33: 42140.28 | W33: =W91 -> 45722 | AA33: Storage | AB33: 0
B34: 4 | M34: 4 | N34: 4. DC Equipment | O34: Retention | Q34: 0.05 | R34: =$P$30*Q34 -> 15484.37 | S34: Cosmic Sun CS_SAM14A_006 | T34: 45716 | U34: 14046.76 | W34: =W92 -> 45744 | AA34: Roof Access | AB34: 55000
B35: 4 | M35: 4 | N35: 4. DC Equipment | U35: =(R35/$X$27*$K$27) -> 0 | AA35: Other | AB35: 0
B36: 4 | M36: 4 | N36: 4. DC Equipment | U36: =(R36/$X$27*$K$27) -> 0 | AA36: Other | AB36: 0
B37: 4 | M37: 4 | N37: 4. DC Equipment | U37: =(R37/$X$27*$K$27) -> 0 | AA37: Other | AB37: 0
T38: =IF(W38>1,EOMONTH(W38,-1),"") | AA38: Total | AB38: =SUM(AB26:AB37) -> 1001380.7
B39: 5 | C39: Monitoring | D39: Smartlogger 3000 | E39: 1 | F39: 26000 | G39: =F39*E39 -> 26000 | H39: =H16 -> 45609 | J39: =SUM(G39:G54) -> 49000 | K39: 58333.333 | M39: 5 | N39: 5. Monitoring | O39: Smartlogger 3000 | P39: 1 | Q39: 8000 | R39: =Q39*P39 -> 8000 | S39: Solarworld SASIV-24-00517 | T39: 45535 | U39: 5797.7857 | V39: =K39-SUM(U39:U54) -> -0.00089976827 | W39: 45561 | X39: =SUM(R39:R54) -> 109045.78 | Z39: MI: Kathea quote 14/08 | AA39: R/Wp | AB39: =+AB38/'Project Plan'!$E$3/1000 -> 1.6829928
B40: 5 | D40: Comms DB | G40: 8000 | H40: =H39 -> 45609 | M40: 5 | N40: 5. Monitoring | O40: CTs | R40: 13740.5 | S40: AccuEnergy ASAI-003743 | T40: 45535 | U40: 9958.0592 | W40: 45562
B41: 5 | D41: Revenue Grade Meter | E41: 1 | F41: 15000 | G41: =F41*E41 -> 15000 | H41: ='Project Plan'!G51 -> 45684 | M41: 5 | N41: 5. Monitoring | O41: Revenue Grade Meter | P41: 1 | Q41: 11169 | R41: =Q41*P41 -> 11169 | S41: MATRIARCH - INV-3278 | T41: 45626 | U41: 14579.835 | W41: 45626
M42: 5 | N42: 5. Monitoring | O42: Delivery of Techsitter Meter | R42: 129.63 | S42: DSV Inv: 180102912 | T42: 45596 | U42: 100.5784 | W42: 45625
B43: 5 | M43: 5 | N43: 5. Monitoring | O43: SCADA | R43: 35750 | S43: Rubicon INVWCRE-0060133 | T43: 45535 | U43: 25908.855 | W43: 45562
M44: 5 | N44: 5. Monitoring | O44: SCADA | R44: -35750 | S44: Allocated to Stock | T44: 45808 | W44: 45808
M45: 5 | N45: 5. Monitoring | Y45: PO3821-SAM14A-20250424 - RV Approved
M46: 5 | N46: 5. Monitoring | O46: Janitza - UMG 604 | R46: 20383.2 | S46: Harmonious - QU100593 | T46: 45777 | W46: 45785 | Y46: PO3824-SA-M-20250425 - RV Approved
M47: 5 | N47: 5. Monitoring | O47: Delivery | R47: 110.44 | S47: DV Inv: 1801311355 | T47: 45808 | W47: 45835
M48: 5 | N48: 5. Monitoring | O48: Apex MCS-G2 Hardware & License | R48: 50000 | S48: Rubicon - INVWCRE-0067407 | T48: 45808 | W48: 45813 | Y48: PO3841-SAM14A-20250429 - RV Approved
M49: 5 | N49: 5. Monitoring
M50: 5 | N50: 5. Monitoring
M51: 5 | N51: 5. Monitoring
M52: 5 | N52: 5. Monitoring
B53: 5 | M53: 5 | N53: 5. Monitoring | O53: Frontline Comms Equipment | R53: =12812.55/5 -> 2562.51 | S53: Frontline Electrical: INV697940 | T53: 45596 | U53: 1988.2216 | W53: 45575 | Y53: PO3387-SAM-20241007 - RV Approved | Z53: PO split across the portfolio
B54: 5 | M54: 5 | N54: 5. Monitoring | O54: Router | R54: 2950.5 | S54: Accuenergy - Inv ASAI-004773 | T54: 45716 | U54: 0 | W54: 45744 | Y54: PO3639-SAM14A-20250211 - RV Approved
T55: =IF(W55>1,EOMONTH(W55,-1),"")
B56: 6 | C56: AC Equipment | J56: =SUM(G56:G69) -> 840770.37 | K56: 1000917.1 | M56: 6 | N56: 6. AC Equipment | T56: =IF(W56>1,EOMONTH(W56,-1),"") | U56: =(R56/$X$56*$K$56) -> 0 | V56: =K56-SUM(U56:U69) -> -0.0047396945 | X56: =SUM(R56:R69) -> 395469.19
M57: 6 | N57: 6. AC Equipment | O57: PVDB | R57: 24166.67 | S57: Cosmic Sun: CS_SAM_001 | T57: 45504 | U57: 33846.877 | W57: =W58 -> 45505 | Y57: RV Approved without PO
M58: 6 | N58: 6. AC Equipment | O58: Installation and Supply of equipment | R58: 218731.24 | S58: Cosmic Sun: CS_SAM_001 | T58: 45504 | U58: 306346.27 | W58: 45505 | Y58: PO3261-SAM-20240726 - RV Approved
M59: 6 | N59: 6. AC Equipment | O59: HSE | R59: 4500 | S59: Cosmic Sun: CS_SAM_001 | T59: 45504 | U59: 6302.521 | W59: 45505
M60: 6 | N60: 6. AC Equipment | T60: 45535 | U60: 337063.73
M61: 6 | N61: 6. AC Equipment | U61: =(R61/$X$56*$K$56) -> 0
B62: 6 | D62: Project Kick Off | F62: 0.1 | G62: =$C$63*F62 -> 84077.037 | H62: =H94 -> 45695 | M62: 6 | N62: 6. AC Equipment | O62: Deposit | P62: =AB26 -> 114860 | Q62: 0.3 | R62: =$P$62*Q62 -> 34458 | S62: Cosmic Sun CS_SAM14A_001 | T62: =T88 -> 45596 | U62: 95207.311 | W62: =W88 -> 45603 | Y62: PO3374-SAM14A-20240930 - RV Approved
B63: 6 | C63: 840770.37 | D63: Site Establishment | F63: 0.15 | G63: =$C$63*F63 -> 126115.56 | H63: =H89 -> 45579 | M63: 6 | N63: 6. AC Equipment | O63: All DC and AC Equipment on site | Q63: 0.2 | R63: =$P$62*Q63 -> 22972 | S63: Cosmic Sun CS_SAM14A_002 | T63: =T89 -> 45626 | U63: 63471.541 | W63: =W89 -> 45638
B64: 6 | D64: AC Installation Complete | F64: 0.2 | G64: =$C$63*F64 -> 168154.07 | H64: =H90 -> 45643 | M64: 6 | N64: 6. AC Equipment | O64: Practical completion | Q64: 0.3 | R64: =$P$62*Q64 -> 34458 | S64: Cosmic Sun CS_SAM14A_005 | T64: =T90 -> 45716 | U64: 87211.855 | W64: =W90 -> 45708
B65: 6 | D65: DC Installation Complete | F65: 0.25 | G65: =$C$63*F65 -> 210192.59 | H65: =H91 -> 45673 | M65: 6 | N65: 6. AC Equipment | O65: Site fully Commissioned | Q65: 0.15 | R65: =$P$62*Q65 -> 17229 | S65: Cosmic Sun CS_SAM14A_005 | T65: =T91 -> 45716 | U65: 43605.928 | W65: =W91 -> 45722
B66: 6 | D66: Commissioning Complete | F66: 0.1 | G66: =$C$63*F66 -> 84077.037 | H66: =H92 -> 45681 | M66: 6 | N66: 6. AC Equipment | O66: Retention | Q66: 0.05 | R66: =$P$62*Q66 -> 5743 | S66: Cosmic Sun CS_SAM14A_006 | T66: 45716 | U66: 14535.309 | W66: =W92 -> 45744
B67: 6 | D67: Site De-establisment | F67: 0.1 | G67: =$C$63*F67 -> 84077.037 | H67: =H93 -> 45688 | M67: 6 | N67: 6. AC Equipment | U67: =(R67/$X$56*$K$56) -> 0
B68: 6 | D68: Handover Document Complete | F68: 0.05 | G68: =$C$63*F68 -> 42038.519 | H68: =H94 -> 45695 | M68: 6 | N68: 6. AC Equipment | O68: Additional AC Cable | R68: 33211.28 | S68: CS_SAM14A_003 | T68: 45716 | U68: 13325.765 | W68: 45701 | Y68: PO3626-SAM14A-20250205 - RV Approved
B69: 6 | D69: End of Defects Period | F69: 0.05 | G69: =$C$63*F69 -> 42038.519 | H69: =H95 -> 45725 | M69: 6 | N69: 6. AC Equipment | T69: =IF(W69>1,EOMONTH(W69,-1),"") | U69: =(R69/$X$56*$K$56) -> 0
T70: =IF(W70>1,EOMONTH(W70,-1),"")
B71: 7 | C71: Battery Systems | J71: =SUM(G71:G78) -> 0 | K71: 0 | M71: 7 | N71: Battery Systems | T71: =IF(W71>1,EOMONTH(W71,-1),"") | V71: =K71-SUM(U71:U78) -> 0 | X71: =SUM(R71:R78) -> 0
B72: 7 | M72: 7 | T72: =IF(W72>1,EOMONTH(W72,-1),"")
B73: 7 | M73: 7 | T73: =IF(W73>1,EOMONTH(W73,-1),"")
B74: 7 | M74: 7 | T74: =IF(W74>1,EOMONTH(W74,-1),"")
B75: 7 | M75: 7 | T75: =IF(W75>1,EOMONTH(W75,-1),"")
B76: 7 | M76: 7 | T76: =IF(W76>1,EOMONTH(W76,-1),"")
B77: 7 | M77: 7 | T77: =IF(W77>1,EOMONTH(W77,-1),"")
B78: 7 | M78: 7 | T78: =IF(W78>1,EOMONTH(W78,-1),"")
T79: =IF(W79>1,EOMONTH(W79,-1),"")
B80: 8 | C80: Product Add On | J80: =SUM(G80:G86) -> 30000 | K80: =35714.28571+98946.32 -> 134660.61 | M80: 8 | N80: 8. Product Add On | O80: Switch Disconnectors | R80: 16916.75 | S80: All Electrical Inv IN142421 | T80: 45626 | U80: 19385.246 | V80: =K80-SUM(U80:U86) -> -0.0015993319 | W80: 45603 | X80: =SUM(R80:R86) -> 121265.17 | Y80: PO3452-SAM-20241105 - RV Approved
B81: 8 | D81: Comms Cable Run | G81: 30000 | H81: =H66 -> 45681 | M81: 8 | N81: 8. Product Add On | O81: Delivery | R81: 1650 | S81: All Electrical SO049152 | T81: 45626 | U81: 35714.29 | W81: 45603
B82: 8 | M82: 8 | N82: 8. Product Add On | O82: Mounting Structure for Walkways | P82: Splice Kit | Q82: =6*94.8 -> 568.8 | R82: =21221.6/5 -> 4244.32 | S82: Schletter INV0951 | T82: 45596 | U82: 4863.6522 | W82: =T82+29 -> 45625 | Y82: PO3389-SAM-20241008 - RV Approved
M83: 8 | N83: 8. Product Add On | O83: Walkway Installation | P83: Labour | Q83: =R83/(52*5.7)*34.2 -> 2492.3077 | R83: 21600 | S83: Cosmic Sun - CS_SAM14A_004 | T83: 45716 | U83: 0 | W83: 45701
B84: 8 | M84: 8 | N84: 8. Product Add On | O84: Walkways | P84: Walkways | Q84: 17847.9 | R84: 89239.5 | S84: Onvlee Engineering: Inv 0148938 | T84: 45626 | U84: 68437.83 | W84: 45603 | Y84: PO3390-SAM-20241008 - RV Approved
M85: 8 | N85: 8. Product Add On | O85: Walkways transport | R85: 5462.5 | S85: Onvlee Engineering: Inv 0148938 | T85: 45626 | U85: 6259.5893 | W85: 45603
B86: 8 | M86: 8 | N86: 8. Product Add On | O86: WAlkways Allocated to Trident Steel - PE | R86: -17847.9 | S86: Allocated to Trident Steel - PE | T86: 45747 | U86: 0 | W86: 45747
L87: Only services to be capture below, products above | T87: =IF(W87>1,EOMONTH(W87,-1),"")
B88: 9 | C88: AC & DC Installation | D88: Project Kick Off | F88: 0.1 | G88: =SUM($C$89:$C$90)*F88 -> 49590 | H88: ='Project Plan'!E19-7 -> 45572 | J88: =SUM(G88:G95) -> 495900 | K88: 583411.76 | M88: 9 | N88: 9. AC & DC installation | O88: Deposit | P88: =AB28+AB30 -> 513333.33 | Q88: 0.3 | R88: =$P$88*Q88 -> 154000 | S88: Cosmic Sun CS_SAM14A_001 | T88: 45596 | U88: 175023.53 | V88: 0 | W88: 45603 | X88: =SUM(R88:R95) -> 513333.33 | Y88: PO3374-SAM14A-20240930 - RV Approved
B89: 9 | C89: 148770 | D89: Site Establishment | F89: 0.15 | G89: =SUM($C$89:$C$90)*F89 -> 74385 | H89: ='Project Plan'!I19 -> 45579 | M89: 9 | N89: 9. AC & DC installation | O89: All DC and AC Equipment on site | Q89: 0.2 | R89: =$P$88*Q89 -> 102666.67 | S89: Cosmic Sun CS_SAM14A_002 | T89: 45626 | U89: 116682.35 | W89: 45638
B90: 9 | C90: 347130 | D90: AC Installation Complete | F90: 0.2 | G90: =SUM($C$89:$C$90)*F90 -> 99180 | H90: ='Project Plan'!G21 -> 45643 | M90: 9 | N90: 9. AC & DC installation | O90: Practical completion | Q90: 0.3 | R90: =$P$88*Q90 -> 154000 | S90: Cosmic Sun CS_SAM14A_005 | T90: 45716 | U90: 175023.53 | W90: 45708
B91: 9 | D91: DC Installation Complete | F91: 0.25 | G91: =SUM($C$89:$C$90)*F91 -> 123975 | H91: ='Project Plan'!G28 -> 45673 | M91: 9 | N91: 9. AC & DC installation | O91: Site fully Commissioned | Q91: 0.15 | R91: =$P$88*Q91 -> 77000 | S91: Cosmic Sun CS_SAM14A_005 | T91: 45716 | U91: 87511.765 | W91: 45722
B92: 9 | D92: Commissioning Complete | F92: 0.1 | G92: =SUM($C$89:$C$90)*F92 -> 49590 | H92: ='Project Plan'!G38 -> 45681 | M92: 9 | N92: 9. AC & DC installation | O92: Retention | Q92: 0.05 | R92: =$P$88*Q92 -> 25666.667 | S92: Cosmic Sun CS_SAM14A_006 | T92: 45716 | U92: 29170.588 | W92: 45744
B93: 9 | D93: Site De-establisment | F93: 0.1 | G93: =SUM($C$89:$C$90)*F93 -> 49590 | H93: ='Project Plan'!G47 -> 45688 | M93: 9 | N93: 9. AC & DC installation | U93: =(R93/$X$88*$K$88) -> 0
B94: 9 | D94: Handover Document Complete | F94: 0.05 | G94: =SUM($C$89:$C$90)*F94 -> 24795 | H94: ='Project Plan'!G49 -> 45695 | M94: 9 | N94: 9. AC & DC installation | U94: =(R94/$X$88*$K$88) -> 0
B95: 9 | D95: End of Defects Period | F95: 0.05 | G95: =SUM($C$89:$C$90)*F95 -> 24795 | H95: =H94+30 -> 45725 | M95: 9 | N95: 9. AC & DC installation | U95: =(R95/$X$88*$K$88) -> 0
T96: =IF(W96>1,EOMONTH(W96,-1),"")
B97: 10 | C97: Site Logistics | J97: =SUM(G97:G107) -> 69299.97 | K97: 81529.373 | M97: 10 | N97: 10. Site Logistics | O97: Security | T97: =IF(W97>1,EOMONTH(W97,0),"") | U97: =R97/$X$97*$K$97 -> 0 | V97: =K97-SUM(U97:U107) -> 0.0010440446 | X97: =SUM(R97:R107) -> 63500
M98: 10 | N98: 10. Site Logistics | T98: =IF(W98>1,EOMONTH(W98,-1),"") | U98: =R98/$X$97*$K$97 -> 0
M99: 10 | N99: 10. Site Logistics | O99: Deposit | P99: =AB31+AB34 -> 63500 | Q99: 0.3 | R99: =$P$99*Q99 -> 19050 | S99: Cosmic Sun CS_SAM14A_001 | T99: 45596 | U99: 19785.153 | W99: =W88 -> 45603 | Y99: PO3374-SAM14A-20240930 - RV Approved
M100: 10 | N100: 10. Site Logistics | O100: All DC and AC Equipment on site | Q100: 0.2 | R100: =$P$99*Q100 -> 12700 | S100: Cosmic Sun CS_SAM14A_002 | T100: =T89 -> 45626 | U100: 24458.812 | W100: =W89 -> 45638
M101: 10 | N101: 10. Site Logistics | O101: Practical completion | Q101: 0.3 | R101: =$P$99*Q101 -> 19050 | S101: Cosmic Sun CS_SAM14A_005 | T101: =T90 -> 45716 | U101: 24458.812 | W101: =W90 -> 45708
M102: 10 | N102: 10. Site Logistics | O102: Site fully Commissioned | Q102: 0.15 | R102: =$P$99*Q102 -> 9525 | S102: Cosmic Sun CS_SAM14A_005 | T102: =T91 -> 45716 | U102: 8750.1259 | W102: =W91 -> 45722
M103: 10 | N103: 10. Site Logistics | O103: Retention | Q103: 0.05 | R103: =$P$99*Q103 -> 3175 | S103: Cosmic Sun CS_SAM14A_006 | T103: 45716 | U103: 4076.4686 | W103: =W92 -> 45744
...

Sheet Cashflow
D1: [RT: Double Check the first date is always a MONDAY] | F1: 45488 | G1: =F1+7 -> 45495 | H1: =G1+7 -> 45502 | I1: =H1+7 -> 45509 | J1: =I1+7 -> 45516 | K1: =J1+7 -> 45523 | L1: =K1+7 -> 45530 | M1: =L1+7 -> 45537 | N1: =M1+7 -> 45544 | ... CW1: =CV1+7 -> 46153
A2: PLANNED | C2: CHECK | D2: CHECK
B3: Planned Revenue | C3: ='Revenue Tracking'!D4 -> 5531086.5 | D3: =SUM(F3:BQ3) -> 5651632.8 | F3: =SUMIFS('Revenue Tracking'!$F$13:$F$19, 'Revenue Tracking'!$H$13:$H$19, ">="&F1,'Revenue Tracking'!$H$13:$H$19, "<"&G1) -> 1935880.3 | G3: =SUMIFS('Revenue Tracking'!$F$13:$F$19, 'Revenue Tracking'!$H$13:$H$19, ">="&G1,'Revenue Tracking'!$H$13:$H$19, "<"&H1) -> 0 | H3: =SUMIFS('Revenue Tracking'!$F$13:$F$19, 'Revenue Tracking'!$H$13:$H$19, ">="&H1,'Revenue Tracking'!$H$13:$H$19, "<"&I1) -> 0 | I3: =SUMIFS('Revenue Tracking'!$F$13:$F$19, 'Revenue Tracking'!$H$13:$H$19, ">="&I1,'Revenue Tracking'!$H$13:$H$19, "<"&J1) -> 0 | J3: =SUMIFS('Revenue Tracking'!$F$13:$F$19, 'Revenue Tracking'!$H$13:$H$19, ">="&J1,'Revenue Tracking'!$H$13:$H$19, "<"&K1) -> 0 | K3: =SUMIFS('Revenue Tracking'!$F$13:$F$19, 'Revenue Tracking'!$H$13:$H$19, ">="&K1,'Revenue Tracking'!$H$13:$H$19, "<"&L1) -> 0 | L3: =SUMIFS('Revenue Tracking'!$F$13:$F$19, 'Revenue Tracking'!$H$13:$H$19, ">="&L1,'Revenue Tracking'!$H$13:$H$19, "<"&M1) -> 0 | M3: =SUMIFS('Revenue Tracking'!$F$13:$F$19, 'Revenue Tracking'!$H$13:$H$19, ">="&M1,'Revenue Tracking'!$H$13:$H$19, "<"&N1) -> 0 | ... BP3: =SUMIFS('Revenue Tracking'!$F$13:$F$19, 'Revenue Tracking'!$H$13:$H$19, ">="&BP1,'Revenue Tracking'!$H$13:$H$19, "<"&BQ1) -> 0 | BQ3: =SUMIFS('Revenue Tracking'!$F$13:$F$19, 'Revenue Tracking'!$H$13:$H$19, ">="&BQ1,'Revenue Tracking'!$H$13:$H$19, "<"&CX1) -> 0 | BR3: =SUMIFS('Revenue Tracking'!$F$13:$F$19, 'Revenue Tracking'!$H$13:$H$19, ">="&BR1,'Revenue Tracking'!$H$13:$H$19, "<"&CY1) -> 0 | BS3: =SUMIFS('Revenue Tracking'!$F$13:$F$19, 'Revenue Tracking'!$H$13:$H$19, ">="&BS1,'Revenue Tracking'!$H$13:$H$19, "<"&CZ1) -> 0 | BT3: =SUMIFS('Revenue Tracking'!$F$13:$F$19, 'Revenue Tracking'!$H$13:$H$19, ">="&BT1,'Revenue Tracking'!$H$13:$H$19, "<"&DA1) -> 0 | BU3: =SUMIFS('Revenue Tracking'!$F$13:$F$19, 'Revenue Tracking'!$H$13:$H$19, ">="&BU1,'Revenue Tracking'!$H$13:$H$19, "<"&DB1) -> 0 | BV3: =SUMIFS('Revenue Tracking'!$F$13:$F$19, 'Revenue Tracking'!$H$13:$H$19, ">="&BV1,'Revenue Tracking'!$H$13:$H$19, "<"&DC1) -> 0 | BW3: =SUMIFS('Revenue Tracking'!$F$13:$F$19, 'Revenue Tracking'!$H$13:$H$19, ">="&BW1,'Revenue Tracking'!$H$13:$H$19, "<"&DD1) -> 0 | BX3: =SUMIFS('Revenue Tracking'!$F$13:$F$19, 'Revenue Tracking'!$H$13:$H$19, ">="&BX1,'Revenue Tracking'!$H$13:$H$19, "<"&DE1) -> 0 | ... CW3: =SUMIFS('Revenue Tracking'!$F$13:$F$19, 'Revenue Tracking'!$H$13:$H$19, ">="&CW1,'Revenue Tracking'!$H$13:$H$19, "<"&ED1) -> 0
B4: Planned Revenue - Cumulative | F4: =F3 -> 1935880.3 | G4: =F4+G3 -> 1935880.3 | H4: =G4+H3 -> 1935880.3 | I4: =H4+I3 -> 1935880.3 | J4: =I4+J3 -> 1935880.3 | K4: =J4+K3 -> 1935880.3 | L4: =K4+L3 -> 1935880.3 | M4: =L4+M3 -> 1935880.3 | N4: =M4+N3 -> 1935880.3 | ... CW4: =CV4+CW3 -> 5651632.8
B5: Planned Expenditure | C5: ='Revenue Tracking'!D5 -> 4800198.7 | D5: =SUM(F5:BQ5) -> 4800198.7 | F5: =SUMIFS('Expenditure Breakdown'!$G$6:$G$140, 'Expenditure Breakdown'!$H$6:$H$140, ">="&F1,'Expenditure Breakdown'!$H$6:$H$140, "<"&G1) -> 0 | G5: =SUMIFS('Expenditure Breakdown'!$G$6:$G$140, 'Expenditure Breakdown'!$H$6:$H$140, ">="&G1,'Expenditure Breakdown'!$H$6:$H$140, "<"&H1) -> 0 | H5: =SUMIFS('Expenditure Breakdown'!$G$6:$G$140, 'Expenditure Breakdown'!$H$6:$H$140, ">="&H1,'Expenditure Breakdown'!$H$6:$H$140, "<"&I1) -> 0 | I5: =SUMIFS('Expenditure Breakdown'!$G$6:$G$140, 'Expenditure Breakdown'!$H$6:$H$140, ">="&I1,'Expenditure Breakdown'!$H$6:$H$140, "<"&J1) -> 0 | J5: =SUMIFS('Expenditure Breakdown'!$G$6:$G$140, 'Expenditure Breakdown'!$H$6:$H$140, ">="&J1,'Expenditure Breakdown'!$H$6:$H$140, "<"&K1) -> 0 | K5: =SUMIFS('Expenditure Breakdown'!$G$6:$G$140, 'Expenditure Breakdown'!$H$6:$H$140, ">="&K1,'Expenditure Breakdown'!$H$6:$H$140, "<"&L1) -> 0 | L5: =SUMIFS('Expenditure Breakdown'!$G$6:$G$140, 'Expenditure Breakdown'!$H$6:$H$140, ">="&L1,'Expenditure Breakdown'!$H$6:$H$140, "<"&M1) -> 0 | M5: =SUMIFS('Expenditure Breakdown'!$G$6:$G$140, 'Expenditure Breakdown'!$H$6:$H$140, ">="&M1,'Expenditure Breakdown'!$H$6:$H$140, "<"&N1) -> 0 | ... BP5: =SUMIFS('Expenditure Breakdown'!$G$6:$G$140, 'Expenditure Breakdown'!$H$6:$H$140, ">="&BP1,'Expenditure Breakdown'!$H$6:$H$140, "<"&BQ1) -> 0 | BQ5: =SUMIFS('Expenditure Breakdown'!$G$6:$G$140, 'Expenditure Breakdown'!$H$6:$H$140, ">="&BQ1,'Expenditure Breakdown'!$H$6:$H$140, "<"&CX1) -> 0 | BR5: =SUMIFS('Expenditure Breakdown'!$G$6:$G$140, 'Expenditure Breakdown'!$H$6:$H$140, ">="&BR1,'Expenditure Breakdown'!$H$6:$H$140, "<"&CY1) -> 0 | BS5: =SUMIFS('Expenditure Breakdown'!$G$6:$G$140, 'Expenditure Breakdown'!$H$6:$H$140, ">="&BS1,'Expenditure Breakdown'!$H$6:$H$140, "<"&CZ1) -> 0 | BT5: =SUMIFS('Expenditure Breakdown'!$G$6:$G$140, 'Expenditure Breakdown'!$H$6:$H$140, ">="&BT1,'Expenditure Breakdown'!$H$6:$H$140, "<"&DA1) -> 0 | BU5: =SUMIFS('Expenditure Breakdown'!$G$6:$G$140, 'Expenditure Breakdown'!$H$6:$H$140, ">="&BU1,'Expenditure Breakdown'!$H$6:$H$140, "<"&DB1) -> 0 | BV5: =SUMIFS('Expenditure Breakdown'!$G$6:$G$140, 'Expenditure Breakdown'!$H$6:$H$140, ">="&BV1,'Expenditure Breakdown'!$H$6:$H$140, "<"&DC1) -> 0 | BW5: =SUMIFS('Expenditure Breakdown'!$G$6:$G$140, 'Expenditure Breakdown'!$H$6:$H$140, ">="&BW1,'Expenditure Breakdown'!$H$6:$H$140, "<"&DD1) -> 0 | BX5: =SUMIFS('Expenditure Breakdown'!$G$6:$G$140, 'Expenditure Breakdown'!$H$6:$H$140, ">="&BX1,'Expenditure Breakdown'!$H$6:$H$140, "<"&DE1) -> 0 | ... CW5: =SUMIFS('Expenditure Breakdown'!$G$6:$G$140, 'Expenditure Breakdown'!$H$6:$H$140, ">="&CW1,'Expenditure Breakdown'!$H$6:$H$140, "<"&ED1) -> 0
B6: Planned Expenditure - Cumulative | F6: =F5 -> 0 | G6: =F6+G5 -> 0 | H6: =G6+H5 -> 0 | I6: =H6+I5 -> 0 | J6: =I6+J5 -> 0 | K6: =J6+K5 -> 0 | L6: =K6+L5 -> 0 | M6: =L6+M5 -> 0 | N6: =M6+N5 -> 0 | ... CW6: =CV6+CW5 -> 4800198.7
B7: PLANNED CashFlow | F7: =F4-F6 -> 1935880.3 | G7: =G4-G6 -> 1935880.3 | H7: =H4-H6 -> 1935880.3 | I7: =I4-I6 -> 1935880.3 | J7: =J4-J6 -> 1935880.3 | K7: =K4-K6 -> 1935880.3 | L7: =L4-L6 -> 1935880.3 | M7: =M4-M6 -> 1935880.3 | ... CW7: =CW4-CW6 -> 851434.11
A8: ACTUAL | C8: CHECK | D8: CHECK
B9: Actual + Planned Revenue | C9: ='Revenue Tracking'!F4 -> 5630723.8 | D9: =SUM(F9:BQ9) -> 4821969.8 | F9: =SUMIFS('Revenue Tracking'!$F$13:$F$19, 'Revenue Tracking'!$P$13:$P$19, ">="&F1,'Revenue Tracking'!$P$13:$P$19, "<"&G1) -> 1935880.3 | G9: =SUMIFS('Revenue Tracking'!$F$13:$F$19, 'Revenue Tracking'!$P$13:$P$19, ">="&G1,'Revenue Tracking'!$P$13:$P$19, "<"&H1) -> 0 | H9: =SUMIFS('Revenue Tracking'!$F$13:$F$19, 'Revenue Tracking'!$P$13:$P$19, ">="&H1,'Revenue Tracking'!$P$13:$P$19, "<"&I1) -> 0 | I9: =SUMIFS('Revenue Tracking'!$F$13:$F$19, 'Revenue Tracking'!$P$13:$P$19, ">="&I1,'Revenue Tracking'!$P$13:$P$19, "<"&J1) -> 0 | J9: =SUMIFS('Revenue Tracking'!$F$13:$F$19, 'Revenue Tracking'!$P$13:$P$19, ">="&J1,'Revenue Tracking'!$P$13:$P$19, "<"&K1) -> 0 | K9: =SUMIFS('Revenue Tracking'!$F$13:$F$19, 'Revenue Tracking'!$P$13:$P$19, ">="&K1,'Revenue Tracking'!$P$13:$P$19, "<"&L1) -> 0 | L9: =SUMIFS('Revenue Tracking'!$F$13:$F$19, 'Revenue Tracking'!$P$13:$P$19, ">="&L1,'Revenue Tracking'!$P$13:$P$19, "<"&M1) -> 0 | M9: =SUMIFS('Revenue Tracking'!$F$13:$F$19, 'Revenue Tracking'!$P$13:$P$19, ">="&M1,'Revenue Tracking'!$P$13:$P$19, "<"&N1) -> 0 | ... CW9: =SUMIFS('Revenue Tracking'!$F$13:$F$19, 'Revenue Tracking'!$P$13:$P$19, ">="&CW1,'Revenue Tracking'!$P$13:$P$19, "<"&CX1) -> 0
B10: Actual + Planned Revenue - Cumulative | F10: =F9 -> 1935880.3 | G10: =F10+G9 -> 1935880.3 | H10: =G10+H9 -> 1935880.3 | I10: =H10+I9 -> 1935880.3 | J10: =I10+J9 -> 1935880.3 | K10: =J10+K9 -> 1935880.3 | L10: =K10+L9 -> 1935880.3 | M10: =L10+M9 -> 1935880.3 | N10: =M10+N9 -> 1935880.3 | ... CW10: =CV10+CW9 -> 5630723.8
B11: Actual + Planned Expenditure | C11: ='Revenue Tracking'!F5 -> 4032944.1 | D11: =SUM(F11:BQ11) -> 4024356.6 | F11: =SUMIFS('Expenditure Breakdown'!$R$6:$R$140, 'Expenditure Breakdown'!$W$6:$W$140, ">="&F1,'Expenditure Breakdown'!$W$6:$W$140, "<"&G1) -> 0 | G11: =SUMIFS('Expenditure Breakdown'!$R$6:$R$140, 'Expenditure Breakdown'!$W$6:$W$140, ">="&G1,'Expenditure Breakdown'!$W$6:$W$140, "<"&H1) -> 0 | H11: =SUMIFS('Expenditure Breakdown'!$R$6:$R$140, 'Expenditure Breakdown'!$W$6:$W$140, ">="&H1,'Expenditure Breakdown'!$W$6:$W$140, "<"&I1) -> 247397.91 | I11: =SUMIFS('Expenditure Breakdown'!$R$6:$R$140, 'Expenditure Breakdown'!$W$6:$W$140, ">="&I1,'Expenditure Breakdown'!$W$6:$W$140, "<"&J1) -> 0 | J11: =SUMIFS('Expenditure Breakdown'!$R$6:$R$140, 'Expenditure Breakdown'!$W$6:$W$140, ">="&J1,'Expenditure Breakdown'!$W$6:$W$140, "<"&K1) -> 0 | K11: =SUMIFS('Expenditure Breakdown'!$R$6:$R$140, 'Expenditure Breakdown'!$W$6:$W$140, ">="&K1,'Expenditure Breakdown'!$W$6:$W$140, "<"&L1) -> 0 | L11: =SUMIFS('Expenditure Breakdown'!$R$6:$R$140, 'Expenditure Breakdown'!$W$6:$W$140, ">="&L1,'Expenditure Breakdown'!$W$6:$W$140, "<"&M1) -> 0 | M11: =SUMIFS('Expenditure Breakdown'!$R$6:$R$140, 'Expenditure Breakdown'!$W$6:$W$140, ">="&M1,'Expenditure Breakdown'!$W$6:$W$140, "<"&N1) -> 69032.82 | ... BP11: =SUMIFS('Expenditure Breakdown'!$R$6:$R$140, 'Expenditure Breakdown'!$W$6:$W$140, ">="&BP1,'Expenditure Breakdown'!$W$6:$W$140, "<"&BQ1) -> 0 | BQ11: =SUMIFS('Expenditure Breakdown'!$R$6:$R$140, 'Expenditure Breakdown'!$W$6:$W$140, ">="&BQ1,'Expenditure Breakdown'!$W$6:$W$140, "<"&CX1) -> 0 | BR11: =SUMIFS('Expenditure Breakdown'!$R$6:$R$140, 'Expenditure Breakdown'!$W$6:$W$140, ">="&BR1,'Expenditure Breakdown'!$W$6:$W$140, "<"&CY1) -> 0 | BS11: =SUMIFS('Expenditure Breakdown'!$R$6:$R$140, 'Expenditure Breakdown'!$W$6:$W$140, ">="&BS1,'Expenditure Breakdown'!$W$6:$W$140, "<"&CZ1) -> 0 | BT11: =SUMIFS('Expenditure Breakdown'!$R$6:$R$140, 'Expenditure Breakdown'!$W$6:$W$140, ">="&BT1,'Expenditure Breakdown'!$W$6:$W$140, "<"&DA1) -> 0 | BU11: =SUMIFS('Expenditure Breakdown'!$R$6:$R$140, 'Expenditure Breakdown'!$W$6:$W$140, ">="&BU1,'Expenditure Breakdown'!$W$6:$W$140, "<"&DB1) -> 0 | BV11: =SUMIFS('Expenditure Breakdown'!$R$6:$R$140, 'Expenditure Breakdown'!$W$6:$W$140, ">="&BV1,'Expenditure Breakdown'!$W$6:$W$140, "<"&DC1) -> 0 | BW11: =SUMIFS('Expenditure Breakdown'!$R$6:$R$140, 'Expenditure Breakdown'!$W$6:$W$140, ">="&BW1,'Expenditure Breakdown'!$W$6:$W$140, "<"&DD1) -> 0 | BX11: =SUMIFS('Expenditure Breakdown'!$R$6:$R$140, 'Expenditure Breakdown'!$W$6:$W$140, ">="&BX1,'Expenditure Breakdown'!$W$6:$W$140, "<"&DE1) -> 0 | ... CW11: =SUMIFS('Expenditure Breakdown'!$R$6:$R$140, 'Expenditure Breakdown'!$W$6:$W$140, ">="&CW1,'Expenditure Breakdown'!$W$6:$W$140, "<"&ED1) -> 0
B12: Actual + Planned Expenditure - Cumulative | F12: =F11 -> 0 | G12: =F12+G11 -> 0 | H12: =G12+H11 -> 247397.91 | I12: =H12+I11 -> 247397.91 | J12: =I12+J11 -> 247397.91 | K12: =J12+K11 -> 247397.91 | L12: =K12+L11 -> 247397.91 | M12: =L12+M11 -> 316430.73 | N12: =M12+N11 -> 316430.73 | ... CW12: =CV12+CW11 -> 4024356.6
B14: ACTUAL CashFlow | F14: =F10-F12 -> 1935880.3 | G14: =G10-G12 -> 1935880.3 | H14: =H10-H12 -> 1688482.3 | I14: =I10-I12 -> 1688482.3 | J14: =J10-J12 -> 1688482.3 | K14: =K10-K12 -> 1688482.3 | L14: =L10-L12 -> 1688482.3 | M14: =M10-M12 -> 1619449.5 | ... CW14: =CW10-CW12 -> 1606367.1
C16: CHECK | D16: CHECK
B17: Revenue Recognition | C17: =C3-D17 -> -98946.321 | D17: =SUM(F17:BQ17) -> 5630032.8 | F17: =SUMIFS('Expenditure Breakdown'!$U$6:$U$140, 'Expenditure Breakdown'!$T$6:$T$140, ">="&F1,'Expenditure Breakdown'!$T$6:$T$140, "<"&G1) -> 0 | G17: =SUMIFS('Expenditure Breakdown'!$U$6:$U$140, 'Expenditure Breakdown'!$T$6:$T$140, ">="&G1,'Expenditure Breakdown'!$T$6:$T$140, "<"&H1) -> 0 | H17: =SUMIFS('Expenditure Breakdown'!$U$6:$U$140, 'Expenditure Breakdown'!$T$6:$T$140, ">="&H1,'Expenditure Breakdown'!$T$6:$T$140, "<"&I1) -> 2227759.3 | I17: =SUMIFS('Expenditure Breakdown'!$U$6:$U$140, 'Expenditure Breakdown'!$T$6:$T$140, ">="&I1,'Expenditure Breakdown'!$T$6:$T$140, "<"&J1) -> 0 | J17: =SUMIFS('Expenditure Breakdown'!$U$6:$U$140, 'Expenditure Breakdown'!$T$6:$T$140, ">="&J1,'Expenditure Breakdown'!$T$6:$T$140, "<"&K1) -> 0 | K17: =SUMIFS('Expenditure Breakdown'!$U$6:$U$140, 'Expenditure Breakdown'!$T$6:$T$140, ">="&K1,'Expenditure Breakdown'!$T$6:$T$140, "<"&L1) -> 0 | L17: =SUMIFS('Expenditure Breakdown'!$U$6:$U$140, 'Expenditure Breakdown'!$T$6:$T$140, ">="&L1,'Expenditure Breakdown'!$T$6:$T$140, "<"&M1) -> 394247.31 | M17: =SUMIFS('Expenditure Breakdown'!$U$6:$U$140, 'Expenditure Breakdown'!$T$6:$T$140, ">="&M1,'Expenditure Breakdown'!$T$6:$T$140, "<"&N1) -> 0 | ... BP17: =SUMIFS('Expenditure Breakdown'!$U$6:$U$140, 'Expenditure Breakdown'!$T$6:$T$140, ">="&BP1,'Expenditure Breakdown'!$T$6:$T$140, "<"&BQ1) -> 0 | BQ17: =SUMIFS('Expenditure Breakdown'!$U$6:$U$140, 'Expenditure Breakdown'!$T$6:$T$140, ">="&BQ1,'Expenditure Breakdown'!$T$6:$T$140, "<"&CX1) -> 0 | BR17: =SUMIFS('Expenditure Breakdown'!$U$6:$U$140, 'Expenditure Breakdown'!$T$6:$T$140, ">="&BR1,'Expenditure Breakdown'!$T$6:$T$140, "<"&CY1) -> 0 | BS17: =SUMIFS('Expenditure Breakdown'!$U$6:$U$140, 'Expenditure Breakdown'!$T$6:$T$140, ">="&BS1,'Expenditure Breakdown'!$T$6:$T$140, "<"&CZ1) -> 0 | BT17: =SUMIFS('Expenditure Breakdown'!$U$6:$U$140, 'Expenditure Breakdown'!$T$6:$T$140, ">="&BT1,'Expenditure Breakdown'!$T$6:$T$140, "<"&DA1) -> 0 | BU17: =SUMIFS('Expenditure Breakdown'!$U$6:$U$140, 'Expenditure Breakdown'!$T$6:$T$140, ">="&BU1,'Expenditure Breakdown'!$T$6:$T$140, "<"&DB1) -> 0 | BV17: =SUMIFS('Expenditure Breakdown'!$U$6:$U$140, 'Expenditure Breakdown'!$T$6:$T$140, ">="&BV1,'Expenditure Breakdown'!$T$6:$T$140, "<"&DC1) -> 0 | BW17: =SUMIFS('Expenditure Breakdown'!$U$6:$U$140, 'Expenditure Breakdown'!$T$6:$T$140, ">="&BW1,'Expenditure Breakdown'!$T$6:$T$140, "<"&DD1) -> 0 | BX17: =SUMIFS('Expenditure Breakdown'!$U$6:$U$140, 'Expenditure Breakdown'!$T$6:$T$140, ">="&BX1,'Expenditure Breakdown'!$T$6:$T$140, "<"&DE1) -> 0 | ... CW17: =SUMIFS('Expenditure Breakdown'!$U$6:$U$140, 'Expenditure Breakdown'!$T$6:$T$140, ">="&CW1,'Expenditure Breakdown'!$T$6:$T$140, "<"&ED1) -> 0
B18: Revenue Recognition Cumulative | C18: =D17-D18 -> 0 | D18: =MAX(F18:BQ18) -> 5630032.8 | F18: =F17 -> 0 | G18: =F18+G17 -> 0 | H18: =G18+H17 -> 2227759.3 | I18: =H18+I17 -> 2227759.3 | J18: =I18+J17 -> 2227759.3 | K18: =J18+K17 -> 2227759.3 | L18: =K18+L17 -> 2622006.6 | M18: =L18+M17 -> 2622006.6 | N18: =M18+N17 -> 2622006.6 | ... CW18: =CV18+CW17 -> 5630032.8
B20: Installer Expenditure | D20: =SUM(F20:BQ20) -> 971092.01 | F20: =SUMIFS('Expenditure Breakdown'!$R$30:$R$37, 'Expenditure Breakdown'!$W$30:$W$37, ">="&F1,'Expenditure Breakdown'!$W$30:$W$37, "<"&G1)+SUMIFS('Expenditure Breakdown'!$R$62:$R$69, 'Expenditure Breakdown'!$W$62:$W$69, ">="&F1,'Expenditure Breakdown'!$W$62:$W$69, "<"&G1)+SUMIFS('Expenditure Breakdown'!$R$88:$R$95, 'Expenditure Breakdown'!$W$88:$W$95, ">="&F1,'Expenditure Breakdown'!$W$88:$W$95, "<"&G1) -> 0 | G20: =SUMIFS('Expenditure Breakdown'!$R$30:$R$37, 'Expenditure Breakdown'!$W$30:$W$37, ">="&G1,'Expenditure Breakdown'!$W$30:$W$37, "<"&H1)+SUMIFS('Expenditure Breakdown'!$R$62:$R$69, 'Expenditure Breakdown'!$W$62:$W$69, ">="&G1,'Expenditure Breakdown'!$W$62:$W$69, "<"&H1)+SUMIFS('Expenditure Breakdown'!$R$88:$R$95, 'Expenditure Breakdown'!$W$88:$W$95, ">="&G1,'Expenditure Breakdown'!$W$88:$W$95, "<"&H1) -> 0 | H20: =SUMIFS('Expenditure Breakdown'!$R$30:$R$37, 'Expenditure Breakdown'!$W$30:$W$37, ">="&H1,'Expenditure Breakdown'!$W$30:$W$37, "<"&I1)+SUMIFS('Expenditure Breakdown'!$R$62:$R$69, 'Expenditure Breakdown'!$W$62:$W$69, ">="&H1,'Expenditure Breakdown'!$W$62:$W$69, "<"&I1)+SUMIFS('Expenditure Breakdown'!$R$88:$R$95, 'Expenditure Breakdown'!$W$88:$W$95, ">="&H1,'Expenditure Breakdown'!$W$88:$W$95, "<"&I1) -> 0 | I20: =SUMIFS('Expenditure Breakdown'!$R$30:$R$37, 'Expenditure Breakdown'!$W$30:$W$37, ">="&I1,'Expenditure Breakdown'!$W$30:$W$37, "<"&J1)+SUMIFS('Expenditure Breakdown'!$R$62:$R$69, 'Expenditure Breakdown'!$W$62:$W$69, ">="&I1,'Expenditure Breakdown'!$W$62:$W$69, "<"&J1)+SUMIFS('Expenditure Breakdown'!$R$88:$R$95, 'Expenditure Breakdown'!$W$88:$W$95, ">="&I1,'Expenditure Breakdown'!$W$88:$W$95, "<"&J1) -> 0 | J20: =SUMIFS('Expenditure Breakdown'!$R$30:$R$37, 'Expenditure Breakdown'!$W$30:$W$37, ">="&J1,'Expenditure Breakdown'!$W$30:$W$37, "<"&K1)+SUMIFS('Expenditure Breakdown'!$R$62:$R$69, 'Expenditure Breakdown'!$W$62:$W$69, ">="&J1,'Expenditure Breakdown'!$W$62:$W$69, "<"&K1)+SUMIFS('Expenditure Breakdown'!$R$88:$R$95, 'Expenditure Breakdown'!$W$88:$W$95, ">="&J1,'Expenditure Breakdown'!$W$88:$W$95, "<"&K1) -> 0 | K20: =SUMIFS('Expenditure Breakdown'!$R$30:$R$37, 'Expenditure Breakdown'!$W$30:$W$37, ">="&K1,'Expenditure Breakdown'!$W$30:$W$37, "<"&L1)+SUMIFS('Expenditure Breakdown'!$R$62:$R$69, 'Expenditure Breakdown'!$W$62:$W$69, ">="&K1,'Expenditure Breakdown'!$W$62:$W$69, "<"&L1)+SUMIFS('Expenditure Breakdown'!$R$88:$R$95, 'Expenditure Breakdown'!$W$88:$W$95, ">="&K1,'Expenditure Breakdown'!$W$88:$W$95, "<"&L1) -> 0 | L20: =SUMIFS('Expenditure Breakdown'!$R$30:$R$37, 'Expenditure Breakdown'!$W$30:$W$37, ">="&L1,'Expenditure Breakdown'!$W$30:$W$37, "<"&M1)+SUMIFS('Expenditure Breakdown'!$R$62:$R$69, 'Expenditure Breakdown'!$W$62:$W$69, ">="&L1,'Expenditure Breakdown'!$W$62:$W$69, "<"&M1)+SUMIFS('Expenditure Breakdown'!$R$88:$R$95, 'Expenditure Breakdown'!$W$88:$W$95, ">="&L1,'Expenditure Breakdown'!$W$88:$W$95, "<"&M1) -> 0 | M20: =SUMIFS('Expenditure Breakdown'!$R$30:$R$37, 'Expenditure Breakdown'!$W$30:$W$37, ">="&M1,'Expenditure Breakdown'!$W$30:$W$37, "<"&N1)+SUMIFS('Expenditure Breakdown'!$R$62:$R$69, 'Expenditure Breakdown'!$W$62:$W$69, ">="&M1,'Expenditure Breakdown'!$W$62:$W$69, "<"&N1)+SUMIFS('Expenditure Breakdown'!$R$88:$R$95, 'Expenditure Breakdown'!$W$88:$W$95, ">="&M1,'Expenditure Breakdown'!$W$88:$W$95, "<"&N1) -> 0 | ... BP20: =SUMIFS('Expenditure Breakdown'!$R$30:$R$37, 'Expenditure Breakdown'!$W$30:$W$37, ">="&BP1,'Expenditure Breakdown'!$W$30:$W$37, "<"&BQ1)+SUMIFS('Expenditure Breakdown'!$R$62:$R$69, 'Expenditure Breakdown'!$W$62:$W$69, ">="&BP1,'Expenditure Breakdown'!$W$62:$W$69, "<"&BQ1)+SUMIFS('Expenditure Breakdown'!$R$88:$R$95, 'Expenditure Breakdown'!$W$88:$W$95, ">="&BP1,'Expenditure Breakdown'!$W$88:$W$95, "<"&BQ1) -> 0 | BQ20: =SUMIFS('Expenditure Breakdown'!$R$30:$R$37, 'Expenditure Breakdown'!$W$30:$W$37, ">="&BQ1,'Expenditure Breakdown'!$W$30:$W$37, "<"&CX1)+SUMIFS('Expenditure Breakdown'!$R$62:$R$69, 'Expenditure Breakdown'!$W$62:$W$69, ">="&BQ1,'Expenditure Breakdown'!$W$62:$W$69, "<"&CX1)+SUMIFS('Expenditure Breakdown'!$R$88:$R$95, 'Expenditure Breakdown'!$W$88:$W$95, ">="&BQ1,'Expenditure Breakdown'!$W$88:$W$95, "<"&CX1) -> 0 | BR20: =SUMIFS('Expenditure Breakdown'!$R$30:$R$37, 'Expenditure Breakdown'!$W$30:$W$37, ">="&BR1,'Expenditure Breakdown'!$W$30:$W$37, "<"&CY1)+SUMIFS('Expenditure Breakdown'!$R$62:$R$69, 'Expenditure Breakdown'!$W$62:$W$69, ">="&BR1,'Expenditure Breakdown'!$W$62:$W$69, "<"&CY1)+SUMIFS('Expenditure Breakdown'!$R$88:$R$95, 'Expenditure Breakdown'!$W$88:$W$95, ">="&BR1,'Expenditure Breakdown'!$W$88:$W$95, "<"&CY1) -> 0 | BS20: =SUMIFS('Expenditure Breakdown'!$R$30:$R$37, 'Expenditure Breakdown'!$W$30:$W$37, ">="&BS1,'Expenditure Breakdown'!$W$30:$W$37, "<"&CZ1)+SUMIFS('Expenditure Breakdown'!$R$62:$R$69, 'Expenditure Breakdown'!$W$62:$W$69, ">="&BS1,'Expenditure Breakdown'!$W$62:$W$69, "<"&CZ1)+SUMIFS('Expenditure Breakdown'!$R$88:$R$95, 'Expenditure Breakdown'!$W$88:$W$95, ">="&BS1,'Expenditure Breakdown'!$W$88:$W$95, "<"&CZ1) -> 0 | BT20: =SUMIFS('Expenditure Breakdown'!$R$30:$R$37, 'Expenditure Breakdown'!$W$30:$W$37, ">="&BT1,'Expenditure Breakdown'!$W$30:$W$37, "<"&DA1)+SUMIFS('Expenditure Breakdown'!$R$62:$R$69, 'Expenditure Breakdown'!$W$62:$W$69, ">="&BT1,'Expenditure Breakdown'!$W$62:$W$69, "<"&DA1)+SUMIFS('Expenditure Breakdown'!$R$88:$R$95, 'Expenditure Breakdown'!$W$88:$W$95, ">="&BT1,'Expenditure Breakdown'!$W$88:$W$95, "<"&DA1) -> 0 | BU20: =SUMIFS('Expenditure Breakdown'!$R$30:$R$37, 'Expenditure Breakdown'!$W$30:$W$37, ">="&BU1,'Expenditure Breakdown'!$W$30:$W$37, "<"&DB1)+SUMIFS('Expenditure Breakdown'!$R$62:$R$69, 'Expenditure Breakdown'!$W$62:$W$69, ">="&BU1,'Expenditure Breakdown'!$W$62:$W$69, "<"&DB1)+SUMIFS('Expenditure Breakdown'!$R$88:$R$95, 'Expenditure Breakdown'!$W$88:$W$95, ">="&BU1,'Expenditure Breakdown'!$W$88:$W$95, "<"&DB1) -> 0 | BV20: =SUMIFS('Expenditure Breakdown'!$R$30:$R$37, 'Expenditure Breakdown'!$W$30:$W$37, ">="&BV1,'Expenditure Breakdown'!$W$30:$W$37, "<"&DC1)+SUMIFS('Expenditure Breakdown'!$R$62:$R$69, 'Expenditure Breakdown'!$W$62:$W$69, ">="&BV1,'Expenditure Breakdown'!$W$62:$W$69, "<"&DC1)+SUMIFS('Expenditure Breakdown'!$R$88:$R$95, 'Expenditure Breakdown'!$W$88:$W$95, ">="&BV1,'Expenditure Breakdown'!$W$88:$W$95, "<"&DC1) -> 0 | BW20: =SUMIFS('Expenditure Breakdown'!$R$30:$R$37, 'Expenditure Breakdown'!$W$30:$W$37, ">="&BW1,'Expenditure Breakdown'!$W$30:$W$37, "<"&DD1)+SUMIFS('Expenditure Breakdown'!$R$62:$R$69, 'Expenditure Breakdown'!$W$62:$W$69, ">="&BW1,'Expenditure Breakdown'!$W$62:$W$69, "<"&DD1)+SUMIFS('Expenditure Breakdown'!$R$88:$R$95, 'Expenditure Breakdown'!$W$88:$W$95, ">="&BW1,'Expenditure Breakdown'!$W$88:$W$95, "<"&DD1) -> 0 | BX20: =SUMIFS('Expenditure Breakdown'!$R$30:$R$37, 'Expenditure Breakdown'!$W$30:$W$37, ">="&BX1,'Expenditure Breakdown'!$W$30:$W$37, "<"&DE1)+SUMIFS('Expenditure Breakdown'!$R$62:$R$69, 'Expenditure Breakdown'!$W$62:$W$69, ">="&BX1,'Expenditure Breakdown'!$W$62:$W$69, "<"&DE1)+SUMIFS('Expenditure Breakdown'!$R$88:$R$95, 'Expenditure Breakdown'!$W$88:$W$95, ">="&BX1,'Expenditure Breakdown'!$W$88:$W$95, "<"&DE1) -> 0 | ... CW20: =SUMIFS('Expenditure Breakdown'!$R$30:$R$37, 'Expenditure Breakdown'!$W$30:$W$37, ">="&CW1,'Expenditure Breakdown'!$W$30:$W$37, "<"&ED1)+SUMIFS('Expenditure Breakdown'!$R$62:$R$69, 'Expenditure Breakdown'!$W$62:$W$69, ">="&CW1,'Expenditure Breakdown'!$W$62:$W$69, "<"&ED1)+SUMIFS('Expenditure Breakdown'!$R$88:$R$95, 'Expenditure Breakdown'!$W$88:$W$95, ">="&CW1,'Expenditure Breakdown'!$W$88:$W$95, "<"&ED1) -> 0
B21: Installer Expenditure - Cumulative | F21: =F20 -> 0 | G21: =G20+F21 -> 0 | H21: =H20+G21 -> 0 | I21: =I20+H21 -> 0 | J21: =J20+I21 -> 0 | K21: =K20+J21 -> 0 | L21: =L20+K21 -> 0 | M21: =M20+L21 -> 0 | N21: =N20+M21 -> 0 | ... CW21: =CW20+CV21 -> 971092.01

Sheet Finance - Revenue
A1: REVENUE RECOGNITION AMOUNT | B1: (All)
A3: Sum of REVENUE RECOGNITION AMOUNT | B3: Column Labels
A4: Row Labels | C4: (blank) | D4: 45504 | E4: 45535 | F4: 45565 | G4: 45596 | H4: 45626 | I4: 45657 | J4: 45688 | K4: 45716 | L4: 45747 | M4: 45777 | N4: 45808 | O4: 45900 | P4: Grand Total
A5: (blank)
A6: Battery Systems
A7: BDP Commission
A8: 1. Panels | D8: 1881263.6 | G8: 5882.6761 | H8: 4989.7399 | I8: 63458.249 | P8: 1955594.3
A9: 2. Inverters | B9: 0 | F9: 469630.95 | P9: 469630.95
A10: 3. Mounting Structures | F10: 283371.43 | H10: 0 | J10: 0 | M10: 0 | P10: 283371.43
A11: 4. DC Equipment | C11: 0 | G11: 92972.106 | H11: 255333.56 | J11: 10968.288 | K11: 140467.6 | P11: 499741.55
A12: 5. Monitoring | E12: 41664.7 | G12: 2088.8 | H12: 14579.835 | K12: 0 | P12: 58333.334
A13: 6. AC Equipment | B13: 0 | C13: 0 | D13: 346495.67 | E13: 337063.73 | G13: 95207.311 | H13: 63471.541 | K13: 158678.86 | P13: 1000917.1
A14: 8. Product Add On | G14: 4863.6522 | H14: 129796.96 | K14: 0 | L14: 0 | P14: 134660.61
A15: 9. AC & DC installation | C15: 0 | G15: 175023.53 | H15: 116682.35 | K15: 291705.88 | P15: 583411.76
A16: 10. Site Logistics | B16: 0 | C16: 0 | G16: 19785.153 | H16: 24458.812 | K16: 37285.406 | P16: 81529.372
A17: 11. Due Dilligence | B17: 0 | C17: 0 | E17: 13475.245 | H17: 68551.201 | I17: 41068.844 | P17: 123095.29
A18: 13. Engineering | C18: 0 | I18: 427600.01 | O18: 0 | P18: 427600.01
A19: 14. General Expenses | E19: 2043.6389 | F19: 1891.2863 | G19: 2295.2209 | H19: 0 | J19: 2112.4106 | K19: 3804.4979 | L19: 0 | P19: 12147.055
A20: 15. Service Add On
A21: Grand Total | B21: 0 | C21: 0 | D21: 2227759.3 | E21: 394247.31 | F21: 754893.67 | G21: 398118.45 | H21: 677863.99 | I21: 532127.1 | J21: 13080.698 | K21: 631942.24 | L21: 0 | M21: 0 | O21: 0 | P21: 5630032.8
D23: 2227759.3 | E23: 429961.6 | F23: 754893.67 | G23: 398118.45 | H23: 677863.99 | I23: 532127.1 | J23: 13080.7 | K23: 631942.24 | L23: =SUM(D23:K23) -> 5665747
D24: =D21-D23 -> 0.0041026543 | E24: =E21-E23 -> -35714.286 | F24: =F21-F23 -> -0.0027489708 | G24: =G21-G23 -> -0.00062906678 | H24: =H21-H23 -> 0.0044473988 | I24: =I21-I23 -> 0.0022922873 | J24: =J21-J23 -> -0.0015927244 | K24: =K21-K23 -> 0.0023675358

Sheet Finance - COS
A3: Sum of Actual Total | B3: Column Labels
A4: Row Labels | B4: (blank) | D4: 45504 | E4: 45535 | F4: 45565 | G4: 45596 | H4: 45626 | I4: 45657 | J4: 45688 | K4: 45716 | L4: 45747 | M4: 45777 | N4: 45808 | O4: 45900 | P4: Grand Total
A5: Battery Systems
A6: BDP Commission | E6: 64490.1 | H6: 64490.1 | P6: 128980.2
A7: (blank)
A8: 1. Panels | D8: 1518563.2 | G8: 4860 | H8: 3920.14 | I8: 9050 | J8: 2600 | K8: -21228.75 | O8: 2830.5 | P8: 1520595.1
A9: 2. Inverters | F9: 345455.23 | P9: 345455.23
A10: 3. Mounting Structures | F10: 114681.4 | H10: -58094.8 | J10: 12065 | M10: 4712.5 | P10: 73364.1
A11: 4. DC Equipment | G11: 92906.22 | H11: 263237.48 | J11: 39900 | K11: 154843.7 | P11: 550887.4
A12: 5. Monitoring | E12: 57490.5 | G12: 2692.14 | H12: 11169 | K12: 2950.5 | M12: 20383.2 | N12: 14360.44 | P12: 109045.78
A13: 6. AC Equipment | D13: 247397.91 | G13: 34458 | H13: 22972 | K13: 90641.28 | P13: 395469.19
A14: 8. Product Add On | G14: 4244.32 | H14: 113268.75 | K14: 21600 | L14: -17847.9 | P14: 121265.17
A15: 9. AC & DC installation | G15: 154000 | H15: 102666.67 | K15: 256666.67 | P15: 513333.33
A16: 10. Site Logistics | G16: 19050 | H16: 12700 | K16: 31750 | P16: 63500
A17: 11. Due Dilligence | E17: 2520 | H17: 13458.33 | I17: 6000 | P17: 21978.33
A18: 13. Engineering | B18: 0 | I18: 69138.581 | O18: 86400 | P18: 155538.58
A19: 14. General Expenses | E19: 2022.72 | F19: 1570.98 | G19: 1671 | H19: 0 | J19: 1634.56 | K19: 423.22 | L19: 318.92 | M19: 1087.98 | P19: 8729.38
A20: 15. Service Add On | N20: 16214.8 | O20: 8587.5 | P20: 24802.3
A21: Grand Total | B21: 0 | D21: 1765961.2 | E21: 126523.32 | F21: 461707.61 | G21: 313881.68 | H21: 549787.67 | I21: 84188.581 | J21: 56199.56 | K21: 537646.61 | L21: -17528.98 | M21: 26183.68 | N21: 30575.24 | O21: 97818 | P21: 4032944.1

Sheet Project Margins
A1: [capture project margins from costing sheet]
A3: Products | D3: 0.32
A4: Services | D4: 0.5
A5: Expenses | D5: 0.15
A6: Subcontractors | D6: 0.2

Sheet Equipment Quotes
B2: Equipment Quote and Budget comparision
B4: Description | D4: Budget | F4: Supplier 1 | H4: Variance | J4: Supplier 2 | L4: Variance | N4: Comments / Notes
F7: >Name< | J7: >Name<
B9: Inverters | D9: =SUM(D10:D11) -> 394490 | F9: =SUM(F10:F13) -> 0 | H9: =$D$9-F9 -> 394490 | J9: =SUM(J10:J13) -> 0 | L9: =$D$9-J9 -> 394490
B10: Inverters | D10: ='Expenditure Breakdown'!G16 -> 394490
B11: Optimizers | D11: ='Expenditure Breakdown'!G17 -> 0
B12: Warranty
B13: Delivery fee
F15: >Name< | J15: >Name<
B17: Mounting Structure | D17: =SUM(D18:D19) -> 238032 | F17: =SUM(F18:F20) -> 0 | H17: =$D$17- F17 -> 238032 | J17: =SUM(J18:J20) -> 0 | L17: =$D$17- J17 -> 238032
B18: Mounting Structure | D18: ='Expenditure Breakdown'!G21 -> 238032
B19: Delivery fee
F21: >Name< | J21: >Name<
B23: DC Cable | D23: =SUM(D24:D25) -> 189360 | F23: =SUM(F24:F25) -> 0 | H23: =$D$23- F23 -> 189360 | J23: =SUM(J24:J25) -> 0 | L23: =$D$23- J23 -> 189360
B24: DC Cable | D24: ='Expenditure Breakdown'!G27 -> 189360
B25: Delivery fee
F27: >Name< | J27: >Name<
B29: Monitoring system | D29: =SUM(D30:D32) -> #REF! | F29: =SUM(F30:F42) -> 0 | H29: =$D$29-F29 -> #REF! | J29: =SUM(J30:J32) -> 0 | L29: =$D$29-J29 -> #REF!
B30: ='Expenditure Breakdown'!D39 -> Smartlogger 3000 | D30: ='Expenditure Breakdown'!G39 -> 26000
B31: ='Expenditure Breakdown'!#REF! -> #REF! | D31: ='Expenditure Breakdown'!#REF! -> #REF!
B32: Delivery fee
F34: >Name< | J34: >Name<
B36: Additional Scope | D36: =SUM(D37:D41) -> 0 | F36: =SUM(F37:F41) -> 0 | H36: =$D$29-F36 -> #REF! | J36: =SUM(J37:J41) -> 0 | L36: =$D$29-J36 -> #REF!
B37: SCADA | D37: ='Expenditure Breakdown'!G80 -> 0
B38: Inverter cage
B39: Cat ladders
B40: Gen Integration
B41: Lifelines
B43: Totals | D43: =D36+D29+D23+D17+D9 -> #REF! | H43: =SUM(H7:H42) -> #REF! | L43: =SUM(L7:L42) -> #REF!
B47: All amounts are incl VAT

Sheet Installer Quotes
B2: Installer Quote and Budget comparision
B4: Description | D4: Budget | G4: Cosmic Sun | J4: Variance | L4: Matthews Group | O4: Variance
B6: AC Equipment | D6: ='Expenditure Breakdown'!AB11 -> 840770.37 | E6: =D6/(1000*'Project Plan'!$E$3) -> 1.4130594 | G6: 277892.91 | H6: =G6/('Project Plan'!$E$3*1000) -> 0.46704691 | J6: =D6-G6 -> 562877.46 | M6: =L6/('Project Plan'!$E$3*1000) -> 0 | O6: =D6-L6 -> 840770.37
B7: DC Equipment | D7: ='Expenditure Breakdown'!AB12 -> 208422.9 | E7: =D7/(1000*'Project Plan'!$E$3) -> 0.35029059 | G7: 142158.25 | H7: =G7/('Project Plan'!$E$3*1000) -> 0.23892143 | J7: =D7-G7 -> 66264.65 | M7: =L7/('Project Plan'!$E$3*1000) -> 0 | O7: =D7-L7 -> 208422.9
B8: AC Labour | D8: ='Expenditure Breakdown'!AB13 -> 347130 | E8: =D8/(1000*'Project Plan'!$E$3) -> 0.58341176 | G8: 96174 | H8: =G8/('Project Plan'!$E$3*1000) -> 0.16163697 | J8: =D8-G8 -> 250956 | M8: =L8/('Project Plan'!$E$3*1000) -> 0 | O8: =D8-L8 -> 347130
B9: DC Labour | D9: ='Expenditure Breakdown'!AB14 -> 148770 | E9: =D9/(1000*'Project Plan'!$E$3) -> 0.25003361 | G9: 230160 | H9: =G9/('Project Plan'!$E$3*1000) -> 0.38682353 | J9: =D9-G9 -> -81390 | M9: =L9/('Project Plan'!$E$3*1000) -> 0 | O9: =D9-L9 -> 148770
B10: Offloading | D10: ='Expenditure Breakdown'!AB15 -> 8500 | G10: 0 | J10: =D10-G10 -> 8500 | O10: =D10-L10 -> 8500
B11: Roof Access/Scaffolding | D11: ='Expenditure Breakdown'!AB16 -> 0 | G11: 29257.61 | J11: =D11-G11 -> -29257.61 | O11: =D11-L11 -> 0
B12: Storage | D12: ='Expenditure Breakdown'!AB17 -> 7276.67 | J12: =D12-G12 -> 7276.67 | O12: =D12-L12 -> 7276.67
B13: Telehandler | D13: ='Expenditure Breakdown'!AB18 -> 53523.3
B14: HSE | D14: 0
B15: Totals | D15: =SUM(D6:D13) -> 1614393.2 | G15: =SUM(G6:G13) -> 775642.77 | J15: =SUM(J6:J14) -> 785227.17 | L15: =SUM(L6:L13) -> 0 | O15: =SUM(O6:O14) -> 1560869.9
B18: Description | D18: Budget | G18: >Installer Name 3< | J18: Variance | L18: >Installer Name 4< | O18: Variance
B20: AC installation | D20: ='Expenditure Breakdown'!#REF! -> #REF! | E20: =D20/(1000*'Project Plan'!$E$3) -> #REF! | H20: =G20/(1000*'Project Plan'!$E$3) -> 0 | J20: =D20-G20 -> #REF! | M20: =L20/(1000*'Project Plan'!$E$3) -> 0 | O20: =D6-L20 -> 840770.37
B21: AC equipment | D21: ='Expenditure Breakdown'!C69 -> 0 | E21: =D21/(1000*'Project Plan'!$E$3) -> 0 | J21: =D21-G21 -> 0 | M21: =L21/(1000*'Project Plan'!$E$3) -> 0 | O21: =D7-L21 -> 208422.9
B22: DC installation | D22: ='Expenditure Breakdown'!#REF! -> #REF! | E22: =D22/(1000*'Project Plan'!$E$3) -> #REF! | H22: =G22/(1000*'Project Plan'!$E$3) -> 0 | J22: =D22-G22 -> #REF! | M22: =L22/(1000*'Project Plan'!$E$3) -> 0 | O22: =D8-L22 -> 347130
B23: DC equipment | D23: =SUM('Expenditure Breakdown'!G35:G36) -> 0 | E23: =D23/(1000*'Project Plan'!$E$3) -> 0 | J23: =D23-G23 -> 0 | O23: =D9-L23 -> 148770
B24: Storage | D24: ='Expenditure Breakdown'!G113 -> 0 | J24: =D24-G24 -> 0 | O24: =D10-L24 -> 8500
B25: Panel lifting equipment | D25: =SUM('Expenditure Breakdown'!G97:G105) -> 15776.67 | J25: =D25-G25 -> 15776.67 | O25: =D11-L25 -> 0
B26: Offloading | D26: ='Expenditure Breakdown'!G107 -> 53523.3 | J26: =D26-G26 -> 53523.3 | O26: =D12-L26 -> 7276.67
B29: Totals | D29: =SUM(D20:D27) -> #REF! | G29: =SUM(G20:G27) -> 0 | J29: =SUM(J20:J28) -> #REF! | L29: =SUM(L20:L27) -> 0 | O29: =SUM(O20:O28) -> 1560869.9
B32: Budget Summary
B34: Budget | D34: =D15 -> 1614393.2
B35: =G4 -> Cosmic Sun | D35: =G15 -> 775642.77
B36: =L4 -> Matthews Group | D36: =L15 -> 0
B37: =G18 -> >Installer Name 3< | D37: =G29 -> 0
B38: =L18 -> >Installer Name 4< | D38: =L29 -> 0
B40: =IF(D40<D34,"Saving","Loss") -> Loss | D40: =D34-MIN(D35:D38) -> 1614393.2
B42: All amounts are exc VAT

Sheet Decision Register
B1: =D15 -> SA Metal - 14 Christiaan_A | E1: Decision Register
B3: ID | C3: Decision Description | D3: Decision Impact | E3: Proposed Date | F3: Proposed By | G3: Status | H3: Approved By | I3: Date | J3: Results / Comments
B4: DEC001
B5: DEC002
B6: DEC003
B7: DEC004
B8: DEC005
B9: DEC006
B10: DEC007
B11: DEC008
B12: DEC009
B13: DEC010
D15: {='Project Plan'!E2:H2} -> SA Metal - 14 Christiaan_A | E15: 0 | F15: 0 | G15: 0
