Workbook
Name Inverter_Capacity: #REF!
Name Inverter_Supplier: #REF!
Name Project_Size: Compliance!Projectsize
Name Project_Size: 'Finance - Revenue'!Projectsize
Name Project_Size: Projectsize
Name Projectsize: #REF!
Name Projectsize: #REF!
Name Projectsize: 'Project Margins'!$K$5
Name Security_Serv: #REF!
Name Security_Serv: #REF!
Name SSS: #REF!
Name SSS: #REF!
Name USD_ZAR: #REF!

Sheet Sheet1
A1: PROJECT PLAN
A2: # | B2: Project Milestone | C2: Planned Start Date | D2: Duration (Work Days) | E2: Planned End Date | F2: Actual Start Date | H2: Actual End Date | J2: Comments | L2: =C3 -> 43831 | M2: =L2+3 -> 43834 | N2: =M2+7 -> 43841 | O2: =N2+7 -> 43848 | P2: =O2+7 -> 43855 | Q2: =P2+6 -> 43861 | R2: =Q2+1 -> 43862 | S2: =R2+7 -> 43869 | T2: =S2+7 -> 43876 | U2: =T2+7 -> 43883 | V2: =U2+6 -> 43889 | W2: =V2+7 -> 43896 | X2: =W2+7 -> 43903 | Y2: =X2+7 -> 43910 | Z2: =Y2+7 -> 43917 | AA2: =Z2+3 -> 43920 | AB2: =AA2+4 -> 43924 | AC2: =AB2+7 -> 43931 | AD2: =AC2+7 -> 43938 | AE2: =AD2+7 -> 43945 | AF2: =AE2+6 -> 43951 | AG2: =AF2+2 -> 43953 | AH2: =AG2+7 -> 43960 | AI2: =AH2+7 -> 43967 | AJ2: =AI2+7 -> 43974 | AK2: =AJ2+7 -> 43981 | AL2: =AK2+1 -> 43982 | AM2: =AL2+6 -> 43988 | AN2: =AM2+7 -> 43995 | AO2: =AN2+7 -> 44002 | AP2: =AO2+7 -> 44009 | AQ2: =AP2+3 -> 44012 | AR2: =AQ2+4 -> 44016 | AS2: =AR2+7 -> 44023 | AT2: =AS2+7 -> 44030 | AU2: =AT2+7 -> 44037 | AV2: =AU2+6 -> 44043 | AW2: =AV2+1 -> 44044 | AX2: =AW2+7 -> 44051 | AY2: =AX2+7 -> 44058 | AZ2: =AY2+7 -> 44065 | BA2: =AZ2+7 -> 44072 | BB2: =BA2+2 -> 44074 | BC2: =BB2+5 -> 44079 | BD2: =BC2+7 -> 44086 | BE2: =BD2+7 -> 44093 | BF2: =BE2+7 -> 44100 | BG2: =BF2+4 -> 44104
A3: 1 | B3: Contract Signature | C3: 43831 | D3: 1 | E3: 43832 | F3: 43831 | G3: 1 | H3: 43832 | L3: =IF(AND($F3<(L$2+7),$F3>L$2),1, IF(AND($H3<L$2+7,$H3>L$2),3, IF(AND($F3<=L$2, $H3>=L$2), 2, "" ))) -> 3 | M3: =IF(AND($F3<(M$2+7),$F3>M$2),1, IF(AND($H3<M$2+7,$H3>M$2),3, IF(AND($F3<=M$2, $H3>=M$2), 2, "" ))) | N3: =IF(AND($F3<(N$2+7),$F3>N$2),1, IF(AND($H3<N$2+7,$H3>N$2),3, IF(AND($F3<=N$2, $H3>=N$2), 2, "" ))) | O3: =IF(AND($F3<(O$2+7),$F3>O$2),1, IF(AND($H3<O$2+7,$H3>O$2),3, IF(AND($F3<=O$2, $H3>=O$2), 2, "" ))) | P3: =IF(AND($F3<(P$2+7),$F3>P$2),1, IF(AND($H3<P$2+7,$H3>P$2),3, IF(AND($F3<=P$2, $H3>=P$2), 2, "" ))) | Q3: =IF(AND($F3<(Q$2+7),$F3>Q$2),1, IF(AND($H3<Q$2+7,$H3>Q$2),3, IF(AND($F3<=Q$2, $H3>=Q$2), 2, "" ))) | R3: =IF(AND($F3<(R$2+7),$F3>R$2),1, IF(AND($H3<R$2+7,$H3>R$2),3, IF(AND($F3<=R$2, $H3>=R$2), 2, "" ))) | S3: =IF(AND($F3<(S$2+7),$F3>S$2),1, IF(AND($H3<S$2+7,$H3>S$2),3, IF(AND($F3<=S$2, $H3>=S$2), 2, "" ))) | ... AQ3: =IF(AND($F3<(AQ$2+7),$F3>AQ$2),1, IF(AND($H3<AQ$2+7,$H3>AQ$2),3, IF(AND($F3<=AQ$2, $H3>=AQ$2), 2, "" )))
A4: A | B4: PAYMENT MILESTONE 1: DEPOSIT | C4: 43832 | D4: 1 | E4: 43833 | F4: 43832 | G4: 1 | H4: 43833 | L4: =IF(AND($F4<(L$2+7),$F4>L$2),1, IF(AND($H4<L$2+7,$H4>L$2),3, IF(AND($F4<=L$2, $H4>=L$2), 2, "" ))) -> 1 | M4: =IF(AND($F4<(M$2+7),$F4>M$2),1, IF(AND($H4<M$2+7,$H4>M$2),3, IF(AND($F4<=M$2, $H4>=M$2), 2, "" ))) | N4: =IF(AND($F4<(N$2+7),$F4>N$2),1, IF(AND($H4<N$2+7,$H4>N$2),3, IF(AND($F4<=N$2, $H4>=N$2), 2, "" ))) | O4: =IF(AND($F4<(O$2+7),$F4>O$2),1, IF(AND($H4<O$2+7,$H4>O$2),3, IF(AND($F4<=O$2, $H4>=O$2), 2, "" ))) | P4: =IF(AND($F4<(P$2+7),$F4>P$2),1, IF(AND($H4<P$2+7,$H4>P$2),3, IF(AND($F4<=P$2, $H4>=P$2), 2, "" ))) | Q4: =IF(AND($F4<(Q$2+7),$F4>Q$2),1, IF(AND($H4<Q$2+7,$H4>Q$2),3, IF(AND($F4<=Q$2, $H4>=Q$2), 2, "" ))) | R4: =IF(AND($F4<(R$2+7),$F4>R$2),1, IF(AND($H4<R$2+7,$H4>R$2),3, IF(AND($F4<=R$2, $H4>=R$2), 2, "" ))) | S4: =IF(AND($F4<(S$2+7),$F4>S$2),1, IF(AND($H4<S$2+7,$H4>S$2),3, IF(AND($F4<=S$2, $H4>=S$2), 2, "" ))) | ... AQ4: =IF(AND($F4<(AQ$2+7),$F4>AQ$2),1, IF(AND($H4<AQ$2+7,$H4>AQ$2),3, IF(AND($F4<=AQ$2, $H4>=AQ$2), 2, "" )))
A5: 2 | B5: Structural and Electrical Due Diligences | C5: 43833 | D5: 5 | E5: 43840 | F5: 43833 | G5: 5 | H5: 43840 | L5: =IF(AND($F5<(L$2+7),$F5>L$2),1, IF(AND($H5<L$2+7,$H5>L$2),3, IF(AND($F5<=L$2, $H5>=L$2), 2, "" ))) -> 1 | M5: =IF(AND($F5<(M$2+7),$F5>M$2),1, IF(AND($H5<M$2+7,$H5>M$2),3, IF(AND($F5<=M$2, $H5>=M$2), 2, "" ))) -> 3 | N5: =IF(AND($F5<(N$2+7),$F5>N$2),1, IF(AND($H5<N$2+7,$H5>N$2),3, IF(AND($F5<=N$2, $H5>=N$2), 2, "" ))) | O5: =IF(AND($F5<(O$2+7),$F5>O$2),1, IF(AND($H5<O$2+7,$H5>O$2),3, IF(AND($F5<=O$2, $H5>=O$2), 2, "" ))) | P5: =IF(AND($F5<(P$2+7),$F5>P$2),1, IF(AND($H5<P$2+7,$H5>P$2),3, IF(AND($F5<=P$2, $H5>=P$2), 2, "" ))) | Q5: =IF(AND($F5<(Q$2+7),$F5>Q$2),1, IF(AND($H5<Q$2+7,$H5>Q$2),3, IF(AND($F5<=Q$2, $H5>=Q$2), 2, "" ))) | R5: =IF(AND($F5<(R$2+7),$F5>R$2),1, IF(AND($H5<R$2+7,$H5>R$2),3, IF(AND($F5<=R$2, $H5>=R$2), 2, "" ))) | S5: =IF(AND($F5<(S$2+7),$F5>S$2),1, IF(AND($H5<S$2+7,$H5>S$2),3, IF(AND($F5<=S$2, $H5>=S$2), 2, "" ))) | ... AQ5: =IF(AND($F5<(AQ$2+7),$F5>AQ$2),1, IF(AND($H5<AQ$2+7,$H5>AQ$2),3, IF(AND($F5<=AQ$2, $H5>=AQ$2), 2, "" )))
A6: 3 | B6: Design Confirmation | C6: 43841 | D6: 2 | E6: 43844 | F6: 43841 | G6: 2 | H6: 43844 | L6: =IF(AND($F6<(L$2+7),$F6>L$2),1, IF(AND($H6<L$2+7,$H6>L$2),3, IF(AND($F6<=L$2, $H6>=L$2), 2, "" ))) | M6: =IF(AND($F6<(M$2+7),$F6>M$2),1, IF(AND($H6<M$2+7,$H6>M$2),3, IF(AND($F6<=M$2, $H6>=M$2), 2, "" ))) | N6: =IF(AND($F6<(N$2+7),$F6>N$2),1, IF(AND($H6<N$2+7,$H6>N$2),3, IF(AND($F6<=N$2, $H6>=N$2), 2, "" ))) -> 3 | O6: =IF(AND($F6<(O$2+7),$F6>O$2),1, IF(AND($H6<O$2+7,$H6>O$2),3, IF(AND($F6<=O$2, $H6>=O$2), 2, "" ))) | P6: =IF(AND($F6<(P$2+7),$F6>P$2),1, IF(AND($H6<P$2+7,$H6>P$2),3, IF(AND($F6<=P$2, $H6>=P$2), 2, "" ))) | Q6: =IF(AND($F6<(Q$2+7),$F6>Q$2),1, IF(AND($H6<Q$2+7,$H6>Q$2),3, IF(AND($F6<=Q$2, $H6>=Q$2), 2, "" ))) | R6: =IF(AND($F6<(R$2+7),$F6>R$2),1, IF(AND($H6<R$2+7,$H6>R$2),3, IF(AND($F6<=R$2, $H6>=R$2), 2, "" ))) | S6: =IF(AND($F6<(S$2+7),$F6>S$2),1, IF(AND($H6<S$2+7,$H6>S$2),3, IF(AND($F6<=S$2, $H6>=S$2), 2, "" ))) | ... AQ6: =IF(AND($F6<(AQ$2+7),$F6>AQ$2),1, IF(AND($H6<AQ$2+7,$H6>AQ$2),3, IF(AND($F6<=AQ$2, $H6>=AQ$2), 2, "" )))
A7: 4 | B7: Equipment Procurement | C7: 43833 | E7: 43949 | F7: 43833 | H7: 43949 | L7: =IF(AND($F7<(L$2+7),$F7>L$2),1, IF(AND($H7<L$2+7,$H7>L$2),3, IF(AND($F7<=L$2, $H7>=L$2), 2, "" ))) -> 1 | M7: =IF(AND($F7<(M$2+7),$F7>M$2),1, IF(AND($H7<M$2+7,$H7>M$2),3, IF(AND($F7<=M$2, $H7>=M$2), 2, "" ))) -> 2 | N7: =IF(AND($F7<(N$2+7),$F7>N$2),1, IF(AND($H7<N$2+7,$H7>N$2),3, IF(AND($F7<=N$2, $H7>=N$2), 2, "" ))) -> 2 | O7: =IF(AND($F7<(O$2+7),$F7>O$2),1, IF(AND($H7<O$2+7,$H7>O$2),3, IF(AND($F7<=O$2, $H7>=O$2), 2, "" ))) -> 2 | P7: =IF(AND($F7<(P$2+7),$F7>P$2),1, IF(AND($H7<P$2+7,$H7>P$2),3, IF(AND($F7<=P$2, $H7>=P$2), 2, "" ))) -> 2 | Q7: =IF(AND($F7<(Q$2+7),$F7>Q$2),1, IF(AND($H7<Q$2+7,$H7>Q$2),3, IF(AND($F7<=Q$2, $H7>=Q$2), 2, "" ))) -> 2 | R7: =IF(AND($F7<(R$2+7),$F7>R$2),1, IF(AND($H7<R$2+7,$H7>R$2),3, IF(AND($F7<=R$2, $H7>=R$2), 2, "" ))) -> 2 | S7: =IF(AND($F7<(S$2+7),$F7>S$2),1, IF(AND($H7<S$2+7,$H7>S$2),3, IF(AND($F7<=S$2, $H7>=S$2), 2, "" ))) -> 2 | ... AQ7: =IF(AND($F7<(AQ$2+7),$F7>AQ$2),1, IF(AND($H7<AQ$2+7,$H7>AQ$2),3, IF(AND($F7<=AQ$2, $H7>=AQ$2), 2, "" )))
B8: Panel Procurement | C8: 43833 | D8: 5 | E8: 43840 | F8: 43833 | G8: 5 | H8: 43840 | L8: =IF(AND($F8<(L$2+7),$F8>L$2),1, IF(AND($H8<L$2+7,$H8>L$2),3, IF(AND($F8<=L$2, $H8>=L$2), 2, "" ))) -> 1 | M8: =IF(AND($F8<(M$2+7),$F8>M$2),1, IF(AND($H8<M$2+7,$H8>M$2),3, IF(AND($F8<=M$2, $H8>=M$2), 2, "" ))) -> 3 | N8: =IF(AND($F8<(N$2+7),$F8>N$2),1, IF(AND($H8<N$2+7,$H8>N$2),3, IF(AND($F8<=N$2, $H8>=N$2), 2, "" ))) | O8: =IF(AND($F8<(O$2+7),$F8>O$2),1, IF(AND($H8<O$2+7,$H8>O$2),3, IF(AND($F8<=O$2, $H8>=O$2), 2, "" ))) | P8: =IF(AND($F8<(P$2+7),$F8>P$2),1, IF(AND($H8<P$2+7,$H8>P$2),3, IF(AND($F8<=P$2, $H8>=P$2), 2, "" ))) | Q8: =IF(AND($F8<(Q$2+7),$F8>Q$2),1, IF(AND($H8<Q$2+7,$H8>Q$2),3, IF(AND($F8<=Q$2, $H8>=Q$2), 2, "" ))) | R8: =IF(AND($F8<(R$2+7),$F8>R$2),1, IF(AND($H8<R$2+7,$H8>R$2),3, IF(AND($F8<=R$2, $H8>=R$2), 2, "" ))) | S8: =IF(AND($F8<(S$2+7),$F8>S$2),1, IF(AND($H8<S$2+7,$H8>S$2),3, IF(AND($F8<=S$2, $H8>=S$2), 2, "" ))) | ... AQ8: =IF(AND($F8<(AQ$2+7),$F8>AQ$2),1, IF(AND($H8<AQ$2+7,$H8>AQ$2),3, IF(AND($F8<=AQ$2, $H8>=AQ$2), 2, "" )))
B9: Inverter Procurement | C9: 43941 | D9: 5 | E9: 43949 | F9: 43941 | G9: 5 | H9: 43949 | L9: =IF(AND($F9<(L$2+7),$F9>L$2),1, IF(AND($H9<L$2+7,$H9>L$2),3, IF(AND($F9<=L$2, $H9>=L$2), 2, "" ))) | M9: =IF(AND($F9<(M$2+7),$F9>M$2),1, IF(AND($H9<M$2+7,$H9>M$2),3, IF(AND($F9<=M$2, $H9>=M$2), 2, "" ))) | N9: =IF(AND($F9<(N$2+7),$F9>N$2),1, IF(AND($H9<N$2+7,$H9>N$2),3, IF(AND($F9<=N$2, $H9>=N$2), 2, "" ))) | O9: =IF(AND($F9<(O$2+7),$F9>O$2),1, IF(AND($H9<O$2+7,$H9>O$2),3, IF(AND($F9<=O$2, $H9>=O$2), 2, "" ))) | P9: =IF(AND($F9<(P$2+7),$F9>P$2),1, IF(AND($H9<P$2+7,$H9>P$2),3, IF(AND($F9<=P$2, $H9>=P$2), 2, "" ))) | Q9: =IF(AND($F9<(Q$2+7),$F9>Q$2),1, IF(AND($H9<Q$2+7,$H9>Q$2),3, IF(AND($F9<=Q$2, $H9>=Q$2), 2, "" ))) | R9: =IF(AND($F9<(R$2+7),$F9>R$2),1, IF(AND($H9<R$2+7,$H9>R$2),3, IF(AND($F9<=R$2, $H9>=R$2), 2, "" ))) | S9: =IF(AND($F9<(S$2+7),$F9>S$2),1, IF(AND($H9<S$2+7,$H9>S$2),3, IF(AND($F9<=S$2, $H9>=S$2), 2, "" ))) | ... AQ9: =IF(AND($F9<(AQ$2+7),$F9>AQ$2),1, IF(AND($H9<AQ$2+7,$H9>AQ$2),3, IF(AND($F9<=AQ$2, $H9>=AQ$2), 2, "" )))
B10: Mounting Structure Procurement | C10: 43941 | D10: 5 | E10: 43949 | F10: 43941 | G10: 5 | H10: 43949 | L10: =IF(AND($F10<(L$2+7),$F10>L$2),1, IF(AND($H10<L$2+7,$H10>L$2),3, IF(AND($F10<=L$2, $H10>=L$2), 2, "" ))) | M10: =IF(AND($F10<(M$2+7),$F10>M$2),1, IF(AND($H10<M$2+7,$H10>M$2),3, IF(AND($F10<=M$2, $H10>=M$2), 2, "" ))) | N10: =IF(AND($F10<(N$2+7),$F10>N$2),1, IF(AND($H10<N$2+7,$H10>N$2),3, IF(AND($F10<=N$2, $H10>=N$2), 2, "" ))) | O10: =IF(AND($F10<(O$2+7),$F10>O$2),1, IF(AND($H10<O$2+7,$H10>O$2),3, IF(AND($F10<=O$2, $H10>=O$2), 2, "" ))) | P10: =IF(AND($F10<(P$2+7),$F10>P$2),1, IF(AND($H10<P$2+7,$H10>P$2),3, IF(AND($F10<=P$2, $H10>=P$2), 2, "" ))) | Q10: =IF(AND($F10<(Q$2+7),$F10>Q$2),1, IF(AND($H10<Q$2+7,$H10>Q$2),3, IF(AND($F10<=Q$2, $H10>=Q$2), 2, "" ))) | R10: =IF(AND($F10<(R$2+7),$F10>R$2),1, IF(AND($H10<R$2+7,$H10>R$2),3, IF(AND($F10<=R$2, $H10>=R$2), 2, "" ))) | S10: =IF(AND($F10<(S$2+7),$F10>S$2),1, IF(AND($H10<S$2+7,$H10>S$2),3, IF(AND($F10<=S$2, $H10>=S$2), 2, "" ))) | ... AQ10: =IF(AND($F10<(AQ$2+7),$F10>AQ$2),1, IF(AND($H10<AQ$2+7,$H10>AQ$2),3, IF(AND($F10<=AQ$2, $H10>=AQ$2), 2, "" )))
B11: BOS Procurement | C11: 43941 | D11: 5 | E11: 43949 | F11: 43941 | G11: 5 | H11: 43949 | L11: =IF(AND($F11<(L$2+7),$F11>L$2),1, IF(AND($H11<L$2+7,$H11>L$2),3, IF(AND($F11<=L$2, $H11>=L$2), 2, "" ))) | M11: =IF(AND($F11<(M$2+7),$F11>M$2),1, IF(AND($H11<M$2+7,$H11>M$2),3, IF(AND($F11<=M$2, $H11>=M$2), 2, "" ))) | N11: =IF(AND($F11<(N$2+7),$F11>N$2),1, IF(AND($H11<N$2+7,$H11>N$2),3, IF(AND($F11<=N$2, $H11>=N$2), 2, "" ))) | O11: =IF(AND($F11<(O$2+7),$F11>O$2),1, IF(AND($H11<O$2+7,$H11>O$2),3, IF(AND($F11<=O$2, $H11>=O$2), 2, "" ))) | P11: =IF(AND($F11<(P$2+7),$F11>P$2),1, IF(AND($H11<P$2+7,$H11>P$2),3, IF(AND($F11<=P$2, $H11>=P$2), 2, "" ))) | Q11: =IF(AND($F11<(Q$2+7),$F11>Q$2),1, IF(AND($H11<Q$2+7,$H11>Q$2),3, IF(AND($F11<=Q$2, $H11>=Q$2), 2, "" ))) | R11: =IF(AND($F11<(R$2+7),$F11>R$2),1, IF(AND($H11<R$2+7,$H11>R$2),3, IF(AND($F11<=R$2, $H11>=R$2), 2, "" ))) | S11: =IF(AND($F11<(S$2+7),$F11>S$2),1, IF(AND($H11<S$2+7,$H11>S$2),3, IF(AND($F11<=S$2, $H11>=S$2), 2, "" ))) | ... AQ11: =IF(AND($F11<(AQ$2+7),$F11>AQ$2),1, IF(AND($H11<AQ$2+7,$H11>AQ$2),3, IF(AND($F11<=AQ$2, $H11>=AQ$2), 2, "" )))
A12: 5 | B12: Internal Project Kick off | C12: 43936 | D12: 5 | E12: 43943 | F12: 43936 | G12: 5 | H12: 43943
A13: 6 | B13: Client Project Kick-off | C13: 43963 | D13: 5 | E13: 43970 | F13: 43963 | G13: 5 | H13: 43970 | L13: =IF(AND($F13<(L$2+7),$F13>L$2),1, IF(AND($H13<L$2+7,$H13>L$2),3, IF(AND($F13<=L$2, $H13>=L$2), 2, "" ))) | M13: =IF(AND($F13<(M$2+7),$F13>M$2),1, IF(AND($H13<M$2+7,$H13>M$2),3, IF(AND($F13<=M$2, $H13>=M$2), 2, "" ))) | N13: =IF(AND($F13<(N$2+7),$F13>N$2),1, IF(AND($H13<N$2+7,$H13>N$2),3, IF(AND($F13<=N$2, $H13>=N$2), 2, "" ))) | O13: =IF(AND($F13<(O$2+7),$F13>O$2),1, IF(AND($H13<O$2+7,$H13>O$2),3, IF(AND($F13<=O$2, $H13>=O$2), 2, "" ))) | P13: =IF(AND($F13<(P$2+7),$F13>P$2),1, IF(AND($H13<P$2+7,$H13>P$2),3, IF(AND($F13<=P$2, $H13>=P$2), 2, "" ))) | Q13: =IF(AND($F13<(Q$2+7),$F13>Q$2),1, IF(AND($H13<Q$2+7,$H13>Q$2),3, IF(AND($F13<=Q$2, $H13>=Q$2), 2, "" ))) | R13: =IF(AND($F13<(R$2+7),$F13>R$2),1, IF(AND($H13<R$2+7,$H13>R$2),3, IF(AND($F13<=R$2, $H13>=R$2), 2, "" ))) | S13: =IF(AND($F13<(S$2+7),$F13>S$2),1, IF(AND($H13<S$2+7,$H13>S$2),3, IF(AND($F13<=S$2, $H13>=S$2), 2, "" ))) | ... AQ13: =IF(AND($F13<(AQ$2+7),$F13>AQ$2),1, IF(AND($H13<AQ$2+7,$H13>AQ$2),3, IF(AND($F13<=AQ$2, $H13>=AQ$2), 2, "" )))
A14: 7 | B14: Equipment Delivery | C14: 43983 | D14: 9 | E14: 43994 | F14: 43983 | G14: 9 | H14: 43994 | L14: =IF(AND($F14<(L$2+7),$F14>L$2),1, IF(AND($H14<L$2+7,$H14>L$2),3, IF(AND($F14<=L$2, $H14>=L$2), 2, "" ))) | M14: =IF(AND($F14<(M$2+7),$F14>M$2),1, IF(AND($H14<M$2+7,$H14>M$2),3, IF(AND($F14<=M$2, $H14>=M$2), 2, "" ))) | N14: =IF(AND($F14<(N$2+7),$F14>N$2),1, IF(AND($H14<N$2+7,$H14>N$2),3, IF(AND($F14<=N$2, $H14>=N$2), 2, "" ))) | O14: =IF(AND($F14<(O$2+7),$F14>O$2),1, IF(AND($H14<O$2+7,$H14>O$2),3, IF(AND($F14<=O$2, $H14>=O$2), 2, "" ))) | P14: =IF(AND($F14<(P$2+7),$F14>P$2),1, IF(AND($H14<P$2+7,$H14>P$2),3, IF(AND($F14<=P$2, $H14>=P$2), 2, "" ))) | Q14: =IF(AND($F14<(Q$2+7),$F14>Q$2),1, IF(AND($H14<Q$2+7,$H14>Q$2),3, IF(AND($F14<=Q$2, $H14>=Q$2), 2, "" ))) | R14: =IF(AND($F14<(R$2+7),$F14>R$2),1, IF(AND($H14<R$2+7,$H14>R$2),3, IF(AND($F14<=R$2, $H14>=R$2), 2, "" ))) | S14: =IF(AND($F14<(S$2+7),$F14>S$2),1, IF(AND($H14<S$2+7,$H14>S$2),3, IF(AND($F14<=S$2, $H14>=S$2), 2, "" ))) | ... AQ14: =IF(AND($F14<(AQ$2+7),$F14>AQ$2),1, IF(AND($H14<AQ$2+7,$H14>AQ$2),3, IF(AND($F14<=AQ$2, $H14>=AQ$2), 2, "" )))
B15: Mounting Structure Delivery | C15: 43983 | D15: 2 | E15: 43985 | F15: 43983 | G15: 2 | H15: 43985
B16: Panel Delivery | C16: 43990 | D16: 2 | E16: 43992 | F16: 43990 | G16: 2 | H16: 43992 | L16: =IF(AND($F16<(L$2+7),$F16>L$2),1, IF(AND($H16<L$2+7,$H16>L$2),3, IF(AND($F16<=L$2, $H16>=L$2), 2, "" ))) | M16: =IF(AND($F16<(M$2+7),$F16>M$2),1, IF(AND($H16<M$2+7,$H16>M$2),3, IF(AND($F16<=M$2, $H16>=M$2), 2, "" ))) | N16: =IF(AND($F16<(N$2+7),$F16>N$2),1, IF(AND($H16<N$2+7,$H16>N$2),3, IF(AND($F16<=N$2, $H16>=N$2), 2, "" ))) | O16: =IF(AND($F16<(O$2+7),$F16>O$2),1, IF(AND($H16<O$2+7,$H16>O$2),3, IF(AND($F16<=O$2, $H16>=O$2), 2, "" ))) | P16: =IF(AND($F16<(P$2+7),$F16>P$2),1, IF(AND($H16<P$2+7,$H16>P$2),3, IF(AND($F16<=P$2, $H16>=P$2), 2, "" ))) | Q16: =IF(AND($F16<(Q$2+7),$F16>Q$2),1, IF(AND($H16<Q$2+7,$H16>Q$2),3, IF(AND($F16<=Q$2, $H16>=Q$2), 2, "" ))) | R16: =IF(AND($F16<(R$2+7),$F16>R$2),1, IF(AND($H16<R$2+7,$H16>R$2),3, IF(AND($F16<=R$2, $H16>=R$2), 2, "" ))) | S16: =IF(AND($F16<(S$2+7),$F16>S$2),1, IF(AND($H16<S$2+7,$H16>S$2),3, IF(AND($F16<=S$2, $H16>=S$2), 2, "" ))) | ... AQ16: =IF(AND($F16<(AQ$2+7),$F16>AQ$2),1, IF(AND($H16<AQ$2+7,$H16>AQ$2),3, IF(AND($F16<=AQ$2, $H16>=AQ$2), 2, "" )))
B17: Generator Delivery | C17: 43983 | D17: 2 | E17: 43985 | F17: 43983 | G17: 2 | H17: 43985
A18: B | B18: PAYMENT MILESTONE 2: DELIVERY OF PV PANELS | C18: 43992 | D18: 2 | E18: 43994 | F18: 43992 | G18: 2 | H18: 43994
B19: Inverter Delivery | C19: 43983 | D19: 2 | E19: 43985 | F19: 43983 | G19: 2 | H19: 43985 | L19: =IF(AND($F19<(L$2+7),$F19>L$2),1, IF(AND($H19<L$2+7,$H19>L$2),3, IF(AND($F19<=L$2, $H19>=L$2), 2, "" ))) | M19: =IF(AND($F19<(M$2+7),$F19>M$2),1, IF(AND($H19<M$2+7,$H19>M$2),3, IF(AND($F19<=M$2, $H19>=M$2), 2, "" ))) | N19: =IF(AND($F19<(N$2+7),$F19>N$2),1, IF(AND($H19<N$2+7,$H19>N$2),3, IF(AND($F19<=N$2, $H19>=N$2), 2, "" ))) | O19: =IF(AND($F19<(O$2+7),$F19>O$2),1, IF(AND($H19<O$2+7,$H19>O$2),3, IF(AND($F19<=O$2, $H19>=O$2), 2, "" ))) | P19: =IF(AND($F19<(P$2+7),$F19>P$2),1, IF(AND($H19<P$2+7,$H19>P$2),3, IF(AND($F19<=P$2, $H19>=P$2), 2, "" ))) | Q19: =IF(AND($F19<(Q$2+7),$F19>Q$2),1, IF(AND($H19<Q$2+7,$H19>Q$2),3, IF(AND($F19<=Q$2, $H19>=Q$2), 2, "" ))) | R19: =IF(AND($F19<(R$2+7),$F19>R$2),1, IF(AND($H19<R$2+7,$H19>R$2),3, IF(AND($F19<=R$2, $H19>=R$2), 2, "" ))) | S19: =IF(AND($F19<(S$2+7),$F19>S$2),1, IF(AND($H19<S$2+7,$H19>S$2),3, IF(AND($F19<=S$2, $H19>=S$2), 2, "" ))) | ... AQ19: =IF(AND($F19<(AQ$2+7),$F19>AQ$2),1, IF(AND($H19<AQ$2+7,$H19>AQ$2),3, IF(AND($F19<=AQ$2, $H19>=AQ$2), 2, "" )))
B20: BOS Delivery | C20: 43983 | D20: 1 | E20: 43984 | F20: 43983 | G20: 1 | H20: 43984 | L20: =IF(AND($F20<(L$2+7),$F20>L$2),1, IF(AND($H20<L$2+7,$H20>L$2),3, IF(AND($F20<=L$2, $H20>=L$2), 2, "" ))) | M20: =IF(AND($F20<(M$2+7),$F20>M$2),1, IF(AND($H20<M$2+7,$H20>M$2),3, IF(AND($F20<=M$2, $H20>=M$2), 2, "" ))) | N20: =IF(AND($F20<(N$2+7),$F20>N$2),1, IF(AND($H20<N$2+7,$H20>N$2),3, IF(AND($F20<=N$2, $H20>=N$2), 2, "" ))) | O20: =IF(AND($F20<(O$2+7),$F20>O$2),1, IF(AND($H20<O$2+7,$H20>O$2),3, IF(AND($F20<=O$2, $H20>=O$2), 2, "" ))) | P20: =IF(AND($F20<(P$2+7),$F20>P$2),1, IF(AND($H20<P$2+7,$H20>P$2),3, IF(AND($F20<=P$2, $H20>=P$2), 2, "" ))) | Q20: =IF(AND($F20<(Q$2+7),$F20>Q$2),1, IF(AND($H20<Q$2+7,$H20>Q$2),3, IF(AND($F20<=Q$2, $H20>=Q$2), 2, "" ))) | R20: =IF(AND($F20<(R$2+7),$F20>R$2),1, IF(AND($H20<R$2+7,$H20>R$2),3, IF(AND($F20<=R$2, $H20>=R$2), 2, "" ))) | S20: =IF(AND($F20<(S$2+7),$F20>S$2),1, IF(AND($H20<S$2+7,$H20>S$2),3, IF(AND($F20<=S$2, $H20>=S$2), 2, "" ))) | ... AQ20: =IF(AND($F20<(AQ$2+7),$F20>AQ$2),1, IF(AND($H20<AQ$2+7,$H20>AQ$2),3, IF(AND($F20<=AQ$2, $H20>=AQ$2), 2, "" )))
A21: C | B21: PAYMENT MILESTONE 3: DELIVERY OF INVERTERS AND BOS | C21: 43985 | D21: 2 | E21: 43987 | F21: 43985 | G21: 2 | H21: 43987
A22: 8 | B22: Installation | C22: 43990 | D22: 22 | E22: 44012 | F22: 43990 | G22: 22 | H22: 44012 | L22: =IF(AND($F22<(L$2+7),$F22>L$2),1, IF(AND($H22<L$2+7,$H22>L$2),3, IF(AND($F22<=L$2, $H22>=L$2), 2, "" ))) | M22: =IF(AND($F22<(M$2+7),$F22>M$2),1, IF(AND($H22<M$2+7,$H22>M$2),3, IF(AND($F22<=M$2, $H22>=M$2), 2, "" ))) | N22: =IF(AND($F22<(N$2+7),$F22>N$2),1, IF(AND($H22<N$2+7,$H22>N$2),3, IF(AND($F22<=N$2, $H22>=N$2), 2, "" ))) | O22: =IF(AND($F22<(O$2+7),$F22>O$2),1, IF(AND($H22<O$2+7,$H22>O$2),3, IF(AND($F22<=O$2, $H22>=O$2), 2, "" ))) | P22: =IF(AND($F22<(P$2+7),$F22>P$2),1, IF(AND($H22<P$2+7,$H22>P$2),3, IF(AND($F22<=P$2, $H22>=P$2), 2, "" ))) | Q22: =IF(AND($F22<(Q$2+7),$F22>Q$2),1, IF(AND($H22<Q$2+7,$H22>Q$2),3, IF(AND($F22<=Q$2, $H22>=Q$2), 2, "" ))) | R22: =IF(AND($F22<(R$2+7),$F22>R$2),1, IF(AND($H22<R$2+7,$H22>R$2),3, IF(AND($F22<=R$2, $H22>=R$2), 2, "" ))) | S22: =IF(AND($F22<(S$2+7),$F22>S$2),1, IF(AND($H22<S$2+7,$H22>S$2),3, IF(AND($F22<=S$2, $H22>=S$2), 2, "" ))) | ... AQ22: =IF(AND($F22<(AQ$2+7),$F22>AQ$2),1, IF(AND($H22<AQ$2+7,$H22>AQ$2),3, IF(AND($F22<=AQ$2, $H22>=AQ$2), 2, "" ))) -> 2
B23: Site Establishment | C23: 43990 | D23: 1 | E23: 43991 | F23: 43990 | G23: 1 | H23: 43991 | J23: Installation placed on hold due to Covid-19 case | L23: =IF(AND($F23<(L$2+7),$F23>L$2),1, IF(AND($H23<L$2+7,$H23>L$2),3, IF(AND($F23<=L$2, $H23>=L$2), 2, "" ))) | M23: =IF(AND($F23<(M$2+7),$F23>M$2),1, IF(AND($H23<M$2+7,$H23>M$2),3, IF(AND($F23<=M$2, $H23>=M$2), 2, "" ))) | N23: =IF(AND($F23<(N$2+7),$F23>N$2),1, IF(AND($H23<N$2+7,$H23>N$2),3, IF(AND($F23<=N$2, $H23>=N$2), 2, "" ))) | O23: =IF(AND($F23<(O$2+7),$F23>O$2),1, IF(AND($H23<O$2+7,$H23>O$2),3, IF(AND($F23<=O$2, $H23>=O$2), 2, "" ))) | P23: =IF(AND($F23<(P$2+7),$F23>P$2),1, IF(AND($H23<P$2+7,$H23>P$2),3, IF(AND($F23<=P$2, $H23>=P$2), 2, "" ))) | Q23: =IF(AND($F23<(Q$2+7),$F23>Q$2),1, IF(AND($H23<Q$2+7,$H23>Q$2),3, IF(AND($F23<=Q$2, $H23>=Q$2), 2, "" ))) | R23: =IF(AND($F23<(R$2+7),$F23>R$2),1, IF(AND($H23<R$2+7,$H23>R$2),3, IF(AND($F23<=R$2, $H23>=R$2), 2, "" ))) | S23: =IF(AND($F23<(S$2+7),$F23>S$2),1, IF(AND($H23<S$2+7,$H23>S$2),3, IF(AND($F23<=S$2, $H23>=S$2), 2, "" ))) | ... AQ23: =IF(AND($F23<(AQ$2+7),$F23>AQ$2),1, IF(AND($H23<AQ$2+7,$H23>AQ$2),3, IF(AND($F23<=AQ$2, $H23>=AQ$2), 2, "" )))
A24: 9 | B24: DC Works | C24: 43991 | D24: 16 | E24: 44012 | F24: 43991 | G24: 16 | H24: 44012 | L24: =IF(AND($F24<(L$2+7),$F24>L$2),1, IF(AND($H24<L$2+7,$H24>L$2),3, IF(AND($F24<=L$2, $H24>=L$2), 2, "" ))) | M24: =IF(AND($F24<(M$2+7),$F24>M$2),1, IF(AND($H24<M$2+7,$H24>M$2),3, IF(AND($F24<=M$2, $H24>=M$2), 2, "" ))) | N24: =IF(AND($F24<(N$2+7),$F24>N$2),1, IF(AND($H24<N$2+7,$H24>N$2),3, IF(AND($F24<=N$2, $H24>=N$2), 2, "" ))) | O24: =IF(AND($F24<(O$2+7),$F24>O$2),1, IF(AND($H24<O$2+7,$H24>O$2),3, IF(AND($F24<=O$2, $H24>=O$2), 2, "" ))) | P24: =IF(AND($F24<(P$2+7),$F24>P$2),1, IF(AND($H24<P$2+7,$H24>P$2),3, IF(AND($F24<=P$2, $H24>=P$2), 2, "" ))) | Q24: =IF(AND($F24<(Q$2+7),$F24>Q$2),1, IF(AND($H24<Q$2+7,$H24>Q$2),3, IF(AND($F24<=Q$2, $H24>=Q$2), 2, "" ))) | R24: =IF(AND($F24<(R$2+7),$F24>R$2),1, IF(AND($H24<R$2+7,$H24>R$2),3, IF(AND($F24<=R$2, $H24>=R$2), 2, "" ))) | S24: =IF(AND($F24<(S$2+7),$F24>S$2),1, IF(AND($H24<S$2+7,$H24>S$2),3, IF(AND($F24<=S$2, $H24>=S$2), 2, "" ))) | ... AQ24: =IF(AND($F24<(AQ$2+7),$F24>AQ$2),1, IF(AND($H24<AQ$2+7,$H24>AQ$2),3, IF(AND($F24<=AQ$2, $H24>=AQ$2), 2, "" ))) -> 2
B25: Mounting structure Installation | C25: 43991 | D25: 4 | E25: 43997 | F25: 43991 | G25: 4 | H25: 43997 | L25: =IF(AND($F25<(L$2+7),$F25>L$2),1, IF(AND($H25<L$2+7,$H25>L$2),3, IF(AND($F25<=L$2, $H25>=L$2), 2, "" ))) | M25: =IF(AND($F25<(M$2+7),$F25>M$2),1, IF(AND($H25<M$2+7,$H25>M$2),3, IF(AND($F25<=M$2, $H25>=M$2), 2, "" ))) | N25: =IF(AND($F25<(N$2+7),$F25>N$2),1, IF(AND($H25<N$2+7,$H25>N$2),3, IF(AND($F25<=N$2, $H25>=N$2), 2, "" ))) | O25: =IF(AND($F25<(O$2+7),$F25>O$2),1, IF(AND($H25<O$2+7,$H25>O$2),3, IF(AND($F25<=O$2, $H25>=O$2), 2, "" ))) | P25: =IF(AND($F25<(P$2+7),$F25>P$2),1, IF(AND($H25<P$2+7,$H25>P$2),3, IF(AND($F25<=P$2, $H25>=P$2), 2, "" ))) | Q25: =IF(AND($F25<(Q$2+7),$F25>Q$2),1, IF(AND($H25<Q$2+7,$H25>Q$2),3, IF(AND($F25<=Q$2, $H25>=Q$2), 2, "" ))) | R25: =IF(AND($F25<(R$2+7),$F25>R$2),1, IF(AND($H25<R$2+7,$H25>R$2),3, IF(AND($F25<=R$2, $H25>=R$2), 2, "" ))) | S25: =IF(AND($F25<(S$2+7),$F25>S$2),1, IF(AND($H25<S$2+7,$H25>S$2),3, IF(AND($F25<=S$2, $H25>=S$2), 2, "" ))) | ... AQ25: =IF(AND($F25<(AQ$2+7),$F25>AQ$2),1, IF(AND($H25<AQ$2+7,$H25>AQ$2),3, IF(AND($F25<=AQ$2, $H25>=AQ$2), 2, "" )))
B26: Cable tray Installation | C26: 43997 | D26: 3 | E26: 44004 | F26: 43997 | G26: 3 | H26: 44004 | L26: =IF(AND($F26<(L$2+7),$F26>L$2),1, IF(AND($H26<L$2+7,$H26>L$2),3, IF(AND($F26<=L$2, $H26>=L$2), 2, "" ))) | M26: =IF(AND($F26<(M$2+7),$F26>M$2),1, IF(AND($H26<M$2+7,$H26>M$2),3, IF(AND($F26<=M$2, $H26>=M$2), 2, "" ))) | N26: =IF(AND($F26<(N$2+7),$F26>N$2),1, IF(AND($H26<N$2+7,$H26>N$2),3, IF(AND($F26<=N$2, $H26>=N$2), 2, "" ))) | O26: =IF(AND($F26<(O$2+7),$F26>O$2),1, IF(AND($H26<O$2+7,$H26>O$2),3, IF(AND($F26<=O$2, $H26>=O$2), 2, "" ))) | P26: =IF(AND($F26<(P$2+7),$F26>P$2),1, IF(AND($H26<P$2+7,$H26>P$2),3, IF(AND($F26<=P$2, $H26>=P$2), 2, "" ))) | Q26: =IF(AND($F26<(Q$2+7),$F26>Q$2),1, IF(AND($H26<Q$2+7,$H26>Q$2),3, IF(AND($F26<=Q$2, $H26>=Q$2), 2, "" ))) | R26: =IF(AND($F26<(R$2+7),$F26>R$2),1, IF(AND($H26<R$2+7,$H26>R$2),3, IF(AND($F26<=R$2, $H26>=R$2), 2, "" ))) | S26: =IF(AND($F26<(S$2+7),$F26>S$2),1, IF(AND($H26<S$2+7,$H26>S$2),3, IF(AND($F26<=S$2, $H26>=S$2), 2, "" ))) | ... AQ26: =IF(AND($F26<(AQ$2+7),$F26>AQ$2),1, IF(AND($H26<AQ$2+7,$H26>AQ$2),3, IF(AND($F26<=AQ$2, $H26>=AQ$2), 2, "" )))
B27: DC Cable Installation | C27: 44004 | D27: 2 | E27: 44006 | F27: 44004 | G27: 2 | H27: 44006 | L27: =IF(AND($F27<(L$2+7),$F27>L$2),1, IF(AND($H27<L$2+7,$H27>L$2),3, IF(AND($F27<=L$2, $H27>=L$2), 2, "" ))) | M27: =IF(AND($F27<(M$2+7),$F27>M$2),1, IF(AND($H27<M$2+7,$H27>M$2),3, IF(AND($F27<=M$2, $H27>=M$2), 2, "" ))) | N27: =IF(AND($F27<(N$2+7),$F27>N$2),1, IF(AND($H27<N$2+7,$H27>N$2),3, IF(AND($F27<=N$2, $H27>=N$2), 2, "" ))) | O27: =IF(AND($F27<(O$2+7),$F27>O$2),1, IF(AND($H27<O$2+7,$H27>O$2),3, IF(AND($F27<=O$2, $H27>=O$2), 2, "" ))) | P27: =IF(AND($F27<(P$2+7),$F27>P$2),1, IF(AND($H27<P$2+7,$H27>P$2),3, IF(AND($F27<=P$2, $H27>=P$2), 2, "" ))) | Q27: =IF(AND($F27<(Q$2+7),$F27>Q$2),1, IF(AND($H27<Q$2+7,$H27>Q$2),3, IF(AND($F27<=Q$2, $H27>=Q$2), 2, "" ))) | R27: =IF(AND($F27<(R$2+7),$F27>R$2),1, IF(AND($H27<R$2+7,$H27>R$2),3, IF(AND($F27<=R$2, $H27>=R$2), 2, "" ))) | S27: =IF(AND($F27<(S$2+7),$F27>S$2),1, IF(AND($H27<S$2+7,$H27>S$2),3, IF(AND($F27<=S$2, $H27>=S$2), 2, "" ))) | ... AQ27: =IF(AND($F27<(AQ$2+7),$F27>AQ$2),1, IF(AND($H27<AQ$2+7,$H27>AQ$2),3, IF(AND($F27<=AQ$2, $H27>=AQ$2), 2, "" )))
B28: Module Installation | C28: 44006 | D28: 4 | E28: 44012 | F28: 44006 | G28: 4 | H28: 44012 | L28: =IF(AND($F28<(L$2+7),$F28>L$2),1, IF(AND($H28<L$2+7,$H28>L$2),3, IF(AND($F28<=L$2, $H28>=L$2), 2, "" ))) | M28: =IF(AND($F28<(M$2+7),$F28>M$2),1, IF(AND($H28<M$2+7,$H28>M$2),3, IF(AND($F28<=M$2, $H28>=M$2), 2, "" ))) | N28: =IF(AND($F28<(N$2+7),$F28>N$2),1, IF(AND($H28<N$2+7,$H28>N$2),3, IF(AND($F28<=N$2, $H28>=N$2), 2, "" ))) | O28: =IF(AND($F28<(O$2+7),$F28>O$2),1, IF(AND($H28<O$2+7,$H28>O$2),3, IF(AND($F28<=O$2, $H28>=O$2), 2, "" ))) | P28: =IF(AND($F28<(P$2+7),$F28>P$2),1, IF(AND($H28<P$2+7,$H28>P$2),3, IF(AND($F28<=P$2, $H28>=P$2), 2, "" ))) | Q28: =IF(AND($F28<(Q$2+7),$F28>Q$2),1, IF(AND($H28<Q$2+7,$H28>Q$2),3, IF(AND($F28<=Q$2, $H28>=Q$2), 2, "" ))) | R28: =IF(AND($F28<(R$2+7),$F28>R$2),1, IF(AND($H28<R$2+7,$H28>R$2),3, IF(AND($F28<=R$2, $H28>=R$2), 2, "" ))) | S28: =IF(AND($F28<(S$2+7),$F28>S$2),1, IF(AND($H28<S$2+7,$H28>S$2),3, IF(AND($F28<=S$2, $H28>=S$2), 2, "" ))) | ... AQ28: =IF(AND($F28<(AQ$2+7),$F28>AQ$2),1, IF(AND($H28<AQ$2+7,$H28>AQ$2),3, IF(AND($F28<=AQ$2, $H28>=AQ$2), 2, "" ))) -> 2
B29: Earth Cable Installation | C29: 44004 | D29: 1 | E29: 44005 | F29: 44004 | G29: 1 | H29: 44005 | L29: =IF(AND($F29<(L$2+7),$F29>L$2),1, IF(AND($H29<L$2+7,$H29>L$2),3, IF(AND($F29<=L$2, $H29>=L$2), 2, "" ))) | M29: =IF(AND($F29<(M$2+7),$F29>M$2),1, IF(AND($H29<M$2+7,$H29>M$2),3, IF(AND($F29<=M$2, $H29>=M$2), 2, "" ))) | N29: =IF(AND($F29<(N$2+7),$F29>N$2),1, IF(AND($H29<N$2+7,$H29>N$2),3, IF(AND($F29<=N$2, $H29>=N$2), 2, "" ))) | O29: =IF(AND($F29<(O$2+7),$F29>O$2),1, IF(AND($H29<O$2+7,$H29>O$2),3, IF(AND($F29<=O$2, $H29>=O$2), 2, "" ))) | P29: =IF(AND($F29<(P$2+7),$F29>P$2),1, IF(AND($H29<P$2+7,$H29>P$2),3, IF(AND($F29<=P$2, $H29>=P$2), 2, "" ))) | Q29: =IF(AND($F29<(Q$2+7),$F29>Q$2),1, IF(AND($H29<Q$2+7,$H29>Q$2),3, IF(AND($F29<=Q$2, $H29>=Q$2), 2, "" ))) | R29: =IF(AND($F29<(R$2+7),$F29>R$2),1, IF(AND($H29<R$2+7,$H29>R$2),3, IF(AND($F29<=R$2, $H29>=R$2), 2, "" ))) | S29: =IF(AND($F29<(S$2+7),$F29>S$2),1, IF(AND($H29<S$2+7,$H29>S$2),3, IF(AND($F29<=S$2, $H29>=S$2), 2, "" ))) | ... AQ29: =IF(AND($F29<(AQ$2+7),$F29>AQ$2),1, IF(AND($H29<AQ$2+7,$H29>AQ$2),3, IF(AND($F29<=AQ$2, $H29>=AQ$2), 2, "" )))
A30: 10 | B30: AC Works | C30: 43991 | D30: 8 | E30: 44000 | F30: 43991 | G30: 8 | H30: 44000
B31: Inverters Installation | C31: 43991 | D31: 2 | E31: 43993 | F31: 43991 | G31: 2 | H31: 43993 | L31: =IF(AND($F31<(L$2+7),$F31>L$2),1, IF(AND($H31<L$2+7,$H31>L$2),3, IF(AND($F31<=L$2, $H31>=L$2), 2, "" ))) | M31: =IF(AND($F31<(M$2+7),$F31>M$2),1, IF(AND($H31<M$2+7,$H31>M$2),3, IF(AND($F31<=M$2, $H31>=M$2), 2, "" ))) | N31: =IF(AND($F31<(N$2+7),$F31>N$2),1, IF(AND($H31<N$2+7,$H31>N$2),3, IF(AND($F31<=N$2, $H31>=N$2), 2, "" ))) | O31: =IF(AND($F31<(O$2+7),$F31>O$2),1, IF(AND($H31<O$2+7,$H31>O$2),3, IF(AND($F31<=O$2, $H31>=O$2), 2, "" ))) | P31: =IF(AND($F31<(P$2+7),$F31>P$2),1, IF(AND($H31<P$2+7,$H31>P$2),3, IF(AND($F31<=P$2, $H31>=P$2), 2, "" ))) | Q31: =IF(AND($F31<(Q$2+7),$F31>Q$2),1, IF(AND($H31<Q$2+7,$H31>Q$2),3, IF(AND($F31<=Q$2, $H31>=Q$2), 2, "" ))) | R31: =IF(AND($F31<(R$2+7),$F31>R$2),1, IF(AND($H31<R$2+7,$H31>R$2),3, IF(AND($F31<=R$2, $H31>=R$2), 2, "" ))) | S31: =IF(AND($F31<(S$2+7),$F31>S$2),1, IF(AND($H31<S$2+7,$H31>S$2),3, IF(AND($F31<=S$2, $H31>=S$2), 2, "" ))) | ... AQ31: =IF(AND($F31<(AQ$2+7),$F31>AQ$2),1, IF(AND($H31<AQ$2+7,$H31>AQ$2),3, IF(AND($F31<=AQ$2, $H31>=AQ$2), 2, "" )))
B32: AC BOS Installation | C32: 43993 | D32: 3 | E32: 44000 | F32: 43993 | G32: 3 | H32: 44000 | L32: =IF(AND($F32<(L$2+7),$F32>L$2),1, IF(AND($H32<L$2+7,$H32>L$2),3, IF(AND($F32<=L$2, $H32>=L$2), 2, "" ))) | M32: =IF(AND($F32<(M$2+7),$F32>M$2),1, IF(AND($H32<M$2+7,$H32>M$2),3, IF(AND($F32<=M$2, $H32>=M$2), 2, "" ))) | N32: =IF(AND($F32<(N$2+7),$F32>N$2),1, IF(AND($H32<N$2+7,$H32>N$2),3, IF(AND($F32<=N$2, $H32>=N$2), 2, "" ))) | O32: =IF(AND($F32<(O$2+7),$F32>O$2),1, IF(AND($H32<O$2+7,$H32>O$2),3, IF(AND($F32<=O$2, $H32>=O$2), 2, "" ))) | P32: =IF(AND($F32<(P$2+7),$F32>P$2),1, IF(AND($H32<P$2+7,$H32>P$2),3, IF(AND($F32<=P$2, $H32>=P$2), 2, "" ))) | Q32: =IF(AND($F32<(Q$2+7),$F32>Q$2),1, IF(AND($H32<Q$2+7,$H32>Q$2),3, IF(AND($F32<=Q$2, $H32>=Q$2), 2, "" ))) | R32: =IF(AND($F32<(R$2+7),$F32>R$2),1, IF(AND($H32<R$2+7,$H32>R$2),3, IF(AND($F32<=R$2, $H32>=R$2), 2, "" ))) | S32: =IF(AND($F32<(S$2+7),$F32>S$2),1, IF(AND($H32<S$2+7,$H32>S$2),3, IF(AND($F32<=S$2, $H32>=S$2), 2, "" ))) | ... AQ32: =IF(AND($F32<(AQ$2+7),$F32>AQ$2),1, IF(AND($H32<AQ$2+7,$H32>AQ$2),3, IF(AND($F32<=AQ$2, $H32>=AQ$2), 2, "" )))
B33: AC Cable/Tie-In | C33: 43992 | D33: 3 | E33: 43997 | F33: 43992 | G33: 3 | H33: 43997 | L33: =IF(AND($F33<(L$2+7),$F33>L$2),1, IF(AND($H33<L$2+7,$H33>L$2),3, IF(AND($F33<=L$2, $H33>=L$2), 2, "" ))) | M33: =IF(AND($F33<(M$2+7),$F33>M$2),1, IF(AND($H33<M$2+7,$H33>M$2),3, IF(AND($F33<=M$2, $H33>=M$2), 2, "" ))) | N33: =IF(AND($F33<(N$2+7),$F33>N$2),1, IF(AND($H33<N$2+7,$H33>N$2),3, IF(AND($F33<=N$2, $H33>=N$2), 2, "" ))) | O33: =IF(AND($F33<(O$2+7),$F33>O$2),1, IF(AND($H33<O$2+7,$H33>O$2),3, IF(AND($F33<=O$2, $H33>=O$2), 2, "" ))) | P33: =IF(AND($F33<(P$2+7),$F33>P$2),1, IF(AND($H33<P$2+7,$H33>P$2),3, IF(AND($F33<=P$2, $H33>=P$2), 2, "" ))) | Q33: =IF(AND($F33<(Q$2+7),$F33>Q$2),1, IF(AND($H33<Q$2+7,$H33>Q$2),3, IF(AND($F33<=Q$2, $H33>=Q$2), 2, "" ))) | R33: =IF(AND($F33<(R$2+7),$F33>R$2),1, IF(AND($H33<R$2+7,$H33>R$2),3, IF(AND($F33<=R$2, $H33>=R$2), 2, "" ))) | S33: =IF(AND($F33<(S$2+7),$F33>S$2),1, IF(AND($H33<S$2+7,$H33>S$2),3, IF(AND($F33<=S$2, $H33>=S$2), 2, "" ))) | ... AQ33: =IF(AND($F33<(AQ$2+7),$F33>AQ$2),1, IF(AND($H33<AQ$2+7,$H33>AQ$2),3, IF(AND($F33<=AQ$2, $H33>=AQ$2), 2, "" )))
B34: Monitoring Platform Installation | C34: 43997 | D34: 1 | E34: 44000 | F34: 43997 | G34: 1 | H34: 44000
A35: 11 | B35: Completion | C35: 44000 | D35: 14 | E35: 44014 | F35: 44000 | G35: 14 | H35: 44014 | L35: =IF(AND($F35<(L$2+7),$F35>L$2),1, IF(AND($H35<L$2+7,$H35>L$2),3, IF(AND($F35<=L$2, $H35>=L$2), 2, "" ))) | M35: =IF(AND($F35<(M$2+7),$F35>M$2),1, IF(AND($H35<M$2+7,$H35>M$2),3, IF(AND($F35<=M$2, $H35>=M$2), 2, "" ))) | N35: =IF(AND($F35<(N$2+7),$F35>N$2),1, IF(AND($H35<N$2+7,$H35>N$2),3, IF(AND($F35<=N$2, $H35>=N$2), 2, "" ))) | O35: =IF(AND($F35<(O$2+7),$F35>O$2),1, IF(AND($H35<O$2+7,$H35>O$2),3, IF(AND($F35<=O$2, $H35>=O$2), 2, "" ))) | P35: =IF(AND($F35<(P$2+7),$F35>P$2),1, IF(AND($H35<P$2+7,$H35>P$2),3, IF(AND($F35<=P$2, $H35>=P$2), 2, "" ))) | Q35: =IF(AND($F35<(Q$2+7),$F35>Q$2),1, IF(AND($H35<Q$2+7,$H35>Q$2),3, IF(AND($F35<=Q$2, $H35>=Q$2), 2, "" ))) | R35: =IF(AND($F35<(R$2+7),$F35>R$2),1, IF(AND($H35<R$2+7,$H35>R$2),3, IF(AND($F35<=R$2, $H35>=R$2), 2, "" ))) | S35: =IF(AND($F35<(S$2+7),$F35>S$2),1, IF(AND($H35<S$2+7,$H35>S$2),3, IF(AND($F35<=S$2, $H35>=S$2), 2, "" ))) | ... AQ35: =IF(AND($F35<(AQ$2+7),$F35>AQ$2),1, IF(AND($H35<AQ$2+7,$H35>AQ$2),3, IF(AND($F35<=AQ$2, $H35>=AQ$2), 2, "" ))) -> 3
B36: DC Works | C36: 44012 | D36: 2 | E36: 44014 | F36: 44012 | G36: 2 | H36: 44014 | L36: =IF(AND($F36<(L$2+7),$F36>L$2),1, IF(AND($H36<L$2+7,$H36>L$2),3, IF(AND($F36<=L$2, $H36>=L$2), 2, "" ))) | M36: =IF(AND($F36<(M$2+7),$F36>M$2),1, IF(AND($H36<M$2+7,$H36>M$2),3, IF(AND($F36<=M$2, $H36>=M$2), 2, "" ))) | N36: =IF(AND($F36<(N$2+7),$F36>N$2),1, IF(AND($H36<N$2+7,$H36>N$2),3, IF(AND($F36<=N$2, $H36>=N$2), 2, "" ))) | O36: =IF(AND($F36<(O$2+7),$F36>O$2),1, IF(AND($H36<O$2+7,$H36>O$2),3, IF(AND($F36<=O$2, $H36>=O$2), 2, "" ))) | P36: =IF(AND($F36<(P$2+7),$F36>P$2),1, IF(AND($H36<P$2+7,$H36>P$2),3, IF(AND($F36<=P$2, $H36>=P$2), 2, "" ))) | Q36: =IF(AND($F36<(Q$2+7),$F36>Q$2),1, IF(AND($H36<Q$2+7,$H36>Q$2),3, IF(AND($F36<=Q$2, $H36>=Q$2), 2, "" ))) | R36: =IF(AND($F36<(R$2+7),$F36>R$2),1, IF(AND($H36<R$2+7,$H36>R$2),3, IF(AND($F36<=R$2, $H36>=R$2), 2, "" ))) | S36: =IF(AND($F36<(S$2+7),$F36>S$2),1, IF(AND($H36<S$2+7,$H36>S$2),3, IF(AND($F36<=S$2, $H36>=S$2), 2, "" ))) | ... AQ36: =IF(AND($F36<(AQ$2+7),$F36>AQ$2),1, IF(AND($H36<AQ$2+7,$H36>AQ$2),3, IF(AND($F36<=AQ$2, $H36>=AQ$2), 2, "" ))) -> 3
B37: AC Works | C37: 44000 | D37: 2 | E37: 44004 | F37: 44000 | G37: 2 | H37: 44004 | L37: =IF(AND($F37<(L$2+7),$F37>L$2),1, IF(AND($H37<L$2+7,$H37>L$2),3, IF(AND($F37<=L$2, $H37>=L$2), 2, "" ))) | M37: =IF(AND($F37<(M$2+7),$F37>M$2),1, IF(AND($H37<M$2+7,$H37>M$2),3, IF(AND($F37<=M$2, $H37>=M$2), 2, "" ))) | N37: =IF(AND($F37<(N$2+7),$F37>N$2),1, IF(AND($H37<N$2+7,$H37>N$2),3, IF(AND($F37<=N$2, $H37>=N$2), 2, "" ))) | O37: =IF(AND($F37<(O$2+7),$F37>O$2),1, IF(AND($H37<O$2+7,$H37>O$2),3, IF(AND($F37<=O$2, $H37>=O$2), 2, "" ))) | P37: =IF(AND($F37<(P$2+7),$F37>P$2),1, IF(AND($H37<P$2+7,$H37>P$2),3, IF(AND($F37<=P$2, $H37>=P$2), 2, "" ))) | Q37: =IF(AND($F37<(Q$2+7),$F37>Q$2),1, IF(AND($H37<Q$2+7,$H37>Q$2),3, IF(AND($F37<=Q$2, $H37>=Q$2), 2, "" ))) | R37: =IF(AND($F37<(R$2+7),$F37>R$2),1, IF(AND($H37<R$2+7,$H37>R$2),3, IF(AND($F37<=R$2, $H37>=R$2), 2, "" ))) | S37: =IF(AND($F37<(S$2+7),$F37>S$2),1, IF(AND($H37<S$2+7,$H37>S$2),3, IF(AND($F37<=S$2, $H37>=S$2), 2, "" ))) | ... AQ37: =IF(AND($F37<(AQ$2+7),$F37>AQ$2),1, IF(AND($H37<AQ$2+7,$H37>AQ$2),3, IF(AND($F37<=AQ$2, $H37>=AQ$2), 2, "" )))
A38: D | B38: PAYMENT MILESTONE 4: PRACTICAL COMPLETION | C38: 44012 | D38: 1 | E38: 44013 | F38: 44012 | G38: 1 | H38: 44013 | L38: =IF(AND($F38<(L$2+7),$F38>L$2),1, IF(AND($H38<L$2+7,$H38>L$2),3, IF(AND($F38<=L$2, $H38>=L$2), 2, "" ))) | M38: =IF(AND($F38<(M$2+7),$F38>M$2),1, IF(AND($H38<M$2+7,$H38>M$2),3, IF(AND($F38<=M$2, $H38>=M$2), 2, "" ))) | N38: =IF(AND($F38<(N$2+7),$F38>N$2),1, IF(AND($H38<N$2+7,$H38>N$2),3, IF(AND($F38<=N$2, $H38>=N$2), 2, "" ))) | O38: =IF(AND($F38<(O$2+7),$F38>O$2),1, IF(AND($H38<O$2+7,$H38>O$2),3, IF(AND($F38<=O$2, $H38>=O$2), 2, "" ))) | P38: =IF(AND($F38<(P$2+7),$F38>P$2),1, IF(AND($H38<P$2+7,$H38>P$2),3, IF(AND($F38<=P$2, $H38>=P$2), 2, "" ))) | Q38: =IF(AND($F38<(Q$2+7),$F38>Q$2),1, IF(AND($H38<Q$2+7,$H38>Q$2),3, IF(AND($F38<=Q$2, $H38>=Q$2), 2, "" ))) | R38: =IF(AND($F38<(R$2+7),$F38>R$2),1, IF(AND($H38<R$2+7,$H38>R$2),3, IF(AND($F38<=R$2, $H38>=R$2), 2, "" ))) | S38: =IF(AND($F38<(S$2+7),$F38>S$2),1, IF(AND($H38<S$2+7,$H38>S$2),3, IF(AND($F38<=S$2, $H38>=S$2), 2, "" ))) | ... AQ38: =IF(AND($F38<(AQ$2+7),$F38>AQ$2),1, IF(AND($H38<AQ$2+7,$H38>AQ$2),3, IF(AND($F38<=AQ$2, $H38>=AQ$2), 2, "" ))) -> 3
A39: 12 | B39: Commissioning | C39: 43997 | D39: 22 | E39: 44019 | F39: 43997 | G39: 22 | H39: 44019 | L39: =IF(AND($F39<(L$2+7),$F39>L$2),1, IF(AND($H39<L$2+7,$H39>L$2),3, IF(AND($F39<=L$2, $H39>=L$2), 2, "" ))) | M39: =IF(AND($F39<(M$2+7),$F39>M$2),1, IF(AND($H39<M$2+7,$H39>M$2),3, IF(AND($F39<=M$2, $H39>=M$2), 2, "" ))) | N39: =IF(AND($F39<(N$2+7),$F39>N$2),1, IF(AND($H39<N$2+7,$H39>N$2),3, IF(AND($F39<=N$2, $H39>=N$2), 2, "" ))) | O39: =IF(AND($F39<(O$2+7),$F39>O$2),1, IF(AND($H39<O$2+7,$H39>O$2),3, IF(AND($F39<=O$2, $H39>=O$2), 2, "" ))) | P39: =IF(AND($F39<(P$2+7),$F39>P$2),1, IF(AND($H39<P$2+7,$H39>P$2),3, IF(AND($F39<=P$2, $H39>=P$2), 2, "" ))) | Q39: =IF(AND($F39<(Q$2+7),$F39>Q$2),1, IF(AND($H39<Q$2+7,$H39>Q$2),3, IF(AND($F39<=Q$2, $H39>=Q$2), 2, "" ))) | R39: =IF(AND($F39<(R$2+7),$F39>R$2),1, IF(AND($H39<R$2+7,$H39>R$2),3, IF(AND($F39<=R$2, $H39>=R$2), 2, "" ))) | S39: =IF(AND($F39<(S$2+7),$F39>S$2),1, IF(AND($H39<S$2+7,$H39>S$2),3, IF(AND($F39<=S$2, $H39>=S$2), 2, "" ))) | ... AQ39: =IF(AND($F39<(AQ$2+7),$F39>AQ$2),1, IF(AND($H39<AQ$2+7,$H39>AQ$2),3, IF(AND($F39<=AQ$2, $H39>=AQ$2), 2, "" ))) -> 2
B40: Snag List | C40: 44014 | D40: 3 | E40: 44019 | F40: 44014 | G40: 3 | H40: 44019
B41: Pre-Commissioning Checks | C41: 44010 | D41: 2 | E41: 44012 | F41: 44010 | G41: 2 | H41: 44012
B42: Issue CoC | C42: 43997 | D42: 2 | E42: 44001 | F42: 43997 | G42: 2 | H42: 44001 | L42: =IF(AND($F42<(L$2+7),$F42>L$2),1, IF(AND($H42<L$2+7,$H42>L$2),3, IF(AND($F42<=L$2, $H42>=L$2), 2, "" ))) | M42: =IF(AND($F42<(M$2+7),$F42>M$2),1, IF(AND($H42<M$2+7,$H42>M$2),3, IF(AND($F42<=M$2, $H42>=M$2), 2, "" ))) | N42: =IF(AND($F42<(N$2+7),$F42>N$2),1, IF(AND($H42<N$2+7,$H42>N$2),3, IF(AND($F42<=N$2, $H42>=N$2), 2, "" ))) | O42: =IF(AND($F42<(O$2+7),$F42>O$2),1, IF(AND($H42<O$2+7,$H42>O$2),3, IF(AND($F42<=O$2, $H42>=O$2), 2, "" ))) | P42: =IF(AND($F42<(P$2+7),$F42>P$2),1, IF(AND($H42<P$2+7,$H42>P$2),3, IF(AND($F42<=P$2, $H42>=P$2), 2, "" ))) | Q42: =IF(AND($F42<(Q$2+7),$F42>Q$2),1, IF(AND($H42<Q$2+7,$H42>Q$2),3, IF(AND($F42<=Q$2, $H42>=Q$2), 2, "" ))) | R42: =IF(AND($F42<(R$2+7),$F42>R$2),1, IF(AND($H42<R$2+7,$H42>R$2),3, IF(AND($F42<=R$2, $H42>=R$2), 2, "" ))) | S42: =IF(AND($F42<(S$2+7),$F42>S$2),1, IF(AND($H42<S$2+7,$H42>S$2),3, IF(AND($F42<=S$2, $H42>=S$2), 2, "" ))) | ... AQ42: =IF(AND($F42<(AQ$2+7),$F42>AQ$2),1, IF(AND($H42<AQ$2+7,$H42>AQ$2),3, IF(AND($F42<=AQ$2, $H42>=AQ$2), 2, "" )))
B43: Cold Commissioning | C43: 44012 | D43: 1 | E43: 44013 | F43: 44012 | G43: 1 | H43: 44013 | L43: =IF(AND($F43<(L$2+7),$F43>L$2),1, IF(AND($H43<L$2+7,$H43>L$2),3, IF(AND($F43<=L$2, $H43>=L$2), 2, "" ))) | M43: =IF(AND($F43<(M$2+7),$F43>M$2),1, IF(AND($H43<M$2+7,$H43>M$2),3, IF(AND($F43<=M$2, $H43>=M$2), 2, "" ))) | N43: =IF(AND($F43<(N$2+7),$F43>N$2),1, IF(AND($H43<N$2+7,$H43>N$2),3, IF(AND($F43<=N$2, $H43>=N$2), 2, "" ))) | O43: =IF(AND($F43<(O$2+7),$F43>O$2),1, IF(AND($H43<O$2+7,$H43>O$2),3, IF(AND($F43<=O$2, $H43>=O$2), 2, "" ))) | P43: =IF(AND($F43<(P$2+7),$F43>P$2),1, IF(AND($H43<P$2+7,$H43>P$2),3, IF(AND($F43<=P$2, $H43>=P$2), 2, "" ))) | Q43: =IF(AND($F43<(Q$2+7),$F43>Q$2),1, IF(AND($H43<Q$2+7,$H43>Q$2),3, IF(AND($F43<=Q$2, $H43>=Q$2), 2, "" ))) | R43: =IF(AND($F43<(R$2+7),$F43>R$2),1, IF(AND($H43<R$2+7,$H43>R$2),3, IF(AND($F43<=R$2, $H43>=R$2), 2, "" ))) | S43: =IF(AND($F43<(S$2+7),$F43>S$2),1, IF(AND($H43<S$2+7,$H43>S$2),3, IF(AND($F43<=S$2, $H43>=S$2), 2, "" ))) | ... AQ43: =IF(AND($F43<(AQ$2+7),$F43>AQ$2),1, IF(AND($H43<AQ$2+7,$H43>AQ$2),3, IF(AND($F43<=AQ$2, $H43>=AQ$2), 2, "" ))) -> 3
B44: Hot Commissioning | C44: 44013 | D44: 2 | E44: 44015 | F44: 44013 | G44: 2 | H44: 44015 | L44: =IF(AND($F44<(L$2+7),$F44>L$2),1, IF(AND($H44<L$2+7,$H44>L$2),3, IF(AND($F44<=L$2, $H44>=L$2), 2, "" ))) | M44: =IF(AND($F44<(M$2+7),$F44>M$2),1, IF(AND($H44<M$2+7,$H44>M$2),3, IF(AND($F44<=M$2, $H44>=M$2), 2, "" ))) | N44: =IF(AND($F44<(N$2+7),$F44>N$2),1, IF(AND($H44<N$2+7,$H44>N$2),3, IF(AND($F44<=N$2, $H44>=N$2), 2, "" ))) | O44: =IF(AND($F44<(O$2+7),$F44>O$2),1, IF(AND($H44<O$2+7,$H44>O$2),3, IF(AND($F44<=O$2, $H44>=O$2), 2, "" ))) | P44: =IF(AND($F44<(P$2+7),$F44>P$2),1, IF(AND($H44<P$2+7,$H44>P$2),3, IF(AND($F44<=P$2, $H44>=P$2), 2, "" ))) | Q44: =IF(AND($F44<(Q$2+7),$F44>Q$2),1, IF(AND($H44<Q$2+7,$H44>Q$2),3, IF(AND($F44<=Q$2, $H44>=Q$2), 2, "" ))) | R44: =IF(AND($F44<(R$2+7),$F44>R$2),1, IF(AND($H44<R$2+7,$H44>R$2),3, IF(AND($F44<=R$2, $H44>=R$2), 2, "" ))) | S44: =IF(AND($F44<(S$2+7),$F44>S$2),1, IF(AND($H44<S$2+7,$H44>S$2),3, IF(AND($F44<=S$2, $H44>=S$2), 2, "" ))) | ... AQ44: =IF(AND($F44<(AQ$2+7),$F44>AQ$2),1, IF(AND($H44<AQ$2+7,$H44>AQ$2),3, IF(AND($F44<=AQ$2, $H44>=AQ$2), 2, "" ))) -> 1
A45: 13 | B45: Handover | C45: 44020 | D45: 1 | E45: 44021 | F45: 44020 | G45: 1 | H45: 44021 | L45: =IF(AND($F45<(L$2+7),$F45>L$2),1, IF(AND($H45<L$2+7,$H45>L$2),3, IF(AND($F45<=L$2, $H45>=L$2), 2, "" ))) | M45: =IF(AND($F45<(M$2+7),$F45>M$2),1, IF(AND($H45<M$2+7,$H45>M$2),3, IF(AND($F45<=M$2, $H45>=M$2), 2, "" ))) | N45: =IF(AND($F45<(N$2+7),$F45>N$2),1, IF(AND($H45<N$2+7,$H45>N$2),3, IF(AND($F45<=N$2, $H45>=N$2), 2, "" ))) | O45: =IF(AND($F45<(O$2+7),$F45>O$2),1, IF(AND($H45<O$2+7,$H45>O$2),3, IF(AND($F45<=O$2, $H45>=O$2), 2, "" ))) | P45: =IF(AND($F45<(P$2+7),$F45>P$2),1, IF(AND($H45<P$2+7,$H45>P$2),3, IF(AND($F45<=P$2, $H45>=P$2), 2, "" ))) | Q45: =IF(AND($F45<(Q$2+7),$F45>Q$2),1, IF(AND($H45<Q$2+7,$H45>Q$2),3, IF(AND($F45<=Q$2, $H45>=Q$2), 2, "" ))) | R45: =IF(AND($F45<(R$2+7),$F45>R$2),1, IF(AND($H45<R$2+7,$H45>R$2),3, IF(AND($F45<=R$2, $H45>=R$2), 2, "" ))) | S45: =IF(AND($F45<(S$2+7),$F45>S$2),1, IF(AND($H45<S$2+7,$H45>S$2),3, IF(AND($F45<=S$2, $H45>=S$2), 2, "" ))) | ... AQ45: =IF(AND($F45<(AQ$2+7),$F45>AQ$2),1, IF(AND($H45<AQ$2+7,$H45>AQ$2),3, IF(AND($F45<=AQ$2, $H45>=AQ$2), 2, "" )))
A46: E | B46: PAYMENT MILESTONE 6: HANDOVER COMPLETE | C46: 44022 | D46: 1 | E46: 44025 | F46: 44022 | G46: 1 | H46: 44025
C47: 43831 | D47: These numbers are used to set the start and end dates on the Gantt Chart
C48: 44014

Sheet Compliance
B2: HSE
B4: Description | C4: Status | D4: Approved By | E4: Date | F4: Results / Comments
B5: NOC
B6: 7.1 Agreement
B7: 13.2 Agreement
B8: EE File
B9: Subbie File
B16: SSEG
B18: Description | C18: Status | D18: Approved By | E18: Date | F18: Results / Comments
B19: SSEG Application
B20: PTI
B21: Commissioning Approval

Sheet Revenue Tracking
B2: HIGH LEVEL PROJECT REVENUE TRACKING
D3: COSTED | F3: ACTUAL | L3: FINANCIAL REVIEW | N3: TIMELINE REVIEW | P3: 2025 Actual Revenue | Q3: 2025 Actual COS | R3: 2026 Budget Revenue | S3: 2026 Budget COS | T3: 2026 Actual Revenue | U3: 2026 Actual COS
B4: 1 | C4: Planned Revenue | D4: ='Project Plan'!E6 -> 12364058 | F4: =F21 -> 12392594 | N4: Start Date | P4: =F4 -> 12392594 | Q4: =SUMIFS('Expenditure Breakdown'!$Q:$Q, 'Expenditure Breakdown'!$T:$T, ">"&DATE(2024,8,31), 'Expenditure Breakdown'!$T:$T, "<="&DATE(2025,8,31), 'Expenditure Breakdown'!$S:$S, "<>") -> 6961407.9 | R4: =SUMIFS('Expenditure Breakdown'!$U:$U, 'Expenditure Breakdown'!$T:$T, ">"&DATE(2025,8,31), 'Expenditure Breakdown'!$T:$T, "<="&DATE(2026,8,31)) -> 1203406.5 | S4: =SUMIFS('Expenditure Breakdown'!$Q:$Q, 'Expenditure Breakdown'!$T:$T, ">"&DATE(2025,8,31), 'Expenditure Breakdown'!$T:$T, "<="&DATE(2026,8,31)) -> 1276793.2 | T4: =SUMIFS('Expenditure Breakdown'!$U:$U, 'Expenditure Breakdown'!$T:$T, ">"&DATE(2025,8,31), 'Expenditure Breakdown'!$T:$T, "<="&DATE(2026,8,31), 'Expenditure Breakdown'!$S:$S, "<>") -> 1238696.9 | U4: =SUMIFS('Expenditure Breakdown'!$Q:$Q, 'Expenditure Breakdown'!$T:$T, ">"&DATE(2025,8,31), 'Expenditure Breakdown'!$T:$T, "<="&DATE(2026,8,31), 'Expenditure Breakdown'!$S:$S, "<>") -> 1229853.4
B5: 2 | C5: Planned Expenditure | D5: =+'Expenditure Tracking'!F5 -> 10416340 | F5: =+'Expenditure Tracking'!H5 -> 8238201.1 | G5: VO PM Limit | H5: Current VO Total
B6: 3 | C6: Planned Profit | D6: =+D4-D5 -> 1947718.6 | F6: =+F4-F5 -> 4154392.9 | G6: =D6*0.05 -> 97385.93 | H6: =SUMIF('Expenditure Breakdown'!N:N,"*VO*",'Expenditure Breakdown'!Q:Q) -> 186543.66 | N6: End Date - PC
B7: 4 | C7: Planned Margin | D7: =+D6/D4 -> 0.15753069 | F7: =+F6/F4 -> 0.33523191
B10: CONTRACT
B12: No. | C12: PAYMENT MILESTONE | E12: % | F12: VALUE | H12: PLANNED PAYMENT DATE | L12: INVOICE NUMBER | N12: INVOICE RAISED DATE | P12: PAYMENT RECEIVED DATE | R12: MILESTONE NOTES & COMMENTS
B13: 1 | C13: Acceptance and Initial Deposit | E13: 0.35 | F13: =$D$4*E13 -> 4327420.4 | H13: 45835 | L13: 004770 | N13: 45826 | P13: 45849
B14: 2 | C14: Delivery of Panels | E14: 0.3 | F14: =$D$4*E14 -> 3709217.5 | H14: ='Project Plan'!E42+7 -> 45884 | L14: 004815 | N14: 45883 | P14: 45897
B15: 3 | C15: Delivery of Inverters | E15: 0.2 | F15: =$D$4*E15 -> 2472811.7 | H15: ='Project Plan'!E23+7 -> 45845 | L15: 004815 | N15: 45883 | P15: 45897
B16: 4 | C16: Practical Completion | E16: 0.1 | F16: =$D$4*E16 -> 1236405.8 | H16: 45947 | L16: 004865 | N16: 45958 | P16: 45968
B17: 5 | C17: Handover | E17: 0.05 | F17: =$D$4*E17 -> 618202.92 | H17: 45958 | L17: 004892 | N17: ='Project Plan'!K81+3 -> 45999 | P17: 46031
B18: 6 | C18: Reduced CAPEX | E18: 0 | F18: =N29*-1 -> -42222.164 | H18: 45958 | L18: 004892 | N18: 45999 | P18: =P17 -> 46031
B19: 7 | C19: Installation of Meters | E19: 0 | F19: 70757.8 | L19: 004892 | N19: 45999 | P19: =P18 -> 46031
E21: =SUM(E13:E19) -> 1 | F21: =SUM(F13:F19) -> 12392594
B23: KEY: | C23: contains an error (in result or a check has failed)
C24: Red Font - IF TEXT : content not yet confirmed
C25: Red Font - IF NUMBER: Negative value | L25: Contract | N25: 682000
C26: Anything in yellow is a concern or risk for noting or action | L26: Installed | N26: 669120
C27: confirmed | N27: =N25-N26 -> 12880
C28: [ADD INITIALS: comment for noting in square brackets, use colour or red to draw attention if important] | L28: DC Rate | N28: 3.2781183
C29: [RT: When adding rows into sheet, ensure you insert between first and last row of each category] | L29: Reduced CAPEX | N29: =N28*N27 -> 42222.164
C30: end of sheet - do not insert information below/beyond this
B40: No. | C40: PAYMENT MILESTONE | E40: %
B41: 1 | C41: Deposit - Project commencement | E41: 0.35
B42: 2 | C42: Delivery of Panels | E42: 0.3
B43: 3 | C43: Delivery of Inverters | E43: 0.2
B44: 4 | C44: Practical Completion | E44: 0.1
B45: 5 | C45: Handover | E45: 0.05
C46: Total | E46: =SUM(E41:E45) -> 1
E47: =SUM(E41:E45) -> 1

Sheet Project Plan
N1: =TODAY() -> 46083 | O1: =TODAY() -> 46083
C2: PROJECT PLAN | E2: Red Rocket | N2: 0 | O2: 1
C3: PROJECT SIZE (kWp) | E3: 682
C4: PROJECT DEVELOPER | E4: Peet Verenney | J4: Target Month | K4: 45869
C5: PROJECT MANAGERS | E5: Justin Franke
C6: CONTRACT VALUE | E6: 12364058
C7: Phase: | E7: DLP
B8: No. | C8: HIGH LEVEL PROGRAMME | E8: Planned Start | F8: Duration (days) | G8: Planned End | I8: Actual Start | J8: Duration (days) | K8: Actual End | M8: Status | N8: Expected Status | O8: Comment
F9: =G52-E20 -> 89 | J9: =K52-I20 -> 105 | M9: =AVERAGE(M11,M19,M22,M31,M41,M52,M69,M65) -> 1 | N9: =AVERAGE(N11,N19,N22,N31,N41,N52,N69,N65) -> 1 | S9: =C8 -> HIGH LEVEL PROGRAMME | T9: =I8 -> Actual Start | U9: =J8 -> Duration (days) | V9: =K8 -> Actual End | W9: =M8 -> Status
B11: 1 | C11: Project Initiation | E11: 45831 | F11: 73 | G11: 45904 | I11: =MIN(I12:I17) -> 45831 | J11: =K11-I11 -> 73 | K11: =MAX(K12:K17) -> 45904 | M11: 1 | N11: 1 | S11: =C11 -> Project Initiation | T11: =I11 -> 45831 | U11: =V11-T11 -> 73 | V11: =K11 -> 45904 | W11: =M11 -> 1 | X11: =N11 -> 1
B12: 1.1 | C12: BD Handover | E12: 45831 | F12: 5 | G12: 45838 | I12: 45831 | J12: 5 | K12: =WORKDAY.INTL(I12,J12,1,Data!$C$3:$C$14) -> 45838 | M12: 1 | N12: =_xlfn.LET( _xlpm.s,VALUE($I12), _xlpm.e,VALUE($K12), IF(OR(_xlpm.s="",_xlpm.e=""),"", IF(_xlpm.e<=_xlpm.s, IF(TODAY()>=_xlpm.e,1,0), MAX(0,MIN(1,(TODAY()-_xlpm.s)/(_xlpm.e-_xlpm.s))))) ) -> 1 | S12: =C19 -> Site Establishment | T12: =I19 -> 45883 | U12: =V12-T12 -> 1 | V12: =K19 -> 45884 | W12: =M19 -> 1 | X12: =N19 -> 1 | Z12: Commencement Date | AA12: 45849
B13: 1.2 | C13: Project Introduction | E13: 45855 | F13: 1 | G13: 45856 | I13: 45855 | J13: 1 | K13: =WORKDAY.INTL(I13,J13,1,Data!$C$3:$C$14) -> 45856 | M13: 1 | N13: =_xlfn.LET( _xlpm.s,VALUE($I13), _xlpm.e,VALUE($K13), IF(OR(_xlpm.s="",_xlpm.e=""),"", IF(_xlpm.e<=_xlpm.s, IF(TODAY()>=_xlpm.e,1,0), MAX(0,MIN(1,(TODAY()-_xlpm.s)/(_xlpm.e-_xlpm.s))))) ) -> 1 | S13: =C22 -> AC Installation - Tie In 1 (Right) | T13: =I20+4 -> 45887 | U13: =V13-T13 -> 65 | V13: =K22 -> 45952 | W13: =M22 -> 1 | X13: =N22 -> 1
B14: 1.3 | C14: HSE - JA Electrical | E14: 45841 | F14: 28 | G14: 45881 | I14: 45841 | J14: 28 | K14: =WORKDAY.INTL(I14,J14,1,Data!$C$3:$C$14) -> 45881 | M14: 1 | N14: =_xlfn.LET( _xlpm.s,VALUE($I14), _xlpm.e,VALUE($K14), IF(OR(_xlpm.s="",_xlpm.e=""),"", IF(_xlpm.e<=_xlpm.s, IF(TODAY()>=_xlpm.e,1,0), MAX(0,MIN(1,(TODAY()-_xlpm.s)/(_xlpm.e-_xlpm.s))))) ) -> 1 | S14: =C31 -> AC Installation - Tie In 2 (Left) | T14: =T12 -> 45883 | U14: =V14-T14 -> 63 | V14: =K31 -> 45946 | W14: =M31 -> 1 | X14: =N31 -> 1 | Y14: =9*7 -> 63
B15: 1.4 | C15: HSE - Ask Fritz | E15: 45902 | F15: 2 | G15: 45904 | I15: 45902 | J15: 2 | K15: =WORKDAY.INTL(I15,J15,1,Data!$C$3:$C$14) -> 45904 | M15: 1 | N15: =_xlfn.LET( _xlpm.s,VALUE($I15), _xlpm.e,VALUE($K15), IF(OR(_xlpm.s="",_xlpm.e=""),"", IF(_xlpm.e<=_xlpm.s, IF(TODAY()>=_xlpm.e,1,0), MAX(0,MIN(1,(TODAY()-_xlpm.s)/(_xlpm.e-_xlpm.s))))) ) -> 1 | S15: =C41 -> DC Works | T15: =I43 -> 45926 | U15: =V15-T15 -> 24 | V15: =K41 -> 45950 | W15: =M41 -> 1
B16: 1.5 | C16: Installer Kick Off | E16: 45855 | F16: 1 | G16: 45856 | I16: 45855 | J16: 1 | K16: =WORKDAY.INTL(I16,J16,1,Data!$C$3:$C$14) -> 45856 | M16: 1 | N16: =_xlfn.LET( _xlpm.s,VALUE($I16), _xlpm.e,VALUE($K16), IF(OR(_xlpm.s="",_xlpm.e=""),"", IF(_xlpm.e<=_xlpm.s, IF(TODAY()>=_xlpm.e,1,0), MAX(0,MIN(1,(TODAY()-_xlpm.s)/(_xlpm.e-_xlpm.s))))) ) -> 1 | S16: =C55 -> Soft Commissioning (Energy Flowing) | T16: =I55 -> 45936 | U16: =J55 -> 11 | V16: =K55 -> 45951 | W16: =M55 -> 1 | X16: =N41 -> 1 | Y16: =75/7 -> 10.714286
B17: 1.6 | C17: Project Review | E17: 45855 | F17: 1 | G17: 45856 | I17: 45855 | J17: 1 | K17: =WORKDAY.INTL(I17,J17,1,Data!$C$3:$C$14) -> 45856 | M17: 1 | N17: =_xlfn.LET( _xlpm.s,VALUE($I17), _xlpm.e,VALUE($K17), IF(OR(_xlpm.s="",_xlpm.e=""),"", IF(_xlpm.e<=_xlpm.s, IF(TODAY()>=_xlpm.e,1,0), MAX(0,MIN(1,(TODAY()-_xlpm.s)/(_xlpm.e-_xlpm.s))))) ) -> 1 | S17: =C58 -> Full Commissioning Monitoring | T17: =I58 -> 45951 | U17: =J58 -> 5 | V17: =K58 -> 45958 | W17: =M58 -> 1 | X17: =N52 -> 1 | Z17: =T16-AA12 -> 87
S18: Higeco Commissioning | T18: =I56 -> 45952 | U18: 1 | V18: =K56 -> 45987 | W18: =M56 -> 1 | X18: =N65 -> 1
B19: 2 | C19: Site Establishment | E19: 45883 | F19: 1 | G19: 45884 | I19: =MIN(I20:I21) -> 45883 | J19: =K19-I19 -> 1 | K19: =MAX(K20) -> 45884 | M19: =(J20*M20)/J19 -> 1 | N19: =(K20*N20)/K19 -> 1 | S19: =C65 -> QA Inspections | T19: =I66 -> 45959 | U19: =J65 -> 1 | V19: =K65 -> 45960 | W19: =M65 -> 1 | X19: =N69 -> 1
B20: 2.1 | C20: Solar Contractor Establishment | E20: 45883 | F20: 1 | G20: 45884 | I20: 45883 | J20: 1 | K20: =I20+J20 -> 45884 | M20: 1 | N20: =_xlfn.LET( _xlpm.s,VALUE($I20), _xlpm.e,VALUE($K20), IF(OR(_xlpm.s="",_xlpm.e=""),"", IF(_xlpm.e<=_xlpm.s, IF(TODAY()>=_xlpm.e,1,0), MAX(0,MIN(1,(TODAY()-_xlpm.s)/(_xlpm.e-_xlpm.s))))) ) -> 1 | S20: =C69 -> Project Closure | T20: =I69 -> 45953 | U20: =J69 -> 43 | V20: =K69 -> 45996 | W20: =M69 -> 1
B22: 3 | C22: AC Installation - Tie In 1 (Right) | E22: 45838 | F22: 142 | G22: 45980 | I22: =MIN(I23:I29) -> 45838 | J22: =K22-I22 -> 114 | K22: =MAX(K23:K29) -> 45952 | M22: =AVERAGE(M23:M30) -> 1 | N22: =AVERAGE(N23:N30) -> 1
B23: 3.1 | C23: Inverters delivered | E23: 45838 | F23: 1 | G23: 45839 | I23: 45838 | J23: 1 | K23: =WORKDAY.INTL(I23,J23,1,Data!$C$3:$C$14) -> 45839 | M23: 1 | N23: =_xlfn.LET( _xlpm.s,VALUE($I23), _xlpm.e,VALUE($K23), IF(OR(_xlpm.s="",_xlpm.e=""),"", IF(_xlpm.e<=_xlpm.s, IF(TODAY()>=_xlpm.e,1,0), MAX(0,MIN(1,(TODAY()-_xlpm.s)/(_xlpm.e-_xlpm.s))))) ) -> 1
B24: 3.2 | C24: Inverters Mounted | E24: 45943 | F24: 1 | G24: 45944 | I24: 45931 | J24: 1 | K24: =WORKDAY.INTL(I24,J24,1,Data!$C$3:$C$14) -> 45932 | M24: 1 | N24: =_xlfn.LET( _xlpm.s,VALUE($I24), _xlpm.e,VALUE($K24), IF(OR(_xlpm.s="",_xlpm.e=""),"", IF(_xlpm.e<=_xlpm.s, IF(TODAY()>=_xlpm.e,1,0), MAX(0,MIN(1,(TODAY()-_xlpm.s)/(_xlpm.e-_xlpm.s))))) ) -> 1
B25: 3.3 | C25: Solar DB Lead Time | E25: 45880 | F25: 25 | G25: 45915 | I25: 45880 | J25: 25 | K25: =WORKDAY.INTL(I25,J25,1,Data!$C$3:$C$14) -> 45915 | M25: =_xlfn.LET( _xlpm.s,VALUE($I25), _xlpm.e,VALUE($K25), IF(OR(_xlpm.s="",_xlpm.e=""),"", IF(_xlpm.e<=_xlpm.s, IF(TODAY()>=_xlpm.e,1,0), MAX(0,MIN(1,(TODAY()-_xlpm.s)/(_xlpm.e-_xlpm.s))))) ) -> 1 | N25: =_xlfn.LET( _xlpm.s,VALUE($I25), _xlpm.e,VALUE($K25), IF(OR(_xlpm.s="",_xlpm.e=""),"", IF(_xlpm.e<=_xlpm.s, IF(TODAY()>=_xlpm.e,1,0), MAX(0,MIN(1,(TODAY()-_xlpm.s)/(_xlpm.e-_xlpm.s))))) ) -> 1
B26: 3.4 | C26: Civil Works - Tie In 1 | E26: 45941 | F26: 28 | G26: 45980 | I26: 45931 | J26: 15 | K26: =WORKDAY.INTL(I26,J26,1,Data!$C$3:$C$14) -> 45952 | M26: =_xlfn.LET( _xlpm.s,VALUE($I26), _xlpm.e,VALUE($K26), IF(OR(_xlpm.s="",_xlpm.e=""),"", IF(_xlpm.e<=_xlpm.s, IF(TODAY()>=_xlpm.e,1,0), MAX(0,MIN(1,(TODAY()-_xlpm.s)/(_xlpm.e-_xlpm.s))))) ) -> 1 | N26: =_xlfn.LET( _xlpm.s,VALUE($I26), _xlpm.e,VALUE($K26), IF(OR(_xlpm.s="",_xlpm.e=""),"", IF(_xlpm.e<=_xlpm.s, IF(TODAY()>=_xlpm.e,1,0), MAX(0,MIN(1,(TODAY()-_xlpm.s)/(_xlpm.e-_xlpm.s))))) ) -> 1 | O26: Adding 7 days as float. Set up meeting with Fritz
B27: 3.5 | C27: Rigging of Batteries | E27: 45922 | F27: 1 | G27: 45940 | I27: 45922 | J27: 1 | K27: 45940 | M27: 1 | N27: =_xlfn.LET( _xlpm.s,VALUE($I27), _xlpm.e,VALUE($K27), IF(OR(_xlpm.s="",_xlpm.e=""),"", IF(_xlpm.e<=_xlpm.s, IF(TODAY()>=_xlpm.e,1,0), MAX(0,MIN(1,(TODAY()-_xlpm.s)/(_xlpm.e-_xlpm.s))))) ) -> 1
B28: 3.6 | C28: AC Works Tie In 1 | E28: 45943 | F28: 10 | G28: 45957 | I28: =I24 -> 45931 | J28: 10 | K28: =WORKDAY.INTL(I28,J28,1,Data!$C$3:$C$14) -> 45945 | M28: 1 | N28: =_xlfn.LET( _xlpm.s,VALUE($I28), _xlpm.e,VALUE($K28), IF(OR(_xlpm.s="",_xlpm.e=""),"", IF(_xlpm.e<=_xlpm.s, IF(TODAY()>=_xlpm.e,1,0), MAX(0,MIN(1,(TODAY()-_xlpm.s)/(_xlpm.e-_xlpm.s))))) ) -> 1
B29: 3.7 | C29: AC Tie-In 1 | E29: 45931 | F29: 1 | G29: 45932 | I29: 45931 | J29: 1 | K29: =WORKDAY.INTL(I29,J29,1,Data!$C$3:$C$14) -> 45932 | M29: 1 | N29: =_xlfn.LET( _xlpm.s,VALUE($I29), _xlpm.e,VALUE($K29), IF(OR(_xlpm.s="",_xlpm.e=""),"", IF(_xlpm.e<=_xlpm.s, IF(TODAY()>=_xlpm.e,1,0), MAX(0,MIN(1,(TODAY()-_xlpm.s)/(_xlpm.e-_xlpm.s))))) ) -> 1
B31: 4 | C31: AC Installation - Tie In 2 (Left) | E31: 45838 | F31: 133 | G31: 45971 | I31: =MIN(I33:I38) -> 45838 | J31: =K31-I31 -> 108 | K31: =MAX(K33:K39) -> 45946 | M31: =AVERAGE(M33:M39) -> 1 | N31: =AVERAGE(N33:N39) -> 1
B32: 4.1 | C32: Lifeline Installation (If Applicable) | M32: 0 | N32: 0
B33: 4.1 | C33: Inverters delivered | E33: 45838 | F33: 1 | G33: 45839 | I33: 45838 | J33: 1 | K33: =WORKDAY.INTL(I33,J33,1,Data!$C$3:$C$14) -> 45839 | M33: 1 | N33: =_xlfn.LET( _xlpm.s,VALUE($I33), _xlpm.e,VALUE($K33), IF(OR(_xlpm.s="",_xlpm.e=""),"", IF(_xlpm.e<=_xlpm.s, IF(TODAY()>=_xlpm.e,1,0), MAX(0,MIN(1,(TODAY()-_xlpm.s)/(_xlpm.e-_xlpm.s))))) ) -> 1
B34: 4.2 | C34: Inverters Mounted | E34: 45943 | F34: 1 | G34: 45944 | I34: 45931 | J34: 1 | K34: =WORKDAY.INTL(I34,J34,1,Data!$C$3:$C$14) -> 45932 | M34: 1 | N34: =_xlfn.LET( _xlpm.s,VALUE($I34), _xlpm.e,VALUE($K34), IF(OR(_xlpm.s="",_xlpm.e=""),"", IF(_xlpm.e<=_xlpm.s, IF(TODAY()>=_xlpm.e,1,0), MAX(0,MIN(1,(TODAY()-_xlpm.s)/(_xlpm.e-_xlpm.s))))) ) -> 1
B35: 4.3 | C35: Solar DB Lead Time | E35: 45880 | F35: 45 | G35: 45944 | I35: =I25 -> 45880 | J35: 45 | K35: =WORKDAY.INTL(I35,J35,1,Data!$C$3:$C$14) -> 45944 | M35: 1 | N35: =_xlfn.LET( _xlpm.s,VALUE($I35), _xlpm.e,VALUE($K35), IF(OR(_xlpm.s="",_xlpm.e=""),"", IF(_xlpm.e<=_xlpm.s, IF(TODAY()>=_xlpm.e,1,0), MAX(0,MIN(1,(TODAY()-_xlpm.s)/(_xlpm.e-_xlpm.s))))) ) -> 1
B36: 4.4 | C36: Civil Works - Tie In 2 | E36: 45941 | F36: 7 | G36: 45951 | I36: 45931 | J36: 5 | K36: =WORKDAY.INTL(I36,J36,1,Data!$C$3:$C$14) -> 45938 | M36: 1 | N36: =_xlfn.LET( _xlpm.s,VALUE($I36), _xlpm.e,VALUE($K36), IF(OR(_xlpm.s="",_xlpm.e=""),"", IF(_xlpm.e<=_xlpm.s, IF(TODAY()>=_xlpm.e,1,0), MAX(0,MIN(1,(TODAY()-_xlpm.s)/(_xlpm.e-_xlpm.s))))) ) -> 1
B37: 4.5 | C37: Rigging of Batteries | E37: 45922 | F37: 1 | G37: 45940 | I37: 45922 | J37: 1 | K37: 45940 | M37: 1 | N37: =_xlfn.LET( _xlpm.s,VALUE($I37), _xlpm.e,VALUE($K37), IF(OR(_xlpm.s="",_xlpm.e=""),"", IF(_xlpm.e<=_xlpm.s, IF(TODAY()>=_xlpm.e,1,0), MAX(0,MIN(1,(TODAY()-_xlpm.s)/(_xlpm.e-_xlpm.s))))) ) -> 1
B38: 4.6 | C38: AC Works Tie In 2 | E38: 45954 | F38: 10 | G38: 45968 | I38: =WORKDAY.INTL(K28,0,1,Data!$C$3:$C$14)-8 -> 45937 | J38: 7 | K38: =WORKDAY.INTL(I38,J38,1,Data!$C$3:$C$14) -> 45946 | M38: 1 | N38: =_xlfn.LET( _xlpm.s,VALUE($I38), _xlpm.e,VALUE($K38), IF(OR(_xlpm.s="",_xlpm.e=""),"", IF(_xlpm.e<=_xlpm.s, IF(TODAY()>=_xlpm.e,1,0), MAX(0,MIN(1,(TODAY()-_xlpm.s)/(_xlpm.e-_xlpm.s))))) ) -> 1
B39: 4.7 | C39: AC Tie-In 2 | E39: 45968 | F39: 1 | G39: 45971 | I39: 45938 | J39: 1 | K39: =WORKDAY.INTL(I39,J39,1,Data!$C$3:$C$14) -> 45939 | M39: 1 | N39: =_xlfn.LET( _xlpm.s,VALUE($I39), _xlpm.e,VALUE($K39), IF(OR(_xlpm.s="",_xlpm.e=""),"", IF(_xlpm.e<=_xlpm.s, IF(TODAY()>=_xlpm.e,1,0), MAX(0,MIN(1,(TODAY()-_xlpm.s)/(_xlpm.e-_xlpm.s))))) ) -> 1
B41: 5 | C41: DC Works | E41: 45877 | F41: 84 | G41: 45961 | I41: =MIN(I42:I43) -> 45877 | J41: =K41-I41 -> 73 | K41: =MAX(K42:K50) -> 45950 | M41: =AVERAGE(M42:M50) -> 1 | N41: =AVERAGE(N42:N50) -> 1
B42: 5.1 | C42: Module delivery | E42: 45877 | F42: 1 | G42: 45880 | I42: 45877 | J42: 1 | K42: =WORKDAY.INTL(I42,J42,1,Data!$C$3:$C$14) -> 45880 | M42: 1 | N42: =_xlfn.LET( _xlpm.s,VALUE($I42), _xlpm.e,VALUE($K42), IF(OR(_xlpm.s="",_xlpm.e=""),"", IF(_xlpm.e<=_xlpm.s, IF(TODAY()>=_xlpm.e,1,0), MAX(0,MIN(1,(TODAY()-_xlpm.s)/(_xlpm.e-_xlpm.s))))) ) -> 1
B43: 5.2 | C43: Module mounting | E43: 45933 | F43: 20 | G43: 45961 | I43: =K45-17 -> 45926 | J43: 12 | K43: =WORKDAY.INTL(I43,J43,1,Data!$C$3:$C$14) -> 45944 | M43: 1 | N43: =_xlfn.LET( _xlpm.s,VALUE($I43), _xlpm.e,VALUE($K43), IF(OR(_xlpm.s="",_xlpm.e=""),"", IF(_xlpm.e<=_xlpm.s, IF(TODAY()>=_xlpm.e,1,0), MAX(0,MIN(1,(TODAY()-_xlpm.s)/(_xlpm.e-_xlpm.s))))) ) -> 1
B44: 5.3 | C44: Mounting Structure delivered | E44: 45878 | F44: 1 | G44: 45880 | I44: 45878 | J44: 1 | K44: =WORKDAY.INTL(I44,J44,1,Data!$C$3:$C$14) -> 45880 | M44: 1 | N44: =_xlfn.LET( _xlpm.s,VALUE($I44), _xlpm.e,VALUE($K44), IF(OR(_xlpm.s="",_xlpm.e=""),"", IF(_xlpm.e<=_xlpm.s, IF(TODAY()>=_xlpm.e,1,0), MAX(0,MIN(1,(TODAY()-_xlpm.s)/(_xlpm.e-_xlpm.s))))) ) -> 1
B45: 5.4 | C45: Mounting Structure installation | E45: 45893 | F45: 40 | G45: 45950 | I45: =I20+10 -> 45893 | J45: 35 | K45: =WORKDAY.INTL(I45,J45,1,Data!$C$3:$C$14) -> 45943 | M45: 1 | N45: =_xlfn.LET( _xlpm.s,VALUE($I45), _xlpm.e,VALUE($K45), IF(OR(_xlpm.s="",_xlpm.e=""),"", IF(_xlpm.e<=_xlpm.s, IF(TODAY()>=_xlpm.e,1,0), MAX(0,MIN(1,(TODAY()-_xlpm.s)/(_xlpm.e-_xlpm.s))))) ) -> 1
B46: 5.5 | C46: Lintel Delivery | E46: 45879 | F46: 10 | G46: 45891 | I46: 45879 | J46: 10 | K46: =WORKDAY.INTL(I46,J46,1,Data!$C$3:$C$14) -> 45891 | M46: 1 | N46: =_xlfn.LET( _xlpm.s,VALUE($I46), _xlpm.e,VALUE($K46), IF(OR(_xlpm.s="",_xlpm.e=""),"", IF(_xlpm.e<=_xlpm.s, IF(TODAY()>=_xlpm.e,1,0), MAX(0,MIN(1,(TODAY()-_xlpm.s)/(_xlpm.e-_xlpm.s))))) ) -> 1
B47: 5.6 | C47: DC Cable delivered | E47: 45838 | F47: 0 | G47: 45838 | I47: =I23 -> 45838 | J47: 0 | K47: =WORKDAY.INTL(I47,J47,1,Data!$C$3:$C$14) -> 45838 | M47: 1 | N47: =_xlfn.LET( _xlpm.s,VALUE($I47), _xlpm.e,VALUE($K47), IF(OR(_xlpm.s="",_xlpm.e=""),"", IF(_xlpm.e<=_xlpm.s, IF(TODAY()>=_xlpm.e,1,0), MAX(0,MIN(1,(TODAY()-_xlpm.s)/(_xlpm.e-_xlpm.s))))) ) -> 1
B48: 5.7 | C48: DC Stringing | E48: 45919 | F48: 20 | G48: 45950 | I48: =I43-14 -> 45912 | J48: 24 | K48: =WORKDAY.INTL(I48,J48,1,Data!$C$3:$C$14) -> 45947 | M48: 1 | N48: =_xlfn.LET( _xlpm.s,VALUE($I48), _xlpm.e,VALUE($K48), IF(OR(_xlpm.s="",_xlpm.e=""),"", IF(_xlpm.e<=_xlpm.s, IF(TODAY()>=_xlpm.e,1,0), MAX(0,MIN(1,(TODAY()-_xlpm.s)/(_xlpm.e-_xlpm.s))))) ) -> 1
B49: 5.8 | C49: DC Ready 1 | E49: 45922 | F49: 1 | G49: 45923 | I49: 45922 | J49: 1 | K49: =WORKDAY.INTL(I49,J49,1,Data!$C$3:$C$14) -> 45923 | M49: 1 | N49: =_xlfn.LET( _xlpm.s,VALUE($I49), _xlpm.e,VALUE($K49), IF(OR(_xlpm.s="",_xlpm.e=""),"", IF(_xlpm.e<=_xlpm.s, IF(TODAY()>=_xlpm.e,1,0), MAX(0,MIN(1,(TODAY()-_xlpm.s)/(_xlpm.e-_xlpm.s))))) ) -> 1
B50: 5.9 | C50: DC Ready 2 | E50: 45950 | F50: 1 | G50: 45951 | I50: =K48 -> 45947 | J50: 1 | K50: =WORKDAY.INTL(I50,J50,1,Data!$C$3:$C$14) -> 45950 | M50: 1 | N50: =_xlfn.LET( _xlpm.s,VALUE($I50), _xlpm.e,VALUE($K50), IF(OR(_xlpm.s="",_xlpm.e=""),"", IF(_xlpm.e<=_xlpm.s, IF(TODAY()>=_xlpm.e,1,0), MAX(0,MIN(1,(TODAY()-_xlpm.s)/(_xlpm.e-_xlpm.s))))) ) -> 1
B52: 6 | C52: Commissioning | E52: 45957 | F52: 15 | G52: 45972 | I52: =MIN(I53:I63) -> 45936 | J52: =K52-I52 -> 52 | K52: =MAX(K53:K63) -> 45988 | M52: 1 | N52: 1
B53: 6.1 | C53: Comms Equipment Testing | E53: 45957 | F53: 1 | G53: 45958 | I53: =K28 -> 45945 | J53: 1 | K53: =WORKDAY.INTL(I53,J53,1,Data!$C$3:$C$14) -> 45946 | M53: 1 | N53: =_xlfn.LET( _xlpm.s,VALUE($I53), _xlpm.e,VALUE($K53), IF(OR(_xlpm.s="",_xlpm.e=""),"", IF(_xlpm.e<=_xlpm.s, IF(TODAY()>=_xlpm.e,1,0), MAX(0,MIN(1,(TODAY()-_xlpm.s)/(_xlpm.e-_xlpm.s))))) ) -> 1
B54: 6.2 | C54: Link to Client Network via Fiber | I54: 45939 | J54: 9 | K54: =WORKDAY.INTL(I54,J54,1,Data!$C$3:$C$14) -> 45952 | M54: 1 | N54: =_xlfn.LET( _xlpm.s,VALUE($I54), _xlpm.e,VALUE($K54), IF(OR(_xlpm.s="",_xlpm.e=""),"", IF(_xlpm.e<=_xlpm.s, IF(TODAY()>=_xlpm.e,1,0), MAX(0,MIN(1,(TODAY()-_xlpm.s)/(_xlpm.e-_xlpm.s))))) ) -> 1
B55: 6.3 | C55: Soft Commissioning (Energy Flowing) | I55: 45936 | J55: 11 | K55: =WORKDAY.INTL(I55,J55,1,Data!$C$3:$C$14) -> 45951 | M55: 1 | N55: =_xlfn.LET( _xlpm.s,VALUE($I55), _xlpm.e,VALUE($K55), IF(OR(_xlpm.s="",_xlpm.e=""),"", IF(_xlpm.e<=_xlpm.s, IF(TODAY()>=_xlpm.e,1,0), MAX(0,MIN(1,(TODAY()-_xlpm.s)/(_xlpm.e-_xlpm.s))))) ) -> 1
B56: 6.4 | C56: Higeco Commissioning | I56: 45952 | J56: 25 | K56: =WORKDAY.INTL(I56,J56,1,Data!$C$3:$C$14) -> 45987 | M56: 1 | N56: =_xlfn.LET( _xlpm.s,VALUE($I56), _xlpm.e,VALUE($K56), IF(OR(_xlpm.s="",_xlpm.e=""),"", IF(_xlpm.e<=_xlpm.s, IF(TODAY()>=_xlpm.e,1,0), MAX(0,MIN(1,(TODAY()-_xlpm.s)/(_xlpm.e-_xlpm.s))))) ) -> 1 | O56: Red rocket running tests this week
B57: 6.5 | C57: Techsitter Commissioning | I57: =WORKDAY.INTL(K55,0,1,Data!$C$3:$C$14)-1 -> 45950 | J57: 1 | K57: =WORKDAY.INTL(I57,J57,1,Data!$C$3:$C$14) -> 45951 | M57: 1 | N57: =_xlfn.LET( _xlpm.s,VALUE($I57), _xlpm.e,VALUE($K57), IF(OR(_xlpm.s="",_xlpm.e=""),"", IF(_xlpm.e<=_xlpm.s, IF(TODAY()>=_xlpm.e,1,0), MAX(0,MIN(1,(TODAY()-_xlpm.s)/(_xlpm.e-_xlpm.s))))) ) -> 1
B58: 6.6 | C58: Full Commissioning Monitoring | I58: =WORKDAY.INTL(K57,0,1,Data!$C$3:$C$14) -> 45951 | J58: 5 | K58: =WORKDAY.INTL(I58,J58,1,Data!$C$3:$C$14) -> 45958 | M58: 1 | N58: =_xlfn.LET( _xlpm.s,VALUE($I58), _xlpm.e,VALUE($K58), IF(OR(_xlpm.s="",_xlpm.e=""),"", IF(_xlpm.e<=_xlpm.s, IF(TODAY()>=_xlpm.e,1,0), MAX(0,MIN(1,(TODAY()-_xlpm.s)/(_xlpm.e-_xlpm.s))))) ) -> 1
B59: 6.7 | C59: Installation of IRR Sensors | I59: 45947 | J59: 1 | K59: =I59+J59 -> 45948 | M59: 1 | N59: =_xlfn.LET( _xlpm.s,VALUE($I59), _xlpm.e,VALUE($K59), IF(OR(_xlpm.s="",_xlpm.e=""),"", IF(_xlpm.e<=_xlpm.s, IF(TODAY()>=_xlpm.e,1,0), MAX(0,MIN(1,(TODAY()-_xlpm.s)/(_xlpm.e-_xlpm.s))))) ) -> 1
B60: 6.8 | C60: Tie In 2 Summation Metering | I60: 45947 | J60: 5 | K60: =I60+J60 -> 45952 | M60: 1 | N60: =_xlfn.LET( _xlpm.s,VALUE($I60), _xlpm.e,VALUE($K60), IF(OR(_xlpm.s="",_xlpm.e=""),"", IF(_xlpm.e<=_xlpm.s, IF(TODAY()>=_xlpm.e,1,0), MAX(0,MIN(1,(TODAY()-_xlpm.s)/(_xlpm.e-_xlpm.s))))) ) -> 1
B61: 6.9 | C61: Inverter Monitoring - (Tie In 2) | I61: 45951 | J61: 5 | K61: =I61+J61 -> 45956 | M61: 1 | N61: =_xlfn.LET( _xlpm.s,VALUE($I61), _xlpm.e,VALUE($K61), IF(OR(_xlpm.s="",_xlpm.e=""),"", IF(_xlpm.e<=_xlpm.s, IF(TODAY()>=_xlpm.e,1,0), MAX(0,MIN(1,(TODAY()-_xlpm.s)/(_xlpm.e-_xlpm.s))))) ) -> 1
B62: 6.10 | C62: Additional Ventilation | I62: 45957 | J62: 31 | K62: =I62+J62 -> 45988 | M62: 1 | N62: =_xlfn.LET( _xlpm.s,VALUE($I62), _xlpm.e,VALUE($K62), IF(OR(_xlpm.s="",_xlpm.e=""),"", IF(_xlpm.e<=_xlpm.s, IF(TODAY()>=_xlpm.e,1,0), MAX(0,MIN(1,(TODAY()-_xlpm.s)/(_xlpm.e-_xlpm.s))))) ) -> 1
B63: 6.11 | C63: BESS Configuration | I63: 45961 | J63: 10 | K63: =I63+J63 -> 45971 | M63: 1 | N63: =_xlfn.LET( _xlpm.s,VALUE($I63), _xlpm.e,VALUE($K63), IF(OR(_xlpm.s="",_xlpm.e=""),"", IF(_xlpm.e<=_xlpm.s, IF(TODAY()>=_xlpm.e,1,0), MAX(0,MIN(1,(TODAY()-_xlpm.s)/(_xlpm.e-_xlpm.s))))) ) -> 1
B65: 7 | C65: QA Inspections | E65: 45957 | F65: 21 | G65: 45978 | I65: =MIN(I66) -> 45959 | J65: =K65-I65 -> 1 | K65: =MAX(K66) -> 45960 | M65: =(J66*M66)/SUM(J66) -> 1 | N65: =(K66*N66)/SUM(K66) -> 1 | S65: Delay damages @ R20 600 | T65: Actual | U65: Contract
B66: 7.1 | C66: Red-Team Inspection | E66: 45957 | F66: 15 | G66: 45978 | I66: 45959 | J66: 1 | K66: =WORKDAY.INTL(I66,J66,1,Data!$C$3:$C$14) -> 45960 | M66: 1 | N66: =_xlfn.LET( _xlpm.s,VALUE($I66), _xlpm.e,VALUE($K66), IF(OR(_xlpm.s="",_xlpm.e=""),"", IF(_xlpm.e<=_xlpm.s, IF(TODAY()>=_xlpm.e,1,0), MAX(0,MIN(1,(TODAY()-_xlpm.s)/(_xlpm.e-_xlpm.s))))) ) -> 1 | S66: Commencement Date | T66: ='Revenue Tracking'!P13 -> 45849 | U66: =T66 -> 45849
B67: 7.2 | C67: Engineering Inspection | E67: 45957 | F67: 15 | G67: 45978 | I67: 45952 | J67: 1 | K67: =WORKDAY.INTL(I67,J67,1,Data!$C$3:$C$14) -> 45953 | M67: 1 | N67: =_xlfn.LET( _xlpm.s,VALUE($I67), _xlpm.e,VALUE($K67), IF(OR(_xlpm.s="",_xlpm.e=""),"", IF(_xlpm.e<=_xlpm.s, IF(TODAY()>=_xlpm.e,1,0), MAX(0,MIN(1,(TODAY()-_xlpm.s)/(_xlpm.e-_xlpm.s))))) ) -> 1 | S67: Energy flowing | T67: =K55 -> 45951 | U67: =U66+75 -> 45924
S68: Duration | T68: =T67-T66 -> 102 | U68: =U67-U66 -> 75
B69: 8 | C69: Project Closure | E69: 45972 | F69: 9 | G69: 45981 | I69: =MIN(I70:I82) -> 45953 | J69: =K69-I69 -> 43 | K69: =MAX(K70:K82) -> 45996 | M69: 1 | N69: 1 | S69: Delayed days | T69: =T68-75 -> 27
B70: 8.1 | C70: Equipment serial numbers | E70: 45978 | F70: 1 | G70: 45979 | I70: =K66 -> 45960 | J70: 1 | K70: =WORKDAY.INTL(I70,J70,1,Data!$C$3:$C$14) -> 45961 | M70: 1 | N70: 1 | S70: Penalties | T70: =T69*20600 -> 556200
B71: 8.2 | C71: Snags completion | E71: 45978 | F71: 1 | G71: 45979 | I71: 45953 | J71: 26 | K71: =WORKDAY.INTL(I71,J71,1,Data!$C$3:$C$14) -> 45989 | M71: 1 | N71: =_xlfn.LET( _xlpm.s,VALUE($I71), _xlpm.e,VALUE($K71), IF(OR(_xlpm.s="",_xlpm.e=""),"", IF(_xlpm.e<=_xlpm.s, IF(TODAY()>=_xlpm.e,1,0), MAX(0,MIN(1,(TODAY()-_xlpm.s)/(_xlpm.e-_xlpm.s))))) ) -> 1 | O71: RS485 SPDs to be installed - Happy Solar
B72: 8.3 | C72: String Updates | E72: 45972 | F72: 1 | G72: 45973 | I72: 45965 | J72: 2 | K72: =WORKDAY.INTL(I72,J72,1,Data!$C$3:$C$14) -> 45967 | M72: 1 | N72: =_xlfn.LET( _xlpm.s,VALUE($I72), _xlpm.e,VALUE($K72), IF(OR(_xlpm.s="",_xlpm.e=""),"", IF(_xlpm.e<=_xlpm.s, IF(TODAY()>=_xlpm.e,1,0), MAX(0,MIN(1,(TODAY()-_xlpm.s)/(_xlpm.e-_xlpm.s))))) ) -> 1
B73: 8.4 | C73: Exit Roof Report | I73: 45964 | J73: 1 | K73: =WORKDAY.INTL(I73,J73,1,Data!$C$3:$C$14) -> 45965 | M73: 1 | N73: =_xlfn.LET( _xlpm.s,VALUE($I73), _xlpm.e,VALUE($K73), IF(OR(_xlpm.s="",_xlpm.e=""),"", IF(_xlpm.e<=_xlpm.s, IF(TODAY()>=_xlpm.e,1,0), MAX(0,MIN(1,(TODAY()-_xlpm.s)/(_xlpm.e-_xlpm.s))))) ) -> 1
B74: 8.5 | C74: As Built Drawings | I74: 45961 | J74: 8 | K74: =WORKDAY.INTL(I74,J74,1,Data!$C$3:$C$14) -> 45973 | M74: 1 | N74: =_xlfn.LET( _xlpm.s,VALUE($I74), _xlpm.e,VALUE($K74), IF(OR(_xlpm.s="",_xlpm.e=""),"", IF(_xlpm.e<=_xlpm.s, IF(TODAY()>=_xlpm.e,1,0), MAX(0,MIN(1,(TODAY()-_xlpm.s)/(_xlpm.e-_xlpm.s))))) ) -> 1
C75: SSEG SLD | I75: 45966 | J75: 10 | K75: =WORKDAY.INTL(I75,J75,1,Data!$C$3:$C$14) -> 45980 | M75: 1 | N75: =_xlfn.LET( _xlpm.s,VALUE($I75), _xlpm.e,VALUE($K75), IF(OR(_xlpm.s="",_xlpm.e=""),"", IF(_xlpm.e<=_xlpm.s, IF(TODAY()>=_xlpm.e,1,0), MAX(0,MIN(1,(TODAY()-_xlpm.s)/(_xlpm.e-_xlpm.s))))) ) -> 1
B76: 8.6 | C76: Commissioning Form | I76: 45961 | J76: 12 | K76: =WORKDAY.INTL(I76,J76,1,Data!$C$3:$C$14) -> 45979 | M76: 1 | N76: =_xlfn.LET( _xlpm.s,VALUE($I76), _xlpm.e,VALUE($K76), IF(OR(_xlpm.s="",_xlpm.e=""),"", IF(_xlpm.e<=_xlpm.s, IF(TODAY()>=_xlpm.e,1,0), MAX(0,MIN(1,(TODAY()-_xlpm.s)/(_xlpm.e-_xlpm.s))))) ) -> 1
B77: 8.7 | C77: Techsitter Targets & Validate Targets | I77: 45961 | J77: 18 | K77: =WORKDAY.INTL(I77,J77,1,Data!$C$3:$C$14) -> 45987 | M77: 1 | N77: =_xlfn.LET( _xlpm.s,VALUE($I77), _xlpm.e,VALUE($K77), IF(OR(_xlpm.s="",_xlpm.e=""),"", IF(_xlpm.e<=_xlpm.s, IF(TODAY()>=_xlpm.e,1,0), MAX(0,MIN(1,(TODAY()-_xlpm.s)/(_xlpm.e-_xlpm.s))))) ) -> 1
B78: 8.8 | C78: PrEng Signoff | I78: 45966 | J78: 2 | K78: =WORKDAY.INTL(I78,J78,1,Data!$C$3:$C$14) -> 45968 | M78: 1 | N78: =_xlfn.LET( _xlpm.s,VALUE($I78), _xlpm.e,VALUE($K78), IF(OR(_xlpm.s="",_xlpm.e=""),"", IF(_xlpm.e<=_xlpm.s, IF(TODAY()>=_xlpm.e,1,0), MAX(0,MIN(1,(TODAY()-_xlpm.s)/(_xlpm.e-_xlpm.s))))) ) -> 1
B79: 8.9 | C79: Fritz HSE incident | I79: 45966 | J79: 1 | K79: =WORKDAY.INTL(I79,J79,1,Data!$C$3:$C$14) -> 45967 | M79: 1 | N79: =_xlfn.LET( _xlpm.s,VALUE($I79), _xlpm.e,VALUE($K79), IF(OR(_xlpm.s="",_xlpm.e=""),"", IF(_xlpm.e<=_xlpm.s, IF(TODAY()>=_xlpm.e,1,0), MAX(0,MIN(1,(TODAY()-_xlpm.s)/(_xlpm.e-_xlpm.s))))) ) -> 1
B80: 8.10 | C80: Handover documentation | E80: 45979 | F80: 1 | G80: 45980 | I80: 45953 | J80: 25 | K80: =WORKDAY.INTL(I80,J80,1,Data!$C$3:$C$14) -> 45988 | M80: 1 | N80: =_xlfn.LET( _xlpm.s,VALUE($I80), _xlpm.e,VALUE($K80), IF(OR(_xlpm.s="",_xlpm.e=""),"", IF(_xlpm.e<=_xlpm.s, IF(TODAY()>=_xlpm.e,1,0), MAX(0,MIN(1,(TODAY()-_xlpm.s)/(_xlpm.e-_xlpm.s))))) ) -> 1
B81: 8.11 | C81: Handover to Client | E81: 45980 | F81: 1 | G81: 45981 | I81: 45995 | J81: 1 | K81: =WORKDAY.INTL(I81,J81,1,Data!$C$3:$C$14) -> 45996 | M81: 1 | N81: =_xlfn.LET( _xlpm.s,VALUE($I81), _xlpm.e,VALUE($K81), IF(OR(_xlpm.s="",_xlpm.e=""),"", IF(_xlpm.e<=_xlpm.s, IF(TODAY()>=_xlpm.e,1,0), MAX(0,MIN(1,(TODAY()-_xlpm.s)/(_xlpm.e-_xlpm.s))))) ) -> 1
B82: 8.12 | C82: Handover to Matriarch | E82: 45980 | F82: 1 | G82: 45981 | I82: 45978 | J82: 11 | K82: =WORKDAY.INTL(I82,J82,1,Data!$C$3:$C$14) -> 45993 | M82: 1 | N82: =_xlfn.LET( _xlpm.s,VALUE($I82), _xlpm.e,VALUE($K82), IF(OR(_xlpm.s="",_xlpm.e=""),"", IF(_xlpm.e<=_xlpm.s, IF(TODAY()>=_xlpm.e,1,0), MAX(0,MIN(1,(TODAY()-_xlpm.s)/(_xlpm.e-_xlpm.s))))) ) -> 1

Sheet Data
C2: Public holidays | F2: Drop down list
C3: 45658 | D3: New Years Day | F3: Approved
C4: 45737 | D4: Human Rights day | F4: Pending
C5: 45765 | D5: Good Friday | F5: Declined
C6: 45768 | D6: Family Day | F6: Abanded
C7: 45774 | D7: Freedom Day
C8: 45765 | D8: Freedom DayObserved
C9: 45778 | D9: Workers day
C10: 45824 | D10: Youth Day Holiday
C11: 45878 | D11: Womens Day
C12: 45924 | D12: Heritage Day
C13: 46007 | D13: Day of Reconciliation | H13: Manual dates
C14: 46016 | D14: Christmas Day
C15: 46017 | D15: Day of Goodwill

Sheet Expenditure Tracking
B2: HIGH LEVEL PROJECT EXPENDITURE TRACKING
F4: COSTED | H4: ACTUAL | J4: Difference from costed
B5: EXPENDITURE | F5: =SUM(F9:F23) -> 10416340 | H5: =SUM(H9:H23) -> 8238201.1 | J5: =SUM(J9:J23) -> 2178138.7
B7: No. | D7: Item | F7: Costed Expenditure | H7: Actual Expenditure | J7: Saving / Overrun | L7: Comments on variations from planned expenditure
B9: ='Expenditure Breakdown'!L6 -> 1 | D9: ='Expenditure Breakdown'!M6 -> 1. Panels | F9: ='Expenditure Breakdown'!I6 -> 1788541.4 | H9: ='Expenditure Breakdown'!X6 -> 1263945.2 | J9: =F9-H9 -> 524596.17
B10: ='Expenditure Breakdown'!L14 -> 2 | D10: ='Expenditure Breakdown'!M14 -> 2. Inverters | F10: ='Expenditure Breakdown'!I14 -> 356200 | H10: ='Expenditure Breakdown'!X14 -> 316436.04 | J10: =F10-H10 -> 39763.96
B11: ='Expenditure Breakdown'!L22 -> 3 | D11: ='Expenditure Breakdown'!M22 -> 3. Mounting Structures | F11: ='Expenditure Breakdown'!I22 -> 1186680 | H11: ='Expenditure Breakdown'!X22 -> 887538.46 | J11: =F11-H11 -> 299141.54
B12: ='Expenditure Breakdown'!L32 -> 4 | D12: ='Expenditure Breakdown'!M32 -> 4. DC Equipment | F12: ='Expenditure Breakdown'!I32 -> 1208947.5 | H12: ='Expenditure Breakdown'!X32 -> 371619.98 | J12: =F12-H12 -> 837327.52
B13: ='Expenditure Breakdown'!L49 -> 5 | D13: ='Expenditure Breakdown'!M49 -> 5. Monitoring | F13: ='Expenditure Breakdown'!I49 -> 45636 | H13: ='Expenditure Breakdown'!X49 -> 200056.25 | J13: =F13-H13 -> -154420.25
B14: ='Expenditure Breakdown'!L86 -> 6 | D14: ='Expenditure Breakdown'!M86 -> 6. AC Equipment | F14: ='Expenditure Breakdown'!I86 -> 849891.5 | H14: ='Expenditure Breakdown'!X86 -> 1071907.2 | J14: =F14-H14 -> -222015.73
B15: ='Expenditure Breakdown'!L104 -> 7 | D15: ='Expenditure Breakdown'!M104 -> 7.BESS | F15: ='Expenditure Breakdown'!I104 -> 3616080.6 | H15: ='Expenditure Breakdown'!X104 -> 2378460 | J15: =F15-H15 -> 1237620.6
B16: ='Expenditure Breakdown'!L113 -> 8 | D16: ='Expenditure Breakdown'!M113 -> 8. Product Add On | F16: ='Expenditure Breakdown'!I113 -> 145000 | H16: ='Expenditure Breakdown'!X113 -> 256749.19 | J16: =F16-H16 -> -111749.19
B17: ='Expenditure Breakdown'!L137 -> 9 | D17: ='Expenditure Breakdown'!M137 -> 9. AC & DC installation | F17: ='Expenditure Breakdown'!I137 -> 687500 | H17: ='Expenditure Breakdown'!X137 -> 900817.81 | J17: =F17-H17 -> -213317.81
B18: ='Expenditure Breakdown'!L150 -> 10 | D18: ='Expenditure Breakdown'!M150 -> 10. Site Logistics | F18: ='Expenditure Breakdown'!I150 -> 8500 | H18: ='Expenditure Breakdown'!X150 -> 216404.8 | J18: =F18-H18 -> -207904.8
B19: ='Expenditure Breakdown'!L177 -> 11 | D19: ='Expenditure Breakdown'!M177 -> 11. Due Dilligence | F19: ='Expenditure Breakdown'!I177 -> 77050 | H19: ='Expenditure Breakdown'!X177 -> 52000 | J19: =F19-H19 -> 25050
B20: ='Expenditure Breakdown'!L183 -> 12 | D20: ='Expenditure Breakdown'!M183 -> 12. BDP Commission | F20: ='Expenditure Breakdown'!I183 -> 0 | H20: ='Expenditure Breakdown'!X183 -> 0 | J20: =F20-H20 -> 0
B21: ='Expenditure Breakdown'!L186 -> 13 | D21: ='Expenditure Breakdown'!M187 -> 13. Engineering | F21: ='Expenditure Breakdown'!I186 -> 434412.84 | H21: ='Expenditure Breakdown'!X186 -> 154022.95 | J21: =F21-H21 -> 280389.89
B22: ='Expenditure Breakdown'!L193 -> 14 | D22: ='Expenditure Breakdown'!M193 -> 14. General Expenses | F22: ='Expenditure Breakdown'!I193 -> 11900 | H22: ='Expenditure Breakdown'!X193 -> 8514.52 | J22: =F22-H22 -> 3385.48
B23: ='Expenditure Breakdown'!L206 -> 15 | D23: ='Expenditure Breakdown'!M206 -> 15. Service Add On | F23: ='Expenditure Breakdown'!I206 -> 0 | H23: ='Expenditure Breakdown'!X206 -> 159728.68 | J23: =F23-H23 -> -159728.68
D25: check: | F25: ='Expenditure Breakdown'!I2-'Expenditure Tracking'!F5 -> 0 | G25: =#REF!-G5 -> #REF! | H25: ='Expenditure Breakdown'!X2-H5 -> 0

Sheet Expenditure Breakdown
B2: COSTED EXPENDITURE BREAKDOWN | I2: =SUM(I6:I218) -> 10416340 | J2: =SUM(J6:J218) -> 12364058 | L2: ACTUAL EXPENDITURE BREAKDOWN | R2: FINANCE ONLY | X2: =SUM(X6:X218) -> 8238201.1
B4: No. | C4: Product / Service | D4: Description of Work | E4: QTY | F4: Rate / Unit | G4: Budget Total | H4: FINANCE PAYMENT DATE | I4: Total COS | J4: =IF(J2-'Revenue Tracking'!D4>=0, "Total Revenue", "ERROR on REV" ) -> ERROR on REV | L4: No. | M4: Product/ Service | N4: Description of Work | O4: QTY | P4: Rate / Unit | Q4: Actual Total | R4: PO NUMBER | S4: INVOICE NUMBER | T4: INVOICE RAISED DATE | U4: REVENUE RECOGNITION AMOUNT | V4: CHECK | W4: FINANCE PAYMENT DATE | X4: Total COS
B6: 1 | C6: Panels | D6: Panels Budget | G6: =D219 -> 1788541.4 | H6: 45898 | I6: =SUM(G6:G12) -> 1788541.4 | J6: =F219 -> 2235676.7 | L6: 1 | M6: 1. Panels | N6: JA 615W | O6: ='Project Plan'!$E$3*1000/615 -> 1108.9431 | P6: 1156.4 | Q6: 1282447.6 | S6: Menlo INV0003051 | T6: 45838 | U6: 2235676.7 | V6: =J6-SUM(U6:U12) -> 42222.164 | W6: 45901 | X6: =SUM(Q6:Q12) -> 1263945.2
B7: 1 | D7: Delivery Budget | L7: 1 | M7: 1. Panels | P7: =P6/615 -> 1.8803252 | T7: =IF(W7>1,EOMONTH(W7,0),"") | U7: 0
B8: 1 | L8: 1 | M8: 1. Panels | T8: =IF(W8>1,EOMONTH(W8,0),"") | U8: 0
B9: 1 | F9: =J6/682/1000 -> 3.2781183 | L9: 1 | M9: 1. Panels | N9: Panels moved to Stock | O9: -16 | P9: 1156.4 | Q9: =O9*P9 -> -18502.4 | S9: Allocated to Cpt Storeroom | T9: 45991 | U9: 0 | W9: 45991
B10: 1 | L10: 1 | M10: 1. Panels | N10: X4 Broken panels | P10: 1156.4 | Q10: =O10*P10 -> 0 | S10: Dont add as a credit | T10: 45991 | U10: 0 | W10: 45991
L11: 1 | M11: 1. Panels | N11: Reduction in Size | T11: 46053 | U11: -42222.164 | W11: 46053
B12: 1 | L12: 1 | M12: 1. Panels | T12: =IF(W12>1,EOMONTH(W12,0),"") | U12: 0 | Y12: BUDGET | Z12: Installer Allocation
T13: =IF(W13>1,EOMONTH(W13,0),"") | Y13: AC Equipment | Z13: =G86 -> 849891.5
B14: 2 | C14: Inverters | D14: Inverter Budget | G14: =D220 -> 356200 | H14: 45867 | I14: =SUM(G14:G20) -> 356200 | J14: =F220 -> 445250 | L14: 2 | M14: 2. Inverters | N14: Sungrow SG125CX | O14: 4 | P14: 69140 | Q14: =O14*P14 -> 276560 | R14: PO4037-RR-20250626 - RV Approved | S14: Herholdts INV1088936 | T14: 45838 | U14: 389826.33 | V14: =J14-SUM(U14:U20) -> 0 | W14: 45867 | X14: =SUM(Q14:Q20) -> 316436.04 | Y14: DC Equipment | Z14: =G33 -> 724197.5
B15: 2 | H15: 45867 | L15: 2 | M15: 2. Inverters | N15: Sungrow SG50CX | O15: 1 | P15: 39320 | Q15: =O15*P15 -> 39320 | S15: Herholdts INV1088936 | T15: 45838 | U15: 55423.674 | W15: 45867 | Y15: AC Labour | Z15: =G137 -> 341000
B16: 2 | L16: 2 | M16: 2. Inverters | N16: Sungrow SG125CX | O16: 1 | Q16: 68050 | S16: Herholdts -INV1165658 | T16: 45961 | U16: 0 | W16: 45989 | Y16: DC Labour | Z16: =G138 -> 346500
B17: 2 | L17: 2 | M17: 2. Inverters | N17: Sungrow SG125CX - RMA | Q17: -69140 | R17: RMA | S17: Herholdts - CN130769 | T17: 46053 | U17: 0 | W17: 46053 | Y17: Offloading | Z17: =G150 -> 8500
B18: 2 | L18: 2 | M18: 2. Inverters | N18: courier of RMA | Q18: 1646.04 | S18: DSV Inv: 180155155 | T18: 45991 | U18: 0 | W18: 46021 | Y18: BESS Installation | Z18: 375000
B19: 2 | L19: 2 | M19: 2. Inverters | T19: =IF(W19>1,EOMONTH(W19,0),"") | U19: 0 | Y19: Inverter Room Upgrades | Z19: 50000
B20: 2 | L20: 2 | M20: 2. Inverters | T20: =IF(W20>1,EOMONTH(W20,0),"") | U20: 0 | Y20: Telehandler | Z20: 0
T21: =IF(W21>1,EOMONTH(W21,0),"")
B22: 3 | C22: Mounting Structures | D22: Structure Budget | G22: =D221 -> 1186680 | H22: 45867 | I22: =SUM(G22:G30) -> 1186680 | J22: =F221 -> 1483350 | L22: 3 | M22: 3. Mounting Structures | N22: Schletter Structure | Q22: 344822.96 | R22: PO4033-RR-20250626 - RV Approved | S22: Schletter INV1906 | T22: 45838 | U22: 431028.7 | V22: =J22-SUM(U22:U30) -> -0.0038501022 | W22: 45867 | X22: =SUM(Q22:Q30) -> 887538.46 | Y22: Other | Z22: 0
B23: 3 | L23: 3 | M23: 3. Mounting Structures | N23: Lintels send back to Lintel for Africa | O23: -120 | P23: 119.75 | Q23: =-16638.3-67.16 -> -16705.46 | S23: Lintels Credit Note - CR2256 | T23: 45991 | U23: 0 | W23: 45991 | Y23: Total | Z23: =SUM(Z13:Z22) -> 2695089
L24: 3. | M24: 3. Mounting Structures | N24: Collection of Lintels | Q24: 1436.9 | S24: Lintels Credit Note - CR2256 | T24: 45991 | U24: 0 | W24: 45991
L25: 3. | M25: 3. Mounting Structures | N25: 1.2m Custom Rails - returned to stock | O25: -55 | P25: 78.4 | T25: 46022 | U25: 0 | W25: 46022
L26: 3. | M26: 3. Mounting Structures | N26: Surface Protection Mats | O26: -65 | P26: 31.54 | Q26: =O26*P26 -> -2050.1 | R26: To be allocated to 7th Avenue | S26: Allocated to 7th Avenue | T26: 46053 | U26: 0 | W26: 46053
H27: 45869 | L27: 3 | M27: 3. Mounting Structures | N27: Lintels | Q27: 278899.16 | R27: PO4164-RR-20250725 - RV Approved | S27: Lintels - 232597 | T27: 45869 | U27: 525027.77 | W27: 45869
B28: 3 | H28: 45899 | L28: 3 | M28: 3. Mounting Structures | N28: Rail Length | Q28: 280280 | R28: PO4033-RR-20250626 - RV Approved | S28: Schletter INV1976 | T28: 45869 | U28: 527293.56 | W28: 45899 | Y28: R/Wp | Z28: =#REF!/'Project Plan'!$E$3/1000 -> #REF!
B29: 3 | H29: =E29+30 -> 30 | L29: 3 | M29: 3. Mounting Structures | N29: End Clamps | Q29: 650 | R29: PO4360-RR-20251009 - RV Approved | S29: Solarworld - Inv SASIV-25-00568 | T29: 45961 | U29: -0.02 | W29: 45974
B30: 3 | L30: 3 | M30: 3. Mounting Structures | N30: Delivery of Clamps | Q30: 205 | S30: Uber Deilvery | T30: 45961 | U30: 0 | W30: 45940 | Y30: ACTUAL - JA Electrical | Z30: Installer Price
T31: =IF(W31>1,EOMONTH(W31,0),"") | Y31: =Y13 -> AC Equipment | Z31: 1058756.2
B32: 4 | C32: DC Equipment | D32: DC Cable Budget | E32: =G32/14*1.15 -> 39818.75 | G32: 484750 | H32: =E32+30 -> 39848.75 | I32: =SUM(G32:G47) -> 1208947.5 | J32: =F222 -> 1511184.4 | L32: 4 | M32: 4. DC Equipment | N32: DC Cable | O32: 40000 | P32: 13.5 | Q32: =O32*P32 -> 540000 | R32: PO4126-RR-20250716 - RV Approved | S32: Rubicon INVWCRE-00069640 | T32: 45869 | U32: 1491518.5 | V32: =J32-SUM(U32:U47) -> 0 | W32: =T32+30 -> 45899 | X32: =SUM(Q32:Q47) -> 371619.98 | Y32: =Y14 -> DC Equipment | Z32: 223119.98
B33: 4 | D33: DC Equipment Budget | G33: =D222-G32 -> 724197.5 | H33: 45869 | L33: 4 | M33: 4. DC Equipment | N33: Move to Stock | O33: -16000 | P33: 13.5 | Q33: =O33*P33 -> -216000 | S33: Allocated to Stock | T33: 45869 | U33: -596607.39 | W33: 45869 | Y33: =Y15 -> AC Labour | Z33: 237440.63
B34: 4 | L34: 4 | M34: 4. DC Equipment | N34: DC Cable - black | O34: -6000 | P34: 13.5 | Q34: =O34*P34 -> -81000 | S34: Allocated to Stock | T34: 45961 | U34: 0 | W34: 45961 | Y34: =Y16 -> DC Labour | Z34: 663377.18 | AA34: =Z34/682000 -> 0.97269381 | AB34: =AA34*'Revenue Tracking'!N27 -> 12528.296
B35: 4 | L35: 4 | M35: 4. DC Equipment | N35: DC Cable - Red | O35: -7000 | P35: 13.5 | Q35: =O35*P35 -> -94500 | S35: Allocated to Stock | T35: 45961 | U35: 0 | W35: 45961 | Y35: =Y17 -> Offloading | Z35: 51940
L36: 4 | M36: 4. DC Equipment
B37: 4 | H37: =H138 -> 45897 | L37: 4 | M37: 4. DC Equipment | N37: Project Kick Off | O37: =Z32 -> 223119.98 | P37: 0.1 | Q37: =$O$37*P37 -> 22311.998 | S37: JA Electrical Inv 1083 | T37: =T138 -> 45900 | U37: 61627.329 | W37: =W138 -> 45883 | Y37: =Y18 -> BESS Installation | Z37: 110262
B38: 4 | H38: =H139 -> 45898 | L38: 4 | M38: 4. DC Equipment | N38: Site Establishment | P38: 0.15 | Q38: =$O$37*P38 -> 33467.997 | S38: JA Electrical Inv 1083 | T38: =T139 -> 45900 | U38: 92440.993 | W38: =W139 -> 45898 | Y38: =Y19 -> Inverter Room Upgrades | Z38: 7284.8
B39: 4 | H39: =H140 -> #REF! | L39: 4 | M39: 4. DC Equipment | N39: AC Installation Complete | P39: 0.2 | Q39: =$O$37*P39 -> 44623.996 | S39: JA Electrical Inv 1083 | T39: 45900 | U39: 123254.66 | W39: =W140 -> 45946 | Y39: Ablutions | Z39: 15620
B40: 4 | H40: =H141 -> #REF! | L40: 4 | M40: 4. DC Equipment | N40: DC Installation Complete | P40: 0.25 | Q40: =$O$37*P40 -> 55779.995 | S40: JA Electrical Inv 1083 | T40: 45900 | U40: 154068.32 | W40: =W141 -> 45946 | Y40: Return of excess material | Z40: 6583
B41: 4 | H41: =H142 -> #REF! | L41: 4 | M41: 4. DC Equipment | N41: Commissioning Complete | P41: 0.1 | Q41: =$O$37*P41 -> 22311.998 | S41: JA Electrical Inv 1083 | T41: 45900 | U41: 61627.329 | W41: =W142 -> 45989 | Y41: Waste Skip | Z41: 15855
B42: 4 | H42: =H143 -> #REF! | L42: 4 | M42: 4. DC Equipment | N42: Site De-establisment | P42: 0.1 | Q42: =$O$37*P42 -> 22311.998 | S42: JA Electrical Inv 1083 | T42: 45900 | U42: 61627.329 | W42: =W143 -> 45996 | Y42: Other | Z42: 0
B43: 4 | H43: =H144 -> #REF! | L43: 4 | M43: 4. DC Equipment | N43: Handover Document Complete | P43: 0.05 | Q43: =$O$37*P43 -> 11155.999 | S43: JA Electrical Inv 1083 | T43: 45900 | U43: 30813.664 | W43: =W144 -> 45996 | Y43: Total | Z43: =SUM(Z31:Z42) -> 2390238.8
B44: 4 | H44: =H145 -> #REF! | L44: 4 | M44: 4. DC Equipment | N44: End of Defects Period | P44: 0.05 | Q44: =$O$37*P44 -> 11155.999 | S44: JA Electrical Inv 1083 | T44: 45900 | U44: 30813.664 | W44: =W145 -> 46015 | Y44: R/Wp | Z44: =Z43/'Project Plan'!$E$3/1000 -> 3.504749
B45: 4 | L45: 4 | M45: 4. DC Equipment | T45: =IF(W45>1,EOMONTH(W45,0),"") | U45: =(Q45/$X$32*$J$32) -> 0
B46: 4 | L46: 4 | M46: 4. DC Equipment | T46: =IF(W46>1,EOMONTH(W46,0),"") | U46: =(Q46/$X$32*$J$32) -> 0
B47: 4 | L47: 4 | M47: 4. DC Equipment | T47: =IF(W47>1,EOMONTH(W47,0),"") | U47: =(Q47/$X$32*$J$32) -> 0
T48: =IF(W48>1,EOMONTH(W48,0),"")
B49: 5 | C49: Monitoring | D49: Monitoring Budget | G49: =D224-G50 -> 30636 | H49: 45866 | I49: =SUM(G49:G84) -> 45636 | J49: =F224 -> 57045 | L49: 5 | M49: 5. Monitoring | U49: =(Q49/$X$49*$J$49) -> 0 | V49: =J49-SUM(U49:U84) -> 0.0022189795 | X49: =SUM(Q49:Q84) -> 200056.25
B50: 5 | D50: Revenue Metering | G50: 15000 | H50: 45867 | L50: 5 | M50: 5. Monitoring | N50: CTs & Meters | Q50: 17131.5 | R50: PO4062-RR-20250630 - RV Approved | S50: AccuEnergy ASAI-005841 | T50: 45838 | U50: 17332.951 | W50: 45867
H51: 45930 | L51: 5 | M51: 5. Monitoring | N51: AcuRev 1313 RCT-XO - Return to stock | O51: 1 | P51: 2970 | Q51: =O51*P51*-1 -> -2970 | S51: Allocated to Cpt Stockroom | T51: 45930 | U51: 0 | W51: 45930
H52: 45930 | L52: 5 | M52: 5. Monitoring | N52: AcuCT3147-1000:5 - Return to stock | O52: 3 | P52: 1260 | Q52: =O52*P52*-1 -> -3780 | S52: Allocated to Cpt Stockroom | T52: 45930 | U52: 0 | W52: 45930
L53: 5 | M53: 5. Monitoring | N53: AcuCT3147-1000:5 - Return to stock | O53: -3 | P53: 1260 | Q53: =O53*P53 -> -3780 | S53: Allocated to Cpt Stockroom | T53: 45991 | U53: 0 | W53: 45991
B54: 5 | H54: 45869 | L54: 5 | M54: 5. Monitoring | N54: Techsitter - (Which Tie In) | Q54: 11169 | S54: Matriarch - INV-4742 | T54: 45869 | U54: 1489.3546 | W54: 45869
H55: =E55+30 -> 30 | L55: 5 | M55: 5. Monitoring | N55: Techsitter - (Which Tie In) | Q55: 11169 | S55: Matriarch - INV-5207 | T55: 45961 | U55: 3098.8521 | W55: 45974
L56: 5 | M56: 5. Monitoring | N56: Delivery of Techsitter | Q56: 206.91 | S56: DSV Inv: 180150385 | T56: 45961 | U56: 34.86 | W56: =T56+30 -> 45991
B57: 5 | H57: 45876 | L57: 5 | M57: 5. Monitoring | N57: UPS | Q57: 2250.5 | R57: PO4071-RR-20250630 - RV Approved | S57: Frontline QTE107315 | T57: 45869 | U57: 300.09781 | W57: 45876
B58: 5 | L58: 5 | M58: 5. Monitoring | N58: Higeco | Q58: 0 | U58: =(Q58/$X$49*$J$49) -> 0
H59: =E59+30 -> 30 | L59: 5 | M59: 5. Monitoring | N59: CT equipement as below | Q59: 25703 | R59: PO4219-RR-20250813 - RV Approved | S59: AccuEnergy ASAI-006148 | T59: 45900 | U59: 5254.2227 | W59: =T59+30 -> 45930
L60: 5 | M60: 5. Monitoring | N60: Intergator kit - RIK 5A | O60: 1 | U60: =(Q60/$X$49*$J$49) -> 0
L61: 5 | M61: 5. Monitoring | N61: SumCT 5A/5+5 | O61: 3 | U61: =(Q61/$X$49*$J$49) -> 0
L62: 5 | M62: 5. Monitoring | N62: CT - 2000A/5A CL 0.5 (Grid Meter) | O62: 6 | U62: =(Q62/$X$49*$J$49) -> 0
L63: 5 | M63: 5. Monitoring | N63: CT - 600A/5A CL 0.5 (Techsitter) | O63: 6 | U63: =(Q63/$X$49*$J$49) -> 0
H64: =E64+30 -> 30 | L64: 5 | M64: 5. Monitoring | N64: Switch and PSU | Q64: 1644.5 | R64: PO4226-RR-20250818 - RV Approved | S64: Accuenergy - ASAI-006183 | T64: 45900 | U64: 336.16968 | W64: =T64+30 -> 45930
H65: 45900 | L65: 5 | M65: 5. Monitoring | N65: Switch and PSU | Q65: -940.5 | S65: Accuenergy - CN-00227 | T65: 45900 | U65: -192.25758 | W65: 45900
H66: 45930 | L66: 5 | M66: 5. Monitoring | N66: Delivery | Q66: 200 | S66: Accuenergy - ASAI-006213 | T66: 45900 | U66: 0 | W66: 45930
H67: =E67+30 -> 30 | L67: 5 | M67: 5. Monitoring | N67: Sungrow COM100 | O67: 2 | Q67: 21200 | R67: PO4221-RR-20250813 - RV Approved | S67: Herholdts - INV1120131 | T67: 45900 | U67: 4333.7168 | W67: =T67+30 -> 45930
H68: =E68+30 -> 30 | L68: 5 | M68: 5. Monitoring | N68: Sungrow DTSD1352 | O68: 2 | Q68: 9040 | S68: Herholdts - INV1120131 | T68: 45900 | U68: 1847.9622 | W68: =T68+30 -> 45930
L69: 5 | M69: 5. Monitoring | U69: =(Q69/$X$49*$J$49) -> 0
L70: 5 | M70: 5. Monitoring | U70: =(Q70/$X$49*$J$49) -> 0
B71: 5 | H71: =E71+30 -> 30 | L71: 5 | M71: 5. Monitoring | N71: Irradiance sensors | O71: 3 | Q71: 28431.28 | R71: RV Approved | S71: IBC Solar - ZA42502457 | T71: 45961 | U71: 7888.2918 | W71: 45947
L72: 5 | M72: 5. Monitoring | U72: 0
H73: =E73 -> 0 | L73: 5 | M73: 5. Monitoring | N73: Optic Fiber | Q73: =81130.56-Q74 -> 52911.24 | R73: PO4359-RR-20251007 - RV Approved | S73: WM Cabling - INV0001211 | T73: 45961 | U73: 6376.4952 | W73: =T73 -> 45961
L74: 5 | M74: 5. Monitoring | Q74: 28219.32 | S74: WM Cabling - INV0001211 | T74: 45961 | U74: 7829.4832 | W74: 45939
L75: 5 | M75: 5. Monitoring | U75: 0
L76: 5 | M76: 5. Monitoring | N76: 8 Port Switch | Q76: 1767.5 | R76: PO4360-RR-20251014 - RV Approved | S76: Accuenergy: ASAI-006611 | T76: 45961 | U76: 490.39493 | W76: =T76+30 -> 45991
L77: 5 | M77: 5. Monitoring | N77: 8 Port Switch | Q77: -1767.5 | S77: Allocated to riverside Mall | T77: 46053 | U77: 0 | W77: 46053
L78: 5 | M78: 5. Monitoring | N78: Second Tie In UPS | Q78: 2250.5 | R78: PO4367-RR-20251014 - RV Approved | S78: Frontline INV746387 | T78: 45961 | U78: 624.40385 | W78: 45961
L79: 5 | M79: 5. Monitoring | U79: =(Q79/$X$49*$J$49) -> 0
L80: 5 | M80: 5. Monitoring | U80: =(Q80/$X$49*$J$49) -> 0
L81: 5 | M81: 5. Monitoring | U81: =(Q81/$X$49*$J$49) -> 0
L82: 5 | M82: 5. Monitoring | U82: =(Q82/$X$49*$J$49) -> 0
L83: 5 | M83: 5. Monitoring | U83: =(Q83/$X$49*$J$49) -> 0
B84: 5 | L84: 5 | M84: 5. Monitoring | T84: =IF(W84>1,EOMONTH(W84,0),"") | U84: =(Q84/$X$49*$J$49) -> 0
T85: =IF(W85>1,EOMONTH(W85,0),"")
B86: 6 | C86: AC Equipment | D86: AC Equipment Budget | G86: =D223 -> 849891.5 | H86: 45900 | I86: =SUM(G86:G102) -> 849891.5 | J86: =F223 -> 1062364.4 | L86: 6 | M86: 6. AC Equipment | T86: =IF(W86>1,EOMONTH(W86,0),"") | U86: =(Q86/$X$86*$J$86) -> 0 | V86: =J86-SUM(U86:U102) -> 0 | X86: =SUM(Q86:Q102) -> 1071907.2
B87: 6 | L87: 6 | M87: 6. AC Equipment | N87: QC4 Connectors | Q87: 13151 | S87: Menlo Inv: INV0003305 + INV0003343 | T87: 45961 | U87: 0 | W87: 46009
B88: 6 | L88: 6 | M88: 6. AC Equipment | T88: =IF(W88>1,EOMONTH(W88,0),"") | U88: =(Q88/$X$86*$J$86) -> 0
B89: 6 | L89: 6 | M89: 6. AC Equipment | T89: =IF(W89>1,EOMONTH(W89,0),"") | U89: =(Q89/$X$86*$J$86) -> 0
B90: 6 | L90: 6 | M90: 6. AC Equipment | N90: Move old breakers to stock | T90: =IF(W90>1,EOMONTH(W90,0),"") | U90: =(Q90/$X$86*$J$86) -> 0
B91: 6 | L91: 6 | M91: 6. AC Equipment | T91: =IF(W91>1,EOMONTH(W91,0),"") | U91: =(Q91/$X$86*$J$86) -> 0
B92: 6 | H92: =H138 -> 45897 | L92: 6 | M92: 6. AC Equipment | N92: Project Kick Off | O92: =Z31 -> 1058756.2 | P92: 0.1 | Q92: =$O$92*P92 -> 105875.62 | S92: JA Electrical Inv 1083 | T92: 45900 | U92: 106236.44 | W92: =W138 -> 45883
B93: 6 | H93: =H139 -> 45898 | L93: 6 | M93: 6. AC Equipment | N93: Site Establishment | P93: 0.15 | Q93: =$O$92*P93 -> 158813.43 | S93: JA Electrical Inv 1083 | T93: 45900 | U93: 159354.66 | W93: =W139 -> 45898
B94: 6 | H94: =H140 -> #REF! | L94: 6 | M94: 6. AC Equipment | N94: AC Installation Complete | P94: 0.2 | Q94: =$O$92*P94 -> 211751.25 | S94: JA Electrical Inv 1083 | T94: 45900 | U94: 212472.88 | W94: =W140 -> 45946
B95: 6 | H95: =H141 -> #REF! | L95: 6 | M95: 6. AC Equipment | N95: DC Installation Complete | P95: 0.25 | Q95: =$O$92*P95 -> 264689.06 | S95: JA Electrical Inv 1083 | T95: 45900 | U95: 265591.09 | W95: =W141 -> 45946
B96: 6 | H96: =H142 -> #REF! | L96: 6 | M96: 6. AC Equipment | N96: Commissioning Complete | P96: 0.1 | Q96: =$O$92*P96 -> 105875.62 | S96: JA Electrical Inv 1083 | T96: 45900 | U96: 106236.44 | W96: =W142 -> 45989
B97: 6 | H97: =H143 -> #REF! | L97: 6 | M97: 6. AC Equipment | N97: Site De-establisment | P97: 0.1 | Q97: =$O$92*P97 -> 105875.62 | S97: JA Electrical Inv 1083 | T97: 45900 | U97: 106236.44 | W97: =W143 -> 45996
B98: 6 | H98: =H144 -> #REF! | L98: 6 | M98: 6. AC Equipment | N98: Handover Document Complete | P98: 0.05 | Q98: =$O$92*P98 -> 52937.812 | S98: JA Electrical Inv 1083 | T98: 45900 | U98: 53118.219 | W98: =W144 -> 45996
B99: 6 | H99: =H145 -> #REF! | L99: 6 | M99: 6. AC Equipment | N99: End of Defects Period | P99: 0.05 | Q99: =$O$92*P99 -> 52937.812 | S99: JA Electrical Inv 1083 | T99: 45900 | U99: 53118.219 | W99: 46015
B100: 6 | L100: 6 | M100: 6. AC Equipment | T100: =IF(W100>1,EOMONTH(W100,0),"") | U100: =(Q100/$X$86*$J$86) -> 0
B101: 6 | L101: 6 | M101: 6. AC Equipment | T101: =IF(W101>1,EOMONTH(W101,0),"") | U101: =(Q101/$X$86*$J$86) -> 0
B102: 6 | L102: 6 | M102: 6. AC Equipment | T102: =IF(W102>1,EOMONTH(W102,0),"") | U102: =(Q102/$X$86*$J$86) -> 0
T103: =IF(W103>1,EOMONTH(W103,0),"")
...

Sheet Cashflow
D1: [RT: Double Check the first date is always a MONDAY] | F1: 45677 | G1: =F1+7 -> 45684 | H1: =G1+7 -> 45691 | I1: =H1+7 -> 45698 | J1: =I1+7 -> 45705 | K1: =J1+7 -> 45712 | L1: =K1+7 -> 45719 | M1: =L1+7 -> 45726 | N1: =M1+7 -> 45733 | ... LD1: =LC1+7 -> 47847
A2: PLANNED | C2: CHECK | D2: CHECK
B3: Planned Revenue | C3: ='Revenue Tracking'!D4 -> 12364058 | D3: =SUM(F3:LD3) -> 12321836 | F3: =SUMIFS('Revenue Tracking'!$F$13:$F$19, 'Revenue Tracking'!$H$13:$H$19, ">="&F1,'Revenue Tracking'!$H$13:$H$19, "<"&G1) -> 0 | G3: =SUMIFS('Revenue Tracking'!$F$13:$F$19, 'Revenue Tracking'!$H$13:$H$19, ">="&G1,'Revenue Tracking'!$H$13:$H$19, "<"&H1) -> 0 | H3: =SUMIFS('Revenue Tracking'!$F$13:$F$19, 'Revenue Tracking'!$H$13:$H$19, ">="&H1,'Revenue Tracking'!$H$13:$H$19, "<"&I1) -> 0 | I3: =SUMIFS('Revenue Tracking'!$F$13:$F$19, 'Revenue Tracking'!$H$13:$H$19, ">="&I1,'Revenue Tracking'!$H$13:$H$19, "<"&J1) -> 0 | J3: =SUMIFS('Revenue Tracking'!$F$13:$F$19, 'Revenue Tracking'!$H$13:$H$19, ">="&J1,'Revenue Tracking'!$H$13:$H$19, "<"&K1) -> 0 | K3: =SUMIFS('Revenue Tracking'!$F$13:$F$19, 'Revenue Tracking'!$H$13:$H$19, ">="&K1,'Revenue Tracking'!$H$13:$H$19, "<"&L1) -> 0 | L3: =SUMIFS('Revenue Tracking'!$F$13:$F$19, 'Revenue Tracking'!$H$13:$H$19, ">="&L1,'Revenue Tracking'!$H$13:$H$19, "<"&M1) -> 0 | M3: =SUMIFS('Revenue Tracking'!$F$13:$F$19, 'Revenue Tracking'!$H$13:$H$19, ">="&M1,'Revenue Tracking'!$H$13:$H$19, "<"&N1) -> 0 | ... LC3: =SUMIFS('Revenue Tracking'!$F$13:$F$19, 'Revenue Tracking'!$H$13:$H$19, ">="&LC1,'Revenue Tracking'!$H$13:$H$19, "<"&LD1) -> 0 | LD3: =SUMIFS('Revenue Tracking'!$F$13:$F$19, 'Revenue Tracking'!$H$13:$H$19, ">="&LD1,'Revenue Tracking'!$H$13:$H$19, "<"&#REF!) -> 0
B4: Planned Revenue - Cumulative | F4: =F3 -> 0 | G4: =F4+G3 -> 0 | H4: =G4+H3 -> 0 | I4: =H4+I3 -> 0 | J4: =I4+J3 -> 0 | K4: =J4+K3 -> 0 | L4: =K4+L3 -> 0 | M4: =L4+M3 -> 0 | N4: =M4+N3 -> 0 | ... LD4: =LC4+LD3 -> 12321836
B5: Planned Expenditure | C5: ='Revenue Tracking'!D5 -> 10416340 | D5: =SUM(F5:LD5) -> 9931589.8 | F5: =SUMIFS('Expenditure Breakdown'!$G$6:$G$222, 'Expenditure Breakdown'!$H$6:$H$222, ">="&F1,'Expenditure Breakdown'!$H$6:$H$222, "<"&G1) -> 0 | G5: =SUMIFS('Expenditure Breakdown'!$G$6:$G$222, 'Expenditure Breakdown'!$H$6:$H$222, ">="&G1,'Expenditure Breakdown'!$H$6:$H$222, "<"&H1) -> 0 | H5: =SUMIFS('Expenditure Breakdown'!$G$6:$G$222, 'Expenditure Breakdown'!$H$6:$H$222, ">="&H1,'Expenditure Breakdown'!$H$6:$H$222, "<"&I1) -> 0 | I5: =SUMIFS('Expenditure Breakdown'!$G$6:$G$222, 'Expenditure Breakdown'!$H$6:$H$222, ">="&I1,'Expenditure Breakdown'!$H$6:$H$222, "<"&J1) -> 0 | J5: =SUMIFS('Expenditure Breakdown'!$G$6:$G$222, 'Expenditure Breakdown'!$H$6:$H$222, ">="&J1,'Expenditure Breakdown'!$H$6:$H$222, "<"&K1) -> 0 | K5: =SUMIFS('Expenditure Breakdown'!$G$6:$G$222, 'Expenditure Breakdown'!$H$6:$H$222, ">="&K1,'Expenditure Breakdown'!$H$6:$H$222, "<"&L1) -> 0 | L5: =SUMIFS('Expenditure Breakdown'!$G$6:$G$222, 'Expenditure Breakdown'!$H$6:$H$222, ">="&L1,'Expenditure Breakdown'!$H$6:$H$222, "<"&M1) -> 0 | M5: =SUMIFS('Expenditure Breakdown'!$G$6:$G$222, 'Expenditure Breakdown'!$H$6:$H$222, ">="&M1,'Expenditure Breakdown'!$H$6:$H$222, "<"&N1) -> 0 | ... LC5: =SUMIFS('Expenditure Breakdown'!$G$6:$G$222, 'Expenditure Breakdown'!$H$6:$H$222, ">="&LC1,'Expenditure Breakdown'!$H$6:$H$222, "<"&LD1) -> 0 | LD5: =SUMIFS('Expenditure Breakdown'!$G$6:$G$222, 'Expenditure Breakdown'!$H$6:$H$222, ">="&LD1,'Expenditure Breakdown'!$H$6:$H$222, "<"&#REF!) -> 0
B6: Planned Expenditure - Cumulative | F6: =F5 -> 0 | G6: =F6+G5 -> 0 | H6: =G6+H5 -> 0 | I6: =H6+I5 -> 0 | J6: =I6+J5 -> 0 | K6: =J6+K5 -> 0 | L6: =K6+L5 -> 0 | M6: =L6+M5 -> 0 | N6: =M6+N5 -> 0 | ... LD6: =LC6+LD5 -> 9931589.8
B7: PLANNED CashFlow | F7: =F4-F6 -> 0 | G7: =G4-G6 -> 0 | H7: =H4-H6 -> 0 | I7: =I4-I6 -> 0 | J7: =J4-J6 -> 0 | K7: =K4-K6 -> 0 | L7: =L4-L6 -> 0 | M7: =M4-M6 -> 0 | ... LD7: =LD4-LD6 -> 2390246.4
A8: ACTUAL | C8: CHECK | D8: CHECK
B9: Actual + Planned Revenue | C9: ='Revenue Tracking'!F4 -> 12392594 | D9: =SUM(F9:LD9) -> 12392594 | F9: =SUMIFS('Revenue Tracking'!$F$13:$F$19, 'Revenue Tracking'!$P$13:$P$19, ">="&F1,'Revenue Tracking'!$P$13:$P$19, "<"&G1) -> 0 | G9: =SUMIFS('Revenue Tracking'!$F$13:$F$19, 'Revenue Tracking'!$P$13:$P$19, ">="&G1,'Revenue Tracking'!$P$13:$P$19, "<"&H1) -> 0 | H9: =SUMIFS('Revenue Tracking'!$F$13:$F$19, 'Revenue Tracking'!$P$13:$P$19, ">="&H1,'Revenue Tracking'!$P$13:$P$19, "<"&I1) -> 0 | I9: =SUMIFS('Revenue Tracking'!$F$13:$F$19, 'Revenue Tracking'!$P$13:$P$19, ">="&I1,'Revenue Tracking'!$P$13:$P$19, "<"&J1) -> 0 | J9: =SUMIFS('Revenue Tracking'!$F$13:$F$19, 'Revenue Tracking'!$P$13:$P$19, ">="&J1,'Revenue Tracking'!$P$13:$P$19, "<"&K1) -> 0 | K9: =SUMIFS('Revenue Tracking'!$F$13:$F$19, 'Revenue Tracking'!$P$13:$P$19, ">="&K1,'Revenue Tracking'!$P$13:$P$19, "<"&L1) -> 0 | L9: =SUMIFS('Revenue Tracking'!$F$13:$F$19, 'Revenue Tracking'!$P$13:$P$19, ">="&L1,'Revenue Tracking'!$P$13:$P$19, "<"&M1) -> 0 | M9: =SUMIFS('Revenue Tracking'!$F$13:$F$19, 'Revenue Tracking'!$P$13:$P$19, ">="&M1,'Revenue Tracking'!$P$13:$P$19, "<"&N1) -> 0 | ... LC9: =SUMIFS('Revenue Tracking'!$F$13:$F$19, 'Revenue Tracking'!$P$13:$P$19, ">="&LC1,'Revenue Tracking'!$P$13:$P$19, "<"&LD1) -> 0 | LD9: =SUMIFS('Revenue Tracking'!$F$13:$F$19, 'Revenue Tracking'!$P$13:$P$19, ">="&LD1,'Revenue Tracking'!$P$13:$P$19, "<"&#REF!) -> 0
B10: Actual + Planned Revenue - Cumulative | F10: =F9 -> 0 | G10: =F10+G9 -> 0 | H10: =G10+H9 -> 0 | I10: =H10+I9 -> 0 | J10: =I10+J9 -> 0 | K10: =J10+K9 -> 0 | L10: =K10+L9 -> 0 | M10: =L10+M9 -> 0 | N10: =M10+N9 -> 0 | ... LD10: =LC10+LD9 -> 12392594
B11: Actual + Planned Expenditure | C11: ='Revenue Tracking'!F5 -> 8238201.1 | D11: =SUM(F11:LD11) -> 8238201.1 | F11: =SUMIFS('Expenditure Breakdown'!$Q$6:$Q$225, 'Expenditure Breakdown'!$W$6:$W$225, ">="&F1,'Expenditure Breakdown'!$W$6:$W$225, "<"&G1) -> 0 | G11: =SUMIFS('Expenditure Breakdown'!$Q$6:$Q$225, 'Expenditure Breakdown'!$W$6:$W$225, ">="&G1,'Expenditure Breakdown'!$W$6:$W$225, "<"&H1) -> 0 | H11: =SUMIFS('Expenditure Breakdown'!$Q$6:$Q$225, 'Expenditure Breakdown'!$W$6:$W$225, ">="&H1,'Expenditure Breakdown'!$W$6:$W$225, "<"&I1) -> 0 | I11: =SUMIFS('Expenditure Breakdown'!$Q$6:$Q$225, 'Expenditure Breakdown'!$W$6:$W$225, ">="&I1,'Expenditure Breakdown'!$W$6:$W$225, "<"&J1) -> 0 | J11: =SUMIFS('Expenditure Breakdown'!$Q$6:$Q$225, 'Expenditure Breakdown'!$W$6:$W$225, ">="&J1,'Expenditure Breakdown'!$W$6:$W$225, "<"&K1) -> 0 | K11: =SUMIFS('Expenditure Breakdown'!$Q$6:$Q$225, 'Expenditure Breakdown'!$W$6:$W$225, ">="&K1,'Expenditure Breakdown'!$W$6:$W$225, "<"&L1) -> 0 | L11: =SUMIFS('Expenditure Breakdown'!$Q$6:$Q$225, 'Expenditure Breakdown'!$W$6:$W$225, ">="&L1,'Expenditure Breakdown'!$W$6:$W$225, "<"&M1) -> 0 | M11: =SUMIFS('Expenditure Breakdown'!$Q$6:$Q$225, 'Expenditure Breakdown'!$W$6:$W$225, ">="&M1,'Expenditure Breakdown'!$W$6:$W$225, "<"&N1) -> 0 | ... LC11: =SUMIFS('Expenditure Breakdown'!$Q$6:$Q$225, 'Expenditure Breakdown'!$W$6:$W$225, ">="&LC1,'Expenditure Breakdown'!$W$6:$W$225, "<"&LD1) -> 0 | LD11: =SUMIFS('Expenditure Breakdown'!$Q$6:$Q$225, 'Expenditure Breakdown'!$W$6:$W$225, ">="&LD1,'Expenditure Breakdown'!$W$6:$W$225, "<"&#REF!) -> 0
B12: Actual + Planned Expenditure - Cumulative | F12: =F11 -> 0 | G12: =F12+G11 -> 0 | H12: =G12+H11 -> 0 | I12: =H12+I11 -> 0 | J12: =I12+J11 -> 0 | K12: =J12+K11 -> 0 | L12: =K12+L11 -> 0 | M12: =L12+M11 -> 0 | N12: =M12+N11 -> 0 | ... LD12: =LC12+LD11 -> 8238201.1
B14: ACTUAL CashFlow | F14: =F10-F12 -> 0 | G14: =G10-G12 -> 0 | H14: =H10-H12 -> 0 | I14: =I10-I12 -> 0 | J14: =J10-J12 -> 0 | K14: =K10-K12 -> 0 | L14: =L10-L12 -> 0 | M14: =M10-M12 -> 0 | ... LD14: =LD10-LD12 -> 4154392.9
C16: CHECK | D16: CHECK
B17: Revenue Recognition | C17: =C3-D17 -> -28535.633 | D17: =SUM(F17:LD17) -> 12392594 | F17: =SUMIFS('Expenditure Breakdown'!$U$6:$U$225, 'Expenditure Breakdown'!$T$6:$T$225, ">="&F1,'Expenditure Breakdown'!$T$6:$T$225, "<"&G1) -> 0 | G17: =SUMIFS('Expenditure Breakdown'!$U$6:$U$225, 'Expenditure Breakdown'!$T$6:$T$225, ">="&G1,'Expenditure Breakdown'!$T$6:$T$225, "<"&H1) -> 0 | H17: =SUMIFS('Expenditure Breakdown'!$U$6:$U$225, 'Expenditure Breakdown'!$T$6:$T$225, ">="&H1,'Expenditure Breakdown'!$T$6:$T$225, "<"&I1) -> 0 | I17: =SUMIFS('Expenditure Breakdown'!$U$6:$U$225, 'Expenditure Breakdown'!$T$6:$T$225, ">="&I1,'Expenditure Breakdown'!$T$6:$T$225, "<"&J1) -> 0 | J17: =SUMIFS('Expenditure Breakdown'!$U$6:$U$225, 'Expenditure Breakdown'!$T$6:$T$225, ">="&J1,'Expenditure Breakdown'!$T$6:$T$225, "<"&K1) -> 0 | K17: =SUMIFS('Expenditure Breakdown'!$U$6:$U$225, 'Expenditure Breakdown'!$T$6:$T$225, ">="&K1,'Expenditure Breakdown'!$T$6:$T$225, "<"&L1) -> 0 | L17: =SUMIFS('Expenditure Breakdown'!$U$6:$U$225, 'Expenditure Breakdown'!$T$6:$T$225, ">="&L1,'Expenditure Breakdown'!$T$6:$T$225, "<"&M1) -> 0 | M17: =SUMIFS('Expenditure Breakdown'!$U$6:$U$225, 'Expenditure Breakdown'!$T$6:$T$225, ">="&M1,'Expenditure Breakdown'!$T$6:$T$225, "<"&N1) -> 0 | ... LC17: =SUMIFS('Expenditure Breakdown'!$U$6:$U$225, 'Expenditure Breakdown'!$T$6:$T$225, ">="&LC1,'Expenditure Breakdown'!$T$6:$T$225, "<"&LD1) -> 0 | LD17: =SUMIFS('Expenditure Breakdown'!$U$6:$U$225, 'Expenditure Breakdown'!$T$6:$T$225, ">="&LD1,'Expenditure Breakdown'!$T$6:$T$225, "<"&#REF!) -> 0
B18: Revenue Recognition Cumulative | C18: =D17-D18 -> 0 | D18: =MAX(F18:LD18) -> 12392594 | F18: =F17 -> 0 | G18: =F18+G17 -> 0 | H18: =G18+H17 -> 0 | I18: =H18+I17 -> 0 | J18: =I18+J17 -> 0 | K18: =J18+K17 -> 0 | L18: =K18+L17 -> 0 | M18: =L18+M17 -> 0 | N18: =M18+N17 -> 0 | ... LD18: =LC18+LD17 -> 12392594

Sheet Finance - Revenue
A3: Sum of REVENUE RECOGNITION AMOUNT | B3: Column Labels
A4: Row Labels | B4: (blank) | C4: 45838 | D4: 45869 | E4: 45900 | F4: 45930 | G4: 45961 | H4: 45991 | I4: 46022 | K4: 46053 | L4: 46081 | M4: Grand Total
A5: (blank)
A6: 1. Panels | C6: 2235676.7 | H6: 0 | J6: 0 | K6: -42222.164 | M6: 2193454.5
A7: 2. Inverters | C7: 445250 | G7: 0 | H7: 0 | J7: 0 | K7: 0 | M7: 445250
A8: 3. Mounting Structures | C8: 431028.7 | D8: 1052321.3 | G8: -0.02 | H8: 0 | I8: 0 | K8: 0 | M8: 1483350
A9: 4. DC Equipment | D9: 894911.09 | E9: 616273.29 | G9: 0 | J9: 0 | M9: 1511184.4
A10: 5. Monitoring | B10: 0 | C10: 17332.951 | D10: 1789.4524 | E10: 11579.814 | F10: 0 | G10: 26342.781 | H10: 0 | J10: 0 | K10: 0 | M10: 57044.998
A11: 6. AC Equipment | E11: 1062364.4 | G11: 0 | J11: 0 | M11: 1062364.4
A12: 8. Product Add On | B12: 0 | C12: 16166.771 | E12: 165083.23 | G12: 0 | H12: 0 | J12: 0 | L12: 0 | M12: 181250
A13: 9. AC & DC installation | E13: 193117.98 | F13: 154494.38 | G13: 424859.55 | I13: 0 | J13: 0 | M13: 772471.91
A14: 10. Site Logistics | B14: 0 | C14: 198.66963 | D14: 311.82577 | E14: 4081.5937 | G14: 4958.4708 | H14: 0 | J14: 0 | M14: 9550.5599
A15: 11. Due Dilligence | D15: 19947.704 | F15: 17946.216 | G15: 15546.224 | H15: 33132.888 | J15: 0 | M15: 86573.031
A16: 13. Engineering | B16: 0 | I16: 488104.31 | J16: 0 | M16: 488104.31
A17: 14. General Expenses | C17: 2574.6702 | D17: 887.44991 | E17: 422.60151 | F17: 1080.6296 | G17: 309.82667 | H17: 0 | I17: 162.20549 | J17: 0 | K17: 1001.6328 | L17: 6931.7683 | M17: 13370.784
A18: 15. Service Add On | K18: 70757.8 | M18: 70757.8
A19: 12. BDP Commission
A20: 7.BESS | B20: 0 | D20: 3444298.5 | E20: 573568.87 | J20: 0 | M20: 4017867.3
A21: Grand Total | B21: 0 | C21: 3148228.5 | D21: 5414467.3 | E21: 2626491.7 | F21: 173521.23 | G21: 472016.84 | H21: 33132.888 | I21: 488266.52 | J21: 0 | K21: 29537.269 | L21: 6931.7683 | M21: 12392594
C23: 3148228.5 | D23: 5414467.3 | E23: 2626491.8 | F23: 173521.23 | G23: 472016.84 | H23: 33132.89 | I23: 488266.52 | K23: =K21 -> 29537.269 | L23: =L21 -> 6931.7683 | M23: =SUM(B23:L23) -> 12392594
C24: =GETPIVOTDATA("REVENUE RECOGNITION AMOUNT",$A$3,"INVOICE RAISED DATE",DATE(2025,6,30))-C23 -> 0.0018536085 | D24: =GETPIVOTDATA("REVENUE RECOGNITION AMOUNT",$A$3,"INVOICE RAISED DATE",DATE(2025,7,31))-D23 -> 0.0042587845 | E24: =GETPIVOTDATA("REVENUE RECOGNITION AMOUNT",$A$3,"INVOICE RAISED DATE",DATE(2025,8,31))-E23 -> -0.0005390523 | F24: =F21-F23 -> -0.0027381796 | G24: =G21-G23 -> -0.0045544659 | H24: =H21-H23 -> -0.0021953328 | I24: =I21-I23 -> -0.0030349186 | K24: =K21-K23 -> 0 | L24: =L21-L23 -> 0
M25: ='Revenue Tracking'!F4 -> 12392594
M27: =M25-M23 -> -0.0043624938

Sheet Finance - COS
A3: Sum of Actual Total | B3: Column Labels
A4: Row Labels | B4: (blank) | C4: 45838 | D4: 45869 | E4: 45900 | F4: 45930 | G4: 45961 | H4: 45991 | I4: 46022 | K4: 46053 | L4: 46081 | M4: Grand Total
A5: (blank)
A6: 1. Panels | C6: 1282447.6 | H6: -18502.4 | M6: 1263945.2
A7: 2. Inverters | C7: 315880 | G7: 68050 | H7: 1646.04 | K7: -69140 | M7: 316436.04
A8: 3. Mounting Structures | C8: 344822.96 | D8: 559179.16 | G8: 855 | H8: -15268.56 | K8: -2050.1 | M8: 887538.46
A9: 4. DC Equipment | D9: 324000 | E9: 223119.98 | G9: -175500 | M9: 371619.98
A10: 5. Monitoring | B10: 0 | C10: 17131.5 | D10: 13419.5 | E10: 56847 | F10: -6750 | G10: 124955.75 | H10: -3780 | K10: -1767.5 | M10: 200056.25
A11: 6. AC Equipment | E11: 1058756.2 | G11: 13151 | M11: 1071907.2
A12: 8. Product Add On | B12: 0 | C12: 14200 | E12: 36608.5 | G12: 20597.8 | H12: 139053.14 | L12: 46289.75 | M12: 256749.19
A13: 9. AC & DC installation | E13: 225204.45 | F13: 180163.56 | G13: 495449.8 | I13: 0 | M13: 900817.81
A14: 10. Site Logistics | C14: 6200 | D14: 5520 | E14: 89095.16 | F14: 620 | G14: 114749.64 | H14: 620 | I14: -400 | M14: 216404.8
A15: 11. Due Dilligence | D15: 7500 | F15: 12000 | G15: 8000 | H15: 24500 | M15: 52000
A16: 13. Engineering | B16: 0 | I16: 154022.95 | M16: 154022.95
A17: 14. General Expenses | C17: 1418.96 | D17: 735.36 | E17: 861.56 | F17: 1311.5 | G17: 2775.54 | H17: 0 | I17: 123.76 | K17: 637.84 | L17: 650 | M17: 8514.52
A18: 15. Service Add On | G18: 801.11 | H18: 24950 | K18: 70757.8 | L18: 60591.17 | M18: 157100.08
A19: 12. BDP Commission
A20: 7.BESS | D20: 1981660 | E20: 396800 | M20: 2378460
A21: Grand Total | B21: 0 | C21: 1982101 | D21: 2892014 | E21: 2087292.9 | F21: 187345.06 | G21: 673885.64 | H21: 153218.22 | I21: 153746.71 | K21: -1561.96 | L21: 107530.92 | M21: 8235572.5

Sheet Project Margins
A1: [capture project margins from costing sheet]
A3: Products | D3: 0.32
A4: Services | D4: 0.5
A5: Expenses | D5: 0.15
A6: Subcontractors | D6: 0.2

Sheet Equipment Quotes
B2: Equipment Quote and Budget comparision
B4: Description | D4: Budget | F4: Supplier 1 | H4: Variance | J4: Supplier 2 | L4: Variance | N4: Comments / Notes
F7: >Name< | J7: >Name<
B9: Inverters | D9: =SUM(D10:D11) -> #REF! | F9: =SUM(F10:F13) -> 0 | H9: =$D$9-F9 -> #REF! | J9: =SUM(J10:J13) -> 0 | L9: =$D$9-J9 -> #REF!
B10: Inverters | D10: =#REF! -> #REF!
B11: Optimizers | D11: =#REF! -> #REF!
B12: Warranty
B13: Delivery fee
F15: >Name< | J15: >Name<
B17: Mounting Structure | D17: =SUM(D18:D19) -> #REF! | F17: =SUM(F18:F20) -> 0 | H17: =$D$17- F17 -> #REF! | J17: =SUM(J18:J20) -> 0 | L17: =$D$17- J17 -> #REF!
B18: Mounting Structure | D18: =#REF! -> #REF!
B19: Delivery fee
F21: >Name< | J21: >Name<
B23: DC Cable | D23: =SUM(D24:D25) -> #REF! | F23: =SUM(F24:F25) -> 0 | H23: =$D$23- F23 -> #REF! | J23: =SUM(J24:J25) -> 0 | L23: =$D$23- J23 -> #REF!
B24: DC Cable | D24: =#REF! -> #REF!
B25: Delivery fee
F27: >Name< | J27: >Name<
B29: Monitoring system | D29: =SUM(D30:D32) -> #REF! | F29: =SUM(F30:F42) -> 0 | H29: =$D$29-F29 -> #REF! | J29: =SUM(J30:J32) -> 0 | L29: =$D$29-J29 -> #REF!
B30: =#REF! -> #REF! | D30: =#REF! -> #REF!
B31: =#REF! -> #REF! | D31: =#REF! -> #REF!
B32: Delivery fee
F34: >Name< | J34: >Name<
B36: Additional Scope | D36: =SUM(D37:D41) -> #REF! | F36: =SUM(F37:F41) -> 0 | H36: =$D$29-F36 -> #REF! | J36: =SUM(J37:J41) -> 0 | L36: =$D$29-J36 -> #REF!
B37: SCADA | D37: =#REF! -> #REF!
B38: Inverter cage
B39: Cat ladders
B40: Gen Integration
B41: Lifelines
B43: Totals | D43: =D36+D29+D23+D17+D9 -> #REF! | H43: =SUM(H7:H42) -> #REF! | L43: =SUM(L7:L42) -> #REF!
B47: All amounts are incl VAT

Sheet Installer Quotes
B2: Installer Quote and Budget comparision
B4: Description | D4: Budget | G4: Cosmic Sun | J4: Variance | L4: Matthews Group | O4: Variance
B6: AC Equipment | D6: =#REF! -> #REF! | E6: =D6/(1000*'Project Plan'!$E$3) -> #REF! | G6: 277892.91 | H6: =G6/('Project Plan'!$E$3*1000) -> 0.40746761 | J6: =D6-G6 -> #REF! | M6: =L6/('Project Plan'!$E$3*1000) -> 0 | O6: =D6-L6 -> #REF!
B7: DC Equipment | D7: =#REF! -> #REF! | E7: =D7/(1000*'Project Plan'!$E$3) -> #REF! | G7: 142158.25 | H7: =G7/('Project Plan'!$E$3*1000) -> 0.20844318 | J7: =D7-G7 -> #REF! | M7: =L7/('Project Plan'!$E$3*1000) -> 0 | O7: =D7-L7 -> #REF!
B8: AC Labour | D8: =#REF! -> #REF! | E8: =D8/(1000*'Project Plan'!$E$3) -> #REF! | G8: 96174 | H8: =G8/('Project Plan'!$E$3*1000) -> 0.1410176 | J8: =D8-G8 -> #REF! | M8: =L8/('Project Plan'!$E$3*1000) -> 0 | O8: =D8-L8 -> #REF!
B9: DC Labour | D9: =#REF! -> #REF! | E9: =D9/(1000*'Project Plan'!$E$3) -> #REF! | G9: 230160 | H9: =G9/('Project Plan'!$E$3*1000) -> 0.33747801 | J9: =D9-G9 -> #REF! | M9: =L9/('Project Plan'!$E$3*1000) -> 0 | O9: =D9-L9 -> #REF!
B10: Offloading | D10: =#REF! -> #REF! | G10: 0 | J10: =D10-G10 -> #REF! | O10: =D10-L10 -> #REF!
B11: Roof Access/Scaffolding | D11: =#REF! -> #REF! | G11: 29257.61 | J11: =D11-G11 -> #REF! | O11: =D11-L11 -> #REF!
B12: Storage | D12: =#REF! -> #REF! | J12: =D12-G12 -> #REF! | O12: =D12-L12 -> #REF!
B13: Telehandler | D13: =#REF! -> #REF!
B14: HSE | D14: 0
B15: Totals | D15: =SUM(D6:D13) -> #REF! | G15: =SUM(G6:G13) -> 775642.77 | J15: =SUM(J6:J14) -> #REF! | L15: =SUM(L6:L13) -> 0 | O15: =SUM(O6:O14) -> #REF!
B18: Description | D18: Budget | G18: >Installer Name 3< | J18: Variance | L18: >Installer Name 4< | O18: Variance
B20: AC installation | D20: =#REF! -> #REF! | E20: =D20/(1000*'Project Plan'!$E$3) -> #REF! | H20: =G20/(1000*'Project Plan'!$E$3) -> 0 | J20: =D20-G20 -> #REF! | M20: =L20/(1000*'Project Plan'!$E$3) -> 0 | O20: =D6-L20 -> #REF!
B21: AC equipment | D21: =#REF! -> #REF! | E21: =D21/(1000*'Project Plan'!$E$3) -> #REF! | J21: =D21-G21 -> #REF! | M21: =L21/(1000*'Project Plan'!$E$3) -> 0 | O21: =D7-L21 -> #REF!
B22: DC installation | D22: =#REF! -> #REF! | E22: =D22/(1000*'Project Plan'!$E$3) -> #REF! | H22: =G22/(1000*'Project Plan'!$E$3) -> 0 | J22: =D22-G22 -> #REF! | M22: =L22/(1000*'Project Plan'!$E$3) -> 0 | O22: =D8-L22 -> #REF!
B23: DC equipment | D23: =SUM(#REF!) -> #REF! | E23: =D23/(1000*'Project Plan'!$E$3) -> #REF! | J23: =D23-G23 -> #REF! | O23: =D9-L23 -> #REF!
B24: Storage | D24: =#REF! -> #REF! | J24: =D24-G24 -> #REF! | O24: =D10-L24 -> #REF!
B25: Panel lifting equipment | D25: =SUM(#REF!) -> #REF! | J25: =D25-G25 -> #REF! | O25: =D11-L25 -> #REF!
B26: Offloading | D26: =#REF! -> #REF! | J26: =D26-G26 -> #REF! | O26: =D12-L26 -> #REF!
B29: Totals | D29: =SUM(D20:D27) -> #REF! | G29: =SUM(G20:G27) -> 0 | J29: =SUM(J20:J28) -> #REF! | L29: =SUM(L20:L27) -> 0 | O29: =SUM(O20:O28) -> #REF!
B32: Budget Summary
B34: Budget | D34: =D15 -> #REF!
B35: =G4 -> Cosmic Sun | D35: =G15 -> 775642.77
B36: =L4 -> Matthews Group | D36: =L15 -> 0
B37: =G18 -> >Installer Name 3< | D37: =G29 -> 0
B38: =L18 -> >Installer Name 4< | D38: =L29 -> 0
B40: =IF(D40<D34,"Saving","Loss") -> #REF! | D40: =D34-MIN(D35:D38) -> #REF!
B42: All amounts are exc VAT

Sheet Decision Register
B1: =D15 -> Red Rocket | E1: Decision Register
B3: ID | C3: Decision Description | D3: Decision Impact | E3: Proposed Date | F3: Proposed By | G3: Status | H3: Approved By | I3: Date | J3: Results / Comments
B4: DEC001
B5: DEC002
B6: DEC003
B7: DEC004
B8: DEC005
B9: DEC006
B10: DEC007
B11: DEC008
B12: DEC009
B13: DEC010
D15: {='Project Plan'!E2:H2} -> Red Rocket | E15: 0 | F15: 0 | G15: 0
